/*     */ package me.konsolas.aac;
/*     */ 
/*     */ 
/*     */ public final class a1 {
/*     */   public static final long[] i;
/*     */   public static final long[] l;
/*     */   private static final int g = 16;
/*     */   private static final int d = 8192;
/*     */   private static final int f = 128;
/*     */   private static final int c = 16;
/*     */   private static final int m = 8;
/*     */   
/*  13 */   private static int a(int[] paramArrayOfint, long[] paramArrayOflong, int paramInt1, int paramInt2, int paramInt3) { long l1 = paramArrayOflong[paramArrayOfint[paramInt1]];
/*     */ 
/*     */ 
/*     */ 
/*     */ 
/*     */ 
/*     */ 
/*     */ 
/*     */ 
/*     */ 
/*     */ 
/*     */ 
/*     */ 
/*     */ 
/*     */ 
/*     */ 
/*     */ 
/*     */ 
/*     */ 
/*     */ 
/*     */ 
/*     */ 
/*     */ 
/*     */ 
/*     */ 
/*     */ 
/*     */ 
/*     */ 
/*     */ 
/*     */ 
/*     */ 
/*     */ 
/*     */ 
/*     */ 
/*     */ 
/*     */ 
/*     */ 
/*     */ 
/*     */ 
/*     */ 
/*     */ 
/*     */ 
/*     */ 
/*     */ 
/*     */ 
/*     */ 
/*     */ 
/*     */ 
/*     */ 
/*     */ 
/*     */ 
/*     */ 
/*     */ 
/*     */ 
/*     */ 
/*     */ 
/*     */ 
/*     */ 
/*     */ 
/*     */ 
/*     */ 
/*     */ 
/*     */ 
/*     */ 
/*     */ 
/*     */ 
/*     */ 
/*     */ 
/*     */ 
/*     */ 
/*     */ 
/*     */ 
/*     */ 
/*     */ 
/*     */ 
/*     */ 
/*     */ 
/*     */ 
/*     */ 
/*     */ 
/*     */ 
/*     */ 
/*     */ 
/*     */ 
/*     */ 
/*     */ 
/*     */ 
/*     */ 
/*     */ 
/*     */ 
/*     */ 
/*     */ 
/*     */ 
/*     */ 
/*     */ 
/*     */ 
/*     */ 
/*     */ 
/*     */ 
/*     */ 
/*     */ 
/*     */ 
/*     */ 
/*     */ 
/*     */ 
/*     */ 
/*     */ 
/*     */ 
/*     */ 
/*     */ 
/*     */ 
/*     */ 
/*     */ 
/*     */ 
/*     */ 
/*     */ 
/*     */ 
/*     */ 
/*     */ 
/*     */ 
/*     */ 
/*     */ 
/*     */ 
/*     */ 
/*     */ 
/*     */ 
/*     */ 
/*     */ 
/*     */ 
/*     */ 
/*     */ 
/*     */ 
/*     */ 
/*     */ 
/*     */ 
/*     */ 
/*     */ 
/*     */ 
/*     */ 
/*     */ 
/*     */ 
/*     */ 
/*     */ 
/*     */ 
/*     */ 
/*     */ 
/*     */ 
/*     */ 
/*     */ 
/*     */ 
/*     */ 
/*     */ 
/*     */ 
/*     */ 
/*     */ 
/*     */ 
/*     */ 
/*     */ 
/*     */ 
/*     */ 
/*     */ 
/*     */ 
/*     */ 
/*     */ 
/*     */ 
/*     */ 
/*     */ 
/*     */ 
/*     */ 
/*     */ 
/*     */ 
/*     */ 
/*     */ 
/*     */ 
/*     */ 
/*     */ 
/*     */ 
/*     */ 
/*     */ 
/*     */ 
/*     */ 
/*     */ 
/*     */ 
/*     */ 
/*     */ 
/*     */ 
/*     */ 
/*     */ 
/*     */ 
/*     */ 
/*     */ 
/*     */ 
/*     */ 
/*     */ 
/*     */ 
/*     */ 
/*     */ 
/*     */ 
/*     */ 
/*     */ 
/*     */ 
/*     */ 
/*     */ 
/*     */ 
/*     */ 
/*     */ 
/*     */ 
/*     */ 
/*     */ 
/*     */ 
/*     */ 
/*     */ 
/*     */ 
/*     */ 
/*     */ 
/*     */ 
/*     */ 
/*     */ 
/*     */ 
/*     */ 
/*     */ 
/*     */ 
/*     */ 
/*     */ 
/*     */ 
/*     */ 
/*     */ 
/*     */ 
/*     */ 
/*     */ 
/*     */ 
/*     */ 
/*     */ 
/*     */ 
/*     */ 
/*     */ 
/*     */ 
/*     */ 
/*     */ 
/*     */ 
/*     */ 
/*     */ 
/*     */ 
/*     */ 
/*     */ 
/*     */ 
/*     */ 
/*     */ 
/*     */ 
/*     */ 
/*     */ 
/*     */ 
/*     */ 
/*     */ 
/*     */ 
/*     */ 
/*     */ 
/*     */ 
/*     */ 
/*     */ 
/*     */ 
/*     */ 
/*     */ 
/*     */ 
/*     */ 
/*     */ 
/*     */ 
/*     */ 
/*     */ 
/*     */ 
/*     */ 
/*     */ 
/*     */ 
/*     */ 
/*     */ 
/*     */ 
/*     */ 
/*     */ 
/*     */ 
/*     */ 
/*     */ 
/*     */ 
/*     */ 
/*     */ 
/*     */ 
/*     */ 
/*     */ 
/*     */ 
/*     */ 
/*     */ 
/*     */ 
/*     */ 
/*     */ 
/*     */ 
/*     */ 
/*     */ 
/*     */ 
/*     */ 
/*     */ 
/*     */ 
/*     */ 
/*     */ 
/*     */ 
/*     */ 
/*     */ 
/*     */ 
/*     */ 
/*     */ 
/*     */ 
/*     */ 
/*     */ 
/*     */ 
/*     */ 
/*     */ 
/*     */ 
/*     */ 
/*     */ 
/*     */ 
/*     */ 
/*     */ 
/*     */ 
/*     */ 
/*     */ 
/*     */ 
/*     */ 
/*     */ 
/*     */ 
/*     */ 
/*     */ 
/*     */ 
/*     */ 
/*     */ 
/*     */ 
/*     */ 
/*     */ 
/*     */ 
/*     */ 
/*     */ 
/*     */ 
/*     */ 
/*     */ 
/*     */ 
/*     */ 
/*     */ 
/*     */ 
/*     */ 
/*     */ 
/*     */ 
/*     */ 
/*     */ 
/*     */ 
/*     */ 
/*     */ 
/*     */ 
/*     */ 
/*     */ 
/*     */ 
/*     */ 
/*     */ 
/*     */ 
/*     */ 
/*     */ 
/*     */ 
/*     */ 
/*     */ 
/*     */ 
/*     */ 
/*     */ 
/*     */ 
/*     */ 
/*     */ 
/*     */ 
/*     */ 
/*     */ 
/*     */ 
/*     */ 
/*     */ 
/*     */ 
/*     */ 
/*     */ 
/*     */ 
/*     */ 
/*     */ 
/*     */ 
/*     */ 
/*     */ 
/*     */ 
/*     */ 
/*     */ 
/*     */ 
/*     */ 
/*     */ 
/*     */ 
/*     */ 
/*     */ 
/*     */ 
/*     */ 
/*     */ 
/*     */ 
/*     */ 
/*     */ 
/*     */ 
/*     */ 
/*     */ 
/*     */ 
/*     */ 
/*     */ 
/*     */ 
/*     */ 
/*     */ 
/*     */ 
/*     */ 
/*     */ 
/*     */ 
/*     */ 
/*     */ 
/*     */ 
/*     */ 
/*     */ 
/*     */ 
/*     */ 
/*     */ 
/*     */ 
/*     */ 
/*     */ 
/*     */ 
/*     */ 
/*     */ 
/*     */ 
/*     */ 
/*     */ 
/*     */ 
/*     */ 
/*     */ 
/*     */ 
/*     */ 
/*     */ 
/*     */ 
/*     */ 
/*     */ 
/*     */ 
/*     */ 
/*     */ 
/*     */ 
/*     */ 
/*     */ 
/*     */ 
/*     */ 
/*     */ 
/*     */ 
/*     */ 
/*     */ 
/*     */ 
/*     */ 
/*     */ 
/*     */ 
/*     */ 
/*     */ 
/*     */ 
/*     */ 
/*     */ 
/*     */ 
/*     */ 
/*     */ 
/*     */ 
/*     */ 
/*     */ 
/*     */ 
/*     */ 
/*     */ 
/*     */ 
/*     */ 
/*     */ 
/*     */ 
/*     */ 
/*     */ 
/*     */ 
/*     */ 
/*     */ 
/*     */ 
/*     */ 
/*     */ 
/*     */ 
/*     */ 
/*     */ 
/*     */ 
/*     */ 
/*     */ 
/*     */ 
/*     */ 
/*     */ 
/*     */ 
/*     */ 
/*     */ 
/*     */ 
/*     */ 
/*     */ 
/*     */ 
/*     */ 
/*     */ 
/*     */ 
/*     */ 
/*     */ 
/*     */ 
/*     */ 
/*     */ 
/*     */ 
/*     */ 
/*     */ 
/*     */ 
/*     */ 
/*     */ 
/*     */ 
/*     */ 
/*     */ 
/*     */ 
/*     */ 
/*     */ 
/*     */ 
/*     */ 
/*     */ 
/*     */ 
/*     */ 
/*     */ 
/*     */ 
/*     */ 
/*     */ 
/*     */ 
/*     */ 
/*     */ 
/*     */ 
/*     */ 
/*     */ 
/*     */ 
/*     */ 
/*     */ 
/*     */ 
/*     */ 
/*     */ 
/*     */ 
/*     */ 
/*     */ 
/*     */ 
/*     */ 
/*     */ 
/*     */ 
/*     */ 
/*     */ 
/*     */ 
/*     */ 
/*     */ 
/*     */ 
/*     */ 
/*     */ 
/*     */ 
/*     */ 
/*     */ 
/*     */ 
/*     */ 
/*     */ 
/*     */ 
/*     */ 
/*     */ 
/*     */ 
/*     */ 
/*     */ 
/*     */ 
/*     */ 
/*     */ 
/*     */ 
/*     */ 
/*     */ 
/*     */ 
/*     */ 
/*     */ 
/*     */ 
/*     */ 
/*     */ 
/*     */ 
/*     */ 
/*     */ 
/*     */ 
/*     */ 
/*     */ 
/*     */ 
/*     */ 
/*     */ 
/*     */ 
/*     */ 
/*     */ 
/*     */ 
/*     */ 
/*     */ 
/*     */ 
/*     */ 
/*     */ 
/*     */ 
/*     */ 
/*     */ 
/*     */ 
/*     */ 
/*     */ 
/*     */ 
/*     */ 
/*     */ 
/*     */ 
/*     */ 
/*     */ 
/*     */ 
/*     */ 
/*     */ 
/*     */ 
/*     */ 
/*     */ 
/*     */ 
/*     */ 
/*     */ 
/*     */ 
/*     */ 
/*     */ 
/*     */ 
/*     */ 
/*     */ 
/*     */ 
/*     */ 
/*     */ 
/*     */ 
/*     */ 
/*     */ 
/*     */ 
/*     */ 
/*     */ 
/*     */ 
/*     */ 
/*     */ 
/*     */ 
/*     */ 
/*     */ 
/*     */ 
/*     */ 
/*     */ 
/*     */ 
/*     */ 
/*     */ 
/*     */ 
/*     */ 
/*     */ 
/*     */ 
/*     */ 
/*     */ 
/*     */ 
/*     */ 
/*     */ 
/*     */ 
/*     */ 
/*     */ 
/*     */ 
/*     */ 
/*     */ 
/*     */ 
/*     */ 
/*     */ 
/*     */ 
/*     */ 
/*     */ 
/*     */ 
/*     */ 
/*     */ 
/*     */ 
/*     */ 
/*     */ 
/*     */ 
/*     */ 
/*     */ 
/*     */ 
/*     */ 
/*     */ 
/*     */ 
/*     */ 
/*     */ 
/*     */ 
/*     */ 
/*     */ 
/*     */ 
/*     */ 
/*     */ 
/*     */ 
/*     */ 
/*     */ 
/*     */ 
/*     */ 
/*     */ 
/*     */ 
/*     */ 
/*     */ 
/*     */ 
/*     */ 
/*     */ 
/*     */ 
/*     */ 
/*     */ 
/*     */ 
/*     */ 
/*     */ 
/*     */ 
/*     */ 
/*     */ 
/*     */ 
/*     */ 
/*     */ 
/*     */ 
/*     */ 
/*     */ 
/*     */ 
/*     */ 
/*     */ 
/*     */ 
/*     */ 
/*     */ 
/*     */ 
/*     */ 
/*     */ 
/*     */ 
/*     */ 
/*     */ 
/*     */ 
/*     */ 
/*     */ 
/*     */ 
/*     */ 
/*     */ 
/*     */ 
/*     */ 
/*     */ 
/*     */ 
/*     */ 
/*     */ 
/*     */ 
/*     */ 
/*     */ 
/*     */ 
/*     */ 
/*     */ 
/*     */ 
/*     */ 
/*     */ 
/*     */     
/* 760 */     long l2 = paramArrayOflong[paramArrayOfint[paramInt2]];
/*     */     long l3 = paramArrayOflong[paramArrayOfint[paramInt3]];
/*     */     int i = Long.compare(l1, l2);
/*     */     int j = Long.compare(l1, l3);
/*     */     int k = Long.compare(l2, l3);
/*     */     try {
/*     */       if (i < 0) {
/*     */         try {
/*     */           try {
/*     */           
/*     */           } catch (IllegalArgumentException illegalArgumentException) {
/*     */             throw a(null);
/*     */           } 
/*     */         } catch (IllegalArgumentException illegalArgumentException) {
/*     */           throw a(null);
/*     */         } 
/*     */       } else {
/*     */         try {
/*     */           try {
/*     */           
/*     */           } catch (IllegalArgumentException illegalArgumentException) {
/*     */             throw a(null);
/*     */           } 
/*     */         } catch (IllegalArgumentException illegalArgumentException) {
/*     */           throw a(null);
/*     */         } 
/*     */       } 
/*     */     } catch (IllegalArgumentException illegalArgumentException) {
/*     */       throw a(null);
/*     */     } 
/*     */     return (k > 0) ? paramInt2 : ((j > 0) ? paramInt3 : paramInt1); }
/*     */   private static final int j = 255;
/*     */   private static final int k = 8;
/*     */   private static final int a = 1024; private static final int b = 1024; static final int n = 4000; protected static final cw e; public static final m9 h; public static void a(long[] paramArrayOflong1, int paramInt1, int paramInt2, hq paramhq, long[] paramArrayOflong2) { // Byte code:
/*     */     //   0: iload_2
/*     */     //   1: iload_1
/*     */     //   2: isub
/*     */     //   3: istore #5
/*     */     //   5: iload #5
/*     */     //   7: bipush #16
/*     */     //   9: if_icmpge -> 24
/*     */     //   12: aload_0
/*     */     //   13: iload_1
/*     */     //   14: iload_2
/*     */     //   15: aload_3
/*     */     //   16: invokestatic a : ([JIILme/konsolas/aac/hq;)V
/*     */     //   19: return
/*     */     //   20: invokestatic a : (Ljava/lang/Exception;)Ljava/lang/Exception;
/*     */     //   23: athrow
/*     */     //   24: aload #4
/*     */     //   26: ifnonnull -> 36
/*     */     //   29: aload_0
/*     */     //   30: iload_2
/*     */     //   31: invokestatic copyOf : ([JI)[J
/*     */     //   34: astore #4
/*     */     //   36: iload_1
/*     */     //   37: iload_2
/*     */     //   38: iadd
/*     */     //   39: iconst_1
/*     */     //   40: iushr
/*     */     //   41: istore #6
/*     */     //   43: aload #4
/*     */     //   45: iload_1
/*     */     //   46: iload #6
/*     */     //   48: aload_3
/*     */     //   49: aload_0
/*     */     //   50: invokestatic a : ([JIILme/konsolas/aac/hq;[J)V
/*     */     //   53: aload #4
/*     */     //   55: iload #6
/*     */     //   57: iload_2
/*     */     //   58: aload_3
/*     */     //   59: aload_0
/*     */     //   60: invokestatic a : ([JIILme/konsolas/aac/hq;[J)V
/*     */     //   63: aload_3
/*     */     //   64: aload #4
/*     */     //   66: iload #6
/*     */     //   68: iconst_1
/*     */     //   69: isub
/*     */     //   70: laload
/*     */     //   71: aload #4
/*     */     //   73: iload #6
/*     */     //   75: laload
/*     */     //   76: invokeinterface a : (JJ)I
/*     */     //   81: ifgt -> 99
/*     */     //   84: aload #4
/*     */     //   86: iload_1
/*     */     //   87: aload_0
/*     */     //   88: iload_1
/*     */     //   89: iload #5
/*     */     //   91: invokestatic arraycopy : (Ljava/lang/Object;ILjava/lang/Object;II)V
/*     */     //   94: return
/*     */     //   95: invokestatic a : (Ljava/lang/Exception;)Ljava/lang/Exception;
/*     */     //   98: athrow
/*     */     //   99: iload_1
/*     */     //   100: istore #7
/*     */     //   102: iload_1
/*     */     //   103: istore #8
/*     */     //   105: iload #6
/*     */     //   107: istore #9
/*     */     //   109: iload #7
/*     */     //   111: iload_2
/*     */     //   112: if_icmpge -> 205
/*     */     //   115: iload #9
/*     */     //   117: iload_2
/*     */     //   118: if_icmpge -> 168
/*     */     //   121: goto -> 128
/*     */     //   124: invokestatic a : (Ljava/lang/Exception;)Ljava/lang/Exception;
/*     */     //   127: athrow
/*     */     //   128: iload #8
/*     */     //   130: iload #6
/*     */     //   132: if_icmpge -> 187
/*     */     //   135: goto -> 142
/*     */     //   138: invokestatic a : (Ljava/lang/Exception;)Ljava/lang/Exception;
/*     */     //   141: athrow
/*     */     //   142: aload_3
/*     */     //   143: aload #4
/*     */     //   145: iload #8
/*     */     //   147: laload
/*     */     //   148: aload #4
/*     */     //   150: iload #9
/*     */     //   152: laload
/*     */     //   153: invokeinterface a : (JJ)I
/*     */     //   158: ifgt -> 187
/*     */     //   161: goto -> 168
/*     */     //   164: invokestatic a : (Ljava/lang/Exception;)Ljava/lang/Exception;
/*     */     //   167: athrow
/*     */     //   168: aload_0
/*     */     //   169: iload #7
/*     */     //   171: aload #4
/*     */     //   173: iload #8
/*     */     //   175: iinc #8, 1
/*     */     //   178: laload
/*     */     //   179: lastore
/*     */     //   180: goto -> 199
/*     */     //   183: invokestatic a : (Ljava/lang/Exception;)Ljava/lang/Exception;
/*     */     //   186: athrow
/*     */     //   187: aload_0
/*     */     //   188: iload #7
/*     */     //   190: aload #4
/*     */     //   192: iload #9
/*     */     //   194: iinc #9, 1
/*     */     //   197: laload
/*     */     //   198: lastore
/*     */     //   199: iinc #7, 1
/*     */     //   202: goto -> 109
/*     */     //   205: return
/*     */     // Line number table:
/*     */     //   Java source line number -> byte code offset
/*     */     //   #9	-> 0
/*     */     //   #115	-> 5
/*     */     //   #742	-> 12
/*     */     //   #303	-> 19
/*     */     //   #851	-> 24
/*     */     //   #42	-> 36
/*     */     //   #479	-> 43
/*     */     //   #123	-> 53
/*     */     //   #645	-> 63
/*     */     //   #595	-> 84
/*     */     //   #756	-> 94
/*     */     //   #748	-> 99
/*     */     //   #290	-> 115
/*     */     //   #802	-> 187
/*     */     //   #625	-> 199
/*     */     //   #800	-> 205
/*     */     // Exception table:
/*     */     //   from	to	target	type
/*     */     //   5	20	20	java/lang/IllegalArgumentException
/*     */     //   43	95	95	java/lang/IllegalArgumentException
/*     */     //   109	121	124	java/lang/IllegalArgumentException
/*     */     //   115	135	138	java/lang/IllegalArgumentException
/*     */     //   128	161	164	java/lang/IllegalArgumentException
/*     */     //   142	183	183	java/lang/IllegalArgumentException } public static void a(long[] paramArrayOflong) { a(paramArrayOflong, 0, paramArrayOflong.length); } public static void b(long[] paramArrayOflong1, long[] paramArrayOflong2, int paramInt1, int paramInt2) { ForkJoinPool forkJoinPool = a();
/*     */     try {
/*     */       if (paramInt2 - paramInt1 >= 8192) {
/*     */         try {
/*     */           if (forkJoinPool.getParallelism() == 1) {
/*     */             c(paramArrayOflong1, paramArrayOflong2, paramInt1, paramInt2);
/*     */             return;
/*     */           } 
/*     */         } catch (IllegalArgumentException illegalArgumentException) {
/*     */           throw a(null);
/*     */         } 
/*     */         forkJoinPool.invoke(new cS(paramArrayOflong1, paramArrayOflong2, paramInt1, paramInt2));
/*     */         return;
/*     */       } 
/*     */     } catch (IllegalArgumentException illegalArgumentException) {
/*     */       throw a(null);
/*     */     } 
/*     */     c(paramArrayOflong1, paramArrayOflong2, paramInt1, paramInt2); } private static int a(long[] paramArrayOflong, int paramInt1, int paramInt2, int paramInt3) {
/*     */     int i = Long.compare(paramArrayOflong[paramInt1], paramArrayOflong[paramInt2]);
/*     */     int j = Long.compare(paramArrayOflong[paramInt1], paramArrayOflong[paramInt3]);
/*     */     int k = Long.compare(paramArrayOflong[paramInt2], paramArrayOflong[paramInt3]);
/*     */     
/*     */     try { if (i < 0)
/*     */       { 
/*     */         try { 
/*     */           try {  }
/*     */           catch (IllegalArgumentException illegalArgumentException)
/* 820 */           { throw a(null); }  } catch (IllegalArgumentException illegalArgumentException) { throw a(null); }  } else { try { try {  } catch (IllegalArgumentException illegalArgumentException) { throw a(null); }  } catch (IllegalArgumentException illegalArgumentException) { throw a(null); }  }  } catch (IllegalArgumentException illegalArgumentException) { throw a(null); }
/*     */     
/*     */     return (k > 0) ? paramInt2 : ((j > 0) ? paramInt3 : paramInt1);
/*     */   }
/*     */ 
/*     */   
/*     */   public static void c(long[] paramArrayOflong) {
/*     */     i(paramArrayOflong, 0, paramArrayOflong.length);
/*     */   }
/*     */ 
/*     */   
/*     */   public static long[] d(long[] paramArrayOflong, int paramInt1, int paramInt2) {
/*     */     try {
/*     */     
/*     */     } catch (IllegalArgumentException illegalArgumentException) {
/*     */       throw a(null);
/*     */     } 
/*     */     return (paramInt1 > paramArrayOflong.length) ? e(paramArrayOflong, paramInt1, paramInt2) : paramArrayOflong;
/*     */   }
/*     */ 
/*     */   
/*     */   private static void b(long[] paramArrayOflong1, long[] paramArrayOflong2, int paramInt1, int paramInt2, int paramInt3) {
/*     */     byte b = 0;
/*     */     try {
/*     */       while (b < paramInt3) {
/*     */         e(paramArrayOflong1, paramArrayOflong2, paramInt1, paramInt2);
/*     */         b++;
/*     */         paramInt1++;
/*     */         paramInt2++;
/*     */       } 
/*     */     } catch (IllegalArgumentException illegalArgumentException) {
/*     */       throw a(null);
/*     */     } 
/*     */   }
/*     */ 
/*     */   
/*     */   public static long[] b(long[] paramArrayOflong) {
/*     */     return (long[])paramArrayOflong.clone();
/*     */   }
/*     */ 
/*     */   
/*     */   public static void f(long[] paramArrayOflong, int paramInt1, int paramInt2) {
/*     */     aL.b(paramArrayOflong.length, paramInt1, paramInt2);
/*     */   }
/*     */   
/*     */   private static void g(long[] paramArrayOflong, int paramInt1, int paramInt2, hq paramhq) {
/*     */     for (int i = paramInt1; i < paramInt2 - 1; i++)
/*     */     { int j = i;
/*     */       int k = i + 1;
/*     */       while (true)
/*     */       { try {
/*     */           if (k < paramInt2) {
/*     */             if (paramhq.a(paramArrayOflong[k], paramArrayOflong[j]) < 0) {
/*     */               j = k;
/*     */             }
/*     */             k++;
/*     */             continue;
/*     */           } 
/*     */         } catch (IllegalArgumentException illegalArgumentException) {
/*     */           throw a(null);
/*     */         } 
/*     */         if (j != i)
/*     */         { long l = paramArrayOflong[i];
/* 883 */           paramArrayOflong[i] = paramArrayOflong[j]; paramArrayOflong[j] = l; }  break; }  } 
/*     */   } public static void g(long[] paramArrayOflong) { c(paramArrayOflong, 0, paramArrayOflong.length); } @Deprecated public static void a(long[] paramArrayOflong, int paramInt1, int paramInt2, long paramLong) { try { f(paramArrayOflong, paramInt1, paramInt2); if (paramInt1 == 0) { try { for (; paramInt2-- != 0; paramArrayOflong[paramInt2] = paramLong); }
/*     */         catch (IllegalArgumentException illegalArgumentException) { throw a(null); }
/*     */          }
/* 887 */       else { int i = paramInt1; try { while (i < paramInt2) { paramArrayOflong[i] = paramLong; i++; }  } catch (IllegalArgumentException illegalArgumentException) { throw a(null); }
/*     */          }
/*     */        }
/*     */     catch (IllegalArgumentException illegalArgumentException)
/*     */     { throw a(null); }
/*     */      }
/*     */ 
/*     */   
/*     */   public static long[] a(long[] paramArrayOflong, int paramInt1, int paramInt2, Random paramRandom) {
/*     */     for (int i = paramInt2 - paramInt1; i-- != 0; paramArrayOflong[paramInt1 + j] = l) {
/*     */       int j = paramRandom.nextInt(i + 1);
/*     */       long l = paramArrayOflong[paramInt1 + i];
/*     */       paramArrayOflong[paramInt1 + i] = paramArrayOflong[paramInt1 + j];
/*     */     } 
/* 901 */     return paramArrayOflong;
/*     */   }
/*     */ 
/*     */   
/*     */   public static void b(int[] paramArrayOfint, long[] paramArrayOflong, boolean paramBoolean) {
/*     */     a(paramArrayOfint, paramArrayOflong, 0, paramArrayOfint.length, paramBoolean);
/*     */   }
/*     */ 
/*     */   
/*     */   public static void b(int[] paramArrayOfint, long[] paramArrayOflong, int paramInt1, int paramInt2) {
/*     */     // Byte code:
/*     */     //   0: iload_2
/*     */     //   1: istore #4
/*     */     //   3: iload_2
/*     */     //   4: iconst_1
/*     */     //   5: iadd
/*     */     //   6: istore #5
/*     */     //   8: iload #5
/*     */     //   10: iload_3
/*     */     //   11: if_icmpge -> 78
/*     */     //   14: aload_1
/*     */     //   15: aload_0
/*     */     //   16: iload #5
/*     */     //   18: iaload
/*     */     //   19: laload
/*     */     //   20: aload_1
/*     */     //   21: aload_0
/*     */     //   22: iload #4
/*     */     //   24: iaload
/*     */     //   25: laload
/*     */     //   26: lcmp
/*     */     //   27: ifeq -> 72
/*     */     //   30: goto -> 37
/*     */     //   33: invokestatic a : (Ljava/lang/Exception;)Ljava/lang/Exception;
/*     */     //   36: athrow
/*     */     //   37: iload #5
/*     */     //   39: iload #4
/*     */     //   41: isub
/*     */     //   42: iconst_1
/*     */     //   43: if_icmple -> 68
/*     */     //   46: goto -> 53
/*     */     //   49: invokestatic a : (Ljava/lang/Exception;)Ljava/lang/Exception;
/*     */     //   52: athrow
/*     */     //   53: aload_0
/*     */     //   54: iload #4
/*     */     //   56: iload #5
/*     */     //   58: invokestatic k : ([III)V
/*     */     //   61: goto -> 68
/*     */     //   64: invokestatic a : (Ljava/lang/Exception;)Ljava/lang/Exception;
/*     */     //   67: athrow
/*     */     //   68: iload #5
/*     */     //   70: istore #4
/*     */     //   72: iinc #5, 1
/*     */     //   75: goto -> 8
/*     */     //   78: iload_3
/*     */     //   79: iload #4
/*     */     //   81: isub
/*     */     //   82: iconst_1
/*     */     //   83: if_icmple -> 100
/*     */     //   86: aload_0
/*     */     //   87: iload #4
/*     */     //   89: iload_3
/*     */     //   90: invokestatic k : ([III)V
/*     */     //   93: goto -> 100
/*     */     //   96: invokestatic a : (Ljava/lang/Exception;)Ljava/lang/Exception;
/*     */     //   99: athrow
/*     */     //   100: return
/*     */     // Line number table:
/*     */     //   Java source line number -> byte code offset
/*     */     //   #154	-> 0
/*     */     //   #443	-> 3
/*     */     //   #666	-> 14
/*     */     //   #220	-> 37
/*     */     //   #450	-> 68
/*     */     //   #663	-> 72
/*     */     //   #878	-> 78
/*     */     //   #586	-> 100
/*     */     // Exception table:
/*     */     //   from	to	target	type
/*     */     //   8	30	33	java/lang/IllegalArgumentException
/*     */     //   14	46	49	java/lang/IllegalArgumentException
/*     */     //   37	61	64	java/lang/IllegalArgumentException
/*     */     //   78	93	96	java/lang/IllegalArgumentException
/*     */   }
/*     */ 
/*     */   
/*     */   public static void d(long[] paramArrayOflong1, long[] paramArrayOflong2) {
/*     */     e(paramArrayOflong1, paramArrayOflong2);
/*     */     b(paramArrayOflong1, paramArrayOflong2, 0, paramArrayOflong1.length);
/*     */   }
/*     */ 
/*     */   
/*     */   public static void e(long[] paramArrayOflong) {
/*     */     l(paramArrayOflong, 0, paramArrayOflong.length);
/*     */   }
/*     */   
/*     */   public static int a(long[] paramArrayOflong, long paramLong) {
/*     */     return a(paramArrayOflong, 0, paramArrayOflong.length, paramLong);
/*     */   }
/*     */   
/*     */   public static void a(int[] paramArrayOfint, long[] paramArrayOflong, int paramInt1, int paramInt2, boolean paramBoolean) {
/*     */     try {
/*     */       if (paramInt2 - paramInt1 < 1024) {
/*     */         a(paramArrayOfint, paramArrayOflong, paramInt1, paramInt2);
/*     */         return;
/*     */       } 
/*     */     } catch (IllegalArgumentException illegalArgumentException) {
/*     */       throw a(null);
/*     */     } 
/*     */     byte b1 = 7;
/*     */     char c = 'ۺ';
/*     */     byte b2 = 0;
/*     */     int[] arrayOfInt1 = new int[1786];
/*     */     int[] arrayOfInt2 = new int[1786];
/*     */     int[] arrayOfInt3 = new int[1786];
/*     */     arrayOfInt1[b2] = paramInt1;
/*     */     arrayOfInt2[b2] = paramInt2 - paramInt1;
/*     */     arrayOfInt3[b2++] = 0;
/* 947 */     int[] arrayOfInt4 = new int[256];
/*     */     int[] arrayOfInt5 = new int[256];
/*     */     try {
/*     */     
/*     */     } catch (IllegalArgumentException illegalArgumentException) {
/*     */       throw a(null);
/*     */     } 
/*     */     int[] arrayOfInt6 = paramBoolean ? new int[paramArrayOfint.length] : null;
/*     */     while (b2 > 0) {
/*     */       int i = arrayOfInt1[--b2];
/*     */       int j = arrayOfInt2[b2];
/*     */       int k = arrayOfInt3[b2];
/*     */       try {
/*     */       
/*     */       } catch (IllegalArgumentException illegalArgumentException) {
/*     */         throw a(null);
/*     */       } 
/*     */       boolean bool = (k % 8 == 0) ? true : false;
/*     */       int m = (7 - k % 8) * 8;
/*     */       int n = i + j;
/*     */     } 
/*     */   }
/*     */   
/*     */   public static void c(int[] paramArrayOfint, long[] paramArrayOflong) {
/*     */     b(paramArrayOfint, paramArrayOflong, 0, paramArrayOfint.length);
/*     */   }
/*     */   
/*     */   public static void d(long[] paramArrayOflong) {
/*     */     h(paramArrayOflong, 0, paramArrayOflong.length);
/*     */   }
/*     */   
/*     */   public static void e(long[] paramArrayOflong, hq paramhq) {
/*     */     f(paramArrayOflong, 0, paramArrayOflong.length, paramhq);
/*     */   }
/*     */   
/*     */   public static void h(long[] paramArrayOflong, int paramInt1, int paramInt2) {
/*     */     try {
/*     */       if (paramInt2 - paramInt1 >= 4000) {
/*     */         b(paramArrayOflong, paramInt1, paramInt2);
/*     */       } else {
/*     */         c(paramArrayOflong, paramInt1, paramInt2);
/*     */       } 
/*     */     } catch (IllegalArgumentException illegalArgumentException) {
/*     */       throw a(null);
/*     */     } 
/*     */   }
/*     */   
/*     */   public static void b(long[] paramArrayOflong, int paramInt1, int paramInt2) {
/*     */     try {
/*     */       if (paramInt2 - paramInt1 < 1024) {
/*     */         c(paramArrayOflong, paramInt1, paramInt2);
/*     */         return;
/*     */       } 
/*     */     } catch (IllegalArgumentException illegalArgumentException) {
/*     */       throw a(null);
/*     */     } 
/*     */     byte b1 = 7;
/*     */     char c = 'ۺ';
/*     */     byte b2 = 0;
/*     */     int[] arrayOfInt1 = new int[1786];
/*     */     int[] arrayOfInt2 = new int[1786];
/*     */     int[] arrayOfInt3 = new int[1786];
/*     */     arrayOfInt1[b2] = paramInt1;
/*     */     arrayOfInt2[b2] = paramInt2 - paramInt1;
/*     */     arrayOfInt3[b2++] = 0;
/*     */     int[] arrayOfInt4 = new int[256];
/*     */     int[] arrayOfInt5 = new int[256];
/*     */     while (b2 > 0) {
/*     */       int i = arrayOfInt1[--b2];
/*     */       int j = arrayOfInt2[b2];
/*     */       int k = arrayOfInt3[b2];
/*     */     } 
/*     */   }
/*     */   
/*     */   public static void e(long[] paramArrayOflong, int paramInt1, int paramInt2, hq paramhq) {
/*     */     ForkJoinPool forkJoinPool = a();
/*     */     try {
/*     */       if (paramInt2 - paramInt1 >= 8192) {
/*     */         try {
/*     */           if (forkJoinPool.getParallelism() == 1) {
/*     */             f(paramArrayOflong, paramInt1, paramInt2, paramhq);
/*     */             return;
/*     */           } 
/*     */         } catch (IllegalArgumentException illegalArgumentException) {
/*     */           throw a(null);
/*     */         } 
/*     */         forkJoinPool.invoke(new im(paramArrayOflong, paramInt1, paramInt2, paramhq));
/*     */         return;
/*     */       } 
/*     */     } catch (IllegalArgumentException illegalArgumentException) {
/*     */       throw a(null);
/*     */     } 
/*     */     f(paramArrayOflong, paramInt1, paramInt2, paramhq);
/*     */   }
/*     */   
/*     */   public static void b(long[] paramArrayOflong1, long[] paramArrayOflong2) {
/*     */     e(paramArrayOflong1, paramArrayOflong2);
/*     */     g(paramArrayOflong1, paramArrayOflong2, 0, paramArrayOflong1.length);
/*     */   }
/*     */   
/*     */   public static void a(long[] paramArrayOflong1, int paramInt1, int paramInt2, long[] paramArrayOflong2) {
/*     */     // Byte code:
/*     */     //   0: iload_2
/*     */     //   1: iload_1
/*     */     //   2: isub
/*     */     //   3: istore #4
/*     */     //   5: iload #4
/*     */     //   7: bipush #16
/*     */     //   9: if_icmpge -> 23
/*     */     //   12: aload_0
/*     */     //   13: iload_1
/*     */     //   14: iload_2
/*     */     //   15: invokestatic j : ([JII)V
/*     */     //   18: return
/*     */     //   19: invokestatic a : (Ljava/lang/Exception;)Ljava/lang/Exception;
/*     */     //   22: athrow
/*     */     //   23: aload_3
/*     */     //   24: ifnonnull -> 33
/*     */     //   27: aload_0
/*     */     //   28: iload_2
/*     */     //   29: invokestatic copyOf : ([JI)[J
/*     */     //   32: astore_3
/*     */     //   33: iload_1
/*     */     //   34: iload_2
/*     */     //   35: iadd
/*     */     //   36: iconst_1
/*     */     //   37: iushr
/*     */     //   38: istore #5
/*     */     //   40: aload_3
/*     */     //   41: iload_1
/*     */     //   42: iload #5
/*     */     //   44: aload_0
/*     */     //   45: invokestatic a : ([JII[J)V
/*     */     //   48: aload_3
/*     */     //   49: iload #5
/*     */     //   51: iload_2
/*     */     //   52: aload_0
/*     */     //   53: invokestatic a : ([JII[J)V
/*     */     //   56: aload_3
/*     */     //   57: iload #5
/*     */     //   59: iconst_1
/*     */     //   60: isub
/*     */     //   61: laload
/*     */     //   62: aload_3
/*     */     //   63: iload #5
/*     */     //   65: laload
/*     */     //   66: lcmp
/*     */     //   67: ifgt -> 84
/*     */     //   70: aload_3
/*     */     //   71: iload_1
/*     */     //   72: aload_0
/*     */     //   73: iload_1
/*     */     //   74: iload #4
/*     */     //   76: invokestatic arraycopy : (Ljava/lang/Object;ILjava/lang/Object;II)V
/*     */     //   79: return
/*     */     //   80: invokestatic a : (Ljava/lang/Exception;)Ljava/lang/Exception;
/*     */     //   83: athrow
/*     */     //   84: iload_1
/*     */     //   85: istore #6
/*     */     //   87: iload_1
/*     */     //   88: istore #7
/*     */     //   90: iload #5
/*     */     //   92: istore #8
/*     */     //   94: iload #6
/*     */     //   96: iload_2
/*     */     //   97: if_icmpge -> 181
/*     */     //   100: iload #8
/*     */     //   102: iload_2
/*     */     //   103: if_icmpge -> 146
/*     */     //   106: goto -> 113
/*     */     //   109: invokestatic a : (Ljava/lang/Exception;)Ljava/lang/Exception;
/*     */     //   112: athrow
/*     */     //   113: iload #7
/*     */     //   115: iload #5
/*     */     //   117: if_icmpge -> 164
/*     */     //   120: goto -> 127
/*     */     //   123: invokestatic a : (Ljava/lang/Exception;)Ljava/lang/Exception;
/*     */     //   126: athrow
/*     */     //   127: aload_3
/*     */     //   128: iload #7
/*     */     //   130: laload
/*     */     //   131: aload_3
/*     */     //   132: iload #8
/*     */     //   134: laload
/*     */     //   135: lcmp
/*     */     //   136: ifgt -> 164
/*     */     //   139: goto -> 146
/*     */     //   142: invokestatic a : (Ljava/lang/Exception;)Ljava/lang/Exception;
/*     */     //   145: athrow
/*     */     //   146: aload_0
/*     */     //   147: iload #6
/*     */     //   149: aload_3
/*     */     //   150: iload #7
/*     */     //   152: iinc #7, 1
/*     */     //   155: laload
/*     */     //   156: lastore
/*     */     //   157: goto -> 175
/*     */     //   160: invokestatic a : (Ljava/lang/Exception;)Ljava/lang/Exception;
/*     */     //   163: athrow
/*     */     //   164: aload_0
/*     */     //   165: iload #6
/*     */     //   167: aload_3
/*     */     //   168: iload #8
/*     */     //   170: iinc #8, 1
/*     */     //   173: laload
/*     */     //   174: lastore
/*     */     //   175: iinc #6, 1
/*     */     //   178: goto -> 94
/*     */     //   181: return
/*     */     // Line number table:
/*     */     //   Java source line number -> byte code offset
/*     */     //   #240	-> 0
/*     */     //   #428	-> 5
/*     */     //   #280	-> 12
/*     */     //   #263	-> 18
/*     */     //   #642	-> 23
/*     */     //   #182	-> 33
/*     */     //   #289	-> 40
/*     */     //   #644	-> 48
/*     */     //   #922	-> 56
/*     */     //   #104	-> 70
/*     */     //   #245	-> 79
/*     */     //   #164	-> 84
/*     */     //   #793	-> 100
/*     */     //   #184	-> 164
/*     */     //   #744	-> 175
/*     */     //   #297	-> 181
/*     */     // Exception table:
/*     */     //   from	to	target	type
/*     */     //   5	19	19	java/lang/IllegalArgumentException
/*     */     //   40	80	80	java/lang/IllegalArgumentException
/*     */     //   94	106	109	java/lang/IllegalArgumentException
/*     */     //   100	120	123	java/lang/IllegalArgumentException
/*     */     //   113	139	142	java/lang/IllegalArgumentException
/*     */     //   127	160	160	java/lang/IllegalArgumentException
/*     */   }
/*     */   
/*     */   private static void d(long[] paramArrayOflong1, long[] paramArrayOflong2, int paramInt1, int paramInt2) {
/*     */     // Byte code:
/*     */     //   0: iload_2
/*     */     //   1: istore #4
/*     */     //   3: iload #4
/*     */     //   5: iload_3
/*     */     //   6: iconst_1
/*     */     //   7: isub
/*     */     //   8: if_icmpge -> 138
/*     */     //   11: iload #4
/*     */     //   13: istore #5
/*     */     //   15: iload #4
/*     */     //   17: iconst_1
/*     */     //   18: iadd
/*     */     //   19: istore #7
/*     */     //   21: iload #7
/*     */     //   23: iload_3
/*     */     //   24: if_icmpge -> 85
/*     */     //   27: aload_0
/*     */     //   28: iload #7
/*     */     //   30: laload
/*     */     //   31: aload_0
/*     */     //   32: iload #5
/*     */     //   34: laload
/*     */     //   35: invokestatic compare : (JJ)I
/*     */     //   38: dup
/*     */     //   39: istore #6
/*     */     //   41: iflt -> 75
/*     */     //   44: iload #6
/*     */     //   46: ifne -> 79
/*     */     //   49: goto -> 56
/*     */     //   52: invokestatic a : (Ljava/lang/Exception;)Ljava/lang/Exception;
/*     */     //   55: athrow
/*     */     //   56: aload_1
/*     */     //   57: iload #7
/*     */     //   59: laload
/*     */     //   60: aload_1
/*     */     //   61: iload #5
/*     */     //   63: laload
/*     */     //   64: lcmp
/*     */     //   65: ifge -> 79
/*     */     //   68: goto -> 75
/*     */     //   71: invokestatic a : (Ljava/lang/Exception;)Ljava/lang/Exception;
/*     */     //   74: athrow
/*     */     //   75: iload #7
/*     */     //   77: istore #5
/*     */     //   79: iinc #7, 1
/*     */     //   82: goto -> 21
/*     */     //   85: iload #5
/*     */     //   87: iload #4
/*     */     //   89: if_icmpeq -> 132
/*     */     //   92: aload_0
/*     */     //   93: iload #4
/*     */     //   95: laload
/*     */     //   96: lstore #7
/*     */     //   98: aload_0
/*     */     //   99: iload #4
/*     */     //   101: aload_0
/*     */     //   102: iload #5
/*     */     //   104: laload
/*     */     //   105: lastore
/*     */     //   106: aload_0
/*     */     //   107: iload #5
/*     */     //   109: lload #7
/*     */     //   111: lastore
/*     */     //   112: aload_1
/*     */     //   113: iload #4
/*     */     //   115: laload
/*     */     //   116: lstore #7
/*     */     //   118: aload_1
/*     */     //   119: iload #4
/*     */     //   121: aload_1
/*     */     //   122: iload #5
/*     */     //   124: laload
/*     */     //   125: lastore
/*     */     //   126: aload_1
/*     */     //   127: iload #5
/*     */     //   129: lload #7
/*     */     //   131: lastore
/*     */     //   132: iinc #4, 1
/*     */     //   135: goto -> 3
/*     */     //   138: return
/*     */     // Line number table:
/*     */     //   Java source line number -> byte code offset
/*     */     //   #254	-> 0
/*     */     //   #324	-> 11
/*     */     //   #391	-> 15
/*     */     //   #496	-> 27
/*     */     //   #783	-> 79
/*     */     //   #229	-> 85
/*     */     //   #242	-> 92
/*     */     //   #870	-> 98
/*     */     //   #294	-> 106
/*     */     //   #476	-> 112
/*     */     //   #771	-> 118
/*     */     //   #499	-> 126
/*     */     //   #931	-> 132
/*     */     //   #512	-> 138
/*     */     // Exception table:
/*     */     //   from	to	target	type
/*     */     //   41	49	52	java/lang/IllegalArgumentException
/*     */     //   44	68	71	java/lang/IllegalArgumentException
/*     */   }
/*     */   
/*     */   public static void c(long[] paramArrayOflong, hq paramhq) {
/*     */     b(paramArrayOflong, 0, paramArrayOflong.length, paramhq);
/*     */   }
/*     */   
/*     */   public static long[] d(long[] paramArrayOflong, int paramInt) {
/*     */     try {
/*     */       if (paramInt == paramArrayOflong.length)
/*     */         return paramArrayOflong; 
/*     */     } catch (IllegalArgumentException illegalArgumentException) {
/*     */       throw a(null);
/*     */     } 
/*     */     try {
/*     */       if (paramInt < paramArrayOflong.length)
/*     */         return b(paramArrayOflong, paramInt); 
/*     */     } catch (IllegalArgumentException illegalArgumentException) {
/*     */       throw a(null);
/*     */     } 
/*     */     return c(paramArrayOflong, paramInt);
/*     */   }
/*     */   
/*     */   private static void e(long[] paramArrayOflong1, long[] paramArrayOflong2, int paramInt1, int paramInt2) {
/*     */     long l1 = paramArrayOflong1[paramInt1];
/*     */     long l2 = paramArrayOflong2[paramInt1];
/*     */     paramArrayOflong1[paramInt1] = paramArrayOflong1[paramInt2];
/*     */     paramArrayOflong2[paramInt1] = paramArrayOflong2[paramInt2];
/*     */     paramArrayOflong1[paramInt2] = l1;
/*     */     paramArrayOflong2[paramInt2] = l2;
/*     */   }
/*     */   
/*     */   public static void c(long[] paramArrayOflong1, long[] paramArrayOflong2, int paramInt1, int paramInt2) {
/*     */     // Byte code:
/*     */     //   0: iload_3
/*     */     //   1: iload_2
/*     */     //   2: isub
/*     */     //   3: istore #4
/*     */     //   5: iload #4
/*     */     //   7: bipush #16
/*     */     //   9: if_icmpge -> 24
/*     */     //   12: aload_0
/*     */     //   13: aload_1
/*     */     //   14: iload_2
/*     */     //   15: iload_3
/*     */     //   16: invokestatic d : ([J[JII)V
/*     */     //   19: return
/*     */     //   20: invokestatic a : (Ljava/lang/Exception;)Ljava/lang/Exception;
/*     */     //   23: athrow
/*     */     //   24: iload_2
/*     */     //   25: iload #4
/*     */     //   27: iconst_2
/*     */     //   28: idiv
/*     */     //   29: iadd
/*     */     //   30: istore #5
/*     */     //   32: iload_2
/*     */     //   33: istore #6
/*     */     //   35: iload_3
/*     */     //   36: iconst_1
/*     */     //   37: isub
/*     */     //   38: istore #7
/*     */     //   40: iload #4
/*     */     //   42: sipush #128
/*     */     //   45: if_icmple -> 116
/*     */     //   48: iload #4
/*     */     //   50: bipush #8
/*     */     //   52: idiv
/*     */     //   53: istore #8
/*     */     //   55: aload_0
/*     */     //   56: aload_1
/*     */     //   57: iload #6
/*     */     //   59: iload #6
/*     */     //   61: iload #8
/*     */     //   63: iadd
/*     */     //   64: iload #6
/*     */     //   66: iconst_2
/*     */     //   67: iload #8
/*     */     //   69: imul
/*     */     //   70: iadd
/*     */     //   71: invokestatic a : ([J[JIII)I
/*     */     //   74: istore #6
/*     */     //   76: aload_0
/*     */     //   77: aload_1
/*     */     //   78: iload #5
/*     */     //   80: iload #8
/*     */     //   82: isub
/*     */     //   83: iload #5
/*     */     //   85: iload #5
/*     */     //   87: iload #8
/*     */     //   89: iadd
/*     */     //   90: invokestatic a : ([J[JIII)I
/*     */     //   93: istore #5
/*     */     //   95: aload_0
/*     */     //   96: aload_1
/*     */     //   97: iload #7
/*     */     //   99: iconst_2
/*     */     //   100: iload #8
/*     */     //   102: imul
/*     */     //   103: isub
/*     */     //   104: iload #7
/*     */     //   106: iload #8
/*     */     //   108: isub
/*     */     //   109: iload #7
/*     */     //   111: invokestatic a : ([J[JIII)I
/*     */     //   114: istore #7
/*     */     //   116: aload_0
/*     */     //   117: aload_1
/*     */     //   118: iload #6
/*     */     //   120: iload #5
/*     */     //   122: iload #7
/*     */     //   124: invokestatic a : ([J[JIII)I
/*     */     //   127: istore #5
/*     */     //   129: aload_0
/*     */     //   130: iload #5
/*     */     //   132: laload
/*     */     //   133: lstore #8
/*     */     //   135: aload_1
/*     */     //   136: iload #5
/*     */     //   138: laload
/*     */     //   139: lstore #10
/*     */     //   141: iload_2
/*     */     //   142: istore #12
/*     */     //   144: iload #12
/*     */     //   146: istore #13
/*     */     //   148: iload_3
/*     */     //   149: iconst_1
/*     */     //   150: isub
/*     */     //   151: istore #14
/*     */     //   153: iload #14
/*     */     //   155: istore #15
/*     */     //   157: iload #13
/*     */     //   159: iload #14
/*     */     //   161: if_icmpgt -> 240
/*     */     //   164: aload_0
/*     */     //   165: iload #13
/*     */     //   167: laload
/*     */     //   168: lload #8
/*     */     //   170: invokestatic compare : (JJ)I
/*     */     //   173: dup
/*     */     //   174: istore #17
/*     */     //   176: ifne -> 195
/*     */     //   179: aload_1
/*     */     //   180: iload #13
/*     */     //   182: laload
/*     */     //   183: lload #10
/*     */     //   185: invokestatic compare : (JJ)I
/*     */     //   188: goto -> 197
/*     */     //   191: invokestatic a : (Ljava/lang/Exception;)Ljava/lang/Exception;
/*     */     //   194: athrow
/*     */     //   195: iload #17
/*     */     //   197: dup
/*     */     //   198: istore #16
/*     */     //   200: ifgt -> 240
/*     */     //   203: iload #16
/*     */     //   205: ifne -> 234
/*     */     //   208: goto -> 215
/*     */     //   211: invokestatic a : (Ljava/lang/Exception;)Ljava/lang/Exception;
/*     */     //   214: athrow
/*     */     //   215: aload_0
/*     */     //   216: aload_1
/*     */     //   217: iload #12
/*     */     //   219: iinc #12, 1
/*     */     //   222: iload #13
/*     */     //   224: invokestatic e : ([J[JII)V
/*     */     //   227: goto -> 234
/*     */     //   230: invokestatic a : (Ljava/lang/Exception;)Ljava/lang/Exception;
/*     */     //   233: athrow
/*     */     //   234: iinc #13, 1
/*     */     //   237: goto -> 157
/*     */     //   240: iload #14
/*     */     //   242: iload #13
/*     */     //   244: if_icmplt -> 323
/*     */     //   247: aload_0
/*     */     //   248: iload #14
/*     */     //   250: laload
/*     */     //   251: lload #8
/*     */     //   253: invokestatic compare : (JJ)I
/*     */     //   256: dup
/*     */     //   257: istore #17
/*     */     //   259: ifne -> 278
/*     */     //   262: aload_1
/*     */     //   263: iload #14
/*     */     //   265: laload
/*     */     //   266: lload #10
/*     */     //   268: invokestatic compare : (JJ)I
/*     */     //   271: goto -> 280
/*     */     //   274: invokestatic a : (Ljava/lang/Exception;)Ljava/lang/Exception;
/*     */     //   277: athrow
/*     */     //   278: iload #17
/*     */     //   280: dup
/*     */     //   281: istore #16
/*     */     //   283: iflt -> 323
/*     */     //   286: iload #16
/*     */     //   288: ifne -> 317
/*     */     //   291: goto -> 298
/*     */     //   294: invokestatic a : (Ljava/lang/Exception;)Ljava/lang/Exception;
/*     */     //   297: athrow
/*     */     //   298: aload_0
/*     */     //   299: aload_1
/*     */     //   300: iload #14
/*     */     //   302: iload #15
/*     */     //   304: iinc #15, -1
/*     */     //   307: invokestatic e : ([J[JII)V
/*     */     //   310: goto -> 317
/*     */     //   313: invokestatic a : (Ljava/lang/Exception;)Ljava/lang/Exception;
/*     */     //   316: athrow
/*     */     //   317: iinc #14, -1
/*     */     //   320: goto -> 240
/*     */     //   323: iload #13
/*     */     //   325: iload #14
/*     */     //   327: if_icmple -> 337
/*     */     //   330: goto -> 355
/*     */     //   333: invokestatic a : (Ljava/lang/Exception;)Ljava/lang/Exception;
/*     */     //   336: athrow
/*     */     //   337: aload_0
/*     */     //   338: aload_1
/*     */     //   339: iload #13
/*     */     //   341: iinc #13, 1
/*     */     //   344: iload #14
/*     */     //   346: iinc #14, -1
/*     */     //   349: invokestatic e : ([J[JII)V
/*     */     //   352: goto -> 157
/*     */     //   355: iload #12
/*     */     //   357: iload_2
/*     */     //   358: isub
/*     */     //   359: iload #13
/*     */     //   361: iload #12
/*     */     //   363: isub
/*     */     //   364: invokestatic min : (II)I
/*     */     //   367: istore #16
/*     */     //   369: aload_0
/*     */     //   370: aload_1
/*     */     //   371: iload_2
/*     */     //   372: iload #13
/*     */     //   374: iload #16
/*     */     //   376: isub
/*     */     //   377: iload #16
/*     */     //   379: invokestatic b : ([J[JIII)V
/*     */     //   382: iload #15
/*     */     //   384: iload #14
/*     */     //   386: isub
/*     */     //   387: iload_3
/*     */     //   388: iload #15
/*     */     //   390: isub
/*     */     //   391: iconst_1
/*     */     //   392: isub
/*     */     //   393: invokestatic min : (II)I
/*     */     //   396: istore #16
/*     */     //   398: aload_0
/*     */     //   399: aload_1
/*     */     //   400: iload #13
/*     */     //   402: iload_3
/*     */     //   403: iload #16
/*     */     //   405: isub
/*     */     //   406: iload #16
/*     */     //   408: invokestatic b : ([J[JIII)V
/*     */     //   411: iload #13
/*     */     //   413: iload #12
/*     */     //   415: isub
/*     */     //   416: dup
/*     */     //   417: istore #16
/*     */     //   419: iconst_1
/*     */     //   420: if_icmple -> 440
/*     */     //   423: aload_0
/*     */     //   424: aload_1
/*     */     //   425: iload_2
/*     */     //   426: iload_2
/*     */     //   427: iload #16
/*     */     //   429: iadd
/*     */     //   430: invokestatic c : ([J[JII)V
/*     */     //   433: goto -> 440
/*     */     //   436: invokestatic a : (Ljava/lang/Exception;)Ljava/lang/Exception;
/*     */     //   439: athrow
/*     */     //   440: iload #15
/*     */     //   442: iload #14
/*     */     //   444: isub
/*     */     //   445: dup
/*     */     //   446: istore #16
/*     */     //   448: iconst_1
/*     */     //   449: if_icmple -> 469
/*     */     //   452: aload_0
/*     */     //   453: aload_1
/*     */     //   454: iload_3
/*     */     //   455: iload #16
/*     */     //   457: isub
/*     */     //   458: iload_3
/*     */     //   459: invokestatic c : ([J[JII)V
/*     */     //   462: goto -> 469
/*     */     //   465: invokestatic a : (Ljava/lang/Exception;)Ljava/lang/Exception;
/*     */     //   468: athrow
/*     */     //   469: return
/*     */     // Line number table:
/*     */     //   Java source line number -> byte code offset
/*     */     //   #276	-> 0
/*     */     //   #575	-> 5
/*     */     //   #637	-> 12
/*     */     //   #384	-> 19
/*     */     //   #328	-> 24
/*     */     //   #430	-> 32
/*     */     //   #21	-> 35
/*     */     //   #942	-> 40
/*     */     //   #264	-> 48
/*     */     //   #203	-> 55
/*     */     //   #452	-> 76
/*     */     //   #849	-> 95
/*     */     //   #579	-> 116
/*     */     //   #687	-> 129
/*     */     //   #147	-> 141
/*     */     //   #397	-> 157
/*     */     //   #15	-> 203
/*     */     //   #810	-> 234
/*     */     //   #93	-> 240
/*     */     //   #464	-> 286
/*     */     //   #225	-> 317
/*     */     //   #180	-> 323
/*     */     //   #413	-> 337
/*     */     //   #348	-> 355
/*     */     //   #624	-> 369
/*     */     //   #562	-> 382
/*     */     //   #500	-> 398
/*     */     //   #713	-> 411
/*     */     //   #582	-> 440
/*     */     //   #568	-> 469
/*     */     // Exception table:
/*     */     //   from	to	target	type
/*     */     //   5	20	20	java/lang/IllegalArgumentException
/*     */     //   176	191	191	java/lang/IllegalArgumentException
/*     */     //   200	208	211	java/lang/IllegalArgumentException
/*     */     //   203	227	230	java/lang/IllegalArgumentException
/*     */     //   259	274	274	java/lang/IllegalArgumentException
/*     */     //   283	291	294	java/lang/IllegalArgumentException
/*     */     //   286	310	313	java/lang/IllegalArgumentException
/*     */     //   323	333	333	java/lang/IllegalArgumentException
/*     */     //   419	433	436	java/lang/IllegalArgumentException
/*     */     //   448	462	465	java/lang/IllegalArgumentException
/*     */   }
/*     */   
/*     */   private static void a(int[] paramArrayOfint, long[] paramArrayOflong1, long[] paramArrayOflong2, int paramInt1, int paramInt2) {
/*     */     for (int i = paramInt1; ++i < paramInt2; ) {
/*     */       int j = paramArrayOfint[i];
/*     */       int k = i;
/*     */       int m = paramArrayOfint[k - 1];
/*     */       for (;; m = paramArrayOfint[--k - 1]) {
/*     */         try {
/*     */           if (paramArrayOflong1[j] >= paramArrayOflong1[m]) {
/*     */             try {
/*     */               if (paramArrayOflong1[j] == paramArrayOflong1[m])
/*     */                 try {
/*     */                   if (paramArrayOflong2[j] < paramArrayOflong2[m])
/*     */                     continue; 
/*     */                 } catch (IllegalArgumentException illegalArgumentException) {
/*     */                   throw a(null);
/*     */                 }  
/*     */             } catch (IllegalArgumentException illegalArgumentException) {
/*     */               throw a(null);
/*     */             } 
/*     */             break;
/*     */           } 
/*     */         } catch (IllegalArgumentException illegalArgumentException) {
/*     */           throw a(null);
/*     */         } 
/*     */         continue;
/*     */         try {
/*     */           paramArrayOfint[k] = m;
/*     */           if (paramInt1 == k - 1) {
/*     */             k--;
/*     */             break;
/*     */           } 
/*     */         } catch (IllegalArgumentException illegalArgumentException) {
/*     */           throw a(null);
/*     */         } 
/*     */       } 
/*     */       paramArrayOfint[k] = j;
/*     */     } 
/*     */   }
/*     */   
/*     */   private static void j(long[] paramArrayOflong, int paramInt1, int paramInt2) {
/*     */     for (int i = paramInt1; ++i < paramInt2; ) {
/*     */       long l1 = paramArrayOflong[i];
/*     */       int j = i;
/*     */       long l2 = paramArrayOflong[j - 1];
/*     */       while (true) {
/*     */         try {
/*     */           if (l1 < l2) {
/*     */             try {
/*     */               paramArrayOflong[j] = l2;
/*     */               if (paramInt1 == j - 1) {
/*     */                 j--;
/*     */                 break;
/*     */               } 
/*     */             } catch (IllegalArgumentException illegalArgumentException) {
/*     */               throw a(null);
/*     */             } 
/*     */             l2 = paramArrayOflong[--j - 1];
/*     */             continue;
/*     */           } 
/*     */         } catch (IllegalArgumentException illegalArgumentException) {
/*     */           throw a(null);
/*     */         } 
/*     */         break;
/*     */       } 
/*     */       paramArrayOflong[j] = l1;
/*     */     } 
/*     */   }
/*     */   
/*     */   public static void b(int[] paramArrayOfint, long[] paramArrayOflong) {
/*     */     c(paramArrayOfint, paramArrayOflong, 0, paramArrayOflong.length);
/*     */   }
/*     */   
/*     */   public static void b(int[] paramArrayOfint, long[] paramArrayOflong, int paramInt1, int paramInt2, boolean paramBoolean) {
/*     */     ForkJoinPool forkJoinPool = a();
/*     */     try {
/*     */       if (paramInt2 - paramInt1 >= 1024)
/*     */         try {
/*     */           if (forkJoinPool.getParallelism() != 1) {
/*     */             byte b = 7;
/*     */             LinkedBlockingQueue<cw> linkedBlockingQueue = new LinkedBlockingQueue();
/*     */             linkedBlockingQueue.add(new cw(paramInt1, paramInt2 - paramInt1, 0));
/*     */             AtomicInteger atomicInteger = new AtomicInteger(1);
/*     */             int i = forkJoinPool.getParallelism();
/*     */             ExecutorCompletionService executorCompletionService = new ExecutorCompletionService(forkJoinPool);
/*     */             try {
/*     */             
/*     */             } catch (Exception exception) {
/*     */               throw a(null);
/*     */             } 
/*     */             int[] arrayOfInt = paramBoolean ? new int[paramArrayOfint.length] : null;
/*     */             int j = i;
/*     */             try {
/*     */               for (; j-- != 0; executorCompletionService.submit(() -> {
/*     */                     int[] arrayOfInt1 = new int[256];
/*     */                     int[] arrayOfInt2 = new int[256];
/*     */                     while (true) {
/*     */                       if (paramAtomicInteger.get() == 0) {
/*     */                         int i3 = paramInt;
/*     */                         try {
/*     */                           while (i3-- != 0)
/*     */                             paramLinkedBlockingQueue.add(e); 
/*     */                         } catch (Exception exception) {
/*     */                           throw a(null);
/*     */                         } 
/*     */                       } 
/*     */                       cw cw1 = paramLinkedBlockingQueue.take();
/*     */                       try {
/*     */                         if (cw1 == e)
/*     */                           return null; 
/*     */                       } catch (Exception exception) {
/*     */                         throw a(null);
/*     */                       } 
/*     */                       int i = cw1.a;
/*     */                       int j = cw1.c;
/*     */                       int k = cw1.b;
/*     */                       try {
/*     */                       
/*     */                       } catch (Exception exception) {
/*     */                         throw a(null);
/*     */                       } 
/*     */                       boolean bool = (k % 8 == 0) ? true : false;
/*     */                       int m = (7 - k % 8) * 8;
/*     */                       int n = i + j;
/*     */                       try {
/*     */                         while (n-- != i)
/*     */                           arrayOfInt1[(int)(paramArrayOflong[paramArrayOfint1[n]] >>> m & 0xFFL ^ bool)] = arrayOfInt1[(int)(paramArrayOflong[paramArrayOfint1[n]] >>> m & 0xFFL ^ bool)] + 1; 
/*     */                       } catch (Exception exception) {
/*     */                         throw a(null);
/*     */                       } 
/*     */                       n = -1;
/*     */                       int i1 = 0;
/*     */                       int i2 = i;
/*     */                       while (true) {
/*     */                         try {
/*     */                           if (i1 < 256) {
/*     */                             if (arrayOfInt1[i1] != 0)
/*     */                               n = i1; 
/*     */                             arrayOfInt2[i1] = i2 += arrayOfInt1[i1];
/*     */                             i1++;
/*     */                           } 
/*     */                         } catch (Exception exception) {
/*     */                           throw a(null);
/*     */                         } 
/*     */                         if (paramBoolean) {
/*     */                           i1 = i + j;
/*     */                           try {
/*     */                             while (i1-- != i) {
/*     */                               arrayOfInt2[(int)(paramArrayOflong[paramArrayOfint1[i1]] >>> m & 0xFFL ^ bool)] = arrayOfInt2[(int)(paramArrayOflong[paramArrayOfint1[i1]] >>> m & 0xFFL ^ bool)] - 1;
/*     */                               paramArrayOfint2[arrayOfInt2[(int)(paramArrayOflong[paramArrayOfint1[i1]] >>> m & 0xFFL ^ bool)] - 1] = paramArrayOfint1[i1];
/*     */                             } 
/*     */                           } catch (Exception exception) {
/*     */                             throw a(null);
/*     */                           } 
/*     */                           System.arraycopy(paramArrayOfint2, i, paramArrayOfint1, i, j);
/*     */                           i1 = 0;
/*     */                           i2 = i;
/*     */                           while (true) {
/*     */                             try {
/*     */                               if (i1 <= n) {
/*     */                                 try {
/*     */                                   if (k < 7)
/*     */                                     try {
/*     */                                       if (arrayOfInt1[i1] > 1)
/*     */                                         try {
/*     */                                           if (arrayOfInt1[i1] < 1024) {
/*     */                                             a(paramArrayOfint1, paramArrayOflong, i2, i2 + arrayOfInt1[i1], paramBoolean);
/*     */                                           } else {
/*     */                                             paramAtomicInteger.incrementAndGet();
/*     */                                             paramLinkedBlockingQueue.add(new cw(i2, arrayOfInt1[i1], k + 1));
/*     */                                           } 
/*     */                                         } catch (Exception exception) {
/*     */                                           throw a(null);
/*     */                                         }  
/*     */                                     } catch (Exception exception) {
/*     */                                       throw a(null);
/*     */                                     }  
/*     */                                 } catch (Exception exception) {
/*     */                                   throw a(null);
/*     */                                 } 
/*     */                                 i2 += arrayOfInt1[i1];
/*     */                               } 
/*     */                             } catch (Exception exception) {
/*     */                               throw a(null);
/*     */                             } 
/*     */                             Arrays.fill(arrayOfInt1, 0);
/*     */                             break;
/*     */                           } 
/*     */                           break;
/*     */                         } 
/*     */                         i1 = i + j - arrayOfInt1[n];
/*     */                         i2 = i;
/*     */                         int i3 = -1;
/*     */                         while (i2 <= i1) {
/*     */                           int i4 = paramArrayOfint1[i2];
/*     */                           i3 = (int)(paramArrayOflong[i4] >>> m & 0xFFL ^ bool);
/*     */                           if (i2 < i1) {
/*     */                             arrayOfInt2[i3] = arrayOfInt2[i3] - 1;
/*     */                             int i5;
/*     */                             while ((i5 = arrayOfInt2[i3] - 1) > i2) {
/*     */                               int i6 = i4;
/*     */                               i4 = paramArrayOfint1[i5];
/*     */                               paramArrayOfint1[i5] = i6;
/*     */                               i3 = (int)(paramArrayOflong[i4] >>> m & 0xFFL ^ bool);
/*     */                             } 
/*     */                             paramArrayOfint1[i2] = i4;
/*     */                           } 
/*     */                           try {
/*     */                             if (k < 7)
/*     */                               try {
/*     */                                 if (arrayOfInt1[i3] > 1)
/*     */                                   try {
/*     */                                     if (arrayOfInt1[i3] < 1024) {
/*     */                                       a(paramArrayOfint1, paramArrayOflong, i2, i2 + arrayOfInt1[i3], paramBoolean);
/*     */                                     } else {
/*     */                                       paramAtomicInteger.incrementAndGet();
/*     */                                       paramLinkedBlockingQueue.add(new cw(i2, arrayOfInt1[i3], k + 1));
/*     */                                     } 
/*     */                                   } catch (Exception exception) {
/*     */                                     throw a(null);
/*     */                                   }  
/*     */                               } catch (Exception exception) {
/*     */                                 throw a(null);
/*     */                               }  
/*     */                           } catch (Exception exception) {
/*     */                             throw a(null);
/*     */                           } 
/*     */                           i2 += arrayOfInt1[i3];
/*     */                           arrayOfInt1[i3] = 0;
/*     */                         } 
/*     */                         paramAtomicInteger.decrementAndGet();
/*     */                       } 
/*     */                       paramAtomicInteger.decrementAndGet();
/*     */                     } 
/*     */                   }));
/*     */             } catch (Exception exception) {
/*     */               throw a(null);
/*     */             } 
/*     */             Throwable throwable = null;
/*     */             for (int k = i; k-- != 0; throwable = exception.getCause()) {
/*     */               try {
/*     */                 executorCompletionService.take().get();
/*     */                 continue;
/*     */               } catch (Exception exception) {}
/*     */             } 
/*     */             try {
/*     */               if (throwable != null) {
/*     */                 try {
/*     */                 
/*     */                 } catch (Exception exception) {
/*     */                   throw a(null);
/*     */                 } 
/*     */                 throw (throwable instanceof RuntimeException) ? (RuntimeException)throwable : new RuntimeException(throwable);
/*     */               } 
/*     */             } catch (Exception exception) {
/*     */               throw a(null);
/*     */             } 
/*     */             return;
/*     */           } 
/*     */           a(paramArrayOfint, paramArrayOflong, paramInt1, paramInt2, paramBoolean);
/*     */           return;
/*     */         } catch (Exception exception) {
/*     */           throw a(null);
/*     */         }  
/*     */     } catch (Exception exception) {
/*     */       throw a(null);
/*     */     } 
/*     */     a(paramArrayOfint, paramArrayOflong, paramInt1, paramInt2, paramBoolean);
/*     */   }
/*     */   
/*     */   public static void e(long[] paramArrayOflong, int paramInt1, int paramInt2) {
/*     */     aL.a(paramArrayOflong.length, paramInt1, paramInt2);
/*     */   }
/*     */   
/*     */   public static void g(long[] paramArrayOflong1, long[] paramArrayOflong2, int paramInt1, int paramInt2) {
/*     */     // Byte code:
/*     */     //   0: getstatic me/konsolas/aac/a1.o : J
/*     */     //   3: ldc2_w 136716239400977
/*     */     //   6: lxor
/*     */     //   7: lstore #4
/*     */     //   9: invokestatic a : ()Ljava/util/concurrent/ForkJoinPool;
/*     */     //   12: astore #6
/*     */     //   14: iload_3
/*     */     //   15: iload_2
/*     */     //   16: isub
/*     */     //   17: sipush #1024
/*     */     //   20: if_icmplt -> 46
/*     */     //   23: aload #6
/*     */     //   25: invokevirtual getParallelism : ()I
/*     */     //   28: iconst_1
/*     */     //   29: if_icmpne -> 65
/*     */     //   32: goto -> 46
/*     */     //   35: ldc2_w 1371971430527489396
/*     */     //   38: lload #4
/*     */     //   40: <illegal opcode> w : (Ljava/lang/Exception;JJ)Ljava/lang/Exception;
/*     */     //   45: athrow
/*     */     //   46: aload_0
/*     */     //   47: aload_1
/*     */     //   48: iload_2
/*     */     //   49: iload_3
/*     */     //   50: invokestatic c : ([J[JII)V
/*     */     //   53: return
/*     */     //   54: ldc2_w 1371971430527489396
/*     */     //   57: lload #4
/*     */     //   59: <illegal opcode> w : (Ljava/lang/Exception;JJ)Ljava/lang/Exception;
/*     */     //   64: athrow
/*     */     //   65: iconst_2
/*     */     //   66: istore #7
/*     */     //   68: aload_0
/*     */     //   69: arraylength
/*     */     //   70: aload_1
/*     */     //   71: arraylength
/*     */     //   72: if_icmpeq -> 119
/*     */     //   75: new java/lang/IllegalArgumentException
/*     */     //   78: dup
/*     */     //   79: ldc_w '؇開튙뮋損㩃ѽᐕ⹉찺帓辇?搶ꀞꃷ薘ኯ쾰⸁'
/*     */     //   82: invokevirtual toCharArray : ()[C
/*     */     //   85: dup
/*     */     //   86: dup
/*     */     //   87: iconst_0
/*     */     //   88: dup_x1
/*     */     //   89: caload
/*     */     //   90: sipush #14801
/*     */     //   93: ixor
/*     */     //   94: i2c
/*     */     //   95: castore
/*     */     //   96: sipush #4701
/*     */     //   99: iconst_1
/*     */     //   100: iconst_0
/*     */     //   101: invokestatic A : (Ljava/lang/Object;SZI)Ljava/lang/String;
/*     */     //   104: invokespecial <init> : (Ljava/lang/String;)V
/*     */     //   107: athrow
/*     */     //   108: ldc2_w 1371971430527489396
/*     */     //   111: lload #4
/*     */     //   113: <illegal opcode> w : (Ljava/lang/Exception;JJ)Ljava/lang/Exception;
/*     */     //   118: athrow
/*     */     //   119: bipush #15
/*     */     //   121: istore #8
/*     */     //   123: new java/util/concurrent/LinkedBlockingQueue
/*     */     //   126: dup
/*     */     //   127: invokespecial <init> : ()V
/*     */     //   130: astore #9
/*     */     //   132: aload #9
/*     */     //   134: new me/konsolas/aac/cw
/*     */     //   137: dup
/*     */     //   138: iload_2
/*     */     //   139: iload_3
/*     */     //   140: iload_2
/*     */     //   141: isub
/*     */     //   142: iconst_0
/*     */     //   143: invokespecial <init> : (III)V
/*     */     //   146: invokevirtual add : (Ljava/lang/Object;)Z
/*     */     //   149: pop
/*     */     //   150: new java/util/concurrent/atomic/AtomicInteger
/*     */     //   153: dup
/*     */     //   154: iconst_1
/*     */     //   155: invokespecial <init> : (I)V
/*     */     //   158: astore #10
/*     */     //   160: aload #6
/*     */     //   162: invokevirtual getParallelism : ()I
/*     */     //   165: istore #11
/*     */     //   167: new java/util/concurrent/ExecutorCompletionService
/*     */     //   170: dup
/*     */     //   171: aload #6
/*     */     //   173: invokespecial <init> : (Ljava/util/concurrent/Executor;)V
/*     */     //   176: astore #12
/*     */     //   178: iload #11
/*     */     //   180: istore #13
/*     */     //   182: iload #13
/*     */     //   184: iinc #13, -1
/*     */     //   187: ifeq -> 223
/*     */     //   190: aload #12
/*     */     //   192: aload #10
/*     */     //   194: iload #11
/*     */     //   196: aload #9
/*     */     //   198: aload_0
/*     */     //   199: aload_1
/*     */     //   200: <illegal opcode> call : (Ljava/util/concurrent/atomic/AtomicInteger;ILjava/util/concurrent/LinkedBlockingQueue;[J[J)Ljava/util/concurrent/Callable;
/*     */     //   205: invokevirtual submit : (Ljava/util/concurrent/Callable;)Ljava/util/concurrent/Future;
/*     */     //   208: pop
/*     */     //   209: goto -> 182
/*     */     //   212: ldc2_w 1371971430527489396
/*     */     //   215: lload #4
/*     */     //   217: <illegal opcode> w : (Ljava/lang/Exception;JJ)Ljava/lang/Exception;
/*     */     //   222: athrow
/*     */     //   223: aconst_null
/*     */     //   224: astore #13
/*     */     //   226: iload #11
/*     */     //   228: istore #14
/*     */     //   230: iload #14
/*     */     //   232: iinc #14, -1
/*     */     //   235: ifeq -> 264
/*     */     //   238: aload #12
/*     */     //   240: invokevirtual take : ()Ljava/util/concurrent/Future;
/*     */     //   243: invokeinterface get : ()Ljava/lang/Object;
/*     */     //   248: pop
/*     */     //   249: goto -> 230
/*     */     //   252: astore #15
/*     */     //   254: aload #15
/*     */     //   256: invokevirtual getCause : ()Ljava/lang/Throwable;
/*     */     //   259: astore #13
/*     */     //   261: goto -> 230
/*     */     //   264: aload #13
/*     */     //   266: ifnull -> 320
/*     */     //   269: aload #13
/*     */     //   271: instanceof java/lang/RuntimeException
/*     */     //   274: ifeq -> 310
/*     */     //   277: goto -> 291
/*     */     //   280: ldc2_w 1371971430527489396
/*     */     //   283: lload #4
/*     */     //   285: <illegal opcode> w : (Ljava/lang/Exception;JJ)Ljava/lang/Exception;
/*     */     //   290: athrow
/*     */     //   291: aload #13
/*     */     //   293: checkcast java/lang/RuntimeException
/*     */     //   296: goto -> 319
/*     */     //   299: ldc2_w 1371971430527489396
/*     */     //   302: lload #4
/*     */     //   304: <illegal opcode> w : (Ljava/lang/Exception;JJ)Ljava/lang/Exception;
/*     */     //   309: athrow
/*     */     //   310: new java/lang/RuntimeException
/*     */     //   313: dup
/*     */     //   314: aload #13
/*     */     //   316: invokespecial <init> : (Ljava/lang/Throwable;)V
/*     */     //   319: athrow
/*     */     //   320: return
/*     */     // Line number table:
/*     */     //   Java source line number -> byte code offset
/*     */     //   #389	-> 9
/*     */     //   #928	-> 14
/*     */     //   #619	-> 46
/*     */     //   #86	-> 53
/*     */     //   #787	-> 65
/*     */     //   #921	-> 68
/*     */     //   #772	-> 119
/*     */     //   #26	-> 123
/*     */     //   #569	-> 132
/*     */     //   #213	-> 150
/*     */     //   #475	-> 160
/*     */     //   #398	-> 167
/*     */     //   #917	-> 178
/*     */     //   #601	-> 223
/*     */     //   #72	-> 226
/*     */     //   #149	-> 238
/*     */     //   #679	-> 249
/*     */     //   #117	-> 252
/*     */     //   #807	-> 254
/*     */     //   #345	-> 261
/*     */     //   #736	-> 264
/*     */     //   #359	-> 320
/*     */     // Exception table:
/*     */     //   from	to	target	type
/*     */     //   14	32	35	java/lang/Exception
/*     */     //   23	54	54	java/lang/Exception
/*     */     //   68	108	108	java/lang/Exception
/*     */     //   182	212	212	java/lang/Exception
/*     */     //   238	249	252	java/lang/Exception
/*     */     //   264	277	280	java/lang/Exception
/*     */     //   269	299	299	java/lang/Exception
/*     */   }
/*     */   
/*     */   public static long[] c(long[] paramArrayOflong, int paramInt1, int paramInt2) {
/*     */     if (paramInt1 > paramArrayOflong.length) {
/*     */       int i = (int)Math.max(Math.min(paramArrayOflong.length + (paramArrayOflong.length >> 1), 2147483639L), paramInt1);
/*     */       long[] arrayOfLong = new long[i];
/*     */       System.arraycopy(paramArrayOflong, 0, arrayOfLong, 0, paramInt2);
/*     */     } 
/*     */     return paramArrayOflong;
/*     */   }
/*     */   
/*     */   public static long[] e(long[] paramArrayOflong, int paramInt1, int paramInt2) {
/*     */     long[] arrayOfLong = new long[paramInt1];
/*     */     System.arraycopy(paramArrayOflong, 0, arrayOfLong, 0, paramInt2);
/*     */     return arrayOfLong;
/*     */   }
/*     */   
/*     */   public static void b(long[] paramArrayOflong, hq paramhq) {
/*     */     e(paramArrayOflong, 0, paramArrayOflong.length, paramhq);
/*     */   }
/*     */   
/*     */   public static void g(long[] paramArrayOflong, int paramInt1, int paramInt2) {
/*     */     a(paramArrayOflong, paramInt1, paramInt2, (long[])null);
/*     */   }
/*     */   
/*     */   public static void i(long[] paramArrayOflong, int paramInt1, int paramInt2) {
/*     */     ForkJoinPool forkJoinPool = a();
/*     */     try {
/*     */       if (paramInt2 - paramInt1 >= 8192) {
/*     */         try {
/*     */           if (forkJoinPool.getParallelism() == 1) {
/*     */             c(paramArrayOflong, paramInt1, paramInt2);
/*     */             return;
/*     */           } 
/*     */         } catch (IllegalArgumentException illegalArgumentException) {
/*     */           throw a(null);
/*     */         } 
/*     */         forkJoinPool.invoke(new hX(paramArrayOflong, paramInt1, paramInt2));
/*     */         return;
/*     */       } 
/*     */     } catch (IllegalArgumentException illegalArgumentException) {
/*     */       throw a(null);
/*     */     } 
/*     */     c(paramArrayOflong, paramInt1, paramInt2);
/*     */   }
/*     */   
/*     */   public static void c(int[] paramArrayOfint, long[] paramArrayOflong, int paramInt1, int paramInt2) {
/*     */     // Byte code:
/*     */     //   0: iload_3
/*     */     //   1: iload_2
/*     */     //   2: isub
/*     */     //   3: istore #4
/*     */     //   5: iload #4
/*     */     //   7: bipush #16
/*     */     //   9: if_icmpge -> 24
/*     */     //   12: aload_0
/*     */     //   13: aload_1
/*     */     //   14: iload_2
/*     */     //   15: iload_3
/*     */     //   16: invokestatic a : ([I[JII)V
/*     */     //   19: return
/*     */     //   20: invokestatic a : (Ljava/lang/Exception;)Ljava/lang/Exception;
/*     */     //   23: athrow
/*     */     //   24: iload_2
/*     */     //   25: iload #4
/*     */     //   27: iconst_2
/*     */     //   28: idiv
/*     */     //   29: iadd
/*     */     //   30: istore #5
/*     */     //   32: iload_2
/*     */     //   33: istore #6
/*     */     //   35: iload_3
/*     */     //   36: iconst_1
/*     */     //   37: isub
/*     */     //   38: istore #7
/*     */     //   40: iload #4
/*     */     //   42: sipush #128
/*     */     //   45: if_icmple -> 116
/*     */     //   48: iload #4
/*     */     //   50: bipush #8
/*     */     //   52: idiv
/*     */     //   53: istore #8
/*     */     //   55: aload_0
/*     */     //   56: aload_1
/*     */     //   57: iload #6
/*     */     //   59: iload #6
/*     */     //   61: iload #8
/*     */     //   63: iadd
/*     */     //   64: iload #6
/*     */     //   66: iconst_2
/*     */     //   67: iload #8
/*     */     //   69: imul
/*     */     //   70: iadd
/*     */     //   71: invokestatic a : ([I[JIII)I
/*     */     //   74: istore #6
/*     */     //   76: aload_0
/*     */     //   77: aload_1
/*     */     //   78: iload #5
/*     */     //   80: iload #8
/*     */     //   82: isub
/*     */     //   83: iload #5
/*     */     //   85: iload #5
/*     */     //   87: iload #8
/*     */     //   89: iadd
/*     */     //   90: invokestatic a : ([I[JIII)I
/*     */     //   93: istore #5
/*     */     //   95: aload_0
/*     */     //   96: aload_1
/*     */     //   97: iload #7
/*     */     //   99: iconst_2
/*     */     //   100: iload #8
/*     */     //   102: imul
/*     */     //   103: isub
/*     */     //   104: iload #7
/*     */     //   106: iload #8
/*     */     //   108: isub
/*     */     //   109: iload #7
/*     */     //   111: invokestatic a : ([I[JIII)I
/*     */     //   114: istore #7
/*     */     //   116: aload_0
/*     */     //   117: aload_1
/*     */     //   118: iload #6
/*     */     //   120: iload #5
/*     */     //   122: iload #7
/*     */     //   124: invokestatic a : ([I[JIII)I
/*     */     //   127: istore #5
/*     */     //   129: aload_1
/*     */     //   130: aload_0
/*     */     //   131: iload #5
/*     */     //   133: iaload
/*     */     //   134: laload
/*     */     //   135: lstore #8
/*     */     //   137: iload_2
/*     */     //   138: istore #10
/*     */     //   140: iload #10
/*     */     //   142: istore #11
/*     */     //   144: iload_3
/*     */     //   145: iconst_1
/*     */     //   146: isub
/*     */     //   147: istore #12
/*     */     //   149: iload #12
/*     */     //   151: istore #13
/*     */     //   153: iload #11
/*     */     //   155: iload #12
/*     */     //   157: if_icmpgt -> 213
/*     */     //   160: aload_1
/*     */     //   161: aload_0
/*     */     //   162: iload #11
/*     */     //   164: iaload
/*     */     //   165: laload
/*     */     //   166: lload #8
/*     */     //   168: invokestatic compare : (JJ)I
/*     */     //   171: dup
/*     */     //   172: istore #14
/*     */     //   174: ifgt -> 213
/*     */     //   177: iload #14
/*     */     //   179: ifne -> 207
/*     */     //   182: goto -> 189
/*     */     //   185: invokestatic a : (Ljava/lang/Exception;)Ljava/lang/Exception;
/*     */     //   188: athrow
/*     */     //   189: aload_0
/*     */     //   190: iload #10
/*     */     //   192: iinc #10, 1
/*     */     //   195: iload #11
/*     */     //   197: invokestatic g : ([III)V
/*     */     //   200: goto -> 207
/*     */     //   203: invokestatic a : (Ljava/lang/Exception;)Ljava/lang/Exception;
/*     */     //   206: athrow
/*     */     //   207: iinc #11, 1
/*     */     //   210: goto -> 153
/*     */     //   213: iload #12
/*     */     //   215: iload #11
/*     */     //   217: if_icmplt -> 273
/*     */     //   220: aload_1
/*     */     //   221: aload_0
/*     */     //   222: iload #12
/*     */     //   224: iaload
/*     */     //   225: laload
/*     */     //   226: lload #8
/*     */     //   228: invokestatic compare : (JJ)I
/*     */     //   231: dup
/*     */     //   232: istore #14
/*     */     //   234: iflt -> 273
/*     */     //   237: iload #14
/*     */     //   239: ifne -> 267
/*     */     //   242: goto -> 249
/*     */     //   245: invokestatic a : (Ljava/lang/Exception;)Ljava/lang/Exception;
/*     */     //   248: athrow
/*     */     //   249: aload_0
/*     */     //   250: iload #12
/*     */     //   252: iload #13
/*     */     //   254: iinc #13, -1
/*     */     //   257: invokestatic g : ([III)V
/*     */     //   260: goto -> 267
/*     */     //   263: invokestatic a : (Ljava/lang/Exception;)Ljava/lang/Exception;
/*     */     //   266: athrow
/*     */     //   267: iinc #12, -1
/*     */     //   270: goto -> 213
/*     */     //   273: iload #11
/*     */     //   275: iload #12
/*     */     //   277: if_icmple -> 287
/*     */     //   280: goto -> 304
/*     */     //   283: invokestatic a : (Ljava/lang/Exception;)Ljava/lang/Exception;
/*     */     //   286: athrow
/*     */     //   287: aload_0
/*     */     //   288: iload #11
/*     */     //   290: iinc #11, 1
/*     */     //   293: iload #12
/*     */     //   295: iinc #12, -1
/*     */     //   298: invokestatic g : ([III)V
/*     */     //   301: goto -> 153
/*     */     //   304: iload #10
/*     */     //   306: iload_2
/*     */     //   307: isub
/*     */     //   308: iload #11
/*     */     //   310: iload #10
/*     */     //   312: isub
/*     */     //   313: invokestatic min : (II)I
/*     */     //   316: istore #14
/*     */     //   318: aload_0
/*     */     //   319: iload_2
/*     */     //   320: iload #11
/*     */     //   322: iload #14
/*     */     //   324: isub
/*     */     //   325: iload #14
/*     */     //   327: invokestatic b : ([IIII)V
/*     */     //   330: iload #13
/*     */     //   332: iload #12
/*     */     //   334: isub
/*     */     //   335: iload_3
/*     */     //   336: iload #13
/*     */     //   338: isub
/*     */     //   339: iconst_1
/*     */     //   340: isub
/*     */     //   341: invokestatic min : (II)I
/*     */     //   344: istore #14
/*     */     //   346: aload_0
/*     */     //   347: iload #11
/*     */     //   349: iload_3
/*     */     //   350: iload #14
/*     */     //   352: isub
/*     */     //   353: iload #14
/*     */     //   355: invokestatic b : ([IIII)V
/*     */     //   358: iload #11
/*     */     //   360: iload #10
/*     */     //   362: isub
/*     */     //   363: dup
/*     */     //   364: istore #14
/*     */     //   366: iconst_1
/*     */     //   367: if_icmple -> 387
/*     */     //   370: aload_0
/*     */     //   371: aload_1
/*     */     //   372: iload_2
/*     */     //   373: iload_2
/*     */     //   374: iload #14
/*     */     //   376: iadd
/*     */     //   377: invokestatic c : ([I[JII)V
/*     */     //   380: goto -> 387
/*     */     //   383: invokestatic a : (Ljava/lang/Exception;)Ljava/lang/Exception;
/*     */     //   386: athrow
/*     */     //   387: iload #13
/*     */     //   389: iload #12
/*     */     //   391: isub
/*     */     //   392: dup
/*     */     //   393: istore #14
/*     */     //   395: iconst_1
/*     */     //   396: if_icmple -> 416
/*     */     //   399: aload_0
/*     */     //   400: aload_1
/*     */     //   401: iload_3
/*     */     //   402: iload #14
/*     */     //   404: isub
/*     */     //   405: iload_3
/*     */     //   406: invokestatic c : ([I[JII)V
/*     */     //   409: goto -> 416
/*     */     //   412: invokestatic a : (Ljava/lang/Exception;)Ljava/lang/Exception;
/*     */     //   415: athrow
/*     */     //   416: return
/*     */     // Line number table:
/*     */     //   Java source line number -> byte code offset
/*     */     //   #454	-> 0
/*     */     //   #839	-> 5
/*     */     //   #333	-> 12
/*     */     //   #509	-> 19
/*     */     //   #695	-> 24
/*     */     //   #709	-> 32
/*     */     //   #890	-> 35
/*     */     //   #757	-> 40
/*     */     //   #519	-> 48
/*     */     //   #185	-> 55
/*     */     //   #417	-> 76
/*     */     //   #524	-> 95
/*     */     //   #837	-> 116
/*     */     //   #501	-> 129
/*     */     //   #518	-> 137
/*     */     //   #660	-> 153
/*     */     //   #449	-> 177
/*     */     //   #46	-> 207
/*     */     //   #487	-> 213
/*     */     //   #110	-> 237
/*     */     //   #541	-> 267
/*     */     //   #903	-> 273
/*     */     //   #396	-> 287
/*     */     //   #200	-> 304
/*     */     //   #194	-> 318
/*     */     //   #248	-> 330
/*     */     //   #338	-> 346
/*     */     //   #208	-> 358
/*     */     //   #542	-> 387
/*     */     //   #361	-> 416
/*     */     // Exception table:
/*     */     //   from	to	target	type
/*     */     //   5	20	20	java/lang/IllegalArgumentException
/*     */     //   174	182	185	java/lang/IllegalArgumentException
/*     */     //   177	200	203	java/lang/IllegalArgumentException
/*     */     //   234	242	245	java/lang/IllegalArgumentException
/*     */     //   237	260	263	java/lang/IllegalArgumentException
/*     */     //   273	283	283	java/lang/IllegalArgumentException
/*     */     //   366	380	383	java/lang/IllegalArgumentException
/*     */     //   395	409	412	java/lang/IllegalArgumentException
/*     */   }
/*     */   
/*     */   public static void a(int[] paramArrayOfint, long[] paramArrayOflong1, long[] paramArrayOflong2, boolean paramBoolean) {
/*     */     e(paramArrayOflong1, paramArrayOflong2);
/*     */     a(paramArrayOfint, paramArrayOflong1, paramArrayOflong2, 0, paramArrayOflong1.length, paramBoolean);
/*     */   }
/*     */   
/*     */   public static void a(int[] paramArrayOfint, long[] paramArrayOflong1, long[] paramArrayOflong2, int paramInt1, int paramInt2, boolean paramBoolean) {
/*     */     try {
/*     */       if (paramInt2 - paramInt1 < 1024) {
/*     */         a(paramArrayOfint, paramArrayOflong1, paramArrayOflong2, paramInt1, paramInt2);
/*     */         return;
/*     */       } 
/*     */     } catch (IllegalArgumentException illegalArgumentException) {
/*     */       throw a(null);
/*     */     } 
/*     */     byte b1 = 2;
/*     */     byte b2 = 15;
/*     */     char c = '໲';
/*     */     byte b3 = 0;
/*     */     int[] arrayOfInt1 = new int[3826];
/*     */     int[] arrayOfInt2 = new int[3826];
/*     */     int[] arrayOfInt3 = new int[3826];
/*     */     arrayOfInt1[b3] = paramInt1;
/*     */     arrayOfInt2[b3] = paramInt2 - paramInt1;
/*     */     arrayOfInt3[b3++] = 0;
/*     */     int[] arrayOfInt4 = new int[256];
/*     */     int[] arrayOfInt5 = new int[256];
/*     */     try {
/*     */     
/*     */     } catch (IllegalArgumentException illegalArgumentException) {
/*     */       throw a(null);
/*     */     } 
/*     */     int[] arrayOfInt6 = paramBoolean ? new int[paramArrayOfint.length] : null;
/*     */     while (b3 > 0) {
/*     */       int i = arrayOfInt1[--b3];
/*     */       int j = arrayOfInt2[b3];
/*     */       int k = arrayOfInt3[b3];
/*     */     } 
/*     */   }
/*     */   
/*     */   public static void a(long[][] paramArrayOflong, int paramInt1, int paramInt2) {
/*     */     // Byte code:
/*     */     //   0: getstatic me/konsolas/aac/a1.o : J
/*     */     //   3: ldc2_w 39576515733121
/*     */     //   6: lxor
/*     */     //   7: lstore_3
/*     */     //   8: iload_2
/*     */     //   9: iload_1
/*     */     //   10: isub
/*     */     //   11: sipush #1024
/*     */     //   14: if_icmpge -> 35
/*     */     //   17: aload_0
/*     */     //   18: iload_1
/*     */     //   19: iload_2
/*     */     //   20: iconst_0
/*     */     //   21: invokestatic a : ([[JIII)V
/*     */     //   24: return
/*     */     //   25: ldc2_w 403748461399786468
/*     */     //   28: lload_3
/*     */     //   29: <illegal opcode> w : (Ljava/lang/Exception;JJ)Ljava/lang/Exception;
/*     */     //   34: athrow
/*     */     //   35: aload_0
/*     */     //   36: arraylength
/*     */     //   37: istore #5
/*     */     //   39: bipush #8
/*     */     //   41: iload #5
/*     */     //   43: imul
/*     */     //   44: iconst_1
/*     */     //   45: isub
/*     */     //   46: istore #6
/*     */     //   48: iload #5
/*     */     //   50: istore #7
/*     */     //   52: aload_0
/*     */     //   53: iconst_0
/*     */     //   54: aaload
/*     */     //   55: arraylength
/*     */     //   56: istore #8
/*     */     //   58: iload #7
/*     */     //   60: iinc #7, -1
/*     */     //   63: ifeq -> 157
/*     */     //   66: aload_0
/*     */     //   67: iload #7
/*     */     //   69: aaload
/*     */     //   70: arraylength
/*     */     //   71: iload #8
/*     */     //   73: if_icmpeq -> 58
/*     */     //   76: new java/lang/IllegalArgumentException
/*     */     //   79: dup
/*     */     //   80: new java/lang/StringBuilder
/*     */     //   83: dup
/*     */     //   84: invokespecial <init> : ()V
/*     */     //   87: ldc_w '鋤䂙Ɵ饘࿂꼧?墂튠眤뺚ẕ㼐齬㞐촢㕱'
/*     */     //   90: invokevirtual toCharArray : ()[C
/*     */     //   93: dup
/*     */     //   94: dup
/*     */     //   95: bipush #11
/*     */     //   97: dup_x1
/*     */     //   98: caload
/*     */     //   99: sipush #8774
/*     */     //   102: ixor
/*     */     //   103: i2c
/*     */     //   104: castore
/*     */     //   105: sipush #29839
/*     */     //   108: iconst_5
/*     */     //   109: iconst_5
/*     */     //   110: invokestatic H : (Ljava/lang/Object;SBB)Ljava/lang/String;
/*     */     //   113: invokevirtual append : (Ljava/lang/String;)Ljava/lang/StringBuilder;
/*     */     //   116: iload #7
/*     */     //   118: invokevirtual append : (I)Ljava/lang/StringBuilder;
/*     */     //   121: ldc_w '?ᛱꨕ怜嵫뒔ㅆ㸓맛埓쟬??אּ�佲䪮뽃즂챑瑩䮕몍딄꺳ꬫ童웻䊏쑄讎팿ꡔㅉ澎乐댋Ჶ陦䓃?衂ᦲ尘'
/*     */     //   124: invokevirtual toCharArray : ()[C
/*     */     //   127: dup
/*     */     //   128: dup
/*     */     //   129: bipush #18
/*     */     //   131: dup_x1
/*     */     //   132: caload
/*     */     //   133: sipush #18218
/*     */     //   136: ixor
/*     */     //   137: i2c
/*     */     //   138: castore
/*     */     //   139: sipush #1748
/*     */     //   142: iconst_1
/*     */     //   143: iconst_0
/*     */     //   144: invokestatic H : (Ljava/lang/Object;SBB)Ljava/lang/String;
/*     */     //   147: invokevirtual append : (Ljava/lang/String;)Ljava/lang/StringBuilder;
/*     */     //   150: invokevirtual toString : ()Ljava/lang/String;
/*     */     //   153: invokespecial <init> : (Ljava/lang/String;)V
/*     */     //   156: athrow
/*     */     //   157: sipush #255
/*     */     //   160: iload #5
/*     */     //   162: bipush #8
/*     */     //   164: imul
/*     */     //   165: iconst_1
/*     */     //   166: isub
/*     */     //   167: imul
/*     */     //   168: iconst_1
/*     */     //   169: iadd
/*     */     //   170: istore #7
/*     */     //   172: iconst_0
/*     */     //   173: istore #8
/*     */     //   175: iload #7
/*     */     //   177: newarray int
/*     */     //   179: astore #9
/*     */     //   181: iload #7
/*     */     //   183: newarray int
/*     */     //   185: astore #10
/*     */     //   187: iload #7
/*     */     //   189: newarray int
/*     */     //   191: astore #11
/*     */     //   193: aload #9
/*     */     //   195: iload #8
/*     */     //   197: iload_1
/*     */     //   198: iastore
/*     */     //   199: aload #10
/*     */     //   201: iload #8
/*     */     //   203: iload_2
/*     */     //   204: iload_1
/*     */     //   205: isub
/*     */     //   206: iastore
/*     */     //   207: aload #11
/*     */     //   209: iload #8
/*     */     //   211: iinc #8, 1
/*     */     //   214: iconst_0
/*     */     //   215: iastore
/*     */     //   216: sipush #256
/*     */     //   219: newarray int
/*     */     //   221: astore #12
/*     */     //   223: sipush #256
/*     */     //   226: newarray int
/*     */     //   228: astore #13
/*     */     //   230: iload #5
/*     */     //   232: newarray long
/*     */     //   234: astore #14
/*     */     //   236: iload #8
/*     */     //   238: ifle -> 778
/*     */     //   241: aload #9
/*     */     //   243: iinc #8, -1
/*     */     //   246: iload #8
/*     */     //   248: iaload
/*     */     //   249: istore #15
/*     */     //   251: aload #10
/*     */     //   253: iload #8
/*     */     //   255: iaload
/*     */     //   256: istore #16
/*     */     //   258: aload #11
/*     */     //   260: iload #8
/*     */     //   262: iaload
/*     */     //   263: istore #17
/*     */     //   265: iload #17
/*     */     //   267: bipush #8
/*     */     //   269: irem
/*     */     //   270: ifne -> 289
/*     */     //   273: sipush #128
/*     */     //   276: goto -> 290
/*     */     //   279: ldc2_w 403748461399786468
/*     */     //   282: lload_3
/*     */     //   283: <illegal opcode> w : (Ljava/lang/Exception;JJ)Ljava/lang/Exception;
/*     */     //   288: athrow
/*     */     //   289: iconst_0
/*     */     //   290: istore #18
/*     */     //   292: aload_0
/*     */     //   293: iload #17
/*     */     //   295: bipush #8
/*     */     //   297: idiv
/*     */     //   298: aaload
/*     */     //   299: astore #19
/*     */     //   301: bipush #7
/*     */     //   303: iload #17
/*     */     //   305: bipush #8
/*     */     //   307: irem
/*     */     //   308: isub
/*     */     //   309: bipush #8
/*     */     //   311: imul
/*     */     //   312: istore #20
/*     */     //   314: iload #15
/*     */     //   316: iload #16
/*     */     //   318: iadd
/*     */     //   319: istore #21
/*     */     //   321: iload #21
/*     */     //   323: iinc #21, -1
/*     */     //   326: iload #15
/*     */     //   328: if_icmpeq -> 368
/*     */     //   331: aload #12
/*     */     //   333: aload #19
/*     */     //   335: iload #21
/*     */     //   337: laload
/*     */     //   338: iload #20
/*     */     //   340: lushr
/*     */     //   341: ldc2_w 255
/*     */     //   344: land
/*     */     //   345: iload #18
/*     */     //   347: i2l
/*     */     //   348: lxor
/*     */     //   349: l2i
/*     */     //   350: dup2
/*     */     //   351: iaload
/*     */     //   352: iconst_1
/*     */     //   353: iadd
/*     */     //   354: iastore
/*     */     //   355: goto -> 321
/*     */     //   358: ldc2_w 403748461399786468
/*     */     //   361: lload_3
/*     */     //   362: <illegal opcode> w : (Ljava/lang/Exception;JJ)Ljava/lang/Exception;
/*     */     //   367: athrow
/*     */     //   368: iconst_m1
/*     */     //   369: istore #21
/*     */     //   371: iconst_0
/*     */     //   372: istore #22
/*     */     //   374: iload #15
/*     */     //   376: istore #23
/*     */     //   378: iload #22
/*     */     //   380: sipush #256
/*     */     //   383: if_icmpge -> 433
/*     */     //   386: aload #12
/*     */     //   388: iload #22
/*     */     //   390: iaload
/*     */     //   391: ifeq -> 411
/*     */     //   394: goto -> 407
/*     */     //   397: ldc2_w 403748461399786468
/*     */     //   400: lload_3
/*     */     //   401: <illegal opcode> w : (Ljava/lang/Exception;JJ)Ljava/lang/Exception;
/*     */     //   406: athrow
/*     */     //   407: iload #22
/*     */     //   409: istore #21
/*     */     //   411: aload #13
/*     */     //   413: iload #22
/*     */     //   415: iload #23
/*     */     //   417: aload #12
/*     */     //   419: iload #22
/*     */     //   421: iaload
/*     */     //   422: iadd
/*     */     //   423: dup
/*     */     //   424: istore #23
/*     */     //   426: iastore
/*     */     //   427: iinc #22, 1
/*     */     //   430: goto -> 378
/*     */     //   433: iload #15
/*     */     //   435: iload #16
/*     */     //   437: iadd
/*     */     //   438: aload #12
/*     */     //   440: iload #21
/*     */     //   442: iaload
/*     */     //   443: isub
/*     */     //   444: istore #22
/*     */     //   446: iload #15
/*     */     //   448: istore #23
/*     */     //   450: iconst_m1
/*     */     //   451: istore #24
/*     */     //   453: iload #23
/*     */     //   455: iload #22
/*     */     //   457: if_icmpgt -> 775
/*     */     //   460: iload #5
/*     */     //   462: istore #26
/*     */     //   464: iload #26
/*     */     //   466: iinc #26, -1
/*     */     //   469: ifeq -> 497
/*     */     //   472: aload #14
/*     */     //   474: iload #26
/*     */     //   476: aload_0
/*     */     //   477: iload #26
/*     */     //   479: aaload
/*     */     //   480: iload #23
/*     */     //   482: laload
/*     */     //   483: lastore
/*     */     //   484: goto -> 464
/*     */     //   487: ldc2_w 403748461399786468
/*     */     //   490: lload_3
/*     */     //   491: <illegal opcode> w : (Ljava/lang/Exception;JJ)Ljava/lang/Exception;
/*     */     //   496: athrow
/*     */     //   497: aload #19
/*     */     //   499: iload #23
/*     */     //   501: laload
/*     */     //   502: iload #20
/*     */     //   504: lushr
/*     */     //   505: ldc2_w 255
/*     */     //   508: land
/*     */     //   509: iload #18
/*     */     //   511: i2l
/*     */     //   512: lxor
/*     */     //   513: l2i
/*     */     //   514: istore #24
/*     */     //   516: iload #23
/*     */     //   518: iload #22
/*     */     //   520: if_icmpge -> 643
/*     */     //   523: aload #13
/*     */     //   525: iload #24
/*     */     //   527: dup2
/*     */     //   528: iaload
/*     */     //   529: iconst_1
/*     */     //   530: isub
/*     */     //   531: dup_x2
/*     */     //   532: iastore
/*     */     //   533: dup
/*     */     //   534: istore #25
/*     */     //   536: iload #23
/*     */     //   538: if_icmple -> 606
/*     */     //   541: aload #19
/*     */     //   543: iload #25
/*     */     //   545: laload
/*     */     //   546: iload #20
/*     */     //   548: lushr
/*     */     //   549: ldc2_w 255
/*     */     //   552: land
/*     */     //   553: iload #18
/*     */     //   555: i2l
/*     */     //   556: lxor
/*     */     //   557: l2i
/*     */     //   558: istore #24
/*     */     //   560: iload #5
/*     */     //   562: istore #26
/*     */     //   564: iload #26
/*     */     //   566: iinc #26, -1
/*     */     //   569: ifeq -> 603
/*     */     //   572: aload #14
/*     */     //   574: iload #26
/*     */     //   576: laload
/*     */     //   577: lstore #27
/*     */     //   579: aload #14
/*     */     //   581: iload #26
/*     */     //   583: aload_0
/*     */     //   584: iload #26
/*     */     //   586: aaload
/*     */     //   587: iload #25
/*     */     //   589: laload
/*     */     //   590: lastore
/*     */     //   591: aload_0
/*     */     //   592: iload #26
/*     */     //   594: aaload
/*     */     //   595: iload #25
/*     */     //   597: lload #27
/*     */     //   599: lastore
/*     */     //   600: goto -> 564
/*     */     //   603: goto -> 523
/*     */     //   606: iload #5
/*     */     //   608: istore #26
/*     */     //   610: iload #26
/*     */     //   612: iinc #26, -1
/*     */     //   615: ifeq -> 643
/*     */     //   618: aload_0
/*     */     //   619: iload #26
/*     */     //   621: aaload
/*     */     //   622: iload #23
/*     */     //   624: aload #14
/*     */     //   626: iload #26
/*     */     //   628: laload
/*     */     //   629: lastore
/*     */     //   630: goto -> 610
/*     */     //   633: ldc2_w 403748461399786468
/*     */     //   636: lload_3
/*     */     //   637: <illegal opcode> w : (Ljava/lang/Exception;JJ)Ljava/lang/Exception;
/*     */     //   642: athrow
/*     */     //   643: iload #17
/*     */     //   645: iload #6
/*     */     //   647: if_icmpge -> 756
/*     */     //   650: aload #12
/*     */     //   652: iload #24
/*     */     //   654: iaload
/*     */     //   655: iconst_1
/*     */     //   656: if_icmple -> 756
/*     */     //   659: goto -> 672
/*     */     //   662: ldc2_w 403748461399786468
/*     */     //   665: lload_3
/*     */     //   666: <illegal opcode> w : (Ljava/lang/Exception;JJ)Ljava/lang/Exception;
/*     */     //   671: athrow
/*     */     //   672: aload #12
/*     */     //   674: iload #24
/*     */     //   676: iaload
/*     */     //   677: sipush #1024
/*     */     //   680: if_icmpge -> 727
/*     */     //   683: goto -> 696
/*     */     //   686: ldc2_w 403748461399786468
/*     */     //   689: lload_3
/*     */     //   690: <illegal opcode> w : (Ljava/lang/Exception;JJ)Ljava/lang/Exception;
/*     */     //   695: athrow
/*     */     //   696: aload_0
/*     */     //   697: iload #23
/*     */     //   699: iload #23
/*     */     //   701: aload #12
/*     */     //   703: iload #24
/*     */     //   705: iaload
/*     */     //   706: iadd
/*     */     //   707: iload #17
/*     */     //   709: iconst_1
/*     */     //   710: iadd
/*     */     //   711: invokestatic a : ([[JIII)V
/*     */     //   714: goto -> 756
/*     */     //   717: ldc2_w 403748461399786468
/*     */     //   720: lload_3
/*     */     //   721: <illegal opcode> w : (Ljava/lang/Exception;JJ)Ljava/lang/Exception;
/*     */     //   726: athrow
/*     */     //   727: aload #9
/*     */     //   729: iload #8
/*     */     //   731: iload #23
/*     */     //   733: iastore
/*     */     //   734: aload #10
/*     */     //   736: iload #8
/*     */     //   738: aload #12
/*     */     //   740: iload #24
/*     */     //   742: iaload
/*     */     //   743: iastore
/*     */     //   744: aload #11
/*     */     //   746: iload #8
/*     */     //   748: iinc #8, 1
/*     */     //   751: iload #17
/*     */     //   753: iconst_1
/*     */     //   754: iadd
/*     */     //   755: iastore
/*     */     //   756: iload #23
/*     */     //   758: aload #12
/*     */     //   760: iload #24
/*     */     //   762: iaload
/*     */     //   763: iadd
/*     */     //   764: istore #23
/*     */     //   766: aload #12
/*     */     //   768: iload #24
/*     */     //   770: iconst_0
/*     */     //   771: iastore
/*     */     //   772: goto -> 453
/*     */     //   775: goto -> 236
/*     */     //   778: return
/*     */     // Line number table:
/*     */     //   Java source line number -> byte code offset
/*     */     //   #472	-> 8
/*     */     //   #495	-> 17
/*     */     //   #796	-> 24
/*     */     //   #610	-> 35
/*     */     //   #380	-> 39
/*     */     //   #699	-> 48
/*     */     //   #727	-> 157
/*     */     //   #827	-> 172
/*     */     //   #206	-> 175
/*     */     //   #785	-> 181
/*     */     //   #190	-> 187
/*     */     //   #278	-> 193
/*     */     //   #105	-> 199
/*     */     //   #41	-> 207
/*     */     //   #780	-> 216
/*     */     //   #465	-> 223
/*     */     //   #106	-> 230
/*     */     //   #120	-> 236
/*     */     //   #151	-> 241
/*     */     //   #10	-> 251
/*     */     //   #60	-> 258
/*     */     //   #163	-> 265
/*     */     //   #722	-> 292
/*     */     //   #143	-> 301
/*     */     //   #438	-> 314
/*     */     //   #137	-> 368
/*     */     //   #236	-> 371
/*     */     //   #365	-> 386
/*     */     //   #74	-> 411
/*     */     //   #426	-> 427
/*     */     //   #145	-> 433
/*     */     //   #494	-> 446
/*     */     //   #372	-> 460
/*     */     //   #924	-> 497
/*     */     //   #885	-> 516
/*     */     //   #19	-> 523
/*     */     //   #87	-> 541
/*     */     //   #819	-> 560
/*     */     //   #65	-> 572
/*     */     //   #18	-> 579
/*     */     //   #304	-> 591
/*     */     //   #746	-> 600
/*     */     //   #580	-> 606
/*     */     //   #250	-> 643
/*     */     //   #2	-> 672
/*     */     //   #910	-> 727
/*     */     //   #906	-> 734
/*     */     //   #283	-> 744
/*     */     //   #933	-> 756
/*     */     //   #930	-> 775
/*     */     //   #209	-> 778
/*     */     // Exception table:
/*     */     //   from	to	target	type
/*     */     //   8	25	25	java/lang/IllegalArgumentException
/*     */     //   265	279	279	java/lang/IllegalArgumentException
/*     */     //   321	358	358	java/lang/IllegalArgumentException
/*     */     //   378	394	397	java/lang/IllegalArgumentException
/*     */     //   464	487	487	java/lang/IllegalArgumentException
/*     */     //   610	633	633	java/lang/IllegalArgumentException
/*     */     //   643	659	662	java/lang/IllegalArgumentException
/*     */     //   650	683	686	java/lang/IllegalArgumentException
/*     */     //   672	717	717	java/lang/IllegalArgumentException
/*     */   }
/*     */   
/*     */   public static void b(long[] paramArrayOflong) {
/*     */     g(paramArrayOflong, 0, paramArrayOflong.length);
/*     */   }
/*     */   
/*     */   public static long[] a(long[] paramArrayOflong) {
/*     */     int i = paramArrayOflong.length;
/*     */     for (int j = i / 2; j-- != 0; ) {
/*     */       long l = paramArrayOflong[i - j - 1];
/*     */       paramArrayOflong[i - j - 1] = paramArrayOflong[j];
/*     */       paramArrayOflong[j] = l;
/*     */     } 
/*     */     return paramArrayOflong;
/*     */   }
/*     */   
/*     */   public static void d(int[] paramArrayOfint, long[] paramArrayOflong, int paramInt1, int paramInt2) {
/*     */     ForkJoinPool forkJoinPool = a();
/*     */     try {
/*     */       if (paramInt2 - paramInt1 >= 8192) {
/*     */         try {
/*     */           if (forkJoinPool.getParallelism() == 1) {
/*     */             c(paramArrayOfint, paramArrayOflong, paramInt1, paramInt2);
/*     */             return;
/*     */           } 
/*     */         } catch (IllegalArgumentException illegalArgumentException) {
/*     */           throw a(null);
/*     */         } 
/*     */         forkJoinPool.invoke(new fE(paramArrayOfint, paramArrayOflong, paramInt1, paramInt2));
/*     */         return;
/*     */       } 
/*     */     } catch (IllegalArgumentException illegalArgumentException) {
/*     */       throw a(null);
/*     */     } 
/*     */     c(paramArrayOfint, paramArrayOflong, paramInt1, paramInt2);
/*     */   }
/*     */   
/*     */   public static void a(int[] paramArrayOfint, long[] paramArrayOflong, boolean paramBoolean) {
/*     */     b(paramArrayOfint, paramArrayOflong, 0, paramArrayOflong.length, paramBoolean);
/*     */   }
/*     */   
/*     */   public static void a(long[][] paramArrayOflong) {
/*     */     a(paramArrayOflong, 0, (paramArrayOflong[0]).length);
/*     */   }
/*     */   
/*     */   public static void d(long[] paramArrayOflong, int paramInt1, int paramInt2, hq paramhq) {
/*     */     f(paramArrayOflong, paramInt1, paramInt2, paramhq);
/*     */   }
/*     */   
/*     */   public static void a(int[] paramArrayOfint, long[] paramArrayOflong) {
/*     */     d(paramArrayOfint, paramArrayOflong, 0, paramArrayOflong.length);
/*     */   }
/*     */   
/*     */   public static void d(long[] paramArrayOflong, int paramInt1, int paramInt2) {
/*     */     long l = paramArrayOflong[paramInt1];
/*     */     paramArrayOflong[paramInt1] = paramArrayOflong[paramInt2];
/*     */     paramArrayOflong[paramInt2] = l;
/*     */   }
/*     */   
/*     */   private static void a(int[] paramArrayOfint, long[] paramArrayOflong, int paramInt1, int paramInt2) {
/*     */     for (int i = paramInt1; ++i < paramInt2; ) {
/*     */       int j = paramArrayOfint[i];
/*     */       int k = i;
/*     */       int m = paramArrayOfint[k - 1];
/*     */     } 
/*     */   }
/*     */   
/*     */   private static void a(long[][] paramArrayOflong, int paramInt1, int paramInt2, int paramInt3) {
/*     */     int i = paramArrayOflong.length;
/*     */     int j = paramInt3 / 8;
/*     */     for (int k = paramInt1; k < paramInt2 - 1; n = k + 1)
/*     */       int n, m = k; 
/*     */   }
/*     */   
/*     */   @Deprecated
/*     */   public static boolean a(long[] paramArrayOflong1, long[] paramArrayOflong2) {
/*     */     int i = paramArrayOflong1.length;
/*     */     try {
/*     */       if (i != paramArrayOflong2.length)
/*     */         return false; 
/*     */     } catch (IllegalArgumentException illegalArgumentException) {
/*     */       throw a(null);
/*     */     } 
/*     */     while (i-- != 0) {
/*     */       if (paramArrayOflong1[i] != paramArrayOflong2[i])
/*     */         return false; 
/*     */     } 
/*     */     return true;
/*     */   }
/*     */   
/*     */   public static long[] a(long[] paramArrayOflong, int paramInt1, int paramInt2) {
/*     */     int i = paramInt2 - paramInt1;
/*     */     for (int j = i / 2; j-- != 0; paramArrayOflong[paramInt1 + i - j - 1] = paramArrayOflong[paramInt1 + j], paramArrayOflong[paramInt1 + j] = l)
/*     */       long l = paramArrayOflong[paramInt1 + i - j - 1]; 
/*     */     return paramArrayOflong;
/*     */   }
/*     */   
/*     */   private static ForkJoinPool a() {
/*     */     ForkJoinPool forkJoinPool = ForkJoinTask.getPool();
/*     */     try {
/*     */     
/*     */     } catch (IllegalArgumentException illegalArgumentException) {
/*     */       throw a(null);
/*     */     } 
/*     */     return (forkJoinPool == null) ? ForkJoinPool.commonPool() : forkJoinPool;
/*     */   }
/*     */   
/*     */   public static void c(long[] paramArrayOflong, int paramInt1, int paramInt2, hq paramhq) {
/*     */     b(paramArrayOflong, paramInt1, paramInt2, paramhq);
/*     */   }
/*     */   
/*     */   private static void a(long[] paramArrayOflong, int paramInt1, int paramInt2, hq paramhq) {
/*     */     for (int i = paramInt1; ++i < paramInt2; j = i) {
/*     */       int j;
/*     */       long l = paramArrayOflong[i];
/*     */     } 
/*     */   }
/*     */   
/*     */   @Deprecated
/*     */   public static void a(long[] paramArrayOflong, long paramLong) {
/*     */     int i = paramArrayOflong.length;
/*     */     try {
/*     */       for (; i-- != 0; paramArrayOflong[i] = paramLong);
/*     */     } catch (IllegalArgumentException illegalArgumentException) {
/*     */       throw a(null);
/*     */     } 
/*     */   }
/*     */   
/*     */   public static int a(long[] paramArrayOflong, long paramLong, hq paramhq) {
/*     */     return a(paramArrayOflong, 0, paramArrayOflong.length, paramLong, paramhq);
/*     */   }
/*     */   
/*     */   public static long[] b(long[] paramArrayOflong, int paramInt1, int paramInt2) {
/*     */     try {
/*     */       e(paramArrayOflong, paramInt1, paramInt2);
/*     */     } catch (IllegalArgumentException illegalArgumentException) {
/*     */       throw a(null);
/*     */     } 
/*     */     long[] arrayOfLong = (paramInt2 == 0) ? i : new long[paramInt2];
/*     */     System.arraycopy(paramArrayOflong, paramInt1, arrayOfLong, 0, paramInt2);
/*     */     return arrayOfLong;
/*     */   }
/*     */   
/*     */   public static long[] b(long[] paramArrayOflong, int paramInt) {
/*     */     try {
/*     */       if (paramInt >= paramArrayOflong.length)
/*     */         return paramArrayOflong; 
/*     */     } catch (IllegalArgumentException illegalArgumentException) {
/*     */       throw a(null);
/*     */     } 
/*     */     try {
/*     */     
/*     */     } catch (IllegalArgumentException illegalArgumentException) {
/*     */       throw a(null);
/*     */     } 
/*     */     long[] arrayOfLong = (paramInt == 0) ? i : new long[paramInt];
/*     */     System.arraycopy(paramArrayOflong, 0, arrayOfLong, 0, paramInt);
/*     */     return arrayOfLong;
/*     */   }
/*     */   
/*     */   private static int a(long[] paramArrayOflong1, long[] paramArrayOflong2, int paramInt1, int paramInt2, int paramInt3) {
/*     */     try {
/*     */     
/*     */     } catch (IllegalArgumentException illegalArgumentException) {
/*     */       throw a(null);
/*     */     } 
/*     */     int i, j = ((i = Long.compare(paramArrayOflong1[paramInt1], paramArrayOflong1[paramInt2])) == 0) ? Long.compare(paramArrayOflong2[paramInt1], paramArrayOflong2[paramInt2]) : i;
/*     */     try {
/*     */     
/*     */     } catch (IllegalArgumentException illegalArgumentException) {
/*     */       throw a(null);
/*     */     } 
/*     */     int k = ((i = Long.compare(paramArrayOflong1[paramInt1], paramArrayOflong1[paramInt3])) == 0) ? Long.compare(paramArrayOflong2[paramInt1], paramArrayOflong2[paramInt3]) : i;
/*     */     try {
/*     */     
/*     */     } catch (IllegalArgumentException illegalArgumentException) {
/*     */       throw a(null);
/*     */     } 
/*     */     int m = ((i = Long.compare(paramArrayOflong1[paramInt2], paramArrayOflong1[paramInt3])) == 0) ? Long.compare(paramArrayOflong2[paramInt2], paramArrayOflong2[paramInt3]) : i;
/*     */     try {
/*     */       if (j < 0) {
/*     */         try {
/*     */           try {
/*     */           
/*     */           } catch (IllegalArgumentException illegalArgumentException) {
/*     */             throw a(null);
/*     */           } 
/*     */         } catch (IllegalArgumentException illegalArgumentException) {
/*     */           throw a(null);
/*     */         } 
/*     */       } else {
/*     */         try {
/*     */           try {
/*     */           
/*     */           } catch (IllegalArgumentException illegalArgumentException) {
/*     */             throw a(null);
/*     */           } 
/*     */         } catch (IllegalArgumentException illegalArgumentException) {
/*     */           throw a(null);
/*     */         } 
/*     */       } 
/*     */     } catch (IllegalArgumentException illegalArgumentException) {
/*     */       throw a(null);
/*     */     } 
/*     */     return (m > 0) ? paramInt2 : ((k > 0) ? paramInt3 : paramInt1);
/*     */   }
/*     */   
/*     */   public static long[] a(long[] paramArrayOflong, int paramInt) {
/*     */     return c(paramArrayOflong, paramInt, paramArrayOflong.length);
/*     */   }
/*     */   
/*     */   public static void b(long[] paramArrayOflong, int paramInt1, int paramInt2, hq paramhq) {
/*     */     a(paramArrayOflong, paramInt1, paramInt2, paramhq, (long[])null);
/*     */   }
/*     */   
/*     */   public static void d(long[] paramArrayOflong, hq paramhq) {
/*     */     d(paramArrayOflong, 0, paramArrayOflong.length, paramhq);
/*     */   }
/*     */   
/*     */   public static void f(long[] paramArrayOflong1, long[] paramArrayOflong2, int paramInt1, int paramInt2) {
/*     */     try {
/*     */       if (paramInt2 - paramInt1 < 1024) {
/*     */         d(paramArrayOflong1, paramArrayOflong2, paramInt1, paramInt2);
/*     */         return;
/*     */       } 
/*     */     } catch (IllegalArgumentException illegalArgumentException) {
/*     */       throw a(null);
/*     */     } 
/*     */     byte b1 = 2;
/*     */     byte b2 = 15;
/*     */     char c = '໲';
/*     */     byte b3 = 0;
/*     */     int[] arrayOfInt1 = new int[3826];
/*     */     int[] arrayOfInt2 = new int[3826];
/*     */     int[] arrayOfInt3 = new int[3826];
/*     */     arrayOfInt1[b3] = paramInt1;
/*     */     arrayOfInt2[b3] = paramInt2 - paramInt1;
/*     */     arrayOfInt3[b3++] = 0;
/*     */     int[] arrayOfInt4 = new int[256];
/*     */     int[] arrayOfInt5 = new int[256];
/*     */     for (; b3 > 0; j = arrayOfInt2[b3], k = arrayOfInt3[b3])
/*     */       int j, k, i = arrayOfInt1[--b3]; 
/*     */   }
/*     */   
/*     */   public static void f(long[] paramArrayOflong, int paramInt1, int paramInt2, hq paramhq) {
/*     */     // Byte code:
/*     */     //   0: iload_2
/*     */     //   1: iload_1
/*     */     //   2: isub
/*     */     //   3: istore #4
/*     */     //   5: iload #4
/*     */     //   7: bipush #16
/*     */     //   9: if_icmpge -> 24
/*     */     //   12: aload_0
/*     */     //   13: iload_1
/*     */     //   14: iload_2
/*     */     //   15: aload_3
/*     */     //   16: invokestatic g : ([JIILme/konsolas/aac/hq;)V
/*     */     //   19: return
/*     */     //   20: invokestatic a : (Ljava/lang/Exception;)Ljava/lang/Exception;
/*     */     //   23: athrow
/*     */     //   24: iload_1
/*     */     //   25: iload #4
/*     */     //   27: iconst_2
/*     */     //   28: idiv
/*     */     //   29: iadd
/*     */     //   30: istore #5
/*     */     //   32: iload_1
/*     */     //   33: istore #6
/*     */     //   35: iload_2
/*     */     //   36: iconst_1
/*     */     //   37: isub
/*     */     //   38: istore #7
/*     */     //   40: iload #4
/*     */     //   42: sipush #128
/*     */     //   45: if_icmple -> 116
/*     */     //   48: iload #4
/*     */     //   50: bipush #8
/*     */     //   52: idiv
/*     */     //   53: istore #8
/*     */     //   55: aload_0
/*     */     //   56: iload #6
/*     */     //   58: iload #6
/*     */     //   60: iload #8
/*     */     //   62: iadd
/*     */     //   63: iload #6
/*     */     //   65: iconst_2
/*     */     //   66: iload #8
/*     */     //   68: imul
/*     */     //   69: iadd
/*     */     //   70: aload_3
/*     */     //   71: invokestatic b : ([JIIILme/konsolas/aac/hq;)I
/*     */     //   74: istore #6
/*     */     //   76: aload_0
/*     */     //   77: iload #5
/*     */     //   79: iload #8
/*     */     //   81: isub
/*     */     //   82: iload #5
/*     */     //   84: iload #5
/*     */     //   86: iload #8
/*     */     //   88: iadd
/*     */     //   89: aload_3
/*     */     //   90: invokestatic b : ([JIIILme/konsolas/aac/hq;)I
/*     */     //   93: istore #5
/*     */     //   95: aload_0
/*     */     //   96: iload #7
/*     */     //   98: iconst_2
/*     */     //   99: iload #8
/*     */     //   101: imul
/*     */     //   102: isub
/*     */     //   103: iload #7
/*     */     //   105: iload #8
/*     */     //   107: isub
/*     */     //   108: iload #7
/*     */     //   110: aload_3
/*     */     //   111: invokestatic b : ([JIIILme/konsolas/aac/hq;)I
/*     */     //   114: istore #7
/*     */     //   116: aload_0
/*     */     //   117: iload #6
/*     */     //   119: iload #5
/*     */     //   121: iload #7
/*     */     //   123: aload_3
/*     */     //   124: invokestatic b : ([JIIILme/konsolas/aac/hq;)I
/*     */     //   127: istore #5
/*     */     //   129: aload_0
/*     */     //   130: iload #5
/*     */     //   132: laload
/*     */     //   133: lstore #8
/*     */     //   135: iload_1
/*     */     //   136: istore #10
/*     */     //   138: iload #10
/*     */     //   140: istore #11
/*     */     //   142: iload_2
/*     */     //   143: iconst_1
/*     */     //   144: isub
/*     */     //   145: istore #12
/*     */     //   147: iload #12
/*     */     //   149: istore #13
/*     */     //   151: iload #11
/*     */     //   153: iload #12
/*     */     //   155: if_icmpgt -> 212
/*     */     //   158: aload_3
/*     */     //   159: aload_0
/*     */     //   160: iload #11
/*     */     //   162: laload
/*     */     //   163: lload #8
/*     */     //   165: invokeinterface a : (JJ)I
/*     */     //   170: dup
/*     */     //   171: istore #14
/*     */     //   173: ifgt -> 212
/*     */     //   176: iload #14
/*     */     //   178: ifne -> 206
/*     */     //   181: goto -> 188
/*     */     //   184: invokestatic a : (Ljava/lang/Exception;)Ljava/lang/Exception;
/*     */     //   187: athrow
/*     */     //   188: aload_0
/*     */     //   189: iload #10
/*     */     //   191: iinc #10, 1
/*     */     //   194: iload #11
/*     */     //   196: invokestatic d : ([JII)V
/*     */     //   199: goto -> 206
/*     */     //   202: invokestatic a : (Ljava/lang/Exception;)Ljava/lang/Exception;
/*     */     //   205: athrow
/*     */     //   206: iinc #11, 1
/*     */     //   209: goto -> 151
/*     */     //   212: iload #12
/*     */     //   214: iload #11
/*     */     //   216: if_icmplt -> 273
/*     */     //   219: aload_3
/*     */     //   220: aload_0
/*     */     //   221: iload #12
/*     */     //   223: laload
/*     */     //   224: lload #8
/*     */     //   226: invokeinterface a : (JJ)I
/*     */     //   231: dup
/*     */     //   232: istore #14
/*     */     //   234: iflt -> 273
/*     */     //   237: iload #14
/*     */     //   239: ifne -> 267
/*     */     //   242: goto -> 249
/*     */     //   245: invokestatic a : (Ljava/lang/Exception;)Ljava/lang/Exception;
/*     */     //   248: athrow
/*     */     //   249: aload_0
/*     */     //   250: iload #12
/*     */     //   252: iload #13
/*     */     //   254: iinc #13, -1
/*     */     //   257: invokestatic d : ([JII)V
/*     */     //   260: goto -> 267
/*     */     //   263: invokestatic a : (Ljava/lang/Exception;)Ljava/lang/Exception;
/*     */     //   266: athrow
/*     */     //   267: iinc #12, -1
/*     */     //   270: goto -> 212
/*     */     //   273: iload #11
/*     */     //   275: iload #12
/*     */     //   277: if_icmple -> 287
/*     */     //   280: goto -> 304
/*     */     //   283: invokestatic a : (Ljava/lang/Exception;)Ljava/lang/Exception;
/*     */     //   286: athrow
/*     */     //   287: aload_0
/*     */     //   288: iload #11
/*     */     //   290: iinc #11, 1
/*     */     //   293: iload #12
/*     */     //   295: iinc #12, -1
/*     */     //   298: invokestatic d : ([JII)V
/*     */     //   301: goto -> 151
/*     */     //   304: iload #10
/*     */     //   306: iload_1
/*     */     //   307: isub
/*     */     //   308: iload #11
/*     */     //   310: iload #10
/*     */     //   312: isub
/*     */     //   313: invokestatic min : (II)I
/*     */     //   316: istore #14
/*     */     //   318: aload_0
/*     */     //   319: iload_1
/*     */     //   320: iload #11
/*     */     //   322: iload #14
/*     */     //   324: isub
/*     */     //   325: iload #14
/*     */     //   327: invokestatic a : ([JIII)V
/*     */     //   330: iload #13
/*     */     //   332: iload #12
/*     */     //   334: isub
/*     */     //   335: iload_2
/*     */     //   336: iload #13
/*     */     //   338: isub
/*     */     //   339: iconst_1
/*     */     //   340: isub
/*     */     //   341: invokestatic min : (II)I
/*     */     //   344: istore #14
/*     */     //   346: aload_0
/*     */     //   347: iload #11
/*     */     //   349: iload_2
/*     */     //   350: iload #14
/*     */     //   352: isub
/*     */     //   353: iload #14
/*     */     //   355: invokestatic a : ([JIII)V
/*     */     //   358: iload #11
/*     */     //   360: iload #10
/*     */     //   362: isub
/*     */     //   363: dup
/*     */     //   364: istore #14
/*     */     //   366: iconst_1
/*     */     //   367: if_icmple -> 387
/*     */     //   370: aload_0
/*     */     //   371: iload_1
/*     */     //   372: iload_1
/*     */     //   373: iload #14
/*     */     //   375: iadd
/*     */     //   376: aload_3
/*     */     //   377: invokestatic f : ([JIILme/konsolas/aac/hq;)V
/*     */     //   380: goto -> 387
/*     */     //   383: invokestatic a : (Ljava/lang/Exception;)Ljava/lang/Exception;
/*     */     //   386: athrow
/*     */     //   387: iload #13
/*     */     //   389: iload #12
/*     */     //   391: isub
/*     */     //   392: dup
/*     */     //   393: istore #14
/*     */     //   395: iconst_1
/*     */     //   396: if_icmple -> 416
/*     */     //   399: aload_0
/*     */     //   400: iload_2
/*     */     //   401: iload #14
/*     */     //   403: isub
/*     */     //   404: iload_2
/*     */     //   405: aload_3
/*     */     //   406: invokestatic f : ([JIILme/konsolas/aac/hq;)V
/*     */     //   409: goto -> 416
/*     */     //   412: invokestatic a : (Ljava/lang/Exception;)Ljava/lang/Exception;
/*     */     //   415: athrow
/*     */     //   416: return
/*     */     // Line number table:
/*     */     //   Java source line number -> byte code offset
/*     */     //   #762	-> 0
/*     */     //   #650	-> 5
/*     */     //   #170	-> 12
/*     */     //   #680	-> 19
/*     */     //   #20	-> 24
/*     */     //   #670	-> 32
/*     */     //   #791	-> 35
/*     */     //   #231	-> 40
/*     */     //   #39	-> 48
/*     */     //   #144	-> 55
/*     */     //   #366	-> 76
/*     */     //   #686	-> 95
/*     */     //   #828	-> 116
/*     */     //   #76	-> 129
/*     */     //   #84	-> 135
/*     */     //   #218	-> 151
/*     */     //   #329	-> 176
/*     */     //   #24	-> 206
/*     */     //   #795	-> 212
/*     */     //   #550	-> 237
/*     */     //   #671	-> 267
/*     */     //   #313	-> 273
/*     */     //   #559	-> 287
/*     */     //   #198	-> 304
/*     */     //   #536	-> 318
/*     */     //   #821	-> 330
/*     */     //   #350	-> 346
/*     */     //   #697	-> 358
/*     */     //   #287	-> 387
/*     */     //   #447	-> 416
/*     */     // Exception table:
/*     */     //   from	to	target	type
/*     */     //   5	20	20	java/lang/IllegalArgumentException
/*     */     //   173	181	184	java/lang/IllegalArgumentException
/*     */     //   176	199	202	java/lang/IllegalArgumentException
/*     */     //   234	242	245	java/lang/IllegalArgumentException
/*     */     //   237	260	263	java/lang/IllegalArgumentException
/*     */     //   273	283	283	java/lang/IllegalArgumentException
/*     */     //   366	380	383	java/lang/IllegalArgumentException
/*     */     //   395	409	412	java/lang/IllegalArgumentException
/*     */   }
/*     */   
/*     */   public static long[] c(long[] paramArrayOflong, int paramInt) {
/*     */     return d(paramArrayOflong, paramInt, paramArrayOflong.length);
/*     */   }
/*     */   
/*     */   public static void a(long[] paramArrayOflong, int paramInt1, int paramInt2, int paramInt3) {
/*     */     byte b = 0;
/*     */     try {
/*     */       while (b < paramInt3) {
/*     */         d(paramArrayOflong, paramInt1, paramInt2);
/*     */         b++;
/*     */         paramInt1++;
/*     */         paramInt2++;
/*     */       } 
/*     */     } catch (IllegalArgumentException illegalArgumentException) {
/*     */       throw a(null);
/*     */     } 
/*     */   }
/*     */   
/*     */   private static int b(long[] paramArrayOflong, int paramInt1, int paramInt2, int paramInt3, hq paramhq) {
/*     */     int i = paramhq.a(paramArrayOflong[paramInt1], paramArrayOflong[paramInt2]);
/*     */     int j = paramhq.a(paramArrayOflong[paramInt1], paramArrayOflong[paramInt3]);
/*     */     int k = paramhq.a(paramArrayOflong[paramInt2], paramArrayOflong[paramInt3]);
/*     */     try {
/*     */       if (i < 0) {
/*     */         try {
/*     */           try {
/*     */           
/*     */           } catch (IllegalArgumentException illegalArgumentException) {
/*     */             throw a(null);
/*     */           } 
/*     */         } catch (IllegalArgumentException illegalArgumentException) {
/*     */           throw a(null);
/*     */         } 
/*     */       } else {
/*     */         try {
/*     */           try {
/*     */           
/*     */           } catch (IllegalArgumentException illegalArgumentException) {
/*     */             throw a(null);
/*     */           } 
/*     */         } catch (IllegalArgumentException illegalArgumentException) {
/*     */           throw a(null);
/*     */         } 
/*     */       } 
/*     */     } catch (IllegalArgumentException illegalArgumentException) {
/*     */       throw a(null);
/*     */     } 
/*     */     return (k > 0) ? paramInt2 : ((j > 0) ? paramInt3 : paramInt1);
/*     */   }
/*     */   
/*     */   public static void c(long[] paramArrayOflong1, long[] paramArrayOflong2) {
/*     */     e(paramArrayOflong1, paramArrayOflong2);
/*     */     f(paramArrayOflong1, paramArrayOflong2, 0, paramArrayOflong1.length);
/*     */   }
/*     */   
/*     */   public static int a(long[] paramArrayOflong, int paramInt1, int paramInt2, long paramLong) {
/*     */     paramInt2--;
/*     */     while (paramInt1 <= paramInt2) {
/*     */       int i = paramInt1 + paramInt2 >>> 1;
/*     */       long l = paramArrayOflong[i];
/*     */       if (l < paramLong) {
/*     */         paramInt1 = i + 1;
/*     */         continue;
/*     */       } 
/*     */       if (l > paramLong) {
/*     */         paramInt2 = i - 1;
/*     */         continue;
/*     */       } 
/*     */       return i;
/*     */     } 
/*     */     return -(paramInt1 + 1);
/*     */   }
/*     */   
/*     */   public static int a(long[] paramArrayOflong, int paramInt1, int paramInt2, long paramLong, hq paramhq) {
/*     */     paramInt2--;
/*     */     while (paramInt1 <= paramInt2) {
/*     */       int i = paramInt1 + paramInt2 >>> 1;
/*     */       long l = paramArrayOflong[i];
/*     */       int j = paramhq.a(l, paramLong);
/*     */     } 
/*     */     return -(paramInt1 + 1);
/*     */   }
/*     */   
/*     */   private static final long o = nc.a(-4794253147010387942L, 8023129867959596960L, MethodHandles.lookup().lookupClass()).a(82144984715553L);
/*     */   
/*     */   static {
/*     */     i = new long[0];
/*     */     l = new long[0];
/*     */     e = new cw(-1, -1, -1);
/*     */     h = new f9(null);
/*     */   }
/*     */   
/*     */   public static void l(long[] paramArrayOflong, int paramInt1, int paramInt2) {
/*     */     ForkJoinPool forkJoinPool = a();
/*     */     try {
/*     */       if (paramInt2 - paramInt1 >= 1024)
/*     */         try {
/*     */           if (forkJoinPool.getParallelism() != 1) {
/*     */             byte b = 7;
/*     */             LinkedBlockingQueue<cw> linkedBlockingQueue = new LinkedBlockingQueue();
/*     */             linkedBlockingQueue.add(new cw(paramInt1, paramInt2 - paramInt1, 0));
/*     */             AtomicInteger atomicInteger = new AtomicInteger(1);
/*     */             int i = forkJoinPool.getParallelism();
/*     */             ExecutorCompletionService executorCompletionService = new ExecutorCompletionService(forkJoinPool);
/*     */             int j = i;
/*     */             try {
/*     */               for (; j-- != 0; executorCompletionService.submit(() -> {
/*     */                     int[] arrayOfInt1 = new int[256];
/*     */                     int[] arrayOfInt2 = new int[256];
/*     */                     while (true) {
/*     */                       if (paramAtomicInteger.get() == 0) {
/*     */                         int i3 = paramInt;
/*     */                         try {
/*     */                           while (i3-- != 0)
/*     */                             paramLinkedBlockingQueue.add(e); 
/*     */                         } catch (Exception exception) {
/*     */                           throw a(null);
/*     */                         } 
/*     */                       } 
/*     */                       cw cw1 = paramLinkedBlockingQueue.take();
/*     */                       try {
/*     */                         if (cw1 == e)
/*     */                           return null; 
/*     */                       } catch (Exception exception) {
/*     */                         throw a(null);
/*     */                       } 
/*     */                       int i = cw1.a;
/*     */                       int j = cw1.c;
/*     */                       int k = cw1.b;
/*     */                       try {
/*     */                       
/*     */                       } catch (Exception exception) {
/*     */                         throw a(null);
/*     */                       } 
/*     */                       boolean bool = (k % 8 == 0) ? true : false;
/*     */                       int m = (7 - k % 8) * 8;
/*     */                       int n = i + j;
/*     */                       try {
/*     */                         while (n-- != i)
/*     */                           arrayOfInt1[(int)(paramArrayOflong[n] >>> m & 0xFFL ^ bool)] = arrayOfInt1[(int)(paramArrayOflong[n] >>> m & 0xFFL ^ bool)] + 1; 
/*     */                       } catch (Exception exception) {
/*     */                         throw a(null);
/*     */                       } 
/*     */                       n = -1;
/*     */                       int i1 = 0;
/*     */                       int i2 = i;
/*     */                       while (true) {
/*     */                         try {
/*     */                           if (i1 < 256) {
/*     */                             if (arrayOfInt1[i1] != 0)
/*     */                               n = i1; 
/*     */                             arrayOfInt2[i1] = i2 += arrayOfInt1[i1];
/*     */                             i1++;
/*     */                             continue;
/*     */                           } 
/*     */                         } catch (Exception exception) {
/*     */                           throw a(null);
/*     */                         } 
/*     */                         i1 = i + j - arrayOfInt1[n];
/*     */                         i2 = i;
/*     */                         for (int i3 = -1; i2 <= i1; i3 = (int)(l >>> m & 0xFFL ^ bool)) {
/*     */                           continue;
/*     */                           l = paramArrayOflong[i2];
/*     */                         } 
/*     */                         break;
/*     */                       } 
/*     */                       paramAtomicInteger.decrementAndGet();
/*     */                     } 
/*     */                   }));
/*     */             } catch (Exception exception) {
/*     */               throw a(null);
/*     */             } 
/*     */             Throwable throwable = null;
/*     */             for (int k = i; k-- != 0; throwable = exception.getCause()) {
/*     */               try {
/*     */                 executorCompletionService.take().get();
/*     */                 continue;
/*     */               } catch (Exception exception) {}
/*     */             } 
/*     */             try {
/*     */               if (throwable != null) {
/*     */                 try {
/*     */                 
/*     */                 } catch (Exception exception) {
/*     */                   throw a(null);
/*     */                 } 
/*     */                 throw (throwable instanceof RuntimeException) ? (RuntimeException)throwable : new RuntimeException(throwable);
/*     */               } 
/*     */             } catch (Exception exception) {
/*     */               throw a(null);
/*     */             } 
/*     */             return;
/*     */           } 
/*     */           c(paramArrayOflong, paramInt1, paramInt2);
/*     */           return;
/*     */         } catch (Exception exception) {
/*     */           throw a(null);
/*     */         }  
/*     */     } catch (Exception exception) {
/*     */       throw a(null);
/*     */     } 
/*     */     c(paramArrayOflong, paramInt1, paramInt2);
/*     */   }
/*     */   
/*     */   public static void e(long[] paramArrayOflong1, long[] paramArrayOflong2) {
/*     */     // Byte code:
/*     */     //   0: getstatic me/konsolas/aac/a1.o : J
/*     */     //   3: ldc2_w 22586608371560
/*     */     //   6: lxor
/*     */     //   7: lstore_2
/*     */     //   8: aload_0
/*     */     //   9: arraylength
/*     */     //   10: aload_1
/*     */     //   11: arraylength
/*     */     //   12: if_icmpeq -> 107
/*     */     //   15: new java/lang/IllegalArgumentException
/*     */     //   18: dup
/*     */     //   19: new java/lang/StringBuilder
/*     */     //   22: dup
/*     */     //   23: invokespecial <init> : ()V
/*     */     //   26: ldc '⚨㢿섳鬇堇⤊컁낒樀찌溴藏策䙚䇼鞳Eﶼ?㟗'
/*     */     //   28: invokevirtual toCharArray : ()[C
/*     */     //   31: dup
/*     */     //   32: dup
/*     */     //   33: iconst_4
/*     */     //   34: dup_x1
/*     */     //   35: caload
/*     */     //   36: sipush #723
/*     */     //   39: ixor
/*     */     //   40: i2c
/*     */     //   41: castore
/*     */     //   42: sipush #14834
/*     */     //   45: iconst_1
/*     */     //   46: iconst_3
/*     */     //   47: invokestatic A : (Ljava/lang/Object;SZI)Ljava/lang/String;
/*     */     //   50: invokevirtual append : (Ljava/lang/String;)Ljava/lang/StringBuilder;
/*     */     //   53: aload_0
/*     */     //   54: arraylength
/*     */     //   55: invokevirtual append : (I)Ljava/lang/StringBuilder;
/*     */     //   58: ldc '僼૔懶겨奥'
/*     */     //   60: invokevirtual toCharArray : ()[C
/*     */     //   63: dup
/*     */     //   64: dup
/*     */     //   65: iconst_2
/*     */     //   66: dup_x1
/*     */     //   67: caload
/*     */     //   68: sipush #24088
/*     */     //   71: ixor
/*     */     //   72: i2c
/*     */     //   73: castore
/*     */     //   74: sipush #7758
/*     */     //   77: iconst_0
/*     */     //   78: iconst_3
/*     */     //   79: invokestatic A : (Ljava/lang/Object;SZI)Ljava/lang/String;
/*     */     //   82: invokevirtual append : (Ljava/lang/String;)Ljava/lang/StringBuilder;
/*     */     //   85: aload_1
/*     */     //   86: arraylength
/*     */     //   87: invokevirtual append : (I)Ljava/lang/StringBuilder;
/*     */     //   90: invokevirtual toString : ()Ljava/lang/String;
/*     */     //   93: invokespecial <init> : (Ljava/lang/String;)V
/*     */     //   96: athrow
/*     */     //   97: ldc2_w -6596840645741649395
/*     */     //   100: lload_2
/*     */     //   101: <illegal opcode> w : (Ljava/lang/Exception;JJ)Ljava/lang/Exception;
/*     */     //   106: athrow
/*     */     //   107: return
/*     */     // Line number table:
/*     */     //   Java source line number -> byte code offset
/*     */     //   #855	-> 8
/*     */     //   #155	-> 107
/*     */     // Exception table:
/*     */     //   from	to	target	type
/*     */     //   8	97	97	java/lang/IllegalArgumentException
/*     */   }
/*     */   
/*     */   public static void a(long[] paramArrayOflong, int paramInt1, int paramInt2) {
/*     */     h(paramArrayOflong, paramInt1, paramInt2);
/*     */   }
/*     */   
/*     */   public static void c(long[] paramArrayOflong, int paramInt1, int paramInt2) {
/*     */     int i = paramInt2 - paramInt1;
/*     */     try {
/*     */       if (i < 16) {
/*     */         k(paramArrayOflong, paramInt1, paramInt2);
/*     */         return;
/*     */       } 
/*     */     } catch (IllegalArgumentException illegalArgumentException) {
/*     */       throw a(null);
/*     */     } 
/*     */     int j = paramInt1 + i / 2;
/*     */     int k = paramInt1;
/*     */     int m = paramInt2 - 1;
/*     */     if (i > 128) {
/*     */       int i5 = i / 8;
/*     */       k = a(paramArrayOflong, k, k + i5, k + 2 * i5);
/*     */       j = a(paramArrayOflong, j - i5, j, j + i5);
/*     */       m = a(paramArrayOflong, m - 2 * i5, m - i5, m);
/*     */     } 
/*     */     j = a(paramArrayOflong, k, j, m);
/*     */     long l = paramArrayOflong[j];
/*     */     int n = paramInt1, i1 = n, i2 = paramInt2 - 1, i3 = i2;
/*     */     for (;; d(paramArrayOflong, i1++, i2--)) {
/*     */       if (i1 <= i2) {
/*     */         int i5;
/*     */         try {
/*     */           if ((i5 = Long.compare(paramArrayOflong[i1], l)) <= 0) {
/*     */             try {
/*     */               if (i5 == 0)
/*     */                 d(paramArrayOflong, n++, i1); 
/*     */             } catch (IllegalArgumentException illegalArgumentException) {
/*     */               throw a(null);
/*     */             } 
/*     */             i1++;
/*     */           } 
/*     */         } catch (IllegalArgumentException illegalArgumentException) {
/*     */           throw a(null);
/*     */         } 
/*     */       } 
/*     */       continue;
/*     */       while (i2 >= i1) {
/*     */         int i5;
/*     */         try {
/*     */           if ((i5 = Long.compare(paramArrayOflong[i2], l)) >= 0) {
/*     */             try {
/*     */               if (i5 == 0)
/*     */                 d(paramArrayOflong, i2, i3--); 
/*     */             } catch (IllegalArgumentException illegalArgumentException) {
/*     */               throw a(null);
/*     */             } 
/*     */             i2--;
/*     */           } 
/*     */         } catch (IllegalArgumentException illegalArgumentException) {
/*     */           throw a(null);
/*     */         } 
/*     */       } 
/*     */       try {
/*     */         if (i1 > i2)
/*     */           break; 
/*     */       } catch (IllegalArgumentException illegalArgumentException) {
/*     */         throw a(null);
/*     */       } 
/*     */     } 
/*     */     int i4 = Math.min(n - paramInt1, i1 - n);
/*     */     a(paramArrayOflong, paramInt1, i1 - i4, i4);
/*     */     i4 = Math.min(i3 - i2, paramInt2 - i3 - 1);
/*     */     a(paramArrayOflong, i1, paramInt2 - i4, i4);
/*     */     try {
/*     */       if ((i4 = i1 - n) > 1)
/*     */         c(paramArrayOflong, paramInt1, paramInt1 + i4); 
/*     */     } catch (IllegalArgumentException illegalArgumentException) {
/*     */       throw a(null);
/*     */     } 
/*     */     try {
/*     */       if ((i4 = i3 - i2) > 1)
/*     */         c(paramArrayOflong, paramInt2 - i4, paramInt2); 
/*     */     } catch (IllegalArgumentException illegalArgumentException) {
/*     */       throw a(null);
/*     */     } 
/*     */   }
/*     */   
/*     */   private static void k(long[] paramArrayOflong, int paramInt1, int paramInt2) {
/*     */     for (int i = paramInt1; i < paramInt2 - 1; ) {
/*     */       int j = i;
/*     */       int k = i + 1;
/*     */       while (true) {
/*     */         try {
/*     */           if (k < paramInt2) {
/*     */             if (paramArrayOflong[k] < paramArrayOflong[j])
/*     */               j = k; 
/*     */             k++;
/*     */             continue;
/*     */           } 
/*     */         } catch (IllegalArgumentException illegalArgumentException) {
/*     */           throw a(null);
/*     */         } 
/*     */         break;
/*     */       } 
/*     */     } 
/*     */   }
/*     */   
/*     */   public static void a(long[] paramArrayOflong1, long[] paramArrayOflong2) {
/*     */     e(paramArrayOflong1, paramArrayOflong2);
/*     */     c(paramArrayOflong1, paramArrayOflong2, 0, paramArrayOflong1.length);
/*     */   }
/*     */   
/*     */   public static void f(long[] paramArrayOflong) {
/*     */     b(paramArrayOflong, 0, paramArrayOflong.length);
/*     */   }
/*     */   
/*     */   public static long[] a(long[] paramArrayOflong, Random paramRandom) {
/*     */     for (int i = paramArrayOflong.length; i-- != 0; ) {
/*     */       int j = paramRandom.nextInt(i + 1);
/*     */       long l = paramArrayOflong[i];
/*     */       paramArrayOflong[i] = paramArrayOflong[j];
/*     */     } 
/*     */     return paramArrayOflong;
/*     */   }
/*     */   
/*     */   public static void a(long[] paramArrayOflong, hq paramhq) {
/*     */     c(paramArrayOflong, 0, paramArrayOflong.length, paramhq);
/*     */   }
/*     */   
/*     */   private static Exception a(Exception paramException) {
/*     */     return paramException;
/*     */   }
/*     */ }


/* Location:              C:\Users\BukkitBypass\Desktop\MatrixAC\AAC\AAC-spigot-5.2.0.jar!\me\konsolas\aac\a1.class
 * Java compiler version: 8 (52.0)
 * JD-Core Version:       1.1.3
 */