/*    */ package me.konsolas.aac;
/*    */ import java.lang.invoke.MethodHandle;
/*    */ import javax.crypto.Cipher;
/*    */ 
/*    */ public class a6 {
/*    */   static {
/*    */     byte b1;
/*    */     long l1, l2, l3, l4, l5, l6, l7;
/*    */     int j;
/*    */     long l8, l9;
/* 11 */     for (n = nc.a(-8002644883524331246L, 4680740895246678658L, MethodHandles.lookup().lookupClass()).a(88176145464708L), l1 = n ^ 0x3D15D1A07F69L, l2 = l1 ^ 0x17F46BA67747L, l3 = l1 ^ 0x28A6FF213DAEL, l4 = l1 ^ 0x692C010B0E3FL, l5 = l1 ^ 0x60D9D16DB33L, l6 = l1 ^ 0x7912B68D1076L, l7 = (l1 ^ 0x3931DA3E11D1L) >>> 32L, j = (int)((l1 ^ 0x3931DA3E11D1L) << 32L >>> 32L), l1 ^ 0x3931DA3E11D1L, l8 = l1 ^ 0x3D6003EB97A9L, l9 = l1 ^ 0x3A2C4FC4DA87L, "妏䟠鯿镏녩졍艒⾿눇爨⮈鮤욇效售絪뗁眾ᓕ㗸".toCharArray()[17] = (char)("妏䟠鯿镏녩졍艒⾿눇爨⮈鮤욇效售絪뗁眾ᓕ㗸".toCharArray()[17] ^ 0xBF), "㑠??ᕂ".toCharArray()[0] = (char)("㑠??ᕂ".toCharArray()[0] ^ 0x6BA), (new byte[8])[0] = (byte)(int)(l1 >>> 56L), b1 = 1; b1 < 8; ) { (new byte[8])[b1] = (byte)(int)(l1 << b1 * 8 >>> 56L); b1++; }  Cipher cipher; (cipher = Cipher.getInstance(hY$g6.H("妏䟠鯿镏녩졍艒⾿눇爨⮈鮤욇效售絪뗁眾ᓕ㗸".toCharArray(), (short)935, (byte)0, (byte)5))).init(2, SecretKeyFactory.getInstance(hY$g6.H("㑠??ᕂ".toCharArray(), (short)2935, (byte)4, (byte)4)).generateSecret(new DESKeySpec(new byte[8])), new IvParameterSpec(new byte[8])); String[] arrayOfString = new String[11]; boolean bool = false; "ꄬ擸쁎➼⠻贵렼䝔酪ᒾ껐ꏐ梋諟ଭ駶ㆭ㤩ি឵Ỹ灖⑛豍䩾琰褗땧朧ᩂ쳲᧱【좗뭂ﱆ苞초ꟴ㭲馆댲ꊽゑ⿊걆⼆坫⅕郳၍쾕⛰볙㦰贇涁?﨎솁뙏ꔕ靕∎嫼奔䩮㠼ᅘ搗㙊澗純ᛶ줷鍇⋺챶⤣঩蟀ꮮ?鬮፫㮱뿘ᓛ磍狹끾㬷쯜棃珕リࠟ훉柯餰ᭋ࿗č♕۱럇稨딺赘ᶺ邃ᤱ徻뢶だ꧲紀䀭䐘敶첲ꦯ묎濙鬒אָ㕛".toCharArray()[63] = (char)("ꄬ擸쁎➼⠻贵렼䝔酪ᒾ껐ꏐ梋諟ଭ駶ㆭ㤩ি឵Ỹ灖⑛豍䩾琰褗땧朧ᩂ쳲᧱【좗뭂ﱆ苞초ꟴ㭲馆댲ꊽゑ⿊걆⼆坫⅕郳၍쾕⛰볙㦰贇涁?﨎솁뙏ꔕ靕∎嫼奔䩮㠼ᅘ搗㙊澗純ᛶ줷鍇⋺챶⤣঩蟀ꮮ?鬮፫㮱뿘ᓛ磍狹끾㬷쯜棃珕リࠟ훉柯餰ᭋ࿗č♕۱럇稨딺赘ᶺ邃ᤱ徻뢶だ꧲紀䀭䐘敶첲ꦯ묎濙鬒אָ㕛".toCharArray()[63] ^ 0x6E7C); String str; int i = (str = hY$g6.H("ꄬ擸쁎➼⠻贵렼䝔酪ᒾ껐ꏐ梋諟ଭ駶ㆭ㤩ি឵Ỹ灖⑛豍䩾琰褗땧朧ᩂ쳲᧱【좗뭂ﱆ苞초ꟴ㭲馆댲ꊽゑ⿊걆⼆坫⅕郳၍쾕⛰볙㦰贇涁?﨎솁뙏ꔕ靕∎嫼奔䩮㠼ᅘ搗㙊澗純ᛶ줷鍇⋺챶⤣঩蟀ꮮ?鬮፫㮱뿘ᓛ磍狹끾㬷쯜棃珕リࠟ훉柯餰ᭋ࿗č♕۱럇稨딺赘ᶺ邃ᤱ徻뢶だ꧲紀䀭䐘敶첲ꦯ묎濙鬒אָ㕛".toCharArray(), (short)26370, (byte)2, (byte)1)).length(); byte b3 = 16; byte b2 = -1;
/*    */ 
/*    */ 
/*    */ 
/*    */     
/*    */     while (true);
/*    */ 
/*    */ 
/*    */ 
/*    */     
/* 21 */     byte b4 = -1;
/*    */ 
/*    */ 
/*    */ 
/*    */ 
/*    */ 
/*    */ 
/*    */ 
/*    */ 
/*    */ 
/*    */ 
/*    */ 
/*    */ 
/*    */ 
/*    */     
/* 36 */     throw new RuntimeException(SYNTHETIC_LOCAL_VARIABLE_0[9], b4);
/*    */   }
/*    */   
/*    */   private static final MethodHandle h;
/*    */   private static final MethodHandle g;
/*    */   private static final MethodHandle b;
/*    */   private static final MethodHandle l;
/*    */   private static final MethodHandle i;
/*    */   private static final MethodHandle e;
/*    */   private static final MethodHandle a;
/*    */   private static final MethodHandle m;
/*    */   private static final MethodHandle k;
/*    */   private static final MethodHandle d;
/*    */   private static final MethodHandle c;
/*    */   private static final MethodHandle j;
/*    */   private static final MethodHandle f;
/*    */   private static final long n;
/*    */   
/*    */   public static d7 a(Entity paramEntity, long paramLong, Vector paramVector1, Vector paramVector2, double paramDouble) {
/*    */     // Byte code:
/*    */     //   0: getstatic me/konsolas/aac/a6.n : J
/*    */     //   3: lload_1
/*    */     //   4: lxor
/*    */     //   5: lstore_1
/*    */     //   6: lload_1
/*    */     //   7: dup2
/*    */     //   8: ldc2_w 119835396391898
/*    */     //   11: lxor
/*    */     //   12: dup2
/*    */     //   13: bipush #16
/*    */     //   15: lushr
/*    */     //   16: lstore #7
/*    */     //   18: dup2
/*    */     //   19: bipush #48
/*    */     //   21: lshl
/*    */     //   22: bipush #48
/*    */     //   24: lushr
/*    */     //   25: l2i
/*    */     //   26: istore #9
/*    */     //   28: pop2
/*    */     //   29: pop2
/*    */     //   30: ldc2_w 5805399039375423992
/*    */     //   33: lload_1
/*    */     //   34: <illegal opcode> w : (JJ)[Lme/konsolas/aac/aN;
/*    */     //   39: aload_3
/*    */     //   40: invokevirtual clone : ()Lorg/bukkit/util/Vector;
/*    */     //   43: aload #4
/*    */     //   45: invokevirtual clone : ()Lorg/bukkit/util/Vector;
/*    */     //   48: invokevirtual normalize : ()Lorg/bukkit/util/Vector;
/*    */     //   51: dload #5
/*    */     //   53: invokevirtual multiply : (D)Lorg/bukkit/util/Vector;
/*    */     //   56: invokevirtual add : (Lorg/bukkit/util/Vector;)Lorg/bukkit/util/Vector;
/*    */     //   59: astore #11
/*    */     //   61: astore #10
/*    */     //   63: getstatic me/konsolas/aac/a6.h : Ljava/lang/invoke/MethodHandle;
/*    */     //   66: aload_0
/*    */     //   67: invokeinterface getWorld : ()Lorg/bukkit/World;
/*    */     //   72: invokevirtual invoke : (Lorg/bukkit/World;)Ljava/lang/Object;
/*    */     //   75: astore #12
/*    */     //   77: getstatic me/konsolas/aac/a6.g : Ljava/lang/invoke/MethodHandle;
/*    */     //   80: aload_3
/*    */     //   81: invokevirtual getX : ()D
/*    */     //   84: aload_3
/*    */     //   85: invokevirtual getY : ()D
/*    */     //   88: aload_3
/*    */     //   89: invokevirtual getZ : ()D
/*    */     //   92: invokevirtual invoke : (DDD)Ljava/lang/Object;
/*    */     //   95: astore #13
/*    */     //   97: getstatic me/konsolas/aac/a6.g : Ljava/lang/invoke/MethodHandle;
/*    */     //   100: aload #11
/*    */     //   102: invokevirtual getX : ()D
/*    */     //   105: aload #11
/*    */     //   107: invokevirtual getY : ()D
/*    */     //   110: aload #11
/*    */     //   112: invokevirtual getZ : ()D
/*    */     //   115: invokevirtual invoke : (DDD)Ljava/lang/Object;
/*    */     //   118: astore #14
/*    */     //   120: getstatic me/konsolas/aac/a6.f : Ljava/lang/invoke/MethodHandle;
/*    */     //   123: aload #12
/*    */     //   125: aload #13
/*    */     //   127: aload #14
/*    */     //   129: invokevirtual invoke : (Ljava/lang/Object;Ljava/lang/Object;Ljava/lang/Object;)Ljava/lang/Object;
/*    */     //   132: astore #15
/*    */     //   134: aload #15
/*    */     //   136: aload #10
/*    */     //   138: ifnull -> 173
/*    */     //   141: ifnonnull -> 165
/*    */     //   144: goto -> 157
/*    */     //   147: ldc2_w 5863385691466944937
/*    */     //   150: lload_1
/*    */     //   151: <illegal opcode> w : (Ljava/lang/Throwable;JJ)Ljava/lang/Throwable;
/*    */     //   156: athrow
/*    */     //   157: new me/konsolas/aac/d7
/*    */     //   160: dup
/*    */     //   161: invokespecial <init> : ()V
/*    */     //   164: areturn
/*    */     //   165: getstatic me/konsolas/aac/a6.e : Ljava/lang/invoke/MethodHandle;
/*    */     //   168: aload #15
/*    */     //   170: invokevirtual invoke : (Ljava/lang/Object;)Ljava/lang/Object;
/*    */     //   173: astore #16
/*    */     //   175: getstatic me/konsolas/aac/a6.b : Ljava/lang/invoke/MethodHandle;
/*    */     //   178: aload #15
/*    */     //   180: invokevirtual invoke : (Ljava/lang/Object;)Ljava/lang/Object;
/*    */     //   183: astore #17
/*    */     //   185: new org/bukkit/util/Vector
/*    */     //   188: dup
/*    */     //   189: getstatic me/konsolas/aac/a6.a : Ljava/lang/invoke/MethodHandle;
/*    */     //   192: aload #16
/*    */     //   194: invokevirtual invoke : (Ljava/lang/Object;)D
/*    */     //   197: getstatic me/konsolas/aac/a6.m : Ljava/lang/invoke/MethodHandle;
/*    */     //   200: aload #16
/*    */     //   202: invokevirtual invoke : (Ljava/lang/Object;)D
/*    */     //   205: getstatic me/konsolas/aac/a6.k : Ljava/lang/invoke/MethodHandle;
/*    */     //   208: aload #16
/*    */     //   210: invokevirtual invoke : (Ljava/lang/Object;)D
/*    */     //   213: invokespecial <init> : (DDD)V
/*    */     //   216: astore #18
/*    */     //   218: new org/bukkit/util/BlockVector
/*    */     //   221: dup
/*    */     //   222: getstatic me/konsolas/aac/a6.d : Ljava/lang/invoke/MethodHandle;
/*    */     //   225: aload #17
/*    */     //   227: invokevirtual invoke : (Ljava/lang/Object;)I
/*    */     //   230: getstatic me/konsolas/aac/a6.c : Ljava/lang/invoke/MethodHandle;
/*    */     //   233: aload #17
/*    */     //   235: invokevirtual invoke : (Ljava/lang/Object;)I
/*    */     //   238: getstatic me/konsolas/aac/a6.j : Ljava/lang/invoke/MethodHandle;
/*    */     //   241: aload #17
/*    */     //   243: invokevirtual invoke : (Ljava/lang/Object;)I
/*    */     //   246: invokespecial <init> : (III)V
/*    */     //   249: astore #19
/*    */     //   251: getstatic me/konsolas/aac/a6.i : Ljava/lang/invoke/MethodHandle;
/*    */     //   254: getstatic me/konsolas/aac/a6.l : Ljava/lang/invoke/MethodHandle;
/*    */     //   257: aload #15
/*    */     //   259: invokevirtual invoke : (Ljava/lang/Object;)Ljava/lang/Object;
/*    */     //   262: invokevirtual invoke : (Ljava/lang/Object;)Lorg/bukkit/block/BlockFace;
/*    */     //   265: astore #20
/*    */     //   267: new me/konsolas/aac/d7
/*    */     //   270: dup
/*    */     //   271: lload #7
/*    */     //   273: iload #9
/*    */     //   275: i2s
/*    */     //   276: aload #18
/*    */     //   278: aload #19
/*    */     //   280: aload #20
/*    */     //   282: invokespecial <init> : (JSLorg/bukkit/util/Vector;Lorg/bukkit/util/BlockVector;Lorg/bukkit/block/BlockFace;)V
/*    */     //   285: areturn
/*    */     //   286: astore #12
/*    */     //   288: new java/lang/RuntimeException
/*    */     //   291: dup
/*    */     //   292: aload #12
/*    */     //   294: invokespecial <init> : (Ljava/lang/Throwable;)V
/*    */     //   297: athrow
/*    */     // Line number table:
/*    */     //   Java source line number -> byte code offset
/*    */     //   #7	-> 39
/*    */     //   #9	-> 63
/*    */     //   #22	-> 77
/*    */     //   #4	-> 97
/*    */     //   #24	-> 120
/*    */     //   #19	-> 134
/*    */     //   #40	-> 165
/*    */     //   #12	-> 175
/*    */     //   #31	-> 185
/*    */     //   #33	-> 218
/*    */     //   #16	-> 251
/*    */     //   #45	-> 267
/*    */     //   #35	-> 286
/*    */     //   #1	-> 288
/*    */     // Exception table:
/*    */     //   from	to	target	type
/*    */     //   63	164	286	java/lang/Throwable
/*    */     //   134	144	147	java/lang/Throwable
/*    */     //   165	285	286	java/lang/Throwable
/*    */   }
/*    */   
/*    */   private static Throwable a(Throwable paramThrowable) {
/*    */     return paramThrowable;
/*    */   }
/*    */   
/*    */   private static String a(byte[] paramArrayOfbyte) {
/*    */     byte b1 = 0;
/*    */     int i;
/*    */     char[] arrayOfChar = new char[i = paramArrayOfbyte.length];
/*    */     for (byte b2 = 0; b2 < i; b2++) {
/*    */       int j;
/*    */       if ((j = 0xFF & paramArrayOfbyte[b2]) < 192) {
/*    */         arrayOfChar[b1++] = (char)j;
/*    */       } else if (j < 224) {
/*    */         char c = (char)((char)(j & 0x1F) << 6);
/*    */         j = paramArrayOfbyte[++b2];
/*    */         c = (char)(c | (char)(j & 0x3F));
/*    */         arrayOfChar[b1++] = c;
/*    */       } else if (b2 < i - 2) {
/*    */         char c = (char)((char)(j & 0xF) << 12);
/*    */         j = paramArrayOfbyte[++b2];
/*    */         c = (char)(c | (char)(j & 0x3F) << 6);
/*    */         j = paramArrayOfbyte[++b2];
/*    */         c = (char)(c | (char)(j & 0x3F));
/*    */         arrayOfChar[b1++] = c;
/*    */       } 
/*    */     } 
/*    */     return new String(arrayOfChar, 0, b1);
/*    */   }
/*    */ }


/* Location:              C:\Users\BukkitBypass\Desktop\MatrixAC\AAC\AAC-spigot-5.2.0.jar!\me\konsolas\aac\a6.class
 * Java compiler version: 8 (52.0)
 * JD-Core Version:       1.1.3
 */