/*   1 */ package me.konsolas.aac;public final class b0 { public static final b0 b; public static final b0 l; private final boolean a; private final boolean m; static { byte b1; long l1, l2; for (p = nc.a(-567554977811166646L, 881943658706195814L, MethodHandles.lookup().lookupClass()).a(91834491258033L), l1 = p ^ 0x71AEAFAB142AL, l2 = l1 ^ 0x72CE2C825F36L, s = new HashMap<>(13), "謮탒훡뇒㆞ደ棛㩉䆇酅Ᵹ튩娋鋣⼥溉䢞".toCharArray()[16] = (char)("謮탒훡뇒㆞ደ棛㩉䆇酅Ᵹ튩娋鋣⼥溉䢞".toCharArray()[16] ^ 0x7CEB), "ᡛ빊云䜝".toCharArray()[0] = (char)("ᡛ빊云䜝".toCharArray()[0] ^ 0x3B27), (new byte[8])[0] = (byte)(int)(l1 >>> 56L), b1 = 1; b1 < 8; ) { (new byte[8])[b1] = (byte)(int)(l1 << b1 * 8 >>> 56L); b1++; }  Cipher cipher; (cipher = Cipher.getInstance(hY$g6.H("謮탒훡뇒㆞ደ棛㩉䆇酅Ᵹ튩娋鋣⼥溉䢞".toCharArray(), (short)15825, (byte)1, (byte)4))).init(2, SecretKeyFactory.getInstance(hY$g6.H("ᡛ빊云䜝".toCharArray(), (short)24020, (byte)4, (byte)0)).generateSecret(new DESKeySpec(new byte[8])), new IvParameterSpec(new byte[8])); String[] arrayOfString = new String[30]; boolean bool = false; "펋딾놃齶␤鱓ླྀ㘌녒㈃搶홇썇딎ⰻ쪑フͺ￱䁴ᘎҵ⭰꫓䌭藹멌뭬鰷꯰帹帖〆客碥ﳺ㽣珣⚛╤랫䘬㺠퉶ދ衄粧龯◖騚卪࿢ुꢸꃏཾ탬읞섊滪坩縣銀뉚ⲏ䂕햔뒝ﻸ慸龺꫉늤퀮ᄰຏ鱈ㄆ㧠쾖⑝ᜂö껳硨䨜퓡轍ၗ錢湊ꥍ벪ᬬ䙋ዟ䵔䂵෼࢞銖앇ꀛ㵲㪂᷑릌衢黎?⎾ẻ⁼엚翏✑᪳㹖絁軨횎螀?駐䐨啡?媘ἭＶ律뜤⋐ސ꧷뱟ꆙ滬?ꈎ컷ᓉ秕Ѭ熘薮鰫膭∌釢넭䟯㊤䦄ꄽ溭Ժ㛨㛭១ퟲ጖ᖭ䮨謀볢鼎钭쩗麝涮ႛ⼎厉鳛꯺ࡍ뭤䯞㏝ᱩ灤薟鍽㋂븠镏?场⛭哳튜㍤樵紇떔❫뜃좆⼷칻䃃鑲슓邈䅤鵬ꅷ࣮?릊൏㾀넇﵊䍊啣葤驾童淡铇쬥⦂㮽?䐓耗싷뎴樍푦闃⁜醼À⾆趓䚖禊뵣洜晗꺧䳰撦诲ࡗ랆밟ݗⳐ栦셞㪹꿰掝褢洮﫾セ䄉碍츯懬ꂰ찶⧼Ƹ⭣氛捌꧿䘾쎎쭽ꃠ䛰眠系鎚꯾฀ΰ㉂ं㫲ꋚ瑏숽㸴쾸▘呑㯜Ⲹ庖솺㚄뾰测놏婟呅ఊ⑳콉?黿틬䅷䜩組⧨魡㿥匣群혲坐ⷋ熮욭䝇㒩ꍊꃞ挕꽼놟﫱?Ꮞ轢劯妎媯尘낂郹ɍ離Ꙕ๤᳧╉昁㯹摢䋖꽥愘猋蚙䅒乡⴬迋⫰ჵ瞸ㄴꮳ┶夲蛞奔譃涨緍햻畝䰠漬鸚?陽먗ꄘ뻌﵃뜝鯒ꇭၠ?汩꺙탢웨茐꽎䌮ꀞ꽑면꒑⨞ᱩ?襳㚯읊µ盽邒樧ᗁಗ衰첨ᡎ嫺?ሗ쯮諏䔉?뎙㹼ⅅ黶闲䷭饧왕끶ġ윳ᛦ躔ꓡ楶杻㌂꾔踠诣댋ꃔ㪫ज猷漑퇾幭퍮㎫ج⒏趍諐곊춿ઽ灡䯆콻?⣜Ⳑ뗳⫛Ļ휔ᐏ뭋䌺玭넇?茒寸木펛曮ϻ꾬ᒇ橵꙼⦒鎌饧캧쏧禐䛝橣ۍ㯍䎂쒋㐅౹噽鬪ॻˋ౦䀱叙瓷?涴擡၁ꊇ삧?㢋삧䭻⬡﹟㩼鑹⵰ｩ餜勮蒋㩏똪஢ᰄ鿵潾勵䲼此ꆏ뢆ל瞐良￹ᖦ﵃죐厸饨ஔ枷뷷䞩⾶츋ꯒ専ᑝ㿎䄢ؔ?ㄺ惼ᓫ฽䲵ᑭ베?魘樷땄ᦼᣡᵉ陌귒륃햴˗崣햺煄険鱜쇪಺⍟䞱㸐湨齺贆䖄쳨㆘뀚ꦧ蜳孲쀫䯾ᜏ㪍陨꿴또ⶣ蘋⢖复薺⅄뼒뫋壐큊?钝ꆑ扏쒤흫뒾괹匝뵩ͦ梄늲暙꼱충쿯暘匒覒ῠ봀ᕰ叧㙰鉢튰듏铥ኻ횵ึ៤䝖୎䄢鸫?巸ꪟꮭ؋絜⯳鰪侺샆鴖뜶理鐀꜃빛ꔧ쯣⃣".toCharArray()[195] = (char)("펋딾놃齶␤鱓ླྀ㘌녒㈃搶홇썇딎ⰻ쪑フͺ￱䁴ᘎҵ⭰꫓䌭藹멌뭬鰷꯰帹帖〆客碥ﳺ㽣珣⚛╤랫䘬㺠퉶ދ衄粧龯◖騚卪࿢ुꢸꃏཾ탬읞섊滪坩縣銀뉚ⲏ䂕햔뒝ﻸ慸龺꫉늤퀮ᄰຏ鱈ㄆ㧠쾖⑝ᜂö껳硨䨜퓡轍ၗ錢湊ꥍ벪ᬬ䙋ዟ䵔䂵෼࢞銖앇ꀛ㵲㪂᷑릌衢黎?⎾ẻ⁼엚翏✑᪳㹖絁軨횎螀?駐䐨啡?媘ἭＶ律뜤⋐ސ꧷뱟ꆙ滬?ꈎ컷ᓉ秕Ѭ熘薮鰫膭∌釢넭䟯㊤䦄ꄽ溭Ժ㛨㛭១ퟲ጖ᖭ䮨謀볢鼎钭쩗麝涮ႛ⼎厉鳛꯺ࡍ뭤䯞㏝ᱩ灤薟鍽㋂븠镏?场⛭哳튜㍤樵紇떔❫뜃좆⼷칻䃃鑲슓邈䅤鵬ꅷ࣮?릊൏㾀넇﵊䍊啣葤驾童淡铇쬥⦂㮽?䐓耗싷뎴樍푦闃⁜醼À⾆趓䚖禊뵣洜晗꺧䳰撦诲ࡗ랆밟ݗⳐ栦셞㪹꿰掝褢洮﫾セ䄉碍츯懬ꂰ찶⧼Ƹ⭣氛捌꧿䘾쎎쭽ꃠ䛰眠系鎚꯾฀ΰ㉂ं㫲ꋚ瑏숽㸴쾸▘呑㯜Ⲹ庖솺㚄뾰测놏婟呅ఊ⑳콉?黿틬䅷䜩組⧨魡㿥匣群혲坐ⷋ熮욭䝇㒩ꍊꃞ挕꽼놟﫱?Ꮞ轢劯妎媯尘낂郹ɍ離Ꙕ๤᳧╉昁㯹摢䋖꽥愘猋蚙䅒乡⴬迋⫰ჵ瞸ㄴꮳ┶夲蛞奔譃涨緍햻畝䰠漬鸚?陽먗ꄘ뻌﵃뜝鯒ꇭၠ?汩꺙탢웨茐꽎䌮ꀞ꽑면꒑⨞ᱩ?襳㚯읊µ盽邒樧ᗁಗ衰첨ᡎ嫺?ሗ쯮諏䔉?뎙㹼ⅅ黶闲䷭饧왕끶ġ윳ᛦ躔ꓡ楶杻㌂꾔踠诣댋ꃔ㪫ज猷漑퇾幭퍮㎫ج⒏趍諐곊춿ઽ灡䯆콻?⣜Ⳑ뗳⫛Ļ휔ᐏ뭋䌺玭넇?茒寸木펛曮ϻ꾬ᒇ橵꙼⦒鎌饧캧쏧禐䛝橣ۍ㯍䎂쒋㐅౹噽鬪ॻˋ౦䀱叙瓷?涴擡၁ꊇ삧?㢋삧䭻⬡﹟㩼鑹⵰ｩ餜勮蒋㩏똪஢ᰄ鿵潾勵䲼此ꆏ뢆ל瞐良￹ᖦ﵃죐厸饨ஔ枷뷷䞩⾶츋ꯒ専ᑝ㿎䄢ؔ?ㄺ惼ᓫ฽䲵ᑭ베?魘樷땄ᦼᣡᵉ陌귒륃햴˗崣햺煄険鱜쇪಺⍟䞱㸐湨齺贆䖄쳨㆘뀚ꦧ蜳孲쀫䯾ᜏ㪍陨꿴또ⶣ蘋⢖复薺⅄뼒뫋壐큊?钝ꆑ扏쒤흫뒾괹匝뵩ͦ梄늲暙꼱충쿯暘匒覒ῠ봀ᕰ叧㙰鉢튰듏铥ኻ횵ึ៤䝖୎䄢鸫?巸ꪟꮭ؋絜⯳鰪侺샆鴖뜶理鐀꜃빛ꔧ쯣⃣".toCharArray()[195] ^ 0x7C47); String str; int i = (str = hY$g6.H("펋딾놃齶␤鱓ླྀ㘌녒㈃搶홇썇딎ⰻ쪑フͺ￱䁴ᘎҵ⭰꫓䌭藹멌뭬鰷꯰帹帖〆客碥ﳺ㽣珣⚛╤랫䘬㺠퉶ދ衄粧龯◖騚卪࿢ुꢸꃏཾ탬읞섊滪坩縣銀뉚ⲏ䂕햔뒝ﻸ慸龺꫉늤퀮ᄰຏ鱈ㄆ㧠쾖⑝ᜂö껳硨䨜퓡轍ၗ錢湊ꥍ벪ᬬ䙋ዟ䵔䂵෼࢞銖앇ꀛ㵲㪂᷑릌衢黎?⎾ẻ⁼엚翏✑᪳㹖絁軨횎螀?駐䐨啡?媘ἭＶ律뜤⋐ސ꧷뱟ꆙ滬?ꈎ컷ᓉ秕Ѭ熘薮鰫膭∌釢넭䟯㊤䦄ꄽ溭Ժ㛨㛭១ퟲ጖ᖭ䮨謀볢鼎钭쩗麝涮ႛ⼎厉鳛꯺ࡍ뭤䯞㏝ᱩ灤薟鍽㋂븠镏?场⛭哳튜㍤樵紇떔❫뜃좆⼷칻䃃鑲슓邈䅤鵬ꅷ࣮?릊൏㾀넇﵊䍊啣葤驾童淡铇쬥⦂㮽?䐓耗싷뎴樍푦闃⁜醼À⾆趓䚖禊뵣洜晗꺧䳰撦诲ࡗ랆밟ݗⳐ栦셞㪹꿰掝褢洮﫾セ䄉碍츯懬ꂰ찶⧼Ƹ⭣氛捌꧿䘾쎎쭽ꃠ䛰眠系鎚꯾฀ΰ㉂ं㫲ꋚ瑏숽㸴쾸▘呑㯜Ⲹ庖솺㚄뾰测놏婟呅ఊ⑳콉?黿틬䅷䜩組⧨魡㿥匣群혲坐ⷋ熮욭䝇㒩ꍊꃞ挕꽼놟﫱?Ꮞ轢劯妎媯尘낂郹ɍ離Ꙕ๤᳧╉昁㯹摢䋖꽥愘猋蚙䅒乡⴬迋⫰ჵ瞸ㄴꮳ┶夲蛞奔譃涨緍햻畝䰠漬鸚?陽먗ꄘ뻌﵃뜝鯒ꇭၠ?汩꺙탢웨茐꽎䌮ꀞ꽑면꒑⨞ᱩ?襳㚯읊µ盽邒樧ᗁಗ衰첨ᡎ嫺?ሗ쯮諏䔉?뎙㹼ⅅ黶闲䷭饧왕끶ġ윳ᛦ躔ꓡ楶杻㌂꾔踠诣댋ꃔ㪫ज猷漑퇾幭퍮㎫ج⒏趍諐곊춿ઽ灡䯆콻?⣜Ⳑ뗳⫛Ļ휔ᐏ뭋䌺玭넇?茒寸木펛曮ϻ꾬ᒇ橵꙼⦒鎌饧캧쏧禐䛝橣ۍ㯍䎂쒋㐅౹噽鬪ॻˋ౦䀱叙瓷?涴擡၁ꊇ삧?㢋삧䭻⬡﹟㩼鑹⵰ｩ餜勮蒋㩏똪஢ᰄ鿵潾勵䲼此ꆏ뢆ל瞐良￹ᖦ﵃죐厸饨ஔ枷뷷䞩⾶츋ꯒ専ᑝ㿎䄢ؔ?ㄺ惼ᓫ฽䲵ᑭ베?魘樷땄ᦼᣡᵉ陌귒륃햴˗崣햺煄険鱜쇪಺⍟䞱㸐湨齺贆䖄쳨㆘뀚ꦧ蜳孲쀫䯾ᜏ㪍陨꿴또ⶣ蘋⢖复薺⅄뼒뫋壐큊?钝ꆑ扏쒤흫뒾괹匝뵩ͦ梄늲暙꼱충쿯暘匒覒ῠ봀ᕰ叧㙰鉢튰듏铥ኻ횵ึ៤䝖୎䄢鸫?巸ꪟꮭ؋絜⯳鰪侺샆鴖뜶理鐀꜃빛ꔧ쯣⃣".toCharArray(), (short)20038, (byte)0, (byte)4)).length(); byte b2 = 16; byte b = -1;
/*     */     while (true); }
/*     */   
/*     */   private final int d; private final int g; private final boolean o; private final boolean c; private final boolean i; private final int e; private final int f; private final boolean h; private final boolean n; private final boolean k; @Nullable
/*     */   String j; private static final long p; private static final String[] q; private static final String[] r; private static final Map s;
/*     */   
/*     */   public boolean h() {
/*   8 */     return this.n;
/*     */   }
/*     */ 
/*     */ 
/*     */ 
/*     */ 
/*     */ 
/*     */ 
/*     */ 
/*     */ 
/*     */ 
/*     */ 
/*     */ 
/*     */   
/*     */   public boolean a() {
/*  23 */     return this.m;
/*     */   }
/*     */   public boolean g() {
/*  26 */     return this.o;
/*     */   }
/*     */ 
/*     */ 
/*     */ 
/*     */ 
/*     */ 
/*     */ 
/*     */ 
/*     */ 
/*     */ 
/*     */ 
/*     */   
/*     */   public int a() {
/*  40 */     return this.e;
/*     */   }
/*     */ 
/*     */ 
/*     */   
/*     */   public boolean f() {
/*  46 */     return this.h;
/*     */   }
/*     */ 
/*     */ 
/*     */ 
/*     */ 
/*     */ 
/*     */ 
/*     */ 
/*     */ 
/*     */ 
/*     */ 
/*     */ 
/*     */ 
/*     */ 
/*     */ 
/*     */ 
/*     */ 
/*     */ 
/*     */ 
/*     */ 
/*     */ 
/*     */ 
/*     */ 
/*     */ 
/*     */ 
/*     */ 
/*     */ 
/*     */ 
/*     */ 
/*     */ 
/*     */ 
/*     */ 
/*     */ 
/*     */ 
/*     */ 
/*     */ 
/*     */ 
/*     */ 
/*     */   
/*     */   b0(c4 paramc4) {
/*  87 */     this.a = paramc4.g;
/*     */ 
/*     */ 
/*     */ 
/*     */ 
/*     */     
/*     */     this.m = paramc4.c;
/*     */ 
/*     */ 
/*     */ 
/*     */ 
/*     */     
/*     */     this.d = paramc4.e;
/*     */ 
/*     */ 
/*     */ 
/*     */ 
/*     */     
/* 105 */     this.g = -1;
/*     */ 
/*     */ 
/*     */ 
/*     */ 
/*     */ 
/*     */ 
/*     */ 
/*     */ 
/*     */ 
/*     */ 
/*     */ 
/*     */ 
/*     */ 
/*     */ 
/*     */ 
/*     */ 
/*     */ 
/*     */ 
/*     */     
/* 125 */     this.o = false;
/*     */ 
/*     */ 
/*     */ 
/*     */     
/*     */     this.c = false;
/*     */ 
/*     */ 
/*     */ 
/*     */     
/* 135 */     this.i = false;
/*     */     this.e = paramc4.a;
/*     */     this.f = paramc4.d;
/*     */     this.h = paramc4.b;
/*     */     this.n = paramc4.f;
/*     */     this.k = paramc4.h;
/*     */   }
/*     */   
/*     */   public int c() {
/*     */     return this.f;
/*     */   }
/*     */   
/*     */   public boolean d() {
/*     */     return this.i;
/*     */   }
/*     */   
/*     */   public int d() {
/*     */     return this.d;
/*     */   }
/*     */   
/*     */   public String toString() {
/*     */     // Byte code:
/*     */     //   0: getstatic me/konsolas/aac/b0.p : J
/*     */     //   3: ldc2_w 108324393448135
/*     */     //   6: lxor
/*     */     //   7: lstore_1
/*     */     //   8: lload_1
/*     */     //   9: dup2
/*     */     //   10: ldc2_w 40995982563644
/*     */     //   13: lxor
/*     */     //   14: dup2
/*     */     //   15: bipush #56
/*     */     //   17: lushr
/*     */     //   18: l2i
/*     */     //   19: istore_3
/*     */     //   20: dup2
/*     */     //   21: bipush #8
/*     */     //   23: lshl
/*     */     //   24: bipush #32
/*     */     //   26: lushr
/*     */     //   27: l2i
/*     */     //   28: istore #4
/*     */     //   30: dup2
/*     */     //   31: bipush #40
/*     */     //   33: lshl
/*     */     //   34: bipush #40
/*     */     //   36: lushr
/*     */     //   37: l2i
/*     */     //   38: istore #5
/*     */     //   40: pop2
/*     */     //   41: pop2
/*     */     //   42: ldc2_w -5956333091657896556
/*     */     //   45: lload_1
/*     */     //   46: <illegal opcode> w : (JJ)[Lme/konsolas/aac/aN;
/*     */     //   51: aload_0
/*     */     //   52: getfield j : Ljava/lang/String;
/*     */     //   55: astore #7
/*     */     //   57: astore #6
/*     */     //   59: aload #7
/*     */     //   61: aload #6
/*     */     //   63: ifnonnull -> 84
/*     */     //   66: ifnull -> 87
/*     */     //   69: goto -> 82
/*     */     //   72: ldc2_w -5951971712051042760
/*     */     //   75: lload_1
/*     */     //   76: <illegal opcode> w : (Laacinternal/v;JJ)Laacinternal/v;
/*     */     //   81: athrow
/*     */     //   82: aload #7
/*     */     //   84: goto -> 102
/*     */     //   87: aload_0
/*     */     //   88: aload_0
/*     */     //   89: iload_3
/*     */     //   90: i2b
/*     */     //   91: iload #4
/*     */     //   93: iload #5
/*     */     //   95: invokespecial a : (BII)Ljava/lang/String;
/*     */     //   98: dup_x1
/*     */     //   99: putfield j : Ljava/lang/String;
/*     */     //   102: areturn
/*     */     // Line number table:
/*     */     //   Java source line number -> byte code offset
/*     */     //   #77	-> 51
/*     */     //   #75	-> 59
/*     */     // Exception table:
/*     */     //   from	to	target	type
/*     */     //   59	69	72	aacinternal/v
/*     */   }
/*     */   
/*     */   private String a(byte paramByte, int paramInt1, int paramInt2) {
/*     */     // Byte code:
/*     */     //   0: iload_1
/*     */     //   1: i2l
/*     */     //   2: bipush #56
/*     */     //   4: lshl
/*     */     //   5: iload_2
/*     */     //   6: i2l
/*     */     //   7: bipush #32
/*     */     //   9: lshl
/*     */     //   10: bipush #8
/*     */     //   12: lushr
/*     */     //   13: lor
/*     */     //   14: iload_3
/*     */     //   15: i2l
/*     */     //   16: bipush #40
/*     */     //   18: lshl
/*     */     //   19: bipush #40
/*     */     //   21: lushr
/*     */     //   22: lor
/*     */     //   23: getstatic me/konsolas/aac/b0.p : J
/*     */     //   26: lxor
/*     */     //   27: lstore #4
/*     */     //   29: ldc2_w -6115907103327933475
/*     */     //   32: lload #4
/*     */     //   34: <illegal opcode> w : (JJ)[Lme/konsolas/aac/aN;
/*     */     //   39: new java/lang/StringBuilder
/*     */     //   42: dup
/*     */     //   43: invokespecial <init> : ()V
/*     */     //   46: astore #7
/*     */     //   48: astore #6
/*     */     //   50: aload_0
/*     */     //   51: getfield a : Z
/*     */     //   54: aload #6
/*     */     //   56: ifnonnull -> 114
/*     */     //   59: ifeq -> 110
/*     */     //   62: goto -> 76
/*     */     //   65: ldc2_w -6111546066211168143
/*     */     //   68: lload #4
/*     */     //   70: <illegal opcode> w : (Laacinternal/v;JJ)Laacinternal/v;
/*     */     //   75: athrow
/*     */     //   76: aload #7
/*     */     //   78: sipush #7077
/*     */     //   81: ldc2_w 4804074269986201972
/*     */     //   84: lload #4
/*     */     //   86: lxor
/*     */     //   87: <illegal opcode> a : (IJ)Ljava/lang/String;
/*     */     //   92: invokevirtual append : (Ljava/lang/String;)Ljava/lang/StringBuilder;
/*     */     //   95: pop
/*     */     //   96: goto -> 110
/*     */     //   99: ldc2_w -6111546066211168143
/*     */     //   102: lload #4
/*     */     //   104: <illegal opcode> w : (Laacinternal/v;JJ)Laacinternal/v;
/*     */     //   109: athrow
/*     */     //   110: aload_0
/*     */     //   111: getfield m : Z
/*     */     //   114: iload_1
/*     */     //   115: iflt -> 178
/*     */     //   118: aload #6
/*     */     //   120: ifnonnull -> 178
/*     */     //   123: ifeq -> 174
/*     */     //   126: goto -> 140
/*     */     //   129: ldc2_w -6111546066211168143
/*     */     //   132: lload #4
/*     */     //   134: <illegal opcode> w : (Laacinternal/v;JJ)Laacinternal/v;
/*     */     //   139: athrow
/*     */     //   140: aload #7
/*     */     //   142: sipush #18761
/*     */     //   145: ldc2_w 5605290189214118812
/*     */     //   148: lload #4
/*     */     //   150: lxor
/*     */     //   151: <illegal opcode> a : (IJ)Ljava/lang/String;
/*     */     //   156: invokevirtual append : (Ljava/lang/String;)Ljava/lang/StringBuilder;
/*     */     //   159: pop
/*     */     //   160: goto -> 174
/*     */     //   163: ldc2_w -6111546066211168143
/*     */     //   166: lload #4
/*     */     //   168: <illegal opcode> w : (Laacinternal/v;JJ)Laacinternal/v;
/*     */     //   173: athrow
/*     */     //   174: aload_0
/*     */     //   175: getfield d : I
/*     */     //   178: iconst_m1
/*     */     //   179: iload_2
/*     */     //   180: iflt -> 291
/*     */     //   183: aload #6
/*     */     //   185: ifnonnull -> 291
/*     */     //   188: if_icmpeq -> 263
/*     */     //   191: goto -> 205
/*     */     //   194: ldc2_w -6111546066211168143
/*     */     //   197: lload #4
/*     */     //   199: <illegal opcode> w : (Laacinternal/v;JJ)Laacinternal/v;
/*     */     //   204: athrow
/*     */     //   205: aload #7
/*     */     //   207: sipush #15970
/*     */     //   210: ldc2_w 342075131577795748
/*     */     //   213: lload #4
/*     */     //   215: lxor
/*     */     //   216: <illegal opcode> a : (IJ)Ljava/lang/String;
/*     */     //   221: invokevirtual append : (Ljava/lang/String;)Ljava/lang/StringBuilder;
/*     */     //   224: aload_0
/*     */     //   225: getfield d : I
/*     */     //   228: invokevirtual append : (I)Ljava/lang/StringBuilder;
/*     */     //   231: sipush #27443
/*     */     //   234: ldc2_w 6574306629623992823
/*     */     //   237: lload #4
/*     */     //   239: lxor
/*     */     //   240: <illegal opcode> a : (IJ)Ljava/lang/String;
/*     */     //   245: invokevirtual append : (Ljava/lang/String;)Ljava/lang/StringBuilder;
/*     */     //   248: pop
/*     */     //   249: goto -> 263
/*     */     //   252: ldc2_w -6111546066211168143
/*     */     //   255: lload #4
/*     */     //   257: <illegal opcode> w : (Laacinternal/v;JJ)Laacinternal/v;
/*     */     //   262: athrow
/*     */     //   263: aload_0
/*     */     //   264: getfield g : I
/*     */     //   267: aload #6
/*     */     //   269: iload_3
/*     */     //   270: iflt -> 358
/*     */     //   273: ifnonnull -> 356
/*     */     //   276: iconst_m1
/*     */     //   277: goto -> 291
/*     */     //   280: ldc2_w -6111546066211168143
/*     */     //   283: lload #4
/*     */     //   285: <illegal opcode> w : (Laacinternal/v;JJ)Laacinternal/v;
/*     */     //   290: athrow
/*     */     //   291: if_icmpeq -> 352
/*     */     //   294: aload #7
/*     */     //   296: sipush #20044
/*     */     //   299: ldc2_w 4849340731694478467
/*     */     //   302: lload #4
/*     */     //   304: lxor
/*     */     //   305: <illegal opcode> a : (IJ)Ljava/lang/String;
/*     */     //   310: invokevirtual append : (Ljava/lang/String;)Ljava/lang/StringBuilder;
/*     */     //   313: aload_0
/*     */     //   314: getfield g : I
/*     */     //   317: invokevirtual append : (I)Ljava/lang/StringBuilder;
/*     */     //   320: sipush #7494
/*     */     //   323: ldc2_w 8762155303089481608
/*     */     //   326: lload #4
/*     */     //   328: lxor
/*     */     //   329: <illegal opcode> a : (IJ)Ljava/lang/String;
/*     */     //   334: invokevirtual append : (Ljava/lang/String;)Ljava/lang/StringBuilder;
/*     */     //   337: pop
/*     */     //   338: goto -> 352
/*     */     //   341: ldc2_w -6111546066211168143
/*     */     //   344: lload #4
/*     */     //   346: <illegal opcode> w : (Laacinternal/v;JJ)Laacinternal/v;
/*     */     //   351: athrow
/*     */     //   352: aload_0
/*     */     //   353: getfield o : Z
/*     */     //   356: aload #6
/*     */     //   358: iload_1
/*     */     //   359: iflt -> 422
/*     */     //   362: ifnonnull -> 420
/*     */     //   365: ifeq -> 416
/*     */     //   368: goto -> 382
/*     */     //   371: ldc2_w -6111546066211168143
/*     */     //   374: lload #4
/*     */     //   376: <illegal opcode> w : (Laacinternal/v;JJ)Laacinternal/v;
/*     */     //   381: athrow
/*     */     //   382: aload #7
/*     */     //   384: sipush #11385
/*     */     //   387: ldc2_w 7740209428481119931
/*     */     //   390: lload #4
/*     */     //   392: lxor
/*     */     //   393: <illegal opcode> a : (IJ)Ljava/lang/String;
/*     */     //   398: invokevirtual append : (Ljava/lang/String;)Ljava/lang/StringBuilder;
/*     */     //   401: pop
/*     */     //   402: goto -> 416
/*     */     //   405: ldc2_w -6111546066211168143
/*     */     //   408: lload #4
/*     */     //   410: <illegal opcode> w : (Laacinternal/v;JJ)Laacinternal/v;
/*     */     //   415: athrow
/*     */     //   416: aload_0
/*     */     //   417: getfield c : Z
/*     */     //   420: aload #6
/*     */     //   422: iload_2
/*     */     //   423: ifle -> 490
/*     */     //   426: ifnonnull -> 484
/*     */     //   429: ifeq -> 480
/*     */     //   432: goto -> 446
/*     */     //   435: ldc2_w -6111546066211168143
/*     */     //   438: lload #4
/*     */     //   440: <illegal opcode> w : (Laacinternal/v;JJ)Laacinternal/v;
/*     */     //   445: athrow
/*     */     //   446: aload #7
/*     */     //   448: sipush #26881
/*     */     //   451: ldc2_w 1343731633576170460
/*     */     //   454: lload #4
/*     */     //   456: lxor
/*     */     //   457: <illegal opcode> a : (IJ)Ljava/lang/String;
/*     */     //   462: invokevirtual append : (Ljava/lang/String;)Ljava/lang/StringBuilder;
/*     */     //   465: pop
/*     */     //   466: goto -> 480
/*     */     //   469: ldc2_w -6111546066211168143
/*     */     //   472: lload #4
/*     */     //   474: <illegal opcode> w : (Laacinternal/v;JJ)Laacinternal/v;
/*     */     //   479: athrow
/*     */     //   480: aload_0
/*     */     //   481: getfield i : Z
/*     */     //   484: iload_3
/*     */     //   485: iflt -> 548
/*     */     //   488: aload #6
/*     */     //   490: ifnonnull -> 548
/*     */     //   493: ifeq -> 544
/*     */     //   496: goto -> 510
/*     */     //   499: ldc2_w -6111546066211168143
/*     */     //   502: lload #4
/*     */     //   504: <illegal opcode> w : (Laacinternal/v;JJ)Laacinternal/v;
/*     */     //   509: athrow
/*     */     //   510: aload #7
/*     */     //   512: sipush #20231
/*     */     //   515: ldc2_w 6037930815677003217
/*     */     //   518: lload #4
/*     */     //   520: lxor
/*     */     //   521: <illegal opcode> a : (IJ)Ljava/lang/String;
/*     */     //   526: invokevirtual append : (Ljava/lang/String;)Ljava/lang/StringBuilder;
/*     */     //   529: pop
/*     */     //   530: goto -> 544
/*     */     //   533: ldc2_w -6111546066211168143
/*     */     //   536: lload #4
/*     */     //   538: <illegal opcode> w : (Laacinternal/v;JJ)Laacinternal/v;
/*     */     //   543: athrow
/*     */     //   544: aload_0
/*     */     //   545: getfield e : I
/*     */     //   548: iconst_m1
/*     */     //   549: iload_2
/*     */     //   550: ifle -> 661
/*     */     //   553: aload #6
/*     */     //   555: ifnonnull -> 661
/*     */     //   558: if_icmpeq -> 633
/*     */     //   561: goto -> 575
/*     */     //   564: ldc2_w -6111546066211168143
/*     */     //   567: lload #4
/*     */     //   569: <illegal opcode> w : (Laacinternal/v;JJ)Laacinternal/v;
/*     */     //   574: athrow
/*     */     //   575: aload #7
/*     */     //   577: sipush #16742
/*     */     //   580: ldc2_w 8293155229632363436
/*     */     //   583: lload #4
/*     */     //   585: lxor
/*     */     //   586: <illegal opcode> a : (IJ)Ljava/lang/String;
/*     */     //   591: invokevirtual append : (Ljava/lang/String;)Ljava/lang/StringBuilder;
/*     */     //   594: aload_0
/*     */     //   595: getfield e : I
/*     */     //   598: invokevirtual append : (I)Ljava/lang/StringBuilder;
/*     */     //   601: sipush #7494
/*     */     //   604: ldc2_w 8762155303089481608
/*     */     //   607: lload #4
/*     */     //   609: lxor
/*     */     //   610: <illegal opcode> a : (IJ)Ljava/lang/String;
/*     */     //   615: invokevirtual append : (Ljava/lang/String;)Ljava/lang/StringBuilder;
/*     */     //   618: pop
/*     */     //   619: goto -> 633
/*     */     //   622: ldc2_w -6111546066211168143
/*     */     //   625: lload #4
/*     */     //   627: <illegal opcode> w : (Laacinternal/v;JJ)Laacinternal/v;
/*     */     //   632: athrow
/*     */     //   633: aload_0
/*     */     //   634: getfield f : I
/*     */     //   637: aload #6
/*     */     //   639: iload_3
/*     */     //   640: ifle -> 728
/*     */     //   643: ifnonnull -> 726
/*     */     //   646: iconst_m1
/*     */     //   647: goto -> 661
/*     */     //   650: ldc2_w -6111546066211168143
/*     */     //   653: lload #4
/*     */     //   655: <illegal opcode> w : (Laacinternal/v;JJ)Laacinternal/v;
/*     */     //   660: athrow
/*     */     //   661: if_icmpeq -> 722
/*     */     //   664: aload #7
/*     */     //   666: sipush #16323
/*     */     //   669: ldc2_w 2675447711119508738
/*     */     //   672: lload #4
/*     */     //   674: lxor
/*     */     //   675: <illegal opcode> a : (IJ)Ljava/lang/String;
/*     */     //   680: invokevirtual append : (Ljava/lang/String;)Ljava/lang/StringBuilder;
/*     */     //   683: aload_0
/*     */     //   684: getfield f : I
/*     */     //   687: invokevirtual append : (I)Ljava/lang/StringBuilder;
/*     */     //   690: sipush #7494
/*     */     //   693: ldc2_w 8762155303089481608
/*     */     //   696: lload #4
/*     */     //   698: lxor
/*     */     //   699: <illegal opcode> a : (IJ)Ljava/lang/String;
/*     */     //   704: invokevirtual append : (Ljava/lang/String;)Ljava/lang/StringBuilder;
/*     */     //   707: pop
/*     */     //   708: goto -> 722
/*     */     //   711: ldc2_w -6111546066211168143
/*     */     //   714: lload #4
/*     */     //   716: <illegal opcode> w : (Laacinternal/v;JJ)Laacinternal/v;
/*     */     //   721: athrow
/*     */     //   722: aload_0
/*     */     //   723: getfield h : Z
/*     */     //   726: aload #6
/*     */     //   728: iload_2
/*     */     //   729: ifle -> 792
/*     */     //   732: ifnonnull -> 790
/*     */     //   735: ifeq -> 786
/*     */     //   738: goto -> 752
/*     */     //   741: ldc2_w -6111546066211168143
/*     */     //   744: lload #4
/*     */     //   746: <illegal opcode> w : (Laacinternal/v;JJ)Laacinternal/v;
/*     */     //   751: athrow
/*     */     //   752: aload #7
/*     */     //   754: sipush #579
/*     */     //   757: ldc2_w 5077562634230544539
/*     */     //   760: lload #4
/*     */     //   762: lxor
/*     */     //   763: <illegal opcode> a : (IJ)Ljava/lang/String;
/*     */     //   768: invokevirtual append : (Ljava/lang/String;)Ljava/lang/StringBuilder;
/*     */     //   771: pop
/*     */     //   772: goto -> 786
/*     */     //   775: ldc2_w -6111546066211168143
/*     */     //   778: lload #4
/*     */     //   780: <illegal opcode> w : (Laacinternal/v;JJ)Laacinternal/v;
/*     */     //   785: athrow
/*     */     //   786: aload_0
/*     */     //   787: getfield n : Z
/*     */     //   790: aload #6
/*     */     //   792: iload_1
/*     */     //   793: iflt -> 860
/*     */     //   796: ifnonnull -> 854
/*     */     //   799: ifeq -> 850
/*     */     //   802: goto -> 816
/*     */     //   805: ldc2_w -6111546066211168143
/*     */     //   808: lload #4
/*     */     //   810: <illegal opcode> w : (Laacinternal/v;JJ)Laacinternal/v;
/*     */     //   815: athrow
/*     */     //   816: aload #7
/*     */     //   818: sipush #18336
/*     */     //   821: ldc2_w 2904122499419831660
/*     */     //   824: lload #4
/*     */     //   826: lxor
/*     */     //   827: <illegal opcode> a : (IJ)Ljava/lang/String;
/*     */     //   832: invokevirtual append : (Ljava/lang/String;)Ljava/lang/StringBuilder;
/*     */     //   835: pop
/*     */     //   836: goto -> 850
/*     */     //   839: ldc2_w -6111546066211168143
/*     */     //   842: lload #4
/*     */     //   844: <illegal opcode> w : (Laacinternal/v;JJ)Laacinternal/v;
/*     */     //   849: athrow
/*     */     //   850: aload_0
/*     */     //   851: getfield k : Z
/*     */     //   854: iload_3
/*     */     //   855: iflt -> 938
/*     */     //   858: aload #6
/*     */     //   860: ifnonnull -> 938
/*     */     //   863: ifeq -> 914
/*     */     //   866: goto -> 880
/*     */     //   869: ldc2_w -6111546066211168143
/*     */     //   872: lload #4
/*     */     //   874: <illegal opcode> w : (Laacinternal/v;JJ)Laacinternal/v;
/*     */     //   879: athrow
/*     */     //   880: aload #7
/*     */     //   882: sipush #7473
/*     */     //   885: ldc2_w 6814254230853265402
/*     */     //   888: lload #4
/*     */     //   890: lxor
/*     */     //   891: <illegal opcode> a : (IJ)Ljava/lang/String;
/*     */     //   896: invokevirtual append : (Ljava/lang/String;)Ljava/lang/StringBuilder;
/*     */     //   899: pop
/*     */     //   900: goto -> 914
/*     */     //   903: ldc2_w -6111546066211168143
/*     */     //   906: lload #4
/*     */     //   908: <illegal opcode> w : (Laacinternal/v;JJ)Laacinternal/v;
/*     */     //   913: athrow
/*     */     //   914: aload #7
/*     */     //   916: aload #6
/*     */     //   918: ifnonnull -> 976
/*     */     //   921: invokevirtual length : ()I
/*     */     //   924: goto -> 938
/*     */     //   927: ldc2_w -6111546066211168143
/*     */     //   930: lload #4
/*     */     //   932: <illegal opcode> w : (Laacinternal/v;JJ)Laacinternal/v;
/*     */     //   937: athrow
/*     */     //   938: ifne -> 956
/*     */     //   941: ldc_w ''
/*     */     //   944: areturn
/*     */     //   945: ldc2_w -6111546066211168143
/*     */     //   948: lload #4
/*     */     //   950: <illegal opcode> w : (Laacinternal/v;JJ)Laacinternal/v;
/*     */     //   955: athrow
/*     */     //   956: aload #7
/*     */     //   958: aload #7
/*     */     //   960: invokevirtual length : ()I
/*     */     //   963: iconst_2
/*     */     //   964: isub
/*     */     //   965: aload #7
/*     */     //   967: invokevirtual length : ()I
/*     */     //   970: invokevirtual delete : (II)Ljava/lang/StringBuilder;
/*     */     //   973: pop
/*     */     //   974: aload #7
/*     */     //   976: invokevirtual toString : ()Ljava/lang/String;
/*     */     //   979: areturn
/*     */     // Line number table:
/*     */     //   Java source line number -> byte code offset
/*     */     //   #99	-> 39
/*     */     //   #82	-> 50
/*     */     //   #106	-> 110
/*     */     //   #119	-> 174
/*     */     //   #91	-> 263
/*     */     //   #7	-> 352
/*     */     //   #39	-> 416
/*     */     //   #62	-> 480
/*     */     //   #97	-> 544
/*     */     //   #115	-> 633
/*     */     //   #72	-> 722
/*     */     //   #29	-> 786
/*     */     //   #100	-> 850
/*     */     //   #65	-> 914
/*     */     //   #128	-> 956
/*     */     //   #76	-> 974
/*     */     // Exception table:
/*     */     //   from	to	target	type
/*     */     //   50	62	65	aacinternal/v
/*     */     //   59	96	99	aacinternal/v
/*     */     //   114	126	129	aacinternal/v
/*     */     //   123	160	163	aacinternal/v
/*     */     //   178	191	194	aacinternal/v
/*     */     //   188	249	252	aacinternal/v
/*     */     //   263	277	280	aacinternal/v
/*     */     //   291	338	341	aacinternal/v
/*     */     //   356	368	371	aacinternal/v
/*     */     //   365	402	405	aacinternal/v
/*     */     //   420	432	435	aacinternal/v
/*     */     //   429	466	469	aacinternal/v
/*     */     //   484	496	499	aacinternal/v
/*     */     //   493	530	533	aacinternal/v
/*     */     //   548	561	564	aacinternal/v
/*     */     //   558	619	622	aacinternal/v
/*     */     //   633	647	650	aacinternal/v
/*     */     //   661	708	711	aacinternal/v
/*     */     //   726	738	741	aacinternal/v
/*     */     //   735	772	775	aacinternal/v
/*     */     //   790	802	805	aacinternal/v
/*     */     //   799	836	839	aacinternal/v
/*     */     //   854	866	869	aacinternal/v
/*     */     //   863	900	903	aacinternal/v
/*     */     //   914	924	927	aacinternal/v
/*     */     //   938	945	945	aacinternal/v
/*     */   }
/*     */   
/*     */   public int b() {
/*     */     return this.g;
/*     */   }
/*     */   
/*     */   public boolean c() {
/*     */     return this.a;
/*     */   }
/*     */   
/*     */   public boolean b() {
/*     */     return this.k;
/*     */   }
/*     */   
/*     */   private b0(boolean paramBoolean1, boolean paramBoolean2, int paramInt1, int paramInt2, boolean paramBoolean3, boolean paramBoolean4, boolean paramBoolean5, int paramInt3, int paramInt4, boolean paramBoolean6, boolean paramBoolean7, boolean paramBoolean8, @Nullable String paramString) {
/*     */     this.a = paramBoolean1;
/*     */     this.m = paramBoolean2;
/*     */     this.d = paramInt1;
/*     */     this.g = paramInt2;
/*     */     this.o = paramBoolean3;
/*     */     this.c = paramBoolean4;
/*     */     this.i = paramBoolean5;
/*     */     this.e = paramInt3;
/*     */     this.f = paramInt4;
/*     */     this.h = paramBoolean6;
/*     */     this.n = paramBoolean7;
/*     */     this.k = paramBoolean8;
/*     */     this.j = paramString;
/*     */   }
/*     */   
/*     */   public boolean e() {
/*     */     return this.c;
/*     */   }
/*     */   
/*     */   public static b0 a(J paramJ, long paramLong) {
/*     */     // Byte code:
/*     */     //   0: getstatic me/konsolas/aac/b0.p : J
/*     */     //   3: lload_1
/*     */     //   4: lxor
/*     */     //   5: lstore_1
/*     */     //   6: lload_1
/*     */     //   7: dup2
/*     */     //   8: ldc2_w 47652667366905
/*     */     //   11: lxor
/*     */     //   12: lstore_3
/*     */     //   13: dup2
/*     */     //   14: ldc2_w 66716607975465
/*     */     //   17: lxor
/*     */     //   18: lstore #5
/*     */     //   20: dup2
/*     */     //   21: ldc2_w 97017229870584
/*     */     //   24: lxor
/*     */     //   25: dup2
/*     */     //   26: bipush #48
/*     */     //   28: lushr
/*     */     //   29: l2i
/*     */     //   30: istore #7
/*     */     //   32: dup2
/*     */     //   33: bipush #16
/*     */     //   35: lshl
/*     */     //   36: bipush #48
/*     */     //   38: lushr
/*     */     //   39: l2i
/*     */     //   40: istore #8
/*     */     //   42: dup2
/*     */     //   43: bipush #32
/*     */     //   45: lshl
/*     */     //   46: bipush #32
/*     */     //   48: lushr
/*     */     //   49: l2i
/*     */     //   50: istore #9
/*     */     //   52: pop2
/*     */     //   53: pop2
/*     */     //   54: iconst_0
/*     */     //   55: istore #11
/*     */     //   57: iconst_0
/*     */     //   58: istore #12
/*     */     //   60: ldc2_w 7928294036098543300
/*     */     //   63: lload_1
/*     */     //   64: <illegal opcode> w : (JJ)[Lme/konsolas/aac/aN;
/*     */     //   69: iconst_m1
/*     */     //   70: istore #13
/*     */     //   72: iconst_m1
/*     */     //   73: istore #14
/*     */     //   75: astore #10
/*     */     //   77: iconst_0
/*     */     //   78: istore #15
/*     */     //   80: iconst_0
/*     */     //   81: istore #16
/*     */     //   83: iconst_0
/*     */     //   84: istore #17
/*     */     //   86: iconst_m1
/*     */     //   87: istore #18
/*     */     //   89: iconst_m1
/*     */     //   90: istore #19
/*     */     //   92: iconst_0
/*     */     //   93: istore #20
/*     */     //   95: iconst_0
/*     */     //   96: istore #21
/*     */     //   98: iconst_0
/*     */     //   99: istore #22
/*     */     //   101: iconst_1
/*     */     //   102: istore #23
/*     */     //   104: aconst_null
/*     */     //   105: astore #24
/*     */     //   107: iconst_0
/*     */     //   108: istore #25
/*     */     //   110: aload_0
/*     */     //   111: invokevirtual a : ()I
/*     */     //   114: istore #26
/*     */     //   116: iload #25
/*     */     //   118: iload #26
/*     */     //   120: if_icmpge -> 1654
/*     */     //   123: aload_0
/*     */     //   124: iload #25
/*     */     //   126: invokevirtual a : (I)Ljava/lang/String;
/*     */     //   129: astore #27
/*     */     //   131: aload_0
/*     */     //   132: iload #25
/*     */     //   134: invokevirtual b : (I)Ljava/lang/String;
/*     */     //   137: astore #28
/*     */     //   139: aload #27
/*     */     //   141: sipush #1109
/*     */     //   144: ldc2_w 2388785526273440656
/*     */     //   147: lload_1
/*     */     //   148: lxor
/*     */     //   149: <illegal opcode> a : (IJ)Ljava/lang/String;
/*     */     //   154: invokevirtual equalsIgnoreCase : (Ljava/lang/String;)Z
/*     */     //   157: aload #10
/*     */     //   159: lload_1
/*     */     //   160: lconst_0
/*     */     //   161: lcmp
/*     */     //   162: iflt -> 170
/*     */     //   165: ifnonnull -> 1662
/*     */     //   168: aload #10
/*     */     //   170: lload_1
/*     */     //   171: lconst_0
/*     */     //   172: lcmp
/*     */     //   173: iflt -> 325
/*     */     //   176: ifnonnull -> 323
/*     */     //   179: goto -> 192
/*     */     //   182: ldc2_w 7941665511422944616
/*     */     //   185: lload_1
/*     */     //   186: <illegal opcode> w : (Laacinternal/v;JJ)Laacinternal/v;
/*     */     //   191: athrow
/*     */     //   192: lload_1
/*     */     //   193: lconst_0
/*     */     //   194: lcmp
/*     */     //   195: iflt -> 310
/*     */     //   198: ifeq -> 292
/*     */     //   201: goto -> 214
/*     */     //   204: ldc2_w 7941665511422944616
/*     */     //   207: lload_1
/*     */     //   208: <illegal opcode> w : (Laacinternal/v;JJ)Laacinternal/v;
/*     */     //   213: athrow
/*     */     //   214: lload_1
/*     */     //   215: lconst_0
/*     */     //   216: lcmp
/*     */     //   217: ifle -> 287
/*     */     //   220: aload #24
/*     */     //   222: aload #10
/*     */     //   224: ifnonnull -> 285
/*     */     //   227: goto -> 240
/*     */     //   230: ldc2_w 7941665511422944616
/*     */     //   233: lload_1
/*     */     //   234: <illegal opcode> w : (Laacinternal/v;JJ)Laacinternal/v;
/*     */     //   239: athrow
/*     */     //   240: ifnull -> 270
/*     */     //   243: goto -> 256
/*     */     //   246: ldc2_w 7941665511422944616
/*     */     //   249: lload_1
/*     */     //   250: <illegal opcode> w : (Laacinternal/v;JJ)Laacinternal/v;
/*     */     //   255: athrow
/*     */     //   256: iconst_0
/*     */     //   257: lload_1
/*     */     //   258: lconst_0
/*     */     //   259: lcmp
/*     */     //   260: ifle -> 348
/*     */     //   263: istore #23
/*     */     //   265: aload #10
/*     */     //   267: ifnull -> 347
/*     */     //   270: aload #28
/*     */     //   272: goto -> 285
/*     */     //   275: ldc2_w 7941665511422944616
/*     */     //   278: lload_1
/*     */     //   279: <illegal opcode> w : (Laacinternal/v;JJ)Laacinternal/v;
/*     */     //   284: athrow
/*     */     //   285: astore #24
/*     */     //   287: aload #10
/*     */     //   289: ifnull -> 347
/*     */     //   292: aload #27
/*     */     //   294: sipush #16726
/*     */     //   297: ldc2_w 3286675499056479879
/*     */     //   300: lload_1
/*     */     //   301: lxor
/*     */     //   302: <illegal opcode> a : (IJ)Ljava/lang/String;
/*     */     //   307: invokevirtual equalsIgnoreCase : (Ljava/lang/String;)Z
/*     */     //   310: goto -> 323
/*     */     //   313: ldc2_w 7941665511422944616
/*     */     //   316: lload_1
/*     */     //   317: <illegal opcode> w : (Laacinternal/v;JJ)Laacinternal/v;
/*     */     //   322: athrow
/*     */     //   323: aload #10
/*     */     //   325: ifnonnull -> 345
/*     */     //   328: ifeq -> 1640
/*     */     //   331: goto -> 344
/*     */     //   334: ldc2_w 7941665511422944616
/*     */     //   337: lload_1
/*     */     //   338: <illegal opcode> w : (Laacinternal/v;JJ)Laacinternal/v;
/*     */     //   343: athrow
/*     */     //   344: iconst_0
/*     */     //   345: istore #23
/*     */     //   347: iconst_0
/*     */     //   348: istore #29
/*     */     //   350: iload #29
/*     */     //   352: aload #28
/*     */     //   354: invokevirtual length : ()I
/*     */     //   357: if_icmpge -> 1640
/*     */     //   360: iload #29
/*     */     //   362: istore #30
/*     */     //   364: aload #28
/*     */     //   366: iload #29
/*     */     //   368: lload_3
/*     */     //   369: sipush #27772
/*     */     //   372: ldc2_w 7009718852708242341
/*     */     //   375: lload_1
/*     */     //   376: lxor
/*     */     //   377: <illegal opcode> a : (IJ)Ljava/lang/String;
/*     */     //   382: invokestatic a : (Ljava/lang/String;IJLjava/lang/String;)I
/*     */     //   385: istore #29
/*     */     //   387: aload #28
/*     */     //   389: iload #30
/*     */     //   391: iload #29
/*     */     //   393: invokevirtual substring : (II)Ljava/lang/String;
/*     */     //   396: invokevirtual trim : ()Ljava/lang/String;
/*     */     //   399: astore #31
/*     */     //   401: aload #10
/*     */     //   403: ifnonnull -> 547
/*     */     //   406: iload #29
/*     */     //   408: aload #28
/*     */     //   410: invokevirtual length : ()I
/*     */     //   413: aload #10
/*     */     //   415: ifnonnull -> 120
/*     */     //   418: lload_1
/*     */     //   419: lconst_0
/*     */     //   420: lcmp
/*     */     //   421: ifle -> 357
/*     */     //   424: goto -> 437
/*     */     //   427: ldc2_w 7941665511422944616
/*     */     //   430: lload_1
/*     */     //   431: <illegal opcode> w : (Laacinternal/v;JJ)Laacinternal/v;
/*     */     //   436: athrow
/*     */     //   437: lload_1
/*     */     //   438: lconst_0
/*     */     //   439: lcmp
/*     */     //   440: iflt -> 455
/*     */     //   443: if_icmpeq -> 544
/*     */     //   446: aload #28
/*     */     //   448: iload #29
/*     */     //   450: invokevirtual charAt : (I)C
/*     */     //   453: bipush #44
/*     */     //   455: aload #10
/*     */     //   457: lload_1
/*     */     //   458: lconst_0
/*     */     //   459: lcmp
/*     */     //   460: ifle -> 525
/*     */     //   463: ifnonnull -> 517
/*     */     //   466: goto -> 479
/*     */     //   469: ldc2_w 7941665511422944616
/*     */     //   472: lload_1
/*     */     //   473: <illegal opcode> w : (Laacinternal/v;JJ)Laacinternal/v;
/*     */     //   478: athrow
/*     */     //   479: if_icmpeq -> 544
/*     */     //   482: goto -> 495
/*     */     //   485: ldc2_w 7941665511422944616
/*     */     //   488: lload_1
/*     */     //   489: <illegal opcode> w : (Laacinternal/v;JJ)Laacinternal/v;
/*     */     //   494: athrow
/*     */     //   495: aload #28
/*     */     //   497: iload #29
/*     */     //   499: invokevirtual charAt : (I)C
/*     */     //   502: bipush #59
/*     */     //   504: goto -> 517
/*     */     //   507: ldc2_w 7941665511422944616
/*     */     //   510: lload_1
/*     */     //   511: <illegal opcode> w : (Laacinternal/v;JJ)Laacinternal/v;
/*     */     //   516: athrow
/*     */     //   517: lload_1
/*     */     //   518: lconst_0
/*     */     //   519: lcmp
/*     */     //   520: ifle -> 606
/*     */     //   523: aload #10
/*     */     //   525: ifnonnull -> 606
/*     */     //   528: if_icmpne -> 561
/*     */     //   531: goto -> 544
/*     */     //   534: ldc2_w 7941665511422944616
/*     */     //   537: lload_1
/*     */     //   538: <illegal opcode> w : (Laacinternal/v;JJ)Laacinternal/v;
/*     */     //   543: athrow
/*     */     //   544: iinc #29, 1
/*     */     //   547: aconst_null
/*     */     //   548: astore #32
/*     */     //   550: lload_1
/*     */     //   551: lconst_0
/*     */     //   552: lcmp
/*     */     //   553: ifle -> 581
/*     */     //   556: aload #10
/*     */     //   558: ifnull -> 772
/*     */     //   561: iinc #29, 1
/*     */     //   564: aload #28
/*     */     //   566: iload #29
/*     */     //   568: iload #7
/*     */     //   570: i2c
/*     */     //   571: iload #8
/*     */     //   573: i2c
/*     */     //   574: iload #9
/*     */     //   576: invokestatic b : (Ljava/lang/String;ICCI)I
/*     */     //   579: istore #29
/*     */     //   581: iload #29
/*     */     //   583: aload #10
/*     */     //   585: ifnonnull -> 733
/*     */     //   588: aload #28
/*     */     //   590: invokevirtual length : ()I
/*     */     //   593: goto -> 606
/*     */     //   596: ldc2_w 7941665511422944616
/*     */     //   599: lload_1
/*     */     //   600: <illegal opcode> w : (Laacinternal/v;JJ)Laacinternal/v;
/*     */     //   605: athrow
/*     */     //   606: if_icmpge -> 718
/*     */     //   609: aload #28
/*     */     //   611: iload #29
/*     */     //   613: invokevirtual charAt : (I)C
/*     */     //   616: aload #10
/*     */     //   618: ifnonnull -> 733
/*     */     //   621: goto -> 634
/*     */     //   624: ldc2_w 7941665511422944616
/*     */     //   627: lload_1
/*     */     //   628: <illegal opcode> w : (Laacinternal/v;JJ)Laacinternal/v;
/*     */     //   633: athrow
/*     */     //   634: bipush #34
/*     */     //   636: if_icmpne -> 718
/*     */     //   639: goto -> 652
/*     */     //   642: ldc2_w 7941665511422944616
/*     */     //   645: lload_1
/*     */     //   646: <illegal opcode> w : (Laacinternal/v;JJ)Laacinternal/v;
/*     */     //   651: athrow
/*     */     //   652: iinc #29, 1
/*     */     //   655: iload #29
/*     */     //   657: istore #33
/*     */     //   659: aload #28
/*     */     //   661: iload #29
/*     */     //   663: lload_3
/*     */     //   664: ldc '㎼沢'
/*     */     //   666: invokevirtual toCharArray : ()[C
/*     */     //   669: dup
/*     */     //   670: dup
/*     */     //   671: iconst_0
/*     */     //   672: dup_x1
/*     */     //   673: caload
/*     */     //   674: sipush #13294
/*     */     //   677: ixor
/*     */     //   678: i2c
/*     */     //   679: castore
/*     */     //   680: sipush #11251
/*     */     //   683: iconst_0
/*     */     //   684: iconst_1
/*     */     //   685: invokestatic A : (Ljava/lang/Object;SZI)Ljava/lang/String;
/*     */     //   688: invokestatic a : (Ljava/lang/String;IJLjava/lang/String;)I
/*     */     //   691: istore #29
/*     */     //   693: aload #28
/*     */     //   695: iload #33
/*     */     //   697: iload #29
/*     */     //   699: invokevirtual substring : (II)Ljava/lang/String;
/*     */     //   702: astore #32
/*     */     //   704: iinc #29, 1
/*     */     //   707: lload_1
/*     */     //   708: lconst_0
/*     */     //   709: lcmp
/*     */     //   710: ifle -> 772
/*     */     //   713: aload #10
/*     */     //   715: ifnull -> 772
/*     */     //   718: iload #29
/*     */     //   720: goto -> 733
/*     */     //   723: ldc2_w 7941665511422944616
/*     */     //   726: lload_1
/*     */     //   727: <illegal opcode> w : (Laacinternal/v;JJ)Laacinternal/v;
/*     */     //   732: athrow
/*     */     //   733: istore #33
/*     */     //   735: aload #28
/*     */     //   737: iload #29
/*     */     //   739: lload_3
/*     */     //   740: sipush #7688
/*     */     //   743: ldc2_w 1894801148134842817
/*     */     //   746: lload_1
/*     */     //   747: lxor
/*     */     //   748: <illegal opcode> a : (IJ)Ljava/lang/String;
/*     */     //   753: invokestatic a : (Ljava/lang/String;IJLjava/lang/String;)I
/*     */     //   756: istore #29
/*     */     //   758: aload #28
/*     */     //   760: iload #33
/*     */     //   762: iload #29
/*     */     //   764: invokevirtual substring : (II)Ljava/lang/String;
/*     */     //   767: invokevirtual trim : ()Ljava/lang/String;
/*     */     //   770: astore #32
/*     */     //   772: sipush #19670
/*     */     //   775: ldc2_w 5387259201917727517
/*     */     //   778: lload_1
/*     */     //   779: lxor
/*     */     //   780: <illegal opcode> a : (IJ)Ljava/lang/String;
/*     */     //   785: aload #31
/*     */     //   787: invokevirtual equalsIgnoreCase : (Ljava/lang/String;)Z
/*     */     //   790: aload #10
/*     */     //   792: lload_1
/*     */     //   793: lconst_0
/*     */     //   794: lcmp
/*     */     //   795: iflt -> 864
/*     */     //   798: ifnonnull -> 862
/*     */     //   801: ifeq -> 831
/*     */     //   804: goto -> 817
/*     */     //   807: ldc2_w 7941665511422944616
/*     */     //   810: lload_1
/*     */     //   811: <illegal opcode> w : (Laacinternal/v;JJ)Laacinternal/v;
/*     */     //   816: athrow
/*     */     //   817: iconst_1
/*     */     //   818: istore #11
/*     */     //   820: aload #10
/*     */     //   822: lload_1
/*     */     //   823: lconst_0
/*     */     //   824: lcmp
/*     */     //   825: iflt -> 1637
/*     */     //   828: ifnull -> 1635
/*     */     //   831: sipush #5481
/*     */     //   834: ldc2_w 841342816305310377
/*     */     //   837: lload_1
/*     */     //   838: lxor
/*     */     //   839: <illegal opcode> a : (IJ)Ljava/lang/String;
/*     */     //   844: aload #31
/*     */     //   846: invokevirtual equalsIgnoreCase : (Ljava/lang/String;)Z
/*     */     //   849: goto -> 862
/*     */     //   852: ldc2_w 7941665511422944616
/*     */     //   855: lload_1
/*     */     //   856: <illegal opcode> w : (Laacinternal/v;JJ)Laacinternal/v;
/*     */     //   861: athrow
/*     */     //   862: aload #10
/*     */     //   864: lload_1
/*     */     //   865: lconst_0
/*     */     //   866: lcmp
/*     */     //   867: ifle -> 936
/*     */     //   870: ifnonnull -> 934
/*     */     //   873: ifeq -> 903
/*     */     //   876: goto -> 889
/*     */     //   879: ldc2_w 7941665511422944616
/*     */     //   882: lload_1
/*     */     //   883: <illegal opcode> w : (Laacinternal/v;JJ)Laacinternal/v;
/*     */     //   888: athrow
/*     */     //   889: iconst_1
/*     */     //   890: istore #12
/*     */     //   892: aload #10
/*     */     //   894: lload_1
/*     */     //   895: lconst_0
/*     */     //   896: lcmp
/*     */     //   897: ifle -> 1637
/*     */     //   900: ifnull -> 1635
/*     */     //   903: sipush #20367
/*     */     //   906: ldc2_w 4881407649405972546
/*     */     //   909: lload_1
/*     */     //   910: lxor
/*     */     //   911: <illegal opcode> a : (IJ)Ljava/lang/String;
/*     */     //   916: aload #31
/*     */     //   918: invokevirtual equalsIgnoreCase : (Ljava/lang/String;)Z
/*     */     //   921: goto -> 934
/*     */     //   924: ldc2_w 7941665511422944616
/*     */     //   927: lload_1
/*     */     //   928: <illegal opcode> w : (Laacinternal/v;JJ)Laacinternal/v;
/*     */     //   933: athrow
/*     */     //   934: aload #10
/*     */     //   936: lload_1
/*     */     //   937: lconst_0
/*     */     //   938: lcmp
/*     */     //   939: iflt -> 1015
/*     */     //   942: ifnonnull -> 1013
/*     */     //   945: ifeq -> 982
/*     */     //   948: goto -> 961
/*     */     //   951: ldc2_w 7941665511422944616
/*     */     //   954: lload_1
/*     */     //   955: <illegal opcode> w : (Laacinternal/v;JJ)Laacinternal/v;
/*     */     //   960: athrow
/*     */     //   961: aload #32
/*     */     //   963: lload #5
/*     */     //   965: iconst_m1
/*     */     //   966: invokestatic a : (Ljava/lang/String;JI)I
/*     */     //   969: istore #13
/*     */     //   971: aload #10
/*     */     //   973: lload_1
/*     */     //   974: lconst_0
/*     */     //   975: lcmp
/*     */     //   976: ifle -> 1637
/*     */     //   979: ifnull -> 1635
/*     */     //   982: sipush #29064
/*     */     //   985: ldc2_w 4573298495092887110
/*     */     //   988: lload_1
/*     */     //   989: lxor
/*     */     //   990: <illegal opcode> a : (IJ)Ljava/lang/String;
/*     */     //   995: aload #31
/*     */     //   997: invokevirtual equalsIgnoreCase : (Ljava/lang/String;)Z
/*     */     //   1000: goto -> 1013
/*     */     //   1003: ldc2_w 7941665511422944616
/*     */     //   1006: lload_1
/*     */     //   1007: <illegal opcode> w : (Laacinternal/v;JJ)Laacinternal/v;
/*     */     //   1012: athrow
/*     */     //   1013: aload #10
/*     */     //   1015: lload_1
/*     */     //   1016: lconst_0
/*     */     //   1017: lcmp
/*     */     //   1018: ifle -> 1094
/*     */     //   1021: ifnonnull -> 1092
/*     */     //   1024: ifeq -> 1061
/*     */     //   1027: goto -> 1040
/*     */     //   1030: ldc2_w 7941665511422944616
/*     */     //   1033: lload_1
/*     */     //   1034: <illegal opcode> w : (Laacinternal/v;JJ)Laacinternal/v;
/*     */     //   1039: athrow
/*     */     //   1040: aload #32
/*     */     //   1042: lload #5
/*     */     //   1044: iconst_m1
/*     */     //   1045: invokestatic a : (Ljava/lang/String;JI)I
/*     */     //   1048: istore #14
/*     */     //   1050: aload #10
/*     */     //   1052: lload_1
/*     */     //   1053: lconst_0
/*     */     //   1054: lcmp
/*     */     //   1055: ifle -> 1637
/*     */     //   1058: ifnull -> 1635
/*     */     //   1061: sipush #4076
/*     */     //   1064: ldc2_w 5955139203841257528
/*     */     //   1067: lload_1
/*     */     //   1068: lxor
/*     */     //   1069: <illegal opcode> a : (IJ)Ljava/lang/String;
/*     */     //   1074: aload #31
/*     */     //   1076: invokevirtual equalsIgnoreCase : (Ljava/lang/String;)Z
/*     */     //   1079: goto -> 1092
/*     */     //   1082: ldc2_w 7941665511422944616
/*     */     //   1085: lload_1
/*     */     //   1086: <illegal opcode> w : (Laacinternal/v;JJ)Laacinternal/v;
/*     */     //   1091: athrow
/*     */     //   1092: aload #10
/*     */     //   1094: lload_1
/*     */     //   1095: lconst_0
/*     */     //   1096: lcmp
/*     */     //   1097: iflt -> 1166
/*     */     //   1100: ifnonnull -> 1164
/*     */     //   1103: ifeq -> 1133
/*     */     //   1106: goto -> 1119
/*     */     //   1109: ldc2_w 7941665511422944616
/*     */     //   1112: lload_1
/*     */     //   1113: <illegal opcode> w : (Laacinternal/v;JJ)Laacinternal/v;
/*     */     //   1118: athrow
/*     */     //   1119: iconst_1
/*     */     //   1120: istore #15
/*     */     //   1122: aload #10
/*     */     //   1124: lload_1
/*     */     //   1125: lconst_0
/*     */     //   1126: lcmp
/*     */     //   1127: ifle -> 1637
/*     */     //   1130: ifnull -> 1635
/*     */     //   1133: sipush #4402
/*     */     //   1136: ldc2_w 1653654772338847480
/*     */     //   1139: lload_1
/*     */     //   1140: lxor
/*     */     //   1141: <illegal opcode> a : (IJ)Ljava/lang/String;
/*     */     //   1146: aload #31
/*     */     //   1148: invokevirtual equalsIgnoreCase : (Ljava/lang/String;)Z
/*     */     //   1151: goto -> 1164
/*     */     //   1154: ldc2_w 7941665511422944616
/*     */     //   1157: lload_1
/*     */     //   1158: <illegal opcode> w : (Laacinternal/v;JJ)Laacinternal/v;
/*     */     //   1163: athrow
/*     */     //   1164: aload #10
/*     */     //   1166: lload_1
/*     */     //   1167: lconst_0
/*     */     //   1168: lcmp
/*     */     //   1169: iflt -> 1238
/*     */     //   1172: ifnonnull -> 1236
/*     */     //   1175: ifeq -> 1205
/*     */     //   1178: goto -> 1191
/*     */     //   1181: ldc2_w 7941665511422944616
/*     */     //   1184: lload_1
/*     */     //   1185: <illegal opcode> w : (Laacinternal/v;JJ)Laacinternal/v;
/*     */     //   1190: athrow
/*     */     //   1191: iconst_1
/*     */     //   1192: istore #16
/*     */     //   1194: aload #10
/*     */     //   1196: lload_1
/*     */     //   1197: lconst_0
/*     */     //   1198: lcmp
/*     */     //   1199: iflt -> 1637
/*     */     //   1202: ifnull -> 1635
/*     */     //   1205: sipush #9186
/*     */     //   1208: ldc2_w 8280396916972903461
/*     */     //   1211: lload_1
/*     */     //   1212: lxor
/*     */     //   1213: <illegal opcode> a : (IJ)Ljava/lang/String;
/*     */     //   1218: aload #31
/*     */     //   1220: invokevirtual equalsIgnoreCase : (Ljava/lang/String;)Z
/*     */     //   1223: goto -> 1236
/*     */     //   1226: ldc2_w 7941665511422944616
/*     */     //   1229: lload_1
/*     */     //   1230: <illegal opcode> w : (Laacinternal/v;JJ)Laacinternal/v;
/*     */     //   1235: athrow
/*     */     //   1236: aload #10
/*     */     //   1238: lload_1
/*     */     //   1239: lconst_0
/*     */     //   1240: lcmp
/*     */     //   1241: ifle -> 1310
/*     */     //   1244: ifnonnull -> 1308
/*     */     //   1247: ifeq -> 1277
/*     */     //   1250: goto -> 1263
/*     */     //   1253: ldc2_w 7941665511422944616
/*     */     //   1256: lload_1
/*     */     //   1257: <illegal opcode> w : (Laacinternal/v;JJ)Laacinternal/v;
/*     */     //   1262: athrow
/*     */     //   1263: iconst_1
/*     */     //   1264: istore #17
/*     */     //   1266: aload #10
/*     */     //   1268: lload_1
/*     */     //   1269: lconst_0
/*     */     //   1270: lcmp
/*     */     //   1271: iflt -> 1637
/*     */     //   1274: ifnull -> 1635
/*     */     //   1277: sipush #25435
/*     */     //   1280: ldc2_w 4769467920324828299
/*     */     //   1283: lload_1
/*     */     //   1284: lxor
/*     */     //   1285: <illegal opcode> a : (IJ)Ljava/lang/String;
/*     */     //   1290: aload #31
/*     */     //   1292: invokevirtual equalsIgnoreCase : (Ljava/lang/String;)Z
/*     */     //   1295: goto -> 1308
/*     */     //   1298: ldc2_w 7941665511422944616
/*     */     //   1301: lload_1
/*     */     //   1302: <illegal opcode> w : (Laacinternal/v;JJ)Laacinternal/v;
/*     */     //   1307: athrow
/*     */     //   1308: aload #10
/*     */     //   1310: lload_1
/*     */     //   1311: lconst_0
/*     */     //   1312: lcmp
/*     */     //   1313: iflt -> 1390
/*     */     //   1316: ifnonnull -> 1388
/*     */     //   1319: ifeq -> 1357
/*     */     //   1322: goto -> 1335
/*     */     //   1325: ldc2_w 7941665511422944616
/*     */     //   1328: lload_1
/*     */     //   1329: <illegal opcode> w : (Laacinternal/v;JJ)Laacinternal/v;
/*     */     //   1334: athrow
/*     */     //   1335: aload #32
/*     */     //   1337: lload #5
/*     */     //   1339: ldc 2147483647
/*     */     //   1341: invokestatic a : (Ljava/lang/String;JI)I
/*     */     //   1344: istore #18
/*     */     //   1346: aload #10
/*     */     //   1348: lload_1
/*     */     //   1349: lconst_0
/*     */     //   1350: lcmp
/*     */     //   1351: ifle -> 1637
/*     */     //   1354: ifnull -> 1635
/*     */     //   1357: sipush #2910
/*     */     //   1360: ldc2_w 1820656313464878210
/*     */     //   1363: lload_1
/*     */     //   1364: lxor
/*     */     //   1365: <illegal opcode> a : (IJ)Ljava/lang/String;
/*     */     //   1370: aload #31
/*     */     //   1372: invokevirtual equalsIgnoreCase : (Ljava/lang/String;)Z
/*     */     //   1375: goto -> 1388
/*     */     //   1378: ldc2_w 7941665511422944616
/*     */     //   1381: lload_1
/*     */     //   1382: <illegal opcode> w : (Laacinternal/v;JJ)Laacinternal/v;
/*     */     //   1387: athrow
/*     */     //   1388: aload #10
/*     */     //   1390: lload_1
/*     */     //   1391: lconst_0
/*     */     //   1392: lcmp
/*     */     //   1393: iflt -> 1469
/*     */     //   1396: ifnonnull -> 1467
/*     */     //   1399: ifeq -> 1436
/*     */     //   1402: goto -> 1415
/*     */     //   1405: ldc2_w 7941665511422944616
/*     */     //   1408: lload_1
/*     */     //   1409: <illegal opcode> w : (Laacinternal/v;JJ)Laacinternal/v;
/*     */     //   1414: athrow
/*     */     //   1415: aload #32
/*     */     //   1417: lload #5
/*     */     //   1419: iconst_m1
/*     */     //   1420: invokestatic a : (Ljava/lang/String;JI)I
/*     */     //   1423: istore #19
/*     */     //   1425: aload #10
/*     */     //   1427: lload_1
/*     */     //   1428: lconst_0
/*     */     //   1429: lcmp
/*     */     //   1430: iflt -> 1637
/*     */     //   1433: ifnull -> 1635
/*     */     //   1436: sipush #15513
/*     */     //   1439: ldc2_w 3102062330961871711
/*     */     //   1442: lload_1
/*     */     //   1443: lxor
/*     */     //   1444: <illegal opcode> a : (IJ)Ljava/lang/String;
/*     */     //   1449: aload #31
/*     */     //   1451: invokevirtual equalsIgnoreCase : (Ljava/lang/String;)Z
/*     */     //   1454: goto -> 1467
/*     */     //   1457: ldc2_w 7941665511422944616
/*     */     //   1460: lload_1
/*     */     //   1461: <illegal opcode> w : (Laacinternal/v;JJ)Laacinternal/v;
/*     */     //   1466: athrow
/*     */     //   1467: aload #10
/*     */     //   1469: lload_1
/*     */     //   1470: lconst_0
/*     */     //   1471: lcmp
/*     */     //   1472: ifle -> 1541
/*     */     //   1475: ifnonnull -> 1539
/*     */     //   1478: ifeq -> 1508
/*     */     //   1481: goto -> 1494
/*     */     //   1484: ldc2_w 7941665511422944616
/*     */     //   1487: lload_1
/*     */     //   1488: <illegal opcode> w : (Laacinternal/v;JJ)Laacinternal/v;
/*     */     //   1493: athrow
/*     */     //   1494: iconst_1
/*     */     //   1495: istore #20
/*     */     //   1497: aload #10
/*     */     //   1499: lload_1
/*     */     //   1500: lconst_0
/*     */     //   1501: lcmp
/*     */     //   1502: iflt -> 1637
/*     */     //   1505: ifnull -> 1635
/*     */     //   1508: sipush #7442
/*     */     //   1511: ldc2_w 1898858589565280972
/*     */     //   1514: lload_1
/*     */     //   1515: lxor
/*     */     //   1516: <illegal opcode> a : (IJ)Ljava/lang/String;
/*     */     //   1521: aload #31
/*     */     //   1523: invokevirtual equalsIgnoreCase : (Ljava/lang/String;)Z
/*     */     //   1526: goto -> 1539
/*     */     //   1529: ldc2_w 7941665511422944616
/*     */     //   1532: lload_1
/*     */     //   1533: <illegal opcode> w : (Laacinternal/v;JJ)Laacinternal/v;
/*     */     //   1538: athrow
/*     */     //   1539: aload #10
/*     */     //   1541: lload_1
/*     */     //   1542: lconst_0
/*     */     //   1543: lcmp
/*     */     //   1544: iflt -> 1613
/*     */     //   1547: ifnonnull -> 1611
/*     */     //   1550: ifeq -> 1580
/*     */     //   1553: goto -> 1566
/*     */     //   1556: ldc2_w 7941665511422944616
/*     */     //   1559: lload_1
/*     */     //   1560: <illegal opcode> w : (Laacinternal/v;JJ)Laacinternal/v;
/*     */     //   1565: athrow
/*     */     //   1566: iconst_1
/*     */     //   1567: istore #21
/*     */     //   1569: aload #10
/*     */     //   1571: lload_1
/*     */     //   1572: lconst_0
/*     */     //   1573: lcmp
/*     */     //   1574: ifle -> 1637
/*     */     //   1577: ifnull -> 1635
/*     */     //   1580: sipush #3281
/*     */     //   1583: ldc2_w 1070269649286624011
/*     */     //   1586: lload_1
/*     */     //   1587: lxor
/*     */     //   1588: <illegal opcode> a : (IJ)Ljava/lang/String;
/*     */     //   1593: aload #31
/*     */     //   1595: invokevirtual equalsIgnoreCase : (Ljava/lang/String;)Z
/*     */     //   1598: goto -> 1611
/*     */     //   1601: ldc2_w 7941665511422944616
/*     */     //   1604: lload_1
/*     */     //   1605: <illegal opcode> w : (Laacinternal/v;JJ)Laacinternal/v;
/*     */     //   1610: athrow
/*     */     //   1611: aload #10
/*     */     //   1613: ifnonnull -> 1633
/*     */     //   1616: ifeq -> 1635
/*     */     //   1619: goto -> 1632
/*     */     //   1622: ldc2_w 7941665511422944616
/*     */     //   1625: lload_1
/*     */     //   1626: <illegal opcode> w : (Laacinternal/v;JJ)Laacinternal/v;
/*     */     //   1631: athrow
/*     */     //   1632: iconst_1
/*     */     //   1633: istore #22
/*     */     //   1635: aload #10
/*     */     //   1637: ifnull -> 350
/*     */     //   1640: iinc #25, 1
/*     */     //   1643: aload #10
/*     */     //   1645: lload_1
/*     */     //   1646: lconst_0
/*     */     //   1647: lcmp
/*     */     //   1648: iflt -> 289
/*     */     //   1651: ifnull -> 116
/*     */     //   1654: lload_1
/*     */     //   1655: lconst_0
/*     */     //   1656: lcmp
/*     */     //   1657: ifle -> 123
/*     */     //   1660: iload #23
/*     */     //   1662: ifne -> 1668
/*     */     //   1665: aconst_null
/*     */     //   1666: astore #24
/*     */     //   1668: new me/konsolas/aac/b0
/*     */     //   1671: dup
/*     */     //   1672: iload #11
/*     */     //   1674: iload #12
/*     */     //   1676: iload #13
/*     */     //   1678: iload #14
/*     */     //   1680: iload #15
/*     */     //   1682: iload #16
/*     */     //   1684: iload #17
/*     */     //   1686: iload #18
/*     */     //   1688: iload #19
/*     */     //   1690: iload #20
/*     */     //   1692: iload #21
/*     */     //   1694: iload #22
/*     */     //   1696: aload #24
/*     */     //   1698: invokespecial <init> : (ZZIIZZZIIZZZLjava/lang/String;)V
/*     */     //   1701: areturn
/*     */     // Line number table:
/*     */     //   Java source line number -> byte code offset
/*     */     //   #126	-> 54
/*     */     //   #55	-> 57
/*     */     //   #90	-> 69
/*     */     //   #73	-> 72
/*     */     //   #36	-> 77
/*     */     //   #14	-> 80
/*     */     //   #89	-> 83
/*     */     //   #94	-> 86
/*     */     //   #131	-> 89
/*     */     //   #64	-> 92
/*     */     //   #121	-> 95
/*     */     //   #33	-> 98
/*     */     //   #60	-> 101
/*     */     //   #127	-> 104
/*     */     //   #85	-> 107
/*     */     //   #69	-> 123
/*     */     //   #120	-> 131
/*     */     //   #31	-> 139
/*     */     //   #107	-> 214
/*     */     //   #57	-> 256
/*     */     //   #11	-> 270
/*     */     //   #3	-> 292
/*     */     //   #35	-> 344
/*     */     //   #80	-> 347
/*     */     //   #19	-> 350
/*     */     //   #25	-> 360
/*     */     //   #95	-> 364
/*     */     //   #134	-> 387
/*     */     //   #102	-> 401
/*     */     //   #130	-> 544
/*     */     //   #78	-> 547
/*     */     //   #47	-> 561
/*     */     //   #5	-> 564
/*     */     //   #68	-> 581
/*     */     //   #51	-> 652
/*     */     //   #108	-> 655
/*     */     //   #16	-> 659
/*     */     //   #122	-> 693
/*     */     //   #53	-> 704
/*     */     //   #34	-> 707
/*     */     //   #15	-> 718
/*     */     //   #32	-> 735
/*     */     //   #22	-> 758
/*     */     //   #103	-> 772
/*     */     //   #52	-> 817
/*     */     //   #81	-> 831
/*     */     //   #24	-> 889
/*     */     //   #10	-> 903
/*     */     //   #129	-> 961
/*     */     //   #45	-> 982
/*     */     //   #30	-> 1040
/*     */     //   #136	-> 1061
/*     */     //   #56	-> 1119
/*     */     //   #114	-> 1133
/*     */     //   #117	-> 1191
/*     */     //   #92	-> 1205
/*     */     //   #21	-> 1263
/*     */     //   #18	-> 1277
/*     */     //   #17	-> 1335
/*     */     //   #116	-> 1357
/*     */     //   #133	-> 1415
/*     */     //   #123	-> 1436
/*     */     //   #50	-> 1494
/*     */     //   #84	-> 1508
/*     */     //   #93	-> 1566
/*     */     //   #98	-> 1580
/*     */     //   #137	-> 1632
/*     */     //   #20	-> 1635
/*     */     //   #27	-> 1640
/*     */     //   #132	-> 1654
/*     */     //   #9	-> 1665
/*     */     //   #88	-> 1668
/*     */     // Exception table:
/*     */     //   from	to	target	type
/*     */     //   139	179	182	aacinternal/v
/*     */     //   168	201	204	aacinternal/v
/*     */     //   192	227	230	aacinternal/v
/*     */     //   214	243	246	aacinternal/v
/*     */     //   265	272	275	aacinternal/v
/*     */     //   287	310	313	aacinternal/v
/*     */     //   323	331	334	aacinternal/v
/*     */     //   401	418	427	aacinternal/v
/*     */     //   437	466	469	aacinternal/v
/*     */     //   446	482	485	aacinternal/v
/*     */     //   479	504	507	aacinternal/v
/*     */     //   517	531	534	aacinternal/v
/*     */     //   581	593	596	aacinternal/v
/*     */     //   606	621	624	aacinternal/v
/*     */     //   609	639	642	aacinternal/v
/*     */     //   704	720	723	aacinternal/v
/*     */     //   772	804	807	aacinternal/v
/*     */     //   820	849	852	aacinternal/v
/*     */     //   862	876	879	aacinternal/v
/*     */     //   892	921	924	aacinternal/v
/*     */     //   934	948	951	aacinternal/v
/*     */     //   971	1000	1003	aacinternal/v
/*     */     //   1013	1027	1030	aacinternal/v
/*     */     //   1050	1079	1082	aacinternal/v
/*     */     //   1092	1106	1109	aacinternal/v
/*     */     //   1122	1151	1154	aacinternal/v
/*     */     //   1164	1178	1181	aacinternal/v
/*     */     //   1194	1223	1226	aacinternal/v
/*     */     //   1236	1250	1253	aacinternal/v
/*     */     //   1266	1295	1298	aacinternal/v
/*     */     //   1308	1322	1325	aacinternal/v
/*     */     //   1346	1375	1378	aacinternal/v
/*     */     //   1388	1402	1405	aacinternal/v
/*     */     //   1425	1454	1457	aacinternal/v
/*     */     //   1467	1481	1484	aacinternal/v
/*     */     //   1497	1526	1529	aacinternal/v
/*     */     //   1539	1553	1556	aacinternal/v
/*     */     //   1569	1598	1601	aacinternal/v
/*     */     //   1611	1619	1622	aacinternal/v
/*     */   }
/*     */   
/*     */   private static v a(v paramv) {
/*     */     return paramv;
/*     */   }
/*     */   
/*     */   private static String a(byte[] paramArrayOfbyte) {
/*     */     byte b1 = 0;
/*     */     int i;
/*     */     char[] arrayOfChar = new char[i = paramArrayOfbyte.length];
/*     */     for (byte b2 = 0; b2 < i; b2++) {
/*     */       int j;
/*     */       if ((j = 0xFF & paramArrayOfbyte[b2]) < 192) {
/*     */         arrayOfChar[b1++] = (char)j;
/*     */       } else if (j < 224) {
/*     */         char c = (char)((char)(j & 0x1F) << 6);
/*     */         j = paramArrayOfbyte[++b2];
/*     */         c = (char)(c | (char)(j & 0x3F));
/*     */         arrayOfChar[b1++] = c;
/*     */       } else if (b2 < i - 2) {
/*     */         char c = (char)((char)(j & 0xF) << 12);
/*     */         j = paramArrayOfbyte[++b2];
/*     */         c = (char)(c | (char)(j & 0x3F) << 6);
/*     */         j = paramArrayOfbyte[++b2];
/*     */         c = (char)(c | (char)(j & 0x3F));
/*     */         arrayOfChar[b1++] = c;
/*     */       } 
/*     */     } 
/*     */     return new String(arrayOfChar, 0, b1);
/*     */   }
/*     */   
/*     */   private static String a(int paramInt, long paramLong) {
/*     */     int i = paramInt ^ (int)(paramLong & 0x7FFFL) ^ 0x113F;
/*     */     if (r[i] == null) {
/*     */       Object[] arrayOfObject;
/*     */       try {
/*     */         Long long_ = Long.valueOf(Thread.currentThread().getId());
/*     */         arrayOfObject = (Object[])s.get(long_);
/*     */         if (arrayOfObject == null) {
/*     */           arrayOfObject = new Object[3];
/*     */           "媥㳴吖畗圕枝圿ﱙ疀퓨♩昈꺔菄쉸巪涂䓓".toCharArray()[18] = (char)("媥㳴吖畗圕枝圿ﱙ疀퓨♩昈꺔菄쉸巪涂䓓".toCharArray()[18] ^ 0x1974);
/*     */           arrayOfObject[0] = Cipher.getInstance(a0$cc.G("媥㳴吖畗圕枝圿ﱙ疀퓨♩昈꺔菄쉸巪涂䓓".toCharArray(), (short)28388, true, (byte)0));
/*     */           "蜖펃繶⽧".toCharArray()[2] = (char)("蜖펃繶⽧".toCharArray()[2] ^ 0x723C);
/*     */           arrayOfObject[1] = SecretKeyFactory.getInstance(a0$cc.G("蜖펃繶⽧".toCharArray(), (short)29891, true, (byte)0));
/*     */           arrayOfObject[2] = new IvParameterSpec(new byte[8]);
/*     */           s.put(long_, arrayOfObject);
/*     */         } 
/*     */       } catch (Exception exception) {
/*     */         "蔎䘊芪톯鑅痠⪝⥧왡슎뾭㈃Ἥ㒏侹쭷㫭櫋倎".toCharArray()[3] = (char)("蔎䘊芪톯鑅痠⪝⥧왡슎뾭㈃Ἥ㒏侹쭷㫭櫋倎".toCharArray()[3] ^ 0x585);
/*     */         throw new RuntimeException(a0$cc.G("蔎䘊芪톯鑅痠⪝⥧왡슎뾭㈃Ἥ㒏侹쭷㫭櫋倎".toCharArray(), (short)27225, true, (byte)0), exception);
/*     */       } 
/*     */       byte[] arrayOfByte1 = new byte[8];
/*     */       arrayOfByte1[0] = (byte)(int)(paramLong >>> 56L);
/*     */       for (byte b = 1; b < 8; b++)
/*     */         arrayOfByte1[b] = (byte)(int)(paramLong << b * 8 >>> 56L); 
/*     */       DESKeySpec dESKeySpec = new DESKeySpec(arrayOfByte1);
/*     */       SecretKey secretKey = ((SecretKeyFactory)arrayOfObject[1]).generateSecret(dESKeySpec);
/*     */       ((Cipher)arrayOfObject[0]).init(2, secretKey, (IvParameterSpec)arrayOfObject[2]);
/*     */       "赨蚁魢仑粙漏⫴࿛?㶮".toCharArray()[3] = (char)("赨蚁魢仑粙漏⫴࿛?㶮".toCharArray()[3] ^ 0x48C4);
/*     */       byte[] arrayOfByte2 = q[i].getBytes(a0$cc.G("赨蚁魢仑粙漏⫴࿛?㶮".toCharArray(), (short)22944, false, (byte)2));
/*     */       r[i] = a(((Cipher)arrayOfObject[0]).doFinal(arrayOfByte2));
/*     */     } 
/*     */     return r[i];
/*     */   }
/*     */   
/*     */   private static Object a(MethodHandles.Lookup paramLookup, MutableCallSite paramMutableCallSite, String paramString, Object[] paramArrayOfObject) {
/*     */     int i = ((Integer)paramArrayOfObject[0]).intValue();
/*     */     long l = ((Long)paramArrayOfObject[1]).longValue();
/*     */     String str = a(i, l);
/*     */     MethodHandle methodHandle = MethodHandles.constant(String.class, str);
/*     */     paramMutableCallSite.setTarget(MethodHandles.dropArguments(methodHandle, 0, new Class[] { int.class, long.class }));
/*     */     return str;
/*     */   }
/*     */   
/*     */   private static CallSite a(MethodHandles.Lookup paramLookup, String paramString, MethodType paramMethodType) {
/*     */     // Byte code:
/*     */     //   0: new java/lang/invoke/MutableCallSite
/*     */     //   3: dup
/*     */     //   4: aload_2
/*     */     //   5: invokespecial <init> : (Ljava/lang/invoke/MethodType;)V
/*     */     //   8: astore_3
/*     */     //   9: aload_3
/*     */     //   10: ldc_w
/*     */     //   13: ldc_w [Ljava/lang/Object;
/*     */     //   16: aload_2
/*     */     //   17: invokevirtual parameterCount : ()I
/*     */     //   20: invokevirtual asCollector : (Ljava/lang/Class;I)Ljava/lang/invoke/MethodHandle;
/*     */     //   23: iconst_0
/*     */     //   24: iconst_3
/*     */     //   25: anewarray java/lang/Object
/*     */     //   28: dup
/*     */     //   29: iconst_0
/*     */     //   30: aload_0
/*     */     //   31: aastore
/*     */     //   32: dup
/*     */     //   33: iconst_1
/*     */     //   34: aload_3
/*     */     //   35: aastore
/*     */     //   36: dup
/*     */     //   37: iconst_2
/*     */     //   38: aload_1
/*     */     //   39: aastore
/*     */     //   40: invokestatic insertArguments : (Ljava/lang/invoke/MethodHandle;I[Ljava/lang/Object;)Ljava/lang/invoke/MethodHandle;
/*     */     //   43: aload_2
/*     */     //   44: invokestatic explicitCastArguments : (Ljava/lang/invoke/MethodHandle;Ljava/lang/invoke/MethodType;)Ljava/lang/invoke/MethodHandle;
/*     */     //   47: invokevirtual setTarget : (Ljava/lang/invoke/MethodHandle;)V
/*     */     //   50: goto -> 171
/*     */     //   53: astore #4
/*     */     //   55: new java/lang/RuntimeException
/*     */     //   58: dup
/*     */     //   59: new java/lang/StringBuilder
/*     */     //   62: dup
/*     */     //   63: invokespecial <init> : ()V
/*     */     //   66: ldc_w '삵ㄊ칼缴䕂ꖟ蓍ᰮ됎查諱嵛钸錟ꊫ덾ہ'
/*     */     //   69: invokevirtual toCharArray : ()[C
/*     */     //   72: dup
/*     */     //   73: dup
/*     */     //   74: bipush #11
/*     */     //   76: dup_x1
/*     */     //   77: caload
/*     */     //   78: sipush #19073
/*     */     //   81: ixor
/*     */     //   82: i2c
/*     */     //   83: castore
/*     */     //   84: sipush #4491
/*     */     //   87: iconst_1
/*     */     //   88: iconst_0
/*     */     //   89: invokestatic U : (Ljava/lang/Object;SZZ)Ljava/lang/String;
/*     */     //   92: invokevirtual append : (Ljava/lang/String;)Ljava/lang/StringBuilder;
/*     */     //   95: ldc_w '?薒㈨䡧'
/*     */     //   98: invokevirtual toCharArray : ()[C
/*     */     //   101: dup
/*     */     //   102: dup
/*     */     //   103: iconst_2
/*     */     //   104: dup_x1
/*     */     //   105: caload
/*     */     //   106: sipush #23871
/*     */     //   109: ixor
/*     */     //   110: i2c
/*     */     //   111: castore
/*     */     //   112: sipush #4204
/*     */     //   115: iconst_0
/*     */     //   116: iconst_1
/*     */     //   117: invokestatic U : (Ljava/lang/Object;SZZ)Ljava/lang/String;
/*     */     //   120: invokevirtual append : (Ljava/lang/String;)Ljava/lang/StringBuilder;
/*     */     //   123: aload_1
/*     */     //   124: invokevirtual append : (Ljava/lang/String;)Ljava/lang/StringBuilder;
/*     */     //   127: ldc_w 'Ẓ詵砻ࡄ'
/*     */     //   130: invokevirtual toCharArray : ()[C
/*     */     //   133: dup
/*     */     //   134: dup
/*     */     //   135: iconst_2
/*     */     //   136: dup_x1
/*     */     //   137: caload
/*     */     //   138: sipush #30188
/*     */     //   141: ixor
/*     */     //   142: i2c
/*     */     //   143: castore
/*     */     //   144: sipush #9175
/*     */     //   147: iconst_0
/*     */     //   148: iconst_1
/*     */     //   149: invokestatic U : (Ljava/lang/Object;SZZ)Ljava/lang/String;
/*     */     //   152: invokevirtual append : (Ljava/lang/String;)Ljava/lang/StringBuilder;
/*     */     //   155: aload_2
/*     */     //   156: invokevirtual toString : ()Ljava/lang/String;
/*     */     //   159: invokevirtual append : (Ljava/lang/String;)Ljava/lang/StringBuilder;
/*     */     //   162: invokevirtual toString : ()Ljava/lang/String;
/*     */     //   165: aload #4
/*     */     //   167: invokespecial <init> : (Ljava/lang/String;Ljava/lang/Throwable;)V
/*     */     //   170: athrow
/*     */     //   171: aload_3
/*     */     //   172: areturn
/*     */     // Exception table:
/*     */     //   from	to	target	type
/*     */     //   9	50	53	java/lang/Exception
/*     */   } }


/* Location:              C:\Users\BukkitBypass\Desktop\MatrixAC\AAC\AAC-spigot-5.2.0.jar!\me\konsolas\aac\b0.class
 * Java compiler version: 8 (52.0)
 * JD-Core Version:       1.1.3
 */