/*    */ package me.konsolas.aac;
/*    */ public class bh implements mJ { private final MethodHandle b; private final Object d; private final MethodHandle f; private final MethodHandle g; private final MethodHandle h; private final MethodHandle a; private final MethodHandle j; private final MethodHandle k;
/*    */   
/*  4 */   public lq a(Entity paramEntity, long paramLong) { BoundingBox boundingBox = paramEntity.getBoundingBox();
/*    */ 
/*    */ 
/*    */ 
/*    */ 
/*    */ 
/*    */ 
/*    */ 
/*    */ 
/*    */ 
/*    */ 
/*    */ 
/*    */ 
/*    */ 
/*    */ 
/*    */ 
/*    */ 
/*    */ 
/*    */ 
/*    */ 
/*    */ 
/*    */ 
/*    */ 
/*    */ 
/*    */ 
/*    */ 
/*    */ 
/*    */     
/* 32 */     return new lq(boundingBox.getMinX(), boundingBox.getMinY(), boundingBox.getMinZ(), boundingBox.getMaxX(), boundingBox.getMaxY(), boundingBox.getMaxZ()); }
/*    */   private final MethodHandle c;
/*    */   private final MethodHandle i; private final MethodHandle e; private static final long l = nc.a(-7014838445543990022L, -5376790989993171216L, MethodHandles.lookup().lookupClass()).a(25953989640178L); private static final String[] m; private static final String[] n; private static final Map o = new HashMap<>(13); public float a(long paramLong, Block paramBlock) { // Byte code:
/*    */     //   0: aload_0
/*    */     //   1: getfield h : Ljava/lang/invoke/MethodHandle;
/*    */     //   4: aload_0
/*    */     //   5: getfield g : Ljava/lang/invoke/MethodHandle;
/*    */     //   8: aload_3
/*    */     //   9: invokevirtual invoke : (Lorg/bukkit/block/Block;)Ljava/lang/Object;
/*    */     //   12: invokevirtual invoke : (Ljava/lang/Object;)F
/*    */     //   15: freturn
/*    */     //   16: astore #4
/*    */     //   18: new java/lang/RuntimeException
/*    */     //   21: dup
/*    */     //   22: sipush #20231
/*    */     //   25: ldc2_w 9150304924351207507
/*    */     //   28: lload_1
/*    */     //   29: lxor
/*    */     //   30: <illegal opcode> c : (IJ)Ljava/lang/String;
/*    */     //   35: aload #4
/*    */     //   37: invokespecial <init> : (Ljava/lang/String;Ljava/lang/Throwable;)V
/*    */     //   40: athrow
/*    */     // Line number table:
/*    */     //   Java source line number -> byte code offset
/*    */     //   #2	-> 0
/*    */     //   #24	-> 16
/*    */     //   #11	-> 18
/*    */     // Exception table:
/*    */     //   from	to	target	type
/*    */     //   0	15	16	java/lang/Throwable } public List a(Block paramBlock, char paramChar, long paramLong, Entity paramEntity) { // Byte code:
/*    */     //   0: iload_2
/*    */     //   1: i2l
/*    */     //   2: bipush #48
/*    */     //   4: lshl
/*    */     //   5: lload_3
/*    */     //   6: bipush #16
/*    */     //   8: lshl
/*    */     //   9: bipush #16
/*    */     //   11: lushr
/*    */     //   12: lor
/*    */     //   13: lstore #6
/*    */     //   15: lload #6
/*    */     //   17: dup2
/*    */     //   18: ldc2_w 109397216446913
/*    */     //   21: lxor
/*    */     //   22: lstore #8
/*    */     //   24: pop2
/*    */     //   25: ldc2_w -4127385674211381296
/*    */     //   28: lload #6
/*    */     //   30: <illegal opcode> w : (JJ)[Lme/konsolas/aac/aN;
/*    */     //   35: astore #10
/*    */     //   37: aload_0
/*    */     //   38: getfield j : Ljava/lang/invoke/MethodHandle;
/*    */     //   41: aload_1
/*    */     //   42: invokeinterface getWorld : ()Lorg/bukkit/World;
/*    */     //   47: invokevirtual invoke : (Lorg/bukkit/World;)Ljava/lang/Object;
/*    */     //   50: astore #11
/*    */     //   52: aload_0
/*    */     //   53: getfield k : Ljava/lang/invoke/MethodHandle;
/*    */     //   56: aload_1
/*    */     //   57: invokeinterface getX : ()I
/*    */     //   62: aload_1
/*    */     //   63: invokeinterface getY : ()I
/*    */     //   68: aload_1
/*    */     //   69: invokeinterface getZ : ()I
/*    */     //   74: invokevirtual invoke : (III)Ljava/lang/Object;
/*    */     //   77: astore #12
/*    */     //   79: aload_0
/*    */     //   80: getfield i : Ljava/lang/invoke/MethodHandle;
/*    */     //   83: aload_0
/*    */     //   84: getfield c : Ljava/lang/invoke/MethodHandle;
/*    */     //   87: aload #11
/*    */     //   89: aload #12
/*    */     //   91: invokevirtual invoke : (Ljava/lang/Object;Ljava/lang/Object;)Ljava/lang/Object;
/*    */     //   94: aload #11
/*    */     //   96: aload #12
/*    */     //   98: invokevirtual invoke : (Ljava/lang/Object;Ljava/lang/Object;Ljava/lang/Object;)Ljava/lang/Object;
/*    */     //   101: astore #13
/*    */     //   103: aload_0
/*    */     //   104: getfield e : Ljava/lang/invoke/MethodHandle;
/*    */     //   107: aload #13
/*    */     //   109: invokevirtual invoke : (Ljava/lang/Object;)Ljava/util/List;
/*    */     //   112: astore #14
/*    */     //   114: new java/util/ArrayList
/*    */     //   117: dup
/*    */     //   118: aload #14
/*    */     //   120: invokeinterface size : ()I
/*    */     //   125: invokespecial <init> : (I)V
/*    */     //   128: astore #15
/*    */     //   130: aload #14
/*    */     //   132: invokeinterface iterator : ()Ljava/util/Iterator;
/*    */     //   137: astore #16
/*    */     //   139: aload #16
/*    */     //   141: invokeinterface hasNext : ()Z
/*    */     //   146: ifeq -> 209
/*    */     //   149: aload #16
/*    */     //   151: invokeinterface next : ()Ljava/lang/Object;
/*    */     //   156: astore #17
/*    */     //   158: lload_3
/*    */     //   159: lconst_0
/*    */     //   160: lcmp
/*    */     //   161: ifle -> 184
/*    */     //   164: aload #15
/*    */     //   166: aload #10
/*    */     //   168: ifnull -> 211
/*    */     //   171: lload #8
/*    */     //   173: aload #17
/*    */     //   175: invokestatic a : (JLjava/lang/Object;)Lme/konsolas/aac/lq;
/*    */     //   178: invokeinterface add : (Ljava/lang/Object;)Z
/*    */     //   183: pop
/*    */     //   184: aload #10
/*    */     //   186: ifnonnull -> 139
/*    */     //   189: lload_3
/*    */     //   190: lconst_0
/*    */     //   191: lcmp
/*    */     //   192: ifle -> 158
/*    */     //   195: goto -> 209
/*    */     //   198: ldc2_w -4143234953588120024
/*    */     //   201: lload #6
/*    */     //   203: <illegal opcode> w : (Ljava/lang/Throwable;JJ)Ljava/lang/Throwable;
/*    */     //   208: athrow
/*    */     //   209: aload #15
/*    */     //   211: areturn
/*    */     //   212: astore #11
/*    */     //   214: new java/lang/RuntimeException
/*    */     //   217: dup
/*    */     //   218: sipush #266
/*    */     //   221: ldc2_w 4913376278984979399
/*    */     //   224: lload #6
/*    */     //   226: lxor
/*    */     //   227: <illegal opcode> c : (IJ)Ljava/lang/String;
/*    */     //   232: aload #11
/*    */     //   234: invokespecial <init> : (Ljava/lang/String;Ljava/lang/Throwable;)V
/*    */     //   237: athrow
/*    */     // Line number table:
/*    */     //   Java source line number -> byte code offset
/*    */     //   #9	-> 37
/*    */     //   #43	-> 52
/*    */     //   #51	-> 79
/*    */     //   #3	-> 91
/*    */     //   #7	-> 98
/*    */     //   #44	-> 103
/*    */     //   #13	-> 114
/*    */     //   #31	-> 130
/*    */     //   #40	-> 209
/*    */     //   #22	-> 212
/*    */     //   #10	-> 214
/*    */     // Exception table:
/*    */     //   from	to	target	type
/*    */     //   37	211	212	java/lang/Throwable
/*    */     //   158	189	198	java/lang/Throwable } public ItemStack a(Player paramPlayer, long paramLong) { // Byte code:
/*    */     //   0: aload_0
/*    */     //   1: getfield b : Ljava/lang/invoke/MethodHandle;
/*    */     //   4: aload_0
/*    */     //   5: getfield a : Ljava/lang/invoke/MethodHandle;
/*    */     //   8: aload_1
/*    */     //   9: invokevirtual invoke : (Lorg/bukkit/entity/Player;)Ljava/lang/Object;
/*    */     //   12: invokevirtual invoke : (Ljava/lang/Object;)Ljava/lang/Object;
/*    */     //   15: astore #4
/*    */     //   17: aload #4
/*    */     //   19: aload_0
/*    */     //   20: getfield d : Ljava/lang/Object;
/*    */     //   23: invokestatic equals : (Ljava/lang/Object;Ljava/lang/Object;)Z
/*    */     //   26: ifeq -> 43
/*    */     //   29: aconst_null
/*    */     //   30: goto -> 52
/*    */     //   33: ldc2_w 7090105979940389581
/*    */     //   36: lload_2
/*    */     //   37: <illegal opcode> w : (Ljava/lang/Throwable;JJ)Ljava/lang/Throwable;
/*    */     //   42: athrow
/*    */     //   43: aload_0
/*    */     //   44: getfield f : Ljava/lang/invoke/MethodHandle;
/*    */     //   47: aload #4
/*    */     //   49: invokevirtual invoke : (Ljava/lang/Object;)Lorg/bukkit/inventory/ItemStack;
/*    */     //   52: areturn
/*    */     //   53: astore #4
/*    */     //   55: new java/lang/RuntimeException
/*    */     //   58: dup
/*    */     //   59: sipush #10161
/*    */     //   62: ldc2_w 1156193381388480923
/*    */     //   65: lload_2
/*    */     //   66: lxor
/*    */     //   67: <illegal opcode> c : (IJ)Ljava/lang/String;
/*    */     //   72: aload #4
/*    */     //   74: invokespecial <init> : (Ljava/lang/String;Ljava/lang/Throwable;)V
/*    */     //   77: athrow
/*    */     // Line number table:
/*    */     //   Java source line number -> byte code offset
/*    */     //   #15	-> 0
/*    */     //   #14	-> 17
/*    */     //   #55	-> 53
/*    */     //   #38	-> 55
/*    */     // Exception table:
/*    */     //   from	to	target	type
/*    */     //   0	52	53	java/lang/Throwable
/* 34 */     //   17	33	33	java/lang/Throwable } public float a(short paramShort1, Player paramPlayer, Block paramBlock, short paramShort2, int paramInt) { long l = paramShort1 << 48L | paramShort2 << 48L >>> 16L | paramInt << 32L >>> 32L; int i = (int)((l ^ 0x18425AE8BFB6L) >>> 32L), j = (int)((l ^ 0x18425AE8BFB6L) << 32L >>> 48L), k = (int)((l ^ 0x18425AE8BFB6L) << 48L >>> 48L); l ^ 0x18425AE8BFB6L; return g4.a(i, paramBlock, (char)j, paramPlayer, (short)k); } public Collection a(Player paramPlayer) { return Arrays.asList(new ItemStack[] { paramPlayer.getInventory().getItemInMainHand(), paramPlayer.getInventory().getItemInOffHand() }); }
/*    */    public d7 a(Entity paramEntity, Vector paramVector1, long paramLong, Vector paramVector2, double paramDouble) {
/* 36 */     long l = paramLong ^ 0x7041759F5296L;
/*    */ 
/*    */     
/* 39 */     return d7.a(paramEntity.getWorld().rayTraceBlocks(paramVector1
/*    */ 
/*    */ 
/*    */ 
/*    */ 
/*    */ 
/*    */ 
/*    */ 
/*    */ 
/*    */           
/* 49 */           .toLocation(paramEntity.getWorld()), paramVector2.clone().normalize(), paramDouble), l);
/*    */   } public bh(long paramLong, kP paramkP) {
/*    */     // Byte code:
/*    */     //   0: getstatic me/konsolas/aac/bh.l : J
/*    */     //   3: lload_1
/*    */     //   4: lxor
/*    */     //   5: lstore_1
/*    */     //   6: lload_1
/*    */     //   7: dup2
/*    */     //   8: ldc2_w 18481213382463
/*    */     //   11: lxor
/*    */     //   12: lstore #4
/*    */     //   14: dup2
/*    */     //   15: ldc2_w 130311042293459
/*    */     //   18: lxor
/*    */     //   19: lstore #6
/*    */     //   21: dup2
/*    */     //   22: ldc2_w 74766352092264
/*    */     //   25: lxor
/*    */     //   26: lstore #8
/*    */     //   28: dup2
/*    */     //   29: ldc2_w 138710851254286
/*    */     //   32: lxor
/*    */     //   33: lstore #10
/*    */     //   35: dup2
/*    */     //   36: ldc2_w 67168360870655
/*    */     //   39: lxor
/*    */     //   40: lstore #12
/*    */     //   42: dup2
/*    */     //   43: ldc2_w 131333594787185
/*    */     //   46: lxor
/*    */     //   47: dup2
/*    */     //   48: bipush #32
/*    */     //   50: lushr
/*    */     //   51: l2i
/*    */     //   52: istore #14
/*    */     //   54: dup2
/*    */     //   55: bipush #32
/*    */     //   57: lshl
/*    */     //   58: bipush #56
/*    */     //   60: lushr
/*    */     //   61: l2i
/*    */     //   62: istore #15
/*    */     //   64: dup2
/*    */     //   65: bipush #40
/*    */     //   67: lshl
/*    */     //   68: bipush #40
/*    */     //   70: lushr
/*    */     //   71: l2i
/*    */     //   72: istore #16
/*    */     //   74: pop2
/*    */     //   75: pop2
/*    */     //   76: aload_0
/*    */     //   77: invokespecial <init> : ()V
/*    */     //   80: aload_3
/*    */     //   81: getstatic me/konsolas/aac/kP.V1_13 : Lme/konsolas/aac/kP;
/*    */     //   84: if_acmpeq -> 125
/*    */     //   87: new java/lang/IllegalArgumentException
/*    */     //   90: dup
/*    */     //   91: new java/lang/StringBuilder
/*    */     //   94: dup
/*    */     //   95: invokespecial <init> : ()V
/*    */     //   98: sipush #2459
/*    */     //   101: ldc2_w 4816987325902745114
/*    */     //   104: lload_1
/*    */     //   105: lxor
/*    */     //   106: <illegal opcode> c : (IJ)Ljava/lang/String;
/*    */     //   111: invokevirtual append : (Ljava/lang/String;)Ljava/lang/StringBuilder;
/*    */     //   114: aload_3
/*    */     //   115: invokevirtual append : (Ljava/lang/Object;)Ljava/lang/StringBuilder;
/*    */     //   118: invokevirtual toString : ()Ljava/lang/String;
/*    */     //   121: invokespecial <init> : (Ljava/lang/String;)V
/*    */     //   124: athrow
/*    */     //   125: invokestatic getServer : ()Lorg/bukkit/Server;
/*    */     //   128: invokevirtual getClass : ()Ljava/lang/Class;
/*    */     //   131: invokevirtual getPackage : ()Ljava/lang/Package;
/*    */     //   134: invokevirtual getName : ()Ljava/lang/String;
/*    */     //   137: astore #17
/*    */     //   139: aload #17
/*    */     //   141: sipush #1092
/*    */     //   144: ldc2_w 6608346595242173403
/*    */     //   147: lload_1
/*    */     //   148: lxor
/*    */     //   149: <illegal opcode> c : (IJ)Ljava/lang/String;
/*    */     //   154: sipush #8546
/*    */     //   157: ldc2_w 7611295960015062761
/*    */     //   160: lload_1
/*    */     //   161: lxor
/*    */     //   162: <illegal opcode> c : (IJ)Ljava/lang/String;
/*    */     //   167: invokevirtual replace : (Ljava/lang/CharSequence;Ljava/lang/CharSequence;)Ljava/lang/String;
/*    */     //   170: astore #18
/*    */     //   172: new java/lang/StringBuilder
/*    */     //   175: dup
/*    */     //   176: invokespecial <init> : ()V
/*    */     //   179: aload #17
/*    */     //   181: invokevirtual append : (Ljava/lang/String;)Ljava/lang/StringBuilder;
/*    */     //   184: sipush #30695
/*    */     //   187: ldc2_w 8303066254676693089
/*    */     //   190: lload_1
/*    */     //   191: lxor
/*    */     //   192: <illegal opcode> c : (IJ)Ljava/lang/String;
/*    */     //   197: invokevirtual append : (Ljava/lang/String;)Ljava/lang/StringBuilder;
/*    */     //   200: invokevirtual toString : ()Ljava/lang/String;
/*    */     //   203: invokestatic forName : (Ljava/lang/String;)Ljava/lang/Class;
/*    */     //   206: astore #19
/*    */     //   208: new java/lang/StringBuilder
/*    */     //   211: dup
/*    */     //   212: invokespecial <init> : ()V
/*    */     //   215: aload #17
/*    */     //   217: invokevirtual append : (Ljava/lang/String;)Ljava/lang/StringBuilder;
/*    */     //   220: sipush #8359
/*    */     //   223: ldc2_w 840055385669748515
/*    */     //   226: lload_1
/*    */     //   227: lxor
/*    */     //   228: <illegal opcode> c : (IJ)Ljava/lang/String;
/*    */     //   233: invokevirtual append : (Ljava/lang/String;)Ljava/lang/StringBuilder;
/*    */     //   236: invokevirtual toString : ()Ljava/lang/String;
/*    */     //   239: invokestatic forName : (Ljava/lang/String;)Ljava/lang/Class;
/*    */     //   242: astore #20
/*    */     //   244: new java/lang/StringBuilder
/*    */     //   247: dup
/*    */     //   248: invokespecial <init> : ()V
/*    */     //   251: aload #17
/*    */     //   253: invokevirtual append : (Ljava/lang/String;)Ljava/lang/StringBuilder;
/*    */     //   256: sipush #3645
/*    */     //   259: ldc2_w 8128520247939197355
/*    */     //   262: lload_1
/*    */     //   263: lxor
/*    */     //   264: <illegal opcode> c : (IJ)Ljava/lang/String;
/*    */     //   269: invokevirtual append : (Ljava/lang/String;)Ljava/lang/StringBuilder;
/*    */     //   272: invokevirtual toString : ()Ljava/lang/String;
/*    */     //   275: invokestatic forName : (Ljava/lang/String;)Ljava/lang/Class;
/*    */     //   278: astore #21
/*    */     //   280: new java/lang/StringBuilder
/*    */     //   283: dup
/*    */     //   284: invokespecial <init> : ()V
/*    */     //   287: aload #18
/*    */     //   289: invokevirtual append : (Ljava/lang/String;)Ljava/lang/StringBuilder;
/*    */     //   292: sipush #26620
/*    */     //   295: ldc2_w 6845545951454756973
/*    */     //   298: lload_1
/*    */     //   299: lxor
/*    */     //   300: <illegal opcode> c : (IJ)Ljava/lang/String;
/*    */     //   305: invokevirtual append : (Ljava/lang/String;)Ljava/lang/StringBuilder;
/*    */     //   308: invokevirtual toString : ()Ljava/lang/String;
/*    */     //   311: invokestatic forName : (Ljava/lang/String;)Ljava/lang/Class;
/*    */     //   314: astore #22
/*    */     //   316: new java/lang/StringBuilder
/*    */     //   319: dup
/*    */     //   320: invokespecial <init> : ()V
/*    */     //   323: aload #18
/*    */     //   325: invokevirtual append : (Ljava/lang/String;)Ljava/lang/StringBuilder;
/*    */     //   328: sipush #19957
/*    */     //   331: ldc2_w 9123230958091545212
/*    */     //   334: lload_1
/*    */     //   335: lxor
/*    */     //   336: <illegal opcode> c : (IJ)Ljava/lang/String;
/*    */     //   341: invokevirtual append : (Ljava/lang/String;)Ljava/lang/StringBuilder;
/*    */     //   344: invokevirtual toString : ()Ljava/lang/String;
/*    */     //   347: invokestatic forName : (Ljava/lang/String;)Ljava/lang/Class;
/*    */     //   350: astore #23
/*    */     //   352: new java/lang/StringBuilder
/*    */     //   355: dup
/*    */     //   356: invokespecial <init> : ()V
/*    */     //   359: aload #18
/*    */     //   361: invokevirtual append : (Ljava/lang/String;)Ljava/lang/StringBuilder;
/*    */     //   364: sipush #8065
/*    */     //   367: ldc2_w 3391957678730541077
/*    */     //   370: lload_1
/*    */     //   371: lxor
/*    */     //   372: <illegal opcode> c : (IJ)Ljava/lang/String;
/*    */     //   377: invokevirtual append : (Ljava/lang/String;)Ljava/lang/StringBuilder;
/*    */     //   380: invokevirtual toString : ()Ljava/lang/String;
/*    */     //   383: invokestatic forName : (Ljava/lang/String;)Ljava/lang/Class;
/*    */     //   386: astore #24
/*    */     //   388: new java/lang/StringBuilder
/*    */     //   391: dup
/*    */     //   392: invokespecial <init> : ()V
/*    */     //   395: aload #18
/*    */     //   397: invokevirtual append : (Ljava/lang/String;)Ljava/lang/StringBuilder;
/*    */     //   400: sipush #10113
/*    */     //   403: ldc2_w 7424190176194281476
/*    */     //   406: lload_1
/*    */     //   407: lxor
/*    */     //   408: <illegal opcode> c : (IJ)Ljava/lang/String;
/*    */     //   413: invokevirtual append : (Ljava/lang/String;)Ljava/lang/StringBuilder;
/*    */     //   416: invokevirtual toString : ()Ljava/lang/String;
/*    */     //   419: invokestatic forName : (Ljava/lang/String;)Ljava/lang/Class;
/*    */     //   422: astore #25
/*    */     //   424: new java/lang/StringBuilder
/*    */     //   427: dup
/*    */     //   428: invokespecial <init> : ()V
/*    */     //   431: aload #18
/*    */     //   433: invokevirtual append : (Ljava/lang/String;)Ljava/lang/StringBuilder;
/*    */     //   436: sipush #21899
/*    */     //   439: ldc2_w 3275035397377208836
/*    */     //   442: lload_1
/*    */     //   443: lxor
/*    */     //   444: <illegal opcode> c : (IJ)Ljava/lang/String;
/*    */     //   449: invokevirtual append : (Ljava/lang/String;)Ljava/lang/StringBuilder;
/*    */     //   452: invokevirtual toString : ()Ljava/lang/String;
/*    */     //   455: invokestatic forName : (Ljava/lang/String;)Ljava/lang/Class;
/*    */     //   458: astore #26
/*    */     //   460: new java/lang/StringBuilder
/*    */     //   463: dup
/*    */     //   464: invokespecial <init> : ()V
/*    */     //   467: aload #18
/*    */     //   469: invokevirtual append : (Ljava/lang/String;)Ljava/lang/StringBuilder;
/*    */     //   472: sipush #18274
/*    */     //   475: ldc2_w 7344113261178003692
/*    */     //   478: lload_1
/*    */     //   479: lxor
/*    */     //   480: <illegal opcode> c : (IJ)Ljava/lang/String;
/*    */     //   485: invokevirtual append : (Ljava/lang/String;)Ljava/lang/StringBuilder;
/*    */     //   488: invokevirtual toString : ()Ljava/lang/String;
/*    */     //   491: invokestatic forName : (Ljava/lang/String;)Ljava/lang/Class;
/*    */     //   494: astore #27
/*    */     //   496: new java/lang/StringBuilder
/*    */     //   499: dup
/*    */     //   500: invokespecial <init> : ()V
/*    */     //   503: aload #18
/*    */     //   505: invokevirtual append : (Ljava/lang/String;)Ljava/lang/StringBuilder;
/*    */     //   508: sipush #31009
/*    */     //   511: ldc2_w 7815564290712149675
/*    */     //   514: lload_1
/*    */     //   515: lxor
/*    */     //   516: <illegal opcode> c : (IJ)Ljava/lang/String;
/*    */     //   521: invokevirtual append : (Ljava/lang/String;)Ljava/lang/StringBuilder;
/*    */     //   524: invokevirtual toString : ()Ljava/lang/String;
/*    */     //   527: invokestatic forName : (Ljava/lang/String;)Ljava/lang/Class;
/*    */     //   530: astore #28
/*    */     //   532: aload_0
/*    */     //   533: getstatic me/konsolas/aac/x.a : Ljava/lang/invoke/MethodHandles$Lookup;
/*    */     //   536: aload #24
/*    */     //   538: invokevirtual getSuperclass : ()Ljava/lang/Class;
/*    */     //   541: invokevirtual getSuperclass : ()Ljava/lang/Class;
/*    */     //   544: sipush #26473
/*    */     //   547: ldc2_w 4848790465710555369
/*    */     //   550: lload_1
/*    */     //   551: lxor
/*    */     //   552: <illegal opcode> c : (IJ)Ljava/lang/String;
/*    */     //   557: invokevirtual getDeclaredField : (Ljava/lang/String;)Ljava/lang/reflect/Field;
/*    */     //   560: invokestatic a : (Ljava/lang/reflect/AccessibleObject;)Ljava/lang/reflect/AccessibleObject;
/*    */     //   563: checkcast java/lang/reflect/Field
/*    */     //   566: invokevirtual unreflectGetter : (Ljava/lang/reflect/Field;)Ljava/lang/invoke/MethodHandle;
/*    */     //   569: putfield b : Ljava/lang/invoke/MethodHandle;
/*    */     //   572: aload_0
/*    */     //   573: aload #25
/*    */     //   575: ldc '䏑猃'
/*    */     //   577: invokevirtual toCharArray : ()[C
/*    */     //   580: dup
/*    */     //   581: dup
/*    */     //   582: iconst_0
/*    */     //   583: dup_x1
/*    */     //   584: caload
/*    */     //   585: sipush #8617
/*    */     //   588: ixor
/*    */     //   589: i2c
/*    */     //   590: castore
/*    */     //   591: sipush #16266
/*    */     //   594: iconst_4
/*    */     //   595: iconst_0
/*    */     //   596: invokestatic H : (Ljava/lang/Object;SBB)Ljava/lang/String;
/*    */     //   599: invokevirtual getField : (Ljava/lang/String;)Ljava/lang/reflect/Field;
/*    */     //   602: aconst_null
/*    */     //   603: invokevirtual get : (Ljava/lang/Object;)Ljava/lang/Object;
/*    */     //   606: putfield d : Ljava/lang/Object;
/*    */     //   609: aload_0
/*    */     //   610: getstatic me/konsolas/aac/x.a : Ljava/lang/invoke/MethodHandles$Lookup;
/*    */     //   613: aload #21
/*    */     //   615: sipush #32334
/*    */     //   618: ldc2_w 7211503477292145090
/*    */     //   621: lload_1
/*    */     //   622: lxor
/*    */     //   623: <illegal opcode> c : (IJ)Ljava/lang/String;
/*    */     //   628: iconst_1
/*    */     //   629: anewarray java/lang/Class
/*    */     //   632: dup
/*    */     //   633: iconst_0
/*    */     //   634: aload #25
/*    */     //   636: aastore
/*    */     //   637: invokevirtual getMethod : (Ljava/lang/String;[Ljava/lang/Class;)Ljava/lang/reflect/Method;
/*    */     //   640: invokestatic a : (Ljava/lang/reflect/AccessibleObject;)Ljava/lang/reflect/AccessibleObject;
/*    */     //   643: checkcast java/lang/reflect/Method
/*    */     //   646: invokevirtual unreflect : (Ljava/lang/reflect/Method;)Ljava/lang/invoke/MethodHandle;
/*    */     //   649: putfield f : Ljava/lang/invoke/MethodHandle;
/*    */     //   652: aload_0
/*    */     //   653: getstatic me/konsolas/aac/x.a : Ljava/lang/invoke/MethodHandles$Lookup;
/*    */     //   656: lload #12
/*    */     //   658: invokestatic g : (J)Ljava/lang/Class;
/*    */     //   661: sipush #1885
/*    */     //   664: ldc2_w 9100476122065133773
/*    */     //   667: lload_1
/*    */     //   668: lxor
/*    */     //   669: <illegal opcode> c : (IJ)Ljava/lang/String;
/*    */     //   674: iconst_0
/*    */     //   675: anewarray java/lang/Class
/*    */     //   678: invokevirtual getDeclaredMethod : (Ljava/lang/String;[Ljava/lang/Class;)Ljava/lang/reflect/Method;
/*    */     //   681: invokestatic a : (Ljava/lang/reflect/AccessibleObject;)Ljava/lang/reflect/AccessibleObject;
/*    */     //   684: checkcast java/lang/reflect/Method
/*    */     //   687: invokevirtual unreflect : (Ljava/lang/reflect/Method;)Ljava/lang/invoke/MethodHandle;
/*    */     //   690: putfield g : Ljava/lang/invoke/MethodHandle;
/*    */     //   693: aload_0
/*    */     //   694: getstatic me/konsolas/aac/x.a : Ljava/lang/invoke/MethodHandles$Lookup;
/*    */     //   697: iload #14
/*    */     //   699: iload #15
/*    */     //   701: i2b
/*    */     //   702: iload #16
/*    */     //   704: invokestatic p : (IBI)Ljava/lang/Class;
/*    */     //   707: sipush #3121
/*    */     //   710: ldc2_w 851326811854728121
/*    */     //   713: lload_1
/*    */     //   714: lxor
/*    */     //   715: <illegal opcode> c : (IJ)Ljava/lang/String;
/*    */     //   720: invokevirtual getDeclaredField : (Ljava/lang/String;)Ljava/lang/reflect/Field;
/*    */     //   723: invokestatic a : (Ljava/lang/reflect/AccessibleObject;)Ljava/lang/reflect/AccessibleObject;
/*    */     //   726: checkcast java/lang/reflect/Field
/*    */     //   729: invokevirtual unreflectGetter : (Ljava/lang/reflect/Field;)Ljava/lang/invoke/MethodHandle;
/*    */     //   732: putfield h : Ljava/lang/invoke/MethodHandle;
/*    */     //   735: aload_0
/*    */     //   736: getstatic me/konsolas/aac/x.a : Ljava/lang/invoke/MethodHandles$Lookup;
/*    */     //   739: aload #19
/*    */     //   741: sipush #18545
/*    */     //   744: ldc2_w 7392293493941776374
/*    */     //   747: lload_1
/*    */     //   748: lxor
/*    */     //   749: <illegal opcode> c : (IJ)Ljava/lang/String;
/*    */     //   754: iconst_0
/*    */     //   755: anewarray java/lang/Class
/*    */     //   758: invokevirtual getMethod : (Ljava/lang/String;[Ljava/lang/Class;)Ljava/lang/reflect/Method;
/*    */     //   761: invokevirtual unreflect : (Ljava/lang/reflect/Method;)Ljava/lang/invoke/MethodHandle;
/*    */     //   764: putfield a : Ljava/lang/invoke/MethodHandle;
/*    */     //   767: aload_0
/*    */     //   768: getstatic me/konsolas/aac/x.a : Ljava/lang/invoke/MethodHandles$Lookup;
/*    */     //   771: aload #20
/*    */     //   773: sipush #14840
/*    */     //   776: ldc2_w 1098465799273012838
/*    */     //   779: lload_1
/*    */     //   780: lxor
/*    */     //   781: <illegal opcode> c : (IJ)Ljava/lang/String;
/*    */     //   786: iconst_0
/*    */     //   787: anewarray java/lang/Class
/*    */     //   790: invokevirtual getMethod : (Ljava/lang/String;[Ljava/lang/Class;)Ljava/lang/reflect/Method;
/*    */     //   793: invokevirtual unreflect : (Ljava/lang/reflect/Method;)Ljava/lang/invoke/MethodHandle;
/*    */     //   796: putfield j : Ljava/lang/invoke/MethodHandle;
/*    */     //   799: aload_0
/*    */     //   800: getstatic me/konsolas/aac/x.a : Ljava/lang/invoke/MethodHandles$Lookup;
/*    */     //   803: aload #27
/*    */     //   805: iconst_3
/*    */     //   806: anewarray java/lang/Class
/*    */     //   809: dup
/*    */     //   810: iconst_0
/*    */     //   811: getstatic java/lang/Integer.TYPE : Ljava/lang/Class;
/*    */     //   814: aastore
/*    */     //   815: dup
/*    */     //   816: iconst_1
/*    */     //   817: getstatic java/lang/Integer.TYPE : Ljava/lang/Class;
/*    */     //   820: aastore
/*    */     //   821: dup
/*    */     //   822: iconst_2
/*    */     //   823: getstatic java/lang/Integer.TYPE : Ljava/lang/Class;
/*    */     //   826: aastore
/*    */     //   827: invokevirtual getConstructor : ([Ljava/lang/Class;)Ljava/lang/reflect/Constructor;
/*    */     //   830: invokevirtual unreflectConstructor : (Ljava/lang/reflect/Constructor;)Ljava/lang/invoke/MethodHandle;
/*    */     //   833: putfield k : Ljava/lang/invoke/MethodHandle;
/*    */     //   836: aload_0
/*    */     //   837: getstatic me/konsolas/aac/x.a : Ljava/lang/invoke/MethodHandles$Lookup;
/*    */     //   840: aload #22
/*    */     //   842: sipush #5574
/*    */     //   845: ldc2_w 2347960091043328581
/*    */     //   848: lload_1
/*    */     //   849: lxor
/*    */     //   850: <illegal opcode> c : (IJ)Ljava/lang/String;
/*    */     //   855: iconst_1
/*    */     //   856: anewarray java/lang/Class
/*    */     //   859: dup
/*    */     //   860: iconst_0
/*    */     //   861: aload #27
/*    */     //   863: aastore
/*    */     //   864: invokevirtual getMethod : (Ljava/lang/String;[Ljava/lang/Class;)Ljava/lang/reflect/Method;
/*    */     //   867: invokestatic a : (Ljava/lang/reflect/AccessibleObject;)Ljava/lang/reflect/AccessibleObject;
/*    */     //   870: checkcast java/lang/reflect/Method
/*    */     //   873: invokevirtual unreflect : (Ljava/lang/reflect/Method;)Ljava/lang/invoke/MethodHandle;
/*    */     //   876: putfield c : Ljava/lang/invoke/MethodHandle;
/*    */     //   879: aload_0
/*    */     //   880: getstatic me/konsolas/aac/x.a : Ljava/lang/invoke/MethodHandles$Lookup;
/*    */     //   883: lload #8
/*    */     //   885: invokestatic a : (J)Ljava/lang/Class;
/*    */     //   888: sipush #18225
/*    */     //   891: ldc2_w 5569775996187222204
/*    */     //   894: lload_1
/*    */     //   895: lxor
/*    */     //   896: <illegal opcode> c : (IJ)Ljava/lang/String;
/*    */     //   901: iconst_2
/*    */     //   902: anewarray java/lang/Class
/*    */     //   905: dup
/*    */     //   906: iconst_0
/*    */     //   907: lload #6
/*    */     //   909: invokestatic r : (J)Ljava/lang/Class;
/*    */     //   912: aastore
/*    */     //   913: dup
/*    */     //   914: iconst_1
/*    */     //   915: lload #4
/*    */     //   917: invokestatic f : (J)Ljava/lang/Class;
/*    */     //   920: aastore
/*    */     //   921: invokevirtual getMethod : (Ljava/lang/String;[Ljava/lang/Class;)Ljava/lang/reflect/Method;
/*    */     //   924: invokestatic a : (Ljava/lang/reflect/AccessibleObject;)Ljava/lang/reflect/AccessibleObject;
/*    */     //   927: checkcast java/lang/reflect/Method
/*    */     //   930: invokevirtual unreflect : (Ljava/lang/reflect/Method;)Ljava/lang/invoke/MethodHandle;
/*    */     //   933: putfield i : Ljava/lang/invoke/MethodHandle;
/*    */     //   936: aload_0
/*    */     //   937: getstatic me/konsolas/aac/x.a : Ljava/lang/invoke/MethodHandles$Lookup;
/*    */     //   940: lload #10
/*    */     //   942: sipush #12732
/*    */     //   945: ldc2_w 9003947769571530287
/*    */     //   948: lload_1
/*    */     //   949: lxor
/*    */     //   950: <illegal opcode> c : (IJ)Ljava/lang/String;
/*    */     //   955: invokestatic c : (JLjava/lang/String;)Ljava/lang/Class;
/*    */     //   958: ldc_w '歊獔'
/*    */     //   961: invokevirtual toCharArray : ()[C
/*    */     //   964: dup
/*    */     //   965: dup
/*    */     //   966: iconst_0
/*    */     //   967: dup_x1
/*    */     //   968: caload
/*    */     //   969: sipush #25306
/*    */     //   972: ixor
/*    */     //   973: i2c
/*    */     //   974: castore
/*    */     //   975: sipush #6499
/*    */     //   978: iconst_0
/*    */     //   979: iconst_5
/*    */     //   980: invokestatic H : (Ljava/lang/Object;SBB)Ljava/lang/String;
/*    */     //   983: iconst_0
/*    */     //   984: anewarray java/lang/Class
/*    */     //   987: invokevirtual getMethod : (Ljava/lang/String;[Ljava/lang/Class;)Ljava/lang/reflect/Method;
/*    */     //   990: invokestatic a : (Ljava/lang/reflect/AccessibleObject;)Ljava/lang/reflect/AccessibleObject;
/*    */     //   993: checkcast java/lang/reflect/Method
/*    */     //   996: invokevirtual unreflect : (Ljava/lang/reflect/Method;)Ljava/lang/invoke/MethodHandle;
/*    */     //   999: putfield e : Ljava/lang/invoke/MethodHandle;
/*    */     //   1002: goto -> 1030
/*    */     //   1005: astore #17
/*    */     //   1007: new java/lang/RuntimeException
/*    */     //   1010: dup
/*    */     //   1011: sipush #23029
/*    */     //   1014: ldc2_w 94077573019680359
/*    */     //   1017: lload_1
/*    */     //   1018: lxor
/*    */     //   1019: <illegal opcode> c : (IJ)Ljava/lang/String;
/*    */     //   1024: aload #17
/*    */     //   1026: invokespecial <init> : (Ljava/lang/String;Ljava/lang/Throwable;)V
/*    */     //   1029: athrow
/*    */     //   1030: return
/*    */     // Line number table:
/*    */     //   Java source line number -> byte code offset
/*    */     //   #45	-> 76
/*    */     //   #56	-> 80
/*    */     //   #41	-> 87
/*    */     //   #62	-> 125
/*    */     //   #21	-> 139
/*    */     //   #28	-> 172
/*    */     //   #33	-> 208
/*    */     //   #26	-> 244
/*    */     //   #18	-> 280
/*    */     //   #25	-> 316
/*    */     //   #42	-> 352
/*    */     //   #46	-> 388
/*    */     //   #8	-> 424
/*    */     //   #27	-> 460
/*    */     //   #5	-> 496
/*    */     //   #23	-> 532
/*    */     //   #54	-> 557
/*    */     //   #1	-> 560
/*    */     //   #48	-> 572
/*    */     //   #30	-> 609
/*    */     //   #16	-> 652
/*    */     //   #59	-> 693
/*    */     //   #19	-> 735
/*    */     //   #47	-> 767
/*    */     //   #61	-> 799
/*    */     //   #35	-> 836
/*    */     //   #12	-> 879
/*    */     //   #50	-> 883
/*    */     //   #37	-> 907
/*    */     //   #60	-> 921
/*    */     //   #20	-> 924
/*    */     //   #6	-> 936
/*    */     //   #52	-> 1002
/*    */     //   #58	-> 1005
/*    */     //   #57	-> 1007
/*    */     //   #29	-> 1030
/*    */     // Exception table:
/*    */     //   from	to	target	type
/*    */     //   125	1002	1005	java/lang/IllegalAccessException
/*    */     //   125	1002	1005	java/lang/NoSuchMethodException
/*    */     //   125	1002	1005	java/lang/NoSuchFieldException
/*    */     //   125	1002	1005	java/lang/ClassNotFoundException
/*    */   } public boolean a(Player paramPlayer) {
/* 53 */     return paramPlayer.isGliding();
/*    */   }
/*    */   
/*    */   static {
/*    */     long l = l ^ 0x6B34D9D5ECA6L;
/*    */     "⧶幍棋㶒«世왍᳒?뤨⊡⿞ĺ栝♀?ꪼ煪뢧降熻".toCharArray()[1] = (char)("⧶幍棋㶒«世왍᳒?뤨⊡⿞ĺ栝♀?ꪼ煪뢧降熻".toCharArray()[1] ^ 0x7745);
/*    */     "⟆ⷖ亂ჼ".toCharArray()[2] = (char)("⟆ⷖ亂ჼ".toCharArray()[2] ^ 0x1C34);
/*    */     (new byte[8])[0] = (byte)(int)(l >>> 56L);
/*    */     for (byte b1 = 1; b1 < 8; b1++)
/*    */       (new byte[8])[b1] = (byte)(int)(l << b1 * 8 >>> 56L); 
/*    */     Cipher cipher;
/*    */     (cipher = Cipher.getInstance(fW$gy.A("⧶幍棋㶒«世왍᳒?뤨⊡⿞ĺ栝♀?ꪼ煪뢧降熻".toCharArray(), (short)6782, true, 2))).init(2, SecretKeyFactory.getInstance(fW$gy.A("⟆ⷖ亂ჼ".toCharArray(), (short)24411, false, 2)).generateSecret(new DESKeySpec(new byte[8])), new IvParameterSpec(new byte[8]));
/*    */     String[] arrayOfString = new String[26];
/*    */     boolean bool = false;
/*    */     "蠭ᑚ扔?佛盜ܚ뀓䞝䉣䖻㻭⬫䔁壜좖R??觴鸬떞끇㡬杄춽淰আ꠯寄꼺衟蜖?ꝕ笡힁畡嵟乽㛰츫૽㗡豛健売뛃뀞콞쌰╻暥堝ꪱ礶䊼≢腃鄡奧雟ɴ?蜯稵铕䮏?횮鐖씠呻泸醜?눂쨺䦺ན罜궎琬ὅ盚û뾬粀䌭?脵⑥ꁧṒ胤뽋㓼밄耘䩩䔐?팶俊뭏锁ႊ㢆羝乍퇕◉࣎벴ﰜᝩ㑮⟀徥䓬せ龎滿횧枳ꭤૐꡜ鈁瘠㨄휦䴼❗웋ẖ駼倌瞪\021૲韛✾ퟮ︩Ḕ绑팳⋖岠쮣਷?ưꎤ走픧ݧ銔⽗澦赞읅ጘ夷ﻞȇ㪰ꭃ㗱㒳ᐺꁾ藋竟듹훈䶃ߢ⍐塁﹇䥼観?薋졷᎗瀘藻ႜ㆝㸭ۆ喯쁊킕畵쀉쐦ᘷਵ뤋㰻O燒鞸귍퟾ꙩ풋㶀㏕ㄗ굞혹뗻ὢᕰ嘦洮욦瘚੉힕唪ఇ鎤恙?ᠫԮ墷뉮੶䷚?臔蘌ॾ嬰騩薻ᚃ旪諭嫮꣼楏鰾㸰뼥ঈ焮뿨ব긥卲錧?﫨쭰樭Ᾱ㭽㒩똞첤Z籙ᄡ‱ꊒۿ巪ว⋒ꊥ债औ㐀꽶黕௪困弊柾ࡲ磲ꙻ솯ᎆ륙㣹ո⨢෵䷯蕊玱∊‸˧働㥵棪楧臜蒡뢀춡砕鯮䫍쯻봅捆瀘盧喻閏ꕇᠶ죓ၹ씫똭ᢺ?䧲ٜ睓㭊졠粛栏㊋쌫쮳奻併㙼蹤﯅ഴ༉챀ᚬ氿ᅛ⏢冠峮皼杍쒡䚈۱脎鍚㵺ꤝ?䓆鱗虡爟녑䔁ꧠ祈棫ỏ坳炛༅?࿼疤쮇욘㤥鼅궨鹓ᕤ籭稢⭨᫟?⑙߹孴ᥒ౏㮽鲗?怤탪䏆蠔㾏ᕍ记흡䞪ዻ쁩搹좞㔠円欇ᚑ첃㩨홮캽禢ኅʉ蓁긯囝᱔㏢쬄玁鎝쫄妒煍雷켎✪戛齛뺶Հꠑ웠䮄㐠螸耇엁䫞鉚뒹鞨삼겞ⶮﬤ睟땓惮ᐜ൛瀞꭪帶?溺씄樷봆蘓岢唉㽀ࢿ셻틼Ј⌞ࢅ崙䴖扙秮㝙ꢅ?끀ߒ鄠ﾅ賋欮梅᧔寭胍랋뢶돵렔ﴙ䣌﬈ਐ즊縖䊳犋ପ꩕翖옖嗸㻿쳆녾៦릿拦ᵉ哒㚣楗ᮬﱖ塨媼⮈﹐ꔄ殇軚Ƙ뽺若뉘ॽ魅⏞쒍竔脗朓악ꩡ숩꬗쓳?ꌐ违俶梉ᆕ왂湫㼠㸅ᮃỵ䶇Ⴛ︑䷞䆘調ᴯ妍绍⹾᥸䮾揚ꕆ錊ﶔ಄ﶤ醱崦ꤨ澭ꆎ눕ј셱࠺᝾啥볮睞␂鼽虖詛척鲷?뀲?᥶⒐夯韏緆?䙭븠ဏꅵ᮪휑⸀㒦฻믐䕑ﵯ社๫嫉嵐〟鋉ⴑ뻷ꫪ俪棫뺰葆僣麑ߕ㎪襞ӱ쇙嗄አ琁⭋傄讫壮恑洆햯燓ḓ䇐㚒栳䷩ꅜ酏諏䶣縟씀䃗餚瑁컅ⅷᱸ猕鍺V褐凎ࡳ瓅ࢲॅḻЕ뼂⒖궘ˢ鍼⑆᜘하⳵筶掌ɘ?퓻諍쏂?榚ጩ帎ƌ꩙疭ꐺ㝵៦ꝕ雛箲趼㥔?뜭뫭畫㋮슦ꋚ횝鍇矀龬?䯶圴惧裝紐ꣳ캍로?뼥߼黎⠗틉촄픋墴ᘣ铻婃?휚夥蒡㪲䯻絛蟃놅熓옞略㍂꩓巎陋趰ﺮ쑉玘?旭乑꙱ꥣޓ".toCharArray()[641] = (char)("蠭ᑚ扔?佛盜ܚ뀓䞝䉣䖻㻭⬫䔁壜좖R??觴鸬떞끇㡬杄춽淰আ꠯寄꼺衟蜖?ꝕ笡힁畡嵟乽㛰츫૽㗡豛健売뛃뀞콞쌰╻暥堝ꪱ礶䊼≢腃鄡奧雟ɴ?蜯稵铕䮏?횮鐖씠呻泸醜?눂쨺䦺ན罜궎琬ὅ盚û뾬粀䌭?脵⑥ꁧṒ胤뽋㓼밄耘䩩䔐?팶俊뭏锁ႊ㢆羝乍퇕◉࣎벴ﰜᝩ㑮⟀徥䓬せ龎滿횧枳ꭤૐꡜ鈁瘠㨄휦䴼❗웋ẖ駼倌瞪\021૲韛✾ퟮ︩Ḕ绑팳⋖岠쮣਷?ưꎤ走픧ݧ銔⽗澦赞읅ጘ夷ﻞȇ㪰ꭃ㗱㒳ᐺꁾ藋竟듹훈䶃ߢ⍐塁﹇䥼観?薋졷᎗瀘藻ႜ㆝㸭ۆ喯쁊킕畵쀉쐦ᘷਵ뤋㰻O燒鞸귍퟾ꙩ풋㶀㏕ㄗ굞혹뗻ὢᕰ嘦洮욦瘚੉힕唪ఇ鎤恙?ᠫԮ墷뉮੶䷚?臔蘌ॾ嬰騩薻ᚃ旪諭嫮꣼楏鰾㸰뼥ঈ焮뿨ব긥卲錧?﫨쭰樭Ᾱ㭽㒩똞첤Z籙ᄡ‱ꊒۿ巪ว⋒ꊥ债औ㐀꽶黕௪困弊柾ࡲ磲ꙻ솯ᎆ륙㣹ո⨢෵䷯蕊玱∊‸˧働㥵棪楧臜蒡뢀춡砕鯮䫍쯻봅捆瀘盧喻閏ꕇᠶ죓ၹ씫똭ᢺ?䧲ٜ睓㭊졠粛栏㊋쌫쮳奻併㙼蹤﯅ഴ༉챀ᚬ氿ᅛ⏢冠峮皼杍쒡䚈۱脎鍚㵺ꤝ?䓆鱗虡爟녑䔁ꧠ祈棫ỏ坳炛༅?࿼疤쮇욘㤥鼅궨鹓ᕤ籭稢⭨᫟?⑙߹孴ᥒ౏㮽鲗?怤탪䏆蠔㾏ᕍ记흡䞪ዻ쁩搹좞㔠円欇ᚑ첃㩨홮캽禢ኅʉ蓁긯囝᱔㏢쬄玁鎝쫄妒煍雷켎✪戛齛뺶Հꠑ웠䮄㐠螸耇엁䫞鉚뒹鞨삼겞ⶮﬤ睟땓惮ᐜ൛瀞꭪帶?溺씄樷봆蘓岢唉㽀ࢿ셻틼Ј⌞ࢅ崙䴖扙秮㝙ꢅ?끀ߒ鄠ﾅ賋欮梅᧔寭胍랋뢶돵렔ﴙ䣌﬈ਐ즊縖䊳犋ପ꩕翖옖嗸㻿쳆녾៦릿拦ᵉ哒㚣楗ᮬﱖ塨媼⮈﹐ꔄ殇軚Ƙ뽺若뉘ॽ魅⏞쒍竔脗朓악ꩡ숩꬗쓳?ꌐ违俶梉ᆕ왂湫㼠㸅ᮃỵ䶇Ⴛ︑䷞䆘調ᴯ妍绍⹾᥸䮾揚ꕆ錊ﶔ಄ﶤ醱崦ꤨ澭ꆎ눕ј셱࠺᝾啥볮睞␂鼽虖詛척鲷?뀲?᥶⒐夯韏緆?䙭븠ဏꅵ᮪휑⸀㒦฻믐䕑ﵯ社๫嫉嵐〟鋉ⴑ뻷ꫪ俪棫뺰葆僣麑ߕ㎪襞ӱ쇙嗄አ琁⭋傄讫壮恑洆햯燓ḓ䇐㚒栳䷩ꅜ酏諏䶣縟씀䃗餚瑁컅ⅷᱸ猕鍺V褐凎ࡳ瓅ࢲॅḻЕ뼂⒖궘ˢ鍼⑆᜘하⳵筶掌ɘ?퓻諍쏂?榚ጩ帎ƌ꩙疭ꐺ㝵៦ꝕ雛箲趼㥔?뜭뫭畫㋮슦ꋚ횝鍇矀龬?䯶圴惧裝紐ꣳ캍로?뼥߼黎⠗틉촄픋墴ᘣ铻婃?휚夥蒡㪲䯻絛蟃놅熓옞略㍂꩓巎陋趰ﺮ쑉玘?旭乑꙱ꥣޓ".toCharArray()[641] ^ 0x7CB6);
/*    */     String str;
/*    */     int i = (str = fW$gy.A("蠭ᑚ扔?佛盜ܚ뀓䞝䉣䖻㻭⬫䔁壜좖R??觴鸬떞끇㡬杄춽淰আ꠯寄꼺衟蜖?ꝕ笡힁畡嵟乽㛰츫૽㗡豛健売뛃뀞콞쌰╻暥堝ꪱ礶䊼≢腃鄡奧雟ɴ?蜯稵铕䮏?횮鐖씠呻泸醜?눂쨺䦺ན罜궎琬ὅ盚û뾬粀䌭?脵⑥ꁧṒ胤뽋㓼밄耘䩩䔐?팶俊뭏锁ႊ㢆羝乍퇕◉࣎벴ﰜᝩ㑮⟀徥䓬せ龎滿횧枳ꭤૐꡜ鈁瘠㨄휦䴼❗웋ẖ駼倌瞪\021૲韛✾ퟮ︩Ḕ绑팳⋖岠쮣਷?ưꎤ走픧ݧ銔⽗澦赞읅ጘ夷ﻞȇ㪰ꭃ㗱㒳ᐺꁾ藋竟듹훈䶃ߢ⍐塁﹇䥼観?薋졷᎗瀘藻ႜ㆝㸭ۆ喯쁊킕畵쀉쐦ᘷਵ뤋㰻O燒鞸귍퟾ꙩ풋㶀㏕ㄗ굞혹뗻ὢᕰ嘦洮욦瘚੉힕唪ఇ鎤恙?ᠫԮ墷뉮੶䷚?臔蘌ॾ嬰騩薻ᚃ旪諭嫮꣼楏鰾㸰뼥ঈ焮뿨ব긥卲錧?﫨쭰樭Ᾱ㭽㒩똞첤Z籙ᄡ‱ꊒۿ巪ว⋒ꊥ债औ㐀꽶黕௪困弊柾ࡲ磲ꙻ솯ᎆ륙㣹ո⨢෵䷯蕊玱∊‸˧働㥵棪楧臜蒡뢀춡砕鯮䫍쯻봅捆瀘盧喻閏ꕇᠶ죓ၹ씫똭ᢺ?䧲ٜ睓㭊졠粛栏㊋쌫쮳奻併㙼蹤﯅ഴ༉챀ᚬ氿ᅛ⏢冠峮皼杍쒡䚈۱脎鍚㵺ꤝ?䓆鱗虡爟녑䔁ꧠ祈棫ỏ坳炛༅?࿼疤쮇욘㤥鼅궨鹓ᕤ籭稢⭨᫟?⑙߹孴ᥒ౏㮽鲗?怤탪䏆蠔㾏ᕍ记흡䞪ዻ쁩搹좞㔠円欇ᚑ첃㩨홮캽禢ኅʉ蓁긯囝᱔㏢쬄玁鎝쫄妒煍雷켎✪戛齛뺶Հꠑ웠䮄㐠螸耇엁䫞鉚뒹鞨삼겞ⶮﬤ睟땓惮ᐜ൛瀞꭪帶?溺씄樷봆蘓岢唉㽀ࢿ셻틼Ј⌞ࢅ崙䴖扙秮㝙ꢅ?끀ߒ鄠ﾅ賋欮梅᧔寭胍랋뢶돵렔ﴙ䣌﬈ਐ즊縖䊳犋ପ꩕翖옖嗸㻿쳆녾៦릿拦ᵉ哒㚣楗ᮬﱖ塨媼⮈﹐ꔄ殇軚Ƙ뽺若뉘ॽ魅⏞쒍竔脗朓악ꩡ숩꬗쓳?ꌐ违俶梉ᆕ왂湫㼠㸅ᮃỵ䶇Ⴛ︑䷞䆘調ᴯ妍绍⹾᥸䮾揚ꕆ錊ﶔ಄ﶤ醱崦ꤨ澭ꆎ눕ј셱࠺᝾啥볮睞␂鼽虖詛척鲷?뀲?᥶⒐夯韏緆?䙭븠ဏꅵ᮪휑⸀㒦฻믐䕑ﵯ社๫嫉嵐〟鋉ⴑ뻷ꫪ俪棫뺰葆僣麑ߕ㎪襞ӱ쇙嗄አ琁⭋傄讫壮恑洆햯燓ḓ䇐㚒栳䷩ꅜ酏諏䶣縟씀䃗餚瑁컅ⅷᱸ猕鍺V褐凎ࡳ瓅ࢲॅḻЕ뼂⒖궘ˢ鍼⑆᜘하⳵筶掌ɘ?퓻諍쏂?榚ጩ帎ƌ꩙疭ꐺ㝵៦ꝕ雛箲趼㥔?뜭뫭畫㋮슦ꋚ횝鍇矀龬?䯶圴惧裝紐ꣳ캍로?뼥߼黎⠗틉촄픋墴ᘣ铻婃?휚夥蒡㪲䯻絛蟃놅熓옞略㍂꩓巎陋趰ﺮ쑉玘?旭乑꙱ꥣޓ".toCharArray(), (short)3705, false, 2)).length();
/*    */     byte b2 = 32;
/*    */     byte b = -1;
/*    */     while (true);
/*    */   }
/*    */   
/*    */   private static Throwable a(Throwable paramThrowable) {
/*    */     return paramThrowable;
/*    */   }
/*    */   
/*    */   private static String a(byte[] paramArrayOfbyte) {
/*    */     byte b1 = 0;
/*    */     int i;
/*    */     char[] arrayOfChar = new char[i = paramArrayOfbyte.length];
/*    */     for (byte b2 = 0; b2 < i; b2++) {
/*    */       int j;
/*    */       if ((j = 0xFF & paramArrayOfbyte[b2]) < 192) {
/*    */         arrayOfChar[b1++] = (char)j;
/*    */       } else if (j < 224) {
/*    */         char c = (char)((char)(j & 0x1F) << 6);
/*    */         j = paramArrayOfbyte[++b2];
/*    */         c = (char)(c | (char)(j & 0x3F));
/*    */         arrayOfChar[b1++] = c;
/*    */       } else if (b2 < i - 2) {
/*    */         char c = (char)((char)(j & 0xF) << 12);
/*    */         j = paramArrayOfbyte[++b2];
/*    */         c = (char)(c | (char)(j & 0x3F) << 6);
/*    */         j = paramArrayOfbyte[++b2];
/*    */         c = (char)(c | (char)(j & 0x3F));
/*    */         arrayOfChar[b1++] = c;
/*    */       } 
/*    */     } 
/*    */     return new String(arrayOfChar, 0, b1);
/*    */   }
/*    */   
/*    */   private static String a(int paramInt, long paramLong) {
/*    */     int i = paramInt ^ (int)(paramLong & 0x7FFFL) ^ 0x355D;
/*    */     if (n[i] == null) {
/*    */       Object[] arrayOfObject;
/*    */       try {
/*    */         Long long_ = Long.valueOf(Thread.currentThread().getId());
/*    */         arrayOfObject = (Object[])o.get(long_);
/*    */         if (arrayOfObject == null) {
/*    */           arrayOfObject = new Object[3];
/*    */           "뇭褚䥘윲⵺䄵闆䒱靿Ⲹ头鉧啝ﱃﶨえ㑡".toCharArray()[1] = (char)("뇭褚䥘윲⵺䄵闆䒱靿Ⲹ头鉧啝ﱃﶨえ㑡".toCharArray()[1] ^ 0x7B3E);
/*    */           arrayOfObject[0] = Cipher.getInstance(hY$g6.H("뇭褚䥘윲⵺䄵闆䒱靿Ⲹ头鉧啝ﱃﶨえ㑡".toCharArray(), (short)10716, (byte)1, (byte)3));
/*    */           "丳솹何扬".toCharArray()[0] = (char)("丳솹何扬".toCharArray()[0] ^ 0x636E);
/*    */           arrayOfObject[1] = SecretKeyFactory.getInstance(hY$g6.H("丳솹何扬".toCharArray(), (short)20334, (byte)0, (byte)2));
/*    */           arrayOfObject[2] = new IvParameterSpec(new byte[8]);
/*    */           o.put(long_, arrayOfObject);
/*    */         } 
/*    */       } catch (Exception exception) {
/*    */         "蘿ᆯƪ掸᭻癑ꬡὸ㔇ﾀ䢶㾩副↻္牿㚛".toCharArray()[17] = (char)("蘿ᆯƪ掸᭻癑ꬡὸ㔇ﾀ䢶㾩副↻္牿㚛".toCharArray()[17] ^ 0x18BA);
/*    */         throw new RuntimeException(hY$g6.H("蘿ᆯƪ掸᭻癑ꬡὸ㔇ﾀ䢶㾩副↻္牿㚛".toCharArray(), (short)20428, (byte)5, (byte)4), exception);
/*    */       } 
/*    */       byte[] arrayOfByte1 = new byte[8];
/*    */       arrayOfByte1[0] = (byte)(int)(paramLong >>> 56L);
/*    */       for (byte b = 1; b < 8; b++)
/*    */         arrayOfByte1[b] = (byte)(int)(paramLong << b * 8 >>> 56L); 
/*    */       DESKeySpec dESKeySpec = new DESKeySpec(arrayOfByte1);
/*    */       SecretKey secretKey = ((SecretKeyFactory)arrayOfObject[1]).generateSecret(dESKeySpec);
/*    */       ((Cipher)arrayOfObject[0]).init(2, secretKey, (IvParameterSpec)arrayOfObject[2]);
/*    */       "㈴貼뛨➛梘蜲Τ俊".toCharArray()[7] = (char)("㈴貼뛨➛梘蜲Τ俊".toCharArray()[7] ^ 0x3FCF);
/*    */       byte[] arrayOfByte2 = m[i].getBytes(hY$g6.H("㈴貼뛨➛梘蜲Τ俊".toCharArray(), (short)12713, (byte)3, (byte)1));
/*    */       n[i] = a(((Cipher)arrayOfObject[0]).doFinal(arrayOfByte2));
/*    */     } 
/*    */     return n[i];
/*    */   }
/*    */   
/*    */   private static Object a(MethodHandles.Lookup paramLookup, MutableCallSite paramMutableCallSite, String paramString, Object[] paramArrayOfObject) {
/*    */     int i = ((Integer)paramArrayOfObject[0]).intValue();
/*    */     long l = ((Long)paramArrayOfObject[1]).longValue();
/*    */     String str = a(i, l);
/*    */     MethodHandle methodHandle = MethodHandles.constant(String.class, str);
/*    */     paramMutableCallSite.setTarget(MethodHandles.dropArguments(methodHandle, 0, new Class[] { int.class, long.class }));
/*    */     return str;
/*    */   }
/*    */   
/*    */   private static CallSite a(MethodHandles.Lookup paramLookup, String paramString, MethodType paramMethodType) {
/*    */     // Byte code:
/*    */     //   0: new java/lang/invoke/MutableCallSite
/*    */     //   3: dup
/*    */     //   4: aload_2
/*    */     //   5: invokespecial <init> : (Ljava/lang/invoke/MethodType;)V
/*    */     //   8: astore_3
/*    */     //   9: aload_3
/*    */     //   10: ldc_w
/*    */     //   13: ldc_w [Ljava/lang/Object;
/*    */     //   16: aload_2
/*    */     //   17: invokevirtual parameterCount : ()I
/*    */     //   20: invokevirtual asCollector : (Ljava/lang/Class;I)Ljava/lang/invoke/MethodHandle;
/*    */     //   23: iconst_0
/*    */     //   24: iconst_3
/*    */     //   25: anewarray java/lang/Object
/*    */     //   28: dup
/*    */     //   29: iconst_0
/*    */     //   30: aload_0
/*    */     //   31: aastore
/*    */     //   32: dup
/*    */     //   33: iconst_1
/*    */     //   34: aload_3
/*    */     //   35: aastore
/*    */     //   36: dup
/*    */     //   37: iconst_2
/*    */     //   38: aload_1
/*    */     //   39: aastore
/*    */     //   40: invokestatic insertArguments : (Ljava/lang/invoke/MethodHandle;I[Ljava/lang/Object;)Ljava/lang/invoke/MethodHandle;
/*    */     //   43: aload_2
/*    */     //   44: invokestatic explicitCastArguments : (Ljava/lang/invoke/MethodHandle;Ljava/lang/invoke/MethodType;)Ljava/lang/invoke/MethodHandle;
/*    */     //   47: invokevirtual setTarget : (Ljava/lang/invoke/MethodHandle;)V
/*    */     //   50: goto -> 170
/*    */     //   53: astore #4
/*    */     //   55: new java/lang/RuntimeException
/*    */     //   58: dup
/*    */     //   59: new java/lang/StringBuilder
/*    */     //   62: dup
/*    */     //   63: invokespecial <init> : ()V
/*    */     //   66: ldc_w 'Ɓ곘瓥ﮒ욨ꃋ伊떴腣ᦣ䙰플Ά㭫脸荕໖'
/*    */     //   69: invokevirtual toCharArray : ()[C
/*    */     //   72: dup
/*    */     //   73: dup
/*    */     //   74: iconst_0
/*    */     //   75: dup_x1
/*    */     //   76: caload
/*    */     //   77: sipush #30962
/*    */     //   80: ixor
/*    */     //   81: i2c
/*    */     //   82: castore
/*    */     //   83: sipush #24711
/*    */     //   86: iconst_1
/*    */     //   87: iconst_2
/*    */     //   88: invokestatic A : (Ljava/lang/Object;SZI)Ljava/lang/String;
/*    */     //   91: invokevirtual append : (Ljava/lang/String;)Ljava/lang/StringBuilder;
/*    */     //   94: ldc_w '塑庴ઉ䌮'
/*    */     //   97: invokevirtual toCharArray : ()[C
/*    */     //   100: dup
/*    */     //   101: dup
/*    */     //   102: iconst_0
/*    */     //   103: dup_x1
/*    */     //   104: caload
/*    */     //   105: sipush #23621
/*    */     //   108: ixor
/*    */     //   109: i2c
/*    */     //   110: castore
/*    */     //   111: sipush #11720
/*    */     //   114: iconst_1
/*    */     //   115: iconst_1
/*    */     //   116: invokestatic A : (Ljava/lang/Object;SZI)Ljava/lang/String;
/*    */     //   119: invokevirtual append : (Ljava/lang/String;)Ljava/lang/StringBuilder;
/*    */     //   122: aload_1
/*    */     //   123: invokevirtual append : (Ljava/lang/String;)Ljava/lang/StringBuilder;
/*    */     //   126: ldc_w '౑烩ᅄ疸'
/*    */     //   129: invokevirtual toCharArray : ()[C
/*    */     //   132: dup
/*    */     //   133: dup
/*    */     //   134: iconst_0
/*    */     //   135: dup_x1
/*    */     //   136: caload
/*    */     //   137: sipush #26921
/*    */     //   140: ixor
/*    */     //   141: i2c
/*    */     //   142: castore
/*    */     //   143: sipush #26236
/*    */     //   146: iconst_0
/*    */     //   147: iconst_0
/*    */     //   148: invokestatic A : (Ljava/lang/Object;SZI)Ljava/lang/String;
/*    */     //   151: invokevirtual append : (Ljava/lang/String;)Ljava/lang/StringBuilder;
/*    */     //   154: aload_2
/*    */     //   155: invokevirtual toString : ()Ljava/lang/String;
/*    */     //   158: invokevirtual append : (Ljava/lang/String;)Ljava/lang/StringBuilder;
/*    */     //   161: invokevirtual toString : ()Ljava/lang/String;
/*    */     //   164: aload #4
/*    */     //   166: invokespecial <init> : (Ljava/lang/String;Ljava/lang/Throwable;)V
/*    */     //   169: athrow
/*    */     //   170: aload_3
/*    */     //   171: areturn
/*    */     // Exception table:
/*    */     //   from	to	target	type
/*    */     //   9	50	53	java/lang/Exception
/*    */   } }


/* Location:              C:\Users\BukkitBypass\Desktop\MatrixAC\AAC\AAC-spigot-5.2.0.jar!\me\konsolas\aac\bh.class
 * Java compiler version: 8 (52.0)
 * JD-Core Version:       1.1.3
 */