/*    */ package me.konsolas.aac;
/*    */ 
/*    */ public class bz extends RecursiveAction {
/*    */   public bz(int paramInt1, int paramInt2, kx paramkx, kU paramkU) {
/*  5 */     this.d = paramInt1;
/*    */ 
/*    */ 
/*    */ 
/*    */ 
/*    */ 
/*    */ 
/*    */ 
/*    */ 
/*    */ 
/*    */ 
/*    */ 
/*    */ 
/*    */ 
/*    */ 
/*    */ 
/*    */     
/* 22 */     this.a = paramInt2;
/*    */     this.c = paramkx;
/*    */     this.b = paramkU;
/*    */   }
/*    */   
/*    */   private static final long serialVersionUID = 1L;
/*    */   private final int d;
/*    */   private final int a;
/*    */   private final kx c;
/*    */   private final kU b;
/*    */   
/*    */   private static v a(v paramv) {
/*    */     return paramv;
/*    */   }
/*    */   
/*    */   protected void compute() {
/*    */     // Byte code:
/*    */     //   0: aload_0
/*    */     //   1: getfield a : I
/*    */     //   4: aload_0
/*    */     //   5: getfield d : I
/*    */     //   8: isub
/*    */     //   9: istore_1
/*    */     //   10: iload_1
/*    */     //   11: sipush #8192
/*    */     //   14: if_icmpge -> 41
/*    */     //   17: aload_0
/*    */     //   18: getfield d : I
/*    */     //   21: aload_0
/*    */     //   22: getfield a : I
/*    */     //   25: aload_0
/*    */     //   26: getfield c : Lme/konsolas/aac/kx;
/*    */     //   29: aload_0
/*    */     //   30: getfield b : Lme/konsolas/aac/kU;
/*    */     //   33: invokestatic a : (IILme/konsolas/aac/kx;Lme/konsolas/aac/kU;)V
/*    */     //   36: return
/*    */     //   37: invokestatic a : (Laacinternal/v;)Laacinternal/v;
/*    */     //   40: athrow
/*    */     //   41: aload_0
/*    */     //   42: getfield d : I
/*    */     //   45: iload_1
/*    */     //   46: iconst_2
/*    */     //   47: idiv
/*    */     //   48: iadd
/*    */     //   49: istore_2
/*    */     //   50: aload_0
/*    */     //   51: getfield d : I
/*    */     //   54: istore_3
/*    */     //   55: aload_0
/*    */     //   56: getfield a : I
/*    */     //   59: iconst_1
/*    */     //   60: isub
/*    */     //   61: istore #4
/*    */     //   63: iload_1
/*    */     //   64: bipush #8
/*    */     //   66: idiv
/*    */     //   67: istore #5
/*    */     //   69: iload_3
/*    */     //   70: iload_3
/*    */     //   71: iload #5
/*    */     //   73: iadd
/*    */     //   74: iload_3
/*    */     //   75: iconst_2
/*    */     //   76: iload #5
/*    */     //   78: imul
/*    */     //   79: iadd
/*    */     //   80: aload_0
/*    */     //   81: getfield c : Lme/konsolas/aac/kx;
/*    */     //   84: invokestatic d : (IIILme/konsolas/aac/kx;)I
/*    */     //   87: istore_3
/*    */     //   88: iload_2
/*    */     //   89: iload #5
/*    */     //   91: isub
/*    */     //   92: iload_2
/*    */     //   93: iload_2
/*    */     //   94: iload #5
/*    */     //   96: iadd
/*    */     //   97: aload_0
/*    */     //   98: getfield c : Lme/konsolas/aac/kx;
/*    */     //   101: invokestatic d : (IIILme/konsolas/aac/kx;)I
/*    */     //   104: istore_2
/*    */     //   105: iload #4
/*    */     //   107: iconst_2
/*    */     //   108: iload #5
/*    */     //   110: imul
/*    */     //   111: isub
/*    */     //   112: iload #4
/*    */     //   114: iload #5
/*    */     //   116: isub
/*    */     //   117: iload #4
/*    */     //   119: aload_0
/*    */     //   120: getfield c : Lme/konsolas/aac/kx;
/*    */     //   123: invokestatic d : (IIILme/konsolas/aac/kx;)I
/*    */     //   126: istore #4
/*    */     //   128: iload_3
/*    */     //   129: iload_2
/*    */     //   130: iload #4
/*    */     //   132: aload_0
/*    */     //   133: getfield c : Lme/konsolas/aac/kx;
/*    */     //   136: invokestatic d : (IIILme/konsolas/aac/kx;)I
/*    */     //   139: istore_2
/*    */     //   140: aload_0
/*    */     //   141: getfield d : I
/*    */     //   144: istore #6
/*    */     //   146: iload #6
/*    */     //   148: istore #7
/*    */     //   150: aload_0
/*    */     //   151: getfield a : I
/*    */     //   154: iconst_1
/*    */     //   155: isub
/*    */     //   156: istore #8
/*    */     //   158: iload #8
/*    */     //   160: istore #9
/*    */     //   162: iload #7
/*    */     //   164: iload #8
/*    */     //   166: if_icmpgt -> 249
/*    */     //   169: aload_0
/*    */     //   170: getfield c : Lme/konsolas/aac/kx;
/*    */     //   173: iload #7
/*    */     //   175: iload_2
/*    */     //   176: invokeinterface a : (II)I
/*    */     //   181: dup
/*    */     //   182: istore #10
/*    */     //   184: ifgt -> 249
/*    */     //   187: iload #10
/*    */     //   189: ifne -> 243
/*    */     //   192: goto -> 199
/*    */     //   195: invokestatic a : (Laacinternal/v;)Laacinternal/v;
/*    */     //   198: athrow
/*    */     //   199: iload #6
/*    */     //   201: iload_2
/*    */     //   202: if_icmpne -> 218
/*    */     //   205: goto -> 212
/*    */     //   208: invokestatic a : (Laacinternal/v;)Laacinternal/v;
/*    */     //   211: athrow
/*    */     //   212: iload #7
/*    */     //   214: istore_2
/*    */     //   215: goto -> 227
/*    */     //   218: iload #7
/*    */     //   220: iload_2
/*    */     //   221: if_icmpne -> 227
/*    */     //   224: iload #6
/*    */     //   226: istore_2
/*    */     //   227: aload_0
/*    */     //   228: getfield b : Lme/konsolas/aac/kU;
/*    */     //   231: iload #6
/*    */     //   233: iinc #6, 1
/*    */     //   236: iload #7
/*    */     //   238: invokeinterface a : (II)V
/*    */     //   243: iinc #7, 1
/*    */     //   246: goto -> 162
/*    */     //   249: iload #8
/*    */     //   251: iload #7
/*    */     //   253: if_icmplt -> 336
/*    */     //   256: aload_0
/*    */     //   257: getfield c : Lme/konsolas/aac/kx;
/*    */     //   260: iload #8
/*    */     //   262: iload_2
/*    */     //   263: invokeinterface a : (II)I
/*    */     //   268: dup
/*    */     //   269: istore #10
/*    */     //   271: iflt -> 336
/*    */     //   274: iload #10
/*    */     //   276: ifne -> 330
/*    */     //   279: goto -> 286
/*    */     //   282: invokestatic a : (Laacinternal/v;)Laacinternal/v;
/*    */     //   285: athrow
/*    */     //   286: iload #8
/*    */     //   288: iload_2
/*    */     //   289: if_icmpne -> 305
/*    */     //   292: goto -> 299
/*    */     //   295: invokestatic a : (Laacinternal/v;)Laacinternal/v;
/*    */     //   298: athrow
/*    */     //   299: iload #9
/*    */     //   301: istore_2
/*    */     //   302: goto -> 314
/*    */     //   305: iload #9
/*    */     //   307: iload_2
/*    */     //   308: if_icmpne -> 314
/*    */     //   311: iload #8
/*    */     //   313: istore_2
/*    */     //   314: aload_0
/*    */     //   315: getfield b : Lme/konsolas/aac/kU;
/*    */     //   318: iload #8
/*    */     //   320: iload #9
/*    */     //   322: iinc #9, -1
/*    */     //   325: invokeinterface a : (II)V
/*    */     //   330: iinc #8, -1
/*    */     //   333: goto -> 249
/*    */     //   336: iload #7
/*    */     //   338: iload #8
/*    */     //   340: if_icmple -> 350
/*    */     //   343: goto -> 393
/*    */     //   346: invokestatic a : (Laacinternal/v;)Laacinternal/v;
/*    */     //   349: athrow
/*    */     //   350: iload #7
/*    */     //   352: iload_2
/*    */     //   353: if_icmpne -> 362
/*    */     //   356: iload #9
/*    */     //   358: istore_2
/*    */     //   359: goto -> 371
/*    */     //   362: iload #8
/*    */     //   364: iload_2
/*    */     //   365: if_icmpne -> 371
/*    */     //   368: iload #8
/*    */     //   370: istore_2
/*    */     //   371: aload_0
/*    */     //   372: getfield b : Lme/konsolas/aac/kU;
/*    */     //   375: iload #7
/*    */     //   377: iinc #7, 1
/*    */     //   380: iload #8
/*    */     //   382: iinc #8, -1
/*    */     //   385: invokeinterface a : (II)V
/*    */     //   390: goto -> 162
/*    */     //   393: iload #6
/*    */     //   395: aload_0
/*    */     //   396: getfield d : I
/*    */     //   399: isub
/*    */     //   400: iload #7
/*    */     //   402: iload #6
/*    */     //   404: isub
/*    */     //   405: invokestatic min : (II)I
/*    */     //   408: istore #5
/*    */     //   410: aload_0
/*    */     //   411: getfield b : Lme/konsolas/aac/kU;
/*    */     //   414: aload_0
/*    */     //   415: getfield d : I
/*    */     //   418: iload #7
/*    */     //   420: iload #5
/*    */     //   422: isub
/*    */     //   423: iload #5
/*    */     //   425: invokestatic a : (Lme/konsolas/aac/kU;III)V
/*    */     //   428: iload #9
/*    */     //   430: iload #8
/*    */     //   432: isub
/*    */     //   433: aload_0
/*    */     //   434: getfield a : I
/*    */     //   437: iload #9
/*    */     //   439: isub
/*    */     //   440: iconst_1
/*    */     //   441: isub
/*    */     //   442: invokestatic min : (II)I
/*    */     //   445: istore #5
/*    */     //   447: aload_0
/*    */     //   448: getfield b : Lme/konsolas/aac/kU;
/*    */     //   451: iload #7
/*    */     //   453: aload_0
/*    */     //   454: getfield a : I
/*    */     //   457: iload #5
/*    */     //   459: isub
/*    */     //   460: iload #5
/*    */     //   462: invokestatic a : (Lme/konsolas/aac/kU;III)V
/*    */     //   465: iload #7
/*    */     //   467: iload #6
/*    */     //   469: isub
/*    */     //   470: istore #5
/*    */     //   472: iload #9
/*    */     //   474: iload #8
/*    */     //   476: isub
/*    */     //   477: istore #10
/*    */     //   479: iload #5
/*    */     //   481: iconst_1
/*    */     //   482: if_icmple -> 560
/*    */     //   485: iload #10
/*    */     //   487: iconst_1
/*    */     //   488: if_icmple -> 560
/*    */     //   491: goto -> 498
/*    */     //   494: invokestatic a : (Laacinternal/v;)Laacinternal/v;
/*    */     //   497: athrow
/*    */     //   498: new me/konsolas/aac/bz
/*    */     //   501: dup
/*    */     //   502: aload_0
/*    */     //   503: getfield d : I
/*    */     //   506: aload_0
/*    */     //   507: getfield d : I
/*    */     //   510: iload #5
/*    */     //   512: iadd
/*    */     //   513: aload_0
/*    */     //   514: getfield c : Lme/konsolas/aac/kx;
/*    */     //   517: aload_0
/*    */     //   518: getfield b : Lme/konsolas/aac/kU;
/*    */     //   521: invokespecial <init> : (IILme/konsolas/aac/kx;Lme/konsolas/aac/kU;)V
/*    */     //   524: new me/konsolas/aac/bz
/*    */     //   527: dup
/*    */     //   528: aload_0
/*    */     //   529: getfield a : I
/*    */     //   532: iload #10
/*    */     //   534: isub
/*    */     //   535: aload_0
/*    */     //   536: getfield a : I
/*    */     //   539: aload_0
/*    */     //   540: getfield c : Lme/konsolas/aac/kx;
/*    */     //   543: aload_0
/*    */     //   544: getfield b : Lme/konsolas/aac/kU;
/*    */     //   547: invokespecial <init> : (IILme/konsolas/aac/kx;Lme/konsolas/aac/kU;)V
/*    */     //   550: invokestatic invokeAll : (Ljava/util/concurrent/ForkJoinTask;Ljava/util/concurrent/ForkJoinTask;)V
/*    */     //   553: goto -> 645
/*    */     //   556: invokestatic a : (Laacinternal/v;)Laacinternal/v;
/*    */     //   559: athrow
/*    */     //   560: iload #5
/*    */     //   562: iconst_1
/*    */     //   563: if_icmple -> 609
/*    */     //   566: iconst_1
/*    */     //   567: anewarray java/util/concurrent/ForkJoinTask
/*    */     //   570: dup
/*    */     //   571: iconst_0
/*    */     //   572: new me/konsolas/aac/bz
/*    */     //   575: dup
/*    */     //   576: aload_0
/*    */     //   577: getfield d : I
/*    */     //   580: aload_0
/*    */     //   581: getfield d : I
/*    */     //   584: iload #5
/*    */     //   586: iadd
/*    */     //   587: aload_0
/*    */     //   588: getfield c : Lme/konsolas/aac/kx;
/*    */     //   591: aload_0
/*    */     //   592: getfield b : Lme/konsolas/aac/kU;
/*    */     //   595: invokespecial <init> : (IILme/konsolas/aac/kx;Lme/konsolas/aac/kU;)V
/*    */     //   598: aastore
/*    */     //   599: invokestatic invokeAll : ([Ljava/util/concurrent/ForkJoinTask;)V
/*    */     //   602: goto -> 645
/*    */     //   605: invokestatic a : (Laacinternal/v;)Laacinternal/v;
/*    */     //   608: athrow
/*    */     //   609: iconst_1
/*    */     //   610: anewarray java/util/concurrent/ForkJoinTask
/*    */     //   613: dup
/*    */     //   614: iconst_0
/*    */     //   615: new me/konsolas/aac/bz
/*    */     //   618: dup
/*    */     //   619: aload_0
/*    */     //   620: getfield a : I
/*    */     //   623: iload #10
/*    */     //   625: isub
/*    */     //   626: aload_0
/*    */     //   627: getfield a : I
/*    */     //   630: aload_0
/*    */     //   631: getfield c : Lme/konsolas/aac/kx;
/*    */     //   634: aload_0
/*    */     //   635: getfield b : Lme/konsolas/aac/kU;
/*    */     //   638: invokespecial <init> : (IILme/konsolas/aac/kx;Lme/konsolas/aac/kU;)V
/*    */     //   641: aastore
/*    */     //   642: invokestatic invokeAll : ([Ljava/util/concurrent/ForkJoinTask;)V
/*    */     //   645: return
/*    */     // Line number table:
/*    */     //   Java source line number -> byte code offset
/*    */     //   #18	-> 0
/*    */     //   #29	-> 10
/*    */     //   #40	-> 17
/*    */     //   #24	-> 36
/*    */     //   #3	-> 41
/*    */     //   #41	-> 50
/*    */     //   #43	-> 55
/*    */     //   #11	-> 63
/*    */     //   #6	-> 69
/*    */     //   #25	-> 88
/*    */     //   #33	-> 105
/*    */     //   #4	-> 128
/*    */     //   #27	-> 140
/*    */     //   #36	-> 162
/*    */     //   #45	-> 187
/*    */     //   #10	-> 199
/*    */     //   #1	-> 218
/*    */     //   #16	-> 227
/*    */     //   #20	-> 243
/*    */     //   #12	-> 249
/*    */     //   #39	-> 274
/*    */     //   #2	-> 286
/*    */     //   #34	-> 305
/*    */     //   #35	-> 314
/*    */     //   #31	-> 330
/*    */     //   #9	-> 336
/*    */     //   #26	-> 350
/*    */     //   #17	-> 362
/*    */     //   #42	-> 371
/*    */     //   #37	-> 393
/*    */     //   #44	-> 410
/*    */     //   #28	-> 428
/*    */     //   #7	-> 447
/*    */     //   #21	-> 465
/*    */     //   #15	-> 472
/*    */     //   #38	-> 479
/*    */     //   #13	-> 560
/*    */     //   #30	-> 609
/*    */     //   #8	-> 645
/*    */     // Exception table:
/*    */     //   from	to	target	type
/*    */     //   10	37	37	aacinternal/v
/*    */     //   184	192	195	aacinternal/v
/*    */     //   187	205	208	aacinternal/v
/*    */     //   271	279	282	aacinternal/v
/*    */     //   274	292	295	aacinternal/v
/*    */     //   336	346	346	aacinternal/v
/*    */     //   479	491	494	aacinternal/v
/*    */     //   485	556	556	aacinternal/v
/*    */     //   560	605	605	aacinternal/v
/*    */   }
/*    */ }


/* Location:              C:\Users\BukkitBypass\Desktop\MatrixAC\AAC\AAC-spigot-5.2.0.jar!\me\konsolas\aac\bz.class
 * Java compiler version: 8 (52.0)
 * JD-Core Version:       1.1.3
 */