/*     */ package me.konsolas.aac;
/*     */ 
/*     */ import java.lang.invoke.CallSite;
/*     */ import java.lang.invoke.MethodHandle;
/*     */ import java.lang.invoke.MethodHandles;
/*     */ import java.lang.invoke.MethodType;
/*     */ import java.lang.invoke.MutableCallSite;
/*     */ import java.util.HashMap;
/*     */ import java.util.List;
/*     */ import java.util.Map;
/*     */ import java.util.regex.Pattern;
/*     */ import javax.annotation.Nullable;
/*     */ import javax.crypto.Cipher;
/*     */ import javax.crypto.SecretKey;
/*     */ import javax.crypto.SecretKeyFactory;
/*     */ import javax.crypto.spec.DESKeySpec;
/*     */ import javax.crypto.spec.IvParameterSpec;
/*     */ 
/*     */ 
/*     */ 
/*     */ 
/*     */ 
/*     */ 
/*     */ 
/*     */ public final class c2
/*     */ {
/*     */   private static final Pattern k;
/*     */   private static final Pattern i;
/*     */   private static final Pattern m;
/*     */   private static final Pattern b;
/*     */   private final String c;
/*     */   private final String l;
/*     */   private final long f;
/*     */   private final String j;
/*     */   private final String e;
/*     */   private final boolean g;
/*     */   
/*     */   public long a() {
/*  39 */     return this.f;
/*     */   }
/*     */   private final boolean a; private final boolean h; private final boolean d; private static final long n; private static final String[] o; private static final String[] p; private static final Map q;
/*     */   private static String a(String paramString, long paramLong) {
/*     */     // Byte code:
/*     */     //   0: getstatic me/konsolas/aac/c2.n : J
/*     */     //   3: lload_1
/*     */     //   4: lxor
/*     */     //   5: lstore_1
/*     */     //   6: lload_1
/*     */     //   7: dup2
/*     */     //   8: ldc2_w 42828250175778
/*     */     //   11: lxor
/*     */     //   12: lstore_3
/*     */     //   13: pop2
/*     */     //   14: ldc2_w 2742321410705073868
/*     */     //   17: lload_1
/*     */     //   18: <illegal opcode> w : (JJ)[Lme/konsolas/aac/aN;
/*     */     //   23: astore #5
/*     */     //   25: aload_0
/*     */     //   26: ldc_w '䠕՘'
/*     */     //   29: invokevirtual toCharArray : ()[C
/*     */     //   32: dup
/*     */     //   33: dup
/*     */     //   34: iconst_0
/*     */     //   35: dup_x1
/*     */     //   36: caload
/*     */     //   37: sipush #8027
/*     */     //   40: ixor
/*     */     //   41: i2c
/*     */     //   42: castore
/*     */     //   43: sipush #25990
/*     */     //   46: iconst_1
/*     */     //   47: iconst_0
/*     */     //   48: invokestatic U : (Ljava/lang/Object;SZZ)Ljava/lang/String;
/*     */     //   51: invokevirtual endsWith : (Ljava/lang/String;)Z
/*     */     //   54: aload #5
/*     */     //   56: ifnonnull -> 140
/*     */     //   59: ifeq -> 93
/*     */     //   62: goto -> 75
/*     */     //   65: ldc2_w 2755201443521842236
/*     */     //   68: lload_1
/*     */     //   69: <illegal opcode> w : (Ljava/lang/RuntimeException;JJ)Ljava/lang/RuntimeException;
/*     */     //   74: athrow
/*     */     //   75: new java/lang/IllegalArgumentException
/*     */     //   78: dup
/*     */     //   79: invokespecial <init> : ()V
/*     */     //   82: athrow
/*     */     //   83: ldc2_w 2755201443521842236
/*     */     //   86: lload_1
/*     */     //   87: <illegal opcode> w : (Ljava/lang/RuntimeException;JJ)Ljava/lang/RuntimeException;
/*     */     //   92: athrow
/*     */     //   93: aload_0
/*     */     //   94: aload #5
/*     */     //   96: ifnonnull -> 154
/*     */     //   99: ldc_w '䡠哠'
/*     */     //   102: invokevirtual toCharArray : ()[C
/*     */     //   105: dup
/*     */     //   106: dup
/*     */     //   107: iconst_0
/*     */     //   108: dup_x1
/*     */     //   109: caload
/*     */     //   110: sipush #30046
/*     */     //   113: ixor
/*     */     //   114: i2c
/*     */     //   115: castore
/*     */     //   116: sipush #425
/*     */     //   119: iconst_0
/*     */     //   120: iconst_0
/*     */     //   121: invokestatic U : (Ljava/lang/Object;SZZ)Ljava/lang/String;
/*     */     //   124: invokevirtual startsWith : (Ljava/lang/String;)Z
/*     */     //   127: goto -> 140
/*     */     //   130: ldc2_w 2755201443521842236
/*     */     //   133: lload_1
/*     */     //   134: <illegal opcode> w : (Ljava/lang/RuntimeException;JJ)Ljava/lang/RuntimeException;
/*     */     //   139: athrow
/*     */     //   140: ifeq -> 149
/*     */     //   143: aload_0
/*     */     //   144: iconst_1
/*     */     //   145: invokevirtual substring : (I)Ljava/lang/String;
/*     */     //   148: astore_0
/*     */     //   149: lload_3
/*     */     //   150: aload_0
/*     */     //   151: invokestatic a : (JLjava/lang/String;)Ljava/lang/String;
/*     */     //   154: astore #6
/*     */     //   156: aload #6
/*     */     //   158: aload #5
/*     */     //   160: ifnonnull -> 199
/*     */     //   163: ifnonnull -> 197
/*     */     //   166: goto -> 179
/*     */     //   169: ldc2_w 2755201443521842236
/*     */     //   172: lload_1
/*     */     //   173: <illegal opcode> w : (Ljava/lang/RuntimeException;JJ)Ljava/lang/RuntimeException;
/*     */     //   178: athrow
/*     */     //   179: new java/lang/IllegalArgumentException
/*     */     //   182: dup
/*     */     //   183: invokespecial <init> : ()V
/*     */     //   186: athrow
/*     */     //   187: ldc2_w 2755201443521842236
/*     */     //   190: lload_1
/*     */     //   191: <illegal opcode> w : (Ljava/lang/RuntimeException;JJ)Ljava/lang/RuntimeException;
/*     */     //   196: athrow
/*     */     //   197: aload #6
/*     */     //   199: areturn
/*     */     // Line number table:
/*     */     //   Java source line number -> byte code offset
/*     */     //   #3	-> 25
/*     */     //   #213	-> 75
/*     */     //   #141	-> 93
/*     */     //   #149	-> 143
/*     */     //   #65	-> 149
/*     */     //   #236	-> 156
/*     */     //   #54	-> 179
/*     */     //   #219	-> 197
/*     */     // Exception table:
/*     */     //   from	to	target	type
/*     */     //   25	62	65	java/lang/NullPointerException
/*     */     //   59	83	83	java/lang/NullPointerException
/*     */     //   93	127	130	java/lang/NullPointerException
/*     */     //   156	166	169	java/lang/NullPointerException
/*     */     //   163	187	187	java/lang/NullPointerException
/*     */   }
/*     */   private static int a(String paramString, int paramInt1, int paramInt2, boolean paramBoolean, long paramLong) {
/*     */     // Byte code:
/*     */     //   0: getstatic me/konsolas/aac/c2.n : J
/*     */     //   3: lload #4
/*     */     //   5: lxor
/*     */     //   6: lstore #4
/*     */     //   8: ldc2_w 4463614401171963187
/*     */     //   11: lload #4
/*     */     //   13: <illegal opcode> w : (JJ)[Lme/konsolas/aac/aN;
/*     */     //   18: iload_1
/*     */     //   19: istore #7
/*     */     //   21: astore #6
/*     */     //   23: iload #7
/*     */     //   25: iload_2
/*     */     //   26: if_icmpge -> 539
/*     */     //   29: aload_0
/*     */     //   30: iload #7
/*     */     //   32: invokevirtual charAt : (I)C
/*     */     //   35: istore #8
/*     */     //   37: iload #8
/*     */     //   39: aload #6
/*     */     //   41: ifnonnull -> 540
/*     */     //   44: bipush #32
/*     */     //   46: lload #4
/*     */     //   48: lconst_0
/*     */     //   49: lcmp
/*     */     //   50: iflt -> 166
/*     */     //   53: aload #6
/*     */     //   55: ifnonnull -> 166
/*     */     //   58: goto -> 72
/*     */     //   61: ldc2_w 4450451916835084227
/*     */     //   64: lload #4
/*     */     //   66: <illegal opcode> w : (Ljava/lang/RuntimeException;JJ)Ljava/lang/RuntimeException;
/*     */     //   71: athrow
/*     */     //   72: if_icmpge -> 129
/*     */     //   75: goto -> 89
/*     */     //   78: ldc2_w 4450451916835084227
/*     */     //   81: lload #4
/*     */     //   83: <illegal opcode> w : (Ljava/lang/RuntimeException;JJ)Ljava/lang/RuntimeException;
/*     */     //   88: athrow
/*     */     //   89: iload #8
/*     */     //   91: aload #6
/*     */     //   93: ifnonnull -> 478
/*     */     //   96: goto -> 110
/*     */     //   99: ldc2_w 4450451916835084227
/*     */     //   102: lload #4
/*     */     //   104: <illegal opcode> w : (Ljava/lang/RuntimeException;JJ)Ljava/lang/RuntimeException;
/*     */     //   109: athrow
/*     */     //   110: bipush #9
/*     */     //   112: if_icmpne -> 477
/*     */     //   115: goto -> 129
/*     */     //   118: ldc2_w 4450451916835084227
/*     */     //   121: lload #4
/*     */     //   123: <illegal opcode> w : (Ljava/lang/RuntimeException;JJ)Ljava/lang/RuntimeException;
/*     */     //   128: athrow
/*     */     //   129: iload #8
/*     */     //   131: aload #6
/*     */     //   133: ifnonnull -> 478
/*     */     //   136: goto -> 150
/*     */     //   139: ldc2_w 4450451916835084227
/*     */     //   142: lload #4
/*     */     //   144: <illegal opcode> w : (Ljava/lang/RuntimeException;JJ)Ljava/lang/RuntimeException;
/*     */     //   149: athrow
/*     */     //   150: bipush #127
/*     */     //   152: goto -> 166
/*     */     //   155: ldc2_w 4450451916835084227
/*     */     //   158: lload #4
/*     */     //   160: <illegal opcode> w : (Ljava/lang/RuntimeException;JJ)Ljava/lang/RuntimeException;
/*     */     //   165: athrow
/*     */     //   166: lload #4
/*     */     //   168: lconst_0
/*     */     //   169: lcmp
/*     */     //   170: ifle -> 180
/*     */     //   173: if_icmpge -> 477
/*     */     //   176: iload #8
/*     */     //   178: bipush #48
/*     */     //   180: aload #6
/*     */     //   182: lload #4
/*     */     //   184: lconst_0
/*     */     //   185: lcmp
/*     */     //   186: ifle -> 290
/*     */     //   189: ifnonnull -> 288
/*     */     //   192: goto -> 206
/*     */     //   195: ldc2_w 4450451916835084227
/*     */     //   198: lload #4
/*     */     //   200: <illegal opcode> w : (Ljava/lang/RuntimeException;JJ)Ljava/lang/RuntimeException;
/*     */     //   205: athrow
/*     */     //   206: lload #4
/*     */     //   208: lconst_0
/*     */     //   209: lcmp
/*     */     //   210: iflt -> 274
/*     */     //   213: if_icmplt -> 270
/*     */     //   216: goto -> 230
/*     */     //   219: ldc2_w 4450451916835084227
/*     */     //   222: lload #4
/*     */     //   224: <illegal opcode> w : (Ljava/lang/RuntimeException;JJ)Ljava/lang/RuntimeException;
/*     */     //   229: athrow
/*     */     //   230: iload #8
/*     */     //   232: aload #6
/*     */     //   234: ifnonnull -> 478
/*     */     //   237: goto -> 251
/*     */     //   240: ldc2_w 4450451916835084227
/*     */     //   243: lload #4
/*     */     //   245: <illegal opcode> w : (Ljava/lang/RuntimeException;JJ)Ljava/lang/RuntimeException;
/*     */     //   250: athrow
/*     */     //   251: bipush #57
/*     */     //   253: if_icmple -> 477
/*     */     //   256: goto -> 270
/*     */     //   259: ldc2_w 4450451916835084227
/*     */     //   262: lload #4
/*     */     //   264: <illegal opcode> w : (Ljava/lang/RuntimeException;JJ)Ljava/lang/RuntimeException;
/*     */     //   269: athrow
/*     */     //   270: iload #8
/*     */     //   272: bipush #97
/*     */     //   274: goto -> 288
/*     */     //   277: ldc2_w 4450451916835084227
/*     */     //   280: lload #4
/*     */     //   282: <illegal opcode> w : (Ljava/lang/RuntimeException;JJ)Ljava/lang/RuntimeException;
/*     */     //   287: athrow
/*     */     //   288: aload #6
/*     */     //   290: lload #4
/*     */     //   292: lconst_0
/*     */     //   293: lcmp
/*     */     //   294: iflt -> 377
/*     */     //   297: ifnonnull -> 375
/*     */     //   300: if_icmplt -> 357
/*     */     //   303: goto -> 317
/*     */     //   306: ldc2_w 4450451916835084227
/*     */     //   309: lload #4
/*     */     //   311: <illegal opcode> w : (Ljava/lang/RuntimeException;JJ)Ljava/lang/RuntimeException;
/*     */     //   316: athrow
/*     */     //   317: iload #8
/*     */     //   319: aload #6
/*     */     //   321: ifnonnull -> 478
/*     */     //   324: goto -> 338
/*     */     //   327: ldc2_w 4450451916835084227
/*     */     //   330: lload #4
/*     */     //   332: <illegal opcode> w : (Ljava/lang/RuntimeException;JJ)Ljava/lang/RuntimeException;
/*     */     //   337: athrow
/*     */     //   338: bipush #122
/*     */     //   340: if_icmple -> 477
/*     */     //   343: goto -> 357
/*     */     //   346: ldc2_w 4450451916835084227
/*     */     //   349: lload #4
/*     */     //   351: <illegal opcode> w : (Ljava/lang/RuntimeException;JJ)Ljava/lang/RuntimeException;
/*     */     //   356: athrow
/*     */     //   357: iload #8
/*     */     //   359: bipush #65
/*     */     //   361: goto -> 375
/*     */     //   364: ldc2_w 4450451916835084227
/*     */     //   367: lload #4
/*     */     //   369: <illegal opcode> w : (Ljava/lang/RuntimeException;JJ)Ljava/lang/RuntimeException;
/*     */     //   374: athrow
/*     */     //   375: aload #6
/*     */     //   377: ifnonnull -> 474
/*     */     //   380: if_icmplt -> 437
/*     */     //   383: goto -> 397
/*     */     //   386: ldc2_w 4450451916835084227
/*     */     //   389: lload #4
/*     */     //   391: <illegal opcode> w : (Ljava/lang/RuntimeException;JJ)Ljava/lang/RuntimeException;
/*     */     //   396: athrow
/*     */     //   397: iload #8
/*     */     //   399: aload #6
/*     */     //   401: ifnonnull -> 478
/*     */     //   404: goto -> 418
/*     */     //   407: ldc2_w 4450451916835084227
/*     */     //   410: lload #4
/*     */     //   412: <illegal opcode> w : (Ljava/lang/RuntimeException;JJ)Ljava/lang/RuntimeException;
/*     */     //   417: athrow
/*     */     //   418: bipush #90
/*     */     //   420: if_icmple -> 477
/*     */     //   423: goto -> 437
/*     */     //   426: ldc2_w 4450451916835084227
/*     */     //   429: lload #4
/*     */     //   431: <illegal opcode> w : (Ljava/lang/RuntimeException;JJ)Ljava/lang/RuntimeException;
/*     */     //   436: athrow
/*     */     //   437: iload #8
/*     */     //   439: aload #6
/*     */     //   441: ifnonnull -> 478
/*     */     //   444: goto -> 458
/*     */     //   447: ldc2_w 4450451916835084227
/*     */     //   450: lload #4
/*     */     //   452: <illegal opcode> w : (Ljava/lang/RuntimeException;JJ)Ljava/lang/RuntimeException;
/*     */     //   457: athrow
/*     */     //   458: bipush #58
/*     */     //   460: goto -> 474
/*     */     //   463: ldc2_w 4450451916835084227
/*     */     //   466: lload #4
/*     */     //   468: <illegal opcode> w : (Ljava/lang/RuntimeException;JJ)Ljava/lang/RuntimeException;
/*     */     //   473: athrow
/*     */     //   474: if_icmpne -> 481
/*     */     //   477: iconst_1
/*     */     //   478: goto -> 482
/*     */     //   481: iconst_0
/*     */     //   482: istore #9
/*     */     //   484: iload #9
/*     */     //   486: iload_3
/*     */     //   487: aload #6
/*     */     //   489: ifnonnull -> 510
/*     */     //   492: ifne -> 513
/*     */     //   495: goto -> 509
/*     */     //   498: ldc2_w 4450451916835084227
/*     */     //   501: lload #4
/*     */     //   503: <illegal opcode> w : (Ljava/lang/RuntimeException;JJ)Ljava/lang/RuntimeException;
/*     */     //   508: athrow
/*     */     //   509: iconst_1
/*     */     //   510: goto -> 514
/*     */     //   513: iconst_0
/*     */     //   514: if_icmpne -> 531
/*     */     //   517: iload #7
/*     */     //   519: ireturn
/*     */     //   520: ldc2_w 4450451916835084227
/*     */     //   523: lload #4
/*     */     //   525: <illegal opcode> w : (Ljava/lang/RuntimeException;JJ)Ljava/lang/RuntimeException;
/*     */     //   530: athrow
/*     */     //   531: iinc #7, 1
/*     */     //   534: aload #6
/*     */     //   536: ifnull -> 23
/*     */     //   539: iload_2
/*     */     //   540: ireturn
/*     */     // Line number table:
/*     */     //   Java source line number -> byte code offset
/*     */     //   #19	-> 18
/*     */     //   #52	-> 29
/*     */     //   #145	-> 37
/*     */     //   #198	-> 484
/*     */     //   #64	-> 531
/*     */     //   #241	-> 539
/*     */     // Exception table:
/*     */     //   from	to	target	type
/*     */     //   37	58	61	java/lang/NullPointerException
/*     */     //   44	75	78	java/lang/NullPointerException
/*     */     //   72	96	99	java/lang/NullPointerException
/*     */     //   89	115	118	java/lang/NullPointerException
/*     */     //   110	136	139	java/lang/NullPointerException
/*     */     //   129	152	155	java/lang/NullPointerException
/*     */     //   166	192	195	java/lang/NullPointerException
/*     */     //   176	216	219	java/lang/NullPointerException
/*     */     //   206	237	240	java/lang/NullPointerException
/*     */     //   230	256	259	java/lang/NullPointerException
/*     */     //   251	274	277	java/lang/NullPointerException
/*     */     //   288	303	306	java/lang/NullPointerException
/*     */     //   300	324	327	java/lang/NullPointerException
/*     */     //   317	343	346	java/lang/NullPointerException
/*     */     //   338	361	364	java/lang/NullPointerException
/*     */     //   375	383	386	java/lang/NullPointerException
/*     */     //   380	404	407	java/lang/NullPointerException
/*     */     //   397	423	426	java/lang/NullPointerException
/*     */     //   418	444	447	java/lang/NullPointerException
/*     */     //   437	460	463	java/lang/NullPointerException
/*     */     //   484	495	498	java/lang/NullPointerException
/*     */     //   514	520	520	java/lang/NullPointerException
/*     */   }
/*     */   public static List a(int paramInt1, l6 paraml6, char paramChar, J paramJ, int paramInt2) {
/*     */     // Byte code:
/*     */     //   0: iload_0
/*     */     //   1: i2l
/*     */     //   2: bipush #32
/*     */     //   4: lshl
/*     */     //   5: iload_2
/*     */     //   6: i2l
/*     */     //   7: bipush #48
/*     */     //   9: lshl
/*     */     //   10: bipush #32
/*     */     //   12: lushr
/*     */     //   13: lor
/*     */     //   14: iload #4
/*     */     //   16: i2l
/*     */     //   17: bipush #48
/*     */     //   19: lshl
/*     */     //   20: bipush #48
/*     */     //   22: lushr
/*     */     //   23: lor
/*     */     //   24: getstatic me/konsolas/aac/c2.n : J
/*     */     //   27: lxor
/*     */     //   28: lstore #5
/*     */     //   30: lload #5
/*     */     //   32: dup2
/*     */     //   33: ldc2_w 127298593934940
/*     */     //   36: lxor
/*     */     //   37: lstore #7
/*     */     //   39: dup2
/*     */     //   40: ldc2_w 106227709831031
/*     */     //   43: lxor
/*     */     //   44: lstore #9
/*     */     //   46: pop2
/*     */     //   47: aload_3
/*     */     //   48: sipush #18235
/*     */     //   51: ldc2_w 891129241228075421
/*     */     //   54: lload #5
/*     */     //   56: lxor
/*     */     //   57: <illegal opcode> v : (IJ)Ljava/lang/String;
/*     */     //   62: lload #9
/*     */     //   64: invokevirtual a : (Ljava/lang/String;J)Ljava/util/List;
/*     */     //   67: astore #12
/*     */     //   69: aconst_null
/*     */     //   70: astore #13
/*     */     //   72: ldc2_w -3944619493932938877
/*     */     //   75: lload #5
/*     */     //   77: <illegal opcode> w : (JJ)[Lme/konsolas/aac/aN;
/*     */     //   82: iconst_0
/*     */     //   83: istore #14
/*     */     //   85: astore #11
/*     */     //   87: aload #12
/*     */     //   89: invokeinterface size : ()I
/*     */     //   94: istore #15
/*     */     //   96: iload #14
/*     */     //   98: iload #15
/*     */     //   100: if_icmpge -> 212
/*     */     //   103: lload #7
/*     */     //   105: aload_1
/*     */     //   106: aload #12
/*     */     //   108: iload #14
/*     */     //   110: invokeinterface get : (I)Ljava/lang/Object;
/*     */     //   115: checkcast java/lang/String
/*     */     //   118: invokestatic a : (JLme/konsolas/aac/l6;Ljava/lang/String;)Lme/konsolas/aac/c2;
/*     */     //   121: astore #16
/*     */     //   123: aload #11
/*     */     //   125: ifnonnull -> 263
/*     */     //   128: aload #16
/*     */     //   130: ifnonnull -> 161
/*     */     //   133: goto -> 147
/*     */     //   136: ldc2_w -3930733530382949517
/*     */     //   139: lload #5
/*     */     //   141: <illegal opcode> w : (Ljava/lang/RuntimeException;JJ)Ljava/lang/RuntimeException;
/*     */     //   146: athrow
/*     */     //   147: goto -> 204
/*     */     //   150: ldc2_w -3930733530382949517
/*     */     //   153: lload #5
/*     */     //   155: <illegal opcode> w : (Ljava/lang/RuntimeException;JJ)Ljava/lang/RuntimeException;
/*     */     //   160: athrow
/*     */     //   161: aload #13
/*     */     //   163: aload #11
/*     */     //   165: ifnonnull -> 196
/*     */     //   168: ifnonnull -> 194
/*     */     //   171: goto -> 185
/*     */     //   174: ldc2_w -3930733530382949517
/*     */     //   177: lload #5
/*     */     //   179: <illegal opcode> w : (Ljava/lang/RuntimeException;JJ)Ljava/lang/RuntimeException;
/*     */     //   184: athrow
/*     */     //   185: new java/util/ArrayList
/*     */     //   188: dup
/*     */     //   189: invokespecial <init> : ()V
/*     */     //   192: astore #13
/*     */     //   194: aload #13
/*     */     //   196: aload #16
/*     */     //   198: invokeinterface add : (Ljava/lang/Object;)Z
/*     */     //   203: pop
/*     */     //   204: iinc #14, 1
/*     */     //   207: aload #11
/*     */     //   209: ifnull -> 96
/*     */     //   212: aload #13
/*     */     //   214: iload #4
/*     */     //   216: ifle -> 266
/*     */     //   219: aload #11
/*     */     //   221: ifnonnull -> 260
/*     */     //   224: ifnull -> 263
/*     */     //   227: goto -> 241
/*     */     //   230: ldc2_w -3930733530382949517
/*     */     //   233: lload #5
/*     */     //   235: <illegal opcode> w : (Ljava/lang/RuntimeException;JJ)Ljava/lang/RuntimeException;
/*     */     //   240: athrow
/*     */     //   241: aload #13
/*     */     //   243: invokestatic unmodifiableList : (Ljava/util/List;)Ljava/util/List;
/*     */     //   246: goto -> 260
/*     */     //   249: ldc2_w -3930733530382949517
/*     */     //   252: lload #5
/*     */     //   254: <illegal opcode> w : (Ljava/lang/RuntimeException;JJ)Ljava/lang/RuntimeException;
/*     */     //   259: athrow
/*     */     //   260: goto -> 266
/*     */     //   263: invokestatic emptyList : ()Ljava/util/List;
/*     */     //   266: areturn
/*     */     // Line number table:
/*     */     //   Java source line number -> byte code offset
/*     */     //   #26	-> 47
/*     */     //   #210	-> 69
/*     */     //   #233	-> 82
/*     */     //   #37	-> 103
/*     */     //   #196	-> 123
/*     */     //   #218	-> 161
/*     */     //   #229	-> 194
/*     */     //   #62	-> 204
/*     */     //   #69	-> 212
/*     */     //   #10	-> 241
/*     */     //   #101	-> 263
/*     */     //   #67	-> 266
/*     */     // Exception table:
/*     */     //   from	to	target	type
/*     */     //   123	133	136	java/lang/NullPointerException
/*     */     //   128	150	150	java/lang/NullPointerException
/*     */     //   161	171	174	java/lang/NullPointerException
/*     */     //   212	227	230	java/lang/NullPointerException
/*     */     //   224	246	249	java/lang/NullPointerException
/*     */   }
/*     */   private static long a(long paramLong, String paramString) {
/*     */     // Byte code:
/*     */     //   0: getstatic me/konsolas/aac/c2.n : J
/*     */     //   3: lload_0
/*     */     //   4: lxor
/*     */     //   5: lstore_0
/*     */     //   6: ldc2_w 8482730439515338106
/*     */     //   9: lload_0
/*     */     //   10: <illegal opcode> w : (JJ)[Lme/konsolas/aac/aN;
/*     */     //   15: astore_3
/*     */     //   16: aload_2
/*     */     //   17: invokestatic parseLong : (Ljava/lang/String;)J
/*     */     //   20: lstore #4
/*     */     //   22: lload #4
/*     */     //   24: aload_3
/*     */     //   25: ifnonnull -> 62
/*     */     //   28: lconst_0
/*     */     //   29: lcmp
/*     */     //   30: ifgt -> 65
/*     */     //   33: goto -> 46
/*     */     //   36: ldc2_w 8469698264469413770
/*     */     //   39: lload_0
/*     */     //   40: <illegal opcode> w : (Ljava/lang/RuntimeException;JJ)Ljava/lang/RuntimeException;
/*     */     //   45: athrow
/*     */     //   46: ldc2_w -9223372036854775808
/*     */     //   49: goto -> 62
/*     */     //   52: ldc2_w 8469698264469413770
/*     */     //   55: lload_0
/*     */     //   56: <illegal opcode> w : (Ljava/lang/RuntimeException;JJ)Ljava/lang/RuntimeException;
/*     */     //   61: athrow
/*     */     //   62: goto -> 67
/*     */     //   65: lload #4
/*     */     //   67: lreturn
/*     */     //   68: astore #4
/*     */     //   70: aload_2
/*     */     //   71: sipush #16670
/*     */     //   74: ldc2_w 3276079384212527959
/*     */     //   77: lload_0
/*     */     //   78: lxor
/*     */     //   79: <illegal opcode> v : (IJ)Ljava/lang/String;
/*     */     //   84: invokevirtual matches : (Ljava/lang/String;)Z
/*     */     //   87: lload_0
/*     */     //   88: lconst_0
/*     */     //   89: lcmp
/*     */     //   90: iflt -> 155
/*     */     //   93: aload_3
/*     */     //   94: ifnonnull -> 155
/*     */     //   97: ifeq -> 178
/*     */     //   100: goto -> 113
/*     */     //   103: ldc2_w 8469698264469413770
/*     */     //   106: lload_0
/*     */     //   107: <illegal opcode> w : (Ljava/lang/RuntimeException;JJ)Ljava/lang/RuntimeException;
/*     */     //   112: athrow
/*     */     //   113: aload_2
/*     */     //   114: ldc_w '䄔群'
/*     */     //   117: invokevirtual toCharArray : ()[C
/*     */     //   120: dup
/*     */     //   121: dup
/*     */     //   122: iconst_0
/*     */     //   123: dup_x1
/*     */     //   124: caload
/*     */     //   125: sipush #20595
/*     */     //   128: ixor
/*     */     //   129: i2c
/*     */     //   130: castore
/*     */     //   131: sipush #3929
/*     */     //   134: iconst_0
/*     */     //   135: iconst_0
/*     */     //   136: invokestatic G : (Ljava/lang/Object;SZB)Ljava/lang/String;
/*     */     //   139: invokevirtual startsWith : (Ljava/lang/String;)Z
/*     */     //   142: goto -> 155
/*     */     //   145: ldc2_w 8469698264469413770
/*     */     //   148: lload_0
/*     */     //   149: <illegal opcode> w : (Ljava/lang/RuntimeException;JJ)Ljava/lang/RuntimeException;
/*     */     //   154: athrow
/*     */     //   155: ifeq -> 174
/*     */     //   158: ldc2_w -9223372036854775808
/*     */     //   161: goto -> 177
/*     */     //   164: ldc2_w 8469698264469413770
/*     */     //   167: lload_0
/*     */     //   168: <illegal opcode> w : (Ljava/lang/RuntimeException;JJ)Ljava/lang/RuntimeException;
/*     */     //   173: athrow
/*     */     //   174: ldc2_w 9223372036854775807
/*     */     //   177: lreturn
/*     */     //   178: aload #4
/*     */     //   180: athrow
/*     */     // Line number table:
/*     */     //   Java source line number -> byte code offset
/*     */     //   #49	-> 16
/*     */     //   #59	-> 22
/*     */     //   #249	-> 68
/*     */     //   #203	-> 70
/*     */     //   #43	-> 113
/*     */     //   #154	-> 178
/*     */     // Exception table:
/*     */     //   from	to	target	type
/*     */     //   16	67	68	java/lang/NumberFormatException
/*     */     //   22	33	36	java/lang/NumberFormatException
/*     */     //   28	49	52	java/lang/NumberFormatException
/*     */     //   70	100	103	java/lang/NumberFormatException
/*     */     //   97	142	145	java/lang/NumberFormatException
/*     */     //   155	164	164	java/lang/NumberFormatException
/*     */   }
/*     */   public String b() {
/*  55 */     return this.l;
/*     */   }
/*     */ 
/*     */ 
/*     */ 
/*     */ 
/*     */ 
/*     */ 
/*     */ 
/*     */ 
/*     */ 
/*     */   
/*     */   static {
/*     */     byte b1;
/*     */     long l;
/*  70 */     for (n = nc.a(-3012296695933467912L, -402183021732307414L, MethodHandles.lookup().lookupClass()).a(33963525279241L), l = n ^ 0x33A873FCAD6FL, q = new HashMap<>(13), "텠棐솙嬃౳◤媲湞頢䡉韾켎욁齼ᡐ譾⒢".toCharArray()[12] = (char)("텠棐솙嬃౳◤媲湞頢䡉韾켎욁齼ᡐ譾⒢".toCharArray()[12] ^ 0x64F3), "ᯱ㓭㤡㇉".toCharArray()[0] = (char)("ᯱ㓭㤡㇉".toCharArray()[0] ^ 0x2C30), (new byte[8])[0] = (byte)(int)(l >>> 56L), b1 = 1; b1 < 8; ) { (new byte[8])[b1] = (byte)(int)(l << b1 * 8 >>> 56L); b1++; }  Cipher cipher; (cipher = Cipher.getInstance(a0$cc.G("텠棐솙嬃౳◤媲湞頢䡉韾켎욁齼ᡐ譾⒢".toCharArray(), (short)4121, true, (byte)2))).init(2, SecretKeyFactory.getInstance(a0$cc.G("ᯱ㓭㤡㇉".toCharArray(), (short)12559, true, (byte)3)).generateSecret(new DESKeySpec(new byte[8])), new IvParameterSpec(new byte[8])); String[] arrayOfString = new String[21]; boolean bool = false; "Ꞝ슟≫潯셮扜똂啷᧍楩✖ᬞ輐琇꺢莺䤙﬙ꊿ䈣풿쨬֒苈ꌫ㦁↼ု൮늸?枥潡늫된蒄ዏ鿳攳琅谀槻ㆯ≑旐ᣭꏿ䩌㫤㈺흓蝟놙ꈦ茰蟯戻ག묫ʣ?퀿嚈㐦뿞๟핺목੆鬀㺢䅔᝝ᙯ⑹蹼︧鈤༹䃉䧫싑촺뗓紅딤ﵬ焏䫃庶毳꺄낑Ԓ췍ꍟㅆ㓯钏椼栽雊ꮩ㶷슲瀳깿躉蕛關䛞ﲰ맥죀瀄?竀털䯟?ᾍ臕붭餇衡뇌슊땧꣰뇖ꯄ苓맟䓼ㅃ㐓䜳녚峇茽哌钧ᦗ쒋슉닄汉鄞婳࿗밲쨦?ꉕ풵⸭?➩禼䬁뮝魳邳괽䗁嚞ሆ柱豽⡚⃃侠먅懂沘덳똔䧧ꌺ꼧䫐붼䂐夞᯳脧㰎寧䩟藝鿝ἄ鰵㌹댐宕ᡪꘑ뀐炊߂ﴕ蛿㧤ꥷ蝆垠㭙㿿⟫﷟밂▫§쓴摸䉸蠔ﻆㆾ뢀ꇑച䡶傶鎎ꥱ껿좙뤶ℬល卪獗ூ딌㓃?ܯ㴈＾銿싻鸷想쒀୰혚솪ু崹꣯귵ⴳ╇砨쀡฼虴䯢ᾰⰳฏ꣣溶⊹ᧃ貞ນ贪㮔昒멒췋䄩关෽䶩䛚피ꊞ坌䂤?윪䧑眦煄믽刜咛竻蔔ᒜ㛪뻵ጪ䣈坉Ω膙絽Ɗ過⌦ꍃ瓲趝ࢅᩋꞅ㌦꾷๶눫뭥疄׎췅?ꦂ㯹ཤ脂㩁㩝ꬃ㇠懀鲟ᢺ⺠毡쿤쥯釅섬磻ݗ˄챃ꎺ䊈몲᦭侔잻᜸๑ㅺ㼇俓晳较뼨챏跮ਜ਼⪌࿎厜玹꟧?닰撇熉굁嵿䡚⸻㇡ᯩ榊ﺓ⭱낽ꗐ?辊糫✕욾ஊ֎荧ྣ⃪㞑閵⯘∊왴큅좘ᆿի坮큪??䐴搾膅ଫ䊪碡楅ꁟ箟䁳꺊㪐煞琉螟칕䙴꒒㸋瓪烠蹢蘫튛쎇鲘僶턞⛎䘃⻹‖渤髙옘睯૩취逡ﱓ⸮.ꞕ粴뛡㱻ዐሃ晕邞௙歇즅꜕贻ጯ숌쎤䶩熎퍞⬇栙ꏛ͡謞匴蔳?ᗫ魎䦣ꤲㅥ⁈톮௨九⓪吉銸쫦ﴔ礫鬉Ⰿᛋ刚悙ᇘ咽⎗ꛑ麊롷﫬鵉擘{敯镬⣻蚳뮼䔇滩ﱐ꾿ཥ嘘㵳疓䱫惖☈쭞ꚫ膰犜윚꧆䴬ｾຯ㱯鿱嶹脣諙剈魛ዮ廫裏礧쿟癣ࠩឿ죟齅놕碰꫞र鎚༝┥矂镻಍☭a髫Ⰹ籮间䙽쒙祴⅕쉉廳簟ⳑ抣".toCharArray()[41] = (char)("Ꞝ슟≫潯셮扜똂啷᧍楩✖ᬞ輐琇꺢莺䤙﬙ꊿ䈣풿쨬֒苈ꌫ㦁↼ု൮늸?枥潡늫된蒄ዏ鿳攳琅谀槻ㆯ≑旐ᣭꏿ䩌㫤㈺흓蝟놙ꈦ茰蟯戻ག묫ʣ?퀿嚈㐦뿞๟핺목੆鬀㺢䅔᝝ᙯ⑹蹼︧鈤༹䃉䧫싑촺뗓紅딤ﵬ焏䫃庶毳꺄낑Ԓ췍ꍟㅆ㓯钏椼栽雊ꮩ㶷슲瀳깿躉蕛關䛞ﲰ맥죀瀄?竀털䯟?ᾍ臕붭餇衡뇌슊땧꣰뇖ꯄ苓맟䓼ㅃ㐓䜳녚峇茽哌钧ᦗ쒋슉닄汉鄞婳࿗밲쨦?ꉕ풵⸭?➩禼䬁뮝魳邳괽䗁嚞ሆ柱豽⡚⃃侠먅懂沘덳똔䧧ꌺ꼧䫐붼䂐夞᯳脧㰎寧䩟藝鿝ἄ鰵㌹댐宕ᡪꘑ뀐炊߂ﴕ蛿㧤ꥷ蝆垠㭙㿿⟫﷟밂▫§쓴摸䉸蠔ﻆㆾ뢀ꇑച䡶傶鎎ꥱ껿좙뤶ℬល卪獗ூ딌㓃?ܯ㴈＾銿싻鸷想쒀୰혚솪ু崹꣯귵ⴳ╇砨쀡฼虴䯢ᾰⰳฏ꣣溶⊹ᧃ貞ນ贪㮔昒멒췋䄩关෽䶩䛚피ꊞ坌䂤?윪䧑眦煄믽刜咛竻蔔ᒜ㛪뻵ጪ䣈坉Ω膙絽Ɗ過⌦ꍃ瓲趝ࢅᩋꞅ㌦꾷๶눫뭥疄׎췅?ꦂ㯹ཤ脂㩁㩝ꬃ㇠懀鲟ᢺ⺠毡쿤쥯釅섬磻ݗ˄챃ꎺ䊈몲᦭侔잻᜸๑ㅺ㼇俓晳较뼨챏跮ਜ਼⪌࿎厜玹꟧?닰撇熉굁嵿䡚⸻㇡ᯩ榊ﺓ⭱낽ꗐ?辊糫✕욾ஊ֎荧ྣ⃪㞑閵⯘∊왴큅좘ᆿի坮큪??䐴搾膅ଫ䊪碡楅ꁟ箟䁳꺊㪐煞琉螟칕䙴꒒㸋瓪烠蹢蘫튛쎇鲘僶턞⛎䘃⻹‖渤髙옘睯૩취逡ﱓ⸮.ꞕ粴뛡㱻ዐሃ晕邞௙歇즅꜕贻ጯ숌쎤䶩熎퍞⬇栙ꏛ͡謞匴蔳?ᗫ魎䦣ꤲㅥ⁈톮௨九⓪吉銸쫦ﴔ礫鬉Ⰿᛋ刚悙ᇘ咽⎗ꛑ麊롷﫬鵉擘{敯镬⣻蚳뮼䔇滩ﱐ꾿ཥ嘘㵳疓䱫惖☈쭞ꚫ膰犜윚꧆䴬ｾຯ㱯鿱嶹脣諙剈魛ዮ廫裏礧쿟癣ࠩឿ죟齅놕碰꫞र鎚༝┥矂镻಍☭a髫Ⰹ籮间䙽쒙祴⅕쉉廳簟ⳑ抣".toCharArray()[41] ^ 0x52B7); String str; int i = (str = a0$cc.G("Ꞝ슟≫潯셮扜똂啷᧍楩✖ᬞ輐琇꺢莺䤙﬙ꊿ䈣풿쨬֒苈ꌫ㦁↼ု൮늸?枥潡늫된蒄ዏ鿳攳琅谀槻ㆯ≑旐ᣭꏿ䩌㫤㈺흓蝟놙ꈦ茰蟯戻ག묫ʣ?퀿嚈㐦뿞๟핺목੆鬀㺢䅔᝝ᙯ⑹蹼︧鈤༹䃉䧫싑촺뗓紅딤ﵬ焏䫃庶毳꺄낑Ԓ췍ꍟㅆ㓯钏椼栽雊ꮩ㶷슲瀳깿躉蕛關䛞ﲰ맥죀瀄?竀털䯟?ᾍ臕붭餇衡뇌슊땧꣰뇖ꯄ苓맟䓼ㅃ㐓䜳녚峇茽哌钧ᦗ쒋슉닄汉鄞婳࿗밲쨦?ꉕ풵⸭?➩禼䬁뮝魳邳괽䗁嚞ሆ柱豽⡚⃃侠먅懂沘덳똔䧧ꌺ꼧䫐붼䂐夞᯳脧㰎寧䩟藝鿝ἄ鰵㌹댐宕ᡪꘑ뀐炊߂ﴕ蛿㧤ꥷ蝆垠㭙㿿⟫﷟밂▫§쓴摸䉸蠔ﻆㆾ뢀ꇑച䡶傶鎎ꥱ껿좙뤶ℬល卪獗ூ딌㓃?ܯ㴈＾銿싻鸷想쒀୰혚솪ু崹꣯귵ⴳ╇砨쀡฼虴䯢ᾰⰳฏ꣣溶⊹ᧃ貞ນ贪㮔昒멒췋䄩关෽䶩䛚피ꊞ坌䂤?윪䧑眦煄믽刜咛竻蔔ᒜ㛪뻵ጪ䣈坉Ω膙絽Ɗ過⌦ꍃ瓲趝ࢅᩋꞅ㌦꾷๶눫뭥疄׎췅?ꦂ㯹ཤ脂㩁㩝ꬃ㇠懀鲟ᢺ⺠毡쿤쥯釅섬磻ݗ˄챃ꎺ䊈몲᦭侔잻᜸๑ㅺ㼇俓晳较뼨챏跮ਜ਼⪌࿎厜玹꟧?닰撇熉굁嵿䡚⸻㇡ᯩ榊ﺓ⭱낽ꗐ?辊糫✕욾ஊ֎荧ྣ⃪㞑閵⯘∊왴큅좘ᆿի坮큪??䐴搾膅ଫ䊪碡楅ꁟ箟䁳꺊㪐煞琉螟칕䙴꒒㸋瓪烠蹢蘫튛쎇鲘僶턞⛎䘃⻹‖渤髙옘睯૩취逡ﱓ⸮.ꞕ粴뛡㱻ዐሃ晕邞௙歇즅꜕贻ጯ숌쎤䶩熎퍞⬇栙ꏛ͡謞匴蔳?ᗫ魎䦣ꤲㅥ⁈톮௨九⓪吉銸쫦ﴔ礫鬉Ⰿᛋ刚悙ᇘ咽⎗ꛑ麊롷﫬鵉擘{敯镬⣻蚳뮼䔇滩ﱐ꾿ཥ嘘㵳疓䱫惖☈쭞ꚫ膰犜윚꧆䴬ｾຯ㱯鿱嶹脣諙剈魛ዮ廫裏礧쿟癣ࠩឿ죟齅놕碰꫞र鎚༝┥矂镻಍☭a髫Ⰹ籮间䙽쒙祴⅕쉉廳簟ⳑ抣".toCharArray(), (short)10214, false, (byte)2)).length(); byte b2 = 40; byte b = -1;
/*     */     while (true);
/*     */   }
/*     */ 
/*     */ 
/*     */ 
/*     */   
/*     */   public boolean c() {
/*  78 */     return this.d;
/*     */   }
/*     */ 
/*     */ 
/*     */ 
/*     */   
/*     */   public int hashCode() {
/*     */     // Byte code:
/*     */     //   0: getstatic me/konsolas/aac/c2.n : J
/*     */     //   3: ldc2_w 125866475299625
/*     */     //   6: lxor
/*     */     //   7: lstore_1
/*     */     //   8: bipush #17
/*     */     //   10: istore #4
/*     */     //   12: ldc2_w -1431133276305953567
/*     */     //   15: lload_1
/*     */     //   16: <illegal opcode> w : (JJ)[Lme/konsolas/aac/aN;
/*     */     //   21: bipush #31
/*     */     //   23: iload #4
/*     */     //   25: imul
/*     */     //   26: aload_0
/*     */     //   27: getfield c : Ljava/lang/String;
/*     */     //   30: invokevirtual hashCode : ()I
/*     */     //   33: iadd
/*     */     //   34: istore #4
/*     */     //   36: astore_3
/*     */     //   37: bipush #31
/*     */     //   39: iload #4
/*     */     //   41: imul
/*     */     //   42: aload_0
/*     */     //   43: getfield l : Ljava/lang/String;
/*     */     //   46: invokevirtual hashCode : ()I
/*     */     //   49: iadd
/*     */     //   50: istore #4
/*     */     //   52: bipush #31
/*     */     //   54: iload #4
/*     */     //   56: imul
/*     */     //   57: aload_0
/*     */     //   58: getfield j : Ljava/lang/String;
/*     */     //   61: invokevirtual hashCode : ()I
/*     */     //   64: iadd
/*     */     //   65: istore #4
/*     */     //   67: bipush #31
/*     */     //   69: iload #4
/*     */     //   71: imul
/*     */     //   72: aload_0
/*     */     //   73: getfield e : Ljava/lang/String;
/*     */     //   76: invokevirtual hashCode : ()I
/*     */     //   79: iadd
/*     */     //   80: istore #4
/*     */     //   82: bipush #31
/*     */     //   84: iload #4
/*     */     //   86: imul
/*     */     //   87: aload_0
/*     */     //   88: getfield f : J
/*     */     //   91: aload_0
/*     */     //   92: getfield f : J
/*     */     //   95: bipush #32
/*     */     //   97: lushr
/*     */     //   98: lxor
/*     */     //   99: l2i
/*     */     //   100: iadd
/*     */     //   101: istore #4
/*     */     //   103: bipush #31
/*     */     //   105: iload #4
/*     */     //   107: imul
/*     */     //   108: aload_0
/*     */     //   109: getfield g : Z
/*     */     //   112: aload_3
/*     */     //   113: ifnonnull -> 133
/*     */     //   116: ifeq -> 136
/*     */     //   119: goto -> 132
/*     */     //   122: ldc2_w -1436287605694036463
/*     */     //   125: lload_1
/*     */     //   126: <illegal opcode> w : (Ljava/lang/RuntimeException;JJ)Ljava/lang/RuntimeException;
/*     */     //   131: athrow
/*     */     //   132: iconst_0
/*     */     //   133: goto -> 137
/*     */     //   136: iconst_1
/*     */     //   137: iadd
/*     */     //   138: istore #4
/*     */     //   140: bipush #31
/*     */     //   142: iload #4
/*     */     //   144: imul
/*     */     //   145: aload_0
/*     */     //   146: getfield a : Z
/*     */     //   149: aload_3
/*     */     //   150: ifnonnull -> 170
/*     */     //   153: ifeq -> 173
/*     */     //   156: goto -> 169
/*     */     //   159: ldc2_w -1436287605694036463
/*     */     //   162: lload_1
/*     */     //   163: <illegal opcode> w : (Ljava/lang/RuntimeException;JJ)Ljava/lang/RuntimeException;
/*     */     //   168: athrow
/*     */     //   169: iconst_0
/*     */     //   170: goto -> 174
/*     */     //   173: iconst_1
/*     */     //   174: iadd
/*     */     //   175: istore #4
/*     */     //   177: bipush #31
/*     */     //   179: iload #4
/*     */     //   181: imul
/*     */     //   182: aload_0
/*     */     //   183: getfield h : Z
/*     */     //   186: aload_3
/*     */     //   187: ifnonnull -> 207
/*     */     //   190: ifeq -> 210
/*     */     //   193: goto -> 206
/*     */     //   196: ldc2_w -1436287605694036463
/*     */     //   199: lload_1
/*     */     //   200: <illegal opcode> w : (Ljava/lang/RuntimeException;JJ)Ljava/lang/RuntimeException;
/*     */     //   205: athrow
/*     */     //   206: iconst_0
/*     */     //   207: goto -> 211
/*     */     //   210: iconst_1
/*     */     //   211: iadd
/*     */     //   212: istore #4
/*     */     //   214: bipush #31
/*     */     //   216: iload #4
/*     */     //   218: imul
/*     */     //   219: aload_0
/*     */     //   220: getfield d : Z
/*     */     //   223: aload_3
/*     */     //   224: ifnonnull -> 244
/*     */     //   227: ifeq -> 247
/*     */     //   230: goto -> 243
/*     */     //   233: ldc2_w -1436287605694036463
/*     */     //   236: lload_1
/*     */     //   237: <illegal opcode> w : (Ljava/lang/RuntimeException;JJ)Ljava/lang/RuntimeException;
/*     */     //   242: athrow
/*     */     //   243: iconst_0
/*     */     //   244: goto -> 248
/*     */     //   247: iconst_1
/*     */     //   248: iadd
/*     */     //   249: istore #4
/*     */     //   251: iload #4
/*     */     //   253: ireturn
/*     */     // Line number table:
/*     */     //   Java source line number -> byte code offset
/*     */     //   #83	-> 8
/*     */     //   #116	-> 21
/*     */     //   #47	-> 37
/*     */     //   #166	-> 52
/*     */     //   #35	-> 67
/*     */     //   #8	-> 82
/*     */     //   #57	-> 103
/*     */     //   #187	-> 140
/*     */     //   #1	-> 177
/*     */     //   #224	-> 214
/*     */     //   #217	-> 251
/*     */     // Exception table:
/*     */     //   from	to	target	type
/*     */     //   103	119	122	java/lang/NullPointerException
/*     */     //   140	156	159	java/lang/NullPointerException
/*     */     //   177	193	196	java/lang/NullPointerException
/*     */     //   214	230	233	java/lang/NullPointerException
/*     */   }
/*     */ 
/*     */ 
/*     */   
/*     */   public String d() {
/*  91 */     return this.c;
/*     */   }
/*     */ 
/*     */ 
/*     */ 
/*     */ 
/*     */   
/*     */   private static long a(String paramString, int paramInt1, long paramLong, int paramInt2) {
/*     */     // Byte code:
/*     */     //   0: getstatic me/konsolas/aac/c2.n : J
/*     */     //   3: lload_2
/*     */     //   4: lxor
/*     */     //   5: lstore_2
/*     */     //   6: lload_2
/*     */     //   7: dup2
/*     */     //   8: ldc2_w 89592037624837
/*     */     //   11: lxor
/*     */     //   12: lstore #5
/*     */     //   14: pop2
/*     */     //   15: aload_0
/*     */     //   16: iload_1
/*     */     //   17: iload #4
/*     */     //   19: iconst_0
/*     */     //   20: lload #5
/*     */     //   22: invokestatic a : (Ljava/lang/String;IIZJ)I
/*     */     //   25: istore_1
/*     */     //   26: iconst_m1
/*     */     //   27: istore #8
/*     */     //   29: ldc2_w -4748223015942635816
/*     */     //   32: lload_2
/*     */     //   33: <illegal opcode> w : (JJ)[Lme/konsolas/aac/aN;
/*     */     //   38: iconst_m1
/*     */     //   39: istore #9
/*     */     //   41: iconst_m1
/*     */     //   42: istore #10
/*     */     //   44: iconst_m1
/*     */     //   45: istore #11
/*     */     //   47: astore #7
/*     */     //   49: iconst_m1
/*     */     //   50: istore #12
/*     */     //   52: iconst_m1
/*     */     //   53: istore #13
/*     */     //   55: getstatic me/konsolas/aac/c2.b : Ljava/util/regex/Pattern;
/*     */     //   58: aload_0
/*     */     //   59: invokevirtual matcher : (Ljava/lang/CharSequence;)Ljava/util/regex/Matcher;
/*     */     //   62: astore #14
/*     */     //   64: iload_1
/*     */     //   65: iload #4
/*     */     //   67: if_icmpge -> 592
/*     */     //   70: aload_0
/*     */     //   71: iload_1
/*     */     //   72: iconst_1
/*     */     //   73: iadd
/*     */     //   74: iload #4
/*     */     //   76: iconst_1
/*     */     //   77: lload #5
/*     */     //   79: invokestatic a : (Ljava/lang/String;IIZJ)I
/*     */     //   82: istore #15
/*     */     //   84: aload #14
/*     */     //   86: iload_1
/*     */     //   87: iload #15
/*     */     //   89: invokevirtual region : (II)Ljava/util/regex/Matcher;
/*     */     //   92: pop
/*     */     //   93: iload #8
/*     */     //   95: iconst_m1
/*     */     //   96: lload_2
/*     */     //   97: lconst_0
/*     */     //   98: lcmp
/*     */     //   99: iflt -> 620
/*     */     //   102: aload #7
/*     */     //   104: ifnonnull -> 620
/*     */     //   107: aload #7
/*     */     //   109: lload_2
/*     */     //   110: lconst_0
/*     */     //   111: lcmp
/*     */     //   112: ifle -> 254
/*     */     //   115: ifnonnull -> 252
/*     */     //   118: goto -> 131
/*     */     //   121: ldc2_w -4744485562576874456
/*     */     //   124: lload_2
/*     */     //   125: <illegal opcode> w : (Ljava/lang/RuntimeException;JJ)Ljava/lang/RuntimeException;
/*     */     //   130: athrow
/*     */     //   131: if_icmpne -> 236
/*     */     //   134: goto -> 147
/*     */     //   137: ldc2_w -4744485562576874456
/*     */     //   140: lload_2
/*     */     //   141: <illegal opcode> w : (Ljava/lang/RuntimeException;JJ)Ljava/lang/RuntimeException;
/*     */     //   146: athrow
/*     */     //   147: aload #14
/*     */     //   149: getstatic me/konsolas/aac/c2.b : Ljava/util/regex/Pattern;
/*     */     //   152: invokevirtual usePattern : (Ljava/util/regex/Pattern;)Ljava/util/regex/Matcher;
/*     */     //   155: invokevirtual matches : ()Z
/*     */     //   158: aload #7
/*     */     //   160: ifnonnull -> 251
/*     */     //   163: goto -> 176
/*     */     //   166: ldc2_w -4744485562576874456
/*     */     //   169: lload_2
/*     */     //   170: <illegal opcode> w : (Ljava/lang/RuntimeException;JJ)Ljava/lang/RuntimeException;
/*     */     //   175: athrow
/*     */     //   176: ifeq -> 236
/*     */     //   179: goto -> 192
/*     */     //   182: ldc2_w -4744485562576874456
/*     */     //   185: lload_2
/*     */     //   186: <illegal opcode> w : (Ljava/lang/RuntimeException;JJ)Ljava/lang/RuntimeException;
/*     */     //   191: athrow
/*     */     //   192: aload #14
/*     */     //   194: iconst_1
/*     */     //   195: invokevirtual group : (I)Ljava/lang/String;
/*     */     //   198: invokestatic parseInt : (Ljava/lang/String;)I
/*     */     //   201: istore #8
/*     */     //   203: aload #14
/*     */     //   205: iconst_2
/*     */     //   206: invokevirtual group : (I)Ljava/lang/String;
/*     */     //   209: invokestatic parseInt : (Ljava/lang/String;)I
/*     */     //   212: istore #9
/*     */     //   214: aload #14
/*     */     //   216: iconst_3
/*     */     //   217: invokevirtual group : (I)Ljava/lang/String;
/*     */     //   220: lload_2
/*     */     //   221: lconst_0
/*     */     //   222: lcmp
/*     */     //   223: iflt -> 574
/*     */     //   226: invokestatic parseInt : (Ljava/lang/String;)I
/*     */     //   229: istore #10
/*     */     //   231: aload #7
/*     */     //   233: ifnull -> 573
/*     */     //   236: iload #11
/*     */     //   238: goto -> 251
/*     */     //   241: ldc2_w -4744485562576874456
/*     */     //   244: lload_2
/*     */     //   245: <illegal opcode> w : (Ljava/lang/RuntimeException;JJ)Ljava/lang/RuntimeException;
/*     */     //   250: athrow
/*     */     //   251: iconst_m1
/*     */     //   252: aload #7
/*     */     //   254: lload_2
/*     */     //   255: lconst_0
/*     */     //   256: lcmp
/*     */     //   257: iflt -> 370
/*     */     //   260: ifnonnull -> 362
/*     */     //   263: if_icmpne -> 346
/*     */     //   266: goto -> 279
/*     */     //   269: ldc2_w -4744485562576874456
/*     */     //   272: lload_2
/*     */     //   273: <illegal opcode> w : (Ljava/lang/RuntimeException;JJ)Ljava/lang/RuntimeException;
/*     */     //   278: athrow
/*     */     //   279: aload #14
/*     */     //   281: getstatic me/konsolas/aac/c2.m : Ljava/util/regex/Pattern;
/*     */     //   284: invokevirtual usePattern : (Ljava/util/regex/Pattern;)Ljava/util/regex/Matcher;
/*     */     //   287: invokevirtual matches : ()Z
/*     */     //   290: aload #7
/*     */     //   292: ifnonnull -> 361
/*     */     //   295: goto -> 308
/*     */     //   298: ldc2_w -4744485562576874456
/*     */     //   301: lload_2
/*     */     //   302: <illegal opcode> w : (Ljava/lang/RuntimeException;JJ)Ljava/lang/RuntimeException;
/*     */     //   307: athrow
/*     */     //   308: ifeq -> 346
/*     */     //   311: goto -> 324
/*     */     //   314: ldc2_w -4744485562576874456
/*     */     //   317: lload_2
/*     */     //   318: <illegal opcode> w : (Ljava/lang/RuntimeException;JJ)Ljava/lang/RuntimeException;
/*     */     //   323: athrow
/*     */     //   324: aload #14
/*     */     //   326: iconst_1
/*     */     //   327: invokevirtual group : (I)Ljava/lang/String;
/*     */     //   330: lload_2
/*     */     //   331: lconst_0
/*     */     //   332: lcmp
/*     */     //   333: ifle -> 574
/*     */     //   336: invokestatic parseInt : (Ljava/lang/String;)I
/*     */     //   339: istore #11
/*     */     //   341: aload #7
/*     */     //   343: ifnull -> 573
/*     */     //   346: iload #12
/*     */     //   348: goto -> 361
/*     */     //   351: ldc2_w -4744485562576874456
/*     */     //   354: lload_2
/*     */     //   355: <illegal opcode> w : (Ljava/lang/RuntimeException;JJ)Ljava/lang/RuntimeException;
/*     */     //   360: athrow
/*     */     //   361: iconst_m1
/*     */     //   362: lload_2
/*     */     //   363: lconst_0
/*     */     //   364: lcmp
/*     */     //   365: ifle -> 514
/*     */     //   368: aload #7
/*     */     //   370: ifnonnull -> 514
/*     */     //   373: if_icmpne -> 480
/*     */     //   376: goto -> 389
/*     */     //   379: ldc2_w -4744485562576874456
/*     */     //   382: lload_2
/*     */     //   383: <illegal opcode> w : (Ljava/lang/RuntimeException;JJ)Ljava/lang/RuntimeException;
/*     */     //   388: athrow
/*     */     //   389: aload #14
/*     */     //   391: getstatic me/konsolas/aac/c2.i : Ljava/util/regex/Pattern;
/*     */     //   394: invokevirtual usePattern : (Ljava/util/regex/Pattern;)Ljava/util/regex/Matcher;
/*     */     //   397: invokevirtual matches : ()Z
/*     */     //   400: aload #7
/*     */     //   402: lload_2
/*     */     //   403: lconst_0
/*     */     //   404: lcmp
/*     */     //   405: ifle -> 497
/*     */     //   408: ifnonnull -> 495
/*     */     //   411: goto -> 424
/*     */     //   414: ldc2_w -4744485562576874456
/*     */     //   417: lload_2
/*     */     //   418: <illegal opcode> w : (Ljava/lang/RuntimeException;JJ)Ljava/lang/RuntimeException;
/*     */     //   423: athrow
/*     */     //   424: ifeq -> 480
/*     */     //   427: goto -> 440
/*     */     //   430: ldc2_w -4744485562576874456
/*     */     //   433: lload_2
/*     */     //   434: <illegal opcode> w : (Ljava/lang/RuntimeException;JJ)Ljava/lang/RuntimeException;
/*     */     //   439: athrow
/*     */     //   440: aload #14
/*     */     //   442: iconst_1
/*     */     //   443: invokevirtual group : (I)Ljava/lang/String;
/*     */     //   446: getstatic java/util/Locale.US : Ljava/util/Locale;
/*     */     //   449: invokevirtual toLowerCase : (Ljava/util/Locale;)Ljava/lang/String;
/*     */     //   452: astore #16
/*     */     //   454: getstatic me/konsolas/aac/c2.i : Ljava/util/regex/Pattern;
/*     */     //   457: invokevirtual pattern : ()Ljava/lang/String;
/*     */     //   460: lload_2
/*     */     //   461: lconst_0
/*     */     //   462: lcmp
/*     */     //   463: iflt -> 574
/*     */     //   466: aload #16
/*     */     //   468: invokevirtual indexOf : (Ljava/lang/String;)I
/*     */     //   471: iconst_4
/*     */     //   472: idiv
/*     */     //   473: istore #12
/*     */     //   475: aload #7
/*     */     //   477: ifnull -> 573
/*     */     //   480: iload #13
/*     */     //   482: goto -> 495
/*     */     //   485: ldc2_w -4744485562576874456
/*     */     //   488: lload_2
/*     */     //   489: <illegal opcode> w : (Ljava/lang/RuntimeException;JJ)Ljava/lang/RuntimeException;
/*     */     //   494: athrow
/*     */     //   495: aload #7
/*     */     //   497: ifnonnull -> 586
/*     */     //   500: iconst_m1
/*     */     //   501: goto -> 514
/*     */     //   504: ldc2_w -4744485562576874456
/*     */     //   507: lload_2
/*     */     //   508: <illegal opcode> w : (Ljava/lang/RuntimeException;JJ)Ljava/lang/RuntimeException;
/*     */     //   513: athrow
/*     */     //   514: if_icmpne -> 573
/*     */     //   517: aload #14
/*     */     //   519: getstatic me/konsolas/aac/c2.k : Ljava/util/regex/Pattern;
/*     */     //   522: invokevirtual usePattern : (Ljava/util/regex/Pattern;)Ljava/util/regex/Matcher;
/*     */     //   525: invokevirtual matches : ()Z
/*     */     //   528: aload #7
/*     */     //   530: ifnonnull -> 586
/*     */     //   533: goto -> 546
/*     */     //   536: ldc2_w -4744485562576874456
/*     */     //   539: lload_2
/*     */     //   540: <illegal opcode> w : (Ljava/lang/RuntimeException;JJ)Ljava/lang/RuntimeException;
/*     */     //   545: athrow
/*     */     //   546: ifeq -> 573
/*     */     //   549: goto -> 562
/*     */     //   552: ldc2_w -4744485562576874456
/*     */     //   555: lload_2
/*     */     //   556: <illegal opcode> w : (Ljava/lang/RuntimeException;JJ)Ljava/lang/RuntimeException;
/*     */     //   561: athrow
/*     */     //   562: aload #14
/*     */     //   564: iconst_1
/*     */     //   565: invokevirtual group : (I)Ljava/lang/String;
/*     */     //   568: invokestatic parseInt : (Ljava/lang/String;)I
/*     */     //   571: istore #13
/*     */     //   573: aload_0
/*     */     //   574: iload #15
/*     */     //   576: iconst_1
/*     */     //   577: iadd
/*     */     //   578: iload #4
/*     */     //   580: iconst_0
/*     */     //   581: lload #5
/*     */     //   583: invokestatic a : (Ljava/lang/String;IIZJ)I
/*     */     //   586: istore_1
/*     */     //   587: aload #7
/*     */     //   589: ifnull -> 64
/*     */     //   592: iload #13
/*     */     //   594: aload #7
/*     */     //   596: lload_2
/*     */     //   597: lconst_0
/*     */     //   598: lcmp
/*     */     //   599: ifle -> 690
/*     */     //   602: ifnonnull -> 688
/*     */     //   605: bipush #70
/*     */     //   607: goto -> 620
/*     */     //   610: ldc2_w -4744485562576874456
/*     */     //   613: lload_2
/*     */     //   614: <illegal opcode> w : (Ljava/lang/RuntimeException;JJ)Ljava/lang/RuntimeException;
/*     */     //   619: athrow
/*     */     //   620: if_icmplt -> 686
/*     */     //   623: iload #13
/*     */     //   625: aload #7
/*     */     //   627: lload_2
/*     */     //   628: lconst_0
/*     */     //   629: lcmp
/*     */     //   630: ifle -> 690
/*     */     //   633: ifnonnull -> 688
/*     */     //   636: goto -> 649
/*     */     //   639: ldc2_w -4744485562576874456
/*     */     //   642: lload_2
/*     */     //   643: <illegal opcode> w : (Ljava/lang/RuntimeException;JJ)Ljava/lang/RuntimeException;
/*     */     //   648: athrow
/*     */     //   649: bipush #99
/*     */     //   651: if_icmpgt -> 686
/*     */     //   654: goto -> 667
/*     */     //   657: ldc2_w -4744485562576874456
/*     */     //   660: lload_2
/*     */     //   661: <illegal opcode> w : (Ljava/lang/RuntimeException;JJ)Ljava/lang/RuntimeException;
/*     */     //   666: athrow
/*     */     //   667: wide iinc #13 1900
/*     */     //   673: goto -> 686
/*     */     //   676: ldc2_w -4744485562576874456
/*     */     //   679: lload_2
/*     */     //   680: <illegal opcode> w : (Ljava/lang/RuntimeException;JJ)Ljava/lang/RuntimeException;
/*     */     //   685: athrow
/*     */     //   686: iload #13
/*     */     //   688: aload #7
/*     */     //   690: ifnonnull -> 761
/*     */     //   693: iflt -> 759
/*     */     //   696: goto -> 709
/*     */     //   699: ldc2_w -4744485562576874456
/*     */     //   702: lload_2
/*     */     //   703: <illegal opcode> w : (Ljava/lang/RuntimeException;JJ)Ljava/lang/RuntimeException;
/*     */     //   708: athrow
/*     */     //   709: iload #13
/*     */     //   711: bipush #69
/*     */     //   713: aload #7
/*     */     //   715: lload_2
/*     */     //   716: lconst_0
/*     */     //   717: lcmp
/*     */     //   718: ifle -> 766
/*     */     //   721: ifnonnull -> 764
/*     */     //   724: goto -> 737
/*     */     //   727: ldc2_w -4744485562576874456
/*     */     //   730: lload_2
/*     */     //   731: <illegal opcode> w : (Ljava/lang/RuntimeException;JJ)Ljava/lang/RuntimeException;
/*     */     //   736: athrow
/*     */     //   737: if_icmpgt -> 759
/*     */     //   740: goto -> 753
/*     */     //   743: ldc2_w -4744485562576874456
/*     */     //   746: lload_2
/*     */     //   747: <illegal opcode> w : (Ljava/lang/RuntimeException;JJ)Ljava/lang/RuntimeException;
/*     */     //   752: athrow
/*     */     //   753: wide iinc #13 2000
/*     */     //   759: iload #13
/*     */     //   761: sipush #1601
/*     */     //   764: aload #7
/*     */     //   766: lload_2
/*     */     //   767: lconst_0
/*     */     //   768: lcmp
/*     */     //   769: iflt -> 814
/*     */     //   772: ifnonnull -> 812
/*     */     //   775: if_icmpge -> 809
/*     */     //   778: goto -> 791
/*     */     //   781: ldc2_w -4744485562576874456
/*     */     //   784: lload_2
/*     */     //   785: <illegal opcode> w : (Ljava/lang/RuntimeException;JJ)Ljava/lang/RuntimeException;
/*     */     //   790: athrow
/*     */     //   791: new java/lang/IllegalArgumentException
/*     */     //   794: dup
/*     */     //   795: invokespecial <init> : ()V
/*     */     //   798: athrow
/*     */     //   799: ldc2_w -4744485562576874456
/*     */     //   802: lload_2
/*     */     //   803: <illegal opcode> w : (Ljava/lang/RuntimeException;JJ)Ljava/lang/RuntimeException;
/*     */     //   808: athrow
/*     */     //   809: iload #12
/*     */     //   811: iconst_m1
/*     */     //   812: aload #7
/*     */     //   814: lload_2
/*     */     //   815: lconst_0
/*     */     //   816: lcmp
/*     */     //   817: iflt -> 868
/*     */     //   820: ifnonnull -> 860
/*     */     //   823: if_icmpne -> 857
/*     */     //   826: goto -> 839
/*     */     //   829: ldc2_w -4744485562576874456
/*     */     //   832: lload_2
/*     */     //   833: <illegal opcode> w : (Ljava/lang/RuntimeException;JJ)Ljava/lang/RuntimeException;
/*     */     //   838: athrow
/*     */     //   839: new java/lang/IllegalArgumentException
/*     */     //   842: dup
/*     */     //   843: invokespecial <init> : ()V
/*     */     //   846: athrow
/*     */     //   847: ldc2_w -4744485562576874456
/*     */     //   850: lload_2
/*     */     //   851: <illegal opcode> w : (Ljava/lang/RuntimeException;JJ)Ljava/lang/RuntimeException;
/*     */     //   856: athrow
/*     */     //   857: iload #11
/*     */     //   859: iconst_1
/*     */     //   860: lload_2
/*     */     //   861: lconst_0
/*     */     //   862: lcmp
/*     */     //   863: iflt -> 928
/*     */     //   866: aload #7
/*     */     //   868: ifnonnull -> 928
/*     */     //   871: if_icmplt -> 931
/*     */     //   874: goto -> 887
/*     */     //   877: ldc2_w -4744485562576874456
/*     */     //   880: lload_2
/*     */     //   881: <illegal opcode> w : (Ljava/lang/RuntimeException;JJ)Ljava/lang/RuntimeException;
/*     */     //   886: athrow
/*     */     //   887: iload #11
/*     */     //   889: aload #7
/*     */     //   891: lload_2
/*     */     //   892: lconst_0
/*     */     //   893: lcmp
/*     */     //   894: ifle -> 953
/*     */     //   897: ifnonnull -> 951
/*     */     //   900: goto -> 913
/*     */     //   903: ldc2_w -4744485562576874456
/*     */     //   906: lload_2
/*     */     //   907: <illegal opcode> w : (Ljava/lang/RuntimeException;JJ)Ljava/lang/RuntimeException;
/*     */     //   912: athrow
/*     */     //   913: bipush #31
/*     */     //   915: goto -> 928
/*     */     //   918: ldc2_w -4744485562576874456
/*     */     //   921: lload_2
/*     */     //   922: <illegal opcode> w : (Ljava/lang/RuntimeException;JJ)Ljava/lang/RuntimeException;
/*     */     //   927: athrow
/*     */     //   928: if_icmple -> 949
/*     */     //   931: new java/lang/IllegalArgumentException
/*     */     //   934: dup
/*     */     //   935: invokespecial <init> : ()V
/*     */     //   938: athrow
/*     */     //   939: ldc2_w -4744485562576874456
/*     */     //   942: lload_2
/*     */     //   943: <illegal opcode> w : (Ljava/lang/RuntimeException;JJ)Ljava/lang/RuntimeException;
/*     */     //   948: athrow
/*     */     //   949: iload #8
/*     */     //   951: aload #7
/*     */     //   953: lload_2
/*     */     //   954: lconst_0
/*     */     //   955: lcmp
/*     */     //   956: ifle -> 982
/*     */     //   959: ifnonnull -> 980
/*     */     //   962: iflt -> 1009
/*     */     //   965: goto -> 978
/*     */     //   968: ldc2_w -4744485562576874456
/*     */     //   971: lload_2
/*     */     //   972: <illegal opcode> w : (Ljava/lang/RuntimeException;JJ)Ljava/lang/RuntimeException;
/*     */     //   977: athrow
/*     */     //   978: iload #8
/*     */     //   980: aload #7
/*     */     //   982: lload_2
/*     */     //   983: lconst_0
/*     */     //   984: lcmp
/*     */     //   985: ifle -> 1031
/*     */     //   988: ifnonnull -> 1029
/*     */     //   991: bipush #23
/*     */     //   993: if_icmple -> 1027
/*     */     //   996: goto -> 1009
/*     */     //   999: ldc2_w -4744485562576874456
/*     */     //   1002: lload_2
/*     */     //   1003: <illegal opcode> w : (Ljava/lang/RuntimeException;JJ)Ljava/lang/RuntimeException;
/*     */     //   1008: athrow
/*     */     //   1009: new java/lang/IllegalArgumentException
/*     */     //   1012: dup
/*     */     //   1013: invokespecial <init> : ()V
/*     */     //   1016: athrow
/*     */     //   1017: ldc2_w -4744485562576874456
/*     */     //   1020: lload_2
/*     */     //   1021: <illegal opcode> w : (Ljava/lang/RuntimeException;JJ)Ljava/lang/RuntimeException;
/*     */     //   1026: athrow
/*     */     //   1027: iload #9
/*     */     //   1029: aload #7
/*     */     //   1031: lload_2
/*     */     //   1032: lconst_0
/*     */     //   1033: lcmp
/*     */     //   1034: iflt -> 1060
/*     */     //   1037: ifnonnull -> 1058
/*     */     //   1040: iflt -> 1087
/*     */     //   1043: goto -> 1056
/*     */     //   1046: ldc2_w -4744485562576874456
/*     */     //   1049: lload_2
/*     */     //   1050: <illegal opcode> w : (Ljava/lang/RuntimeException;JJ)Ljava/lang/RuntimeException;
/*     */     //   1055: athrow
/*     */     //   1056: iload #9
/*     */     //   1058: aload #7
/*     */     //   1060: lload_2
/*     */     //   1061: lconst_0
/*     */     //   1062: lcmp
/*     */     //   1063: ifle -> 1115
/*     */     //   1066: ifnonnull -> 1107
/*     */     //   1069: bipush #59
/*     */     //   1071: if_icmple -> 1105
/*     */     //   1074: goto -> 1087
/*     */     //   1077: ldc2_w -4744485562576874456
/*     */     //   1080: lload_2
/*     */     //   1081: <illegal opcode> w : (Ljava/lang/RuntimeException;JJ)Ljava/lang/RuntimeException;
/*     */     //   1086: athrow
/*     */     //   1087: new java/lang/IllegalArgumentException
/*     */     //   1090: dup
/*     */     //   1091: invokespecial <init> : ()V
/*     */     //   1094: athrow
/*     */     //   1095: ldc2_w -4744485562576874456
/*     */     //   1098: lload_2
/*     */     //   1099: <illegal opcode> w : (Ljava/lang/RuntimeException;JJ)Ljava/lang/RuntimeException;
/*     */     //   1104: athrow
/*     */     //   1105: iload #10
/*     */     //   1107: lload_2
/*     */     //   1108: lconst_0
/*     */     //   1109: lcmp
/*     */     //   1110: ifle -> 1136
/*     */     //   1113: aload #7
/*     */     //   1115: ifnonnull -> 1136
/*     */     //   1118: iflt -> 1141
/*     */     //   1121: goto -> 1134
/*     */     //   1124: ldc2_w -4744485562576874456
/*     */     //   1127: lload_2
/*     */     //   1128: <illegal opcode> w : (Ljava/lang/RuntimeException;JJ)Ljava/lang/RuntimeException;
/*     */     //   1133: athrow
/*     */     //   1134: iload #10
/*     */     //   1136: bipush #59
/*     */     //   1138: if_icmple -> 1159
/*     */     //   1141: new java/lang/IllegalArgumentException
/*     */     //   1144: dup
/*     */     //   1145: invokespecial <init> : ()V
/*     */     //   1148: athrow
/*     */     //   1149: ldc2_w -4744485562576874456
/*     */     //   1152: lload_2
/*     */     //   1153: <illegal opcode> w : (Ljava/lang/RuntimeException;JJ)Ljava/lang/RuntimeException;
/*     */     //   1158: athrow
/*     */     //   1159: new java/util/GregorianCalendar
/*     */     //   1162: dup
/*     */     //   1163: getstatic me/konsolas/aac/eO.e : Ljava/util/TimeZone;
/*     */     //   1166: invokespecial <init> : (Ljava/util/TimeZone;)V
/*     */     //   1169: astore #15
/*     */     //   1171: aload #15
/*     */     //   1173: iconst_0
/*     */     //   1174: invokevirtual setLenient : (Z)V
/*     */     //   1177: aload #15
/*     */     //   1179: iconst_1
/*     */     //   1180: iload #13
/*     */     //   1182: invokevirtual set : (II)V
/*     */     //   1185: aload #15
/*     */     //   1187: iconst_2
/*     */     //   1188: iload #12
/*     */     //   1190: iconst_1
/*     */     //   1191: isub
/*     */     //   1192: invokevirtual set : (II)V
/*     */     //   1195: aload #15
/*     */     //   1197: iconst_5
/*     */     //   1198: iload #11
/*     */     //   1200: invokevirtual set : (II)V
/*     */     //   1203: aload #15
/*     */     //   1205: bipush #11
/*     */     //   1207: iload #8
/*     */     //   1209: invokevirtual set : (II)V
/*     */     //   1212: aload #15
/*     */     //   1214: bipush #12
/*     */     //   1216: iload #9
/*     */     //   1218: invokevirtual set : (II)V
/*     */     //   1221: aload #15
/*     */     //   1223: bipush #13
/*     */     //   1225: iload #10
/*     */     //   1227: invokevirtual set : (II)V
/*     */     //   1230: aload #15
/*     */     //   1232: bipush #14
/*     */     //   1234: iconst_0
/*     */     //   1235: invokevirtual set : (II)V
/*     */     //   1238: aload #15
/*     */     //   1240: invokevirtual getTimeInMillis : ()J
/*     */     //   1243: lreturn
/*     */     // Line number table:
/*     */     //   Java source line number -> byte code offset
/*     */     //   #95	-> 15
/*     */     //   #21	-> 26
/*     */     //   #182	-> 38
/*     */     //   #77	-> 41
/*     */     //   #162	-> 44
/*     */     //   #92	-> 49
/*     */     //   #250	-> 52
/*     */     //   #30	-> 55
/*     */     //   #212	-> 64
/*     */     //   #207	-> 70
/*     */     //   #237	-> 84
/*     */     //   #44	-> 93
/*     */     //   #40	-> 192
/*     */     //   #227	-> 203
/*     */     //   #180	-> 214
/*     */     //   #142	-> 236
/*     */     //   #130	-> 324
/*     */     //   #192	-> 346
/*     */     //   #115	-> 440
/*     */     //   #66	-> 454
/*     */     //   #45	-> 475
/*     */     //   #194	-> 562
/*     */     //   #226	-> 573
/*     */     //   #152	-> 587
/*     */     //   #240	-> 592
/*     */     //   #74	-> 686
/*     */     //   #18	-> 759
/*     */     //   #160	-> 809
/*     */     //   #4	-> 857
/*     */     //   #105	-> 949
/*     */     //   #147	-> 1027
/*     */     //   #104	-> 1105
/*     */     //   #148	-> 1159
/*     */     //   #117	-> 1171
/*     */     //   #99	-> 1177
/*     */     //   #157	-> 1185
/*     */     //   #48	-> 1195
/*     */     //   #214	-> 1203
/*     */     //   #155	-> 1212
/*     */     //   #24	-> 1221
/*     */     //   #80	-> 1230
/*     */     //   #60	-> 1238
/*     */     // Exception table:
/*     */     //   from	to	target	type
/*     */     //   84	118	121	java/lang/NullPointerException
/*     */     //   107	134	137	java/lang/NullPointerException
/*     */     //   131	163	166	java/lang/NullPointerException
/*     */     //   147	179	182	java/lang/NullPointerException
/*     */     //   231	238	241	java/lang/NullPointerException
/*     */     //   252	266	269	java/lang/NullPointerException
/*     */     //   263	295	298	java/lang/NullPointerException
/*     */     //   279	311	314	java/lang/NullPointerException
/*     */     //   341	348	351	java/lang/NullPointerException
/*     */     //   362	376	379	java/lang/NullPointerException
/*     */     //   373	411	414	java/lang/NullPointerException
/*     */     //   389	427	430	java/lang/NullPointerException
/*     */     //   475	482	485	java/lang/NullPointerException
/*     */     //   495	501	504	java/lang/NullPointerException
/*     */     //   514	533	536	java/lang/NullPointerException
/*     */     //   517	549	552	java/lang/NullPointerException
/*     */     //   592	607	610	java/lang/NullPointerException
/*     */     //   620	636	639	java/lang/NullPointerException
/*     */     //   623	654	657	java/lang/NullPointerException
/*     */     //   649	673	676	java/lang/NullPointerException
/*     */     //   688	696	699	java/lang/NullPointerException
/*     */     //   693	724	727	java/lang/NullPointerException
/*     */     //   709	740	743	java/lang/NullPointerException
/*     */     //   764	778	781	java/lang/NullPointerException
/*     */     //   775	799	799	java/lang/NullPointerException
/*     */     //   812	826	829	java/lang/NullPointerException
/*     */     //   823	847	847	java/lang/NullPointerException
/*     */     //   860	874	877	java/lang/NullPointerException
/*     */     //   871	900	903	java/lang/NullPointerException
/*     */     //   887	915	918	java/lang/NullPointerException
/*     */     //   928	939	939	java/lang/NullPointerException
/*     */     //   951	965	968	java/lang/NullPointerException
/*     */     //   980	996	999	java/lang/NullPointerException
/*     */     //   991	1017	1017	java/lang/NullPointerException
/*     */     //   1029	1043	1046	java/lang/NullPointerException
/*     */     //   1058	1074	1077	java/lang/NullPointerException
/*     */     //   1069	1095	1095	java/lang/NullPointerException
/*     */     //   1107	1121	1124	java/lang/NullPointerException
/*     */     //   1136	1149	1149	java/lang/NullPointerException
/*     */   }
/*     */ 
/*     */ 
/*     */ 
/*     */ 
/*     */   
/*     */   c2(long paramLong, bN parambN) {
/*     */     // Byte code:
/*     */     //   0: getstatic me/konsolas/aac/c2.n : J
/*     */     //   3: lload_1
/*     */     //   4: lxor
/*     */     //   5: lstore_1
/*     */     //   6: ldc2_w 2449621565720568124
/*     */     //   9: lload_1
/*     */     //   10: <illegal opcode> w : (JJ)[Lme/konsolas/aac/aN;
/*     */     //   15: aload_0
/*     */     //   16: invokespecial <init> : ()V
/*     */     //   19: astore #4
/*     */     //   21: aload_3
/*     */     //   22: getfield h : Ljava/lang/String;
/*     */     //   25: aload #4
/*     */     //   27: ifnonnull -> 81
/*     */     //   30: ifnonnull -> 77
/*     */     //   33: goto -> 46
/*     */     //   36: ldc2_w 2435341304980065228
/*     */     //   39: lload_1
/*     */     //   40: <illegal opcode> w : (Ljava/lang/RuntimeException;JJ)Ljava/lang/RuntimeException;
/*     */     //   45: athrow
/*     */     //   46: new java/lang/NullPointerException
/*     */     //   49: dup
/*     */     //   50: sipush #4494
/*     */     //   53: ldc2_w 2993965245447364496
/*     */     //   56: lload_1
/*     */     //   57: lxor
/*     */     //   58: <illegal opcode> v : (IJ)Ljava/lang/String;
/*     */     //   63: invokespecial <init> : (Ljava/lang/String;)V
/*     */     //   66: athrow
/*     */     //   67: ldc2_w 2435341304980065228
/*     */     //   70: lload_1
/*     */     //   71: <illegal opcode> w : (Ljava/lang/RuntimeException;JJ)Ljava/lang/RuntimeException;
/*     */     //   76: athrow
/*     */     //   77: aload_3
/*     */     //   78: getfield e : Ljava/lang/String;
/*     */     //   81: lload_1
/*     */     //   82: lconst_0
/*     */     //   83: lcmp
/*     */     //   84: iflt -> 143
/*     */     //   87: aload #4
/*     */     //   89: ifnonnull -> 143
/*     */     //   92: ifnonnull -> 139
/*     */     //   95: goto -> 108
/*     */     //   98: ldc2_w 2435341304980065228
/*     */     //   101: lload_1
/*     */     //   102: <illegal opcode> w : (Ljava/lang/RuntimeException;JJ)Ljava/lang/RuntimeException;
/*     */     //   107: athrow
/*     */     //   108: new java/lang/NullPointerException
/*     */     //   111: dup
/*     */     //   112: sipush #27238
/*     */     //   115: ldc2_w 6509036552398447739
/*     */     //   118: lload_1
/*     */     //   119: lxor
/*     */     //   120: <illegal opcode> v : (IJ)Ljava/lang/String;
/*     */     //   125: invokespecial <init> : (Ljava/lang/String;)V
/*     */     //   128: athrow
/*     */     //   129: ldc2_w 2435341304980065228
/*     */     //   132: lload_1
/*     */     //   133: <illegal opcode> w : (Ljava/lang/RuntimeException;JJ)Ljava/lang/RuntimeException;
/*     */     //   138: athrow
/*     */     //   139: aload_3
/*     */     //   140: getfield c : Ljava/lang/String;
/*     */     //   143: ifnonnull -> 177
/*     */     //   146: new java/lang/NullPointerException
/*     */     //   149: dup
/*     */     //   150: sipush #31730
/*     */     //   153: ldc2_w 1484005106703513056
/*     */     //   156: lload_1
/*     */     //   157: lxor
/*     */     //   158: <illegal opcode> v : (IJ)Ljava/lang/String;
/*     */     //   163: invokespecial <init> : (Ljava/lang/String;)V
/*     */     //   166: athrow
/*     */     //   167: ldc2_w 2435341304980065228
/*     */     //   170: lload_1
/*     */     //   171: <illegal opcode> w : (Ljava/lang/RuntimeException;JJ)Ljava/lang/RuntimeException;
/*     */     //   176: athrow
/*     */     //   177: aload_0
/*     */     //   178: aload_3
/*     */     //   179: getfield h : Ljava/lang/String;
/*     */     //   182: putfield c : Ljava/lang/String;
/*     */     //   185: aload_0
/*     */     //   186: aload_3
/*     */     //   187: getfield e : Ljava/lang/String;
/*     */     //   190: putfield l : Ljava/lang/String;
/*     */     //   193: aload_0
/*     */     //   194: aload_3
/*     */     //   195: getfield i : J
/*     */     //   198: putfield f : J
/*     */     //   201: aload_0
/*     */     //   202: aload_3
/*     */     //   203: getfield c : Ljava/lang/String;
/*     */     //   206: putfield j : Ljava/lang/String;
/*     */     //   209: aload_0
/*     */     //   210: aload_3
/*     */     //   211: getfield d : Ljava/lang/String;
/*     */     //   214: putfield e : Ljava/lang/String;
/*     */     //   217: aload_0
/*     */     //   218: aload_3
/*     */     //   219: getfield b : Z
/*     */     //   222: putfield g : Z
/*     */     //   225: aload_0
/*     */     //   226: aload_3
/*     */     //   227: getfield f : Z
/*     */     //   230: putfield a : Z
/*     */     //   233: aload_0
/*     */     //   234: aload_3
/*     */     //   235: getfield a : Z
/*     */     //   238: putfield h : Z
/*     */     //   241: aload_0
/*     */     //   242: aload_3
/*     */     //   243: getfield g : Z
/*     */     //   246: putfield d : Z
/*     */     //   249: return
/*     */     // Line number table:
/*     */     //   Java source line number -> byte code offset
/*     */     //   #119	-> 15
/*     */     //   #73	-> 21
/*     */     //   #38	-> 77
/*     */     //   #195	-> 139
/*     */     //   #225	-> 177
/*     */     //   #28	-> 185
/*     */     //   #110	-> 193
/*     */     //   #146	-> 201
/*     */     //   #75	-> 209
/*     */     //   #12	-> 217
/*     */     //   #161	-> 225
/*     */     //   #29	-> 233
/*     */     //   #230	-> 241
/*     */     //   #176	-> 249
/*     */     // Exception table:
/*     */     //   from	to	target	type
/*     */     //   21	33	36	java/lang/NullPointerException
/*     */     //   30	67	67	java/lang/NullPointerException
/*     */     //   81	95	98	java/lang/NullPointerException
/*     */     //   92	129	129	java/lang/NullPointerException
/*     */     //   143	167	167	java/lang/NullPointerException
/*     */   }
/*     */ 
/*     */ 
/*     */ 
/*     */ 
/*     */   
/*     */   private static boolean a(l6 paraml6, String paramString, long paramLong) {
/*     */     // Byte code:
/*     */     //   0: getstatic me/konsolas/aac/c2.n : J
/*     */     //   3: lload_2
/*     */     //   4: lxor
/*     */     //   5: lstore_2
/*     */     //   6: lload_2
/*     */     //   7: dup2
/*     */     //   8: ldc2_w 90319401451140
/*     */     //   11: lxor
/*     */     //   12: lstore #4
/*     */     //   14: pop2
/*     */     //   15: ldc2_w 1607731809057576589
/*     */     //   18: lload_2
/*     */     //   19: <illegal opcode> w : (JJ)[Lme/konsolas/aac/aN;
/*     */     //   24: aload_0
/*     */     //   25: lload #4
/*     */     //   27: invokevirtual l : (J)Ljava/lang/String;
/*     */     //   30: astore #7
/*     */     //   32: astore #6
/*     */     //   34: aload #7
/*     */     //   36: aload_1
/*     */     //   37: invokevirtual equals : (Ljava/lang/Object;)Z
/*     */     //   40: aload #6
/*     */     //   42: ifnonnull -> 79
/*     */     //   45: ifeq -> 73
/*     */     //   48: goto -> 61
/*     */     //   51: ldc2_w 1620469418452352125
/*     */     //   54: lload_2
/*     */     //   55: <illegal opcode> w : (Ljava/lang/RuntimeException;JJ)Ljava/lang/RuntimeException;
/*     */     //   60: athrow
/*     */     //   61: iconst_1
/*     */     //   62: ireturn
/*     */     //   63: ldc2_w 1620469418452352125
/*     */     //   66: lload_2
/*     */     //   67: <illegal opcode> w : (Ljava/lang/RuntimeException;JJ)Ljava/lang/RuntimeException;
/*     */     //   72: athrow
/*     */     //   73: aload #7
/*     */     //   75: aload_1
/*     */     //   76: invokevirtual startsWith : (Ljava/lang/String;)Z
/*     */     //   79: aload #6
/*     */     //   81: ifnonnull -> 225
/*     */     //   84: ifeq -> 224
/*     */     //   87: goto -> 100
/*     */     //   90: ldc2_w 1620469418452352125
/*     */     //   93: lload_2
/*     */     //   94: <illegal opcode> w : (Ljava/lang/RuntimeException;JJ)Ljava/lang/RuntimeException;
/*     */     //   99: athrow
/*     */     //   100: aload_1
/*     */     //   101: ldc '፬䰔'
/*     */     //   103: invokevirtual toCharArray : ()[C
/*     */     //   106: dup
/*     */     //   107: dup
/*     */     //   108: iconst_0
/*     */     //   109: dup_x1
/*     */     //   110: caload
/*     */     //   111: sipush #20612
/*     */     //   114: ixor
/*     */     //   115: i2c
/*     */     //   116: castore
/*     */     //   117: sipush #4882
/*     */     //   120: iconst_0
/*     */     //   121: iconst_1
/*     */     //   122: invokestatic X : (Ljava/lang/Object;SZZ)Ljava/lang/String;
/*     */     //   125: invokevirtual endsWith : (Ljava/lang/String;)Z
/*     */     //   128: aload #6
/*     */     //   130: lload_2
/*     */     //   131: lconst_0
/*     */     //   132: lcmp
/*     */     //   133: iflt -> 191
/*     */     //   136: ifnonnull -> 189
/*     */     //   139: goto -> 152
/*     */     //   142: ldc2_w 1620469418452352125
/*     */     //   145: lload_2
/*     */     //   146: <illegal opcode> w : (Ljava/lang/RuntimeException;JJ)Ljava/lang/RuntimeException;
/*     */     //   151: athrow
/*     */     //   152: ifeq -> 180
/*     */     //   155: goto -> 168
/*     */     //   158: ldc2_w 1620469418452352125
/*     */     //   161: lload_2
/*     */     //   162: <illegal opcode> w : (Ljava/lang/RuntimeException;JJ)Ljava/lang/RuntimeException;
/*     */     //   167: athrow
/*     */     //   168: iconst_1
/*     */     //   169: ireturn
/*     */     //   170: ldc2_w 1620469418452352125
/*     */     //   173: lload_2
/*     */     //   174: <illegal opcode> w : (Ljava/lang/RuntimeException;JJ)Ljava/lang/RuntimeException;
/*     */     //   179: athrow
/*     */     //   180: aload #7
/*     */     //   182: aload_1
/*     */     //   183: invokevirtual length : ()I
/*     */     //   186: invokevirtual charAt : (I)C
/*     */     //   189: aload #6
/*     */     //   191: ifnonnull -> 225
/*     */     //   194: bipush #47
/*     */     //   196: if_icmpne -> 224
/*     */     //   199: goto -> 212
/*     */     //   202: ldc2_w 1620469418452352125
/*     */     //   205: lload_2
/*     */     //   206: <illegal opcode> w : (Ljava/lang/RuntimeException;JJ)Ljava/lang/RuntimeException;
/*     */     //   211: athrow
/*     */     //   212: iconst_1
/*     */     //   213: ireturn
/*     */     //   214: ldc2_w 1620469418452352125
/*     */     //   217: lload_2
/*     */     //   218: <illegal opcode> w : (Ljava/lang/RuntimeException;JJ)Ljava/lang/RuntimeException;
/*     */     //   223: athrow
/*     */     //   224: iconst_0
/*     */     //   225: ireturn
/*     */     // Line number table:
/*     */     //   Java source line number -> byte code offset
/*     */     //   #120	-> 24
/*     */     //   #112	-> 34
/*     */     //   #50	-> 61
/*     */     //   #71	-> 73
/*     */     //   #204	-> 100
/*     */     //   #68	-> 180
/*     */     //   #34	-> 224
/*     */     // Exception table:
/*     */     //   from	to	target	type
/*     */     //   34	48	51	java/lang/NullPointerException
/*     */     //   45	63	63	java/lang/NullPointerException
/*     */     //   79	87	90	java/lang/NullPointerException
/*     */     //   84	139	142	java/lang/NullPointerException
/*     */     //   100	155	158	java/lang/NullPointerException
/*     */     //   152	170	170	java/lang/NullPointerException
/*     */     //   189	199	202	java/lang/NullPointerException
/*     */     //   194	214	214	java/lang/NullPointerException
/*     */   }
/*     */ 
/*     */ 
/*     */ 
/*     */   
/*     */   public String toString() {
/* 122 */     long l1 = n ^ 0x6491C25AE428L, l2 = l1 ^ 0x1A185635B57CL; return a(l2, false);
/*     */   }
/*     */   public String c() {
/* 125 */     return this.e;
/*     */   }
/*     */ 
/*     */ 
/*     */ 
/*     */ 
/*     */ 
/*     */ 
/*     */ 
/*     */ 
/*     */   
/*     */   public boolean a() {
/* 137 */     return this.h;
/*     */   }
/*     */ 
/*     */ 
/*     */ 
/*     */ 
/*     */   
/*     */   String a(long paramLong, boolean paramBoolean) {
/*     */     // Byte code:
/*     */     //   0: getstatic me/konsolas/aac/c2.n : J
/*     */     //   3: lload_1
/*     */     //   4: lxor
/*     */     //   5: lstore_1
/*     */     //   6: new java/lang/StringBuilder
/*     */     //   9: dup
/*     */     //   10: invokespecial <init> : ()V
/*     */     //   13: astore #5
/*     */     //   15: ldc2_w 5886441800212762994
/*     */     //   18: lload_1
/*     */     //   19: <illegal opcode> w : (JJ)[Lme/konsolas/aac/aN;
/*     */     //   24: aload #5
/*     */     //   26: aload_0
/*     */     //   27: getfield c : Ljava/lang/String;
/*     */     //   30: invokevirtual append : (Ljava/lang/String;)Ljava/lang/StringBuilder;
/*     */     //   33: pop
/*     */     //   34: astore #4
/*     */     //   36: aload #5
/*     */     //   38: bipush #61
/*     */     //   40: invokevirtual append : (C)Ljava/lang/StringBuilder;
/*     */     //   43: pop
/*     */     //   44: aload #5
/*     */     //   46: aload_0
/*     */     //   47: getfield l : Ljava/lang/String;
/*     */     //   50: invokevirtual append : (Ljava/lang/String;)Ljava/lang/StringBuilder;
/*     */     //   53: pop
/*     */     //   54: aload_0
/*     */     //   55: getfield h : Z
/*     */     //   58: aload #4
/*     */     //   60: ifnonnull -> 199
/*     */     //   63: ifeq -> 195
/*     */     //   66: goto -> 79
/*     */     //   69: ldc2_w 5873266173259561858
/*     */     //   72: lload_1
/*     */     //   73: <illegal opcode> w : (Ljava/lang/RuntimeException;JJ)Ljava/lang/RuntimeException;
/*     */     //   78: athrow
/*     */     //   79: lload_1
/*     */     //   80: lconst_0
/*     */     //   81: lcmp
/*     */     //   82: iflt -> 182
/*     */     //   85: aload_0
/*     */     //   86: getfield f : J
/*     */     //   89: ldc2_w -9223372036854775808
/*     */     //   92: lcmp
/*     */     //   93: ifne -> 146
/*     */     //   96: goto -> 109
/*     */     //   99: ldc2_w 5873266173259561858
/*     */     //   102: lload_1
/*     */     //   103: <illegal opcode> w : (Ljava/lang/RuntimeException;JJ)Ljava/lang/RuntimeException;
/*     */     //   108: athrow
/*     */     //   109: aload #5
/*     */     //   111: sipush #9484
/*     */     //   114: ldc2_w 1903395055493684046
/*     */     //   117: lload_1
/*     */     //   118: lxor
/*     */     //   119: <illegal opcode> v : (IJ)Ljava/lang/String;
/*     */     //   124: invokevirtual append : (Ljava/lang/String;)Ljava/lang/StringBuilder;
/*     */     //   127: pop
/*     */     //   128: aload #4
/*     */     //   130: ifnull -> 195
/*     */     //   133: goto -> 146
/*     */     //   136: ldc2_w 5873266173259561858
/*     */     //   139: lload_1
/*     */     //   140: <illegal opcode> w : (Ljava/lang/RuntimeException;JJ)Ljava/lang/RuntimeException;
/*     */     //   145: athrow
/*     */     //   146: aload #5
/*     */     //   148: sipush #26357
/*     */     //   151: ldc2_w 7161754956350478518
/*     */     //   154: lload_1
/*     */     //   155: lxor
/*     */     //   156: <illegal opcode> v : (IJ)Ljava/lang/String;
/*     */     //   161: invokevirtual append : (Ljava/lang/String;)Ljava/lang/StringBuilder;
/*     */     //   164: new java/util/Date
/*     */     //   167: dup
/*     */     //   168: aload_0
/*     */     //   169: getfield f : J
/*     */     //   172: invokespecial <init> : (J)V
/*     */     //   175: invokestatic a : (Ljava/util/Date;)Ljava/lang/String;
/*     */     //   178: invokevirtual append : (Ljava/lang/String;)Ljava/lang/StringBuilder;
/*     */     //   181: pop
/*     */     //   182: goto -> 195
/*     */     //   185: ldc2_w 5873266173259561858
/*     */     //   188: lload_1
/*     */     //   189: <illegal opcode> w : (Ljava/lang/RuntimeException;JJ)Ljava/lang/RuntimeException;
/*     */     //   194: athrow
/*     */     //   195: aload_0
/*     */     //   196: getfield d : Z
/*     */     //   199: aload #4
/*     */     //   201: lload_1
/*     */     //   202: lconst_0
/*     */     //   203: lcmp
/*     */     //   204: iflt -> 378
/*     */     //   207: ifnonnull -> 370
/*     */     //   210: ifne -> 340
/*     */     //   213: goto -> 226
/*     */     //   216: ldc2_w 5873266173259561858
/*     */     //   219: lload_1
/*     */     //   220: <illegal opcode> w : (Ljava/lang/RuntimeException;JJ)Ljava/lang/RuntimeException;
/*     */     //   225: athrow
/*     */     //   226: aload #5
/*     */     //   228: sipush #17791
/*     */     //   231: ldc2_w 8531094983843511085
/*     */     //   234: lload_1
/*     */     //   235: lxor
/*     */     //   236: <illegal opcode> v : (IJ)Ljava/lang/String;
/*     */     //   241: invokevirtual append : (Ljava/lang/String;)Ljava/lang/StringBuilder;
/*     */     //   244: aload #4
/*     */     //   246: ifnonnull -> 339
/*     */     //   249: goto -> 262
/*     */     //   252: ldc2_w 5873266173259561858
/*     */     //   255: lload_1
/*     */     //   256: <illegal opcode> w : (Ljava/lang/RuntimeException;JJ)Ljava/lang/RuntimeException;
/*     */     //   261: athrow
/*     */     //   262: lload_1
/*     */     //   263: lconst_0
/*     */     //   264: lcmp
/*     */     //   265: ifle -> 332
/*     */     //   268: pop
/*     */     //   269: iload_3
/*     */     //   270: ifeq -> 330
/*     */     //   273: goto -> 286
/*     */     //   276: ldc2_w 5873266173259561858
/*     */     //   279: lload_1
/*     */     //   280: <illegal opcode> w : (Ljava/lang/RuntimeException;JJ)Ljava/lang/RuntimeException;
/*     */     //   285: athrow
/*     */     //   286: aload #5
/*     */     //   288: ldc_w '놕৩'
/*     */     //   291: invokevirtual toCharArray : ()[C
/*     */     //   294: dup
/*     */     //   295: dup
/*     */     //   296: iconst_0
/*     */     //   297: dup_x1
/*     */     //   298: caload
/*     */     //   299: sipush #30936
/*     */     //   302: ixor
/*     */     //   303: i2c
/*     */     //   304: castore
/*     */     //   305: sipush #13451
/*     */     //   308: iconst_1
/*     */     //   309: iconst_1
/*     */     //   310: invokestatic G : (Ljava/lang/Object;SZB)Ljava/lang/String;
/*     */     //   313: invokevirtual append : (Ljava/lang/String;)Ljava/lang/StringBuilder;
/*     */     //   316: pop
/*     */     //   317: goto -> 330
/*     */     //   320: ldc2_w 5873266173259561858
/*     */     //   323: lload_1
/*     */     //   324: <illegal opcode> w : (Ljava/lang/RuntimeException;JJ)Ljava/lang/RuntimeException;
/*     */     //   329: athrow
/*     */     //   330: aload #5
/*     */     //   332: aload_0
/*     */     //   333: getfield j : Ljava/lang/String;
/*     */     //   336: invokevirtual append : (Ljava/lang/String;)Ljava/lang/StringBuilder;
/*     */     //   339: pop
/*     */     //   340: aload #5
/*     */     //   342: sipush #17398
/*     */     //   345: ldc2_w 9041080205849984438
/*     */     //   348: lload_1
/*     */     //   349: lxor
/*     */     //   350: <illegal opcode> v : (IJ)Ljava/lang/String;
/*     */     //   355: invokevirtual append : (Ljava/lang/String;)Ljava/lang/StringBuilder;
/*     */     //   358: aload_0
/*     */     //   359: getfield e : Ljava/lang/String;
/*     */     //   362: invokevirtual append : (Ljava/lang/String;)Ljava/lang/StringBuilder;
/*     */     //   365: pop
/*     */     //   366: aload_0
/*     */     //   367: getfield g : Z
/*     */     //   370: lload_1
/*     */     //   371: lconst_0
/*     */     //   372: lcmp
/*     */     //   373: iflt -> 433
/*     */     //   376: aload #4
/*     */     //   378: ifnonnull -> 433
/*     */     //   381: ifeq -> 429
/*     */     //   384: goto -> 397
/*     */     //   387: ldc2_w 5873266173259561858
/*     */     //   390: lload_1
/*     */     //   391: <illegal opcode> w : (Ljava/lang/RuntimeException;JJ)Ljava/lang/RuntimeException;
/*     */     //   396: athrow
/*     */     //   397: aload #5
/*     */     //   399: sipush #27720
/*     */     //   402: ldc2_w 6788826279994970653
/*     */     //   405: lload_1
/*     */     //   406: lxor
/*     */     //   407: <illegal opcode> v : (IJ)Ljava/lang/String;
/*     */     //   412: invokevirtual append : (Ljava/lang/String;)Ljava/lang/StringBuilder;
/*     */     //   415: pop
/*     */     //   416: goto -> 429
/*     */     //   419: ldc2_w 5873266173259561858
/*     */     //   422: lload_1
/*     */     //   423: <illegal opcode> w : (Ljava/lang/RuntimeException;JJ)Ljava/lang/RuntimeException;
/*     */     //   428: athrow
/*     */     //   429: aload_0
/*     */     //   430: getfield a : Z
/*     */     //   433: ifeq -> 468
/*     */     //   436: aload #5
/*     */     //   438: sipush #13961
/*     */     //   441: ldc2_w 398678385883121879
/*     */     //   444: lload_1
/*     */     //   445: lxor
/*     */     //   446: <illegal opcode> v : (IJ)Ljava/lang/String;
/*     */     //   451: invokevirtual append : (Ljava/lang/String;)Ljava/lang/StringBuilder;
/*     */     //   454: pop
/*     */     //   455: goto -> 468
/*     */     //   458: ldc2_w 5873266173259561858
/*     */     //   461: lload_1
/*     */     //   462: <illegal opcode> w : (Ljava/lang/RuntimeException;JJ)Ljava/lang/RuntimeException;
/*     */     //   467: athrow
/*     */     //   468: aload #5
/*     */     //   470: invokevirtual toString : ()Ljava/lang/String;
/*     */     //   473: areturn
/*     */     // Line number table:
/*     */     //   Java source line number -> byte code offset
/*     */     //   #140	-> 6
/*     */     //   #51	-> 24
/*     */     //   #184	-> 36
/*     */     //   #179	-> 44
/*     */     //   #90	-> 54
/*     */     //   #143	-> 79
/*     */     //   #201	-> 109
/*     */     //   #144	-> 146
/*     */     //   #27	-> 195
/*     */     //   #235	-> 226
/*     */     //   #113	-> 269
/*     */     //   #23	-> 286
/*     */     //   #205	-> 330
/*     */     //   #9	-> 340
/*     */     //   #124	-> 366
/*     */     //   #170	-> 397
/*     */     //   #153	-> 429
/*     */     //   #76	-> 436
/*     */     //   #111	-> 468
/*     */     // Exception table:
/*     */     //   from	to	target	type
/*     */     //   36	66	69	java/lang/NullPointerException
/*     */     //   63	96	99	java/lang/NullPointerException
/*     */     //   79	133	136	java/lang/NullPointerException
/*     */     //   109	182	185	java/lang/NullPointerException
/*     */     //   199	213	216	java/lang/NullPointerException
/*     */     //   210	249	252	java/lang/NullPointerException
/*     */     //   226	273	276	java/lang/NullPointerException
/*     */     //   262	317	320	java/lang/NullPointerException
/*     */     //   370	384	387	java/lang/NullPointerException
/*     */     //   381	416	419	java/lang/NullPointerException
/*     */     //   433	455	458	java/lang/NullPointerException
/*     */   }
/*     */ 
/*     */ 
/*     */ 
/*     */ 
/*     */   
/*     */   @Nullable
/*     */   static c2 a(long paramLong1, l6 paraml6, String paramString, long paramLong2) {
/*     */     // Byte code:
/*     */     //   0: getstatic me/konsolas/aac/c2.n : J
/*     */     //   3: lload #4
/*     */     //   5: lxor
/*     */     //   6: lstore #4
/*     */     //   8: lload #4
/*     */     //   10: dup2
/*     */     //   11: ldc2_w 103114594170367
/*     */     //   14: lxor
/*     */     //   15: lstore #6
/*     */     //   17: dup2
/*     */     //   18: ldc2_w 72998233601796
/*     */     //   21: lxor
/*     */     //   22: lstore #8
/*     */     //   24: dup2
/*     */     //   25: ldc2_w 26744377293990
/*     */     //   28: lxor
/*     */     //   29: lstore #10
/*     */     //   31: dup2
/*     */     //   32: ldc2_w 9120622663702
/*     */     //   35: lxor
/*     */     //   36: lstore #12
/*     */     //   38: dup2
/*     */     //   39: ldc2_w 1090597285648
/*     */     //   42: lxor
/*     */     //   43: lstore #14
/*     */     //   45: dup2
/*     */     //   46: ldc2_w 126809425382824
/*     */     //   49: lxor
/*     */     //   50: lstore #16
/*     */     //   52: dup2
/*     */     //   53: ldc2_w 73041887441187
/*     */     //   56: lxor
/*     */     //   57: lstore #18
/*     */     //   59: dup2
/*     */     //   60: ldc2_w 139719637233211
/*     */     //   63: lxor
/*     */     //   64: lstore #20
/*     */     //   66: dup2
/*     */     //   67: ldc2_w 3542459251837
/*     */     //   70: lxor
/*     */     //   71: lstore #22
/*     */     //   73: pop2
/*     */     //   74: ldc2_w -8723223189985458638
/*     */     //   77: lload #4
/*     */     //   79: <illegal opcode> w : (JJ)[Lme/konsolas/aac/aN;
/*     */     //   84: iconst_0
/*     */     //   85: istore #25
/*     */     //   87: astore #24
/*     */     //   89: aload_3
/*     */     //   90: invokevirtual length : ()I
/*     */     //   93: istore #26
/*     */     //   95: aload_3
/*     */     //   96: iload #25
/*     */     //   98: lload #16
/*     */     //   100: iload #26
/*     */     //   102: bipush #59
/*     */     //   104: invokestatic a : (Ljava/lang/String;IJIC)I
/*     */     //   107: istore #27
/*     */     //   109: aload_3
/*     */     //   110: iload #25
/*     */     //   112: lload #16
/*     */     //   114: iload #27
/*     */     //   116: bipush #61
/*     */     //   118: invokestatic a : (Ljava/lang/String;IJIC)I
/*     */     //   121: istore #28
/*     */     //   123: iload #28
/*     */     //   125: iload #27
/*     */     //   127: if_icmpne -> 143
/*     */     //   130: aconst_null
/*     */     //   131: areturn
/*     */     //   132: ldc2_w -8736352777431487294
/*     */     //   135: lload #4
/*     */     //   137: <illegal opcode> w : (Ljava/lang/RuntimeException;JJ)Ljava/lang/RuntimeException;
/*     */     //   142: athrow
/*     */     //   143: lload #22
/*     */     //   145: aload_3
/*     */     //   146: iload #25
/*     */     //   148: iload #28
/*     */     //   150: invokestatic a : (JLjava/lang/String;II)Ljava/lang/String;
/*     */     //   153: astore #29
/*     */     //   155: aload #29
/*     */     //   157: invokevirtual isEmpty : ()Z
/*     */     //   160: lload #4
/*     */     //   162: lconst_0
/*     */     //   163: lcmp
/*     */     //   164: iflt -> 229
/*     */     //   167: aload #24
/*     */     //   169: ifnonnull -> 229
/*     */     //   172: ifne -> 233
/*     */     //   175: goto -> 189
/*     */     //   178: ldc2_w -8736352777431487294
/*     */     //   181: lload #4
/*     */     //   183: <illegal opcode> w : (Ljava/lang/RuntimeException;JJ)Ljava/lang/RuntimeException;
/*     */     //   188: athrow
/*     */     //   189: aload #29
/*     */     //   191: aload #24
/*     */     //   193: ifnonnull -> 258
/*     */     //   196: goto -> 210
/*     */     //   199: ldc2_w -8736352777431487294
/*     */     //   202: lload #4
/*     */     //   204: <illegal opcode> w : (Ljava/lang/RuntimeException;JJ)Ljava/lang/RuntimeException;
/*     */     //   209: athrow
/*     */     //   210: lload #6
/*     */     //   212: invokestatic a : (Ljava/lang/String;J)I
/*     */     //   215: goto -> 229
/*     */     //   218: ldc2_w -8736352777431487294
/*     */     //   221: lload #4
/*     */     //   223: <illegal opcode> w : (Ljava/lang/RuntimeException;JJ)Ljava/lang/RuntimeException;
/*     */     //   228: athrow
/*     */     //   229: iconst_m1
/*     */     //   230: if_icmpeq -> 246
/*     */     //   233: aconst_null
/*     */     //   234: areturn
/*     */     //   235: ldc2_w -8736352777431487294
/*     */     //   238: lload #4
/*     */     //   240: <illegal opcode> w : (Ljava/lang/RuntimeException;JJ)Ljava/lang/RuntimeException;
/*     */     //   245: athrow
/*     */     //   246: lload #22
/*     */     //   248: aload_3
/*     */     //   249: iload #28
/*     */     //   251: iconst_1
/*     */     //   252: iadd
/*     */     //   253: iload #27
/*     */     //   255: invokestatic a : (JLjava/lang/String;II)Ljava/lang/String;
/*     */     //   258: astore #30
/*     */     //   260: aload #30
/*     */     //   262: lload #6
/*     */     //   264: invokestatic a : (Ljava/lang/String;J)I
/*     */     //   267: iconst_m1
/*     */     //   268: if_icmpeq -> 284
/*     */     //   271: aconst_null
/*     */     //   272: areturn
/*     */     //   273: ldc2_w -8736352777431487294
/*     */     //   276: lload #4
/*     */     //   278: <illegal opcode> w : (Ljava/lang/RuntimeException;JJ)Ljava/lang/RuntimeException;
/*     */     //   283: athrow
/*     */     //   284: ldc2_w 253402300799999
/*     */     //   287: lstore #31
/*     */     //   289: ldc2_w -1
/*     */     //   292: lstore #33
/*     */     //   294: aconst_null
/*     */     //   295: astore #35
/*     */     //   297: aconst_null
/*     */     //   298: astore #36
/*     */     //   300: iconst_0
/*     */     //   301: istore #37
/*     */     //   303: iconst_0
/*     */     //   304: istore #38
/*     */     //   306: iconst_1
/*     */     //   307: istore #39
/*     */     //   309: iconst_0
/*     */     //   310: istore #40
/*     */     //   312: iload #27
/*     */     //   314: iconst_1
/*     */     //   315: iadd
/*     */     //   316: istore #25
/*     */     //   318: iload #25
/*     */     //   320: iload #26
/*     */     //   322: if_icmpge -> 898
/*     */     //   325: aload_3
/*     */     //   326: iload #25
/*     */     //   328: lload #16
/*     */     //   330: iload #26
/*     */     //   332: bipush #59
/*     */     //   334: invokestatic a : (Ljava/lang/String;IJIC)I
/*     */     //   337: istore #41
/*     */     //   339: aload_3
/*     */     //   340: iload #25
/*     */     //   342: lload #16
/*     */     //   344: iload #41
/*     */     //   346: bipush #61
/*     */     //   348: invokestatic a : (Ljava/lang/String;IJIC)I
/*     */     //   351: istore #42
/*     */     //   353: lload #22
/*     */     //   355: aload_3
/*     */     //   356: iload #25
/*     */     //   358: iload #42
/*     */     //   360: invokestatic a : (JLjava/lang/String;II)Ljava/lang/String;
/*     */     //   363: astore #43
/*     */     //   365: iload #42
/*     */     //   367: aload #24
/*     */     //   369: lload #4
/*     */     //   371: lconst_0
/*     */     //   372: lcmp
/*     */     //   373: iflt -> 913
/*     */     //   376: ifnonnull -> 911
/*     */     //   379: iload #41
/*     */     //   381: if_icmpge -> 424
/*     */     //   384: goto -> 398
/*     */     //   387: ldc2_w -8736352777431487294
/*     */     //   390: lload #4
/*     */     //   392: <illegal opcode> w : (Ljava/lang/RuntimeException;JJ)Ljava/lang/RuntimeException;
/*     */     //   397: athrow
/*     */     //   398: lload #22
/*     */     //   400: aload_3
/*     */     //   401: iload #42
/*     */     //   403: iconst_1
/*     */     //   404: iadd
/*     */     //   405: iload #41
/*     */     //   407: invokestatic a : (JLjava/lang/String;II)Ljava/lang/String;
/*     */     //   410: goto -> 426
/*     */     //   413: ldc2_w -8736352777431487294
/*     */     //   416: lload #4
/*     */     //   418: <illegal opcode> w : (Ljava/lang/RuntimeException;JJ)Ljava/lang/RuntimeException;
/*     */     //   423: athrow
/*     */     //   424: ldc ''
/*     */     //   426: astore #44
/*     */     //   428: aload #43
/*     */     //   430: sipush #11272
/*     */     //   433: ldc2_w 6717699616934118673
/*     */     //   436: lload #4
/*     */     //   438: lxor
/*     */     //   439: <illegal opcode> v : (IJ)Ljava/lang/String;
/*     */     //   444: invokevirtual equalsIgnoreCase : (Ljava/lang/String;)Z
/*     */     //   447: aload #24
/*     */     //   449: lload #4
/*     */     //   451: lconst_0
/*     */     //   452: lcmp
/*     */     //   453: iflt -> 541
/*     */     //   456: ifnonnull -> 539
/*     */     //   459: ifeq -> 506
/*     */     //   462: goto -> 476
/*     */     //   465: ldc2_w -8736352777431487294
/*     */     //   468: lload #4
/*     */     //   470: <illegal opcode> w : (Ljava/lang/RuntimeException;JJ)Ljava/lang/RuntimeException;
/*     */     //   475: athrow
/*     */     //   476: aload #44
/*     */     //   478: iconst_0
/*     */     //   479: aload #44
/*     */     //   481: invokevirtual length : ()I
/*     */     //   484: lload #8
/*     */     //   486: dup2_x1
/*     */     //   487: pop2
/*     */     //   488: invokestatic a : (Ljava/lang/String;IJI)J
/*     */     //   491: lstore #31
/*     */     //   493: iconst_1
/*     */     //   494: istore #40
/*     */     //   496: goto -> 887
/*     */     //   499: astore #45
/*     */     //   501: aload #24
/*     */     //   503: ifnull -> 887
/*     */     //   506: aload #43
/*     */     //   508: sipush #4109
/*     */     //   511: ldc2_w 2833177343999899920
/*     */     //   514: lload #4
/*     */     //   516: lxor
/*     */     //   517: <illegal opcode> v : (IJ)Ljava/lang/String;
/*     */     //   522: invokevirtual equalsIgnoreCase : (Ljava/lang/String;)Z
/*     */     //   525: goto -> 539
/*     */     //   528: ldc2_w -8736352777431487294
/*     */     //   531: lload #4
/*     */     //   533: <illegal opcode> w : (Ljava/lang/RuntimeException;JJ)Ljava/lang/RuntimeException;
/*     */     //   538: athrow
/*     */     //   539: aload #24
/*     */     //   541: lload #4
/*     */     //   543: lconst_0
/*     */     //   544: lcmp
/*     */     //   545: iflt -> 625
/*     */     //   548: ifnonnull -> 623
/*     */     //   551: ifeq -> 590
/*     */     //   554: goto -> 568
/*     */     //   557: ldc2_w -8736352777431487294
/*     */     //   560: lload #4
/*     */     //   562: <illegal opcode> w : (Ljava/lang/RuntimeException;JJ)Ljava/lang/RuntimeException;
/*     */     //   567: athrow
/*     */     //   568: lload #10
/*     */     //   570: aload #44
/*     */     //   572: invokestatic a : (JLjava/lang/String;)J
/*     */     //   575: lstore #33
/*     */     //   577: iconst_1
/*     */     //   578: istore #40
/*     */     //   580: goto -> 887
/*     */     //   583: astore #45
/*     */     //   585: aload #24
/*     */     //   587: ifnull -> 887
/*     */     //   590: aload #43
/*     */     //   592: sipush #21859
/*     */     //   595: ldc2_w 865396184377146489
/*     */     //   598: lload #4
/*     */     //   600: lxor
/*     */     //   601: <illegal opcode> v : (IJ)Ljava/lang/String;
/*     */     //   606: invokevirtual equalsIgnoreCase : (Ljava/lang/String;)Z
/*     */     //   609: goto -> 623
/*     */     //   612: ldc2_w -8736352777431487294
/*     */     //   615: lload #4
/*     */     //   617: <illegal opcode> w : (Ljava/lang/RuntimeException;JJ)Ljava/lang/RuntimeException;
/*     */     //   622: athrow
/*     */     //   623: aload #24
/*     */     //   625: lload #4
/*     */     //   627: lconst_0
/*     */     //   628: lcmp
/*     */     //   629: iflt -> 709
/*     */     //   632: ifnonnull -> 707
/*     */     //   635: ifeq -> 674
/*     */     //   638: goto -> 652
/*     */     //   641: ldc2_w -8736352777431487294
/*     */     //   644: lload #4
/*     */     //   646: <illegal opcode> w : (Ljava/lang/RuntimeException;JJ)Ljava/lang/RuntimeException;
/*     */     //   651: athrow
/*     */     //   652: aload #44
/*     */     //   654: lload #14
/*     */     //   656: invokestatic a : (Ljava/lang/String;J)Ljava/lang/String;
/*     */     //   659: astore #35
/*     */     //   661: iconst_0
/*     */     //   662: istore #39
/*     */     //   664: goto -> 887
/*     */     //   667: astore #45
/*     */     //   669: aload #24
/*     */     //   671: ifnull -> 887
/*     */     //   674: aload #43
/*     */     //   676: sipush #19590
/*     */     //   679: ldc2_w 7786303046743827863
/*     */     //   682: lload #4
/*     */     //   684: lxor
/*     */     //   685: <illegal opcode> v : (IJ)Ljava/lang/String;
/*     */     //   690: invokevirtual equalsIgnoreCase : (Ljava/lang/String;)Z
/*     */     //   693: goto -> 707
/*     */     //   696: ldc2_w -8736352777431487294
/*     */     //   699: lload #4
/*     */     //   701: <illegal opcode> w : (Ljava/lang/RuntimeException;JJ)Ljava/lang/RuntimeException;
/*     */     //   706: athrow
/*     */     //   707: aload #24
/*     */     //   709: lload #4
/*     */     //   711: lconst_0
/*     */     //   712: lcmp
/*     */     //   713: ifle -> 787
/*     */     //   716: ifnonnull -> 785
/*     */     //   719: ifeq -> 752
/*     */     //   722: goto -> 736
/*     */     //   725: ldc2_w -8736352777431487294
/*     */     //   728: lload #4
/*     */     //   730: <illegal opcode> w : (Ljava/lang/RuntimeException;JJ)Ljava/lang/RuntimeException;
/*     */     //   735: athrow
/*     */     //   736: aload #44
/*     */     //   738: lload #4
/*     */     //   740: lconst_0
/*     */     //   741: lcmp
/*     */     //   742: iflt -> 754
/*     */     //   745: astore #36
/*     */     //   747: aload #24
/*     */     //   749: ifnull -> 887
/*     */     //   752: aload #43
/*     */     //   754: sipush #5695
/*     */     //   757: ldc2_w 1937555498010083131
/*     */     //   760: lload #4
/*     */     //   762: lxor
/*     */     //   763: <illegal opcode> v : (IJ)Ljava/lang/String;
/*     */     //   768: invokevirtual equalsIgnoreCase : (Ljava/lang/String;)Z
/*     */     //   771: goto -> 785
/*     */     //   774: ldc2_w -8736352777431487294
/*     */     //   777: lload #4
/*     */     //   779: <illegal opcode> w : (Ljava/lang/RuntimeException;JJ)Ljava/lang/RuntimeException;
/*     */     //   784: athrow
/*     */     //   785: aload #24
/*     */     //   787: lload #4
/*     */     //   789: lconst_0
/*     */     //   790: lcmp
/*     */     //   791: ifle -> 864
/*     */     //   794: ifnonnull -> 862
/*     */     //   797: ifeq -> 829
/*     */     //   800: goto -> 814
/*     */     //   803: ldc2_w -8736352777431487294
/*     */     //   806: lload #4
/*     */     //   808: <illegal opcode> w : (Ljava/lang/RuntimeException;JJ)Ljava/lang/RuntimeException;
/*     */     //   813: athrow
/*     */     //   814: iconst_1
/*     */     //   815: lload #4
/*     */     //   817: lconst_0
/*     */     //   818: lcmp
/*     */     //   819: iflt -> 889
/*     */     //   822: istore #37
/*     */     //   824: aload #24
/*     */     //   826: ifnull -> 887
/*     */     //   829: aload #43
/*     */     //   831: sipush #18092
/*     */     //   834: ldc2_w 7973472763906109367
/*     */     //   837: lload #4
/*     */     //   839: lxor
/*     */     //   840: <illegal opcode> v : (IJ)Ljava/lang/String;
/*     */     //   845: invokevirtual equalsIgnoreCase : (Ljava/lang/String;)Z
/*     */     //   848: goto -> 862
/*     */     //   851: ldc2_w -8736352777431487294
/*     */     //   854: lload #4
/*     */     //   856: <illegal opcode> w : (Ljava/lang/RuntimeException;JJ)Ljava/lang/RuntimeException;
/*     */     //   861: athrow
/*     */     //   862: aload #24
/*     */     //   864: ifnonnull -> 891
/*     */     //   867: ifeq -> 887
/*     */     //   870: goto -> 884
/*     */     //   873: ldc2_w -8736352777431487294
/*     */     //   876: lload #4
/*     */     //   878: <illegal opcode> w : (Ljava/lang/RuntimeException;JJ)Ljava/lang/RuntimeException;
/*     */     //   883: athrow
/*     */     //   884: iconst_1
/*     */     //   885: istore #38
/*     */     //   887: iload #41
/*     */     //   889: iconst_1
/*     */     //   890: iadd
/*     */     //   891: istore #25
/*     */     //   893: aload #24
/*     */     //   895: ifnull -> 318
/*     */     //   898: lload #33
/*     */     //   900: ldc2_w -9223372036854775808
/*     */     //   903: lload #4
/*     */     //   905: lconst_0
/*     */     //   906: lcmp
/*     */     //   907: iflt -> 1060
/*     */     //   910: lcmp
/*     */     //   911: aload #24
/*     */     //   913: lload #4
/*     */     //   915: lconst_0
/*     */     //   916: lcmp
/*     */     //   917: ifle -> 986
/*     */     //   920: ifnonnull -> 977
/*     */     //   923: ifne -> 957
/*     */     //   926: goto -> 940
/*     */     //   929: ldc2_w -8736352777431487294
/*     */     //   932: lload #4
/*     */     //   934: <illegal opcode> w : (Ljava/lang/RuntimeException;JJ)Ljava/lang/RuntimeException;
/*     */     //   939: athrow
/*     */     //   940: ldc2_w -9223372036854775808
/*     */     //   943: lload #4
/*     */     //   945: lconst_0
/*     */     //   946: lcmp
/*     */     //   947: ifle -> 959
/*     */     //   950: lstore #31
/*     */     //   952: aload #24
/*     */     //   954: ifnull -> 1183
/*     */     //   957: lload #33
/*     */     //   959: ldc2_w -1
/*     */     //   962: lcmp
/*     */     //   963: goto -> 977
/*     */     //   966: ldc2_w -8736352777431487294
/*     */     //   969: lload #4
/*     */     //   971: <illegal opcode> w : (Ljava/lang/RuntimeException;JJ)Ljava/lang/RuntimeException;
/*     */     //   976: athrow
/*     */     //   977: lload #4
/*     */     //   979: lconst_0
/*     */     //   980: lcmp
/*     */     //   981: iflt -> 1052
/*     */     //   984: aload #24
/*     */     //   986: ifnonnull -> 1052
/*     */     //   989: ifeq -> 1183
/*     */     //   992: goto -> 1006
/*     */     //   995: ldc2_w -8736352777431487294
/*     */     //   998: lload #4
/*     */     //   1000: <illegal opcode> w : (Ljava/lang/RuntimeException;JJ)Ljava/lang/RuntimeException;
/*     */     //   1005: athrow
/*     */     //   1006: lload #33
/*     */     //   1008: lload #4
/*     */     //   1010: lconst_0
/*     */     //   1011: lcmp
/*     */     //   1012: ifle -> 1075
/*     */     //   1015: ldc2_w 9223372036854775
/*     */     //   1018: aload #24
/*     */     //   1020: ifnonnull -> 1074
/*     */     //   1023: goto -> 1037
/*     */     //   1026: ldc2_w -8736352777431487294
/*     */     //   1029: lload #4
/*     */     //   1031: <illegal opcode> w : (Ljava/lang/RuntimeException;JJ)Ljava/lang/RuntimeException;
/*     */     //   1036: athrow
/*     */     //   1037: lcmp
/*     */     //   1038: goto -> 1052
/*     */     //   1041: ldc2_w -8736352777431487294
/*     */     //   1044: lload #4
/*     */     //   1046: <illegal opcode> w : (Ljava/lang/RuntimeException;JJ)Ljava/lang/RuntimeException;
/*     */     //   1051: athrow
/*     */     //   1052: ifgt -> 1078
/*     */     //   1055: lload #33
/*     */     //   1057: ldc2_w 1000
/*     */     //   1060: goto -> 1074
/*     */     //   1063: ldc2_w -8736352777431487294
/*     */     //   1066: lload #4
/*     */     //   1068: <illegal opcode> w : (Ljava/lang/RuntimeException;JJ)Ljava/lang/RuntimeException;
/*     */     //   1073: athrow
/*     */     //   1074: lmul
/*     */     //   1075: goto -> 1081
/*     */     //   1078: ldc2_w 9223372036854775807
/*     */     //   1081: lstore #41
/*     */     //   1083: lload_0
/*     */     //   1084: lload #41
/*     */     //   1086: lload #4
/*     */     //   1088: lconst_0
/*     */     //   1089: lcmp
/*     */     //   1090: ifle -> 1104
/*     */     //   1093: ladd
/*     */     //   1094: lstore #31
/*     */     //   1096: lload #31
/*     */     //   1098: aload #24
/*     */     //   1100: ifnonnull -> 1181
/*     */     //   1103: lload_0
/*     */     //   1104: lcmp
/*     */     //   1105: iflt -> 1164
/*     */     //   1108: goto -> 1122
/*     */     //   1111: ldc2_w -8736352777431487294
/*     */     //   1114: lload #4
/*     */     //   1116: <illegal opcode> w : (Ljava/lang/RuntimeException;JJ)Ljava/lang/RuntimeException;
/*     */     //   1121: athrow
/*     */     //   1122: lload #31
/*     */     //   1124: aload #24
/*     */     //   1126: ifnonnull -> 1181
/*     */     //   1129: goto -> 1143
/*     */     //   1132: ldc2_w -8736352777431487294
/*     */     //   1135: lload #4
/*     */     //   1137: <illegal opcode> w : (Ljava/lang/RuntimeException;JJ)Ljava/lang/RuntimeException;
/*     */     //   1142: athrow
/*     */     //   1143: ldc2_w 253402300799999
/*     */     //   1146: lcmp
/*     */     //   1147: ifle -> 1183
/*     */     //   1150: goto -> 1164
/*     */     //   1153: ldc2_w -8736352777431487294
/*     */     //   1156: lload #4
/*     */     //   1158: <illegal opcode> w : (Ljava/lang/RuntimeException;JJ)Ljava/lang/RuntimeException;
/*     */     //   1163: athrow
/*     */     //   1164: ldc2_w 253402300799999
/*     */     //   1167: goto -> 1181
/*     */     //   1170: ldc2_w -8736352777431487294
/*     */     //   1173: lload #4
/*     */     //   1175: <illegal opcode> w : (Ljava/lang/RuntimeException;JJ)Ljava/lang/RuntimeException;
/*     */     //   1180: athrow
/*     */     //   1181: lstore #31
/*     */     //   1183: aload_2
/*     */     //   1184: invokevirtual d : ()Ljava/lang/String;
/*     */     //   1187: astore #41
/*     */     //   1189: aload #35
/*     */     //   1191: lload #4
/*     */     //   1193: lconst_0
/*     */     //   1194: lcmp
/*     */     //   1195: ifle -> 1252
/*     */     //   1198: aload #24
/*     */     //   1200: ifnonnull -> 1252
/*     */     //   1203: ifnonnull -> 1236
/*     */     //   1206: goto -> 1220
/*     */     //   1209: ldc2_w -8736352777431487294
/*     */     //   1212: lload #4
/*     */     //   1214: <illegal opcode> w : (Ljava/lang/RuntimeException;JJ)Ljava/lang/RuntimeException;
/*     */     //   1219: athrow
/*     */     //   1220: aload #41
/*     */     //   1222: astore #35
/*     */     //   1224: lload #4
/*     */     //   1226: lconst_0
/*     */     //   1227: lcmp
/*     */     //   1228: iflt -> 1303
/*     */     //   1231: aload #24
/*     */     //   1233: ifnull -> 1303
/*     */     //   1236: aload #41
/*     */     //   1238: goto -> 1252
/*     */     //   1241: ldc2_w -8736352777431487294
/*     */     //   1244: lload #4
/*     */     //   1246: <illegal opcode> w : (Ljava/lang/RuntimeException;JJ)Ljava/lang/RuntimeException;
/*     */     //   1251: athrow
/*     */     //   1252: aload #35
/*     */     //   1254: lload #12
/*     */     //   1256: dup2_x2
/*     */     //   1257: pop2
/*     */     //   1258: invokestatic a : (JLjava/lang/String;Ljava/lang/String;)Z
/*     */     //   1261: lload #4
/*     */     //   1263: lconst_0
/*     */     //   1264: lcmp
/*     */     //   1265: iflt -> 1327
/*     */     //   1268: aload #24
/*     */     //   1270: ifnonnull -> 1327
/*     */     //   1273: ifne -> 1303
/*     */     //   1276: goto -> 1290
/*     */     //   1279: ldc2_w -8736352777431487294
/*     */     //   1282: lload #4
/*     */     //   1284: <illegal opcode> w : (Ljava/lang/RuntimeException;JJ)Ljava/lang/RuntimeException;
/*     */     //   1289: athrow
/*     */     //   1290: aconst_null
/*     */     //   1291: areturn
/*     */     //   1292: ldc2_w -8736352777431487294
/*     */     //   1295: lload #4
/*     */     //   1297: <illegal opcode> w : (Ljava/lang/RuntimeException;JJ)Ljava/lang/RuntimeException;
/*     */     //   1302: athrow
/*     */     //   1303: aload #41
/*     */     //   1305: aload #24
/*     */     //   1307: ifnonnull -> 1403
/*     */     //   1310: invokevirtual length : ()I
/*     */     //   1313: goto -> 1327
/*     */     //   1316: ldc2_w -8736352777431487294
/*     */     //   1319: lload #4
/*     */     //   1321: <illegal opcode> w : (Ljava/lang/RuntimeException;JJ)Ljava/lang/RuntimeException;
/*     */     //   1326: athrow
/*     */     //   1327: aload #35
/*     */     //   1329: invokevirtual length : ()I
/*     */     //   1332: if_icmpeq -> 1401
/*     */     //   1335: invokestatic a : ()Lme/konsolas/aac/hB;
/*     */     //   1338: lload #18
/*     */     //   1340: aload #35
/*     */     //   1342: invokevirtual a : (JLjava/lang/String;)Ljava/lang/String;
/*     */     //   1345: aload #24
/*     */     //   1347: lload #4
/*     */     //   1349: lconst_0
/*     */     //   1350: lcmp
/*     */     //   1351: ifle -> 1405
/*     */     //   1354: ifnonnull -> 1403
/*     */     //   1357: goto -> 1371
/*     */     //   1360: ldc2_w -8736352777431487294
/*     */     //   1363: lload #4
/*     */     //   1365: <illegal opcode> w : (Ljava/lang/RuntimeException;JJ)Ljava/lang/RuntimeException;
/*     */     //   1370: athrow
/*     */     //   1371: ifnonnull -> 1401
/*     */     //   1374: goto -> 1388
/*     */     //   1377: ldc2_w -8736352777431487294
/*     */     //   1380: lload #4
/*     */     //   1382: <illegal opcode> w : (Ljava/lang/RuntimeException;JJ)Ljava/lang/RuntimeException;
/*     */     //   1387: athrow
/*     */     //   1388: aconst_null
/*     */     //   1389: areturn
/*     */     //   1390: ldc2_w -8736352777431487294
/*     */     //   1393: lload #4
/*     */     //   1395: <illegal opcode> w : (Ljava/lang/RuntimeException;JJ)Ljava/lang/RuntimeException;
/*     */     //   1400: athrow
/*     */     //   1401: aload #36
/*     */     //   1403: aload #24
/*     */     //   1405: ifnonnull -> 1511
/*     */     //   1408: ifnull -> 1491
/*     */     //   1411: goto -> 1425
/*     */     //   1414: ldc2_w -8736352777431487294
/*     */     //   1417: lload #4
/*     */     //   1419: <illegal opcode> w : (Ljava/lang/RuntimeException;JJ)Ljava/lang/RuntimeException;
/*     */     //   1424: athrow
/*     */     //   1425: aload #36
/*     */     //   1427: aload #24
/*     */     //   1429: ifnonnull -> 1511
/*     */     //   1432: goto -> 1446
/*     */     //   1435: ldc2_w -8736352777431487294
/*     */     //   1438: lload #4
/*     */     //   1440: <illegal opcode> w : (Ljava/lang/RuntimeException;JJ)Ljava/lang/RuntimeException;
/*     */     //   1445: athrow
/*     */     //   1446: ldc_w '᭦扐'
/*     */     //   1449: invokevirtual toCharArray : ()[C
/*     */     //   1452: dup
/*     */     //   1453: dup
/*     */     //   1454: iconst_0
/*     */     //   1455: dup_x1
/*     */     //   1456: caload
/*     */     //   1457: sipush #17560
/*     */     //   1460: ixor
/*     */     //   1461: i2c
/*     */     //   1462: castore
/*     */     //   1463: sipush #30384
/*     */     //   1466: iconst_1
/*     */     //   1467: iconst_1
/*     */     //   1468: invokestatic U : (Ljava/lang/Object;SZZ)Ljava/lang/String;
/*     */     //   1471: invokevirtual startsWith : (Ljava/lang/String;)Z
/*     */     //   1474: ifne -> 1576
/*     */     //   1477: goto -> 1491
/*     */     //   1480: ldc2_w -8736352777431487294
/*     */     //   1483: lload #4
/*     */     //   1485: <illegal opcode> w : (Ljava/lang/RuntimeException;JJ)Ljava/lang/RuntimeException;
/*     */     //   1490: athrow
/*     */     //   1491: aload_2
/*     */     //   1492: lload #20
/*     */     //   1494: invokevirtual l : (J)Ljava/lang/String;
/*     */     //   1497: goto -> 1511
/*     */     //   1500: ldc2_w -8736352777431487294
/*     */     //   1503: lload #4
/*     */     //   1505: <illegal opcode> w : (Ljava/lang/RuntimeException;JJ)Ljava/lang/RuntimeException;
/*     */     //   1510: athrow
/*     */     //   1511: astore #42
/*     */     //   1513: aload #42
/*     */     //   1515: bipush #47
/*     */     //   1517: invokevirtual lastIndexOf : (I)I
/*     */     //   1520: istore #43
/*     */     //   1522: iload #43
/*     */     //   1524: ifeq -> 1549
/*     */     //   1527: aload #42
/*     */     //   1529: iconst_0
/*     */     //   1530: iload #43
/*     */     //   1532: invokevirtual substring : (II)Ljava/lang/String;
/*     */     //   1535: goto -> 1574
/*     */     //   1538: ldc2_w -8736352777431487294
/*     */     //   1541: lload #4
/*     */     //   1543: <illegal opcode> w : (Ljava/lang/RuntimeException;JJ)Ljava/lang/RuntimeException;
/*     */     //   1548: athrow
/*     */     //   1549: ldc_w '⟞寖'
/*     */     //   1552: invokevirtual toCharArray : ()[C
/*     */     //   1555: dup
/*     */     //   1556: dup
/*     */     //   1557: iconst_0
/*     */     //   1558: dup_x1
/*     */     //   1559: caload
/*     */     //   1560: sipush #13126
/*     */     //   1563: ixor
/*     */     //   1564: i2c
/*     */     //   1565: castore
/*     */     //   1566: sipush #20673
/*     */     //   1569: iconst_0
/*     */     //   1570: iconst_1
/*     */     //   1571: invokestatic U : (Ljava/lang/Object;SZZ)Ljava/lang/String;
/*     */     //   1574: astore #36
/*     */     //   1576: new me/konsolas/aac/c2
/*     */     //   1579: dup
/*     */     //   1580: aload #29
/*     */     //   1582: aload #30
/*     */     //   1584: lload #31
/*     */     //   1586: aload #35
/*     */     //   1588: aload #36
/*     */     //   1590: iload #37
/*     */     //   1592: iload #38
/*     */     //   1594: iload #39
/*     */     //   1596: iload #40
/*     */     //   1598: invokespecial <init> : (Ljava/lang/String;Ljava/lang/String;JLjava/lang/String;Ljava/lang/String;ZZZZ)V
/*     */     //   1601: areturn
/*     */     // Line number table:
/*     */     //   Java source line number -> byte code offset
/*     */     //   #156	-> 84
/*     */     //   #129	-> 89
/*     */     //   #86	-> 95
/*     */     //   #82	-> 109
/*     */     //   #31	-> 123
/*     */     //   #5	-> 143
/*     */     //   #169	-> 155
/*     */     //   #46	-> 246
/*     */     //   #234	-> 260
/*     */     //   #173	-> 284
/*     */     //   #188	-> 289
/*     */     //   #22	-> 294
/*     */     //   #102	-> 297
/*     */     //   #103	-> 300
/*     */     //   #221	-> 303
/*     */     //   #168	-> 306
/*     */     //   #197	-> 309
/*     */     //   #41	-> 312
/*     */     //   #244	-> 318
/*     */     //   #136	-> 325
/*     */     //   #32	-> 339
/*     */     //   #139	-> 353
/*     */     //   #199	-> 365
/*     */     //   #107	-> 398
/*     */     //   #15	-> 424
/*     */     //   #215	-> 428
/*     */     //   #127	-> 476
/*     */     //   #158	-> 493
/*     */     //   #247	-> 496
/*     */     //   #165	-> 499
/*     */     //   #56	-> 501
/*     */     //   #206	-> 506
/*     */     //   #106	-> 568
/*     */     //   #245	-> 577
/*     */     //   #216	-> 580
/*     */     //   #13	-> 583
/*     */     //   #89	-> 585
/*     */     //   #175	-> 590
/*     */     //   #186	-> 652
/*     */     //   #190	-> 661
/*     */     //   #239	-> 664
/*     */     //   #223	-> 667
/*     */     //   #131	-> 669
/*     */     //   #94	-> 674
/*     */     //   #171	-> 736
/*     */     //   #232	-> 752
/*     */     //   #200	-> 814
/*     */     //   #242	-> 829
/*     */     //   #53	-> 884
/*     */     //   #151	-> 887
/*     */     //   #174	-> 893
/*     */     //   #11	-> 898
/*     */     //   #220	-> 940
/*     */     //   #150	-> 957
/*     */     //   #16	-> 1006
/*     */     //   #118	-> 1055
/*     */     //   #108	-> 1078
/*     */     //   #36	-> 1083
/*     */     //   #228	-> 1096
/*     */     //   #172	-> 1164
/*     */     //   #100	-> 1183
/*     */     //   #208	-> 1189
/*     */     //   #72	-> 1220
/*     */     //   #167	-> 1236
/*     */     //   #79	-> 1290
/*     */     //   #58	-> 1303
/*     */     //   #121	-> 1335
/*     */     //   #42	-> 1388
/*     */     //   #88	-> 1401
/*     */     //   #126	-> 1491
/*     */     //   #222	-> 1513
/*     */     //   #7	-> 1522
/*     */     //   #202	-> 1576
/*     */     // Exception table:
/*     */     //   from	to	target	type
/*     */     //   123	132	132	java/lang/IllegalArgumentException
/*     */     //   155	175	178	java/lang/IllegalArgumentException
/*     */     //   172	196	199	java/lang/IllegalArgumentException
/*     */     //   189	215	218	java/lang/IllegalArgumentException
/*     */     //   229	235	235	java/lang/IllegalArgumentException
/*     */     //   260	273	273	java/lang/IllegalArgumentException
/*     */     //   365	384	387	java/lang/IllegalArgumentException
/*     */     //   379	413	413	java/lang/IllegalArgumentException
/*     */     //   428	462	465	java/lang/IllegalArgumentException
/*     */     //   476	496	499	java/lang/IllegalArgumentException
/*     */     //   501	525	528	java/lang/IllegalArgumentException
/*     */     //   539	554	557	java/lang/IllegalArgumentException
/*     */     //   568	580	583	java/lang/NumberFormatException
/*     */     //   585	609	612	java/lang/IllegalArgumentException
/*     */     //   623	638	641	java/lang/IllegalArgumentException
/*     */     //   652	664	667	java/lang/IllegalArgumentException
/*     */     //   669	693	696	java/lang/IllegalArgumentException
/*     */     //   707	722	725	java/lang/IllegalArgumentException
/*     */     //   747	771	774	java/lang/IllegalArgumentException
/*     */     //   785	800	803	java/lang/IllegalArgumentException
/*     */     //   824	848	851	java/lang/IllegalArgumentException
/*     */     //   862	870	873	java/lang/IllegalArgumentException
/*     */     //   911	926	929	java/lang/IllegalArgumentException
/*     */     //   952	963	966	java/lang/IllegalArgumentException
/*     */     //   977	992	995	java/lang/IllegalArgumentException
/*     */     //   989	1023	1026	java/lang/IllegalArgumentException
/*     */     //   1006	1038	1041	java/lang/IllegalArgumentException
/*     */     //   1052	1060	1063	java/lang/IllegalArgumentException
/*     */     //   1096	1108	1111	java/lang/IllegalArgumentException
/*     */     //   1103	1129	1132	java/lang/IllegalArgumentException
/*     */     //   1122	1150	1153	java/lang/IllegalArgumentException
/*     */     //   1143	1167	1170	java/lang/IllegalArgumentException
/*     */     //   1189	1206	1209	java/lang/IllegalArgumentException
/*     */     //   1224	1238	1241	java/lang/IllegalArgumentException
/*     */     //   1252	1276	1279	java/lang/IllegalArgumentException
/*     */     //   1273	1292	1292	java/lang/IllegalArgumentException
/*     */     //   1303	1313	1316	java/lang/IllegalArgumentException
/*     */     //   1327	1357	1360	java/lang/IllegalArgumentException
/*     */     //   1335	1374	1377	java/lang/IllegalArgumentException
/*     */     //   1371	1390	1390	java/lang/IllegalArgumentException
/*     */     //   1403	1411	1414	java/lang/IllegalArgumentException
/*     */     //   1408	1432	1435	java/lang/IllegalArgumentException
/*     */     //   1425	1477	1480	java/lang/IllegalArgumentException
/*     */     //   1446	1497	1500	java/lang/IllegalArgumentException
/*     */     //   1522	1538	1538	java/lang/IllegalArgumentException
/*     */   }
/*     */ 
/*     */ 
/*     */ 
/*     */ 
/*     */   
/*     */   @Nullable
/*     */   public static c2 a(long paramLong, l6 paraml6, String paramString) {
/* 163 */     paramLong = n ^ paramLong; long l = paramLong ^ 0x7406B10481EDL; return a(System.currentTimeMillis(), paraml6, paramString, l);
/*     */   }
/*     */ 
/*     */ 
/*     */ 
/*     */ 
/*     */ 
/*     */ 
/*     */   
/*     */   public boolean equals(@Nullable Object paramObject) {
/*     */     // Byte code:
/*     */     //   0: getstatic me/konsolas/aac/c2.n : J
/*     */     //   3: ldc2_w 44425794037487
/*     */     //   6: lxor
/*     */     //   7: lstore_2
/*     */     //   8: ldc2_w 7630731368748181799
/*     */     //   11: lload_2
/*     */     //   12: <illegal opcode> w : (JJ)[Lme/konsolas/aac/aN;
/*     */     //   17: astore #4
/*     */     //   19: aload_1
/*     */     //   20: aload #4
/*     */     //   22: ifnonnull -> 57
/*     */     //   25: instanceof me/konsolas/aac/c2
/*     */     //   28: ifne -> 56
/*     */     //   31: goto -> 44
/*     */     //   34: ldc2_w 7626584381660791767
/*     */     //   37: lload_2
/*     */     //   38: <illegal opcode> w : (Ljava/lang/RuntimeException;JJ)Ljava/lang/RuntimeException;
/*     */     //   43: athrow
/*     */     //   44: iconst_0
/*     */     //   45: ireturn
/*     */     //   46: ldc2_w 7626584381660791767
/*     */     //   49: lload_2
/*     */     //   50: <illegal opcode> w : (Ljava/lang/RuntimeException;JJ)Ljava/lang/RuntimeException;
/*     */     //   55: athrow
/*     */     //   56: aload_1
/*     */     //   57: checkcast me/konsolas/aac/c2
/*     */     //   60: astore #5
/*     */     //   62: aload #5
/*     */     //   64: getfield c : Ljava/lang/String;
/*     */     //   67: aload_0
/*     */     //   68: getfield c : Ljava/lang/String;
/*     */     //   71: invokevirtual equals : (Ljava/lang/Object;)Z
/*     */     //   74: aload #4
/*     */     //   76: ifnonnull -> 120
/*     */     //   79: ifeq -> 453
/*     */     //   82: goto -> 95
/*     */     //   85: ldc2_w 7626584381660791767
/*     */     //   88: lload_2
/*     */     //   89: <illegal opcode> w : (Ljava/lang/RuntimeException;JJ)Ljava/lang/RuntimeException;
/*     */     //   94: athrow
/*     */     //   95: aload #5
/*     */     //   97: getfield l : Ljava/lang/String;
/*     */     //   100: aload_0
/*     */     //   101: getfield l : Ljava/lang/String;
/*     */     //   104: invokevirtual equals : (Ljava/lang/Object;)Z
/*     */     //   107: goto -> 120
/*     */     //   110: ldc2_w 7626584381660791767
/*     */     //   113: lload_2
/*     */     //   114: <illegal opcode> w : (Ljava/lang/RuntimeException;JJ)Ljava/lang/RuntimeException;
/*     */     //   119: athrow
/*     */     //   120: aload #4
/*     */     //   122: ifnonnull -> 166
/*     */     //   125: ifeq -> 453
/*     */     //   128: goto -> 141
/*     */     //   131: ldc2_w 7626584381660791767
/*     */     //   134: lload_2
/*     */     //   135: <illegal opcode> w : (Ljava/lang/RuntimeException;JJ)Ljava/lang/RuntimeException;
/*     */     //   140: athrow
/*     */     //   141: aload #5
/*     */     //   143: getfield j : Ljava/lang/String;
/*     */     //   146: aload_0
/*     */     //   147: getfield j : Ljava/lang/String;
/*     */     //   150: invokevirtual equals : (Ljava/lang/Object;)Z
/*     */     //   153: goto -> 166
/*     */     //   156: ldc2_w 7626584381660791767
/*     */     //   159: lload_2
/*     */     //   160: <illegal opcode> w : (Ljava/lang/RuntimeException;JJ)Ljava/lang/RuntimeException;
/*     */     //   165: athrow
/*     */     //   166: aload #4
/*     */     //   168: ifnonnull -> 212
/*     */     //   171: ifeq -> 453
/*     */     //   174: goto -> 187
/*     */     //   177: ldc2_w 7626584381660791767
/*     */     //   180: lload_2
/*     */     //   181: <illegal opcode> w : (Ljava/lang/RuntimeException;JJ)Ljava/lang/RuntimeException;
/*     */     //   186: athrow
/*     */     //   187: aload #5
/*     */     //   189: getfield e : Ljava/lang/String;
/*     */     //   192: aload_0
/*     */     //   193: getfield e : Ljava/lang/String;
/*     */     //   196: invokevirtual equals : (Ljava/lang/Object;)Z
/*     */     //   199: goto -> 212
/*     */     //   202: ldc2_w 7626584381660791767
/*     */     //   205: lload_2
/*     */     //   206: <illegal opcode> w : (Ljava/lang/RuntimeException;JJ)Ljava/lang/RuntimeException;
/*     */     //   211: athrow
/*     */     //   212: aload #4
/*     */     //   214: ifnonnull -> 256
/*     */     //   217: ifeq -> 453
/*     */     //   220: goto -> 233
/*     */     //   223: ldc2_w 7626584381660791767
/*     */     //   226: lload_2
/*     */     //   227: <illegal opcode> w : (Ljava/lang/RuntimeException;JJ)Ljava/lang/RuntimeException;
/*     */     //   232: athrow
/*     */     //   233: aload #5
/*     */     //   235: getfield f : J
/*     */     //   238: aload_0
/*     */     //   239: getfield f : J
/*     */     //   242: lcmp
/*     */     //   243: goto -> 256
/*     */     //   246: ldc2_w 7626584381660791767
/*     */     //   249: lload_2
/*     */     //   250: <illegal opcode> w : (Ljava/lang/RuntimeException;JJ)Ljava/lang/RuntimeException;
/*     */     //   255: athrow
/*     */     //   256: aload #4
/*     */     //   258: ifnonnull -> 295
/*     */     //   261: ifne -> 453
/*     */     //   264: goto -> 277
/*     */     //   267: ldc2_w 7626584381660791767
/*     */     //   270: lload_2
/*     */     //   271: <illegal opcode> w : (Ljava/lang/RuntimeException;JJ)Ljava/lang/RuntimeException;
/*     */     //   276: athrow
/*     */     //   277: aload #5
/*     */     //   279: getfield g : Z
/*     */     //   282: goto -> 295
/*     */     //   285: ldc2_w 7626584381660791767
/*     */     //   288: lload_2
/*     */     //   289: <illegal opcode> w : (Ljava/lang/RuntimeException;JJ)Ljava/lang/RuntimeException;
/*     */     //   294: athrow
/*     */     //   295: aload_0
/*     */     //   296: getfield g : Z
/*     */     //   299: aload #4
/*     */     //   301: ifnonnull -> 342
/*     */     //   304: if_icmpne -> 453
/*     */     //   307: goto -> 320
/*     */     //   310: ldc2_w 7626584381660791767
/*     */     //   313: lload_2
/*     */     //   314: <illegal opcode> w : (Ljava/lang/RuntimeException;JJ)Ljava/lang/RuntimeException;
/*     */     //   319: athrow
/*     */     //   320: aload #5
/*     */     //   322: getfield a : Z
/*     */     //   325: aload_0
/*     */     //   326: getfield a : Z
/*     */     //   329: goto -> 342
/*     */     //   332: ldc2_w 7626584381660791767
/*     */     //   335: lload_2
/*     */     //   336: <illegal opcode> w : (Ljava/lang/RuntimeException;JJ)Ljava/lang/RuntimeException;
/*     */     //   341: athrow
/*     */     //   342: aload #4
/*     */     //   344: ifnonnull -> 385
/*     */     //   347: if_icmpne -> 453
/*     */     //   350: goto -> 363
/*     */     //   353: ldc2_w 7626584381660791767
/*     */     //   356: lload_2
/*     */     //   357: <illegal opcode> w : (Ljava/lang/RuntimeException;JJ)Ljava/lang/RuntimeException;
/*     */     //   362: athrow
/*     */     //   363: aload #5
/*     */     //   365: getfield h : Z
/*     */     //   368: aload_0
/*     */     //   369: getfield h : Z
/*     */     //   372: goto -> 385
/*     */     //   375: ldc2_w 7626584381660791767
/*     */     //   378: lload_2
/*     */     //   379: <illegal opcode> w : (Ljava/lang/RuntimeException;JJ)Ljava/lang/RuntimeException;
/*     */     //   384: athrow
/*     */     //   385: aload #4
/*     */     //   387: ifnonnull -> 446
/*     */     //   390: if_icmpne -> 453
/*     */     //   393: goto -> 406
/*     */     //   396: ldc2_w 7626584381660791767
/*     */     //   399: lload_2
/*     */     //   400: <illegal opcode> w : (Ljava/lang/RuntimeException;JJ)Ljava/lang/RuntimeException;
/*     */     //   405: athrow
/*     */     //   406: aload #5
/*     */     //   408: getfield d : Z
/*     */     //   411: aload #4
/*     */     //   413: ifnonnull -> 450
/*     */     //   416: goto -> 429
/*     */     //   419: ldc2_w 7626584381660791767
/*     */     //   422: lload_2
/*     */     //   423: <illegal opcode> w : (Ljava/lang/RuntimeException;JJ)Ljava/lang/RuntimeException;
/*     */     //   428: athrow
/*     */     //   429: aload_0
/*     */     //   430: getfield d : Z
/*     */     //   433: goto -> 446
/*     */     //   436: ldc2_w 7626584381660791767
/*     */     //   439: lload_2
/*     */     //   440: <illegal opcode> w : (Ljava/lang/RuntimeException;JJ)Ljava/lang/RuntimeException;
/*     */     //   445: athrow
/*     */     //   446: if_icmpne -> 453
/*     */     //   449: iconst_1
/*     */     //   450: goto -> 454
/*     */     //   453: iconst_0
/*     */     //   454: ireturn
/*     */     // Line number table:
/*     */     //   Java source line number -> byte code offset
/*     */     //   #164	-> 19
/*     */     //   #135	-> 56
/*     */     //   #185	-> 62
/*     */     //   #114	-> 104
/*     */     //   #81	-> 150
/*     */     //   #14	-> 196
/*     */     //   #85	-> 454
/*     */     // Exception table:
/*     */     //   from	to	target	type
/*     */     //   19	31	34	java/lang/NullPointerException
/*     */     //   25	46	46	java/lang/NullPointerException
/*     */     //   62	82	85	java/lang/NullPointerException
/*     */     //   79	107	110	java/lang/NullPointerException
/*     */     //   120	128	131	java/lang/NullPointerException
/*     */     //   125	153	156	java/lang/NullPointerException
/*     */     //   166	174	177	java/lang/NullPointerException
/*     */     //   171	199	202	java/lang/NullPointerException
/*     */     //   212	220	223	java/lang/NullPointerException
/*     */     //   217	243	246	java/lang/NullPointerException
/*     */     //   256	264	267	java/lang/NullPointerException
/*     */     //   261	282	285	java/lang/NullPointerException
/*     */     //   295	307	310	java/lang/NullPointerException
/*     */     //   304	329	332	java/lang/NullPointerException
/*     */     //   342	350	353	java/lang/NullPointerException
/*     */     //   347	372	375	java/lang/NullPointerException
/*     */     //   385	393	396	java/lang/NullPointerException
/*     */     //   390	416	419	java/lang/NullPointerException
/*     */     //   406	433	436	java/lang/NullPointerException
/*     */   }
/*     */ 
/*     */ 
/*     */ 
/*     */ 
/*     */ 
/*     */   
/*     */   public boolean a(l6 paraml6, long paramLong) {
/*     */     // Byte code:
/*     */     //   0: getstatic me/konsolas/aac/c2.n : J
/*     */     //   3: lload_2
/*     */     //   4: lxor
/*     */     //   5: lstore_2
/*     */     //   6: lload_2
/*     */     //   7: dup2
/*     */     //   8: ldc2_w 116400437979577
/*     */     //   11: lxor
/*     */     //   12: lstore #4
/*     */     //   14: dup2
/*     */     //   15: ldc2_w 202684395262
/*     */     //   18: lxor
/*     */     //   19: lstore #6
/*     */     //   21: dup2
/*     */     //   22: ldc2_w 95738389808647
/*     */     //   25: lxor
/*     */     //   26: lstore #8
/*     */     //   28: pop2
/*     */     //   29: ldc2_w -5757593887344381734
/*     */     //   32: lload_2
/*     */     //   33: <illegal opcode> w : (JJ)[Lme/konsolas/aac/aN;
/*     */     //   38: astore #10
/*     */     //   40: aload_0
/*     */     //   41: getfield d : Z
/*     */     //   44: aload #10
/*     */     //   46: ifnonnull -> 89
/*     */     //   49: ifeq -> 92
/*     */     //   52: goto -> 65
/*     */     //   55: ldc2_w -5752727252196009430
/*     */     //   58: lload_2
/*     */     //   59: <illegal opcode> w : (Ljava/lang/RuntimeException;JJ)Ljava/lang/RuntimeException;
/*     */     //   64: athrow
/*     */     //   65: aload_1
/*     */     //   66: invokevirtual d : ()Ljava/lang/String;
/*     */     //   69: aload_0
/*     */     //   70: getfield j : Ljava/lang/String;
/*     */     //   73: invokevirtual equals : (Ljava/lang/Object;)Z
/*     */     //   76: goto -> 89
/*     */     //   79: ldc2_w -5752727252196009430
/*     */     //   82: lload_2
/*     */     //   83: <illegal opcode> w : (Ljava/lang/RuntimeException;JJ)Ljava/lang/RuntimeException;
/*     */     //   88: athrow
/*     */     //   89: goto -> 107
/*     */     //   92: aload_1
/*     */     //   93: invokevirtual d : ()Ljava/lang/String;
/*     */     //   96: lload #6
/*     */     //   98: dup2_x1
/*     */     //   99: pop2
/*     */     //   100: aload_0
/*     */     //   101: getfield j : Ljava/lang/String;
/*     */     //   104: invokestatic a : (JLjava/lang/String;Ljava/lang/String;)Z
/*     */     //   107: istore #11
/*     */     //   109: iload #11
/*     */     //   111: aload #10
/*     */     //   113: lload_2
/*     */     //   114: lconst_0
/*     */     //   115: lcmp
/*     */     //   116: iflt -> 162
/*     */     //   119: ifnonnull -> 160
/*     */     //   122: ifne -> 150
/*     */     //   125: goto -> 138
/*     */     //   128: ldc2_w -5752727252196009430
/*     */     //   131: lload_2
/*     */     //   132: <illegal opcode> w : (Ljava/lang/RuntimeException;JJ)Ljava/lang/RuntimeException;
/*     */     //   137: athrow
/*     */     //   138: iconst_0
/*     */     //   139: ireturn
/*     */     //   140: ldc2_w -5752727252196009430
/*     */     //   143: lload_2
/*     */     //   144: <illegal opcode> w : (Ljava/lang/RuntimeException;JJ)Ljava/lang/RuntimeException;
/*     */     //   149: athrow
/*     */     //   150: aload_1
/*     */     //   151: aload_0
/*     */     //   152: getfield e : Ljava/lang/String;
/*     */     //   155: lload #4
/*     */     //   157: invokestatic a : (Lme/konsolas/aac/l6;Ljava/lang/String;J)Z
/*     */     //   160: aload #10
/*     */     //   162: lload_2
/*     */     //   163: lconst_0
/*     */     //   164: lcmp
/*     */     //   165: iflt -> 205
/*     */     //   168: ifnonnull -> 203
/*     */     //   171: ifne -> 199
/*     */     //   174: goto -> 187
/*     */     //   177: ldc2_w -5752727252196009430
/*     */     //   180: lload_2
/*     */     //   181: <illegal opcode> w : (Ljava/lang/RuntimeException;JJ)Ljava/lang/RuntimeException;
/*     */     //   186: athrow
/*     */     //   187: iconst_0
/*     */     //   188: ireturn
/*     */     //   189: ldc2_w -5752727252196009430
/*     */     //   192: lload_2
/*     */     //   193: <illegal opcode> w : (Ljava/lang/RuntimeException;JJ)Ljava/lang/RuntimeException;
/*     */     //   198: athrow
/*     */     //   199: aload_0
/*     */     //   200: getfield g : Z
/*     */     //   203: aload #10
/*     */     //   205: ifnonnull -> 277
/*     */     //   208: ifeq -> 276
/*     */     //   211: goto -> 224
/*     */     //   214: ldc2_w -5752727252196009430
/*     */     //   217: lload_2
/*     */     //   218: <illegal opcode> w : (Ljava/lang/RuntimeException;JJ)Ljava/lang/RuntimeException;
/*     */     //   223: athrow
/*     */     //   224: aload_1
/*     */     //   225: lload #8
/*     */     //   227: invokevirtual a : (J)Z
/*     */     //   230: aload #10
/*     */     //   232: ifnonnull -> 277
/*     */     //   235: goto -> 248
/*     */     //   238: ldc2_w -5752727252196009430
/*     */     //   241: lload_2
/*     */     //   242: <illegal opcode> w : (Ljava/lang/RuntimeException;JJ)Ljava/lang/RuntimeException;
/*     */     //   247: athrow
/*     */     //   248: ifne -> 276
/*     */     //   251: goto -> 264
/*     */     //   254: ldc2_w -5752727252196009430
/*     */     //   257: lload_2
/*     */     //   258: <illegal opcode> w : (Ljava/lang/RuntimeException;JJ)Ljava/lang/RuntimeException;
/*     */     //   263: athrow
/*     */     //   264: iconst_0
/*     */     //   265: ireturn
/*     */     //   266: ldc2_w -5752727252196009430
/*     */     //   269: lload_2
/*     */     //   270: <illegal opcode> w : (Ljava/lang/RuntimeException;JJ)Ljava/lang/RuntimeException;
/*     */     //   275: athrow
/*     */     //   276: iconst_1
/*     */     //   277: ireturn
/*     */     // Line number table:
/*     */     //   Java source line number -> byte code offset
/*     */     //   #181	-> 40
/*     */     //   #128	-> 65
/*     */     //   #98	-> 92
/*     */     //   #109	-> 109
/*     */     //   #133	-> 150
/*     */     //   #209	-> 199
/*     */     //   #123	-> 276
/*     */     // Exception table:
/*     */     //   from	to	target	type
/*     */     //   40	52	55	java/lang/NullPointerException
/*     */     //   49	76	79	java/lang/NullPointerException
/*     */     //   109	125	128	java/lang/NullPointerException
/*     */     //   122	140	140	java/lang/NullPointerException
/*     */     //   160	174	177	java/lang/NullPointerException
/*     */     //   171	189	189	java/lang/NullPointerException
/*     */     //   203	211	214	java/lang/NullPointerException
/*     */     //   208	235	238	java/lang/NullPointerException
/*     */     //   224	251	254	java/lang/NullPointerException
/*     */     //   248	266	266	java/lang/NullPointerException
/*     */   }
/*     */ 
/*     */ 
/*     */ 
/*     */ 
/*     */ 
/*     */   
/*     */   public String a() {
/* 191 */     return this.j;
/*     */   }
/*     */ 
/*     */ 
/*     */ 
/*     */ 
/*     */ 
/*     */ 
/*     */ 
/*     */ 
/*     */ 
/*     */ 
/*     */ 
/*     */ 
/*     */ 
/*     */ 
/*     */ 
/*     */ 
/*     */   
/*     */   private c2(String paramString1, String paramString2, long paramLong, String paramString3, String paramString4, boolean paramBoolean1, boolean paramBoolean2, boolean paramBoolean3, boolean paramBoolean4) {
/* 211 */     this.c = paramString1;
/*     */     this.l = paramString2;
/*     */     this.f = paramLong;
/*     */     this.j = paramString3;
/*     */     this.e = paramString4;
/*     */     this.g = paramBoolean1;
/*     */     this.a = paramBoolean2;
/*     */     this.d = paramBoolean3;
/*     */     this.h = paramBoolean4;
/*     */   }
/*     */ 
/*     */ 
/*     */ 
/*     */ 
/*     */ 
/*     */ 
/*     */ 
/*     */ 
/*     */ 
/*     */ 
/*     */ 
/*     */ 
/*     */ 
/*     */ 
/*     */ 
/*     */   
/*     */   public boolean b() {
/* 238 */     return this.g;
/*     */   }
/*     */ 
/*     */ 
/*     */ 
/*     */ 
/*     */   
/*     */   public boolean d() {
/* 246 */     return this.a;
/*     */   }
/*     */   
/*     */   private static boolean a(long paramLong, String paramString1, String paramString2) {
/*     */     // Byte code:
/*     */     //   0: getstatic me/konsolas/aac/c2.n : J
/*     */     //   3: lload_0
/*     */     //   4: lxor
/*     */     //   5: lstore_0
/*     */     //   6: ldc2_w -7995958081339616822
/*     */     //   9: lload_0
/*     */     //   10: <illegal opcode> w : (JJ)[Lme/konsolas/aac/aN;
/*     */     //   15: astore #4
/*     */     //   17: aload_2
/*     */     //   18: aload_3
/*     */     //   19: invokevirtual equals : (Ljava/lang/Object;)Z
/*     */     //   22: aload #4
/*     */     //   24: ifnonnull -> 60
/*     */     //   27: ifeq -> 55
/*     */     //   30: goto -> 43
/*     */     //   33: ldc2_w -7981933613709788358
/*     */     //   36: lload_0
/*     */     //   37: <illegal opcode> w : (Ljava/lang/RuntimeException;JJ)Ljava/lang/RuntimeException;
/*     */     //   42: athrow
/*     */     //   43: iconst_1
/*     */     //   44: ireturn
/*     */     //   45: ldc2_w -7981933613709788358
/*     */     //   48: lload_0
/*     */     //   49: <illegal opcode> w : (Ljava/lang/RuntimeException;JJ)Ljava/lang/RuntimeException;
/*     */     //   54: athrow
/*     */     //   55: aload_2
/*     */     //   56: aload_3
/*     */     //   57: invokevirtual endsWith : (Ljava/lang/String;)Z
/*     */     //   60: aload #4
/*     */     //   62: ifnonnull -> 183
/*     */     //   65: ifeq -> 182
/*     */     //   68: goto -> 81
/*     */     //   71: ldc2_w -7981933613709788358
/*     */     //   74: lload_0
/*     */     //   75: <illegal opcode> w : (Ljava/lang/RuntimeException;JJ)Ljava/lang/RuntimeException;
/*     */     //   80: athrow
/*     */     //   81: aload_2
/*     */     //   82: aload_2
/*     */     //   83: invokevirtual length : ()I
/*     */     //   86: aload_3
/*     */     //   87: invokevirtual length : ()I
/*     */     //   90: isub
/*     */     //   91: iconst_1
/*     */     //   92: isub
/*     */     //   93: invokevirtual charAt : (I)C
/*     */     //   96: aload #4
/*     */     //   98: ifnonnull -> 183
/*     */     //   101: goto -> 114
/*     */     //   104: ldc2_w -7981933613709788358
/*     */     //   107: lload_0
/*     */     //   108: <illegal opcode> w : (Ljava/lang/RuntimeException;JJ)Ljava/lang/RuntimeException;
/*     */     //   113: athrow
/*     */     //   114: bipush #46
/*     */     //   116: if_icmpne -> 182
/*     */     //   119: goto -> 132
/*     */     //   122: ldc2_w -7981933613709788358
/*     */     //   125: lload_0
/*     */     //   126: <illegal opcode> w : (Ljava/lang/RuntimeException;JJ)Ljava/lang/RuntimeException;
/*     */     //   131: athrow
/*     */     //   132: aload_2
/*     */     //   133: invokestatic a : (Ljava/lang/String;)Z
/*     */     //   136: aload #4
/*     */     //   138: ifnonnull -> 183
/*     */     //   141: goto -> 154
/*     */     //   144: ldc2_w -7981933613709788358
/*     */     //   147: lload_0
/*     */     //   148: <illegal opcode> w : (Ljava/lang/RuntimeException;JJ)Ljava/lang/RuntimeException;
/*     */     //   153: athrow
/*     */     //   154: ifne -> 182
/*     */     //   157: goto -> 170
/*     */     //   160: ldc2_w -7981933613709788358
/*     */     //   163: lload_0
/*     */     //   164: <illegal opcode> w : (Ljava/lang/RuntimeException;JJ)Ljava/lang/RuntimeException;
/*     */     //   169: athrow
/*     */     //   170: iconst_1
/*     */     //   171: ireturn
/*     */     //   172: ldc2_w -7981933613709788358
/*     */     //   175: lload_0
/*     */     //   176: <illegal opcode> w : (Ljava/lang/RuntimeException;JJ)Ljava/lang/RuntimeException;
/*     */     //   181: athrow
/*     */     //   182: iconst_0
/*     */     //   183: ireturn
/*     */     // Line number table:
/*     */     //   Java source line number -> byte code offset
/*     */     //   #248	-> 17
/*     */     //   #87	-> 43
/*     */     //   #61	-> 55
/*     */     //   #231	-> 83
/*     */     //   #178	-> 133
/*     */     //   #25	-> 170
/*     */     //   #177	-> 182
/*     */     // Exception table:
/*     */     //   from	to	target	type
/*     */     //   17	30	33	java/lang/NullPointerException
/*     */     //   27	45	45	java/lang/NullPointerException
/*     */     //   60	68	71	java/lang/NullPointerException
/*     */     //   65	101	104	java/lang/NullPointerException
/*     */     //   81	119	122	java/lang/NullPointerException
/*     */     //   114	141	144	java/lang/NullPointerException
/*     */     //   132	157	160	java/lang/NullPointerException
/*     */     //   154	172	172	java/lang/NullPointerException
/*     */   }
/*     */   
/*     */   private static RuntimeException a(RuntimeException paramRuntimeException) {
/*     */     return paramRuntimeException;
/*     */   }
/*     */   
/*     */   private static String a(byte[] paramArrayOfbyte) {
/*     */     byte b1 = 0;
/*     */     int i;
/*     */     char[] arrayOfChar = new char[i = paramArrayOfbyte.length];
/*     */     for (byte b2 = 0; b2 < i; b2++) {
/*     */       int j;
/*     */       if ((j = 0xFF & paramArrayOfbyte[b2]) < 192) {
/*     */         arrayOfChar[b1++] = (char)j;
/*     */       } else if (j < 224) {
/*     */         char c = (char)((char)(j & 0x1F) << 6);
/*     */         j = paramArrayOfbyte[++b2];
/*     */         c = (char)(c | (char)(j & 0x3F));
/*     */         arrayOfChar[b1++] = c;
/*     */       } else if (b2 < i - 2) {
/*     */         char c = (char)((char)(j & 0xF) << 12);
/*     */         j = paramArrayOfbyte[++b2];
/*     */         c = (char)(c | (char)(j & 0x3F) << 6);
/*     */         j = paramArrayOfbyte[++b2];
/*     */         c = (char)(c | (char)(j & 0x3F));
/*     */         arrayOfChar[b1++] = c;
/*     */       } 
/*     */     } 
/*     */     return new String(arrayOfChar, 0, b1);
/*     */   }
/*     */   
/*     */   private static String a(int paramInt, long paramLong) {
/*     */     int i = paramInt ^ (int)(paramLong & 0x7FFFL) ^ 0x6F04;
/*     */     if (p[i] == null) {
/*     */       Object[] arrayOfObject;
/*     */       try {
/*     */         Long long_ = Long.valueOf(Thread.currentThread().getId());
/*     */         arrayOfObject = (Object[])q.get(long_);
/*     */         if (arrayOfObject == null) {
/*     */           arrayOfObject = new Object[3];
/*     */           "ᤥ詵㫛ᖨ盝ﺘ尦撀葁聙䪂Ṣ㪢櫻✐畽䃏᥄⠤펤ᨹ".toCharArray()[12] = (char)("ᤥ詵㫛ᖨ盝ﺘ尦撀葁聙䪂Ṣ㪢櫻✐畽䃏᥄⠤펤ᨹ".toCharArray()[12] ^ 0x6063);
/*     */           arrayOfObject[0] = Cipher.getInstance(a0$cc.G("ᤥ詵㫛ᖨ盝ﺘ尦撀葁聙䪂Ṣ㪢櫻✐畽䃏᥄⠤펤ᨹ".toCharArray(), (short)9260, true, (byte)5));
/*     */           "쮏懀".toCharArray()[0] = (char)("쮏懀".toCharArray()[0] ^ 0x2574);
/*     */           arrayOfObject[1] = SecretKeyFactory.getInstance(a0$cc.G("쮏懀".toCharArray(), (short)13476, false, (byte)4));
/*     */           arrayOfObject[2] = new IvParameterSpec(new byte[8]);
/*     */           q.put(long_, arrayOfObject);
/*     */         } 
/*     */       } catch (Exception exception) {
/*     */         "剩釔㸚埶爓ḎΘ㝯妀廝遊頝ெ㎙텼蛦န聘抜".toCharArray()[1] = (char)("剩釔㸚埶爓ḎΘ㝯妀廝遊頝ெ㎙텼蛦န聘抜".toCharArray()[1] ^ 0x6E5E);
/*     */         throw new RuntimeException(a0$cc.G("剩釔㸚埶爓ḎΘ㝯妀廝遊頝ெ㎙텼蛦န聘抜".toCharArray(), (short)4934, false, (byte)2), exception);
/*     */       } 
/*     */       byte[] arrayOfByte1 = new byte[8];
/*     */       arrayOfByte1[0] = (byte)(int)(paramLong >>> 56L);
/*     */       for (byte b = 1; b < 8; b++)
/*     */         arrayOfByte1[b] = (byte)(int)(paramLong << b * 8 >>> 56L); 
/*     */       DESKeySpec dESKeySpec = new DESKeySpec(arrayOfByte1);
/*     */       SecretKey secretKey = ((SecretKeyFactory)arrayOfObject[1]).generateSecret(dESKeySpec);
/*     */       ((Cipher)arrayOfObject[0]).init(2, secretKey, (IvParameterSpec)arrayOfObject[2]);
/*     */       "ݸ㳓䯍쭥讨‌悽蓆穻䔱".toCharArray()[7] = (char)("ݸ㳓䯍쭥讨‌悽蓆穻䔱".toCharArray()[7] ^ 0x74DC);
/*     */       byte[] arrayOfByte2 = o[i].getBytes(a0$cc.G("ݸ㳓䯍쭥讨‌悽蓆穻䔱".toCharArray(), (short)25674, true, (byte)2));
/*     */       p[i] = a(((Cipher)arrayOfObject[0]).doFinal(arrayOfByte2));
/*     */     } 
/*     */     return p[i];
/*     */   }
/*     */   
/*     */   private static Object a(MethodHandles.Lookup paramLookup, MutableCallSite paramMutableCallSite, String paramString, Object[] paramArrayOfObject) {
/*     */     int i = ((Integer)paramArrayOfObject[0]).intValue();
/*     */     long l = ((Long)paramArrayOfObject[1]).longValue();
/*     */     String str = a(i, l);
/*     */     MethodHandle methodHandle = MethodHandles.constant(String.class, str);
/*     */     paramMutableCallSite.setTarget(MethodHandles.dropArguments(methodHandle, 0, new Class[] { int.class, long.class }));
/*     */     return str;
/*     */   }
/*     */   
/*     */   private static CallSite a(MethodHandles.Lookup paramLookup, String paramString, MethodType paramMethodType) {
/*     */     // Byte code:
/*     */     //   0: new java/lang/invoke/MutableCallSite
/*     */     //   3: dup
/*     */     //   4: aload_2
/*     */     //   5: invokespecial <init> : (Ljava/lang/invoke/MethodType;)V
/*     */     //   8: astore_3
/*     */     //   9: aload_3
/*     */     //   10: ldc_w
/*     */     //   13: ldc_w [Ljava/lang/Object;
/*     */     //   16: aload_2
/*     */     //   17: invokevirtual parameterCount : ()I
/*     */     //   20: invokevirtual asCollector : (Ljava/lang/Class;I)Ljava/lang/invoke/MethodHandle;
/*     */     //   23: iconst_0
/*     */     //   24: iconst_3
/*     */     //   25: anewarray java/lang/Object
/*     */     //   28: dup
/*     */     //   29: iconst_0
/*     */     //   30: aload_0
/*     */     //   31: aastore
/*     */     //   32: dup
/*     */     //   33: iconst_1
/*     */     //   34: aload_3
/*     */     //   35: aastore
/*     */     //   36: dup
/*     */     //   37: iconst_2
/*     */     //   38: aload_1
/*     */     //   39: aastore
/*     */     //   40: invokestatic insertArguments : (Ljava/lang/invoke/MethodHandle;I[Ljava/lang/Object;)Ljava/lang/invoke/MethodHandle;
/*     */     //   43: aload_2
/*     */     //   44: invokestatic explicitCastArguments : (Ljava/lang/invoke/MethodHandle;Ljava/lang/invoke/MethodType;)Ljava/lang/invoke/MethodHandle;
/*     */     //   47: invokevirtual setTarget : (Ljava/lang/invoke/MethodHandle;)V
/*     */     //   50: goto -> 170
/*     */     //   53: astore #4
/*     */     //   55: new java/lang/RuntimeException
/*     */     //   58: dup
/*     */     //   59: new java/lang/StringBuilder
/*     */     //   62: dup
/*     */     //   63: invokespecial <init> : ()V
/*     */     //   66: ldc_w 'ﷸ壨Ǥ鍚ㅝ蠎㗿䚷⫈ᡁ鍮ꉠ㯊ṇ濡⨔옗⓵'
/*     */     //   69: invokevirtual toCharArray : ()[C
/*     */     //   72: dup
/*     */     //   73: dup
/*     */     //   74: iconst_5
/*     */     //   75: dup_x1
/*     */     //   76: caload
/*     */     //   77: sipush #23923
/*     */     //   80: ixor
/*     */     //   81: i2c
/*     */     //   82: castore
/*     */     //   83: sipush #5492
/*     */     //   86: iconst_1
/*     */     //   87: iconst_0
/*     */     //   88: invokestatic U : (Ljava/lang/Object;SZZ)Ljava/lang/String;
/*     */     //   91: invokevirtual append : (Ljava/lang/String;)Ljava/lang/StringBuilder;
/*     */     //   94: ldc_w '鑹঍蟜㓮'
/*     */     //   97: invokevirtual toCharArray : ()[C
/*     */     //   100: dup
/*     */     //   101: dup
/*     */     //   102: iconst_1
/*     */     //   103: dup_x1
/*     */     //   104: caload
/*     */     //   105: sipush #9333
/*     */     //   108: ixor
/*     */     //   109: i2c
/*     */     //   110: castore
/*     */     //   111: sipush #16814
/*     */     //   114: iconst_1
/*     */     //   115: iconst_0
/*     */     //   116: invokestatic U : (Ljava/lang/Object;SZZ)Ljava/lang/String;
/*     */     //   119: invokevirtual append : (Ljava/lang/String;)Ljava/lang/StringBuilder;
/*     */     //   122: aload_1
/*     */     //   123: invokevirtual append : (Ljava/lang/String;)Ljava/lang/StringBuilder;
/*     */     //   126: ldc_w '黎撤銮察'
/*     */     //   129: invokevirtual toCharArray : ()[C
/*     */     //   132: dup
/*     */     //   133: dup
/*     */     //   134: iconst_0
/*     */     //   135: dup_x1
/*     */     //   136: caload
/*     */     //   137: sipush #28245
/*     */     //   140: ixor
/*     */     //   141: i2c
/*     */     //   142: castore
/*     */     //   143: sipush #20910
/*     */     //   146: iconst_1
/*     */     //   147: iconst_1
/*     */     //   148: invokestatic U : (Ljava/lang/Object;SZZ)Ljava/lang/String;
/*     */     //   151: invokevirtual append : (Ljava/lang/String;)Ljava/lang/StringBuilder;
/*     */     //   154: aload_2
/*     */     //   155: invokevirtual toString : ()Ljava/lang/String;
/*     */     //   158: invokevirtual append : (Ljava/lang/String;)Ljava/lang/StringBuilder;
/*     */     //   161: invokevirtual toString : ()Ljava/lang/String;
/*     */     //   164: aload #4
/*     */     //   166: invokespecial <init> : (Ljava/lang/String;Ljava/lang/Throwable;)V
/*     */     //   169: athrow
/*     */     //   170: aload_3
/*     */     //   171: areturn
/*     */     // Exception table:
/*     */     //   from	to	target	type
/*     */     //   9	50	53	java/lang/Exception
/*     */   }
/*     */ }


/* Location:              C:\Users\BukkitBypass\Desktop\MatrixAC\AAC\AAC-spigot-5.2.0.jar!\me\konsolas\aac\c2.class
 * Java compiler version: 8 (52.0)
 * JD-Core Version:       1.1.3
 */