/*    */ package me.konsolas.aac;
/*    */ public final class c4 {
/*  3 */   int d = -1;
/*    */   
/*    */   public c4 b() {
/*  6 */     this.g = true;
/*    */ 
/*    */ 
/*    */ 
/*    */ 
/*    */ 
/*    */ 
/*    */ 
/*    */ 
/*    */ 
/*    */ 
/*    */ 
/*    */ 
/*    */ 
/*    */ 
/*    */ 
/*    */ 
/*    */ 
/*    */ 
/*    */ 
/*    */ 
/*    */ 
/*    */ 
/*    */ 
/*    */ 
/*    */     
/* 32 */     return this;
/* 33 */   } public b0 a() { return new b0(this); } public c4 d() { this.b = true; return this; } public c4 c() { this.f = true;
/*    */     return this; }
/*    */ 
/*    */   
/*    */   int e = -1;
/*    */   
/*    */   public c4 a(int paramInt1, int paramInt2, char paramChar, TimeUnit paramTimeUnit, short paramShort) {
/*    */     // Byte code:
/*    */     //   0: iload_2
/*    */     //   1: i2l
/*    */     //   2: bipush #32
/*    */     //   4: lshl
/*    */     //   5: iload_3
/*    */     //   6: i2l
/*    */     //   7: bipush #48
/*    */     //   9: lshl
/*    */     //   10: bipush #32
/*    */     //   12: lushr
/*    */     //   13: lor
/*    */     //   14: iload #5
/*    */     //   16: i2l
/*    */     //   17: bipush #48
/*    */     //   19: lshl
/*    */     //   20: bipush #48
/*    */     //   22: lushr
/*    */     //   23: lor
/*    */     //   24: getstatic me/konsolas/aac/c4.i : J
/*    */     //   27: lxor
/*    */     //   28: lstore #6
/*    */     //   30: ldc2_w -5843842696373948892
/*    */     //   33: lload #6
/*    */     //   35: <illegal opcode> w : (JJ)[Lme/konsolas/aac/aN;
/*    */     //   40: astore #8
/*    */     //   42: iload_1
/*    */     //   43: ifge -> 96
/*    */     //   46: new java/lang/IllegalArgumentException
/*    */     //   49: dup
/*    */     //   50: new java/lang/StringBuilder
/*    */     //   53: dup
/*    */     //   54: invokespecial <init> : ()V
/*    */     //   57: sipush #2029
/*    */     //   60: ldc2_w 4850870700081487465
/*    */     //   63: lload #6
/*    */     //   65: lxor
/*    */     //   66: <illegal opcode> i : (IJ)Ljava/lang/String;
/*    */     //   71: invokevirtual append : (Ljava/lang/String;)Ljava/lang/StringBuilder;
/*    */     //   74: iload_1
/*    */     //   75: invokevirtual append : (I)Ljava/lang/StringBuilder;
/*    */     //   78: invokevirtual toString : ()Ljava/lang/String;
/*    */     //   81: invokespecial <init> : (Ljava/lang/String;)V
/*    */     //   84: athrow
/*    */     //   85: ldc2_w -5787957526038248861
/*    */     //   88: lload #6
/*    */     //   90: <illegal opcode> w : (Ljava/lang/IllegalArgumentException;JJ)Ljava/lang/IllegalArgumentException;
/*    */     //   95: athrow
/*    */     //   96: aload #4
/*    */     //   98: iload_1
/*    */     //   99: i2l
/*    */     //   100: invokevirtual toSeconds : (J)J
/*    */     //   103: lstore #9
/*    */     //   105: aload_0
/*    */     //   106: lload #9
/*    */     //   108: aload #8
/*    */     //   110: ifnonnull -> 152
/*    */     //   113: ldc2_w 2147483647
/*    */     //   116: lcmp
/*    */     //   117: ifle -> 150
/*    */     //   120: goto -> 134
/*    */     //   123: ldc2_w -5787957526038248861
/*    */     //   126: lload #6
/*    */     //   128: <illegal opcode> w : (Ljava/lang/IllegalArgumentException;JJ)Ljava/lang/IllegalArgumentException;
/*    */     //   133: athrow
/*    */     //   134: ldc 2147483647
/*    */     //   136: goto -> 153
/*    */     //   139: ldc2_w -5787957526038248861
/*    */     //   142: lload #6
/*    */     //   144: <illegal opcode> w : (Ljava/lang/IllegalArgumentException;JJ)Ljava/lang/IllegalArgumentException;
/*    */     //   149: athrow
/*    */     //   150: lload #9
/*    */     //   152: l2i
/*    */     //   153: putfield d : I
/*    */     //   156: aload_0
/*    */     //   157: areturn
/*    */     // Line number table:
/*    */     //   Java source line number -> byte code offset
/*    */     //   #15	-> 42
/*    */     //   #5	-> 96
/*    */     //   #26	-> 105
/*    */     //   #14	-> 134
/*    */     //   #2	-> 150
/*    */     //   #21	-> 156
/*    */     // Exception table:
/*    */     //   from	to	target	type
/*    */     //   42	85	85	java/lang/IllegalArgumentException
/*    */     //   105	120	123	java/lang/IllegalArgumentException
/*    */     //   113	139	139	java/lang/IllegalArgumentException
/*    */   }
/*    */   
/*    */   public c4 c(int paramInt, long paramLong, TimeUnit paramTimeUnit) {
/*    */     // Byte code:
/*    */     //   0: getstatic me/konsolas/aac/c4.i : J
/*    */     //   3: lload_2
/*    */     //   4: lxor
/*    */     //   5: lstore_2
/*    */     //   6: ldc2_w 7956678509022768809
/*    */     //   9: lload_2
/*    */     //   10: <illegal opcode> w : (JJ)[Lme/konsolas/aac/aN;
/*    */     //   15: astore #5
/*    */     //   17: iload_1
/*    */     //   18: ifge -> 69
/*    */     //   21: new java/lang/IllegalArgumentException
/*    */     //   24: dup
/*    */     //   25: new java/lang/StringBuilder
/*    */     //   28: dup
/*    */     //   29: invokespecial <init> : ()V
/*    */     //   32: sipush #10103
/*    */     //   35: ldc2_w 265301100702596735
/*    */     //   38: lload_2
/*    */     //   39: lxor
/*    */     //   40: <illegal opcode> i : (IJ)Ljava/lang/String;
/*    */     //   45: invokevirtual append : (Ljava/lang/String;)Ljava/lang/StringBuilder;
/*    */     //   48: iload_1
/*    */     //   49: invokevirtual append : (I)Ljava/lang/StringBuilder;
/*    */     //   52: invokevirtual toString : ()Ljava/lang/String;
/*    */     //   55: invokespecial <init> : (Ljava/lang/String;)V
/*    */     //   58: athrow
/*    */     //   59: ldc2_w 8007479022196277998
/*    */     //   62: lload_2
/*    */     //   63: <illegal opcode> w : (Ljava/lang/IllegalArgumentException;JJ)Ljava/lang/IllegalArgumentException;
/*    */     //   68: athrow
/*    */     //   69: aload #4
/*    */     //   71: iload_1
/*    */     //   72: i2l
/*    */     //   73: invokevirtual toSeconds : (J)J
/*    */     //   76: lstore #6
/*    */     //   78: aload_0
/*    */     //   79: lload #6
/*    */     //   81: aload #5
/*    */     //   83: ifnonnull -> 123
/*    */     //   86: ldc2_w 2147483647
/*    */     //   89: lcmp
/*    */     //   90: ifle -> 121
/*    */     //   93: goto -> 106
/*    */     //   96: ldc2_w 8007479022196277998
/*    */     //   99: lload_2
/*    */     //   100: <illegal opcode> w : (Ljava/lang/IllegalArgumentException;JJ)Ljava/lang/IllegalArgumentException;
/*    */     //   105: athrow
/*    */     //   106: ldc 2147483647
/*    */     //   108: goto -> 124
/*    */     //   111: ldc2_w 8007479022196277998
/*    */     //   114: lload_2
/*    */     //   115: <illegal opcode> w : (Ljava/lang/IllegalArgumentException;JJ)Ljava/lang/IllegalArgumentException;
/*    */     //   120: athrow
/*    */     //   121: lload #6
/*    */     //   123: l2i
/*    */     //   124: putfield e : I
/*    */     //   127: aload_0
/*    */     //   128: areturn
/*    */     // Line number table:
/*    */     //   Java source line number -> byte code offset
/*    */     //   #16	-> 17
/*    */     //   #12	-> 69
/*    */     //   #23	-> 78
/*    */     //   #11	-> 106
/*    */     //   #30	-> 121
/*    */     //   #18	-> 127
/*    */     // Exception table:
/*    */     //   from	to	target	type
/*    */     //   17	59	59	java/lang/IllegalArgumentException
/*    */     //   78	93	96	java/lang/IllegalArgumentException
/*    */     //   86	111	111	java/lang/IllegalArgumentException
/*    */   }
/*    */   
/*    */   int a = -1;
/*    */   boolean g;
/*    */   boolean c;
/*    */   boolean b;
/*    */   boolean f;
/*    */   boolean h;
/*    */   private static final long i = nc.a(-1419962337570244208L, -2843480687849660456L, MethodHandles.lookup().lookupClass()).a(66765704085642L);
/*    */   private static final String[] j;
/*    */   private static final String[] k;
/*    */   private static final Map l = new HashMap<>(13);
/*    */   
/*    */   public c4 b(long paramLong, int paramInt, TimeUnit paramTimeUnit) {
/*    */     // Byte code:
/*    */     //   0: getstatic me/konsolas/aac/c4.i : J
/*    */     //   3: lload_1
/*    */     //   4: lxor
/*    */     //   5: lstore_1
/*    */     //   6: iload_3
/*    */     //   7: ifge -> 58
/*    */     //   10: new java/lang/IllegalArgumentException
/*    */     //   13: dup
/*    */     //   14: new java/lang/StringBuilder
/*    */     //   17: dup
/*    */     //   18: invokespecial <init> : ()V
/*    */     //   21: sipush #27943
/*    */     //   24: ldc2_w 3114667973398169176
/*    */     //   27: lload_1
/*    */     //   28: lxor
/*    */     //   29: <illegal opcode> i : (IJ)Ljava/lang/String;
/*    */     //   34: invokevirtual append : (Ljava/lang/String;)Ljava/lang/StringBuilder;
/*    */     //   37: iload_3
/*    */     //   38: invokevirtual append : (I)Ljava/lang/StringBuilder;
/*    */     //   41: invokevirtual toString : ()Ljava/lang/String;
/*    */     //   44: invokespecial <init> : (Ljava/lang/String;)V
/*    */     //   47: athrow
/*    */     //   48: ldc2_w -2498300246913748838
/*    */     //   51: lload_1
/*    */     //   52: <illegal opcode> w : (Ljava/lang/IllegalArgumentException;JJ)Ljava/lang/IllegalArgumentException;
/*    */     //   57: athrow
/*    */     //   58: aload #4
/*    */     //   60: iload_3
/*    */     //   61: i2l
/*    */     //   62: invokevirtual toSeconds : (J)J
/*    */     //   65: lstore #5
/*    */     //   67: aload_0
/*    */     //   68: lload #5
/*    */     //   70: lload_1
/*    */     //   71: lconst_0
/*    */     //   72: lcmp
/*    */     //   73: ifle -> 100
/*    */     //   76: ldc2_w 2147483647
/*    */     //   79: lcmp
/*    */     //   80: ifle -> 98
/*    */     //   83: ldc 2147483647
/*    */     //   85: goto -> 101
/*    */     //   88: ldc2_w -2498300246913748838
/*    */     //   91: lload_1
/*    */     //   92: <illegal opcode> w : (Ljava/lang/IllegalArgumentException;JJ)Ljava/lang/IllegalArgumentException;
/*    */     //   97: athrow
/*    */     //   98: lload #5
/*    */     //   100: l2i
/*    */     //   101: putfield a : I
/*    */     //   104: aload_0
/*    */     //   105: areturn
/*    */     // Line number table:
/*    */     //   Java source line number -> byte code offset
/*    */     //   #19	-> 6
/*    */     //   #24	-> 58
/*    */     //   #25	-> 67
/*    */     //   #22	-> 83
/*    */     //   #20	-> 98
/*    */     //   #4	-> 104
/*    */     // Exception table:
/*    */     //   from	to	target	type
/*    */     //   6	48	48	java/lang/IllegalArgumentException
/*    */     //   67	88	88	java/lang/IllegalArgumentException
/*    */   }
/*    */   
/*    */   public c4 a() {
/*    */     this.c = true;
/*    */     return this;
/*    */   }
/*    */   
/*    */   public c4 e() {
/*    */     this.h = true;
/*    */     return this;
/*    */   }
/*    */   
/*    */   static {
/*    */     long l = i ^ 0x625585473DDCL;
/*    */     "㦂翚㹐ᜢ淲먆␷핞戺瞅鴍Ɤ脇뱒尗࿤씪❭ﷃြ".toCharArray()[12] = (char)("㦂翚㹐ᜢ淲먆␷핞戺瞅鴍Ɤ脇뱒尗࿤씪❭ﷃြ".toCharArray()[12] ^ 0x4DFE);
/*    */     "?풏놘Ӵ".toCharArray()[0] = (char)("?풏놘Ӵ".toCharArray()[0] ^ 0x6CA5);
/*    */     (new byte[8])[0] = (byte)(int)(l >>> 56L);
/*    */     for (byte b1 = 1; b1 < 8; b1++)
/*    */       (new byte[8])[b1] = (byte)(int)(l << b1 * 8 >>> 56L); 
/*    */     Cipher cipher;
/*    */     (cipher = Cipher.getInstance(hY$g6.H("㦂翚㹐ᜢ淲먆␷핞戺瞅鴍Ɤ脇뱒尗࿤씪❭ﷃြ".toCharArray(), (short)24766, (byte)5, (byte)1))).init(2, SecretKeyFactory.getInstance(hY$g6.H("?풏놘Ӵ".toCharArray(), (short)22112, (byte)0, (byte)4)).generateSecret(new DESKeySpec(new byte[8])), new IvParameterSpec(new byte[8]));
/*    */     String[] arrayOfString = new String[3];
/*    */     boolean bool = false;
/*    */     "ᮠꎩⰛ蛜薼⢉ရ猋芨䩸㠄⨴炗껦Ⱁ踣ʴ떓둰◝ડ㝏섗ﰅ撏哸㚼㬬㵳ﳿ㊦哚ꔆ吆㧽핤匹㔶㜝짨铓쁃⍅䘕畑⤈苫퓐橝썅使띱谁싮椠뼃愃鸹黉７ꞹ㧆甝춄ꡒ܌鼁貋猼蹇ᭃꜗ?⠧ẝᦍ晔掦亩闿䉂藙雳졀痵䗘ᖹ糴".toCharArray()[81] = (char)("ᮠꎩⰛ蛜薼⢉ရ猋芨䩸㠄⨴炗껦Ⱁ踣ʴ떓둰◝ડ㝏섗ﰅ撏哸㚼㬬㵳ﳿ㊦哚ꔆ吆㧽핤匹㔶㜝짨铓쁃⍅䘕畑⤈苫퓐橝썅使띱谁싮椠뼃愃鸹黉７ꞹ㧆甝춄ꡒ܌鼁貋猼蹇ᭃꜗ?⠧ẝᦍ晔掦亩闿䉂藙雳졀痵䗘ᖹ糴".toCharArray()[81] ^ 0x242);
/*    */     String str;
/*    */     int i = (str = hY$g6.H("ᮠꎩⰛ蛜薼⢉ရ猋芨䩸㠄⨴炗껦Ⱁ踣ʴ떓둰◝ડ㝏섗ﰅ撏哸㚼㬬㵳ﳿ㊦哚ꔆ吆㧽핤匹㔶㜝짨铓쁃⍅䘕畑⤈苫퓐橝썅使띱谁싮椠뼃愃鸹黉７ꞹ㧆甝춄ꡒ܌鼁貋猼蹇ᭃꜗ?⠧ẝᦍ晔掦亩闿䉂藙雳졀痵䗘ᖹ糴".toCharArray(), (short)14992, (byte)3, (byte)4)).length();
/*    */     byte b2 = 32;
/*    */     byte b = -1;
/*    */     while (true);
/*    */   }
/*    */   
/*    */   private static IllegalArgumentException a(IllegalArgumentException paramIllegalArgumentException) {
/*    */     return paramIllegalArgumentException;
/*    */   }
/*    */   
/*    */   private static String a(byte[] paramArrayOfbyte) {
/*    */     byte b1 = 0;
/*    */     int i;
/*    */     char[] arrayOfChar = new char[i = paramArrayOfbyte.length];
/*    */     for (byte b2 = 0; b2 < i; b2++) {
/*    */       int j;
/*    */       if ((j = 0xFF & paramArrayOfbyte[b2]) < 192) {
/*    */         arrayOfChar[b1++] = (char)j;
/*    */       } else if (j < 224) {
/*    */         char c = (char)((char)(j & 0x1F) << 6);
/*    */         j = paramArrayOfbyte[++b2];
/*    */         c = (char)(c | (char)(j & 0x3F));
/*    */         arrayOfChar[b1++] = c;
/*    */       } else if (b2 < i - 2) {
/*    */         char c = (char)((char)(j & 0xF) << 12);
/*    */         j = paramArrayOfbyte[++b2];
/*    */         c = (char)(c | (char)(j & 0x3F) << 6);
/*    */         j = paramArrayOfbyte[++b2];
/*    */         c = (char)(c | (char)(j & 0x3F));
/*    */         arrayOfChar[b1++] = c;
/*    */       } 
/*    */     } 
/*    */     return new String(arrayOfChar, 0, b1);
/*    */   }
/*    */   
/*    */   private static String a(int paramInt, long paramLong) {
/*    */     int i = paramInt ^ (int)(paramLong & 0x7FFFL) ^ 0x3786;
/*    */     if (k[i] == null) {
/*    */       Object[] arrayOfObject;
/*    */       try {
/*    */         Long long_ = Long.valueOf(Thread.currentThread().getId());
/*    */         arrayOfObject = (Object[])l.get(long_);
/*    */         if (arrayOfObject == null) {
/*    */           arrayOfObject = new Object[3];
/*    */           "퍲䐚ꛪ퍺꧑ꂀ蟇焜㉞췣?䕹鿤䫡狵椠砨".toCharArray()[16] = (char)("퍲䐚ꛪ퍺꧑ꂀ蟇焜㉞췣?䕹鿤䫡狵椠砨".toCharArray()[16] ^ 0x6A2B);
/*    */           arrayOfObject[0] = Cipher.getInstance(da$gx.U("퍲䐚ꛪ퍺꧑ꂀ蟇焜㉞췣?䕹鿤䫡狵椠砨".toCharArray(), (short)5242, false, false));
/*    */           "☮붖⿬㶳".toCharArray()[1] = (char)("☮붖⿬㶳".toCharArray()[1] ^ 0x4C61);
/*    */           arrayOfObject[1] = SecretKeyFactory.getInstance(da$gx.U("☮붖⿬㶳".toCharArray(), (short)11438, true, false));
/*    */           arrayOfObject[2] = new IvParameterSpec(new byte[8]);
/*    */           l.put(long_, arrayOfObject);
/*    */         } 
/*    */       } catch (Exception exception) {
/*    */         "퇦컌ꃸ얲蠬ꚃ?후䃆혈⾶௃覱딻笾Ⳳ穌菉ᘊ".toCharArray()[7] = (char)("퇦컌ꃸ얲蠬ꚃ?후䃆혈⾶௃覱딻笾Ⳳ穌菉ᘊ".toCharArray()[7] ^ 0x3D8B);
/*    */         throw new RuntimeException(da$gx.U("퇦컌ꃸ얲蠬ꚃ?후䃆혈⾶௃覱딻笾Ⳳ穌菉ᘊ".toCharArray(), (short)6377, true, false), exception);
/*    */       } 
/*    */       byte[] arrayOfByte1 = new byte[8];
/*    */       arrayOfByte1[0] = (byte)(int)(paramLong >>> 56L);
/*    */       for (byte b = 1; b < 8; b++)
/*    */         arrayOfByte1[b] = (byte)(int)(paramLong << b * 8 >>> 56L); 
/*    */       DESKeySpec dESKeySpec = new DESKeySpec(arrayOfByte1);
/*    */       SecretKey secretKey = ((SecretKeyFactory)arrayOfObject[1]).generateSecret(dESKeySpec);
/*    */       ((Cipher)arrayOfObject[0]).init(2, secretKey, (IvParameterSpec)arrayOfObject[2]);
/*    */       "厨ⵢ䫪ᭂ뀘嘦懏驑캁天".toCharArray()[1] = (char)("厨ⵢ䫪ᭂ뀘嘦懏驑캁天".toCharArray()[1] ^ 0x6744);
/*    */       byte[] arrayOfByte2 = j[i].getBytes(da$gx.U("厨ⵢ䫪ᭂ뀘嘦懏驑캁天".toCharArray(), (short)26191, true, true));
/*    */       k[i] = a(((Cipher)arrayOfObject[0]).doFinal(arrayOfByte2));
/*    */     } 
/*    */     return k[i];
/*    */   }
/*    */   
/*    */   private static Object a(MethodHandles.Lookup paramLookup, MutableCallSite paramMutableCallSite, String paramString, Object[] paramArrayOfObject) {
/*    */     int i = ((Integer)paramArrayOfObject[0]).intValue();
/*    */     long l = ((Long)paramArrayOfObject[1]).longValue();
/*    */     String str = a(i, l);
/*    */     MethodHandle methodHandle = MethodHandles.constant(String.class, str);
/*    */     paramMutableCallSite.setTarget(MethodHandles.dropArguments(methodHandle, 0, new Class[] { int.class, long.class }));
/*    */     return str;
/*    */   }
/*    */   
/*    */   private static CallSite a(MethodHandles.Lookup paramLookup, String paramString, MethodType paramMethodType) {
/*    */     // Byte code:
/*    */     //   0: new java/lang/invoke/MutableCallSite
/*    */     //   3: dup
/*    */     //   4: aload_2
/*    */     //   5: invokespecial <init> : (Ljava/lang/invoke/MethodType;)V
/*    */     //   8: astore_3
/*    */     //   9: aload_3
/*    */     //   10: ldc_w
/*    */     //   13: ldc_w [Ljava/lang/Object;
/*    */     //   16: aload_2
/*    */     //   17: invokevirtual parameterCount : ()I
/*    */     //   20: invokevirtual asCollector : (Ljava/lang/Class;I)Ljava/lang/invoke/MethodHandle;
/*    */     //   23: iconst_0
/*    */     //   24: iconst_3
/*    */     //   25: anewarray java/lang/Object
/*    */     //   28: dup
/*    */     //   29: iconst_0
/*    */     //   30: aload_0
/*    */     //   31: aastore
/*    */     //   32: dup
/*    */     //   33: iconst_1
/*    */     //   34: aload_3
/*    */     //   35: aastore
/*    */     //   36: dup
/*    */     //   37: iconst_2
/*    */     //   38: aload_1
/*    */     //   39: aastore
/*    */     //   40: invokestatic insertArguments : (Ljava/lang/invoke/MethodHandle;I[Ljava/lang/Object;)Ljava/lang/invoke/MethodHandle;
/*    */     //   43: aload_2
/*    */     //   44: invokestatic explicitCastArguments : (Ljava/lang/invoke/MethodHandle;Ljava/lang/invoke/MethodType;)Ljava/lang/invoke/MethodHandle;
/*    */     //   47: invokevirtual setTarget : (Ljava/lang/invoke/MethodHandle;)V
/*    */     //   50: goto -> 171
/*    */     //   53: astore #4
/*    */     //   55: new java/lang/RuntimeException
/*    */     //   58: dup
/*    */     //   59: new java/lang/StringBuilder
/*    */     //   62: dup
/*    */     //   63: invokespecial <init> : ()V
/*    */     //   66: ldc_w '퍔駯㤈숃͉邠鮥篟흼῰ﶸ讔༾䦑쟸煥⋀㌱ឋ'
/*    */     //   69: invokevirtual toCharArray : ()[C
/*    */     //   72: dup
/*    */     //   73: dup
/*    */     //   74: bipush #10
/*    */     //   76: dup_x1
/*    */     //   77: caload
/*    */     //   78: sipush #22964
/*    */     //   81: ixor
/*    */     //   82: i2c
/*    */     //   83: castore
/*    */     //   84: sipush #21358
/*    */     //   87: iconst_3
/*    */     //   88: iconst_1
/*    */     //   89: invokestatic H : (Ljava/lang/Object;SBB)Ljava/lang/String;
/*    */     //   92: invokevirtual append : (Ljava/lang/String;)Ljava/lang/StringBuilder;
/*    */     //   95: ldc_w '㦝췁㸎绽'
/*    */     //   98: invokevirtual toCharArray : ()[C
/*    */     //   101: dup
/*    */     //   102: dup
/*    */     //   103: iconst_0
/*    */     //   104: dup_x1
/*    */     //   105: caload
/*    */     //   106: sipush #10713
/*    */     //   109: ixor
/*    */     //   110: i2c
/*    */     //   111: castore
/*    */     //   112: sipush #15380
/*    */     //   115: iconst_1
/*    */     //   116: iconst_5
/*    */     //   117: invokestatic H : (Ljava/lang/Object;SBB)Ljava/lang/String;
/*    */     //   120: invokevirtual append : (Ljava/lang/String;)Ljava/lang/StringBuilder;
/*    */     //   123: aload_1
/*    */     //   124: invokevirtual append : (Ljava/lang/String;)Ljava/lang/StringBuilder;
/*    */     //   127: ldc_w 'ଲ탍꘶穘'
/*    */     //   130: invokevirtual toCharArray : ()[C
/*    */     //   133: dup
/*    */     //   134: dup
/*    */     //   135: iconst_2
/*    */     //   136: dup_x1
/*    */     //   137: caload
/*    */     //   138: sipush #1645
/*    */     //   141: ixor
/*    */     //   142: i2c
/*    */     //   143: castore
/*    */     //   144: sipush #2276
/*    */     //   147: iconst_3
/*    */     //   148: iconst_2
/*    */     //   149: invokestatic H : (Ljava/lang/Object;SBB)Ljava/lang/String;
/*    */     //   152: invokevirtual append : (Ljava/lang/String;)Ljava/lang/StringBuilder;
/*    */     //   155: aload_2
/*    */     //   156: invokevirtual toString : ()Ljava/lang/String;
/*    */     //   159: invokevirtual append : (Ljava/lang/String;)Ljava/lang/StringBuilder;
/*    */     //   162: invokevirtual toString : ()Ljava/lang/String;
/*    */     //   165: aload #4
/*    */     //   167: invokespecial <init> : (Ljava/lang/String;Ljava/lang/Throwable;)V
/*    */     //   170: athrow
/*    */     //   171: aload_3
/*    */     //   172: areturn
/*    */     // Exception table:
/*    */     //   from	to	target	type
/*    */     //   9	50	53	java/lang/Exception
/*    */   }
/*    */ }


/* Location:              C:\Users\BukkitBypass\Desktop\MatrixAC\AAC\AAC-spigot-5.2.0.jar!\me\konsolas\aac\c4.class
 * Java compiler version: 8 (52.0)
 * JD-Core Version:       1.1.3
 */