/*    */ package me.konsolas.aac;
/*    */ 
/*    */ import aacinternal.v;
/*    */ import java.lang.invoke.CallSite;
/*    */ import java.lang.invoke.MethodHandle;
/*    */ import java.lang.invoke.MethodHandles;
/*    */ import java.lang.invoke.MethodType;
/*    */ import java.lang.invoke.MutableCallSite;
/*    */ import java.util.HashMap;
/*    */ import java.util.Map;
/*    */ import javax.crypto.Cipher;
/*    */ import javax.crypto.SecretKey;
/*    */ import javax.crypto.SecretKeyFactory;
/*    */ import javax.crypto.spec.DESKeySpec;
/*    */ import javax.crypto.spec.IvParameterSpec;
/*    */ import org.bukkit.Location;
/*    */ import org.bukkit.entity.Player;
/*    */ 
/*    */ 
/*    */ 
/*    */ 
/*    */ 
/*    */ 
/*    */ 
/*    */ 
/*    */ public class c7
/*    */   extends ck
/*    */ {
/*    */   private long j;
/*    */   private final iV o;
/*    */   private float k;
/*    */   private float w;
/*    */   private float q;
/*    */   private float x;
/*    */   private static final int s = 50;
/*    */   private final double[] f;
/*    */   private final double[] a;
/*    */   private int n;
/*    */   private boolean v;
/*    */   private boolean g;
/*    */   private double h;
/*    */   
/*    */   public void a() {
/* 44 */     this.j = System.currentTimeMillis();
/*    */   }
/*    */   
/*    */   private double u;
/*    */   private float i;
/*    */   private final cU l;
/*    */   private final cF p;
/*    */   private final cp m;
/*    */   private final cI t;
/*    */   private final boolean r;
/*    */   private static final long y = nc.a(6816900326009827325L, -7922763173507349436L, MethodHandles.lookup().lookupClass()).a(253848663445155L);
/*    */   private static final String[] z;
/*    */   private static final String[] A;
/*    */   private static final Map B = new HashMap<>(13);
/*    */   
/*    */   private void a(long paramLong, float paramFloat1, float paramFloat2) {
/*    */     // Byte code:
/*    */     //   0: getstatic me/konsolas/aac/c7.y : J
/*    */     //   3: lload_1
/*    */     //   4: lxor
/*    */     //   5: lstore_1
/*    */     //   6: lload_1
/*    */     //   7: dup2
/*    */     //   8: ldc2_w 89433754216553
/*    */     //   11: lxor
/*    */     //   12: lstore #5
/*    */     //   14: dup2
/*    */     //   15: ldc2_w 125071834459046
/*    */     //   18: lxor
/*    */     //   19: dup2
/*    */     //   20: bipush #32
/*    */     //   22: lushr
/*    */     //   23: l2i
/*    */     //   24: istore #7
/*    */     //   26: dup2
/*    */     //   27: bipush #32
/*    */     //   29: lshl
/*    */     //   30: bipush #48
/*    */     //   32: lushr
/*    */     //   33: l2i
/*    */     //   34: istore #8
/*    */     //   36: dup2
/*    */     //   37: bipush #48
/*    */     //   39: lshl
/*    */     //   40: bipush #48
/*    */     //   42: lushr
/*    */     //   43: l2i
/*    */     //   44: istore #9
/*    */     //   46: pop2
/*    */     //   47: dup2
/*    */     //   48: ldc2_w 137176214230393
/*    */     //   51: lxor
/*    */     //   52: lstore #10
/*    */     //   54: dup2
/*    */     //   55: ldc2_w 128634739214649
/*    */     //   58: lxor
/*    */     //   59: lstore #12
/*    */     //   61: dup2
/*    */     //   62: ldc2_w 53437945633501
/*    */     //   65: lxor
/*    */     //   66: lstore #14
/*    */     //   68: dup2
/*    */     //   69: ldc2_w 19869218418717
/*    */     //   72: lxor
/*    */     //   73: lstore #16
/*    */     //   75: dup2
/*    */     //   76: ldc2_w 66379752908104
/*    */     //   79: lxor
/*    */     //   80: lstore #18
/*    */     //   82: dup2
/*    */     //   83: ldc2_w 71414170257787
/*    */     //   86: lxor
/*    */     //   87: lstore #20
/*    */     //   89: pop2
/*    */     //   90: ldc2_w 7233441266952794912
/*    */     //   93: lload_1
/*    */     //   94: <illegal opcode> w : (JJ)Z
/*    */     //   99: istore #22
/*    */     //   101: aload_0
/*    */     //   102: getfield g : Z
/*    */     //   105: iload #22
/*    */     //   107: ifne -> 326
/*    */     //   110: ifeq -> 309
/*    */     //   113: goto -> 126
/*    */     //   116: ldc2_w 7326288228393430439
/*    */     //   119: lload_1
/*    */     //   120: <illegal opcode> w : (Laacinternal/v;JJ)Laacinternal/v;
/*    */     //   125: athrow
/*    */     //   126: aload_0
/*    */     //   127: iconst_0
/*    */     //   128: putfield g : Z
/*    */     //   131: aload_0
/*    */     //   132: aload_0
/*    */     //   133: getfield f : [D
/*    */     //   136: iload #7
/*    */     //   138: swap
/*    */     //   139: iload #8
/*    */     //   141: i2c
/*    */     //   142: swap
/*    */     //   143: iload #9
/*    */     //   145: i2c
/*    */     //   146: swap
/*    */     //   147: ldc2_w 7327801460170984600
/*    */     //   150: lload_1
/*    */     //   151: <illegal opcode> w : (ICC[DJJ)D
/*    */     //   156: putfield h : D
/*    */     //   159: aload_0
/*    */     //   160: aload_0
/*    */     //   161: getfield a : [D
/*    */     //   164: iload #7
/*    */     //   166: swap
/*    */     //   167: iload #8
/*    */     //   169: i2c
/*    */     //   170: swap
/*    */     //   171: iload #9
/*    */     //   173: i2c
/*    */     //   174: swap
/*    */     //   175: ldc2_w 7327801460170984600
/*    */     //   178: lload_1
/*    */     //   179: <illegal opcode> w : (ICC[DJJ)D
/*    */     //   184: putfield u : D
/*    */     //   187: aload_0
/*    */     //   188: getfield h : D
/*    */     //   191: lload #18
/*    */     //   193: dup2_x2
/*    */     //   194: pop2
/*    */     //   195: invokestatic f : (JD)D
/*    */     //   198: dstore #23
/*    */     //   200: aload_0
/*    */     //   201: getfield u : D
/*    */     //   204: lload #5
/*    */     //   206: invokestatic c : (DJ)D
/*    */     //   209: dstore #25
/*    */     //   211: lload #12
/*    */     //   213: dload #23
/*    */     //   215: ldc2_w 7207750349598527673
/*    */     //   218: lload_1
/*    */     //   219: <illegal opcode> w : (JDJJ)I
/*    */     //   224: istore #27
/*    */     //   226: lload #12
/*    */     //   228: dload #25
/*    */     //   230: ldc2_w 7207750349598527673
/*    */     //   233: lload_1
/*    */     //   234: <illegal opcode> w : (JDJJ)I
/*    */     //   239: istore #28
/*    */     //   241: aload_0
/*    */     //   242: iload #22
/*    */     //   244: ifne -> 303
/*    */     //   247: getfield l : Lme/konsolas/aac/cU;
/*    */     //   250: iload #27
/*    */     //   252: iload #28
/*    */     //   254: lload #20
/*    */     //   256: ldc2_w 7301954207172622878
/*    */     //   259: lload_1
/*    */     //   260: <illegal opcode> b : (Lme/konsolas/aac/cU;IIJJJ)Z
/*    */     //   265: ifne -> 302
/*    */     //   268: goto -> 281
/*    */     //   271: ldc2_w 7326288228393430439
/*    */     //   274: lload_1
/*    */     //   275: <illegal opcode> w : (Laacinternal/v;JJ)Laacinternal/v;
/*    */     //   280: athrow
/*    */     //   281: aload_0
/*    */     //   282: iconst_0
/*    */     //   283: putfield n : I
/*    */     //   286: aload_0
/*    */     //   287: iconst_0
/*    */     //   288: putfield v : Z
/*    */     //   291: return
/*    */     //   292: ldc2_w 7326288228393430439
/*    */     //   295: lload_1
/*    */     //   296: <illegal opcode> w : (Laacinternal/v;JJ)Laacinternal/v;
/*    */     //   301: athrow
/*    */     //   302: aload_0
/*    */     //   303: dload #23
/*    */     //   305: d2f
/*    */     //   306: putfield i : F
/*    */     //   309: fload_3
/*    */     //   310: f2d
/*    */     //   311: aload_0
/*    */     //   312: getfield h : D
/*    */     //   315: lload #14
/*    */     //   317: ldc2_w 7307546524733715052
/*    */     //   320: lload_1
/*    */     //   321: <illegal opcode> w : (DDJJJ)I
/*    */     //   326: istore #23
/*    */     //   328: fload #4
/*    */     //   330: f2d
/*    */     //   331: lload #10
/*    */     //   333: dup2_x2
/*    */     //   334: pop2
/*    */     //   335: aload_0
/*    */     //   336: getfield u : D
/*    */     //   339: ldc2_w 7208490523723096398
/*    */     //   342: lload_1
/*    */     //   343: <illegal opcode> w : (JDDJJ)I
/*    */     //   348: istore #24
/*    */     //   350: aload_0
/*    */     //   351: getfield p : Lme/konsolas/aac/cF;
/*    */     //   354: iload #23
/*    */     //   356: lload #16
/*    */     //   358: iload #24
/*    */     //   360: fload_3
/*    */     //   361: fload #4
/*    */     //   363: aload_0
/*    */     //   364: getfield i : F
/*    */     //   367: ldc2_w 7325411930625425916
/*    */     //   370: lload_1
/*    */     //   371: <illegal opcode> b : (Lme/konsolas/aac/cF;IJIFFFJJ)V
/*    */     //   376: return
/*    */     // Line number table:
/*    */     //   Java source line number -> byte code offset
/*    */     //   #23	-> 101
/*    */     //   #56	-> 126
/*    */     //   #31	-> 131
/*    */     //   #12	-> 159
/*    */     //   #24	-> 187
/*    */     //   #35	-> 200
/*    */     //   #14	-> 211
/*    */     //   #47	-> 226
/*    */     //   #16	-> 241
/*    */     //   #48	-> 281
/*    */     //   #25	-> 291
/*    */     //   #29	-> 302
/*    */     //   #2	-> 309
/*    */     //   #30	-> 328
/*    */     //   #7	-> 350
/*    */     //   #17	-> 376
/*    */     // Exception table:
/*    */     //   from	to	target	type
/*    */     //   101	113	116	aacinternal/v
/*    */     //   241	268	271	aacinternal/v
/*    */     //   247	292	292	aacinternal/v
/*    */   }
/*    */   
/*    */   public void b(float paramFloat1, int paramInt1, int paramInt2, short paramShort, float paramFloat2) {
/*    */     // Byte code:
/*    */     //   0: iload_2
/*    */     //   1: i2l
/*    */     //   2: bipush #32
/*    */     //   4: lshl
/*    */     //   5: iload_3
/*    */     //   6: i2l
/*    */     //   7: bipush #48
/*    */     //   9: lshl
/*    */     //   10: bipush #32
/*    */     //   12: lushr
/*    */     //   13: lor
/*    */     //   14: iload #4
/*    */     //   16: i2l
/*    */     //   17: bipush #48
/*    */     //   19: lshl
/*    */     //   20: bipush #48
/*    */     //   22: lushr
/*    */     //   23: lor
/*    */     //   24: getstatic me/konsolas/aac/c7.y : J
/*    */     //   27: lxor
/*    */     //   28: lstore #6
/*    */     //   30: lload #6
/*    */     //   32: dup2
/*    */     //   33: ldc2_w 133907164514174
/*    */     //   36: lxor
/*    */     //   37: lstore #8
/*    */     //   39: dup2
/*    */     //   40: ldc2_w 111285643133048
/*    */     //   43: lxor
/*    */     //   44: lstore #10
/*    */     //   46: dup2
/*    */     //   47: ldc2_w 93699975887929
/*    */     //   50: lxor
/*    */     //   51: lstore #12
/*    */     //   53: dup2
/*    */     //   54: ldc2_w 15345388258342
/*    */     //   57: lxor
/*    */     //   58: lstore #14
/*    */     //   60: dup2
/*    */     //   61: ldc2_w 61413898666959
/*    */     //   64: lxor
/*    */     //   65: dup2
/*    */     //   66: bipush #48
/*    */     //   68: lushr
/*    */     //   69: l2i
/*    */     //   70: istore #16
/*    */     //   72: dup2
/*    */     //   73: bipush #16
/*    */     //   75: lshl
/*    */     //   76: bipush #32
/*    */     //   78: lushr
/*    */     //   79: l2i
/*    */     //   80: istore #17
/*    */     //   82: dup2
/*    */     //   83: bipush #48
/*    */     //   85: lshl
/*    */     //   86: bipush #48
/*    */     //   88: lushr
/*    */     //   89: l2i
/*    */     //   90: istore #18
/*    */     //   92: pop2
/*    */     //   93: pop2
/*    */     //   94: ldc2_w 5940891351674602800
/*    */     //   97: lload #6
/*    */     //   99: <illegal opcode> w : (JJ)Z
/*    */     //   104: istore #19
/*    */     //   106: aload_0
/*    */     //   107: iload #19
/*    */     //   109: ifne -> 174
/*    */     //   112: ldc2_w 5923527703712685635
/*    */     //   115: lload #6
/*    */     //   117: <illegal opcode> b : (Lme/konsolas/aac/ck;JJ)Lorg/bukkit/entity/Player;
/*    */     //   122: ldc2_w 6037822007234027478
/*    */     //   125: lload #6
/*    */     //   127: <illegal opcode> b : (Lorg/bukkit/entity/Player;JJ)Lorg/bukkit/entity/Entity;
/*    */     //   132: ifnull -> 185
/*    */     //   135: goto -> 149
/*    */     //   138: ldc2_w 6033739264135142327
/*    */     //   141: lload #6
/*    */     //   143: <illegal opcode> w : (Laacinternal/v;JJ)Laacinternal/v;
/*    */     //   148: athrow
/*    */     //   149: aload_0
/*    */     //   150: aload_0
/*    */     //   151: fload_1
/*    */     //   152: dup_x1
/*    */     //   153: putfield w : F
/*    */     //   156: putfield x : F
/*    */     //   159: aload_0
/*    */     //   160: goto -> 174
/*    */     //   163: ldc2_w 6033739264135142327
/*    */     //   166: lload #6
/*    */     //   168: <illegal opcode> w : (Laacinternal/v;JJ)Laacinternal/v;
/*    */     //   173: athrow
/*    */     //   174: aload_0
/*    */     //   175: fload #5
/*    */     //   177: dup_x1
/*    */     //   178: putfield k : F
/*    */     //   181: putfield q : F
/*    */     //   184: return
/*    */     //   185: fload #5
/*    */     //   187: aload_0
/*    */     //   188: getfield x : F
/*    */     //   191: fsub
/*    */     //   192: ldc2_w 6013968696229961030
/*    */     //   195: lload #6
/*    */     //   197: <illegal opcode> w : (FJJ)F
/*    */     //   202: fstore #20
/*    */     //   204: fload_1
/*    */     //   205: aload_0
/*    */     //   206: getfield q : F
/*    */     //   209: fsub
/*    */     //   210: ldc2_w 6013968696229961030
/*    */     //   213: lload #6
/*    */     //   215: <illegal opcode> w : (FJJ)F
/*    */     //   220: fstore #21
/*    */     //   222: fload #20
/*    */     //   224: f2d
/*    */     //   225: ldc2_w 0.1
/*    */     //   228: dcmpl
/*    */     //   229: iload #19
/*    */     //   231: ifne -> 586
/*    */     //   234: ifle -> 540
/*    */     //   237: goto -> 251
/*    */     //   240: ldc2_w 6033739264135142327
/*    */     //   243: lload #6
/*    */     //   245: <illegal opcode> w : (Laacinternal/v;JJ)Laacinternal/v;
/*    */     //   250: athrow
/*    */     //   251: fload #21
/*    */     //   253: f2d
/*    */     //   254: ldc2_w 0.1
/*    */     //   257: dcmpl
/*    */     //   258: iload #19
/*    */     //   260: ifne -> 586
/*    */     //   263: goto -> 277
/*    */     //   266: ldc2_w 6033739264135142327
/*    */     //   269: lload #6
/*    */     //   271: <illegal opcode> w : (Laacinternal/v;JJ)Laacinternal/v;
/*    */     //   276: athrow
/*    */     //   277: ifle -> 540
/*    */     //   280: goto -> 294
/*    */     //   283: ldc2_w 6033739264135142327
/*    */     //   286: lload #6
/*    */     //   288: <illegal opcode> w : (Laacinternal/v;JJ)Laacinternal/v;
/*    */     //   293: athrow
/*    */     //   294: fload #20
/*    */     //   296: ldc 180.0
/*    */     //   298: fcmpg
/*    */     //   299: iload #19
/*    */     //   301: ifne -> 586
/*    */     //   304: goto -> 318
/*    */     //   307: ldc2_w 6033739264135142327
/*    */     //   310: lload #6
/*    */     //   312: <illegal opcode> w : (Laacinternal/v;JJ)Laacinternal/v;
/*    */     //   317: athrow
/*    */     //   318: ifge -> 540
/*    */     //   321: goto -> 335
/*    */     //   324: ldc2_w 6033739264135142327
/*    */     //   327: lload #6
/*    */     //   329: <illegal opcode> w : (Laacinternal/v;JJ)Laacinternal/v;
/*    */     //   334: athrow
/*    */     //   335: fload_1
/*    */     //   336: ldc2_w 6013968696229961030
/*    */     //   339: lload #6
/*    */     //   341: <illegal opcode> w : (FJJ)F
/*    */     //   346: ldc 89.0
/*    */     //   348: fcmpg
/*    */     //   349: iload #19
/*    */     //   351: ifne -> 586
/*    */     //   354: goto -> 368
/*    */     //   357: ldc2_w 6033739264135142327
/*    */     //   360: lload #6
/*    */     //   362: <illegal opcode> w : (Laacinternal/v;JJ)Laacinternal/v;
/*    */     //   367: athrow
/*    */     //   368: ifge -> 540
/*    */     //   371: goto -> 385
/*    */     //   374: ldc2_w 6033739264135142327
/*    */     //   377: lload #6
/*    */     //   379: <illegal opcode> w : (Laacinternal/v;JJ)Laacinternal/v;
/*    */     //   384: athrow
/*    */     //   385: aload_0
/*    */     //   386: getfield q : F
/*    */     //   389: ldc2_w 6013968696229961030
/*    */     //   392: lload #6
/*    */     //   394: <illegal opcode> w : (FJJ)F
/*    */     //   399: ldc 89.0
/*    */     //   401: fcmpg
/*    */     //   402: iload #19
/*    */     //   404: ifne -> 586
/*    */     //   407: goto -> 421
/*    */     //   410: ldc2_w 6033739264135142327
/*    */     //   413: lload #6
/*    */     //   415: <illegal opcode> w : (Laacinternal/v;JJ)Laacinternal/v;
/*    */     //   420: athrow
/*    */     //   421: ifge -> 540
/*    */     //   424: goto -> 438
/*    */     //   427: ldc2_w 6033739264135142327
/*    */     //   430: lload #6
/*    */     //   432: <illegal opcode> w : (Laacinternal/v;JJ)Laacinternal/v;
/*    */     //   437: athrow
/*    */     //   438: aload_0
/*    */     //   439: getfield f : [D
/*    */     //   442: aload_0
/*    */     //   443: getfield n : I
/*    */     //   446: fload #20
/*    */     //   448: f2d
/*    */     //   449: dastore
/*    */     //   450: aload_0
/*    */     //   451: getfield a : [D
/*    */     //   454: aload_0
/*    */     //   455: getfield n : I
/*    */     //   458: fload #21
/*    */     //   460: f2d
/*    */     //   461: dastore
/*    */     //   462: aload_0
/*    */     //   463: dup
/*    */     //   464: getfield n : I
/*    */     //   467: iconst_1
/*    */     //   468: iadd
/*    */     //   469: dup_x1
/*    */     //   470: putfield n : I
/*    */     //   473: iload #19
/*    */     //   475: ifne -> 586
/*    */     //   478: goto -> 492
/*    */     //   481: ldc2_w 6033739264135142327
/*    */     //   484: lload #6
/*    */     //   486: <illegal opcode> w : (Laacinternal/v;JJ)Laacinternal/v;
/*    */     //   491: athrow
/*    */     //   492: bipush #50
/*    */     //   494: if_icmpne -> 540
/*    */     //   497: goto -> 511
/*    */     //   500: ldc2_w 6033739264135142327
/*    */     //   503: lload #6
/*    */     //   505: <illegal opcode> w : (Laacinternal/v;JJ)Laacinternal/v;
/*    */     //   510: athrow
/*    */     //   511: aload_0
/*    */     //   512: iconst_0
/*    */     //   513: putfield n : I
/*    */     //   516: aload_0
/*    */     //   517: iconst_1
/*    */     //   518: putfield v : Z
/*    */     //   521: aload_0
/*    */     //   522: iconst_1
/*    */     //   523: putfield g : Z
/*    */     //   526: goto -> 540
/*    */     //   529: ldc2_w 6033739264135142327
/*    */     //   532: lload #6
/*    */     //   534: <illegal opcode> w : (Laacinternal/v;JJ)Laacinternal/v;
/*    */     //   539: athrow
/*    */     //   540: aload_0
/*    */     //   541: fload_1
/*    */     //   542: putfield q : F
/*    */     //   545: aload_0
/*    */     //   546: iload #19
/*    */     //   548: iload_2
/*    */     //   549: iflt -> 593
/*    */     //   552: ifne -> 591
/*    */     //   555: fload #5
/*    */     //   557: putfield x : F
/*    */     //   560: invokestatic currentTimeMillis : ()J
/*    */     //   563: aload_0
/*    */     //   564: getfield j : J
/*    */     //   567: lsub
/*    */     //   568: ldc2_w 500
/*    */     //   571: lcmp
/*    */     //   572: goto -> 586
/*    */     //   575: ldc2_w 6033739264135142327
/*    */     //   578: lload #6
/*    */     //   580: <illegal opcode> w : (Laacinternal/v;JJ)Laacinternal/v;
/*    */     //   585: athrow
/*    */     //   586: ifle -> 590
/*    */     //   589: return
/*    */     //   590: aload_0
/*    */     //   591: iload #19
/*    */     //   593: iload_3
/*    */     //   594: ifle -> 661
/*    */     //   597: ifne -> 655
/*    */     //   600: getfield t : Lme/konsolas/aac/cI;
/*    */     //   603: ifnull -> 654
/*    */     //   606: goto -> 620
/*    */     //   609: ldc2_w 6033739264135142327
/*    */     //   612: lload #6
/*    */     //   614: <illegal opcode> w : (Laacinternal/v;JJ)Laacinternal/v;
/*    */     //   619: athrow
/*    */     //   620: aload_0
/*    */     //   621: getfield t : Lme/konsolas/aac/cI;
/*    */     //   624: fload #21
/*    */     //   626: fload #20
/*    */     //   628: lload #14
/*    */     //   630: ldc2_w 6008921442566020236
/*    */     //   633: lload #6
/*    */     //   635: <illegal opcode> b : (Lme/konsolas/aac/cI;FFJJJ)V
/*    */     //   640: goto -> 654
/*    */     //   643: ldc2_w 6033739264135142327
/*    */     //   646: lload #6
/*    */     //   648: <illegal opcode> w : (Laacinternal/v;JJ)Laacinternal/v;
/*    */     //   653: athrow
/*    */     //   654: aload_0
/*    */     //   655: iload_3
/*    */     //   656: ifle -> 719
/*    */     //   659: iload #19
/*    */     //   661: ifne -> 719
/*    */     //   664: getfield m : Lme/konsolas/aac/cp;
/*    */     //   667: ifnull -> 718
/*    */     //   670: goto -> 684
/*    */     //   673: ldc2_w 6033739264135142327
/*    */     //   676: lload #6
/*    */     //   678: <illegal opcode> w : (Laacinternal/v;JJ)Laacinternal/v;
/*    */     //   683: athrow
/*    */     //   684: aload_0
/*    */     //   685: getfield m : Lme/konsolas/aac/cp;
/*    */     //   688: fload #21
/*    */     //   690: fload #20
/*    */     //   692: lload #10
/*    */     //   694: ldc2_w 5918106316634756886
/*    */     //   697: lload #6
/*    */     //   699: <illegal opcode> b : (Lme/konsolas/aac/cp;FFJJJ)V
/*    */     //   704: goto -> 718
/*    */     //   707: ldc2_w 6033739264135142327
/*    */     //   710: lload #6
/*    */     //   712: <illegal opcode> w : (Laacinternal/v;JJ)Laacinternal/v;
/*    */     //   717: athrow
/*    */     //   718: aload_0
/*    */     //   719: getfield v : Z
/*    */     //   722: iload #19
/*    */     //   724: iload_3
/*    */     //   725: ifle -> 825
/*    */     //   728: ifne -> 823
/*    */     //   731: ifeq -> 819
/*    */     //   734: goto -> 748
/*    */     //   737: ldc2_w 6033739264135142327
/*    */     //   740: lload #6
/*    */     //   742: <illegal opcode> w : (Laacinternal/v;JJ)Laacinternal/v;
/*    */     //   747: athrow
/*    */     //   748: aload_0
/*    */     //   749: iload #19
/*    */     //   751: ifne -> 820
/*    */     //   754: goto -> 768
/*    */     //   757: ldc2_w 6033739264135142327
/*    */     //   760: lload #6
/*    */     //   762: <illegal opcode> w : (Laacinternal/v;JJ)Laacinternal/v;
/*    */     //   767: athrow
/*    */     //   768: getfield l : Lme/konsolas/aac/cU;
/*    */     //   771: ifnull -> 819
/*    */     //   774: goto -> 788
/*    */     //   777: ldc2_w 6033739264135142327
/*    */     //   780: lload #6
/*    */     //   782: <illegal opcode> w : (Laacinternal/v;JJ)Laacinternal/v;
/*    */     //   787: athrow
/*    */     //   788: aload_0
/*    */     //   789: lload #12
/*    */     //   791: fload #20
/*    */     //   793: fload #21
/*    */     //   795: ldc2_w 5916336167063708179
/*    */     //   798: lload #6
/*    */     //   800: <illegal opcode> Ö : (Lme/konsolas/aac/c7;JFFJJ)V
/*    */     //   805: goto -> 819
/*    */     //   808: ldc2_w 6033739264135142327
/*    */     //   811: lload #6
/*    */     //   813: <illegal opcode> w : (Laacinternal/v;JJ)Laacinternal/v;
/*    */     //   818: athrow
/*    */     //   819: aload_0
/*    */     //   820: getfield v : Z
/*    */     //   823: iload #19
/*    */     //   825: ifne -> 882
/*    */     //   828: ifeq -> 1117
/*    */     //   831: goto -> 845
/*    */     //   834: ldc2_w 6033739264135142327
/*    */     //   837: lload #6
/*    */     //   839: <illegal opcode> w : (Laacinternal/v;JJ)Laacinternal/v;
/*    */     //   844: athrow
/*    */     //   845: aload_0
/*    */     //   846: iload #19
/*    */     //   848: ifne -> 886
/*    */     //   851: goto -> 865
/*    */     //   854: ldc2_w 6033739264135142327
/*    */     //   857: lload #6
/*    */     //   859: <illegal opcode> w : (Laacinternal/v;JJ)Laacinternal/v;
/*    */     //   864: athrow
/*    */     //   865: getfield r : Z
/*    */     //   868: goto -> 882
/*    */     //   871: ldc2_w 6033739264135142327
/*    */     //   874: lload #6
/*    */     //   876: <illegal opcode> w : (Laacinternal/v;JJ)Laacinternal/v;
/*    */     //   881: athrow
/*    */     //   882: ifeq -> 1117
/*    */     //   885: aload_0
/*    */     //   886: getfield w : F
/*    */     //   889: f2d
/*    */     //   890: aload_0
/*    */     //   891: getfield w : F
/*    */     //   894: f2d
/*    */     //   895: aload_0
/*    */     //   896: getfield h : D
/*    */     //   899: ddiv
/*    */     //   900: ldc2_w 5916078237556011014
/*    */     //   903: lload #6
/*    */     //   905: <illegal opcode> w : (DJJ)J
/*    */     //   910: l2d
/*    */     //   911: aload_0
/*    */     //   912: getfield h : D
/*    */     //   915: dmul
/*    */     //   916: dsub
/*    */     //   917: invokestatic abs : (D)D
/*    */     //   920: d2f
/*    */     //   921: fstore #22
/*    */     //   923: fload_1
/*    */     //   924: f2d
/*    */     //   925: fload #5
/*    */     //   927: f2d
/*    */     //   928: aload_0
/*    */     //   929: getfield h : D
/*    */     //   932: ddiv
/*    */     //   933: ldc2_w 5916078237556011014
/*    */     //   936: lload #6
/*    */     //   938: <illegal opcode> w : (DJJ)J
/*    */     //   943: l2d
/*    */     //   944: aload_0
/*    */     //   945: getfield h : D
/*    */     //   948: dmul
/*    */     //   949: dsub
/*    */     //   950: invokestatic abs : (D)D
/*    */     //   953: d2f
/*    */     //   954: fstore #23
/*    */     //   956: fload #23
/*    */     //   958: f2d
/*    */     //   959: ldc2_w 1.0E-5
/*    */     //   962: dcmpg
/*    */     //   963: iload #19
/*    */     //   965: iload_2
/*    */     //   966: iflt -> 1012
/*    */     //   969: ifne -> 1010
/*    */     //   972: ifge -> 1117
/*    */     //   975: goto -> 989
/*    */     //   978: ldc2_w 6033739264135142327
/*    */     //   981: lload #6
/*    */     //   983: <illegal opcode> w : (Laacinternal/v;JJ)Laacinternal/v;
/*    */     //   988: athrow
/*    */     //   989: fload #22
/*    */     //   991: f2d
/*    */     //   992: ldc2_w 0.001
/*    */     //   995: dcmpl
/*    */     //   996: goto -> 1010
/*    */     //   999: ldc2_w 6033739264135142327
/*    */     //   1002: lload #6
/*    */     //   1004: <illegal opcode> w : (Laacinternal/v;JJ)Laacinternal/v;
/*    */     //   1009: athrow
/*    */     //   1010: iload #19
/*    */     //   1012: ifne -> 1086
/*    */     //   1015: ifle -> 1117
/*    */     //   1018: goto -> 1032
/*    */     //   1021: ldc2_w 6033739264135142327
/*    */     //   1024: lload #6
/*    */     //   1026: <illegal opcode> w : (Laacinternal/v;JJ)Laacinternal/v;
/*    */     //   1031: athrow
/*    */     //   1032: aload_0
/*    */     //   1033: iload #19
/*    */     //   1035: ifne -> 1090
/*    */     //   1038: goto -> 1052
/*    */     //   1041: ldc2_w 6033739264135142327
/*    */     //   1044: lload #6
/*    */     //   1046: <illegal opcode> w : (Laacinternal/v;JJ)Laacinternal/v;
/*    */     //   1051: athrow
/*    */     //   1052: getfield o : Lme/konsolas/aac/iV;
/*    */     //   1055: iload #16
/*    */     //   1057: i2c
/*    */     //   1058: iload #17
/*    */     //   1060: iload #18
/*    */     //   1062: ldc2_w 6046495105044516777
/*    */     //   1065: lload #6
/*    */     //   1067: <illegal opcode> b : (Lme/konsolas/aac/iV;CIIJJ)Z
/*    */     //   1072: goto -> 1086
/*    */     //   1075: ldc2_w 6033739264135142327
/*    */     //   1078: lload #6
/*    */     //   1080: <illegal opcode> w : (Laacinternal/v;JJ)Laacinternal/v;
/*    */     //   1085: athrow
/*    */     //   1086: ifeq -> 1117
/*    */     //   1089: aload_0
/*    */     //   1090: ldc2_w 6031133811595612135
/*    */     //   1093: lload #6
/*    */     //   1095: <illegal opcode> Ñ : (JJ)Lme/konsolas/aac/eA;
/*    */     //   1100: aload_0
/*    */     //   1101: getfield h : D
/*    */     //   1104: d2f
/*    */     //   1105: lload #8
/*    */     //   1107: ldc2_w 6002275069652277016
/*    */     //   1110: lload #6
/*    */     //   1112: <illegal opcode> b : (Lme/konsolas/aac/ck;Lme/konsolas/aac/eA;FJJJ)V
/*    */     //   1117: return
/*    */     // Line number table:
/*    */     //   Java source line number -> byte code offset
/*    */     //   #42	-> 106
/*    */     //   #55	-> 149
/*    */     //   #18	-> 159
/*    */     //   #38	-> 184
/*    */     //   #1	-> 185
/*    */     //   #21	-> 204
/*    */     //   #11	-> 222
/*    */     //   #19	-> 438
/*    */     //   #41	-> 450
/*    */     //   #28	-> 462
/*    */     //   #37	-> 511
/*    */     //   #3	-> 540
/*    */     //   #8	-> 560
/*    */     //   #36	-> 590
/*    */     //   #40	-> 654
/*    */     //   #6	-> 718
/*    */     //   #50	-> 819
/*    */     //   #32	-> 885
/*    */     //   #5	-> 923
/*    */     //   #45	-> 956
/*    */     //   #13	-> 1032
/*    */     //   #43	-> 1089
/*    */     //   #26	-> 1117
/*    */     // Exception table:
/*    */     //   from	to	target	type
/*    */     //   106	135	138	aacinternal/v
/*    */     //   112	160	163	aacinternal/v
/*    */     //   222	237	240	aacinternal/v
/*    */     //   234	263	266	aacinternal/v
/*    */     //   251	280	283	aacinternal/v
/*    */     //   277	304	307	aacinternal/v
/*    */     //   294	321	324	aacinternal/v
/*    */     //   318	354	357	aacinternal/v
/*    */     //   335	371	374	aacinternal/v
/*    */     //   368	407	410	aacinternal/v
/*    */     //   385	424	427	aacinternal/v
/*    */     //   421	478	481	aacinternal/v
/*    */     //   438	497	500	aacinternal/v
/*    */     //   492	526	529	aacinternal/v
/*    */     //   540	572	575	aacinternal/v
/*    */     //   591	606	609	aacinternal/v
/*    */     //   600	640	643	aacinternal/v
/*    */     //   655	670	673	aacinternal/v
/*    */     //   664	704	707	aacinternal/v
/*    */     //   719	734	737	aacinternal/v
/*    */     //   731	754	757	aacinternal/v
/*    */     //   748	774	777	aacinternal/v
/*    */     //   768	805	808	aacinternal/v
/*    */     //   823	831	834	aacinternal/v
/*    */     //   828	851	854	aacinternal/v
/*    */     //   845	868	871	aacinternal/v
/*    */     //   956	975	978	aacinternal/v
/*    */     //   972	996	999	aacinternal/v
/*    */     //   1010	1018	1021	aacinternal/v
/*    */     //   1015	1038	1041	aacinternal/v
/*    */     //   1032	1072	1075	aacinternal/v
/*    */   }
/*    */   
/*    */   public void a(long paramLong, Location paramLocation) {
/*    */     // Byte code:
/*    */     //   0: getstatic me/konsolas/aac/c7.y : J
/*    */     //   3: lload_1
/*    */     //   4: lxor
/*    */     //   5: lstore_1
/*    */     //   6: aload_0
/*    */     //   7: aload_0
/*    */     //   8: aload_3
/*    */     //   9: ldc2_w -5916744817325886765
/*    */     //   12: lload_1
/*    */     //   13: <illegal opcode> b : (Lorg/bukkit/Location;JJ)F
/*    */     //   18: dup_x1
/*    */     //   19: putfield w : F
/*    */     //   22: putfield x : F
/*    */     //   25: aload_0
/*    */     //   26: aload_0
/*    */     //   27: aload_3
/*    */     //   28: ldc2_w -6005629931425284871
/*    */     //   31: lload_1
/*    */     //   32: <illegal opcode> b : (Lorg/bukkit/Location;JJ)F
/*    */     //   37: dup_x1
/*    */     //   38: putfield k : F
/*    */     //   41: putfield q : F
/*    */     //   44: return
/*    */     // Line number table:
/*    */     //   Java source line number -> byte code offset
/*    */     //   #54	-> 6
/*    */     //   #10	-> 25
/*    */     //   #52	-> 44
/*    */   }
/*    */   
/*    */   public c7(AAC paramAAC, Player paramPlayer, long paramLong) {
/*    */     // Byte code:
/*    */     //   0: getstatic me/konsolas/aac/c7.y : J
/*    */     //   3: lload_3
/*    */     //   4: lxor
/*    */     //   5: lstore_3
/*    */     //   6: lload_3
/*    */     //   7: dup2
/*    */     //   8: ldc2_w 9617721966761
/*    */     //   11: lxor
/*    */     //   12: lstore #5
/*    */     //   14: dup2
/*    */     //   15: ldc2_w 131407990209102
/*    */     //   18: lxor
/*    */     //   19: lstore #7
/*    */     //   21: dup2
/*    */     //   22: ldc2_w 112640477151505
/*    */     //   25: lxor
/*    */     //   26: dup2
/*    */     //   27: bipush #48
/*    */     //   29: lushr
/*    */     //   30: l2i
/*    */     //   31: istore #9
/*    */     //   33: dup2
/*    */     //   34: bipush #16
/*    */     //   36: lshl
/*    */     //   37: bipush #48
/*    */     //   39: lushr
/*    */     //   40: l2i
/*    */     //   41: istore #10
/*    */     //   43: dup2
/*    */     //   44: bipush #32
/*    */     //   46: lshl
/*    */     //   47: bipush #32
/*    */     //   49: lushr
/*    */     //   50: l2i
/*    */     //   51: istore #11
/*    */     //   53: pop2
/*    */     //   54: dup2
/*    */     //   55: ldc2_w 62872004955373
/*    */     //   58: lxor
/*    */     //   59: lstore #12
/*    */     //   61: dup2
/*    */     //   62: ldc2_w 114115974636965
/*    */     //   65: lxor
/*    */     //   66: lstore #14
/*    */     //   68: dup2
/*    */     //   69: ldc2_w 104996554524913
/*    */     //   72: lxor
/*    */     //   73: lstore #16
/*    */     //   75: dup2
/*    */     //   76: ldc2_w 81016108132390
/*    */     //   79: lxor
/*    */     //   80: lstore #18
/*    */     //   82: pop2
/*    */     //   83: ldc2_w 214009185909747776
/*    */     //   86: lload_3
/*    */     //   87: <illegal opcode> w : (JJ)Z
/*    */     //   92: aload_0
/*    */     //   93: iload #9
/*    */     //   95: i2s
/*    */     //   96: iload #10
/*    */     //   98: i2s
/*    */     //   99: aload_1
/*    */     //   100: aload_2
/*    */     //   101: iload #11
/*    */     //   103: sipush #24506
/*    */     //   106: ldc2_w 1770848415410175280
/*    */     //   109: lload_3
/*    */     //   110: lxor
/*    */     //   111: <illegal opcode> k : (IJ)Ljava/lang/String;
/*    */     //   116: invokespecial <init> : (SSLme/konsolas/aac/AAC;Lorg/bukkit/entity/Player;ILjava/lang/String;)V
/*    */     //   119: istore #20
/*    */     //   121: aload_0
/*    */     //   122: new me/konsolas/aac/iV
/*    */     //   125: dup
/*    */     //   126: lload #5
/*    */     //   128: invokespecial <init> : (J)V
/*    */     //   131: putfield o : Lme/konsolas/aac/iV;
/*    */     //   134: aload_0
/*    */     //   135: bipush #50
/*    */     //   137: newarray double
/*    */     //   139: putfield f : [D
/*    */     //   142: aload_0
/*    */     //   143: bipush #50
/*    */     //   145: newarray double
/*    */     //   147: putfield a : [D
/*    */     //   150: aload_0
/*    */     //   151: iconst_0
/*    */     //   152: putfield n : I
/*    */     //   155: aload_0
/*    */     //   156: iconst_0
/*    */     //   157: putfield v : Z
/*    */     //   160: aload_0
/*    */     //   161: aload_0
/*    */     //   162: ldc2_w 244179988898839274
/*    */     //   165: lload_3
/*    */     //   166: <illegal opcode> b : (Lme/konsolas/aac/ck;JJ)Lorg/bukkit/configuration/ConfigurationSection;
/*    */     //   171: sipush #25689
/*    */     //   174: ldc2_w 1705441893102323415
/*    */     //   177: lload_3
/*    */     //   178: lxor
/*    */     //   179: <illegal opcode> k : (IJ)Ljava/lang/String;
/*    */     //   184: ldc2_w 245529704094969344
/*    */     //   187: lload_3
/*    */     //   188: <illegal opcode> b : (Lorg/bukkit/configuration/ConfigurationSection;Ljava/lang/String;JJ)Z
/*    */     //   193: ifeq -> 220
/*    */     //   196: new me/konsolas/aac/cU
/*    */     //   199: dup
/*    */     //   200: aload_1
/*    */     //   201: aload_2
/*    */     //   202: lload #7
/*    */     //   204: invokespecial <init> : (Lme/konsolas/aac/AAC;Lorg/bukkit/entity/Player;J)V
/*    */     //   207: goto -> 221
/*    */     //   210: ldc2_w 189853243598850729
/*    */     //   213: lload_3
/*    */     //   214: <illegal opcode> w : (Laacinternal/v;JJ)Laacinternal/v;
/*    */     //   219: athrow
/*    */     //   220: aconst_null
/*    */     //   221: putfield l : Lme/konsolas/aac/cU;
/*    */     //   224: aload_0
/*    */     //   225: aload_0
/*    */     //   226: ldc2_w 244179988898839274
/*    */     //   229: lload_3
/*    */     //   230: <illegal opcode> b : (Lme/konsolas/aac/ck;JJ)Lorg/bukkit/configuration/ConfigurationSection;
/*    */     //   235: sipush #12016
/*    */     //   238: ldc2_w 2478356120514743423
/*    */     //   241: lload_3
/*    */     //   242: lxor
/*    */     //   243: <illegal opcode> k : (IJ)Ljava/lang/String;
/*    */     //   248: ldc2_w 245529704094969344
/*    */     //   251: lload_3
/*    */     //   252: <illegal opcode> b : (Lorg/bukkit/configuration/ConfigurationSection;Ljava/lang/String;JJ)Z
/*    */     //   257: ifeq -> 284
/*    */     //   260: new me/konsolas/aac/cF
/*    */     //   263: dup
/*    */     //   264: lload #16
/*    */     //   266: aload_1
/*    */     //   267: aload_2
/*    */     //   268: invokespecial <init> : (JLme/konsolas/aac/AAC;Lorg/bukkit/entity/Player;)V
/*    */     //   271: goto -> 285
/*    */     //   274: ldc2_w 189853243598850729
/*    */     //   277: lload_3
/*    */     //   278: <illegal opcode> w : (Laacinternal/v;JJ)Laacinternal/v;
/*    */     //   283: athrow
/*    */     //   284: aconst_null
/*    */     //   285: putfield p : Lme/konsolas/aac/cF;
/*    */     //   288: aload_0
/*    */     //   289: aload_0
/*    */     //   290: ldc2_w 244179988898839274
/*    */     //   293: lload_3
/*    */     //   294: <illegal opcode> b : (Lme/konsolas/aac/ck;JJ)Lorg/bukkit/configuration/ConfigurationSection;
/*    */     //   299: sipush #2223
/*    */     //   302: ldc2_w 3641012227528649255
/*    */     //   305: lload_3
/*    */     //   306: lxor
/*    */     //   307: <illegal opcode> k : (IJ)Ljava/lang/String;
/*    */     //   312: ldc2_w 245529704094969344
/*    */     //   315: lload_3
/*    */     //   316: <illegal opcode> b : (Lorg/bukkit/configuration/ConfigurationSection;Ljava/lang/String;JJ)Z
/*    */     //   321: ifeq -> 348
/*    */     //   324: new me/konsolas/aac/cp
/*    */     //   327: dup
/*    */     //   328: lload #18
/*    */     //   330: aload_1
/*    */     //   331: aload_2
/*    */     //   332: invokespecial <init> : (JLme/konsolas/aac/AAC;Lorg/bukkit/entity/Player;)V
/*    */     //   335: goto -> 349
/*    */     //   338: ldc2_w 189853243598850729
/*    */     //   341: lload_3
/*    */     //   342: <illegal opcode> w : (Laacinternal/v;JJ)Laacinternal/v;
/*    */     //   347: athrow
/*    */     //   348: aconst_null
/*    */     //   349: putfield m : Lme/konsolas/aac/cp;
/*    */     //   352: aload_0
/*    */     //   353: aload_0
/*    */     //   354: ldc2_w 244179988898839274
/*    */     //   357: lload_3
/*    */     //   358: <illegal opcode> b : (Lme/konsolas/aac/ck;JJ)Lorg/bukkit/configuration/ConfigurationSection;
/*    */     //   363: sipush #17776
/*    */     //   366: ldc2_w 9125408350056261627
/*    */     //   369: lload_3
/*    */     //   370: lxor
/*    */     //   371: <illegal opcode> k : (IJ)Ljava/lang/String;
/*    */     //   376: ldc2_w 245529704094969344
/*    */     //   379: lload_3
/*    */     //   380: <illegal opcode> b : (Lorg/bukkit/configuration/ConfigurationSection;Ljava/lang/String;JJ)Z
/*    */     //   385: ifeq -> 412
/*    */     //   388: new me/konsolas/aac/cI
/*    */     //   391: dup
/*    */     //   392: aload_1
/*    */     //   393: aload_2
/*    */     //   394: lload #12
/*    */     //   396: invokespecial <init> : (Lme/konsolas/aac/AAC;Lorg/bukkit/entity/Player;J)V
/*    */     //   399: goto -> 413
/*    */     //   402: ldc2_w 189853243598850729
/*    */     //   405: lload_3
/*    */     //   406: <illegal opcode> w : (Laacinternal/v;JJ)Laacinternal/v;
/*    */     //   411: athrow
/*    */     //   412: aconst_null
/*    */     //   413: putfield t : Lme/konsolas/aac/cI;
/*    */     //   416: aload_0
/*    */     //   417: aload_0
/*    */     //   418: ldc2_w 244179988898839274
/*    */     //   421: lload_3
/*    */     //   422: <illegal opcode> b : (Lme/konsolas/aac/ck;JJ)Lorg/bukkit/configuration/ConfigurationSection;
/*    */     //   427: sipush #2371
/*    */     //   430: ldc2_w 6719222681986427850
/*    */     //   433: lload_3
/*    */     //   434: lxor
/*    */     //   435: <illegal opcode> k : (IJ)Ljava/lang/String;
/*    */     //   440: ldc2_w 245529704094969344
/*    */     //   443: lload_3
/*    */     //   444: <illegal opcode> b : (Lorg/bukkit/configuration/ConfigurationSection;Ljava/lang/String;JJ)Z
/*    */     //   449: putfield r : Z
/*    */     //   452: aload_0
/*    */     //   453: aload_2
/*    */     //   454: ldc2_w 229017730852027918
/*    */     //   457: lload_3
/*    */     //   458: <illegal opcode> b : (Lorg/bukkit/entity/Player;JJ)Lorg/bukkit/Location;
/*    */     //   463: lload #14
/*    */     //   465: dup2_x1
/*    */     //   466: pop2
/*    */     //   467: ldc2_w 218186272061964081
/*    */     //   470: lload_3
/*    */     //   471: <illegal opcode> b : (Lme/konsolas/aac/c7;JLorg/bukkit/Location;JJ)V
/*    */     //   476: iload #20
/*    */     //   478: lload_3
/*    */     //   479: lconst_0
/*    */     //   480: lcmp
/*    */     //   481: ifle -> 488
/*    */     //   484: ifne -> 513
/*    */     //   487: iconst_1
/*    */     //   488: anewarray me/konsolas/aac/aN
/*    */     //   491: ldc2_w 180897986783664983
/*    */     //   494: lload_3
/*    */     //   495: <illegal opcode> w : ([Lme/konsolas/aac/aN;JJ)V
/*    */     //   500: goto -> 513
/*    */     //   503: ldc2_w 189853243598850729
/*    */     //   506: lload_3
/*    */     //   507: <illegal opcode> w : (Laacinternal/v;JJ)Laacinternal/v;
/*    */     //   512: athrow
/*    */     //   513: return
/*    */     // Line number table:
/*    */     //   Java source line number -> byte code offset
/*    */     //   #57	-> 92
/*    */     //   #27	-> 121
/*    */     //   #33	-> 134
/*    */     //   #34	-> 142
/*    */     //   #46	-> 150
/*    */     //   #49	-> 155
/*    */     //   #15	-> 160
/*    */     //   #51	-> 224
/*    */     //   #20	-> 288
/*    */     //   #9	-> 352
/*    */     //   #22	-> 416
/*    */     //   #53	-> 452
/*    */     //   #39	-> 476
/*    */     // Exception table:
/*    */     //   from	to	target	type
/*    */     //   121	210	210	aacinternal/v
/*    */     //   221	274	274	aacinternal/v
/*    */     //   285	338	338	aacinternal/v
/*    */     //   349	402	402	aacinternal/v
/*    */     //   413	500	503	aacinternal/v
/*    */   }
/*    */   
/*    */   static {
/*    */     long l = y ^ 0x3021E0A82289L;
/*    */     "쇃Ⳅ門嶫冚伝Ꭲ썢瑪⵩흪㻲엟၄漅㙇䇡덭羽".toCharArray()[16] = (char)("쇃Ⳅ門嶫冚伝Ꭲ썢瑪⵩흪㻲엟၄漅㙇䇡덭羽".toCharArray()[16] ^ 0x71B4);
/*    */     "ꁏ谬䏊冾".toCharArray()[0] = (char)("ꁏ谬䏊冾".toCharArray()[0] ^ 0x3);
/*    */     (new byte[8])[0] = (byte)(int)(l >>> 56L);
/*    */     for (byte b1 = 1; b1 < 8; b1++)
/*    */       (new byte[8])[b1] = (byte)(int)(l << b1 * 8 >>> 56L); 
/*    */     Cipher cipher;
/*    */     (cipher = Cipher.getInstance(hY$g6.H("쇃Ⳅ門嶫冚伝Ꭲ썢瑪⵩흪㻲엟၄漅㙇䇡덭羽".toCharArray(), (short)18603, (byte)4, (byte)3))).init(2, SecretKeyFactory.getInstance(hY$g6.H("ꁏ谬䏊冾".toCharArray(), (short)17395, (byte)2, (byte)4)).generateSecret(new DESKeySpec(new byte[8])), new IvParameterSpec(new byte[8]));
/*    */     String[] arrayOfString = new String[6];
/*    */     boolean bool = false;
/*    */     "업䶳잎뜬鈘ᯋ䪈恺ꝏ䱴䞍ᕲ쾐й쒭⍝ﵩ輰볓嶃ڀ奃㑔⺲行㾑灶ڄ㗧꽦䚨Ƒ媾?䙝᭹懋쟙韡ﺆ䈉忞䉨ᔓ뉨ᬷ纫欤?滅ۈ톇চ웧킖㇬絘ꚊΑ㾃⌙ഇ䭜㫷㷋럎⶷籿ࡇ퀎鵨㩹㯓䝧Ⓛ聘룼굇車곛୩梡瀒쩫?䒃㫺鎆᪵噌⫑믠꣫␇匠ꨖ꩔좠㋇掉䐸撶淨ᾕᤥ紽更஡ﱦ⫯䴉醮ॸ䯞ᬧ鶍摞脏?苬ᖦᮖ".toCharArray()[101] = (char)("업䶳잎뜬鈘ᯋ䪈恺ꝏ䱴䞍ᕲ쾐й쒭⍝ﵩ輰볓嶃ڀ奃㑔⺲行㾑灶ڄ㗧꽦䚨Ƒ媾?䙝᭹懋쟙韡ﺆ䈉忞䉨ᔓ뉨ᬷ纫欤?滅ۈ톇চ웧킖㇬絘ꚊΑ㾃⌙ഇ䭜㫷㷋럎⶷籿ࡇ퀎鵨㩹㯓䝧Ⓛ聘룼굇車곛୩梡瀒쩫?䒃㫺鎆᪵噌⫑믠꣫␇匠ꨖ꩔좠㋇掉䐸撶淨ᾕᤥ紽更஡ﱦ⫯䴉醮ॸ䯞ᬧ鶍摞脏?苬ᖦᮖ".toCharArray()[101] ^ 0x7E21);
/*    */     String str;
/*    */     int i = (str = hY$g6.H("업䶳잎뜬鈘ᯋ䪈恺ꝏ䱴䞍ᕲ쾐й쒭⍝ﵩ輰볓嶃ڀ奃㑔⺲行㾑灶ڄ㗧꽦䚨Ƒ媾?䙝᭹懋쟙韡ﺆ䈉忞䉨ᔓ뉨ᬷ纫欤?滅ۈ톇চ웧킖㇬絘ꚊΑ㾃⌙ഇ䭜㫷㷋럎⶷籿ࡇ퀎鵨㩹㯓䝧Ⓛ聘룼굇車곛୩梡瀒쩫?䒃㫺鎆᪵噌⫑믠꣫␇匠ꨖ꩔좠㋇掉䐸撶淨ᾕᤥ紽更஡ﱦ⫯䴉醮ॸ䯞ᬧ鶍摞脏?苬ᖦᮖ".toCharArray(), (short)8041, (byte)3, (byte)0)).length();
/*    */     byte b2 = 40;
/*    */     byte b = -1;
/*    */     while (true);
/*    */   }
/*    */   
/*    */   private static v a(v paramv) {
/*    */     return paramv;
/*    */   }
/*    */   
/*    */   private static String b(byte[] paramArrayOfbyte) {
/*    */     byte b1 = 0;
/*    */     int i;
/*    */     char[] arrayOfChar = new char[i = paramArrayOfbyte.length];
/*    */     for (byte b2 = 0; b2 < i; b2++) {
/*    */       int j;
/*    */       if ((j = 0xFF & paramArrayOfbyte[b2]) < 192) {
/*    */         arrayOfChar[b1++] = (char)j;
/*    */       } else if (j < 224) {
/*    */         char c = (char)((char)(j & 0x1F) << 6);
/*    */         j = paramArrayOfbyte[++b2];
/*    */         c = (char)(c | (char)(j & 0x3F));
/*    */         arrayOfChar[b1++] = c;
/*    */       } else if (b2 < i - 2) {
/*    */         char c = (char)((char)(j & 0xF) << 12);
/*    */         j = paramArrayOfbyte[++b2];
/*    */         c = (char)(c | (char)(j & 0x3F) << 6);
/*    */         j = paramArrayOfbyte[++b2];
/*    */         c = (char)(c | (char)(j & 0x3F));
/*    */         arrayOfChar[b1++] = c;
/*    */       } 
/*    */     } 
/*    */     return new String(arrayOfChar, 0, b1);
/*    */   }
/*    */   
/*    */   private static String b(int paramInt, long paramLong) {
/*    */     int i = paramInt ^ (int)(paramLong & 0x7FFFL) ^ 0x615F;
/*    */     if (A[i] == null) {
/*    */       Object[] arrayOfObject;
/*    */       try {
/*    */         Long long_ = Long.valueOf(Thread.currentThread().getId());
/*    */         arrayOfObject = (Object[])B.get(long_);
/*    */         if (arrayOfObject == null) {
/*    */           arrayOfObject = new Object[3];
/*    */           "묇馧拽⾠䐠냼췳墊ኽ碹쓖Ĝ蚥ꙏᨉ⠕涚㔖炭Ⲟ".toCharArray()[18] = (char)("묇馧拽⾠䐠냼췳墊ኽ碹쓖Ĝ蚥ꙏᨉ⠕涚㔖炭Ⲟ".toCharArray()[18] ^ 0x2593);
/*    */           arrayOfObject[0] = Cipher.getInstance(da$gx.U("묇馧拽⾠䐠냼췳墊ኽ碹쓖Ĝ蚥ꙏᨉ⠕涚㔖炭Ⲟ".toCharArray(), (short)17014, false, false));
/*    */           "⽠꼩丽ណ".toCharArray()[0] = (char)("⽠꼩丽ណ".toCharArray()[0] ^ 0x3298);
/*    */           arrayOfObject[1] = SecretKeyFactory.getInstance(da$gx.U("⽠꼩丽ណ".toCharArray(), (short)17199, false, false));
/*    */           arrayOfObject[2] = new IvParameterSpec(new byte[8]);
/*    */           B.put(long_, arrayOfObject);
/*    */         } 
/*    */       } catch (Exception exception) {
/*    */         "⮣줳鍑?ㄠ짖?눔ꐮ쮎ꊰ≧рⷥ㾄뿨䨨괊崼".toCharArray()[7] = (char)("⮣줳鍑?ㄠ짖?눔ꐮ쮎ꊰ≧рⷥ㾄뿨䨨괊崼".toCharArray()[7] ^ 0x2426);
/*    */         throw new RuntimeException(da$gx.U("⮣줳鍑?ㄠ짖?눔ꐮ쮎ꊰ≧рⷥ㾄뿨䨨괊崼".toCharArray(), (short)18314, true, true), exception);
/*    */       } 
/*    */       byte[] arrayOfByte1 = new byte[8];
/*    */       arrayOfByte1[0] = (byte)(int)(paramLong >>> 56L);
/*    */       for (byte b = 1; b < 8; b++)
/*    */         arrayOfByte1[b] = (byte)(int)(paramLong << b * 8 >>> 56L); 
/*    */       DESKeySpec dESKeySpec = new DESKeySpec(arrayOfByte1);
/*    */       SecretKey secretKey = ((SecretKeyFactory)arrayOfObject[1]).generateSecret(dESKeySpec);
/*    */       ((Cipher)arrayOfObject[0]).init(2, secretKey, (IvParameterSpec)arrayOfObject[2]);
/*    */       "轥踣ᓗ턛ꀙ⓲ᗖ岮ᓱ紉".toCharArray()[8] = (char)("轥踣ᓗ턛ꀙ⓲ᗖ岮ᓱ紉".toCharArray()[8] ^ 0x14EF);
/*    */       byte[] arrayOfByte2 = z[i].getBytes(da$gx.U("轥踣ᓗ턛ꀙ⓲ᗖ岮ᓱ紉".toCharArray(), (short)16672, false, false));
/*    */       A[i] = b(((Cipher)arrayOfObject[0]).doFinal(arrayOfByte2));
/*    */     } 
/*    */     return A[i];
/*    */   }
/*    */   
/*    */   private static Object b(MethodHandles.Lookup paramLookup, MutableCallSite paramMutableCallSite, String paramString, Object[] paramArrayOfObject) {
/*    */     int i = ((Integer)paramArrayOfObject[0]).intValue();
/*    */     long l = ((Long)paramArrayOfObject[1]).longValue();
/*    */     String str = b(i, l);
/*    */     MethodHandle methodHandle = MethodHandles.constant(String.class, str);
/*    */     paramMutableCallSite.setTarget(MethodHandles.dropArguments(methodHandle, 0, new Class[] { int.class, long.class }));
/*    */     return str;
/*    */   }
/*    */   
/*    */   private static CallSite b(MethodHandles.Lookup paramLookup, String paramString, MethodType paramMethodType) {
/*    */     // Byte code:
/*    */     //   0: new java/lang/invoke/MutableCallSite
/*    */     //   3: dup
/*    */     //   4: aload_2
/*    */     //   5: invokespecial <init> : (Ljava/lang/invoke/MethodType;)V
/*    */     //   8: astore_3
/*    */     //   9: aload_3
/*    */     //   10: ldc_w
/*    */     //   13: ldc_w [Ljava/lang/Object;
/*    */     //   16: aload_2
/*    */     //   17: invokevirtual parameterCount : ()I
/*    */     //   20: invokevirtual asCollector : (Ljava/lang/Class;I)Ljava/lang/invoke/MethodHandle;
/*    */     //   23: iconst_0
/*    */     //   24: iconst_3
/*    */     //   25: anewarray java/lang/Object
/*    */     //   28: dup
/*    */     //   29: iconst_0
/*    */     //   30: aload_0
/*    */     //   31: aastore
/*    */     //   32: dup
/*    */     //   33: iconst_1
/*    */     //   34: aload_3
/*    */     //   35: aastore
/*    */     //   36: dup
/*    */     //   37: iconst_2
/*    */     //   38: aload_1
/*    */     //   39: aastore
/*    */     //   40: invokestatic insertArguments : (Ljava/lang/invoke/MethodHandle;I[Ljava/lang/Object;)Ljava/lang/invoke/MethodHandle;
/*    */     //   43: aload_2
/*    */     //   44: invokestatic explicitCastArguments : (Ljava/lang/invoke/MethodHandle;Ljava/lang/invoke/MethodType;)Ljava/lang/invoke/MethodHandle;
/*    */     //   47: invokevirtual setTarget : (Ljava/lang/invoke/MethodHandle;)V
/*    */     //   50: goto -> 170
/*    */     //   53: astore #4
/*    */     //   55: new java/lang/RuntimeException
/*    */     //   58: dup
/*    */     //   59: new java/lang/StringBuilder
/*    */     //   62: dup
/*    */     //   63: invokespecial <init> : ()V
/*    */     //   66: ldc_w '餤䂇颔Ԑ轗徺ݛ膥㷲抿᧳爹韴帆袩ҫᇗꈸざ'
/*    */     //   69: invokevirtual toCharArray : ()[C
/*    */     //   72: dup
/*    */     //   73: dup
/*    */     //   74: iconst_3
/*    */     //   75: dup_x1
/*    */     //   76: caload
/*    */     //   77: sipush #30248
/*    */     //   80: ixor
/*    */     //   81: i2c
/*    */     //   82: castore
/*    */     //   83: sipush #1861
/*    */     //   86: iconst_3
/*    */     //   87: iconst_5
/*    */     //   88: invokestatic H : (Ljava/lang/Object;SBB)Ljava/lang/String;
/*    */     //   91: invokevirtual append : (Ljava/lang/String;)Ljava/lang/StringBuilder;
/*    */     //   94: ldc_w '⟼ꅖ?対'
/*    */     //   97: invokevirtual toCharArray : ()[C
/*    */     //   100: dup
/*    */     //   101: dup
/*    */     //   102: iconst_0
/*    */     //   103: dup_x1
/*    */     //   104: caload
/*    */     //   105: sipush #30210
/*    */     //   108: ixor
/*    */     //   109: i2c
/*    */     //   110: castore
/*    */     //   111: sipush #25952
/*    */     //   114: iconst_4
/*    */     //   115: iconst_4
/*    */     //   116: invokestatic H : (Ljava/lang/Object;SBB)Ljava/lang/String;
/*    */     //   119: invokevirtual append : (Ljava/lang/String;)Ljava/lang/StringBuilder;
/*    */     //   122: aload_1
/*    */     //   123: invokevirtual append : (Ljava/lang/String;)Ljava/lang/StringBuilder;
/*    */     //   126: ldc_w '?砫퇕䘄'
/*    */     //   129: invokevirtual toCharArray : ()[C
/*    */     //   132: dup
/*    */     //   133: dup
/*    */     //   134: iconst_2
/*    */     //   135: dup_x1
/*    */     //   136: caload
/*    */     //   137: sipush #10813
/*    */     //   140: ixor
/*    */     //   141: i2c
/*    */     //   142: castore
/*    */     //   143: sipush #31529
/*    */     //   146: iconst_1
/*    */     //   147: iconst_2
/*    */     //   148: invokestatic H : (Ljava/lang/Object;SBB)Ljava/lang/String;
/*    */     //   151: invokevirtual append : (Ljava/lang/String;)Ljava/lang/StringBuilder;
/*    */     //   154: aload_2
/*    */     //   155: invokevirtual toString : ()Ljava/lang/String;
/*    */     //   158: invokevirtual append : (Ljava/lang/String;)Ljava/lang/StringBuilder;
/*    */     //   161: invokevirtual toString : ()Ljava/lang/String;
/*    */     //   164: aload #4
/*    */     //   166: invokespecial <init> : (Ljava/lang/String;Ljava/lang/Throwable;)V
/*    */     //   169: athrow
/*    */     //   170: aload_3
/*    */     //   171: areturn
/*    */     // Exception table:
/*    */     //   from	to	target	type
/*    */     //   9	50	53	java/lang/Exception
/*    */   }
/*    */ }


/* Location:              C:\Users\BukkitBypass\Desktop\MatrixAC\AAC\AAC-spigot-5.2.0.jar!\me\konsolas\aac\c7.class
 * Java compiler version: 8 (52.0)
 * JD-Core Version:       1.1.3
 */