/*   */ package me.konsolas.aac;
/*   */ public abstract class ck { private final AAC e; private final Player d; private final ConfigurationSection c; private static String b;
/* 3 */   protected ConfigurationSection a() { return this.c; }
/*   */   private static final long bb; private static final String[] db; private static final String[] eb; private static final Map fb; public ck(short paramShort1, short paramShort2, AAC paramAAC, Player paramPlayer, int paramInt, String paramString) { // Byte code:
/*   */     //   0: iload_1
/*   */     //   1: i2l
/*   */     //   2: bipush #48
/*   */     //   4: lshl
/*   */     //   5: iload_2
/*   */     //   6: i2l
/*   */     //   7: bipush #48
/*   */     //   9: lshl
/*   */     //   10: bipush #16
/*   */     //   12: lushr
/*   */     //   13: lor
/*   */     //   14: iload #5
/*   */     //   16: i2l
/*   */     //   17: bipush #32
/*   */     //   19: lshl
/*   */     //   20: bipush #32
/*   */     //   22: lushr
/*   */     //   23: lor
/*   */     //   24: getstatic me/konsolas/aac/ck.bb : J
/*   */     //   27: lxor
/*   */     //   28: lstore #7
/*   */     //   30: ldc2_w 3574488608260864363
/*   */     //   33: lload #7
/*   */     //   35: <illegal opcode> w : (JJ)Ljava/lang/String;
/*   */     //   40: aload_0
/*   */     //   41: invokespecial <init> : ()V
/*   */     //   44: astore #9
/*   */     //   46: aload_0
/*   */     //   47: aload_3
/*   */     //   48: aload #9
/*   */     //   50: ifnull -> 117
/*   */     //   53: putfield e : Lme/konsolas/aac/AAC;
/*   */     //   56: aload_0
/*   */     //   57: aload #4
/*   */     //   59: putfield d : Lorg/bukkit/entity/Player;
/*   */     //   62: aload_0
/*   */     //   63: aload #6
/*   */     //   65: ifnonnull -> 116
/*   */     //   68: goto -> 82
/*   */     //   71: ldc2_w 3589103746151050078
/*   */     //   74: lload #7
/*   */     //   76: <illegal opcode> w : (Ljava/lang/IllegalArgumentException;JJ)Ljava/lang/IllegalArgumentException;
/*   */     //   81: athrow
/*   */     //   82: aload_3
/*   */     //   83: invokevirtual getConfig : ()Lorg/bukkit/configuration/file/FileConfiguration;
/*   */     //   86: bipush #33
/*   */     //   88: ldc2_w 7424037993843176755
/*   */     //   91: lload #7
/*   */     //   93: lxor
/*   */     //   94: <illegal opcode> d : (IJ)Ljava/lang/String;
/*   */     //   99: invokevirtual getConfigurationSection : (Ljava/lang/String;)Lorg/bukkit/configuration/ConfigurationSection;
/*   */     //   102: goto -> 155
/*   */     //   105: ldc2_w 3589103746151050078
/*   */     //   108: lload #7
/*   */     //   110: <illegal opcode> w : (Ljava/lang/IllegalArgumentException;JJ)Ljava/lang/IllegalArgumentException;
/*   */     //   115: athrow
/*   */     //   116: aload_3
/*   */     //   117: invokevirtual getConfig : ()Lorg/bukkit/configuration/file/FileConfiguration;
/*   */     //   120: new java/lang/StringBuilder
/*   */     //   123: dup
/*   */     //   124: invokespecial <init> : ()V
/*   */     //   127: sipush #19599
/*   */     //   130: ldc2_w 5566921239747033500
/*   */     //   133: lload #7
/*   */     //   135: lxor
/*   */     //   136: <illegal opcode> d : (IJ)Ljava/lang/String;
/*   */     //   141: invokevirtual append : (Ljava/lang/String;)Ljava/lang/StringBuilder;
/*   */     //   144: aload #6
/*   */     //   146: invokevirtual append : (Ljava/lang/String;)Ljava/lang/StringBuilder;
/*   */     //   149: invokevirtual toString : ()Ljava/lang/String;
/*   */     //   152: invokevirtual getConfigurationSection : (Ljava/lang/String;)Lorg/bukkit/configuration/ConfigurationSection;
/*   */     //   155: putfield c : Lorg/bukkit/configuration/ConfigurationSection;
/*   */     //   158: aload_0
/*   */     //   159: getfield c : Lorg/bukkit/configuration/ConfigurationSection;
/*   */     //   162: ifnonnull -> 216
/*   */     //   165: new java/lang/IllegalArgumentException
/*   */     //   168: dup
/*   */     //   169: new java/lang/StringBuilder
/*   */     //   172: dup
/*   */     //   173: invokespecial <init> : ()V
/*   */     //   176: sipush #31571
/*   */     //   179: ldc2_w 2355287725046713922
/*   */     //   182: lload #7
/*   */     //   184: lxor
/*   */     //   185: <illegal opcode> d : (IJ)Ljava/lang/String;
/*   */     //   190: invokevirtual append : (Ljava/lang/String;)Ljava/lang/StringBuilder;
/*   */     //   193: aload #6
/*   */     //   195: invokevirtual append : (Ljava/lang/String;)Ljava/lang/StringBuilder;
/*   */     //   198: invokevirtual toString : ()Ljava/lang/String;
/*   */     //   201: invokespecial <init> : (Ljava/lang/String;)V
/*   */     //   204: athrow
/*   */     //   205: ldc2_w 3589103746151050078
/*   */     //   208: lload #7
/*   */     //   210: <illegal opcode> w : (Ljava/lang/IllegalArgumentException;JJ)Ljava/lang/IllegalArgumentException;
/*   */     //   215: athrow
/*   */     //   216: return
/*   */     // Line number table:
/*   */     //   Java source line number -> byte code offset
/*   */     //   #2	-> 40
/*   */     //   #10	-> 46
/*   */     //   #6	-> 56
/*   */     //   #1	-> 62
/*   */     //   #8	-> 82
/*   */     //   #11	-> 158
/*   */     //   #12	-> 216
/*   */     // Exception table:
/*   */     //   from	to	target	type
/*   */     //   46	68	71	java/lang/IllegalArgumentException
/*   */     //   53	105	105	java/lang/IllegalArgumentException
/* 4 */     //   155	205	205	java/lang/IllegalArgumentException } public Player a() { return this.d; }
/*   */   
/*   */   public AAC a() {
/* 7 */     return this.e;
/*   */   } protected void a(eA parameA, float paramFloat, long paramLong) {
/* 9 */     paramLong = bb ^ paramLong; long l = paramLong ^ 0x19133000CBA1L; a().a().a(a(), parameA, paramFloat, l);
/*   */   }
/*   */   
/*   */   public static void b(String paramString) {
/*   */     b = paramString;
/*   */   }
/*   */   
/*   */   public static String b() {
/*   */     return b;
/*   */   }
/*   */   
/*   */   static {
/*   */     // Byte code:
/*   */     //   0: ldc2_w 7538031262518855130
/*   */     //   3: ldc2_w 6354659373567953486
/*   */     //   6: invokestatic lookup : ()Ljava/lang/invoke/MethodHandles$Lookup;
/*   */     //   9: invokevirtual lookupClass : ()Ljava/lang/Class;
/*   */     //   12: invokestatic a : (JJLjava/lang/Object;)Lme/konsolas/aac/na;
/*   */     //   15: ldc2_w 19512109258976
/*   */     //   18: invokeinterface a : (J)J
/*   */     //   23: putstatic me/konsolas/aac/ck.bb : J
/*   */     //   26: getstatic me/konsolas/aac/ck.bb : J
/*   */     //   29: ldc2_w 77684202389691
/*   */     //   32: lxor
/*   */     //   33: lstore #9
/*   */     //   35: ldc '绌ﵠ㼲袬㛗'
/*   */     //   37: invokevirtual toCharArray : ()[C
/*   */     //   40: dup
/*   */     //   41: dup
/*   */     //   42: iconst_2
/*   */     //   43: dup_x1
/*   */     //   44: caload
/*   */     //   45: sipush #1108
/*   */     //   48: ixor
/*   */     //   49: i2c
/*   */     //   50: castore
/*   */     //   51: sipush #9850
/*   */     //   54: iconst_0
/*   */     //   55: iconst_1
/*   */     //   56: invokestatic X : (Ljava/lang/Object;SZZ)Ljava/lang/String;
/*   */     //   59: new java/util/HashMap
/*   */     //   62: dup
/*   */     //   63: bipush #13
/*   */     //   65: invokespecial <init> : (I)V
/*   */     //   68: putstatic me/konsolas/aac/ck.fb : Ljava/util/Map;
/*   */     //   71: ldc2_w 3709019738959909222
/*   */     //   74: lload #9
/*   */     //   76: <illegal opcode> w : (Ljava/lang/String;JJ)V
/*   */     //   81: ldc 'ꙗ檈ݵ∘몃ᑫᎧ樵蕸ᢏ︭턅ㇺ狏낀畘횺闙晞譱嗅'
/*   */     //   83: invokevirtual toCharArray : ()[C
/*   */     //   86: dup
/*   */     //   87: dup
/*   */     //   88: bipush #11
/*   */     //   90: dup_x1
/*   */     //   91: caload
/*   */     //   92: sipush #2896
/*   */     //   95: ixor
/*   */     //   96: i2c
/*   */     //   97: castore
/*   */     //   98: sipush #27893
/*   */     //   101: iconst_0
/*   */     //   102: iconst_0
/*   */     //   103: invokestatic X : (Ljava/lang/Object;SZZ)Ljava/lang/String;
/*   */     //   106: invokestatic getInstance : (Ljava/lang/String;)Ljavax/crypto/Cipher;
/*   */     //   109: dup
/*   */     //   110: astore_0
/*   */     //   111: iconst_2
/*   */     //   112: ldc '힐胨暏'
/*   */     //   114: invokevirtual toCharArray : ()[C
/*   */     //   117: dup
/*   */     //   118: dup
/*   */     //   119: iconst_0
/*   */     //   120: dup_x1
/*   */     //   121: caload
/*   */     //   122: sipush #25349
/*   */     //   125: ixor
/*   */     //   126: i2c
/*   */     //   127: castore
/*   */     //   128: sipush #13336
/*   */     //   131: iconst_1
/*   */     //   132: iconst_1
/*   */     //   133: invokestatic X : (Ljava/lang/Object;SZZ)Ljava/lang/String;
/*   */     //   136: invokestatic getInstance : (Ljava/lang/String;)Ljavax/crypto/SecretKeyFactory;
/*   */     //   139: bipush #8
/*   */     //   141: newarray byte
/*   */     //   143: dup
/*   */     //   144: iconst_0
/*   */     //   145: lload #9
/*   */     //   147: bipush #56
/*   */     //   149: lushr
/*   */     //   150: l2i
/*   */     //   151: i2b
/*   */     //   152: bastore
/*   */     //   153: iconst_1
/*   */     //   154: istore_1
/*   */     //   155: iload_1
/*   */     //   156: bipush #8
/*   */     //   158: if_icmpge -> 182
/*   */     //   161: dup
/*   */     //   162: iload_1
/*   */     //   163: lload #9
/*   */     //   165: iload_1
/*   */     //   166: bipush #8
/*   */     //   168: imul
/*   */     //   169: lshl
/*   */     //   170: bipush #56
/*   */     //   172: lushr
/*   */     //   173: l2i
/*   */     //   174: i2b
/*   */     //   175: bastore
/*   */     //   176: iinc #1, 1
/*   */     //   179: goto -> 155
/*   */     //   182: new javax/crypto/spec/DESKeySpec
/*   */     //   185: dup_x1
/*   */     //   186: swap
/*   */     //   187: invokespecial <init> : ([B)V
/*   */     //   190: invokevirtual generateSecret : (Ljava/security/spec/KeySpec;)Ljavax/crypto/SecretKey;
/*   */     //   193: new javax/crypto/spec/IvParameterSpec
/*   */     //   196: dup
/*   */     //   197: bipush #8
/*   */     //   199: newarray byte
/*   */     //   201: invokespecial <init> : ([B)V
/*   */     //   204: invokevirtual init : (ILjava/security/Key;Ljava/security/spec/AlgorithmParameterSpec;)V
/*   */     //   207: iconst_3
/*   */     //   208: anewarray java/lang/String
/*   */     //   211: astore #7
/*   */     //   213: iconst_0
/*   */     //   214: istore #5
/*   */     //   216: ldc '➅潡爳湓꘴ݽ묽㊵보㇈ﰽ势茜虰㻤챤晗䠮緬ഺҤ鍂払孾㜸ᒵᐶ뼠ꇧ財둦攪㲹쭪ť肦ி섟᫻屾궾诡㮠暛ヵ?퓪㟘蒝䓌꟰颳D睭똡迦芮┎ຟ?빴ᇵ࢈슗켢য়ꓕ얅గ➸㘎놯剕ꍋ㞭꿋?鯠㚽㋳䄉ᣠ舓?颽⾄ᷪ䌻䕬眸꣞畚鄌攑䕎斍䚈ࢎ㑜쇜ცⷓ兟㱩'
/*   */     //   218: invokevirtual toCharArray : ()[C
/*   */     //   221: dup
/*   */     //   222: dup
/*   */     //   223: bipush #45
/*   */     //   225: dup_x1
/*   */     //   226: caload
/*   */     //   227: sipush #4466
/*   */     //   230: ixor
/*   */     //   231: i2c
/*   */     //   232: castore
/*   */     //   233: sipush #12264
/*   */     //   236: iconst_1
/*   */     //   237: iconst_0
/*   */     //   238: invokestatic X : (Ljava/lang/Object;SZZ)Ljava/lang/String;
/*   */     //   241: dup
/*   */     //   242: astore #4
/*   */     //   244: invokevirtual length : ()I
/*   */     //   247: istore #6
/*   */     //   249: bipush #16
/*   */     //   251: istore_3
/*   */     //   252: iconst_m1
/*   */     //   253: istore_2
/*   */     //   254: iinc #2, 1
/*   */     //   257: aload #4
/*   */     //   259: iload_2
/*   */     //   260: dup
/*   */     //   261: iload_3
/*   */     //   262: iadd
/*   */     //   263: invokevirtual substring : (II)Ljava/lang/String;
/*   */     //   266: iconst_m1
/*   */     //   267: goto -> 315
/*   */     //   270: aload #7
/*   */     //   272: swap
/*   */     //   273: iload #5
/*   */     //   275: iinc #5, 1
/*   */     //   278: swap
/*   */     //   279: aastore
/*   */     //   280: iload_2
/*   */     //   281: iload_3
/*   */     //   282: iadd
/*   */     //   283: dup
/*   */     //   284: istore_2
/*   */     //   285: iload #6
/*   */     //   287: if_icmpge -> 300
/*   */     //   290: aload #4
/*   */     //   292: iload_2
/*   */     //   293: invokevirtual charAt : (I)C
/*   */     //   296: istore_3
/*   */     //   297: goto -> 254
/*   */     //   300: aload #7
/*   */     //   302: putstatic me/konsolas/aac/ck.db : [Ljava/lang/String;
/*   */     //   305: iconst_3
/*   */     //   306: anewarray java/lang/String
/*   */     //   309: putstatic me/konsolas/aac/ck.eb : [Ljava/lang/String;
/*   */     //   312: goto -> 364
/*   */     //   315: swap
/*   */     //   316: ldc '攉焜딻狩裎ꨜ夊紕빊剣'
/*   */     //   318: invokevirtual toCharArray : ()[C
/*   */     //   321: dup
/*   */     //   322: dup
/*   */     //   323: bipush #8
/*   */     //   325: dup_x1
/*   */     //   326: caload
/*   */     //   327: sipush #32582
/*   */     //   330: ixor
/*   */     //   331: i2c
/*   */     //   332: castore
/*   */     //   333: sipush #28378
/*   */     //   336: iconst_1
/*   */     //   337: iconst_1
/*   */     //   338: invokestatic X : (Ljava/lang/Object;SZZ)Ljava/lang/String;
/*   */     //   341: invokevirtual getBytes : (Ljava/lang/String;)[B
/*   */     //   344: aload_0
/*   */     //   345: swap
/*   */     //   346: invokevirtual doFinal : ([B)[B
/*   */     //   349: astore #8
/*   */     //   351: aload #8
/*   */     //   353: invokestatic a : ([B)Ljava/lang/String;
/*   */     //   356: invokevirtual intern : ()Ljava/lang/String;
/*   */     //   359: swap
/*   */     //   360: pop
/*   */     //   361: goto -> 270
/*   */     //   364: return
/*   */   }
/*   */   
/*   */   private static IllegalArgumentException a(IllegalArgumentException paramIllegalArgumentException) {
/*   */     return paramIllegalArgumentException;
/*   */   }
/*   */   
/*   */   private static String a(byte[] paramArrayOfbyte) {
/*   */     byte b1 = 0;
/*   */     int i;
/*   */     char[] arrayOfChar = new char[i = paramArrayOfbyte.length];
/*   */     for (byte b2 = 0; b2 < i; b2++) {
/*   */       int j;
/*   */       if ((j = 0xFF & paramArrayOfbyte[b2]) < 192) {
/*   */         arrayOfChar[b1++] = (char)j;
/*   */       } else if (j < 224) {
/*   */         char c = (char)((char)(j & 0x1F) << 6);
/*   */         j = paramArrayOfbyte[++b2];
/*   */         c = (char)(c | (char)(j & 0x3F));
/*   */         arrayOfChar[b1++] = c;
/*   */       } else if (b2 < i - 2) {
/*   */         char c = (char)((char)(j & 0xF) << 12);
/*   */         j = paramArrayOfbyte[++b2];
/*   */         c = (char)(c | (char)(j & 0x3F) << 6);
/*   */         j = paramArrayOfbyte[++b2];
/*   */         c = (char)(c | (char)(j & 0x3F));
/*   */         arrayOfChar[b1++] = c;
/*   */       } 
/*   */     } 
/*   */     return new String(arrayOfChar, 0, b1);
/*   */   }
/*   */   
/*   */   private static String a(int paramInt, long paramLong) {
/*   */     int i = paramInt ^ (int)(paramLong & 0x7FFFL) ^ 0x588;
/*   */     if (eb[i] == null) {
/*   */       Object[] arrayOfObject;
/*   */       try {
/*   */         Long long_ = Long.valueOf(Thread.currentThread().getId());
/*   */         arrayOfObject = (Object[])fb.get(long_);
/*   */         if (arrayOfObject == null) {
/*   */           arrayOfObject = new Object[3];
/*   */           "﷊龺⹟簰䐏쐀칒톆익薗涫퀯埞᠄ᧉ堦㌆ިএҸ".toCharArray()[0] = (char)("﷊龺⹟簰䐏쐀칒톆익薗涫퀯埞᠄ᧉ堦㌆ިএҸ".toCharArray()[0] ^ 0x496B);
/*   */           arrayOfObject[0] = Cipher.getInstance(a0$cc.G("﷊龺⹟簰䐏쐀칒톆익薗涫퀯埞᠄ᧉ堦㌆ިএҸ".toCharArray(), (short)26172, false, (byte)3));
/*   */           "犿勾䍍⡭".toCharArray()[0] = (char)("犿勾䍍⡭".toCharArray()[0] ^ 0x50E6);
/*   */           arrayOfObject[1] = SecretKeyFactory.getInstance(a0$cc.G("犿勾䍍⡭".toCharArray(), (short)9688, true, (byte)1));
/*   */           arrayOfObject[2] = new IvParameterSpec(new byte[8]);
/*   */           fb.put(long_, arrayOfObject);
/*   */         } 
/*   */       } catch (Exception exception) {
/*   */         "혙䒽?ꫬ犬邺硃뎻엗㽷?쪭欷븛鮉잔㗏".toCharArray()[4] = (char)("혙䒽?ꫬ犬邺硃뎻엗㽷?쪭欷븛鮉잔㗏".toCharArray()[4] ^ 0x49F7);
/*   */         throw new RuntimeException(a0$cc.G("혙䒽?ꫬ犬邺硃뎻엗㽷?쪭欷븛鮉잔㗏".toCharArray(), (short)5515, true, (byte)1), exception);
/*   */       } 
/*   */       byte[] arrayOfByte1 = new byte[8];
/*   */       arrayOfByte1[0] = (byte)(int)(paramLong >>> 56L);
/*   */       for (byte b = 1; b < 8; b++)
/*   */         arrayOfByte1[b] = (byte)(int)(paramLong << b * 8 >>> 56L); 
/*   */       DESKeySpec dESKeySpec = new DESKeySpec(arrayOfByte1);
/*   */       SecretKey secretKey = ((SecretKeyFactory)arrayOfObject[1]).generateSecret(dESKeySpec);
/*   */       ((Cipher)arrayOfObject[0]).init(2, secretKey, (IvParameterSpec)arrayOfObject[2]);
/*   */       "髺䁖ý᯸塚돦漕踝ꍥ魠瘿".toCharArray()[8] = (char)("髺䁖ý᯸塚돦漕踝ꍥ魠瘿".toCharArray()[8] ^ 0x51B9);
/*   */       byte[] arrayOfByte2 = db[i].getBytes(a0$cc.G("髺䁖ý᯸塚돦漕踝ꍥ魠瘿".toCharArray(), (short)25937, false, (byte)3));
/*   */       eb[i] = a(((Cipher)arrayOfObject[0]).doFinal(arrayOfByte2));
/*   */     } 
/*   */     return eb[i];
/*   */   }
/*   */   
/*   */   private static Object a(MethodHandles.Lookup paramLookup, MutableCallSite paramMutableCallSite, String paramString, Object[] paramArrayOfObject) {
/*   */     int i = ((Integer)paramArrayOfObject[0]).intValue();
/*   */     long l = ((Long)paramArrayOfObject[1]).longValue();
/*   */     String str = a(i, l);
/*   */     MethodHandle methodHandle = MethodHandles.constant(String.class, str);
/*   */     paramMutableCallSite.setTarget(MethodHandles.dropArguments(methodHandle, 0, new Class[] { int.class, long.class }));
/*   */     return str;
/*   */   }
/*   */   
/*   */   private static CallSite a(MethodHandles.Lookup paramLookup, String paramString, MethodType paramMethodType) {
/*   */     // Byte code:
/*   */     //   0: new java/lang/invoke/MutableCallSite
/*   */     //   3: dup
/*   */     //   4: aload_2
/*   */     //   5: invokespecial <init> : (Ljava/lang/invoke/MethodType;)V
/*   */     //   8: astore_3
/*   */     //   9: aload_3
/*   */     //   10: ldc_w
/*   */     //   13: ldc_w [Ljava/lang/Object;
/*   */     //   16: aload_2
/*   */     //   17: invokevirtual parameterCount : ()I
/*   */     //   20: invokevirtual asCollector : (Ljava/lang/Class;I)Ljava/lang/invoke/MethodHandle;
/*   */     //   23: iconst_0
/*   */     //   24: iconst_3
/*   */     //   25: anewarray java/lang/Object
/*   */     //   28: dup
/*   */     //   29: iconst_0
/*   */     //   30: aload_0
/*   */     //   31: aastore
/*   */     //   32: dup
/*   */     //   33: iconst_1
/*   */     //   34: aload_3
/*   */     //   35: aastore
/*   */     //   36: dup
/*   */     //   37: iconst_2
/*   */     //   38: aload_1
/*   */     //   39: aastore
/*   */     //   40: invokestatic insertArguments : (Ljava/lang/invoke/MethodHandle;I[Ljava/lang/Object;)Ljava/lang/invoke/MethodHandle;
/*   */     //   43: aload_2
/*   */     //   44: invokestatic explicitCastArguments : (Ljava/lang/invoke/MethodHandle;Ljava/lang/invoke/MethodType;)Ljava/lang/invoke/MethodHandle;
/*   */     //   47: invokevirtual setTarget : (Ljava/lang/invoke/MethodHandle;)V
/*   */     //   50: goto -> 170
/*   */     //   53: astore #4
/*   */     //   55: new java/lang/RuntimeException
/*   */     //   58: dup
/*   */     //   59: new java/lang/StringBuilder
/*   */     //   62: dup
/*   */     //   63: invokespecial <init> : ()V
/*   */     //   66: ldc_w '㳓갾ⷃ䫬크漜⃂ꦎ鸖摖㕴쇈ⶀ梞噛䌹繀'
/*   */     //   69: invokevirtual toCharArray : ()[C
/*   */     //   72: dup
/*   */     //   73: dup
/*   */     //   74: iconst_4
/*   */     //   75: dup_x1
/*   */     //   76: caload
/*   */     //   77: sipush #30276
/*   */     //   80: ixor
/*   */     //   81: i2c
/*   */     //   82: castore
/*   */     //   83: sipush #19741
/*   */     //   86: iconst_5
/*   */     //   87: iconst_5
/*   */     //   88: invokestatic H : (Ljava/lang/Object;SBB)Ljava/lang/String;
/*   */     //   91: invokevirtual append : (Ljava/lang/String;)Ljava/lang/StringBuilder;
/*   */     //   94: ldc_w '䍓䠅ۉ娶'
/*   */     //   97: invokevirtual toCharArray : ()[C
/*   */     //   100: dup
/*   */     //   101: dup
/*   */     //   102: iconst_2
/*   */     //   103: dup_x1
/*   */     //   104: caload
/*   */     //   105: sipush #25229
/*   */     //   108: ixor
/*   */     //   109: i2c
/*   */     //   110: castore
/*   */     //   111: sipush #17168
/*   */     //   114: iconst_1
/*   */     //   115: iconst_1
/*   */     //   116: invokestatic H : (Ljava/lang/Object;SBB)Ljava/lang/String;
/*   */     //   119: invokevirtual append : (Ljava/lang/String;)Ljava/lang/StringBuilder;
/*   */     //   122: aload_1
/*   */     //   123: invokevirtual append : (Ljava/lang/String;)Ljava/lang/StringBuilder;
/*   */     //   126: ldc_w '萅紀ꝫ䖀'
/*   */     //   129: invokevirtual toCharArray : ()[C
/*   */     //   132: dup
/*   */     //   133: dup
/*   */     //   134: iconst_0
/*   */     //   135: dup_x1
/*   */     //   136: caload
/*   */     //   137: sipush #7879
/*   */     //   140: ixor
/*   */     //   141: i2c
/*   */     //   142: castore
/*   */     //   143: sipush #14719
/*   */     //   146: iconst_3
/*   */     //   147: iconst_4
/*   */     //   148: invokestatic H : (Ljava/lang/Object;SBB)Ljava/lang/String;
/*   */     //   151: invokevirtual append : (Ljava/lang/String;)Ljava/lang/StringBuilder;
/*   */     //   154: aload_2
/*   */     //   155: invokevirtual toString : ()Ljava/lang/String;
/*   */     //   158: invokevirtual append : (Ljava/lang/String;)Ljava/lang/StringBuilder;
/*   */     //   161: invokevirtual toString : ()Ljava/lang/String;
/*   */     //   164: aload #4
/*   */     //   166: invokespecial <init> : (Ljava/lang/String;Ljava/lang/Throwable;)V
/*   */     //   169: athrow
/*   */     //   170: aload_3
/*   */     //   171: areturn
/*   */     // Exception table:
/*   */     //   from	to	target	type
/*   */     //   9	50	53	java/lang/Exception
/*   */   } }


/* Location:              C:\Users\BukkitBypass\Desktop\MatrixAC\AAC\AAC-spigot-5.2.0.jar!\me\konsolas\aac\ck.class
 * Java compiler version: 8 (52.0)
 * JD-Core Version:       1.1.3
 */