/*     */ package me.konsolas.aac;public final class ct { public static final short[][] e; public static final short[][] c; public static final m9 b; private static final int i = 7; private static final int j = 8192; private static final int g = 40; private static final int h = 8; private static final int f = 255; private static final int a = 2; private static final int d = 1024; @Deprecated
/*     */   public static void b(short[][] paramArrayOfshort, long paramLong) {
/*   3 */     paramArrayOfshort[k.b(paramLong)][k.a(paramLong)] = (short)(paramArrayOfshort[k.b(paramLong)][k.a(paramLong)] + 1);
/*     */   }
/*     */   
/*     */   @Deprecated
/*     */   public static short[][] d(short[][] paramArrayOfshort, long paramLong1, long paramLong2)
/*     */   {
/*   9 */     long l = a(paramArrayOfshort);
/*     */ 
/*     */ 
/*     */ 
/*     */ 
/*     */ 
/*     */ 
/*     */ 
/*     */ 
/*     */ 
/*     */ 
/*     */ 
/*     */ 
/*     */ 
/*     */ 
/*     */ 
/*     */ 
/*     */ 
/*     */ 
/*     */ 
/*     */ 
/*     */ 
/*     */ 
/*     */ 
/*     */ 
/*     */ 
/*     */ 
/*     */ 
/*     */ 
/*     */ 
/*     */ 
/*     */ 
/*     */ 
/*     */ 
/*     */ 
/*     */ 
/*     */ 
/*     */ 
/*     */ 
/*     */ 
/*     */ 
/*     */ 
/*     */ 
/*     */ 
/*     */ 
/*     */ 
/*     */ 
/*     */ 
/*     */ 
/*     */ 
/*     */ 
/*     */ 
/*     */ 
/*     */ 
/*     */ 
/*     */ 
/*     */ 
/*     */ 
/*     */ 
/*     */ 
/*     */ 
/*     */ 
/*     */ 
/*     */ 
/*     */ 
/*     */ 
/*     */ 
/*     */ 
/*     */ 
/*     */ 
/*     */ 
/*     */ 
/*     */ 
/*     */ 
/*     */ 
/*     */ 
/*     */ 
/*     */ 
/*     */ 
/*     */ 
/*     */ 
/*     */ 
/*     */ 
/*     */ 
/*     */ 
/*     */ 
/*     */ 
/*     */ 
/*     */ 
/*     */ 
/*     */ 
/*     */ 
/*     */ 
/*     */ 
/*     */ 
/*     */ 
/*     */ 
/*     */ 
/*     */ 
/*     */ 
/*     */ 
/*     */ 
/*     */ 
/*     */ 
/*     */ 
/*     */ 
/*     */ 
/*     */ 
/*     */ 
/*     */ 
/*     */ 
/*     */ 
/*     */ 
/*     */ 
/*     */ 
/*     */ 
/*     */ 
/*     */ 
/*     */ 
/*     */ 
/*     */ 
/*     */ 
/*     */ 
/*     */ 
/*     */ 
/*     */ 
/*     */ 
/*     */ 
/*     */ 
/*     */ 
/*     */ 
/*     */ 
/*     */ 
/*     */ 
/*     */ 
/*     */ 
/*     */ 
/*     */ 
/*     */ 
/*     */ 
/*     */ 
/*     */ 
/*     */ 
/*     */ 
/*     */ 
/*     */ 
/*     */ 
/*     */ 
/*     */ 
/*     */ 
/*     */ 
/*     */ 
/*     */ 
/*     */ 
/*     */ 
/*     */ 
/*     */ 
/*     */ 
/*     */ 
/*     */ 
/*     */ 
/*     */ 
/*     */ 
/*     */ 
/*     */ 
/*     */ 
/*     */ 
/*     */ 
/*     */ 
/*     */ 
/*     */ 
/*     */ 
/*     */ 
/*     */ 
/*     */ 
/*     */ 
/*     */ 
/*     */ 
/*     */ 
/*     */ 
/*     */ 
/*     */ 
/*     */ 
/*     */ 
/*     */ 
/*     */ 
/*     */ 
/*     */ 
/*     */ 
/*     */ 
/*     */ 
/*     */ 
/*     */ 
/*     */ 
/*     */ 
/*     */ 
/*     */ 
/*     */ 
/*     */ 
/*     */ 
/*     */ 
/*     */ 
/*     */ 
/*     */ 
/*     */ 
/*     */ 
/*     */ 
/*     */ 
/*     */ 
/*     */ 
/*     */ 
/*     */ 
/*     */ 
/*     */ 
/*     */ 
/*     */ 
/*     */ 
/*     */ 
/*     */ 
/*     */ 
/*     */ 
/*     */ 
/*     */ 
/*     */ 
/*     */ 
/*     */ 
/*     */ 
/*     */ 
/*     */ 
/*     */ 
/*     */ 
/*     */ 
/*     */ 
/*     */ 
/*     */ 
/*     */ 
/*     */ 
/*     */ 
/*     */ 
/*     */ 
/*     */ 
/*     */ 
/*     */ 
/*     */ 
/*     */ 
/*     */ 
/*     */ 
/*     */ 
/*     */ 
/*     */ 
/*     */     
/*     */     try {  }
/*     */     catch (IllegalArgumentException illegalArgumentException)
/* 262 */     { throw a(null); }  return (paramLong1 > l) ? b(paramArrayOfshort, Math.max(l + (l >> 1L), paramLong1), paramLong2) : paramArrayOfshort;
/*     */   } public static void a(short[][] paramArrayOfshort, ad paramad) { b(paramArrayOfshort, 0L, k.a(paramArrayOfshort), paramad); } @Deprecated public static void a(short[] paramArrayOfshort, int paramInt, short[][] paramArrayOfshort1, long paramLong1, long paramLong2) { k.a(paramArrayOfshort, paramInt, paramArrayOfshort1, paramLong1, paramLong2); } public static void d(short[][] paramArrayOfshort, long paramLong1, long paramLong2) { // Byte code:
/*     */     //   0: lload_3
/*     */     //   1: lload_1
/*     */     //   2: lsub
/*     */     //   3: lstore #5
/*     */     //   5: lload #5
/*     */     //   7: ldc2_w 7
/*     */     //   10: lcmp
/*     */     //   11: ifge -> 25
/*     */     //   14: aload_0
/*     */     //   15: lload_1
/*     */     //   16: lload_3
/*     */     //   17: invokestatic f : ([[SJJ)V
/*     */     //   20: return
/*     */     //   21: invokestatic a : (Ljava/lang/IllegalArgumentException;)Ljava/lang/IllegalArgumentException;
/*     */     //   24: athrow
/*     */     //   25: lload_1
/*     */     //   26: lload #5
/*     */     //   28: ldc2_w 2
/*     */     //   31: ldiv
/*     */     //   32: ladd
/*     */     //   33: lstore #7
/*     */     //   35: lload #5
/*     */     //   37: ldc2_w 7
/*     */     //   40: lcmp
/*     */     //   41: ifle -> 143
/*     */     //   44: lload_1
/*     */     //   45: lstore #9
/*     */     //   47: lload_3
/*     */     //   48: lconst_1
/*     */     //   49: lsub
/*     */     //   50: lstore #11
/*     */     //   52: lload #5
/*     */     //   54: ldc2_w 40
/*     */     //   57: lcmp
/*     */     //   58: ifle -> 131
/*     */     //   61: lload #5
/*     */     //   63: ldc2_w 8
/*     */     //   66: ldiv
/*     */     //   67: lstore #13
/*     */     //   69: aload_0
/*     */     //   70: lload #9
/*     */     //   72: lload #9
/*     */     //   74: lload #13
/*     */     //   76: ladd
/*     */     //   77: lload #9
/*     */     //   79: ldc2_w 2
/*     */     //   82: lload #13
/*     */     //   84: lmul
/*     */     //   85: ladd
/*     */     //   86: invokestatic a : ([[SJJJ)J
/*     */     //   89: lstore #9
/*     */     //   91: aload_0
/*     */     //   92: lload #7
/*     */     //   94: lload #13
/*     */     //   96: lsub
/*     */     //   97: lload #7
/*     */     //   99: lload #7
/*     */     //   101: lload #13
/*     */     //   103: ladd
/*     */     //   104: invokestatic a : ([[SJJJ)J
/*     */     //   107: lstore #7
/*     */     //   109: aload_0
/*     */     //   110: lload #11
/*     */     //   112: ldc2_w 2
/*     */     //   115: lload #13
/*     */     //   117: lmul
/*     */     //   118: lsub
/*     */     //   119: lload #11
/*     */     //   121: lload #13
/*     */     //   123: lsub
/*     */     //   124: lload #11
/*     */     //   126: invokestatic a : ([[SJJJ)J
/*     */     //   129: lstore #11
/*     */     //   131: aload_0
/*     */     //   132: lload #9
/*     */     //   134: lload #7
/*     */     //   136: lload #11
/*     */     //   138: invokestatic a : ([[SJJJ)J
/*     */     //   141: lstore #7
/*     */     //   143: aload_0
/*     */     //   144: lload #7
/*     */     //   146: invokestatic a : ([[SJ)S
/*     */     //   149: istore #9
/*     */     //   151: lload_1
/*     */     //   152: lstore #10
/*     */     //   154: lload #10
/*     */     //   156: lstore #12
/*     */     //   158: lload_3
/*     */     //   159: lconst_1
/*     */     //   160: lsub
/*     */     //   161: lstore #14
/*     */     //   163: lload #14
/*     */     //   165: lstore #16
/*     */     //   167: lload #12
/*     */     //   169: lload #14
/*     */     //   171: lcmp
/*     */     //   172: ifgt -> 226
/*     */     //   175: aload_0
/*     */     //   176: lload #12
/*     */     //   178: invokestatic a : ([[SJ)S
/*     */     //   181: iload #9
/*     */     //   183: invokestatic compare : (SS)I
/*     */     //   186: dup
/*     */     //   187: istore #18
/*     */     //   189: ifgt -> 226
/*     */     //   192: iload #18
/*     */     //   194: ifne -> 217
/*     */     //   197: goto -> 204
/*     */     //   200: invokestatic a : (Ljava/lang/IllegalArgumentException;)Ljava/lang/IllegalArgumentException;
/*     */     //   203: athrow
/*     */     //   204: aload_0
/*     */     //   205: lload #10
/*     */     //   207: dup2
/*     */     //   208: lconst_1
/*     */     //   209: ladd
/*     */     //   210: lstore #10
/*     */     //   212: lload #12
/*     */     //   214: invokestatic c : ([[SJJ)V
/*     */     //   217: lload #12
/*     */     //   219: lconst_1
/*     */     //   220: ladd
/*     */     //   221: lstore #12
/*     */     //   223: goto -> 167
/*     */     //   226: lload #14
/*     */     //   228: lload #12
/*     */     //   230: lcmp
/*     */     //   231: iflt -> 285
/*     */     //   234: aload_0
/*     */     //   235: lload #14
/*     */     //   237: invokestatic a : ([[SJ)S
/*     */     //   240: iload #9
/*     */     //   242: invokestatic compare : (SS)I
/*     */     //   245: dup
/*     */     //   246: istore #18
/*     */     //   248: iflt -> 285
/*     */     //   251: iload #18
/*     */     //   253: ifne -> 276
/*     */     //   256: goto -> 263
/*     */     //   259: invokestatic a : (Ljava/lang/IllegalArgumentException;)Ljava/lang/IllegalArgumentException;
/*     */     //   262: athrow
/*     */     //   263: aload_0
/*     */     //   264: lload #14
/*     */     //   266: lload #16
/*     */     //   268: dup2
/*     */     //   269: lconst_1
/*     */     //   270: lsub
/*     */     //   271: lstore #16
/*     */     //   273: invokestatic c : ([[SJJ)V
/*     */     //   276: lload #14
/*     */     //   278: lconst_1
/*     */     //   279: lsub
/*     */     //   280: lstore #14
/*     */     //   282: goto -> 226
/*     */     //   285: lload #12
/*     */     //   287: lload #14
/*     */     //   289: lcmp
/*     */     //   290: ifle -> 300
/*     */     //   293: goto -> 321
/*     */     //   296: invokestatic a : (Ljava/lang/IllegalArgumentException;)Ljava/lang/IllegalArgumentException;
/*     */     //   299: athrow
/*     */     //   300: aload_0
/*     */     //   301: lload #12
/*     */     //   303: dup2
/*     */     //   304: lconst_1
/*     */     //   305: ladd
/*     */     //   306: lstore #12
/*     */     //   308: lload #14
/*     */     //   310: dup2
/*     */     //   311: lconst_1
/*     */     //   312: lsub
/*     */     //   313: lstore #14
/*     */     //   315: invokestatic c : ([[SJJ)V
/*     */     //   318: goto -> 167
/*     */     //   321: lload_3
/*     */     //   322: lstore #20
/*     */     //   324: lload #10
/*     */     //   326: lload_1
/*     */     //   327: lsub
/*     */     //   328: lload #12
/*     */     //   330: lload #10
/*     */     //   332: lsub
/*     */     //   333: invokestatic min : (JJ)J
/*     */     //   336: lstore #18
/*     */     //   338: aload_0
/*     */     //   339: lload_1
/*     */     //   340: lload #12
/*     */     //   342: lload #18
/*     */     //   344: lsub
/*     */     //   345: lload #18
/*     */     //   347: invokestatic a : ([[SJJJ)V
/*     */     //   350: lload #16
/*     */     //   352: lload #14
/*     */     //   354: lsub
/*     */     //   355: lload #20
/*     */     //   357: lload #16
/*     */     //   359: lsub
/*     */     //   360: lconst_1
/*     */     //   361: lsub
/*     */     //   362: invokestatic min : (JJ)J
/*     */     //   365: lstore #18
/*     */     //   367: aload_0
/*     */     //   368: lload #12
/*     */     //   370: lload #20
/*     */     //   372: lload #18
/*     */     //   374: lsub
/*     */     //   375: lload #18
/*     */     //   377: invokestatic a : ([[SJJJ)V
/*     */     //   380: lload #12
/*     */     //   382: lload #10
/*     */     //   384: lsub
/*     */     //   385: dup2
/*     */     //   386: lstore #18
/*     */     //   388: lconst_1
/*     */     //   389: lcmp
/*     */     //   390: ifle -> 409
/*     */     //   393: aload_0
/*     */     //   394: lload_1
/*     */     //   395: lload_1
/*     */     //   396: lload #18
/*     */     //   398: ladd
/*     */     //   399: invokestatic d : ([[SJJ)V
/*     */     //   402: goto -> 409
/*     */     //   405: invokestatic a : (Ljava/lang/IllegalArgumentException;)Ljava/lang/IllegalArgumentException;
/*     */     //   408: athrow
/*     */     //   409: lload #16
/*     */     //   411: lload #14
/*     */     //   413: lsub
/*     */     //   414: dup2
/*     */     //   415: lstore #18
/*     */     //   417: lconst_1
/*     */     //   418: lcmp
/*     */     //   419: ifle -> 440
/*     */     //   422: aload_0
/*     */     //   423: lload #20
/*     */     //   425: lload #18
/*     */     //   427: lsub
/*     */     //   428: lload #20
/*     */     //   430: invokestatic d : ([[SJJ)V
/*     */     //   433: goto -> 440
/*     */     //   436: invokestatic a : (Ljava/lang/IllegalArgumentException;)Ljava/lang/IllegalArgumentException;
/*     */     //   439: athrow
/*     */     //   440: return
/*     */     // Line number table:
/*     */     //   Java source line number -> byte code offset
/*     */     //   #17	-> 0
/*     */     //   #91	-> 5
/*     */     //   #5	-> 14
/*     */     //   #203	-> 20
/*     */     //   #116	-> 25
/*     */     //   #121	-> 35
/*     */     //   #320	-> 44
/*     */     //   #400	-> 47
/*     */     //   #299	-> 52
/*     */     //   #65	-> 61
/*     */     //   #97	-> 69
/*     */     //   #214	-> 91
/*     */     //   #158	-> 109
/*     */     //   #254	-> 131
/*     */     //   #304	-> 143
/*     */     //   #163	-> 151
/*     */     //   #382	-> 167
/*     */     //   #403	-> 192
/*     */     //   #74	-> 217
/*     */     //   #162	-> 226
/*     */     //   #264	-> 251
/*     */     //   #7	-> 276
/*     */     //   #66	-> 285
/*     */     //   #359	-> 300
/*     */     //   #396	-> 321
/*     */     //   #136	-> 324
/*     */     //   #193	-> 338
/*     */     //   #410	-> 350
/*     */     //   #171	-> 367
/*     */     //   #271	-> 380
/*     */     //   #336	-> 409
/*     */     //   #323	-> 440
/*     */     // Exception table:
/*     */     //   from	to	target	type
/*     */     //   5	21	21	java/lang/IllegalArgumentException
/*     */     //   189	197	200	java/lang/IllegalArgumentException
/*     */     //   248	256	259	java/lang/IllegalArgumentException
/*     */     //   285	296	296	java/lang/IllegalArgumentException
/*     */     //   388	402	405	java/lang/IllegalArgumentException
/*     */     //   417	433	436	java/lang/IllegalArgumentException }
/*     */   public static long a(short[][] paramArrayOfshort, short paramShort) { return a(paramArrayOfshort, 0L, k.a(paramArrayOfshort), paramShort); }
/* 265 */   private static void c(short[][] paramArrayOfshort, long paramLong1, long paramLong2, ad paramad) { long l; for (l = paramLong1; l < paramLong2 - 1L; ) { long l1 = l; long l2 = l + 1L; while (true) { try { if (l2 < paramLong2) { if (paramad.a(k.a(paramArrayOfshort, l2), k.a(paramArrayOfshort, l1)) < 0) l1 = l2;  l2++; continue; }  } catch (IllegalArgumentException illegalArgumentException) { throw a(null); }
/*     */         
/*     */         try {
/*     */           if (l1 != l) {
/*     */             k.c(paramArrayOfshort, l, l1);
/*     */           }
/*     */         } catch (IllegalArgumentException illegalArgumentException) {
/*     */           throw a(null);
/*     */         } 
/*     */         break; }
/*     */       
/*     */       l++; }
/*     */      }
/*     */ 
/*     */ 
/*     */ 
/*     */ 
/*     */ 
/*     */ 
/*     */ 
/*     */ 
/*     */ 
/*     */ 
/*     */ 
/*     */ 
/*     */ 
/*     */ 
/*     */ 
/*     */ 
/*     */ 
/*     */   
/*     */   @Deprecated
/*     */   public static void a(short[][] paramArrayOfshort, long paramLong) {
/*     */     paramArrayOfshort[k.b(paramLong)][k.a(paramLong)] = (short)(paramArrayOfshort[k.b(paramLong)][k.a(paramLong)] - 1);
/*     */   }
/*     */ 
/*     */ 
/*     */ 
/*     */ 
/*     */ 
/*     */ 
/*     */ 
/*     */ 
/*     */ 
/*     */ 
/*     */ 
/*     */ 
/*     */ 
/*     */ 
/*     */ 
/*     */ 
/*     */   
/*     */   @Deprecated
/*     */   public static boolean a(short[][] paramArrayOfshort1, short[][] paramArrayOfshort2) {
/*     */     return k.a(paramArrayOfshort1, paramArrayOfshort2);
/*     */   }
/*     */ 
/*     */ 
/*     */ 
/*     */ 
/*     */ 
/*     */ 
/*     */ 
/*     */ 
/*     */ 
/*     */ 
/*     */ 
/*     */ 
/*     */ 
/*     */ 
/*     */ 
/*     */ 
/*     */   
/*     */   @Deprecated
/*     */   public static void b(short[][] paramArrayOfshort, long paramLong, short paramShort) {
/*     */     paramArrayOfshort[k.b(paramLong)][k.a(paramLong)] = paramShort;
/*     */   }
/*     */ 
/*     */ 
/*     */ 
/*     */ 
/*     */ 
/*     */ 
/*     */ 
/*     */ 
/*     */ 
/*     */ 
/*     */ 
/*     */ 
/*     */ 
/*     */ 
/*     */ 
/*     */   
/*     */   @Deprecated
/*     */   public static void a(short[][] paramArrayOfshort, long paramLong, short paramShort) {
/*     */     paramArrayOfshort[k.b(paramLong)][k.a(paramLong)] = (short)(paramArrayOfshort[k.b(paramLong)][k.a(paramLong)] * paramShort);
/*     */   }
/*     */ 
/*     */ 
/*     */ 
/*     */ 
/*     */ 
/*     */ 
/*     */ 
/*     */ 
/*     */ 
/*     */ 
/*     */ 
/*     */ 
/*     */ 
/*     */ 
/*     */ 
/*     */   
/*     */   public static void a(long[][] paramArrayOflong, short[][] paramArrayOfshort1, short[][] paramArrayOfshort2, long paramLong1, long paramLong2, boolean paramBoolean) {
/*     */     // Byte code:
/*     */     //   0: lload #5
/*     */     //   2: lload_3
/*     */     //   3: lsub
/*     */     //   4: ldc2_w 1024
/*     */     //   7: lcmp
/*     */     //   8: ifge -> 25
/*     */     //   11: aload_0
/*     */     //   12: aload_1
/*     */     //   13: aload_2
/*     */     //   14: lload_3
/*     */     //   15: lload #5
/*     */     //   17: invokestatic a : ([[J[[S[[SJJ)V
/*     */     //   20: return
/*     */     //   21: invokestatic a : (Ljava/lang/IllegalArgumentException;)Ljava/lang/IllegalArgumentException;
/*     */     //   24: athrow
/*     */     //   25: iconst_2
/*     */     //   26: istore #8
/*     */     //   28: iconst_3
/*     */     //   29: istore #9
/*     */     //   31: sipush #766
/*     */     //   34: istore #10
/*     */     //   36: iconst_0
/*     */     //   37: istore #11
/*     */     //   39: sipush #766
/*     */     //   42: newarray long
/*     */     //   44: astore #12
/*     */     //   46: sipush #766
/*     */     //   49: newarray long
/*     */     //   51: astore #13
/*     */     //   53: sipush #766
/*     */     //   56: newarray int
/*     */     //   58: astore #14
/*     */     //   60: aload #12
/*     */     //   62: iload #11
/*     */     //   64: lload_3
/*     */     //   65: lastore
/*     */     //   66: aload #13
/*     */     //   68: iload #11
/*     */     //   70: lload #5
/*     */     //   72: lload_3
/*     */     //   73: lsub
/*     */     //   74: lastore
/*     */     //   75: aload #14
/*     */     //   77: iload #11
/*     */     //   79: iinc #11, 1
/*     */     //   82: iconst_0
/*     */     //   83: iastore
/*     */     //   84: sipush #256
/*     */     //   87: newarray long
/*     */     //   89: astore #15
/*     */     //   91: sipush #256
/*     */     //   94: newarray long
/*     */     //   96: astore #16
/*     */     //   98: iload #7
/*     */     //   100: ifeq -> 117
/*     */     //   103: aload_0
/*     */     //   104: invokestatic a : ([[J)J
/*     */     //   107: invokestatic a : (J)[[J
/*     */     //   110: goto -> 118
/*     */     //   113: invokestatic a : (Ljava/lang/IllegalArgumentException;)Ljava/lang/IllegalArgumentException;
/*     */     //   116: athrow
/*     */     //   117: aconst_null
/*     */     //   118: astore #17
/*     */     //   120: iload #11
/*     */     //   122: ifle -> 798
/*     */     //   125: aload #12
/*     */     //   127: iinc #11, -1
/*     */     //   130: iload #11
/*     */     //   132: laload
/*     */     //   133: lstore #18
/*     */     //   135: aload #13
/*     */     //   137: iload #11
/*     */     //   139: laload
/*     */     //   140: lstore #20
/*     */     //   142: aload #14
/*     */     //   144: iload #11
/*     */     //   146: iaload
/*     */     //   147: istore #22
/*     */     //   149: iload #22
/*     */     //   151: iconst_2
/*     */     //   152: irem
/*     */     //   153: ifne -> 166
/*     */     //   156: sipush #128
/*     */     //   159: goto -> 167
/*     */     //   162: invokestatic a : (Ljava/lang/IllegalArgumentException;)Ljava/lang/IllegalArgumentException;
/*     */     //   165: athrow
/*     */     //   166: iconst_0
/*     */     //   167: istore #23
/*     */     //   169: iload #22
/*     */     //   171: iconst_2
/*     */     //   172: if_icmpge -> 183
/*     */     //   175: aload_1
/*     */     //   176: goto -> 184
/*     */     //   179: invokestatic a : (Ljava/lang/IllegalArgumentException;)Ljava/lang/IllegalArgumentException;
/*     */     //   182: athrow
/*     */     //   183: aload_2
/*     */     //   184: astore #24
/*     */     //   186: iconst_1
/*     */     //   187: iload #22
/*     */     //   189: iconst_2
/*     */     //   190: irem
/*     */     //   191: isub
/*     */     //   192: bipush #8
/*     */     //   194: imul
/*     */     //   195: istore #25
/*     */     //   197: lload #18
/*     */     //   199: lload #20
/*     */     //   201: ladd
/*     */     //   202: lstore #26
/*     */     //   204: lload #26
/*     */     //   206: dup2
/*     */     //   207: lconst_1
/*     */     //   208: lsub
/*     */     //   209: lstore #26
/*     */     //   211: lload #18
/*     */     //   213: lcmp
/*     */     //   214: ifeq -> 252
/*     */     //   217: aload #15
/*     */     //   219: aload #24
/*     */     //   221: aload_0
/*     */     //   222: lload #26
/*     */     //   224: invokestatic a : ([[JJ)J
/*     */     //   227: invokestatic a : ([[SJ)S
/*     */     //   230: iload #25
/*     */     //   232: iushr
/*     */     //   233: sipush #255
/*     */     //   236: iand
/*     */     //   237: iload #23
/*     */     //   239: ixor
/*     */     //   240: dup2
/*     */     //   241: laload
/*     */     //   242: lconst_1
/*     */     //   243: ladd
/*     */     //   244: lastore
/*     */     //   245: goto -> 204
/*     */     //   248: invokestatic a : (Ljava/lang/IllegalArgumentException;)Ljava/lang/IllegalArgumentException;
/*     */     //   251: athrow
/*     */     //   252: iconst_m1
/*     */     //   253: istore #26
/*     */     //   255: iload #7
/*     */     //   257: ifeq -> 268
/*     */     //   260: lconst_0
/*     */     //   261: goto -> 270
/*     */     //   264: invokestatic a : (Ljava/lang/IllegalArgumentException;)Ljava/lang/IllegalArgumentException;
/*     */     //   267: athrow
/*     */     //   268: lload #18
/*     */     //   270: lstore #27
/*     */     //   272: iconst_0
/*     */     //   273: istore #29
/*     */     //   275: iload #29
/*     */     //   277: sipush #256
/*     */     //   280: if_icmpge -> 326
/*     */     //   283: aload #15
/*     */     //   285: iload #29
/*     */     //   287: laload
/*     */     //   288: lconst_0
/*     */     //   289: lcmp
/*     */     //   290: ifeq -> 304
/*     */     //   293: goto -> 300
/*     */     //   296: invokestatic a : (Ljava/lang/IllegalArgumentException;)Ljava/lang/IllegalArgumentException;
/*     */     //   299: athrow
/*     */     //   300: iload #29
/*     */     //   302: istore #26
/*     */     //   304: aload #16
/*     */     //   306: iload #29
/*     */     //   308: lload #27
/*     */     //   310: aload #15
/*     */     //   312: iload #29
/*     */     //   314: laload
/*     */     //   315: ladd
/*     */     //   316: dup2
/*     */     //   317: lstore #27
/*     */     //   319: lastore
/*     */     //   320: iinc #29, 1
/*     */     //   323: goto -> 275
/*     */     //   326: iload #7
/*     */     //   328: ifeq -> 550
/*     */     //   331: lload #18
/*     */     //   333: lload #20
/*     */     //   335: ladd
/*     */     //   336: lstore #29
/*     */     //   338: lload #29
/*     */     //   340: dup2
/*     */     //   341: lconst_1
/*     */     //   342: lsub
/*     */     //   343: lstore #29
/*     */     //   345: lload #18
/*     */     //   347: lcmp
/*     */     //   348: ifeq -> 398
/*     */     //   351: aload #17
/*     */     //   353: aload #16
/*     */     //   355: aload #24
/*     */     //   357: aload_0
/*     */     //   358: lload #29
/*     */     //   360: invokestatic a : ([[JJ)J
/*     */     //   363: invokestatic a : ([[SJ)S
/*     */     //   366: iload #25
/*     */     //   368: iushr
/*     */     //   369: sipush #255
/*     */     //   372: iand
/*     */     //   373: iload #23
/*     */     //   375: ixor
/*     */     //   376: dup2
/*     */     //   377: laload
/*     */     //   378: lconst_1
/*     */     //   379: lsub
/*     */     //   380: dup2_x2
/*     */     //   381: lastore
/*     */     //   382: aload_0
/*     */     //   383: lload #29
/*     */     //   385: invokestatic a : ([[JJ)J
/*     */     //   388: invokestatic d : ([[JJJ)V
/*     */     //   391: goto -> 338
/*     */     //   394: invokestatic a : (Ljava/lang/IllegalArgumentException;)Ljava/lang/IllegalArgumentException;
/*     */     //   397: athrow
/*     */     //   398: aload #17
/*     */     //   400: lconst_0
/*     */     //   401: aload_0
/*     */     //   402: lload #18
/*     */     //   404: lload #20
/*     */     //   406: invokestatic a : ([[JJ[[JJJ)V
/*     */     //   409: lload #18
/*     */     //   411: lstore #27
/*     */     //   413: iconst_0
/*     */     //   414: istore #29
/*     */     //   416: iload #29
/*     */     //   418: sipush #256
/*     */     //   421: if_icmpge -> 541
/*     */     //   424: iload #22
/*     */     //   426: iconst_3
/*     */     //   427: if_icmpge -> 525
/*     */     //   430: goto -> 437
/*     */     //   433: invokestatic a : (Ljava/lang/IllegalArgumentException;)Ljava/lang/IllegalArgumentException;
/*     */     //   436: athrow
/*     */     //   437: aload #15
/*     */     //   439: iload #29
/*     */     //   441: laload
/*     */     //   442: lconst_1
/*     */     //   443: lcmp
/*     */     //   444: ifle -> 525
/*     */     //   447: goto -> 454
/*     */     //   450: invokestatic a : (Ljava/lang/IllegalArgumentException;)Ljava/lang/IllegalArgumentException;
/*     */     //   453: athrow
/*     */     //   454: aload #15
/*     */     //   456: iload #29
/*     */     //   458: laload
/*     */     //   459: ldc2_w 1024
/*     */     //   462: lcmp
/*     */     //   463: ifge -> 496
/*     */     //   466: goto -> 473
/*     */     //   469: invokestatic a : (Ljava/lang/IllegalArgumentException;)Ljava/lang/IllegalArgumentException;
/*     */     //   472: athrow
/*     */     //   473: aload_0
/*     */     //   474: aload_1
/*     */     //   475: aload_2
/*     */     //   476: lload #27
/*     */     //   478: lload #27
/*     */     //   480: aload #15
/*     */     //   482: iload #29
/*     */     //   484: laload
/*     */     //   485: ladd
/*     */     //   486: invokestatic a : ([[J[[S[[SJJ)V
/*     */     //   489: goto -> 525
/*     */     //   492: invokestatic a : (Ljava/lang/IllegalArgumentException;)Ljava/lang/IllegalArgumentException;
/*     */     //   495: athrow
/*     */     //   496: aload #12
/*     */     //   498: iload #11
/*     */     //   500: lload #27
/*     */     //   502: lastore
/*     */     //   503: aload #13
/*     */     //   505: iload #11
/*     */     //   507: aload #15
/*     */     //   509: iload #29
/*     */     //   511: laload
/*     */     //   512: lastore
/*     */     //   513: aload #14
/*     */     //   515: iload #11
/*     */     //   517: iinc #11, 1
/*     */     //   520: iload #22
/*     */     //   522: iconst_1
/*     */     //   523: iadd
/*     */     //   524: iastore
/*     */     //   525: lload #27
/*     */     //   527: aload #15
/*     */     //   529: iload #29
/*     */     //   531: laload
/*     */     //   532: ladd
/*     */     //   533: lstore #27
/*     */     //   535: iinc #29, 1
/*     */     //   538: goto -> 416
/*     */     //   541: aload #15
/*     */     //   543: lconst_0
/*     */     //   544: invokestatic fill : ([JJ)V
/*     */     //   547: goto -> 795
/*     */     //   550: lload #18
/*     */     //   552: lload #20
/*     */     //   554: ladd
/*     */     //   555: aload #15
/*     */     //   557: iload #26
/*     */     //   559: laload
/*     */     //   560: lsub
/*     */     //   561: lstore #29
/*     */     //   563: iconst_m1
/*     */     //   564: istore #31
/*     */     //   566: lload #18
/*     */     //   568: lstore #32
/*     */     //   570: lload #32
/*     */     //   572: lload #29
/*     */     //   574: lcmp
/*     */     //   575: ifgt -> 795
/*     */     //   578: aload_0
/*     */     //   579: lload #32
/*     */     //   581: invokestatic a : ([[JJ)J
/*     */     //   584: lstore #36
/*     */     //   586: aload #24
/*     */     //   588: lload #36
/*     */     //   590: invokestatic a : ([[SJ)S
/*     */     //   593: iload #25
/*     */     //   595: iushr
/*     */     //   596: sipush #255
/*     */     //   599: iand
/*     */     //   600: iload #23
/*     */     //   602: ixor
/*     */     //   603: istore #31
/*     */     //   605: lload #32
/*     */     //   607: lload #29
/*     */     //   609: lcmp
/*     */     //   610: ifge -> 682
/*     */     //   613: aload #16
/*     */     //   615: iload #31
/*     */     //   617: dup2
/*     */     //   618: laload
/*     */     //   619: lconst_1
/*     */     //   620: lsub
/*     */     //   621: dup2_x2
/*     */     //   622: lastore
/*     */     //   623: dup2
/*     */     //   624: lstore #34
/*     */     //   626: lload #32
/*     */     //   628: lcmp
/*     */     //   629: ifle -> 674
/*     */     //   632: lload #36
/*     */     //   634: lstore #38
/*     */     //   636: aload_0
/*     */     //   637: lload #34
/*     */     //   639: invokestatic a : ([[JJ)J
/*     */     //   642: lstore #36
/*     */     //   644: aload_0
/*     */     //   645: lload #34
/*     */     //   647: lload #38
/*     */     //   649: invokestatic d : ([[JJJ)V
/*     */     //   652: aload #24
/*     */     //   654: lload #36
/*     */     //   656: invokestatic a : ([[SJ)S
/*     */     //   659: iload #25
/*     */     //   661: iushr
/*     */     //   662: sipush #255
/*     */     //   665: iand
/*     */     //   666: iload #23
/*     */     //   668: ixor
/*     */     //   669: istore #31
/*     */     //   671: goto -> 613
/*     */     //   674: aload_0
/*     */     //   675: lload #32
/*     */     //   677: lload #36
/*     */     //   679: invokestatic d : ([[JJJ)V
/*     */     //   682: iload #22
/*     */     //   684: iconst_3
/*     */     //   685: if_icmpge -> 776
/*     */     //   688: aload #15
/*     */     //   690: iload #31
/*     */     //   692: laload
/*     */     //   693: lconst_1
/*     */     //   694: lcmp
/*     */     //   695: ifle -> 776
/*     */     //   698: goto -> 705
/*     */     //   701: invokestatic a : (Ljava/lang/IllegalArgumentException;)Ljava/lang/IllegalArgumentException;
/*     */     //   704: athrow
/*     */     //   705: aload #15
/*     */     //   707: iload #31
/*     */     //   709: laload
/*     */     //   710: ldc2_w 1024
/*     */     //   713: lcmp
/*     */     //   714: ifge -> 747
/*     */     //   717: goto -> 724
/*     */     //   720: invokestatic a : (Ljava/lang/IllegalArgumentException;)Ljava/lang/IllegalArgumentException;
/*     */     //   723: athrow
/*     */     //   724: aload_0
/*     */     //   725: aload_1
/*     */     //   726: aload_2
/*     */     //   727: lload #32
/*     */     //   729: lload #32
/*     */     //   731: aload #15
/*     */     //   733: iload #31
/*     */     //   735: laload
/*     */     //   736: ladd
/*     */     //   737: invokestatic a : ([[J[[S[[SJJ)V
/*     */     //   740: goto -> 776
/*     */     //   743: invokestatic a : (Ljava/lang/IllegalArgumentException;)Ljava/lang/IllegalArgumentException;
/*     */     //   746: athrow
/*     */     //   747: aload #12
/*     */     //   749: iload #11
/*     */     //   751: lload #32
/*     */     //   753: lastore
/*     */     //   754: aload #13
/*     */     //   756: iload #11
/*     */     //   758: aload #15
/*     */     //   760: iload #31
/*     */     //   762: laload
/*     */     //   763: lastore
/*     */     //   764: aload #14
/*     */     //   766: iload #11
/*     */     //   768: iinc #11, 1
/*     */     //   771: iload #22
/*     */     //   773: iconst_1
/*     */     //   774: iadd
/*     */     //   775: iastore
/*     */     //   776: lload #32
/*     */     //   778: aload #15
/*     */     //   780: iload #31
/*     */     //   782: laload
/*     */     //   783: ladd
/*     */     //   784: lstore #32
/*     */     //   786: aload #15
/*     */     //   788: iload #31
/*     */     //   790: lconst_0
/*     */     //   791: lastore
/*     */     //   792: goto -> 570
/*     */     //   795: goto -> 120
/*     */     //   798: return
/*     */     // Line number table:
/*     */     //   Java source line number -> byte code offset
/*     */     //   #60	-> 0
/*     */     //   #394	-> 11
/*     */     //   #321	-> 20
/*     */     //   #161	-> 25
/*     */     //   #11	-> 28
/*     */     //   #398	-> 31
/*     */     //   #86	-> 36
/*     */     //   #373	-> 39
/*     */     //   #220	-> 46
/*     */     //   #248	-> 53
/*     */     //   #241	-> 60
/*     */     //   #19	-> 66
/*     */     //   #178	-> 75
/*     */     //   #252	-> 84
/*     */     //   #103	-> 91
/*     */     //   #195	-> 98
/*     */     //   #196	-> 120
/*     */     //   #415	-> 125
/*     */     //   #181	-> 135
/*     */     //   #102	-> 142
/*     */     //   #50	-> 149
/*     */     //   #31	-> 169
/*     */     //   #278	-> 186
/*     */     //   #67	-> 197
/*     */     //   #63	-> 252
/*     */     //   #219	-> 255
/*     */     //   #104	-> 272
/*     */     //   #399	-> 283
/*     */     //   #340	-> 304
/*     */     //   #183	-> 320
/*     */     //   #34	-> 326
/*     */     //   #245	-> 331
/*     */     //   #358	-> 398
/*     */     //   #80	-> 409
/*     */     //   #138	-> 413
/*     */     //   #92	-> 424
/*     */     //   #191	-> 454
/*     */     //   #329	-> 496
/*     */     //   #308	-> 503
/*     */     //   #187	-> 513
/*     */     //   #357	-> 525
/*     */     //   #253	-> 535
/*     */     //   #389	-> 541
/*     */     //   #337	-> 550
/*     */     //   #270	-> 563
/*     */     //   #386	-> 566
/*     */     //   #32	-> 578
/*     */     //   #155	-> 586
/*     */     //   #182	-> 605
/*     */     //   #379	-> 613
/*     */     //   #205	-> 632
/*     */     //   #279	-> 636
/*     */     //   #243	-> 644
/*     */     //   #117	-> 652
/*     */     //   #146	-> 671
/*     */     //   #106	-> 674
/*     */     //   #149	-> 682
/*     */     //   #6	-> 705
/*     */     //   #414	-> 747
/*     */     //   #55	-> 754
/*     */     //   #73	-> 764
/*     */     //   #225	-> 776
/*     */     //   #267	-> 795
/*     */     //   #383	-> 798
/*     */     // Exception table:
/*     */     //   from	to	target	type
/*     */     //   0	21	21	java/lang/IllegalArgumentException
/*     */     //   98	113	113	java/lang/IllegalArgumentException
/*     */     //   149	162	162	java/lang/IllegalArgumentException
/*     */     //   169	179	179	java/lang/IllegalArgumentException
/*     */     //   211	248	248	java/lang/IllegalArgumentException
/*     */     //   255	264	264	java/lang/IllegalArgumentException
/*     */     //   275	293	296	java/lang/IllegalArgumentException
/*     */     //   345	394	394	java/lang/IllegalArgumentException
/*     */     //   416	430	433	java/lang/IllegalArgumentException
/*     */     //   424	447	450	java/lang/IllegalArgumentException
/*     */     //   437	466	469	java/lang/IllegalArgumentException
/*     */     //   454	492	492	java/lang/IllegalArgumentException
/*     */     //   682	698	701	java/lang/IllegalArgumentException
/*     */     //   688	717	720	java/lang/IllegalArgumentException
/*     */     //   705	743	743	java/lang/IllegalArgumentException
/*     */   }
/*     */ 
/*     */ 
/*     */ 
/*     */ 
/*     */ 
/*     */ 
/*     */ 
/*     */ 
/*     */ 
/*     */ 
/*     */ 
/*     */ 
/*     */ 
/*     */ 
/*     */ 
/*     */   
/*     */   @Deprecated
/*     */   public static short[][] c(short[][] paramArrayOfshort, long paramLong)
/*     */   {
/*     */     k.a(paramLong);
/* 401 */     long l = a(paramArrayOfshort); try { if (paramLong >= l)
/*     */         return paramArrayOfshort;  } catch (IllegalArgumentException illegalArgumentException) { throw a(null); }  int i = (int)(paramLong + 134217727L >>> 27L); short[][] arrayOfShort = Arrays.<short[]>copyOf(paramArrayOfshort, i); int j = (int)(paramLong & 0x7FFFFFFL); try { if (j != 0)
/*     */         arrayOfShort[i - 1] = j.c(arrayOfShort[i - 1], j);  } catch (IllegalArgumentException illegalArgumentException) { throw a(null); }
/* 404 */      return arrayOfShort; } public static void b(short[][] paramArrayOfshort, long paramLong1, long paramLong2, ad paramad) { ForkJoinPool forkJoinPool = a(); try { if (paramLong2 - paramLong1 >= 8192L) { try { if (forkJoinPool.getParallelism() == 1) { a(paramArrayOfshort, paramLong1, paramLong2, paramad); return; }  } catch (IllegalArgumentException illegalArgumentException) { throw a(null); }  forkJoinPool.invoke(new jB(paramArrayOfshort, paramLong1, paramLong2, paramad)); return; }  } catch (IllegalArgumentException illegalArgumentException) { throw a(null); }  a(paramArrayOfshort, paramLong1, paramLong2, paramad); }
/*     */ 
/*     */ 
/*     */   
/*     */   public static void b(short[][] paramArrayOfshort) {
/*     */     a(paramArrayOfshort, 0L, k.a(paramArrayOfshort));
/*     */   }
/*     */ 
/*     */   
/*     */   public static long a(short[][] paramArrayOfshort, long paramLong1, long paramLong2, short paramShort) {
/*     */     paramLong2--;
/*     */     while (paramLong1 <= paramLong2)
/* 416 */     { long l = paramLong1 + paramLong2 >>> 1L; short s = k.a(paramArrayOfshort, l); if (s < paramShort) paramLong1 = l + 1L;  }  return -(paramLong1 + 1L);
/* 417 */   } private static long a(short[][] paramArrayOfshort, long paramLong1, long paramLong2, long paramLong3, ad paramad) { int i = paramad.a(k.a(paramArrayOfshort, paramLong1), k.a(paramArrayOfshort, paramLong2)); int j = paramad.a(k.a(paramArrayOfshort, paramLong1), k.a(paramArrayOfshort, paramLong3)); int k = paramad.a(k.a(paramArrayOfshort, paramLong2), k.a(paramArrayOfshort, paramLong3)); try { if (i < 0) { try { try {  } catch (IllegalArgumentException illegalArgumentException) { throw a(null); }  } catch (IllegalArgumentException illegalArgumentException) { throw a(null); }  } else { try { try {  } catch (IllegalArgumentException illegalArgumentException) { throw a(null); }  } catch (IllegalArgumentException illegalArgumentException) { throw a(null); }  }  } catch (IllegalArgumentException illegalArgumentException) { throw a(null); }  return (k > 0) ? paramLong2 : ((j > 0) ? paramLong3 : paramLong1); } @Deprecated public static void g(short[][] paramArrayOfshort, long paramLong1, long paramLong2) { short s = paramArrayOfshort[k.b(paramLong1)][k.a(paramLong1)]; paramArrayOfshort[k.b(paramLong1)][k.a(paramLong1)] = paramArrayOfshort[k.b(paramLong2)][k.a(paramLong2)]; paramArrayOfshort[k.b(paramLong2)][k.a(paramLong2)] = s; } public static long a(short[][] paramArrayOfshort, long paramLong1, long paramLong2, short paramShort, ad paramad) { paramLong2--;
/*     */     while (paramLong1 <= paramLong2) {
/*     */       long l = paramLong1 + paramLong2 >>> 1L;
/*     */       short s = k.a(paramArrayOfshort, l);
/*     */       int i = paramad.a(s, paramShort);
/*     */       if (i < 0) {
/*     */         paramLong1 = l + 1L;
/*     */         continue;
/*     */       } 
/*     */       if (i > 0) {
/*     */         paramLong2 = l - 1L;
/*     */         continue;
/*     */       } 
/*     */       return l;
/*     */     } 
/*     */     return -(paramLong1 + 1L); }
/*     */ 
/*     */   
/*     */   private static long a(short[][] paramArrayOfshort, long paramLong1, long paramLong2, long paramLong3) {
/*     */     int i = Short.compare(k.a(paramArrayOfshort, paramLong1), k.a(paramArrayOfshort, paramLong2));
/*     */     int j = Short.compare(k.a(paramArrayOfshort, paramLong1), k.a(paramArrayOfshort, paramLong3));
/*     */     int k = Short.compare(k.a(paramArrayOfshort, paramLong2), k.a(paramArrayOfshort, paramLong3));
/*     */     try {
/*     */       if (i < 0) {
/*     */         try {
/*     */           try {
/*     */           
/*     */           } catch (IllegalArgumentException illegalArgumentException) {
/*     */             throw a(null);
/*     */           } 
/*     */         } catch (IllegalArgumentException illegalArgumentException) {
/*     */           throw a(null);
/*     */         } 
/*     */       } else {
/*     */         try {
/*     */           try {
/*     */           
/*     */           } catch (IllegalArgumentException illegalArgumentException) {
/*     */             throw a(null);
/*     */           } 
/*     */         } catch (IllegalArgumentException illegalArgumentException) {
/*     */           throw a(null);
/*     */         } 
/*     */       } 
/*     */     } catch (IllegalArgumentException illegalArgumentException) {
/*     */       throw a(null);
/*     */     } 
/*     */     return (k > 0) ? paramLong2 : ((j > 0) ? paramLong3 : paramLong1);
/*     */   }
/*     */   
/*     */   public static void b(short[][] paramArrayOfshort, long paramLong1, long paramLong2) {
/*     */     ForkJoinPool forkJoinPool = a();
/*     */     try {
/*     */       if (paramLong2 - paramLong1 >= 8192L) {
/*     */         try {
/*     */           if (forkJoinPool.getParallelism() == 1) {
/*     */             d(paramArrayOfshort, paramLong1, paramLong2);
/*     */             return;
/*     */           } 
/*     */         } catch (IllegalArgumentException illegalArgumentException) {
/*     */           throw a(null);
/*     */         } 
/*     */         forkJoinPool.invoke(new cq(paramArrayOfshort, paramLong1, paramLong2));
/*     */         return;
/*     */       } 
/*     */     } catch (IllegalArgumentException illegalArgumentException) {
/*     */       throw a(null);
/*     */     } 
/*     */     d(paramArrayOfshort, paramLong1, paramLong2);
/*     */   }
/*     */   
/*     */   @Deprecated
/*     */   public static short[][] a(short[][] paramArrayOfshort, long paramLong1, long paramLong2) {
/*     */     return k.c(paramArrayOfshort, paramLong1, paramLong2);
/*     */   }
/*     */   
/*     */   @Deprecated
/*     */   public static void a(short[][] paramArrayOfshort, long paramLong1, long paramLong2, short paramShort) {
/*     */     k.a(paramArrayOfshort, paramLong1, paramLong2, paramShort);
/*     */   }
/*     */   
/*     */   @Deprecated
/*     */   public static short[][] c(short[][] paramArrayOfshort, long paramLong1, long paramLong2) {
/*     */     return k.d(paramArrayOfshort, paramLong1, paramLong2);
/*     */   }
/*     */   
/*     */   @Deprecated
/*     */   public static void a(short[][] paramArrayOfshort1, long paramLong1, short[][] paramArrayOfshort2, long paramLong2, long paramLong3) {
/*     */     k.a(paramArrayOfshort1, paramLong1, paramArrayOfshort2, paramLong2, paramLong3);
/*     */   }
/*     */   
/*     */   public static short[][] a(short[][] paramArrayOfshort, Random paramRandom) {
/*     */     return k.a(paramArrayOfshort, paramRandom);
/*     */   }
/*     */   
/*     */   public static long a(short[][] paramArrayOfshort, short paramShort, ad paramad) {
/*     */     return a(paramArrayOfshort, 0L, k.a(paramArrayOfshort), paramShort, paramad);
/*     */   }
/*     */   
/*     */   public static short[][] a(long paramLong) {
/*     */     try {
/*     */       if (paramLong == 0L)
/*     */         return e; 
/*     */     } catch (IllegalArgumentException illegalArgumentException) {
/*     */       throw a(null);
/*     */     } 
/*     */     k.a(paramLong);
/*     */     int i = (int)(paramLong + 134217727L >>> 27L);
/*     */     short[][] arrayOfShort = new short[i][];
/*     */     int j = (int)(paramLong & 0x7FFFFFFL);
/*     */     if (j != 0) {
/*     */       byte b = 0;
/*     */       try {
/*     */         while (b < i - 1) {
/*     */           arrayOfShort[b] = new short[134217728];
/*     */           b++;
/*     */         } 
/*     */       } catch (IllegalArgumentException illegalArgumentException) {
/*     */         throw a(null);
/*     */       } 
/*     */       arrayOfShort[i - 1] = new short[j];
/*     */     } else {
/*     */       byte b = 0;
/*     */       try {
/*     */         while (b < i) {
/*     */           arrayOfShort[b] = new short[134217728];
/*     */           b++;
/*     */         } 
/*     */       } catch (IllegalArgumentException illegalArgumentException) {
/*     */         throw a(null);
/*     */       } 
/*     */     } 
/*     */     return arrayOfShort;
/*     */   }
/*     */   
/*     */   public static short[][] a(short[][] paramArrayOfshort, long paramLong1, long paramLong2, Random paramRandom) {
/*     */     return k.a(paramArrayOfshort, paramLong1, paramLong2, paramRandom);
/*     */   }
/*     */   
/*     */   public static void a(short[][] paramArrayOfshort) {
/*     */     b(paramArrayOfshort, 0L, k.a(paramArrayOfshort));
/*     */   }
/*     */   
/*     */   @Deprecated
/*     */   public static short[][] a(short[] paramArrayOfshort) {
/*     */     return k.a(paramArrayOfshort);
/*     */   }
/*     */   
/*     */   private static ForkJoinPool a() {
/*     */     ForkJoinPool forkJoinPool = ForkJoinTask.getPool();
/*     */     try {
/*     */     
/*     */     } catch (IllegalArgumentException illegalArgumentException) {
/*     */       throw a(null);
/*     */     } 
/*     */     return (forkJoinPool == null) ? ForkJoinPool.commonPool() : forkJoinPool;
/*     */   }
/*     */   
/*     */   @Deprecated
/*     */   public static String a(short[][] paramArrayOfshort) {
/*     */     return k.a(paramArrayOfshort);
/*     */   }
/*     */   
/*     */   public static void a(short[][] paramArrayOfshort, long paramLong1, long paramLong2, ad paramad) {
/*     */     // Byte code:
/*     */     //   0: lload_3
/*     */     //   1: lload_1
/*     */     //   2: lsub
/*     */     //   3: lstore #6
/*     */     //   5: lload #6
/*     */     //   7: ldc2_w 7
/*     */     //   10: lcmp
/*     */     //   11: ifge -> 27
/*     */     //   14: aload_0
/*     */     //   15: lload_1
/*     */     //   16: lload_3
/*     */     //   17: aload #5
/*     */     //   19: invokestatic c : ([[SJJLme/konsolas/aac/ad;)V
/*     */     //   22: return
/*     */     //   23: invokestatic a : (Ljava/lang/IllegalArgumentException;)Ljava/lang/IllegalArgumentException;
/*     */     //   26: athrow
/*     */     //   27: lload_1
/*     */     //   28: lload #6
/*     */     //   30: ldc2_w 2
/*     */     //   33: ldiv
/*     */     //   34: ladd
/*     */     //   35: lstore #8
/*     */     //   37: lload #6
/*     */     //   39: ldc2_w 7
/*     */     //   42: lcmp
/*     */     //   43: ifle -> 153
/*     */     //   46: lload_1
/*     */     //   47: lstore #10
/*     */     //   49: lload_3
/*     */     //   50: lconst_1
/*     */     //   51: lsub
/*     */     //   52: lstore #12
/*     */     //   54: lload #6
/*     */     //   56: ldc2_w 40
/*     */     //   59: lcmp
/*     */     //   60: ifle -> 139
/*     */     //   63: lload #6
/*     */     //   65: ldc2_w 8
/*     */     //   68: ldiv
/*     */     //   69: lstore #14
/*     */     //   71: aload_0
/*     */     //   72: lload #10
/*     */     //   74: lload #10
/*     */     //   76: lload #14
/*     */     //   78: ladd
/*     */     //   79: lload #10
/*     */     //   81: ldc2_w 2
/*     */     //   84: lload #14
/*     */     //   86: lmul
/*     */     //   87: ladd
/*     */     //   88: aload #5
/*     */     //   90: invokestatic a : ([[SJJJLme/konsolas/aac/ad;)J
/*     */     //   93: lstore #10
/*     */     //   95: aload_0
/*     */     //   96: lload #8
/*     */     //   98: lload #14
/*     */     //   100: lsub
/*     */     //   101: lload #8
/*     */     //   103: lload #8
/*     */     //   105: lload #14
/*     */     //   107: ladd
/*     */     //   108: aload #5
/*     */     //   110: invokestatic a : ([[SJJJLme/konsolas/aac/ad;)J
/*     */     //   113: lstore #8
/*     */     //   115: aload_0
/*     */     //   116: lload #12
/*     */     //   118: ldc2_w 2
/*     */     //   121: lload #14
/*     */     //   123: lmul
/*     */     //   124: lsub
/*     */     //   125: lload #12
/*     */     //   127: lload #14
/*     */     //   129: lsub
/*     */     //   130: lload #12
/*     */     //   132: aload #5
/*     */     //   134: invokestatic a : ([[SJJJLme/konsolas/aac/ad;)J
/*     */     //   137: lstore #12
/*     */     //   139: aload_0
/*     */     //   140: lload #10
/*     */     //   142: lload #8
/*     */     //   144: lload #12
/*     */     //   146: aload #5
/*     */     //   148: invokestatic a : ([[SJJJLme/konsolas/aac/ad;)J
/*     */     //   151: lstore #8
/*     */     //   153: aload_0
/*     */     //   154: lload #8
/*     */     //   156: invokestatic a : ([[SJ)S
/*     */     //   159: istore #10
/*     */     //   161: lload_1
/*     */     //   162: lstore #11
/*     */     //   164: lload #11
/*     */     //   166: lstore #13
/*     */     //   168: lload_3
/*     */     //   169: lconst_1
/*     */     //   170: lsub
/*     */     //   171: lstore #15
/*     */     //   173: lload #15
/*     */     //   175: lstore #17
/*     */     //   177: lload #13
/*     */     //   179: lload #15
/*     */     //   181: lcmp
/*     */     //   182: ifgt -> 240
/*     */     //   185: aload #5
/*     */     //   187: aload_0
/*     */     //   188: lload #13
/*     */     //   190: invokestatic a : ([[SJ)S
/*     */     //   193: iload #10
/*     */     //   195: invokeinterface a : (SS)I
/*     */     //   200: dup
/*     */     //   201: istore #19
/*     */     //   203: ifgt -> 240
/*     */     //   206: iload #19
/*     */     //   208: ifne -> 231
/*     */     //   211: goto -> 218
/*     */     //   214: invokestatic a : (Ljava/lang/IllegalArgumentException;)Ljava/lang/IllegalArgumentException;
/*     */     //   217: athrow
/*     */     //   218: aload_0
/*     */     //   219: lload #11
/*     */     //   221: dup2
/*     */     //   222: lconst_1
/*     */     //   223: ladd
/*     */     //   224: lstore #11
/*     */     //   226: lload #13
/*     */     //   228: invokestatic c : ([[SJJ)V
/*     */     //   231: lload #13
/*     */     //   233: lconst_1
/*     */     //   234: ladd
/*     */     //   235: lstore #13
/*     */     //   237: goto -> 177
/*     */     //   240: lload #15
/*     */     //   242: lload #13
/*     */     //   244: lcmp
/*     */     //   245: iflt -> 303
/*     */     //   248: aload #5
/*     */     //   250: aload_0
/*     */     //   251: lload #15
/*     */     //   253: invokestatic a : ([[SJ)S
/*     */     //   256: iload #10
/*     */     //   258: invokeinterface a : (SS)I
/*     */     //   263: dup
/*     */     //   264: istore #19
/*     */     //   266: iflt -> 303
/*     */     //   269: iload #19
/*     */     //   271: ifne -> 294
/*     */     //   274: goto -> 281
/*     */     //   277: invokestatic a : (Ljava/lang/IllegalArgumentException;)Ljava/lang/IllegalArgumentException;
/*     */     //   280: athrow
/*     */     //   281: aload_0
/*     */     //   282: lload #15
/*     */     //   284: lload #17
/*     */     //   286: dup2
/*     */     //   287: lconst_1
/*     */     //   288: lsub
/*     */     //   289: lstore #17
/*     */     //   291: invokestatic c : ([[SJJ)V
/*     */     //   294: lload #15
/*     */     //   296: lconst_1
/*     */     //   297: lsub
/*     */     //   298: lstore #15
/*     */     //   300: goto -> 240
/*     */     //   303: lload #13
/*     */     //   305: lload #15
/*     */     //   307: lcmp
/*     */     //   308: ifle -> 318
/*     */     //   311: goto -> 339
/*     */     //   314: invokestatic a : (Ljava/lang/IllegalArgumentException;)Ljava/lang/IllegalArgumentException;
/*     */     //   317: athrow
/*     */     //   318: aload_0
/*     */     //   319: lload #13
/*     */     //   321: dup2
/*     */     //   322: lconst_1
/*     */     //   323: ladd
/*     */     //   324: lstore #13
/*     */     //   326: lload #15
/*     */     //   328: dup2
/*     */     //   329: lconst_1
/*     */     //   330: lsub
/*     */     //   331: lstore #15
/*     */     //   333: invokestatic c : ([[SJJ)V
/*     */     //   336: goto -> 177
/*     */     //   339: lload_3
/*     */     //   340: lstore #21
/*     */     //   342: lload #11
/*     */     //   344: lload_1
/*     */     //   345: lsub
/*     */     //   346: lload #13
/*     */     //   348: lload #11
/*     */     //   350: lsub
/*     */     //   351: invokestatic min : (JJ)J
/*     */     //   354: lstore #19
/*     */     //   356: aload_0
/*     */     //   357: lload_1
/*     */     //   358: lload #13
/*     */     //   360: lload #19
/*     */     //   362: lsub
/*     */     //   363: lload #19
/*     */     //   365: invokestatic a : ([[SJJJ)V
/*     */     //   368: lload #17
/*     */     //   370: lload #15
/*     */     //   372: lsub
/*     */     //   373: lload #21
/*     */     //   375: lload #17
/*     */     //   377: lsub
/*     */     //   378: lconst_1
/*     */     //   379: lsub
/*     */     //   380: invokestatic min : (JJ)J
/*     */     //   383: lstore #19
/*     */     //   385: aload_0
/*     */     //   386: lload #13
/*     */     //   388: lload #21
/*     */     //   390: lload #19
/*     */     //   392: lsub
/*     */     //   393: lload #19
/*     */     //   395: invokestatic a : ([[SJJJ)V
/*     */     //   398: lload #13
/*     */     //   400: lload #11
/*     */     //   402: lsub
/*     */     //   403: dup2
/*     */     //   404: lstore #19
/*     */     //   406: lconst_1
/*     */     //   407: lcmp
/*     */     //   408: ifle -> 429
/*     */     //   411: aload_0
/*     */     //   412: lload_1
/*     */     //   413: lload_1
/*     */     //   414: lload #19
/*     */     //   416: ladd
/*     */     //   417: aload #5
/*     */     //   419: invokestatic a : ([[SJJLme/konsolas/aac/ad;)V
/*     */     //   422: goto -> 429
/*     */     //   425: invokestatic a : (Ljava/lang/IllegalArgumentException;)Ljava/lang/IllegalArgumentException;
/*     */     //   428: athrow
/*     */     //   429: lload #17
/*     */     //   431: lload #15
/*     */     //   433: lsub
/*     */     //   434: dup2
/*     */     //   435: lstore #19
/*     */     //   437: lconst_1
/*     */     //   438: lcmp
/*     */     //   439: ifle -> 462
/*     */     //   442: aload_0
/*     */     //   443: lload #21
/*     */     //   445: lload #19
/*     */     //   447: lsub
/*     */     //   448: lload #21
/*     */     //   450: aload #5
/*     */     //   452: invokestatic a : ([[SJJLme/konsolas/aac/ad;)V
/*     */     //   455: goto -> 462
/*     */     //   458: invokestatic a : (Ljava/lang/IllegalArgumentException;)Ljava/lang/IllegalArgumentException;
/*     */     //   461: athrow
/*     */     //   462: return
/*     */     // Line number table:
/*     */     //   Java source line number -> byte code offset
/*     */     //   #234	-> 0
/*     */     //   #78	-> 5
/*     */     //   #360	-> 14
/*     */     //   #137	-> 22
/*     */     //   #48	-> 27
/*     */     //   #266	-> 37
/*     */     //   #353	-> 46
/*     */     //   #190	-> 49
/*     */     //   #345	-> 54
/*     */     //   #362	-> 63
/*     */     //   #53	-> 71
/*     */     //   #164	-> 95
/*     */     //   #288	-> 115
/*     */     //   #351	-> 139
/*     */     //   #174	-> 153
/*     */     //   #302	-> 161
/*     */     //   #64	-> 177
/*     */     //   #247	-> 206
/*     */     //   #114	-> 231
/*     */     //   #330	-> 240
/*     */     //   #213	-> 269
/*     */     //   #344	-> 294
/*     */     //   #295	-> 303
/*     */     //   #296	-> 318
/*     */     //   #212	-> 339
/*     */     //   #33	-> 342
/*     */     //   #402	-> 356
/*     */     //   #79	-> 368
/*     */     //   #405	-> 385
/*     */     //   #14	-> 398
/*     */     //   #22	-> 429
/*     */     //   #77	-> 462
/*     */     // Exception table:
/*     */     //   from	to	target	type
/*     */     //   5	23	23	java/lang/IllegalArgumentException
/*     */     //   203	211	214	java/lang/IllegalArgumentException
/*     */     //   266	274	277	java/lang/IllegalArgumentException
/*     */     //   303	314	314	java/lang/IllegalArgumentException
/*     */     //   406	422	425	java/lang/IllegalArgumentException
/*     */     //   437	455	458	java/lang/IllegalArgumentException
/*     */   }
/*     */   
/*     */   public static void a(short[][] paramArrayOfshort, long paramLong1, long paramLong2) {
/*     */     boolean bool = true;
/*     */     char c = '';
/*     */     long[] arrayOfLong1 = new long[256];
/*     */     byte b1 = 0;
/*     */     long[] arrayOfLong2 = new long[256];
/*     */     byte b2 = 0;
/*     */     int[] arrayOfInt = new int[256];
/*     */     byte b3 = 0;
/*     */     arrayOfLong1[b1++] = paramLong1;
/*     */     arrayOfLong2[b2++] = paramLong2 - paramLong1;
/*     */     arrayOfInt[b3++] = 0;
/*     */     long[] arrayOfLong3 = new long[256];
/*     */     long[] arrayOfLong4 = new long[256];
/*     */     byte[][] arrayOfByte = fd.a(paramLong2 - paramLong1);
/*     */     for (; b1 > 0; l2 = arrayOfLong2[--b2], i = arrayOfInt[--b3]) {
/*     */       long l2;
/*     */       int i;
/*     */       long l1 = arrayOfLong1[--b1];
/*     */     } 
/*     */   }
/*     */   
/*     */   public static void a(long[][] paramArrayOflong, short[][] paramArrayOfshort1, short[][] paramArrayOfshort2, boolean paramBoolean) {
/*     */     b(paramArrayOfshort1, paramArrayOfshort2);
/*     */     a(paramArrayOflong, paramArrayOfshort1, paramArrayOfshort2, 0L, k.a(paramArrayOfshort1), paramBoolean);
/*     */   }
/*     */   
/*     */   @Deprecated
/*     */   public static short[][] d(short[][] paramArrayOfshort, long paramLong) {
/*     */     long l = a(paramArrayOfshort);
/*     */     try {
/*     */     
/*     */     } catch (IllegalArgumentException illegalArgumentException) {
/*     */       throw a(null);
/*     */     } 
/*     */     return (paramLong > l) ? d(paramArrayOfshort, paramLong, l) : paramArrayOfshort;
/*     */   }
/*     */   
/*     */   @Deprecated
/*     */   public static void a(short[][] paramArrayOfshort, short paramShort) {
/*     */     int i = paramArrayOfshort.length;
/*     */     try {
/*     */       for (; i-- != 0; Arrays.fill(paramArrayOfshort[i], paramShort));
/*     */     } catch (IllegalArgumentException illegalArgumentException) {
/*     */       throw a(null);
/*     */     } 
/*     */   }
/*     */   
/*     */   @Deprecated
/*     */   public static void e(short[][] paramArrayOfshort, long paramLong1, long paramLong2) {
/*     */     k.a(a(paramArrayOfshort), paramLong1, paramLong2);
/*     */   }
/*     */   
/*     */   public static void b(short[][] paramArrayOfshort, ad paramad) {
/*     */     a(paramArrayOfshort, 0L, k.a(paramArrayOfshort), paramad);
/*     */   }
/*     */   
/*     */   private static void a(long[][] paramArrayOflong, short[][] paramArrayOfshort1, short[][] paramArrayOfshort2, long paramLong1, long paramLong2) {
/*     */     for (long l = paramLong1; ++l < paramLong2; ) {
/*     */       continue;
/*     */       l1 = k.a(paramArrayOflong, l);
/*     */       l2 = l;
/*     */       l3 = k.a(paramArrayOflong, l2 - 1L);
/*     */     } 
/*     */   }
/*     */   
/*     */   @Deprecated
/*     */   public static long a(short[][] paramArrayOfshort) {
/*     */     int i = paramArrayOfshort.length;
/*     */     try {
/*     */     
/*     */     } catch (IllegalArgumentException illegalArgumentException) {
/*     */       throw a(null);
/*     */     } 
/*     */     return (i == 0) ? 0L : (k.a(i - 1) + (paramArrayOfshort[i - 1]).length);
/*     */   }
/*     */   
/*     */   @Deprecated
/*     */   public static void a(short[][] paramArrayOfshort, long paramLong, short[] paramArrayOfshort1, int paramInt1, int paramInt2) {
/*     */     k.a(paramArrayOfshort, paramLong, paramArrayOfshort1, paramInt1, paramInt2);
/*     */   }
/*     */   
/*     */   @Deprecated
/*     */   public static short[][] a(short[][] paramArrayOfshort, long paramLong) {
/*     */     return k.d(paramArrayOfshort, paramLong);
/*     */   }
/*     */   
/*     */   private static void f(short[][] paramArrayOfshort, long paramLong1, long paramLong2) {
/*     */     for (long l = paramLong1; l < paramLong2 - 1L; l2 = l + 1L)
/*     */       long l2, l1 = l; 
/*     */   }
/*     */   
/*     */   private static void a(short[][] paramArrayOfshort, long paramLong1, long paramLong2, long paramLong3) {
/*     */     for (byte b = 0; b < paramLong3; ) {
/*     */       k.c(paramArrayOfshort, paramLong1, paramLong2);
/*     */       b++;
/*     */       paramLong1++;
/*     */       paramLong2++;
/*     */     } 
/*     */   }
/*     */   
/*     */   public static void a(short[][] paramArrayOfshort1, short[][] paramArrayOfshort2) {
/*     */     b(paramArrayOfshort1, paramArrayOfshort2, 0L, k.a(paramArrayOfshort1));
/*     */   }
/*     */   
/*     */   @Deprecated
/*     */   public static short[][] a(short[][] paramArrayOfshort) {
/*     */     return k.b(paramArrayOfshort);
/*     */   }
/*     */   
/*     */   private static final long k = nc.a(-5695746019414532614L, -8202451829905116596L, MethodHandles.lookup().lookupClass()).a(177755058622895L);
/*     */   
/*     */   static {
/*     */     e = new short[0][];
/*     */     c = new short[0][];
/*     */     b = new iN(null);
/*     */   }
/*     */   
/*     */   @Deprecated
/*     */   public static short a(short[][] paramArrayOfshort, long paramLong) {
/*     */     return paramArrayOfshort[k.b(paramLong)][k.a(paramLong)];
/*     */   }
/*     */   
/*     */   @Deprecated
/*     */   public static void c(short[][] paramArrayOfshort, long paramLong1, long paramLong2) {
/*     */     k.b(a(paramArrayOfshort), paramLong1, paramLong2);
/*     */   }
/*     */   
/*     */   @Deprecated
/*     */   public static short[][] b(short[][] paramArrayOfshort, long paramLong1, long paramLong2) {
/*     */     try {
/*     */     
/*     */     } catch (IllegalArgumentException illegalArgumentException) {
/*     */       throw a(null);
/*     */     } 
/*     */     return (paramLong1 > a(paramArrayOfshort)) ? a(paramArrayOfshort, paramLong1, paramLong2) : paramArrayOfshort;
/*     */   }
/*     */   
/*     */   public static void b(short[][] paramArrayOfshort1, short[][] paramArrayOfshort2, long paramLong1, long paramLong2) {
/*     */     // Byte code:
/*     */     //   0: getstatic me/konsolas/aac/ct.k : J
/*     */     //   3: ldc2_w 78712334281176
/*     */     //   6: lxor
/*     */     //   7: lstore #6
/*     */     //   9: iconst_2
/*     */     //   10: istore #8
/*     */     //   12: aload_0
/*     */     //   13: invokestatic a : ([[S)J
/*     */     //   16: aload_1
/*     */     //   17: invokestatic a : ([[S)J
/*     */     //   20: lcmp
/*     */     //   21: ifeq -> 68
/*     */     //   24: new java/lang/IllegalArgumentException
/*     */     //   27: dup
/*     */     //   28: ldc_w ''
/*     */     //   31: invokevirtual toCharArray : ()[C
/*     */     //   34: dup
/*     */     //   35: dup
/*     */     //   36: iconst_5
/*     */     //   37: dup_x1
/*     */     //   38: caload
/*     */     //   39: sipush #32388
/*     */     //   42: ixor
/*     */     //   43: i2c
/*     */     //   44: castore
/*     */     //   45: sipush #11151
/*     */     //   48: iconst_1
/*     */     //   49: iconst_0
/*     */     //   50: invokestatic X : (Ljava/lang/Object;SZZ)Ljava/lang/String;
/*     */     //   53: invokespecial <init> : (Ljava/lang/String;)V
/*     */     //   56: athrow
/*     */     //   57: ldc2_w -2772902564851675403
/*     */     //   60: lload #6
/*     */     //   62: <illegal opcode> w : (Ljava/lang/IllegalArgumentException;JJ)Ljava/lang/IllegalArgumentException;
/*     */     //   67: athrow
/*     */     //   68: iconst_3
/*     */     //   69: istore #9
/*     */     //   71: sipush #766
/*     */     //   74: istore #10
/*     */     //   76: sipush #766
/*     */     //   79: newarray long
/*     */     //   81: astore #11
/*     */     //   83: iconst_0
/*     */     //   84: istore #12
/*     */     //   86: sipush #766
/*     */     //   89: newarray long
/*     */     //   91: astore #13
/*     */     //   93: iconst_0
/*     */     //   94: istore #14
/*     */     //   96: sipush #766
/*     */     //   99: newarray int
/*     */     //   101: astore #15
/*     */     //   103: iconst_0
/*     */     //   104: istore #16
/*     */     //   106: aload #11
/*     */     //   108: iload #12
/*     */     //   110: iinc #12, 1
/*     */     //   113: lload_2
/*     */     //   114: lastore
/*     */     //   115: aload #13
/*     */     //   117: iload #14
/*     */     //   119: iinc #14, 1
/*     */     //   122: lload #4
/*     */     //   124: lload_2
/*     */     //   125: lsub
/*     */     //   126: lastore
/*     */     //   127: aload #15
/*     */     //   129: iload #16
/*     */     //   131: iinc #16, 1
/*     */     //   134: iconst_0
/*     */     //   135: iastore
/*     */     //   136: sipush #256
/*     */     //   139: newarray long
/*     */     //   141: astore #17
/*     */     //   143: sipush #256
/*     */     //   146: newarray long
/*     */     //   148: astore #18
/*     */     //   150: lload #4
/*     */     //   152: lload_2
/*     */     //   153: lsub
/*     */     //   154: invokestatic a : (J)[[B
/*     */     //   157: astore #19
/*     */     //   159: iload #12
/*     */     //   161: ifle -> 756
/*     */     //   164: aload #11
/*     */     //   166: iinc #12, -1
/*     */     //   169: iload #12
/*     */     //   171: laload
/*     */     //   172: lstore #20
/*     */     //   174: aload #13
/*     */     //   176: iinc #14, -1
/*     */     //   179: iload #14
/*     */     //   181: laload
/*     */     //   182: lstore #22
/*     */     //   184: aload #15
/*     */     //   186: iinc #16, -1
/*     */     //   189: iload #16
/*     */     //   191: iaload
/*     */     //   192: istore #24
/*     */     //   194: iload #24
/*     */     //   196: iconst_2
/*     */     //   197: irem
/*     */     //   198: ifne -> 218
/*     */     //   201: sipush #128
/*     */     //   204: goto -> 219
/*     */     //   207: ldc2_w -2772902564851675403
/*     */     //   210: lload #6
/*     */     //   212: <illegal opcode> w : (Ljava/lang/IllegalArgumentException;JJ)Ljava/lang/IllegalArgumentException;
/*     */     //   217: athrow
/*     */     //   218: iconst_0
/*     */     //   219: istore #25
/*     */     //   221: lload #22
/*     */     //   223: ldc2_w 40
/*     */     //   226: lcmp
/*     */     //   227: ifge -> 256
/*     */     //   230: aload_0
/*     */     //   231: aload_1
/*     */     //   232: lload #20
/*     */     //   234: lload #20
/*     */     //   236: lload #22
/*     */     //   238: ladd
/*     */     //   239: invokestatic a : ([[S[[SJJ)V
/*     */     //   242: goto -> 159
/*     */     //   245: ldc2_w -2772902564851675403
/*     */     //   248: lload #6
/*     */     //   250: <illegal opcode> w : (Ljava/lang/IllegalArgumentException;JJ)Ljava/lang/IllegalArgumentException;
/*     */     //   255: athrow
/*     */     //   256: iload #24
/*     */     //   258: iconst_2
/*     */     //   259: if_icmpge -> 277
/*     */     //   262: aload_0
/*     */     //   263: goto -> 278
/*     */     //   266: ldc2_w -2772902564851675403
/*     */     //   269: lload #6
/*     */     //   271: <illegal opcode> w : (Ljava/lang/IllegalArgumentException;JJ)Ljava/lang/IllegalArgumentException;
/*     */     //   276: athrow
/*     */     //   277: aload_1
/*     */     //   278: astore #26
/*     */     //   280: iconst_1
/*     */     //   281: iload #24
/*     */     //   283: iconst_2
/*     */     //   284: irem
/*     */     //   285: isub
/*     */     //   286: bipush #8
/*     */     //   288: imul
/*     */     //   289: istore #27
/*     */     //   291: lload #22
/*     */     //   293: lstore #28
/*     */     //   295: lload #28
/*     */     //   297: dup2
/*     */     //   298: lconst_1
/*     */     //   299: lsub
/*     */     //   300: lstore #28
/*     */     //   302: lconst_0
/*     */     //   303: lcmp
/*     */     //   304: ifeq -> 349
/*     */     //   307: aload #19
/*     */     //   309: lload #28
/*     */     //   311: aload #26
/*     */     //   313: lload #20
/*     */     //   315: lload #28
/*     */     //   317: ladd
/*     */     //   318: invokestatic a : ([[SJ)S
/*     */     //   321: iload #27
/*     */     //   323: iushr
/*     */     //   324: sipush #255
/*     */     //   327: iand
/*     */     //   328: iload #25
/*     */     //   330: ixor
/*     */     //   331: i2b
/*     */     //   332: invokestatic b : ([[BJB)V
/*     */     //   335: goto -> 295
/*     */     //   338: ldc2_w -2772902564851675403
/*     */     //   341: lload #6
/*     */     //   343: <illegal opcode> w : (Ljava/lang/IllegalArgumentException;JJ)Ljava/lang/IllegalArgumentException;
/*     */     //   348: athrow
/*     */     //   349: lload #22
/*     */     //   351: lstore #28
/*     */     //   353: lload #28
/*     */     //   355: dup2
/*     */     //   356: lconst_1
/*     */     //   357: lsub
/*     */     //   358: lstore #28
/*     */     //   360: lconst_0
/*     */     //   361: lcmp
/*     */     //   362: ifeq -> 397
/*     */     //   365: aload #17
/*     */     //   367: aload #19
/*     */     //   369: lload #28
/*     */     //   371: invokestatic a : ([[BJ)B
/*     */     //   374: sipush #255
/*     */     //   377: iand
/*     */     //   378: dup2
/*     */     //   379: laload
/*     */     //   380: lconst_1
/*     */     //   381: ladd
/*     */     //   382: lastore
/*     */     //   383: goto -> 353
/*     */     //   386: ldc2_w -2772902564851675403
/*     */     //   389: lload #6
/*     */     //   391: <illegal opcode> w : (Ljava/lang/IllegalArgumentException;JJ)Ljava/lang/IllegalArgumentException;
/*     */     //   396: athrow
/*     */     //   397: iconst_m1
/*     */     //   398: istore #28
/*     */     //   400: lconst_0
/*     */     //   401: lstore #29
/*     */     //   403: iconst_0
/*     */     //   404: istore #31
/*     */     //   406: iload #31
/*     */     //   408: sipush #256
/*     */     //   411: if_icmpge -> 546
/*     */     //   414: aload #17
/*     */     //   416: iload #31
/*     */     //   418: laload
/*     */     //   419: lconst_0
/*     */     //   420: lcmp
/*     */     //   421: ifeq -> 524
/*     */     //   424: goto -> 438
/*     */     //   427: ldc2_w -2772902564851675403
/*     */     //   430: lload #6
/*     */     //   432: <illegal opcode> w : (Ljava/lang/IllegalArgumentException;JJ)Ljava/lang/IllegalArgumentException;
/*     */     //   437: athrow
/*     */     //   438: iload #31
/*     */     //   440: istore #28
/*     */     //   442: iload #24
/*     */     //   444: iconst_3
/*     */     //   445: if_icmpge -> 524
/*     */     //   448: aload #17
/*     */     //   450: iload #31
/*     */     //   452: laload
/*     */     //   453: lconst_1
/*     */     //   454: lcmp
/*     */     //   455: ifle -> 524
/*     */     //   458: goto -> 472
/*     */     //   461: ldc2_w -2772902564851675403
/*     */     //   464: lload #6
/*     */     //   466: <illegal opcode> w : (Ljava/lang/IllegalArgumentException;JJ)Ljava/lang/IllegalArgumentException;
/*     */     //   471: athrow
/*     */     //   472: aload #11
/*     */     //   474: iload #12
/*     */     //   476: iinc #12, 1
/*     */     //   479: lload #29
/*     */     //   481: lload #20
/*     */     //   483: ladd
/*     */     //   484: lastore
/*     */     //   485: aload #13
/*     */     //   487: iload #14
/*     */     //   489: iinc #14, 1
/*     */     //   492: aload #17
/*     */     //   494: iload #31
/*     */     //   496: laload
/*     */     //   497: lastore
/*     */     //   498: aload #15
/*     */     //   500: iload #16
/*     */     //   502: iinc #16, 1
/*     */     //   505: iload #24
/*     */     //   507: iconst_1
/*     */     //   508: iadd
/*     */     //   509: iastore
/*     */     //   510: goto -> 524
/*     */     //   513: ldc2_w -2772902564851675403
/*     */     //   516: lload #6
/*     */     //   518: <illegal opcode> w : (Ljava/lang/IllegalArgumentException;JJ)Ljava/lang/IllegalArgumentException;
/*     */     //   523: athrow
/*     */     //   524: aload #18
/*     */     //   526: iload #31
/*     */     //   528: lload #29
/*     */     //   530: aload #17
/*     */     //   532: iload #31
/*     */     //   534: laload
/*     */     //   535: ladd
/*     */     //   536: dup2
/*     */     //   537: lstore #29
/*     */     //   539: lastore
/*     */     //   540: iinc #31, 1
/*     */     //   543: goto -> 406
/*     */     //   546: lload #22
/*     */     //   548: aload #17
/*     */     //   550: iload #28
/*     */     //   552: laload
/*     */     //   553: lsub
/*     */     //   554: lstore #31
/*     */     //   556: aload #17
/*     */     //   558: iload #28
/*     */     //   560: lconst_0
/*     */     //   561: lastore
/*     */     //   562: iconst_m1
/*     */     //   563: istore #33
/*     */     //   565: lconst_0
/*     */     //   566: lstore #34
/*     */     //   568: lload #34
/*     */     //   570: lload #31
/*     */     //   572: lcmp
/*     */     //   573: ifge -> 753
/*     */     //   576: aload_0
/*     */     //   577: lload #34
/*     */     //   579: lload #20
/*     */     //   581: ladd
/*     */     //   582: invokestatic a : ([[SJ)S
/*     */     //   585: istore #38
/*     */     //   587: aload_1
/*     */     //   588: lload #34
/*     */     //   590: lload #20
/*     */     //   592: ladd
/*     */     //   593: invokestatic a : ([[SJ)S
/*     */     //   596: istore #39
/*     */     //   598: aload #19
/*     */     //   600: lload #34
/*     */     //   602: invokestatic a : ([[BJ)B
/*     */     //   605: sipush #255
/*     */     //   608: iand
/*     */     //   609: istore #33
/*     */     //   611: aload #18
/*     */     //   613: iload #33
/*     */     //   615: dup2
/*     */     //   616: laload
/*     */     //   617: lconst_1
/*     */     //   618: lsub
/*     */     //   619: dup2_x2
/*     */     //   620: lastore
/*     */     //   621: dup2
/*     */     //   622: lstore #36
/*     */     //   624: lload #34
/*     */     //   626: lcmp
/*     */     //   627: ifle -> 712
/*     */     //   630: iload #38
/*     */     //   632: istore #40
/*     */     //   634: iload #33
/*     */     //   636: istore #41
/*     */     //   638: aload_0
/*     */     //   639: lload #36
/*     */     //   641: lload #20
/*     */     //   643: ladd
/*     */     //   644: invokestatic a : ([[SJ)S
/*     */     //   647: istore #38
/*     */     //   649: aload_0
/*     */     //   650: lload #36
/*     */     //   652: lload #20
/*     */     //   654: ladd
/*     */     //   655: iload #40
/*     */     //   657: invokestatic b : ([[SJS)V
/*     */     //   660: iload #39
/*     */     //   662: istore #40
/*     */     //   664: aload_1
/*     */     //   665: lload #36
/*     */     //   667: lload #20
/*     */     //   669: ladd
/*     */     //   670: invokestatic a : ([[SJ)S
/*     */     //   673: istore #39
/*     */     //   675: aload_1
/*     */     //   676: lload #36
/*     */     //   678: lload #20
/*     */     //   680: ladd
/*     */     //   681: iload #40
/*     */     //   683: invokestatic b : ([[SJS)V
/*     */     //   686: aload #19
/*     */     //   688: lload #36
/*     */     //   690: invokestatic a : ([[BJ)B
/*     */     //   693: sipush #255
/*     */     //   696: iand
/*     */     //   697: istore #33
/*     */     //   699: aload #19
/*     */     //   701: lload #36
/*     */     //   703: iload #41
/*     */     //   705: i2b
/*     */     //   706: invokestatic b : ([[BJB)V
/*     */     //   709: goto -> 611
/*     */     //   712: aload_0
/*     */     //   713: lload #34
/*     */     //   715: lload #20
/*     */     //   717: ladd
/*     */     //   718: iload #38
/*     */     //   720: invokestatic b : ([[SJS)V
/*     */     //   723: aload_1
/*     */     //   724: lload #34
/*     */     //   726: lload #20
/*     */     //   728: ladd
/*     */     //   729: iload #39
/*     */     //   731: invokestatic b : ([[SJS)V
/*     */     //   734: lload #34
/*     */     //   736: aload #17
/*     */     //   738: iload #33
/*     */     //   740: laload
/*     */     //   741: ladd
/*     */     //   742: lstore #34
/*     */     //   744: aload #17
/*     */     //   746: iload #33
/*     */     //   748: lconst_0
/*     */     //   749: lastore
/*     */     //   750: goto -> 568
/*     */     //   753: goto -> 159
/*     */     //   756: return
/*     */     // Line number table:
/*     */     //   Java source line number -> byte code offset
/*     */     //   #366	-> 9
/*     */     //   #211	-> 12
/*     */     //   #280	-> 68
/*     */     //   #26	-> 71
/*     */     //   #159	-> 76
/*     */     //   #407	-> 83
/*     */     //   #319	-> 86
/*     */     //   #297	-> 93
/*     */     //   #100	-> 96
/*     */     //   #268	-> 103
/*     */     //   #229	-> 106
/*     */     //   #256	-> 115
/*     */     //   #58	-> 127
/*     */     //   #287	-> 136
/*     */     //   #237	-> 143
/*     */     //   #221	-> 150
/*     */     //   #2	-> 159
/*     */     //   #18	-> 164
/*     */     //   #40	-> 174
/*     */     //   #250	-> 184
/*     */     //   #83	-> 194
/*     */     //   #395	-> 221
/*     */     //   #385	-> 230
/*     */     //   #135	-> 242
/*     */     //   #23	-> 256
/*     */     //   #363	-> 280
/*     */     //   #142	-> 291
/*     */     //   #307	-> 349
/*     */     //   #216	-> 397
/*     */     //   #199	-> 400
/*     */     //   #355	-> 403
/*     */     //   #235	-> 414
/*     */     //   #356	-> 438
/*     */     //   #390	-> 442
/*     */     //   #215	-> 472
/*     */     //   #244	-> 485
/*     */     //   #387	-> 498
/*     */     //   #397	-> 524
/*     */     //   #123	-> 540
/*     */     //   #368	-> 546
/*     */     //   #44	-> 556
/*     */     //   #206	-> 562
/*     */     //   #375	-> 565
/*     */     //   #89	-> 576
/*     */     //   #194	-> 587
/*     */     //   #364	-> 598
/*     */     //   #276	-> 611
/*     */     //   #98	-> 630
/*     */     //   #298	-> 634
/*     */     //   #39	-> 638
/*     */     //   #309	-> 649
/*     */     //   #222	-> 660
/*     */     //   #61	-> 664
/*     */     //   #69	-> 675
/*     */     //   #352	-> 686
/*     */     //   #128	-> 699
/*     */     //   #208	-> 709
/*     */     //   #282	-> 712
/*     */     //   #342	-> 723
/*     */     //   #232	-> 734
/*     */     //   #105	-> 753
/*     */     //   #376	-> 756
/*     */     // Exception table:
/*     */     //   from	to	target	type
/*     */     //   12	57	57	java/lang/IllegalArgumentException
/*     */     //   194	207	207	java/lang/IllegalArgumentException
/*     */     //   221	245	245	java/lang/IllegalArgumentException
/*     */     //   256	266	266	java/lang/IllegalArgumentException
/*     */     //   302	338	338	java/lang/IllegalArgumentException
/*     */     //   360	386	386	java/lang/IllegalArgumentException
/*     */     //   406	424	427	java/lang/IllegalArgumentException
/*     */     //   442	458	461	java/lang/IllegalArgumentException
/*     */     //   448	510	513	java/lang/IllegalArgumentException
/*     */   }
/*     */   
/*     */   private static void a(short[][] paramArrayOfshort1, short[][] paramArrayOfshort2, long paramLong1, long paramLong2) {
/*     */     long l;
/*     */     for (l = paramLong1; l < paramLong2 - 1L; ) {
/*     */       continue;
/*     */       l1 = l;
/*     */       l2 = l + 1L;
/*     */       while (true)
/*     */         l2++; 
/*     */       if (l1 != l) {
/*     */         short s = k.a(paramArrayOfshort1, l);
/*     */         k.b(paramArrayOfshort1, l, k.a(paramArrayOfshort1, l1));
/*     */         k.b(paramArrayOfshort1, l1, s);
/*     */         s = k.a(paramArrayOfshort2, l);
/*     */         k.b(paramArrayOfshort2, l, k.a(paramArrayOfshort2, l1));
/*     */         k.b(paramArrayOfshort2, l1, s);
/*     */       } 
/*     */       l++;
/*     */     } 
/*     */   }
/*     */   
/*     */   @Deprecated
/*     */   public static void c(short[][] paramArrayOfshort, long paramLong, short paramShort) {
/*     */     paramArrayOfshort[k.b(paramLong)][k.a(paramLong)] = (short)(paramArrayOfshort[k.b(paramLong)][k.a(paramLong)] + paramShort);
/*     */   }
/*     */   
/*     */   @Deprecated
/*     */   public static short[][] b(short[][] paramArrayOfshort, long paramLong) {
/*     */     return b(paramArrayOfshort, paramLong, a(paramArrayOfshort));
/*     */   }
/*     */   
/*     */   public static void c(short[][] paramArrayOfshort) {
/*     */     d(paramArrayOfshort, 0L, k.a(paramArrayOfshort));
/*     */   }
/*     */   
/*     */   @Deprecated
/*     */   public static void b(short[][] paramArrayOfshort1, short[][] paramArrayOfshort2) {
/*     */     // Byte code:
/*     */     //   0: getstatic me/konsolas/aac/ct.k : J
/*     */     //   3: ldc2_w 50261337808349
/*     */     //   6: lxor
/*     */     //   7: lstore_2
/*     */     //   8: aload_0
/*     */     //   9: invokestatic a : ([[S)J
/*     */     //   12: aload_1
/*     */     //   13: invokestatic a : ([[S)J
/*     */     //   16: lcmp
/*     */     //   17: ifeq -> 116
/*     */     //   20: new java/lang/IllegalArgumentException
/*     */     //   23: dup
/*     */     //   24: new java/lang/StringBuilder
/*     */     //   27: dup
/*     */     //   28: invokespecial <init> : ()V
/*     */     //   31: ldc ''
/*     */     //   33: invokevirtual toCharArray : ()[C
/*     */     //   36: dup
/*     */     //   37: dup
/*     */     //   38: iconst_3
/*     */     //   39: dup_x1
/*     */     //   40: caload
/*     */     //   41: sipush #17183
/*     */     //   44: ixor
/*     */     //   45: i2c
/*     */     //   46: castore
/*     */     //   47: sipush #12440
/*     */     //   50: iconst_1
/*     */     //   51: iconst_1
/*     */     //   52: invokestatic G : (Ljava/lang/Object;SZB)Ljava/lang/String;
/*     */     //   55: invokevirtual append : (Ljava/lang/String;)Ljava/lang/StringBuilder;
/*     */     //   58: aload_0
/*     */     //   59: invokestatic a : ([[S)J
/*     */     //   62: invokevirtual append : (J)Ljava/lang/StringBuilder;
/*     */     //   65: ldc '?'
/*     */     //   67: invokevirtual toCharArray : ()[C
/*     */     //   70: dup
/*     */     //   71: dup
/*     */     //   72: iconst_1
/*     */     //   73: dup_x1
/*     */     //   74: caload
/*     */     //   75: sipush #14252
/*     */     //   78: ixor
/*     */     //   79: i2c
/*     */     //   80: castore
/*     */     //   81: sipush #16611
/*     */     //   84: iconst_1
/*     */     //   85: iconst_5
/*     */     //   86: invokestatic G : (Ljava/lang/Object;SZB)Ljava/lang/String;
/*     */     //   89: invokevirtual append : (Ljava/lang/String;)Ljava/lang/StringBuilder;
/*     */     //   92: aload_1
/*     */     //   93: invokestatic a : ([[S)J
/*     */     //   96: invokevirtual append : (J)Ljava/lang/StringBuilder;
/*     */     //   99: invokevirtual toString : ()Ljava/lang/String;
/*     */     //   102: invokespecial <init> : (Ljava/lang/String;)V
/*     */     //   105: athrow
/*     */     //   106: ldc2_w 3279115239377468144
/*     */     //   109: lload_2
/*     */     //   110: <illegal opcode> w : (Ljava/lang/IllegalArgumentException;JJ)Ljava/lang/IllegalArgumentException;
/*     */     //   115: athrow
/*     */     //   116: return
/*     */     // Line number table:
/*     */     //   Java source line number -> byte code offset
/*     */     //   #411	-> 8
/*     */     //   #204	-> 116
/*     */     // Exception table:
/*     */     //   from	to	target	type
/*     */     //   8	106	106	java/lang/IllegalArgumentException
/*     */   }
/*     */   
/*     */   private static IllegalArgumentException a(IllegalArgumentException paramIllegalArgumentException) {
/*     */     return paramIllegalArgumentException;
/*     */   } }


/* Location:              C:\Users\BukkitBypass\Desktop\MatrixAC\AAC\AAC-spigot-5.2.0.jar!\me\konsolas\aac\ct.class
 * Java compiler version: 8 (52.0)
 * JD-Core Version:       1.1.3
 */