/*    */ package me.konsolas.aac;
/*    */ 
/*    */ import java.io.IOException;
/*    */ import java.lang.invoke.CallSite;
/*    */ import java.lang.invoke.MethodHandle;
/*    */ import java.lang.invoke.MethodHandles;
/*    */ import java.lang.invoke.MethodType;
/*    */ import java.lang.invoke.MutableCallSite;
/*    */ import java.util.Map;
/*    */ import javax.crypto.Cipher;
/*    */ import javax.crypto.SecretKey;
/*    */ import javax.crypto.SecretKeyFactory;
/*    */ import javax.crypto.spec.DESKeySpec;
/*    */ import javax.crypto.spec.IvParameterSpec;
/*    */ 
/*    */ public final class cx {
/*    */   static final gZ c;
/*    */   static final int s = 16384;
/*    */   static final byte j = 0;
/*    */   static final byte w = 1;
/*    */   static final byte f = 2;
/*    */   static final byte g = 3;
/*    */   
/*    */   static IOException a(String paramString, Object[] paramArrayOfObject) {
/* 25 */     throw new IOException(eO.a(paramString, paramArrayOfObject));
/*    */   }
/*    */ 
/*    */   
/*    */   static final byte q = 4;
/*    */   
/*    */   static final byte k = 5;
/*    */   static final byte v = 6;
/*    */   static final byte a = 7;
/*    */   static final byte d = 8;
/*    */   static final byte p = 9;
/*    */   static final byte o = 0;
/*    */   
/*    */   static IllegalArgumentException a(String paramString, Object[] paramArrayOfObject) {
/* 39 */     throw new IllegalArgumentException(eO.a(paramString, paramArrayOfObject));
/*    */   }
/*    */   
/*    */   static final byte n = 1;
/*    */   static final byte m = 1;
/*    */   static final byte t = 4;
/*    */   static final byte b = 4;
/*    */   static final byte i = 8;
/*    */   static final byte u = 32;
/*    */   static final byte r = 32;
/*    */   private static final String[] l;
/*    */   static final String[] e;
/*    */   static final String[] h;
/*    */   private static final long x;
/*    */   private static final String[] y;
/*    */   private static final String[] z;
/*    */   private static final Map A;
/*    */   
/*    */   static String a(boolean paramBoolean, char paramChar1, int paramInt1, int paramInt2, int paramInt3, char paramChar2, byte paramByte1, byte paramByte2) {
/*    */     // Byte code:
/*    */     //   0: iload_1
/*    */     //   1: i2l
/*    */     //   2: bipush #48
/*    */     //   4: lshl
/*    */     //   5: iload #4
/*    */     //   7: i2l
/*    */     //   8: bipush #32
/*    */     //   10: lshl
/*    */     //   11: bipush #16
/*    */     //   13: lushr
/*    */     //   14: lor
/*    */     //   15: iload #5
/*    */     //   17: i2l
/*    */     //   18: bipush #48
/*    */     //   20: lshl
/*    */     //   21: bipush #48
/*    */     //   23: lushr
/*    */     //   24: lor
/*    */     //   25: getstatic me/konsolas/aac/cx.x : J
/*    */     //   28: lxor
/*    */     //   29: lstore #8
/*    */     //   31: lload #8
/*    */     //   33: dup2
/*    */     //   34: ldc2_w 109794053354759
/*    */     //   37: lxor
/*    */     //   38: lstore #10
/*    */     //   40: pop2
/*    */     //   41: iload #6
/*    */     //   43: getstatic me/konsolas/aac/cx.l : [Ljava/lang/String;
/*    */     //   46: arraylength
/*    */     //   47: if_icmpge -> 70
/*    */     //   50: getstatic me/konsolas/aac/cx.l : [Ljava/lang/String;
/*    */     //   53: iload #6
/*    */     //   55: aaload
/*    */     //   56: goto -> 99
/*    */     //   59: ldc2_w -4001822966413152321
/*    */     //   62: lload #8
/*    */     //   64: <illegal opcode> w : (Ljava/lang/IllegalArgumentException;JJ)Ljava/lang/IllegalArgumentException;
/*    */     //   69: athrow
/*    */     //   70: sipush #9761
/*    */     //   73: ldc2_w 8610425715491260410
/*    */     //   76: lload #8
/*    */     //   78: lxor
/*    */     //   79: <illegal opcode> r : (IJ)Ljava/lang/String;
/*    */     //   84: iconst_1
/*    */     //   85: anewarray java/lang/Object
/*    */     //   88: dup
/*    */     //   89: iconst_0
/*    */     //   90: iload #6
/*    */     //   92: invokestatic valueOf : (B)Ljava/lang/Byte;
/*    */     //   95: aastore
/*    */     //   96: invokestatic a : (Ljava/lang/String;[Ljava/lang/Object;)Ljava/lang/String;
/*    */     //   99: astore #12
/*    */     //   101: iload #6
/*    */     //   103: lload #10
/*    */     //   105: iload #7
/*    */     //   107: invokestatic a : (BJB)Ljava/lang/String;
/*    */     //   110: astore #13
/*    */     //   112: sipush #25022
/*    */     //   115: ldc2_w 1818248235489263742
/*    */     //   118: lload #8
/*    */     //   120: lxor
/*    */     //   121: <illegal opcode> r : (IJ)Ljava/lang/String;
/*    */     //   126: iconst_5
/*    */     //   127: anewarray java/lang/Object
/*    */     //   130: dup
/*    */     //   131: iconst_0
/*    */     //   132: iload_0
/*    */     //   133: iload #4
/*    */     //   135: iflt -> 172
/*    */     //   138: ifeq -> 169
/*    */     //   141: sipush #18916
/*    */     //   144: ldc2_w 1222817041885079603
/*    */     //   147: lload #8
/*    */     //   149: lxor
/*    */     //   150: <illegal opcode> r : (IJ)Ljava/lang/String;
/*    */     //   155: goto -> 183
/*    */     //   158: ldc2_w -4001822966413152321
/*    */     //   161: lload #8
/*    */     //   163: <illegal opcode> w : (Ljava/lang/IllegalArgumentException;JJ)Ljava/lang/IllegalArgumentException;
/*    */     //   168: athrow
/*    */     //   169: sipush #25804
/*    */     //   172: ldc2_w 5045121638827853071
/*    */     //   175: lload #8
/*    */     //   177: lxor
/*    */     //   178: <illegal opcode> r : (IJ)Ljava/lang/String;
/*    */     //   183: aastore
/*    */     //   184: dup
/*    */     //   185: iconst_1
/*    */     //   186: iload_2
/*    */     //   187: invokestatic valueOf : (I)Ljava/lang/Integer;
/*    */     //   190: aastore
/*    */     //   191: dup
/*    */     //   192: iconst_2
/*    */     //   193: iload_3
/*    */     //   194: invokestatic valueOf : (I)Ljava/lang/Integer;
/*    */     //   197: aastore
/*    */     //   198: dup
/*    */     //   199: iconst_3
/*    */     //   200: aload #12
/*    */     //   202: aastore
/*    */     //   203: dup
/*    */     //   204: iconst_4
/*    */     //   205: aload #13
/*    */     //   207: aastore
/*    */     //   208: invokestatic a : (Ljava/lang/String;[Ljava/lang/Object;)Ljava/lang/String;
/*    */     //   211: areturn
/*    */     // Line number table:
/*    */     //   Java source line number -> byte code offset
/*    */     //   #37	-> 41
/*    */     //   #31	-> 101
/*    */     //   #16	-> 112
/*    */     // Exception table:
/*    */     //   from	to	target	type
/*    */     //   41	59	59	java/lang/IllegalArgumentException
/*    */     //   112	158	158	java/lang/IllegalArgumentException
/*    */   }
/*    */   
/*    */   static String a(byte paramByte1, long paramLong, byte paramByte2) {
/*    */     // Byte code:
/*    */     //   0: getstatic me/konsolas/aac/cx.x : J
/*    */     //   3: lload_1
/*    */     //   4: lxor
/*    */     //   5: lstore_1
/*    */     //   6: ldc2_w 6273632108850361110
/*    */     //   9: lload_1
/*    */     //   10: <illegal opcode> w : (JJ)[Lme/konsolas/aac/aN;
/*    */     //   15: astore #4
/*    */     //   17: iload_3
/*    */     //   18: aload #4
/*    */     //   20: ifnull -> 53
/*    */     //   23: ifne -> 52
/*    */     //   26: goto -> 39
/*    */     //   29: ldc2_w 6205060783442833877
/*    */     //   32: lload_1
/*    */     //   33: <illegal opcode> w : (Ljava/lang/IllegalArgumentException;JJ)Ljava/lang/IllegalArgumentException;
/*    */     //   38: athrow
/*    */     //   39: ldc ''
/*    */     //   41: areturn
/*    */     //   42: ldc2_w 6205060783442833877
/*    */     //   45: lload_1
/*    */     //   46: <illegal opcode> w : (Ljava/lang/IllegalArgumentException;JJ)Ljava/lang/IllegalArgumentException;
/*    */     //   51: athrow
/*    */     //   52: iload_0
/*    */     //   53: lload_1
/*    */     //   54: lconst_0
/*    */     //   55: lcmp
/*    */     //   56: iflt -> 175
/*    */     //   59: aload #4
/*    */     //   61: ifnull -> 175
/*    */     //   64: tableswitch default -> 174, 2 -> 168, 3 -> 168, 4 -> 118, 5 -> 174, 6 -> 118, 7 -> 168, 8 -> 168
/*    */     //   108: ldc2_w 6205060783442833877
/*    */     //   111: lload_1
/*    */     //   112: <illegal opcode> w : (Ljava/lang/IllegalArgumentException;JJ)Ljava/lang/IllegalArgumentException;
/*    */     //   117: athrow
/*    */     //   118: iload_3
/*    */     //   119: iconst_1
/*    */     //   120: if_icmpne -> 162
/*    */     //   123: goto -> 136
/*    */     //   126: ldc2_w 6205060783442833877
/*    */     //   129: lload_1
/*    */     //   130: <illegal opcode> w : (Ljava/lang/IllegalArgumentException;JJ)Ljava/lang/IllegalArgumentException;
/*    */     //   135: athrow
/*    */     //   136: sipush #23023
/*    */     //   139: ldc2_w 1310193683922331224
/*    */     //   142: lload_1
/*    */     //   143: lxor
/*    */     //   144: <illegal opcode> r : (IJ)Ljava/lang/String;
/*    */     //   149: goto -> 167
/*    */     //   152: ldc2_w 6205060783442833877
/*    */     //   155: lload_1
/*    */     //   156: <illegal opcode> w : (Ljava/lang/IllegalArgumentException;JJ)Ljava/lang/IllegalArgumentException;
/*    */     //   161: athrow
/*    */     //   162: getstatic me/konsolas/aac/cx.h : [Ljava/lang/String;
/*    */     //   165: iload_3
/*    */     //   166: aaload
/*    */     //   167: areturn
/*    */     //   168: getstatic me/konsolas/aac/cx.h : [Ljava/lang/String;
/*    */     //   171: iload_3
/*    */     //   172: aaload
/*    */     //   173: areturn
/*    */     //   174: iload_3
/*    */     //   175: getstatic me/konsolas/aac/cx.e : [Ljava/lang/String;
/*    */     //   178: arraylength
/*    */     //   179: if_icmpge -> 200
/*    */     //   182: getstatic me/konsolas/aac/cx.e : [Ljava/lang/String;
/*    */     //   185: iload_3
/*    */     //   186: aaload
/*    */     //   187: goto -> 205
/*    */     //   190: ldc2_w 6205060783442833877
/*    */     //   193: lload_1
/*    */     //   194: <illegal opcode> w : (Ljava/lang/IllegalArgumentException;JJ)Ljava/lang/IllegalArgumentException;
/*    */     //   199: athrow
/*    */     //   200: getstatic me/konsolas/aac/cx.h : [Ljava/lang/String;
/*    */     //   203: iload_3
/*    */     //   204: aaload
/*    */     //   205: astore #5
/*    */     //   207: iload_0
/*    */     //   208: aload #4
/*    */     //   210: ifnull -> 316
/*    */     //   213: iconst_5
/*    */     //   214: if_icmpne -> 315
/*    */     //   217: goto -> 230
/*    */     //   220: ldc2_w 6205060783442833877
/*    */     //   223: lload_1
/*    */     //   224: <illegal opcode> w : (Ljava/lang/IllegalArgumentException;JJ)Ljava/lang/IllegalArgumentException;
/*    */     //   229: athrow
/*    */     //   230: iload_3
/*    */     //   231: iconst_4
/*    */     //   232: iand
/*    */     //   233: aload #4
/*    */     //   235: lload_1
/*    */     //   236: lconst_0
/*    */     //   237: lcmp
/*    */     //   238: iflt -> 324
/*    */     //   241: ifnull -> 316
/*    */     //   244: goto -> 257
/*    */     //   247: ldc2_w 6205060783442833877
/*    */     //   250: lload_1
/*    */     //   251: <illegal opcode> w : (Ljava/lang/IllegalArgumentException;JJ)Ljava/lang/IllegalArgumentException;
/*    */     //   256: athrow
/*    */     //   257: ifeq -> 315
/*    */     //   260: goto -> 273
/*    */     //   263: ldc2_w 6205060783442833877
/*    */     //   266: lload_1
/*    */     //   267: <illegal opcode> w : (Ljava/lang/IllegalArgumentException;JJ)Ljava/lang/IllegalArgumentException;
/*    */     //   272: athrow
/*    */     //   273: aload #5
/*    */     //   275: sipush #31329
/*    */     //   278: ldc2_w 7341943432483309015
/*    */     //   281: lload_1
/*    */     //   282: lxor
/*    */     //   283: <illegal opcode> r : (IJ)Ljava/lang/String;
/*    */     //   288: sipush #24447
/*    */     //   291: ldc2_w 723706067157721300
/*    */     //   294: lload_1
/*    */     //   295: lxor
/*    */     //   296: <illegal opcode> r : (IJ)Ljava/lang/String;
/*    */     //   301: invokevirtual replace : (Ljava/lang/CharSequence;Ljava/lang/CharSequence;)Ljava/lang/String;
/*    */     //   304: areturn
/*    */     //   305: ldc2_w 6205060783442833877
/*    */     //   308: lload_1
/*    */     //   309: <illegal opcode> w : (Ljava/lang/IllegalArgumentException;JJ)Ljava/lang/IllegalArgumentException;
/*    */     //   314: athrow
/*    */     //   315: iload_0
/*    */     //   316: lload_1
/*    */     //   317: lconst_0
/*    */     //   318: lcmp
/*    */     //   319: iflt -> 360
/*    */     //   322: aload #4
/*    */     //   324: ifnull -> 360
/*    */     //   327: ifne -> 405
/*    */     //   330: goto -> 343
/*    */     //   333: ldc2_w 6205060783442833877
/*    */     //   336: lload_1
/*    */     //   337: <illegal opcode> w : (Ljava/lang/IllegalArgumentException;JJ)Ljava/lang/IllegalArgumentException;
/*    */     //   342: athrow
/*    */     //   343: iload_3
/*    */     //   344: bipush #32
/*    */     //   346: iand
/*    */     //   347: goto -> 360
/*    */     //   350: ldc2_w 6205060783442833877
/*    */     //   353: lload_1
/*    */     //   354: <illegal opcode> w : (Ljava/lang/IllegalArgumentException;JJ)Ljava/lang/IllegalArgumentException;
/*    */     //   359: athrow
/*    */     //   360: ifeq -> 405
/*    */     //   363: aload #5
/*    */     //   365: sipush #9453
/*    */     //   368: ldc2_w 3245432469170805573
/*    */     //   371: lload_1
/*    */     //   372: lxor
/*    */     //   373: <illegal opcode> r : (IJ)Ljava/lang/String;
/*    */     //   378: sipush #1634
/*    */     //   381: ldc2_w 7227729259691342297
/*    */     //   384: lload_1
/*    */     //   385: lxor
/*    */     //   386: <illegal opcode> r : (IJ)Ljava/lang/String;
/*    */     //   391: invokevirtual replace : (Ljava/lang/CharSequence;Ljava/lang/CharSequence;)Ljava/lang/String;
/*    */     //   394: areturn
/*    */     //   395: ldc2_w 6205060783442833877
/*    */     //   398: lload_1
/*    */     //   399: <illegal opcode> w : (Ljava/lang/IllegalArgumentException;JJ)Ljava/lang/IllegalArgumentException;
/*    */     //   404: athrow
/*    */     //   405: aload #5
/*    */     //   407: areturn
/*    */     // Line number table:
/*    */     //   Java source line number -> byte code offset
/*    */     //   #38	-> 17
/*    */     //   #14	-> 52
/*    */     //   #7	-> 118
/*    */     //   #33	-> 168
/*    */     //   #32	-> 174
/*    */     //   #43	-> 207
/*    */     //   #46	-> 273
/*    */     //   #45	-> 315
/*    */     //   #40	-> 363
/*    */     //   #18	-> 405
/*    */     // Exception table:
/*    */     //   from	to	target	type
/*    */     //   17	26	29	java/lang/IllegalArgumentException
/*    */     //   23	42	42	java/lang/IllegalArgumentException
/*    */     //   53	108	108	java/lang/IllegalArgumentException
/*    */     //   64	123	126	java/lang/IllegalArgumentException
/*    */     //   118	152	152	java/lang/IllegalArgumentException
/*    */     //   175	190	190	java/lang/IllegalArgumentException
/*    */     //   207	217	220	java/lang/IllegalArgumentException
/*    */     //   213	244	247	java/lang/IllegalArgumentException
/*    */     //   230	260	263	java/lang/IllegalArgumentException
/*    */     //   257	305	305	java/lang/IllegalArgumentException
/*    */     //   316	330	333	java/lang/IllegalArgumentException
/*    */     //   327	347	350	java/lang/IllegalArgumentException
/*    */     //   360	395	395	java/lang/IllegalArgumentException
/*    */   }
/*    */   
/*    */   static {
/*    */     // Byte code:
/*    */     //   0: ldc2_w -2837159946074725720
/*    */     //   3: ldc2_w -91494598624236906
/*    */     //   6: invokestatic lookup : ()Ljava/lang/invoke/MethodHandles$Lookup;
/*    */     //   9: invokevirtual lookupClass : ()Ljava/lang/Class;
/*    */     //   12: invokestatic a : (JJLjava/lang/Object;)Lme/konsolas/aac/na;
/*    */     //   15: ldc2_w 275676098094721
/*    */     //   18: invokeinterface a : (J)J
/*    */     //   23: putstatic me/konsolas/aac/cx.x : J
/*    */     //   26: getstatic me/konsolas/aac/cx.x : J
/*    */     //   29: ldc2_w 63214644592461
/*    */     //   32: lxor
/*    */     //   33: lstore #9
/*    */     //   35: lload #9
/*    */     //   37: dup2
/*    */     //   38: ldc2_w 116854201524238
/*    */     //   41: lxor
/*    */     //   42: lstore #11
/*    */     //   44: pop2
/*    */     //   45: new java/util/HashMap
/*    */     //   48: dup
/*    */     //   49: bipush #13
/*    */     //   51: invokespecial <init> : (I)V
/*    */     //   54: putstatic me/konsolas/aac/cx.A : Ljava/util/Map;
/*    */     //   57: ldc '蝎哘嵥欷쿎䜵폟祈㷇씥?굝퓎膫㻪몄䝋ꖭ簷콳䤼'
/*    */     //   59: invokevirtual toCharArray : ()[C
/*    */     //   62: dup
/*    */     //   63: dup
/*    */     //   64: bipush #17
/*    */     //   66: dup_x1
/*    */     //   67: caload
/*    */     //   68: sipush #17509
/*    */     //   71: ixor
/*    */     //   72: i2c
/*    */     //   73: castore
/*    */     //   74: sipush #28771
/*    */     //   77: iconst_0
/*    */     //   78: iconst_0
/*    */     //   79: invokestatic U : (Ljava/lang/Object;SZZ)Ljava/lang/String;
/*    */     //   82: invokestatic getInstance : (Ljava/lang/String;)Ljavax/crypto/Cipher;
/*    */     //   85: dup
/*    */     //   86: astore_0
/*    */     //   87: iconst_2
/*    */     //   88: ldc '좰?ᦪ仒'
/*    */     //   90: invokevirtual toCharArray : ()[C
/*    */     //   93: dup
/*    */     //   94: dup
/*    */     //   95: iconst_1
/*    */     //   96: dup_x1
/*    */     //   97: caload
/*    */     //   98: sipush #11560
/*    */     //   101: ixor
/*    */     //   102: i2c
/*    */     //   103: castore
/*    */     //   104: sipush #4688
/*    */     //   107: iconst_1
/*    */     //   108: iconst_1
/*    */     //   109: invokestatic U : (Ljava/lang/Object;SZZ)Ljava/lang/String;
/*    */     //   112: invokestatic getInstance : (Ljava/lang/String;)Ljavax/crypto/SecretKeyFactory;
/*    */     //   115: bipush #8
/*    */     //   117: newarray byte
/*    */     //   119: dup
/*    */     //   120: iconst_0
/*    */     //   121: lload #9
/*    */     //   123: bipush #56
/*    */     //   125: lushr
/*    */     //   126: l2i
/*    */     //   127: i2b
/*    */     //   128: bastore
/*    */     //   129: iconst_1
/*    */     //   130: istore_1
/*    */     //   131: iload_1
/*    */     //   132: bipush #8
/*    */     //   134: if_icmpge -> 158
/*    */     //   137: dup
/*    */     //   138: iload_1
/*    */     //   139: lload #9
/*    */     //   141: iload_1
/*    */     //   142: bipush #8
/*    */     //   144: imul
/*    */     //   145: lshl
/*    */     //   146: bipush #56
/*    */     //   148: lushr
/*    */     //   149: l2i
/*    */     //   150: i2b
/*    */     //   151: bastore
/*    */     //   152: iinc #1, 1
/*    */     //   155: goto -> 131
/*    */     //   158: new javax/crypto/spec/DESKeySpec
/*    */     //   161: dup_x1
/*    */     //   162: swap
/*    */     //   163: invokespecial <init> : ([B)V
/*    */     //   166: invokevirtual generateSecret : (Ljava/security/spec/KeySpec;)Ljavax/crypto/SecretKey;
/*    */     //   169: new javax/crypto/spec/IvParameterSpec
/*    */     //   172: dup
/*    */     //   173: bipush #8
/*    */     //   175: newarray byte
/*    */     //   177: invokespecial <init> : ([B)V
/*    */     //   180: invokevirtual init : (ILjava/security/Key;Ljava/security/spec/AlgorithmParameterSpec;)V
/*    */     //   183: bipush #27
/*    */     //   185: anewarray java/lang/String
/*    */     //   188: astore #7
/*    */     //   190: iconst_0
/*    */     //   191: istore #5
/*    */     //   193: ldc '吶氰ૃ茗練?ʼ퇭諱ᱚ킜㊘奲徙秈韑쩞㐮䰠ꍢ錙䛚ꨚჼ➃鷙삠穀럱涨뙯Ⱶ蔱௫莱됾㡊秕㾰ⵝ嘸ཟ౴禀硿慤할⨨黼̲綄㡕ꊯ예᩶챋๥퇲䀮嵀㚘✃䷷냋ѣ쀿빩빽₭熿夭ꢏ᜹柳ᕱ뚿麗쵧澖닙ᰦ롖懁岰虒䑴?쥽슺㑆썷⬮ጪ怏ⶖ솆⸆뜊솨𢡄࿆㊋᤺宽퍰ﴗ縻쓁㹓ఒ㪿撘ﴍ?徃お䛘㿿᛭㇑徂丕ᾑⴷ┲ٻ揰㭞ډௗ쁏ᥬ㭥움찁陵翓㽂灞巅邵ŋ᠈ເ乻涹꫽麶ڿ뢁詹蚝㪵⻰閑꾺펊ﮞ䓆ꊞ愭菬⣼㑤爵圆嫭䟄縑줶ᓦᤍො㞏᱾鑱窢ᓼ㨼꼫榲㣀䆶᧽☩⽋力㵶춮ײ뇦⠉⽇紐꨽廇갩婊鳕公ᙢ惗ꨎቌ长붰精臮㥺墛勽ꓖ?蚗க꿳ಗ픝ʄ⯩蜩뛵⭀즥㱩ꢛ嶐혃븑쪭➹⊔侒旯⪽䝉?貱溴킬⢹沾⿗꧜瞗㊡ᡯӜꕘጰ?䜣욶ᛝￌꑩ?꼂¾綬먀ꂾ鷼㮒ċ嶅⋐犍讣䇿̅?꼓ꄹ臢綳鵙纣⧍㑽쫟仿菐翯白ළ康䀠늠꣭鏬收䥿땞춉ꫀ啲轢뮜掞恱?䟚㭦茟䅄ㆰᱯ틕䇯ꐝ⏇Ꝛ⭨ퟣ腎䊸㣊匂늾꯲꿿ꆞ䵁덍괜࿃᰸욽據ᕫ丒ೇ앃ഽ퀎撴땕㪤鯶췌憫셦瀢둳쀺冉טﮃ꟞짎伻쒛̬㨀?㈾≹槒ᑋퟵ۱郂餆成ꩡﮉ?딤喊쌥踡┰㶵늴?멙氛᭽⓵鵅抺?㼜닍癟⊿䤩똝픺샍Ợꟴ锅ඦ᜞褳㈣?ぎ譢⤵⺊쐾オ郐ꭶ慣穥俼靑望댮婸ꆻ䵑譊须?剉냚떏꿡啍⽍苭ை둘Ꞗ晀䦣㢚䰩卾岺㐟媡짔㫃嚄鈹櫈楋⡒鏖ꔐ嬯饨赾段㗏∖ꑎ牒、?䩰얌䉱â䎭茎䅝Ď隽⡶絅✞殾ﹿ♂쉳㩳鼖嬘쉵뮌饄ꇡꞜ믚깰ᔼ?緱蜢巺?ر몒帨䄛ἥ莃䀉럌㱲낸ﯣ竇וּޮ쭾덑뺤ᑭ푐풄흇𳏗嵗⾨㻠鐜ῴʒ⭏깂箲矫⶷❃秤᛺阮귁?煩׆냵ᖹ嗨獀䋀ᴠ糶褂娖⊤慹㬮贯쭾돬纵׽䭷ᙤ秣䑫烾귤涵쌴镠ਫ਼脕⻔ﳵꤘ?ᶹ뇤⼈㋢Ὼ滙햺嘏䂄'
/*    */     //   195: invokevirtual toCharArray : ()[C
/*    */     //   198: dup
/*    */     //   199: dup
/*    */     //   200: bipush #30
/*    */     //   202: dup_x1
/*    */     //   203: caload
/*    */     //   204: sipush #10896
/*    */     //   207: ixor
/*    */     //   208: i2c
/*    */     //   209: castore
/*    */     //   210: sipush #972
/*    */     //   213: iconst_1
/*    */     //   214: iconst_0
/*    */     //   215: invokestatic U : (Ljava/lang/Object;SZZ)Ljava/lang/String;
/*    */     //   218: dup
/*    */     //   219: astore #4
/*    */     //   221: invokevirtual length : ()I
/*    */     //   224: istore #6
/*    */     //   226: bipush #24
/*    */     //   228: istore_3
/*    */     //   229: iconst_m1
/*    */     //   230: istore_2
/*    */     //   231: iinc #2, 1
/*    */     //   234: aload #4
/*    */     //   236: iload_2
/*    */     //   237: dup
/*    */     //   238: iload_3
/*    */     //   239: iadd
/*    */     //   240: invokevirtual substring : (II)Ljava/lang/String;
/*    */     //   243: iconst_m1
/*    */     //   244: goto -> 377
/*    */     //   247: aload #7
/*    */     //   249: swap
/*    */     //   250: iload #5
/*    */     //   252: iinc #5, 1
/*    */     //   255: swap
/*    */     //   256: aastore
/*    */     //   257: iload_2
/*    */     //   258: iload_3
/*    */     //   259: iadd
/*    */     //   260: dup
/*    */     //   261: istore_2
/*    */     //   262: iload #6
/*    */     //   264: if_icmpge -> 277
/*    */     //   267: aload #4
/*    */     //   269: iload_2
/*    */     //   270: invokevirtual charAt : (I)C
/*    */     //   273: istore_3
/*    */     //   274: goto -> 231
/*    */     //   277: ldc 'ﰤ镠쟠鷼┪꯭㈍㇫ጺ쏄份竻ꋧ欈륍䉋Ꮔ㬐ꀀ䇪땹ꗮ憇㧬才ᕨ掐窧岫垡ᱧᄗ飕ꌋ䈗'
/*    */     //   279: invokevirtual toCharArray : ()[C
/*    */     //   282: dup
/*    */     //   283: dup
/*    */     //   284: bipush #20
/*    */     //   286: dup_x1
/*    */     //   287: caload
/*    */     //   288: sipush #11527
/*    */     //   291: ixor
/*    */     //   292: i2c
/*    */     //   293: castore
/*    */     //   294: sipush #22707
/*    */     //   297: iconst_1
/*    */     //   298: iconst_0
/*    */     //   299: invokestatic U : (Ljava/lang/Object;SZZ)Ljava/lang/String;
/*    */     //   302: dup
/*    */     //   303: astore #4
/*    */     //   305: invokevirtual length : ()I
/*    */     //   308: istore #6
/*    */     //   310: bipush #16
/*    */     //   312: istore_3
/*    */     //   313: iconst_m1
/*    */     //   314: istore_2
/*    */     //   315: iinc #2, 1
/*    */     //   318: aload #4
/*    */     //   320: iload_2
/*    */     //   321: dup
/*    */     //   322: iload_3
/*    */     //   323: iadd
/*    */     //   324: invokevirtual substring : (II)Ljava/lang/String;
/*    */     //   327: iconst_0
/*    */     //   328: goto -> 377
/*    */     //   331: aload #7
/*    */     //   333: swap
/*    */     //   334: iload #5
/*    */     //   336: iinc #5, 1
/*    */     //   339: swap
/*    */     //   340: aastore
/*    */     //   341: iload_2
/*    */     //   342: iload_3
/*    */     //   343: iadd
/*    */     //   344: dup
/*    */     //   345: istore_2
/*    */     //   346: iload #6
/*    */     //   348: if_icmpge -> 361
/*    */     //   351: aload #4
/*    */     //   353: iload_2
/*    */     //   354: invokevirtual charAt : (I)C
/*    */     //   357: istore_3
/*    */     //   358: goto -> 315
/*    */     //   361: aload #7
/*    */     //   363: putstatic me/konsolas/aac/cx.y : [Ljava/lang/String;
/*    */     //   366: bipush #27
/*    */     //   368: anewarray java/lang/String
/*    */     //   371: putstatic me/konsolas/aac/cx.z : [Ljava/lang/String;
/*    */     //   374: goto -> 440
/*    */     //   377: swap
/*    */     //   378: ldc '펦咎⑟㙱᧣垹㥪㭅¶'
/*    */     //   380: invokevirtual toCharArray : ()[C
/*    */     //   383: dup
/*    */     //   384: dup
/*    */     //   385: iconst_1
/*    */     //   386: dup_x1
/*    */     //   387: caload
/*    */     //   388: sipush #4661
/*    */     //   391: ixor
/*    */     //   392: i2c
/*    */     //   393: castore
/*    */     //   394: sipush #9254
/*    */     //   397: iconst_0
/*    */     //   398: iconst_0
/*    */     //   399: invokestatic U : (Ljava/lang/Object;SZZ)Ljava/lang/String;
/*    */     //   402: invokevirtual getBytes : (Ljava/lang/String;)[B
/*    */     //   405: aload_0
/*    */     //   406: swap
/*    */     //   407: invokevirtual doFinal : ([B)[B
/*    */     //   410: astore #8
/*    */     //   412: aload #8
/*    */     //   414: invokestatic a : ([B)Ljava/lang/String;
/*    */     //   417: invokevirtual intern : ()Ljava/lang/String;
/*    */     //   420: swap
/*    */     //   421: tableswitch default -> 247, 0 -> 331
/*    */     //   440: sipush #19698
/*    */     //   443: ldc2_w 4556739141319061980
/*    */     //   446: lload #9
/*    */     //   448: lxor
/*    */     //   449: <illegal opcode> r : (IJ)Ljava/lang/String;
/*    */     //   454: lload #11
/*    */     //   456: invokestatic a : (Ljava/lang/String;J)Lme/konsolas/aac/gZ;
/*    */     //   459: putstatic me/konsolas/aac/cx.c : Lme/konsolas/aac/gZ;
/*    */     //   462: bipush #10
/*    */     //   464: anewarray java/lang/String
/*    */     //   467: dup
/*    */     //   468: iconst_0
/*    */     //   469: sipush #32362
/*    */     //   472: ldc2_w 5315507429190812509
/*    */     //   475: lload #9
/*    */     //   477: lxor
/*    */     //   478: <illegal opcode> r : (IJ)Ljava/lang/String;
/*    */     //   483: aastore
/*    */     //   484: dup
/*    */     //   485: iconst_1
/*    */     //   486: sipush #32646
/*    */     //   489: ldc2_w 6228197809384637118
/*    */     //   492: lload #9
/*    */     //   494: lxor
/*    */     //   495: <illegal opcode> r : (IJ)Ljava/lang/String;
/*    */     //   500: aastore
/*    */     //   501: dup
/*    */     //   502: iconst_2
/*    */     //   503: sipush #13384
/*    */     //   506: ldc2_w 7226072478385768815
/*    */     //   509: lload #9
/*    */     //   511: lxor
/*    */     //   512: <illegal opcode> r : (IJ)Ljava/lang/String;
/*    */     //   517: aastore
/*    */     //   518: dup
/*    */     //   519: iconst_3
/*    */     //   520: sipush #26526
/*    */     //   523: ldc2_w 876466148187822754
/*    */     //   526: lload #9
/*    */     //   528: lxor
/*    */     //   529: <illegal opcode> r : (IJ)Ljava/lang/String;
/*    */     //   534: aastore
/*    */     //   535: dup
/*    */     //   536: iconst_4
/*    */     //   537: sipush #28546
/*    */     //   540: ldc2_w 8098779079576736435
/*    */     //   543: lload #9
/*    */     //   545: lxor
/*    */     //   546: <illegal opcode> r : (IJ)Ljava/lang/String;
/*    */     //   551: aastore
/*    */     //   552: dup
/*    */     //   553: iconst_5
/*    */     //   554: sipush #4500
/*    */     //   557: ldc2_w 7143799498701974690
/*    */     //   560: lload #9
/*    */     //   562: lxor
/*    */     //   563: <illegal opcode> r : (IJ)Ljava/lang/String;
/*    */     //   568: aastore
/*    */     //   569: dup
/*    */     //   570: bipush #6
/*    */     //   572: sipush #18750
/*    */     //   575: ldc2_w 4627115507740800017
/*    */     //   578: lload #9
/*    */     //   580: lxor
/*    */     //   581: <illegal opcode> r : (IJ)Ljava/lang/String;
/*    */     //   586: aastore
/*    */     //   587: dup
/*    */     //   588: bipush #7
/*    */     //   590: sipush #21396
/*    */     //   593: ldc2_w 3655008516829146798
/*    */     //   596: lload #9
/*    */     //   598: lxor
/*    */     //   599: <illegal opcode> r : (IJ)Ljava/lang/String;
/*    */     //   604: aastore
/*    */     //   605: dup
/*    */     //   606: bipush #8
/*    */     //   608: sipush #7038
/*    */     //   611: ldc2_w 6580754162867119707
/*    */     //   614: lload #9
/*    */     //   616: lxor
/*    */     //   617: <illegal opcode> r : (IJ)Ljava/lang/String;
/*    */     //   622: aastore
/*    */     //   623: dup
/*    */     //   624: bipush #9
/*    */     //   626: sipush #31985
/*    */     //   629: ldc2_w 2824844882151981525
/*    */     //   632: lload #9
/*    */     //   634: lxor
/*    */     //   635: <illegal opcode> r : (IJ)Ljava/lang/String;
/*    */     //   640: aastore
/*    */     //   641: putstatic me/konsolas/aac/cx.l : [Ljava/lang/String;
/*    */     //   644: bipush #64
/*    */     //   646: anewarray java/lang/String
/*    */     //   649: putstatic me/konsolas/aac/cx.e : [Ljava/lang/String;
/*    */     //   652: sipush #256
/*    */     //   655: anewarray java/lang/String
/*    */     //   658: putstatic me/konsolas/aac/cx.h : [Ljava/lang/String;
/*    */     //   661: iconst_0
/*    */     //   662: istore #13
/*    */     //   664: iload #13
/*    */     //   666: getstatic me/konsolas/aac/cx.h : [Ljava/lang/String;
/*    */     //   669: arraylength
/*    */     //   670: if_icmpge -> 732
/*    */     //   673: getstatic me/konsolas/aac/cx.h : [Ljava/lang/String;
/*    */     //   676: iload #13
/*    */     //   678: sipush #4646
/*    */     //   681: ldc2_w 3890243766967512832
/*    */     //   684: lload #9
/*    */     //   686: lxor
/*    */     //   687: <illegal opcode> r : (IJ)Ljava/lang/String;
/*    */     //   692: iconst_1
/*    */     //   693: anewarray java/lang/Object
/*    */     //   696: dup
/*    */     //   697: iconst_0
/*    */     //   698: iload #13
/*    */     //   700: invokestatic toBinaryString : (I)Ljava/lang/String;
/*    */     //   703: aastore
/*    */     //   704: invokestatic a : (Ljava/lang/String;[Ljava/lang/Object;)Ljava/lang/String;
/*    */     //   707: bipush #32
/*    */     //   709: bipush #48
/*    */     //   711: invokevirtual replace : (CC)Ljava/lang/String;
/*    */     //   714: aastore
/*    */     //   715: iinc #13, 1
/*    */     //   718: goto -> 664
/*    */     //   721: ldc2_w -7740387630838582435
/*    */     //   724: lload #9
/*    */     //   726: <illegal opcode> w : (Ljava/lang/IllegalArgumentException;JJ)Ljava/lang/IllegalArgumentException;
/*    */     //   731: athrow
/*    */     //   732: getstatic me/konsolas/aac/cx.e : [Ljava/lang/String;
/*    */     //   735: iconst_0
/*    */     //   736: ldc ''
/*    */     //   738: aastore
/*    */     //   739: getstatic me/konsolas/aac/cx.e : [Ljava/lang/String;
/*    */     //   742: iconst_1
/*    */     //   743: sipush #20863
/*    */     //   746: ldc2_w 3726951088959548484
/*    */     //   749: lload #9
/*    */     //   751: lxor
/*    */     //   752: <illegal opcode> r : (IJ)Ljava/lang/String;
/*    */     //   757: aastore
/*    */     //   758: iconst_1
/*    */     //   759: newarray int
/*    */     //   761: dup
/*    */     //   762: iconst_0
/*    */     //   763: iconst_1
/*    */     //   764: iastore
/*    */     //   765: astore #13
/*    */     //   767: getstatic me/konsolas/aac/cx.e : [Ljava/lang/String;
/*    */     //   770: bipush #8
/*    */     //   772: sipush #4347
/*    */     //   775: ldc2_w 8085060059801890246
/*    */     //   778: lload #9
/*    */     //   780: lxor
/*    */     //   781: <illegal opcode> r : (IJ)Ljava/lang/String;
/*    */     //   786: aastore
/*    */     //   787: aload #13
/*    */     //   789: astore #14
/*    */     //   791: aload #14
/*    */     //   793: arraylength
/*    */     //   794: istore #15
/*    */     //   796: iconst_0
/*    */     //   797: istore #16
/*    */     //   799: iload #16
/*    */     //   801: iload #15
/*    */     //   803: if_icmpge -> 864
/*    */     //   806: aload #14
/*    */     //   808: iload #16
/*    */     //   810: iaload
/*    */     //   811: istore #17
/*    */     //   813: getstatic me/konsolas/aac/cx.e : [Ljava/lang/String;
/*    */     //   816: iload #17
/*    */     //   818: bipush #8
/*    */     //   820: ior
/*    */     //   821: new java/lang/StringBuilder
/*    */     //   824: dup
/*    */     //   825: invokespecial <init> : ()V
/*    */     //   828: getstatic me/konsolas/aac/cx.e : [Ljava/lang/String;
/*    */     //   831: iload #17
/*    */     //   833: aaload
/*    */     //   834: invokevirtual append : (Ljava/lang/String;)Ljava/lang/StringBuilder;
/*    */     //   837: sipush #32386
/*    */     //   840: ldc2_w 5891746894948615094
/*    */     //   843: lload #9
/*    */     //   845: lxor
/*    */     //   846: <illegal opcode> r : (IJ)Ljava/lang/String;
/*    */     //   851: invokevirtual append : (Ljava/lang/String;)Ljava/lang/StringBuilder;
/*    */     //   854: invokevirtual toString : ()Ljava/lang/String;
/*    */     //   857: aastore
/*    */     //   858: iinc #16, 1
/*    */     //   861: goto -> 799
/*    */     //   864: getstatic me/konsolas/aac/cx.e : [Ljava/lang/String;
/*    */     //   867: iconst_4
/*    */     //   868: sipush #2441
/*    */     //   871: ldc2_w 3789318854872282277
/*    */     //   874: lload #9
/*    */     //   876: lxor
/*    */     //   877: <illegal opcode> r : (IJ)Ljava/lang/String;
/*    */     //   882: aastore
/*    */     //   883: getstatic me/konsolas/aac/cx.e : [Ljava/lang/String;
/*    */     //   886: bipush #32
/*    */     //   888: sipush #13384
/*    */     //   891: ldc2_w 7226072478385768815
/*    */     //   894: lload #9
/*    */     //   896: lxor
/*    */     //   897: <illegal opcode> r : (IJ)Ljava/lang/String;
/*    */     //   902: aastore
/*    */     //   903: getstatic me/konsolas/aac/cx.e : [Ljava/lang/String;
/*    */     //   906: bipush #36
/*    */     //   908: sipush #16923
/*    */     //   911: ldc2_w 3399127881287073577
/*    */     //   914: lload #9
/*    */     //   916: lxor
/*    */     //   917: <illegal opcode> r : (IJ)Ljava/lang/String;
/*    */     //   922: aastore
/*    */     //   923: iconst_3
/*    */     //   924: newarray int
/*    */     //   926: dup
/*    */     //   927: iconst_0
/*    */     //   928: iconst_4
/*    */     //   929: iastore
/*    */     //   930: dup
/*    */     //   931: iconst_1
/*    */     //   932: bipush #32
/*    */     //   934: iastore
/*    */     //   935: dup
/*    */     //   936: iconst_2
/*    */     //   937: bipush #36
/*    */     //   939: iastore
/*    */     //   940: astore #14
/*    */     //   942: aload #14
/*    */     //   944: astore #15
/*    */     //   946: aload #15
/*    */     //   948: arraylength
/*    */     //   949: istore #16
/*    */     //   951: iconst_0
/*    */     //   952: istore #17
/*    */     //   954: iload #17
/*    */     //   956: iload #16
/*    */     //   958: if_icmpge -> 1110
/*    */     //   961: aload #15
/*    */     //   963: iload #17
/*    */     //   965: iaload
/*    */     //   966: istore #18
/*    */     //   968: aload #13
/*    */     //   970: astore #19
/*    */     //   972: aload #19
/*    */     //   974: arraylength
/*    */     //   975: istore #20
/*    */     //   977: iconst_0
/*    */     //   978: istore #21
/*    */     //   980: iload #21
/*    */     //   982: iload #20
/*    */     //   984: if_icmpge -> 1104
/*    */     //   987: aload #19
/*    */     //   989: iload #21
/*    */     //   991: iaload
/*    */     //   992: istore #22
/*    */     //   994: getstatic me/konsolas/aac/cx.e : [Ljava/lang/String;
/*    */     //   997: iload #22
/*    */     //   999: iload #18
/*    */     //   1001: ior
/*    */     //   1002: new java/lang/StringBuilder
/*    */     //   1005: dup
/*    */     //   1006: invokespecial <init> : ()V
/*    */     //   1009: getstatic me/konsolas/aac/cx.e : [Ljava/lang/String;
/*    */     //   1012: iload #22
/*    */     //   1014: aaload
/*    */     //   1015: invokevirtual append : (Ljava/lang/String;)Ljava/lang/StringBuilder;
/*    */     //   1018: bipush #124
/*    */     //   1020: invokevirtual append : (C)Ljava/lang/StringBuilder;
/*    */     //   1023: getstatic me/konsolas/aac/cx.e : [Ljava/lang/String;
/*    */     //   1026: iload #18
/*    */     //   1028: aaload
/*    */     //   1029: invokevirtual append : (Ljava/lang/String;)Ljava/lang/StringBuilder;
/*    */     //   1032: invokevirtual toString : ()Ljava/lang/String;
/*    */     //   1035: aastore
/*    */     //   1036: getstatic me/konsolas/aac/cx.e : [Ljava/lang/String;
/*    */     //   1039: iload #22
/*    */     //   1041: iload #18
/*    */     //   1043: ior
/*    */     //   1044: bipush #8
/*    */     //   1046: ior
/*    */     //   1047: new java/lang/StringBuilder
/*    */     //   1050: dup
/*    */     //   1051: invokespecial <init> : ()V
/*    */     //   1054: getstatic me/konsolas/aac/cx.e : [Ljava/lang/String;
/*    */     //   1057: iload #22
/*    */     //   1059: aaload
/*    */     //   1060: invokevirtual append : (Ljava/lang/String;)Ljava/lang/StringBuilder;
/*    */     //   1063: bipush #124
/*    */     //   1065: invokevirtual append : (C)Ljava/lang/StringBuilder;
/*    */     //   1068: getstatic me/konsolas/aac/cx.e : [Ljava/lang/String;
/*    */     //   1071: iload #18
/*    */     //   1073: aaload
/*    */     //   1074: invokevirtual append : (Ljava/lang/String;)Ljava/lang/StringBuilder;
/*    */     //   1077: sipush #12925
/*    */     //   1080: ldc2_w 8794302959946174285
/*    */     //   1083: lload #9
/*    */     //   1085: lxor
/*    */     //   1086: <illegal opcode> r : (IJ)Ljava/lang/String;
/*    */     //   1091: invokevirtual append : (Ljava/lang/String;)Ljava/lang/StringBuilder;
/*    */     //   1094: invokevirtual toString : ()Ljava/lang/String;
/*    */     //   1097: aastore
/*    */     //   1098: iinc #21, 1
/*    */     //   1101: goto -> 980
/*    */     //   1104: iinc #17, 1
/*    */     //   1107: goto -> 954
/*    */     //   1110: iconst_0
/*    */     //   1111: istore #15
/*    */     //   1113: iload #15
/*    */     //   1115: getstatic me/konsolas/aac/cx.e : [Ljava/lang/String;
/*    */     //   1118: arraylength
/*    */     //   1119: if_icmpge -> 1177
/*    */     //   1122: getstatic me/konsolas/aac/cx.e : [Ljava/lang/String;
/*    */     //   1125: iload #15
/*    */     //   1127: aaload
/*    */     //   1128: ifnonnull -> 1171
/*    */     //   1131: goto -> 1145
/*    */     //   1134: ldc2_w -7740387630838582435
/*    */     //   1137: lload #9
/*    */     //   1139: <illegal opcode> w : (Ljava/lang/IllegalArgumentException;JJ)Ljava/lang/IllegalArgumentException;
/*    */     //   1144: athrow
/*    */     //   1145: getstatic me/konsolas/aac/cx.e : [Ljava/lang/String;
/*    */     //   1148: iload #15
/*    */     //   1150: getstatic me/konsolas/aac/cx.h : [Ljava/lang/String;
/*    */     //   1153: iload #15
/*    */     //   1155: aaload
/*    */     //   1156: aastore
/*    */     //   1157: goto -> 1171
/*    */     //   1160: ldc2_w -7740387630838582435
/*    */     //   1163: lload #9
/*    */     //   1165: <illegal opcode> w : (Ljava/lang/IllegalArgumentException;JJ)Ljava/lang/IllegalArgumentException;
/*    */     //   1170: athrow
/*    */     //   1171: iinc #15, 1
/*    */     //   1174: goto -> 1113
/*    */     //   1177: return
/*    */     // Line number table:
/*    */     //   Java source line number -> byte code offset
/*    */     //   #41	-> 440
/*    */     //   #10	-> 454
/*    */     //   #1	-> 462
/*    */     //   #27	-> 644
/*    */     //   #5	-> 652
/*    */     //   #8	-> 661
/*    */     //   #19	-> 673
/*    */     //   #13	-> 715
/*    */     //   #24	-> 732
/*    */     //   #34	-> 739
/*    */     //   #6	-> 758
/*    */     //   #26	-> 767
/*    */     //   #22	-> 787
/*    */     //   #20	-> 813
/*    */     //   #15	-> 858
/*    */     //   #23	-> 864
/*    */     //   #30	-> 883
/*    */     //   #29	-> 903
/*    */     //   #28	-> 923
/*    */     //   #4	-> 942
/*    */     //   #12	-> 968
/*    */     //   #9	-> 994
/*    */     //   #42	-> 1036
/*    */     //   #3	-> 1098
/*    */     //   #36	-> 1104
/*    */     //   #11	-> 1110
/*    */     //   #17	-> 1122
/*    */     //   #35	-> 1171
/*    */     //   #21	-> 1177
/*    */     // Exception table:
/*    */     //   from	to	target	type
/*    */     //   664	721	721	java/lang/IllegalArgumentException
/*    */     //   1113	1131	1134	java/lang/IllegalArgumentException
/*    */     //   1122	1157	1160	java/lang/IllegalArgumentException
/*    */   }
/*    */   
/*    */   private static IllegalArgumentException a(IllegalArgumentException paramIllegalArgumentException) {
/*    */     return paramIllegalArgumentException;
/*    */   }
/*    */   
/*    */   private static String a(byte[] paramArrayOfbyte) {
/*    */     byte b1 = 0;
/*    */     int i;
/*    */     char[] arrayOfChar = new char[i = paramArrayOfbyte.length];
/*    */     for (byte b2 = 0; b2 < i; b2++) {
/*    */       int j;
/*    */       if ((j = 0xFF & paramArrayOfbyte[b2]) < 192) {
/*    */         arrayOfChar[b1++] = (char)j;
/*    */       } else if (j < 224) {
/*    */         char c = (char)((char)(j & 0x1F) << 6);
/*    */         j = paramArrayOfbyte[++b2];
/*    */         c = (char)(c | (char)(j & 0x3F));
/*    */         arrayOfChar[b1++] = c;
/*    */       } else if (b2 < i - 2) {
/*    */         char c = (char)((char)(j & 0xF) << 12);
/*    */         j = paramArrayOfbyte[++b2];
/*    */         c = (char)(c | (char)(j & 0x3F) << 6);
/*    */         j = paramArrayOfbyte[++b2];
/*    */         c = (char)(c | (char)(j & 0x3F));
/*    */         arrayOfChar[b1++] = c;
/*    */       } 
/*    */     } 
/*    */     return new String(arrayOfChar, 0, b1);
/*    */   }
/*    */   
/*    */   private static String a(int paramInt, long paramLong) {
/*    */     int i = paramInt ^ (int)(paramLong & 0x7FFFL) ^ 0x2916;
/*    */     if (z[i] == null) {
/*    */       Object[] arrayOfObject;
/*    */       try {
/*    */         Long long_ = Long.valueOf(Thread.currentThread().getId());
/*    */         arrayOfObject = (Object[])A.get(long_);
/*    */         if (arrayOfObject == null) {
/*    */           arrayOfObject = new Object[3];
/*    */           "빧톗묙締犸抁?爣婘揄臘䅍뷹逳ꊭ쁢췟潧쑴呦⸎".toCharArray()[4] = (char)("빧톗묙締犸抁?爣婘揄臘䅍뷹逳ꊭ쁢췟潧쑴呦⸎".toCharArray()[4] ^ 0x4BFC);
/*    */           arrayOfObject[0] = Cipher.getInstance(hY$g6.H("빧톗묙締犸抁?爣婘揄臘䅍뷹逳ꊭ쁢췟潧쑴呦⸎".toCharArray(), (short)13501, (byte)2, (byte)1));
/*    */           "䞘੆否".toCharArray()[1] = (char)("䞘੆否".toCharArray()[1] ^ 0x2B0);
/*    */           arrayOfObject[1] = SecretKeyFactory.getInstance(hY$g6.H("䞘੆否".toCharArray(), (short)18163, (byte)5, (byte)4));
/*    */           arrayOfObject[2] = new IvParameterSpec(new byte[8]);
/*    */           A.put(long_, arrayOfObject);
/*    */         } 
/*    */       } catch (Exception exception) {
/*    */         "谼鷋➇씵꒫⭫㈂֓붂꤆ݒ騥ശ卝ꐮ뙫怘俑".toCharArray()[15] = (char)("谼鷋➇씵꒫⭫㈂֓붂꤆ݒ騥ശ卝ꐮ뙫怘俑".toCharArray()[15] ^ 0x7D58);
/*    */         throw new RuntimeException(hY$g6.H("谼鷋➇씵꒫⭫㈂֓붂꤆ݒ騥ശ卝ꐮ뙫怘俑".toCharArray(), (short)18750, (byte)4, (byte)2), exception);
/*    */       } 
/*    */       byte[] arrayOfByte1 = new byte[8];
/*    */       arrayOfByte1[0] = (byte)(int)(paramLong >>> 56L);
/*    */       for (byte b = 1; b < 8; b++)
/*    */         arrayOfByte1[b] = (byte)(int)(paramLong << b * 8 >>> 56L); 
/*    */       DESKeySpec dESKeySpec = new DESKeySpec(arrayOfByte1);
/*    */       SecretKey secretKey = ((SecretKeyFactory)arrayOfObject[1]).generateSecret(dESKeySpec);
/*    */       ((Cipher)arrayOfObject[0]).init(2, secretKey, (IvParameterSpec)arrayOfObject[2]);
/*    */       "颳殣쁦ৱ᥋倹녒쾏뻔涡ὤ".toCharArray()[3] = (char)("颳殣쁦ৱ᥋倹녒쾏뻔涡ὤ".toCharArray()[3] ^ 0x7B45);
/*    */       byte[] arrayOfByte2 = y[i].getBytes(hY$g6.H("颳殣쁦ৱ᥋倹녒쾏뻔涡ὤ".toCharArray(), (short)31222, (byte)0, (byte)2));
/*    */       z[i] = a(((Cipher)arrayOfObject[0]).doFinal(arrayOfByte2));
/*    */     } 
/*    */     return z[i];
/*    */   }
/*    */   
/*    */   private static Object a(MethodHandles.Lookup paramLookup, MutableCallSite paramMutableCallSite, String paramString, Object[] paramArrayOfObject) {
/*    */     int i = ((Integer)paramArrayOfObject[0]).intValue();
/*    */     long l = ((Long)paramArrayOfObject[1]).longValue();
/*    */     String str = a(i, l);
/*    */     MethodHandle methodHandle = MethodHandles.constant(String.class, str);
/*    */     paramMutableCallSite.setTarget(MethodHandles.dropArguments(methodHandle, 0, new Class[] { int.class, long.class }));
/*    */     return str;
/*    */   }
/*    */   
/*    */   private static CallSite a(MethodHandles.Lookup paramLookup, String paramString, MethodType paramMethodType) {
/*    */     // Byte code:
/*    */     //   0: new java/lang/invoke/MutableCallSite
/*    */     //   3: dup
/*    */     //   4: aload_2
/*    */     //   5: invokespecial <init> : (Ljava/lang/invoke/MethodType;)V
/*    */     //   8: astore_3
/*    */     //   9: aload_3
/*    */     //   10: ldc_w
/*    */     //   13: ldc [Ljava/lang/Object;
/*    */     //   15: aload_2
/*    */     //   16: invokevirtual parameterCount : ()I
/*    */     //   19: invokevirtual asCollector : (Ljava/lang/Class;I)Ljava/lang/invoke/MethodHandle;
/*    */     //   22: iconst_0
/*    */     //   23: iconst_3
/*    */     //   24: anewarray java/lang/Object
/*    */     //   27: dup
/*    */     //   28: iconst_0
/*    */     //   29: aload_0
/*    */     //   30: aastore
/*    */     //   31: dup
/*    */     //   32: iconst_1
/*    */     //   33: aload_3
/*    */     //   34: aastore
/*    */     //   35: dup
/*    */     //   36: iconst_2
/*    */     //   37: aload_1
/*    */     //   38: aastore
/*    */     //   39: invokestatic insertArguments : (Ljava/lang/invoke/MethodHandle;I[Ljava/lang/Object;)Ljava/lang/invoke/MethodHandle;
/*    */     //   42: aload_2
/*    */     //   43: invokestatic explicitCastArguments : (Ljava/lang/invoke/MethodHandle;Ljava/lang/invoke/MethodType;)Ljava/lang/invoke/MethodHandle;
/*    */     //   46: invokevirtual setTarget : (Ljava/lang/invoke/MethodHandle;)V
/*    */     //   49: goto -> 169
/*    */     //   52: astore #4
/*    */     //   54: new java/lang/RuntimeException
/*    */     //   57: dup
/*    */     //   58: new java/lang/StringBuilder
/*    */     //   61: dup
/*    */     //   62: invokespecial <init> : ()V
/*    */     //   65: ldc_w '嶍뷉줃蚃ﴭᤃ愼㫓苝꼊쫽Ŧ浴?彝㔱鴾晢'
/*    */     //   68: invokevirtual toCharArray : ()[C
/*    */     //   71: dup
/*    */     //   72: dup
/*    */     //   73: iconst_1
/*    */     //   74: dup_x1
/*    */     //   75: caload
/*    */     //   76: sipush #18426
/*    */     //   79: ixor
/*    */     //   80: i2c
/*    */     //   81: castore
/*    */     //   82: sipush #10947
/*    */     //   85: iconst_4
/*    */     //   86: iconst_4
/*    */     //   87: invokestatic H : (Ljava/lang/Object;SBB)Ljava/lang/String;
/*    */     //   90: invokevirtual append : (Ljava/lang/String;)Ljava/lang/StringBuilder;
/*    */     //   93: ldc_w '㽃✏㲸༽'
/*    */     //   96: invokevirtual toCharArray : ()[C
/*    */     //   99: dup
/*    */     //   100: dup
/*    */     //   101: iconst_1
/*    */     //   102: dup_x1
/*    */     //   103: caload
/*    */     //   104: sipush #25149
/*    */     //   107: ixor
/*    */     //   108: i2c
/*    */     //   109: castore
/*    */     //   110: sipush #2030
/*    */     //   113: iconst_3
/*    */     //   114: iconst_5
/*    */     //   115: invokestatic H : (Ljava/lang/Object;SBB)Ljava/lang/String;
/*    */     //   118: invokevirtual append : (Ljava/lang/String;)Ljava/lang/StringBuilder;
/*    */     //   121: aload_1
/*    */     //   122: invokevirtual append : (Ljava/lang/String;)Ljava/lang/StringBuilder;
/*    */     //   125: ldc_w '膈ᰔ᎓砭'
/*    */     //   128: invokevirtual toCharArray : ()[C
/*    */     //   131: dup
/*    */     //   132: dup
/*    */     //   133: iconst_1
/*    */     //   134: dup_x1
/*    */     //   135: caload
/*    */     //   136: sipush #5581
/*    */     //   139: ixor
/*    */     //   140: i2c
/*    */     //   141: castore
/*    */     //   142: sipush #22344
/*    */     //   145: iconst_0
/*    */     //   146: iconst_4
/*    */     //   147: invokestatic H : (Ljava/lang/Object;SBB)Ljava/lang/String;
/*    */     //   150: invokevirtual append : (Ljava/lang/String;)Ljava/lang/StringBuilder;
/*    */     //   153: aload_2
/*    */     //   154: invokevirtual toString : ()Ljava/lang/String;
/*    */     //   157: invokevirtual append : (Ljava/lang/String;)Ljava/lang/StringBuilder;
/*    */     //   160: invokevirtual toString : ()Ljava/lang/String;
/*    */     //   163: aload #4
/*    */     //   165: invokespecial <init> : (Ljava/lang/String;Ljava/lang/Throwable;)V
/*    */     //   168: athrow
/*    */     //   169: aload_3
/*    */     //   170: areturn
/*    */     // Exception table:
/*    */     //   from	to	target	type
/*    */     //   9	49	52	java/lang/Exception
/*    */   }
/*    */ }


/* Location:              C:\Users\BukkitBypass\Desktop\MatrixAC\AAC\AAC-spigot-5.2.0.jar!\me\konsolas\aac\cx.class
 * Java compiler version: 8 (52.0)
 * JD-Core Version:       1.1.3
 */