/*    */ package me.konsolas.aac;
/*    */ public final class d0 {
/*    */   private final String b;
/*    */   private final Map a;
/*    */   private static final long c = nc.a(-7107035843571368558L, -4696446398503948748L, MethodHandles.lookup().lookupClass()).a(255536599129970L);
/*    */   
/*    */   public Map a() {
/*  8 */     return this.a;
/*    */   } private static final String[] d; private static final String[] e; private static final Map f = new HashMap<>(13); public boolean equals(@Nullable Object paramObject) {
/*    */     // Byte code:
/*    */     //   0: getstatic me/konsolas/aac/d0.c : J
/*    */     //   3: ldc2_w 136080789413694
/*    */     //   6: lxor
/*    */     //   7: lstore_2
/*    */     //   8: ldc2_w -4454062261333081363
/*    */     //   11: lload_2
/*    */     //   12: <illegal opcode> w : (JJ)[Lme/konsolas/aac/aN;
/*    */     //   17: astore #4
/*    */     //   19: aload_1
/*    */     //   20: instanceof me/konsolas/aac/d0
/*    */     //   23: aload #4
/*    */     //   25: ifnonnull -> 71
/*    */     //   28: ifeq -> 146
/*    */     //   31: goto -> 44
/*    */     //   34: ldc2_w -4454215017261535429
/*    */     //   37: lload_2
/*    */     //   38: <illegal opcode> w : (Ljava/lang/Exception;JJ)Ljava/lang/Exception;
/*    */     //   43: athrow
/*    */     //   44: aload_1
/*    */     //   45: checkcast me/konsolas/aac/d0
/*    */     //   48: getfield b : Ljava/lang/String;
/*    */     //   51: aload_0
/*    */     //   52: getfield b : Ljava/lang/String;
/*    */     //   55: invokevirtual equals : (Ljava/lang/Object;)Z
/*    */     //   58: goto -> 71
/*    */     //   61: ldc2_w -4454215017261535429
/*    */     //   64: lload_2
/*    */     //   65: <illegal opcode> w : (Ljava/lang/Exception;JJ)Ljava/lang/Exception;
/*    */     //   70: athrow
/*    */     //   71: aload #4
/*    */     //   73: ifnonnull -> 121
/*    */     //   76: ifeq -> 146
/*    */     //   79: goto -> 92
/*    */     //   82: ldc2_w -4454215017261535429
/*    */     //   85: lload_2
/*    */     //   86: <illegal opcode> w : (Ljava/lang/Exception;JJ)Ljava/lang/Exception;
/*    */     //   91: athrow
/*    */     //   92: aload_1
/*    */     //   93: checkcast me/konsolas/aac/d0
/*    */     //   96: getfield a : Ljava/util/Map;
/*    */     //   99: aload_0
/*    */     //   100: getfield a : Ljava/util/Map;
/*    */     //   103: invokeinterface equals : (Ljava/lang/Object;)Z
/*    */     //   108: goto -> 121
/*    */     //   111: ldc2_w -4454215017261535429
/*    */     //   114: lload_2
/*    */     //   115: <illegal opcode> w : (Ljava/lang/Exception;JJ)Ljava/lang/Exception;
/*    */     //   120: athrow
/*    */     //   121: aload #4
/*    */     //   123: ifnonnull -> 143
/*    */     //   126: ifeq -> 146
/*    */     //   129: goto -> 142
/*    */     //   132: ldc2_w -4454215017261535429
/*    */     //   135: lload_2
/*    */     //   136: <illegal opcode> w : (Ljava/lang/Exception;JJ)Ljava/lang/Exception;
/*    */     //   141: athrow
/*    */     //   142: iconst_1
/*    */     //   143: goto -> 147
/*    */     //   146: iconst_0
/*    */     //   147: ireturn
/*    */     // Line number table:
/*    */     //   Java source line number -> byte code offset
/*    */     //   #6	-> 19
/*    */     //   #13	-> 55
/*    */     //   #23	-> 103
/*    */     //   #11	-> 147
/*    */     // Exception table:
/*    */     //   from	to	target	type
/*    */     //   19	31	34	java/lang/NullPointerException
/*    */     //   28	58	61	java/lang/NullPointerException
/*    */     //   71	79	82	java/lang/NullPointerException
/*    */     //   76	108	111	java/lang/NullPointerException
/*    */     //   121	129	132	java/lang/NullPointerException
/*    */   } public String a(long paramLong) {
/*    */     // Byte code:
/*    */     //   0: getstatic me/konsolas/aac/d0.c : J
/*    */     //   3: lload_1
/*    */     //   4: lxor
/*    */     //   5: lstore_1
/*    */     //   6: aload_0
/*    */     //   7: getfield a : Ljava/util/Map;
/*    */     //   10: sipush #4565
/*    */     //   13: ldc2_w 7904201100339471280
/*    */     //   16: lload_1
/*    */     //   17: lxor
/*    */     //   18: <illegal opcode> r : (IJ)Ljava/lang/String;
/*    */     //   23: invokeinterface get : (Ljava/lang/Object;)Ljava/lang/Object;
/*    */     //   28: checkcast java/lang/String
/*    */     //   31: areturn
/*    */     // Line number table:
/*    */     //   Java source line number -> byte code offset
/*    */     //   #9	-> 6
/*    */   }
/*    */   public d0 a(int paramInt, Charset paramCharset, short paramShort, char paramChar) {
/*    */     // Byte code:
/*    */     //   0: iload_1
/*    */     //   1: i2l
/*    */     //   2: bipush #32
/*    */     //   4: lshl
/*    */     //   5: iload_3
/*    */     //   6: i2l
/*    */     //   7: bipush #48
/*    */     //   9: lshl
/*    */     //   10: bipush #32
/*    */     //   12: lushr
/*    */     //   13: lor
/*    */     //   14: iload #4
/*    */     //   16: i2l
/*    */     //   17: bipush #48
/*    */     //   19: lshl
/*    */     //   20: bipush #48
/*    */     //   22: lushr
/*    */     //   23: lor
/*    */     //   24: getstatic me/konsolas/aac/d0.c : J
/*    */     //   27: lxor
/*    */     //   28: lstore #5
/*    */     //   30: lload #5
/*    */     //   32: dup2
/*    */     //   33: ldc2_w 67733766343138
/*    */     //   36: lxor
/*    */     //   37: lstore #7
/*    */     //   39: pop2
/*    */     //   40: aload_2
/*    */     //   41: ifnonnull -> 77
/*    */     //   44: new java/lang/NullPointerException
/*    */     //   47: dup
/*    */     //   48: sipush #2679
/*    */     //   51: ldc2_w 761029128859058526
/*    */     //   54: lload #5
/*    */     //   56: lxor
/*    */     //   57: <illegal opcode> r : (IJ)Ljava/lang/String;
/*    */     //   62: invokespecial <init> : (Ljava/lang/String;)V
/*    */     //   65: athrow
/*    */     //   66: ldc2_w 2843483664079620706
/*    */     //   69: lload #5
/*    */     //   71: <illegal opcode> w : (Ljava/lang/Exception;JJ)Ljava/lang/Exception;
/*    */     //   76: athrow
/*    */     //   77: new java/util/LinkedHashMap
/*    */     //   80: dup
/*    */     //   81: aload_0
/*    */     //   82: getfield a : Ljava/util/Map;
/*    */     //   85: invokespecial <init> : (Ljava/util/Map;)V
/*    */     //   88: astore #9
/*    */     //   90: aload #9
/*    */     //   92: sipush #3222
/*    */     //   95: ldc2_w 6386087254003451832
/*    */     //   98: lload #5
/*    */     //   100: lxor
/*    */     //   101: <illegal opcode> r : (IJ)Ljava/lang/String;
/*    */     //   106: aload_2
/*    */     //   107: invokevirtual name : ()Ljava/lang/String;
/*    */     //   110: invokeinterface put : (Ljava/lang/Object;Ljava/lang/Object;)Ljava/lang/Object;
/*    */     //   115: pop
/*    */     //   116: new me/konsolas/aac/d0
/*    */     //   119: dup
/*    */     //   120: aload_0
/*    */     //   121: getfield b : Ljava/lang/String;
/*    */     //   124: aload #9
/*    */     //   126: lload #7
/*    */     //   128: invokespecial <init> : (Ljava/lang/String;Ljava/util/Map;J)V
/*    */     //   131: areturn
/*    */     // Line number table:
/*    */     //   Java source line number -> byte code offset
/*    */     //   #12	-> 40
/*    */     //   #15	-> 77
/*    */     //   #16	-> 90
/*    */     //   #14	-> 116
/*    */     // Exception table:
/*    */     //   from	to	target	type
/*    */     //   40	66	66	java/lang/NullPointerException
/*    */   }
/*    */   public String toString() {
/*    */     // Byte code:
/*    */     //   0: getstatic me/konsolas/aac/d0.c : J
/*    */     //   3: ldc2_w 42801014236388
/*    */     //   6: lxor
/*    */     //   7: lstore_1
/*    */     //   8: new java/lang/StringBuilder
/*    */     //   11: dup
/*    */     //   12: invokespecial <init> : ()V
/*    */     //   15: aload_0
/*    */     //   16: getfield b : Ljava/lang/String;
/*    */     //   19: invokevirtual append : (Ljava/lang/String;)Ljava/lang/StringBuilder;
/*    */     //   22: sipush #27092
/*    */     //   25: ldc2_w 5871061600585383037
/*    */     //   28: lload_1
/*    */     //   29: lxor
/*    */     //   30: <illegal opcode> r : (IJ)Ljava/lang/String;
/*    */     //   35: invokevirtual append : (Ljava/lang/String;)Ljava/lang/StringBuilder;
/*    */     //   38: aload_0
/*    */     //   39: getfield a : Ljava/util/Map;
/*    */     //   42: invokevirtual append : (Ljava/lang/Object;)Ljava/lang/StringBuilder;
/*    */     //   45: invokevirtual toString : ()Ljava/lang/String;
/*    */     //   48: areturn
/*    */     // Line number table:
/*    */     //   Java source line number -> byte code offset
/*    */     //   #17	-> 8
/*    */   }
/*    */   public d0(char paramChar, String paramString1, int paramInt, short paramShort, String paramString2) {
/*    */     // Byte code:
/*    */     //   0: iload_1
/*    */     //   1: i2l
/*    */     //   2: bipush #48
/*    */     //   4: lshl
/*    */     //   5: iload_3
/*    */     //   6: i2l
/*    */     //   7: bipush #32
/*    */     //   9: lshl
/*    */     //   10: bipush #16
/*    */     //   12: lushr
/*    */     //   13: lor
/*    */     //   14: iload #4
/*    */     //   16: i2l
/*    */     //   17: bipush #48
/*    */     //   19: lshl
/*    */     //   20: bipush #48
/*    */     //   22: lushr
/*    */     //   23: lor
/*    */     //   24: getstatic me/konsolas/aac/d0.c : J
/*    */     //   27: lxor
/*    */     //   28: lstore #6
/*    */     //   30: ldc2_w 8673808075511855261
/*    */     //   33: lload #6
/*    */     //   35: <illegal opcode> w : (JJ)[Lme/konsolas/aac/aN;
/*    */     //   40: aload_0
/*    */     //   41: invokespecial <init> : ()V
/*    */     //   44: astore #8
/*    */     //   46: aload_2
/*    */     //   47: aload #8
/*    */     //   49: ifnonnull -> 104
/*    */     //   52: ifnonnull -> 102
/*    */     //   55: goto -> 69
/*    */     //   58: ldc2_w 8673652023564096843
/*    */     //   61: lload #6
/*    */     //   63: <illegal opcode> w : (Ljava/lang/Exception;JJ)Ljava/lang/Exception;
/*    */     //   68: athrow
/*    */     //   69: new java/lang/NullPointerException
/*    */     //   72: dup
/*    */     //   73: sipush #12271
/*    */     //   76: ldc2_w 3572981354857561070
/*    */     //   79: lload #6
/*    */     //   81: lxor
/*    */     //   82: <illegal opcode> r : (IJ)Ljava/lang/String;
/*    */     //   87: invokespecial <init> : (Ljava/lang/String;)V
/*    */     //   90: athrow
/*    */     //   91: ldc2_w 8673652023564096843
/*    */     //   94: lload #6
/*    */     //   96: <illegal opcode> w : (Ljava/lang/Exception;JJ)Ljava/lang/Exception;
/*    */     //   101: athrow
/*    */     //   102: aload #5
/*    */     //   104: ifnonnull -> 140
/*    */     //   107: new java/lang/NullPointerException
/*    */     //   110: dup
/*    */     //   111: sipush #14059
/*    */     //   114: ldc2_w 2165086045006717673
/*    */     //   117: lload #6
/*    */     //   119: lxor
/*    */     //   120: <illegal opcode> r : (IJ)Ljava/lang/String;
/*    */     //   125: invokespecial <init> : (Ljava/lang/String;)V
/*    */     //   128: athrow
/*    */     //   129: ldc2_w 8673652023564096843
/*    */     //   132: lload #6
/*    */     //   134: <illegal opcode> w : (Ljava/lang/Exception;JJ)Ljava/lang/Exception;
/*    */     //   139: athrow
/*    */     //   140: aload_0
/*    */     //   141: aload_2
/*    */     //   142: putfield b : Ljava/lang/String;
/*    */     //   145: aload_0
/*    */     //   146: sipush #11037
/*    */     //   149: ldc2_w 6621904243994820376
/*    */     //   152: lload #6
/*    */     //   154: lxor
/*    */     //   155: <illegal opcode> r : (IJ)Ljava/lang/String;
/*    */     //   160: aload #5
/*    */     //   162: invokestatic singletonMap : (Ljava/lang/Object;Ljava/lang/Object;)Ljava/util/Map;
/*    */     //   165: putfield a : Ljava/util/Map;
/*    */     //   168: return
/*    */     // Line number table:
/*    */     //   Java source line number -> byte code offset
/*    */     //   #21	-> 40
/*    */     //   #10	-> 46
/*    */     //   #26	-> 102
/*    */     //   #5	-> 140
/*    */     //   #36	-> 145
/*    */     //   #30	-> 168
/*    */     // Exception table:
/*    */     //   from	to	target	type
/*    */     //   46	55	58	java/lang/NullPointerException
/*    */     //   52	91	91	java/lang/NullPointerException
/*    */     //   104	129	129	java/lang/NullPointerException
/*    */   }
/*    */   public Charset a(long paramLong) {
/*    */     // Byte code:
/*    */     //   0: getstatic me/konsolas/aac/d0.c : J
/*    */     //   3: lload_1
/*    */     //   4: lxor
/*    */     //   5: lstore_1
/*    */     //   6: ldc2_w -6978632415615934492
/*    */     //   9: lload_1
/*    */     //   10: <illegal opcode> w : (JJ)[Lme/konsolas/aac/aN;
/*    */     //   15: aload_0
/*    */     //   16: getfield a : Ljava/util/Map;
/*    */     //   19: sipush #6256
/*    */     //   22: ldc2_w 4009642819199314701
/*    */     //   25: lload_1
/*    */     //   26: lxor
/*    */     //   27: <illegal opcode> r : (IJ)Ljava/lang/String;
/*    */     //   32: invokeinterface get : (Ljava/lang/Object;)Ljava/lang/Object;
/*    */     //   37: checkcast java/lang/String
/*    */     //   40: astore #4
/*    */     //   42: astore_3
/*    */     //   43: aload #4
/*    */     //   45: aload_3
/*    */     //   46: ifnonnull -> 67
/*    */     //   49: ifnull -> 73
/*    */     //   52: goto -> 65
/*    */     //   55: ldc2_w -6978780378634833358
/*    */     //   58: lload_1
/*    */     //   59: <illegal opcode> w : (Ljava/lang/Exception;JJ)Ljava/lang/Exception;
/*    */     //   64: athrow
/*    */     //   65: aload #4
/*    */     //   67: invokestatic forName : (Ljava/lang/String;)Ljava/nio/charset/Charset;
/*    */     //   70: areturn
/*    */     //   71: astore #5
/*    */     //   73: getstatic java/nio/charset/StandardCharsets.ISO_8859_1 : Ljava/nio/charset/Charset;
/*    */     //   76: areturn
/*    */     // Line number table:
/*    */     //   Java source line number -> byte code offset
/*    */     //   #25	-> 15
/*    */     //   #31	-> 43
/*    */     //   #22	-> 65
/*    */     //   #1	-> 71
/*    */     //   #32	-> 73
/*    */     // Exception table:
/*    */     //   from	to	target	type
/*    */     //   43	52	55	java/lang/Exception
/*    */     //   65	70	71	java/lang/Exception
/*    */   }
/*    */   public String b() {
/* 27 */     return this.b;
/*    */   }
/*    */ 
/*    */ 
/*    */ 
/*    */   
/*    */   public int hashCode() {
/* 34 */     int i = 29;
/*    */     
/*    */     i = 31 * i + this.b.hashCode();
/*    */     i = 31 * i + this.a.hashCode();
/* 38 */     return i;
/*    */   }
/*    */   
/*    */   public d0(String paramString, Map paramMap, long paramLong) {
/*    */     // Byte code:
/*    */     //   0: getstatic me/konsolas/aac/d0.c : J
/*    */     //   3: lload_3
/*    */     //   4: lxor
/*    */     //   5: lstore_3
/*    */     //   6: ldc2_w -909294843985136733
/*    */     //   9: lload_3
/*    */     //   10: <illegal opcode> w : (JJ)[Lme/konsolas/aac/aN;
/*    */     //   15: aload_0
/*    */     //   16: invokespecial <init> : ()V
/*    */     //   19: astore #5
/*    */     //   21: aload_1
/*    */     //   22: ifnonnull -> 56
/*    */     //   25: new java/lang/NullPointerException
/*    */     //   28: dup
/*    */     //   29: sipush #15503
/*    */     //   32: ldc2_w 2767754475411235769
/*    */     //   35: lload_3
/*    */     //   36: lxor
/*    */     //   37: <illegal opcode> r : (IJ)Ljava/lang/String;
/*    */     //   42: invokespecial <init> : (Ljava/lang/String;)V
/*    */     //   45: athrow
/*    */     //   46: ldc2_w -909437015072350603
/*    */     //   49: lload_3
/*    */     //   50: <illegal opcode> w : (Ljava/lang/Exception;JJ)Ljava/lang/Exception;
/*    */     //   55: athrow
/*    */     //   56: lload_3
/*    */     //   57: lconst_0
/*    */     //   58: lcmp
/*    */     //   59: ifle -> 102
/*    */     //   62: aload_2
/*    */     //   63: ifnonnull -> 97
/*    */     //   66: new java/lang/NullPointerException
/*    */     //   69: dup
/*    */     //   70: sipush #19116
/*    */     //   73: ldc2_w 991630597346661780
/*    */     //   76: lload_3
/*    */     //   77: lxor
/*    */     //   78: <illegal opcode> r : (IJ)Ljava/lang/String;
/*    */     //   83: invokespecial <init> : (Ljava/lang/String;)V
/*    */     //   86: athrow
/*    */     //   87: ldc2_w -909437015072350603
/*    */     //   90: lload_3
/*    */     //   91: <illegal opcode> w : (Ljava/lang/Exception;JJ)Ljava/lang/Exception;
/*    */     //   96: athrow
/*    */     //   97: aload_0
/*    */     //   98: aload_1
/*    */     //   99: putfield b : Ljava/lang/String;
/*    */     //   102: new java/util/LinkedHashMap
/*    */     //   105: dup
/*    */     //   106: invokespecial <init> : ()V
/*    */     //   109: astore #6
/*    */     //   111: aload_2
/*    */     //   112: invokeinterface entrySet : ()Ljava/util/Set;
/*    */     //   117: invokeinterface iterator : ()Ljava/util/Iterator;
/*    */     //   122: astore #7
/*    */     //   124: aload #7
/*    */     //   126: invokeinterface hasNext : ()Z
/*    */     //   131: ifeq -> 255
/*    */     //   134: aload #7
/*    */     //   136: invokeinterface next : ()Ljava/lang/Object;
/*    */     //   141: checkcast java/util/Map$Entry
/*    */     //   144: astore #8
/*    */     //   146: aload #5
/*    */     //   148: lload_3
/*    */     //   149: lconst_0
/*    */     //   150: lcmp
/*    */     //   151: iflt -> 164
/*    */     //   154: ifnonnull -> 270
/*    */     //   157: aload #8
/*    */     //   159: invokeinterface getKey : ()Ljava/lang/Object;
/*    */     //   164: aload #5
/*    */     //   166: ifnonnull -> 219
/*    */     //   169: goto -> 182
/*    */     //   172: ldc2_w -909437015072350603
/*    */     //   175: lload_3
/*    */     //   176: <illegal opcode> w : (Ljava/lang/Exception;JJ)Ljava/lang/Exception;
/*    */     //   181: athrow
/*    */     //   182: ifnonnull -> 212
/*    */     //   185: goto -> 198
/*    */     //   188: ldc2_w -909437015072350603
/*    */     //   191: lload_3
/*    */     //   192: <illegal opcode> w : (Ljava/lang/Exception;JJ)Ljava/lang/Exception;
/*    */     //   197: athrow
/*    */     //   198: aconst_null
/*    */     //   199: goto -> 228
/*    */     //   202: ldc2_w -909437015072350603
/*    */     //   205: lload_3
/*    */     //   206: <illegal opcode> w : (Ljava/lang/Exception;JJ)Ljava/lang/Exception;
/*    */     //   211: athrow
/*    */     //   212: aload #8
/*    */     //   214: invokeinterface getKey : ()Ljava/lang/Object;
/*    */     //   219: checkcast java/lang/String
/*    */     //   222: getstatic java/util/Locale.US : Ljava/util/Locale;
/*    */     //   225: invokevirtual toLowerCase : (Ljava/util/Locale;)Ljava/lang/String;
/*    */     //   228: astore #9
/*    */     //   230: aload #6
/*    */     //   232: aload #9
/*    */     //   234: aload #8
/*    */     //   236: invokeinterface getValue : ()Ljava/lang/Object;
/*    */     //   241: checkcast java/lang/String
/*    */     //   244: invokeinterface put : (Ljava/lang/Object;Ljava/lang/Object;)Ljava/lang/Object;
/*    */     //   249: pop
/*    */     //   250: aload #5
/*    */     //   252: ifnull -> 124
/*    */     //   255: aload_0
/*    */     //   256: aload #6
/*    */     //   258: invokestatic unmodifiableMap : (Ljava/util/Map;)Ljava/util/Map;
/*    */     //   261: putfield a : Ljava/util/Map;
/*    */     //   264: lload_3
/*    */     //   265: lconst_0
/*    */     //   266: lcmp
/*    */     //   267: ifle -> 270
/*    */     //   270: return
/*    */     // Line number table:
/*    */     //   Java source line number -> byte code offset
/*    */     //   #37	-> 15
/*    */     //   #29	-> 21
/*    */     //   #35	-> 56
/*    */     //   #24	-> 97
/*    */     //   #28	-> 102
/*    */     //   #7	-> 111
/*    */     //   #18	-> 146
/*    */     //   #33	-> 230
/*    */     //   #2	-> 250
/*    */     //   #4	-> 255
/*    */     //   #20	-> 270
/*    */     // Exception table:
/*    */     //   from	to	target	type
/*    */     //   21	46	46	java/lang/NullPointerException
/*    */     //   56	87	87	java/lang/NullPointerException
/*    */     //   146	169	172	java/lang/NullPointerException
/*    */     //   157	185	188	java/lang/NullPointerException
/*    */     //   182	202	202	java/lang/NullPointerException
/*    */   }
/*    */   
/*    */   static {
/*    */     long l = c ^ 0x29F0EC6166C2L;
/*    */     "몛㍀獂섈盈ၩ椿筰鵤梕쑌犽쓊ା⡕ໆ쀝館礅".toCharArray()[9] = (char)("몛㍀獂섈盈ၩ椿筰鵤梕쑌犽쓊ା⡕ໆ쀝館礅".toCharArray()[9] ^ 0x6C6);
/*    */     "⇎儱췂ㇺ".toCharArray()[1] = (char)("⇎儱췂ㇺ".toCharArray()[1] ^ 0x303E);
/*    */     (new byte[8])[0] = (byte)(int)(l >>> 56L);
/*    */     for (byte b1 = 1; b1 < 8; b1++)
/*    */       (new byte[8])[b1] = (byte)(int)(l << b1 * 8 >>> 56L); 
/*    */     Cipher cipher;
/*    */     (cipher = Cipher.getInstance(a0$cc.G("몛㍀獂섈盈ၩ椿筰鵤梕쑌犽쓊ା⡕ໆ쀝館礅".toCharArray(), (short)26234, true, (byte)2))).init(2, SecretKeyFactory.getInstance(a0$cc.G("⇎儱췂ㇺ".toCharArray(), (short)21868, false, (byte)4)).generateSecret(new DESKeySpec(new byte[8])), new IvParameterSpec(new byte[8]));
/*    */     String[] arrayOfString = new String[10];
/*    */     boolean bool = false;
/*    */     "㛵躬삗ᏩɌ넞邯ᆙ궻십㷆谽≊౵塞ꐰ⨐䝦퉚짒䄥遢赔㶷귎៼⚳첆菥閿傃껡䍵橔㏀ﳾ벨剤̐ꦕ侻?丛뒖뾖₹茻ꭒᩎ볜淑퀖璎闢뙖ㄘ諑䬖煰톀힩쀒ᶑ췉騮ꍯ唖́з뇋샾⚀ㆿ䶻뒶䣼๫맞?ᙯ㼹㸩㽗㩡ﾱ第鏊捌큝˥鐸뚣얄쓡嫼쪻䯖敧ᘊ꛾⧢捹Յ坂곹꼎盪ꚗɦ??넟飧玐斅૎烉箅茩낈쐕Ծ䇐ꨴ苵峓Εớꄝ䑮６Ѣ⽊䐆⼧ᱨ鍁Ή㮜⒎ᦽY迺ᮛ?霼洚꼰됁໮঩羮ⷿ释?㭱膭遏鯨᠅㉍碲?녛鑟잹ﾂᦣꐍ뀡侀滸谧䮟ᯆ잢舵讙꜀ㆪ눖ᡞ轈蜿灁눫퟼ᨼ룳࡞蕁뺟⌀퇩키ᥘ绨꺠샓矠".toCharArray()[94] = (char)("㛵躬삗ᏩɌ넞邯ᆙ궻십㷆谽≊౵塞ꐰ⨐䝦퉚짒䄥遢赔㶷귎៼⚳첆菥閿傃껡䍵橔㏀ﳾ벨剤̐ꦕ侻?丛뒖뾖₹茻ꭒᩎ볜淑퀖璎闢뙖ㄘ諑䬖煰톀힩쀒ᶑ췉騮ꍯ唖́з뇋샾⚀ㆿ䶻뒶䣼๫맞?ᙯ㼹㸩㽗㩡ﾱ第鏊捌큝˥鐸뚣얄쓡嫼쪻䯖敧ᘊ꛾⧢捹Յ坂곹꼎盪ꚗɦ??넟飧玐斅૎烉箅茩낈쐕Ծ䇐ꨴ苵峓Εớꄝ䑮６Ѣ⽊䐆⼧ᱨ鍁Ή㮜⒎ᦽY迺ᮛ?霼洚꼰됁໮঩羮ⷿ释?㭱膭遏鯨᠅㉍碲?녛鑟잹ﾂᦣꐍ뀡侀滸谧䮟ᯆ잢舵讙꜀ㆪ눖ᡞ轈蜿灁눫퟼ᨼ룳࡞蕁뺟⌀퇩키ᥘ绨꺠샓矠".toCharArray()[94] ^ 0x5FD4);
/*    */     String str;
/*    */     int i = (str = a0$cc.G("㛵躬삗ᏩɌ넞邯ᆙ궻십㷆谽≊౵塞ꐰ⨐䝦퉚짒䄥遢赔㶷귎៼⚳첆菥閿傃껡䍵橔㏀ﳾ벨剤̐ꦕ侻?丛뒖뾖₹茻ꭒᩎ볜淑퀖璎闢뙖ㄘ諑䬖煰톀힩쀒ᶑ췉騮ꍯ唖́з뇋샾⚀ㆿ䶻뒶䣼๫맞?ᙯ㼹㸩㽗㩡ﾱ第鏊捌큝˥鐸뚣얄쓡嫼쪻䯖敧ᘊ꛾⧢捹Յ坂곹꼎盪ꚗɦ??넟飧玐斅૎烉箅茩낈쐕Ծ䇐ꨴ苵峓Εớꄝ䑮６Ѣ⽊䐆⼧ᱨ鍁Ή㮜⒎ᦽY迺ᮛ?霼洚꼰됁໮঩羮ⷿ释?㭱膭遏鯨᠅㉍碲?녛鑟잹ﾂᦣꐍ뀡侀滸谧䮟ᯆ잢舵讙꜀ㆪ눖ᡞ轈蜿灁눫퟼ᨼ룳࡞蕁뺟⌀퇩키ᥘ绨꺠샓矠".toCharArray(), (short)489, false, (byte)0)).length();
/*    */     byte b2 = 24;
/*    */     byte b = -1;
/*    */     while (true);
/*    */   }
/*    */   
/*    */   private static Exception a(Exception paramException) {
/*    */     return paramException;
/*    */   }
/*    */   
/*    */   private static String a(byte[] paramArrayOfbyte) {
/*    */     byte b1 = 0;
/*    */     int i;
/*    */     char[] arrayOfChar = new char[i = paramArrayOfbyte.length];
/*    */     for (byte b2 = 0; b2 < i; b2++) {
/*    */       int j;
/*    */       if ((j = 0xFF & paramArrayOfbyte[b2]) < 192) {
/*    */         arrayOfChar[b1++] = (char)j;
/*    */       } else if (j < 224) {
/*    */         char c = (char)((char)(j & 0x1F) << 6);
/*    */         j = paramArrayOfbyte[++b2];
/*    */         c = (char)(c | (char)(j & 0x3F));
/*    */         arrayOfChar[b1++] = c;
/*    */       } else if (b2 < i - 2) {
/*    */         char c = (char)((char)(j & 0xF) << 12);
/*    */         j = paramArrayOfbyte[++b2];
/*    */         c = (char)(c | (char)(j & 0x3F) << 6);
/*    */         j = paramArrayOfbyte[++b2];
/*    */         c = (char)(c | (char)(j & 0x3F));
/*    */         arrayOfChar[b1++] = c;
/*    */       } 
/*    */     } 
/*    */     return new String(arrayOfChar, 0, b1);
/*    */   }
/*    */   
/*    */   private static String a(int paramInt, long paramLong) {
/*    */     int i = paramInt ^ (int)(paramLong & 0x7FFFL) ^ 0x2CBB;
/*    */     if (e[i] == null) {
/*    */       Object[] arrayOfObject;
/*    */       try {
/*    */         Long long_ = Long.valueOf(Thread.currentThread().getId());
/*    */         arrayOfObject = (Object[])f.get(long_);
/*    */         if (arrayOfObject == null) {
/*    */           arrayOfObject = new Object[3];
/*    */           "쬧坡嚂䥤졽쿺胍䢾䗺䎒າ竩룂懇쌡㣚浴먋乸㷯".toCharArray()[12] = (char)("쬧坡嚂䥤졽쿺胍䢾䗺䎒າ竩룂懇쌡㣚浴먋乸㷯".toCharArray()[12] ^ 0x57FD);
/*    */           arrayOfObject[0] = Cipher.getInstance(fW$gy.A("쬧坡嚂䥤졽쿺胍䢾䗺䎒າ竩룂懇쌡㣚浴먋乸㷯".toCharArray(), (short)15754, false, 2));
/*    */           "펛㩪몺摮".toCharArray()[1] = (char)("펛㩪몺摮".toCharArray()[1] ^ 0x2FFE);
/*    */           arrayOfObject[1] = SecretKeyFactory.getInstance(fW$gy.A("펛㩪몺摮".toCharArray(), (short)31093, true, 0));
/*    */           arrayOfObject[2] = new IvParameterSpec(new byte[8]);
/*    */           f.put(long_, arrayOfObject);
/*    */         } 
/*    */       } catch (Exception exception) {
/*    */         "봵儮뚭漹浉⨧鉎깏휄쏢⩮⃉赭ளꤒꪗꃺᘬ".toCharArray()[9] = (char)("봵儮뚭漹浉⨧鉎깏휄쏢⩮⃉赭ளꤒꪗꃺᘬ".toCharArray()[9] ^ 0x56E4);
/*    */         throw new RuntimeException(fW$gy.A("봵儮뚭漹浉⨧鉎깏휄쏢⩮⃉赭ளꤒꪗꃺᘬ".toCharArray(), (short)1111, false, 5), exception);
/*    */       } 
/*    */       byte[] arrayOfByte1 = new byte[8];
/*    */       arrayOfByte1[0] = (byte)(int)(paramLong >>> 56L);
/*    */       for (byte b = 1; b < 8; b++)
/*    */         arrayOfByte1[b] = (byte)(int)(paramLong << b * 8 >>> 56L); 
/*    */       DESKeySpec dESKeySpec = new DESKeySpec(arrayOfByte1);
/*    */       SecretKey secretKey = ((SecretKeyFactory)arrayOfObject[1]).generateSecret(dESKeySpec);
/*    */       ((Cipher)arrayOfObject[0]).init(2, secretKey, (IvParameterSpec)arrayOfObject[2]);
/*    */       "沿㘕륃?殫颲㚷㈄ະ".toCharArray()[2] = (char)("沿㘕륃?殫颲㚷㈄ະ".toCharArray()[2] ^ 0xBD4);
/*    */       byte[] arrayOfByte2 = d[i].getBytes(fW$gy.A("沿㘕륃?殫颲㚷㈄ະ".toCharArray(), (short)1404, true, 0));
/*    */       e[i] = a(((Cipher)arrayOfObject[0]).doFinal(arrayOfByte2));
/*    */     } 
/*    */     return e[i];
/*    */   }
/*    */   
/*    */   private static Object a(MethodHandles.Lookup paramLookup, MutableCallSite paramMutableCallSite, String paramString, Object[] paramArrayOfObject) {
/*    */     int i = ((Integer)paramArrayOfObject[0]).intValue();
/*    */     long l = ((Long)paramArrayOfObject[1]).longValue();
/*    */     String str = a(i, l);
/*    */     MethodHandle methodHandle = MethodHandles.constant(String.class, str);
/*    */     paramMutableCallSite.setTarget(MethodHandles.dropArguments(methodHandle, 0, new Class[] { int.class, long.class }));
/*    */     return str;
/*    */   }
/*    */   
/*    */   private static CallSite a(MethodHandles.Lookup paramLookup, String paramString, MethodType paramMethodType) {
/*    */     // Byte code:
/*    */     //   0: new java/lang/invoke/MutableCallSite
/*    */     //   3: dup
/*    */     //   4: aload_2
/*    */     //   5: invokespecial <init> : (Ljava/lang/invoke/MethodType;)V
/*    */     //   8: astore_3
/*    */     //   9: aload_3
/*    */     //   10: ldc_w
/*    */     //   13: ldc_w [Ljava/lang/Object;
/*    */     //   16: aload_2
/*    */     //   17: invokevirtual parameterCount : ()I
/*    */     //   20: invokevirtual asCollector : (Ljava/lang/Class;I)Ljava/lang/invoke/MethodHandle;
/*    */     //   23: iconst_0
/*    */     //   24: iconst_3
/*    */     //   25: anewarray java/lang/Object
/*    */     //   28: dup
/*    */     //   29: iconst_0
/*    */     //   30: aload_0
/*    */     //   31: aastore
/*    */     //   32: dup
/*    */     //   33: iconst_1
/*    */     //   34: aload_3
/*    */     //   35: aastore
/*    */     //   36: dup
/*    */     //   37: iconst_2
/*    */     //   38: aload_1
/*    */     //   39: aastore
/*    */     //   40: invokestatic insertArguments : (Ljava/lang/invoke/MethodHandle;I[Ljava/lang/Object;)Ljava/lang/invoke/MethodHandle;
/*    */     //   43: aload_2
/*    */     //   44: invokestatic explicitCastArguments : (Ljava/lang/invoke/MethodHandle;Ljava/lang/invoke/MethodType;)Ljava/lang/invoke/MethodHandle;
/*    */     //   47: invokevirtual setTarget : (Ljava/lang/invoke/MethodHandle;)V
/*    */     //   50: goto -> 170
/*    */     //   53: astore #4
/*    */     //   55: new java/lang/RuntimeException
/*    */     //   58: dup
/*    */     //   59: new java/lang/StringBuilder
/*    */     //   62: dup
/*    */     //   63: invokespecial <init> : ()V
/*    */     //   66: ldc_w '띗쵱ི⟃᳐焚⋐拗ꑧ굮╏褳䆮铥蛽海曦'
/*    */     //   69: invokevirtual toCharArray : ()[C
/*    */     //   72: dup
/*    */     //   73: dup
/*    */     //   74: iconst_0
/*    */     //   75: dup_x1
/*    */     //   76: caload
/*    */     //   77: sipush #3862
/*    */     //   80: ixor
/*    */     //   81: i2c
/*    */     //   82: castore
/*    */     //   83: sipush #22939
/*    */     //   86: iconst_0
/*    */     //   87: iconst_1
/*    */     //   88: invokestatic X : (Ljava/lang/Object;SZZ)Ljava/lang/String;
/*    */     //   91: invokevirtual append : (Ljava/lang/String;)Ljava/lang/StringBuilder;
/*    */     //   94: ldc_w 'ꏻ퉇࠵'
/*    */     //   97: invokevirtual toCharArray : ()[C
/*    */     //   100: dup
/*    */     //   101: dup
/*    */     //   102: iconst_2
/*    */     //   103: dup_x1
/*    */     //   104: caload
/*    */     //   105: sipush #31421
/*    */     //   108: ixor
/*    */     //   109: i2c
/*    */     //   110: castore
/*    */     //   111: sipush #15478
/*    */     //   114: iconst_1
/*    */     //   115: iconst_1
/*    */     //   116: invokestatic X : (Ljava/lang/Object;SZZ)Ljava/lang/String;
/*    */     //   119: invokevirtual append : (Ljava/lang/String;)Ljava/lang/StringBuilder;
/*    */     //   122: aload_1
/*    */     //   123: invokevirtual append : (Ljava/lang/String;)Ljava/lang/StringBuilder;
/*    */     //   126: ldc_w '瓽됡憗'
/*    */     //   129: invokevirtual toCharArray : ()[C
/*    */     //   132: dup
/*    */     //   133: dup
/*    */     //   134: iconst_0
/*    */     //   135: dup_x1
/*    */     //   136: caload
/*    */     //   137: sipush #12790
/*    */     //   140: ixor
/*    */     //   141: i2c
/*    */     //   142: castore
/*    */     //   143: sipush #11812
/*    */     //   146: iconst_1
/*    */     //   147: iconst_1
/*    */     //   148: invokestatic X : (Ljava/lang/Object;SZZ)Ljava/lang/String;
/*    */     //   151: invokevirtual append : (Ljava/lang/String;)Ljava/lang/StringBuilder;
/*    */     //   154: aload_2
/*    */     //   155: invokevirtual toString : ()Ljava/lang/String;
/*    */     //   158: invokevirtual append : (Ljava/lang/String;)Ljava/lang/StringBuilder;
/*    */     //   161: invokevirtual toString : ()Ljava/lang/String;
/*    */     //   164: aload #4
/*    */     //   166: invokespecial <init> : (Ljava/lang/String;Ljava/lang/Throwable;)V
/*    */     //   169: athrow
/*    */     //   170: aload_3
/*    */     //   171: areturn
/*    */     // Exception table:
/*    */     //   from	to	target	type
/*    */     //   9	50	53	java/lang/Exception
/*    */   }
/*    */ }


/* Location:              C:\Users\BukkitBypass\Desktop\MatrixAC\AAC\AAC-spigot-5.2.0.jar!\me\konsolas\aac\d0.class
 * Java compiler version: 8 (52.0)
 * JD-Core Version:       1.1.3
 */