/*    */ package me.konsolas.aac;
/*    */ import java.io.IOException;
/*    */ import java.lang.invoke.MethodHandles;
/*    */ import javax.crypto.Cipher;
/*    */ import javax.crypto.spec.DESKeySpec;
/*    */ import javax.crypto.spec.IvParameterSpec;
/*    */ 
/*    */ final class db implements hp {
/*    */   public li a() {
/* 10 */     return this.f.a();
/*    */   }
/*    */   
/*    */   private final bX f;
/*    */   
/*    */   int b;
/*    */   byte c;
/*    */   int d;
/*    */   int a;
/*    */   short e;
/*    */   private static final long g = nc.a(6833639503579013328L, -4189259065996054112L, MethodHandles.lookup().lookupClass()).a(63870801237377L);
/*    */   private static final String[] h;
/*    */   private static final String[] i;
/*    */   private static final Map j = new HashMap<>(13);
/*    */   
/*    */   public void close() {}
/*    */   
/*    */   public long a(long paramLong1, fw paramfw, long paramLong2) {
/*    */     // Byte code:
/*    */     //   0: lload_1
/*    */     //   1: dup2
/*    */     //   2: ldc2_w 0
/*    */     //   5: lxor
/*    */     //   6: lstore #6
/*    */     //   8: dup2
/*    */     //   9: ldc2_w 92191371223851
/*    */     //   12: lxor
/*    */     //   13: lstore #8
/*    */     //   15: dup2
/*    */     //   16: ldc2_w 63062641999687
/*    */     //   19: lxor
/*    */     //   20: lstore #10
/*    */     //   22: pop2
/*    */     //   23: ldc2_w -8543312552004129418
/*    */     //   26: lload_1
/*    */     //   27: <illegal opcode> w : (JJ)[Lme/konsolas/aac/aN;
/*    */     //   32: astore #12
/*    */     //   34: aload_0
/*    */     //   35: getfield a : I
/*    */     //   38: ifne -> 138
/*    */     //   41: aload_0
/*    */     //   42: getfield f : Lme/konsolas/aac/bX;
/*    */     //   45: aload_0
/*    */     //   46: getfield e : S
/*    */     //   49: i2l
/*    */     //   50: lload_1
/*    */     //   51: lconst_0
/*    */     //   52: lcmp
/*    */     //   53: iflt -> 150
/*    */     //   56: lload #10
/*    */     //   58: invokeinterface a : (JJ)V
/*    */     //   63: aload_0
/*    */     //   64: iconst_0
/*    */     //   65: putfield e : S
/*    */     //   68: aload_0
/*    */     //   69: aload #12
/*    */     //   71: ifnull -> 145
/*    */     //   74: aload #12
/*    */     //   76: ifnull -> 128
/*    */     //   79: goto -> 92
/*    */     //   82: ldc2_w -8539012475944136359
/*    */     //   85: lload_1
/*    */     //   86: <illegal opcode> w : (Ljava/io/IOException;JJ)Ljava/io/IOException;
/*    */     //   91: athrow
/*    */     //   92: getfield c : B
/*    */     //   95: iconst_4
/*    */     //   96: iand
/*    */     //   97: ifeq -> 127
/*    */     //   100: goto -> 113
/*    */     //   103: ldc2_w -8539012475944136359
/*    */     //   106: lload_1
/*    */     //   107: <illegal opcode> w : (Ljava/io/IOException;JJ)Ljava/io/IOException;
/*    */     //   112: athrow
/*    */     //   113: ldc2_w -1
/*    */     //   116: lreturn
/*    */     //   117: ldc2_w -8539012475944136359
/*    */     //   120: lload_1
/*    */     //   121: <illegal opcode> w : (Ljava/io/IOException;JJ)Ljava/io/IOException;
/*    */     //   126: athrow
/*    */     //   127: aload_0
/*    */     //   128: lload #8
/*    */     //   130: invokespecial a : (J)V
/*    */     //   133: aload #12
/*    */     //   135: ifnonnull -> 34
/*    */     //   138: lload_1
/*    */     //   139: lconst_0
/*    */     //   140: lcmp
/*    */     //   141: iflt -> 68
/*    */     //   144: aload_0
/*    */     //   145: getfield f : Lme/konsolas/aac/bX;
/*    */     //   148: lload #6
/*    */     //   150: aload_3
/*    */     //   151: lload #4
/*    */     //   153: aload_0
/*    */     //   154: getfield a : I
/*    */     //   157: i2l
/*    */     //   158: invokestatic min : (JJ)J
/*    */     //   161: invokeinterface a : (JLme/konsolas/aac/fw;J)J
/*    */     //   166: lstore #13
/*    */     //   168: lload #13
/*    */     //   170: aload #12
/*    */     //   172: ifnull -> 224
/*    */     //   175: ldc2_w -1
/*    */     //   178: lcmp
/*    */     //   179: ifne -> 209
/*    */     //   182: goto -> 195
/*    */     //   185: ldc2_w -8539012475944136359
/*    */     //   188: lload_1
/*    */     //   189: <illegal opcode> w : (Ljava/io/IOException;JJ)Ljava/io/IOException;
/*    */     //   194: athrow
/*    */     //   195: ldc2_w -1
/*    */     //   198: lreturn
/*    */     //   199: ldc2_w -8539012475944136359
/*    */     //   202: lload_1
/*    */     //   203: <illegal opcode> w : (Ljava/io/IOException;JJ)Ljava/io/IOException;
/*    */     //   208: athrow
/*    */     //   209: aload_0
/*    */     //   210: dup
/*    */     //   211: getfield a : I
/*    */     //   214: i2l
/*    */     //   215: lload #13
/*    */     //   217: lsub
/*    */     //   218: l2i
/*    */     //   219: putfield a : I
/*    */     //   222: lload #13
/*    */     //   224: lreturn
/*    */     // Line number table:
/*    */     //   Java source line number -> byte code offset
/*    */     //   #11	-> 34
/*    */     //   #4	-> 41
/*    */     //   #13	-> 63
/*    */     //   #21	-> 68
/*    */     //   #9	-> 127
/*    */     //   #8	-> 138
/*    */     //   #1	-> 168
/*    */     //   #16	-> 209
/*    */     //   #23	-> 222
/*    */     // Exception table:
/*    */     //   from	to	target	type
/*    */     //   41	79	82	java/io/IOException
/*    */     //   74	100	103	java/io/IOException
/*    */     //   92	117	117	java/io/IOException
/*    */     //   168	182	185	java/io/IOException
/*    */     //   175	199	199	java/io/IOException
/*    */   }
/*    */   
/*    */   private void a(long paramLong) {
/*    */     // Byte code:
/*    */     //   0: getstatic me/konsolas/aac/db.g : J
/*    */     //   3: lload_1
/*    */     //   4: lxor
/*    */     //   5: lstore_1
/*    */     //   6: lload_1
/*    */     //   7: dup2
/*    */     //   8: ldc2_w 76210272036230
/*    */     //   11: lxor
/*    */     //   12: lstore_3
/*    */     //   13: dup2
/*    */     //   14: ldc2_w 112757229742455
/*    */     //   17: lxor
/*    */     //   18: lstore #5
/*    */     //   20: dup2
/*    */     //   21: ldc2_w 93334090165398
/*    */     //   24: lxor
/*    */     //   25: lstore #7
/*    */     //   27: dup2
/*    */     //   28: ldc2_w 109941456847448
/*    */     //   31: lxor
/*    */     //   32: dup2
/*    */     //   33: bipush #48
/*    */     //   35: lushr
/*    */     //   36: l2i
/*    */     //   37: istore #9
/*    */     //   39: dup2
/*    */     //   40: bipush #16
/*    */     //   42: lshl
/*    */     //   43: bipush #32
/*    */     //   45: lushr
/*    */     //   46: l2i
/*    */     //   47: istore #10
/*    */     //   49: dup2
/*    */     //   50: bipush #48
/*    */     //   52: lshl
/*    */     //   53: bipush #48
/*    */     //   55: lushr
/*    */     //   56: l2i
/*    */     //   57: istore #11
/*    */     //   59: pop2
/*    */     //   60: pop2
/*    */     //   61: ldc2_w 6939883263598363721
/*    */     //   64: lload_1
/*    */     //   65: <illegal opcode> w : (JJ)[Lme/konsolas/aac/aN;
/*    */     //   70: aload_0
/*    */     //   71: getfield d : I
/*    */     //   74: istore #13
/*    */     //   76: astore #12
/*    */     //   78: aload_0
/*    */     //   79: aload_0
/*    */     //   80: aload_0
/*    */     //   81: getfield f : Lme/konsolas/aac/bX;
/*    */     //   84: lload_3
/*    */     //   85: invokestatic a : (Lme/konsolas/aac/bX;J)I
/*    */     //   88: dup_x1
/*    */     //   89: putfield a : I
/*    */     //   92: putfield b : I
/*    */     //   95: aload_0
/*    */     //   96: getfield f : Lme/konsolas/aac/bX;
/*    */     //   99: lload #5
/*    */     //   101: invokeinterface a : (J)B
/*    */     //   106: sipush #255
/*    */     //   109: iand
/*    */     //   110: i2b
/*    */     //   111: istore #14
/*    */     //   113: aload_0
/*    */     //   114: aload_0
/*    */     //   115: getfield f : Lme/konsolas/aac/bX;
/*    */     //   118: lload #5
/*    */     //   120: invokeinterface a : (J)B
/*    */     //   125: sipush #255
/*    */     //   128: iand
/*    */     //   129: i2b
/*    */     //   130: putfield c : B
/*    */     //   133: getstatic me/konsolas/aac/hM.b : Ljava/util/logging/Logger;
/*    */     //   136: getstatic java/util/logging/Level.FINE : Ljava/util/logging/Level;
/*    */     //   139: invokevirtual isLoggable : (Ljava/util/logging/Level;)Z
/*    */     //   142: aload #12
/*    */     //   144: ifnull -> 229
/*    */     //   147: ifeq -> 209
/*    */     //   150: goto -> 163
/*    */     //   153: ldc2_w 6935596296114108518
/*    */     //   156: lload_1
/*    */     //   157: <illegal opcode> w : (Ljava/io/IOException;JJ)Ljava/io/IOException;
/*    */     //   162: athrow
/*    */     //   163: getstatic me/konsolas/aac/hM.b : Ljava/util/logging/Logger;
/*    */     //   166: iconst_1
/*    */     //   167: aload_0
/*    */     //   168: getfield d : I
/*    */     //   171: iload #9
/*    */     //   173: i2c
/*    */     //   174: swap
/*    */     //   175: aload_0
/*    */     //   176: getfield b : I
/*    */     //   179: iload #10
/*    */     //   181: iload #11
/*    */     //   183: i2c
/*    */     //   184: iload #14
/*    */     //   186: aload_0
/*    */     //   187: getfield c : B
/*    */     //   190: invokestatic a : (ZCIIICBB)Ljava/lang/String;
/*    */     //   193: invokevirtual fine : (Ljava/lang/String;)V
/*    */     //   196: goto -> 209
/*    */     //   199: ldc2_w 6935596296114108518
/*    */     //   202: lload_1
/*    */     //   203: <illegal opcode> w : (Ljava/io/IOException;JJ)Ljava/io/IOException;
/*    */     //   208: athrow
/*    */     //   209: aload_0
/*    */     //   210: aload_0
/*    */     //   211: getfield f : Lme/konsolas/aac/bX;
/*    */     //   214: lload #7
/*    */     //   216: invokeinterface c : (J)I
/*    */     //   221: ldc 2147483647
/*    */     //   223: iand
/*    */     //   224: putfield d : I
/*    */     //   227: iload #14
/*    */     //   229: bipush #9
/*    */     //   231: lload_1
/*    */     //   232: lconst_0
/*    */     //   233: lcmp
/*    */     //   234: ifle -> 303
/*    */     //   237: aload #12
/*    */     //   239: ifnull -> 303
/*    */     //   242: if_icmpeq -> 297
/*    */     //   245: goto -> 258
/*    */     //   248: ldc2_w 6935596296114108518
/*    */     //   251: lload_1
/*    */     //   252: <illegal opcode> w : (Ljava/io/IOException;JJ)Ljava/io/IOException;
/*    */     //   257: athrow
/*    */     //   258: sipush #1460
/*    */     //   261: ldc2_w 6916803166883551453
/*    */     //   264: lload_1
/*    */     //   265: lxor
/*    */     //   266: <illegal opcode> f : (IJ)Ljava/lang/String;
/*    */     //   271: iconst_1
/*    */     //   272: anewarray java/lang/Object
/*    */     //   275: dup
/*    */     //   276: iconst_0
/*    */     //   277: iload #14
/*    */     //   279: invokestatic valueOf : (B)Ljava/lang/Byte;
/*    */     //   282: aastore
/*    */     //   283: invokestatic a : (Ljava/lang/String;[Ljava/lang/Object;)Ljava/io/IOException;
/*    */     //   286: athrow
/*    */     //   287: ldc2_w 6935596296114108518
/*    */     //   290: lload_1
/*    */     //   291: <illegal opcode> w : (Ljava/io/IOException;JJ)Ljava/io/IOException;
/*    */     //   296: athrow
/*    */     //   297: aload_0
/*    */     //   298: getfield d : I
/*    */     //   301: iload #13
/*    */     //   303: if_icmpeq -> 337
/*    */     //   306: sipush #2541
/*    */     //   309: ldc2_w 4513602433099142277
/*    */     //   312: lload_1
/*    */     //   313: lxor
/*    */     //   314: <illegal opcode> f : (IJ)Ljava/lang/String;
/*    */     //   319: iconst_0
/*    */     //   320: anewarray java/lang/Object
/*    */     //   323: invokestatic a : (Ljava/lang/String;[Ljava/lang/Object;)Ljava/io/IOException;
/*    */     //   326: athrow
/*    */     //   327: ldc2_w 6935596296114108518
/*    */     //   330: lload_1
/*    */     //   331: <illegal opcode> w : (Ljava/io/IOException;JJ)Ljava/io/IOException;
/*    */     //   336: athrow
/*    */     //   337: return
/*    */     // Line number table:
/*    */     //   Java source line number -> byte code offset
/*    */     //   #12	-> 70
/*    */     //   #20	-> 78
/*    */     //   #19	-> 95
/*    */     //   #22	-> 113
/*    */     //   #5	-> 133
/*    */     //   #14	-> 209
/*    */     //   #2	-> 227
/*    */     //   #18	-> 297
/*    */     //   #17	-> 337
/*    */     // Exception table:
/*    */     //   from	to	target	type
/*    */     //   113	150	153	java/io/IOException
/*    */     //   147	196	199	java/io/IOException
/*    */     //   229	245	248	java/io/IOException
/*    */     //   242	287	287	java/io/IOException
/*    */     //   303	327	327	java/io/IOException
/*    */   }
/*    */   
/*    */   db(bX parambX) {
/*    */     this.f = parambX;
/*    */   }
/*    */   
/*    */   static {
/*    */     long l = g ^ 0x26C93B4C042DL;
/*    */     "﷋⃈ὖᅭ䏣碈ᛞ徑耩缐⵹ጩ罔?뭺䦼咃粘".toCharArray()[10] = (char)("﷋⃈ὖᅭ䏣碈ᛞ徑耩缐⵹ጩ罔?뭺䦼咃粘".toCharArray()[10] ^ 0x2C1B);
/*    */     "⚖鿉ᬑ屇".toCharArray()[1] = (char)("⚖鿉ᬑ屇".toCharArray()[1] ^ 0x5F51);
/*    */     (new byte[8])[0] = (byte)(int)(l >>> 56L);
/*    */     for (byte b1 = 1; b1 < 8; b1++)
/*    */       (new byte[8])[b1] = (byte)(int)(l << b1 * 8 >>> 56L); 
/*    */     Cipher cipher;
/*    */     (cipher = Cipher.getInstance(dP$dt.X("﷋⃈ὖᅭ䏣碈ᛞ徑耩缐⵹ጩ罔?뭺䦼咃粘".toCharArray(), (short)25569, false, false))).init(2, SecretKeyFactory.getInstance(dP$dt.X("⚖鿉ᬑ屇".toCharArray(), (short)6248, true, false)).generateSecret(new DESKeySpec(new byte[8])), new IvParameterSpec(new byte[8]));
/*    */     String[] arrayOfString = new String[2];
/*    */     boolean bool = false;
/*    */     "欉⤧熥ﺶᐗ랢삋箭有껷餰䒸ഽẛ툢棼쾶䄽옑旫䲗졸涜敏䖲쿬鑭⩱仧清ꌌ혺꯺달Ἰ짴됳նㆇ캻Ⲹ團젦馰떺䬳샥⯅躂ਯﮑᵘ잜ᵞꗸⓏ罇ꖀ⸱⳹碪퐘ȧ㼿횏㵴㿶欽㸬牴薄ᩜ钄?㼵陑프憴仓ಁ쉰쪁켓䚐䯝젣烙⇁".toCharArray()[23] = (char)("欉⤧熥ﺶᐗ랢삋箭有껷餰䒸ഽẛ툢棼쾶䄽옑旫䲗졸涜敏䖲쿬鑭⩱仧清ꌌ혺꯺달Ἰ짴됳նㆇ캻Ⲹ團젦馰떺䬳샥⯅躂ਯﮑᵘ잜ᵞꗸⓏ罇ꖀ⸱⳹碪퐘ȧ㼿횏㵴㿶欽㸬牴薄ᩜ钄?㼵陑프憴仓ಁ쉰쪁켓䚐䯝젣烙⇁".toCharArray()[23] ^ 0x4EDD);
/*    */     String str;
/*    */     int i = (str = dP$dt.X("欉⤧熥ﺶᐗ랢삋箭有껷餰䒸ഽẛ툢棼쾶䄽옑旫䲗졸涜敏䖲쿬鑭⩱仧清ꌌ혺꯺달Ἰ짴됳նㆇ캻Ⲹ團젦馰떺䬳샥⯅躂ਯﮑᵘ잜ᵞꗸⓏ罇ꖀ⸱⳹碪퐘ȧ㼿횏㵴㿶欽㸬牴薄ᩜ钄?㼵陑프憴仓ಁ쉰쪁켓䚐䯝젣烙⇁".toCharArray(), (short)7521, false, true)).length();
/*    */     byte b2 = 40;
/*    */     byte b = -1;
/*    */     while (true);
/*    */   }
/*    */   
/*    */   private static IOException a(IOException paramIOException) {
/*    */     return paramIOException;
/*    */   }
/*    */   
/*    */   private static String a(byte[] paramArrayOfbyte) {
/*    */     byte b1 = 0;
/*    */     int i;
/*    */     char[] arrayOfChar = new char[i = paramArrayOfbyte.length];
/*    */     for (byte b2 = 0; b2 < i; b2++) {
/*    */       int j;
/*    */       if ((j = 0xFF & paramArrayOfbyte[b2]) < 192) {
/*    */         arrayOfChar[b1++] = (char)j;
/*    */       } else if (j < 224) {
/*    */         char c = (char)((char)(j & 0x1F) << 6);
/*    */         j = paramArrayOfbyte[++b2];
/*    */         c = (char)(c | (char)(j & 0x3F));
/*    */         arrayOfChar[b1++] = c;
/*    */       } else if (b2 < i - 2) {
/*    */         char c = (char)((char)(j & 0xF) << 12);
/*    */         j = paramArrayOfbyte[++b2];
/*    */         c = (char)(c | (char)(j & 0x3F) << 6);
/*    */         j = paramArrayOfbyte[++b2];
/*    */         c = (char)(c | (char)(j & 0x3F));
/*    */         arrayOfChar[b1++] = c;
/*    */       } 
/*    */     } 
/*    */     return new String(arrayOfChar, 0, b1);
/*    */   }
/*    */   
/*    */   private static String a(int paramInt, long paramLong) {
/*    */     int i = paramInt ^ (int)(paramLong & 0x7FFFL) ^ 0x7C9E;
/*    */     if (i[i] == null) {
/*    */       Object[] arrayOfObject;
/*    */       try {
/*    */         Long long_ = Long.valueOf(Thread.currentThread().getId());
/*    */         arrayOfObject = (Object[])j.get(long_);
/*    */         if (arrayOfObject == null) {
/*    */           arrayOfObject = new Object[3];
/*    */           "녗鸩ⱺ㦃ﺅ湜礶缾ⱜ퀂땰㢻硠劉僩旖螭抨ᆏ".toCharArray()[6] = (char)("녗鸩ⱺ㦃ﺅ湜礶缾ⱜ퀂땰㢻硠劉僩旖螭抨ᆏ".toCharArray()[6] ^ 0x7BE2);
/*    */           arrayOfObject[0] = Cipher.getInstance(dP$dt.X("녗鸩ⱺ㦃ﺅ湜礶缾ⱜ퀂땰㢻硠劉僩旖螭抨ᆏ".toCharArray(), (short)18086, false, false));
/*    */           "꫐녯㕸䁠".toCharArray()[1] = (char)("꫐녯㕸䁠".toCharArray()[1] ^ 0x5CB1);
/*    */           arrayOfObject[1] = SecretKeyFactory.getInstance(dP$dt.X("꫐녯㕸䁠".toCharArray(), (short)21007, true, true));
/*    */           arrayOfObject[2] = new IvParameterSpec(new byte[8]);
/*    */           j.put(long_, arrayOfObject);
/*    */         } 
/*    */       } catch (Exception exception) {
/*    */         "⸳띥捵僻呂㕉㳦ῆ?Ⱙ讆滛꽪⺙ૹ밷뜩座㘰".toCharArray()[11] = (char)("⸳띥捵僻呂㕉㳦ῆ?Ⱙ讆滛꽪⺙ૹ밷뜩座㘰".toCharArray()[11] ^ 0x72CA);
/*    */         throw new RuntimeException(dP$dt.X("⸳띥捵僻呂㕉㳦ῆ?Ⱙ讆滛꽪⺙ૹ밷뜩座㘰".toCharArray(), (short)18093, false, true), exception);
/*    */       } 
/*    */       byte[] arrayOfByte1 = new byte[8];
/*    */       arrayOfByte1[0] = (byte)(int)(paramLong >>> 56L);
/*    */       for (byte b = 1; b < 8; b++)
/*    */         arrayOfByte1[b] = (byte)(int)(paramLong << b * 8 >>> 56L); 
/*    */       DESKeySpec dESKeySpec = new DESKeySpec(arrayOfByte1);
/*    */       SecretKey secretKey = ((SecretKeyFactory)arrayOfObject[1]).generateSecret(dESKeySpec);
/*    */       ((Cipher)arrayOfObject[0]).init(2, secretKey, (IvParameterSpec)arrayOfObject[2]);
/*    */       "ᅸ䬅՜츐뺬ꓔ恳ŝᛠ잍织".toCharArray()[8] = (char)("ᅸ䬅՜츐뺬ꓔ恳ŝᛠ잍织".toCharArray()[8] ^ 0x62E4);
/*    */       byte[] arrayOfByte2 = h[i].getBytes(dP$dt.X("ᅸ䬅՜츐뺬ꓔ恳ŝᛠ잍织".toCharArray(), (short)26751, true, false));
/*    */       i[i] = a(((Cipher)arrayOfObject[0]).doFinal(arrayOfByte2));
/*    */     } 
/*    */     return i[i];
/*    */   }
/*    */   
/*    */   private static Object a(MethodHandles.Lookup paramLookup, MutableCallSite paramMutableCallSite, String paramString, Object[] paramArrayOfObject) {
/*    */     int i = ((Integer)paramArrayOfObject[0]).intValue();
/*    */     long l = ((Long)paramArrayOfObject[1]).longValue();
/*    */     String str = a(i, l);
/*    */     MethodHandle methodHandle = MethodHandles.constant(String.class, str);
/*    */     paramMutableCallSite.setTarget(MethodHandles.dropArguments(methodHandle, 0, new Class[] { int.class, long.class }));
/*    */     return str;
/*    */   }
/*    */   
/*    */   private static CallSite a(MethodHandles.Lookup paramLookup, String paramString, MethodType paramMethodType) {
/*    */     // Byte code:
/*    */     //   0: new java/lang/invoke/MutableCallSite
/*    */     //   3: dup
/*    */     //   4: aload_2
/*    */     //   5: invokespecial <init> : (Ljava/lang/invoke/MethodType;)V
/*    */     //   8: astore_3
/*    */     //   9: aload_3
/*    */     //   10: ldc_w
/*    */     //   13: ldc_w [Ljava/lang/Object;
/*    */     //   16: aload_2
/*    */     //   17: invokevirtual parameterCount : ()I
/*    */     //   20: invokevirtual asCollector : (Ljava/lang/Class;I)Ljava/lang/invoke/MethodHandle;
/*    */     //   23: iconst_0
/*    */     //   24: iconst_3
/*    */     //   25: anewarray java/lang/Object
/*    */     //   28: dup
/*    */     //   29: iconst_0
/*    */     //   30: aload_0
/*    */     //   31: aastore
/*    */     //   32: dup
/*    */     //   33: iconst_1
/*    */     //   34: aload_3
/*    */     //   35: aastore
/*    */     //   36: dup
/*    */     //   37: iconst_2
/*    */     //   38: aload_1
/*    */     //   39: aastore
/*    */     //   40: invokestatic insertArguments : (Ljava/lang/invoke/MethodHandle;I[Ljava/lang/Object;)Ljava/lang/invoke/MethodHandle;
/*    */     //   43: aload_2
/*    */     //   44: invokestatic explicitCastArguments : (Ljava/lang/invoke/MethodHandle;Ljava/lang/invoke/MethodType;)Ljava/lang/invoke/MethodHandle;
/*    */     //   47: invokevirtual setTarget : (Ljava/lang/invoke/MethodHandle;)V
/*    */     //   50: goto -> 171
/*    */     //   53: astore #4
/*    */     //   55: new java/lang/RuntimeException
/*    */     //   58: dup
/*    */     //   59: new java/lang/StringBuilder
/*    */     //   62: dup
/*    */     //   63: invokespecial <init> : ()V
/*    */     //   66: ldc_w '엑늹觭㈌뵼쿼塈鍠잰鳢䊀븶畴'
/*    */     //   69: invokevirtual toCharArray : ()[C
/*    */     //   72: dup
/*    */     //   73: dup
/*    */     //   74: bipush #14
/*    */     //   76: dup_x1
/*    */     //   77: caload
/*    */     //   78: sipush #25016
/*    */     //   81: ixor
/*    */     //   82: i2c
/*    */     //   83: castore
/*    */     //   84: sipush #2780
/*    */     //   87: iconst_0
/*    */     //   88: iconst_1
/*    */     //   89: invokestatic X : (Ljava/lang/Object;SZZ)Ljava/lang/String;
/*    */     //   92: invokevirtual append : (Ljava/lang/String;)Ljava/lang/StringBuilder;
/*    */     //   95: ldc_w '赀욧蒱粑'
/*    */     //   98: invokevirtual toCharArray : ()[C
/*    */     //   101: dup
/*    */     //   102: dup
/*    */     //   103: iconst_2
/*    */     //   104: dup_x1
/*    */     //   105: caload
/*    */     //   106: sipush #29231
/*    */     //   109: ixor
/*    */     //   110: i2c
/*    */     //   111: castore
/*    */     //   112: sipush #24920
/*    */     //   115: iconst_1
/*    */     //   116: iconst_0
/*    */     //   117: invokestatic X : (Ljava/lang/Object;SZZ)Ljava/lang/String;
/*    */     //   120: invokevirtual append : (Ljava/lang/String;)Ljava/lang/StringBuilder;
/*    */     //   123: aload_1
/*    */     //   124: invokevirtual append : (Ljava/lang/String;)Ljava/lang/StringBuilder;
/*    */     //   127: ldc_w '龁쪗깙楏'
/*    */     //   130: invokevirtual toCharArray : ()[C
/*    */     //   133: dup
/*    */     //   134: dup
/*    */     //   135: iconst_1
/*    */     //   136: dup_x1
/*    */     //   137: caload
/*    */     //   138: sipush #14405
/*    */     //   141: ixor
/*    */     //   142: i2c
/*    */     //   143: castore
/*    */     //   144: sipush #9074
/*    */     //   147: iconst_0
/*    */     //   148: iconst_1
/*    */     //   149: invokestatic X : (Ljava/lang/Object;SZZ)Ljava/lang/String;
/*    */     //   152: invokevirtual append : (Ljava/lang/String;)Ljava/lang/StringBuilder;
/*    */     //   155: aload_2
/*    */     //   156: invokevirtual toString : ()Ljava/lang/String;
/*    */     //   159: invokevirtual append : (Ljava/lang/String;)Ljava/lang/StringBuilder;
/*    */     //   162: invokevirtual toString : ()Ljava/lang/String;
/*    */     //   165: aload #4
/*    */     //   167: invokespecial <init> : (Ljava/lang/String;Ljava/lang/Throwable;)V
/*    */     //   170: athrow
/*    */     //   171: aload_3
/*    */     //   172: areturn
/*    */     // Exception table:
/*    */     //   from	to	target	type
/*    */     //   9	50	53	java/lang/Exception
/*    */   }
/*    */ }


/* Location:              C:\Users\BukkitBypass\Desktop\MatrixAC\AAC\AAC-spigot-5.2.0.jar!\me\konsolas\aac\db.class
 * Java compiler version: 8 (52.0)
 * JD-Core Version:       1.1.3
 */