package me.konsolas.aac;

import java.lang.invoke.MethodHandles;

public final class dO {
  final bT c;
  
  final boolean[] b;
  
  private boolean d;
  
  final m5 a;
  
  private static final long e = nc.a(754876309774122824L, 5776166668067842816L, MethodHandles.lookup().lookupClass()).a(29652827639017L);
  
  public void c(long paramLong) {
    // Byte code:
    //   0: getstatic me/konsolas/aac/dO.e : J
    //   3: lload_1
    //   4: lxor
    //   5: lstore_1
    //   6: lload_1
    //   7: dup2
    //   8: ldc2_w 54497322020191
    //   11: lxor
    //   12: lstore_3
    //   13: pop2
    //   14: ldc2_w 6871412364145586235
    //   17: lload_1
    //   18: <illegal opcode> w : (JJ)[Ljava/lang/String;
    //   23: aload_0
    //   24: getfield a : Lme/konsolas/aac/m5;
    //   27: dup
    //   28: astore #6
    //   30: monitorenter
    //   31: astore #5
    //   33: aload_0
    //   34: aload #5
    //   36: ifnonnull -> 83
    //   39: getfield d : Z
    //   42: ifeq -> 76
    //   45: goto -> 58
    //   48: ldc2_w 6883138915445968696
    //   51: lload_1
    //   52: <illegal opcode> w : (Ljava/lang/Exception;JJ)Ljava/lang/Exception;
    //   57: athrow
    //   58: new java/lang/IllegalStateException
    //   61: dup
    //   62: invokespecial <init> : ()V
    //   65: athrow
    //   66: ldc2_w 6883138915445968696
    //   69: lload_1
    //   70: <illegal opcode> w : (Ljava/lang/Exception;JJ)Ljava/lang/Exception;
    //   75: athrow
    //   76: aload_0
    //   77: getfield c : Lme/konsolas/aac/bT;
    //   80: getfield f : Lme/konsolas/aac/dO;
    //   83: aload #5
    //   85: ifnonnull -> 129
    //   88: aload_0
    //   89: if_acmpne -> 128
    //   92: goto -> 105
    //   95: ldc2_w 6883138915445968696
    //   98: lload_1
    //   99: <illegal opcode> w : (Ljava/lang/Exception;JJ)Ljava/lang/Exception;
    //   104: athrow
    //   105: aload_0
    //   106: getfield a : Lme/konsolas/aac/m5;
    //   109: aload_0
    //   110: lload_3
    //   111: iconst_1
    //   112: invokevirtual a : (Lme/konsolas/aac/dO;JZ)V
    //   115: goto -> 128
    //   118: ldc2_w 6883138915445968696
    //   121: lload_1
    //   122: <illegal opcode> w : (Ljava/lang/Exception;JJ)Ljava/lang/Exception;
    //   127: athrow
    //   128: aload_0
    //   129: iconst_1
    //   130: putfield d : Z
    //   133: aload #6
    //   135: monitorexit
    //   136: goto -> 147
    //   139: astore #7
    //   141: aload #6
    //   143: monitorexit
    //   144: aload #7
    //   146: athrow
    //   147: return
    // Line number table:
    //   Java source line number -> byte code offset
    //   #27	-> 23
    //   #41	-> 33
    //   #3	-> 58
    //   #42	-> 76
    //   #25	-> 105
    //   #11	-> 128
    //   #31	-> 133
    //   #43	-> 147
    // Exception table:
    //   from	to	target	type
    //   33	45	48	java/io/IOException
    //   33	136	139	finally
    //   39	66	66	java/io/IOException
    //   83	92	95	java/io/IOException
    //   88	115	118	java/io/IOException
    //   139	144	139	finally
  }
  
  public hp a(long paramLong, int paramInt) {
    // Byte code:
    //   0: getstatic me/konsolas/aac/dO.e : J
    //   3: lload_1
    //   4: lxor
    //   5: lstore_1
    //   6: lload_1
    //   7: dup2
    //   8: ldc2_w 29828255456921
    //   11: lxor
    //   12: dup2
    //   13: bipush #32
    //   15: lushr
    //   16: l2i
    //   17: istore #4
    //   19: dup2
    //   20: bipush #32
    //   22: lshl
    //   23: bipush #32
    //   25: lushr
    //   26: lstore #5
    //   28: pop2
    //   29: pop2
    //   30: ldc2_w -7225124344322837284
    //   33: lload_1
    //   34: <illegal opcode> w : (JJ)[Ljava/lang/String;
    //   39: aload_0
    //   40: getfield a : Lme/konsolas/aac/m5;
    //   43: dup
    //   44: astore #8
    //   46: monitorenter
    //   47: astore #7
    //   49: aload_0
    //   50: getfield d : Z
    //   53: aload #7
    //   55: ifnonnull -> 123
    //   58: ifeq -> 92
    //   61: goto -> 74
    //   64: ldc2_w -7250011500179305505
    //   67: lload_1
    //   68: <illegal opcode> w : (Ljava/lang/Exception;JJ)Ljava/lang/Exception;
    //   73: athrow
    //   74: new java/lang/IllegalStateException
    //   77: dup
    //   78: invokespecial <init> : ()V
    //   81: athrow
    //   82: ldc2_w -7250011500179305505
    //   85: lload_1
    //   86: <illegal opcode> w : (Ljava/lang/Exception;JJ)Ljava/lang/Exception;
    //   91: athrow
    //   92: aload_0
    //   93: getfield c : Lme/konsolas/aac/bT;
    //   96: lload_1
    //   97: lconst_0
    //   98: lcmp
    //   99: ifle -> 143
    //   102: aload #7
    //   104: ifnonnull -> 143
    //   107: getfield d : Z
    //   110: goto -> 123
    //   113: ldc2_w -7250011500179305505
    //   116: lload_1
    //   117: <illegal opcode> w : (Ljava/lang/Exception;JJ)Ljava/lang/Exception;
    //   122: athrow
    //   123: ifeq -> 168
    //   126: aload_0
    //   127: getfield c : Lme/konsolas/aac/bT;
    //   130: goto -> 143
    //   133: ldc2_w -7250011500179305505
    //   136: lload_1
    //   137: <illegal opcode> w : (Ljava/lang/Exception;JJ)Ljava/lang/Exception;
    //   142: athrow
    //   143: getfield f : Lme/konsolas/aac/dO;
    //   146: aload #7
    //   148: ifnonnull -> 174
    //   151: aload_0
    //   152: if_acmpeq -> 173
    //   155: goto -> 168
    //   158: ldc2_w -7250011500179305505
    //   161: lload_1
    //   162: <illegal opcode> w : (Ljava/lang/Exception;JJ)Ljava/lang/Exception;
    //   167: athrow
    //   168: aconst_null
    //   169: aload #8
    //   171: monitorexit
    //   172: areturn
    //   173: aload_0
    //   174: getfield a : Lme/konsolas/aac/m5;
    //   177: getfield h : Lme/konsolas/aac/j9;
    //   180: aload_0
    //   181: getfield c : Lme/konsolas/aac/bT;
    //   184: getfield b : [Ljava/io/File;
    //   187: iload_3
    //   188: aaload
    //   189: iload #4
    //   191: lload #5
    //   193: invokeinterface a : (Ljava/io/File;IJ)Lme/konsolas/aac/hp;
    //   198: aload #8
    //   200: monitorexit
    //   201: areturn
    //   202: astore #9
    //   204: aconst_null
    //   205: aload #8
    //   207: monitorexit
    //   208: areturn
    //   209: astore #10
    //   211: aload #8
    //   213: monitorexit
    //   214: aload #10
    //   216: athrow
    // Line number table:
    //   Java source line number -> byte code offset
    //   #28	-> 39
    //   #40	-> 49
    //   #4	-> 74
    //   #12	-> 92
    //   #6	-> 168
    //   #14	-> 173
    //   #24	-> 202
    //   #37	-> 204
    //   #5	-> 209
    // Exception table:
    //   from	to	target	type
    //   49	61	64	java/io/FileNotFoundException
    //   49	172	209	finally
    //   58	82	82	java/io/FileNotFoundException
    //   92	110	113	java/io/FileNotFoundException
    //   123	130	133	java/io/FileNotFoundException
    //   143	155	158	java/io/FileNotFoundException
    //   173	198	202	java/io/FileNotFoundException
    //   173	201	209	finally
    //   202	208	209	finally
    //   209	214	209	finally
  }
  
  public void d(char paramChar1, char paramChar2, int paramInt) {
    // Byte code:
    //   0: iload_1
    //   1: i2l
    //   2: bipush #48
    //   4: lshl
    //   5: iload_2
    //   6: i2l
    //   7: bipush #48
    //   9: lshl
    //   10: bipush #16
    //   12: lushr
    //   13: lor
    //   14: iload_3
    //   15: i2l
    //   16: bipush #32
    //   18: lshl
    //   19: bipush #32
    //   21: lushr
    //   22: lor
    //   23: getstatic me/konsolas/aac/dO.e : J
    //   26: lxor
    //   27: lstore #4
    //   29: lload #4
    //   31: dup2
    //   32: ldc2_w 47145407618855
    //   35: lxor
    //   36: lstore #6
    //   38: pop2
    //   39: ldc2_w 7864466184829977155
    //   42: lload #4
    //   44: <illegal opcode> w : (JJ)[Ljava/lang/String;
    //   49: aload_0
    //   50: getfield a : Lme/konsolas/aac/m5;
    //   53: dup
    //   54: astore #9
    //   56: monitorenter
    //   57: astore #8
    //   59: aload_0
    //   60: aload #8
    //   62: ifnonnull -> 111
    //   65: getfield d : Z
    //   68: ifeq -> 104
    //   71: goto -> 85
    //   74: ldc2_w 7925711991041178944
    //   77: lload #4
    //   79: <illegal opcode> w : (Ljava/lang/Exception;JJ)Ljava/lang/Exception;
    //   84: athrow
    //   85: new java/lang/IllegalStateException
    //   88: dup
    //   89: invokespecial <init> : ()V
    //   92: athrow
    //   93: ldc2_w 7925711991041178944
    //   96: lload #4
    //   98: <illegal opcode> w : (Ljava/lang/Exception;JJ)Ljava/lang/Exception;
    //   103: athrow
    //   104: aload_0
    //   105: getfield c : Lme/konsolas/aac/bT;
    //   108: getfield f : Lme/konsolas/aac/dO;
    //   111: aload #8
    //   113: ifnonnull -> 160
    //   116: aload_0
    //   117: if_acmpne -> 159
    //   120: goto -> 134
    //   123: ldc2_w 7925711991041178944
    //   126: lload #4
    //   128: <illegal opcode> w : (Ljava/lang/Exception;JJ)Ljava/lang/Exception;
    //   133: athrow
    //   134: aload_0
    //   135: getfield a : Lme/konsolas/aac/m5;
    //   138: aload_0
    //   139: lload #6
    //   141: iconst_0
    //   142: invokevirtual a : (Lme/konsolas/aac/dO;JZ)V
    //   145: goto -> 159
    //   148: ldc2_w 7925711991041178944
    //   151: lload #4
    //   153: <illegal opcode> w : (Ljava/lang/Exception;JJ)Ljava/lang/Exception;
    //   158: athrow
    //   159: aload_0
    //   160: iconst_1
    //   161: putfield d : Z
    //   164: aload #9
    //   166: monitorexit
    //   167: goto -> 178
    //   170: astore #10
    //   172: aload #9
    //   174: monitorexit
    //   175: aload #10
    //   177: athrow
    //   178: return
    // Line number table:
    //   Java source line number -> byte code offset
    //   #35	-> 49
    //   #49	-> 59
    //   #13	-> 85
    //   #51	-> 104
    //   #18	-> 134
    //   #20	-> 159
    //   #58	-> 164
    //   #34	-> 178
    // Exception table:
    //   from	to	target	type
    //   59	71	74	java/io/IOException
    //   59	167	170	finally
    //   65	93	93	java/io/IOException
    //   111	120	123	java/io/IOException
    //   116	145	148	java/io/IOException
    //   170	175	170	finally
  }
  
  void a(long paramLong) {
    // Byte code:
    //   0: getstatic me/konsolas/aac/dO.e : J
    //   3: lload_1
    //   4: lxor
    //   5: lstore_1
    //   6: lload_1
    //   7: dup2
    //   8: ldc2_w 101949863216232
    //   11: lxor
    //   12: lstore_3
    //   13: pop2
    //   14: ldc2_w 3541895119983713856
    //   17: lload_1
    //   18: <illegal opcode> w : (JJ)[Ljava/lang/String;
    //   23: astore #5
    //   25: aload_0
    //   26: getfield c : Lme/konsolas/aac/bT;
    //   29: getfield f : Lme/konsolas/aac/dO;
    //   32: aload_0
    //   33: if_acmpne -> 118
    //   36: iconst_0
    //   37: istore #6
    //   39: iload #6
    //   41: aload_0
    //   42: getfield a : Lme/konsolas/aac/m5;
    //   45: getfield r : I
    //   48: if_icmpge -> 104
    //   51: aload_0
    //   52: getfield a : Lme/konsolas/aac/m5;
    //   55: getfield h : Lme/konsolas/aac/j9;
    //   58: aload_0
    //   59: getfield c : Lme/konsolas/aac/bT;
    //   62: getfield h : [Ljava/io/File;
    //   65: iload #6
    //   67: aaload
    //   68: lload_3
    //   69: dup2_x1
    //   70: pop2
    //   71: invokeinterface b : (JLjava/io/File;)V
    //   76: aload #5
    //   78: ifnonnull -> 118
    //   81: goto -> 96
    //   84: ldc2_w 3602507633419706691
    //   87: lload_1
    //   88: <illegal opcode> w : (Ljava/lang/Exception;JJ)Ljava/lang/Exception;
    //   93: athrow
    //   94: astore #7
    //   96: iinc #6, 1
    //   99: aload #5
    //   101: ifnull -> 39
    //   104: aload_0
    //   105: lload_1
    //   106: lconst_0
    //   107: lcmp
    //   108: iflt -> 52
    //   111: getfield c : Lme/konsolas/aac/bT;
    //   114: aconst_null
    //   115: putfield f : Lme/konsolas/aac/dO;
    //   118: return
    // Line number table:
    //   Java source line number -> byte code offset
    //   #44	-> 25
    //   #56	-> 36
    //   #39	-> 51
    //   #9	-> 76
    //   #45	-> 94
    //   #17	-> 96
    //   #19	-> 104
    //   #53	-> 118
    // Exception table:
    //   from	to	target	type
    //   51	76	94	java/io/IOException
    //   51	84	84	java/lang/IllegalStateException
  }
  
  public gp a(long paramLong, int paramInt) {
    // Byte code:
    //   0: getstatic me/konsolas/aac/dO.e : J
    //   3: lload_1
    //   4: lxor
    //   5: lstore_1
    //   6: lload_1
    //   7: dup2
    //   8: ldc2_w 51312809168685
    //   11: lxor
    //   12: lstore #4
    //   14: dup2
    //   15: ldc2_w 50603613469827
    //   18: lxor
    //   19: dup2
    //   20: bipush #32
    //   22: lushr
    //   23: l2i
    //   24: istore #6
    //   26: dup2
    //   27: bipush #32
    //   29: lshl
    //   30: bipush #48
    //   32: lushr
    //   33: l2i
    //   34: istore #7
    //   36: dup2
    //   37: bipush #48
    //   39: lshl
    //   40: bipush #48
    //   42: lushr
    //   43: l2i
    //   44: istore #8
    //   46: pop2
    //   47: pop2
    //   48: ldc2_w 5018261047681608387
    //   51: lload_1
    //   52: <illegal opcode> w : (JJ)[Ljava/lang/String;
    //   57: aload_0
    //   58: getfield a : Lme/konsolas/aac/m5;
    //   61: dup
    //   62: astore #10
    //   64: monitorenter
    //   65: astore #9
    //   67: aload_0
    //   68: aload #9
    //   70: ifnonnull -> 117
    //   73: getfield d : Z
    //   76: ifeq -> 110
    //   79: goto -> 92
    //   82: ldc2_w 5007310738729014720
    //   85: lload_1
    //   86: <illegal opcode> w : (Ljava/lang/Exception;JJ)Ljava/lang/Exception;
    //   91: athrow
    //   92: new java/lang/IllegalStateException
    //   95: dup
    //   96: invokespecial <init> : ()V
    //   99: athrow
    //   100: ldc2_w 5007310738729014720
    //   103: lload_1
    //   104: <illegal opcode> w : (Ljava/lang/Exception;JJ)Ljava/lang/Exception;
    //   109: athrow
    //   110: aload_0
    //   111: getfield c : Lme/konsolas/aac/bT;
    //   114: getfield f : Lme/konsolas/aac/dO;
    //   117: lload_1
    //   118: lconst_0
    //   119: lcmp
    //   120: ifle -> 153
    //   123: aload #9
    //   125: ifnonnull -> 153
    //   128: aload_0
    //   129: if_acmpeq -> 152
    //   132: goto -> 145
    //   135: ldc2_w 5007310738729014720
    //   138: lload_1
    //   139: <illegal opcode> w : (Ljava/lang/Exception;JJ)Ljava/lang/Exception;
    //   144: athrow
    //   145: invokestatic a : ()Lme/konsolas/aac/gp;
    //   148: aload #10
    //   150: monitorexit
    //   151: areturn
    //   152: aload_0
    //   153: getfield c : Lme/konsolas/aac/bT;
    //   156: aload #9
    //   158: ifnonnull -> 204
    //   161: getfield d : Z
    //   164: ifne -> 200
    //   167: goto -> 180
    //   170: ldc2_w 5007310738729014720
    //   173: lload_1
    //   174: <illegal opcode> w : (Ljava/lang/Exception;JJ)Ljava/lang/Exception;
    //   179: athrow
    //   180: aload_0
    //   181: getfield b : [Z
    //   184: iload_3
    //   185: iconst_1
    //   186: bastore
    //   187: goto -> 200
    //   190: ldc2_w 5007310738729014720
    //   193: lload_1
    //   194: <illegal opcode> w : (Ljava/lang/Exception;JJ)Ljava/lang/Exception;
    //   199: athrow
    //   200: aload_0
    //   201: getfield c : Lme/konsolas/aac/bT;
    //   204: getfield h : [Ljava/io/File;
    //   207: iload_3
    //   208: aaload
    //   209: astore #11
    //   211: aload_0
    //   212: getfield a : Lme/konsolas/aac/m5;
    //   215: getfield h : Lme/konsolas/aac/j9;
    //   218: lload #4
    //   220: aload #11
    //   222: invokeinterface a : (JLjava/io/File;)Lme/konsolas/aac/gp;
    //   227: astore #12
    //   229: goto -> 241
    //   232: astore #13
    //   234: invokestatic a : ()Lme/konsolas/aac/gp;
    //   237: aload #10
    //   239: monitorexit
    //   240: areturn
    //   241: new me/konsolas/aac/lS
    //   244: dup
    //   245: iload #6
    //   247: iload #7
    //   249: i2c
    //   250: iload #8
    //   252: i2c
    //   253: aload_0
    //   254: aload #12
    //   256: invokespecial <init> : (ICCLme/konsolas/aac/dO;Lme/konsolas/aac/gp;)V
    //   259: aload #10
    //   261: monitorexit
    //   262: areturn
    //   263: astore #14
    //   265: aload #10
    //   267: monitorexit
    //   268: aload #14
    //   270: athrow
    // Line number table:
    //   Java source line number -> byte code offset
    //   #48	-> 57
    //   #38	-> 67
    //   #46	-> 92
    //   #2	-> 110
    //   #1	-> 145
    //   #22	-> 152
    //   #33	-> 180
    //   #10	-> 200
    //   #54	-> 211
    //   #23	-> 229
    //   #26	-> 232
    //   #36	-> 234
    //   #30	-> 241
    //   #16	-> 263
    // Exception table:
    //   from	to	target	type
    //   67	79	82	java/io/FileNotFoundException
    //   67	151	263	finally
    //   73	100	100	java/io/FileNotFoundException
    //   117	132	135	java/io/FileNotFoundException
    //   152	240	263	finally
    //   153	167	170	java/io/FileNotFoundException
    //   161	187	190	java/io/FileNotFoundException
    //   211	229	232	java/io/FileNotFoundException
    //   241	262	263	finally
    //   263	268	263	finally
  }
  
  dO(m5 paramm5, bT parambT, long paramLong) {
    // Byte code:
    //   0: getstatic me/konsolas/aac/dO.e : J
    //   3: lload_3
    //   4: lxor
    //   5: lstore_3
    //   6: aload_0
    //   7: aload_1
    //   8: putfield a : Lme/konsolas/aac/m5;
    //   11: ldc2_w -8469740132059044590
    //   14: lload_3
    //   15: <illegal opcode> w : (JJ)[Ljava/lang/String;
    //   20: aload_0
    //   21: invokespecial <init> : ()V
    //   24: astore #5
    //   26: aload_0
    //   27: aload_2
    //   28: putfield c : Lme/konsolas/aac/bT;
    //   31: aload_0
    //   32: aload_2
    //   33: getfield d : Z
    //   36: aload #5
    //   38: ifnonnull -> 75
    //   41: ifeq -> 71
    //   44: goto -> 57
    //   47: ldc2_w -8454229040150291951
    //   50: lload_3
    //   51: <illegal opcode> w : (Ljava/lang/Exception;JJ)Ljava/lang/Exception;
    //   56: athrow
    //   57: aconst_null
    //   58: goto -> 77
    //   61: ldc2_w -8454229040150291951
    //   64: lload_3
    //   65: <illegal opcode> w : (Ljava/lang/Exception;JJ)Ljava/lang/Exception;
    //   70: athrow
    //   71: aload_1
    //   72: getfield r : I
    //   75: newarray boolean
    //   77: putfield b : [Z
    //   80: return
    // Line number table:
    //   Java source line number -> byte code offset
    //   #52	-> 6
    //   #15	-> 26
    //   #29	-> 31
    //   #47	-> 80
    // Exception table:
    //   from	to	target	type
    //   26	44	47	java/lang/IllegalStateException
    //   41	61	61	java/lang/IllegalStateException
  }
  
  public void b(long paramLong) {
    // Byte code:
    //   0: getstatic me/konsolas/aac/dO.e : J
    //   3: lload_1
    //   4: lxor
    //   5: lstore_1
    //   6: lload_1
    //   7: dup2
    //   8: ldc2_w 26588033613281
    //   11: lxor
    //   12: lstore_3
    //   13: pop2
    //   14: ldc2_w 1144477932464808069
    //   17: lload_1
    //   18: <illegal opcode> w : (JJ)[Ljava/lang/String;
    //   23: aload_0
    //   24: getfield a : Lme/konsolas/aac/m5;
    //   27: dup
    //   28: astore #6
    //   30: monitorenter
    //   31: astore #5
    //   33: aload #5
    //   35: ifnonnull -> 124
    //   38: aload_0
    //   39: getfield d : Z
    //   42: ifne -> 121
    //   45: goto -> 58
    //   48: ldc2_w 1097747865852862342
    //   51: lload_1
    //   52: <illegal opcode> w : (Ljava/lang/Exception;JJ)Ljava/lang/Exception;
    //   57: athrow
    //   58: lload_1
    //   59: lconst_0
    //   60: lcmp
    //   61: ifle -> 116
    //   64: aload_0
    //   65: getfield c : Lme/konsolas/aac/bT;
    //   68: getfield f : Lme/konsolas/aac/dO;
    //   71: aload #5
    //   73: ifnonnull -> 107
    //   76: goto -> 89
    //   79: ldc2_w 1097747865852862342
    //   82: lload_1
    //   83: <illegal opcode> w : (Ljava/lang/Exception;JJ)Ljava/lang/Exception;
    //   88: athrow
    //   89: aload_0
    //   90: if_acmpne -> 121
    //   93: goto -> 106
    //   96: ldc2_w 1097747865852862342
    //   99: lload_1
    //   100: <illegal opcode> w : (Ljava/lang/Exception;JJ)Ljava/lang/Exception;
    //   105: athrow
    //   106: aload_0
    //   107: getfield a : Lme/konsolas/aac/m5;
    //   110: aload_0
    //   111: lload_3
    //   112: iconst_0
    //   113: invokevirtual a : (Lme/konsolas/aac/dO;JZ)V
    //   116: goto -> 121
    //   119: astore #7
    //   121: aload #6
    //   123: monitorexit
    //   124: goto -> 135
    //   127: astore #8
    //   129: aload #6
    //   131: monitorexit
    //   132: aload #8
    //   134: athrow
    //   135: return
    // Line number table:
    //   Java source line number -> byte code offset
    //   #55	-> 23
    //   #32	-> 33
    //   #50	-> 106
    //   #8	-> 116
    //   #57	-> 119
    //   #7	-> 121
    //   #21	-> 135
    // Exception table:
    //   from	to	target	type
    //   33	45	48	java/io/IOException
    //   33	124	127	finally
    //   38	76	79	java/io/IOException
    //   58	93	96	java/io/IOException
    //   106	116	119	java/io/IOException
    //   127	132	127	finally
  }
  
  private static Exception a(Exception paramException) {
    return paramException;
  }
}


/* Location:              C:\Users\BukkitBypass\Desktop\MatrixAC\AAC\AAC-spigot-5.2.0.jar!\me\konsolas\aac\dO.class
 * Java compiler version: 8 (52.0)
 * JD-Core Version:       1.1.3
 */