/*    */ package me.konsolas.aac;public final class ds {
/*    */   static final Logger a;
/*    */   private static final long b;
/*    */   
/*    */   public static gi a(gp paramgp, long paramLong) {
/*  6 */     paramLong = b ^ paramLong; int i = (int)((paramLong ^ 0x64FC819FE11L) >>> 56L); long l = (paramLong ^ 0x64FC819FE11L) << 8L >>> 8L; paramLong ^ 0x64FC819FE11L; return new j0(paramgp, (byte)i, l);
/*    */   } private static final String[] c; private static final String[] d; private static final Map e;
/*    */   private static lH a(Socket paramSocket) {
/*  9 */     return new lL(paramSocket); } private static gp a(OutputStream paramOutputStream, long paramLong, li paramli) { // Byte code:
/*    */     //   0: getstatic me/konsolas/aac/ds.b : J
/*    */     //   3: lload_1
/*    */     //   4: lxor
/*    */     //   5: lstore_1
/*    */     //   6: aload_0
/*    */     //   7: ifnonnull -> 41
/*    */     //   10: new java/lang/IllegalArgumentException
/*    */     //   13: dup
/*    */     //   14: sipush #20381
/*    */     //   17: ldc2_w 8430186932922309868
/*    */     //   20: lload_1
/*    */     //   21: lxor
/*    */     //   22: <illegal opcode> f : (IJ)Ljava/lang/String;
/*    */     //   27: invokespecial <init> : (Ljava/lang/String;)V
/*    */     //   30: athrow
/*    */     //   31: ldc2_w -7630555509421477400
/*    */     //   34: lload_1
/*    */     //   35: <illegal opcode> w : (Ljava/lang/Exception;JJ)Ljava/lang/Exception;
/*    */     //   40: athrow
/*    */     //   41: aload_3
/*    */     //   42: ifnonnull -> 76
/*    */     //   45: new java/lang/IllegalArgumentException
/*    */     //   48: dup
/*    */     //   49: sipush #19707
/*    */     //   52: ldc2_w 4442429131457355650
/*    */     //   55: lload_1
/*    */     //   56: lxor
/*    */     //   57: <illegal opcode> f : (IJ)Ljava/lang/String;
/*    */     //   62: invokespecial <init> : (Ljava/lang/String;)V
/*    */     //   65: athrow
/*    */     //   66: ldc2_w -7630555509421477400
/*    */     //   69: lload_1
/*    */     //   70: <illegal opcode> w : (Ljava/lang/Exception;JJ)Ljava/lang/Exception;
/*    */     //   75: athrow
/*    */     //   76: new me/konsolas/aac/C
/*    */     //   79: dup
/*    */     //   80: aload_3
/*    */     //   81: aload_0
/*    */     //   82: invokespecial <init> : (Lme/konsolas/aac/li;Ljava/io/OutputStream;)V
/*    */     //   85: areturn
/*    */     // Line number table:
/*    */     //   Java source line number -> byte code offset
/*    */     //   #10	-> 6
/*    */     //   #19	-> 41
/*    */     //   #29	-> 76
/*    */     // Exception table:
/*    */     //   from	to	target	type
/*    */     //   6	31	31	java/lang/IllegalArgumentException
/*    */     //   41	66	66	java/lang/IllegalArgumentException }
/*    */   public static bX a(short paramShort, hp paramhp, char paramChar, int paramInt) {
/* 11 */     long l1 = (paramShort << 48L | paramChar << 48L >>> 16L | paramInt << 32L >>> 32L) ^ b, l2 = l1 ^ 0x18DCAB74E926L; return new q(l2, paramhp);
/*    */   }
/*    */   public static gp a(long paramLong, OutputStream paramOutputStream) {
/* 14 */     paramLong = b ^ paramLong; long l = paramLong ^ 0x218EB12E9989L; return a(paramOutputStream, l, new li());
/*    */   } public static gp b(File paramFile, long paramLong) {
/*    */     // Byte code:
/*    */     //   0: getstatic me/konsolas/aac/ds.b : J
/*    */     //   3: lload_1
/*    */     //   4: lxor
/*    */     //   5: lstore_1
/*    */     //   6: lload_1
/*    */     //   7: dup2
/*    */     //   8: ldc2_w 5720339508450
/*    */     //   11: lxor
/*    */     //   12: lstore_3
/*    */     //   13: pop2
/*    */     //   14: aload_0
/*    */     //   15: ifnonnull -> 49
/*    */     //   18: new java/lang/IllegalArgumentException
/*    */     //   21: dup
/*    */     //   22: sipush #11072
/*    */     //   25: ldc2_w 4831682378364407134
/*    */     //   28: lload_1
/*    */     //   29: lxor
/*    */     //   30: <illegal opcode> f : (IJ)Ljava/lang/String;
/*    */     //   35: invokespecial <init> : (Ljava/lang/String;)V
/*    */     //   38: athrow
/*    */     //   39: ldc2_w -2057592473006701437
/*    */     //   42: lload_1
/*    */     //   43: <illegal opcode> w : (Ljava/lang/Exception;JJ)Ljava/lang/Exception;
/*    */     //   48: athrow
/*    */     //   49: new java/io/FileOutputStream
/*    */     //   52: dup
/*    */     //   53: aload_0
/*    */     //   54: invokespecial <init> : (Ljava/io/File;)V
/*    */     //   57: lload_3
/*    */     //   58: dup2_x1
/*    */     //   59: pop2
/*    */     //   60: invokestatic a : (JLjava/io/OutputStream;)Lme/konsolas/aac/gp;
/*    */     //   63: areturn
/*    */     // Line number table:
/*    */     //   Java source line number -> byte code offset
/*    */     //   #15	-> 14
/*    */     //   #16	-> 49
/*    */     // Exception table:
/*    */     //   from	to	target	type
/*    */     //   14	39	39	java/io/FileNotFoundException
/*    */   } static boolean a(AssertionError paramAssertionError, int paramInt, char paramChar, short paramShort) {
/*    */     // Byte code:
/*    */     //   0: iload_1
/*    */     //   1: i2l
/*    */     //   2: bipush #32
/*    */     //   4: lshl
/*    */     //   5: iload_2
/*    */     //   6: i2l
/*    */     //   7: bipush #48
/*    */     //   9: lshl
/*    */     //   10: bipush #32
/*    */     //   12: lushr
/*    */     //   13: lor
/*    */     //   14: iload_3
/*    */     //   15: i2l
/*    */     //   16: bipush #48
/*    */     //   18: lshl
/*    */     //   19: bipush #48
/*    */     //   21: lushr
/*    */     //   22: lor
/*    */     //   23: getstatic me/konsolas/aac/ds.b : J
/*    */     //   26: lxor
/*    */     //   27: lstore #4
/*    */     //   29: ldc2_w 8344910005453147015
/*    */     //   32: lload #4
/*    */     //   34: <illegal opcode> w : (JJ)I
/*    */     //   39: istore #6
/*    */     //   41: aload_0
/*    */     //   42: iload #6
/*    */     //   44: ifeq -> 82
/*    */     //   47: invokevirtual getCause : ()Ljava/lang/Throwable;
/*    */     //   50: ifnull -> 172
/*    */     //   53: goto -> 67
/*    */     //   56: ldc2_w 8338327752659145797
/*    */     //   59: lload #4
/*    */     //   61: <illegal opcode> w : (Ljava/lang/Exception;JJ)Ljava/lang/Exception;
/*    */     //   66: athrow
/*    */     //   67: aload_0
/*    */     //   68: goto -> 82
/*    */     //   71: ldc2_w 8338327752659145797
/*    */     //   74: lload #4
/*    */     //   76: <illegal opcode> w : (Ljava/lang/Exception;JJ)Ljava/lang/Exception;
/*    */     //   81: athrow
/*    */     //   82: invokevirtual getMessage : ()Ljava/lang/String;
/*    */     //   85: iload #6
/*    */     //   87: iload_3
/*    */     //   88: ifgt -> 132
/*    */     //   91: ifeq -> 129
/*    */     //   94: ifnull -> 172
/*    */     //   97: goto -> 111
/*    */     //   100: ldc2_w 8338327752659145797
/*    */     //   103: lload #4
/*    */     //   105: <illegal opcode> w : (Ljava/lang/Exception;JJ)Ljava/lang/Exception;
/*    */     //   110: athrow
/*    */     //   111: aload_0
/*    */     //   112: invokevirtual getMessage : ()Ljava/lang/String;
/*    */     //   115: goto -> 129
/*    */     //   118: ldc2_w 8338327752659145797
/*    */     //   121: lload #4
/*    */     //   123: <illegal opcode> w : (Ljava/lang/Exception;JJ)Ljava/lang/Exception;
/*    */     //   128: athrow
/*    */     //   129: sipush #3076
/*    */     //   132: ldc2_w 5825005754930559702
/*    */     //   135: lload #4
/*    */     //   137: lxor
/*    */     //   138: <illegal opcode> f : (IJ)Ljava/lang/String;
/*    */     //   143: invokevirtual contains : (Ljava/lang/CharSequence;)Z
/*    */     //   146: iload #6
/*    */     //   148: ifeq -> 169
/*    */     //   151: ifeq -> 172
/*    */     //   154: goto -> 168
/*    */     //   157: ldc2_w 8338327752659145797
/*    */     //   160: lload #4
/*    */     //   162: <illegal opcode> w : (Ljava/lang/Exception;JJ)Ljava/lang/Exception;
/*    */     //   167: athrow
/*    */     //   168: iconst_1
/*    */     //   169: goto -> 173
/*    */     //   172: iconst_0
/*    */     //   173: ireturn
/*    */     // Line number table:
/*    */     //   Java source line number -> byte code offset
/*    */     //   #17	-> 41
/*    */     //   #32	-> 112
/*    */     //   #2	-> 173
/*    */     // Exception table:
/*    */     //   from	to	target	type
/*    */     //   41	53	56	java/lang/IllegalArgumentException
/*    */     //   47	68	71	java/lang/IllegalArgumentException
/*    */     //   82	97	100	java/lang/IllegalArgumentException
/*    */     //   94	115	118	java/lang/IllegalArgumentException
/*    */     //   129	154	157	java/lang/IllegalArgumentException
/*    */   } @IgnoreJRERequirement
/*    */   public static gp a(Path paramPath, OpenOption[] paramArrayOfOpenOption, long paramLong) {
/*    */     // Byte code:
/*    */     //   0: getstatic me/konsolas/aac/ds.b : J
/*    */     //   3: lload_2
/*    */     //   4: lxor
/*    */     //   5: lstore_2
/*    */     //   6: lload_2
/*    */     //   7: dup2
/*    */     //   8: ldc2_w 36558960735180
/*    */     //   11: lxor
/*    */     //   12: lstore #4
/*    */     //   14: pop2
/*    */     //   15: ldc2_w 4334557933545981039
/*    */     //   18: lload_2
/*    */     //   19: <illegal opcode> w : (JJ)I
/*    */     //   24: istore #6
/*    */     //   26: aload_0
/*    */     //   27: iload #6
/*    */     //   29: ifeq -> 80
/*    */     //   32: ifnonnull -> 79
/*    */     //   35: goto -> 48
/*    */     //   38: ldc2_w 4350427761831631789
/*    */     //   41: lload_2
/*    */     //   42: <illegal opcode> w : (Ljava/lang/Exception;JJ)Ljava/lang/Exception;
/*    */     //   47: athrow
/*    */     //   48: new java/lang/IllegalArgumentException
/*    */     //   51: dup
/*    */     //   52: sipush #27094
/*    */     //   55: ldc2_w 5223418684422050030
/*    */     //   58: lload_2
/*    */     //   59: lxor
/*    */     //   60: <illegal opcode> f : (IJ)Ljava/lang/String;
/*    */     //   65: invokespecial <init> : (Ljava/lang/String;)V
/*    */     //   68: athrow
/*    */     //   69: ldc2_w 4350427761831631789
/*    */     //   72: lload_2
/*    */     //   73: <illegal opcode> w : (Ljava/lang/Exception;JJ)Ljava/lang/Exception;
/*    */     //   78: athrow
/*    */     //   79: aload_0
/*    */     //   80: aload_1
/*    */     //   81: invokestatic newOutputStream : (Ljava/nio/file/Path;[Ljava/nio/file/OpenOption;)Ljava/io/OutputStream;
/*    */     //   84: lload #4
/*    */     //   86: dup2_x1
/*    */     //   87: pop2
/*    */     //   88: invokestatic a : (JLjava/io/OutputStream;)Lme/konsolas/aac/gp;
/*    */     //   91: areturn
/*    */     // Line number table:
/*    */     //   Java source line number -> byte code offset
/*    */     //   #20	-> 26
/*    */     //   #8	-> 79
/*    */     // Exception table:
/*    */     //   from	to	target	type
/*    */     //   26	35	38	java/io/IOException
/*    */     //   32	69	69	java/io/IOException
/*    */   } public static gp a(long paramLong, Socket paramSocket) {
/*    */     // Byte code:
/*    */     //   0: getstatic me/konsolas/aac/ds.b : J
/*    */     //   3: lload_0
/*    */     //   4: lxor
/*    */     //   5: lstore_0
/*    */     //   6: lload_0
/*    */     //   7: dup2
/*    */     //   8: ldc2_w 34837380722297
/*    */     //   11: lxor
/*    */     //   12: lstore_3
/*    */     //   13: pop2
/*    */     //   14: ldc2_w -5672615934745581698
/*    */     //   17: lload_0
/*    */     //   18: <illegal opcode> w : (JJ)I
/*    */     //   23: istore #5
/*    */     //   25: aload_2
/*    */     //   26: iload #5
/*    */     //   28: ifne -> 79
/*    */     //   31: ifnonnull -> 78
/*    */     //   34: goto -> 47
/*    */     //   37: ldc2_w -5638514837298129331
/*    */     //   40: lload_0
/*    */     //   41: <illegal opcode> w : (Ljava/lang/Exception;JJ)Ljava/lang/Exception;
/*    */     //   46: athrow
/*    */     //   47: new java/lang/IllegalArgumentException
/*    */     //   50: dup
/*    */     //   51: sipush #15491
/*    */     //   54: ldc2_w 916818301364504656
/*    */     //   57: lload_0
/*    */     //   58: lxor
/*    */     //   59: <illegal opcode> f : (IJ)Ljava/lang/String;
/*    */     //   64: invokespecial <init> : (Ljava/lang/String;)V
/*    */     //   67: athrow
/*    */     //   68: ldc2_w -5638514837298129331
/*    */     //   71: lload_0
/*    */     //   72: <illegal opcode> w : (Ljava/lang/Exception;JJ)Ljava/lang/Exception;
/*    */     //   77: athrow
/*    */     //   78: aload_2
/*    */     //   79: iload #5
/*    */     //   81: ifne -> 135
/*    */     //   84: invokevirtual getOutputStream : ()Ljava/io/OutputStream;
/*    */     //   87: ifnonnull -> 134
/*    */     //   90: goto -> 103
/*    */     //   93: ldc2_w -5638514837298129331
/*    */     //   96: lload_0
/*    */     //   97: <illegal opcode> w : (Ljava/lang/Exception;JJ)Ljava/lang/Exception;
/*    */     //   102: athrow
/*    */     //   103: new java/io/IOException
/*    */     //   106: dup
/*    */     //   107: sipush #23729
/*    */     //   110: ldc2_w 5030220363946977379
/*    */     //   113: lload_0
/*    */     //   114: lxor
/*    */     //   115: <illegal opcode> f : (IJ)Ljava/lang/String;
/*    */     //   120: invokespecial <init> : (Ljava/lang/String;)V
/*    */     //   123: athrow
/*    */     //   124: ldc2_w -5638514837298129331
/*    */     //   127: lload_0
/*    */     //   128: <illegal opcode> w : (Ljava/lang/Exception;JJ)Ljava/lang/Exception;
/*    */     //   133: athrow
/*    */     //   134: aload_2
/*    */     //   135: invokestatic a : (Ljava/net/Socket;)Lme/konsolas/aac/lH;
/*    */     //   138: astore #6
/*    */     //   140: aload_2
/*    */     //   141: invokevirtual getOutputStream : ()Ljava/io/OutputStream;
/*    */     //   144: lload_3
/*    */     //   145: aload #6
/*    */     //   147: invokestatic a : (Ljava/io/OutputStream;JLme/konsolas/aac/li;)Lme/konsolas/aac/gp;
/*    */     //   150: astore #7
/*    */     //   152: aload #6
/*    */     //   154: aload #7
/*    */     //   156: invokevirtual a : (Lme/konsolas/aac/gp;)Lme/konsolas/aac/gp;
/*    */     //   159: areturn
/*    */     // Line number table:
/*    */     //   Java source line number -> byte code offset
/*    */     //   #21	-> 25
/*    */     //   #3	-> 78
/*    */     //   #4	-> 134
/*    */     //   #33	-> 140
/*    */     //   #24	-> 152
/*    */     // Exception table:
/*    */     //   from	to	target	type
/*    */     //   25	34	37	java/io/IOException
/*    */     //   31	68	68	java/io/IOException
/*    */     //   79	90	93	java/io/IOException
/*    */     //   84	124	124	java/io/IOException
/*    */   } public static hp a(long paramLong, Socket paramSocket) {
/*    */     // Byte code:
/*    */     //   0: getstatic me/konsolas/aac/ds.b : J
/*    */     //   3: lload_0
/*    */     //   4: lxor
/*    */     //   5: lstore_0
/*    */     //   6: lload_0
/*    */     //   7: dup2
/*    */     //   8: ldc2_w 90479178545690
/*    */     //   11: lxor
/*    */     //   12: lstore_3
/*    */     //   13: pop2
/*    */     //   14: ldc2_w 5654640583457535537
/*    */     //   17: lload_0
/*    */     //   18: <illegal opcode> w : (JJ)I
/*    */     //   23: istore #5
/*    */     //   25: aload_2
/*    */     //   26: iload #5
/*    */     //   28: ifeq -> 79
/*    */     //   31: ifnonnull -> 78
/*    */     //   34: goto -> 47
/*    */     //   37: ldc2_w 5621040032524184051
/*    */     //   40: lload_0
/*    */     //   41: <illegal opcode> w : (Ljava/lang/Exception;JJ)Ljava/lang/Exception;
/*    */     //   46: athrow
/*    */     //   47: new java/lang/IllegalArgumentException
/*    */     //   50: dup
/*    */     //   51: sipush #12973
/*    */     //   54: ldc2_w 5466509343810517442
/*    */     //   57: lload_0
/*    */     //   58: lxor
/*    */     //   59: <illegal opcode> f : (IJ)Ljava/lang/String;
/*    */     //   64: invokespecial <init> : (Ljava/lang/String;)V
/*    */     //   67: athrow
/*    */     //   68: ldc2_w 5621040032524184051
/*    */     //   71: lload_0
/*    */     //   72: <illegal opcode> w : (Ljava/lang/Exception;JJ)Ljava/lang/Exception;
/*    */     //   77: athrow
/*    */     //   78: aload_2
/*    */     //   79: iload #5
/*    */     //   81: ifeq -> 135
/*    */     //   84: invokevirtual getInputStream : ()Ljava/io/InputStream;
/*    */     //   87: ifnonnull -> 134
/*    */     //   90: goto -> 103
/*    */     //   93: ldc2_w 5621040032524184051
/*    */     //   96: lload_0
/*    */     //   97: <illegal opcode> w : (Ljava/lang/Exception;JJ)Ljava/lang/Exception;
/*    */     //   102: athrow
/*    */     //   103: new java/io/IOException
/*    */     //   106: dup
/*    */     //   107: sipush #26431
/*    */     //   110: ldc2_w 3520852968372317276
/*    */     //   113: lload_0
/*    */     //   114: lxor
/*    */     //   115: <illegal opcode> f : (IJ)Ljava/lang/String;
/*    */     //   120: invokespecial <init> : (Ljava/lang/String;)V
/*    */     //   123: athrow
/*    */     //   124: ldc2_w 5621040032524184051
/*    */     //   127: lload_0
/*    */     //   128: <illegal opcode> w : (Ljava/lang/Exception;JJ)Ljava/lang/Exception;
/*    */     //   133: athrow
/*    */     //   134: aload_2
/*    */     //   135: invokestatic a : (Ljava/net/Socket;)Lme/konsolas/aac/lH;
/*    */     //   138: astore #6
/*    */     //   140: aload_2
/*    */     //   141: invokevirtual getInputStream : ()Ljava/io/InputStream;
/*    */     //   144: aload #6
/*    */     //   146: lload_3
/*    */     //   147: invokestatic a : (Ljava/io/InputStream;Lme/konsolas/aac/li;J)Lme/konsolas/aac/hp;
/*    */     //   150: astore #7
/*    */     //   152: aload #6
/*    */     //   154: aload #7
/*    */     //   156: invokevirtual a : (Lme/konsolas/aac/hp;)Lme/konsolas/aac/hp;
/*    */     //   159: areturn
/*    */     // Line number table:
/*    */     //   Java source line number -> byte code offset
/*    */     //   #23	-> 25
/*    */     //   #1	-> 78
/*    */     //   #28	-> 134
/*    */     //   #30	-> 140
/*    */     //   #18	-> 152
/*    */     // Exception table:
/*    */     //   from	to	target	type
/*    */     //   25	34	37	java/io/IOException
/*    */     //   31	68	68	java/io/IOException
/*    */     //   79	90	93	java/io/IOException
/*    */     //   84	124	124	java/io/IOException
/*    */   } private static hp a(InputStream paramInputStream, li paramli, long paramLong) {
/*    */     // Byte code:
/*    */     //   0: getstatic me/konsolas/aac/ds.b : J
/*    */     //   3: lload_2
/*    */     //   4: lxor
/*    */     //   5: lstore_2
/*    */     //   6: aload_0
/*    */     //   7: ifnonnull -> 41
/*    */     //   10: new java/lang/IllegalArgumentException
/*    */     //   13: dup
/*    */     //   14: sipush #3982
/*    */     //   17: ldc2_w 6384202980508137261
/*    */     //   20: lload_2
/*    */     //   21: lxor
/*    */     //   22: <illegal opcode> f : (IJ)Ljava/lang/String;
/*    */     //   27: invokespecial <init> : (Ljava/lang/String;)V
/*    */     //   30: athrow
/*    */     //   31: ldc2_w 9063376970636171829
/*    */     //   34: lload_2
/*    */     //   35: <illegal opcode> w : (Ljava/lang/Exception;JJ)Ljava/lang/Exception;
/*    */     //   40: athrow
/*    */     //   41: aload_1
/*    */     //   42: ifnonnull -> 76
/*    */     //   45: new java/lang/IllegalArgumentException
/*    */     //   48: dup
/*    */     //   49: sipush #13238
/*    */     //   52: ldc2_w 8673098890011495185
/*    */     //   55: lload_2
/*    */     //   56: lxor
/*    */     //   57: <illegal opcode> f : (IJ)Ljava/lang/String;
/*    */     //   62: invokespecial <init> : (Ljava/lang/String;)V
/*    */     //   65: athrow
/*    */     //   66: ldc2_w 9063376970636171829
/*    */     //   69: lload_2
/*    */     //   70: <illegal opcode> w : (Ljava/lang/Exception;JJ)Ljava/lang/Exception;
/*    */     //   75: athrow
/*    */     //   76: new me/konsolas/aac/hI
/*    */     //   79: dup
/*    */     //   80: aload_1
/*    */     //   81: aload_0
/*    */     //   82: invokespecial <init> : (Lme/konsolas/aac/li;Ljava/io/InputStream;)V
/*    */     //   85: areturn
/*    */     // Line number table:
/*    */     //   Java source line number -> byte code offset
/*    */     //   #25	-> 6
/*    */     //   #5	-> 41
/*    */     //   #22	-> 76
/*    */     // Exception table:
/*    */     //   from	to	target	type
/*    */     //   6	31	31	java/lang/IllegalArgumentException
/*    */     //   41	66	66	java/lang/IllegalArgumentException
/*    */   }
/*    */   public static hp a(short paramShort, File paramFile, int paramInt, char paramChar) {
/*    */     // Byte code:
/*    */     //   0: iload_0
/*    */     //   1: i2l
/*    */     //   2: bipush #48
/*    */     //   4: lshl
/*    */     //   5: iload_2
/*    */     //   6: i2l
/*    */     //   7: bipush #32
/*    */     //   9: lshl
/*    */     //   10: bipush #16
/*    */     //   12: lushr
/*    */     //   13: lor
/*    */     //   14: iload_3
/*    */     //   15: i2l
/*    */     //   16: bipush #48
/*    */     //   18: lshl
/*    */     //   19: bipush #48
/*    */     //   21: lushr
/*    */     //   22: lor
/*    */     //   23: getstatic me/konsolas/aac/ds.b : J
/*    */     //   26: lxor
/*    */     //   27: lstore #4
/*    */     //   29: lload #4
/*    */     //   31: dup2
/*    */     //   32: ldc2_w 37457333314112
/*    */     //   35: lxor
/*    */     //   36: lstore #6
/*    */     //   38: pop2
/*    */     //   39: aload_1
/*    */     //   40: ifnonnull -> 76
/*    */     //   43: new java/lang/IllegalArgumentException
/*    */     //   46: dup
/*    */     //   47: sipush #8721
/*    */     //   50: ldc2_w 7104175552002996855
/*    */     //   53: lload #4
/*    */     //   55: lxor
/*    */     //   56: <illegal opcode> f : (IJ)Ljava/lang/String;
/*    */     //   61: invokespecial <init> : (Ljava/lang/String;)V
/*    */     //   64: athrow
/*    */     //   65: ldc2_w 2089889113327794930
/*    */     //   68: lload #4
/*    */     //   70: <illegal opcode> w : (Ljava/lang/Exception;JJ)Ljava/lang/Exception;
/*    */     //   75: athrow
/*    */     //   76: new java/io/FileInputStream
/*    */     //   79: dup
/*    */     //   80: aload_1
/*    */     //   81: invokespecial <init> : (Ljava/io/File;)V
/*    */     //   84: lload #6
/*    */     //   86: invokestatic a : (Ljava/io/InputStream;J)Lme/konsolas/aac/hp;
/*    */     //   89: areturn
/*    */     // Line number table:
/*    */     //   Java source line number -> byte code offset
/*    */     //   #26	-> 39
/*    */     //   #7	-> 76
/*    */     // Exception table:
/*    */     //   from	to	target	type
/*    */     //   39	65	65	java/io/FileNotFoundException
/*    */   }
/*    */   public static gp a(File paramFile, long paramLong) {
/*    */     // Byte code:
/*    */     //   0: getstatic me/konsolas/aac/ds.b : J
/*    */     //   3: lload_1
/*    */     //   4: lxor
/*    */     //   5: lstore_1
/*    */     //   6: lload_1
/*    */     //   7: dup2
/*    */     //   8: ldc2_w 29064459064423
/*    */     //   11: lxor
/*    */     //   12: lstore_3
/*    */     //   13: pop2
/*    */     //   14: aload_0
/*    */     //   15: ifnonnull -> 49
/*    */     //   18: new java/lang/IllegalArgumentException
/*    */     //   21: dup
/*    */     //   22: sipush #11072
/*    */     //   25: ldc2_w 4831670647700796891
/*    */     //   28: lload_1
/*    */     //   29: lxor
/*    */     //   30: <illegal opcode> f : (IJ)Ljava/lang/String;
/*    */     //   35: invokespecial <init> : (Ljava/lang/String;)V
/*    */     //   38: athrow
/*    */     //   39: ldc2_w 2014492016794467334
/*    */     //   42: lload_1
/*    */     //   43: <illegal opcode> w : (Ljava/lang/Exception;JJ)Ljava/lang/Exception;
/*    */     //   48: athrow
/*    */     //   49: new java/io/FileOutputStream
/*    */     //   52: dup
/*    */     //   53: aload_0
/*    */     //   54: iconst_1
/*    */     //   55: invokespecial <init> : (Ljava/io/File;Z)V
/*    */     //   58: lload_3
/*    */     //   59: dup2_x1
/*    */     //   60: pop2
/*    */     //   61: invokestatic a : (JLjava/io/OutputStream;)Lme/konsolas/aac/gp;
/*    */     //   64: areturn
/*    */     // Line number table:
/*    */     //   Java source line number -> byte code offset
/*    */     //   #31	-> 14
/*    */     //   #13	-> 49
/*    */     // Exception table:
/*    */     //   from	to	target	type
/*    */     //   14	39	39	java/io/FileNotFoundException
/*    */   }
/* 35 */   public static gp a() { return new l8(); } static { long l; byte b1;
/* 36 */     for (b = nc.a(7270165996500106868L, -4889000018794561318L, MethodHandles.lookup().lookupClass()).a(228267858535366L), e = new HashMap<>(13), l = b ^ 0x21C9CEFCA5DAL, "ꎵᥑ뾊큹鱟윯앇㷨鋖↚㰐癏쾝꟪몢碱怨⎽㑅".toCharArray()[18] = (char)("ꎵᥑ뾊큹鱟윯앇㷨鋖↚㰐癏쾝꟪몢碱怨⎽㑅".toCharArray()[18] ^ 0x2DCA), "뭄褶泖".toCharArray()[0] = (char)("뭄褶泖".toCharArray()[0] ^ 0x19C5), (new byte[8])[0] = (byte)(int)(l >>> 56L), b1 = 1; b1 < 8; ) { (new byte[8])[b1] = (byte)(int)(l << b1 * 8 >>> 56L); b1++; }  Cipher cipher; (cipher = Cipher.getInstance(fW$gy.A("ꎵᥑ뾊큹鱟윯앇㷨鋖↚㰐癏쾝꟪몢碱怨⎽㑅".toCharArray(), (short)16227, false, 2))).init(2, SecretKeyFactory.getInstance(fW$gy.A("뭄褶泖".toCharArray(), (short)18115, false, 2)).generateSecret(new DESKeySpec(new byte[8])), new IvParameterSpec(new byte[8])); String[] arrayOfString = new String[13]; boolean bool = false; "?ᩣ䉦꜂㯽??쬨蜺㐇犎뢁ቢ龇喯묟혈♆鱄ℤꜙ뽮?㯞敦᷀惾뼈롙㭣☫እ逸켽₽洨ࢲ懲䲓ճ脇鎱겿㪗釼璐㩽獋䁑ꓠ馓嶝隹毳릮粍⒄ᮏ?疄䶬뎲լ㭒?좌䳣༰ゐ୲ґ⇿퇵郤谭⠂玄䬮ᵥ᳽旹牏魶晹牮谾꣰聃ﮗ굝䯙䬙묱䬆芊㢰ᕫﱯ駿﹈?ෆ䓨艗픮纂뛭ꗈ劵䶼瘡棢旼ၖ?㣅镉䉱Є⭱⼭?㛑䤲峰簊⣕䏛竡㛘蜌♾脴ן⁫䖳㭮쑦ᒬ艓㎨䀰ᝡઠ崮皛缇塓誧廆?꒔따ꧣꘝ쟮喐⯝褤ﻚ壠Ĩ㱍ꇏ놷༞冄啺Ⴓ膽᫜ڥ㟐?급琘괈럯㣠啯鰣捼䀻쉹ا簠ਿ广筿\000㶲蔹﷤䬍鴎?យ糖曰ｾ?켖⡂흝⁨勪?韑㍽슃䅻䫔㉴厂죀텰꩙ϝ䗛἖ꆣ츻잏艴僽Ե珲햧窱蘏릝頻?풤㈦ጓ롅냫ஏ㤱⌆⚤뛤⡞驱靖䛋蛫嬏澅藻㉔睟싍?꼕杨눏᢬瀹Ⲧ碑䊥威ｕ뇞톌Ꮼ?쮅곣⬍沀?淦ย㖃宎墿᙭⣒㦐ﻻﲱ䓨㚷㼡帩疐ᅁ੘鍠흜巩绥?洿센ꑧᦚ≜饘⎑⏞៥ᶾ䶺酴㉲ᚳ순⾆欄捠﮳豣蚮⑄ป田嵊崕憚텊⼻ῧ㬋䒆呍ꮒ㒆玚".toCharArray()[44] = (char)("?ᩣ䉦꜂㯽??쬨蜺㐇犎뢁ቢ龇喯묟혈♆鱄ℤꜙ뽮?㯞敦᷀惾뼈롙㭣☫እ逸켽₽洨ࢲ懲䲓ճ脇鎱겿㪗釼璐㩽獋䁑ꓠ馓嶝隹毳릮粍⒄ᮏ?疄䶬뎲լ㭒?좌䳣༰ゐ୲ґ⇿퇵郤谭⠂玄䬮ᵥ᳽旹牏魶晹牮谾꣰聃ﮗ굝䯙䬙묱䬆芊㢰ᕫﱯ駿﹈?ෆ䓨艗픮纂뛭ꗈ劵䶼瘡棢旼ၖ?㣅镉䉱Є⭱⼭?㛑䤲峰簊⣕䏛竡㛘蜌♾脴ן⁫䖳㭮쑦ᒬ艓㎨䀰ᝡઠ崮皛缇塓誧廆?꒔따ꧣꘝ쟮喐⯝褤ﻚ壠Ĩ㱍ꇏ놷༞冄啺Ⴓ膽᫜ڥ㟐?급琘괈럯㣠啯鰣捼䀻쉹ا簠ਿ广筿\000㶲蔹﷤䬍鴎?យ糖曰ｾ?켖⡂흝⁨勪?韑㍽슃䅻䫔㉴厂죀텰꩙ϝ䗛἖ꆣ츻잏艴僽Ե珲햧窱蘏릝頻?풤㈦ጓ롅냫ஏ㤱⌆⚤뛤⡞驱靖䛋蛫嬏澅藻㉔睟싍?꼕杨눏᢬瀹Ⲧ碑䊥威ｕ뇞톌Ꮼ?쮅곣⬍沀?淦ย㖃宎墿᙭⣒㦐ﻻﲱ䓨㚷㼡帩疐ᅁ੘鍠흜巩绥?洿센ꑧᦚ≜饘⎑⏞៥ᶾ䶺酴㉲ᚳ순⾆欄捠﮳豣蚮⑄ป田嵊崕憚텊⼻ῧ㬋䒆呍ꮒ㒆玚".toCharArray()[44] ^ 0x363); String str; int i = (str = fW$gy.A("?ᩣ䉦꜂㯽??쬨蜺㐇犎뢁ቢ龇喯묟혈♆鱄ℤꜙ뽮?㯞敦᷀惾뼈롙㭣☫እ逸켽₽洨ࢲ懲䲓ճ脇鎱겿㪗釼璐㩽獋䁑ꓠ馓嶝隹毳릮粍⒄ᮏ?疄䶬뎲լ㭒?좌䳣༰ゐ୲ґ⇿퇵郤谭⠂玄䬮ᵥ᳽旹牏魶晹牮谾꣰聃ﮗ굝䯙䬙묱䬆芊㢰ᕫﱯ駿﹈?ෆ䓨艗픮纂뛭ꗈ劵䶼瘡棢旼ၖ?㣅镉䉱Є⭱⼭?㛑䤲峰簊⣕䏛竡㛘蜌♾脴ן⁫䖳㭮쑦ᒬ艓㎨䀰ᝡઠ崮皛缇塓誧廆?꒔따ꧣꘝ쟮喐⯝褤ﻚ壠Ĩ㱍ꇏ놷༞冄啺Ⴓ膽᫜ڥ㟐?급琘괈럯㣠啯鰣捼䀻쉹ا簠ਿ广筿\000㶲蔹﷤䬍鴎?យ糖曰ｾ?켖⡂흝⁨勪?韑㍽슃䅻䫔㉴厂죀텰꩙ϝ䗛἖ꆣ츻잏艴僽Ե珲햧窱蘏릝頻?풤㈦ጓ롅냫ஏ㤱⌆⚤뛤⡞驱靖䛋蛫嬏澅藻㉔睟싍?꼕杨눏᢬瀹Ⲧ碑䊥威ｕ뇞톌Ꮼ?쮅곣⬍沀?淦ย㖃宎墿᙭⣒㦐ﻻﲱ䓨㚷㼡帩疐ᅁ੘鍠흜巩绥?洿센ꑧᦚ≜饘⎑⏞៥ᶾ䶺酴㉲ᚳ순⾆欄捠﮳豣蚮⑄ป田嵊崕憚텊⼻ῧ㬋䒆呍ꮒ㒆玚".toCharArray(), (short)9488, true, 5)).length(); byte b2 = 24; byte b = -1;
/*    */     while (true); } @IgnoreJRERequirement public static hp a(long paramLong, Path paramPath, OpenOption[] paramArrayOfOpenOption) { // Byte code:
/*    */     //   0: getstatic me/konsolas/aac/ds.b : J
/*    */     //   3: lload_0
/*    */     //   4: lxor
/*    */     //   5: lstore_0
/*    */     //   6: lload_0
/*    */     //   7: dup2
/*    */     //   8: ldc2_w 7158456266963
/*    */     //   11: lxor
/*    */     //   12: lstore #4
/*    */     //   14: pop2
/*    */     //   15: ldc2_w -3464605091631532125
/*    */     //   18: lload_0
/*    */     //   19: <illegal opcode> w : (JJ)I
/*    */     //   24: istore #6
/*    */     //   26: aload_2
/*    */     //   27: iload #6
/*    */     //   29: ifeq -> 80
/*    */     //   32: ifnonnull -> 79
/*    */     //   35: goto -> 48
/*    */     //   38: ldc2_w -3489195143461984159
/*    */     //   41: lload_0
/*    */     //   42: <illegal opcode> w : (Ljava/lang/Exception;JJ)Ljava/lang/Exception;
/*    */     //   47: athrow
/*    */     //   48: new java/lang/IllegalArgumentException
/*    */     //   51: dup
/*    */     //   52: sipush #28438
/*    */     //   55: ldc2_w 6302682423786710500
/*    */     //   58: lload_0
/*    */     //   59: lxor
/*    */     //   60: <illegal opcode> f : (IJ)Ljava/lang/String;
/*    */     //   65: invokespecial <init> : (Ljava/lang/String;)V
/*    */     //   68: athrow
/*    */     //   69: ldc2_w -3489195143461984159
/*    */     //   72: lload_0
/*    */     //   73: <illegal opcode> w : (Ljava/lang/Exception;JJ)Ljava/lang/Exception;
/*    */     //   78: athrow
/*    */     //   79: aload_2
/*    */     //   80: aload_3
/*    */     //   81: invokestatic newInputStream : (Ljava/nio/file/Path;[Ljava/nio/file/OpenOption;)Ljava/io/InputStream;
/*    */     //   84: lload #4
/*    */     //   86: invokestatic a : (Ljava/io/InputStream;J)Lme/konsolas/aac/hp;
/*    */     //   89: areturn
/*    */     // Line number table:
/*    */     //   Java source line number -> byte code offset
/*    */     //   #37	-> 26
/*    */     //   #34	-> 79
/*    */     // Exception table:
/*    */     //   from	to	target	type
/*    */     //   26	35	38	java/io/IOException
/*    */     //   32	69	69	java/io/IOException }
/* 38 */   public static hp a(InputStream paramInputStream, long paramLong) { paramLong = b ^ paramLong; long l = paramLong ^ 0x70579CE98287L; return a(paramInputStream, new li(), l); }
/*    */ 
/*    */   
/*    */   private static Exception a(Exception paramException) {
/*    */     return paramException;
/*    */   }
/*    */   
/*    */   private static String a(byte[] paramArrayOfbyte) {
/*    */     byte b1 = 0;
/*    */     int i;
/*    */     char[] arrayOfChar = new char[i = paramArrayOfbyte.length];
/*    */     for (byte b2 = 0; b2 < i; b2++) {
/*    */       int j;
/*    */       if ((j = 0xFF & paramArrayOfbyte[b2]) < 192) {
/*    */         arrayOfChar[b1++] = (char)j;
/*    */       } else if (j < 224) {
/*    */         char c = (char)((char)(j & 0x1F) << 6);
/*    */         j = paramArrayOfbyte[++b2];
/*    */         c = (char)(c | (char)(j & 0x3F));
/*    */         arrayOfChar[b1++] = c;
/*    */       } else if (b2 < i - 2) {
/*    */         char c = (char)((char)(j & 0xF) << 12);
/*    */         j = paramArrayOfbyte[++b2];
/*    */         c = (char)(c | (char)(j & 0x3F) << 6);
/*    */         j = paramArrayOfbyte[++b2];
/*    */         c = (char)(c | (char)(j & 0x3F));
/*    */         arrayOfChar[b1++] = c;
/*    */       } 
/*    */     } 
/*    */     return new String(arrayOfChar, 0, b1);
/*    */   }
/*    */   
/*    */   private static String a(int paramInt, long paramLong) {
/*    */     int i = paramInt ^ (int)(paramLong & 0x7FFFL) ^ 0x41D;
/*    */     if (d[i] == null) {
/*    */       Object[] arrayOfObject;
/*    */       try {
/*    */         Long long_ = Long.valueOf(Thread.currentThread().getId());
/*    */         arrayOfObject = (Object[])e.get(long_);
/*    */         if (arrayOfObject == null) {
/*    */           arrayOfObject = new Object[3];
/*    */           "鬕殮κ椟뚀࡝႕砪ೂ榒଀᱖蔠餧䀹⹂㸸".toCharArray()[3] = (char)("鬕殮κ椟뚀࡝႕砪ೂ榒଀᱖蔠餧䀹⹂㸸".toCharArray()[3] ^ 0xE7F);
/*    */           arrayOfObject[0] = Cipher.getInstance(dP$dt.X("鬕殮κ椟뚀࡝႕砪ೂ榒଀᱖蔠餧䀹⹂㸸".toCharArray(), (short)30329, false, false));
/*    */           "闚൫⁁ⅿ".toCharArray()[2] = (char)("闚൫⁁ⅿ".toCharArray()[2] ^ 0x373E);
/*    */           arrayOfObject[1] = SecretKeyFactory.getInstance(dP$dt.X("闚൫⁁ⅿ".toCharArray(), (short)26980, true, false));
/*    */           arrayOfObject[2] = new IvParameterSpec(new byte[8]);
/*    */           e.put(long_, arrayOfObject);
/*    */         } 
/*    */       } catch (Exception exception) {
/*    */         "毀记ᙤ餲䲙庬簩醱蟩悛툿㑰똟䌮툚䎢慑戒".toCharArray()[11] = (char)("毀记ᙤ餲䲙庬簩醱蟩悛툿㑰똟䌮툚䎢慑戒".toCharArray()[11] ^ 0x73AC);
/*    */         throw new RuntimeException(dP$dt.X("毀记ᙤ餲䲙庬簩醱蟩悛툿㑰똟䌮툚䎢慑戒".toCharArray(), (short)14569, true, false), exception);
/*    */       } 
/*    */       byte[] arrayOfByte1 = new byte[8];
/*    */       arrayOfByte1[0] = (byte)(int)(paramLong >>> 56L);
/*    */       for (byte b = 1; b < 8; b++)
/*    */         arrayOfByte1[b] = (byte)(int)(paramLong << b * 8 >>> 56L); 
/*    */       DESKeySpec dESKeySpec = new DESKeySpec(arrayOfByte1);
/*    */       SecretKey secretKey = ((SecretKeyFactory)arrayOfObject[1]).generateSecret(dESKeySpec);
/*    */       ((Cipher)arrayOfObject[0]).init(2, secretKey, (IvParameterSpec)arrayOfObject[2]);
/*    */       "瘌ં楁ಲ޺＼ﮜ朮Ꮚ渰".toCharArray()[5] = (char)("瘌ં楁ಲ޺＼ﮜ朮Ꮚ渰".toCharArray()[5] ^ 0x7ACF);
/*    */       byte[] arrayOfByte2 = c[i].getBytes(dP$dt.X("瘌ં楁ಲ޺＼ﮜ朮Ꮚ渰".toCharArray(), (short)4417, false, true));
/*    */       d[i] = a(((Cipher)arrayOfObject[0]).doFinal(arrayOfByte2));
/*    */     } 
/*    */     return d[i];
/*    */   }
/*    */   
/*    */   private static Object a(MethodHandles.Lookup paramLookup, MutableCallSite paramMutableCallSite, String paramString, Object[] paramArrayOfObject) {
/*    */     int i = ((Integer)paramArrayOfObject[0]).intValue();
/*    */     long l = ((Long)paramArrayOfObject[1]).longValue();
/*    */     String str = a(i, l);
/*    */     MethodHandle methodHandle = MethodHandles.constant(String.class, str);
/*    */     paramMutableCallSite.setTarget(MethodHandles.dropArguments(methodHandle, 0, new Class[] { int.class, long.class }));
/*    */     return str;
/*    */   }
/*    */   
/*    */   private static CallSite a(MethodHandles.Lookup paramLookup, String paramString, MethodType paramMethodType) {
/*    */     // Byte code:
/*    */     //   0: new java/lang/invoke/MutableCallSite
/*    */     //   3: dup
/*    */     //   4: aload_2
/*    */     //   5: invokespecial <init> : (Ljava/lang/invoke/MethodType;)V
/*    */     //   8: astore_3
/*    */     //   9: aload_3
/*    */     //   10: ldc_w
/*    */     //   13: ldc_w [Ljava/lang/Object;
/*    */     //   16: aload_2
/*    */     //   17: invokevirtual parameterCount : ()I
/*    */     //   20: invokevirtual asCollector : (Ljava/lang/Class;I)Ljava/lang/invoke/MethodHandle;
/*    */     //   23: iconst_0
/*    */     //   24: iconst_3
/*    */     //   25: anewarray java/lang/Object
/*    */     //   28: dup
/*    */     //   29: iconst_0
/*    */     //   30: aload_0
/*    */     //   31: aastore
/*    */     //   32: dup
/*    */     //   33: iconst_1
/*    */     //   34: aload_3
/*    */     //   35: aastore
/*    */     //   36: dup
/*    */     //   37: iconst_2
/*    */     //   38: aload_1
/*    */     //   39: aastore
/*    */     //   40: invokestatic insertArguments : (Ljava/lang/invoke/MethodHandle;I[Ljava/lang/Object;)Ljava/lang/invoke/MethodHandle;
/*    */     //   43: aload_2
/*    */     //   44: invokestatic explicitCastArguments : (Ljava/lang/invoke/MethodHandle;Ljava/lang/invoke/MethodType;)Ljava/lang/invoke/MethodHandle;
/*    */     //   47: invokevirtual setTarget : (Ljava/lang/invoke/MethodHandle;)V
/*    */     //   50: goto -> 171
/*    */     //   53: astore #4
/*    */     //   55: new java/lang/RuntimeException
/*    */     //   58: dup
/*    */     //   59: new java/lang/StringBuilder
/*    */     //   62: dup
/*    */     //   63: invokespecial <init> : ()V
/*    */     //   66: ldc_w '餏♺ୀ⬳Ř唫쮕陈ዟ壒魔袪甾⊎蛍䛄ｄᷴ竣'
/*    */     //   69: invokevirtual toCharArray : ()[C
/*    */     //   72: dup
/*    */     //   73: dup
/*    */     //   74: bipush #8
/*    */     //   76: dup_x1
/*    */     //   77: caload
/*    */     //   78: sipush #6483
/*    */     //   81: ixor
/*    */     //   82: i2c
/*    */     //   83: castore
/*    */     //   84: sipush #6108
/*    */     //   87: iconst_1
/*    */     //   88: iconst_5
/*    */     //   89: invokestatic A : (Ljava/lang/Object;SZI)Ljava/lang/String;
/*    */     //   92: invokevirtual append : (Ljava/lang/String;)Ljava/lang/StringBuilder;
/*    */     //   95: ldc_w 'ࣴ㇅ᶶ'
/*    */     //   98: invokevirtual toCharArray : ()[C
/*    */     //   101: dup
/*    */     //   102: dup
/*    */     //   103: iconst_1
/*    */     //   104: dup_x1
/*    */     //   105: caload
/*    */     //   106: sipush #17431
/*    */     //   109: ixor
/*    */     //   110: i2c
/*    */     //   111: castore
/*    */     //   112: sipush #3947
/*    */     //   115: iconst_1
/*    */     //   116: iconst_2
/*    */     //   117: invokestatic A : (Ljava/lang/Object;SZI)Ljava/lang/String;
/*    */     //   120: invokevirtual append : (Ljava/lang/String;)Ljava/lang/StringBuilder;
/*    */     //   123: aload_1
/*    */     //   124: invokevirtual append : (Ljava/lang/String;)Ljava/lang/StringBuilder;
/*    */     //   127: ldc_w '쫆桎ᅨ'
/*    */     //   130: invokevirtual toCharArray : ()[C
/*    */     //   133: dup
/*    */     //   134: dup
/*    */     //   135: iconst_2
/*    */     //   136: dup_x1
/*    */     //   137: caload
/*    */     //   138: sipush #6825
/*    */     //   141: ixor
/*    */     //   142: i2c
/*    */     //   143: castore
/*    */     //   144: sipush #8645
/*    */     //   147: iconst_1
/*    */     //   148: iconst_5
/*    */     //   149: invokestatic A : (Ljava/lang/Object;SZI)Ljava/lang/String;
/*    */     //   152: invokevirtual append : (Ljava/lang/String;)Ljava/lang/StringBuilder;
/*    */     //   155: aload_2
/*    */     //   156: invokevirtual toString : ()Ljava/lang/String;
/*    */     //   159: invokevirtual append : (Ljava/lang/String;)Ljava/lang/StringBuilder;
/*    */     //   162: invokevirtual toString : ()Ljava/lang/String;
/*    */     //   165: aload #4
/*    */     //   167: invokespecial <init> : (Ljava/lang/String;Ljava/lang/Throwable;)V
/*    */     //   170: athrow
/*    */     //   171: aload_3
/*    */     //   172: areturn
/*    */     // Exception table:
/*    */     //   from	to	target	type
/*    */     //   9	50	53	java/lang/Exception
/*    */   }
/*    */ }


/* Location:              C:\Users\BukkitBypass\Desktop\MatrixAC\AAC\AAC-spigot-5.2.0.jar!\me\konsolas\aac\ds.class
 * Java compiler version: 7 (51.0)
 * JD-Core Version:       1.1.3
 */