/*     */ package me.konsolas.aac;public final class dw implements k3, mQ { private static final List f; private static final long u = 16777216L; private static final long k = 60000L; private final s s; final jn l; private final Random j;
/*     */   private final long y;
/*     */   
/*     */   public synchronized long a() {
/*   5 */     return this.w;
/*     */   }
/*     */   private final String h; private gC t; private final Runnable d; private c_ m; private bB o; private ScheduledExecutorService x; private fr B; private final ArrayDeque i; private final ArrayDeque b; private long w; private boolean c; private ScheduledFuture g; private int e; private String z; private boolean A;
/*     */   private int q;
/*     */   private int r;
/*     */   private int a;
/*     */   private boolean n;
/*     */   private static int[] v;
/*     */   private static final long C;
/*     */   private static final String[] D;
/*     */   private static final String[] E;
/*     */   private static final Map F;
/*     */   
/*     */   public void a(int paramInt, String paramString, long paramLong) {
/*     */     // Byte code:
/*     */     //   0: lload_3
/*     */     //   1: dup2
/*     */     //   2: ldc2_w 79931710940351
/*     */     //   5: lxor
/*     */     //   6: lstore #5
/*     */     //   8: pop2
/*     */     //   9: ldc2_w -4570842991835515655
/*     */     //   12: lload_3
/*     */     //   13: <illegal opcode> w : (JJ)[I
/*     */     //   18: astore #7
/*     */     //   20: iload_1
/*     */     //   21: iconst_m1
/*     */     //   22: if_icmpne -> 43
/*     */     //   25: new java/lang/IllegalArgumentException
/*     */     //   28: dup
/*     */     //   29: invokespecial <init> : ()V
/*     */     //   32: athrow
/*     */     //   33: ldc2_w -4549131292087159527
/*     */     //   36: lload_3
/*     */     //   37: <illegal opcode> w : (Ljava/lang/Exception;JJ)Ljava/lang/Exception;
/*     */     //   42: athrow
/*     */     //   43: aconst_null
/*     */     //   44: astore #8
/*     */     //   46: aload_0
/*     */     //   47: dup
/*     */     //   48: astore #9
/*     */     //   50: monitorenter
/*     */     //   51: aload_0
/*     */     //   52: getfield e : I
/*     */     //   55: aload #7
/*     */     //   57: lload_3
/*     */     //   58: lconst_0
/*     */     //   59: lcmp
/*     */     //   60: ifle -> 117
/*     */     //   63: ifnonnull -> 115
/*     */     //   66: iconst_m1
/*     */     //   67: if_icmpeq -> 101
/*     */     //   70: new java/lang/IllegalStateException
/*     */     //   73: dup
/*     */     //   74: sipush #29687
/*     */     //   77: ldc2_w 3837625512310939306
/*     */     //   80: lload_3
/*     */     //   81: lxor
/*     */     //   82: <illegal opcode> o : (IJ)Ljava/lang/String;
/*     */     //   87: invokespecial <init> : (Ljava/lang/String;)V
/*     */     //   90: athrow
/*     */     //   91: ldc2_w -4549131292087159527
/*     */     //   94: lload_3
/*     */     //   95: <illegal opcode> w : (Ljava/lang/Exception;JJ)Ljava/lang/Exception;
/*     */     //   100: athrow
/*     */     //   101: aload_0
/*     */     //   102: iload_1
/*     */     //   103: putfield e : I
/*     */     //   106: aload_0
/*     */     //   107: aload_2
/*     */     //   108: putfield z : Ljava/lang/String;
/*     */     //   111: aload_0
/*     */     //   112: getfield c : Z
/*     */     //   115: aload #7
/*     */     //   117: ifnonnull -> 174
/*     */     //   120: ifeq -> 246
/*     */     //   123: goto -> 136
/*     */     //   126: ldc2_w -4549131292087159527
/*     */     //   129: lload_3
/*     */     //   130: <illegal opcode> w : (Ljava/lang/Exception;JJ)Ljava/lang/Exception;
/*     */     //   135: athrow
/*     */     //   136: aload_0
/*     */     //   137: aload #7
/*     */     //   139: ifnonnull -> 178
/*     */     //   142: goto -> 155
/*     */     //   145: ldc2_w -4549131292087159527
/*     */     //   148: lload_3
/*     */     //   149: <illegal opcode> w : (Ljava/lang/Exception;JJ)Ljava/lang/Exception;
/*     */     //   154: athrow
/*     */     //   155: getfield b : Ljava/util/ArrayDeque;
/*     */     //   158: invokevirtual isEmpty : ()Z
/*     */     //   161: goto -> 174
/*     */     //   164: ldc2_w -4549131292087159527
/*     */     //   167: lload_3
/*     */     //   168: <illegal opcode> w : (Ljava/lang/Exception;JJ)Ljava/lang/Exception;
/*     */     //   173: athrow
/*     */     //   174: ifeq -> 246
/*     */     //   177: aload_0
/*     */     //   178: getfield B : Lme/konsolas/aac/fr;
/*     */     //   181: astore #8
/*     */     //   183: aload_0
/*     */     //   184: aconst_null
/*     */     //   185: putfield B : Lme/konsolas/aac/fr;
/*     */     //   188: aload_0
/*     */     //   189: aload #7
/*     */     //   191: ifnonnull -> 238
/*     */     //   194: getfield g : Ljava/util/concurrent/ScheduledFuture;
/*     */     //   197: ifnull -> 237
/*     */     //   200: goto -> 213
/*     */     //   203: ldc2_w -4549131292087159527
/*     */     //   206: lload_3
/*     */     //   207: <illegal opcode> w : (Ljava/lang/Exception;JJ)Ljava/lang/Exception;
/*     */     //   212: athrow
/*     */     //   213: aload_0
/*     */     //   214: getfield g : Ljava/util/concurrent/ScheduledFuture;
/*     */     //   217: iconst_0
/*     */     //   218: invokeinterface cancel : (Z)Z
/*     */     //   223: pop
/*     */     //   224: goto -> 237
/*     */     //   227: ldc2_w -4549131292087159527
/*     */     //   230: lload_3
/*     */     //   231: <illegal opcode> w : (Ljava/lang/Exception;JJ)Ljava/lang/Exception;
/*     */     //   236: athrow
/*     */     //   237: aload_0
/*     */     //   238: getfield x : Ljava/util/concurrent/ScheduledExecutorService;
/*     */     //   241: invokeinterface shutdown : ()V
/*     */     //   246: aload #9
/*     */     //   248: monitorexit
/*     */     //   249: goto -> 260
/*     */     //   252: astore #10
/*     */     //   254: aload #9
/*     */     //   256: monitorexit
/*     */     //   257: aload #10
/*     */     //   259: athrow
/*     */     //   260: aload_0
/*     */     //   261: getfield l : Lme/konsolas/aac/jn;
/*     */     //   264: aload_0
/*     */     //   265: iload_1
/*     */     //   266: aload_2
/*     */     //   267: invokevirtual b : (Lme/konsolas/aac/k3;ILjava/lang/String;)V
/*     */     //   270: lload_3
/*     */     //   271: lconst_0
/*     */     //   272: lcmp
/*     */     //   273: ifle -> 331
/*     */     //   276: aload #8
/*     */     //   278: aload #7
/*     */     //   280: ifnonnull -> 324
/*     */     //   283: ifnull -> 322
/*     */     //   286: goto -> 299
/*     */     //   289: ldc2_w -4549131292087159527
/*     */     //   292: lload_3
/*     */     //   293: <illegal opcode> w : (Ljava/lang/Exception;JJ)Ljava/lang/Exception;
/*     */     //   298: athrow
/*     */     //   299: aload_0
/*     */     //   300: getfield l : Lme/konsolas/aac/jn;
/*     */     //   303: aload_0
/*     */     //   304: iload_1
/*     */     //   305: aload_2
/*     */     //   306: invokevirtual a : (Lme/konsolas/aac/k3;ILjava/lang/String;)V
/*     */     //   309: goto -> 322
/*     */     //   312: ldc2_w -4549131292087159527
/*     */     //   315: lload_3
/*     */     //   316: <illegal opcode> w : (Ljava/lang/Exception;JJ)Ljava/lang/Exception;
/*     */     //   321: athrow
/*     */     //   322: aload #8
/*     */     //   324: lload #5
/*     */     //   326: dup2_x1
/*     */     //   327: pop2
/*     */     //   328: invokestatic a : (JLjava/io/Closeable;)V
/*     */     //   331: goto -> 346
/*     */     //   334: astore #11
/*     */     //   336: lload #5
/*     */     //   338: aload #8
/*     */     //   340: invokestatic a : (JLjava/io/Closeable;)V
/*     */     //   343: aload #11
/*     */     //   345: athrow
/*     */     //   346: return
/*     */     // Line number table:
/*     */     //   Java source line number -> byte code offset
/*     */     //   #20	-> 20
/*     */     //   #3	-> 43
/*     */     //   #19	-> 46
/*     */     //   #122	-> 51
/*     */     //   #95	-> 101
/*     */     //   #157	-> 106
/*     */     //   #34	-> 111
/*     */     //   #151	-> 177
/*     */     //   #119	-> 183
/*     */     //   #141	-> 188
/*     */     //   #123	-> 237
/*     */     //   #128	-> 246
/*     */     //   #1	-> 260
/*     */     //   #177	-> 270
/*     */     //   #209	-> 299
/*     */     //   #207	-> 322
/*     */     //   #198	-> 331
/*     */     //   #47	-> 334
/*     */     //   #116	-> 346
/*     */     // Exception table:
/*     */     //   from	to	target	type
/*     */     //   20	33	33	java/lang/IllegalArgumentException
/*     */     //   51	249	252	finally
/*     */     //   66	91	91	java/lang/IllegalArgumentException
/*     */     //   115	123	126	java/lang/IllegalArgumentException
/*     */     //   120	142	145	java/lang/IllegalArgumentException
/*     */     //   136	161	164	java/lang/IllegalArgumentException
/*     */     //   183	200	203	java/lang/IllegalArgumentException
/*     */     //   194	224	227	java/lang/IllegalArgumentException
/*     */     //   252	257	252	finally
/*     */     //   260	286	289	java/lang/IllegalArgumentException
/*     */     //   260	322	334	finally
/*     */     //   283	309	312	java/lang/IllegalArgumentException
/*     */     //   334	336	334	finally
/*     */   }
/*     */   
/*     */   synchronized int c() {
/*  23 */     return this.q;
/*     */   }
/*     */ 
/*     */ 
/*     */   
/*     */   public void a(String paramString, long paramLong, fr paramfr) {
/*     */     // Byte code:
/*     */     //   0: getstatic me/konsolas/aac/dw.C : J
/*     */     //   3: lload_2
/*     */     //   4: lxor
/*     */     //   5: lstore_2
/*     */     //   6: lload_2
/*     */     //   7: dup2
/*     */     //   8: ldc2_w 35723162855529
/*     */     //   11: lxor
/*     */     //   12: lstore #5
/*     */     //   14: dup2
/*     */     //   15: ldc2_w 29973247370863
/*     */     //   18: lxor
/*     */     //   19: dup2
/*     */     //   20: bipush #48
/*     */     //   22: lushr
/*     */     //   23: l2i
/*     */     //   24: istore #7
/*     */     //   26: dup2
/*     */     //   27: bipush #16
/*     */     //   29: lshl
/*     */     //   30: bipush #32
/*     */     //   32: lushr
/*     */     //   33: l2i
/*     */     //   34: istore #8
/*     */     //   36: dup2
/*     */     //   37: bipush #48
/*     */     //   39: lshl
/*     */     //   40: bipush #48
/*     */     //   42: lushr
/*     */     //   43: l2i
/*     */     //   44: istore #9
/*     */     //   46: pop2
/*     */     //   47: dup2
/*     */     //   48: ldc2_w 36936404289056
/*     */     //   51: lxor
/*     */     //   52: lstore #10
/*     */     //   54: pop2
/*     */     //   55: ldc2_w -8217904835485943396
/*     */     //   58: lload_2
/*     */     //   59: <illegal opcode> w : (JJ)[I
/*     */     //   64: aload_0
/*     */     //   65: dup
/*     */     //   66: astore #13
/*     */     //   68: monitorenter
/*     */     //   69: astore #12
/*     */     //   71: aload_0
/*     */     //   72: aload #4
/*     */     //   74: putfield B : Lme/konsolas/aac/fr;
/*     */     //   77: aload_0
/*     */     //   78: new me/konsolas/aac/bB
/*     */     //   81: dup
/*     */     //   82: aload #4
/*     */     //   84: getfield c : Z
/*     */     //   87: lload #5
/*     */     //   89: dup2_x1
/*     */     //   90: pop2
/*     */     //   91: aload #4
/*     */     //   93: getfield b : Lme/konsolas/aac/gi;
/*     */     //   96: aload_0
/*     */     //   97: getfield j : Ljava/util/Random;
/*     */     //   100: invokespecial <init> : (JZLme/konsolas/aac/gi;Ljava/util/Random;)V
/*     */     //   103: putfield o : Lme/konsolas/aac/bB;
/*     */     //   106: aload_0
/*     */     //   107: new java/util/concurrent/ScheduledThreadPoolExecutor
/*     */     //   110: dup
/*     */     //   111: iconst_1
/*     */     //   112: aload_1
/*     */     //   113: iconst_0
/*     */     //   114: invokestatic a : (Ljava/lang/String;Z)Ljava/util/concurrent/ThreadFactory;
/*     */     //   117: invokespecial <init> : (ILjava/util/concurrent/ThreadFactory;)V
/*     */     //   120: putfield x : Ljava/util/concurrent/ScheduledExecutorService;
/*     */     //   123: aload_0
/*     */     //   124: getfield y : J
/*     */     //   127: lconst_0
/*     */     //   128: lcmp
/*     */     //   129: aload #12
/*     */     //   131: ifnonnull -> 223
/*     */     //   134: ifeq -> 192
/*     */     //   137: goto -> 150
/*     */     //   140: ldc2_w -8233982396866905988
/*     */     //   143: lload_2
/*     */     //   144: <illegal opcode> w : (Ljava/lang/Exception;JJ)Ljava/lang/Exception;
/*     */     //   149: athrow
/*     */     //   150: aload_0
/*     */     //   151: getfield x : Ljava/util/concurrent/ScheduledExecutorService;
/*     */     //   154: new me/konsolas/aac/dc
/*     */     //   157: dup
/*     */     //   158: aload_0
/*     */     //   159: invokespecial <init> : (Lme/konsolas/aac/dw;)V
/*     */     //   162: aload_0
/*     */     //   163: getfield y : J
/*     */     //   166: aload_0
/*     */     //   167: getfield y : J
/*     */     //   170: getstatic java/util/concurrent/TimeUnit.MILLISECONDS : Ljava/util/concurrent/TimeUnit;
/*     */     //   173: invokeinterface scheduleAtFixedRate : (Ljava/lang/Runnable;JJLjava/util/concurrent/TimeUnit;)Ljava/util/concurrent/ScheduledFuture;
/*     */     //   178: pop
/*     */     //   179: goto -> 192
/*     */     //   182: ldc2_w -8233982396866905988
/*     */     //   185: lload_2
/*     */     //   186: <illegal opcode> w : (Ljava/lang/Exception;JJ)Ljava/lang/Exception;
/*     */     //   191: athrow
/*     */     //   192: lload_2
/*     */     //   193: lconst_0
/*     */     //   194: lcmp
/*     */     //   195: ifle -> 253
/*     */     //   198: aload_0
/*     */     //   199: aload #12
/*     */     //   201: ifnonnull -> 252
/*     */     //   204: getfield b : Ljava/util/ArrayDeque;
/*     */     //   207: invokevirtual isEmpty : ()Z
/*     */     //   210: goto -> 223
/*     */     //   213: ldc2_w -8233982396866905988
/*     */     //   216: lload_2
/*     */     //   217: <illegal opcode> w : (Ljava/lang/Exception;JJ)Ljava/lang/Exception;
/*     */     //   222: athrow
/*     */     //   223: ifne -> 250
/*     */     //   226: aload_0
/*     */     //   227: iload #7
/*     */     //   229: i2s
/*     */     //   230: iload #8
/*     */     //   232: iload #9
/*     */     //   234: invokespecial b : (SII)V
/*     */     //   237: goto -> 250
/*     */     //   240: ldc2_w -8233982396866905988
/*     */     //   243: lload_2
/*     */     //   244: <illegal opcode> w : (Ljava/lang/Exception;JJ)Ljava/lang/Exception;
/*     */     //   249: athrow
/*     */     //   250: aload #13
/*     */     //   252: monitorexit
/*     */     //   253: goto -> 264
/*     */     //   256: astore #14
/*     */     //   258: aload #13
/*     */     //   260: monitorexit
/*     */     //   261: aload #14
/*     */     //   263: athrow
/*     */     //   264: aload_0
/*     */     //   265: new me/konsolas/aac/c_
/*     */     //   268: dup
/*     */     //   269: aload #4
/*     */     //   271: getfield c : Z
/*     */     //   274: aload #4
/*     */     //   276: getfield a : Lme/konsolas/aac/bX;
/*     */     //   279: lload #10
/*     */     //   281: dup2_x1
/*     */     //   282: pop2
/*     */     //   283: aload_0
/*     */     //   284: invokespecial <init> : (ZJLme/konsolas/aac/bX;Lme/konsolas/aac/mQ;)V
/*     */     //   287: putfield m : Lme/konsolas/aac/c_;
/*     */     //   290: return
/*     */     // Line number table:
/*     */     //   Java source line number -> byte code offset
/*     */     //   #27	-> 64
/*     */     //   #31	-> 71
/*     */     //   #106	-> 77
/*     */     //   #210	-> 106
/*     */     //   #162	-> 123
/*     */     //   #147	-> 150
/*     */     //   #161	-> 192
/*     */     //   #203	-> 226
/*     */     //   #167	-> 250
/*     */     //   #105	-> 264
/*     */     //   #192	-> 290
/*     */     // Exception table:
/*     */     //   from	to	target	type
/*     */     //   71	137	140	java/io/IOException
/*     */     //   71	253	256	finally
/*     */     //   134	179	182	java/io/IOException
/*     */     //   192	210	213	java/io/IOException
/*     */     //   223	237	240	java/io/IOException
/*     */     //   256	261	256	finally
/*     */   }
/*     */ 
/*     */ 
/*     */   
/*     */   void d(short paramShort, int paramInt, char paramChar) {
/*     */     // Byte code:
/*     */     //   0: iload_1
/*     */     //   1: i2l
/*     */     //   2: bipush #48
/*     */     //   4: lshl
/*     */     //   5: iload_2
/*     */     //   6: i2l
/*     */     //   7: bipush #32
/*     */     //   9: lshl
/*     */     //   10: bipush #16
/*     */     //   12: lushr
/*     */     //   13: lor
/*     */     //   14: iload_3
/*     */     //   15: i2l
/*     */     //   16: bipush #48
/*     */     //   18: lshl
/*     */     //   19: bipush #48
/*     */     //   21: lushr
/*     */     //   22: lor
/*     */     //   23: getstatic me/konsolas/aac/dw.C : J
/*     */     //   26: lxor
/*     */     //   27: lstore #4
/*     */     //   29: lload #4
/*     */     //   31: dup2
/*     */     //   32: ldc2_w 91835383732086
/*     */     //   35: lxor
/*     */     //   36: dup2
/*     */     //   37: bipush #16
/*     */     //   39: lushr
/*     */     //   40: lstore #6
/*     */     //   42: dup2
/*     */     //   43: bipush #48
/*     */     //   45: lshl
/*     */     //   46: bipush #48
/*     */     //   48: lushr
/*     */     //   49: l2i
/*     */     //   50: istore #8
/*     */     //   52: pop2
/*     */     //   53: dup2
/*     */     //   54: ldc2_w 108213474182459
/*     */     //   57: lxor
/*     */     //   58: lstore #9
/*     */     //   60: pop2
/*     */     //   61: ldc2_w 315848371522678794
/*     */     //   64: lload #4
/*     */     //   66: <illegal opcode> w : (JJ)[I
/*     */     //   71: aload_0
/*     */     //   72: dup
/*     */     //   73: astore #14
/*     */     //   75: monitorenter
/*     */     //   76: astore #11
/*     */     //   78: aload_0
/*     */     //   79: aload #11
/*     */     //   81: ifnonnull -> 109
/*     */     //   84: getfield A : Z
/*     */     //   87: ifeq -> 108
/*     */     //   90: goto -> 104
/*     */     //   93: ldc2_w 300960378877522410
/*     */     //   96: lload #4
/*     */     //   98: <illegal opcode> w : (Ljava/lang/Exception;JJ)Ljava/lang/Exception;
/*     */     //   103: athrow
/*     */     //   104: aload #14
/*     */     //   106: monitorexit
/*     */     //   107: return
/*     */     //   108: aload_0
/*     */     //   109: getfield o : Lme/konsolas/aac/bB;
/*     */     //   112: astore #12
/*     */     //   114: aload_0
/*     */     //   115: getfield n : Z
/*     */     //   118: aload #11
/*     */     //   120: ifnonnull -> 158
/*     */     //   123: ifeq -> 161
/*     */     //   126: goto -> 140
/*     */     //   129: ldc2_w 300960378877522410
/*     */     //   132: lload #4
/*     */     //   134: <illegal opcode> w : (Ljava/lang/Exception;JJ)Ljava/lang/Exception;
/*     */     //   139: athrow
/*     */     //   140: aload_0
/*     */     //   141: getfield q : I
/*     */     //   144: goto -> 158
/*     */     //   147: ldc2_w 300960378877522410
/*     */     //   150: lload #4
/*     */     //   152: <illegal opcode> w : (Ljava/lang/Exception;JJ)Ljava/lang/Exception;
/*     */     //   157: athrow
/*     */     //   158: goto -> 162
/*     */     //   161: iconst_m1
/*     */     //   162: istore #13
/*     */     //   164: aload_0
/*     */     //   165: dup
/*     */     //   166: getfield q : I
/*     */     //   169: iconst_1
/*     */     //   170: iadd
/*     */     //   171: putfield q : I
/*     */     //   174: aload_0
/*     */     //   175: iconst_1
/*     */     //   176: putfield n : Z
/*     */     //   179: aload #14
/*     */     //   181: monitorexit
/*     */     //   182: goto -> 193
/*     */     //   185: astore #15
/*     */     //   187: aload #14
/*     */     //   189: monitorexit
/*     */     //   190: aload #15
/*     */     //   192: athrow
/*     */     //   193: iload_3
/*     */     //   194: ifle -> 317
/*     */     //   197: iload #13
/*     */     //   199: iconst_m1
/*     */     //   200: if_icmpeq -> 307
/*     */     //   203: aload_0
/*     */     //   204: new java/net/SocketTimeoutException
/*     */     //   207: dup
/*     */     //   208: new java/lang/StringBuilder
/*     */     //   211: dup
/*     */     //   212: invokespecial <init> : ()V
/*     */     //   215: sipush #32279
/*     */     //   218: ldc2_w 1744827215041320870
/*     */     //   221: lload #4
/*     */     //   223: lxor
/*     */     //   224: <illegal opcode> o : (IJ)Ljava/lang/String;
/*     */     //   229: invokevirtual append : (Ljava/lang/String;)Ljava/lang/StringBuilder;
/*     */     //   232: aload_0
/*     */     //   233: getfield y : J
/*     */     //   236: invokevirtual append : (J)Ljava/lang/StringBuilder;
/*     */     //   239: sipush #7371
/*     */     //   242: ldc2_w 5816608182288987499
/*     */     //   245: lload #4
/*     */     //   247: lxor
/*     */     //   248: <illegal opcode> o : (IJ)Ljava/lang/String;
/*     */     //   253: invokevirtual append : (Ljava/lang/String;)Ljava/lang/StringBuilder;
/*     */     //   256: iload #13
/*     */     //   258: iconst_1
/*     */     //   259: isub
/*     */     //   260: invokevirtual append : (I)Ljava/lang/StringBuilder;
/*     */     //   263: sipush #4978
/*     */     //   266: ldc2_w 8981852310585424586
/*     */     //   269: lload #4
/*     */     //   271: lxor
/*     */     //   272: <illegal opcode> o : (IJ)Ljava/lang/String;
/*     */     //   277: invokevirtual append : (Ljava/lang/String;)Ljava/lang/StringBuilder;
/*     */     //   280: invokevirtual toString : ()Ljava/lang/String;
/*     */     //   283: invokespecial <init> : (Ljava/lang/String;)V
/*     */     //   286: lload #6
/*     */     //   288: aconst_null
/*     */     //   289: iload #8
/*     */     //   291: i2s
/*     */     //   292: invokevirtual a : (Ljava/lang/Exception;JLme/konsolas/aac/H;S)V
/*     */     //   295: return
/*     */     //   296: ldc2_w 300960378877522410
/*     */     //   299: lload #4
/*     */     //   301: <illegal opcode> w : (Ljava/lang/Exception;JJ)Ljava/lang/Exception;
/*     */     //   306: athrow
/*     */     //   307: aload #12
/*     */     //   309: lload #9
/*     */     //   311: getstatic me/konsolas/aac/gZ.a : Lme/konsolas/aac/gZ;
/*     */     //   314: invokevirtual a : (JLme/konsolas/aac/gZ;)V
/*     */     //   317: goto -> 334
/*     */     //   320: astore #14
/*     */     //   322: aload_0
/*     */     //   323: aload #14
/*     */     //   325: lload #6
/*     */     //   327: aconst_null
/*     */     //   328: iload #8
/*     */     //   330: i2s
/*     */     //   331: invokevirtual a : (Ljava/lang/Exception;JLme/konsolas/aac/H;S)V
/*     */     //   334: return
/*     */     // Line number table:
/*     */     //   Java source line number -> byte code offset
/*     */     //   #28	-> 71
/*     */     //   #49	-> 78
/*     */     //   #67	-> 108
/*     */     //   #135	-> 114
/*     */     //   #146	-> 164
/*     */     //   #113	-> 174
/*     */     //   #115	-> 179
/*     */     //   #48	-> 193
/*     */     //   #125	-> 203
/*     */     //   #15	-> 295
/*     */     //   #12	-> 307
/*     */     //   #156	-> 317
/*     */     //   #85	-> 320
/*     */     //   #63	-> 322
/*     */     //   #168	-> 334
/*     */     // Exception table:
/*     */     //   from	to	target	type
/*     */     //   78	90	93	java/io/IOException
/*     */     //   78	107	185	finally
/*     */     //   108	182	185	finally
/*     */     //   114	126	129	java/io/IOException
/*     */     //   123	144	147	java/io/IOException
/*     */     //   185	190	185	finally
/*     */     //   193	296	296	java/io/IOException
/*     */     //   307	317	320	java/io/IOException
/*     */   }
/*     */ 
/*     */ 
/*     */   
/*     */   public void c(gZ paramgZ) {
/*  41 */     this.l.a(this, paramgZ);
/*     */   } synchronized int a() {
/*  43 */     return this.r;
/*     */   }
/*     */ 
/*     */ 
/*     */ 
/*     */ 
/*     */ 
/*     */ 
/*     */ 
/*     */ 
/*     */ 
/*     */ 
/*     */ 
/*     */ 
/*     */ 
/*     */ 
/*     */ 
/*     */ 
/*     */ 
/*     */ 
/*     */ 
/*     */ 
/*     */ 
/*     */   
/*     */   boolean a(long paramLong) {
/*     */     // Byte code:
/*     */     //   0: getstatic me/konsolas/aac/dw.C : J
/*     */     //   3: lload_1
/*     */     //   4: lxor
/*     */     //   5: lstore_1
/*     */     //   6: lload_1
/*     */     //   7: dup2
/*     */     //   8: ldc2_w 114077354518842
/*     */     //   11: lxor
/*     */     //   12: lstore_3
/*     */     //   13: dup2
/*     */     //   14: ldc2_w 67438293728792
/*     */     //   17: lxor
/*     */     //   18: dup2
/*     */     //   19: bipush #32
/*     */     //   21: lushr
/*     */     //   22: l2i
/*     */     //   23: istore #5
/*     */     //   25: dup2
/*     */     //   26: bipush #32
/*     */     //   28: lshl
/*     */     //   29: bipush #56
/*     */     //   31: lushr
/*     */     //   32: l2i
/*     */     //   33: istore #6
/*     */     //   35: dup2
/*     */     //   36: bipush #40
/*     */     //   38: lshl
/*     */     //   39: bipush #40
/*     */     //   41: lushr
/*     */     //   42: l2i
/*     */     //   43: istore #7
/*     */     //   45: pop2
/*     */     //   46: dup2
/*     */     //   47: ldc2_w 63174026334297
/*     */     //   50: lxor
/*     */     //   51: lstore #8
/*     */     //   53: dup2
/*     */     //   54: ldc2_w 93954412271145
/*     */     //   57: lxor
/*     */     //   58: lstore #10
/*     */     //   60: dup2
/*     */     //   61: ldc2_w 77847344229592
/*     */     //   64: lxor
/*     */     //   65: lstore #12
/*     */     //   67: dup2
/*     */     //   68: ldc2_w 90834968931477
/*     */     //   71: lxor
/*     */     //   72: dup2
/*     */     //   73: bipush #32
/*     */     //   75: lushr
/*     */     //   76: l2i
/*     */     //   77: istore #14
/*     */     //   79: dup2
/*     */     //   80: bipush #32
/*     */     //   82: lshl
/*     */     //   83: bipush #40
/*     */     //   85: lushr
/*     */     //   86: l2i
/*     */     //   87: istore #15
/*     */     //   89: dup2
/*     */     //   90: bipush #56
/*     */     //   92: lshl
/*     */     //   93: bipush #56
/*     */     //   95: lushr
/*     */     //   96: l2i
/*     */     //   97: istore #16
/*     */     //   99: pop2
/*     */     //   100: pop2
/*     */     //   101: ldc2_w -3965959351000138594
/*     */     //   104: lload_1
/*     */     //   105: <illegal opcode> w : (JJ)[I
/*     */     //   110: aconst_null
/*     */     //   111: astore #20
/*     */     //   113: iconst_m1
/*     */     //   114: istore #21
/*     */     //   116: aconst_null
/*     */     //   117: astore #22
/*     */     //   119: aconst_null
/*     */     //   120: astore #23
/*     */     //   122: aload_0
/*     */     //   123: dup
/*     */     //   124: astore #24
/*     */     //   126: monitorenter
/*     */     //   127: astore #17
/*     */     //   129: aload_0
/*     */     //   130: aload #17
/*     */     //   132: ifnonnull -> 160
/*     */     //   135: getfield A : Z
/*     */     //   138: ifeq -> 159
/*     */     //   141: goto -> 154
/*     */     //   144: ldc2_w -3983095983168291458
/*     */     //   147: lload_1
/*     */     //   148: <illegal opcode> w : (Ljava/lang/Exception;JJ)Ljava/lang/Exception;
/*     */     //   153: athrow
/*     */     //   154: iconst_0
/*     */     //   155: aload #24
/*     */     //   157: monitorexit
/*     */     //   158: ireturn
/*     */     //   159: aload_0
/*     */     //   160: getfield o : Lme/konsolas/aac/bB;
/*     */     //   163: astore #18
/*     */     //   165: aload_0
/*     */     //   166: getfield i : Ljava/util/ArrayDeque;
/*     */     //   169: invokevirtual poll : ()Ljava/lang/Object;
/*     */     //   172: checkcast me/konsolas/aac/gZ
/*     */     //   175: astore #19
/*     */     //   177: aload #19
/*     */     //   179: aload #17
/*     */     //   181: ifnonnull -> 220
/*     */     //   184: ifnonnull -> 352
/*     */     //   187: goto -> 200
/*     */     //   190: ldc2_w -3983095983168291458
/*     */     //   193: lload_1
/*     */     //   194: <illegal opcode> w : (Ljava/lang/Exception;JJ)Ljava/lang/Exception;
/*     */     //   199: athrow
/*     */     //   200: aload_0
/*     */     //   201: getfield b : Ljava/util/ArrayDeque;
/*     */     //   204: invokevirtual poll : ()Ljava/lang/Object;
/*     */     //   207: goto -> 220
/*     */     //   210: ldc2_w -3983095983168291458
/*     */     //   213: lload_1
/*     */     //   214: <illegal opcode> w : (Ljava/lang/Exception;JJ)Ljava/lang/Exception;
/*     */     //   219: athrow
/*     */     //   220: astore #20
/*     */     //   222: aload #20
/*     */     //   224: aload #17
/*     */     //   226: ifnonnull -> 344
/*     */     //   229: instanceof me/konsolas/aac/kv
/*     */     //   232: ifeq -> 342
/*     */     //   235: goto -> 248
/*     */     //   238: ldc2_w -3983095983168291458
/*     */     //   241: lload_1
/*     */     //   242: <illegal opcode> w : (Ljava/lang/Exception;JJ)Ljava/lang/Exception;
/*     */     //   247: athrow
/*     */     //   248: aload_0
/*     */     //   249: getfield e : I
/*     */     //   252: istore #21
/*     */     //   254: aload_0
/*     */     //   255: getfield z : Ljava/lang/String;
/*     */     //   258: astore #22
/*     */     //   260: aload #17
/*     */     //   262: ifnonnull -> 339
/*     */     //   265: iload #21
/*     */     //   267: iconst_m1
/*     */     //   268: if_icmpeq -> 307
/*     */     //   271: goto -> 284
/*     */     //   274: ldc2_w -3983095983168291458
/*     */     //   277: lload_1
/*     */     //   278: <illegal opcode> w : (Ljava/lang/Exception;JJ)Ljava/lang/Exception;
/*     */     //   283: athrow
/*     */     //   284: aload_0
/*     */     //   285: getfield B : Lme/konsolas/aac/fr;
/*     */     //   288: astore #23
/*     */     //   290: aload_0
/*     */     //   291: aconst_null
/*     */     //   292: putfield B : Lme/konsolas/aac/fr;
/*     */     //   295: aload_0
/*     */     //   296: getfield x : Ljava/util/concurrent/ScheduledExecutorService;
/*     */     //   299: invokeinterface shutdown : ()V
/*     */     //   304: goto -> 352
/*     */     //   307: aload_0
/*     */     //   308: aload_0
/*     */     //   309: getfield x : Ljava/util/concurrent/ScheduledExecutorService;
/*     */     //   312: new me/konsolas/aac/hg
/*     */     //   315: dup
/*     */     //   316: aload_0
/*     */     //   317: invokespecial <init> : (Lme/konsolas/aac/dw;)V
/*     */     //   320: aload #20
/*     */     //   322: checkcast me/konsolas/aac/kv
/*     */     //   325: getfield c : J
/*     */     //   328: getstatic java/util/concurrent/TimeUnit.MILLISECONDS : Ljava/util/concurrent/TimeUnit;
/*     */     //   331: invokeinterface schedule : (Ljava/lang/Runnable;JLjava/util/concurrent/TimeUnit;)Ljava/util/concurrent/ScheduledFuture;
/*     */     //   336: putfield g : Ljava/util/concurrent/ScheduledFuture;
/*     */     //   339: goto -> 352
/*     */     //   342: aload #20
/*     */     //   344: ifnonnull -> 352
/*     */     //   347: iconst_0
/*     */     //   348: aload #24
/*     */     //   350: monitorexit
/*     */     //   351: ireturn
/*     */     //   352: aload #24
/*     */     //   354: monitorexit
/*     */     //   355: goto -> 366
/*     */     //   358: astore #25
/*     */     //   360: aload #24
/*     */     //   362: monitorexit
/*     */     //   363: aload #25
/*     */     //   365: athrow
/*     */     //   366: aload #19
/*     */     //   368: lload_1
/*     */     //   369: lconst_0
/*     */     //   370: lcmp
/*     */     //   371: ifle -> 442
/*     */     //   374: aload #17
/*     */     //   376: ifnonnull -> 442
/*     */     //   379: ifnull -> 427
/*     */     //   382: goto -> 395
/*     */     //   385: ldc2_w -3983095983168291458
/*     */     //   388: lload_1
/*     */     //   389: <illegal opcode> w : (Ljava/lang/Exception;JJ)Ljava/lang/Exception;
/*     */     //   394: athrow
/*     */     //   395: aload #18
/*     */     //   397: aload #19
/*     */     //   399: iload #5
/*     */     //   401: iload #6
/*     */     //   403: i2b
/*     */     //   404: iload #7
/*     */     //   406: invokevirtual b : (Lme/konsolas/aac/gZ;IBI)V
/*     */     //   409: aload #17
/*     */     //   411: ifnull -> 667
/*     */     //   414: goto -> 427
/*     */     //   417: ldc2_w -3983095983168291458
/*     */     //   420: lload_1
/*     */     //   421: <illegal opcode> w : (Ljava/lang/Exception;JJ)Ljava/lang/Exception;
/*     */     //   426: athrow
/*     */     //   427: aload #20
/*     */     //   429: goto -> 442
/*     */     //   432: ldc2_w -3983095983168291458
/*     */     //   435: lload_1
/*     */     //   436: <illegal opcode> w : (Ljava/lang/Exception;JJ)Ljava/lang/Exception;
/*     */     //   441: athrow
/*     */     //   442: instanceof me/konsolas/aac/hc
/*     */     //   445: aload #17
/*     */     //   447: ifnonnull -> 592
/*     */     //   450: ifeq -> 569
/*     */     //   453: goto -> 466
/*     */     //   456: ldc2_w -3983095983168291458
/*     */     //   459: lload_1
/*     */     //   460: <illegal opcode> w : (Ljava/lang/Exception;JJ)Ljava/lang/Exception;
/*     */     //   465: athrow
/*     */     //   466: aload #20
/*     */     //   468: checkcast me/konsolas/aac/hc
/*     */     //   471: getfield a : Lme/konsolas/aac/gZ;
/*     */     //   474: astore #24
/*     */     //   476: aload #18
/*     */     //   478: aload #20
/*     */     //   480: checkcast me/konsolas/aac/hc
/*     */     //   483: getfield b : I
/*     */     //   486: aload #24
/*     */     //   488: invokevirtual a : ()I
/*     */     //   491: i2l
/*     */     //   492: iload #14
/*     */     //   494: dup_x2
/*     */     //   495: pop
/*     */     //   496: iload #15
/*     */     //   498: dup_x2
/*     */     //   499: pop
/*     */     //   500: iload #16
/*     */     //   502: i2b
/*     */     //   503: invokevirtual a : (IIIJB)Lme/konsolas/aac/gp;
/*     */     //   506: lload #8
/*     */     //   508: invokestatic a : (Lme/konsolas/aac/gp;J)Lme/konsolas/aac/gi;
/*     */     //   511: astore #25
/*     */     //   513: aload #25
/*     */     //   515: aload #24
/*     */     //   517: lload #10
/*     */     //   519: invokeinterface a : (Lme/konsolas/aac/gZ;J)Lme/konsolas/aac/gi;
/*     */     //   524: pop
/*     */     //   525: aload #25
/*     */     //   527: invokeinterface close : ()V
/*     */     //   532: aload_0
/*     */     //   533: dup
/*     */     //   534: astore #26
/*     */     //   536: monitorenter
/*     */     //   537: aload_0
/*     */     //   538: dup
/*     */     //   539: getfield w : J
/*     */     //   542: aload #24
/*     */     //   544: invokevirtual a : ()I
/*     */     //   547: i2l
/*     */     //   548: lsub
/*     */     //   549: putfield w : J
/*     */     //   552: aload #26
/*     */     //   554: monitorexit
/*     */     //   555: goto -> 566
/*     */     //   558: astore #27
/*     */     //   560: aload #26
/*     */     //   562: monitorexit
/*     */     //   563: aload #27
/*     */     //   565: athrow
/*     */     //   566: goto -> 667
/*     */     //   569: aload #20
/*     */     //   571: aload #17
/*     */     //   573: ifnonnull -> 597
/*     */     //   576: instanceof me/konsolas/aac/kv
/*     */     //   579: goto -> 592
/*     */     //   582: ldc2_w -3983095983168291458
/*     */     //   585: lload_1
/*     */     //   586: <illegal opcode> w : (Ljava/lang/Exception;JJ)Ljava/lang/Exception;
/*     */     //   591: athrow
/*     */     //   592: ifeq -> 659
/*     */     //   595: aload #20
/*     */     //   597: checkcast me/konsolas/aac/kv
/*     */     //   600: astore #24
/*     */     //   602: aload #18
/*     */     //   604: aload #24
/*     */     //   606: getfield b : I
/*     */     //   609: lload_3
/*     */     //   610: dup2_x1
/*     */     //   611: pop2
/*     */     //   612: aload #24
/*     */     //   614: getfield a : Lme/konsolas/aac/gZ;
/*     */     //   617: invokevirtual a : (JILme/konsolas/aac/gZ;)V
/*     */     //   620: lload_1
/*     */     //   621: lconst_0
/*     */     //   622: lcmp
/*     */     //   623: iflt -> 643
/*     */     //   626: aload #23
/*     */     //   628: ifnull -> 656
/*     */     //   631: aload_0
/*     */     //   632: getfield l : Lme/konsolas/aac/jn;
/*     */     //   635: aload_0
/*     */     //   636: iload #21
/*     */     //   638: aload #22
/*     */     //   640: invokevirtual a : (Lme/konsolas/aac/k3;ILjava/lang/String;)V
/*     */     //   643: goto -> 656
/*     */     //   646: ldc2_w -3983095983168291458
/*     */     //   649: lload_1
/*     */     //   650: <illegal opcode> w : (Ljava/lang/Exception;JJ)Ljava/lang/Exception;
/*     */     //   655: athrow
/*     */     //   656: goto -> 667
/*     */     //   659: new java/lang/AssertionError
/*     */     //   662: dup
/*     */     //   663: invokespecial <init> : ()V
/*     */     //   666: athrow
/*     */     //   667: iconst_1
/*     */     //   668: istore #24
/*     */     //   670: lload #12
/*     */     //   672: aload #23
/*     */     //   674: invokestatic a : (JLjava/io/Closeable;)V
/*     */     //   677: iload #24
/*     */     //   679: ireturn
/*     */     //   680: astore #28
/*     */     //   682: lload #12
/*     */     //   684: aload #23
/*     */     //   686: invokestatic a : (JLjava/io/Closeable;)V
/*     */     //   689: aload #28
/*     */     //   691: athrow
/*     */     // Line number table:
/*     */     //   Java source line number -> byte code offset
/*     */     //   #91	-> 110
/*     */     //   #178	-> 113
/*     */     //   #211	-> 116
/*     */     //   #39	-> 119
/*     */     //   #206	-> 122
/*     */     //   #188	-> 129
/*     */     //   #160	-> 154
/*     */     //   #81	-> 159
/*     */     //   #11	-> 165
/*     */     //   #175	-> 177
/*     */     //   #103	-> 200
/*     */     //   #32	-> 222
/*     */     //   #118	-> 248
/*     */     //   #62	-> 254
/*     */     //   #139	-> 260
/*     */     //   #88	-> 284
/*     */     //   #208	-> 290
/*     */     //   #120	-> 295
/*     */     //   #138	-> 307
/*     */     //   #114	-> 342
/*     */     //   #71	-> 347
/*     */     //   #150	-> 352
/*     */     //   #37	-> 366
/*     */     //   #194	-> 395
/*     */     //   #57	-> 427
/*     */     //   #65	-> 466
/*     */     //   #78	-> 476
/*     */     //   #17	-> 488
/*     */     //   #44	-> 500
/*     */     //   #76	-> 513
/*     */     //   #83	-> 525
/*     */     //   #66	-> 532
/*     */     //   #24	-> 537
/*     */     //   #87	-> 552
/*     */     //   #132	-> 566
/*     */     //   #191	-> 595
/*     */     //   #107	-> 602
/*     */     //   #131	-> 620
/*     */     //   #73	-> 631
/*     */     //   #60	-> 656
/*     */     //   #97	-> 659
/*     */     //   #136	-> 667
/*     */     //   #154	-> 670
/*     */     //   #52	-> 677
/*     */     //   #64	-> 680
/*     */     // Exception table:
/*     */     //   from	to	target	type
/*     */     //   129	141	144	java/io/IOException
/*     */     //   129	158	358	finally
/*     */     //   159	351	358	finally
/*     */     //   177	187	190	java/io/IOException
/*     */     //   184	207	210	java/io/IOException
/*     */     //   222	235	238	java/io/IOException
/*     */     //   260	271	274	java/io/IOException
/*     */     //   352	355	358	finally
/*     */     //   358	363	358	finally
/*     */     //   366	382	385	java/io/IOException
/*     */     //   366	670	680	finally
/*     */     //   379	414	417	java/io/IOException
/*     */     //   395	429	432	java/io/IOException
/*     */     //   442	453	456	java/io/IOException
/*     */     //   537	555	558	finally
/*     */     //   558	563	558	finally
/*     */     //   569	579	582	java/io/IOException
/*     */     //   602	643	646	java/io/IOException
/*     */     //   680	682	680	finally
/*     */   }
/*     */ 
/*     */ 
/*     */ 
/*     */ 
/*     */ 
/*     */ 
/*     */ 
/*     */ 
/*     */ 
/*     */ 
/*     */ 
/*     */ 
/*     */ 
/*     */ 
/*     */ 
/*     */ 
/*     */ 
/*     */ 
/*     */ 
/*     */ 
/*     */   
/*     */   public void a(long paramLong) {
/*  92 */     long l = paramLong ^ 0x668D155A36B2L; this.t.a(l);
/*     */   }
/*     */ 
/*     */ 
/*     */ 
/*     */   
/*     */   public boolean a(char paramChar1, int paramInt1, char paramChar2, String paramString, int paramInt2) {
/*  99 */     long l1 = paramChar1 << 48L | paramChar2 << 48L >>> 16L | paramInt2 << 32L >>> 32L, l2 = l1 ^ 0x65AA4338A932L; return a(paramInt1, l2, paramString, 60000L);
/*     */   }
/*     */ 
/*     */   
/*     */   void c(long paramLong) {
/*     */     // Byte code:
/*     */     //   0: getstatic me/konsolas/aac/dw.C : J
/*     */     //   3: lload_1
/*     */     //   4: lxor
/*     */     //   5: lstore_1
/*     */     //   6: ldc2_w -7638025917884521880
/*     */     //   9: lload_1
/*     */     //   10: <illegal opcode> w : (JJ)[I
/*     */     //   15: astore_3
/*     */     //   16: aload_0
/*     */     //   17: aload_3
/*     */     //   18: ifnonnull -> 74
/*     */     //   21: getfield g : Ljava/util/concurrent/ScheduledFuture;
/*     */     //   24: ifnull -> 64
/*     */     //   27: goto -> 40
/*     */     //   30: ldc2_w -7615762546765814904
/*     */     //   33: lload_1
/*     */     //   34: <illegal opcode> w : (Ljava/lang/Exception;JJ)Ljava/lang/Exception;
/*     */     //   39: athrow
/*     */     //   40: aload_0
/*     */     //   41: getfield g : Ljava/util/concurrent/ScheduledFuture;
/*     */     //   44: iconst_0
/*     */     //   45: invokeinterface cancel : (Z)Z
/*     */     //   50: pop
/*     */     //   51: goto -> 64
/*     */     //   54: ldc2_w -7615762546765814904
/*     */     //   57: lload_1
/*     */     //   58: <illegal opcode> w : (Ljava/lang/Exception;JJ)Ljava/lang/Exception;
/*     */     //   63: athrow
/*     */     //   64: aload_0
/*     */     //   65: getfield x : Ljava/util/concurrent/ScheduledExecutorService;
/*     */     //   68: invokeinterface shutdown : ()V
/*     */     //   73: aload_0
/*     */     //   74: getfield x : Ljava/util/concurrent/ScheduledExecutorService;
/*     */     //   77: ldc2_w 10
/*     */     //   80: getstatic java/util/concurrent/TimeUnit.SECONDS : Ljava/util/concurrent/TimeUnit;
/*     */     //   83: invokeinterface awaitTermination : (JLjava/util/concurrent/TimeUnit;)Z
/*     */     //   88: pop
/*     */     //   89: return
/*     */     // Line number table:
/*     */     //   Java source line number -> byte code offset
/*     */     //   #100	-> 16
/*     */     //   #33	-> 40
/*     */     //   #50	-> 64
/*     */     //   #16	-> 73
/*     */     //   #14	-> 89
/*     */     // Exception table:
/*     */     //   from	to	target	type
/*     */     //   16	27	30	java/lang/InterruptedException
/*     */     //   21	51	54	java/lang/InterruptedException
/*     */   }
/*     */ 
/*     */   
/*     */   public s a() {
/* 109 */     return this.s;
/*     */   }
/*     */ 
/*     */ 
/*     */   
/*     */   public void a(Exception paramException, long paramLong, @Nullable H paramH, short paramShort) {
/*     */     // Byte code:
/*     */     //   0: lload_2
/*     */     //   1: bipush #16
/*     */     //   3: lshl
/*     */     //   4: iload #5
/*     */     //   6: i2l
/*     */     //   7: bipush #48
/*     */     //   9: lshl
/*     */     //   10: bipush #48
/*     */     //   12: lushr
/*     */     //   13: lor
/*     */     //   14: getstatic me/konsolas/aac/dw.C : J
/*     */     //   17: lxor
/*     */     //   18: lstore #6
/*     */     //   20: lload #6
/*     */     //   22: dup2
/*     */     //   23: ldc2_w 18210001804636
/*     */     //   26: lxor
/*     */     //   27: lstore #8
/*     */     //   29: pop2
/*     */     //   30: ldc2_w 4139444371957452058
/*     */     //   33: lload #6
/*     */     //   35: <illegal opcode> w : (JJ)[I
/*     */     //   40: aload_0
/*     */     //   41: dup
/*     */     //   42: astore #12
/*     */     //   44: monitorenter
/*     */     //   45: astore #10
/*     */     //   47: aload_0
/*     */     //   48: aload #10
/*     */     //   50: ifnonnull -> 83
/*     */     //   53: getfield A : Z
/*     */     //   56: ifeq -> 77
/*     */     //   59: goto -> 73
/*     */     //   62: ldc2_w 4124563937684032762
/*     */     //   65: lload #6
/*     */     //   67: <illegal opcode> w : (Ljava/lang/Exception;JJ)Ljava/lang/Exception;
/*     */     //   72: athrow
/*     */     //   73: aload #12
/*     */     //   75: monitorexit
/*     */     //   76: return
/*     */     //   77: aload_0
/*     */     //   78: iconst_1
/*     */     //   79: putfield A : Z
/*     */     //   82: aload_0
/*     */     //   83: getfield B : Lme/konsolas/aac/fr;
/*     */     //   86: astore #11
/*     */     //   88: aload_0
/*     */     //   89: aconst_null
/*     */     //   90: putfield B : Lme/konsolas/aac/fr;
/*     */     //   93: aload_0
/*     */     //   94: aload #10
/*     */     //   96: lload_2
/*     */     //   97: lconst_0
/*     */     //   98: lcmp
/*     */     //   99: ifle -> 153
/*     */     //   102: ifnonnull -> 151
/*     */     //   105: getfield g : Ljava/util/concurrent/ScheduledFuture;
/*     */     //   108: ifnull -> 150
/*     */     //   111: goto -> 125
/*     */     //   114: ldc2_w 4124563937684032762
/*     */     //   117: lload #6
/*     */     //   119: <illegal opcode> w : (Ljava/lang/Exception;JJ)Ljava/lang/Exception;
/*     */     //   124: athrow
/*     */     //   125: aload_0
/*     */     //   126: getfield g : Ljava/util/concurrent/ScheduledFuture;
/*     */     //   129: iconst_0
/*     */     //   130: invokeinterface cancel : (Z)Z
/*     */     //   135: pop
/*     */     //   136: goto -> 150
/*     */     //   139: ldc2_w 4124563937684032762
/*     */     //   142: lload #6
/*     */     //   144: <illegal opcode> w : (Ljava/lang/Exception;JJ)Ljava/lang/Exception;
/*     */     //   149: athrow
/*     */     //   150: aload_0
/*     */     //   151: aload #10
/*     */     //   153: ifnonnull -> 201
/*     */     //   156: getfield x : Ljava/util/concurrent/ScheduledExecutorService;
/*     */     //   159: ifnull -> 199
/*     */     //   162: goto -> 176
/*     */     //   165: ldc2_w 4124563937684032762
/*     */     //   168: lload #6
/*     */     //   170: <illegal opcode> w : (Ljava/lang/Exception;JJ)Ljava/lang/Exception;
/*     */     //   175: athrow
/*     */     //   176: aload_0
/*     */     //   177: getfield x : Ljava/util/concurrent/ScheduledExecutorService;
/*     */     //   180: invokeinterface shutdown : ()V
/*     */     //   185: goto -> 199
/*     */     //   188: ldc2_w 4124563937684032762
/*     */     //   191: lload #6
/*     */     //   193: <illegal opcode> w : (Ljava/lang/Exception;JJ)Ljava/lang/Exception;
/*     */     //   198: athrow
/*     */     //   199: aload #12
/*     */     //   201: monitorexit
/*     */     //   202: goto -> 213
/*     */     //   205: astore #13
/*     */     //   207: aload #12
/*     */     //   209: monitorexit
/*     */     //   210: aload #13
/*     */     //   212: athrow
/*     */     //   213: aload_0
/*     */     //   214: getfield l : Lme/konsolas/aac/jn;
/*     */     //   217: aload_0
/*     */     //   218: aload_1
/*     */     //   219: aload #4
/*     */     //   221: invokevirtual a : (Lme/konsolas/aac/k3;Ljava/lang/Throwable;Lme/konsolas/aac/H;)V
/*     */     //   224: lload #8
/*     */     //   226: aload #11
/*     */     //   228: invokestatic a : (JLjava/io/Closeable;)V
/*     */     //   231: goto -> 246
/*     */     //   234: astore #14
/*     */     //   236: lload #8
/*     */     //   238: aload #11
/*     */     //   240: invokestatic a : (JLjava/io/Closeable;)V
/*     */     //   243: aload #14
/*     */     //   245: athrow
/*     */     //   246: return
/*     */     // Line number table:
/*     */     //   Java source line number -> byte code offset
/*     */     //   #124	-> 40
/*     */     //   #108	-> 47
/*     */     //   #2	-> 77
/*     */     //   #110	-> 82
/*     */     //   #59	-> 88
/*     */     //   #84	-> 93
/*     */     //   #166	-> 150
/*     */     //   #179	-> 199
/*     */     //   #30	-> 213
/*     */     //   #158	-> 224
/*     */     //   #221	-> 231
/*     */     //   #184	-> 234
/*     */     //   #6	-> 246
/*     */     // Exception table:
/*     */     //   from	to	target	type
/*     */     //   47	59	62	java/lang/IllegalArgumentException
/*     */     //   47	76	205	finally
/*     */     //   77	202	205	finally
/*     */     //   88	111	114	java/lang/IllegalArgumentException
/*     */     //   105	136	139	java/lang/IllegalArgumentException
/*     */     //   151	162	165	java/lang/IllegalArgumentException
/*     */     //   156	185	188	java/lang/IllegalArgumentException
/*     */     //   205	210	205	finally
/*     */     //   213	224	234	finally
/*     */     //   234	236	234	finally
/*     */   }
/*     */ 
/*     */   
/*     */   public void a(gf paramgf, long paramLong) {
/*     */     // Byte code:
/*     */     //   0: getstatic me/konsolas/aac/dw.C : J
/*     */     //   3: lload_2
/*     */     //   4: lxor
/*     */     //   5: lstore_2
/*     */     //   6: lload_2
/*     */     //   7: dup2
/*     */     //   8: ldc2_w 95823970742922
/*     */     //   11: lxor
/*     */     //   12: dup2
/*     */     //   13: bipush #48
/*     */     //   15: lushr
/*     */     //   16: l2i
/*     */     //   17: istore #4
/*     */     //   19: dup2
/*     */     //   20: bipush #16
/*     */     //   22: lshl
/*     */     //   23: bipush #16
/*     */     //   25: lushr
/*     */     //   26: lstore #5
/*     */     //   28: pop2
/*     */     //   29: dup2
/*     */     //   30: ldc2_w 87876801726900
/*     */     //   33: lxor
/*     */     //   34: dup2
/*     */     //   35: bipush #8
/*     */     //   37: lushr
/*     */     //   38: lstore #7
/*     */     //   40: dup2
/*     */     //   41: bipush #56
/*     */     //   43: lshl
/*     */     //   44: bipush #56
/*     */     //   46: lushr
/*     */     //   47: l2i
/*     */     //   48: istore #9
/*     */     //   50: pop2
/*     */     //   51: dup2
/*     */     //   52: ldc2_w 123638163058026
/*     */     //   55: lxor
/*     */     //   56: lstore #10
/*     */     //   58: dup2
/*     */     //   59: ldc2_w 103086326286201
/*     */     //   62: lxor
/*     */     //   63: lstore #12
/*     */     //   65: dup2
/*     */     //   66: ldc2_w 76259493345986
/*     */     //   69: lxor
/*     */     //   70: lstore #14
/*     */     //   72: dup2
/*     */     //   73: ldc2_w 94027235158166
/*     */     //   76: lxor
/*     */     //   77: lstore #16
/*     */     //   79: dup2
/*     */     //   80: ldc2_w 123563049689492
/*     */     //   83: lxor
/*     */     //   84: lstore #18
/*     */     //   86: dup2
/*     */     //   87: ldc2_w 41986270559527
/*     */     //   90: lxor
/*     */     //   91: dup2
/*     */     //   92: bipush #48
/*     */     //   94: lushr
/*     */     //   95: l2i
/*     */     //   96: istore #20
/*     */     //   98: dup2
/*     */     //   99: bipush #16
/*     */     //   101: lshl
/*     */     //   102: bipush #32
/*     */     //   104: lushr
/*     */     //   105: l2i
/*     */     //   106: istore #21
/*     */     //   108: dup2
/*     */     //   109: bipush #48
/*     */     //   111: lshl
/*     */     //   112: bipush #48
/*     */     //   114: lushr
/*     */     //   115: l2i
/*     */     //   116: istore #22
/*     */     //   118: pop2
/*     */     //   119: dup2
/*     */     //   120: ldc2_w 63158757720299
/*     */     //   123: lxor
/*     */     //   124: lstore #23
/*     */     //   126: pop2
/*     */     //   127: aload_1
/*     */     //   128: lload #12
/*     */     //   130: invokevirtual a : (J)Lme/konsolas/aac/gI;
/*     */     //   133: iload #4
/*     */     //   135: i2c
/*     */     //   136: getstatic me/konsolas/aac/cv.a : Lme/konsolas/aac/cv;
/*     */     //   139: lload #5
/*     */     //   141: invokevirtual a : (CLme/konsolas/aac/cv;J)Lme/konsolas/aac/gI;
/*     */     //   144: getstatic me/konsolas/aac/dw.f : Ljava/util/List;
/*     */     //   147: lload #23
/*     */     //   149: invokevirtual b : (Ljava/util/List;J)Lme/konsolas/aac/gI;
/*     */     //   152: lload #16
/*     */     //   154: invokevirtual a : (J)Lme/konsolas/aac/gf;
/*     */     //   157: astore_1
/*     */     //   158: aload_0
/*     */     //   159: getfield s : Lme/konsolas/aac/s;
/*     */     //   162: lload #18
/*     */     //   164: invokevirtual a : (J)Lme/konsolas/aac/k_;
/*     */     //   167: sipush #22440
/*     */     //   170: ldc2_w 280439258783476061
/*     */     //   173: lload_2
/*     */     //   174: lxor
/*     */     //   175: <illegal opcode> o : (IJ)Ljava/lang/String;
/*     */     //   180: lload #7
/*     */     //   182: iload #9
/*     */     //   184: i2b
/*     */     //   185: sipush #12102
/*     */     //   188: ldc2_w 381931042254164408
/*     */     //   191: lload_2
/*     */     //   192: lxor
/*     */     //   193: <illegal opcode> o : (IJ)Ljava/lang/String;
/*     */     //   198: invokevirtual a : (Ljava/lang/String;JBLjava/lang/String;)Lme/konsolas/aac/k_;
/*     */     //   201: sipush #1064
/*     */     //   204: ldc2_w 2316166072293800645
/*     */     //   207: lload_2
/*     */     //   208: lxor
/*     */     //   209: <illegal opcode> o : (IJ)Ljava/lang/String;
/*     */     //   214: lload #7
/*     */     //   216: iload #9
/*     */     //   218: i2b
/*     */     //   219: sipush #9885
/*     */     //   222: ldc2_w 3058999451506055274
/*     */     //   225: lload_2
/*     */     //   226: lxor
/*     */     //   227: <illegal opcode> o : (IJ)Ljava/lang/String;
/*     */     //   232: invokevirtual a : (Ljava/lang/String;JBLjava/lang/String;)Lme/konsolas/aac/k_;
/*     */     //   235: sipush #14561
/*     */     //   238: ldc2_w 8634086202057295386
/*     */     //   241: lload_2
/*     */     //   242: lxor
/*     */     //   243: <illegal opcode> o : (IJ)Ljava/lang/String;
/*     */     //   248: aload_0
/*     */     //   249: getfield h : Ljava/lang/String;
/*     */     //   252: lload #7
/*     */     //   254: dup2_x1
/*     */     //   255: pop2
/*     */     //   256: iload #9
/*     */     //   258: i2b
/*     */     //   259: swap
/*     */     //   260: invokevirtual a : (Ljava/lang/String;JBLjava/lang/String;)Lme/konsolas/aac/k_;
/*     */     //   263: sipush #9362
/*     */     //   266: ldc2_w 5961597412265171560
/*     */     //   269: lload_2
/*     */     //   270: lxor
/*     */     //   271: <illegal opcode> o : (IJ)Ljava/lang/String;
/*     */     //   276: lload #7
/*     */     //   278: iload #9
/*     */     //   280: i2b
/*     */     //   281: sipush #10791
/*     */     //   284: ldc2_w 8831002955623535825
/*     */     //   287: lload_2
/*     */     //   288: lxor
/*     */     //   289: <illegal opcode> o : (IJ)Ljava/lang/String;
/*     */     //   294: invokevirtual a : (Ljava/lang/String;JBLjava/lang/String;)Lme/konsolas/aac/k_;
/*     */     //   297: lload #10
/*     */     //   299: invokevirtual a : (J)Lme/konsolas/aac/s;
/*     */     //   302: astore #25
/*     */     //   304: aload_0
/*     */     //   305: getstatic me/konsolas/aac/dJ.a : Lme/konsolas/aac/dJ;
/*     */     //   308: aload_1
/*     */     //   309: iload #20
/*     */     //   311: i2c
/*     */     //   312: iload #21
/*     */     //   314: iload #22
/*     */     //   316: i2s
/*     */     //   317: aload #25
/*     */     //   319: invokevirtual a : (Lme/konsolas/aac/gf;CISLme/konsolas/aac/s;)Lme/konsolas/aac/gC;
/*     */     //   322: putfield t : Lme/konsolas/aac/gC;
/*     */     //   325: aload_0
/*     */     //   326: getfield t : Lme/konsolas/aac/gC;
/*     */     //   329: new me/konsolas/aac/j3
/*     */     //   332: dup
/*     */     //   333: aload_0
/*     */     //   334: aload #25
/*     */     //   336: invokespecial <init> : (Lme/konsolas/aac/dw;Lme/konsolas/aac/s;)V
/*     */     //   339: lload #14
/*     */     //   341: dup2_x1
/*     */     //   342: pop2
/*     */     //   343: invokeinterface a : (JLme/konsolas/aac/lR;)V
/*     */     //   348: return
/*     */     // Line number table:
/*     */     //   Java source line number -> byte code offset
/*     */     //   #126	-> 127
/*     */     //   #200	-> 139
/*     */     //   #112	-> 147
/*     */     //   #176	-> 152
/*     */     //   #180	-> 158
/*     */     //   #36	-> 198
/*     */     //   #142	-> 232
/*     */     //   #190	-> 260
/*     */     //   #26	-> 294
/*     */     //   #202	-> 297
/*     */     //   #51	-> 304
/*     */     //   #46	-> 325
/*     */     //   #21	-> 348
/*     */   }
/*     */ 
/*     */   
/*     */   synchronized boolean a(int paramInt, long paramLong1, String paramString, long paramLong2) {
/*     */     // Byte code:
/*     */     //   0: getstatic me/konsolas/aac/dw.C : J
/*     */     //   3: lload_2
/*     */     //   4: lxor
/*     */     //   5: lstore_2
/*     */     //   6: lload_2
/*     */     //   7: dup2
/*     */     //   8: ldc2_w 127695222758025
/*     */     //   11: lxor
/*     */     //   12: lstore #7
/*     */     //   14: dup2
/*     */     //   15: ldc2_w 10538084185922
/*     */     //   18: lxor
/*     */     //   19: lstore #9
/*     */     //   21: dup2
/*     */     //   22: ldc2_w 98316840249759
/*     */     //   25: lxor
/*     */     //   26: dup2
/*     */     //   27: bipush #48
/*     */     //   29: lushr
/*     */     //   30: l2i
/*     */     //   31: istore #11
/*     */     //   33: dup2
/*     */     //   34: bipush #16
/*     */     //   36: lshl
/*     */     //   37: bipush #32
/*     */     //   39: lushr
/*     */     //   40: l2i
/*     */     //   41: istore #12
/*     */     //   43: dup2
/*     */     //   44: bipush #48
/*     */     //   46: lshl
/*     */     //   47: bipush #48
/*     */     //   49: lushr
/*     */     //   50: l2i
/*     */     //   51: istore #13
/*     */     //   53: pop2
/*     */     //   54: pop2
/*     */     //   55: iload_1
/*     */     //   56: lload #7
/*     */     //   58: invokestatic a : (IJ)V
/*     */     //   61: ldc2_w 145348007811921516
/*     */     //   64: lload_2
/*     */     //   65: <illegal opcode> w : (JJ)[I
/*     */     //   70: aconst_null
/*     */     //   71: astore #15
/*     */     //   73: astore #14
/*     */     //   75: aload #4
/*     */     //   77: aload #14
/*     */     //   79: ifnonnull -> 100
/*     */     //   82: ifnull -> 193
/*     */     //   85: goto -> 98
/*     */     //   88: ldc2_w 165303374939961228
/*     */     //   91: lload_2
/*     */     //   92: <illegal opcode> w : (Ljava/lang/Exception;JJ)Ljava/lang/Exception;
/*     */     //   97: athrow
/*     */     //   98: aload #4
/*     */     //   100: lload #9
/*     */     //   102: invokestatic a : (Ljava/lang/String;J)Lme/konsolas/aac/gZ;
/*     */     //   105: astore #15
/*     */     //   107: aload #15
/*     */     //   109: invokevirtual a : ()I
/*     */     //   112: i2l
/*     */     //   113: ldc2_w 123
/*     */     //   116: lcmp
/*     */     //   117: aload #14
/*     */     //   119: lload_2
/*     */     //   120: lconst_0
/*     */     //   121: lcmp
/*     */     //   122: iflt -> 199
/*     */     //   125: ifnonnull -> 197
/*     */     //   128: ifle -> 193
/*     */     //   131: goto -> 144
/*     */     //   134: ldc2_w 165303374939961228
/*     */     //   137: lload_2
/*     */     //   138: <illegal opcode> w : (Ljava/lang/Exception;JJ)Ljava/lang/Exception;
/*     */     //   143: athrow
/*     */     //   144: new java/lang/IllegalArgumentException
/*     */     //   147: dup
/*     */     //   148: new java/lang/StringBuilder
/*     */     //   151: dup
/*     */     //   152: invokespecial <init> : ()V
/*     */     //   155: sipush #25694
/*     */     //   158: ldc2_w 5749313057388284803
/*     */     //   161: lload_2
/*     */     //   162: lxor
/*     */     //   163: <illegal opcode> o : (IJ)Ljava/lang/String;
/*     */     //   168: invokevirtual append : (Ljava/lang/String;)Ljava/lang/StringBuilder;
/*     */     //   171: aload #4
/*     */     //   173: invokevirtual append : (Ljava/lang/String;)Ljava/lang/StringBuilder;
/*     */     //   176: invokevirtual toString : ()Ljava/lang/String;
/*     */     //   179: invokespecial <init> : (Ljava/lang/String;)V
/*     */     //   182: athrow
/*     */     //   183: ldc2_w 165303374939961228
/*     */     //   186: lload_2
/*     */     //   187: <illegal opcode> w : (Ljava/lang/Exception;JJ)Ljava/lang/Exception;
/*     */     //   192: athrow
/*     */     //   193: aload_0
/*     */     //   194: getfield A : Z
/*     */     //   197: aload #14
/*     */     //   199: ifnonnull -> 257
/*     */     //   202: ifne -> 256
/*     */     //   205: goto -> 218
/*     */     //   208: ldc2_w 165303374939961228
/*     */     //   211: lload_2
/*     */     //   212: <illegal opcode> w : (Ljava/lang/Exception;JJ)Ljava/lang/Exception;
/*     */     //   217: athrow
/*     */     //   218: aload_0
/*     */     //   219: getfield c : Z
/*     */     //   222: aload #14
/*     */     //   224: ifnonnull -> 295
/*     */     //   227: goto -> 240
/*     */     //   230: ldc2_w 165303374939961228
/*     */     //   233: lload_2
/*     */     //   234: <illegal opcode> w : (Ljava/lang/Exception;JJ)Ljava/lang/Exception;
/*     */     //   239: athrow
/*     */     //   240: ifeq -> 258
/*     */     //   243: goto -> 256
/*     */     //   246: ldc2_w 165303374939961228
/*     */     //   249: lload_2
/*     */     //   250: <illegal opcode> w : (Ljava/lang/Exception;JJ)Ljava/lang/Exception;
/*     */     //   255: athrow
/*     */     //   256: iconst_0
/*     */     //   257: ireturn
/*     */     //   258: aload_0
/*     */     //   259: iconst_1
/*     */     //   260: putfield c : Z
/*     */     //   263: aload_0
/*     */     //   264: getfield b : Ljava/util/ArrayDeque;
/*     */     //   267: new me/konsolas/aac/kv
/*     */     //   270: dup
/*     */     //   271: iload_1
/*     */     //   272: aload #15
/*     */     //   274: lload #5
/*     */     //   276: invokespecial <init> : (ILme/konsolas/aac/gZ;J)V
/*     */     //   279: invokevirtual add : (Ljava/lang/Object;)Z
/*     */     //   282: pop
/*     */     //   283: aload_0
/*     */     //   284: iload #11
/*     */     //   286: i2s
/*     */     //   287: iload #12
/*     */     //   289: iload #13
/*     */     //   291: invokespecial b : (SII)V
/*     */     //   294: iconst_1
/*     */     //   295: ireturn
/*     */     // Line number table:
/*     */     //   Java source line number -> byte code offset
/*     */     //   #127	-> 55
/*     */     //   #9	-> 70
/*     */     //   #199	-> 75
/*     */     //   #204	-> 98
/*     */     //   #58	-> 107
/*     */     //   #143	-> 144
/*     */     //   #212	-> 193
/*     */     //   #8	-> 258
/*     */     //   #149	-> 263
/*     */     //   #89	-> 283
/*     */     //   #196	-> 294
/*     */     // Exception table:
/*     */     //   from	to	target	type
/*     */     //   75	85	88	java/lang/IllegalArgumentException
/*     */     //   107	131	134	java/lang/IllegalArgumentException
/*     */     //   128	183	183	java/lang/IllegalArgumentException
/*     */     //   197	205	208	java/lang/IllegalArgumentException
/*     */     //   202	227	230	java/lang/IllegalArgumentException
/*     */     //   218	243	246	java/lang/IllegalArgumentException
/*     */   }
/*     */ 
/*     */   
/*     */   public synchronized void a(gZ paramgZ) {
/* 130 */     this.a++;
/*     */ 
/*     */ 
/*     */ 
/*     */ 
/*     */ 
/*     */ 
/*     */ 
/*     */ 
/*     */ 
/*     */ 
/*     */ 
/*     */ 
/*     */ 
/*     */ 
/*     */ 
/*     */ 
/*     */ 
/*     */ 
/*     */ 
/*     */ 
/*     */ 
/*     */ 
/*     */ 
/*     */ 
/*     */ 
/*     */ 
/*     */ 
/*     */     
/* 159 */     this.n = false;
/*     */   } public synchronized void b(int paramInt, long paramLong, gZ paramgZ) { // Byte code:
/*     */     //   0: iload_1
/*     */     //   1: i2l
/*     */     //   2: bipush #32
/*     */     //   4: lshl
/*     */     //   5: lload_2
/*     */     //   6: bipush #32
/*     */     //   8: lshl
/*     */     //   9: bipush #32
/*     */     //   11: lushr
/*     */     //   12: lor
/*     */     //   13: lstore #5
/*     */     //   15: lload #5
/*     */     //   17: dup2
/*     */     //   18: ldc2_w 86697862109587
/*     */     //   21: lxor
/*     */     //   22: dup2
/*     */     //   23: bipush #48
/*     */     //   25: lushr
/*     */     //   26: l2i
/*     */     //   27: istore #7
/*     */     //   29: dup2
/*     */     //   30: bipush #16
/*     */     //   32: lshl
/*     */     //   33: bipush #32
/*     */     //   35: lushr
/*     */     //   36: l2i
/*     */     //   37: istore #8
/*     */     //   39: dup2
/*     */     //   40: bipush #48
/*     */     //   42: lshl
/*     */     //   43: bipush #48
/*     */     //   45: lushr
/*     */     //   46: l2i
/*     */     //   47: istore #9
/*     */     //   49: pop2
/*     */     //   50: pop2
/*     */     //   51: ldc2_w -5618110187427592608
/*     */     //   54: lload #5
/*     */     //   56: <illegal opcode> w : (JJ)[I
/*     */     //   61: astore #10
/*     */     //   63: aload_0
/*     */     //   64: getfield A : Z
/*     */     //   67: aload #10
/*     */     //   69: ifnonnull -> 107
/*     */     //   72: ifne -> 178
/*     */     //   75: goto -> 89
/*     */     //   78: ldc2_w -5600418302457772160
/*     */     //   81: lload #5
/*     */     //   83: <illegal opcode> w : (Ljava/lang/Exception;JJ)Ljava/lang/Exception;
/*     */     //   88: athrow
/*     */     //   89: aload_0
/*     */     //   90: getfield c : Z
/*     */     //   93: goto -> 107
/*     */     //   96: ldc2_w -5600418302457772160
/*     */     //   99: lload #5
/*     */     //   101: <illegal opcode> w : (Ljava/lang/Exception;JJ)Ljava/lang/Exception;
/*     */     //   106: athrow
/*     */     //   107: aload #10
/*     */     //   109: ifnonnull -> 188
/*     */     //   112: ifeq -> 179
/*     */     //   115: goto -> 129
/*     */     //   118: ldc2_w -5600418302457772160
/*     */     //   121: lload #5
/*     */     //   123: <illegal opcode> w : (Ljava/lang/Exception;JJ)Ljava/lang/Exception;
/*     */     //   128: athrow
/*     */     //   129: aload_0
/*     */     //   130: lload_2
/*     */     //   131: lconst_0
/*     */     //   132: lcmp
/*     */     //   133: ifle -> 201
/*     */     //   136: getfield b : Ljava/util/ArrayDeque;
/*     */     //   139: invokevirtual isEmpty : ()Z
/*     */     //   142: aload #10
/*     */     //   144: ifnonnull -> 188
/*     */     //   147: goto -> 161
/*     */     //   150: ldc2_w -5600418302457772160
/*     */     //   153: lload #5
/*     */     //   155: <illegal opcode> w : (Ljava/lang/Exception;JJ)Ljava/lang/Exception;
/*     */     //   160: athrow
/*     */     //   161: ifeq -> 179
/*     */     //   164: goto -> 178
/*     */     //   167: ldc2_w -5600418302457772160
/*     */     //   170: lload #5
/*     */     //   172: <illegal opcode> w : (Ljava/lang/Exception;JJ)Ljava/lang/Exception;
/*     */     //   177: athrow
/*     */     //   178: return
/*     */     //   179: aload_0
/*     */     //   180: getfield i : Ljava/util/ArrayDeque;
/*     */     //   183: aload #4
/*     */     //   185: invokevirtual add : (Ljava/lang/Object;)Z
/*     */     //   188: pop
/*     */     //   189: aload_0
/*     */     //   190: iload #7
/*     */     //   192: i2s
/*     */     //   193: iload #8
/*     */     //   195: iload #9
/*     */     //   197: invokespecial b : (SII)V
/*     */     //   200: aload_0
/*     */     //   201: dup
/*     */     //   202: getfield r : I
/*     */     //   205: iconst_1
/*     */     //   206: iadd
/*     */     //   207: putfield r : I
/*     */     //   210: return
/*     */     // Line number table:
/*     */     //   Java source line number -> byte code offset
/*     */     //   #133	-> 63
/*     */     //   #56	-> 179
/*     */     //   #101	-> 189
/*     */     //   #10	-> 200
/*     */     //   #182	-> 210
/*     */     // Exception table:
/*     */     //   from	to	target	type
/*     */     //   63	75	78	java/lang/IllegalArgumentException
/*     */     //   72	93	96	java/lang/IllegalArgumentException
/*     */     //   107	115	118	java/lang/IllegalArgumentException
/*     */     //   112	147	150	java/lang/IllegalArgumentException
/*     */     //   129	164	167	java/lang/IllegalArgumentException } public boolean a(int paramInt, short paramShort, char paramChar, String paramString) { // Byte code:
/*     */     //   0: iload_1
/*     */     //   1: i2l
/*     */     //   2: bipush #32
/*     */     //   4: lshl
/*     */     //   5: iload_2
/*     */     //   6: i2l
/*     */     //   7: bipush #48
/*     */     //   9: lshl
/*     */     //   10: bipush #32
/*     */     //   12: lushr
/*     */     //   13: lor
/*     */     //   14: iload_3
/*     */     //   15: i2l
/*     */     //   16: bipush #48
/*     */     //   18: lshl
/*     */     //   19: bipush #48
/*     */     //   21: lushr
/*     */     //   22: lor
/*     */     //   23: lstore #5
/*     */     //   25: lload #5
/*     */     //   27: dup2
/*     */     //   28: ldc2_w 6640268056991
/*     */     //   31: lxor
/*     */     //   32: lstore #7
/*     */     //   34: dup2
/*     */     //   35: ldc2_w 130749700705457
/*     */     //   38: lxor
/*     */     //   39: lstore #9
/*     */     //   41: pop2
/*     */     //   42: aload #4
/*     */     //   44: ifnonnull -> 80
/*     */     //   47: new java/lang/NullPointerException
/*     */     //   50: dup
/*     */     //   51: sipush #24919
/*     */     //   54: ldc2_w 7323928093485293649
/*     */     //   57: lload #5
/*     */     //   59: lxor
/*     */     //   60: <illegal opcode> o : (IJ)Ljava/lang/String;
/*     */     //   65: invokespecial <init> : (Ljava/lang/String;)V
/*     */     //   68: athrow
/*     */     //   69: ldc2_w 3212835737500784977
/*     */     //   72: lload #5
/*     */     //   74: <illegal opcode> w : (Ljava/lang/Exception;JJ)Ljava/lang/Exception;
/*     */     //   79: athrow
/*     */     //   80: aload_0
/*     */     //   81: aload #4
/*     */     //   83: lload #7
/*     */     //   85: invokestatic a : (Ljava/lang/String;J)Lme/konsolas/aac/gZ;
/*     */     //   88: iconst_1
/*     */     //   89: lload #9
/*     */     //   91: invokespecial a : (Lme/konsolas/aac/gZ;IJ)Z
/*     */     //   94: ireturn
/*     */     // Line number table:
/*     */     //   Java source line number -> byte code offset
/*     */     //   #144	-> 42
/*     */     //   #215	-> 80
/*     */     // Exception table:
/*     */     //   from	to	target	type
/*     */     //   42	69	69	java/lang/IllegalArgumentException }
/*     */   public void e(long paramLong) { // Byte code:
/*     */     //   0: getstatic me/konsolas/aac/dw.C : J
/*     */     //   3: lload_1
/*     */     //   4: lxor
/*     */     //   5: lstore_1
/*     */     //   6: lload_1
/*     */     //   7: dup2
/*     */     //   8: ldc2_w 86254464228271
/*     */     //   11: lxor
/*     */     //   12: lstore_3
/*     */     //   13: pop2
/*     */     //   14: ldc2_w -9051316872844397045
/*     */     //   17: lload_1
/*     */     //   18: <illegal opcode> w : (JJ)[I
/*     */     //   23: astore #5
/*     */     //   25: aload_0
/*     */     //   26: getfield e : I
/*     */     //   29: iconst_m1
/*     */     //   30: if_icmpne -> 46
/*     */     //   33: aload_0
/*     */     //   34: getfield m : Lme/konsolas/aac/c_;
/*     */     //   37: lload_3
/*     */     //   38: invokevirtual c : (J)V
/*     */     //   41: aload #5
/*     */     //   43: ifnull -> 25
/*     */     //   46: lload_1
/*     */     //   47: lconst_0
/*     */     //   48: lcmp
/*     */     //   49: ifle -> 41
/*     */     //   52: return
/*     */     // Line number table:
/*     */     //   Java source line number -> byte code offset
/*     */     //   #145	-> 25
/*     */     //   #111	-> 33
/*     */     //   #214	-> 46 }
/*     */   private void b(short paramShort, int paramInt1, int paramInt2) { // Byte code:
/*     */     //   0: iload_1
/*     */     //   1: i2l
/*     */     //   2: bipush #48
/*     */     //   4: lshl
/*     */     //   5: iload_2
/*     */     //   6: i2l
/*     */     //   7: bipush #32
/*     */     //   9: lshl
/*     */     //   10: bipush #16
/*     */     //   12: lushr
/*     */     //   13: lor
/*     */     //   14: iload_3
/*     */     //   15: i2l
/*     */     //   16: bipush #48
/*     */     //   18: lshl
/*     */     //   19: bipush #48
/*     */     //   21: lushr
/*     */     //   22: lor
/*     */     //   23: getstatic me/konsolas/aac/dw.C : J
/*     */     //   26: lxor
/*     */     //   27: lstore #4
/*     */     //   29: ldc2_w 4755017262500935061
/*     */     //   32: lload #4
/*     */     //   34: <illegal opcode> w : (JJ)[I
/*     */     //   39: astore #6
/*     */     //   41: getstatic me/konsolas/aac/dw.p : Z
/*     */     //   44: aload #6
/*     */     //   46: ifnonnull -> 107
/*     */     //   49: ifne -> 129
/*     */     //   52: goto -> 66
/*     */     //   55: ldc2_w 4733864526976349301
/*     */     //   58: lload #4
/*     */     //   60: <illegal opcode> w : (Ljava/lang/Exception;JJ)Ljava/lang/Exception;
/*     */     //   65: athrow
/*     */     //   66: aload_0
/*     */     //   67: iload_2
/*     */     //   68: ifle -> 130
/*     */     //   71: aload #6
/*     */     //   73: ifnonnull -> 130
/*     */     //   76: goto -> 90
/*     */     //   79: ldc2_w 4733864526976349301
/*     */     //   82: lload #4
/*     */     //   84: <illegal opcode> w : (Ljava/lang/Exception;JJ)Ljava/lang/Exception;
/*     */     //   89: athrow
/*     */     //   90: invokestatic holdsLock : (Ljava/lang/Object;)Z
/*     */     //   93: goto -> 107
/*     */     //   96: ldc2_w 4733864526976349301
/*     */     //   99: lload #4
/*     */     //   101: <illegal opcode> w : (Ljava/lang/Exception;JJ)Ljava/lang/Exception;
/*     */     //   106: athrow
/*     */     //   107: ifne -> 129
/*     */     //   110: new java/lang/AssertionError
/*     */     //   113: dup
/*     */     //   114: invokespecial <init> : ()V
/*     */     //   117: athrow
/*     */     //   118: ldc2_w 4733864526976349301
/*     */     //   121: lload #4
/*     */     //   123: <illegal opcode> w : (Ljava/lang/Exception;JJ)Ljava/lang/Exception;
/*     */     //   128: athrow
/*     */     //   129: aload_0
/*     */     //   130: getfield x : Ljava/util/concurrent/ScheduledExecutorService;
/*     */     //   133: aload #6
/*     */     //   135: ifnonnull -> 173
/*     */     //   138: ifnull -> 182
/*     */     //   141: goto -> 155
/*     */     //   144: ldc2_w 4733864526976349301
/*     */     //   147: lload #4
/*     */     //   149: <illegal opcode> w : (Ljava/lang/Exception;JJ)Ljava/lang/Exception;
/*     */     //   154: athrow
/*     */     //   155: aload_0
/*     */     //   156: getfield x : Ljava/util/concurrent/ScheduledExecutorService;
/*     */     //   159: goto -> 173
/*     */     //   162: ldc2_w 4733864526976349301
/*     */     //   165: lload #4
/*     */     //   167: <illegal opcode> w : (Ljava/lang/Exception;JJ)Ljava/lang/Exception;
/*     */     //   172: athrow
/*     */     //   173: aload_0
/*     */     //   174: getfield d : Ljava/lang/Runnable;
/*     */     //   177: invokeinterface execute : (Ljava/lang/Runnable;)V
/*     */     //   182: return
/*     */     // Line number table:
/*     */     //   Java source line number -> byte code offset
/*     */     //   #153	-> 41
/*     */     //   #117	-> 129
/*     */     //   #77	-> 155
/*     */     //   #94	-> 182
/*     */     // Exception table:
/*     */     //   from	to	target	type
/*     */     //   41	52	55	java/lang/IllegalArgumentException
/*     */     //   49	76	79	java/lang/IllegalArgumentException
/*     */     //   66	93	96	java/lang/IllegalArgumentException
/*     */     //   107	118	118	java/lang/IllegalArgumentException
/*     */     //   130	141	144	java/lang/IllegalArgumentException
/*     */     //   138	159	162	java/lang/IllegalArgumentException }
/*     */   public dw(s params, jn paramjn, long paramLong1, Random paramRandom, long paramLong2) { // Byte code:
/*     */     //   0: getstatic me/konsolas/aac/dw.C : J
/*     */     //   3: lload_3
/*     */     //   4: lxor
/*     */     //   5: lstore_3
/*     */     //   6: lload_3
/*     */     //   7: dup2
/*     */     //   8: ldc2_w 92387731602987
/*     */     //   11: lxor
/*     */     //   12: lstore #8
/*     */     //   14: dup2
/*     */     //   15: ldc2_w 5364521740182
/*     */     //   18: lxor
/*     */     //   19: lstore #10
/*     */     //   21: pop2
/*     */     //   22: ldc2_w 6062450849930272842
/*     */     //   25: lload_3
/*     */     //   26: <illegal opcode> w : (JJ)[I
/*     */     //   31: aload_0
/*     */     //   32: invokespecial <init> : ()V
/*     */     //   35: aload_0
/*     */     //   36: new java/util/ArrayDeque
/*     */     //   39: dup
/*     */     //   40: invokespecial <init> : ()V
/*     */     //   43: putfield i : Ljava/util/ArrayDeque;
/*     */     //   46: astore #12
/*     */     //   48: aload_0
/*     */     //   49: new java/util/ArrayDeque
/*     */     //   52: dup
/*     */     //   53: invokespecial <init> : ()V
/*     */     //   56: putfield b : Ljava/util/ArrayDeque;
/*     */     //   59: aload_0
/*     */     //   60: iconst_m1
/*     */     //   61: putfield e : I
/*     */     //   64: sipush #9537
/*     */     //   67: ldc2_w 7587917068660792509
/*     */     //   70: lload_3
/*     */     //   71: lxor
/*     */     //   72: <illegal opcode> o : (IJ)Ljava/lang/String;
/*     */     //   77: aload_1
/*     */     //   78: invokevirtual a : ()Ljava/lang/String;
/*     */     //   81: invokevirtual equals : (Ljava/lang/Object;)Z
/*     */     //   84: aload #12
/*     */     //   86: ifnonnull -> 180
/*     */     //   89: ifne -> 156
/*     */     //   92: goto -> 105
/*     */     //   95: ldc2_w 6083520151722090922
/*     */     //   98: lload_3
/*     */     //   99: <illegal opcode> w : (Ljava/lang/Exception;JJ)Ljava/lang/Exception;
/*     */     //   104: athrow
/*     */     //   105: new java/lang/IllegalArgumentException
/*     */     //   108: dup
/*     */     //   109: new java/lang/StringBuilder
/*     */     //   112: dup
/*     */     //   113: invokespecial <init> : ()V
/*     */     //   116: sipush #21774
/*     */     //   119: ldc2_w 2715040268867742959
/*     */     //   122: lload_3
/*     */     //   123: lxor
/*     */     //   124: <illegal opcode> o : (IJ)Ljava/lang/String;
/*     */     //   129: invokevirtual append : (Ljava/lang/String;)Ljava/lang/StringBuilder;
/*     */     //   132: aload_1
/*     */     //   133: invokevirtual a : ()Ljava/lang/String;
/*     */     //   136: invokevirtual append : (Ljava/lang/String;)Ljava/lang/StringBuilder;
/*     */     //   139: invokevirtual toString : ()Ljava/lang/String;
/*     */     //   142: invokespecial <init> : (Ljava/lang/String;)V
/*     */     //   145: athrow
/*     */     //   146: ldc2_w 6083520151722090922
/*     */     //   149: lload_3
/*     */     //   150: <illegal opcode> w : (Ljava/lang/Exception;JJ)Ljava/lang/Exception;
/*     */     //   155: athrow
/*     */     //   156: aload_0
/*     */     //   157: aload_1
/*     */     //   158: putfield s : Lme/konsolas/aac/s;
/*     */     //   161: aload_0
/*     */     //   162: aload_2
/*     */     //   163: putfield l : Lme/konsolas/aac/jn;
/*     */     //   166: aload_0
/*     */     //   167: aload #5
/*     */     //   169: putfield j : Ljava/util/Random;
/*     */     //   172: aload_0
/*     */     //   173: lload #6
/*     */     //   175: putfield y : J
/*     */     //   178: bipush #16
/*     */     //   180: newarray byte
/*     */     //   182: astore #13
/*     */     //   184: aload #5
/*     */     //   186: aload #13
/*     */     //   188: invokevirtual nextBytes : ([B)V
/*     */     //   191: aload_0
/*     */     //   192: aload #13
/*     */     //   194: lload #8
/*     */     //   196: invokestatic a : ([BJ)Lme/konsolas/aac/gZ;
/*     */     //   199: lload #10
/*     */     //   201: invokevirtual b : (J)Ljava/lang/String;
/*     */     //   204: putfield h : Ljava/lang/String;
/*     */     //   207: aload_0
/*     */     //   208: aload_0
/*     */     //   209: <illegal opcode> run : (Lme/konsolas/aac/dw;)Ljava/lang/Runnable;
/*     */     //   214: putfield d : Ljava/lang/Runnable;
/*     */     //   217: lload_3
/*     */     //   218: lconst_0
/*     */     //   219: lcmp
/*     */     //   220: iflt -> 247
/*     */     //   223: ldc2_w 6062213361943711874
/*     */     //   226: lload_3
/*     */     //   227: <illegal opcode> w : (JJ)[Lme/konsolas/aac/aN;
/*     */     //   232: ifnull -> 260
/*     */     //   235: iconst_5
/*     */     //   236: newarray int
/*     */     //   238: ldc2_w 6108332840177296105
/*     */     //   241: lload_3
/*     */     //   242: <illegal opcode> w : ([IJJ)V
/*     */     //   247: goto -> 260
/*     */     //   250: ldc2_w 6083520151722090922
/*     */     //   253: lload_3
/*     */     //   254: <illegal opcode> w : (Ljava/lang/Exception;JJ)Ljava/lang/Exception;
/*     */     //   259: athrow
/*     */     //   260: return
/*     */     // Line number table:
/*     */     //   Java source line number -> byte code offset
/*     */     //   #155	-> 31
/*     */     //   #152	-> 35
/*     */     //   #4	-> 48
/*     */     //   #173	-> 59
/*     */     //   #54	-> 64
/*     */     //   #72	-> 105
/*     */     //   #13	-> 156
/*     */     //   #29	-> 161
/*     */     //   #217	-> 166
/*     */     //   #75	-> 172
/*     */     //   #121	-> 178
/*     */     //   #171	-> 184
/*     */     //   #40	-> 191
/*     */     //   #61	-> 207
/*     */     //   #185	-> 217
/*     */     // Exception table:
/*     */     //   from	to	target	type
/*     */     //   48	92	95	java/lang/IllegalArgumentException
/*     */     //   89	146	146	java/lang/IllegalArgumentException
/*     */     //   184	247	250	java/lang/IllegalArgumentException }
/* 164 */   public void a(String paramString) { this.l.a(this, paramString); }
/*     */ 
/*     */ 
/*     */ 
/*     */ 
/*     */ 
/*     */ 
/*     */   
/*     */   boolean b(long paramLong) {
/*     */     // Byte code:
/*     */     //   0: getstatic me/konsolas/aac/dw.C : J
/*     */     //   3: lload_1
/*     */     //   4: lxor
/*     */     //   5: lstore_1
/*     */     //   6: lload_1
/*     */     //   7: dup2
/*     */     //   8: ldc2_w 112026722695328
/*     */     //   11: lxor
/*     */     //   12: lstore_3
/*     */     //   13: dup2
/*     */     //   14: ldc2_w 40951695274616
/*     */     //   17: lxor
/*     */     //   18: dup2
/*     */     //   19: bipush #16
/*     */     //   21: lushr
/*     */     //   22: lstore #5
/*     */     //   24: dup2
/*     */     //   25: bipush #48
/*     */     //   27: lshl
/*     */     //   28: bipush #48
/*     */     //   30: lushr
/*     */     //   31: l2i
/*     */     //   32: istore #7
/*     */     //   34: pop2
/*     */     //   35: pop2
/*     */     //   36: ldc2_w 2408415158250345732
/*     */     //   39: lload_1
/*     */     //   40: <illegal opcode> w : (JJ)[I
/*     */     //   45: astore #8
/*     */     //   47: aload_0
/*     */     //   48: getfield m : Lme/konsolas/aac/c_;
/*     */     //   51: lload_3
/*     */     //   52: invokevirtual c : (J)V
/*     */     //   55: aload_0
/*     */     //   56: getfield e : I
/*     */     //   59: aload #8
/*     */     //   61: ifnonnull -> 95
/*     */     //   64: iconst_m1
/*     */     //   65: if_icmpne -> 98
/*     */     //   68: goto -> 81
/*     */     //   71: ldc2_w 2387839528588350692
/*     */     //   74: lload_1
/*     */     //   75: <illegal opcode> w : (Ljava/lang/Exception;JJ)Ljava/lang/Exception;
/*     */     //   80: athrow
/*     */     //   81: iconst_1
/*     */     //   82: goto -> 95
/*     */     //   85: ldc2_w 2387839528588350692
/*     */     //   88: lload_1
/*     */     //   89: <illegal opcode> w : (Ljava/lang/Exception;JJ)Ljava/lang/Exception;
/*     */     //   94: athrow
/*     */     //   95: goto -> 99
/*     */     //   98: iconst_0
/*     */     //   99: ireturn
/*     */     //   100: astore #9
/*     */     //   102: aload_0
/*     */     //   103: aload #9
/*     */     //   105: lload #5
/*     */     //   107: aconst_null
/*     */     //   108: iload #7
/*     */     //   110: i2s
/*     */     //   111: invokevirtual a : (Ljava/lang/Exception;JLme/konsolas/aac/H;S)V
/*     */     //   114: iconst_0
/*     */     //   115: ireturn
/*     */     // Line number table:
/*     */     //   Java source line number -> byte code offset
/*     */     //   #169	-> 47
/*     */     //   #45	-> 55
/*     */     //   #69	-> 100
/*     */     //   #35	-> 102
/*     */     //   #86	-> 114
/*     */     // Exception table:
/*     */     //   from	to	target	type
/*     */     //   47	68	71	java/lang/Exception
/*     */     //   47	99	100	java/lang/Exception
/*     */     //   64	82	85	java/lang/Exception
/*     */   }
/*     */ 
/*     */ 
/*     */ 
/*     */ 
/*     */ 
/*     */   
/*     */   synchronized boolean b(short paramShort, long paramLong, gZ paramgZ) {
/*     */     // Byte code:
/*     */     //   0: iload_1
/*     */     //   1: i2l
/*     */     //   2: bipush #48
/*     */     //   4: lshl
/*     */     //   5: lload_2
/*     */     //   6: bipush #16
/*     */     //   8: lshl
/*     */     //   9: bipush #16
/*     */     //   11: lushr
/*     */     //   12: lor
/*     */     //   13: getstatic me/konsolas/aac/dw.C : J
/*     */     //   16: lxor
/*     */     //   17: lstore #5
/*     */     //   19: lload #5
/*     */     //   21: dup2
/*     */     //   22: ldc2_w 66483507439647
/*     */     //   25: lxor
/*     */     //   26: dup2
/*     */     //   27: bipush #48
/*     */     //   29: lushr
/*     */     //   30: l2i
/*     */     //   31: istore #7
/*     */     //   33: dup2
/*     */     //   34: bipush #16
/*     */     //   36: lshl
/*     */     //   37: bipush #32
/*     */     //   39: lushr
/*     */     //   40: l2i
/*     */     //   41: istore #8
/*     */     //   43: dup2
/*     */     //   44: bipush #48
/*     */     //   46: lshl
/*     */     //   47: bipush #48
/*     */     //   49: lushr
/*     */     //   50: l2i
/*     */     //   51: istore #9
/*     */     //   53: pop2
/*     */     //   54: pop2
/*     */     //   55: ldc2_w -8970040011592419348
/*     */     //   58: lload #5
/*     */     //   60: <illegal opcode> w : (JJ)[I
/*     */     //   65: astore #10
/*     */     //   67: aload_0
/*     */     //   68: getfield A : Z
/*     */     //   71: aload #10
/*     */     //   73: ifnonnull -> 181
/*     */     //   76: ifne -> 180
/*     */     //   79: goto -> 93
/*     */     //   82: ldc2_w -8950020701294250484
/*     */     //   85: lload #5
/*     */     //   87: <illegal opcode> w : (Ljava/lang/Exception;JJ)Ljava/lang/Exception;
/*     */     //   92: athrow
/*     */     //   93: aload_0
/*     */     //   94: getfield c : Z
/*     */     //   97: aload #10
/*     */     //   99: ifnonnull -> 204
/*     */     //   102: goto -> 116
/*     */     //   105: ldc2_w -8950020701294250484
/*     */     //   108: lload #5
/*     */     //   110: <illegal opcode> w : (Ljava/lang/Exception;JJ)Ljava/lang/Exception;
/*     */     //   115: athrow
/*     */     //   116: iload_1
/*     */     //   117: iflt -> 191
/*     */     //   120: ifeq -> 182
/*     */     //   123: goto -> 137
/*     */     //   126: ldc2_w -8950020701294250484
/*     */     //   129: lload #5
/*     */     //   131: <illegal opcode> w : (Ljava/lang/Exception;JJ)Ljava/lang/Exception;
/*     */     //   136: athrow
/*     */     //   137: aload_0
/*     */     //   138: getfield b : Ljava/util/ArrayDeque;
/*     */     //   141: invokevirtual isEmpty : ()Z
/*     */     //   144: aload #10
/*     */     //   146: ifnonnull -> 204
/*     */     //   149: goto -> 163
/*     */     //   152: ldc2_w -8950020701294250484
/*     */     //   155: lload #5
/*     */     //   157: <illegal opcode> w : (Ljava/lang/Exception;JJ)Ljava/lang/Exception;
/*     */     //   162: athrow
/*     */     //   163: ifeq -> 182
/*     */     //   166: goto -> 180
/*     */     //   169: ldc2_w -8950020701294250484
/*     */     //   172: lload #5
/*     */     //   174: <illegal opcode> w : (Ljava/lang/Exception;JJ)Ljava/lang/Exception;
/*     */     //   179: athrow
/*     */     //   180: iconst_0
/*     */     //   181: ireturn
/*     */     //   182: aload_0
/*     */     //   183: getfield i : Ljava/util/ArrayDeque;
/*     */     //   186: aload #4
/*     */     //   188: invokevirtual add : (Ljava/lang/Object;)Z
/*     */     //   191: pop
/*     */     //   192: aload_0
/*     */     //   193: iload #7
/*     */     //   195: i2s
/*     */     //   196: iload #8
/*     */     //   198: iload #9
/*     */     //   200: invokespecial b : (SII)V
/*     */     //   203: iconst_1
/*     */     //   204: ireturn
/*     */     // Line number table:
/*     */     //   Java source line number -> byte code offset
/*     */     //   #174	-> 67
/*     */     //   #93	-> 182
/*     */     //   #193	-> 192
/*     */     //   #181	-> 203
/*     */     // Exception table:
/*     */     //   from	to	target	type
/*     */     //   67	79	82	java/lang/IllegalArgumentException
/*     */     //   76	102	105	java/lang/IllegalArgumentException
/*     */     //   93	123	126	java/lang/IllegalArgumentException
/*     */     //   116	149	152	java/lang/IllegalArgumentException
/*     */     //   137	166	169	java/lang/IllegalArgumentException
/*     */   }
/*     */ 
/*     */ 
/*     */ 
/*     */ 
/*     */ 
/*     */   
/*     */   public boolean a(gZ paramgZ, long paramLong) {
/*     */     // Byte code:
/*     */     //   0: lload_2
/*     */     //   1: dup2
/*     */     //   2: ldc2_w 40464675046735
/*     */     //   5: lxor
/*     */     //   6: lstore #4
/*     */     //   8: pop2
/*     */     //   9: aload_1
/*     */     //   10: ifnonnull -> 44
/*     */     //   13: new java/lang/NullPointerException
/*     */     //   16: dup
/*     */     //   17: sipush #15059
/*     */     //   20: ldc2_w 6848858065383567924
/*     */     //   23: lload_2
/*     */     //   24: lxor
/*     */     //   25: <illegal opcode> o : (IJ)Ljava/lang/String;
/*     */     //   30: invokespecial <init> : (Ljava/lang/String;)V
/*     */     //   33: athrow
/*     */     //   34: ldc2_w 2695434284256727215
/*     */     //   37: lload_2
/*     */     //   38: <illegal opcode> w : (Ljava/lang/Exception;JJ)Ljava/lang/Exception;
/*     */     //   43: athrow
/*     */     //   44: aload_0
/*     */     //   45: aload_1
/*     */     //   46: iconst_2
/*     */     //   47: lload #4
/*     */     //   49: invokespecial a : (Lme/konsolas/aac/gZ;IJ)Z
/*     */     //   52: ireturn
/*     */     // Line number table:
/*     */     //   Java source line number -> byte code offset
/*     */     //   #183	-> 9
/*     */     //   #172	-> 44
/*     */     // Exception table:
/*     */     //   from	to	target	type
/*     */     //   9	34	34	java/lang/IllegalArgumentException
/*     */   }
/*     */ 
/*     */ 
/*     */ 
/*     */ 
/*     */ 
/*     */   
/*     */   private synchronized boolean a(gZ paramgZ, int paramInt, long paramLong) {
/*     */     // Byte code:
/*     */     //   0: getstatic me/konsolas/aac/dw.C : J
/*     */     //   3: lload_3
/*     */     //   4: lxor
/*     */     //   5: lstore_3
/*     */     //   6: lload_3
/*     */     //   7: dup2
/*     */     //   8: ldc2_w 31745485146974
/*     */     //   11: lxor
/*     */     //   12: dup2
/*     */     //   13: bipush #48
/*     */     //   15: lushr
/*     */     //   16: l2i
/*     */     //   17: istore #5
/*     */     //   19: dup2
/*     */     //   20: bipush #16
/*     */     //   22: lshl
/*     */     //   23: bipush #48
/*     */     //   25: lushr
/*     */     //   26: l2i
/*     */     //   27: istore #6
/*     */     //   29: dup2
/*     */     //   30: bipush #32
/*     */     //   32: lshl
/*     */     //   33: bipush #32
/*     */     //   35: lushr
/*     */     //   36: l2i
/*     */     //   37: istore #7
/*     */     //   39: pop2
/*     */     //   40: dup2
/*     */     //   41: ldc2_w 51999020310933
/*     */     //   44: lxor
/*     */     //   45: dup2
/*     */     //   46: bipush #48
/*     */     //   48: lushr
/*     */     //   49: l2i
/*     */     //   50: istore #8
/*     */     //   52: dup2
/*     */     //   53: bipush #16
/*     */     //   55: lshl
/*     */     //   56: bipush #32
/*     */     //   58: lushr
/*     */     //   59: l2i
/*     */     //   60: istore #9
/*     */     //   62: dup2
/*     */     //   63: bipush #48
/*     */     //   65: lshl
/*     */     //   66: bipush #48
/*     */     //   68: lushr
/*     */     //   69: l2i
/*     */     //   70: istore #10
/*     */     //   72: pop2
/*     */     //   73: pop2
/*     */     //   74: ldc2_w -3887144002486239642
/*     */     //   77: lload_3
/*     */     //   78: <illegal opcode> w : (JJ)[I
/*     */     //   83: astore #11
/*     */     //   85: aload_0
/*     */     //   86: getfield A : Z
/*     */     //   89: aload #11
/*     */     //   91: ifnonnull -> 155
/*     */     //   94: ifne -> 154
/*     */     //   97: goto -> 110
/*     */     //   100: ldc2_w -3872760693764849786
/*     */     //   103: lload_3
/*     */     //   104: <illegal opcode> w : (Ljava/lang/Exception;JJ)Ljava/lang/Exception;
/*     */     //   109: athrow
/*     */     //   110: aload_0
/*     */     //   111: getfield c : Z
/*     */     //   114: aload #11
/*     */     //   116: lload_3
/*     */     //   117: lconst_0
/*     */     //   118: lcmp
/*     */     //   119: iflt -> 172
/*     */     //   122: ifnonnull -> 170
/*     */     //   125: goto -> 138
/*     */     //   128: ldc2_w -3872760693764849786
/*     */     //   131: lload_3
/*     */     //   132: <illegal opcode> w : (Ljava/lang/Exception;JJ)Ljava/lang/Exception;
/*     */     //   137: athrow
/*     */     //   138: ifeq -> 156
/*     */     //   141: goto -> 154
/*     */     //   144: ldc2_w -3872760693764849786
/*     */     //   147: lload_3
/*     */     //   148: <illegal opcode> w : (Ljava/lang/Exception;JJ)Ljava/lang/Exception;
/*     */     //   153: athrow
/*     */     //   154: iconst_0
/*     */     //   155: ireturn
/*     */     //   156: aload_0
/*     */     //   157: getfield w : J
/*     */     //   160: aload_1
/*     */     //   161: invokevirtual a : ()I
/*     */     //   164: i2l
/*     */     //   165: ladd
/*     */     //   166: ldc2_w 16777216
/*     */     //   169: lcmp
/*     */     //   170: aload #11
/*     */     //   172: ifnonnull -> 263
/*     */     //   175: ifle -> 220
/*     */     //   178: goto -> 191
/*     */     //   181: ldc2_w -3872760693764849786
/*     */     //   184: lload_3
/*     */     //   185: <illegal opcode> w : (Ljava/lang/Exception;JJ)Ljava/lang/Exception;
/*     */     //   190: athrow
/*     */     //   191: aload_0
/*     */     //   192: iload #5
/*     */     //   194: i2c
/*     */     //   195: sipush #1001
/*     */     //   198: iload #6
/*     */     //   200: i2c
/*     */     //   201: aconst_null
/*     */     //   202: iload #7
/*     */     //   204: invokevirtual a : (CICLjava/lang/String;I)Z
/*     */     //   207: pop
/*     */     //   208: iconst_0
/*     */     //   209: ireturn
/*     */     //   210: ldc2_w -3872760693764849786
/*     */     //   213: lload_3
/*     */     //   214: <illegal opcode> w : (Ljava/lang/Exception;JJ)Ljava/lang/Exception;
/*     */     //   219: athrow
/*     */     //   220: aload_0
/*     */     //   221: dup
/*     */     //   222: getfield w : J
/*     */     //   225: aload_1
/*     */     //   226: invokevirtual a : ()I
/*     */     //   229: i2l
/*     */     //   230: ladd
/*     */     //   231: putfield w : J
/*     */     //   234: aload_0
/*     */     //   235: getfield b : Ljava/util/ArrayDeque;
/*     */     //   238: new me/konsolas/aac/hc
/*     */     //   241: dup
/*     */     //   242: iload_2
/*     */     //   243: aload_1
/*     */     //   244: invokespecial <init> : (ILme/konsolas/aac/gZ;)V
/*     */     //   247: invokevirtual add : (Ljava/lang/Object;)Z
/*     */     //   250: pop
/*     */     //   251: aload_0
/*     */     //   252: iload #8
/*     */     //   254: i2s
/*     */     //   255: iload #9
/*     */     //   257: iload #10
/*     */     //   259: invokespecial b : (SII)V
/*     */     //   262: iconst_1
/*     */     //   263: ireturn
/*     */     // Line number table:
/*     */     //   Java source line number -> byte code offset
/*     */     //   #187	-> 85
/*     */     //   #96	-> 156
/*     */     //   #38	-> 191
/*     */     //   #163	-> 208
/*     */     //   #7	-> 220
/*     */     //   #80	-> 234
/*     */     //   #219	-> 251
/*     */     //   #134	-> 262
/*     */     // Exception table:
/*     */     //   from	to	target	type
/*     */     //   85	97	100	java/lang/IllegalArgumentException
/*     */     //   94	125	128	java/lang/IllegalArgumentException
/*     */     //   110	141	144	java/lang/IllegalArgumentException
/*     */     //   170	178	181	java/lang/IllegalArgumentException
/*     */     //   175	210	210	java/lang/IllegalArgumentException
/*     */   }
/*     */ 
/*     */ 
/*     */ 
/*     */ 
/*     */   
/*     */   void a(H paramH, short paramShort, char paramChar, int paramInt, @Nullable ec paramec) {
/*     */     // Byte code:
/*     */     //   0: iload_2
/*     */     //   1: i2l
/*     */     //   2: bipush #48
/*     */     //   4: lshl
/*     */     //   5: iload_3
/*     */     //   6: i2l
/*     */     //   7: bipush #48
/*     */     //   9: lshl
/*     */     //   10: bipush #16
/*     */     //   12: lushr
/*     */     //   13: lor
/*     */     //   14: iload #4
/*     */     //   16: i2l
/*     */     //   17: bipush #32
/*     */     //   19: lshl
/*     */     //   20: bipush #32
/*     */     //   22: lushr
/*     */     //   23: lor
/*     */     //   24: getstatic me/konsolas/aac/dw.C : J
/*     */     //   27: lxor
/*     */     //   28: lstore #6
/*     */     //   30: lload #6
/*     */     //   32: dup2
/*     */     //   33: ldc2_w 92867314344304
/*     */     //   36: lxor
/*     */     //   37: dup2
/*     */     //   38: bipush #32
/*     */     //   40: lushr
/*     */     //   41: l2i
/*     */     //   42: istore #8
/*     */     //   44: dup2
/*     */     //   45: bipush #32
/*     */     //   47: lshl
/*     */     //   48: bipush #48
/*     */     //   50: lushr
/*     */     //   51: l2i
/*     */     //   52: istore #9
/*     */     //   54: dup2
/*     */     //   55: bipush #48
/*     */     //   57: lshl
/*     */     //   58: bipush #48
/*     */     //   60: lushr
/*     */     //   61: l2i
/*     */     //   62: istore #10
/*     */     //   64: pop2
/*     */     //   65: dup2
/*     */     //   66: ldc2_w 95117267435308
/*     */     //   69: lxor
/*     */     //   70: lstore #11
/*     */     //   72: dup2
/*     */     //   73: ldc2_w 30945548614110
/*     */     //   76: lxor
/*     */     //   77: lstore #13
/*     */     //   79: dup2
/*     */     //   80: ldc2_w 82319543666934
/*     */     //   83: lxor
/*     */     //   84: lstore #15
/*     */     //   86: pop2
/*     */     //   87: ldc2_w 5362166654675254786
/*     */     //   90: lload #6
/*     */     //   92: <illegal opcode> w : (JJ)[I
/*     */     //   97: astore #17
/*     */     //   99: aload_1
/*     */     //   100: aload #17
/*     */     //   102: ifnonnull -> 244
/*     */     //   105: invokevirtual a : ()I
/*     */     //   108: bipush #101
/*     */     //   110: if_icmpeq -> 243
/*     */     //   113: goto -> 127
/*     */     //   116: ldc2_w 5342704693155233762
/*     */     //   119: lload #6
/*     */     //   121: <illegal opcode> w : (Ljava/lang/Exception;JJ)Ljava/lang/Exception;
/*     */     //   126: athrow
/*     */     //   127: new java/net/ProtocolException
/*     */     //   130: dup
/*     */     //   131: new java/lang/StringBuilder
/*     */     //   134: dup
/*     */     //   135: invokespecial <init> : ()V
/*     */     //   138: sipush #17493
/*     */     //   141: ldc2_w 199581431663109095
/*     */     //   144: lload #6
/*     */     //   146: lxor
/*     */     //   147: <illegal opcode> o : (IJ)Ljava/lang/String;
/*     */     //   152: invokevirtual append : (Ljava/lang/String;)Ljava/lang/StringBuilder;
/*     */     //   155: aload_1
/*     */     //   156: invokevirtual a : ()I
/*     */     //   159: invokevirtual append : (I)Ljava/lang/StringBuilder;
/*     */     //   162: ldc_w ''
/*     */     //   165: invokevirtual toCharArray : ()[C
/*     */     //   168: dup
/*     */     //   169: dup
/*     */     //   170: iconst_0
/*     */     //   171: dup_x1
/*     */     //   172: caload
/*     */     //   173: sipush #14813
/*     */     //   176: ixor
/*     */     //   177: i2c
/*     */     //   178: castore
/*     */     //   179: sipush #29782
/*     */     //   182: iconst_0
/*     */     //   183: iconst_1
/*     */     //   184: invokestatic X : (Ljava/lang/Object;SZZ)Ljava/lang/String;
/*     */     //   187: invokevirtual append : (Ljava/lang/String;)Ljava/lang/StringBuilder;
/*     */     //   190: aload_1
/*     */     //   191: invokevirtual a : ()Ljava/lang/String;
/*     */     //   194: invokevirtual append : (Ljava/lang/String;)Ljava/lang/StringBuilder;
/*     */     //   197: ldc_w ''
/*     */     //   200: invokevirtual toCharArray : ()[C
/*     */     //   203: dup
/*     */     //   204: dup
/*     */     //   205: iconst_0
/*     */     //   206: dup_x1
/*     */     //   207: caload
/*     */     //   208: sipush #24978
/*     */     //   211: ixor
/*     */     //   212: i2c
/*     */     //   213: castore
/*     */     //   214: sipush #18519
/*     */     //   217: iconst_1
/*     */     //   218: iconst_0
/*     */     //   219: invokestatic X : (Ljava/lang/Object;SZZ)Ljava/lang/String;
/*     */     //   222: invokevirtual append : (Ljava/lang/String;)Ljava/lang/StringBuilder;
/*     */     //   225: invokevirtual toString : ()Ljava/lang/String;
/*     */     //   228: invokespecial <init> : (Ljava/lang/String;)V
/*     */     //   231: athrow
/*     */     //   232: ldc2_w 5342704693155233762
/*     */     //   235: lload #6
/*     */     //   237: <illegal opcode> w : (Ljava/lang/Exception;JJ)Ljava/lang/Exception;
/*     */     //   242: athrow
/*     */     //   243: aload_1
/*     */     //   244: lload #15
/*     */     //   246: sipush #5319
/*     */     //   249: ldc2_w 4473502492425352037
/*     */     //   252: lload #6
/*     */     //   254: lxor
/*     */     //   255: <illegal opcode> o : (IJ)Ljava/lang/String;
/*     */     //   260: invokevirtual a : (JLjava/lang/String;)Ljava/lang/String;
/*     */     //   263: astore #18
/*     */     //   265: sipush #9885
/*     */     //   268: iload_3
/*     */     //   269: ifle -> 293
/*     */     //   272: ldc2_w 3058982551029596464
/*     */     //   275: lload #6
/*     */     //   277: lxor
/*     */     //   278: <illegal opcode> o : (IJ)Ljava/lang/String;
/*     */     //   283: aload #17
/*     */     //   285: ifnonnull -> 409
/*     */     //   288: aload #18
/*     */     //   290: invokevirtual equalsIgnoreCase : (Ljava/lang/String;)Z
/*     */     //   293: ifne -> 389
/*     */     //   296: goto -> 310
/*     */     //   299: ldc2_w 5342704693155233762
/*     */     //   302: lload #6
/*     */     //   304: <illegal opcode> w : (Ljava/lang/Exception;JJ)Ljava/lang/Exception;
/*     */     //   309: athrow
/*     */     //   310: new java/net/ProtocolException
/*     */     //   313: dup
/*     */     //   314: new java/lang/StringBuilder
/*     */     //   317: dup
/*     */     //   318: invokespecial <init> : ()V
/*     */     //   321: sipush #22797
/*     */     //   324: ldc2_w 2376831878560136885
/*     */     //   327: lload #6
/*     */     //   329: lxor
/*     */     //   330: <illegal opcode> o : (IJ)Ljava/lang/String;
/*     */     //   335: invokevirtual append : (Ljava/lang/String;)Ljava/lang/StringBuilder;
/*     */     //   338: aload #18
/*     */     //   340: invokevirtual append : (Ljava/lang/String;)Ljava/lang/StringBuilder;
/*     */     //   343: ldc_w ''
/*     */     //   346: invokevirtual toCharArray : ()[C
/*     */     //   349: dup
/*     */     //   350: dup
/*     */     //   351: iconst_0
/*     */     //   352: dup_x1
/*     */     //   353: caload
/*     */     //   354: sipush #4926
/*     */     //   357: ixor
/*     */     //   358: i2c
/*     */     //   359: castore
/*     */     //   360: sipush #7769
/*     */     //   363: iconst_1
/*     */     //   364: iconst_0
/*     */     //   365: invokestatic X : (Ljava/lang/Object;SZZ)Ljava/lang/String;
/*     */     //   368: invokevirtual append : (Ljava/lang/String;)Ljava/lang/StringBuilder;
/*     */     //   371: invokevirtual toString : ()Ljava/lang/String;
/*     */     //   374: invokespecial <init> : (Ljava/lang/String;)V
/*     */     //   377: athrow
/*     */     //   378: ldc2_w 5342704693155233762
/*     */     //   381: lload #6
/*     */     //   383: <illegal opcode> w : (Ljava/lang/Exception;JJ)Ljava/lang/Exception;
/*     */     //   388: athrow
/*     */     //   389: aload_1
/*     */     //   390: lload #15
/*     */     //   392: sipush #9885
/*     */     //   395: ldc2_w 3058982551029596464
/*     */     //   398: lload #6
/*     */     //   400: lxor
/*     */     //   401: <illegal opcode> o : (IJ)Ljava/lang/String;
/*     */     //   406: invokevirtual a : (JLjava/lang/String;)Ljava/lang/String;
/*     */     //   409: astore #19
/*     */     //   411: sipush #16644
/*     */     //   414: iload_3
/*     */     //   415: iflt -> 439
/*     */     //   418: ldc2_w 5712570039568803509
/*     */     //   421: lload #6
/*     */     //   423: lxor
/*     */     //   424: <illegal opcode> o : (IJ)Ljava/lang/String;
/*     */     //   429: aload #17
/*     */     //   431: ifnonnull -> 555
/*     */     //   434: aload #19
/*     */     //   436: invokevirtual equalsIgnoreCase : (Ljava/lang/String;)Z
/*     */     //   439: ifne -> 535
/*     */     //   442: goto -> 456
/*     */     //   445: ldc2_w 5342704693155233762
/*     */     //   448: lload #6
/*     */     //   450: <illegal opcode> w : (Ljava/lang/Exception;JJ)Ljava/lang/Exception;
/*     */     //   455: athrow
/*     */     //   456: new java/net/ProtocolException
/*     */     //   459: dup
/*     */     //   460: new java/lang/StringBuilder
/*     */     //   463: dup
/*     */     //   464: invokespecial <init> : ()V
/*     */     //   467: sipush #22474
/*     */     //   470: ldc2_w 1897133360193712237
/*     */     //   473: lload #6
/*     */     //   475: lxor
/*     */     //   476: <illegal opcode> o : (IJ)Ljava/lang/String;
/*     */     //   481: invokevirtual append : (Ljava/lang/String;)Ljava/lang/StringBuilder;
/*     */     //   484: aload #19
/*     */     //   486: invokevirtual append : (Ljava/lang/String;)Ljava/lang/StringBuilder;
/*     */     //   489: ldc_w ''
/*     */     //   492: invokevirtual toCharArray : ()[C
/*     */     //   495: dup
/*     */     //   496: dup
/*     */     //   497: iconst_0
/*     */     //   498: dup_x1
/*     */     //   499: caload
/*     */     //   500: sipush #32373
/*     */     //   503: ixor
/*     */     //   504: i2c
/*     */     //   505: castore
/*     */     //   506: sipush #2512
/*     */     //   509: iconst_0
/*     */     //   510: iconst_0
/*     */     //   511: invokestatic X : (Ljava/lang/Object;SZZ)Ljava/lang/String;
/*     */     //   514: invokevirtual append : (Ljava/lang/String;)Ljava/lang/StringBuilder;
/*     */     //   517: invokevirtual toString : ()Ljava/lang/String;
/*     */     //   520: invokespecial <init> : (Ljava/lang/String;)V
/*     */     //   523: athrow
/*     */     //   524: ldc2_w 5342704693155233762
/*     */     //   527: lload #6
/*     */     //   529: <illegal opcode> w : (Ljava/lang/Exception;JJ)Ljava/lang/Exception;
/*     */     //   534: athrow
/*     */     //   535: aload_1
/*     */     //   536: lload #15
/*     */     //   538: sipush #5106
/*     */     //   541: ldc2_w 5333484268275758161
/*     */     //   544: lload #6
/*     */     //   546: lxor
/*     */     //   547: <illegal opcode> o : (IJ)Ljava/lang/String;
/*     */     //   552: invokevirtual a : (JLjava/lang/String;)Ljava/lang/String;
/*     */     //   555: astore #20
/*     */     //   557: new java/lang/StringBuilder
/*     */     //   560: dup
/*     */     //   561: invokespecial <init> : ()V
/*     */     //   564: aload_0
/*     */     //   565: getfield h : Ljava/lang/String;
/*     */     //   568: invokevirtual append : (Ljava/lang/String;)Ljava/lang/StringBuilder;
/*     */     //   571: sipush #23517
/*     */     //   574: ldc2_w 258414649885015155
/*     */     //   577: lload #6
/*     */     //   579: lxor
/*     */     //   580: <illegal opcode> o : (IJ)Ljava/lang/String;
/*     */     //   585: invokevirtual append : (Ljava/lang/String;)Ljava/lang/StringBuilder;
/*     */     //   588: invokevirtual toString : ()Ljava/lang/String;
/*     */     //   591: lload #11
/*     */     //   593: invokestatic a : (Ljava/lang/String;J)Lme/konsolas/aac/gZ;
/*     */     //   596: iload #8
/*     */     //   598: iload #9
/*     */     //   600: iload #10
/*     */     //   602: invokevirtual a : (III)Lme/konsolas/aac/gZ;
/*     */     //   605: lload #13
/*     */     //   607: invokevirtual b : (J)Ljava/lang/String;
/*     */     //   610: astore #21
/*     */     //   612: iload #4
/*     */     //   614: iflt -> 728
/*     */     //   617: aload #21
/*     */     //   619: aload #20
/*     */     //   621: invokevirtual equals : (Ljava/lang/Object;)Z
/*     */     //   624: ifne -> 728
/*     */     //   627: new java/net/ProtocolException
/*     */     //   630: dup
/*     */     //   631: new java/lang/StringBuilder
/*     */     //   634: dup
/*     */     //   635: invokespecial <init> : ()V
/*     */     //   638: sipush #30055
/*     */     //   641: ldc2_w 725242406362911436
/*     */     //   644: lload #6
/*     */     //   646: lxor
/*     */     //   647: <illegal opcode> o : (IJ)Ljava/lang/String;
/*     */     //   652: invokevirtual append : (Ljava/lang/String;)Ljava/lang/StringBuilder;
/*     */     //   655: aload #21
/*     */     //   657: invokevirtual append : (Ljava/lang/String;)Ljava/lang/StringBuilder;
/*     */     //   660: sipush #13648
/*     */     //   663: ldc2_w 5880421773874549478
/*     */     //   666: lload #6
/*     */     //   668: lxor
/*     */     //   669: <illegal opcode> o : (IJ)Ljava/lang/String;
/*     */     //   674: invokevirtual append : (Ljava/lang/String;)Ljava/lang/StringBuilder;
/*     */     //   677: aload #20
/*     */     //   679: invokevirtual append : (Ljava/lang/String;)Ljava/lang/StringBuilder;
/*     */     //   682: ldc_w ''
/*     */     //   685: invokevirtual toCharArray : ()[C
/*     */     //   688: dup
/*     */     //   689: dup
/*     */     //   690: iconst_0
/*     */     //   691: dup_x1
/*     */     //   692: caload
/*     */     //   693: sipush #6891
/*     */     //   696: ixor
/*     */     //   697: i2c
/*     */     //   698: castore
/*     */     //   699: sipush #2768
/*     */     //   702: iconst_0
/*     */     //   703: iconst_1
/*     */     //   704: invokestatic X : (Ljava/lang/Object;SZZ)Ljava/lang/String;
/*     */     //   707: invokevirtual append : (Ljava/lang/String;)Ljava/lang/StringBuilder;
/*     */     //   710: invokevirtual toString : ()Ljava/lang/String;
/*     */     //   713: invokespecial <init> : (Ljava/lang/String;)V
/*     */     //   716: athrow
/*     */     //   717: ldc2_w 5342704693155233762
/*     */     //   720: lload #6
/*     */     //   722: <illegal opcode> w : (Ljava/lang/Exception;JJ)Ljava/lang/Exception;
/*     */     //   727: athrow
/*     */     //   728: aload #5
/*     */     //   730: ifnonnull -> 766
/*     */     //   733: new java/net/ProtocolException
/*     */     //   736: dup
/*     */     //   737: sipush #27926
/*     */     //   740: ldc2_w 8885416535594502835
/*     */     //   743: lload #6
/*     */     //   745: lxor
/*     */     //   746: <illegal opcode> o : (IJ)Ljava/lang/String;
/*     */     //   751: invokespecial <init> : (Ljava/lang/String;)V
/*     */     //   754: athrow
/*     */     //   755: ldc2_w 5342704693155233762
/*     */     //   758: lload #6
/*     */     //   760: <illegal opcode> w : (Ljava/lang/Exception;JJ)Ljava/lang/Exception;
/*     */     //   765: athrow
/*     */     //   766: return
/*     */     // Line number table:
/*     */     //   Java source line number -> byte code offset
/*     */     //   #189	-> 99
/*     */     //   #165	-> 127
/*     */     //   #98	-> 156
/*     */     //   #213	-> 243
/*     */     //   #18	-> 265
/*     */     //   #74	-> 310
/*     */     //   #55	-> 389
/*     */     //   #42	-> 411
/*     */     //   #82	-> 456
/*     */     //   #140	-> 535
/*     */     //   #218	-> 557
/*     */     //   #79	-> 596
/*     */     //   #205	-> 612
/*     */     //   #25	-> 627
/*     */     //   #186	-> 728
/*     */     //   #70	-> 733
/*     */     //   #102	-> 766
/*     */     // Exception table:
/*     */     //   from	to	target	type
/*     */     //   99	113	116	java/io/IOException
/*     */     //   105	232	232	java/io/IOException
/*     */     //   265	296	299	java/io/IOException
/*     */     //   288	378	378	java/io/IOException
/*     */     //   411	442	445	java/io/IOException
/*     */     //   434	524	524	java/io/IOException
/*     */     //   612	717	717	java/io/IOException
/*     */     //   728	755	755	java/io/IOException
/*     */   }
/*     */ 
/*     */ 
/*     */ 
/*     */ 
/*     */   
/*     */   void a(int paramInt, TimeUnit paramTimeUnit) {
/* 216 */     this.x.awaitTermination(paramInt, paramTimeUnit);
/*     */   }
/*     */   
/*     */   synchronized int b() {
/* 220 */     return this.a;
/*     */   }
/*     */   
/*     */   static {
/*     */     // Byte code:
/*     */     //   0: ldc2_w 7692354781371383390
/*     */     //   3: ldc2_w 3634189521185546816
/*     */     //   6: invokestatic lookup : ()Ljava/lang/invoke/MethodHandles$Lookup;
/*     */     //   9: invokevirtual lookupClass : ()Ljava/lang/Class;
/*     */     //   12: invokestatic a : (JJLjava/lang/Object;)Lme/konsolas/aac/na;
/*     */     //   15: ldc2_w 101368722471651
/*     */     //   18: invokeinterface a : (J)J
/*     */     //   23: putstatic me/konsolas/aac/dw.C : J
/*     */     //   26: getstatic me/konsolas/aac/dw.C : J
/*     */     //   29: ldc2_w 22007015431148
/*     */     //   32: lxor
/*     */     //   33: lstore #9
/*     */     //   35: aconst_null
/*     */     //   36: new java/util/HashMap
/*     */     //   39: dup
/*     */     //   40: bipush #13
/*     */     //   42: invokespecial <init> : (I)V
/*     */     //   45: putstatic me/konsolas/aac/dw.F : Ljava/util/Map;
/*     */     //   48: ldc2_w -5763152357464603095
/*     */     //   51: lload #9
/*     */     //   53: <illegal opcode> w : ([IJJ)V
/*     */     //   58: ldc_w '?'
/*     */     //   61: invokevirtual toCharArray : ()[C
/*     */     //   64: dup
/*     */     //   65: dup
/*     */     //   66: iconst_2
/*     */     //   67: dup_x1
/*     */     //   68: caload
/*     */     //   69: sipush #1484
/*     */     //   72: ixor
/*     */     //   73: i2c
/*     */     //   74: castore
/*     */     //   75: sipush #25472
/*     */     //   78: iconst_1
/*     */     //   79: iconst_3
/*     */     //   80: invokestatic A : (Ljava/lang/Object;SZI)Ljava/lang/String;
/*     */     //   83: invokestatic getInstance : (Ljava/lang/String;)Ljavax/crypto/Cipher;
/*     */     //   86: dup
/*     */     //   87: astore_0
/*     */     //   88: iconst_2
/*     */     //   89: ldc_w '?'
/*     */     //   92: invokevirtual toCharArray : ()[C
/*     */     //   95: dup
/*     */     //   96: dup
/*     */     //   97: iconst_1
/*     */     //   98: dup_x1
/*     */     //   99: caload
/*     */     //   100: sipush #16507
/*     */     //   103: ixor
/*     */     //   104: i2c
/*     */     //   105: castore
/*     */     //   106: sipush #24859
/*     */     //   109: iconst_0
/*     */     //   110: iconst_2
/*     */     //   111: invokestatic A : (Ljava/lang/Object;SZI)Ljava/lang/String;
/*     */     //   114: invokestatic getInstance : (Ljava/lang/String;)Ljavax/crypto/SecretKeyFactory;
/*     */     //   117: bipush #8
/*     */     //   119: newarray byte
/*     */     //   121: dup
/*     */     //   122: iconst_0
/*     */     //   123: lload #9
/*     */     //   125: bipush #56
/*     */     //   127: lushr
/*     */     //   128: l2i
/*     */     //   129: i2b
/*     */     //   130: bastore
/*     */     //   131: iconst_1
/*     */     //   132: istore_1
/*     */     //   133: iload_1
/*     */     //   134: bipush #8
/*     */     //   136: if_icmpge -> 160
/*     */     //   139: dup
/*     */     //   140: iload_1
/*     */     //   141: lload #9
/*     */     //   143: iload_1
/*     */     //   144: bipush #8
/*     */     //   146: imul
/*     */     //   147: lshl
/*     */     //   148: bipush #56
/*     */     //   150: lushr
/*     */     //   151: l2i
/*     */     //   152: i2b
/*     */     //   153: bastore
/*     */     //   154: iinc #1, 1
/*     */     //   157: goto -> 133
/*     */     //   160: new javax/crypto/spec/DESKeySpec
/*     */     //   163: dup_x1
/*     */     //   164: swap
/*     */     //   165: invokespecial <init> : ([B)V
/*     */     //   168: invokevirtual generateSecret : (Ljava/security/spec/KeySpec;)Ljavax/crypto/SecretKey;
/*     */     //   171: new javax/crypto/spec/IvParameterSpec
/*     */     //   174: dup
/*     */     //   175: bipush #8
/*     */     //   177: newarray byte
/*     */     //   179: invokespecial <init> : ([B)V
/*     */     //   182: invokevirtual init : (ILjava/security/Key;Ljava/security/spec/AlgorithmParameterSpec;)V
/*     */     //   185: bipush #26
/*     */     //   187: anewarray java/lang/String
/*     */     //   190: astore #7
/*     */     //   192: iconst_0
/*     */     //   193: istore #5
/*     */     //   195: ldc_w '?????????????????????????Q'
/*     */     //   198: invokevirtual toCharArray : ()[C
/*     */     //   201: dup
/*     */     //   202: dup
/*     */     //   203: sipush #208
/*     */     //   206: dup_x1
/*     */     //   207: caload
/*     */     //   208: sipush #25143
/*     */     //   211: ixor
/*     */     //   212: i2c
/*     */     //   213: castore
/*     */     //   214: sipush #5342
/*     */     //   217: iconst_0
/*     */     //   218: iconst_1
/*     */     //   219: invokestatic A : (Ljava/lang/Object;SZI)Ljava/lang/String;
/*     */     //   222: dup
/*     */     //   223: astore #4
/*     */     //   225: invokevirtual length : ()I
/*     */     //   228: istore #6
/*     */     //   230: bipush #48
/*     */     //   232: istore_3
/*     */     //   233: iconst_m1
/*     */     //   234: istore_2
/*     */     //   235: iinc #2, 1
/*     */     //   238: aload #4
/*     */     //   240: iload_2
/*     */     //   241: dup
/*     */     //   242: iload_3
/*     */     //   243: iadd
/*     */     //   244: invokevirtual substring : (II)Ljava/lang/String;
/*     */     //   247: iconst_m1
/*     */     //   248: goto -> 382
/*     */     //   251: aload #7
/*     */     //   253: swap
/*     */     //   254: iload #5
/*     */     //   256: iinc #5, 1
/*     */     //   259: swap
/*     */     //   260: aastore
/*     */     //   261: iload_2
/*     */     //   262: iload_3
/*     */     //   263: iadd
/*     */     //   264: dup
/*     */     //   265: istore_2
/*     */     //   266: iload #6
/*     */     //   268: if_icmpge -> 281
/*     */     //   271: aload #4
/*     */     //   273: iload_2
/*     */     //   274: invokevirtual charAt : (I)C
/*     */     //   277: istore_3
/*     */     //   278: goto -> 235
/*     */     //   281: ldc_w '????'
/*     */     //   284: invokevirtual toCharArray : ()[C
/*     */     //   287: dup
/*     */     //   288: dup
/*     */     //   289: bipush #27
/*     */     //   291: dup_x1
/*     */     //   292: caload
/*     */     //   293: sipush #9202
/*     */     //   296: ixor
/*     */     //   297: i2c
/*     */     //   298: castore
/*     */     //   299: sipush #27890
/*     */     //   302: iconst_0
/*     */     //   303: iconst_1
/*     */     //   304: invokestatic A : (Ljava/lang/Object;SZI)Ljava/lang/String;
/*     */     //   307: dup
/*     */     //   308: astore #4
/*     */     //   310: invokevirtual length : ()I
/*     */     //   313: istore #6
/*     */     //   315: bipush #80
/*     */     //   317: istore_3
/*     */     //   318: iconst_m1
/*     */     //   319: istore_2
/*     */     //   320: iinc #2, 1
/*     */     //   323: aload #4
/*     */     //   325: iload_2
/*     */     //   326: dup
/*     */     //   327: iload_3
/*     */     //   328: iadd
/*     */     //   329: invokevirtual substring : (II)Ljava/lang/String;
/*     */     //   332: iconst_0
/*     */     //   333: goto -> 382
/*     */     //   336: aload #7
/*     */     //   338: swap
/*     */     //   339: iload #5
/*     */     //   341: iinc #5, 1
/*     */     //   344: swap
/*     */     //   345: aastore
/*     */     //   346: iload_2
/*     */     //   347: iload_3
/*     */     //   348: iadd
/*     */     //   349: dup
/*     */     //   350: istore_2
/*     */     //   351: iload #6
/*     */     //   353: if_icmpge -> 366
/*     */     //   356: aload #4
/*     */     //   358: iload_2
/*     */     //   359: invokevirtual charAt : (I)C
/*     */     //   362: istore_3
/*     */     //   363: goto -> 320
/*     */     //   366: aload #7
/*     */     //   368: putstatic me/konsolas/aac/dw.D : [Ljava/lang/String;
/*     */     //   371: bipush #26
/*     */     //   373: anewarray java/lang/String
/*     */     //   376: putstatic me/konsolas/aac/dw.E : [Ljava/lang/String;
/*     */     //   379: goto -> 444
/*     */     //   382: swap
/*     */     //   383: ldc_w ''
/*     */     //   386: invokevirtual toCharArray : ()[C
/*     */     //   389: dup
/*     */     //   390: dup
/*     */     //   391: iconst_0
/*     */     //   392: dup_x1
/*     */     //   393: caload
/*     */     //   394: sipush #30526
/*     */     //   397: ixor
/*     */     //   398: i2c
/*     */     //   399: castore
/*     */     //   400: sipush #1959
/*     */     //   403: iconst_0
/*     */     //   404: iconst_1
/*     */     //   405: invokestatic A : (Ljava/lang/Object;SZI)Ljava/lang/String;
/*     */     //   408: invokevirtual getBytes : (Ljava/lang/String;)[B
/*     */     //   411: aload_0
/*     */     //   412: swap
/*     */     //   413: invokevirtual doFinal : ([B)[B
/*     */     //   416: astore #8
/*     */     //   418: aload #8
/*     */     //   420: invokestatic a : ([B)Ljava/lang/String;
/*     */     //   423: invokevirtual intern : ()Ljava/lang/String;
/*     */     //   426: swap
/*     */     //   427: tableswitch default -> 251, 0 -> 336
/*     */     //   444: ldc me/konsolas/aac/dw
/*     */     //   446: invokevirtual desiredAssertionStatus : ()Z
/*     */     //   449: ifne -> 467
/*     */     //   452: iconst_1
/*     */     //   453: goto -> 468
/*     */     //   456: ldc2_w -5715909648698866326
/*     */     //   459: lload #9
/*     */     //   461: <illegal opcode> w : (Ljava/lang/Exception;JJ)Ljava/lang/Exception;
/*     */     //   466: athrow
/*     */     //   467: iconst_0
/*     */     //   468: putstatic me/konsolas/aac/dw.p : Z
/*     */     //   471: getstatic me/konsolas/aac/le.HTTP_1_1 : Lme/konsolas/aac/le;
/*     */     //   474: invokestatic singletonList : (Ljava/lang/Object;)Ljava/util/List;
/*     */     //   477: putstatic me/konsolas/aac/dw.f : Ljava/util/List;
/*     */     //   480: return
/*     */     // Line number table:
/*     */     //   Java source line number -> byte code offset
/*     */     //   #22	-> 444
/*     */     //   #68	-> 471
/*     */     // Exception table:
/*     */     //   from	to	target	type
/*     */     //   444	456	456	java/lang/IllegalArgumentException
/*     */   }
/*     */   
/*     */   public static void b(int[] paramArrayOfint) {
/*     */     v = paramArrayOfint;
/*     */   }
/*     */   
/*     */   public static int[] b() {
/*     */     return v;
/*     */   }
/*     */   
/*     */   private static Exception a(Exception paramException) {
/*     */     return paramException;
/*     */   }
/*     */   
/*     */   private static String a(byte[] paramArrayOfbyte) {
/*     */     byte b1 = 0;
/*     */     int i;
/*     */     char[] arrayOfChar = new char[i = paramArrayOfbyte.length];
/*     */     for (byte b2 = 0; b2 < i; b2++) {
/*     */       int j;
/*     */       if ((j = 0xFF & paramArrayOfbyte[b2]) < 192) {
/*     */         arrayOfChar[b1++] = (char)j;
/*     */       } else if (j < 224) {
/*     */         char c = (char)((char)(j & 0x1F) << 6);
/*     */         j = paramArrayOfbyte[++b2];
/*     */         c = (char)(c | (char)(j & 0x3F));
/*     */         arrayOfChar[b1++] = c;
/*     */       } else if (b2 < i - 2) {
/*     */         char c = (char)((char)(j & 0xF) << 12);
/*     */         j = paramArrayOfbyte[++b2];
/*     */         c = (char)(c | (char)(j & 0x3F) << 6);
/*     */         j = paramArrayOfbyte[++b2];
/*     */         c = (char)(c | (char)(j & 0x3F));
/*     */         arrayOfChar[b1++] = c;
/*     */       } 
/*     */     } 
/*     */     return new String(arrayOfChar, 0, b1);
/*     */   }
/*     */   
/*     */   private static String a(int paramInt, long paramLong) {
/*     */     int i = paramInt ^ (int)(paramLong & 0x7FFFL) ^ 0x2CA3;
/*     */     if (E[i] == null) {
/*     */       Object[] arrayOfObject;
/*     */       try {
/*     */         Long long_ = Long.valueOf(Thread.currentThread().getId());
/*     */         arrayOfObject = (Object[])F.get(long_);
/*     */         if (arrayOfObject == null) {
/*     */           arrayOfObject = new Object[3];
/*     */           "".toCharArray()[8] = (char)("".toCharArray()[8] ^ 0x7DC);
/*     */           arrayOfObject[0] = Cipher.getInstance(fW$gy.A("".toCharArray(), (short)2090, false, 5));
/*     */           "".toCharArray()[1] = (char)("".toCharArray()[1] ^ 0x2CEF);
/*     */           arrayOfObject[1] = SecretKeyFactory.getInstance(fW$gy.A("".toCharArray(), (short)23289, true, 1));
/*     */           arrayOfObject[2] = new IvParameterSpec(new byte[8]);
/*     */           F.put(long_, arrayOfObject);
/*     */         } 
/*     */       } catch (Exception exception) {
/*     */         "".toCharArray()[17] = (char)("".toCharArray()[17] ^ 0x309E);
/*     */         throw new RuntimeException(fW$gy.A("".toCharArray(), (short)10944, false, 5), exception);
/*     */       } 
/*     */       byte[] arrayOfByte1 = new byte[8];
/*     */       arrayOfByte1[0] = (byte)(int)(paramLong >>> 56L);
/*     */       for (byte b = 1; b < 8; b++)
/*     */         arrayOfByte1[b] = (byte)(int)(paramLong << b * 8 >>> 56L); 
/*     */       DESKeySpec dESKeySpec = new DESKeySpec(arrayOfByte1);
/*     */       SecretKey secretKey = ((SecretKeyFactory)arrayOfObject[1]).generateSecret(dESKeySpec);
/*     */       ((Cipher)arrayOfObject[0]).init(2, secretKey, (IvParameterSpec)arrayOfObject[2]);
/*     */       "".toCharArray()[8] = (char)("".toCharArray()[8] ^ 0x5C62);
/*     */       byte[] arrayOfByte2 = D[i].getBytes(fW$gy.A("".toCharArray(), (short)14754, true, 5));
/*     */       E[i] = a(((Cipher)arrayOfObject[0]).doFinal(arrayOfByte2));
/*     */     } 
/*     */     return E[i];
/*     */   }
/*     */   
/*     */   private static Object a(MethodHandles.Lookup paramLookup, MutableCallSite paramMutableCallSite, String paramString, Object[] paramArrayOfObject) {
/*     */     int i = ((Integer)paramArrayOfObject[0]).intValue();
/*     */     long l = ((Long)paramArrayOfObject[1]).longValue();
/*     */     String str = a(i, l);
/*     */     MethodHandle methodHandle = MethodHandles.constant(String.class, str);
/*     */     paramMutableCallSite.setTarget(MethodHandles.dropArguments(methodHandle, 0, new Class[] { int.class, long.class }));
/*     */     return str;
/*     */   }
/*     */   
/*     */   private static CallSite a(MethodHandles.Lookup paramLookup, String paramString, MethodType paramMethodType) {
/*     */     // Byte code:
/*     */     //   0: new java/lang/invoke/MutableCallSite
/*     */     //   3: dup
/*     */     //   4: aload_2
/*     */     //   5: invokespecial <init> : (Ljava/lang/invoke/MethodType;)V
/*     */     //   8: astore_3
/*     */     //   9: aload_3
/*     */     //   10: ldc_w
/*     */     //   13: ldc_w [Ljava/lang/Object;
/*     */     //   16: aload_2
/*     */     //   17: invokevirtual parameterCount : ()I
/*     */     //   20: invokevirtual asCollector : (Ljava/lang/Class;I)Ljava/lang/invoke/MethodHandle;
/*     */     //   23: iconst_0
/*     */     //   24: iconst_3
/*     */     //   25: anewarray java/lang/Object
/*     */     //   28: dup
/*     */     //   29: iconst_0
/*     */     //   30: aload_0
/*     */     //   31: aastore
/*     */     //   32: dup
/*     */     //   33: iconst_1
/*     */     //   34: aload_3
/*     */     //   35: aastore
/*     */     //   36: dup
/*     */     //   37: iconst_2
/*     */     //   38: aload_1
/*     */     //   39: aastore
/*     */     //   40: invokestatic insertArguments : (Ljava/lang/invoke/MethodHandle;I[Ljava/lang/Object;)Ljava/lang/invoke/MethodHandle;
/*     */     //   43: aload_2
/*     */     //   44: invokestatic explicitCastArguments : (Ljava/lang/invoke/MethodHandle;Ljava/lang/invoke/MethodType;)Ljava/lang/invoke/MethodHandle;
/*     */     //   47: invokevirtual setTarget : (Ljava/lang/invoke/MethodHandle;)V
/*     */     //   50: goto -> 170
/*     */     //   53: astore #4
/*     */     //   55: new java/lang/RuntimeException
/*     */     //   58: dup
/*     */     //   59: new java/lang/StringBuilder
/*     */     //   62: dup
/*     */     //   63: invokespecial <init> : ()V
/*     */     //   66: ldc_w ''
/*     */     //   69: invokevirtual toCharArray : ()[C
/*     */     //   72: dup
/*     */     //   73: dup
/*     */     //   74: iconst_2
/*     */     //   75: dup_x1
/*     */     //   76: caload
/*     */     //   77: sipush #5413
/*     */     //   80: ixor
/*     */     //   81: i2c
/*     */     //   82: castore
/*     */     //   83: sipush #4807
/*     */     //   86: iconst_0
/*     */     //   87: iconst_1
/*     */     //   88: invokestatic U : (Ljava/lang/Object;SZZ)Ljava/lang/String;
/*     */     //   91: invokevirtual append : (Ljava/lang/String;)Ljava/lang/StringBuilder;
/*     */     //   94: ldc_w ''
/*     */     //   97: invokevirtual toCharArray : ()[C
/*     */     //   100: dup
/*     */     //   101: dup
/*     */     //   102: iconst_2
/*     */     //   103: dup_x1
/*     */     //   104: caload
/*     */     //   105: sipush #25650
/*     */     //   108: ixor
/*     */     //   109: i2c
/*     */     //   110: castore
/*     */     //   111: sipush #10850
/*     */     //   114: iconst_1
/*     */     //   115: iconst_0
/*     */     //   116: invokestatic U : (Ljava/lang/Object;SZZ)Ljava/lang/String;
/*     */     //   119: invokevirtual append : (Ljava/lang/String;)Ljava/lang/StringBuilder;
/*     */     //   122: aload_1
/*     */     //   123: invokevirtual append : (Ljava/lang/String;)Ljava/lang/StringBuilder;
/*     */     //   126: ldc_w ''
/*     */     //   129: invokevirtual toCharArray : ()[C
/*     */     //   132: dup
/*     */     //   133: dup
/*     */     //   134: iconst_2
/*     */     //   135: dup_x1
/*     */     //   136: caload
/*     */     //   137: sipush #12704
/*     */     //   140: ixor
/*     */     //   141: i2c
/*     */     //   142: castore
/*     */     //   143: sipush #25789
/*     */     //   146: iconst_1
/*     */     //   147: iconst_0
/*     */     //   148: invokestatic U : (Ljava/lang/Object;SZZ)Ljava/lang/String;
/*     */     //   151: invokevirtual append : (Ljava/lang/String;)Ljava/lang/StringBuilder;
/*     */     //   154: aload_2
/*     */     //   155: invokevirtual toString : ()Ljava/lang/String;
/*     */     //   158: invokevirtual append : (Ljava/lang/String;)Ljava/lang/StringBuilder;
/*     */     //   161: invokevirtual toString : ()Ljava/lang/String;
/*     */     //   164: aload #4
/*     */     //   166: invokespecial <init> : (Ljava/lang/String;Ljava/lang/Throwable;)V
/*     */     //   169: athrow
/*     */     //   170: aload_3
/*     */     //   171: areturn
/*     */     // Exception table:
/*     */     //   from	to	target	type
/*     */     //   9	50	53	java/lang/Exception
/*     */   } }


/* Location:              C:\Users\BukkitBypass\Desktop\MatrixAC\AAC\AAC-spigot-5.2.0.jar!\me\konsolas\aac\dw.class
 * Java compiler version: 8 (52.0)
 * JD-Core Version:       1.1.3
 */