/*   1 */ package me.konsolas.aac;public final class dx { public static void a(int[] paramArrayOfint, byte[] paramArrayOfbyte1, byte[] paramArrayOfbyte2, boolean paramBoolean) { a(paramArrayOfbyte1, paramArrayOfbyte2);
/*     */ 
/*     */ 
/*     */ 
/*     */ 
/*     */ 
/*     */ 
/*     */ 
/*     */ 
/*     */ 
/*     */ 
/*     */ 
/*     */ 
/*     */ 
/*     */ 
/*     */ 
/*     */ 
/*     */ 
/*     */ 
/*     */ 
/*     */ 
/*     */ 
/*     */ 
/*     */ 
/*     */ 
/*     */ 
/*     */ 
/*     */ 
/*     */ 
/*     */ 
/*     */ 
/*     */ 
/*     */ 
/*     */ 
/*     */ 
/*     */ 
/*     */ 
/*     */ 
/*     */ 
/*     */ 
/*     */ 
/*     */ 
/*     */ 
/*     */ 
/*     */ 
/*     */ 
/*     */ 
/*     */ 
/*     */ 
/*     */ 
/*     */ 
/*     */ 
/*     */ 
/*     */ 
/*     */ 
/*     */ 
/*     */ 
/*     */ 
/*     */ 
/*     */ 
/*     */ 
/*     */ 
/*     */ 
/*     */ 
/*     */ 
/*     */ 
/*     */ 
/*     */ 
/*     */ 
/*     */ 
/*     */ 
/*     */ 
/*     */ 
/*     */ 
/*     */ 
/*     */ 
/*     */ 
/*     */ 
/*     */ 
/*     */ 
/*     */ 
/*     */ 
/*     */ 
/*     */ 
/*     */ 
/*     */ 
/*     */ 
/*     */ 
/*     */ 
/*     */ 
/*     */ 
/*     */ 
/*     */ 
/*     */ 
/*     */ 
/*     */ 
/*     */ 
/*     */ 
/*     */ 
/*     */ 
/*     */ 
/*     */ 
/*     */ 
/*     */ 
/*     */ 
/*     */ 
/*     */ 
/*     */ 
/*     */ 
/*     */ 
/*     */ 
/*     */ 
/*     */ 
/*     */ 
/*     */ 
/*     */ 
/*     */ 
/*     */ 
/*     */ 
/*     */ 
/*     */ 
/*     */ 
/*     */ 
/*     */ 
/*     */ 
/*     */ 
/*     */ 
/*     */ 
/*     */ 
/*     */ 
/*     */ 
/*     */ 
/*     */ 
/*     */ 
/*     */ 
/*     */ 
/*     */ 
/*     */ 
/*     */ 
/*     */ 
/*     */ 
/*     */ 
/*     */ 
/*     */ 
/*     */ 
/*     */ 
/*     */ 
/*     */ 
/*     */ 
/*     */ 
/*     */ 
/*     */ 
/*     */ 
/*     */ 
/*     */ 
/*     */ 
/*     */ 
/*     */ 
/*     */ 
/*     */ 
/*     */ 
/*     */ 
/*     */ 
/*     */ 
/*     */ 
/*     */ 
/*     */ 
/*     */ 
/*     */ 
/*     */ 
/*     */ 
/*     */ 
/*     */ 
/*     */ 
/*     */ 
/*     */ 
/*     */ 
/*     */ 
/*     */ 
/*     */ 
/*     */ 
/*     */ 
/*     */ 
/*     */ 
/*     */ 
/*     */ 
/*     */ 
/*     */ 
/*     */ 
/*     */ 
/*     */ 
/*     */ 
/*     */ 
/*     */ 
/*     */ 
/*     */ 
/*     */ 
/*     */ 
/*     */ 
/*     */ 
/*     */ 
/*     */ 
/*     */ 
/*     */ 
/*     */ 
/*     */ 
/*     */ 
/*     */ 
/*     */ 
/*     */ 
/*     */ 
/*     */ 
/*     */ 
/*     */ 
/*     */ 
/*     */ 
/*     */ 
/*     */ 
/*     */ 
/*     */ 
/*     */ 
/*     */ 
/*     */ 
/*     */ 
/*     */ 
/*     */ 
/*     */ 
/*     */ 
/*     */     
/* 230 */     a(paramArrayOfint, paramArrayOfbyte1, paramArrayOfbyte2, 0, paramArrayOfbyte1.length, paramBoolean); }
/*     */ 
/*     */ 
/*     */ 
/*     */ 
/*     */ 
/*     */ 
/*     */ 
/*     */ 
/*     */ 
/*     */ 
/*     */ 
/*     */ 
/*     */ 
/*     */ 
/*     */   
/*     */   public static final byte[] h;
/*     */ 
/*     */ 
/*     */ 
/*     */ 
/*     */ 
/*     */ 
/*     */ 
/*     */ 
/*     */ 
/*     */ 
/*     */ 
/*     */ 
/*     */   
/*     */   public static final byte[] a;
/*     */ 
/*     */ 
/*     */ 
/*     */ 
/*     */ 
/*     */ 
/*     */ 
/*     */ 
/*     */ 
/*     */ 
/*     */ 
/*     */ 
/*     */   
/*     */   private static final int l = 16;
/*     */ 
/*     */ 
/*     */ 
/*     */ 
/*     */ 
/*     */ 
/*     */ 
/*     */ 
/*     */ 
/*     */ 
/*     */ 
/*     */ 
/*     */   
/*     */   private static final int c = 8192;
/*     */ 
/*     */ 
/*     */ 
/*     */ 
/*     */ 
/*     */ 
/*     */ 
/*     */ 
/*     */ 
/*     */ 
/*     */ 
/*     */   
/*     */   private static final int b = 128;
/*     */ 
/*     */ 
/*     */ 
/*     */ 
/*     */ 
/*     */ 
/*     */ 
/*     */ 
/*     */ 
/*     */ 
/*     */ 
/*     */   
/*     */   private static final int e = 16;
/*     */ 
/*     */ 
/*     */ 
/*     */ 
/*     */ 
/*     */ 
/*     */ 
/*     */ 
/*     */ 
/*     */ 
/*     */ 
/*     */   
/*     */   private static final int m = 8;
/*     */ 
/*     */ 
/*     */ 
/*     */ 
/*     */ 
/*     */ 
/*     */ 
/*     */ 
/*     */ 
/*     */ 
/*     */ 
/*     */   
/*     */   private static final int k = 255;
/*     */ 
/*     */ 
/*     */ 
/*     */ 
/*     */ 
/*     */ 
/*     */ 
/*     */ 
/*     */ 
/*     */ 
/*     */ 
/*     */   
/*     */   private static final int g = 1;
/*     */ 
/*     */ 
/*     */ 
/*     */ 
/*     */ 
/*     */ 
/*     */ 
/*     */ 
/*     */ 
/*     */ 
/*     */ 
/*     */   
/*     */   private static final int d = 1024;
/*     */ 
/*     */ 
/*     */ 
/*     */ 
/*     */ 
/*     */ 
/*     */ 
/*     */ 
/*     */ 
/*     */ 
/*     */ 
/*     */   
/*     */   private static final int j = 1024;
/*     */ 
/*     */ 
/*     */ 
/*     */ 
/*     */ 
/*     */ 
/*     */ 
/*     */ 
/*     */ 
/*     */ 
/*     */ 
/*     */   
/*     */   static final int f = 1000;
/*     */ 
/*     */ 
/*     */ 
/*     */ 
/*     */ 
/*     */ 
/*     */ 
/*     */ 
/*     */ 
/*     */ 
/*     */ 
/*     */   
/*     */   protected static final Q i;
/*     */ 
/*     */ 
/*     */ 
/*     */ 
/*     */ 
/*     */ 
/*     */ 
/*     */ 
/*     */ 
/*     */ 
/*     */ 
/*     */   
/*     */   public static final m9 n;
/*     */ 
/*     */ 
/*     */ 
/*     */ 
/*     */ 
/*     */ 
/*     */ 
/*     */ 
/*     */ 
/*     */ 
/*     */ 
/*     */ 
/*     */   
/*     */   public static void c(byte[] paramArrayOfbyte, g9 paramg9) {
/*     */     a(paramArrayOfbyte, 0, paramArrayOfbyte.length, paramg9);
/*     */   }
/*     */ 
/*     */ 
/*     */ 
/*     */ 
/*     */ 
/*     */ 
/*     */ 
/*     */ 
/*     */ 
/*     */ 
/*     */ 
/*     */ 
/*     */   
/*     */   public static void f(byte[] paramArrayOfbyte, int paramInt1, int paramInt2) {
/*     */     try {
/*     */       if (paramInt2 - paramInt1 < 1024) {
/* 451 */         l(paramArrayOfbyte, paramInt1, paramInt2);
/*     */ 
/*     */ 
/*     */ 
/*     */ 
/*     */ 
/*     */ 
/*     */ 
/*     */ 
/*     */ 
/*     */ 
/*     */ 
/*     */ 
/*     */ 
/*     */ 
/*     */ 
/*     */ 
/*     */ 
/*     */ 
/*     */ 
/*     */ 
/*     */ 
/*     */ 
/*     */ 
/*     */ 
/*     */ 
/*     */ 
/*     */ 
/*     */ 
/*     */ 
/*     */ 
/*     */ 
/*     */ 
/*     */ 
/*     */ 
/*     */ 
/*     */ 
/*     */ 
/*     */ 
/*     */ 
/*     */ 
/*     */ 
/*     */ 
/*     */ 
/*     */ 
/*     */ 
/*     */ 
/*     */ 
/*     */ 
/*     */ 
/*     */ 
/*     */ 
/*     */ 
/*     */ 
/*     */ 
/*     */ 
/*     */ 
/*     */ 
/*     */ 
/*     */ 
/*     */ 
/*     */ 
/*     */ 
/*     */ 
/*     */ 
/*     */ 
/*     */ 
/*     */ 
/*     */ 
/*     */ 
/*     */ 
/*     */ 
/*     */ 
/*     */ 
/*     */ 
/*     */ 
/*     */ 
/*     */ 
/*     */ 
/*     */ 
/*     */ 
/*     */ 
/*     */ 
/*     */ 
/*     */ 
/*     */ 
/*     */ 
/*     */ 
/*     */ 
/*     */ 
/*     */ 
/*     */ 
/*     */ 
/*     */ 
/*     */ 
/*     */ 
/*     */ 
/*     */ 
/*     */ 
/*     */ 
/*     */ 
/*     */ 
/*     */ 
/*     */ 
/*     */ 
/*     */ 
/*     */ 
/*     */ 
/*     */ 
/*     */ 
/*     */ 
/*     */ 
/*     */ 
/*     */ 
/*     */ 
/*     */ 
/*     */ 
/*     */ 
/*     */ 
/*     */ 
/*     */ 
/*     */ 
/*     */ 
/*     */ 
/*     */ 
/*     */ 
/*     */ 
/*     */ 
/*     */ 
/*     */ 
/*     */ 
/*     */ 
/*     */ 
/*     */ 
/*     */ 
/*     */ 
/*     */ 
/*     */ 
/*     */ 
/*     */ 
/*     */ 
/*     */ 
/*     */ 
/*     */ 
/*     */ 
/*     */ 
/*     */ 
/*     */         
/*     */         return;
/*     */       } 
/*     */     } catch (IllegalArgumentException illegalArgumentException) {
/*     */       throw a(null);
/*     */     } 
/*     */ 
/*     */ 
/*     */ 
/*     */ 
/*     */ 
/*     */ 
/*     */ 
/*     */ 
/*     */ 
/*     */ 
/*     */ 
/*     */ 
/*     */ 
/*     */ 
/*     */ 
/*     */ 
/*     */ 
/*     */ 
/*     */ 
/*     */ 
/*     */ 
/*     */ 
/*     */ 
/*     */ 
/*     */ 
/*     */ 
/*     */ 
/*     */ 
/*     */ 
/*     */ 
/*     */ 
/*     */ 
/*     */ 
/*     */ 
/*     */ 
/*     */ 
/*     */ 
/*     */ 
/*     */ 
/*     */ 
/*     */ 
/*     */ 
/*     */ 
/*     */ 
/*     */ 
/*     */ 
/*     */ 
/*     */ 
/*     */ 
/*     */ 
/*     */ 
/*     */ 
/*     */ 
/*     */ 
/*     */ 
/*     */ 
/*     */ 
/*     */ 
/*     */ 
/*     */ 
/*     */ 
/*     */ 
/*     */ 
/*     */ 
/*     */ 
/*     */ 
/*     */ 
/*     */ 
/*     */ 
/*     */ 
/*     */ 
/*     */ 
/*     */ 
/*     */ 
/*     */ 
/*     */ 
/*     */ 
/*     */ 
/*     */ 
/*     */ 
/*     */ 
/*     */ 
/*     */ 
/*     */ 
/*     */ 
/*     */ 
/*     */ 
/*     */ 
/*     */ 
/*     */ 
/*     */ 
/*     */ 
/*     */ 
/*     */ 
/*     */ 
/*     */ 
/*     */ 
/*     */ 
/*     */ 
/*     */ 
/*     */ 
/*     */ 
/*     */ 
/*     */ 
/*     */ 
/*     */ 
/*     */ 
/*     */ 
/*     */ 
/*     */ 
/*     */ 
/*     */ 
/*     */ 
/*     */ 
/*     */ 
/*     */ 
/*     */ 
/*     */ 
/*     */ 
/*     */ 
/*     */ 
/*     */ 
/*     */ 
/*     */ 
/*     */ 
/*     */ 
/*     */ 
/*     */ 
/*     */ 
/*     */ 
/*     */ 
/*     */ 
/*     */ 
/*     */ 
/*     */ 
/*     */ 
/*     */ 
/*     */ 
/*     */ 
/*     */ 
/*     */ 
/*     */ 
/*     */ 
/*     */ 
/*     */ 
/*     */     
/* 750 */     boolean bool1 = false; boolean bool2 = true;
/*     */     byte b = 0;
/*     */     int[] arrayOfInt1 = new int[1];
/* 753 */     int[] arrayOfInt2 = new int[1];
/*     */ 
/*     */ 
/*     */ 
/*     */ 
/*     */ 
/*     */ 
/*     */ 
/*     */ 
/*     */ 
/*     */ 
/*     */ 
/*     */ 
/*     */ 
/*     */ 
/*     */ 
/*     */ 
/*     */ 
/*     */ 
/*     */ 
/*     */ 
/*     */ 
/*     */ 
/*     */ 
/*     */ 
/*     */ 
/*     */ 
/*     */ 
/*     */ 
/*     */ 
/*     */     
/*     */     int[] arrayOfInt3 = new int[1];
/*     */ 
/*     */ 
/*     */ 
/*     */ 
/*     */ 
/*     */ 
/*     */ 
/*     */ 
/*     */ 
/*     */ 
/*     */ 
/*     */ 
/*     */ 
/*     */ 
/*     */ 
/*     */ 
/*     */ 
/*     */ 
/*     */ 
/*     */ 
/*     */ 
/*     */ 
/*     */ 
/*     */ 
/*     */ 
/*     */ 
/*     */ 
/*     */ 
/*     */ 
/*     */     
/*     */     arrayOfInt1[b] = paramInt1;
/*     */ 
/*     */ 
/*     */ 
/*     */ 
/*     */ 
/*     */ 
/*     */ 
/*     */ 
/*     */ 
/*     */ 
/*     */ 
/*     */ 
/*     */ 
/*     */ 
/*     */ 
/*     */ 
/*     */ 
/*     */ 
/*     */ 
/*     */ 
/*     */ 
/*     */ 
/*     */ 
/*     */ 
/*     */ 
/*     */ 
/*     */ 
/*     */ 
/*     */ 
/*     */     
/*     */     arrayOfInt2[b] = paramInt2 - paramInt1;
/*     */ 
/*     */ 
/*     */ 
/*     */ 
/*     */ 
/*     */ 
/*     */ 
/*     */ 
/*     */ 
/*     */ 
/*     */ 
/*     */ 
/*     */ 
/*     */ 
/*     */ 
/*     */ 
/*     */ 
/*     */ 
/*     */ 
/*     */ 
/*     */ 
/*     */ 
/*     */ 
/*     */ 
/*     */ 
/*     */ 
/*     */ 
/*     */ 
/*     */     
/*     */     arrayOfInt3[b++] = 0;
/*     */ 
/*     */ 
/*     */ 
/*     */ 
/*     */ 
/*     */ 
/*     */ 
/*     */ 
/*     */ 
/*     */ 
/*     */ 
/*     */ 
/*     */ 
/*     */ 
/*     */ 
/*     */ 
/*     */ 
/*     */ 
/*     */ 
/*     */ 
/*     */ 
/*     */ 
/*     */ 
/*     */ 
/*     */ 
/*     */ 
/*     */ 
/*     */ 
/*     */     
/*     */     int[] arrayOfInt4 = new int[256];
/*     */ 
/*     */ 
/*     */ 
/*     */ 
/*     */ 
/*     */ 
/*     */ 
/*     */ 
/*     */ 
/*     */ 
/*     */ 
/*     */ 
/*     */ 
/*     */ 
/*     */ 
/*     */ 
/*     */ 
/*     */ 
/*     */ 
/*     */ 
/*     */ 
/*     */ 
/*     */ 
/*     */ 
/*     */ 
/*     */ 
/*     */ 
/*     */ 
/*     */     
/* 936 */     int[] arrayOfInt5 = new int[256]; while (b > 0) {
/*     */       int i = arrayOfInt1[--b]; int j = arrayOfInt2[b]; int k = arrayOfInt3[b];
/*     */       try {
/*     */       
/*     */       } catch (IllegalArgumentException illegalArgumentException) {
/*     */         throw a(null);
/*     */       } 
/*     */     } 
/*     */   } public static void a(int[] paramArrayOfint, byte[] paramArrayOfbyte, boolean paramBoolean) { b(paramArrayOfint, paramArrayOfbyte, 0, paramArrayOfint.length, paramBoolean); } static { h = new byte[0];
/* 945 */     a = new byte[0];
/*     */     i = new Q(-1, -1, -1);
/*     */     n = new eZ(null); }
/*     */ 
/*     */   
/*     */   public static byte[] b(byte[] paramArrayOfbyte, int paramInt) {
/*     */     return e(paramArrayOfbyte, paramInt, paramArrayOfbyte.length);
/*     */   }
/*     */   
/*     */   public static void a(byte[] paramArrayOfbyte1, byte[] paramArrayOfbyte2) {
/*     */     // Byte code:
/*     */     //   0: getstatic me/konsolas/aac/dx.o : J
/*     */     //   3: ldc2_w 73117402715301
/*     */     //   6: lxor
/*     */     //   7: lstore_2
/*     */     //   8: aload_0
/*     */     //   9: arraylength
/*     */     //   10: aload_1
/*     */     //   11: arraylength
/*     */     //   12: if_icmpeq -> 108
/*     */     //   15: new java/lang/IllegalArgumentException
/*     */     //   18: dup
/*     */     //   19: new java/lang/StringBuilder
/*     */     //   22: dup
/*     */     //   23: invokespecial <init> : ()V
/*     */     //   26: ldc '䏉̘仜㸨Ƣ宒䢩뚰늜㝬퓠?⯛둝⏜᧷ᕇᕚ䗐똏τ'
/*     */     //   28: invokevirtual toCharArray : ()[C
/*     */     //   31: dup
/*     */     //   32: dup
/*     */     //   33: bipush #14
/*     */     //   35: dup_x1
/*     */     //   36: caload
/*     */     //   37: sipush #26507
/*     */     //   40: ixor
/*     */     //   41: i2c
/*     */     //   42: castore
/*     */     //   43: sipush #5366
/*     */     //   46: iconst_1
/*     */     //   47: iconst_4
/*     */     //   48: invokestatic G : (Ljava/lang/Object;SZB)Ljava/lang/String;
/*     */     //   51: invokevirtual append : (Ljava/lang/String;)Ljava/lang/StringBuilder;
/*     */     //   54: aload_0
/*     */     //   55: arraylength
/*     */     //   56: invokevirtual append : (I)Ljava/lang/StringBuilder;
/*     */     //   59: ldc '噣죆ኘ납䣜'
/*     */     //   61: invokevirtual toCharArray : ()[C
/*     */     //   64: dup
/*     */     //   65: dup
/*     */     //   66: iconst_2
/*     */     //   67: dup_x1
/*     */     //   68: caload
/*     */     //   69: sipush #18738
/*     */     //   72: ixor
/*     */     //   73: i2c
/*     */     //   74: castore
/*     */     //   75: sipush #5534
/*     */     //   78: iconst_1
/*     */     //   79: iconst_5
/*     */     //   80: invokestatic G : (Ljava/lang/Object;SZB)Ljava/lang/String;
/*     */     //   83: invokevirtual append : (Ljava/lang/String;)Ljava/lang/StringBuilder;
/*     */     //   86: aload_1
/*     */     //   87: arraylength
/*     */     //   88: invokevirtual append : (I)Ljava/lang/StringBuilder;
/*     */     //   91: invokevirtual toString : ()Ljava/lang/String;
/*     */     //   94: invokespecial <init> : (Ljava/lang/String;)V
/*     */     //   97: athrow
/*     */     //   98: ldc2_w 5462572078868487754
/*     */     //   101: lload_2
/*     */     //   102: <illegal opcode> w : (Ljava/lang/Exception;JJ)Ljava/lang/Exception;
/*     */     //   107: athrow
/*     */     //   108: return
/*     */     // Line number table:
/*     */     //   Java source line number -> byte code offset
/*     */     //   #43	-> 8
/*     */     //   #499	-> 108
/*     */     // Exception table:
/*     */     //   from	to	target	type
/*     */     //   8	98	98	java/lang/IllegalArgumentException
/*     */   }
/*     */   
/*     */   public static byte[] d(byte[] paramArrayOfbyte, int paramInt1, int paramInt2) {
/*     */     try {
/*     */       b(paramArrayOfbyte, paramInt1, paramInt2);
/*     */     } catch (IllegalArgumentException illegalArgumentException) {
/*     */       throw a(null);
/*     */     } 
/*     */     byte[] arrayOfByte = (paramInt2 == 0) ? h : new byte[paramInt2];
/*     */     System.arraycopy(paramArrayOfbyte, paramInt1, arrayOfByte, 0, paramInt2);
/*     */     return arrayOfByte;
/*     */   }
/*     */   
/*     */   public static void e(byte[] paramArrayOfbyte, g9 paramg9) {
/*     */     b(paramArrayOfbyte, 0, paramArrayOfbyte.length, paramg9);
/*     */   }
/*     */   
/*     */   public static void l(byte[] paramArrayOfbyte, int paramInt1, int paramInt2) {
/*     */     // Byte code:
/*     */     //   0: iload_2
/*     */     //   1: iload_1
/*     */     //   2: isub
/*     */     //   3: istore_3
/*     */     //   4: iload_3
/*     */     //   5: bipush #16
/*     */     //   7: if_icmpge -> 21
/*     */     //   10: aload_0
/*     */     //   11: iload_1
/*     */     //   12: iload_2
/*     */     //   13: invokestatic a : ([BII)V
/*     */     //   16: return
/*     */     //   17: invokestatic a : (Ljava/lang/Exception;)Ljava/lang/Exception;
/*     */     //   20: athrow
/*     */     //   21: iload_1
/*     */     //   22: iload_3
/*     */     //   23: iconst_2
/*     */     //   24: idiv
/*     */     //   25: iadd
/*     */     //   26: istore #4
/*     */     //   28: iload_1
/*     */     //   29: istore #5
/*     */     //   31: iload_2
/*     */     //   32: iconst_1
/*     */     //   33: isub
/*     */     //   34: istore #6
/*     */     //   36: iload_3
/*     */     //   37: sipush #128
/*     */     //   40: if_icmple -> 107
/*     */     //   43: iload_3
/*     */     //   44: bipush #8
/*     */     //   46: idiv
/*     */     //   47: istore #7
/*     */     //   49: aload_0
/*     */     //   50: iload #5
/*     */     //   52: iload #5
/*     */     //   54: iload #7
/*     */     //   56: iadd
/*     */     //   57: iload #5
/*     */     //   59: iconst_2
/*     */     //   60: iload #7
/*     */     //   62: imul
/*     */     //   63: iadd
/*     */     //   64: invokestatic a : ([BIII)I
/*     */     //   67: istore #5
/*     */     //   69: aload_0
/*     */     //   70: iload #4
/*     */     //   72: iload #7
/*     */     //   74: isub
/*     */     //   75: iload #4
/*     */     //   77: iload #4
/*     */     //   79: iload #7
/*     */     //   81: iadd
/*     */     //   82: invokestatic a : ([BIII)I
/*     */     //   85: istore #4
/*     */     //   87: aload_0
/*     */     //   88: iload #6
/*     */     //   90: iconst_2
/*     */     //   91: iload #7
/*     */     //   93: imul
/*     */     //   94: isub
/*     */     //   95: iload #6
/*     */     //   97: iload #7
/*     */     //   99: isub
/*     */     //   100: iload #6
/*     */     //   102: invokestatic a : ([BIII)I
/*     */     //   105: istore #6
/*     */     //   107: aload_0
/*     */     //   108: iload #5
/*     */     //   110: iload #4
/*     */     //   112: iload #6
/*     */     //   114: invokestatic a : ([BIII)I
/*     */     //   117: istore #4
/*     */     //   119: aload_0
/*     */     //   120: iload #4
/*     */     //   122: baload
/*     */     //   123: istore #7
/*     */     //   125: iload_1
/*     */     //   126: istore #8
/*     */     //   128: iload #8
/*     */     //   130: istore #9
/*     */     //   132: iload_2
/*     */     //   133: iconst_1
/*     */     //   134: isub
/*     */     //   135: istore #10
/*     */     //   137: iload #10
/*     */     //   139: istore #11
/*     */     //   141: iload #9
/*     */     //   143: iload #10
/*     */     //   145: if_icmpgt -> 199
/*     */     //   148: aload_0
/*     */     //   149: iload #9
/*     */     //   151: baload
/*     */     //   152: iload #7
/*     */     //   154: invokestatic compare : (BB)I
/*     */     //   157: dup
/*     */     //   158: istore #12
/*     */     //   160: ifgt -> 199
/*     */     //   163: iload #12
/*     */     //   165: ifne -> 193
/*     */     //   168: goto -> 175
/*     */     //   171: invokestatic a : (Ljava/lang/Exception;)Ljava/lang/Exception;
/*     */     //   174: athrow
/*     */     //   175: aload_0
/*     */     //   176: iload #8
/*     */     //   178: iinc #8, 1
/*     */     //   181: iload #9
/*     */     //   183: invokestatic i : ([BII)V
/*     */     //   186: goto -> 193
/*     */     //   189: invokestatic a : (Ljava/lang/Exception;)Ljava/lang/Exception;
/*     */     //   192: athrow
/*     */     //   193: iinc #9, 1
/*     */     //   196: goto -> 141
/*     */     //   199: iload #10
/*     */     //   201: iload #9
/*     */     //   203: if_icmplt -> 257
/*     */     //   206: aload_0
/*     */     //   207: iload #10
/*     */     //   209: baload
/*     */     //   210: iload #7
/*     */     //   212: invokestatic compare : (BB)I
/*     */     //   215: dup
/*     */     //   216: istore #12
/*     */     //   218: iflt -> 257
/*     */     //   221: iload #12
/*     */     //   223: ifne -> 251
/*     */     //   226: goto -> 233
/*     */     //   229: invokestatic a : (Ljava/lang/Exception;)Ljava/lang/Exception;
/*     */     //   232: athrow
/*     */     //   233: aload_0
/*     */     //   234: iload #10
/*     */     //   236: iload #11
/*     */     //   238: iinc #11, -1
/*     */     //   241: invokestatic i : ([BII)V
/*     */     //   244: goto -> 251
/*     */     //   247: invokestatic a : (Ljava/lang/Exception;)Ljava/lang/Exception;
/*     */     //   250: athrow
/*     */     //   251: iinc #10, -1
/*     */     //   254: goto -> 199
/*     */     //   257: iload #9
/*     */     //   259: iload #10
/*     */     //   261: if_icmple -> 271
/*     */     //   264: goto -> 288
/*     */     //   267: invokestatic a : (Ljava/lang/Exception;)Ljava/lang/Exception;
/*     */     //   270: athrow
/*     */     //   271: aload_0
/*     */     //   272: iload #9
/*     */     //   274: iinc #9, 1
/*     */     //   277: iload #10
/*     */     //   279: iinc #10, -1
/*     */     //   282: invokestatic i : ([BII)V
/*     */     //   285: goto -> 141
/*     */     //   288: iload #8
/*     */     //   290: iload_1
/*     */     //   291: isub
/*     */     //   292: iload #9
/*     */     //   294: iload #8
/*     */     //   296: isub
/*     */     //   297: invokestatic min : (II)I
/*     */     //   300: istore #12
/*     */     //   302: aload_0
/*     */     //   303: iload_1
/*     */     //   304: iload #9
/*     */     //   306: iload #12
/*     */     //   308: isub
/*     */     //   309: iload #12
/*     */     //   311: invokestatic a : ([BIII)V
/*     */     //   314: iload #11
/*     */     //   316: iload #10
/*     */     //   318: isub
/*     */     //   319: iload_2
/*     */     //   320: iload #11
/*     */     //   322: isub
/*     */     //   323: iconst_1
/*     */     //   324: isub
/*     */     //   325: invokestatic min : (II)I
/*     */     //   328: istore #12
/*     */     //   330: aload_0
/*     */     //   331: iload #9
/*     */     //   333: iload_2
/*     */     //   334: iload #12
/*     */     //   336: isub
/*     */     //   337: iload #12
/*     */     //   339: invokestatic a : ([BIII)V
/*     */     //   342: iload #9
/*     */     //   344: iload #8
/*     */     //   346: isub
/*     */     //   347: dup
/*     */     //   348: istore #12
/*     */     //   350: iconst_1
/*     */     //   351: if_icmple -> 370
/*     */     //   354: aload_0
/*     */     //   355: iload_1
/*     */     //   356: iload_1
/*     */     //   357: iload #12
/*     */     //   359: iadd
/*     */     //   360: invokestatic l : ([BII)V
/*     */     //   363: goto -> 370
/*     */     //   366: invokestatic a : (Ljava/lang/Exception;)Ljava/lang/Exception;
/*     */     //   369: athrow
/*     */     //   370: iload #11
/*     */     //   372: iload #10
/*     */     //   374: isub
/*     */     //   375: dup
/*     */     //   376: istore #12
/*     */     //   378: iconst_1
/*     */     //   379: if_icmple -> 398
/*     */     //   382: aload_0
/*     */     //   383: iload_2
/*     */     //   384: iload #12
/*     */     //   386: isub
/*     */     //   387: iload_2
/*     */     //   388: invokestatic l : ([BII)V
/*     */     //   391: goto -> 398
/*     */     //   394: invokestatic a : (Ljava/lang/Exception;)Ljava/lang/Exception;
/*     */     //   397: athrow
/*     */     //   398: return
/*     */     // Line number table:
/*     */     //   Java source line number -> byte code offset
/*     */     //   #67	-> 0
/*     */     //   #65	-> 4
/*     */     //   #320	-> 10
/*     */     //   #48	-> 16
/*     */     //   #35	-> 21
/*     */     //   #331	-> 28
/*     */     //   #228	-> 31
/*     */     //   #113	-> 36
/*     */     //   #675	-> 43
/*     */     //   #891	-> 49
/*     */     //   #27	-> 69
/*     */     //   #538	-> 87
/*     */     //   #464	-> 107
/*     */     //   #58	-> 119
/*     */     //   #567	-> 125
/*     */     //   #562	-> 141
/*     */     //   #327	-> 163
/*     */     //   #289	-> 193
/*     */     //   #52	-> 199
/*     */     //   #913	-> 221
/*     */     //   #718	-> 251
/*     */     //   #373	-> 257
/*     */     //   #23	-> 271
/*     */     //   #543	-> 288
/*     */     //   #803	-> 302
/*     */     //   #480	-> 314
/*     */     //   #689	-> 330
/*     */     //   #880	-> 342
/*     */     //   #399	-> 370
/*     */     //   #821	-> 398
/*     */     // Exception table:
/*     */     //   from	to	target	type
/*     */     //   4	17	17	java/lang/IllegalArgumentException
/*     */     //   160	168	171	java/lang/IllegalArgumentException
/*     */     //   163	186	189	java/lang/IllegalArgumentException
/*     */     //   218	226	229	java/lang/IllegalArgumentException
/*     */     //   221	244	247	java/lang/IllegalArgumentException
/*     */     //   257	267	267	java/lang/IllegalArgumentException
/*     */     //   350	363	366	java/lang/IllegalArgumentException
/*     */     //   378	391	394	java/lang/IllegalArgumentException
/*     */   }
/*     */   
/*     */   private static void d(byte[] paramArrayOfbyte, int paramInt1, int paramInt2, g9 paramg9) {
/*     */     for (int i = paramInt1; ++i < paramInt2; ) {
/*     */       byte b1 = paramArrayOfbyte[i];
/*     */       int j = i;
/*     */       byte b2 = paramArrayOfbyte[j - 1];
/*     */       while (true) {
/*     */         try {
/*     */           if (paramg9.a(b1, b2) < 0) {
/*     */             try {
/*     */               paramArrayOfbyte[j] = b2;
/*     */               if (paramInt1 == j - 1) {
/*     */                 j--;
/*     */                 break;
/*     */               } 
/*     */             } catch (IllegalArgumentException illegalArgumentException) {
/*     */               throw a(null);
/*     */             } 
/*     */             b2 = paramArrayOfbyte[--j - 1];
/*     */           } 
/*     */         } catch (IllegalArgumentException illegalArgumentException) {
/*     */           throw a(null);
/*     */         } 
/*     */         break;
/*     */       } 
/*     */       paramArrayOfbyte[j] = b1;
/*     */     } 
/*     */   }
/*     */   
/*     */   private static final long o = nc.a(-6903451199440583234L, -1127622069886065892L, MethodHandles.lookup().lookupClass()).a(72805022286489L);
/*     */   
/*     */   @Deprecated
/*     */   public static void a(byte[] paramArrayOfbyte, int paramInt1, int paramInt2, byte paramByte) {
/*     */     try {
/*     */       g(paramArrayOfbyte, paramInt1, paramInt2);
/*     */       if (paramInt1 == 0) {
/*     */         try {
/*     */           for (; paramInt2-- != 0; paramArrayOfbyte[paramInt2] = paramByte);
/*     */         } catch (IllegalArgumentException illegalArgumentException) {
/*     */           throw a(null);
/*     */         } 
/*     */       } else {
/*     */         int i = paramInt1;
/*     */         try {
/*     */           while (i < paramInt2) {
/*     */             paramArrayOfbyte[i] = paramByte;
/*     */             i++;
/*     */           } 
/*     */         } catch (IllegalArgumentException illegalArgumentException) {
/*     */           throw a(null);
/*     */         } 
/*     */       } 
/*     */     } catch (IllegalArgumentException illegalArgumentException) {
/*     */       throw a(null);
/*     */     } 
/*     */   }
/*     */   
/*     */   public static void f(byte[] paramArrayOfbyte1, byte[] paramArrayOfbyte2, int paramInt1, int paramInt2) {
/*     */     // Byte code:
/*     */     //   0: iload_3
/*     */     //   1: iload_2
/*     */     //   2: isub
/*     */     //   3: istore #4
/*     */     //   5: iload #4
/*     */     //   7: bipush #16
/*     */     //   9: if_icmpge -> 24
/*     */     //   12: aload_0
/*     */     //   13: aload_1
/*     */     //   14: iload_2
/*     */     //   15: iload_3
/*     */     //   16: invokestatic d : ([B[BII)V
/*     */     //   19: return
/*     */     //   20: invokestatic a : (Ljava/lang/Exception;)Ljava/lang/Exception;
/*     */     //   23: athrow
/*     */     //   24: iload_2
/*     */     //   25: iload #4
/*     */     //   27: iconst_2
/*     */     //   28: idiv
/*     */     //   29: iadd
/*     */     //   30: istore #5
/*     */     //   32: iload_2
/*     */     //   33: istore #6
/*     */     //   35: iload_3
/*     */     //   36: iconst_1
/*     */     //   37: isub
/*     */     //   38: istore #7
/*     */     //   40: iload #4
/*     */     //   42: sipush #128
/*     */     //   45: if_icmple -> 116
/*     */     //   48: iload #4
/*     */     //   50: bipush #8
/*     */     //   52: idiv
/*     */     //   53: istore #8
/*     */     //   55: aload_0
/*     */     //   56: aload_1
/*     */     //   57: iload #6
/*     */     //   59: iload #6
/*     */     //   61: iload #8
/*     */     //   63: iadd
/*     */     //   64: iload #6
/*     */     //   66: iconst_2
/*     */     //   67: iload #8
/*     */     //   69: imul
/*     */     //   70: iadd
/*     */     //   71: invokestatic a : ([B[BIII)I
/*     */     //   74: istore #6
/*     */     //   76: aload_0
/*     */     //   77: aload_1
/*     */     //   78: iload #5
/*     */     //   80: iload #8
/*     */     //   82: isub
/*     */     //   83: iload #5
/*     */     //   85: iload #5
/*     */     //   87: iload #8
/*     */     //   89: iadd
/*     */     //   90: invokestatic a : ([B[BIII)I
/*     */     //   93: istore #5
/*     */     //   95: aload_0
/*     */     //   96: aload_1
/*     */     //   97: iload #7
/*     */     //   99: iconst_2
/*     */     //   100: iload #8
/*     */     //   102: imul
/*     */     //   103: isub
/*     */     //   104: iload #7
/*     */     //   106: iload #8
/*     */     //   108: isub
/*     */     //   109: iload #7
/*     */     //   111: invokestatic a : ([B[BIII)I
/*     */     //   114: istore #7
/*     */     //   116: aload_0
/*     */     //   117: aload_1
/*     */     //   118: iload #6
/*     */     //   120: iload #5
/*     */     //   122: iload #7
/*     */     //   124: invokestatic a : ([B[BIII)I
/*     */     //   127: istore #5
/*     */     //   129: aload_0
/*     */     //   130: iload #5
/*     */     //   132: baload
/*     */     //   133: istore #8
/*     */     //   135: aload_1
/*     */     //   136: iload #5
/*     */     //   138: baload
/*     */     //   139: istore #9
/*     */     //   141: iload_2
/*     */     //   142: istore #10
/*     */     //   144: iload #10
/*     */     //   146: istore #11
/*     */     //   148: iload_3
/*     */     //   149: iconst_1
/*     */     //   150: isub
/*     */     //   151: istore #12
/*     */     //   153: iload #12
/*     */     //   155: istore #13
/*     */     //   157: iload #11
/*     */     //   159: iload #12
/*     */     //   161: if_icmpgt -> 240
/*     */     //   164: aload_0
/*     */     //   165: iload #11
/*     */     //   167: baload
/*     */     //   168: iload #8
/*     */     //   170: invokestatic compare : (BB)I
/*     */     //   173: dup
/*     */     //   174: istore #15
/*     */     //   176: ifne -> 195
/*     */     //   179: aload_1
/*     */     //   180: iload #11
/*     */     //   182: baload
/*     */     //   183: iload #9
/*     */     //   185: invokestatic compare : (BB)I
/*     */     //   188: goto -> 197
/*     */     //   191: invokestatic a : (Ljava/lang/Exception;)Ljava/lang/Exception;
/*     */     //   194: athrow
/*     */     //   195: iload #15
/*     */     //   197: dup
/*     */     //   198: istore #14
/*     */     //   200: ifgt -> 240
/*     */     //   203: iload #14
/*     */     //   205: ifne -> 234
/*     */     //   208: goto -> 215
/*     */     //   211: invokestatic a : (Ljava/lang/Exception;)Ljava/lang/Exception;
/*     */     //   214: athrow
/*     */     //   215: aload_0
/*     */     //   216: aload_1
/*     */     //   217: iload #10
/*     */     //   219: iinc #10, 1
/*     */     //   222: iload #11
/*     */     //   224: invokestatic a : ([B[BII)V
/*     */     //   227: goto -> 234
/*     */     //   230: invokestatic a : (Ljava/lang/Exception;)Ljava/lang/Exception;
/*     */     //   233: athrow
/*     */     //   234: iinc #11, 1
/*     */     //   237: goto -> 157
/*     */     //   240: iload #12
/*     */     //   242: iload #11
/*     */     //   244: if_icmplt -> 323
/*     */     //   247: aload_0
/*     */     //   248: iload #12
/*     */     //   250: baload
/*     */     //   251: iload #8
/*     */     //   253: invokestatic compare : (BB)I
/*     */     //   256: dup
/*     */     //   257: istore #15
/*     */     //   259: ifne -> 278
/*     */     //   262: aload_1
/*     */     //   263: iload #12
/*     */     //   265: baload
/*     */     //   266: iload #9
/*     */     //   268: invokestatic compare : (BB)I
/*     */     //   271: goto -> 280
/*     */     //   274: invokestatic a : (Ljava/lang/Exception;)Ljava/lang/Exception;
/*     */     //   277: athrow
/*     */     //   278: iload #15
/*     */     //   280: dup
/*     */     //   281: istore #14
/*     */     //   283: iflt -> 323
/*     */     //   286: iload #14
/*     */     //   288: ifne -> 317
/*     */     //   291: goto -> 298
/*     */     //   294: invokestatic a : (Ljava/lang/Exception;)Ljava/lang/Exception;
/*     */     //   297: athrow
/*     */     //   298: aload_0
/*     */     //   299: aload_1
/*     */     //   300: iload #12
/*     */     //   302: iload #13
/*     */     //   304: iinc #13, -1
/*     */     //   307: invokestatic a : ([B[BII)V
/*     */     //   310: goto -> 317
/*     */     //   313: invokestatic a : (Ljava/lang/Exception;)Ljava/lang/Exception;
/*     */     //   316: athrow
/*     */     //   317: iinc #12, -1
/*     */     //   320: goto -> 240
/*     */     //   323: iload #11
/*     */     //   325: iload #12
/*     */     //   327: if_icmple -> 337
/*     */     //   330: goto -> 355
/*     */     //   333: invokestatic a : (Ljava/lang/Exception;)Ljava/lang/Exception;
/*     */     //   336: athrow
/*     */     //   337: aload_0
/*     */     //   338: aload_1
/*     */     //   339: iload #11
/*     */     //   341: iinc #11, 1
/*     */     //   344: iload #12
/*     */     //   346: iinc #12, -1
/*     */     //   349: invokestatic a : ([B[BII)V
/*     */     //   352: goto -> 157
/*     */     //   355: iload #10
/*     */     //   357: iload_2
/*     */     //   358: isub
/*     */     //   359: iload #11
/*     */     //   361: iload #10
/*     */     //   363: isub
/*     */     //   364: invokestatic min : (II)I
/*     */     //   367: istore #14
/*     */     //   369: aload_0
/*     */     //   370: aload_1
/*     */     //   371: iload_2
/*     */     //   372: iload #11
/*     */     //   374: iload #14
/*     */     //   376: isub
/*     */     //   377: iload #14
/*     */     //   379: invokestatic a : ([B[BIII)V
/*     */     //   382: iload #13
/*     */     //   384: iload #12
/*     */     //   386: isub
/*     */     //   387: iload_3
/*     */     //   388: iload #13
/*     */     //   390: isub
/*     */     //   391: iconst_1
/*     */     //   392: isub
/*     */     //   393: invokestatic min : (II)I
/*     */     //   396: istore #14
/*     */     //   398: aload_0
/*     */     //   399: aload_1
/*     */     //   400: iload #11
/*     */     //   402: iload_3
/*     */     //   403: iload #14
/*     */     //   405: isub
/*     */     //   406: iload #14
/*     */     //   408: invokestatic a : ([B[BIII)V
/*     */     //   411: iload #11
/*     */     //   413: iload #10
/*     */     //   415: isub
/*     */     //   416: dup
/*     */     //   417: istore #14
/*     */     //   419: iconst_1
/*     */     //   420: if_icmple -> 440
/*     */     //   423: aload_0
/*     */     //   424: aload_1
/*     */     //   425: iload_2
/*     */     //   426: iload_2
/*     */     //   427: iload #14
/*     */     //   429: iadd
/*     */     //   430: invokestatic f : ([B[BII)V
/*     */     //   433: goto -> 440
/*     */     //   436: invokestatic a : (Ljava/lang/Exception;)Ljava/lang/Exception;
/*     */     //   439: athrow
/*     */     //   440: iload #13
/*     */     //   442: iload #12
/*     */     //   444: isub
/*     */     //   445: dup
/*     */     //   446: istore #14
/*     */     //   448: iconst_1
/*     */     //   449: if_icmple -> 469
/*     */     //   452: aload_0
/*     */     //   453: aload_1
/*     */     //   454: iload_3
/*     */     //   455: iload #14
/*     */     //   457: isub
/*     */     //   458: iload_3
/*     */     //   459: invokestatic f : ([B[BII)V
/*     */     //   462: goto -> 469
/*     */     //   465: invokestatic a : (Ljava/lang/Exception;)Ljava/lang/Exception;
/*     */     //   468: athrow
/*     */     //   469: return
/*     */     // Line number table:
/*     */     //   Java source line number -> byte code offset
/*     */     //   #163	-> 0
/*     */     //   #297	-> 5
/*     */     //   #382	-> 12
/*     */     //   #542	-> 19
/*     */     //   #846	-> 24
/*     */     //   #66	-> 32
/*     */     //   #408	-> 35
/*     */     //   #636	-> 40
/*     */     //   #341	-> 48
/*     */     //   #204	-> 55
/*     */     //   #332	-> 76
/*     */     //   #76	-> 95
/*     */     //   #304	-> 116
/*     */     //   #318	-> 129
/*     */     //   #502	-> 141
/*     */     //   #149	-> 157
/*     */     //   #630	-> 203
/*     */     //   #38	-> 234
/*     */     //   #647	-> 240
/*     */     //   #68	-> 286
/*     */     //   #78	-> 317
/*     */     //   #272	-> 323
/*     */     //   #629	-> 337
/*     */     //   #157	-> 355
/*     */     //   #793	-> 369
/*     */     //   #152	-> 382
/*     */     //   #611	-> 398
/*     */     //   #279	-> 411
/*     */     //   #850	-> 440
/*     */     //   #457	-> 469
/*     */     // Exception table:
/*     */     //   from	to	target	type
/*     */     //   5	20	20	java/lang/IllegalArgumentException
/*     */     //   176	191	191	java/lang/IllegalArgumentException
/*     */     //   200	208	211	java/lang/IllegalArgumentException
/*     */     //   203	227	230	java/lang/IllegalArgumentException
/*     */     //   259	274	274	java/lang/IllegalArgumentException
/*     */     //   283	291	294	java/lang/IllegalArgumentException
/*     */     //   286	310	313	java/lang/IllegalArgumentException
/*     */     //   323	333	333	java/lang/IllegalArgumentException
/*     */     //   419	433	436	java/lang/IllegalArgumentException
/*     */     //   448	462	465	java/lang/IllegalArgumentException
/*     */   }
/*     */   
/*     */   public static void a(byte[][] paramArrayOfbyte) {
/*     */     a(paramArrayOfbyte, 0, (paramArrayOfbyte[0]).length);
/*     */   }
/*     */   
/*     */   public static int a(byte[] paramArrayOfbyte, byte paramByte, g9 paramg9) {
/*     */     return a(paramArrayOfbyte, 0, paramArrayOfbyte.length, paramByte, paramg9);
/*     */   }
/*     */   
/*     */   private static int a(int[] paramArrayOfint, byte[] paramArrayOfbyte, int paramInt1, int paramInt2, int paramInt3) {
/*     */     byte b1 = paramArrayOfbyte[paramArrayOfint[paramInt1]];
/*     */     byte b2 = paramArrayOfbyte[paramArrayOfint[paramInt2]];
/*     */     byte b3 = paramArrayOfbyte[paramArrayOfint[paramInt3]];
/*     */     int i = Byte.compare(b1, b2);
/*     */     int j = Byte.compare(b1, b3);
/*     */     int k = Byte.compare(b2, b3);
/*     */     try {
/*     */       if (i < 0) {
/*     */         try {
/*     */           try {
/*     */           
/*     */           } catch (IllegalArgumentException illegalArgumentException) {
/*     */             throw a(null);
/*     */           } 
/*     */         } catch (IllegalArgumentException illegalArgumentException) {
/*     */           throw a(null);
/*     */         } 
/*     */       } else {
/*     */         try {
/*     */           try {
/*     */           
/*     */           } catch (IllegalArgumentException illegalArgumentException) {
/*     */             throw a(null);
/*     */           } 
/*     */         } catch (IllegalArgumentException illegalArgumentException) {
/*     */           throw a(null);
/*     */         } 
/*     */       } 
/*     */     } catch (IllegalArgumentException illegalArgumentException) {
/*     */       throw a(null);
/*     */     } 
/*     */     return (k > 0) ? paramInt2 : ((j > 0) ? paramInt3 : paramInt1);
/*     */   }
/*     */   
/*     */   public static void h(byte[] paramArrayOfbyte, int paramInt1, int paramInt2) {
/*     */     ForkJoinPool forkJoinPool = a();
/*     */     try {
/*     */       if (paramInt2 - paramInt1 >= 1024)
/*     */         try {
/*     */           if (forkJoinPool.getParallelism() != 1) {
/*     */             boolean bool = false;
/*     */             LinkedBlockingQueue<Q> linkedBlockingQueue = new LinkedBlockingQueue();
/*     */             linkedBlockingQueue.add(new Q(paramInt1, paramInt2 - paramInt1, 0));
/*     */             AtomicInteger atomicInteger = new AtomicInteger(1);
/*     */             int i = forkJoinPool.getParallelism();
/*     */             ExecutorCompletionService executorCompletionService = new ExecutorCompletionService(forkJoinPool);
/*     */             int j = i;
/*     */             try {
/*     */               for (; j-- != 0; executorCompletionService.submit(() -> {
/*     */                     int[] arrayOfInt1 = new int[256];
/*     */                     int[] arrayOfInt2 = new int[256];
/*     */                     while (true) {
/*     */                       if (paramAtomicInteger.get() == 0) {
/*     */                         int i4 = paramInt;
/*     */                         try {
/*     */                           while (i4-- != 0)
/*     */                             paramLinkedBlockingQueue.add(i); 
/*     */                         } catch (Exception exception) {
/*     */                           throw a(null);
/*     */                         } 
/*     */                       } 
/*     */                       Q q = paramLinkedBlockingQueue.take();
/*     */                       try {
/*     */                         if (q == i)
/*     */                           return null; 
/*     */                       } catch (Exception exception) {
/*     */                         throw a(null);
/*     */                       } 
/*     */                       int i = q.a;
/*     */                       int j = q.b;
/*     */                       int k = q.c;
/*     */                       try {
/*     */                       
/*     */                       } catch (Exception exception) {
/*     */                         throw a(null);
/*     */                       } 
/*     */                       boolean bool = (k % 1 == 0) ? true : false;
/*     */                       int m = (0 - k % 1) * 8;
/*     */                       int n = i + j;
/*     */                       try {
/*     */                         while (n-- != i)
/*     */                           arrayOfInt1[paramArrayOfbyte[n] >>> m & 0xFF ^ bool] = arrayOfInt1[paramArrayOfbyte[n] >>> m & 0xFF ^ bool] + 1; 
/*     */                       } catch (Exception exception) {
/*     */                         throw a(null);
/*     */                       } 
/*     */                       n = -1;
/*     */                       int i1 = 0;
/*     */                       int i2 = i;
/*     */                       while (true) {
/*     */                         try {
/*     */                           if (i1 < 256) {
/*     */                             if (arrayOfInt1[i1] != 0)
/*     */                               n = i1; 
/*     */                             arrayOfInt2[i1] = i2 += arrayOfInt1[i1];
/*     */                             i1++;
/*     */                           } 
/*     */                         } catch (Exception exception) {
/*     */                           throw a(null);
/*     */                         } 
/*     */                         break;
/*     */                       } 
/*     */                       i1 = i + j - arrayOfInt1[n];
/*     */                       i2 = i;
/*     */                       for (int i3 = -1; i2 <= i1; i3 = SYNTHETIC_LOCAL_VARIABLE_17 >>> m & 0xFF ^ bool) {
/*     */                         byte b = paramArrayOfbyte[i2];
/*     */                         continue;
/*     */                       } 
/*     */                       paramAtomicInteger.decrementAndGet();
/*     */                     } 
/*     */                   }));
/*     */             } catch (Exception exception) {
/*     */               throw a(null);
/*     */             } 
/*     */             Throwable throwable = null;
/*     */             for (int k = i; k-- != 0;) {
/*     */               try {
/*     */                 executorCompletionService.take().get();
/*     */               } catch (Exception exception) {
/*     */                 throwable = exception.getCause();
/*     */               } 
/*     */             } 
/*     */             try {
/*     */               if (throwable != null) {
/*     */                 try {
/*     */                 
/*     */                 } catch (Exception exception) {
/*     */                   throw a(null);
/*     */                 } 
/*     */                 throw (throwable instanceof RuntimeException) ? (RuntimeException)throwable : new RuntimeException(throwable);
/*     */               } 
/*     */             } catch (Exception exception) {
/*     */               throw a(null);
/*     */             } 
/*     */             return;
/*     */           } 
/*     */           l(paramArrayOfbyte, paramInt1, paramInt2);
/*     */           return;
/*     */         } catch (Exception exception) {
/*     */           throw a(null);
/*     */         }  
/*     */     } catch (Exception exception) {
/*     */       throw a(null);
/*     */     } 
/*     */     l(paramArrayOfbyte, paramInt1, paramInt2);
/*     */   }
/*     */   
/*     */   public static void b(int[] paramArrayOfint, byte[] paramArrayOfbyte, int paramInt1, int paramInt2) {
/*     */     ForkJoinPool forkJoinPool = a();
/*     */     try {
/*     */       if (paramInt2 - paramInt1 >= 8192) {
/*     */         try {
/*     */           if (forkJoinPool.getParallelism() == 1) {
/*     */             d(paramArrayOfint, paramArrayOfbyte, paramInt1, paramInt2);
/*     */             return;
/*     */           } 
/*     */         } catch (IllegalArgumentException illegalArgumentException) {
/*     */           throw a(null);
/*     */         } 
/*     */         forkJoinPool.invoke(new d8(paramArrayOfint, paramArrayOfbyte, paramInt1, paramInt2));
/*     */         return;
/*     */       } 
/*     */     } catch (IllegalArgumentException illegalArgumentException) {
/*     */       throw a(null);
/*     */     } 
/*     */     d(paramArrayOfint, paramArrayOfbyte, paramInt1, paramInt2);
/*     */   }
/*     */   
/*     */   public static void c(byte[] paramArrayOfbyte, int paramInt1, int paramInt2, g9 paramg9) {
/*     */     a(paramArrayOfbyte, paramInt1, paramInt2, paramg9, (byte[])null);
/*     */   }
/*     */   
/*     */   public static void b(int[] paramArrayOfint, byte[] paramArrayOfbyte) {
/*     */     d(paramArrayOfint, paramArrayOfbyte, 0, paramArrayOfbyte.length);
/*     */   }
/*     */   
/*     */   public static byte[] a(byte[] paramArrayOfbyte) {
/*     */     int i = paramArrayOfbyte.length;
/*     */     for (int j = i / 2; j-- != 0; ) {
/*     */       byte b = paramArrayOfbyte[i - j - 1];
/*     */       paramArrayOfbyte[i - j - 1] = paramArrayOfbyte[j];
/*     */       paramArrayOfbyte[j] = b;
/*     */     } 
/*     */     return paramArrayOfbyte;
/*     */   }
/*     */   
/*     */   public static byte[] a(byte[] paramArrayOfbyte, int paramInt1, int paramInt2) {
/*     */     int i = paramInt2 - paramInt1;
/*     */     for (int j = i / 2; j-- != 0; paramArrayOfbyte[paramInt1 + i - j - 1] = paramArrayOfbyte[paramInt1 + j], paramArrayOfbyte[paramInt1 + j] = b)
/*     */       byte b = paramArrayOfbyte[paramInt1 + i - j - 1]; 
/*     */     return paramArrayOfbyte;
/*     */   }
/*     */   
/*     */   public static void b(byte[] paramArrayOfbyte) {
/*     */     h(paramArrayOfbyte, 0, paramArrayOfbyte.length);
/*     */   }
/*     */   
/*     */   public static void c(byte[] paramArrayOfbyte1, byte[] paramArrayOfbyte2, int paramInt1, int paramInt2) {
/*     */     // Byte code:
/*     */     //   0: getstatic me/konsolas/aac/dx.o : J
/*     */     //   3: ldc2_w 93303779454525
/*     */     //   6: lxor
/*     */     //   7: lstore #4
/*     */     //   9: invokestatic a : ()Ljava/util/concurrent/ForkJoinPool;
/*     */     //   12: astore #6
/*     */     //   14: iload_3
/*     */     //   15: iload_2
/*     */     //   16: isub
/*     */     //   17: sipush #1024
/*     */     //   20: if_icmplt -> 46
/*     */     //   23: aload #6
/*     */     //   25: invokevirtual getParallelism : ()I
/*     */     //   28: iconst_1
/*     */     //   29: if_icmpne -> 65
/*     */     //   32: goto -> 46
/*     */     //   35: ldc2_w -1056407502916295470
/*     */     //   38: lload #4
/*     */     //   40: <illegal opcode> w : (Ljava/lang/Exception;JJ)Ljava/lang/Exception;
/*     */     //   45: athrow
/*     */     //   46: aload_0
/*     */     //   47: aload_1
/*     */     //   48: iload_2
/*     */     //   49: iload_3
/*     */     //   50: invokestatic f : ([B[BII)V
/*     */     //   53: return
/*     */     //   54: ldc2_w -1056407502916295470
/*     */     //   57: lload #4
/*     */     //   59: <illegal opcode> w : (Ljava/lang/Exception;JJ)Ljava/lang/Exception;
/*     */     //   64: athrow
/*     */     //   65: iconst_2
/*     */     //   66: istore #7
/*     */     //   68: aload_0
/*     */     //   69: arraylength
/*     */     //   70: aload_1
/*     */     //   71: arraylength
/*     */     //   72: if_icmpeq -> 119
/*     */     //   75: new java/lang/IllegalArgumentException
/*     */     //   78: dup
/*     */     //   79: ldc_w '꟦䀴뗏䘟赳?眳铓掲?拁씧짾㗐Ἤ싞짷稲嘙Ⴘ'
/*     */     //   82: invokevirtual toCharArray : ()[C
/*     */     //   85: dup
/*     */     //   86: dup
/*     */     //   87: iconst_5
/*     */     //   88: dup_x1
/*     */     //   89: caload
/*     */     //   90: sipush #19486
/*     */     //   93: ixor
/*     */     //   94: i2c
/*     */     //   95: castore
/*     */     //   96: sipush #21784
/*     */     //   99: iconst_0
/*     */     //   100: iconst_4
/*     */     //   101: invokestatic A : (Ljava/lang/Object;SZI)Ljava/lang/String;
/*     */     //   104: invokespecial <init> : (Ljava/lang/String;)V
/*     */     //   107: athrow
/*     */     //   108: ldc2_w -1056407502916295470
/*     */     //   111: lload #4
/*     */     //   113: <illegal opcode> w : (Ljava/lang/Exception;JJ)Ljava/lang/Exception;
/*     */     //   118: athrow
/*     */     //   119: iconst_1
/*     */     //   120: istore #8
/*     */     //   122: new java/util/concurrent/LinkedBlockingQueue
/*     */     //   125: dup
/*     */     //   126: invokespecial <init> : ()V
/*     */     //   129: astore #9
/*     */     //   131: aload #9
/*     */     //   133: new me/konsolas/aac/Q
/*     */     //   136: dup
/*     */     //   137: iload_2
/*     */     //   138: iload_3
/*     */     //   139: iload_2
/*     */     //   140: isub
/*     */     //   141: iconst_0
/*     */     //   142: invokespecial <init> : (III)V
/*     */     //   145: invokevirtual add : (Ljava/lang/Object;)Z
/*     */     //   148: pop
/*     */     //   149: new java/util/concurrent/atomic/AtomicInteger
/*     */     //   152: dup
/*     */     //   153: iconst_1
/*     */     //   154: invokespecial <init> : (I)V
/*     */     //   157: astore #10
/*     */     //   159: aload #6
/*     */     //   161: invokevirtual getParallelism : ()I
/*     */     //   164: istore #11
/*     */     //   166: new java/util/concurrent/ExecutorCompletionService
/*     */     //   169: dup
/*     */     //   170: aload #6
/*     */     //   172: invokespecial <init> : (Ljava/util/concurrent/Executor;)V
/*     */     //   175: astore #12
/*     */     //   177: iload #11
/*     */     //   179: istore #13
/*     */     //   181: iload #13
/*     */     //   183: iinc #13, -1
/*     */     //   186: ifeq -> 222
/*     */     //   189: aload #12
/*     */     //   191: aload #10
/*     */     //   193: iload #11
/*     */     //   195: aload #9
/*     */     //   197: aload_0
/*     */     //   198: aload_1
/*     */     //   199: <illegal opcode> call : (Ljava/util/concurrent/atomic/AtomicInteger;ILjava/util/concurrent/LinkedBlockingQueue;[B[B)Ljava/util/concurrent/Callable;
/*     */     //   204: invokevirtual submit : (Ljava/util/concurrent/Callable;)Ljava/util/concurrent/Future;
/*     */     //   207: pop
/*     */     //   208: goto -> 181
/*     */     //   211: ldc2_w -1056407502916295470
/*     */     //   214: lload #4
/*     */     //   216: <illegal opcode> w : (Ljava/lang/Exception;JJ)Ljava/lang/Exception;
/*     */     //   221: athrow
/*     */     //   222: aconst_null
/*     */     //   223: astore #13
/*     */     //   225: iload #11
/*     */     //   227: istore #14
/*     */     //   229: iload #14
/*     */     //   231: iinc #14, -1
/*     */     //   234: ifeq -> 263
/*     */     //   237: aload #12
/*     */     //   239: invokevirtual take : ()Ljava/util/concurrent/Future;
/*     */     //   242: invokeinterface get : ()Ljava/lang/Object;
/*     */     //   247: pop
/*     */     //   248: goto -> 229
/*     */     //   251: astore #15
/*     */     //   253: aload #15
/*     */     //   255: invokevirtual getCause : ()Ljava/lang/Throwable;
/*     */     //   258: astore #13
/*     */     //   260: goto -> 229
/*     */     //   263: aload #13
/*     */     //   265: ifnull -> 319
/*     */     //   268: aload #13
/*     */     //   270: instanceof java/lang/RuntimeException
/*     */     //   273: ifeq -> 309
/*     */     //   276: goto -> 290
/*     */     //   279: ldc2_w -1056407502916295470
/*     */     //   282: lload #4
/*     */     //   284: <illegal opcode> w : (Ljava/lang/Exception;JJ)Ljava/lang/Exception;
/*     */     //   289: athrow
/*     */     //   290: aload #13
/*     */     //   292: checkcast java/lang/RuntimeException
/*     */     //   295: goto -> 318
/*     */     //   298: ldc2_w -1056407502916295470
/*     */     //   301: lload #4
/*     */     //   303: <illegal opcode> w : (Ljava/lang/Exception;JJ)Ljava/lang/Exception;
/*     */     //   308: athrow
/*     */     //   309: new java/lang/RuntimeException
/*     */     //   312: dup
/*     */     //   313: aload #13
/*     */     //   315: invokespecial <init> : (Ljava/lang/Throwable;)V
/*     */     //   318: athrow
/*     */     //   319: return
/*     */     // Line number table:
/*     */     //   Java source line number -> byte code offset
/*     */     //   #260	-> 9
/*     */     //   #746	-> 14
/*     */     //   #454	-> 46
/*     */     //   #262	-> 53
/*     */     //   #217	-> 65
/*     */     //   #779	-> 68
/*     */     //   #460	-> 119
/*     */     //   #572	-> 122
/*     */     //   #392	-> 131
/*     */     //   #519	-> 149
/*     */     //   #99	-> 159
/*     */     //   #725	-> 166
/*     */     //   #576	-> 177
/*     */     //   #430	-> 222
/*     */     //   #245	-> 225
/*     */     //   #180	-> 237
/*     */     //   #62	-> 248
/*     */     //   #632	-> 251
/*     */     //   #548	-> 253
/*     */     //   #346	-> 260
/*     */     //   #283	-> 263
/*     */     //   #849	-> 319
/*     */     // Exception table:
/*     */     //   from	to	target	type
/*     */     //   14	32	35	java/lang/Exception
/*     */     //   23	54	54	java/lang/Exception
/*     */     //   68	108	108	java/lang/Exception
/*     */     //   181	211	211	java/lang/Exception
/*     */     //   237	248	251	java/lang/Exception
/*     */     //   263	276	279	java/lang/Exception
/*     */     //   268	298	298	java/lang/Exception
/*     */   }
/*     */   
/*     */   public static void f(byte[] paramArrayOfbyte) {
/*     */     d(paramArrayOfbyte, 0, paramArrayOfbyte.length);
/*     */   }
/*     */   
/*     */   public static void a(int[] paramArrayOfint, byte[] paramArrayOfbyte) {
/*     */     c(paramArrayOfint, paramArrayOfbyte, 0, paramArrayOfint.length);
/*     */   }
/*     */   
/*     */   @Deprecated
/*     */   public static boolean a(byte[] paramArrayOfbyte1, byte[] paramArrayOfbyte2) {
/*     */     int i = paramArrayOfbyte1.length;
/*     */     try {
/*     */       if (i != paramArrayOfbyte2.length)
/*     */         return false; 
/*     */     } catch (IllegalArgumentException illegalArgumentException) {
/*     */       throw a(null);
/*     */     } 
/*     */     while (i-- != 0) {
/*     */       if (paramArrayOfbyte1[i] != paramArrayOfbyte2[i])
/*     */         return false; 
/*     */     } 
/*     */     return true;
/*     */   }
/*     */   
/*     */   public static void b(byte[] paramArrayOfbyte1, byte[] paramArrayOfbyte2, int paramInt1, int paramInt2) {
/*     */     ForkJoinPool forkJoinPool = a();
/*     */     try {
/*     */       if (paramInt2 - paramInt1 >= 8192) {
/*     */         try {
/*     */           if (forkJoinPool.getParallelism() == 1) {
/*     */             f(paramArrayOfbyte1, paramArrayOfbyte2, paramInt1, paramInt2);
/*     */             return;
/*     */           } 
/*     */         } catch (IllegalArgumentException illegalArgumentException) {
/*     */           throw a(null);
/*     */         } 
/*     */         forkJoinPool.invoke(new p(paramArrayOfbyte1, paramArrayOfbyte2, paramInt1, paramInt2));
/*     */         return;
/*     */       } 
/*     */     } catch (IllegalArgumentException illegalArgumentException) {
/*     */       throw a(null);
/*     */     } 
/*     */     f(paramArrayOfbyte1, paramArrayOfbyte2, paramInt1, paramInt2);
/*     */   }
/*     */   
/*     */   private static void e(byte[] paramArrayOfbyte, int paramInt1, int paramInt2, g9 paramg9) {
/*     */     for (int i = paramInt1; i < paramInt2 - 1; ) {
/*     */       int j = i;
/*     */       continue;
/*     */       k = i + 1;
/*     */       while (true) {
/*     */         try {
/*     */           if (k < paramInt2) {
/*     */             if (paramg9.a(paramArrayOfbyte[k], paramArrayOfbyte[SYNTHETIC_LOCAL_VARIABLE_5]) < 0)
/*     */               j = k; 
/*     */             k++;
/*     */             continue;
/*     */           } 
/*     */         } catch (IllegalArgumentException illegalArgumentException) {
/*     */           throw a(null);
/*     */         } 
/*     */         break;
/*     */       } 
/*     */     } 
/*     */   }
/*     */   
/*     */   public static void d(byte[] paramArrayOfbyte1, byte[] paramArrayOfbyte2) {
/*     */     a(paramArrayOfbyte1, paramArrayOfbyte2);
/*     */     b(paramArrayOfbyte1, paramArrayOfbyte2, 0, paramArrayOfbyte1.length);
/*     */   }
/*     */   
/*     */   private static void a(byte[] paramArrayOfbyte1, byte[] paramArrayOfbyte2, int paramInt1, int paramInt2) {
/*     */     byte b1 = paramArrayOfbyte1[paramInt1];
/*     */     byte b2 = paramArrayOfbyte2[paramInt1];
/*     */     paramArrayOfbyte1[paramInt1] = paramArrayOfbyte1[paramInt2];
/*     */     paramArrayOfbyte2[paramInt1] = paramArrayOfbyte2[paramInt2];
/*     */     paramArrayOfbyte1[paramInt2] = b1;
/*     */     paramArrayOfbyte2[paramInt2] = b2;
/*     */   }
/*     */   
/*     */   private static ForkJoinPool a() {
/*     */     ForkJoinPool forkJoinPool = ForkJoinTask.getPool();
/*     */     try {
/*     */     
/*     */     } catch (IllegalArgumentException illegalArgumentException) {
/*     */       throw a(null);
/*     */     } 
/*     */     return (forkJoinPool == null) ? ForkJoinPool.commonPool() : forkJoinPool;
/*     */   }
/*     */   
/*     */   public static void b(int[] paramArrayOfint, byte[] paramArrayOfbyte, boolean paramBoolean) {
/*     */     a(paramArrayOfint, paramArrayOfbyte, 0, paramArrayOfbyte.length, paramBoolean);
/*     */   }
/*     */   
/*     */   public static void e(byte[] paramArrayOfbyte, int paramInt1, int paramInt2) {
/*     */     Arrays.sort(paramArrayOfbyte, paramInt1, paramInt2);
/*     */   }
/*     */   
/*     */   public static void c(int[] paramArrayOfint, byte[] paramArrayOfbyte, int paramInt1, int paramInt2) {
/*     */     // Byte code:
/*     */     //   0: iload_2
/*     */     //   1: istore #4
/*     */     //   3: iload_2
/*     */     //   4: iconst_1
/*     */     //   5: iadd
/*     */     //   6: istore #5
/*     */     //   8: iload #5
/*     */     //   10: iload_3
/*     */     //   11: if_icmpge -> 77
/*     */     //   14: aload_1
/*     */     //   15: aload_0
/*     */     //   16: iload #5
/*     */     //   18: iaload
/*     */     //   19: baload
/*     */     //   20: aload_1
/*     */     //   21: aload_0
/*     */     //   22: iload #4
/*     */     //   24: iaload
/*     */     //   25: baload
/*     */     //   26: if_icmpeq -> 71
/*     */     //   29: goto -> 36
/*     */     //   32: invokestatic a : (Ljava/lang/Exception;)Ljava/lang/Exception;
/*     */     //   35: athrow
/*     */     //   36: iload #5
/*     */     //   38: iload #4
/*     */     //   40: isub
/*     */     //   41: iconst_1
/*     */     //   42: if_icmple -> 67
/*     */     //   45: goto -> 52
/*     */     //   48: invokestatic a : (Ljava/lang/Exception;)Ljava/lang/Exception;
/*     */     //   51: athrow
/*     */     //   52: aload_0
/*     */     //   53: iload #4
/*     */     //   55: iload #5
/*     */     //   57: invokestatic k : ([III)V
/*     */     //   60: goto -> 67
/*     */     //   63: invokestatic a : (Ljava/lang/Exception;)Ljava/lang/Exception;
/*     */     //   66: athrow
/*     */     //   67: iload #5
/*     */     //   69: istore #4
/*     */     //   71: iinc #5, 1
/*     */     //   74: goto -> 8
/*     */     //   77: iload_3
/*     */     //   78: iload #4
/*     */     //   80: isub
/*     */     //   81: iconst_1
/*     */     //   82: if_icmple -> 99
/*     */     //   85: aload_0
/*     */     //   86: iload #4
/*     */     //   88: iload_3
/*     */     //   89: invokestatic k : ([III)V
/*     */     //   92: goto -> 99
/*     */     //   95: invokestatic a : (Ljava/lang/Exception;)Ljava/lang/Exception;
/*     */     //   98: athrow
/*     */     //   99: return
/*     */     // Line number table:
/*     */     //   Java source line number -> byte code offset
/*     */     //   #353	-> 0
/*     */     //   #867	-> 3
/*     */     //   #70	-> 14
/*     */     //   #458	-> 36
/*     */     //   #687	-> 67
/*     */     //   #175	-> 71
/*     */     //   #391	-> 77
/*     */     //   #549	-> 99
/*     */     // Exception table:
/*     */     //   from	to	target	type
/*     */     //   8	29	32	java/lang/IllegalArgumentException
/*     */     //   14	45	48	java/lang/IllegalArgumentException
/*     */     //   36	60	63	java/lang/IllegalArgumentException
/*     */     //   77	92	95	java/lang/IllegalArgumentException
/*     */   }
/*     */   
/*     */   private static void a(int[] paramArrayOfint, byte[] paramArrayOfbyte1, byte[] paramArrayOfbyte2, int paramInt1, int paramInt2) {
/*     */     for (int i = paramInt1; ++i < paramInt2; ) {
/*     */       int j = paramArrayOfint[i];
/*     */       int k = i;
/*     */       int m = paramArrayOfint[k - 1];
/*     */       for (;; m = paramArrayOfint[--k - 1]) {
/*     */         try {
/*     */           if (paramArrayOfbyte1[j] >= paramArrayOfbyte1[m]) {
/*     */             try {
/*     */               if (paramArrayOfbyte1[j] == paramArrayOfbyte1[m])
/*     */                 try {
/*     */                   if (paramArrayOfbyte2[j] < paramArrayOfbyte2[m])
/*     */                     continue; 
/*     */                 } catch (IllegalArgumentException illegalArgumentException) {
/*     */                   throw a(null);
/*     */                 }  
/*     */             } catch (IllegalArgumentException illegalArgumentException) {
/*     */               throw a(null);
/*     */             } 
/*     */             break;
/*     */           } 
/*     */         } catch (IllegalArgumentException illegalArgumentException) {
/*     */           throw a(null);
/*     */         } 
/*     */         continue;
/*     */         try {
/*     */           paramArrayOfint[k] = m;
/*     */           if (paramInt1 == k - 1) {
/*     */             k--;
/*     */             break;
/*     */           } 
/*     */         } catch (IllegalArgumentException illegalArgumentException) {
/*     */           throw a(null);
/*     */         } 
/*     */       } 
/*     */       paramArrayOfint[k] = j;
/*     */     } 
/*     */   }
/*     */   
/*     */   public static int a(byte[] paramArrayOfbyte, byte paramByte) {
/*     */     return a(paramArrayOfbyte, 0, paramArrayOfbyte.length, paramByte);
/*     */   }
/*     */   
/*     */   public static void b(byte[] paramArrayOfbyte, int paramInt1, int paramInt2, g9 paramg9) {
/*     */     // Byte code:
/*     */     //   0: iload_2
/*     */     //   1: iload_1
/*     */     //   2: isub
/*     */     //   3: istore #4
/*     */     //   5: iload #4
/*     */     //   7: bipush #16
/*     */     //   9: if_icmpge -> 24
/*     */     //   12: aload_0
/*     */     //   13: iload_1
/*     */     //   14: iload_2
/*     */     //   15: aload_3
/*     */     //   16: invokestatic e : ([BIILme/konsolas/aac/g9;)V
/*     */     //   19: return
/*     */     //   20: invokestatic a : (Ljava/lang/Exception;)Ljava/lang/Exception;
/*     */     //   23: athrow
/*     */     //   24: iload_1
/*     */     //   25: iload #4
/*     */     //   27: iconst_2
/*     */     //   28: idiv
/*     */     //   29: iadd
/*     */     //   30: istore #5
/*     */     //   32: iload_1
/*     */     //   33: istore #6
/*     */     //   35: iload_2
/*     */     //   36: iconst_1
/*     */     //   37: isub
/*     */     //   38: istore #7
/*     */     //   40: iload #4
/*     */     //   42: sipush #128
/*     */     //   45: if_icmple -> 116
/*     */     //   48: iload #4
/*     */     //   50: bipush #8
/*     */     //   52: idiv
/*     */     //   53: istore #8
/*     */     //   55: aload_0
/*     */     //   56: iload #6
/*     */     //   58: iload #6
/*     */     //   60: iload #8
/*     */     //   62: iadd
/*     */     //   63: iload #6
/*     */     //   65: iconst_2
/*     */     //   66: iload #8
/*     */     //   68: imul
/*     */     //   69: iadd
/*     */     //   70: aload_3
/*     */     //   71: invokestatic b : ([BIIILme/konsolas/aac/g9;)I
/*     */     //   74: istore #6
/*     */     //   76: aload_0
/*     */     //   77: iload #5
/*     */     //   79: iload #8
/*     */     //   81: isub
/*     */     //   82: iload #5
/*     */     //   84: iload #5
/*     */     //   86: iload #8
/*     */     //   88: iadd
/*     */     //   89: aload_3
/*     */     //   90: invokestatic b : ([BIIILme/konsolas/aac/g9;)I
/*     */     //   93: istore #5
/*     */     //   95: aload_0
/*     */     //   96: iload #7
/*     */     //   98: iconst_2
/*     */     //   99: iload #8
/*     */     //   101: imul
/*     */     //   102: isub
/*     */     //   103: iload #7
/*     */     //   105: iload #8
/*     */     //   107: isub
/*     */     //   108: iload #7
/*     */     //   110: aload_3
/*     */     //   111: invokestatic b : ([BIIILme/konsolas/aac/g9;)I
/*     */     //   114: istore #7
/*     */     //   116: aload_0
/*     */     //   117: iload #6
/*     */     //   119: iload #5
/*     */     //   121: iload #7
/*     */     //   123: aload_3
/*     */     //   124: invokestatic b : ([BIIILme/konsolas/aac/g9;)I
/*     */     //   127: istore #5
/*     */     //   129: aload_0
/*     */     //   130: iload #5
/*     */     //   132: baload
/*     */     //   133: istore #8
/*     */     //   135: iload_1
/*     */     //   136: istore #9
/*     */     //   138: iload #9
/*     */     //   140: istore #10
/*     */     //   142: iload_2
/*     */     //   143: iconst_1
/*     */     //   144: isub
/*     */     //   145: istore #11
/*     */     //   147: iload #11
/*     */     //   149: istore #12
/*     */     //   151: iload #10
/*     */     //   153: iload #11
/*     */     //   155: if_icmpgt -> 212
/*     */     //   158: aload_3
/*     */     //   159: aload_0
/*     */     //   160: iload #10
/*     */     //   162: baload
/*     */     //   163: iload #8
/*     */     //   165: invokeinterface a : (BB)I
/*     */     //   170: dup
/*     */     //   171: istore #13
/*     */     //   173: ifgt -> 212
/*     */     //   176: iload #13
/*     */     //   178: ifne -> 206
/*     */     //   181: goto -> 188
/*     */     //   184: invokestatic a : (Ljava/lang/Exception;)Ljava/lang/Exception;
/*     */     //   187: athrow
/*     */     //   188: aload_0
/*     */     //   189: iload #9
/*     */     //   191: iinc #9, 1
/*     */     //   194: iload #10
/*     */     //   196: invokestatic i : ([BII)V
/*     */     //   199: goto -> 206
/*     */     //   202: invokestatic a : (Ljava/lang/Exception;)Ljava/lang/Exception;
/*     */     //   205: athrow
/*     */     //   206: iinc #10, 1
/*     */     //   209: goto -> 151
/*     */     //   212: iload #11
/*     */     //   214: iload #10
/*     */     //   216: if_icmplt -> 273
/*     */     //   219: aload_3
/*     */     //   220: aload_0
/*     */     //   221: iload #11
/*     */     //   223: baload
/*     */     //   224: iload #8
/*     */     //   226: invokeinterface a : (BB)I
/*     */     //   231: dup
/*     */     //   232: istore #13
/*     */     //   234: iflt -> 273
/*     */     //   237: iload #13
/*     */     //   239: ifne -> 267
/*     */     //   242: goto -> 249
/*     */     //   245: invokestatic a : (Ljava/lang/Exception;)Ljava/lang/Exception;
/*     */     //   248: athrow
/*     */     //   249: aload_0
/*     */     //   250: iload #11
/*     */     //   252: iload #12
/*     */     //   254: iinc #12, -1
/*     */     //   257: invokestatic i : ([BII)V
/*     */     //   260: goto -> 267
/*     */     //   263: invokestatic a : (Ljava/lang/Exception;)Ljava/lang/Exception;
/*     */     //   266: athrow
/*     */     //   267: iinc #11, -1
/*     */     //   270: goto -> 212
/*     */     //   273: iload #10
/*     */     //   275: iload #11
/*     */     //   277: if_icmple -> 287
/*     */     //   280: goto -> 304
/*     */     //   283: invokestatic a : (Ljava/lang/Exception;)Ljava/lang/Exception;
/*     */     //   286: athrow
/*     */     //   287: aload_0
/*     */     //   288: iload #10
/*     */     //   290: iinc #10, 1
/*     */     //   293: iload #11
/*     */     //   295: iinc #11, -1
/*     */     //   298: invokestatic i : ([BII)V
/*     */     //   301: goto -> 151
/*     */     //   304: iload #9
/*     */     //   306: iload_1
/*     */     //   307: isub
/*     */     //   308: iload #10
/*     */     //   310: iload #9
/*     */     //   312: isub
/*     */     //   313: invokestatic min : (II)I
/*     */     //   316: istore #13
/*     */     //   318: aload_0
/*     */     //   319: iload_1
/*     */     //   320: iload #10
/*     */     //   322: iload #13
/*     */     //   324: isub
/*     */     //   325: iload #13
/*     */     //   327: invokestatic a : ([BIII)V
/*     */     //   330: iload #12
/*     */     //   332: iload #11
/*     */     //   334: isub
/*     */     //   335: iload_2
/*     */     //   336: iload #12
/*     */     //   338: isub
/*     */     //   339: iconst_1
/*     */     //   340: isub
/*     */     //   341: invokestatic min : (II)I
/*     */     //   344: istore #13
/*     */     //   346: aload_0
/*     */     //   347: iload #10
/*     */     //   349: iload_2
/*     */     //   350: iload #13
/*     */     //   352: isub
/*     */     //   353: iload #13
/*     */     //   355: invokestatic a : ([BIII)V
/*     */     //   358: iload #10
/*     */     //   360: iload #9
/*     */     //   362: isub
/*     */     //   363: dup
/*     */     //   364: istore #13
/*     */     //   366: iconst_1
/*     */     //   367: if_icmple -> 387
/*     */     //   370: aload_0
/*     */     //   371: iload_1
/*     */     //   372: iload_1
/*     */     //   373: iload #13
/*     */     //   375: iadd
/*     */     //   376: aload_3
/*     */     //   377: invokestatic b : ([BIILme/konsolas/aac/g9;)V
/*     */     //   380: goto -> 387
/*     */     //   383: invokestatic a : (Ljava/lang/Exception;)Ljava/lang/Exception;
/*     */     //   386: athrow
/*     */     //   387: iload #12
/*     */     //   389: iload #11
/*     */     //   391: isub
/*     */     //   392: dup
/*     */     //   393: istore #13
/*     */     //   395: iconst_1
/*     */     //   396: if_icmple -> 416
/*     */     //   399: aload_0
/*     */     //   400: iload_2
/*     */     //   401: iload #13
/*     */     //   403: isub
/*     */     //   404: iload_2
/*     */     //   405: aload_3
/*     */     //   406: invokestatic b : ([BIILme/konsolas/aac/g9;)V
/*     */     //   409: goto -> 416
/*     */     //   412: invokestatic a : (Ljava/lang/Exception;)Ljava/lang/Exception;
/*     */     //   415: athrow
/*     */     //   416: return
/*     */     // Line number table:
/*     */     //   Java source line number -> byte code offset
/*     */     //   #379	-> 0
/*     */     //   #293	-> 5
/*     */     //   #160	-> 12
/*     */     //   #902	-> 19
/*     */     //   #688	-> 24
/*     */     //   #219	-> 32
/*     */     //   #254	-> 35
/*     */     //   #273	-> 40
/*     */     //   #221	-> 48
/*     */     //   #628	-> 55
/*     */     //   #645	-> 76
/*     */     //   #45	-> 95
/*     */     //   #446	-> 116
/*     */     //   #358	-> 129
/*     */     //   #904	-> 135
/*     */     //   #686	-> 151
/*     */     //   #536	-> 176
/*     */     //   #864	-> 206
/*     */     //   #710	-> 212
/*     */     //   #103	-> 237
/*     */     //   #381	-> 267
/*     */     //   #325	-> 273
/*     */     //   #211	-> 287
/*     */     //   #484	-> 304
/*     */     //   #734	-> 318
/*     */     //   #909	-> 330
/*     */     //   #89	-> 346
/*     */     //   #580	-> 358
/*     */     //   #363	-> 387
/*     */     //   #914	-> 416
/*     */     // Exception table:
/*     */     //   from	to	target	type
/*     */     //   5	20	20	java/lang/IllegalArgumentException
/*     */     //   173	181	184	java/lang/IllegalArgumentException
/*     */     //   176	199	202	java/lang/IllegalArgumentException
/*     */     //   234	242	245	java/lang/IllegalArgumentException
/*     */     //   237	260	263	java/lang/IllegalArgumentException
/*     */     //   273	283	283	java/lang/IllegalArgumentException
/*     */     //   366	380	383	java/lang/IllegalArgumentException
/*     */     //   395	409	412	java/lang/IllegalArgumentException
/*     */   }
/*     */   
/*     */   public static void a(byte[] paramArrayOfbyte, int paramInt1, int paramInt2, g9 paramg9) {
/*     */     b(paramArrayOfbyte, paramInt1, paramInt2, paramg9);
/*     */   }
/*     */   
/*     */   private static int a(byte[] paramArrayOfbyte1, byte[] paramArrayOfbyte2, int paramInt1, int paramInt2, int paramInt3) {
/*     */     try {
/*     */     
/*     */     } catch (IllegalArgumentException illegalArgumentException) {
/*     */       throw a(null);
/*     */     } 
/*     */     int i, j = ((i = Byte.compare(paramArrayOfbyte1[paramInt1], paramArrayOfbyte1[paramInt2])) == 0) ? Byte.compare(paramArrayOfbyte2[paramInt1], paramArrayOfbyte2[paramInt2]) : i;
/*     */     try {
/*     */     
/*     */     } catch (IllegalArgumentException illegalArgumentException) {
/*     */       throw a(null);
/*     */     } 
/*     */     int k = ((i = Byte.compare(paramArrayOfbyte1[paramInt1], paramArrayOfbyte1[paramInt3])) == 0) ? Byte.compare(paramArrayOfbyte2[paramInt1], paramArrayOfbyte2[paramInt3]) : i;
/*     */     try {
/*     */     
/*     */     } catch (IllegalArgumentException illegalArgumentException) {
/*     */       throw a(null);
/*     */     } 
/*     */     int m = ((i = Byte.compare(paramArrayOfbyte1[paramInt2], paramArrayOfbyte1[paramInt3])) == 0) ? Byte.compare(paramArrayOfbyte2[paramInt2], paramArrayOfbyte2[paramInt3]) : i;
/*     */     try {
/*     */       if (j < 0) {
/*     */         try {
/*     */           try {
/*     */           
/*     */           } catch (IllegalArgumentException illegalArgumentException) {
/*     */             throw a(null);
/*     */           } 
/*     */         } catch (IllegalArgumentException illegalArgumentException) {
/*     */           throw a(null);
/*     */         } 
/*     */       } else {
/*     */         try {
/*     */           try {
/*     */           
/*     */           } catch (IllegalArgumentException illegalArgumentException) {
/*     */             throw a(null);
/*     */           } 
/*     */         } catch (IllegalArgumentException illegalArgumentException) {
/*     */           throw a(null);
/*     */         } 
/*     */       } 
/*     */     } catch (IllegalArgumentException illegalArgumentException) {
/*     */       throw a(null);
/*     */     } 
/*     */     return (m > 0) ? paramInt2 : ((k > 0) ? paramInt3 : paramInt1);
/*     */   }
/*     */   
/*     */   private static void a(byte[] paramArrayOfbyte, int paramInt1, int paramInt2) {
/*     */     for (int i = paramInt1; i < paramInt2 - 1; i++) {
/*     */       int j = i;
/*     */       int k = i + 1;
/*     */       while (true) {
/*     */         try {
/*     */           if (k < paramInt2) {
/*     */             if (paramArrayOfbyte[k] < paramArrayOfbyte[j])
/*     */               j = k; 
/*     */             k++;
/*     */             continue;
/*     */           } 
/*     */         } catch (IllegalArgumentException illegalArgumentException) {
/*     */           throw a(null);
/*     */         } 
/*     */         if (j != i) {
/*     */           k = paramArrayOfbyte[i];
/*     */           paramArrayOfbyte[i] = paramArrayOfbyte[j];
/*     */           paramArrayOfbyte[j] = k;
/*     */         } 
/*     */         break;
/*     */       } 
/*     */     } 
/*     */   }
/*     */   
/*     */   public static void g(byte[] paramArrayOfbyte, int paramInt1, int paramInt2, g9 paramg9) {
/*     */     c(paramArrayOfbyte, paramInt1, paramInt2, paramg9);
/*     */   }
/*     */   
/*     */   public static byte[] a(byte[] paramArrayOfbyte, int paramInt) {
/*     */     try {
/*     */       if (paramInt == paramArrayOfbyte.length)
/*     */         return paramArrayOfbyte; 
/*     */     } catch (IllegalArgumentException illegalArgumentException) {
/*     */       throw a(null);
/*     */     } 
/*     */     try {
/*     */       if (paramInt < paramArrayOfbyte.length)
/*     */         return d(paramArrayOfbyte, paramInt); 
/*     */     } catch (IllegalArgumentException illegalArgumentException) {
/*     */       throw a(null);
/*     */     } 
/*     */     return b(paramArrayOfbyte, paramInt);
/*     */   }
/*     */   
/*     */   public static void e(byte[] paramArrayOfbyte) {
/*     */     k(paramArrayOfbyte, 0, paramArrayOfbyte.length);
/*     */   }
/*     */   
/*     */   private static void d(byte[] paramArrayOfbyte1, byte[] paramArrayOfbyte2, int paramInt1, int paramInt2) {
/*     */     for (int i = paramInt1; i < paramInt2 - 1; ) {
/*     */       int j = i;
/*     */       continue;
/*     */       for (int j = i + 1; j < paramInt2;);
/*     */     } 
/*     */   }
/*     */   
/*     */   public static void a(byte[] paramArrayOfbyte1, int paramInt1, int paramInt2, byte[] paramArrayOfbyte2) {
/*     */     // Byte code:
/*     */     //   0: iload_2
/*     */     //   1: iload_1
/*     */     //   2: isub
/*     */     //   3: istore #4
/*     */     //   5: iload #4
/*     */     //   7: bipush #16
/*     */     //   9: if_icmpge -> 23
/*     */     //   12: aload_0
/*     */     //   13: iload_1
/*     */     //   14: iload_2
/*     */     //   15: invokestatic j : ([BII)V
/*     */     //   18: return
/*     */     //   19: invokestatic a : (Ljava/lang/Exception;)Ljava/lang/Exception;
/*     */     //   22: athrow
/*     */     //   23: aload_3
/*     */     //   24: ifnonnull -> 33
/*     */     //   27: aload_0
/*     */     //   28: iload_2
/*     */     //   29: invokestatic copyOf : ([BI)[B
/*     */     //   32: astore_3
/*     */     //   33: iload_1
/*     */     //   34: iload_2
/*     */     //   35: iadd
/*     */     //   36: iconst_1
/*     */     //   37: iushr
/*     */     //   38: istore #5
/*     */     //   40: aload_3
/*     */     //   41: iload_1
/*     */     //   42: iload #5
/*     */     //   44: aload_0
/*     */     //   45: invokestatic a : ([BII[B)V
/*     */     //   48: aload_3
/*     */     //   49: iload #5
/*     */     //   51: iload_2
/*     */     //   52: aload_0
/*     */     //   53: invokestatic a : ([BII[B)V
/*     */     //   56: aload_3
/*     */     //   57: iload #5
/*     */     //   59: iconst_1
/*     */     //   60: isub
/*     */     //   61: baload
/*     */     //   62: aload_3
/*     */     //   63: iload #5
/*     */     //   65: baload
/*     */     //   66: if_icmpgt -> 83
/*     */     //   69: aload_3
/*     */     //   70: iload_1
/*     */     //   71: aload_0
/*     */     //   72: iload_1
/*     */     //   73: iload #4
/*     */     //   75: invokestatic arraycopy : (Ljava/lang/Object;ILjava/lang/Object;II)V
/*     */     //   78: return
/*     */     //   79: invokestatic a : (Ljava/lang/Exception;)Ljava/lang/Exception;
/*     */     //   82: athrow
/*     */     //   83: iload_1
/*     */     //   84: istore #6
/*     */     //   86: iload_1
/*     */     //   87: istore #7
/*     */     //   89: iload #5
/*     */     //   91: istore #8
/*     */     //   93: iload #6
/*     */     //   95: iload_2
/*     */     //   96: if_icmpge -> 179
/*     */     //   99: iload #8
/*     */     //   101: iload_2
/*     */     //   102: if_icmpge -> 144
/*     */     //   105: goto -> 112
/*     */     //   108: invokestatic a : (Ljava/lang/Exception;)Ljava/lang/Exception;
/*     */     //   111: athrow
/*     */     //   112: iload #7
/*     */     //   114: iload #5
/*     */     //   116: if_icmpge -> 162
/*     */     //   119: goto -> 126
/*     */     //   122: invokestatic a : (Ljava/lang/Exception;)Ljava/lang/Exception;
/*     */     //   125: athrow
/*     */     //   126: aload_3
/*     */     //   127: iload #7
/*     */     //   129: baload
/*     */     //   130: aload_3
/*     */     //   131: iload #8
/*     */     //   133: baload
/*     */     //   134: if_icmpgt -> 162
/*     */     //   137: goto -> 144
/*     */     //   140: invokestatic a : (Ljava/lang/Exception;)Ljava/lang/Exception;
/*     */     //   143: athrow
/*     */     //   144: aload_0
/*     */     //   145: iload #6
/*     */     //   147: aload_3
/*     */     //   148: iload #7
/*     */     //   150: iinc #7, 1
/*     */     //   153: baload
/*     */     //   154: bastore
/*     */     //   155: goto -> 173
/*     */     //   158: invokestatic a : (Ljava/lang/Exception;)Ljava/lang/Exception;
/*     */     //   161: athrow
/*     */     //   162: aload_0
/*     */     //   163: iload #6
/*     */     //   165: aload_3
/*     */     //   166: iload #8
/*     */     //   168: iinc #8, 1
/*     */     //   171: baload
/*     */     //   172: bastore
/*     */     //   173: iinc #6, 1
/*     */     //   176: goto -> 93
/*     */     //   179: return
/*     */     // Line number table:
/*     */     //   Java source line number -> byte code offset
/*     */     //   #475	-> 0
/*     */     //   #876	-> 5
/*     */     //   #579	-> 12
/*     */     //   #188	-> 18
/*     */     //   #441	-> 23
/*     */     //   #473	-> 33
/*     */     //   #26	-> 40
/*     */     //   #811	-> 48
/*     */     //   #857	-> 56
/*     */     //   #614	-> 69
/*     */     //   #334	-> 78
/*     */     //   #467	-> 83
/*     */     //   #819	-> 99
/*     */     //   #193	-> 162
/*     */     //   #624	-> 173
/*     */     //   #310	-> 179
/*     */     // Exception table:
/*     */     //   from	to	target	type
/*     */     //   5	19	19	java/lang/IllegalArgumentException
/*     */     //   40	79	79	java/lang/IllegalArgumentException
/*     */     //   93	105	108	java/lang/IllegalArgumentException
/*     */     //   99	119	122	java/lang/IllegalArgumentException
/*     */     //   112	137	140	java/lang/IllegalArgumentException
/*     */     //   126	158	158	java/lang/IllegalArgumentException
/*     */   }
/*     */   
/*     */   public static void c(byte[] paramArrayOfbyte) {
/*     */     e(paramArrayOfbyte, 0, paramArrayOfbyte.length);
/*     */   }
/*     */   
/*     */   public static void b(byte[] paramArrayOfbyte, int paramInt1, int paramInt2) {
/*     */     aL.a(paramArrayOfbyte.length, paramInt1, paramInt2);
/*     */   }
/*     */   
/*     */   public static void b(byte[] paramArrayOfbyte, g9 paramg9) {
/*     */     g(paramArrayOfbyte, 0, paramArrayOfbyte.length, paramg9);
/*     */   }
/*     */   
/*     */   public static void c(int[] paramArrayOfint, byte[] paramArrayOfbyte) {
/*     */     b(paramArrayOfint, paramArrayOfbyte, 0, paramArrayOfbyte.length);
/*     */   }
/*     */   
/*     */   public static void a(int[] paramArrayOfint, byte[] paramArrayOfbyte, int paramInt1, int paramInt2, boolean paramBoolean) {
/*     */     ForkJoinPool forkJoinPool = a();
/*     */     try {
/*     */       if (paramInt2 - paramInt1 >= 1024)
/*     */         try {
/*     */           if (forkJoinPool.getParallelism() != 1) {
/*     */             boolean bool = false;
/*     */             LinkedBlockingQueue<Q> linkedBlockingQueue = new LinkedBlockingQueue();
/*     */             linkedBlockingQueue.add(new Q(paramInt1, paramInt2 - paramInt1, 0));
/*     */             AtomicInteger atomicInteger = new AtomicInteger(1);
/*     */             int i = forkJoinPool.getParallelism();
/*     */             ExecutorCompletionService executorCompletionService = new ExecutorCompletionService(forkJoinPool);
/*     */             try {
/*     */             
/*     */             } catch (Exception exception) {
/*     */               throw a(null);
/*     */             } 
/*     */             int[] arrayOfInt = paramBoolean ? new int[paramArrayOfint.length] : null;
/*     */             int j = i;
/*     */             try {
/*     */               for (; j-- != 0; executorCompletionService.submit(() -> {
/*     */                     // Byte code:
/*     */                     //   0: sipush #256
/*     */                     //   3: newarray int
/*     */                     //   5: astore #7
/*     */                     //   7: sipush #256
/*     */                     //   10: newarray int
/*     */                     //   12: astore #8
/*     */                     //   14: aload_0
/*     */                     //   15: invokevirtual get : ()I
/*     */                     //   18: ifne -> 47
/*     */                     //   21: iload_1
/*     */                     //   22: istore #9
/*     */                     //   24: iload #9
/*     */                     //   26: iinc #9, -1
/*     */                     //   29: ifeq -> 47
/*     */                     //   32: aload_2
/*     */                     //   33: getstatic me/konsolas/aac/dx.i : Lme/konsolas/aac/Q;
/*     */                     //   36: invokevirtual add : (Ljava/lang/Object;)Z
/*     */                     //   39: pop
/*     */                     //   40: goto -> 24
/*     */                     //   43: invokestatic a : (Ljava/lang/Exception;)Ljava/lang/Exception;
/*     */                     //   46: athrow
/*     */                     //   47: aload_2
/*     */                     //   48: invokevirtual take : ()Ljava/lang/Object;
/*     */                     //   51: checkcast me/konsolas/aac/Q
/*     */                     //   54: astore #9
/*     */                     //   56: aload #9
/*     */                     //   58: getstatic me/konsolas/aac/dx.i : Lme/konsolas/aac/Q;
/*     */                     //   61: if_acmpne -> 70
/*     */                     //   64: aconst_null
/*     */                     //   65: areturn
/*     */                     //   66: invokestatic a : (Ljava/lang/Exception;)Ljava/lang/Exception;
/*     */                     //   69: athrow
/*     */                     //   70: aload #9
/*     */                     //   72: getfield a : I
/*     */                     //   75: istore #10
/*     */                     //   77: aload #9
/*     */                     //   79: getfield b : I
/*     */                     //   82: istore #11
/*     */                     //   84: aload #9
/*     */                     //   86: getfield c : I
/*     */                     //   89: istore #12
/*     */                     //   91: iload #12
/*     */                     //   93: iconst_1
/*     */                     //   94: irem
/*     */                     //   95: ifne -> 108
/*     */                     //   98: sipush #128
/*     */                     //   101: goto -> 109
/*     */                     //   104: invokestatic a : (Ljava/lang/Exception;)Ljava/lang/Exception;
/*     */                     //   107: athrow
/*     */                     //   108: iconst_0
/*     */                     //   109: istore #13
/*     */                     //   111: iconst_0
/*     */                     //   112: iload #12
/*     */                     //   114: iconst_1
/*     */                     //   115: irem
/*     */                     //   116: isub
/*     */                     //   117: bipush #8
/*     */                     //   119: imul
/*     */                     //   120: istore #14
/*     */                     //   122: iload #10
/*     */                     //   124: iload #11
/*     */                     //   126: iadd
/*     */                     //   127: istore #15
/*     */                     //   129: iload #15
/*     */                     //   131: iinc #15, -1
/*     */                     //   134: iload #10
/*     */                     //   136: if_icmpeq -> 170
/*     */                     //   139: aload #7
/*     */                     //   141: aload_3
/*     */                     //   142: aload #4
/*     */                     //   144: iload #15
/*     */                     //   146: iaload
/*     */                     //   147: baload
/*     */                     //   148: iload #14
/*     */                     //   150: iushr
/*     */                     //   151: sipush #255
/*     */                     //   154: iand
/*     */                     //   155: iload #13
/*     */                     //   157: ixor
/*     */                     //   158: dup2
/*     */                     //   159: iaload
/*     */                     //   160: iconst_1
/*     */                     //   161: iadd
/*     */                     //   162: iastore
/*     */                     //   163: goto -> 129
/*     */                     //   166: invokestatic a : (Ljava/lang/Exception;)Ljava/lang/Exception;
/*     */                     //   169: athrow
/*     */                     //   170: iconst_m1
/*     */                     //   171: istore #15
/*     */                     //   173: iconst_0
/*     */                     //   174: istore #16
/*     */                     //   176: iload #10
/*     */                     //   178: istore #17
/*     */                     //   180: iload #16
/*     */                     //   182: sipush #256
/*     */                     //   185: if_icmpge -> 229
/*     */                     //   188: aload #7
/*     */                     //   190: iload #16
/*     */                     //   192: iaload
/*     */                     //   193: ifeq -> 207
/*     */                     //   196: goto -> 203
/*     */                     //   199: invokestatic a : (Ljava/lang/Exception;)Ljava/lang/Exception;
/*     */                     //   202: athrow
/*     */                     //   203: iload #16
/*     */                     //   205: istore #15
/*     */                     //   207: aload #8
/*     */                     //   209: iload #16
/*     */                     //   211: iload #17
/*     */                     //   213: aload #7
/*     */                     //   215: iload #16
/*     */                     //   217: iaload
/*     */                     //   218: iadd
/*     */                     //   219: dup
/*     */                     //   220: istore #17
/*     */                     //   222: iastore
/*     */                     //   223: iinc #16, 1
/*     */                     //   226: goto -> 180
/*     */                     //   229: iload #5
/*     */                     //   231: ifeq -> 442
/*     */                     //   234: iload #10
/*     */                     //   236: iload #11
/*     */                     //   238: iadd
/*     */                     //   239: istore #16
/*     */                     //   241: iload #16
/*     */                     //   243: iinc #16, -1
/*     */                     //   246: iload #10
/*     */                     //   248: if_icmpeq -> 291
/*     */                     //   251: aload #6
/*     */                     //   253: aload #8
/*     */                     //   255: aload_3
/*     */                     //   256: aload #4
/*     */                     //   258: iload #16
/*     */                     //   260: iaload
/*     */                     //   261: baload
/*     */                     //   262: iload #14
/*     */                     //   264: iushr
/*     */                     //   265: sipush #255
/*     */                     //   268: iand
/*     */                     //   269: iload #13
/*     */                     //   271: ixor
/*     */                     //   272: dup2
/*     */                     //   273: iaload
/*     */                     //   274: iconst_1
/*     */                     //   275: isub
/*     */                     //   276: dup_x2
/*     */                     //   277: iastore
/*     */                     //   278: aload #4
/*     */                     //   280: iload #16
/*     */                     //   282: iaload
/*     */                     //   283: iastore
/*     */                     //   284: goto -> 241
/*     */                     //   287: invokestatic a : (Ljava/lang/Exception;)Ljava/lang/Exception;
/*     */                     //   290: athrow
/*     */                     //   291: aload #6
/*     */                     //   293: iload #10
/*     */                     //   295: aload #4
/*     */                     //   297: iload #10
/*     */                     //   299: iload #11
/*     */                     //   301: invokestatic arraycopy : (Ljava/lang/Object;ILjava/lang/Object;II)V
/*     */                     //   304: iconst_0
/*     */                     //   305: istore #16
/*     */                     //   307: iload #10
/*     */                     //   309: istore #17
/*     */                     //   311: iload #16
/*     */                     //   313: iload #15
/*     */                     //   315: if_icmpgt -> 433
/*     */                     //   318: iload #12
/*     */                     //   320: ifge -> 417
/*     */                     //   323: goto -> 330
/*     */                     //   326: invokestatic a : (Ljava/lang/Exception;)Ljava/lang/Exception;
/*     */                     //   329: athrow
/*     */                     //   330: aload #7
/*     */                     //   332: iload #16
/*     */                     //   334: iaload
/*     */                     //   335: iconst_1
/*     */                     //   336: if_icmple -> 417
/*     */                     //   339: goto -> 346
/*     */                     //   342: invokestatic a : (Ljava/lang/Exception;)Ljava/lang/Exception;
/*     */                     //   345: athrow
/*     */                     //   346: aload #7
/*     */                     //   348: iload #16
/*     */                     //   350: iaload
/*     */                     //   351: sipush #1024
/*     */                     //   354: if_icmpge -> 389
/*     */                     //   357: goto -> 364
/*     */                     //   360: invokestatic a : (Ljava/lang/Exception;)Ljava/lang/Exception;
/*     */                     //   363: athrow
/*     */                     //   364: aload #4
/*     */                     //   366: aload_3
/*     */                     //   367: iload #17
/*     */                     //   369: iload #17
/*     */                     //   371: aload #7
/*     */                     //   373: iload #16
/*     */                     //   375: iaload
/*     */                     //   376: iadd
/*     */                     //   377: iload #5
/*     */                     //   379: invokestatic b : ([I[BIIZ)V
/*     */                     //   382: goto -> 417
/*     */                     //   385: invokestatic a : (Ljava/lang/Exception;)Ljava/lang/Exception;
/*     */                     //   388: athrow
/*     */                     //   389: aload_0
/*     */                     //   390: invokevirtual incrementAndGet : ()I
/*     */                     //   393: pop
/*     */                     //   394: aload_2
/*     */                     //   395: new me/konsolas/aac/Q
/*     */                     //   398: dup
/*     */                     //   399: iload #17
/*     */                     //   401: aload #7
/*     */                     //   403: iload #16
/*     */                     //   405: iaload
/*     */                     //   406: iload #12
/*     */                     //   408: iconst_1
/*     */                     //   409: iadd
/*     */                     //   410: invokespecial <init> : (III)V
/*     */                     //   413: invokevirtual add : (Ljava/lang/Object;)Z
/*     */                     //   416: pop
/*     */                     //   417: iload #17
/*     */                     //   419: aload #7
/*     */                     //   421: iload #16
/*     */                     //   423: iaload
/*     */                     //   424: iadd
/*     */                     //   425: istore #17
/*     */                     //   427: iinc #16, 1
/*     */                     //   430: goto -> 311
/*     */                     //   433: aload #7
/*     */                     //   435: iconst_0
/*     */                     //   436: invokestatic fill : ([II)V
/*     */                     //   439: goto -> 672
/*     */                     //   442: iload #10
/*     */                     //   444: iload #11
/*     */                     //   446: iadd
/*     */                     //   447: aload #7
/*     */                     //   449: iload #15
/*     */                     //   451: iaload
/*     */                     //   452: isub
/*     */                     //   453: istore #16
/*     */                     //   455: iload #10
/*     */                     //   457: istore #17
/*     */                     //   459: iconst_m1
/*     */                     //   460: istore #18
/*     */                     //   462: iload #17
/*     */                     //   464: iload #16
/*     */                     //   466: if_icmpgt -> 672
/*     */                     //   469: aload #4
/*     */                     //   471: iload #17
/*     */                     //   473: iaload
/*     */                     //   474: istore #20
/*     */                     //   476: aload_3
/*     */                     //   477: iload #20
/*     */                     //   479: baload
/*     */                     //   480: iload #14
/*     */                     //   482: iushr
/*     */                     //   483: sipush #255
/*     */                     //   486: iand
/*     */                     //   487: iload #13
/*     */                     //   489: ixor
/*     */                     //   490: istore #18
/*     */                     //   492: iload #17
/*     */                     //   494: iload #16
/*     */                     //   496: if_icmpge -> 561
/*     */                     //   499: aload #8
/*     */                     //   501: iload #18
/*     */                     //   503: dup2
/*     */                     //   504: iaload
/*     */                     //   505: iconst_1
/*     */                     //   506: isub
/*     */                     //   507: dup_x2
/*     */                     //   508: iastore
/*     */                     //   509: dup
/*     */                     //   510: istore #19
/*     */                     //   512: iload #17
/*     */                     //   514: if_icmple -> 554
/*     */                     //   517: iload #20
/*     */                     //   519: istore #21
/*     */                     //   521: aload #4
/*     */                     //   523: iload #19
/*     */                     //   525: iaload
/*     */                     //   526: istore #20
/*     */                     //   528: aload #4
/*     */                     //   530: iload #19
/*     */                     //   532: iload #21
/*     */                     //   534: iastore
/*     */                     //   535: aload_3
/*     */                     //   536: iload #20
/*     */                     //   538: baload
/*     */                     //   539: iload #14
/*     */                     //   541: iushr
/*     */                     //   542: sipush #255
/*     */                     //   545: iand
/*     */                     //   546: iload #13
/*     */                     //   548: ixor
/*     */                     //   549: istore #18
/*     */                     //   551: goto -> 499
/*     */                     //   554: aload #4
/*     */                     //   556: iload #17
/*     */                     //   558: iload #20
/*     */                     //   560: iastore
/*     */                     //   561: iload #12
/*     */                     //   563: ifge -> 653
/*     */                     //   566: aload #7
/*     */                     //   568: iload #18
/*     */                     //   570: iaload
/*     */                     //   571: iconst_1
/*     */                     //   572: if_icmple -> 653
/*     */                     //   575: goto -> 582
/*     */                     //   578: invokestatic a : (Ljava/lang/Exception;)Ljava/lang/Exception;
/*     */                     //   581: athrow
/*     */                     //   582: aload #7
/*     */                     //   584: iload #18
/*     */                     //   586: iaload
/*     */                     //   587: sipush #1024
/*     */                     //   590: if_icmpge -> 625
/*     */                     //   593: goto -> 600
/*     */                     //   596: invokestatic a : (Ljava/lang/Exception;)Ljava/lang/Exception;
/*     */                     //   599: athrow
/*     */                     //   600: aload #4
/*     */                     //   602: aload_3
/*     */                     //   603: iload #17
/*     */                     //   605: iload #17
/*     */                     //   607: aload #7
/*     */                     //   609: iload #18
/*     */                     //   611: iaload
/*     */                     //   612: iadd
/*     */                     //   613: iload #5
/*     */                     //   615: invokestatic b : ([I[BIIZ)V
/*     */                     //   618: goto -> 653
/*     */                     //   621: invokestatic a : (Ljava/lang/Exception;)Ljava/lang/Exception;
/*     */                     //   624: athrow
/*     */                     //   625: aload_0
/*     */                     //   626: invokevirtual incrementAndGet : ()I
/*     */                     //   629: pop
/*     */                     //   630: aload_2
/*     */                     //   631: new me/konsolas/aac/Q
/*     */                     //   634: dup
/*     */                     //   635: iload #17
/*     */                     //   637: aload #7
/*     */                     //   639: iload #18
/*     */                     //   641: iaload
/*     */                     //   642: iload #12
/*     */                     //   644: iconst_1
/*     */                     //   645: iadd
/*     */                     //   646: invokespecial <init> : (III)V
/*     */                     //   649: invokevirtual add : (Ljava/lang/Object;)Z
/*     */                     //   652: pop
/*     */                     //   653: iload #17
/*     */                     //   655: aload #7
/*     */                     //   657: iload #18
/*     */                     //   659: iaload
/*     */                     //   660: iadd
/*     */                     //   661: istore #17
/*     */                     //   663: aload #7
/*     */                     //   665: iload #18
/*     */                     //   667: iconst_0
/*     */                     //   668: iastore
/*     */                     //   669: goto -> 462
/*     */                     //   672: aload_0
/*     */                     //   673: invokevirtual decrementAndGet : ()I
/*     */                     //   676: pop
/*     */                     //   677: goto -> 14
/*     */                     // Line number table:
/*     */                     //   Java source line number -> byte code offset
/*     */                     //   #677	-> 0
/*     */                     //   #462	-> 7
/*     */                     //   #731	-> 14
/*     */                     //   #366	-> 47
/*     */                     //   #597	-> 56
/*     */                     //   #908	-> 70
/*     */                     //   #551	-> 77
/*     */                     //   #844	-> 84
/*     */                     //   #834	-> 91
/*     */                     //   #74	-> 111
/*     */                     //   #789	-> 122
/*     */                     //   #575	-> 170
/*     */                     //   #800	-> 173
/*     */                     //   #406	-> 188
/*     */                     //   #316	-> 207
/*     */                     //   #198	-> 223
/*     */                     //   #739	-> 229
/*     */                     //   #780	-> 234
/*     */                     //   #685	-> 291
/*     */                     //   #873	-> 304
/*     */                     //   #492	-> 318
/*     */                     //   #200	-> 346
/*     */                     //   #742	-> 389
/*     */                     //   #884	-> 394
/*     */                     //   #321	-> 417
/*     */                     //   #223	-> 427
/*     */                     //   #663	-> 433
/*     */                     //   #712	-> 442
/*     */                     //   #676	-> 455
/*     */                     //   #708	-> 469
/*     */                     //   #416	-> 476
/*     */                     //   #609	-> 492
/*     */                     //   #253	-> 499
/*     */                     //   #46	-> 517
/*     */                     //   #140	-> 521
/*     */                     //   #619	-> 528
/*     */                     //   #809	-> 535
/*     */                     //   #287	-> 551
/*     */                     //   #178	-> 554
/*     */                     //   #355	-> 561
/*     */                     //   #694	-> 582
/*     */                     //   #695	-> 625
/*     */                     //   #843	-> 630
/*     */                     //   #646	-> 653
/*     */                     //   #397	-> 672
/*     */                     //   #146	-> 677
/*     */                     // Exception table:
/*     */                     //   from	to	target	type
/*     */                     //   24	43	43	java/lang/Exception
/*     */                     //   56	66	66	java/lang/Exception
/*     */                     //   91	104	104	java/lang/Exception
/*     */                     //   129	166	166	java/lang/Exception
/*     */                     //   180	196	199	java/lang/Exception
/*     */                     //   241	287	287	java/lang/Exception
/*     */                     //   311	323	326	java/lang/Exception
/*     */                     //   318	339	342	java/lang/Exception
/*     */                     //   330	357	360	java/lang/Exception
/*     */                     //   346	385	385	java/lang/Exception
/*     */                     //   561	575	578	java/lang/Exception
/*     */                     //   566	593	596	java/lang/Exception
/*     */                     //   582	621	621	java/lang/Exception
/*     */                   }));
/*     */             } catch (Exception exception) {
/*     */               throw a(null);
/*     */             } 
/*     */             Throwable throwable = null;
/*     */             for (int k = i; k-- != 0; ) {
/*     */               try {
/*     */                 executorCompletionService.take().get();
/*     */                 continue;
/*     */               } catch (Exception exception) {}
/*     */               throwable = exception.getCause();
/*     */             } 
/*     */             try {
/*     */               if (throwable != null) {
/*     */                 try {
/*     */                 
/*     */                 } catch (Exception exception) {
/*     */                   throw a(null);
/*     */                 } 
/*     */                 throw (throwable instanceof RuntimeException) ? (RuntimeException)throwable : new RuntimeException(throwable);
/*     */               } 
/*     */             } catch (Exception exception) {
/*     */               throw a(null);
/*     */             } 
/*     */             return;
/*     */           } 
/*     */           b(paramArrayOfint, paramArrayOfbyte, paramInt1, paramInt2, paramBoolean);
/*     */           return;
/*     */         } catch (Exception exception) {
/*     */           throw a(null);
/*     */         }  
/*     */     } catch (Exception exception) {
/*     */       throw a(null);
/*     */     } 
/*     */     b(paramArrayOfint, paramArrayOfbyte, paramInt1, paramInt2, paramBoolean);
/*     */   }
/*     */   
/*     */   public static void b(byte[] paramArrayOfbyte1, byte[] paramArrayOfbyte2) {
/*     */     a(paramArrayOfbyte1, paramArrayOfbyte2);
/*     */     g(paramArrayOfbyte1, paramArrayOfbyte2, 0, paramArrayOfbyte1.length);
/*     */   }
/*     */   
/*     */   public static void a(int[] paramArrayOfint, byte[] paramArrayOfbyte1, byte[] paramArrayOfbyte2, int paramInt1, int paramInt2, boolean paramBoolean) {
/*     */     try {
/*     */       if (paramInt2 - paramInt1 < 1024) {
/*     */         a(paramArrayOfint, paramArrayOfbyte1, paramArrayOfbyte2, paramInt1, paramInt2);
/*     */         return;
/*     */       } 
/*     */     } catch (IllegalArgumentException illegalArgumentException) {
/*     */       throw a(null);
/*     */     } 
/*     */     byte b1 = 2;
/*     */     boolean bool = true;
/*     */     char c = 'Ā';
/*     */     byte b2 = 0;
/*     */     int[] arrayOfInt1 = new int[256];
/*     */     int[] arrayOfInt2 = new int[256];
/*     */     int[] arrayOfInt3 = new int[256];
/*     */     arrayOfInt1[b2] = paramInt1;
/*     */     arrayOfInt2[b2] = paramInt2 - paramInt1;
/*     */     arrayOfInt3[b2++] = 0;
/*     */     int[] arrayOfInt4 = new int[256];
/*     */     int[] arrayOfInt5 = new int[256];
/*     */     try {
/*     */     
/*     */     } catch (IllegalArgumentException illegalArgumentException) {
/*     */       throw a(null);
/*     */     } 
/*     */     int[] arrayOfInt6 = paramBoolean ? new int[paramArrayOfint.length] : null;
/*     */     for (; b2 > 0; j = arrayOfInt2[b2], k = arrayOfInt3[b2])
/*     */       int j, k, i = arrayOfInt1[--b2]; 
/*     */   }
/*     */   
/*     */   public static void k(byte[] paramArrayOfbyte, int paramInt1, int paramInt2) {
/*     */     ForkJoinPool forkJoinPool = a();
/*     */     try {
/*     */       if (paramInt2 - paramInt1 >= 8192) {
/*     */         try {
/*     */           if (forkJoinPool.getParallelism() == 1) {
/*     */             l(paramArrayOfbyte, paramInt1, paramInt2);
/*     */             return;
/*     */           } 
/*     */         } catch (IllegalArgumentException illegalArgumentException) {
/*     */           throw a(null);
/*     */         } 
/*     */         forkJoinPool.invoke(new cu(paramArrayOfbyte, paramInt1, paramInt2));
/*     */         return;
/*     */       } 
/*     */     } catch (IllegalArgumentException illegalArgumentException) {
/*     */       throw a(null);
/*     */     } 
/*     */     l(paramArrayOfbyte, paramInt1, paramInt2);
/*     */   }
/*     */   
/*     */   public static void d(byte[] paramArrayOfbyte, g9 paramg9) {
/*     */     c(paramArrayOfbyte, 0, paramArrayOfbyte.length, paramg9);
/*     */   }
/*     */   
/*     */   private static void a(int[] paramArrayOfint, byte[] paramArrayOfbyte, int paramInt1, int paramInt2) {
/*     */     for (int i = paramInt1; ++i < paramInt2; k = i, m = paramArrayOfint[k - 1])
/*     */       int k, m, j = paramArrayOfint[i]; 
/*     */   }
/*     */   
/*     */   public static void a(byte[] paramArrayOfbyte, g9 paramg9) {
/*     */     f(paramArrayOfbyte, 0, paramArrayOfbyte.length, paramg9);
/*     */   }
/*     */   
/*     */   public static void d(byte[] paramArrayOfbyte, int paramInt1, int paramInt2) {
/*     */     a(paramArrayOfbyte, paramInt1, paramInt2, (byte[])null);
/*     */   }
/*     */   
/*     */   public static int a(byte[] paramArrayOfbyte, int paramInt1, int paramInt2, byte paramByte) {
/*     */     paramInt2--;
/*     */     for (; paramInt1 <= paramInt2; b = paramArrayOfbyte[i]) {
/*     */       byte b;
/*     */       int i = paramInt1 + paramInt2 >>> 1;
/*     */     } 
/*     */     return -(paramInt1 + 1);
/*     */   }
/*     */   
/*     */   public static void a(byte[][] paramArrayOfbyte, int paramInt1, int paramInt2) {
/*     */     // Byte code:
/*     */     //   0: getstatic me/konsolas/aac/dx.o : J
/*     */     //   3: ldc2_w 39477818251380
/*     */     //   6: lxor
/*     */     //   7: lstore_3
/*     */     //   8: iload_2
/*     */     //   9: iload_1
/*     */     //   10: isub
/*     */     //   11: sipush #1024
/*     */     //   14: if_icmpge -> 35
/*     */     //   17: aload_0
/*     */     //   18: iload_1
/*     */     //   19: iload_2
/*     */     //   20: iconst_0
/*     */     //   21: invokestatic a : ([[BIII)V
/*     */     //   24: return
/*     */     //   25: ldc2_w -4098392460438678885
/*     */     //   28: lload_3
/*     */     //   29: <illegal opcode> w : (Ljava/lang/Exception;JJ)Ljava/lang/Exception;
/*     */     //   34: athrow
/*     */     //   35: aload_0
/*     */     //   36: arraylength
/*     */     //   37: istore #5
/*     */     //   39: iconst_1
/*     */     //   40: iload #5
/*     */     //   42: imul
/*     */     //   43: iconst_1
/*     */     //   44: isub
/*     */     //   45: istore #6
/*     */     //   47: iload #5
/*     */     //   49: istore #7
/*     */     //   51: aload_0
/*     */     //   52: iconst_0
/*     */     //   53: aaload
/*     */     //   54: arraylength
/*     */     //   55: istore #8
/*     */     //   57: iload #7
/*     */     //   59: iinc #7, -1
/*     */     //   62: ifeq -> 156
/*     */     //   65: aload_0
/*     */     //   66: iload #7
/*     */     //   68: aaload
/*     */     //   69: arraylength
/*     */     //   70: iload #8
/*     */     //   72: if_icmpeq -> 57
/*     */     //   75: new java/lang/IllegalArgumentException
/*     */     //   78: dup
/*     */     //   79: new java/lang/StringBuilder
/*     */     //   82: dup
/*     */     //   83: invokespecial <init> : ()V
/*     */     //   86: ldc_w '麡稐ด㐱⼖圿瓂樳洩序킞Ⴉ᤿纍䣭㖹僒尯㐔两'
/*     */     //   89: invokevirtual toCharArray : ()[C
/*     */     //   92: dup
/*     */     //   93: dup
/*     */     //   94: bipush #12
/*     */     //   96: dup_x1
/*     */     //   97: caload
/*     */     //   98: sipush #13216
/*     */     //   101: ixor
/*     */     //   102: i2c
/*     */     //   103: castore
/*     */     //   104: sipush #9430
/*     */     //   107: iconst_3
/*     */     //   108: iconst_4
/*     */     //   109: invokestatic H : (Ljava/lang/Object;SBB)Ljava/lang/String;
/*     */     //   112: invokevirtual append : (Ljava/lang/String;)Ljava/lang/StringBuilder;
/*     */     //   115: iload #7
/*     */     //   117: invokevirtual append : (I)Ljava/lang/StringBuilder;
/*     */     //   120: ldc_w '煰汚䇙靛簞ㇾ緘ꅔ֪ࡨႻⶵꄀ疘煂▲᮹ࡓ쩋ࡥ瓯ﴓ餀䁹⊃緺못⁗⛻갫?梼뫭퐎히뮦꿄飛⯩苤᠁햓Ꭳ颐⇛'
/*     */     //   123: invokevirtual toCharArray : ()[C
/*     */     //   126: dup
/*     */     //   127: dup
/*     */     //   128: bipush #31
/*     */     //   130: dup_x1
/*     */     //   131: caload
/*     */     //   132: sipush #5169
/*     */     //   135: ixor
/*     */     //   136: i2c
/*     */     //   137: castore
/*     */     //   138: sipush #16855
/*     */     //   141: iconst_3
/*     */     //   142: iconst_1
/*     */     //   143: invokestatic H : (Ljava/lang/Object;SBB)Ljava/lang/String;
/*     */     //   146: invokevirtual append : (Ljava/lang/String;)Ljava/lang/StringBuilder;
/*     */     //   149: invokevirtual toString : ()Ljava/lang/String;
/*     */     //   152: invokespecial <init> : (Ljava/lang/String;)V
/*     */     //   155: athrow
/*     */     //   156: sipush #255
/*     */     //   159: iload #5
/*     */     //   161: iconst_1
/*     */     //   162: imul
/*     */     //   163: iconst_1
/*     */     //   164: isub
/*     */     //   165: imul
/*     */     //   166: iconst_1
/*     */     //   167: iadd
/*     */     //   168: istore #7
/*     */     //   170: iconst_0
/*     */     //   171: istore #8
/*     */     //   173: iload #7
/*     */     //   175: newarray int
/*     */     //   177: astore #9
/*     */     //   179: iload #7
/*     */     //   181: newarray int
/*     */     //   183: astore #10
/*     */     //   185: iload #7
/*     */     //   187: newarray int
/*     */     //   189: astore #11
/*     */     //   191: aload #9
/*     */     //   193: iload #8
/*     */     //   195: iload_1
/*     */     //   196: iastore
/*     */     //   197: aload #10
/*     */     //   199: iload #8
/*     */     //   201: iload_2
/*     */     //   202: iload_1
/*     */     //   203: isub
/*     */     //   204: iastore
/*     */     //   205: aload #11
/*     */     //   207: iload #8
/*     */     //   209: iinc #8, 1
/*     */     //   212: iconst_0
/*     */     //   213: iastore
/*     */     //   214: sipush #256
/*     */     //   217: newarray int
/*     */     //   219: astore #12
/*     */     //   221: sipush #256
/*     */     //   224: newarray int
/*     */     //   226: astore #13
/*     */     //   228: iload #5
/*     */     //   230: newarray byte
/*     */     //   232: astore #14
/*     */     //   234: iload #8
/*     */     //   236: ifle -> 766
/*     */     //   239: aload #9
/*     */     //   241: iinc #8, -1
/*     */     //   244: iload #8
/*     */     //   246: iaload
/*     */     //   247: istore #15
/*     */     //   249: aload #10
/*     */     //   251: iload #8
/*     */     //   253: iaload
/*     */     //   254: istore #16
/*     */     //   256: aload #11
/*     */     //   258: iload #8
/*     */     //   260: iaload
/*     */     //   261: istore #17
/*     */     //   263: iload #17
/*     */     //   265: iconst_1
/*     */     //   266: irem
/*     */     //   267: ifne -> 286
/*     */     //   270: sipush #128
/*     */     //   273: goto -> 287
/*     */     //   276: ldc2_w -4098392460438678885
/*     */     //   279: lload_3
/*     */     //   280: <illegal opcode> w : (Ljava/lang/Exception;JJ)Ljava/lang/Exception;
/*     */     //   285: athrow
/*     */     //   286: iconst_0
/*     */     //   287: istore #18
/*     */     //   289: aload_0
/*     */     //   290: iload #17
/*     */     //   292: iconst_1
/*     */     //   293: idiv
/*     */     //   294: aaload
/*     */     //   295: astore #19
/*     */     //   297: iconst_0
/*     */     //   298: iload #17
/*     */     //   300: iconst_1
/*     */     //   301: irem
/*     */     //   302: isub
/*     */     //   303: bipush #8
/*     */     //   305: imul
/*     */     //   306: istore #20
/*     */     //   308: iload #15
/*     */     //   310: iload #16
/*     */     //   312: iadd
/*     */     //   313: istore #21
/*     */     //   315: iload #21
/*     */     //   317: iinc #21, -1
/*     */     //   320: iload #15
/*     */     //   322: if_icmpeq -> 360
/*     */     //   325: aload #12
/*     */     //   327: aload #19
/*     */     //   329: iload #21
/*     */     //   331: baload
/*     */     //   332: iload #20
/*     */     //   334: iushr
/*     */     //   335: sipush #255
/*     */     //   338: iand
/*     */     //   339: iload #18
/*     */     //   341: ixor
/*     */     //   342: dup2
/*     */     //   343: iaload
/*     */     //   344: iconst_1
/*     */     //   345: iadd
/*     */     //   346: iastore
/*     */     //   347: goto -> 315
/*     */     //   350: ldc2_w -4098392460438678885
/*     */     //   353: lload_3
/*     */     //   354: <illegal opcode> w : (Ljava/lang/Exception;JJ)Ljava/lang/Exception;
/*     */     //   359: athrow
/*     */     //   360: iconst_m1
/*     */     //   361: istore #21
/*     */     //   363: iconst_0
/*     */     //   364: istore #22
/*     */     //   366: iload #15
/*     */     //   368: istore #23
/*     */     //   370: iload #22
/*     */     //   372: sipush #256
/*     */     //   375: if_icmpge -> 425
/*     */     //   378: aload #12
/*     */     //   380: iload #22
/*     */     //   382: iaload
/*     */     //   383: ifeq -> 403
/*     */     //   386: goto -> 399
/*     */     //   389: ldc2_w -4098392460438678885
/*     */     //   392: lload_3
/*     */     //   393: <illegal opcode> w : (Ljava/lang/Exception;JJ)Ljava/lang/Exception;
/*     */     //   398: athrow
/*     */     //   399: iload #22
/*     */     //   401: istore #21
/*     */     //   403: aload #13
/*     */     //   405: iload #22
/*     */     //   407: iload #23
/*     */     //   409: aload #12
/*     */     //   411: iload #22
/*     */     //   413: iaload
/*     */     //   414: iadd
/*     */     //   415: dup
/*     */     //   416: istore #23
/*     */     //   418: iastore
/*     */     //   419: iinc #22, 1
/*     */     //   422: goto -> 370
/*     */     //   425: iload #15
/*     */     //   427: iload #16
/*     */     //   429: iadd
/*     */     //   430: aload #12
/*     */     //   432: iload #21
/*     */     //   434: iaload
/*     */     //   435: isub
/*     */     //   436: istore #22
/*     */     //   438: iload #15
/*     */     //   440: istore #23
/*     */     //   442: iconst_m1
/*     */     //   443: istore #24
/*     */     //   445: iload #23
/*     */     //   447: iload #22
/*     */     //   449: if_icmpgt -> 763
/*     */     //   452: iload #5
/*     */     //   454: istore #26
/*     */     //   456: iload #26
/*     */     //   458: iinc #26, -1
/*     */     //   461: ifeq -> 489
/*     */     //   464: aload #14
/*     */     //   466: iload #26
/*     */     //   468: aload_0
/*     */     //   469: iload #26
/*     */     //   471: aaload
/*     */     //   472: iload #23
/*     */     //   474: baload
/*     */     //   475: bastore
/*     */     //   476: goto -> 456
/*     */     //   479: ldc2_w -4098392460438678885
/*     */     //   482: lload_3
/*     */     //   483: <illegal opcode> w : (Ljava/lang/Exception;JJ)Ljava/lang/Exception;
/*     */     //   488: athrow
/*     */     //   489: aload #19
/*     */     //   491: iload #23
/*     */     //   493: baload
/*     */     //   494: iload #20
/*     */     //   496: iushr
/*     */     //   497: sipush #255
/*     */     //   500: iand
/*     */     //   501: iload #18
/*     */     //   503: ixor
/*     */     //   504: istore #24
/*     */     //   506: iload #23
/*     */     //   508: iload #22
/*     */     //   510: if_icmpge -> 631
/*     */     //   513: aload #13
/*     */     //   515: iload #24
/*     */     //   517: dup2
/*     */     //   518: iaload
/*     */     //   519: iconst_1
/*     */     //   520: isub
/*     */     //   521: dup_x2
/*     */     //   522: iastore
/*     */     //   523: dup
/*     */     //   524: istore #25
/*     */     //   526: iload #23
/*     */     //   528: if_icmple -> 594
/*     */     //   531: aload #19
/*     */     //   533: iload #25
/*     */     //   535: baload
/*     */     //   536: iload #20
/*     */     //   538: iushr
/*     */     //   539: sipush #255
/*     */     //   542: iand
/*     */     //   543: iload #18
/*     */     //   545: ixor
/*     */     //   546: istore #24
/*     */     //   548: iload #5
/*     */     //   550: istore #26
/*     */     //   552: iload #26
/*     */     //   554: iinc #26, -1
/*     */     //   557: ifeq -> 591
/*     */     //   560: aload #14
/*     */     //   562: iload #26
/*     */     //   564: baload
/*     */     //   565: istore #27
/*     */     //   567: aload #14
/*     */     //   569: iload #26
/*     */     //   571: aload_0
/*     */     //   572: iload #26
/*     */     //   574: aaload
/*     */     //   575: iload #25
/*     */     //   577: baload
/*     */     //   578: bastore
/*     */     //   579: aload_0
/*     */     //   580: iload #26
/*     */     //   582: aaload
/*     */     //   583: iload #25
/*     */     //   585: iload #27
/*     */     //   587: bastore
/*     */     //   588: goto -> 552
/*     */     //   591: goto -> 513
/*     */     //   594: iload #5
/*     */     //   596: istore #26
/*     */     //   598: iload #26
/*     */     //   600: iinc #26, -1
/*     */     //   603: ifeq -> 631
/*     */     //   606: aload_0
/*     */     //   607: iload #26
/*     */     //   609: aaload
/*     */     //   610: iload #23
/*     */     //   612: aload #14
/*     */     //   614: iload #26
/*     */     //   616: baload
/*     */     //   617: bastore
/*     */     //   618: goto -> 598
/*     */     //   621: ldc2_w -4098392460438678885
/*     */     //   624: lload_3
/*     */     //   625: <illegal opcode> w : (Ljava/lang/Exception;JJ)Ljava/lang/Exception;
/*     */     //   630: athrow
/*     */     //   631: iload #17
/*     */     //   633: iload #6
/*     */     //   635: if_icmpge -> 744
/*     */     //   638: aload #12
/*     */     //   640: iload #24
/*     */     //   642: iaload
/*     */     //   643: iconst_1
/*     */     //   644: if_icmple -> 744
/*     */     //   647: goto -> 660
/*     */     //   650: ldc2_w -4098392460438678885
/*     */     //   653: lload_3
/*     */     //   654: <illegal opcode> w : (Ljava/lang/Exception;JJ)Ljava/lang/Exception;
/*     */     //   659: athrow
/*     */     //   660: aload #12
/*     */     //   662: iload #24
/*     */     //   664: iaload
/*     */     //   665: sipush #1024
/*     */     //   668: if_icmpge -> 715
/*     */     //   671: goto -> 684
/*     */     //   674: ldc2_w -4098392460438678885
/*     */     //   677: lload_3
/*     */     //   678: <illegal opcode> w : (Ljava/lang/Exception;JJ)Ljava/lang/Exception;
/*     */     //   683: athrow
/*     */     //   684: aload_0
/*     */     //   685: iload #23
/*     */     //   687: iload #23
/*     */     //   689: aload #12
/*     */     //   691: iload #24
/*     */     //   693: iaload
/*     */     //   694: iadd
/*     */     //   695: iload #17
/*     */     //   697: iconst_1
/*     */     //   698: iadd
/*     */     //   699: invokestatic a : ([[BIII)V
/*     */     //   702: goto -> 744
/*     */     //   705: ldc2_w -4098392460438678885
/*     */     //   708: lload_3
/*     */     //   709: <illegal opcode> w : (Ljava/lang/Exception;JJ)Ljava/lang/Exception;
/*     */     //   714: athrow
/*     */     //   715: aload #9
/*     */     //   717: iload #8
/*     */     //   719: iload #23
/*     */     //   721: iastore
/*     */     //   722: aload #10
/*     */     //   724: iload #8
/*     */     //   726: aload #12
/*     */     //   728: iload #24
/*     */     //   730: iaload
/*     */     //   731: iastore
/*     */     //   732: aload #11
/*     */     //   734: iload #8
/*     */     //   736: iinc #8, 1
/*     */     //   739: iload #17
/*     */     //   741: iconst_1
/*     */     //   742: iadd
/*     */     //   743: iastore
/*     */     //   744: iload #23
/*     */     //   746: aload #12
/*     */     //   748: iload #24
/*     */     //   750: iaload
/*     */     //   751: iadd
/*     */     //   752: istore #23
/*     */     //   754: aload #12
/*     */     //   756: iload #24
/*     */     //   758: iconst_0
/*     */     //   759: iastore
/*     */     //   760: goto -> 445
/*     */     //   763: goto -> 234
/*     */     //   766: return
/*     */     // Line number table:
/*     */     //   Java source line number -> byte code offset
/*     */     //   #615	-> 8
/*     */     //   #790	-> 17
/*     */     //   #837	-> 24
/*     */     //   #374	-> 35
/*     */     //   #85	-> 39
/*     */     //   #847	-> 47
/*     */     //   #380	-> 156
/*     */     //   #319	-> 170
/*     */     //   #671	-> 173
/*     */     //   #251	-> 179
/*     */     //   #226	-> 185
/*     */     //   #736	-> 191
/*     */     //   #641	-> 197
/*     */     //   #281	-> 205
/*     */     //   #177	-> 214
/*     */     //   #882	-> 221
/*     */     //   #561	-> 228
/*     */     //   #564	-> 234
/*     */     //   #696	-> 239
/*     */     //   #354	-> 249
/*     */     //   #7	-> 256
/*     */     //   #431	-> 263
/*     */     //   #639	-> 289
/*     */     //   #128	-> 297
/*     */     //   #521	-> 308
/*     */     //   #30	-> 360
/*     */     //   #722	-> 363
/*     */     //   #552	-> 378
/*     */     //   #82	-> 403
/*     */     //   #214	-> 419
/*     */     //   #311	-> 425
/*     */     //   #324	-> 438
/*     */     //   #459	-> 452
/*     */     //   #921	-> 489
/*     */     //   #432	-> 506
/*     */     //   #795	-> 513
/*     */     //   #683	-> 531
/*     */     //   #487	-> 548
/*     */     //   #826	-> 560
/*     */     //   #910	-> 567
/*     */     //   #807	-> 579
/*     */     //   #613	-> 588
/*     */     //   #885	-> 594
/*     */     //   #653	-> 631
/*     */     //   #879	-> 660
/*     */     //   #606	-> 715
/*     */     //   #261	-> 722
/*     */     //   #756	-> 732
/*     */     //   #349	-> 744
/*     */     //   #241	-> 763
/*     */     //   #212	-> 766
/*     */     // Exception table:
/*     */     //   from	to	target	type
/*     */     //   8	25	25	java/lang/IllegalArgumentException
/*     */     //   263	276	276	java/lang/IllegalArgumentException
/*     */     //   315	350	350	java/lang/IllegalArgumentException
/*     */     //   370	386	389	java/lang/IllegalArgumentException
/*     */     //   456	479	479	java/lang/IllegalArgumentException
/*     */     //   598	621	621	java/lang/IllegalArgumentException
/*     */     //   631	647	650	java/lang/IllegalArgumentException
/*     */     //   638	671	674	java/lang/IllegalArgumentException
/*     */     //   660	705	705	java/lang/IllegalArgumentException
/*     */   }
/*     */   
/*     */   public static byte[] a(byte[] paramArrayOfbyte, int paramInt1, int paramInt2, Random paramRandom) {
/*     */     for (int i = paramInt2 - paramInt1; i-- != 0; ) {
/*     */       int j = paramRandom.nextInt(i + 1);
/*     */       byte b = paramArrayOfbyte[paramInt1 + i];
/*     */       paramArrayOfbyte[paramInt1 + i] = paramArrayOfbyte[paramInt1 + j];
/*     */       paramArrayOfbyte[paramInt1 + j] = b;
/*     */     } 
/*     */     return paramArrayOfbyte;
/*     */   }
/*     */   
/*     */   public static byte[] b(byte[] paramArrayOfbyte) {
/*     */     return (byte[])paramArrayOfbyte.clone();
/*     */   }
/*     */   
/*     */   public static void g(byte[] paramArrayOfbyte1, byte[] paramArrayOfbyte2, int paramInt1, int paramInt2) {
/*     */     try {
/*     */       if (paramInt2 - paramInt1 < 1024) {
/*     */         d(paramArrayOfbyte1, paramArrayOfbyte2, paramInt1, paramInt2);
/*     */         return;
/*     */       } 
/*     */     } catch (IllegalArgumentException illegalArgumentException) {
/*     */       throw a(null);
/*     */     } 
/*     */     byte b1 = 2;
/*     */     boolean bool = true;
/*     */     char c = 'Ā';
/*     */     byte b2 = 0;
/*     */     int[] arrayOfInt1 = new int[256];
/*     */     int[] arrayOfInt2 = new int[256];
/*     */     int[] arrayOfInt3 = new int[256];
/*     */     arrayOfInt1[b2] = paramInt1;
/*     */     arrayOfInt2[b2] = paramInt2 - paramInt1;
/*     */     arrayOfInt3[b2++] = 0;
/*     */     int[] arrayOfInt4 = new int[256];
/*     */     int[] arrayOfInt5 = new int[256];
/*     */     while (b2 > 0) {
/*     */       int i = arrayOfInt1[--b2];
/*     */       int j = arrayOfInt2[b2];
/*     */       int k = arrayOfInt3[b2];
/*     */       try {
/*     */       
/*     */       } catch (IllegalArgumentException illegalArgumentException) {
/*     */         throw a(null);
/*     */       } 
/*     */       boolean bool1 = (k % 1 == 0) ? true : false;
/*     */       try {
/*     */       
/*     */       } catch (IllegalArgumentException illegalArgumentException) {
/*     */         throw a(null);
/*     */       } 
/*     */       byte[] arrayOfByte = (k < 1) ? paramArrayOfbyte1 : paramArrayOfbyte2;
/*     */       int m = (0 - k % 1) * 8;
/*     */       int n = i + j;
/*     */       try {
/*     */         for (; n-- != i; arrayOfInt4[arrayOfByte[n] >>> m & 0xFF ^ bool1] = arrayOfInt4[arrayOfByte[n] >>> m & 0xFF ^ bool1] + 1);
/*     */       } catch (IllegalArgumentException illegalArgumentException) {
/*     */         throw a(null);
/*     */       } 
/*     */       n = -1;
/*     */       boolean bool2 = false;
/*     */       int i1 = i;
/*     */     } 
/*     */   }
/*     */   
/*     */   private static int b(byte[] paramArrayOfbyte, int paramInt1, int paramInt2, int paramInt3, g9 paramg9) {
/*     */     int i = paramg9.a(paramArrayOfbyte[paramInt1], paramArrayOfbyte[paramInt2]);
/*     */     int j = paramg9.a(paramArrayOfbyte[paramInt1], paramArrayOfbyte[paramInt3]);
/*     */     int k = paramg9.a(paramArrayOfbyte[paramInt2], paramArrayOfbyte[paramInt3]);
/*     */     try {
/*     */       if (i < 0) {
/*     */         try {
/*     */           try {
/*     */           
/*     */           } catch (IllegalArgumentException illegalArgumentException) {
/*     */             throw a(null);
/*     */           } 
/*     */         } catch (IllegalArgumentException illegalArgumentException) {
/*     */           throw a(null);
/*     */         } 
/*     */       } else {
/*     */         try {
/*     */           try {
/*     */           
/*     */           } catch (IllegalArgumentException illegalArgumentException) {
/*     */             throw a(null);
/*     */           } 
/*     */         } catch (IllegalArgumentException illegalArgumentException) {
/*     */           throw a(null);
/*     */         } 
/*     */       } 
/*     */     } catch (IllegalArgumentException illegalArgumentException) {
/*     */       throw a(null);
/*     */     } 
/*     */     return (k > 0) ? paramInt2 : ((j > 0) ? paramInt3 : paramInt1);
/*     */   }
/*     */   
/*     */   public static void i(byte[] paramArrayOfbyte, int paramInt1, int paramInt2) {
/*     */     byte b = paramArrayOfbyte[paramInt1];
/*     */     paramArrayOfbyte[paramInt1] = paramArrayOfbyte[paramInt2];
/*     */     paramArrayOfbyte[paramInt2] = b;
/*     */   }
/*     */   
/*     */   public static void f(byte[] paramArrayOfbyte, int paramInt1, int paramInt2, g9 paramg9) {
/*     */     ForkJoinPool forkJoinPool = a();
/*     */     try {
/*     */       if (paramInt2 - paramInt1 >= 8192) {
/*     */         try {
/*     */           if (forkJoinPool.getParallelism() == 1) {
/*     */             b(paramArrayOfbyte, paramInt1, paramInt2, paramg9);
/*     */             return;
/*     */           } 
/*     */         } catch (IllegalArgumentException illegalArgumentException) {
/*     */           throw a(null);
/*     */         } 
/*     */         forkJoinPool.invoke(new cg(paramArrayOfbyte, paramInt1, paramInt2, paramg9));
/*     */         return;
/*     */       } 
/*     */     } catch (IllegalArgumentException illegalArgumentException) {
/*     */       throw a(null);
/*     */     } 
/*     */     b(paramArrayOfbyte, paramInt1, paramInt2, paramg9);
/*     */   }
/*     */   
/*     */   public static byte[] c(byte[] paramArrayOfbyte, int paramInt1, int paramInt2) {
/*     */     if (paramInt1 > paramArrayOfbyte.length) {
/*     */       int i = (int)Math.max(Math.min(paramArrayOfbyte.length + (paramArrayOfbyte.length >> 1), 2147483639L), paramInt1);
/*     */       byte[] arrayOfByte = new byte[i];
/*     */       System.arraycopy(paramArrayOfbyte, 0, arrayOfByte, 0, paramInt2);
/*     */     } 
/*     */     return paramArrayOfbyte;
/*     */   }
/*     */   
/*     */   public static void c(byte[] paramArrayOfbyte1, byte[] paramArrayOfbyte2) {
/*     */     a(paramArrayOfbyte1, paramArrayOfbyte2);
/*     */     c(paramArrayOfbyte1, paramArrayOfbyte2, 0, paramArrayOfbyte1.length);
/*     */   }
/*     */   
/*     */   public static byte[] b(byte[] paramArrayOfbyte, int paramInt1, int paramInt2) {
/*     */     byte[] arrayOfByte = new byte[paramInt1];
/*     */     System.arraycopy(paramArrayOfbyte, 0, arrayOfByte, 0, paramInt2);
/*     */     return arrayOfByte;
/*     */   }
/*     */   
/*     */   public static void g(byte[] paramArrayOfbyte) {
/*     */     l(paramArrayOfbyte, 0, paramArrayOfbyte.length);
/*     */   }
/*     */   
/*     */   private static void a(byte[] paramArrayOfbyte1, byte[] paramArrayOfbyte2, int paramInt1, int paramInt2, int paramInt3) {
/*     */     byte b = 0;
/*     */     try {
/*     */       while (b < paramInt3) {
/*     */         a(paramArrayOfbyte1, paramArrayOfbyte2, paramInt1, paramInt2);
/*     */         b++;
/*     */         paramInt1++;
/*     */         paramInt2++;
/*     */       } 
/*     */     } catch (IllegalArgumentException illegalArgumentException) {
/*     */       throw a(null);
/*     */     } 
/*     */   }
/*     */   
/*     */   public static int a(byte[] paramArrayOfbyte, int paramInt1, int paramInt2, byte paramByte, g9 paramg9) {
/*     */     paramInt2--;
/*     */     for (; paramInt1 <= paramInt2; b = paramArrayOfbyte[i]) {
/*     */       byte b;
/*     */       int i = paramInt1 + paramInt2 >>> 1;
/*     */     } 
/*     */     return -(paramInt1 + 1);
/*     */   }
/*     */   
/*     */   public static void c(byte[] paramArrayOfbyte, int paramInt1, int paramInt2) {
/*     */     e(paramArrayOfbyte, paramInt1, paramInt2);
/*     */   }
/*     */   
/*     */   public static byte[] e(byte[] paramArrayOfbyte, int paramInt1, int paramInt2) {
/*     */     try {
/*     */     
/*     */     } catch (IllegalArgumentException illegalArgumentException) {
/*     */       throw a(null);
/*     */     } 
/*     */     return (paramInt1 > paramArrayOfbyte.length) ? b(paramArrayOfbyte, paramInt1, paramInt2) : paramArrayOfbyte;
/*     */   }
/*     */   
/*     */   public static void d(byte[] paramArrayOfbyte) {
/*     */     f(paramArrayOfbyte, 0, paramArrayOfbyte.length);
/*     */   }
/*     */   
/*     */   public static byte[] c(byte[] paramArrayOfbyte, int paramInt) {
/*     */     return c(paramArrayOfbyte, paramInt, paramArrayOfbyte.length);
/*     */   }
/*     */   
/*     */   public static void g(byte[] paramArrayOfbyte, int paramInt1, int paramInt2) {
/*     */     aL.b(paramArrayOfbyte.length, paramInt1, paramInt2);
/*     */   }
/*     */   
/*     */   public static void d(int[] paramArrayOfint, byte[] paramArrayOfbyte, int paramInt1, int paramInt2) {
/*     */     // Byte code:
/*     */     //   0: iload_3
/*     */     //   1: iload_2
/*     */     //   2: isub
/*     */     //   3: istore #4
/*     */     //   5: iload #4
/*     */     //   7: bipush #16
/*     */     //   9: if_icmpge -> 24
/*     */     //   12: aload_0
/*     */     //   13: aload_1
/*     */     //   14: iload_2
/*     */     //   15: iload_3
/*     */     //   16: invokestatic a : ([I[BII)V
/*     */     //   19: return
/*     */     //   20: invokestatic a : (Ljava/lang/Exception;)Ljava/lang/Exception;
/*     */     //   23: athrow
/*     */     //   24: iload_2
/*     */     //   25: iload #4
/*     */     //   27: iconst_2
/*     */     //   28: idiv
/*     */     //   29: iadd
/*     */     //   30: istore #5
/*     */     //   32: iload_2
/*     */     //   33: istore #6
/*     */     //   35: iload_3
/*     */     //   36: iconst_1
/*     */     //   37: isub
/*     */     //   38: istore #7
/*     */     //   40: iload #4
/*     */     //   42: sipush #128
/*     */     //   45: if_icmple -> 116
/*     */     //   48: iload #4
/*     */     //   50: bipush #8
/*     */     //   52: idiv
/*     */     //   53: istore #8
/*     */     //   55: aload_0
/*     */     //   56: aload_1
/*     */     //   57: iload #6
/*     */     //   59: iload #6
/*     */     //   61: iload #8
/*     */     //   63: iadd
/*     */     //   64: iload #6
/*     */     //   66: iconst_2
/*     */     //   67: iload #8
/*     */     //   69: imul
/*     */     //   70: iadd
/*     */     //   71: invokestatic a : ([I[BIII)I
/*     */     //   74: istore #6
/*     */     //   76: aload_0
/*     */     //   77: aload_1
/*     */     //   78: iload #5
/*     */     //   80: iload #8
/*     */     //   82: isub
/*     */     //   83: iload #5
/*     */     //   85: iload #5
/*     */     //   87: iload #8
/*     */     //   89: iadd
/*     */     //   90: invokestatic a : ([I[BIII)I
/*     */     //   93: istore #5
/*     */     //   95: aload_0
/*     */     //   96: aload_1
/*     */     //   97: iload #7
/*     */     //   99: iconst_2
/*     */     //   100: iload #8
/*     */     //   102: imul
/*     */     //   103: isub
/*     */     //   104: iload #7
/*     */     //   106: iload #8
/*     */     //   108: isub
/*     */     //   109: iload #7
/*     */     //   111: invokestatic a : ([I[BIII)I
/*     */     //   114: istore #7
/*     */     //   116: aload_0
/*     */     //   117: aload_1
/*     */     //   118: iload #6
/*     */     //   120: iload #5
/*     */     //   122: iload #7
/*     */     //   124: invokestatic a : ([I[BIII)I
/*     */     //   127: istore #5
/*     */     //   129: aload_1
/*     */     //   130: aload_0
/*     */     //   131: iload #5
/*     */     //   133: iaload
/*     */     //   134: baload
/*     */     //   135: istore #8
/*     */     //   137: iload_2
/*     */     //   138: istore #9
/*     */     //   140: iload #9
/*     */     //   142: istore #10
/*     */     //   144: iload_3
/*     */     //   145: iconst_1
/*     */     //   146: isub
/*     */     //   147: istore #11
/*     */     //   149: iload #11
/*     */     //   151: istore #12
/*     */     //   153: iload #10
/*     */     //   155: iload #11
/*     */     //   157: if_icmpgt -> 213
/*     */     //   160: aload_1
/*     */     //   161: aload_0
/*     */     //   162: iload #10
/*     */     //   164: iaload
/*     */     //   165: baload
/*     */     //   166: iload #8
/*     */     //   168: invokestatic compare : (BB)I
/*     */     //   171: dup
/*     */     //   172: istore #13
/*     */     //   174: ifgt -> 213
/*     */     //   177: iload #13
/*     */     //   179: ifne -> 207
/*     */     //   182: goto -> 189
/*     */     //   185: invokestatic a : (Ljava/lang/Exception;)Ljava/lang/Exception;
/*     */     //   188: athrow
/*     */     //   189: aload_0
/*     */     //   190: iload #9
/*     */     //   192: iinc #9, 1
/*     */     //   195: iload #10
/*     */     //   197: invokestatic g : ([III)V
/*     */     //   200: goto -> 207
/*     */     //   203: invokestatic a : (Ljava/lang/Exception;)Ljava/lang/Exception;
/*     */     //   206: athrow
/*     */     //   207: iinc #10, 1
/*     */     //   210: goto -> 153
/*     */     //   213: iload #11
/*     */     //   215: iload #10
/*     */     //   217: if_icmplt -> 273
/*     */     //   220: aload_1
/*     */     //   221: aload_0
/*     */     //   222: iload #11
/*     */     //   224: iaload
/*     */     //   225: baload
/*     */     //   226: iload #8
/*     */     //   228: invokestatic compare : (BB)I
/*     */     //   231: dup
/*     */     //   232: istore #13
/*     */     //   234: iflt -> 273
/*     */     //   237: iload #13
/*     */     //   239: ifne -> 267
/*     */     //   242: goto -> 249
/*     */     //   245: invokestatic a : (Ljava/lang/Exception;)Ljava/lang/Exception;
/*     */     //   248: athrow
/*     */     //   249: aload_0
/*     */     //   250: iload #11
/*     */     //   252: iload #12
/*     */     //   254: iinc #12, -1
/*     */     //   257: invokestatic g : ([III)V
/*     */     //   260: goto -> 267
/*     */     //   263: invokestatic a : (Ljava/lang/Exception;)Ljava/lang/Exception;
/*     */     //   266: athrow
/*     */     //   267: iinc #11, -1
/*     */     //   270: goto -> 213
/*     */     //   273: iload #10
/*     */     //   275: iload #11
/*     */     //   277: if_icmple -> 287
/*     */     //   280: goto -> 304
/*     */     //   283: invokestatic a : (Ljava/lang/Exception;)Ljava/lang/Exception;
/*     */     //   286: athrow
/*     */     //   287: aload_0
/*     */     //   288: iload #10
/*     */     //   290: iinc #10, 1
/*     */     //   293: iload #11
/*     */     //   295: iinc #11, -1
/*     */     //   298: invokestatic g : ([III)V
/*     */     //   301: goto -> 153
/*     */     //   304: iload #9
/*     */     //   306: iload_2
/*     */     //   307: isub
/*     */     //   308: iload #10
/*     */     //   310: iload #9
/*     */     //   312: isub
/*     */     //   313: invokestatic min : (II)I
/*     */     //   316: istore #13
/*     */     //   318: aload_0
/*     */     //   319: iload_2
/*     */     //   320: iload #10
/*     */     //   322: iload #13
/*     */     //   324: isub
/*     */     //   325: iload #13
/*     */     //   327: invokestatic b : ([IIII)V
/*     */     //   330: iload #12
/*     */     //   332: iload #11
/*     */     //   334: isub
/*     */     //   335: iload_3
/*     */     //   336: iload #12
/*     */     //   338: isub
/*     */     //   339: iconst_1
/*     */     //   340: isub
/*     */     //   341: invokestatic min : (II)I
/*     */     //   344: istore #13
/*     */     //   346: aload_0
/*     */     //   347: iload #10
/*     */     //   349: iload_3
/*     */     //   350: iload #13
/*     */     //   352: isub
/*     */     //   353: iload #13
/*     */     //   355: invokestatic b : ([IIII)V
/*     */     //   358: iload #10
/*     */     //   360: iload #9
/*     */     //   362: isub
/*     */     //   363: dup
/*     */     //   364: istore #13
/*     */     //   366: iconst_1
/*     */     //   367: if_icmple -> 387
/*     */     //   370: aload_0
/*     */     //   371: aload_1
/*     */     //   372: iload_2
/*     */     //   373: iload_2
/*     */     //   374: iload #13
/*     */     //   376: iadd
/*     */     //   377: invokestatic d : ([I[BII)V
/*     */     //   380: goto -> 387
/*     */     //   383: invokestatic a : (Ljava/lang/Exception;)Ljava/lang/Exception;
/*     */     //   386: athrow
/*     */     //   387: iload #12
/*     */     //   389: iload #11
/*     */     //   391: isub
/*     */     //   392: dup
/*     */     //   393: istore #13
/*     */     //   395: iconst_1
/*     */     //   396: if_icmple -> 416
/*     */     //   399: aload_0
/*     */     //   400: aload_1
/*     */     //   401: iload_3
/*     */     //   402: iload #13
/*     */     //   404: isub
/*     */     //   405: iload_3
/*     */     //   406: invokestatic d : ([I[BII)V
/*     */     //   409: goto -> 416
/*     */     //   412: invokestatic a : (Ljava/lang/Exception;)Ljava/lang/Exception;
/*     */     //   415: athrow
/*     */     //   416: return
/*     */     // Line number table:
/*     */     //   Java source line number -> byte code offset
/*     */     //   #802	-> 0
/*     */     //   #51	-> 5
/*     */     //   #546	-> 12
/*     */     //   #532	-> 19
/*     */     //   #448	-> 24
/*     */     //   #591	-> 32
/*     */     //   #659	-> 35
/*     */     //   #136	-> 40
/*     */     //   #111	-> 48
/*     */     //   #229	-> 55
/*     */     //   #22	-> 76
/*     */     //   #638	-> 95
/*     */     //   #407	-> 116
/*     */     //   #831	-> 129
/*     */     //   #535	-> 137
/*     */     //   #490	-> 153
/*     */     //   #247	-> 177
/*     */     //   #335	-> 207
/*     */     //   #31	-> 213
/*     */     //   #773	-> 237
/*     */     //   #556	-> 267
/*     */     //   #870	-> 273
/*     */     //   #616	-> 287
/*     */     //   #322	-> 304
/*     */     //   #771	-> 318
/*     */     //   #101	-> 330
/*     */     //   #651	-> 346
/*     */     //   #37	-> 358
/*     */     //   #231	-> 387
/*     */     //   #227	-> 416
/*     */     // Exception table:
/*     */     //   from	to	target	type
/*     */     //   5	20	20	java/lang/IllegalArgumentException
/*     */     //   174	182	185	java/lang/IllegalArgumentException
/*     */     //   177	200	203	java/lang/IllegalArgumentException
/*     */     //   234	242	245	java/lang/IllegalArgumentException
/*     */     //   237	260	263	java/lang/IllegalArgumentException
/*     */     //   273	283	283	java/lang/IllegalArgumentException
/*     */     //   366	380	383	java/lang/IllegalArgumentException
/*     */     //   395	409	412	java/lang/IllegalArgumentException
/*     */   }
/*     */   
/*     */   public static byte[] a(byte[] paramArrayOfbyte, Random paramRandom) {
/*     */     for (int i = paramArrayOfbyte.length; i-- != 0; ) {
/*     */       int j = paramRandom.nextInt(i + 1);
/*     */       byte b = paramArrayOfbyte[i];
/*     */       paramArrayOfbyte[i] = paramArrayOfbyte[j];
/*     */       paramArrayOfbyte[j] = b;
/*     */     } 
/*     */     return paramArrayOfbyte;
/*     */   }
/*     */   
/*     */   public static void a(byte[] paramArrayOfbyte1, int paramInt1, int paramInt2, g9 paramg9, byte[] paramArrayOfbyte2) {
/*     */     // Byte code:
/*     */     //   0: iload_2
/*     */     //   1: iload_1
/*     */     //   2: isub
/*     */     //   3: istore #5
/*     */     //   5: iload #5
/*     */     //   7: bipush #16
/*     */     //   9: if_icmpge -> 24
/*     */     //   12: aload_0
/*     */     //   13: iload_1
/*     */     //   14: iload_2
/*     */     //   15: aload_3
/*     */     //   16: invokestatic d : ([BIILme/konsolas/aac/g9;)V
/*     */     //   19: return
/*     */     //   20: invokestatic a : (Ljava/lang/Exception;)Ljava/lang/Exception;
/*     */     //   23: athrow
/*     */     //   24: aload #4
/*     */     //   26: ifnonnull -> 36
/*     */     //   29: aload_0
/*     */     //   30: iload_2
/*     */     //   31: invokestatic copyOf : ([BI)[B
/*     */     //   34: astore #4
/*     */     //   36: iload_1
/*     */     //   37: iload_2
/*     */     //   38: iadd
/*     */     //   39: iconst_1
/*     */     //   40: iushr
/*     */     //   41: istore #6
/*     */     //   43: aload #4
/*     */     //   45: iload_1
/*     */     //   46: iload #6
/*     */     //   48: aload_3
/*     */     //   49: aload_0
/*     */     //   50: invokestatic a : ([BIILme/konsolas/aac/g9;[B)V
/*     */     //   53: aload #4
/*     */     //   55: iload #6
/*     */     //   57: iload_2
/*     */     //   58: aload_3
/*     */     //   59: aload_0
/*     */     //   60: invokestatic a : ([BIILme/konsolas/aac/g9;[B)V
/*     */     //   63: aload_3
/*     */     //   64: aload #4
/*     */     //   66: iload #6
/*     */     //   68: iconst_1
/*     */     //   69: isub
/*     */     //   70: baload
/*     */     //   71: aload #4
/*     */     //   73: iload #6
/*     */     //   75: baload
/*     */     //   76: invokeinterface a : (BB)I
/*     */     //   81: ifgt -> 99
/*     */     //   84: aload #4
/*     */     //   86: iload_1
/*     */     //   87: aload_0
/*     */     //   88: iload_1
/*     */     //   89: iload #5
/*     */     //   91: invokestatic arraycopy : (Ljava/lang/Object;ILjava/lang/Object;II)V
/*     */     //   94: return
/*     */     //   95: invokestatic a : (Ljava/lang/Exception;)Ljava/lang/Exception;
/*     */     //   98: athrow
/*     */     //   99: iload_1
/*     */     //   100: istore #7
/*     */     //   102: iload_1
/*     */     //   103: istore #8
/*     */     //   105: iload #6
/*     */     //   107: istore #9
/*     */     //   109: iload #7
/*     */     //   111: iload_2
/*     */     //   112: if_icmpge -> 205
/*     */     //   115: iload #9
/*     */     //   117: iload_2
/*     */     //   118: if_icmpge -> 168
/*     */     //   121: goto -> 128
/*     */     //   124: invokestatic a : (Ljava/lang/Exception;)Ljava/lang/Exception;
/*     */     //   127: athrow
/*     */     //   128: iload #8
/*     */     //   130: iload #6
/*     */     //   132: if_icmpge -> 187
/*     */     //   135: goto -> 142
/*     */     //   138: invokestatic a : (Ljava/lang/Exception;)Ljava/lang/Exception;
/*     */     //   141: athrow
/*     */     //   142: aload_3
/*     */     //   143: aload #4
/*     */     //   145: iload #8
/*     */     //   147: baload
/*     */     //   148: aload #4
/*     */     //   150: iload #9
/*     */     //   152: baload
/*     */     //   153: invokeinterface a : (BB)I
/*     */     //   158: ifgt -> 187
/*     */     //   161: goto -> 168
/*     */     //   164: invokestatic a : (Ljava/lang/Exception;)Ljava/lang/Exception;
/*     */     //   167: athrow
/*     */     //   168: aload_0
/*     */     //   169: iload #7
/*     */     //   171: aload #4
/*     */     //   173: iload #8
/*     */     //   175: iinc #8, 1
/*     */     //   178: baload
/*     */     //   179: bastore
/*     */     //   180: goto -> 199
/*     */     //   183: invokestatic a : (Ljava/lang/Exception;)Ljava/lang/Exception;
/*     */     //   186: athrow
/*     */     //   187: aload_0
/*     */     //   188: iload #7
/*     */     //   190: aload #4
/*     */     //   192: iload #9
/*     */     //   194: iinc #9, 1
/*     */     //   197: baload
/*     */     //   198: bastore
/*     */     //   199: iinc #7, 1
/*     */     //   202: goto -> 109
/*     */     //   205: return
/*     */     // Line number table:
/*     */     //   Java source line number -> byte code offset
/*     */     //   #818	-> 0
/*     */     //   #423	-> 5
/*     */     //   #720	-> 12
/*     */     //   #878	-> 19
/*     */     //   #730	-> 24
/*     */     //   #125	-> 36
/*     */     //   #634	-> 43
/*     */     //   #608	-> 53
/*     */     //   #384	-> 63
/*     */     //   #69	-> 84
/*     */     //   #705	-> 94
/*     */     //   #595	-> 99
/*     */     //   #239	-> 115
/*     */     //   #724	-> 187
/*     */     //   #202	-> 199
/*     */     //   #174	-> 205
/*     */     // Exception table:
/*     */     //   from	to	target	type
/*     */     //   5	20	20	java/lang/IllegalArgumentException
/*     */     //   43	95	95	java/lang/IllegalArgumentException
/*     */     //   109	121	124	java/lang/IllegalArgumentException
/*     */     //   115	135	138	java/lang/IllegalArgumentException
/*     */     //   128	161	164	java/lang/IllegalArgumentException
/*     */     //   142	183	183	java/lang/IllegalArgumentException
/*     */   }
/*     */   
/*     */   public static void e(byte[] paramArrayOfbyte1, byte[] paramArrayOfbyte2) {
/*     */     a(paramArrayOfbyte1, paramArrayOfbyte2);
/*     */     f(paramArrayOfbyte1, paramArrayOfbyte2, 0, paramArrayOfbyte1.length);
/*     */   }
/*     */   
/*     */   @Deprecated
/*     */   public static void a(byte[] paramArrayOfbyte, byte paramByte) {
/*     */     int i = paramArrayOfbyte.length;
/*     */     try {
/*     */       for (; i-- != 0; paramArrayOfbyte[i] = paramByte);
/*     */     } catch (IllegalArgumentException illegalArgumentException) {
/*     */       throw a(null);
/*     */     } 
/*     */   }
/*     */   
/*     */   private static void j(byte[] paramArrayOfbyte, int paramInt1, int paramInt2) {
/*     */     for (int i = paramInt1; ++i < paramInt2; ) {
/*     */       byte b1 = paramArrayOfbyte[i];
/*     */       int j = i;
/*     */       byte b2 = paramArrayOfbyte[j - 1];
/*     */     } 
/*     */   }
/*     */   
/*     */   public static void a(byte[] paramArrayOfbyte, int paramInt1, int paramInt2, int paramInt3) {
/*     */     byte b = 0;
/*     */     try {
/*     */       while (b < paramInt3) {
/*     */         i(paramArrayOfbyte, paramInt1, paramInt2);
/*     */         b++;
/*     */         paramInt1++;
/*     */         paramInt2++;
/*     */       } 
/*     */     } catch (IllegalArgumentException illegalArgumentException) {
/*     */       throw a(null);
/*     */     } 
/*     */   }
/*     */   
/*     */   public static void a(byte[] paramArrayOfbyte) {
/*     */     c(paramArrayOfbyte, 0, paramArrayOfbyte.length);
/*     */   }
/*     */   
/*     */   public static byte[] d(byte[] paramArrayOfbyte, int paramInt) {
/*     */     try {
/*     */       if (paramInt >= paramArrayOfbyte.length)
/*     */         return paramArrayOfbyte; 
/*     */     } catch (IllegalArgumentException illegalArgumentException) {
/*     */       throw a(null);
/*     */     } 
/*     */     try {
/*     */     
/*     */     } catch (IllegalArgumentException illegalArgumentException) {
/*     */       throw a(null);
/*     */     } 
/*     */     byte[] arrayOfByte = (paramInt == 0) ? h : new byte[paramInt];
/*     */     System.arraycopy(paramArrayOfbyte, 0, arrayOfByte, 0, paramInt);
/*     */     return arrayOfByte;
/*     */   }
/*     */   
/*     */   private static int a(byte[] paramArrayOfbyte, int paramInt1, int paramInt2, int paramInt3) {
/*     */     int i = Byte.compare(paramArrayOfbyte[paramInt1], paramArrayOfbyte[paramInt2]);
/*     */     int j = Byte.compare(paramArrayOfbyte[paramInt1], paramArrayOfbyte[paramInt3]);
/*     */     int k = Byte.compare(paramArrayOfbyte[paramInt2], paramArrayOfbyte[paramInt3]);
/*     */     try {
/*     */       if (i < 0) {
/*     */         try {
/*     */           try {
/*     */           
/*     */           } catch (IllegalArgumentException illegalArgumentException) {
/*     */             throw a(null);
/*     */           } 
/*     */         } catch (IllegalArgumentException illegalArgumentException) {
/*     */           throw a(null);
/*     */         } 
/*     */       } else {
/*     */         try {
/*     */           try {
/*     */           
/*     */           } catch (IllegalArgumentException illegalArgumentException) {
/*     */             throw a(null);
/*     */           } 
/*     */         } catch (IllegalArgumentException illegalArgumentException) {
/*     */           throw a(null);
/*     */         } 
/*     */       } 
/*     */     } catch (IllegalArgumentException illegalArgumentException) {
/*     */       throw a(null);
/*     */     } 
/*     */     return (k > 0) ? paramInt2 : ((j > 0) ? paramInt3 : paramInt1);
/*     */   }
/*     */   
/*     */   private static void a(byte[][] paramArrayOfbyte, int paramInt1, int paramInt2, int paramInt3) {
/*     */     int i = paramArrayOfbyte.length;
/*     */     int j = paramInt3 / 1;
/*     */     for (int k = paramInt1; k < paramInt2 - 1; n = k + 1)
/*     */       int n, m = k; 
/*     */   }
/*     */   
/*     */   public static void b(int[] paramArrayOfint, byte[] paramArrayOfbyte, int paramInt1, int paramInt2, boolean paramBoolean) {
/*     */     try {
/*     */       if (paramInt2 - paramInt1 < 1024) {
/*     */         a(paramArrayOfint, paramArrayOfbyte, paramInt1, paramInt2);
/*     */         return;
/*     */       } 
/*     */     } catch (IllegalArgumentException illegalArgumentException) {
/*     */       throw a(null);
/*     */     } 
/*     */     boolean bool1 = false;
/*     */     boolean bool2 = true;
/*     */     byte b = 0;
/*     */     int[] arrayOfInt1 = new int[1];
/*     */     int[] arrayOfInt2 = new int[1];
/*     */     int[] arrayOfInt3 = new int[1];
/*     */     arrayOfInt1[b] = paramInt1;
/*     */     arrayOfInt2[b] = paramInt2 - paramInt1;
/*     */     arrayOfInt3[b++] = 0;
/*     */     int[] arrayOfInt4 = new int[256];
/*     */     int[] arrayOfInt5 = new int[256];
/*     */     try {
/*     */     
/*     */     } catch (IllegalArgumentException illegalArgumentException) {
/*     */       throw a(null);
/*     */     } 
/*     */     int[] arrayOfInt6 = paramBoolean ? new int[paramArrayOfint.length] : null;
/*     */     while (b > 0) {
/*     */       int i = arrayOfInt1[--b];
/*     */       int j = arrayOfInt2[b];
/*     */       int k = arrayOfInt3[b];
/*     */     } 
/*     */   }
/*     */   
/*     */   private static Exception a(Exception paramException) {
/*     */     return paramException;
/*     */   } }


/* Location:              C:\Users\BukkitBypass\Desktop\MatrixAC\AAC\AAC-spigot-5.2.0.jar!\me\konsolas\aac\dx.class
 * Java compiler version: 8 (52.0)
 * JD-Core Version:       1.1.3
 */