/*    */ package me.konsolas.aac;
/*    */ import java.lang.invoke.MethodHandles;
/*    */ import javax.crypto.Cipher;
/*    */ import javax.crypto.spec.DESKeySpec;
/*    */ 
/*    */ final class e2 {
/*    */   private static final String c;
/*    */   final String e;
/*    */   
/*    */   public String toString() {
/* 11 */     long l1 = f ^ 0x10338C20145CL, l2 = l1 ^ 0x67A7BD8E07BAL; return this.b + this.d.b(l2);
/*    */   }
/*    */   final String a; final String b; final gZ d; private static final long f = nc.a(-1650335074138169332L, -4740105927763428702L, MethodHandles.lookup().lookupClass()).a(124588003988716L); private static final String[] g; private static final String[] h;
/*    */   private static final Map i = new HashMap<>(13);
/*    */   
/*    */   public int hashCode() {
/* 17 */     null = 17; null = 31 * null + this.e.hashCode();
/* 18 */     null = 31 * null + this.b.hashCode();
/*    */ 
/*    */ 
/*    */ 
/*    */ 
/*    */ 
/*    */     
/* 25 */     return 
/* 26 */       31 * null + this.d.hashCode();
/*    */   }
/*    */   
/*    */   public boolean equals(Object paramObject) {
/*    */     // Byte code:
/*    */     //   0: getstatic me/konsolas/aac/e2.f : J
/*    */     //   3: ldc2_w 128396779501932
/*    */     //   6: lxor
/*    */     //   7: lstore_2
/*    */     //   8: ldc2_w 6391371902693169264
/*    */     //   11: lload_2
/*    */     //   12: <illegal opcode> w : (JJ)[Lme/konsolas/aac/aN;
/*    */     //   17: astore #4
/*    */     //   19: aload_1
/*    */     //   20: instanceof me/konsolas/aac/e2
/*    */     //   23: aload #4
/*    */     //   25: ifnonnull -> 71
/*    */     //   28: ifeq -> 192
/*    */     //   31: goto -> 44
/*    */     //   34: ldc2_w 6433575048799394859
/*    */     //   37: lload_2
/*    */     //   38: <illegal opcode> w : (Ljava/lang/IllegalArgumentException;JJ)Ljava/lang/IllegalArgumentException;
/*    */     //   43: athrow
/*    */     //   44: aload_0
/*    */     //   45: getfield e : Ljava/lang/String;
/*    */     //   48: aload_1
/*    */     //   49: checkcast me/konsolas/aac/e2
/*    */     //   52: getfield e : Ljava/lang/String;
/*    */     //   55: invokevirtual equals : (Ljava/lang/Object;)Z
/*    */     //   58: goto -> 71
/*    */     //   61: ldc2_w 6433575048799394859
/*    */     //   64: lload_2
/*    */     //   65: <illegal opcode> w : (Ljava/lang/IllegalArgumentException;JJ)Ljava/lang/IllegalArgumentException;
/*    */     //   70: athrow
/*    */     //   71: aload #4
/*    */     //   73: ifnonnull -> 119
/*    */     //   76: ifeq -> 192
/*    */     //   79: goto -> 92
/*    */     //   82: ldc2_w 6433575048799394859
/*    */     //   85: lload_2
/*    */     //   86: <illegal opcode> w : (Ljava/lang/IllegalArgumentException;JJ)Ljava/lang/IllegalArgumentException;
/*    */     //   91: athrow
/*    */     //   92: aload_0
/*    */     //   93: getfield b : Ljava/lang/String;
/*    */     //   96: aload_1
/*    */     //   97: checkcast me/konsolas/aac/e2
/*    */     //   100: getfield b : Ljava/lang/String;
/*    */     //   103: invokevirtual equals : (Ljava/lang/Object;)Z
/*    */     //   106: goto -> 119
/*    */     //   109: ldc2_w 6433575048799394859
/*    */     //   112: lload_2
/*    */     //   113: <illegal opcode> w : (Ljava/lang/IllegalArgumentException;JJ)Ljava/lang/IllegalArgumentException;
/*    */     //   118: athrow
/*    */     //   119: aload #4
/*    */     //   121: ifnonnull -> 167
/*    */     //   124: ifeq -> 192
/*    */     //   127: goto -> 140
/*    */     //   130: ldc2_w 6433575048799394859
/*    */     //   133: lload_2
/*    */     //   134: <illegal opcode> w : (Ljava/lang/IllegalArgumentException;JJ)Ljava/lang/IllegalArgumentException;
/*    */     //   139: athrow
/*    */     //   140: aload_0
/*    */     //   141: getfield d : Lme/konsolas/aac/gZ;
/*    */     //   144: aload_1
/*    */     //   145: checkcast me/konsolas/aac/e2
/*    */     //   148: getfield d : Lme/konsolas/aac/gZ;
/*    */     //   151: invokevirtual equals : (Ljava/lang/Object;)Z
/*    */     //   154: goto -> 167
/*    */     //   157: ldc2_w 6433575048799394859
/*    */     //   160: lload_2
/*    */     //   161: <illegal opcode> w : (Ljava/lang/IllegalArgumentException;JJ)Ljava/lang/IllegalArgumentException;
/*    */     //   166: athrow
/*    */     //   167: aload #4
/*    */     //   169: ifnonnull -> 189
/*    */     //   172: ifeq -> 192
/*    */     //   175: goto -> 188
/*    */     //   178: ldc2_w 6433575048799394859
/*    */     //   181: lload_2
/*    */     //   182: <illegal opcode> w : (Ljava/lang/IllegalArgumentException;JJ)Ljava/lang/IllegalArgumentException;
/*    */     //   187: athrow
/*    */     //   188: iconst_1
/*    */     //   189: goto -> 193
/*    */     //   192: iconst_0
/*    */     //   193: ireturn
/*    */     // Line number table:
/*    */     //   Java source line number -> byte code offset
/*    */     //   #28	-> 19
/*    */     //   #29	-> 55
/*    */     //   #9	-> 103
/*    */     //   #5	-> 151
/*    */     //   #31	-> 193
/*    */     // Exception table:
/*    */     //   from	to	target	type
/*    */     //   19	31	34	java/lang/IllegalArgumentException
/*    */     //   28	58	61	java/lang/IllegalArgumentException
/*    */     //   71	79	82	java/lang/IllegalArgumentException
/*    */     //   76	106	109	java/lang/IllegalArgumentException
/*    */     //   119	127	130	java/lang/IllegalArgumentException
/*    */     //   124	154	157	java/lang/IllegalArgumentException
/*    */     //   167	175	178	java/lang/IllegalArgumentException
/*    */   }
/*    */   
/*    */   e2(String paramString1, long paramLong, String paramString2) {
/*    */     // Byte code:
/*    */     //   0: getstatic me/konsolas/aac/e2.f : J
/*    */     //   3: lload_2
/*    */     //   4: lxor
/*    */     //   5: lstore_2
/*    */     //   6: lload_2
/*    */     //   7: dup2
/*    */     //   8: ldc2_w 100477615722266
/*    */     //   11: lxor
/*    */     //   12: lstore #5
/*    */     //   14: dup2
/*    */     //   15: ldc2_w 104166954140717
/*    */     //   18: lxor
/*    */     //   19: dup2
/*    */     //   20: bipush #16
/*    */     //   22: lushr
/*    */     //   23: lstore #7
/*    */     //   25: dup2
/*    */     //   26: bipush #48
/*    */     //   28: lshl
/*    */     //   29: bipush #48
/*    */     //   31: lushr
/*    */     //   32: l2i
/*    */     //   33: istore #9
/*    */     //   35: pop2
/*    */     //   36: pop2
/*    */     //   37: ldc2_w 932411070528752690
/*    */     //   40: lload_2
/*    */     //   41: <illegal opcode> w : (JJ)[Lme/konsolas/aac/aN;
/*    */     //   46: aload_0
/*    */     //   47: invokespecial <init> : ()V
/*    */     //   50: astore #10
/*    */     //   52: aload_0
/*    */     //   53: aload_1
/*    */     //   54: putfield e : Ljava/lang/String;
/*    */     //   57: aload_0
/*    */     //   58: aload_1
/*    */     //   59: aload #10
/*    */     //   61: ifnonnull -> 196
/*    */     //   64: sipush #15670
/*    */     //   67: ldc2_w 3941337254685840034
/*    */     //   70: lload_2
/*    */     //   71: lxor
/*    */     //   72: <illegal opcode> t : (IJ)Ljava/lang/String;
/*    */     //   77: invokevirtual startsWith : (Ljava/lang/String;)Z
/*    */     //   80: ifeq -> 166
/*    */     //   83: goto -> 96
/*    */     //   86: ldc2_w 939711252546144361
/*    */     //   89: lload_2
/*    */     //   90: <illegal opcode> w : (Ljava/lang/IllegalArgumentException;JJ)Ljava/lang/IllegalArgumentException;
/*    */     //   95: athrow
/*    */     //   96: new java/lang/StringBuilder
/*    */     //   99: dup
/*    */     //   100: invokespecial <init> : ()V
/*    */     //   103: sipush #28429
/*    */     //   106: ldc2_w 3617206836855390362
/*    */     //   109: lload_2
/*    */     //   110: lxor
/*    */     //   111: <illegal opcode> t : (IJ)Ljava/lang/String;
/*    */     //   116: invokevirtual append : (Ljava/lang/String;)Ljava/lang/StringBuilder;
/*    */     //   119: aload_1
/*    */     //   120: sipush #6606
/*    */     //   123: ldc2_w 4767789019428009560
/*    */     //   126: lload_2
/*    */     //   127: lxor
/*    */     //   128: <illegal opcode> t : (IJ)Ljava/lang/String;
/*    */     //   133: invokevirtual length : ()I
/*    */     //   136: invokevirtual substring : (I)Ljava/lang/String;
/*    */     //   139: invokevirtual append : (Ljava/lang/String;)Ljava/lang/StringBuilder;
/*    */     //   142: invokevirtual toString : ()Ljava/lang/String;
/*    */     //   145: lload #5
/*    */     //   147: invokestatic c : (Ljava/lang/String;J)Lme/konsolas/aac/l6;
/*    */     //   150: invokevirtual d : ()Ljava/lang/String;
/*    */     //   153: goto -> 204
/*    */     //   156: ldc2_w 939711252546144361
/*    */     //   159: lload_2
/*    */     //   160: <illegal opcode> w : (Ljava/lang/IllegalArgumentException;JJ)Ljava/lang/IllegalArgumentException;
/*    */     //   165: athrow
/*    */     //   166: new java/lang/StringBuilder
/*    */     //   169: dup
/*    */     //   170: invokespecial <init> : ()V
/*    */     //   173: sipush #2669
/*    */     //   176: ldc2_w 2016291480452113904
/*    */     //   179: lload_2
/*    */     //   180: lxor
/*    */     //   181: <illegal opcode> t : (IJ)Ljava/lang/String;
/*    */     //   186: invokevirtual append : (Ljava/lang/String;)Ljava/lang/StringBuilder;
/*    */     //   189: aload_1
/*    */     //   190: invokevirtual append : (Ljava/lang/String;)Ljava/lang/StringBuilder;
/*    */     //   193: invokevirtual toString : ()Ljava/lang/String;
/*    */     //   196: lload #5
/*    */     //   198: invokestatic c : (Ljava/lang/String;J)Lme/konsolas/aac/l6;
/*    */     //   201: invokevirtual d : ()Ljava/lang/String;
/*    */     //   204: putfield a : Ljava/lang/String;
/*    */     //   207: aload #4
/*    */     //   209: sipush #13296
/*    */     //   212: ldc2_w 7950150567584799855
/*    */     //   215: lload_2
/*    */     //   216: lxor
/*    */     //   217: <illegal opcode> t : (IJ)Ljava/lang/String;
/*    */     //   222: invokevirtual startsWith : (Ljava/lang/String;)Z
/*    */     //   225: lload_2
/*    */     //   226: lconst_0
/*    */     //   227: lcmp
/*    */     //   228: iflt -> 357
/*    */     //   231: aload #10
/*    */     //   233: ifnonnull -> 357
/*    */     //   236: ifeq -> 326
/*    */     //   239: goto -> 252
/*    */     //   242: ldc2_w 939711252546144361
/*    */     //   245: lload_2
/*    */     //   246: <illegal opcode> w : (Ljava/lang/IllegalArgumentException;JJ)Ljava/lang/IllegalArgumentException;
/*    */     //   251: athrow
/*    */     //   252: aload_0
/*    */     //   253: sipush #12570
/*    */     //   256: ldc2_w 7196769035935784582
/*    */     //   259: lload_2
/*    */     //   260: lxor
/*    */     //   261: <illegal opcode> t : (IJ)Ljava/lang/String;
/*    */     //   266: putfield b : Ljava/lang/String;
/*    */     //   269: aload_0
/*    */     //   270: aload #4
/*    */     //   272: sipush #12570
/*    */     //   275: ldc2_w 7196769035935784582
/*    */     //   278: lload_2
/*    */     //   279: lxor
/*    */     //   280: <illegal opcode> t : (IJ)Ljava/lang/String;
/*    */     //   285: invokevirtual length : ()I
/*    */     //   288: invokevirtual substring : (I)Ljava/lang/String;
/*    */     //   291: lload #7
/*    */     //   293: iload #9
/*    */     //   295: i2s
/*    */     //   296: invokestatic b : (Ljava/lang/String;JS)Lme/konsolas/aac/gZ;
/*    */     //   299: putfield d : Lme/konsolas/aac/gZ;
/*    */     //   302: lload_2
/*    */     //   303: lconst_0
/*    */     //   304: lcmp
/*    */     //   305: ifle -> 483
/*    */     //   308: aload #10
/*    */     //   310: ifnull -> 483
/*    */     //   313: goto -> 326
/*    */     //   316: ldc2_w 939711252546144361
/*    */     //   319: lload_2
/*    */     //   320: <illegal opcode> w : (Ljava/lang/IllegalArgumentException;JJ)Ljava/lang/IllegalArgumentException;
/*    */     //   325: athrow
/*    */     //   326: aload #4
/*    */     //   328: sipush #15361
/*    */     //   331: ldc2_w 1222570309527442321
/*    */     //   334: lload_2
/*    */     //   335: lxor
/*    */     //   336: <illegal opcode> t : (IJ)Ljava/lang/String;
/*    */     //   341: invokevirtual startsWith : (Ljava/lang/String;)Z
/*    */     //   344: goto -> 357
/*    */     //   347: ldc2_w 939711252546144361
/*    */     //   350: lload_2
/*    */     //   351: <illegal opcode> w : (Ljava/lang/IllegalArgumentException;JJ)Ljava/lang/IllegalArgumentException;
/*    */     //   356: athrow
/*    */     //   357: ifeq -> 434
/*    */     //   360: aload_0
/*    */     //   361: sipush #19488
/*    */     //   364: ldc2_w 294508802975294389
/*    */     //   367: lload_2
/*    */     //   368: lxor
/*    */     //   369: <illegal opcode> t : (IJ)Ljava/lang/String;
/*    */     //   374: putfield b : Ljava/lang/String;
/*    */     //   377: aload_0
/*    */     //   378: aload #4
/*    */     //   380: sipush #19488
/*    */     //   383: ldc2_w 294508802975294389
/*    */     //   386: lload_2
/*    */     //   387: lxor
/*    */     //   388: <illegal opcode> t : (IJ)Ljava/lang/String;
/*    */     //   393: invokevirtual length : ()I
/*    */     //   396: invokevirtual substring : (I)Ljava/lang/String;
/*    */     //   399: lload #7
/*    */     //   401: iload #9
/*    */     //   403: i2s
/*    */     //   404: invokestatic b : (Ljava/lang/String;JS)Lme/konsolas/aac/gZ;
/*    */     //   407: putfield d : Lme/konsolas/aac/gZ;
/*    */     //   410: lload_2
/*    */     //   411: lconst_0
/*    */     //   412: lcmp
/*    */     //   413: ifle -> 483
/*    */     //   416: aload #10
/*    */     //   418: ifnull -> 483
/*    */     //   421: goto -> 434
/*    */     //   424: ldc2_w 939711252546144361
/*    */     //   427: lload_2
/*    */     //   428: <illegal opcode> w : (Ljava/lang/IllegalArgumentException;JJ)Ljava/lang/IllegalArgumentException;
/*    */     //   433: athrow
/*    */     //   434: new java/lang/IllegalArgumentException
/*    */     //   437: dup
/*    */     //   438: new java/lang/StringBuilder
/*    */     //   441: dup
/*    */     //   442: invokespecial <init> : ()V
/*    */     //   445: sipush #18034
/*    */     //   448: ldc2_w 6546295021631236576
/*    */     //   451: lload_2
/*    */     //   452: lxor
/*    */     //   453: <illegal opcode> t : (IJ)Ljava/lang/String;
/*    */     //   458: invokevirtual append : (Ljava/lang/String;)Ljava/lang/StringBuilder;
/*    */     //   461: aload #4
/*    */     //   463: invokevirtual append : (Ljava/lang/String;)Ljava/lang/StringBuilder;
/*    */     //   466: invokevirtual toString : ()Ljava/lang/String;
/*    */     //   469: invokespecial <init> : (Ljava/lang/String;)V
/*    */     //   472: athrow
/*    */     //   473: ldc2_w 939711252546144361
/*    */     //   476: lload_2
/*    */     //   477: <illegal opcode> w : (Ljava/lang/IllegalArgumentException;JJ)Ljava/lang/IllegalArgumentException;
/*    */     //   482: athrow
/*    */     //   483: aload_0
/*    */     //   484: getfield d : Lme/konsolas/aac/gZ;
/*    */     //   487: ifnonnull -> 539
/*    */     //   490: new java/lang/IllegalArgumentException
/*    */     //   493: dup
/*    */     //   494: new java/lang/StringBuilder
/*    */     //   497: dup
/*    */     //   498: invokespecial <init> : ()V
/*    */     //   501: sipush #7650
/*    */     //   504: ldc2_w 3857222641318670963
/*    */     //   507: lload_2
/*    */     //   508: lxor
/*    */     //   509: <illegal opcode> t : (IJ)Ljava/lang/String;
/*    */     //   514: invokevirtual append : (Ljava/lang/String;)Ljava/lang/StringBuilder;
/*    */     //   517: aload #4
/*    */     //   519: invokevirtual append : (Ljava/lang/String;)Ljava/lang/StringBuilder;
/*    */     //   522: invokevirtual toString : ()Ljava/lang/String;
/*    */     //   525: invokespecial <init> : (Ljava/lang/String;)V
/*    */     //   528: athrow
/*    */     //   529: ldc2_w 939711252546144361
/*    */     //   532: lload_2
/*    */     //   533: <illegal opcode> w : (Ljava/lang/IllegalArgumentException;JJ)Ljava/lang/IllegalArgumentException;
/*    */     //   538: athrow
/*    */     //   539: return
/*    */     // Line number table:
/*    */     //   Java source line number -> byte code offset
/*    */     //   #30	-> 46
/*    */     //   #27	-> 52
/*    */     //   #16	-> 57
/*    */     //   #6	-> 96
/*    */     //   #15	-> 166
/*    */     //   #20	-> 207
/*    */     //   #14	-> 252
/*    */     //   #13	-> 269
/*    */     //   #8	-> 326
/*    */     //   #32	-> 360
/*    */     //   #10	-> 377
/*    */     //   #4	-> 434
/*    */     //   #23	-> 483
/*    */     //   #24	-> 490
/*    */     //   #21	-> 539
/*    */     // Exception table:
/*    */     //   from	to	target	type
/*    */     //   52	83	86	java/lang/IllegalArgumentException
/*    */     //   64	156	156	java/lang/IllegalArgumentException
/*    */     //   204	239	242	java/lang/IllegalArgumentException
/*    */     //   236	313	316	java/lang/IllegalArgumentException
/*    */     //   252	344	347	java/lang/IllegalArgumentException
/*    */     //   357	421	424	java/lang/IllegalArgumentException
/*    */     //   360	473	473	java/lang/IllegalArgumentException
/*    */     //   483	529	529	java/lang/IllegalArgumentException
/*    */   }
/*    */   
/*    */   boolean a(String paramString, long paramLong) {
/*    */     // Byte code:
/*    */     //   0: getstatic me/konsolas/aac/e2.f : J
/*    */     //   3: lload_2
/*    */     //   4: lxor
/*    */     //   5: lstore_2
/*    */     //   6: ldc2_w -2569029725277332326
/*    */     //   9: lload_2
/*    */     //   10: <illegal opcode> w : (JJ)[Lme/konsolas/aac/aN;
/*    */     //   15: astore #4
/*    */     //   17: aload_0
/*    */     //   18: getfield e : Ljava/lang/String;
/*    */     //   21: sipush #6606
/*    */     //   24: ldc2_w 4767897092832978672
/*    */     //   27: lload_2
/*    */     //   28: lxor
/*    */     //   29: <illegal opcode> t : (IJ)Ljava/lang/String;
/*    */     //   34: invokevirtual startsWith : (Ljava/lang/String;)Z
/*    */     //   37: aload #4
/*    */     //   39: ifnonnull -> 178
/*    */     //   42: ifeq -> 170
/*    */     //   45: goto -> 58
/*    */     //   48: ldc2_w -2476160001566205759
/*    */     //   51: lload_2
/*    */     //   52: <illegal opcode> w : (Ljava/lang/IllegalArgumentException;JJ)Ljava/lang/IllegalArgumentException;
/*    */     //   57: athrow
/*    */     //   58: aload_1
/*    */     //   59: bipush #46
/*    */     //   61: invokevirtual indexOf : (I)I
/*    */     //   64: istore #5
/*    */     //   66: aload_1
/*    */     //   67: invokevirtual length : ()I
/*    */     //   70: iload #5
/*    */     //   72: isub
/*    */     //   73: iconst_1
/*    */     //   74: isub
/*    */     //   75: aload #4
/*    */     //   77: lload_2
/*    */     //   78: lconst_0
/*    */     //   79: lcmp
/*    */     //   80: iflt -> 145
/*    */     //   83: ifnonnull -> 143
/*    */     //   86: aload_0
/*    */     //   87: getfield a : Ljava/lang/String;
/*    */     //   90: invokevirtual length : ()I
/*    */     //   93: if_icmpne -> 168
/*    */     //   96: goto -> 109
/*    */     //   99: ldc2_w -2476160001566205759
/*    */     //   102: lload_2
/*    */     //   103: <illegal opcode> w : (Ljava/lang/IllegalArgumentException;JJ)Ljava/lang/IllegalArgumentException;
/*    */     //   108: athrow
/*    */     //   109: aload_1
/*    */     //   110: iconst_0
/*    */     //   111: iload #5
/*    */     //   113: iconst_1
/*    */     //   114: iadd
/*    */     //   115: aload_0
/*    */     //   116: getfield a : Ljava/lang/String;
/*    */     //   119: iconst_0
/*    */     //   120: aload_0
/*    */     //   121: getfield a : Ljava/lang/String;
/*    */     //   124: invokevirtual length : ()I
/*    */     //   127: invokevirtual regionMatches : (ZILjava/lang/String;II)Z
/*    */     //   130: goto -> 143
/*    */     //   133: ldc2_w -2476160001566205759
/*    */     //   136: lload_2
/*    */     //   137: <illegal opcode> w : (Ljava/lang/IllegalArgumentException;JJ)Ljava/lang/IllegalArgumentException;
/*    */     //   142: athrow
/*    */     //   143: aload #4
/*    */     //   145: ifnonnull -> 165
/*    */     //   148: ifeq -> 168
/*    */     //   151: goto -> 164
/*    */     //   154: ldc2_w -2476160001566205759
/*    */     //   157: lload_2
/*    */     //   158: <illegal opcode> w : (Ljava/lang/IllegalArgumentException;JJ)Ljava/lang/IllegalArgumentException;
/*    */     //   163: athrow
/*    */     //   164: iconst_1
/*    */     //   165: goto -> 169
/*    */     //   168: iconst_0
/*    */     //   169: ireturn
/*    */     //   170: aload_1
/*    */     //   171: aload_0
/*    */     //   172: getfield a : Ljava/lang/String;
/*    */     //   175: invokevirtual equals : (Ljava/lang/Object;)Z
/*    */     //   178: ireturn
/*    */     // Line number table:
/*    */     //   Java source line number -> byte code offset
/*    */     //   #33	-> 17
/*    */     //   #22	-> 58
/*    */     //   #7	-> 66
/*    */     //   #12	-> 124
/*    */     //   #3	-> 127
/*    */     //   #2	-> 169
/*    */     //   #19	-> 170
/*    */     // Exception table:
/*    */     //   from	to	target	type
/*    */     //   17	45	48	java/lang/IllegalArgumentException
/*    */     //   66	96	99	java/lang/IllegalArgumentException
/*    */     //   86	130	133	java/lang/IllegalArgumentException
/*    */     //   143	151	154	java/lang/IllegalArgumentException
/*    */   }
/*    */   
/*    */   static {
/*    */     long l = f ^ 0x9288B79F504L;
/*    */     "撕⩩清쿴⻺퍹ꖲ왇勺⿴뺘↝ࠕ笨휔ⱆ?ຂ㖨".toCharArray()[17] = (char)("撕⩩清쿴⻺퍹ꖲ왇勺⿴뺘↝ࠕ笨휔ⱆ?ຂ㖨".toCharArray()[17] ^ 0x5F71);
/*    */     "喅ⴲ푼䶲".toCharArray()[0] = (char)("喅ⴲ푼䶲".toCharArray()[0] ^ 0x2F53);
/*    */     (new byte[8])[0] = (byte)(int)(l >>> 56L);
/*    */     for (byte b1 = 1; b1 < 8; b1++)
/*    */       (new byte[8])[b1] = (byte)(int)(l << b1 * 8 >>> 56L); 
/*    */     Cipher cipher;
/*    */     (cipher = Cipher.getInstance(hY$g6.H("撕⩩清쿴⻺퍹ꖲ왇勺⿴뺘↝ࠕ笨휔ⱆ?ຂ㖨".toCharArray(), (short)29249, (byte)4, (byte)5))).init(2, SecretKeyFactory.getInstance(hY$g6.H("喅ⴲ푼䶲".toCharArray(), (short)12774, (byte)3, (byte)5)).generateSecret(new DESKeySpec(new byte[8])), new IvParameterSpec(new byte[8]));
/*    */     String[] arrayOfString = new String[11];
/*    */     boolean bool = false;
/*    */     "辱妒ṷ?ቓ藼댦ڇ婺枌葼야⯯䐍Ꮳ䒄縲͋轙宴捳㜄毺陆佔寬년钒ꈠ⇂景⮧얆셏䐨칗笁䑬샨袱།꼄쬌䪩ࣻᘗ呧봖ꄛీ汒䛒ꆋ踲㰀웝ၝ㯐蚀囪㾞룶絽㽴觱⠯戴嚡쁖㊍匙非숍吐凢㊦墎节㬊ⓖ鶓鹾ᮛ픭첑혬碆㬾씠ေ﶐ᑥ濃?헻씒?鞪吪뉞꾱簛虚⿓籌ﰅテﺱ᝛挽?乼寪낻蘃ﳮﾙ锖䐾뀝ᘐ镈₦?㛩ᔃ놴헪䢲ﺃ洶ᢼ퇹瞝䥈㲊햒럠ઑ▾⋁凹콞刕歹覄忀峹눙뮂횣ₙ嗭䁦퀖䨣嵏ち举㼷站┕팓鯿涭먅ⵥ玾⧷㎁?홳ಈ࣋ꖃ饙﨏᪔괄ﮯⲚﾕᔟ?덱隀㉈狽簉䉈Ώ복㱁잟꓃揺蛐텍껝?凜⼤".toCharArray()[201] = (char)("辱妒ṷ?ቓ藼댦ڇ婺枌葼야⯯䐍Ꮳ䒄縲͋轙宴捳㜄毺陆佔寬년钒ꈠ⇂景⮧얆셏䐨칗笁䑬샨袱།꼄쬌䪩ࣻᘗ呧봖ꄛీ汒䛒ꆋ踲㰀웝ၝ㯐蚀囪㾞룶絽㽴觱⠯戴嚡쁖㊍匙非숍吐凢㊦墎节㬊ⓖ鶓鹾ᮛ픭첑혬碆㬾씠ေ﶐ᑥ濃?헻씒?鞪吪뉞꾱簛虚⿓籌ﰅテﺱ᝛挽?乼寪낻蘃ﳮﾙ锖䐾뀝ᘐ镈₦?㛩ᔃ놴헪䢲ﺃ洶ᢼ퇹瞝䥈㲊햒럠ઑ▾⋁凹콞刕歹覄忀峹눙뮂횣ₙ嗭䁦퀖䨣嵏ち举㼷站┕팓鯿涭먅ⵥ玾⧷㎁?홳ಈ࣋ꖃ饙﨏᪔괄ﮯⲚﾕᔟ?덱隀㉈狽簉䉈Ώ복㱁잟꓃揺蛐텍껝?凜⼤".toCharArray()[201] ^ 0x4F0F);
/*    */     String str;
/*    */     int i = (str = hY$g6.H("辱妒ṷ?ቓ藼댦ڇ婺枌葼야⯯䐍Ꮳ䒄縲͋轙宴捳㜄毺陆佔寬년钒ꈠ⇂景⮧얆셏䐨칗笁䑬샨袱།꼄쬌䪩ࣻᘗ呧봖ꄛీ汒䛒ꆋ踲㰀웝ၝ㯐蚀囪㾞룶絽㽴觱⠯戴嚡쁖㊍匙非숍吐凢㊦墎节㬊ⓖ鶓鹾ᮛ픭첑혬碆㬾씠ေ﶐ᑥ濃?헻씒?鞪吪뉞꾱簛虚⿓籌ﰅテﺱ᝛挽?乼寪낻蘃ﳮﾙ锖䐾뀝ᘐ镈₦?㛩ᔃ놴헪䢲ﺃ洶ᢼ퇹瞝䥈㲊햒럠ઑ▾⋁凹콞刕歹覄忀峹눙뮂횣ₙ嗭䁦퀖䨣嵏ち举㼷站┕팓鯿涭먅ⵥ玾⧷㎁?홳ಈ࣋ꖃ饙﨏᪔괄ﮯⲚﾕᔟ?덱隀㉈狽簉䉈Ώ복㱁잟꓃揺蛐텍껝?凜⼤".toCharArray(), (short)23997, (byte)5, (byte)0)).length();
/*    */     byte b2 = 16;
/*    */     byte b = -1;
/*    */     while (true);
/*    */   }
/*    */   
/*    */   private static IllegalArgumentException a(IllegalArgumentException paramIllegalArgumentException) {
/*    */     return paramIllegalArgumentException;
/*    */   }
/*    */   
/*    */   private static String a(byte[] paramArrayOfbyte) {
/*    */     byte b1 = 0;
/*    */     int i;
/*    */     char[] arrayOfChar = new char[i = paramArrayOfbyte.length];
/*    */     for (byte b2 = 0; b2 < i; b2++) {
/*    */       int j;
/*    */       if ((j = 0xFF & paramArrayOfbyte[b2]) < 192) {
/*    */         arrayOfChar[b1++] = (char)j;
/*    */       } else if (j < 224) {
/*    */         char c = (char)((char)(j & 0x1F) << 6);
/*    */         j = paramArrayOfbyte[++b2];
/*    */         c = (char)(c | (char)(j & 0x3F));
/*    */         arrayOfChar[b1++] = c;
/*    */       } else if (b2 < i - 2) {
/*    */         char c = (char)((char)(j & 0xF) << 12);
/*    */         j = paramArrayOfbyte[++b2];
/*    */         c = (char)(c | (char)(j & 0x3F) << 6);
/*    */         j = paramArrayOfbyte[++b2];
/*    */         c = (char)(c | (char)(j & 0x3F));
/*    */         arrayOfChar[b1++] = c;
/*    */       } 
/*    */     } 
/*    */     return new String(arrayOfChar, 0, b1);
/*    */   }
/*    */   
/*    */   private static String a(int paramInt, long paramLong) {
/*    */     int i = paramInt ^ (int)(paramLong & 0x7FFFL) ^ 0x2381;
/*    */     if (h[i] == null) {
/*    */       Object[] arrayOfObject;
/*    */       try {
/*    */         Long long_ = Long.valueOf(Thread.currentThread().getId());
/*    */         arrayOfObject = (Object[])i.get(long_);
/*    */         if (arrayOfObject == null) {
/*    */           arrayOfObject = new Object[3];
/*    */           "䕠㛟䳋䭬⡐྅ᳺ류ꗅᱥ㌑숦鉾Ꮽ錏仹䱦จ".toCharArray()[5] = (char)("䕠㛟䳋䭬⡐྅ᳺ류ꗅᱥ㌑숦鉾Ꮽ錏仹䱦จ".toCharArray()[5] ^ 0xFC9);
/*    */           arrayOfObject[0] = Cipher.getInstance(fW$gy.A("䕠㛟䳋䭬⡐྅ᳺ류ꗅᱥ㌑숦鉾Ꮽ錏仹䱦จ".toCharArray(), (short)6942, true, 5));
/*    */           "큩㭱䈬ᒮ".toCharArray()[1] = (char)("큩㭱䈬ᒮ".toCharArray()[1] ^ 0x77E);
/*    */           arrayOfObject[1] = SecretKeyFactory.getInstance(fW$gy.A("큩㭱䈬ᒮ".toCharArray(), (short)29704, true, 3));
/*    */           arrayOfObject[2] = new IvParameterSpec(new byte[8]);
/*    */           i.put(long_, arrayOfObject);
/*    */         } 
/*    */       } catch (Exception exception) {
/*    */         "ᩘ곍뿆ࢽ䓊㬸ཱྀ곘?力滣ᦢ⇺瘑闭䲻쏬Ò".toCharArray()[14] = (char)("ᩘ곍뿆ࢽ䓊㬸ཱྀ곘?力滣ᦢ⇺瘑闭䲻쏬Ò".toCharArray()[14] ^ 0x318A);
/*    */         throw new RuntimeException(fW$gy.A("ᩘ곍뿆ࢽ䓊㬸ཱྀ곘?力滣ᦢ⇺瘑闭䲻쏬Ò".toCharArray(), (short)12891, true, 0), exception);
/*    */       } 
/*    */       byte[] arrayOfByte1 = new byte[8];
/*    */       arrayOfByte1[0] = (byte)(int)(paramLong >>> 56L);
/*    */       for (byte b = 1; b < 8; b++)
/*    */         arrayOfByte1[b] = (byte)(int)(paramLong << b * 8 >>> 56L); 
/*    */       DESKeySpec dESKeySpec = new DESKeySpec(arrayOfByte1);
/*    */       SecretKey secretKey = ((SecretKeyFactory)arrayOfObject[1]).generateSecret(dESKeySpec);
/*    */       ((Cipher)arrayOfObject[0]).init(2, secretKey, (IvParameterSpec)arrayOfObject[2]);
/*    */       "Ꙥﾽ폡煌?퉩慪돒㭏㲛珶".toCharArray()[5] = (char)("Ꙥﾽ폡煌?퉩慪돒㭏㲛珶".toCharArray()[5] ^ 0x7DC0);
/*    */       byte[] arrayOfByte2 = g[i].getBytes(fW$gy.A("Ꙥﾽ폡煌?퉩慪돒㭏㲛珶".toCharArray(), (short)24946, false, 2));
/*    */       h[i] = a(((Cipher)arrayOfObject[0]).doFinal(arrayOfByte2));
/*    */     } 
/*    */     return h[i];
/*    */   }
/*    */   
/*    */   private static Object a(MethodHandles.Lookup paramLookup, MutableCallSite paramMutableCallSite, String paramString, Object[] paramArrayOfObject) {
/*    */     int i = ((Integer)paramArrayOfObject[0]).intValue();
/*    */     long l = ((Long)paramArrayOfObject[1]).longValue();
/*    */     String str = a(i, l);
/*    */     MethodHandle methodHandle = MethodHandles.constant(String.class, str);
/*    */     paramMutableCallSite.setTarget(MethodHandles.dropArguments(methodHandle, 0, new Class[] { int.class, long.class }));
/*    */     return str;
/*    */   }
/*    */   
/*    */   private static CallSite a(MethodHandles.Lookup paramLookup, String paramString, MethodType paramMethodType) {
/*    */     // Byte code:
/*    */     //   0: new java/lang/invoke/MutableCallSite
/*    */     //   3: dup
/*    */     //   4: aload_2
/*    */     //   5: invokespecial <init> : (Ljava/lang/invoke/MethodType;)V
/*    */     //   8: astore_3
/*    */     //   9: aload_3
/*    */     //   10: ldc_w
/*    */     //   13: ldc_w [Ljava/lang/Object;
/*    */     //   16: aload_2
/*    */     //   17: invokevirtual parameterCount : ()I
/*    */     //   20: invokevirtual asCollector : (Ljava/lang/Class;I)Ljava/lang/invoke/MethodHandle;
/*    */     //   23: iconst_0
/*    */     //   24: iconst_3
/*    */     //   25: anewarray java/lang/Object
/*    */     //   28: dup
/*    */     //   29: iconst_0
/*    */     //   30: aload_0
/*    */     //   31: aastore
/*    */     //   32: dup
/*    */     //   33: iconst_1
/*    */     //   34: aload_3
/*    */     //   35: aastore
/*    */     //   36: dup
/*    */     //   37: iconst_2
/*    */     //   38: aload_1
/*    */     //   39: aastore
/*    */     //   40: invokestatic insertArguments : (Ljava/lang/invoke/MethodHandle;I[Ljava/lang/Object;)Ljava/lang/invoke/MethodHandle;
/*    */     //   43: aload_2
/*    */     //   44: invokestatic explicitCastArguments : (Ljava/lang/invoke/MethodHandle;Ljava/lang/invoke/MethodType;)Ljava/lang/invoke/MethodHandle;
/*    */     //   47: invokevirtual setTarget : (Ljava/lang/invoke/MethodHandle;)V
/*    */     //   50: goto -> 171
/*    */     //   53: astore #4
/*    */     //   55: new java/lang/RuntimeException
/*    */     //   58: dup
/*    */     //   59: new java/lang/StringBuilder
/*    */     //   62: dup
/*    */     //   63: invokespecial <init> : ()V
/*    */     //   66: ldc_w '?듀눘㨾綖菿簧쌳䕛㓈䤺蹟굆闍?﫹丷'
/*    */     //   69: invokevirtual toCharArray : ()[C
/*    */     //   72: dup
/*    */     //   73: dup
/*    */     //   74: bipush #16
/*    */     //   76: dup_x1
/*    */     //   77: caload
/*    */     //   78: sipush #20102
/*    */     //   81: ixor
/*    */     //   82: i2c
/*    */     //   83: castore
/*    */     //   84: sipush #23359
/*    */     //   87: iconst_1
/*    */     //   88: iconst_2
/*    */     //   89: invokestatic A : (Ljava/lang/Object;SZI)Ljava/lang/String;
/*    */     //   92: invokevirtual append : (Ljava/lang/String;)Ljava/lang/StringBuilder;
/*    */     //   95: ldc_w '濳ᛇ㒱'
/*    */     //   98: invokevirtual toCharArray : ()[C
/*    */     //   101: dup
/*    */     //   102: dup
/*    */     //   103: iconst_0
/*    */     //   104: dup_x1
/*    */     //   105: caload
/*    */     //   106: sipush #17134
/*    */     //   109: ixor
/*    */     //   110: i2c
/*    */     //   111: castore
/*    */     //   112: sipush #32638
/*    */     //   115: iconst_1
/*    */     //   116: iconst_3
/*    */     //   117: invokestatic A : (Ljava/lang/Object;SZI)Ljava/lang/String;
/*    */     //   120: invokevirtual append : (Ljava/lang/String;)Ljava/lang/StringBuilder;
/*    */     //   123: aload_1
/*    */     //   124: invokevirtual append : (Ljava/lang/String;)Ljava/lang/StringBuilder;
/*    */     //   127: ldc_w '뼢蹂粿'
/*    */     //   130: invokevirtual toCharArray : ()[C
/*    */     //   133: dup
/*    */     //   134: dup
/*    */     //   135: iconst_2
/*    */     //   136: dup_x1
/*    */     //   137: caload
/*    */     //   138: sipush #28395
/*    */     //   141: ixor
/*    */     //   142: i2c
/*    */     //   143: castore
/*    */     //   144: sipush #19019
/*    */     //   147: iconst_1
/*    */     //   148: iconst_1
/*    */     //   149: invokestatic A : (Ljava/lang/Object;SZI)Ljava/lang/String;
/*    */     //   152: invokevirtual append : (Ljava/lang/String;)Ljava/lang/StringBuilder;
/*    */     //   155: aload_2
/*    */     //   156: invokevirtual toString : ()Ljava/lang/String;
/*    */     //   159: invokevirtual append : (Ljava/lang/String;)Ljava/lang/StringBuilder;
/*    */     //   162: invokevirtual toString : ()Ljava/lang/String;
/*    */     //   165: aload #4
/*    */     //   167: invokespecial <init> : (Ljava/lang/String;Ljava/lang/Throwable;)V
/*    */     //   170: athrow
/*    */     //   171: aload_3
/*    */     //   172: areturn
/*    */     // Exception table:
/*    */     //   from	to	target	type
/*    */     //   9	50	53	java/lang/Exception
/*    */   }
/*    */ }


/* Location:              C:\Users\BukkitBypass\Desktop\MatrixAC\AAC\AAC-spigot-5.2.0.jar!\me\konsolas\aac\e2.class
 * Java compiler version: 8 (52.0)
 * JD-Core Version:       1.1.3
 */