/*   */ package me.konsolas.aac;final class e8 { static { byte b1; long l1; int j, k, m;
/*   */     long l2;
/*   */     int n, i1, i2;
/* 4 */     for (g = nc.a(6460465505208919080L, 3415066841131152132L, MethodHandles.lookup().lookupClass()).a(141995975860748L), l1 = g ^ 0x59C91134CAD5L, j = (int)((l1 ^ 0x5D1E9842A8DFL) >>> 32L), k = (int)((l1 ^ 0x5D1E9842A8DFL) << 32L >>> 48L), m = (int)((l1 ^ 0x5D1E9842A8DFL) << 48L >>> 48L), l1 ^ 0x5D1E9842A8DFL, l2 = l1 ^ 0x68F63C6C617DL, n = (int)((l1 ^ 0x7D8BDA1E1CA0L) >>> 32L), i1 = (int)((l1 ^ 0x7D8BDA1E1CA0L) << 32L >>> 56L), i2 = (int)((l1 ^ 0x7D8BDA1E1CA0L) << 40L >>> 40L), l1 ^ 0x7D8BDA1E1CA0L, j = new HashMap<>(13), "쎗槗硫㟳㪃썇蔔귤칻錟쎟鹢Ĺꎐ퍡࿼귥Ლ".toCharArray()[11] = (char)("쎗槗硫㟳㪃썇蔔귤칻錟쎟鹢Ĺꎐ퍡࿼귥Ლ".toCharArray()[11] ^ 0x38FC), "?㋜ᨷ瑮".toCharArray()[0] = (char)("?㋜ᨷ瑮".toCharArray()[0] ^ 0x6118), (new byte[8])[0] = (byte)(int)(l1 >>> 56L), b1 = 1; b1 < 8; ) { (new byte[8])[b1] = (byte)(int)(l1 << b1 * 8 >>> 56L); b1++; }  Cipher cipher; (cipher = Cipher.getInstance(hY$g6.H("쎗槗硫㟳㪃썇蔔귤칻錟쎟鹢Ĺꎐ퍡࿼귥Ლ".toCharArray(), (short)30448, (byte)3, (byte)1))).init(2, SecretKeyFactory.getInstance(hY$g6.H("?㋜ᨷ瑮".toCharArray(), (short)17577, (byte)3, (byte)3)).generateSecret(new DESKeySpec(new byte[8])), new IvParameterSpec(new byte[8])); String[] arrayOfString = new String[61]; boolean bool = false; "肉妅䉤⪽㚉?勷⛶峥奧䷁䤝᪽墟닒䛰ꞻ㈪ꔥၞ갩炏ሢ핖ᘤ㤻⮞胜暴ﮣ됂ྕ䗁岁퍏쭰ύ쥭텉䃛鋘◿૥꿢ᢶ驴䳊퉼嬚໶デ鏝⚴깔飷?㚦䙱鰯뿏駁痎텆ᔆḺ崎︅함㍧۪덺ẫᐇ갃⺯叹몊颾蔊ગ朔㲍䳈윰ﰇ䜟騑荎㰰क़㊤荫첊萙䲥鋮츋㉆돉빸蟇뗸ꮀ忌煢닽齴ꮃ뭢颧頛衝fﯸ꧝粻ꁧ饻䧮㪮歜좤猩剁➀꽐䧩轀獔鬀⹵회ₖ?畒鎫쟍曬얕릉응鯙⹗졣լ⫨딚楘戮곞쬃䱵퉤됡뤰᝹٬㐍㫰쾧弇ﺲ퀍傫춠腾璷늶໿ꥅ?镪枸뙓㊬滝뛫䱴濎?ꭇ줁蓓⃰ꃧ㐱娳䒤涕3≜ᨩ衭喪⢣폕?䠰燧ᄄ쿨蔰욉⻢ㅼÜ畃饗⵴睻⚤왋跭?긝恳䀍慐稵⵴ꙡ啛﵌쒭韨⸺폼㍵욹욤௛ↈ꽉’⇧ꎟ锐峡⾨긵ﮁ択㥼덪汗㙞냗ኹ礪䊅贊稡供ྂᏼ제䎗뇼嵉꿕ℝⲃㄬ뢐Ǳ钧媏藧チ䓴勥듛┼䘹짼ﺋ蘻㚯ぺ鰯똚桃垶◟降㚵࿤훓ᧉ䭺䊑㣗첄仄뗬膉뉬褞ૄ鐫缨뫆糎䢢裞蚕Ṅ嚯⤾頤盔ᙓ\b㶬郞ᢃ锈今富姻펛ೆ䗪⡐蟕ր簂???㟓子歄垪쎳莮옇帄⥡薼赵䭶쥼嚙溯缟Ь缵뵑ᇢឩ瓧袽љ画種쾎縙?邧㽯䱽饈먜礟퐹鄰ꡫ5뱽ᮡ拐瓔꜑婦庋娺隖ﭓ?접鈼한兆涤몁읂ᘂ〒썯?䥱靝Ⱔ쟀?뺟忀䓿̐㋫韊ꑞ䏝꼮숮꘲⠰䋃庁媈윟䢊?秛訊⭲솗㱺ぺՏ㰗䳥㐞翹ꫥ킻䊞蕽蕋๮Ꙧ꧋♑὘쨩䭝譔㖖̠疎?安ቁ猝柔寋슕펪䵹ᑩ㏇키?蒵䑢┐聳?獧긐杭삖ᩌ긃䘠缄巢좪௳膖?ᙅ톘턝瀦ꆁ䑔⪅ᐏꋵ뮬栃䔷㞙଩♬媯鮛⯎偗￹ꅿꞦസ吥傸⽊凞ꢿ긪⨺৳ꅐ濧㷄뾡愴?먄䲳㓟㺐ᭉό쯄梤㳎泪Ｌႛ᱐䢩ꦷ荁Ή봬蝷㠘脾췹芃䲘멏뮚㣝養䈅飀⯸뾼ꨂ㈪똨鎦⧘簢ᳩ鄙凃ﱢ㏠翆ୌ때䰒ઁ鏽퀇䃽湬长䅿擨征㇤欑㖿馄?怷눅㼟ⷦᩢ珖?둙香₧㽞㖢Ꮦ諠쩪祑柇ⶢ咸⑸䞖鼦び쓾ꯨͥᑊज򔠷듐砢뱭篙譎쿙┉Ҵᅈ鴪ᣲ切欹஻〜랆⤢擖饵뢴椛讫렇㝦쁩鳞䑬껿⒝츖㥹˾ᦓ䨐㍷㝁䭍ꍇ≾愹ꋫဵ恼䣲ᾆ᤬깗홯踏ᖫ솮襍瀘犸쟓邂଱挒鶹혚廢调␭岓驛㽝ဴ쨌痓㋚ꭗ뒾麐ꝏ謚椐꓌迮꧴␂鋌碊籕?Ϝ䪣ⶫ଄蝒뒐肛뜒趄麤顴Ꭶ蟜ԫ?箲ೞꥆ쓹튘䑧%鼾됢꧜襖䛑﹒苳冣螥㖾烑ᾂᆝ瓩ᚪം챊꬛࿱쵛?퐃셰?㖡運ᤏ쌄骸벓뵤嫨墘趁鏆忢耆?콨轰㫾镑崢疝捃㋐䜑碗刴୰ꯗ䦝ꒌ懅ꑴ銚쒉堾涵▚緝Ք됎⸋䔳岿噗笔嬫눟꙯뒖斬賕奝売㍢䘜꿗ቤឺ粨▃禉舁᭼າ坛㕍ꃬሆ嫠簤圪㿦禴䔩✶ᨴ슛⡶턨ꑋ䳃ୗ꾦슌笆Ÿ⥗?곊꠲訥ᴠ쿦?㨕惐ᐤ⃳椥쌌࿥䂒陒蘂௑උ䳂潛ꋬ솽滧筻牝㿬騇밽惂ࠖ፸둎ռ㬞姠Ꮁ撰ꨫ臕ꃛ摬涫뼊遍戕懣됊죒嗚?䰱暀ृॅ୬ᦅꘜ垓㗏ぼ黛妿㗺䔞?໩鿱䳣蛒뿢䷨䌞갰꫻겫崲㇊㋓䪺鋗뤿差믄ﰊ㐟‪蛕쭋㘂ﭔ댪샛䪠ི͂歟蜀특챫⋮惉෥ฅ﬎랝㫪쁞?맋帆㝧掠铥淑ᗔ⢗躲甜୯㼝⏚璄苊㟒쒒筸箅뮿歵稢⨙Ǜᨤ⟠﫜䋞勒♰専ꮇ噕腵丐೗ᮎⲾ保鈲啝䏏꒮䷳绛ු㗝恱ꐃ葚ꂡ몾ッ蝻ᒏ祀闱Ƒﰈꆚ릡旀橆밼酇촲䄏휖ໞꊨ▆↾䅣㩮尹邟䞹거밭錳穛뚏⫬赱왔丫Ꜧӂ?硘拓멿醓珙箰봝㓋詄챓㪙廈ꑙ嫾ꂁ䂕Ӌ齺㸑悳킱ꠉ㼒쯯裿⍩퓆꟮릡㵦磂凮ᆚ⶗퍝讨ඣࣗ헾նꢵ?君\035ꋬ뿍䛦詙鼐죫䃱뤡㪉˚医쬠氟佂惻㣡퀥ỹ柡ဥえ썎톚ঢ슍⬕㮁纓㑐➗ﻍ㭝ゃ験敺퐶馹縱媍뉤㫰?ꠖЅ꽚㶫䏋寢惧菝霣ꄊ쑟ᯄ춫蜯絶뎟厦ꟴ?綢扉뙊煾킵꡴焴鬲ｴ⹱疇ࡹ㚙㡬顇אַ建㋖뙵놠纊ꞃ睘私?龇✩㥭퍉珪㴱郏摔꩒㏄或떌躗砥顖Ⲃ痤塾ᚌⳄ盽귫ꅰ䓝✮犽얎欶㨟帔챋꯭⓺?믎岦ڠ쏑?꣎쐀?룔഑དྷ≚쭑십?တ콙㆜ⰾ䗀䫯䮵叡䨂젻Ꭳ俁஌ᘡ郛ࠨᄲꉖຌ紽漑᫒яﲫ㱍할蔪덪ᯬ﯌烱ￍ桯錞Ꮳ㢄㚃噳ΐ烶ꘃ喬ᙢ㾢鉴鞕䚙힋⑰ꌄ籞?ꗝ⥺殪蓼ᠤ︦⦓栏̬䱋ꐅ曉∥䅕ڃ쁰䝘⠥睲鄕Ｗ슫赬甊赻ꖹ࿡ꉢ⇳ᙽӲ葑ⷡ䟒ꔮ怂푘馒봗젃鮮莡ࣣ瀿乜驌拂╳觤Ő뷜ᵬ蒥?믝䟼Ꮀ睚?䉯硊흸寘ᬋ൭?凈査崄ꉝ䙴鋛୅뾺踊唵ꆮƷꉬ埸䲒ݫℱ鳙鵆팿⯤榍䯷汢?叼ㄬ靧핫蕕?쭃⎆栿꾚ᣚ曂萏?抇嵺礬姦폪䃂㽴韝䢲占黃긕拍븾ᢃΦ魗훣踬輻ﭿﺕ戈⊅鬨놉耬͇ᛘ숇⭁︍薅䗀苟밉㟌䪔窢⺛濍α芓뽻恱㳁悔࿏ጄ駷౓᭦㣿틾᳸딄偲ण䥣㋒壮袕דּ흠倞⽬딭⿎쥢뿔丁⦧ꄹ픨築僯躗߿抬?툽縱橦ᕢⵃ氐盠导߿嘄쾪?ز鱮餆⵻䞿ꐹ୒ꉳᄀ旭昷嘰㣂퐎˙".toCharArray()[990] = (char)("肉妅䉤⪽㚉?勷⛶峥奧䷁䤝᪽墟닒䛰ꞻ㈪ꔥၞ갩炏ሢ핖ᘤ㤻⮞胜暴ﮣ됂ྕ䗁岁퍏쭰ύ쥭텉䃛鋘◿૥꿢ᢶ驴䳊퉼嬚໶デ鏝⚴깔飷?㚦䙱鰯뿏駁痎텆ᔆḺ崎︅함㍧۪덺ẫᐇ갃⺯叹몊颾蔊ગ朔㲍䳈윰ﰇ䜟騑荎㰰क़㊤荫첊萙䲥鋮츋㉆돉빸蟇뗸ꮀ忌煢닽齴ꮃ뭢颧頛衝fﯸ꧝粻ꁧ饻䧮㪮歜좤猩剁➀꽐䧩轀獔鬀⹵회ₖ?畒鎫쟍曬얕릉응鯙⹗졣լ⫨딚楘戮곞쬃䱵퉤됡뤰᝹٬㐍㫰쾧弇ﺲ퀍傫춠腾璷늶໿ꥅ?镪枸뙓㊬滝뛫䱴濎?ꭇ줁蓓⃰ꃧ㐱娳䒤涕3≜ᨩ衭喪⢣폕?䠰燧ᄄ쿨蔰욉⻢ㅼÜ畃饗⵴睻⚤왋跭?긝恳䀍慐稵⵴ꙡ啛﵌쒭韨⸺폼㍵욹욤௛ↈ꽉’⇧ꎟ锐峡⾨긵ﮁ択㥼덪汗㙞냗ኹ礪䊅贊稡供ྂᏼ제䎗뇼嵉꿕ℝⲃㄬ뢐Ǳ钧媏藧チ䓴勥듛┼䘹짼ﺋ蘻㚯ぺ鰯똚桃垶◟降㚵࿤훓ᧉ䭺䊑㣗첄仄뗬膉뉬褞ૄ鐫缨뫆糎䢢裞蚕Ṅ嚯⤾頤盔ᙓ\b㶬郞ᢃ锈今富姻펛ೆ䗪⡐蟕ր簂???㟓子歄垪쎳莮옇帄⥡薼赵䭶쥼嚙溯缟Ь缵뵑ᇢឩ瓧袽љ画種쾎縙?邧㽯䱽饈먜礟퐹鄰ꡫ5뱽ᮡ拐瓔꜑婦庋娺隖ﭓ?접鈼한兆涤몁읂ᘂ〒썯?䥱靝Ⱔ쟀?뺟忀䓿̐㋫韊ꑞ䏝꼮숮꘲⠰䋃庁媈윟䢊?秛訊⭲솗㱺ぺՏ㰗䳥㐞翹ꫥ킻䊞蕽蕋๮Ꙧ꧋♑὘쨩䭝譔㖖̠疎?安ቁ猝柔寋슕펪䵹ᑩ㏇키?蒵䑢┐聳?獧긐杭삖ᩌ긃䘠缄巢좪௳膖?ᙅ톘턝瀦ꆁ䑔⪅ᐏꋵ뮬栃䔷㞙଩♬媯鮛⯎偗￹ꅿꞦസ吥傸⽊凞ꢿ긪⨺৳ꅐ濧㷄뾡愴?먄䲳㓟㺐ᭉό쯄梤㳎泪Ｌႛ᱐䢩ꦷ荁Ή봬蝷㠘脾췹芃䲘멏뮚㣝養䈅飀⯸뾼ꨂ㈪똨鎦⧘簢ᳩ鄙凃ﱢ㏠翆ୌ때䰒ઁ鏽퀇䃽湬长䅿擨征㇤欑㖿馄?怷눅㼟ⷦᩢ珖?둙香₧㽞㖢Ꮦ諠쩪祑柇ⶢ咸⑸䞖鼦び쓾ꯨͥᑊज򔠷듐砢뱭篙譎쿙┉Ҵᅈ鴪ᣲ切欹஻〜랆⤢擖饵뢴椛讫렇㝦쁩鳞䑬껿⒝츖㥹˾ᦓ䨐㍷㝁䭍ꍇ≾愹ꋫဵ恼䣲ᾆ᤬깗홯踏ᖫ솮襍瀘犸쟓邂଱挒鶹혚廢调␭岓驛㽝ဴ쨌痓㋚ꭗ뒾麐ꝏ謚椐꓌迮꧴␂鋌碊籕?Ϝ䪣ⶫ଄蝒뒐肛뜒趄麤顴Ꭶ蟜ԫ?箲ೞꥆ쓹튘䑧%鼾됢꧜襖䛑﹒苳冣螥㖾烑ᾂᆝ瓩ᚪം챊꬛࿱쵛?퐃셰?㖡運ᤏ쌄骸벓뵤嫨墘趁鏆忢耆?콨轰㫾镑崢疝捃㋐䜑碗刴୰ꯗ䦝ꒌ懅ꑴ銚쒉堾涵▚緝Ք됎⸋䔳岿噗笔嬫눟꙯뒖斬賕奝売㍢䘜꿗ቤឺ粨▃禉舁᭼າ坛㕍ꃬሆ嫠簤圪㿦禴䔩✶ᨴ슛⡶턨ꑋ䳃ୗ꾦슌笆Ÿ⥗?곊꠲訥ᴠ쿦?㨕惐ᐤ⃳椥쌌࿥䂒陒蘂௑උ䳂潛ꋬ솽滧筻牝㿬騇밽惂ࠖ፸둎ռ㬞姠Ꮁ撰ꨫ臕ꃛ摬涫뼊遍戕懣됊죒嗚?䰱暀ृॅ୬ᦅꘜ垓㗏ぼ黛妿㗺䔞?໩鿱䳣蛒뿢䷨䌞갰꫻겫崲㇊㋓䪺鋗뤿差믄ﰊ㐟‪蛕쭋㘂ﭔ댪샛䪠ི͂歟蜀특챫⋮惉෥ฅ﬎랝㫪쁞?맋帆㝧掠铥淑ᗔ⢗躲甜୯㼝⏚璄苊㟒쒒筸箅뮿歵稢⨙Ǜᨤ⟠﫜䋞勒♰専ꮇ噕腵丐೗ᮎⲾ保鈲啝䏏꒮䷳绛ු㗝恱ꐃ葚ꂡ몾ッ蝻ᒏ祀闱Ƒﰈꆚ릡旀橆밼酇촲䄏휖ໞꊨ▆↾䅣㩮尹邟䞹거밭錳穛뚏⫬赱왔丫Ꜧӂ?硘拓멿醓珙箰봝㓋詄챓㪙廈ꑙ嫾ꂁ䂕Ӌ齺㸑悳킱ꠉ㼒쯯裿⍩퓆꟮릡㵦磂凮ᆚ⶗퍝讨ඣࣗ헾նꢵ?君\035ꋬ뿍䛦詙鼐죫䃱뤡㪉˚医쬠氟佂惻㣡퀥ỹ柡ဥえ썎톚ঢ슍⬕㮁纓㑐➗ﻍ㭝ゃ験敺퐶馹縱媍뉤㫰?ꠖЅ꽚㶫䏋寢惧菝霣ꄊ쑟ᯄ춫蜯絶뎟厦ꟴ?綢扉뙊煾킵꡴焴鬲ｴ⹱疇ࡹ㚙㡬顇אַ建㋖뙵놠纊ꞃ睘私?龇✩㥭퍉珪㴱郏摔꩒㏄或떌躗砥顖Ⲃ痤塾ᚌⳄ盽귫ꅰ䓝✮犽얎欶㨟帔챋꯭⓺?믎岦ڠ쏑?꣎쐀?룔഑དྷ≚쭑십?တ콙㆜ⰾ䗀䫯䮵叡䨂젻Ꭳ俁஌ᘡ郛ࠨᄲꉖຌ紽漑᫒яﲫ㱍할蔪덪ᯬ﯌烱ￍ桯錞Ꮳ㢄㚃噳ΐ烶ꘃ喬ᙢ㾢鉴鞕䚙힋⑰ꌄ籞?ꗝ⥺殪蓼ᠤ︦⦓栏̬䱋ꐅ曉∥䅕ڃ쁰䝘⠥睲鄕Ｗ슫赬甊赻ꖹ࿡ꉢ⇳ᙽӲ葑ⷡ䟒ꔮ怂푘馒봗젃鮮莡ࣣ瀿乜驌拂╳觤Ő뷜ᵬ蒥?믝䟼Ꮀ睚?䉯硊흸寘ᬋ൭?凈査崄ꉝ䙴鋛୅뾺踊唵ꆮƷꉬ埸䲒ݫℱ鳙鵆팿⯤榍䯷汢?叼ㄬ靧핫蕕?쭃⎆栿꾚ᣚ曂萏?抇嵺礬姦폪䃂㽴韝䢲占黃긕拍븾ᢃΦ魗훣踬輻ﭿﺕ戈⊅鬨놉耬͇ᛘ숇⭁︍薅䗀苟밉㟌䪔窢⺛濍α芓뽻恱㳁悔࿏ጄ駷౓᭦㣿틾᳸딄偲ण䥣㋒壮袕דּ흠倞⽬딭⿎쥢뿔丁⦧ꄹ픨築僯躗߿抬?툽縱橦ᕢⵃ氐盠导߿嘄쾪?ز鱮餆⵻䞿ꐹ୒ꉳᄀ旭昷嘰㣂퐎˙".toCharArray()[990] ^ 0x6841); String str; int i = (str = hY$g6.H("肉妅䉤⪽㚉?勷⛶峥奧䷁䤝᪽墟닒䛰ꞻ㈪ꔥၞ갩炏ሢ핖ᘤ㤻⮞胜暴ﮣ됂ྕ䗁岁퍏쭰ύ쥭텉䃛鋘◿૥꿢ᢶ驴䳊퉼嬚໶デ鏝⚴깔飷?㚦䙱鰯뿏駁痎텆ᔆḺ崎︅함㍧۪덺ẫᐇ갃⺯叹몊颾蔊ગ朔㲍䳈윰ﰇ䜟騑荎㰰क़㊤荫첊萙䲥鋮츋㉆돉빸蟇뗸ꮀ忌煢닽齴ꮃ뭢颧頛衝fﯸ꧝粻ꁧ饻䧮㪮歜좤猩剁➀꽐䧩轀獔鬀⹵회ₖ?畒鎫쟍曬얕릉응鯙⹗졣լ⫨딚楘戮곞쬃䱵퉤됡뤰᝹٬㐍㫰쾧弇ﺲ퀍傫춠腾璷늶໿ꥅ?镪枸뙓㊬滝뛫䱴濎?ꭇ줁蓓⃰ꃧ㐱娳䒤涕3≜ᨩ衭喪⢣폕?䠰燧ᄄ쿨蔰욉⻢ㅼÜ畃饗⵴睻⚤왋跭?긝恳䀍慐稵⵴ꙡ啛﵌쒭韨⸺폼㍵욹욤௛ↈ꽉’⇧ꎟ锐峡⾨긵ﮁ択㥼덪汗㙞냗ኹ礪䊅贊稡供ྂᏼ제䎗뇼嵉꿕ℝⲃㄬ뢐Ǳ钧媏藧チ䓴勥듛┼䘹짼ﺋ蘻㚯ぺ鰯똚桃垶◟降㚵࿤훓ᧉ䭺䊑㣗첄仄뗬膉뉬褞ૄ鐫缨뫆糎䢢裞蚕Ṅ嚯⤾頤盔ᙓ\b㶬郞ᢃ锈今富姻펛ೆ䗪⡐蟕ր簂???㟓子歄垪쎳莮옇帄⥡薼赵䭶쥼嚙溯缟Ь缵뵑ᇢឩ瓧袽љ画種쾎縙?邧㽯䱽饈먜礟퐹鄰ꡫ5뱽ᮡ拐瓔꜑婦庋娺隖ﭓ?접鈼한兆涤몁읂ᘂ〒썯?䥱靝Ⱔ쟀?뺟忀䓿̐㋫韊ꑞ䏝꼮숮꘲⠰䋃庁媈윟䢊?秛訊⭲솗㱺ぺՏ㰗䳥㐞翹ꫥ킻䊞蕽蕋๮Ꙧ꧋♑὘쨩䭝譔㖖̠疎?安ቁ猝柔寋슕펪䵹ᑩ㏇키?蒵䑢┐聳?獧긐杭삖ᩌ긃䘠缄巢좪௳膖?ᙅ톘턝瀦ꆁ䑔⪅ᐏꋵ뮬栃䔷㞙଩♬媯鮛⯎偗￹ꅿꞦസ吥傸⽊凞ꢿ긪⨺৳ꅐ濧㷄뾡愴?먄䲳㓟㺐ᭉό쯄梤㳎泪Ｌႛ᱐䢩ꦷ荁Ή봬蝷㠘脾췹芃䲘멏뮚㣝養䈅飀⯸뾼ꨂ㈪똨鎦⧘簢ᳩ鄙凃ﱢ㏠翆ୌ때䰒ઁ鏽퀇䃽湬长䅿擨征㇤欑㖿馄?怷눅㼟ⷦᩢ珖?둙香₧㽞㖢Ꮦ諠쩪祑柇ⶢ咸⑸䞖鼦び쓾ꯨͥᑊज򔠷듐砢뱭篙譎쿙┉Ҵᅈ鴪ᣲ切欹஻〜랆⤢擖饵뢴椛讫렇㝦쁩鳞䑬껿⒝츖㥹˾ᦓ䨐㍷㝁䭍ꍇ≾愹ꋫဵ恼䣲ᾆ᤬깗홯踏ᖫ솮襍瀘犸쟓邂଱挒鶹혚廢调␭岓驛㽝ဴ쨌痓㋚ꭗ뒾麐ꝏ謚椐꓌迮꧴␂鋌碊籕?Ϝ䪣ⶫ଄蝒뒐肛뜒趄麤顴Ꭶ蟜ԫ?箲ೞꥆ쓹튘䑧%鼾됢꧜襖䛑﹒苳冣螥㖾烑ᾂᆝ瓩ᚪം챊꬛࿱쵛?퐃셰?㖡運ᤏ쌄骸벓뵤嫨墘趁鏆忢耆?콨轰㫾镑崢疝捃㋐䜑碗刴୰ꯗ䦝ꒌ懅ꑴ銚쒉堾涵▚緝Ք됎⸋䔳岿噗笔嬫눟꙯뒖斬賕奝売㍢䘜꿗ቤឺ粨▃禉舁᭼າ坛㕍ꃬሆ嫠簤圪㿦禴䔩✶ᨴ슛⡶턨ꑋ䳃ୗ꾦슌笆Ÿ⥗?곊꠲訥ᴠ쿦?㨕惐ᐤ⃳椥쌌࿥䂒陒蘂௑උ䳂潛ꋬ솽滧筻牝㿬騇밽惂ࠖ፸둎ռ㬞姠Ꮁ撰ꨫ臕ꃛ摬涫뼊遍戕懣됊죒嗚?䰱暀ृॅ୬ᦅꘜ垓㗏ぼ黛妿㗺䔞?໩鿱䳣蛒뿢䷨䌞갰꫻겫崲㇊㋓䪺鋗뤿差믄ﰊ㐟‪蛕쭋㘂ﭔ댪샛䪠ི͂歟蜀특챫⋮惉෥ฅ﬎랝㫪쁞?맋帆㝧掠铥淑ᗔ⢗躲甜୯㼝⏚璄苊㟒쒒筸箅뮿歵稢⨙Ǜᨤ⟠﫜䋞勒♰専ꮇ噕腵丐೗ᮎⲾ保鈲啝䏏꒮䷳绛ු㗝恱ꐃ葚ꂡ몾ッ蝻ᒏ祀闱Ƒﰈꆚ릡旀橆밼酇촲䄏휖ໞꊨ▆↾䅣㩮尹邟䞹거밭錳穛뚏⫬赱왔丫Ꜧӂ?硘拓멿醓珙箰봝㓋詄챓㪙廈ꑙ嫾ꂁ䂕Ӌ齺㸑悳킱ꠉ㼒쯯裿⍩퓆꟮릡㵦磂凮ᆚ⶗퍝讨ඣࣗ헾նꢵ?君\035ꋬ뿍䛦詙鼐죫䃱뤡㪉˚医쬠氟佂惻㣡퀥ỹ柡ဥえ썎톚ঢ슍⬕㮁纓㑐➗ﻍ㭝ゃ験敺퐶馹縱媍뉤㫰?ꠖЅ꽚㶫䏋寢惧菝霣ꄊ쑟ᯄ춫蜯絶뎟厦ꟴ?綢扉뙊煾킵꡴焴鬲ｴ⹱疇ࡹ㚙㡬顇אַ建㋖뙵놠纊ꞃ睘私?龇✩㥭퍉珪㴱郏摔꩒㏄或떌躗砥顖Ⲃ痤塾ᚌⳄ盽귫ꅰ䓝✮犽얎欶㨟帔챋꯭⓺?믎岦ڠ쏑?꣎쐀?룔഑དྷ≚쭑십?တ콙㆜ⰾ䗀䫯䮵叡䨂젻Ꭳ俁஌ᘡ郛ࠨᄲꉖຌ紽漑᫒яﲫ㱍할蔪덪ᯬ﯌烱ￍ桯錞Ꮳ㢄㚃噳ΐ烶ꘃ喬ᙢ㾢鉴鞕䚙힋⑰ꌄ籞?ꗝ⥺殪蓼ᠤ︦⦓栏̬䱋ꐅ曉∥䅕ڃ쁰䝘⠥睲鄕Ｗ슫赬甊赻ꖹ࿡ꉢ⇳ᙽӲ葑ⷡ䟒ꔮ怂푘馒봗젃鮮莡ࣣ瀿乜驌拂╳觤Ő뷜ᵬ蒥?믝䟼Ꮀ睚?䉯硊흸寘ᬋ൭?凈査崄ꉝ䙴鋛୅뾺踊唵ꆮƷꉬ埸䲒ݫℱ鳙鵆팿⯤榍䯷汢?叼ㄬ靧핫蕕?쭃⎆栿꾚ᣚ曂萏?抇嵺礬姦폪䃂㽴韝䢲占黃긕拍븾ᢃΦ魗훣踬輻ﭿﺕ戈⊅鬨놉耬͇ᛘ숇⭁︍薅䗀苟밉㟌䪔窢⺛濍α芓뽻恱㳁悔࿏ጄ駷౓᭦㣿틾᳸딄偲ण䥣㋒壮袕דּ흠倞⽬딭⿎쥢뿔丁⦧ꄹ픨築僯躗߿抬?툽縱橦ᕢⵃ氐盠导߿嘄쾪?ز鱮餆⵻䞿ꐹ୒ꉳᄀ旭昷嘰㣂퐎˙".toCharArray(), (short)2603, (byte)4, (byte)4)).length(); byte b2 = 32; byte b = -1;
/*   */     while (true); }
/*   */ 
/*   */   
/*   */   private static final int e = 15;
/*   */   private static final int a = 31;
/*   */   private static final int d = 63;
/*   */   private static final int c = 127;
/*   */   static final g[] f;
/*   */   static final Map b;
/*   */   private static final long g;
/*   */   private static final String[] h;
/*   */   private static final String[] i;
/*   */   private static final Map j;
/*   */   
/*   */   private static CallSite a(MethodHandles.Lookup paramLookup, String paramString, MethodType paramMethodType) {
/*   */     // Byte code:
/*   */     //   0: new java/lang/invoke/MutableCallSite
/*   */     //   3: dup
/*   */     //   4: aload_2
/*   */     //   5: invokespecial <init> : (Ljava/lang/invoke/MethodType;)V
/*   */     //   8: astore_3
/*   */     //   9: aload_3
/*   */     //   10: ldc_w
/*   */     //   13: ldc_w [Ljava/lang/Object;
/*   */     //   16: aload_2
/*   */     //   17: invokevirtual parameterCount : ()I
/*   */     //   20: invokevirtual asCollector : (Ljava/lang/Class;I)Ljava/lang/invoke/MethodHandle;
/*   */     //   23: iconst_0
/*   */     //   24: iconst_3
/*   */     //   25: anewarray java/lang/Object
/*   */     //   28: dup
/*   */     //   29: iconst_0
/*   */     //   30: aload_0
/*   */     //   31: aastore
/*   */     //   32: dup
/*   */     //   33: iconst_1
/*   */     //   34: aload_3
/*   */     //   35: aastore
/*   */     //   36: dup
/*   */     //   37: iconst_2
/*   */     //   38: aload_1
/*   */     //   39: aastore
/*   */     //   40: invokestatic insertArguments : (Ljava/lang/invoke/MethodHandle;I[Ljava/lang/Object;)Ljava/lang/invoke/MethodHandle;
/*   */     //   43: aload_2
/*   */     //   44: invokestatic explicitCastArguments : (Ljava/lang/invoke/MethodHandle;Ljava/lang/invoke/MethodType;)Ljava/lang/invoke/MethodHandle;
/*   */     //   47: invokevirtual setTarget : (Ljava/lang/invoke/MethodHandle;)V
/*   */     //   50: goto -> 170
/*   */     //   53: astore #4
/*   */     //   55: new java/lang/RuntimeException
/*   */     //   58: dup
/*   */     //   59: new java/lang/StringBuilder
/*   */     //   62: dup
/*   */     //   63: invokespecial <init> : ()V
/*   */     //   66: ldc_w '䚣꫍類핤혌鮰謁痺??甠禖ₖ뻅킟獎摚'
/*   */     //   69: invokevirtual toCharArray : ()[C
/*   */     //   72: dup
/*   */     //   73: dup
/*   */     //   74: iconst_1
/*   */     //   75: dup_x1
/*   */     //   76: caload
/*   */     //   77: sipush #17108
/*   */     //   80: ixor
/*   */     //   81: i2c
/*   */     //   82: castore
/*   */     //   83: sipush #9112
/*   */     //   86: iconst_5
/*   */     //   87: iconst_1
/*   */     //   88: invokestatic H : (Ljava/lang/Object;SBB)Ljava/lang/String;
/*   */     //   91: invokevirtual append : (Ljava/lang/String;)Ljava/lang/StringBuilder;
/*   */     //   94: ldc_w 'ᯌ㐚췺柢'
/*   */     //   97: invokevirtual toCharArray : ()[C
/*   */     //   100: dup
/*   */     //   101: dup
/*   */     //   102: iconst_2
/*   */     //   103: dup_x1
/*   */     //   104: caload
/*   */     //   105: sipush #18159
/*   */     //   108: ixor
/*   */     //   109: i2c
/*   */     //   110: castore
/*   */     //   111: sipush #1015
/*   */     //   114: iconst_1
/*   */     //   115: iconst_0
/*   */     //   116: invokestatic H : (Ljava/lang/Object;SBB)Ljava/lang/String;
/*   */     //   119: invokevirtual append : (Ljava/lang/String;)Ljava/lang/StringBuilder;
/*   */     //   122: aload_1
/*   */     //   123: invokevirtual append : (Ljava/lang/String;)Ljava/lang/StringBuilder;
/*   */     //   126: ldc_w '캆搾ἳ䧺'
/*   */     //   129: invokevirtual toCharArray : ()[C
/*   */     //   132: dup
/*   */     //   133: dup
/*   */     //   134: iconst_1
/*   */     //   135: dup_x1
/*   */     //   136: caload
/*   */     //   137: sipush #5694
/*   */     //   140: ixor
/*   */     //   141: i2c
/*   */     //   142: castore
/*   */     //   143: sipush #21475
/*   */     //   146: iconst_2
/*   */     //   147: iconst_2
/*   */     //   148: invokestatic H : (Ljava/lang/Object;SBB)Ljava/lang/String;
/*   */     //   151: invokevirtual append : (Ljava/lang/String;)Ljava/lang/StringBuilder;
/*   */     //   154: aload_2
/*   */     //   155: invokevirtual toString : ()Ljava/lang/String;
/*   */     //   158: invokevirtual append : (Ljava/lang/String;)Ljava/lang/StringBuilder;
/*   */     //   161: invokevirtual toString : ()Ljava/lang/String;
/*   */     //   164: aload #4
/*   */     //   166: invokespecial <init> : (Ljava/lang/String;Ljava/lang/Throwable;)V
/*   */     //   169: athrow
/*   */     //   170: aload_3
/*   */     //   171: areturn
/*   */     // Exception table:
/*   */     //   from	to	target	type
/*   */     //   9	50	53	java/lang/Exception
/*   */   }
/*   */   
/*   */   private static Object a(MethodHandles.Lookup paramLookup, MutableCallSite paramMutableCallSite, String paramString, Object[] paramArrayOfObject) {
/*   */     int i = ((Integer)paramArrayOfObject[0]).intValue();
/*   */     long l = ((Long)paramArrayOfObject[1]).longValue();
/*   */     String str = a(i, l);
/*   */     MethodHandle methodHandle = MethodHandles.constant(String.class, str);
/*   */     paramMutableCallSite.setTarget(MethodHandles.dropArguments(methodHandle, 0, new Class[] { int.class, long.class }));
/*   */     return str;
/*   */   }
/*   */   
/*   */   private static String a(int paramInt, long paramLong) {
/*   */     int i = paramInt ^ (int)(paramLong & 0x7FFFL) ^ 0x5434;
/*   */     if (i[i] == null) {
/*   */       Object[] arrayOfObject;
/*   */       try {
/*   */         Long long_ = Long.valueOf(Thread.currentThread().getId());
/*   */         arrayOfObject = (Object[])j.get(long_);
/*   */         if (arrayOfObject == null) {
/*   */           arrayOfObject = new Object[3];
/*   */           "蔐㿋㶃᫝䚴⨎慍첿ﱸ紞ﵞ➋㓫劯ᦘꉱ?婚".toCharArray()[14] = (char)("蔐㿋㶃᫝䚴⨎慍첿ﱸ紞ﵞ➋㓫劯ᦘꉱ?婚".toCharArray()[14] ^ 0x6C47);
/*   */           arrayOfObject[0] = Cipher.getInstance(dP$dt.X("蔐㿋㶃᫝䚴⨎慍첿ﱸ紞ﵞ➋㓫劯ᦘꉱ?婚".toCharArray(), (short)17590, true, false));
/*   */           "⭟橧偮".toCharArray()[0] = (char)("⭟橧偮".toCharArray()[0] ^ 0x4579);
/*   */           arrayOfObject[1] = SecretKeyFactory.getInstance(dP$dt.X("⭟橧偮".toCharArray(), (short)15894, false, true));
/*   */           arrayOfObject[2] = new IvParameterSpec(new byte[8]);
/*   */           j.put(long_, arrayOfObject);
/*   */         } 
/*   */       } catch (Exception exception) {
/*   */         "쑈캍픆锎蟨裼炀ಒଶḝල惐㓃ꭲك䭧".toCharArray()[15] = (char)("쑈캍픆锎蟨裼炀ಒଶḝල惐㓃ꭲك䭧".toCharArray()[15] ^ 0x2105);
/*   */         throw new RuntimeException(dP$dt.X("쑈캍픆锎蟨裼炀ಒଶḝල惐㓃ꭲك䭧".toCharArray(), (short)28100, true, false), exception);
/*   */       } 
/*   */       byte[] arrayOfByte1 = new byte[8];
/*   */       arrayOfByte1[0] = (byte)(int)(paramLong >>> 56L);
/*   */       for (byte b = 1; b < 8; b++)
/*   */         arrayOfByte1[b] = (byte)(int)(paramLong << b * 8 >>> 56L); 
/*   */       DESKeySpec dESKeySpec = new DESKeySpec(arrayOfByte1);
/*   */       SecretKey secretKey = ((SecretKeyFactory)arrayOfObject[1]).generateSecret(dESKeySpec);
/*   */       ((Cipher)arrayOfObject[0]).init(2, secretKey, (IvParameterSpec)arrayOfObject[2]);
/*   */       "笷৻빴ฆ⃵㩜伍苖碾䰢".toCharArray()[1] = (char)("笷৻빴ฆ⃵㩜伍苖碾䰢".toCharArray()[1] ^ 0x53B2);
/*   */       byte[] arrayOfByte2 = h[i].getBytes(dP$dt.X("笷৻빴ฆ⃵㩜伍苖碾䰢".toCharArray(), (short)18741, false, false));
/*   */       i[i] = a(((Cipher)arrayOfObject[0]).doFinal(arrayOfByte2));
/*   */     } 
/*   */     return i[i];
/*   */   }
/*   */   
/*   */   private static String a(byte[] paramArrayOfbyte) {
/*   */     byte b1 = 0;
/*   */     int i;
/*   */     char[] arrayOfChar = new char[i = paramArrayOfbyte.length];
/*   */     for (byte b2 = 0; b2 < i; b2++) {
/*   */       int j;
/*   */       if ((j = 0xFF & paramArrayOfbyte[b2]) < 192) {
/*   */         arrayOfChar[b1++] = (char)j;
/*   */       } else if (j < 224) {
/*   */         char c = (char)((char)(j & 0x1F) << 6);
/*   */         j = paramArrayOfbyte[++b2];
/*   */         c = (char)(c | (char)(j & 0x3F));
/*   */         arrayOfChar[b1++] = c;
/*   */       } else if (b2 < i - 2) {
/*   */         char c = (char)((char)(j & 0xF) << 12);
/*   */         j = paramArrayOfbyte[++b2];
/*   */         c = (char)(c | (char)(j & 0x3F) << 6);
/*   */         j = paramArrayOfbyte[++b2];
/*   */         c = (char)(c | (char)(j & 0x3F));
/*   */         arrayOfChar[b1++] = c;
/*   */       } 
/*   */     } 
/*   */     return new String(arrayOfChar, 0, b1);
/*   */   }
/*   */   
/*   */   private static Exception a(Exception paramException) {
/*   */     return paramException;
/*   */   }
/*   */   
/*   */   static gZ a(gZ paramgZ, byte paramByte, int paramInt1, int paramInt2) {
/*   */     // Byte code:
/*   */     //   0: iload_1
/*   */     //   1: i2l
/*   */     //   2: bipush #56
/*   */     //   4: lshl
/*   */     //   5: iload_2
/*   */     //   6: i2l
/*   */     //   7: bipush #32
/*   */     //   9: lshl
/*   */     //   10: bipush #8
/*   */     //   12: lushr
/*   */     //   13: lor
/*   */     //   14: iload_3
/*   */     //   15: i2l
/*   */     //   16: bipush #40
/*   */     //   18: lshl
/*   */     //   19: bipush #40
/*   */     //   21: lushr
/*   */     //   22: lor
/*   */     //   23: getstatic me/konsolas/aac/e8.g : J
/*   */     //   26: lxor
/*   */     //   27: lstore #4
/*   */     //   29: lload #4
/*   */     //   31: dup2
/*   */     //   32: ldc2_w 24199280319257
/*   */     //   35: lxor
/*   */     //   36: lstore #6
/*   */     //   38: dup2
/*   */     //   39: ldc2_w 1303122634726
/*   */     //   42: lxor
/*   */     //   43: lstore #8
/*   */     //   45: pop2
/*   */     //   46: ldc2_w 1971809974167928667
/*   */     //   49: lload #4
/*   */     //   51: <illegal opcode> w : (JJ)[Lme/konsolas/aac/aN;
/*   */     //   56: iconst_0
/*   */     //   57: istore #11
/*   */     //   59: astore #10
/*   */     //   61: aload_0
/*   */     //   62: invokevirtual a : ()I
/*   */     //   65: istore #12
/*   */     //   67: iload #11
/*   */     //   69: iload #12
/*   */     //   71: if_icmpge -> 203
/*   */     //   74: aload_0
/*   */     //   75: aload #10
/*   */     //   77: ifnull -> 204
/*   */     //   80: iload #11
/*   */     //   82: lload #6
/*   */     //   84: invokevirtual a : (IJ)B
/*   */     //   87: istore #13
/*   */     //   89: aload #10
/*   */     //   91: iload_2
/*   */     //   92: ifle -> 200
/*   */     //   95: ifnull -> 198
/*   */     //   98: iload #13
/*   */     //   100: bipush #65
/*   */     //   102: if_icmplt -> 195
/*   */     //   105: goto -> 119
/*   */     //   108: ldc2_w 1983810090659463974
/*   */     //   111: lload #4
/*   */     //   113: <illegal opcode> w : (Ljava/lang/Exception;JJ)Ljava/lang/Exception;
/*   */     //   118: athrow
/*   */     //   119: iload #13
/*   */     //   121: bipush #90
/*   */     //   123: if_icmpgt -> 195
/*   */     //   126: goto -> 140
/*   */     //   129: ldc2_w 1983810090659463974
/*   */     //   132: lload #4
/*   */     //   134: <illegal opcode> w : (Ljava/lang/Exception;JJ)Ljava/lang/Exception;
/*   */     //   139: athrow
/*   */     //   140: new java/io/IOException
/*   */     //   143: dup
/*   */     //   144: new java/lang/StringBuilder
/*   */     //   147: dup
/*   */     //   148: invokespecial <init> : ()V
/*   */     //   151: sipush #1149
/*   */     //   154: ldc2_w 3530680808326744710
/*   */     //   157: lload #4
/*   */     //   159: lxor
/*   */     //   160: <illegal opcode> l : (IJ)Ljava/lang/String;
/*   */     //   165: invokevirtual append : (Ljava/lang/String;)Ljava/lang/StringBuilder;
/*   */     //   168: aload_0
/*   */     //   169: lload #8
/*   */     //   171: invokevirtual c : (J)Ljava/lang/String;
/*   */     //   174: invokevirtual append : (Ljava/lang/String;)Ljava/lang/StringBuilder;
/*   */     //   177: invokevirtual toString : ()Ljava/lang/String;
/*   */     //   180: invokespecial <init> : (Ljava/lang/String;)V
/*   */     //   183: athrow
/*   */     //   184: ldc2_w 1983810090659463974
/*   */     //   187: lload #4
/*   */     //   189: <illegal opcode> w : (Ljava/lang/Exception;JJ)Ljava/lang/Exception;
/*   */     //   194: athrow
/*   */     //   195: iinc #11, 1
/*   */     //   198: aload #10
/*   */     //   200: ifnonnull -> 67
/*   */     //   203: aload_0
/*   */     //   204: areturn
/*   */     // Line number table:
/*   */     //   Java source line number -> byte code offset
/*   */     //   #10	-> 56
/*   */     //   #2	-> 74
/*   */     //   #7	-> 89
/*   */     //   #14	-> 140
/*   */     //   #8	-> 195
/*   */     //   #1	-> 203
/*   */     // Exception table:
/*   */     //   from	to	target	type
/*   */     //   89	105	108	java/io/IOException
/*   */     //   98	126	129	java/io/IOException
/*   */     //   119	184	184	java/io/IOException
/*   */   }
/*   */   
/*   */   private static Map a(long paramLong) {
/*   */     // Byte code:
/*   */     //   0: getstatic me/konsolas/aac/e8.g : J
/*   */     //   3: lload_0
/*   */     //   4: lxor
/*   */     //   5: lstore_0
/*   */     //   6: new java/util/LinkedHashMap
/*   */     //   9: dup
/*   */     //   10: getstatic me/konsolas/aac/e8.f : [Lme/konsolas/aac/g;
/*   */     //   13: arraylength
/*   */     //   14: invokespecial <init> : (I)V
/*   */     //   17: astore_2
/*   */     //   18: iconst_0
/*   */     //   19: istore_3
/*   */     //   20: iload_3
/*   */     //   21: getstatic me/konsolas/aac/e8.f : [Lme/konsolas/aac/g;
/*   */     //   24: arraylength
/*   */     //   25: if_icmpge -> 111
/*   */     //   28: lload_0
/*   */     //   29: lconst_0
/*   */     //   30: lcmp
/*   */     //   31: ifle -> 105
/*   */     //   34: aload_2
/*   */     //   35: lload_0
/*   */     //   36: lconst_0
/*   */     //   37: lcmp
/*   */     //   38: iflt -> 115
/*   */     //   41: getstatic me/konsolas/aac/e8.f : [Lme/konsolas/aac/g;
/*   */     //   44: iload_3
/*   */     //   45: aaload
/*   */     //   46: getfield j : Lme/konsolas/aac/gZ;
/*   */     //   49: invokeinterface containsKey : (Ljava/lang/Object;)Z
/*   */     //   54: ifne -> 102
/*   */     //   57: goto -> 70
/*   */     //   60: ldc2_w -6139924107869851029
/*   */     //   63: lload_0
/*   */     //   64: <illegal opcode> w : (Ljava/lang/Exception;JJ)Ljava/lang/Exception;
/*   */     //   69: athrow
/*   */     //   70: aload_2
/*   */     //   71: getstatic me/konsolas/aac/e8.f : [Lme/konsolas/aac/g;
/*   */     //   74: iload_3
/*   */     //   75: aaload
/*   */     //   76: getfield j : Lme/konsolas/aac/gZ;
/*   */     //   79: iload_3
/*   */     //   80: invokestatic valueOf : (I)Ljava/lang/Integer;
/*   */     //   83: invokeinterface put : (Ljava/lang/Object;Ljava/lang/Object;)Ljava/lang/Object;
/*   */     //   88: pop
/*   */     //   89: goto -> 102
/*   */     //   92: ldc2_w -6139924107869851029
/*   */     //   95: lload_0
/*   */     //   96: <illegal opcode> w : (Ljava/lang/Exception;JJ)Ljava/lang/Exception;
/*   */     //   101: athrow
/*   */     //   102: iinc #3, 1
/*   */     //   105: lload_0
/*   */     //   106: lconst_0
/*   */     //   107: lcmp
/*   */     //   108: ifgt -> 20
/*   */     //   111: aload_2
/*   */     //   112: invokestatic unmodifiableMap : (Ljava/util/Map;)Ljava/util/Map;
/*   */     //   115: areturn
/*   */     // Line number table:
/*   */     //   Java source line number -> byte code offset
/*   */     //   #15	-> 6
/*   */     //   #12	-> 18
/*   */     //   #3	-> 28
/*   */     //   #6	-> 70
/*   */     //   #13	-> 102
/*   */     //   #11	-> 111
/*   */     // Exception table:
/*   */     //   from	to	target	type
/*   */     //   20	57	60	aacinternal/v
/*   */     //   28	89	92	aacinternal/v
/*   */   } }


/* Location:              C:\Users\BukkitBypass\Desktop\MatrixAC\AAC\AAC-spigot-5.2.0.jar!\me\konsolas\aac\e8.class
 * Java compiler version: 8 (52.0)
 * JD-Core Version:       1.1.3
 */