/*    */ package me.konsolas.aac;
/*    */ 
/*    */ import aacinternal.v;
/*    */ 
/*    */ public enum eb {
/*    */   public static final eb NO_ERROR;
/*    */   eb(int paramInt1) {
/*  8 */     this.httpCode = paramInt1;
/*    */   }
/*    */   
/*    */   public static final eb PROTOCOL_ERROR;
/*    */   
/*    */   public static final eb INTERNAL_ERROR;
/*    */   public static final eb FLOW_CONTROL_ERROR;
/*    */   public static final eb REFUSED_STREAM;
/*    */   public static final eb CANCEL;
/*    */   public static final eb COMPRESSION_ERROR;
/*    */   public static final eb CONNECT_ERROR;
/*    */   public static final eb ENHANCE_YOUR_CALM;
/*    */   public static final eb INADEQUATE_SECURITY;
/*    */   public static final eb HTTP_1_1_REQUIRED;
/*    */   public final int httpCode;
/*    */   private static aN[] b;
/*    */   private static final long a;
/*    */   
/*    */   private static String a(byte[] paramArrayOfbyte) {
/*    */     byte b1 = 0;
/*    */     int i;
/*    */     char[] arrayOfChar = new char[i = paramArrayOfbyte.length];
/*    */     for (byte b2 = 0; b2 < i; b2++) {
/*    */       int j;
/*    */       if ((j = 0xFF & paramArrayOfbyte[b2]) < 192) {
/*    */         arrayOfChar[b1++] = (char)j;
/*    */       } else if (j < 224) {
/*    */         char c = (char)((char)(j & 0x1F) << 6);
/*    */         j = paramArrayOfbyte[++b2];
/*    */         c = (char)(c | (char)(j & 0x3F));
/*    */         arrayOfChar[b1++] = c;
/*    */       } else if (b2 < i - 2) {
/*    */         char c = (char)((char)(j & 0xF) << 12);
/*    */         j = paramArrayOfbyte[++b2];
/*    */         c = (char)(c | (char)(j & 0x3F) << 6);
/*    */         j = paramArrayOfbyte[++b2];
/*    */         c = (char)(c | (char)(j & 0x3F));
/*    */         arrayOfChar[b1++] = c;
/*    */       } 
/*    */     } 
/*    */     return new String(arrayOfChar, 0, b1);
/*    */   }
/*    */   
/*    */   private static v a(v paramv) {
/*    */     return paramv;
/*    */   }
/*    */   
/*    */   public static aN[] b() {
/*    */     return b;
/*    */   }
/*    */   
/*    */   public static void b(aN[] paramArrayOfaN) {
/*    */     b = paramArrayOfaN;
/*    */   }
/*    */   
/*    */   static {
/*    */     // Byte code:
/*    */     //   0: ldc2_w 7951716280610040544
/*    */     //   3: ldc2_w 7944981449953478170
/*    */     //   6: invokestatic lookup : ()Ljava/lang/invoke/MethodHandles$Lookup;
/*    */     //   9: invokevirtual lookupClass : ()Ljava/lang/Class;
/*    */     //   12: invokestatic a : (JJLjava/lang/Object;)Lme/konsolas/aac/na;
/*    */     //   15: ldc2_w 242329289635219
/*    */     //   18: invokeinterface a : (J)J
/*    */     //   23: putstatic me/konsolas/aac/eb.a : J
/*    */     //   26: getstatic me/konsolas/aac/eb.a : J
/*    */     //   29: ldc2_w 101303015671365
/*    */     //   32: lxor
/*    */     //   33: lstore #10
/*    */     //   35: ldc2_w 8364427306219507730
/*    */     //   38: lload #10
/*    */     //   40: <illegal opcode> w : (JJ)[Lme/konsolas/aac/aN;
/*    */     //   45: ifnonnull -> 62
/*    */     //   48: iconst_1
/*    */     //   49: anewarray me/konsolas/aac/aN
/*    */     //   52: ldc2_w 8405799033642545141
/*    */     //   55: lload #10
/*    */     //   57: <illegal opcode> w : ([Lme/konsolas/aac/aN;JJ)V
/*    */     //   62: ldc '雂⎗怯감㔏쌔⮞潛ᶔ?૗℆磊澫䦚精⊦䡤緜䐁'
/*    */     //   64: invokevirtual toCharArray : ()[C
/*    */     //   67: dup
/*    */     //   68: dup
/*    */     //   69: bipush #18
/*    */     //   71: dup_x1
/*    */     //   72: caload
/*    */     //   73: sipush #7785
/*    */     //   76: ixor
/*    */     //   77: i2c
/*    */     //   78: castore
/*    */     //   79: sipush #4611
/*    */     //   82: iconst_0
/*    */     //   83: iconst_5
/*    */     //   84: invokestatic G : (Ljava/lang/Object;SZB)Ljava/lang/String;
/*    */     //   87: invokestatic getInstance : (Ljava/lang/String;)Ljavax/crypto/Cipher;
/*    */     //   90: dup
/*    */     //   91: astore_1
/*    */     //   92: iconst_2
/*    */     //   93: ldc '갤섇ꅯɣ'
/*    */     //   95: invokevirtual toCharArray : ()[C
/*    */     //   98: dup
/*    */     //   99: dup
/*    */     //   100: iconst_1
/*    */     //   101: dup_x1
/*    */     //   102: caload
/*    */     //   103: sipush #7886
/*    */     //   106: ixor
/*    */     //   107: i2c
/*    */     //   108: castore
/*    */     //   109: sipush #17915
/*    */     //   112: iconst_0
/*    */     //   113: iconst_0
/*    */     //   114: invokestatic G : (Ljava/lang/Object;SZB)Ljava/lang/String;
/*    */     //   117: invokestatic getInstance : (Ljava/lang/String;)Ljavax/crypto/SecretKeyFactory;
/*    */     //   120: bipush #8
/*    */     //   122: newarray byte
/*    */     //   124: dup
/*    */     //   125: iconst_0
/*    */     //   126: lload #10
/*    */     //   128: bipush #56
/*    */     //   130: lushr
/*    */     //   131: l2i
/*    */     //   132: i2b
/*    */     //   133: bastore
/*    */     //   134: iconst_1
/*    */     //   135: istore_2
/*    */     //   136: iload_2
/*    */     //   137: bipush #8
/*    */     //   139: if_icmpge -> 163
/*    */     //   142: dup
/*    */     //   143: iload_2
/*    */     //   144: lload #10
/*    */     //   146: iload_2
/*    */     //   147: bipush #8
/*    */     //   149: imul
/*    */     //   150: lshl
/*    */     //   151: bipush #56
/*    */     //   153: lushr
/*    */     //   154: l2i
/*    */     //   155: i2b
/*    */     //   156: bastore
/*    */     //   157: iinc #2, 1
/*    */     //   160: goto -> 136
/*    */     //   163: new javax/crypto/spec/DESKeySpec
/*    */     //   166: dup_x1
/*    */     //   167: swap
/*    */     //   168: invokespecial <init> : ([B)V
/*    */     //   171: invokevirtual generateSecret : (Ljava/security/spec/KeySpec;)Ljavax/crypto/SecretKey;
/*    */     //   174: new javax/crypto/spec/IvParameterSpec
/*    */     //   177: dup
/*    */     //   178: bipush #8
/*    */     //   180: newarray byte
/*    */     //   182: invokespecial <init> : ([B)V
/*    */     //   185: invokevirtual init : (ILjava/security/Key;Ljava/security/spec/AlgorithmParameterSpec;)V
/*    */     //   188: bipush #11
/*    */     //   190: anewarray java/lang/String
/*    */     //   193: astore #8
/*    */     //   195: iconst_0
/*    */     //   196: istore #6
/*    */     //   198: ldc '蚌菂앆➺ᬮ怯ꨟꔡ걜➯鎛鏶跗沇ꪂ킬꾪쐝ᎊ觚䗬⊀먖刕萆ம帟څ巍됵糎Ꮛ쀨皕兀ꘐُ쩩䭮ỡق拞न롊飸᱕ࣗ뎯禈혞?መ䡏셸啽ꨩ匎㐆ꕻ웮쟯䂤⺌豥渢?镙괼셷茉Ŝ쥣뫿뇐쯁﷙囶ᒮ鋣ᐘ샄卄怕ᜮ縔徰횼ᯍ盥鷄钠鷳깦ᓔ倪?䱩蒒呏䡪뢞댞剄蝃ꚙ⊡뇰첹큊赈곚䆨薪坦콺ⷀ䃀㒭ｨ榲䙱閑﬌ΰ»ꝼ怹ᾄ籔퓌ﷻ▻〗䬝끦鑘۔ꏀﱊ씜ᅐ⡧ట禗濝悦㾍䵊䴁轜ஏꯧٸ城ឿꦱ륔?舑ඹ镭㙳킏㼹ㄣ䇯뷠䳆ɗ'
/*    */     //   200: invokevirtual toCharArray : ()[C
/*    */     //   203: dup
/*    */     //   204: dup
/*    */     //   205: bipush #27
/*    */     //   207: dup_x1
/*    */     //   208: caload
/*    */     //   209: sipush #6174
/*    */     //   212: ixor
/*    */     //   213: i2c
/*    */     //   214: castore
/*    */     //   215: sipush #2692
/*    */     //   218: iconst_0
/*    */     //   219: iconst_1
/*    */     //   220: invokestatic G : (Ljava/lang/Object;SZB)Ljava/lang/String;
/*    */     //   223: dup
/*    */     //   224: astore #5
/*    */     //   226: invokevirtual length : ()I
/*    */     //   229: istore #7
/*    */     //   231: bipush #24
/*    */     //   233: istore #4
/*    */     //   235: iconst_m1
/*    */     //   236: istore_3
/*    */     //   237: iinc #3, 1
/*    */     //   240: aload #5
/*    */     //   242: iload_3
/*    */     //   243: dup
/*    */     //   244: iload #4
/*    */     //   246: iadd
/*    */     //   247: invokevirtual substring : (II)Ljava/lang/String;
/*    */     //   250: iconst_m1
/*    */     //   251: goto -> 380
/*    */     //   254: aload #8
/*    */     //   256: swap
/*    */     //   257: iload #6
/*    */     //   259: iinc #6, 1
/*    */     //   262: swap
/*    */     //   263: aastore
/*    */     //   264: iload_3
/*    */     //   265: iload #4
/*    */     //   267: iadd
/*    */     //   268: dup
/*    */     //   269: istore_3
/*    */     //   270: iload #7
/*    */     //   272: if_icmpge -> 286
/*    */     //   275: aload #5
/*    */     //   277: iload_3
/*    */     //   278: invokevirtual charAt : (I)C
/*    */     //   281: istore #4
/*    */     //   283: goto -> 237
/*    */     //   286: ldc '?ᗣ?Ɗ諒?ᛕ＃﫷틻胶￞忐첤㎿◠빠्℩딷葂萭䌴௾泮ǎ쿸⿎'
/*    */     //   288: invokevirtual toCharArray : ()[C
/*    */     //   291: dup
/*    */     //   292: dup
/*    */     //   293: bipush #26
/*    */     //   295: dup_x1
/*    */     //   296: caload
/*    */     //   297: sipush #10185
/*    */     //   300: ixor
/*    */     //   301: i2c
/*    */     //   302: castore
/*    */     //   303: sipush #3374
/*    */     //   306: iconst_0
/*    */     //   307: iconst_3
/*    */     //   308: invokestatic G : (Ljava/lang/Object;SZB)Ljava/lang/String;
/*    */     //   311: dup
/*    */     //   312: astore #5
/*    */     //   314: invokevirtual length : ()I
/*    */     //   317: istore #7
/*    */     //   319: bipush #16
/*    */     //   321: istore #4
/*    */     //   323: iconst_m1
/*    */     //   324: istore_3
/*    */     //   325: iinc #3, 1
/*    */     //   328: aload #5
/*    */     //   330: iload_3
/*    */     //   331: dup
/*    */     //   332: iload #4
/*    */     //   334: iadd
/*    */     //   335: invokevirtual substring : (II)Ljava/lang/String;
/*    */     //   338: iconst_0
/*    */     //   339: goto -> 380
/*    */     //   342: aload #8
/*    */     //   344: swap
/*    */     //   345: iload #6
/*    */     //   347: iinc #6, 1
/*    */     //   350: swap
/*    */     //   351: aastore
/*    */     //   352: iload_3
/*    */     //   353: iload #4
/*    */     //   355: iadd
/*    */     //   356: dup
/*    */     //   357: istore_3
/*    */     //   358: iload #7
/*    */     //   360: if_icmpge -> 374
/*    */     //   363: aload #5
/*    */     //   365: iload_3
/*    */     //   366: invokevirtual charAt : (I)C
/*    */     //   369: istore #4
/*    */     //   371: goto -> 325
/*    */     //   374: aload #8
/*    */     //   376: astore_0
/*    */     //   377: goto -> 444
/*    */     //   380: swap
/*    */     //   381: ldc '櫙⡧㟦鑙慄뤑㐦촜ﳍ㎇ി'
/*    */     //   383: invokevirtual toCharArray : ()[C
/*    */     //   386: dup
/*    */     //   387: dup
/*    */     //   388: bipush #6
/*    */     //   390: dup_x1
/*    */     //   391: caload
/*    */     //   392: sipush #8352
/*    */     //   395: ixor
/*    */     //   396: i2c
/*    */     //   397: castore
/*    */     //   398: sipush #9343
/*    */     //   401: iconst_0
/*    */     //   402: iconst_2
/*    */     //   403: invokestatic G : (Ljava/lang/Object;SZB)Ljava/lang/String;
/*    */     //   406: invokevirtual getBytes : (Ljava/lang/String;)[B
/*    */     //   409: aload_1
/*    */     //   410: swap
/*    */     //   411: invokevirtual doFinal : ([B)[B
/*    */     //   414: astore #9
/*    */     //   416: aload #9
/*    */     //   418: invokestatic a : ([B)Ljava/lang/String;
/*    */     //   421: invokevirtual intern : ()Ljava/lang/String;
/*    */     //   424: swap
/*    */     //   425: tableswitch default -> 254, 0 -> 342
/*    */     //   444: new me/konsolas/aac/eb
/*    */     //   447: dup
/*    */     //   448: aload_0
/*    */     //   449: bipush #10
/*    */     //   451: aaload
/*    */     //   452: iconst_0
/*    */     //   453: iconst_0
/*    */     //   454: invokespecial <init> : (Ljava/lang/String;II)V
/*    */     //   457: putstatic me/konsolas/aac/eb.NO_ERROR : Lme/konsolas/aac/eb;
/*    */     //   460: new me/konsolas/aac/eb
/*    */     //   463: dup
/*    */     //   464: aload_0
/*    */     //   465: iconst_5
/*    */     //   466: aaload
/*    */     //   467: iconst_1
/*    */     //   468: iconst_1
/*    */     //   469: invokespecial <init> : (Ljava/lang/String;II)V
/*    */     //   472: putstatic me/konsolas/aac/eb.PROTOCOL_ERROR : Lme/konsolas/aac/eb;
/*    */     //   475: new me/konsolas/aac/eb
/*    */     //   478: dup
/*    */     //   479: aload_0
/*    */     //   480: bipush #9
/*    */     //   482: aaload
/*    */     //   483: iconst_2
/*    */     //   484: iconst_2
/*    */     //   485: invokespecial <init> : (Ljava/lang/String;II)V
/*    */     //   488: putstatic me/konsolas/aac/eb.INTERNAL_ERROR : Lme/konsolas/aac/eb;
/*    */     //   491: new me/konsolas/aac/eb
/*    */     //   494: dup
/*    */     //   495: aload_0
/*    */     //   496: iconst_4
/*    */     //   497: aaload
/*    */     //   498: iconst_3
/*    */     //   499: iconst_3
/*    */     //   500: invokespecial <init> : (Ljava/lang/String;II)V
/*    */     //   503: putstatic me/konsolas/aac/eb.FLOW_CONTROL_ERROR : Lme/konsolas/aac/eb;
/*    */     //   506: new me/konsolas/aac/eb
/*    */     //   509: dup
/*    */     //   510: aload_0
/*    */     //   511: bipush #6
/*    */     //   513: aaload
/*    */     //   514: iconst_4
/*    */     //   515: bipush #7
/*    */     //   517: invokespecial <init> : (Ljava/lang/String;II)V
/*    */     //   520: putstatic me/konsolas/aac/eb.REFUSED_STREAM : Lme/konsolas/aac/eb;
/*    */     //   523: new me/konsolas/aac/eb
/*    */     //   526: dup
/*    */     //   527: aload_0
/*    */     //   528: iconst_3
/*    */     //   529: aaload
/*    */     //   530: iconst_5
/*    */     //   531: bipush #8
/*    */     //   533: invokespecial <init> : (Ljava/lang/String;II)V
/*    */     //   536: putstatic me/konsolas/aac/eb.CANCEL : Lme/konsolas/aac/eb;
/*    */     //   539: new me/konsolas/aac/eb
/*    */     //   542: dup
/*    */     //   543: aload_0
/*    */     //   544: iconst_1
/*    */     //   545: aaload
/*    */     //   546: bipush #6
/*    */     //   548: bipush #9
/*    */     //   550: invokespecial <init> : (Ljava/lang/String;II)V
/*    */     //   553: putstatic me/konsolas/aac/eb.COMPRESSION_ERROR : Lme/konsolas/aac/eb;
/*    */     //   556: new me/konsolas/aac/eb
/*    */     //   559: dup
/*    */     //   560: aload_0
/*    */     //   561: bipush #7
/*    */     //   563: aaload
/*    */     //   564: bipush #7
/*    */     //   566: bipush #10
/*    */     //   568: invokespecial <init> : (Ljava/lang/String;II)V
/*    */     //   571: putstatic me/konsolas/aac/eb.CONNECT_ERROR : Lme/konsolas/aac/eb;
/*    */     //   574: new me/konsolas/aac/eb
/*    */     //   577: dup
/*    */     //   578: aload_0
/*    */     //   579: iconst_2
/*    */     //   580: aaload
/*    */     //   581: bipush #8
/*    */     //   583: bipush #11
/*    */     //   585: invokespecial <init> : (Ljava/lang/String;II)V
/*    */     //   588: putstatic me/konsolas/aac/eb.ENHANCE_YOUR_CALM : Lme/konsolas/aac/eb;
/*    */     //   591: new me/konsolas/aac/eb
/*    */     //   594: dup
/*    */     //   595: aload_0
/*    */     //   596: iconst_0
/*    */     //   597: aaload
/*    */     //   598: bipush #9
/*    */     //   600: bipush #12
/*    */     //   602: invokespecial <init> : (Ljava/lang/String;II)V
/*    */     //   605: putstatic me/konsolas/aac/eb.INADEQUATE_SECURITY : Lme/konsolas/aac/eb;
/*    */     //   608: new me/konsolas/aac/eb
/*    */     //   611: dup
/*    */     //   612: aload_0
/*    */     //   613: bipush #8
/*    */     //   615: aaload
/*    */     //   616: bipush #10
/*    */     //   618: bipush #13
/*    */     //   620: invokespecial <init> : (Ljava/lang/String;II)V
/*    */     //   623: putstatic me/konsolas/aac/eb.HTTP_1_1_REQUIRED : Lme/konsolas/aac/eb;
/*    */     //   626: bipush #11
/*    */     //   628: anewarray me/konsolas/aac/eb
/*    */     //   631: dup
/*    */     //   632: iconst_0
/*    */     //   633: getstatic me/konsolas/aac/eb.NO_ERROR : Lme/konsolas/aac/eb;
/*    */     //   636: aastore
/*    */     //   637: dup
/*    */     //   638: iconst_1
/*    */     //   639: getstatic me/konsolas/aac/eb.PROTOCOL_ERROR : Lme/konsolas/aac/eb;
/*    */     //   642: aastore
/*    */     //   643: dup
/*    */     //   644: iconst_2
/*    */     //   645: getstatic me/konsolas/aac/eb.INTERNAL_ERROR : Lme/konsolas/aac/eb;
/*    */     //   648: aastore
/*    */     //   649: dup
/*    */     //   650: iconst_3
/*    */     //   651: getstatic me/konsolas/aac/eb.FLOW_CONTROL_ERROR : Lme/konsolas/aac/eb;
/*    */     //   654: aastore
/*    */     //   655: dup
/*    */     //   656: iconst_4
/*    */     //   657: getstatic me/konsolas/aac/eb.REFUSED_STREAM : Lme/konsolas/aac/eb;
/*    */     //   660: aastore
/*    */     //   661: dup
/*    */     //   662: iconst_5
/*    */     //   663: getstatic me/konsolas/aac/eb.CANCEL : Lme/konsolas/aac/eb;
/*    */     //   666: aastore
/*    */     //   667: dup
/*    */     //   668: bipush #6
/*    */     //   670: getstatic me/konsolas/aac/eb.COMPRESSION_ERROR : Lme/konsolas/aac/eb;
/*    */     //   673: aastore
/*    */     //   674: dup
/*    */     //   675: bipush #7
/*    */     //   677: getstatic me/konsolas/aac/eb.CONNECT_ERROR : Lme/konsolas/aac/eb;
/*    */     //   680: aastore
/*    */     //   681: dup
/*    */     //   682: bipush #8
/*    */     //   684: getstatic me/konsolas/aac/eb.ENHANCE_YOUR_CALM : Lme/konsolas/aac/eb;
/*    */     //   687: aastore
/*    */     //   688: dup
/*    */     //   689: bipush #9
/*    */     //   691: getstatic me/konsolas/aac/eb.INADEQUATE_SECURITY : Lme/konsolas/aac/eb;
/*    */     //   694: aastore
/*    */     //   695: dup
/*    */     //   696: bipush #10
/*    */     //   698: getstatic me/konsolas/aac/eb.HTTP_1_1_REQUIRED : Lme/konsolas/aac/eb;
/*    */     //   701: aastore
/*    */     //   702: putstatic me/konsolas/aac/eb.c : [Lme/konsolas/aac/eb;
/*    */     //   705: return
/*    */     // Line number table:
/*    */     //   Java source line number -> byte code offset
/*    */     //   #2	-> 444
/*    */     //   #1	-> 460
/*    */     //   #21	-> 475
/*    */     //   #13	-> 491
/*    */     //   #6	-> 506
/*    */     //   #20	-> 523
/*    */     //   #19	-> 539
/*    */     //   #11	-> 556
/*    */     //   #3	-> 574
/*    */     //   #4	-> 591
/*    */     //   #14	-> 608
/*    */     //   #9	-> 626
/*    */   }
/*    */   
/*    */   public static eb a(int paramInt, long paramLong) {
/*    */     // Byte code:
/*    */     //   0: getstatic me/konsolas/aac/eb.a : J
/*    */     //   3: lload_1
/*    */     //   4: lxor
/*    */     //   5: lstore_1
/*    */     //   6: invokestatic values : ()[Lme/konsolas/aac/eb;
/*    */     //   9: astore #4
/*    */     //   11: ldc2_w 7930348860175911432
/*    */     //   14: lload_1
/*    */     //   15: <illegal opcode> w : (JJ)[Lme/konsolas/aac/aN;
/*    */     //   20: aload #4
/*    */     //   22: arraylength
/*    */     //   23: istore #5
/*    */     //   25: iconst_0
/*    */     //   26: istore #6
/*    */     //   28: astore_3
/*    */     //   29: iload #6
/*    */     //   31: iload #5
/*    */     //   33: if_icmpge -> 95
/*    */     //   36: aload #4
/*    */     //   38: iload #6
/*    */     //   40: aaload
/*    */     //   41: astore #7
/*    */     //   43: aload_3
/*    */     //   44: lload_1
/*    */     //   45: lconst_0
/*    */     //   46: lcmp
/*    */     //   47: iflt -> 92
/*    */     //   50: ifnull -> 91
/*    */     //   53: aload #7
/*    */     //   55: getfield httpCode : I
/*    */     //   58: iload_0
/*    */     //   59: if_icmpne -> 88
/*    */     //   62: goto -> 75
/*    */     //   65: ldc2_w 7997906524935296097
/*    */     //   68: lload_1
/*    */     //   69: <illegal opcode> w : (Laacinternal/v;JJ)Laacinternal/v;
/*    */     //   74: athrow
/*    */     //   75: aload #7
/*    */     //   77: areturn
/*    */     //   78: ldc2_w 7997906524935296097
/*    */     //   81: lload_1
/*    */     //   82: <illegal opcode> w : (Laacinternal/v;JJ)Laacinternal/v;
/*    */     //   87: athrow
/*    */     //   88: iinc #6, 1
/*    */     //   91: aload_3
/*    */     //   92: ifnonnull -> 29
/*    */     //   95: aconst_null
/*    */     //   96: areturn
/*    */     // Line number table:
/*    */     //   Java source line number -> byte code offset
/*    */     //   #7	-> 6
/*    */     //   #16	-> 43
/*    */     //   #5	-> 88
/*    */     //   #15	-> 95
/*    */     // Exception table:
/*    */     //   from	to	target	type
/*    */     //   43	62	65	aacinternal/v
/*    */     //   53	78	78	aacinternal/v
/*    */   }
/*    */ }


/* Location:              C:\Users\BukkitBypass\Desktop\MatrixAC\AAC\AAC-spigot-5.2.0.jar!\me\konsolas\aac\eb.class
 * Java compiler version: 8 (52.0)
 * JD-Core Version:       1.1.3
 */