/*    */ package me.konsolas.aac;public final class ec { public void a(long paramLong, s params) {
/*  2 */     paramLong = g ^ paramLong; long l1 = paramLong ^ 0x76F17A026C31L, l2 = (paramLong ^ 0x39DF65E95F3AL) >>> 16L; int i = (int)((paramLong ^ 0x39DF65E95F3AL) << 48L >>> 48L); paramLong ^ 0x39DF65E95F3AL; try { this.c.g(this.b);
/*    */ 
/*    */ 
/*    */ 
/*    */ 
/*    */ 
/*    */ 
/*    */ 
/*    */ 
/*    */ 
/*    */ 
/*    */ 
/*    */ 
/*    */ 
/*    */ 
/*    */ 
/*    */ 
/*    */ 
/*    */ 
/*    */ 
/*    */ 
/*    */ 
/*    */ 
/*    */ 
/*    */ 
/*    */ 
/*    */ 
/*    */ 
/*    */ 
/*    */ 
/*    */ 
/*    */ 
/*    */ 
/*    */ 
/*    */ 
/*    */ 
/*    */ 
/*    */ 
/*    */ 
/*    */ 
/*    */ 
/*    */ 
/*    */ 
/*    */ 
/*    */ 
/*    */ 
/*    */ 
/*    */ 
/*    */ 
/*    */ 
/*    */ 
/*    */ 
/*    */ 
/*    */ 
/*    */ 
/*    */ 
/*    */ 
/*    */ 
/*    */ 
/*    */ 
/*    */ 
/*    */ 
/*    */ 
/*    */ 
/*    */ 
/*    */ 
/*    */ 
/*    */ 
/*    */ 
/*    */       
/* 72 */       this.f.a(params, l1);
/*    */ 
/*    */ 
/*    */ 
/*    */ 
/*    */ 
/*    */ 
/*    */ 
/*    */ 
/*    */ 
/*    */ 
/*    */ 
/*    */ 
/*    */ 
/*    */ 
/*    */       
/*    */       this.c.a(this.b, params); }
/* 89 */     catch (IOException iOException)
/*    */     { this.c.a(this.b, iOException);
/*    */       a(l2, (short)i, iOException);
/*    */       throw iOException; }
/*    */   
/*    */   }
/*    */   
/*    */   final fO e;
/*    */   final gC b;
/*    */   final cv c;
/*    */   final bV a;
/*    */   final gq f;
/*    */   private boolean d;
/*    */   private static final long g = nc.a(4101518791398734870L, 6152242430439262722L, MethodHandles.lookup().lookupClass()).a(195760372254592L);
/*    */   private static final String h;
/*    */   
/*    */   public ec(fO paramfO, gC paramgC, cv paramcv, bV parambV, gq paramgq) {
/*    */     this.e = paramfO;
/*    */     this.b = paramgC;
/*    */     this.c = paramcv;
/*    */     this.a = parambV;
/*    */     this.f = paramgq;
/*    */   }
/*    */   
/*    */   public fr a(long paramLong) {
/*    */     paramLong = g ^ paramLong;
/*    */     long l = paramLong ^ 0x18BADEFEDD3DL;
/*    */     int i = (int)((paramLong ^ 0x75439A02721DL) >>> 32L), j = (int)((paramLong ^ 0x75439A02721DL) << 32L >>> 32L);
/*    */     paramLong ^ 0x75439A02721DL;
/*    */     this.e.c(i, j);
/*    */     return this.f.a().a(this, l);
/*    */   }
/*    */   
/*    */   public void a(H paramH) {
/*    */     this.c.a(this.b, paramH);
/*    */   }
/*    */   
/*    */   public void f(long paramLong) {
/*    */     paramLong = g ^ paramLong;
/*    */     int i = (int)((paramLong ^ 0x53F746DB8963L) >>> 48L), j = (int)((paramLong ^ 0x53F746DB8963L) << 16L >>> 32L), k = (int)((paramLong ^ 0x53F746DB8963L) << 48L >>> 48L);
/*    */     paramLong ^ 0x53F746DB8963L;
/*    */     a(-1L, (short)i, j, true, k, true, null);
/*    */   }
/*    */   
/*    */   public void i(long paramLong) {
/*    */     paramLong = g ^ paramLong;
/*    */     long l = paramLong ^ 0xF71DF3383FAL;
/*    */     this.f.a().a(l);
/*    */   }
/*    */   
/*    */   public boolean a() {
/*    */     return this.d;
/*    */   }
/*    */   
/*    */   public void c(long paramLong) {
/*    */     paramLong = g ^ paramLong;
/*    */     int i = (int)((paramLong ^ 0x23BC5A123510L) >>> 32L), j = (int)((paramLong ^ 0x23BC5A123510L) << 32L >>> 48L), k = (int)((paramLong ^ 0x23BC5A123510L) << 48L >>> 48L);
/*    */     paramLong ^ 0x23BC5A123510L;
/*    */     long l = (paramLong ^ 0x69A33A883878L) >>> 16L;
/*    */     int m = (int)((paramLong ^ 0x69A33A883878L) << 48L >>> 48L);
/*    */     paramLong ^ 0x69A33A883878L;
/*    */     try {
/*    */       this.f.b(i, j, (char)k);
/*    */     } catch (IOException iOException) {
/*    */       this.c.a(this.b, iOException);
/*    */       a(l, (short)m, iOException);
/*    */       throw iOException;
/*    */     } 
/*    */   }
/*    */   
/*    */   public void d(long paramLong) {
/*    */     paramLong = g ^ paramLong;
/*    */     long l = paramLong ^ 0x5CECD1D97636L;
/*    */     this.f.c(l);
/*    */   }
/*    */   
/*    */   public el a() {
/*    */     return this.f.a();
/*    */   }
/*    */   
/*    */   public d2 a(H paramH, long paramLong) {
/*    */     paramLong = g ^ paramLong;
/*    */     long l1 = paramLong ^ 0x2930E37327C8L, l2 = paramLong ^ 0x5270CB4029C6L, l3 = paramLong ^ 0x6BC684AF2C83L, l4 = paramLong ^ 0x7510697DD74FL;
/*    */     int i = (int)((paramLong ^ 0x5EC27765E3CFL) >>> 48L), j = (int)((paramLong ^ 0x5EC27765E3CFL) << 16L >>> 48L), k = (int)((paramLong ^ 0x5EC27765E3CFL) << 32L >>> 32L);
/*    */     paramLong ^ 0x5EC27765E3CFL;
/*    */     long l5 = (paramLong ^ 0x20A29CCFCFADL) >>> 16L;
/*    */     int m = (int)((paramLong ^ 0x20A29CCFCFADL) << 48L >>> 48L);
/*    */     paramLong ^ 0x20A29CCFCFADL;
/*    */     try {
/*    */       this.c.e(this.b);
/*    */       String str = paramH.a(l3, h);
/*    */       long l = this.f.a(l1, paramH);
/*    */       hp hp = this.f.a(l4, paramH);
/*    */       gv gv = new gv(l2, this, hp, l);
/*    */       return new dQ(str, l, ds.a((short)i, gv, (char)j, k));
/*    */     } catch (IOException iOException) {}
/*    */     this.c.b(this.b, iOException);
/*    */     a(l5, (short)m, iOException);
/*    */     throw iOException;
/*    */   }
/*    */   
/*    */   public void b(long paramLong) {
/*    */     paramLong = g ^ paramLong;
/*    */     long l = paramLong ^ 0x5C073FAD5B45L;
/*    */     this.e.a(this, l, true, false, (IOException)null);
/*    */   }
/*    */   
/*    */   public void e(long paramLong) {
/*    */     paramLong = g ^ paramLong;
/*    */     long l1 = paramLong ^ 0x28C480AD0A09L, l2 = (paramLong ^ 0x71FFC9DD6427L) >>> 16L;
/*    */     int i = (int)((paramLong ^ 0x71FFC9DD6427L) << 48L >>> 48L);
/*    */     paramLong ^ 0x71FFC9DD6427L;
/*    */     try {
/*    */       this.f.a(l1);
/*    */     } catch (IOException iOException) {
/*    */       this.c.a(this.b, iOException);
/*    */       a(l2, (short)i, iOException);
/*    */       throw iOException;
/*    */     } 
/*    */   }
/*    */   
/*    */   public void g(long paramLong) {
/*    */     paramLong = g ^ paramLong;
/*    */     int i = (int)((paramLong ^ 0x53512026CDBDL) >>> 32L), j = (int)((paramLong ^ 0x53512026CDBDL) << 32L >>> 32L);
/*    */     paramLong ^ 0x53512026CDBDL;
/*    */     this.e.c(i, j);
/*    */   }
/*    */   
/*    */   @Nullable
/*    */   IOException a(long paramLong, short paramShort, int paramInt1, boolean paramBoolean1, int paramInt2, boolean paramBoolean2, @Nullable IOException paramIOException) {
/*    */     // Byte code:
/*    */     //   0: iload_3
/*    */     //   1: i2l
/*    */     //   2: bipush #48
/*    */     //   4: lshl
/*    */     //   5: iload #4
/*    */     //   7: i2l
/*    */     //   8: bipush #32
/*    */     //   10: lshl
/*    */     //   11: bipush #16
/*    */     //   13: lushr
/*    */     //   14: lor
/*    */     //   15: iload #6
/*    */     //   17: i2l
/*    */     //   18: bipush #48
/*    */     //   20: lshl
/*    */     //   21: bipush #48
/*    */     //   23: lushr
/*    */     //   24: lor
/*    */     //   25: getstatic me/konsolas/aac/ec.g : J
/*    */     //   28: lxor
/*    */     //   29: lstore #9
/*    */     //   31: lload #9
/*    */     //   33: dup2
/*    */     //   34: ldc2_w 79560981822441
/*    */     //   37: lxor
/*    */     //   38: lstore #11
/*    */     //   40: dup2
/*    */     //   41: ldc2_w 70627882434975
/*    */     //   44: lxor
/*    */     //   45: dup2
/*    */     //   46: bipush #16
/*    */     //   48: lushr
/*    */     //   49: lstore #13
/*    */     //   51: dup2
/*    */     //   52: bipush #48
/*    */     //   54: lshl
/*    */     //   55: bipush #48
/*    */     //   57: lushr
/*    */     //   58: l2i
/*    */     //   59: istore #15
/*    */     //   61: pop2
/*    */     //   62: pop2
/*    */     //   63: ldc2_w 2341004011038340188
/*    */     //   66: lload #9
/*    */     //   68: <illegal opcode> w : (JJ)I
/*    */     //   73: istore #16
/*    */     //   75: aload #8
/*    */     //   77: ifnull -> 105
/*    */     //   80: aload_0
/*    */     //   81: lload #13
/*    */     //   83: iload #15
/*    */     //   85: i2s
/*    */     //   86: aload #8
/*    */     //   88: invokevirtual a : (JSLjava/io/IOException;)V
/*    */     //   91: goto -> 105
/*    */     //   94: ldc2_w 2333963362534045347
/*    */     //   97: lload #9
/*    */     //   99: <illegal opcode> w : (Ljava/lang/Exception;JJ)Ljava/lang/Exception;
/*    */     //   104: athrow
/*    */     //   105: iload #7
/*    */     //   107: iload #4
/*    */     //   109: iflt -> 217
/*    */     //   112: iload #16
/*    */     //   114: ifne -> 217
/*    */     //   117: ifeq -> 215
/*    */     //   120: goto -> 134
/*    */     //   123: ldc2_w 2333963362534045347
/*    */     //   126: lload #9
/*    */     //   128: <illegal opcode> w : (Ljava/lang/Exception;JJ)Ljava/lang/Exception;
/*    */     //   133: athrow
/*    */     //   134: iload_3
/*    */     //   135: iflt -> 201
/*    */     //   138: aload #8
/*    */     //   140: ifnull -> 189
/*    */     //   143: goto -> 157
/*    */     //   146: ldc2_w 2333963362534045347
/*    */     //   149: lload #9
/*    */     //   151: <illegal opcode> w : (Ljava/lang/Exception;JJ)Ljava/lang/Exception;
/*    */     //   156: athrow
/*    */     //   157: aload_0
/*    */     //   158: getfield c : Lme/konsolas/aac/cv;
/*    */     //   161: aload_0
/*    */     //   162: getfield b : Lme/konsolas/aac/gC;
/*    */     //   165: aload #8
/*    */     //   167: invokevirtual a : (Lme/konsolas/aac/gC;Ljava/io/IOException;)V
/*    */     //   170: iload #16
/*    */     //   172: ifeq -> 215
/*    */     //   175: goto -> 189
/*    */     //   178: ldc2_w 2333963362534045347
/*    */     //   181: lload #9
/*    */     //   183: <illegal opcode> w : (Ljava/lang/Exception;JJ)Ljava/lang/Exception;
/*    */     //   188: athrow
/*    */     //   189: aload_0
/*    */     //   190: getfield c : Lme/konsolas/aac/cv;
/*    */     //   193: aload_0
/*    */     //   194: getfield b : Lme/konsolas/aac/gC;
/*    */     //   197: lload_1
/*    */     //   198: invokevirtual b : (Lme/konsolas/aac/gC;J)V
/*    */     //   201: goto -> 215
/*    */     //   204: ldc2_w 2333963362534045347
/*    */     //   207: lload #9
/*    */     //   209: <illegal opcode> w : (Ljava/lang/Exception;JJ)Ljava/lang/Exception;
/*    */     //   214: athrow
/*    */     //   215: iload #5
/*    */     //   217: ifeq -> 306
/*    */     //   220: iload_3
/*    */     //   221: iflt -> 292
/*    */     //   224: aload #8
/*    */     //   226: ifnull -> 280
/*    */     //   229: goto -> 243
/*    */     //   232: ldc2_w 2333963362534045347
/*    */     //   235: lload #9
/*    */     //   237: <illegal opcode> w : (Ljava/lang/Exception;JJ)Ljava/lang/Exception;
/*    */     //   242: athrow
/*    */     //   243: aload_0
/*    */     //   244: iload #6
/*    */     //   246: iflt -> 307
/*    */     //   249: getfield c : Lme/konsolas/aac/cv;
/*    */     //   252: aload_0
/*    */     //   253: getfield b : Lme/konsolas/aac/gC;
/*    */     //   256: aload #8
/*    */     //   258: invokevirtual b : (Lme/konsolas/aac/gC;Ljava/io/IOException;)V
/*    */     //   261: iload #16
/*    */     //   263: ifeq -> 306
/*    */     //   266: goto -> 280
/*    */     //   269: ldc2_w 2333963362534045347
/*    */     //   272: lload #9
/*    */     //   274: <illegal opcode> w : (Ljava/lang/Exception;JJ)Ljava/lang/Exception;
/*    */     //   279: athrow
/*    */     //   280: aload_0
/*    */     //   281: getfield c : Lme/konsolas/aac/cv;
/*    */     //   284: aload_0
/*    */     //   285: getfield b : Lme/konsolas/aac/gC;
/*    */     //   288: lload_1
/*    */     //   289: invokevirtual a : (Lme/konsolas/aac/gC;J)V
/*    */     //   292: goto -> 306
/*    */     //   295: ldc2_w 2333963362534045347
/*    */     //   298: lload #9
/*    */     //   300: <illegal opcode> w : (Ljava/lang/Exception;JJ)Ljava/lang/Exception;
/*    */     //   305: athrow
/*    */     //   306: aload_0
/*    */     //   307: getfield e : Lme/konsolas/aac/fO;
/*    */     //   310: aload_0
/*    */     //   311: lload #11
/*    */     //   313: iload #7
/*    */     //   315: iload #5
/*    */     //   317: aload #8
/*    */     //   319: invokevirtual a : (Lme/konsolas/aac/ec;JZZLjava/io/IOException;)Ljava/io/IOException;
/*    */     //   322: areturn
/*    */     // Line number table:
/*    */     //   Java source line number -> byte code offset
/*    */     //   #63	-> 75
/*    */     //   #73	-> 80
/*    */     //   #77	-> 105
/*    */     //   #36	-> 134
/*    */     //   #80	-> 157
/*    */     //   #58	-> 189
/*    */     //   #68	-> 215
/*    */     //   #13	-> 220
/*    */     //   #70	-> 243
/*    */     //   #8	-> 280
/*    */     //   #21	-> 306
/*    */     // Exception table:
/*    */     //   from	to	target	type
/*    */     //   75	91	94	aacinternal/v
/*    */     //   105	120	123	aacinternal/v
/*    */     //   117	143	146	aacinternal/v
/*    */     //   134	175	178	aacinternal/v
/*    */     //   157	201	204	aacinternal/v
/*    */     //   217	229	232	aacinternal/v
/*    */     //   220	266	269	aacinternal/v
/*    */     //   243	292	295	aacinternal/v
/*    */   }
/*    */   
/*    */   void a(long paramLong, short paramShort, IOException paramIOException) {
/*    */     long l1 = (paramLong << 16L | paramShort << 48L >>> 48L) ^ g, l2 = l1 ^ 0x17A24E640F37L;
/*    */     int i = (int)((l1 ^ 0x2BA3267FBE7EL) >>> 48L), j = (int)((l1 ^ 0x2BA3267FBE7EL) << 16L >>> 32L), k = (int)((l1 ^ 0x2BA3267FBE7EL) << 48L >>> 48L);
/*    */     l1 ^ 0x2BA3267FBE7EL;
/*    */     this.a.a(l2);
/*    */     this.f.a().a((short)i, j, (short)k, paramIOException);
/*    */   }
/*    */   
/*    */   public J a(long paramLong) {
/*    */     paramLong = g ^ paramLong;
/*    */     long l = paramLong ^ 0x4C96B070482FL;
/*    */     return this.f.a(l);
/*    */   }
/*    */   
/*    */   public void a(long paramLong) {
/*    */     paramLong = g ^ paramLong;
/*    */     long l1 = paramLong ^ 0x155D2760E99DL, l2 = paramLong ^ 0x690A4A37E7FDL;
/*    */     this.f.c(l1);
/*    */     this.e.a(this, l2, true, true, (IOException)null);
/*    */   }
/*    */   
/*    */   @Nullable
/*    */   public T a(boolean paramBoolean, long paramLong) {
/*    */     // Byte code:
/*    */     //   0: getstatic me/konsolas/aac/ec.g : J
/*    */     //   3: lload_2
/*    */     //   4: lxor
/*    */     //   5: lstore_2
/*    */     //   6: lload_2
/*    */     //   7: dup2
/*    */     //   8: ldc2_w 34384182453279
/*    */     //   11: lxor
/*    */     //   12: dup2
/*    */     //   13: bipush #32
/*    */     //   15: lushr
/*    */     //   16: l2i
/*    */     //   17: istore #4
/*    */     //   19: dup2
/*    */     //   20: bipush #32
/*    */     //   22: lshl
/*    */     //   23: bipush #48
/*    */     //   25: lushr
/*    */     //   26: l2i
/*    */     //   27: istore #5
/*    */     //   29: dup2
/*    */     //   30: bipush #48
/*    */     //   32: lshl
/*    */     //   33: bipush #48
/*    */     //   35: lushr
/*    */     //   36: l2i
/*    */     //   37: istore #6
/*    */     //   39: pop2
/*    */     //   40: dup2
/*    */     //   41: ldc2_w 56893561926833
/*    */     //   44: lxor
/*    */     //   45: dup2
/*    */     //   46: bipush #16
/*    */     //   48: lushr
/*    */     //   49: lstore #7
/*    */     //   51: dup2
/*    */     //   52: bipush #48
/*    */     //   54: lshl
/*    */     //   55: bipush #48
/*    */     //   57: lushr
/*    */     //   58: l2i
/*    */     //   59: istore #9
/*    */     //   61: pop2
/*    */     //   62: pop2
/*    */     //   63: ldc2_w 6148144926084301170
/*    */     //   66: lload_2
/*    */     //   67: <illegal opcode> w : (JJ)I
/*    */     //   72: istore #10
/*    */     //   74: aload_0
/*    */     //   75: getfield f : Lme/konsolas/aac/gq;
/*    */     //   78: iload #4
/*    */     //   80: iload_1
/*    */     //   81: iload #5
/*    */     //   83: i2c
/*    */     //   84: iload #6
/*    */     //   86: invokeinterface a : (IZCI)Lme/konsolas/aac/T;
/*    */     //   91: astore #11
/*    */     //   93: aload #11
/*    */     //   95: iload #10
/*    */     //   97: ifne -> 140
/*    */     //   100: ifnull -> 138
/*    */     //   103: goto -> 116
/*    */     //   106: ldc2_w 6146732675488695181
/*    */     //   109: lload_2
/*    */     //   110: <illegal opcode> w : (Ljava/lang/Exception;JJ)Ljava/lang/Exception;
/*    */     //   115: athrow
/*    */     //   116: getstatic me/konsolas/aac/dJ.a : Lme/konsolas/aac/dJ;
/*    */     //   119: aload #11
/*    */     //   121: aload_0
/*    */     //   122: invokevirtual a : (Lme/konsolas/aac/T;Lme/konsolas/aac/ec;)V
/*    */     //   125: goto -> 138
/*    */     //   128: ldc2_w 6146732675488695181
/*    */     //   131: lload_2
/*    */     //   132: <illegal opcode> w : (Ljava/lang/Exception;JJ)Ljava/lang/Exception;
/*    */     //   137: athrow
/*    */     //   138: aload #11
/*    */     //   140: areturn
/*    */     //   141: astore #11
/*    */     //   143: aload_0
/*    */     //   144: getfield c : Lme/konsolas/aac/cv;
/*    */     //   147: aload_0
/*    */     //   148: getfield b : Lme/konsolas/aac/gC;
/*    */     //   151: aload #11
/*    */     //   153: invokevirtual b : (Lme/konsolas/aac/gC;Ljava/io/IOException;)V
/*    */     //   156: aload_0
/*    */     //   157: lload #7
/*    */     //   159: iload #9
/*    */     //   161: i2s
/*    */     //   162: aload #11
/*    */     //   164: invokevirtual a : (JSLjava/io/IOException;)V
/*    */     //   167: aload #11
/*    */     //   169: athrow
/*    */     // Line number table:
/*    */     //   Java source line number -> byte code offset
/*    */     //   #82	-> 74
/*    */     //   #29	-> 93
/*    */     //   #47	-> 116
/*    */     //   #45	-> 138
/*    */     //   #69	-> 141
/*    */     //   #60	-> 143
/*    */     //   #41	-> 156
/*    */     //   #85	-> 167
/*    */     // Exception table:
/*    */     //   from	to	target	type
/*    */     //   74	140	141	java/io/IOException
/*    */     //   93	103	106	java/io/IOException
/*    */     //   100	125	128	java/io/IOException
/*    */   }
/*    */   
/*    */   public void h() {
/*    */     this.c.a(this.b);
/*    */   }
/*    */   
/*    */   public gp a(long paramLong, s params, boolean paramBoolean) {
/*    */     paramLong = g ^ paramLong;
/*    */     long l1 = paramLong ^ 0x5355D4466065L;
/*    */     int i = (int)((paramLong ^ 0x12495434207FL) >>> 48L);
/*    */     long l2 = (paramLong ^ 0x12495434207FL) << 16L >>> 16L;
/*    */     paramLong ^ 0x12495434207FL;
/*    */     long l3 = paramLong ^ 0x39FC9872D8C0L;
/*    */     this.d = paramBoolean;
/*    */     long l4 = params.a().a(l1);
/*    */     this.c.c(this.b);
/*    */     gp gp = this.f.a(params, l4, l3);
/*    */     return new lJ((short)i, this, l2, gp, l4);
/*    */   }
/*    */   
/*    */   static {
/*    */     long l = g ^ 0x14747DDAADC9L;
/*    */     "艮㦭皎刂胪郎奷꒘?딜骝꧘Ᶎ맼Ɇ?쟍띙 㟋".toCharArray()[12] = (char)("艮㦭皎刂胪郎奷꒘?딜骝꧘Ᶎ맼Ɇ?쟍띙 㟋".toCharArray()[12] ^ 0x2330);
/*    */     "쭐芴㖆⢜".toCharArray()[0] = (char)("쭐芴㖆⢜".toCharArray()[0] ^ 0xF32);
/*    */     (new byte[8])[0] = (byte)(int)(l >>> 56L);
/*    */     for (byte b = 1; b < 8; b++)
/*    */       (new byte[8])[b] = (byte)(int)(l << b * 8 >>> 56L); 
/*    */     Cipher cipher;
/*    */     (cipher = Cipher.getInstance(dP$dt.X("艮㦭皎刂胪郎奷꒘?딜骝꧘Ᶎ맼Ɇ?쟍띙 㟋".toCharArray(), (short)28780, false, true))).init(2, SecretKeyFactory.getInstance(dP$dt.X("쭐芴㖆⢜".toCharArray(), (short)26183, true, false)).generateSecret(new DESKeySpec(new byte[8])), new IvParameterSpec(new byte[8]));
/*    */     "ἠ?ኬ狣梳텅릀↬ﭔ䁨ꕌ䋗瀩㏇≅撚Ⱂ".toCharArray()[3] = (char)("ἠ?ኬ狣梳텅릀↬ﭔ䁨ꕌ䋗瀩㏇≅撚Ⱂ".toCharArray()[3] ^ 0x1C19);
/*    */   }
/*    */   
/*    */   private static Exception a(Exception paramException) {
/*    */     return paramException;
/*    */   }
/*    */   
/*    */   private static String a(byte[] paramArrayOfbyte) {
/*    */     byte b1 = 0;
/*    */     int i;
/*    */     char[] arrayOfChar = new char[i = paramArrayOfbyte.length];
/*    */     for (byte b2 = 0; b2 < i; b2++) {
/*    */       int j;
/*    */       if ((j = 0xFF & paramArrayOfbyte[b2]) < 192) {
/*    */         arrayOfChar[b1++] = (char)j;
/*    */       } else if (j < 224) {
/*    */         char c = (char)((char)(j & 0x1F) << 6);
/*    */         j = paramArrayOfbyte[++b2];
/*    */         c = (char)(c | (char)(j & 0x3F));
/*    */         arrayOfChar[b1++] = c;
/*    */       } else if (b2 < i - 2) {
/*    */         char c = (char)((char)(j & 0xF) << 12);
/*    */         j = paramArrayOfbyte[++b2];
/*    */         c = (char)(c | (char)(j & 0x3F) << 6);
/*    */         j = paramArrayOfbyte[++b2];
/*    */         c = (char)(c | (char)(j & 0x3F));
/*    */         arrayOfChar[b1++] = c;
/*    */       } 
/*    */     } 
/*    */     return new String(arrayOfChar, 0, b1);
/*    */   } }


/* Location:              C:\Users\BukkitBypass\Desktop\MatrixAC\AAC\AAC-spigot-5.2.0.jar!\me\konsolas\aac\ec.class
 * Java compiler version: 8 (52.0)
 * JD-Core Version:       1.1.3
 */