/*    */ package me.konsolas.aac;public enum ei { public static final ei LILY_PAD; public static final ei SKULL; public static final ei GRAY_DYE; public static final ei LIME_DYE; public static final ei BONE_MEAL; public static final ei BOOK_AND_QUILL; public static final ei GREY_GLASS_PANE; public static final ei COMMAND_BLOCK; public static final ei CLOCK; public static final ei GREEN_STAINED_CLAY; public static final ei GRAY_STAINED_CLAY; public static final ei FARMLAND; public static final ei PISTON_BASE;
/*    */   public static final ei PISTON_STICKY_BASE;
/*    */   public static final ei PISTON_EXTENSION;
/*    */   public static final ei PISTON_MOVING;
/*    */   public static final ei COBWEB;
/*    */   
/*    */   public ItemStack a() {
/*  8 */     return this.b.get();
/*    */   }
/*    */   public static final ei FIREWORK; public static final Set TRAPDOORS; public static final Set SPAWN_EGGS; public static final Set BEDS; public static final Set SHULKER_BOXES; public static final Set CHESTS; public static final Set WATER; public static final Set LAVA; public static final Set ICE; public static final Set CARPET; public static final Set HONEY; public static final Set INTERACTABLE; private Supplier b; private Material c; private static final long d; private static final String[] e; private static final String[] f; private static final Map g;
/*    */   public Material a() {
/* 12 */     return this.c;
/*    */   }
/*    */   
/*    */   static {
/*    */     // Byte code:
/*    */     //   0: ldc2_w 5396507158006330320
/*    */     //   3: ldc2_w 4823286340207878636
/*    */     //   6: invokestatic lookup : ()Ljava/lang/invoke/MethodHandles$Lookup;
/*    */     //   9: invokevirtual lookupClass : ()Ljava/lang/Class;
/*    */     //   12: invokestatic a : (JJLjava/lang/Object;)Lme/konsolas/aac/na;
/*    */     //   15: ldc2_w 77894786330506
/*    */     //   18: invokeinterface a : (J)J
/*    */     //   23: putstatic me/konsolas/aac/ei.d : J
/*    */     //   26: getstatic me/konsolas/aac/ei.d : J
/*    */     //   29: ldc2_w 40921973552241
/*    */     //   32: lxor
/*    */     //   33: lstore #9
/*    */     //   35: lload #9
/*    */     //   37: dup2
/*    */     //   38: ldc2_w 28253285863011
/*    */     //   41: lxor
/*    */     //   42: lstore #11
/*    */     //   44: dup2
/*    */     //   45: ldc2_w 17456491481486
/*    */     //   48: lxor
/*    */     //   49: dup2
/*    */     //   50: bipush #48
/*    */     //   52: lushr
/*    */     //   53: l2i
/*    */     //   54: istore #13
/*    */     //   56: dup2
/*    */     //   57: bipush #16
/*    */     //   59: lshl
/*    */     //   60: bipush #32
/*    */     //   62: lushr
/*    */     //   63: l2i
/*    */     //   64: istore #14
/*    */     //   66: dup2
/*    */     //   67: bipush #48
/*    */     //   69: lshl
/*    */     //   70: bipush #48
/*    */     //   72: lushr
/*    */     //   73: l2i
/*    */     //   74: istore #15
/*    */     //   76: pop2
/*    */     //   77: pop2
/*    */     //   78: new java/util/HashMap
/*    */     //   81: dup
/*    */     //   82: bipush #13
/*    */     //   84: invokespecial <init> : (I)V
/*    */     //   87: putstatic me/konsolas/aac/ei.g : Ljava/util/Map;
/*    */     //   90: ldc_w 'ᨾ☽婘座꼢ጎ헧镥栍슩訏䪻䱗왌쏖뀩쀋餑꺕膓㜠'
/*    */     //   93: invokevirtual toCharArray : ()[C
/*    */     //   96: dup
/*    */     //   97: dup
/*    */     //   98: iconst_2
/*    */     //   99: dup_x1
/*    */     //   100: caload
/*    */     //   101: sipush #28229
/*    */     //   104: ixor
/*    */     //   105: i2c
/*    */     //   106: castore
/*    */     //   107: sipush #4134
/*    */     //   110: iconst_1
/*    */     //   111: iconst_3
/*    */     //   112: invokestatic A : (Ljava/lang/Object;SZI)Ljava/lang/String;
/*    */     //   115: invokestatic getInstance : (Ljava/lang/String;)Ljavax/crypto/Cipher;
/*    */     //   118: dup
/*    */     //   119: astore_0
/*    */     //   120: iconst_2
/*    */     //   121: ldc_w 'ꩅ붵밪㸭'
/*    */     //   124: invokevirtual toCharArray : ()[C
/*    */     //   127: dup
/*    */     //   128: dup
/*    */     //   129: iconst_1
/*    */     //   130: dup_x1
/*    */     //   131: caload
/*    */     //   132: sipush #25206
/*    */     //   135: ixor
/*    */     //   136: i2c
/*    */     //   137: castore
/*    */     //   138: sipush #664
/*    */     //   141: iconst_1
/*    */     //   142: iconst_4
/*    */     //   143: invokestatic A : (Ljava/lang/Object;SZI)Ljava/lang/String;
/*    */     //   146: invokestatic getInstance : (Ljava/lang/String;)Ljavax/crypto/SecretKeyFactory;
/*    */     //   149: bipush #8
/*    */     //   151: newarray byte
/*    */     //   153: dup
/*    */     //   154: iconst_0
/*    */     //   155: lload #9
/*    */     //   157: bipush #56
/*    */     //   159: lushr
/*    */     //   160: l2i
/*    */     //   161: i2b
/*    */     //   162: bastore
/*    */     //   163: iconst_1
/*    */     //   164: istore_1
/*    */     //   165: iload_1
/*    */     //   166: bipush #8
/*    */     //   168: if_icmpge -> 192
/*    */     //   171: dup
/*    */     //   172: iload_1
/*    */     //   173: lload #9
/*    */     //   175: iload_1
/*    */     //   176: bipush #8
/*    */     //   178: imul
/*    */     //   179: lshl
/*    */     //   180: bipush #56
/*    */     //   182: lushr
/*    */     //   183: l2i
/*    */     //   184: i2b
/*    */     //   185: bastore
/*    */     //   186: iinc #1, 1
/*    */     //   189: goto -> 165
/*    */     //   192: new javax/crypto/spec/DESKeySpec
/*    */     //   195: dup_x1
/*    */     //   196: swap
/*    */     //   197: invokespecial <init> : ([B)V
/*    */     //   200: invokevirtual generateSecret : (Ljava/security/spec/KeySpec;)Ljavax/crypto/SecretKey;
/*    */     //   203: new javax/crypto/spec/IvParameterSpec
/*    */     //   206: dup
/*    */     //   207: bipush #8
/*    */     //   209: newarray byte
/*    */     //   211: invokespecial <init> : ([B)V
/*    */     //   214: invokevirtual init : (ILjava/security/Key;Ljava/security/spec/AlgorithmParameterSpec;)V
/*    */     //   217: bipush #66
/*    */     //   219: anewarray java/lang/String
/*    */     //   222: astore #7
/*    */     //   224: iconst_0
/*    */     //   225: istore #5
/*    */     //   227: ldc_w '忮??빩໨?ۣ媁ꚳ㞰荌䫡糹늬褈焊䝓⯶庱?郎諼䓦뒇陹橦웚?풮殐퐆邐廾豒롓쿉쒑॔悔쥷㳪윩ᾦ藽ど₟䋴ﯙ뗈魷㼖⊚荋⊼Ⲟ?萎۟؏ឲჲ㐽膸蜥未趲꽡핮喵켍뤋웒쮼鼚䀚Ꟑᵗ瑑ీ譣﾿꺒奞굟怫䛺ಃ䪋⧿ᆉ鏙䖆袴ၨ䨅㜯天㨄ㆥ㭄볥菞㚎珳ᆲ䷯䪿腫ꑨ쐮ﯟ߹໾专㌻鍔䨢みꬂ읅控Ⲧ铬䈥䎎态쳠챮揳嬊Ɛ曟䂫㽝駄Ⱊ∭꯲㹁麽砦쓎굻⼫掁ぱדּ奐窣퀀䕧痼톄殏羭䬔鈤?䋇봦왔ꎸ連鰽吧渇Š휞감윘頪⣐횦䤨儍陼ᔃ餝ﮒꮽ䐛뷓珹易鹘쩁ꭳ莋ⴌꁱ㒄뎢ꃋ汣곐㢊ᕸȭ츈鋵鿳ⳕ罊췞㡃릹໋洤渣븰᫓䙚뾾﫪틞컰넳዁룯ꀫ⤬솗䐆氹㣜폓蕖쥨镾庰觼봋씝죭잵䔒ﲤᕣ騑ꭼ렸㲐猂댮ḷ㙻ꉍ핼?蛴벤Ջ쪀着贼鍈⢄켼ቚ숄琬阮ꥐﵪヌ췣覢￐容⯥ᡎ啧꽧ٺ븞㣠䏛베횃䱧㲺콊㸸ᬬ䶏땵⠿羍䖡肥긤噷ࣣ஽?耙✆嬢얣襅雊違ᙦೌ銒楽ꨂ뭤ࡴᖜ躓庋輀겕쇎봆뙍鑒ట칢ᐍ꒢槙皩韚ŭꋭ똖旴Ҥ䥵铚臝젪儽弓ꇲ巽㛗璂Ꝙ쓒⡕徬Ꭿ䷆跊姍䬟ꇳ鏏箓ؿ啵ᖣ⼠슔꤆뀸付抬朕ퟌ㕳邑爃둆?꘦醝頒郩馴僛糖脨⬑懤載鴭隤㐉靌仺礈퀶뱙멏첇?괦骶䤀茟⮘凶燥㟤௸؎㺵宨㡌醴꥜‿๸嫁犌쮌昫튣ᑕ퐮ꝑᨺᴏ궹嵰뉐ꫳ懏ጬ咱洯⬠?쫭抹겪ㅢ帨퀛韤飰騏笳䋞衳콗缎็潃擲횮蓺둌扖좞贁搡寿媻觗?䍍痨浂泀漁㥩雘蘆㧊Ṿﶀ쁎ㆹ⏊茬ꣻ뿘?릭⯔ߞ瀛ᨉ峄魾鼓慠퐎ơ瘗摧㔤蚰?쬗꿺ັ秨пҒ纐⫙쯜ᕰܯᵥ坨皃쒍줌ᒕ黭袡?諥猶ூ䡦艝齼蚨뤩㠠?졛惜퐍㧴齛駒塊㣁칵텣骬﬈殺ꞹᓒ⮞㤯᳞踚?ﶫ㟏鄖塖蠕䠥䎅僂谉斝ᩀӄ땩虉ﱶ̣痏묜꼖揘늠䞳?먥낐?罌瞵?ꢧ젲즉淪꿏鈤鐵媑咙鞂뜉驸ᓑﵔꐗ૙랭ㄿ뵸벥?暬ᴖ窛ᦂ첶㗇ᷣ젰ᗵ羄쳗뼂ᇏ뚣챮㺦Ꞛ䯒ꝓ౉ၡ垰憆ϙ雰蚬暍芧畀㽂銆咼뭙婶稪땙?揆㭜霿␍姚䵻ㅣᣫ灭吱⚔莗?鿆㽸벶잼ꕖ阊䡐꾸✚䳡앟滇࿹浾졶ﵴ㓜㣆튫蠌௹譭뜥깔⋷狭ộ隑捼瞚뭕嫷ᛔ驡ᕑ嗽큭ɘ鮟ꀁ꧃ᬳꥋ䪭ˤ槫朄?랮䰟聋鳝磠酰?梬ﳪ몡풙ࣺ寚猧ﺶ鷷ⴺ⷏橀䰫ﱥ⏟ឆ딆⛕縒瓹浹礮⣩ᬻ笖틧흸䍹덟㻛峦彃贙踍?哋첊魑?⹹떩엷犀眭砮뾑兑㹑踑靚굆㰚撱፱퐒䬕蒶튞㈖媛贱>䈗￦Ӡ?ㆼꥧ쪗㪀趄傃퀾涀欢蜁쥩맮鍵拭헣♷䉉鐈ﺾ廛酂波䭲ꭙ蜦痏뗚톶य㫌ꑄᢤ풜ᇠ鑭풁삽뵺Ａ穙鞓?ᷡ乃煩槎ᛆ焯栄末ﰍ喕葓篢跿胼辤䳏違뱒蜐ꊝ⩫밀踿࠼鶡馸Ӻꙵ붑鳆㹑¸될褼烮靎ﲒ뉁⛠ꍈ獼͘Ⲥ㋰႓횦鿙樿葬孤뷗饆賧苌嶽紸ꘌ趿雟췙犽葺∊༷桓ᗯ䏽㯆ౕ긂ܞ㹸다柗뱊辽襔觻変碜ꚬㄓ쥭흼촺䈤辪␮氓ᎍૂ췠搹镸쾥鞋ﳵ㮥?è្䫓섓㖃贲𢡊ꝍ韇酫䠔嬰⤭鯽墇輄툱믎䥐믝扽젭䓮吔ꂤ毶㍔懲嘶?裄읨瓫⚕﻽윎⼨㱕瀯⌎枴䮑쑥믁悄ᝊ矧㾂ᘓ殡恟匐?׈푁ﵨ㥬䔚펨Ĭ煣Ὲꢲ㿂ོﳈ໥㱂倅≢?墇ጐ兀ᝁ봫央ꦻഩᗁရ悞䣬蕡⻵遻㑏實㶈喇ꣿ霯혆쁇릩⽩⭄솧賫딳婩芯䎞麽饊놡艡♶￢窆桶难欲瞃䤇⪉䆽Հᖾ￡頋澹?Ꙙ櫝考틑䫚蚳猄雗䞳幀訮馄哅ద괆鈕Ꞿᩕļ갦明᯶箸⇭鵞䐧˃민♷ꕌ镖騮䩦ꎄ▃ᨇ악್ప╇?薓誙녛艚儃菝魛鵯漋Ⓜ뗌鄶먩ꘫ纍倻鎕漹?럭櫛⒚䶈侪л죆2㾭绑꽈衑狼埃얭펟೮?㝘¡檂捱㮘੄蘺ﲹ騱倉⸀鷝꧌ீ镉춬襭辡咲ᇄ꠵ꙸ圤﷒‷믺겙뺓㹛纅ᶄାᰆ鸘樂煲孭讷?㫎ࡠ떱썖ࠒ鋤뉆ԏ?㗔䎻䅴境瑤ⷎ?딛䀓稀⨰ᣇꙁ搀筈쏅ძ㪦㏈ת맒?䏉硃顿勷ત䔲၃嘺쪾畬乤꩛⁧﨎⽔䐫늗㢰몱돶Ѓ⫤ⱍ퉣荮畳㶘囕蘞ꃮ罦栉썑襓쏬㨝㟉㺋衢꧓伭츎㯭龁㿀剛랱?䒦耺ࢱ半땙◲뼬䶯挶髇뜑珗⛷퍉墧ᙗ?顳孜徎靈ᚔ쨕꟦᭥︂䇔ｵ엌㩶᳤ꤲ꘩꾷㌌縃첞菊ﲜ뢝䠯䂉允큢绔멶䠫釫焻ᒟﶷ祐樠柜㲎?琢ᾳ䂾䑃昀굳Უ쩓둬憃ᇲ㲠଩陰招?앷뗠ꗃ谇Ⱪ㏴ꌧશ?䴔ꆡ꿑ᨂ⪬揪㐯㥐ᣥ兜ﴏ一ᛢ䓐甛蕰좸ᆝ聰縮罹⾻豹큀뵺ꏂ㽸繲䝷捂ꚫ姇꭪劔靮ള덵딵ꛈ㓴頃졖墪訛賮ﱧ譑Ꝁ뷫楐ₛ⼶惸ﮚ撰曬傋?朣ꡰꥆ妚뙩耗?ጱ鹘⎠散ᤣ辰♽냿居૰㣳俧걖㏟?꺄瑙丯ꐒ姫裟烧䫰캞폶樲퀦磔捦煤㒊⚄៼ស롐쇋㝢䨴馋ܪ㻩澛䮰脖袃槥?귘ὑꈑ躝㽠㢃电楅癬ཥ寡쁲袰고එ軦顄꽨?昿퉕遨釺Ⱈ⹞鈟ঠ촘걾핍ᔌ権⽧唐گ뻋㕉뛺ট㯌⫺鿦ᾉ⍩餴攟謹?域䈯꿗빙瞻羉땳፦㸻쨄╱?궰늫?뗪鹋傿长傪ꯆ왜葶괆ꕁʀ庳缛돵롖?岌逧돠凞厎왋峿節쪏㧉饶뫾答咚흷虄鮄슌?쏣咁ꆔ뉁▅⠲硓䈹髾烟?♽铿鹢?ʃ?鸠䃚寴ꂖᨩ텲∧ꠉꡌ঎ꯘ볦ए톥埫⑘辯?ષ?䴇綶朳祮遲臶ᳩ魻藩睰샏촐ᣛ躼옿㕍Ì烻舄ﻼមⱑ郐憛鮲瑦덡⷟脚?縜皰⤌걾莴雹н▝✞攢堊徭ࢌ䍒鶘詇᭎縤?㏣뜲쨄丼뽙⹐钥릧풮ힸ␣볐衸邃?䇷䩱鴥툑톷㗴᩿⪂谚퉖縠'
/*    */     //   230: invokevirtual toCharArray : ()[C
/*    */     //   233: dup
/*    */     //   234: dup
/*    */     //   235: bipush #48
/*    */     //   237: dup_x1
/*    */     //   238: caload
/*    */     //   239: sipush #26240
/*    */     //   242: ixor
/*    */     //   243: i2c
/*    */     //   244: castore
/*    */     //   245: sipush #8104
/*    */     //   248: iconst_0
/*    */     //   249: iconst_3
/*    */     //   250: invokestatic A : (Ljava/lang/Object;SZI)Ljava/lang/String;
/*    */     //   253: dup
/*    */     //   254: astore #4
/*    */     //   256: invokevirtual length : ()I
/*    */     //   259: istore #6
/*    */     //   261: bipush #32
/*    */     //   263: istore_3
/*    */     //   264: iconst_m1
/*    */     //   265: istore_2
/*    */     //   266: iinc #2, 1
/*    */     //   269: aload #4
/*    */     //   271: iload_2
/*    */     //   272: dup
/*    */     //   273: iload_3
/*    */     //   274: iadd
/*    */     //   275: invokevirtual substring : (II)Ljava/lang/String;
/*    */     //   278: iconst_m1
/*    */     //   279: goto -> 413
/*    */     //   282: aload #7
/*    */     //   284: swap
/*    */     //   285: iload #5
/*    */     //   287: iinc #5, 1
/*    */     //   290: swap
/*    */     //   291: aastore
/*    */     //   292: iload_2
/*    */     //   293: iload_3
/*    */     //   294: iadd
/*    */     //   295: dup
/*    */     //   296: istore_2
/*    */     //   297: iload #6
/*    */     //   299: if_icmpge -> 312
/*    */     //   302: aload #4
/*    */     //   304: iload_2
/*    */     //   305: invokevirtual charAt : (I)C
/*    */     //   308: istore_3
/*    */     //   309: goto -> 266
/*    */     //   312: ldc_w '忯䲝竵ﬅ㯫陿屑鸎襜춚敽朰賖誠骰쒽?惚쩯녍볷㰇盯숲䡟똘뇈誕ᇕ제ᗾ頤뵛텥ઑ㞺썷ᱤ苕﹉⾀뇏甴嫈'
/*    */     //   315: invokevirtual toCharArray : ()[C
/*    */     //   318: dup
/*    */     //   319: dup
/*    */     //   320: bipush #29
/*    */     //   322: dup_x1
/*    */     //   323: caload
/*    */     //   324: sipush #1241
/*    */     //   327: ixor
/*    */     //   328: i2c
/*    */     //   329: castore
/*    */     //   330: sipush #19613
/*    */     //   333: iconst_0
/*    */     //   334: iconst_4
/*    */     //   335: invokestatic A : (Ljava/lang/Object;SZI)Ljava/lang/String;
/*    */     //   338: dup
/*    */     //   339: astore #4
/*    */     //   341: invokevirtual length : ()I
/*    */     //   344: istore #6
/*    */     //   346: bipush #16
/*    */     //   348: istore_3
/*    */     //   349: iconst_m1
/*    */     //   350: istore_2
/*    */     //   351: iinc #2, 1
/*    */     //   354: aload #4
/*    */     //   356: iload_2
/*    */     //   357: dup
/*    */     //   358: iload_3
/*    */     //   359: iadd
/*    */     //   360: invokevirtual substring : (II)Ljava/lang/String;
/*    */     //   363: iconst_0
/*    */     //   364: goto -> 413
/*    */     //   367: aload #7
/*    */     //   369: swap
/*    */     //   370: iload #5
/*    */     //   372: iinc #5, 1
/*    */     //   375: swap
/*    */     //   376: aastore
/*    */     //   377: iload_2
/*    */     //   378: iload_3
/*    */     //   379: iadd
/*    */     //   380: dup
/*    */     //   381: istore_2
/*    */     //   382: iload #6
/*    */     //   384: if_icmpge -> 397
/*    */     //   387: aload #4
/*    */     //   389: iload_2
/*    */     //   390: invokevirtual charAt : (I)C
/*    */     //   393: istore_3
/*    */     //   394: goto -> 351
/*    */     //   397: aload #7
/*    */     //   399: putstatic me/konsolas/aac/ei.e : [Ljava/lang/String;
/*    */     //   402: bipush #66
/*    */     //   404: anewarray java/lang/String
/*    */     //   407: putstatic me/konsolas/aac/ei.f : [Ljava/lang/String;
/*    */     //   410: goto -> 476
/*    */     //   413: swap
/*    */     //   414: ldc_w '臵篒ﴥ൭擜袲컰쏿띰䮝'
/*    */     //   417: invokevirtual toCharArray : ()[C
/*    */     //   420: dup
/*    */     //   421: dup
/*    */     //   422: bipush #7
/*    */     //   424: dup_x1
/*    */     //   425: caload
/*    */     //   426: sipush #8547
/*    */     //   429: ixor
/*    */     //   430: i2c
/*    */     //   431: castore
/*    */     //   432: sipush #1133
/*    */     //   435: iconst_0
/*    */     //   436: iconst_4
/*    */     //   437: invokestatic A : (Ljava/lang/Object;SZI)Ljava/lang/String;
/*    */     //   440: invokevirtual getBytes : (Ljava/lang/String;)[B
/*    */     //   443: aload_0
/*    */     //   444: swap
/*    */     //   445: invokevirtual doFinal : ([B)[B
/*    */     //   448: astore #8
/*    */     //   450: aload #8
/*    */     //   452: invokestatic a : ([B)Ljava/lang/String;
/*    */     //   455: invokevirtual intern : ()Ljava/lang/String;
/*    */     //   458: swap
/*    */     //   459: tableswitch default -> 282, 0 -> 367
/*    */     //   476: new me/konsolas/aac/ei
/*    */     //   479: dup
/*    */     //   480: sipush #18337
/*    */     //   483: ldc2_w 8933450608484644809
/*    */     //   486: lload #9
/*    */     //   488: lxor
/*    */     //   489: <illegal opcode> l : (IJ)Ljava/lang/String;
/*    */     //   494: iconst_0
/*    */     //   495: lload #11
/*    */     //   497: sipush #22400
/*    */     //   500: ldc2_w 7955606503130851269
/*    */     //   503: lload #9
/*    */     //   505: lxor
/*    */     //   506: <illegal opcode> l : (IJ)Ljava/lang/String;
/*    */     //   511: sipush #30735
/*    */     //   514: ldc2_w 2485198861380208724
/*    */     //   517: lload #9
/*    */     //   519: lxor
/*    */     //   520: <illegal opcode> l : (IJ)Ljava/lang/String;
/*    */     //   525: invokespecial <init> : (Ljava/lang/String;IJLjava/lang/String;Ljava/lang/String;)V
/*    */     //   528: putstatic me/konsolas/aac/ei.LILY_PAD : Lme/konsolas/aac/ei;
/*    */     //   531: new me/konsolas/aac/ei
/*    */     //   534: dup
/*    */     //   535: sipush #24772
/*    */     //   538: ldc2_w 7368525697570361534
/*    */     //   541: lload #9
/*    */     //   543: lxor
/*    */     //   544: <illegal opcode> l : (IJ)Ljava/lang/String;
/*    */     //   549: iconst_1
/*    */     //   550: lload #11
/*    */     //   552: sipush #31373
/*    */     //   555: ldc2_w 1433900719292074722
/*    */     //   558: lload #9
/*    */     //   560: lxor
/*    */     //   561: <illegal opcode> l : (IJ)Ljava/lang/String;
/*    */     //   566: sipush #8413
/*    */     //   569: ldc2_w 7859311108507439253
/*    */     //   572: lload #9
/*    */     //   574: lxor
/*    */     //   575: <illegal opcode> l : (IJ)Ljava/lang/String;
/*    */     //   580: invokespecial <init> : (Ljava/lang/String;IJLjava/lang/String;Ljava/lang/String;)V
/*    */     //   583: putstatic me/konsolas/aac/ei.SKULL : Lme/konsolas/aac/ei;
/*    */     //   586: new me/konsolas/aac/ei
/*    */     //   589: dup
/*    */     //   590: sipush #31839
/*    */     //   593: ldc2_w 4491705124532046892
/*    */     //   596: lload #9
/*    */     //   598: lxor
/*    */     //   599: <illegal opcode> l : (IJ)Ljava/lang/String;
/*    */     //   604: iconst_2
/*    */     //   605: <illegal opcode> get : ()Ljava/util/function/Supplier;
/*    */     //   610: iload #13
/*    */     //   612: i2s
/*    */     //   613: swap
/*    */     //   614: iload #14
/*    */     //   616: swap
/*    */     //   617: <illegal opcode> get : ()Ljava/util/function/Supplier;
/*    */     //   622: iload #15
/*    */     //   624: i2s
/*    */     //   625: swap
/*    */     //   626: invokespecial <init> : (Ljava/lang/String;ISILjava/util/function/Supplier;SLjava/util/function/Supplier;)V
/*    */     //   629: putstatic me/konsolas/aac/ei.GRAY_DYE : Lme/konsolas/aac/ei;
/*    */     //   632: new me/konsolas/aac/ei
/*    */     //   635: dup
/*    */     //   636: sipush #20364
/*    */     //   639: ldc2_w 1277338616225333212
/*    */     //   642: lload #9
/*    */     //   644: lxor
/*    */     //   645: <illegal opcode> l : (IJ)Ljava/lang/String;
/*    */     //   650: iconst_3
/*    */     //   651: <illegal opcode> get : ()Ljava/util/function/Supplier;
/*    */     //   656: iload #13
/*    */     //   658: i2s
/*    */     //   659: swap
/*    */     //   660: iload #14
/*    */     //   662: swap
/*    */     //   663: <illegal opcode> get : ()Ljava/util/function/Supplier;
/*    */     //   668: iload #15
/*    */     //   670: i2s
/*    */     //   671: swap
/*    */     //   672: invokespecial <init> : (Ljava/lang/String;ISILjava/util/function/Supplier;SLjava/util/function/Supplier;)V
/*    */     //   675: putstatic me/konsolas/aac/ei.LIME_DYE : Lme/konsolas/aac/ei;
/*    */     //   678: new me/konsolas/aac/ei
/*    */     //   681: dup
/*    */     //   682: sipush #11683
/*    */     //   685: ldc2_w 1698659083409137107
/*    */     //   688: lload #9
/*    */     //   690: lxor
/*    */     //   691: <illegal opcode> l : (IJ)Ljava/lang/String;
/*    */     //   696: iconst_4
/*    */     //   697: <illegal opcode> get : ()Ljava/util/function/Supplier;
/*    */     //   702: iload #13
/*    */     //   704: i2s
/*    */     //   705: swap
/*    */     //   706: iload #14
/*    */     //   708: swap
/*    */     //   709: <illegal opcode> get : ()Ljava/util/function/Supplier;
/*    */     //   714: iload #15
/*    */     //   716: i2s
/*    */     //   717: swap
/*    */     //   718: invokespecial <init> : (Ljava/lang/String;ISILjava/util/function/Supplier;SLjava/util/function/Supplier;)V
/*    */     //   721: putstatic me/konsolas/aac/ei.BONE_MEAL : Lme/konsolas/aac/ei;
/*    */     //   724: new me/konsolas/aac/ei
/*    */     //   727: dup
/*    */     //   728: sipush #26493
/*    */     //   731: ldc2_w 3776685748551472955
/*    */     //   734: lload #9
/*    */     //   736: lxor
/*    */     //   737: <illegal opcode> l : (IJ)Ljava/lang/String;
/*    */     //   742: iconst_5
/*    */     //   743: lload #11
/*    */     //   745: sipush #5730
/*    */     //   748: ldc2_w 8118494640863716889
/*    */     //   751: lload #9
/*    */     //   753: lxor
/*    */     //   754: <illegal opcode> l : (IJ)Ljava/lang/String;
/*    */     //   759: sipush #5116
/*    */     //   762: ldc2_w 8736447472375276477
/*    */     //   765: lload #9
/*    */     //   767: lxor
/*    */     //   768: <illegal opcode> l : (IJ)Ljava/lang/String;
/*    */     //   773: invokespecial <init> : (Ljava/lang/String;IJLjava/lang/String;Ljava/lang/String;)V
/*    */     //   776: putstatic me/konsolas/aac/ei.BOOK_AND_QUILL : Lme/konsolas/aac/ei;
/*    */     //   779: new me/konsolas/aac/ei
/*    */     //   782: dup
/*    */     //   783: sipush #30909
/*    */     //   786: ldc2_w 926291169759807697
/*    */     //   789: lload #9
/*    */     //   791: lxor
/*    */     //   792: <illegal opcode> l : (IJ)Ljava/lang/String;
/*    */     //   797: bipush #6
/*    */     //   799: lload #11
/*    */     //   801: sipush #4071
/*    */     //   804: ldc2_w 6606402748235431815
/*    */     //   807: lload #9
/*    */     //   809: lxor
/*    */     //   810: <illegal opcode> l : (IJ)Ljava/lang/String;
/*    */     //   815: sipush #10701
/*    */     //   818: ldc2_w 4289933002344962482
/*    */     //   821: lload #9
/*    */     //   823: lxor
/*    */     //   824: <illegal opcode> l : (IJ)Ljava/lang/String;
/*    */     //   829: invokespecial <init> : (Ljava/lang/String;IJLjava/lang/String;Ljava/lang/String;)V
/*    */     //   832: putstatic me/konsolas/aac/ei.GREY_GLASS_PANE : Lme/konsolas/aac/ei;
/*    */     //   835: new me/konsolas/aac/ei
/*    */     //   838: dup
/*    */     //   839: sipush #29290
/*    */     //   842: ldc2_w 965202547429753384
/*    */     //   845: lload #9
/*    */     //   847: lxor
/*    */     //   848: <illegal opcode> l : (IJ)Ljava/lang/String;
/*    */     //   853: bipush #7
/*    */     //   855: lload #11
/*    */     //   857: sipush #14569
/*    */     //   860: ldc2_w 949628136084670612
/*    */     //   863: lload #9
/*    */     //   865: lxor
/*    */     //   866: <illegal opcode> l : (IJ)Ljava/lang/String;
/*    */     //   871: sipush #4358
/*    */     //   874: ldc2_w 3305390669248700772
/*    */     //   877: lload #9
/*    */     //   879: lxor
/*    */     //   880: <illegal opcode> l : (IJ)Ljava/lang/String;
/*    */     //   885: invokespecial <init> : (Ljava/lang/String;IJLjava/lang/String;Ljava/lang/String;)V
/*    */     //   888: putstatic me/konsolas/aac/ei.COMMAND_BLOCK : Lme/konsolas/aac/ei;
/*    */     //   891: new me/konsolas/aac/ei
/*    */     //   894: dup
/*    */     //   895: sipush #17289
/*    */     //   898: ldc2_w 444595891146912647
/*    */     //   901: lload #9
/*    */     //   903: lxor
/*    */     //   904: <illegal opcode> l : (IJ)Ljava/lang/String;
/*    */     //   909: bipush #8
/*    */     //   911: lload #11
/*    */     //   913: sipush #1912
/*    */     //   916: ldc2_w 3560775271508948764
/*    */     //   919: lload #9
/*    */     //   921: lxor
/*    */     //   922: <illegal opcode> l : (IJ)Ljava/lang/String;
/*    */     //   927: sipush #24621
/*    */     //   930: ldc2_w 4567061992736837708
/*    */     //   933: lload #9
/*    */     //   935: lxor
/*    */     //   936: <illegal opcode> l : (IJ)Ljava/lang/String;
/*    */     //   941: invokespecial <init> : (Ljava/lang/String;IJLjava/lang/String;Ljava/lang/String;)V
/*    */     //   944: putstatic me/konsolas/aac/ei.CLOCK : Lme/konsolas/aac/ei;
/*    */     //   947: new me/konsolas/aac/ei
/*    */     //   950: dup
/*    */     //   951: sipush #9281
/*    */     //   954: ldc2_w 3895280319539385355
/*    */     //   957: lload #9
/*    */     //   959: lxor
/*    */     //   960: <illegal opcode> l : (IJ)Ljava/lang/String;
/*    */     //   965: bipush #9
/*    */     //   967: <illegal opcode> get : ()Ljava/util/function/Supplier;
/*    */     //   972: iload #13
/*    */     //   974: i2s
/*    */     //   975: swap
/*    */     //   976: iload #14
/*    */     //   978: swap
/*    */     //   979: <illegal opcode> get : ()Ljava/util/function/Supplier;
/*    */     //   984: iload #15
/*    */     //   986: i2s
/*    */     //   987: swap
/*    */     //   988: invokespecial <init> : (Ljava/lang/String;ISILjava/util/function/Supplier;SLjava/util/function/Supplier;)V
/*    */     //   991: putstatic me/konsolas/aac/ei.GREEN_STAINED_CLAY : Lme/konsolas/aac/ei;
/*    */     //   994: new me/konsolas/aac/ei
/*    */     //   997: dup
/*    */     //   998: sipush #17078
/*    */     //   1001: ldc2_w 8469205575958000328
/*    */     //   1004: lload #9
/*    */     //   1006: lxor
/*    */     //   1007: <illegal opcode> l : (IJ)Ljava/lang/String;
/*    */     //   1012: bipush #10
/*    */     //   1014: <illegal opcode> get : ()Ljava/util/function/Supplier;
/*    */     //   1019: iload #13
/*    */     //   1021: i2s
/*    */     //   1022: swap
/*    */     //   1023: iload #14
/*    */     //   1025: swap
/*    */     //   1026: <illegal opcode> get : ()Ljava/util/function/Supplier;
/*    */     //   1031: iload #15
/*    */     //   1033: i2s
/*    */     //   1034: swap
/*    */     //   1035: invokespecial <init> : (Ljava/lang/String;ISILjava/util/function/Supplier;SLjava/util/function/Supplier;)V
/*    */     //   1038: putstatic me/konsolas/aac/ei.GRAY_STAINED_CLAY : Lme/konsolas/aac/ei;
/*    */     //   1041: new me/konsolas/aac/ei
/*    */     //   1044: dup
/*    */     //   1045: sipush #17672
/*    */     //   1048: ldc2_w 4679464994501981505
/*    */     //   1051: lload #9
/*    */     //   1053: lxor
/*    */     //   1054: <illegal opcode> l : (IJ)Ljava/lang/String;
/*    */     //   1059: bipush #11
/*    */     //   1061: lload #11
/*    */     //   1063: sipush #13451
/*    */     //   1066: ldc2_w 3453348542761960684
/*    */     //   1069: lload #9
/*    */     //   1071: lxor
/*    */     //   1072: <illegal opcode> l : (IJ)Ljava/lang/String;
/*    */     //   1077: sipush #25850
/*    */     //   1080: ldc2_w 3973335402054571189
/*    */     //   1083: lload #9
/*    */     //   1085: lxor
/*    */     //   1086: <illegal opcode> l : (IJ)Ljava/lang/String;
/*    */     //   1091: invokespecial <init> : (Ljava/lang/String;IJLjava/lang/String;Ljava/lang/String;)V
/*    */     //   1094: putstatic me/konsolas/aac/ei.FARMLAND : Lme/konsolas/aac/ei;
/*    */     //   1097: new me/konsolas/aac/ei
/*    */     //   1100: dup
/*    */     //   1101: sipush #17596
/*    */     //   1104: ldc2_w 5419800091533735109
/*    */     //   1107: lload #9
/*    */     //   1109: lxor
/*    */     //   1110: <illegal opcode> l : (IJ)Ljava/lang/String;
/*    */     //   1115: bipush #12
/*    */     //   1117: lload #11
/*    */     //   1119: sipush #14923
/*    */     //   1122: ldc2_w 1518628680018070054
/*    */     //   1125: lload #9
/*    */     //   1127: lxor
/*    */     //   1128: <illegal opcode> l : (IJ)Ljava/lang/String;
/*    */     //   1133: sipush #284
/*    */     //   1136: ldc2_w 1714112446534463821
/*    */     //   1139: lload #9
/*    */     //   1141: lxor
/*    */     //   1142: <illegal opcode> l : (IJ)Ljava/lang/String;
/*    */     //   1147: invokespecial <init> : (Ljava/lang/String;IJLjava/lang/String;Ljava/lang/String;)V
/*    */     //   1150: putstatic me/konsolas/aac/ei.PISTON_BASE : Lme/konsolas/aac/ei;
/*    */     //   1153: new me/konsolas/aac/ei
/*    */     //   1156: dup
/*    */     //   1157: sipush #31100
/*    */     //   1160: ldc2_w 8391742729378875673
/*    */     //   1163: lload #9
/*    */     //   1165: lxor
/*    */     //   1166: <illegal opcode> l : (IJ)Ljava/lang/String;
/*    */     //   1171: bipush #13
/*    */     //   1173: lload #11
/*    */     //   1175: sipush #29925
/*    */     //   1178: ldc2_w 1981378273376912566
/*    */     //   1181: lload #9
/*    */     //   1183: lxor
/*    */     //   1184: <illegal opcode> l : (IJ)Ljava/lang/String;
/*    */     //   1189: sipush #31301
/*    */     //   1192: ldc2_w 5396176935042042420
/*    */     //   1195: lload #9
/*    */     //   1197: lxor
/*    */     //   1198: <illegal opcode> l : (IJ)Ljava/lang/String;
/*    */     //   1203: invokespecial <init> : (Ljava/lang/String;IJLjava/lang/String;Ljava/lang/String;)V
/*    */     //   1206: putstatic me/konsolas/aac/ei.PISTON_STICKY_BASE : Lme/konsolas/aac/ei;
/*    */     //   1209: new me/konsolas/aac/ei
/*    */     //   1212: dup
/*    */     //   1213: sipush #9528
/*    */     //   1216: ldc2_w 6977534176130438479
/*    */     //   1219: lload #9
/*    */     //   1221: lxor
/*    */     //   1222: <illegal opcode> l : (IJ)Ljava/lang/String;
/*    */     //   1227: bipush #14
/*    */     //   1229: lload #11
/*    */     //   1231: sipush #2345
/*    */     //   1234: ldc2_w 2781524835758782839
/*    */     //   1237: lload #9
/*    */     //   1239: lxor
/*    */     //   1240: <illegal opcode> l : (IJ)Ljava/lang/String;
/*    */     //   1245: sipush #5670
/*    */     //   1248: ldc2_w 8136526841746990693
/*    */     //   1251: lload #9
/*    */     //   1253: lxor
/*    */     //   1254: <illegal opcode> l : (IJ)Ljava/lang/String;
/*    */     //   1259: invokespecial <init> : (Ljava/lang/String;IJLjava/lang/String;Ljava/lang/String;)V
/*    */     //   1262: putstatic me/konsolas/aac/ei.PISTON_EXTENSION : Lme/konsolas/aac/ei;
/*    */     //   1265: new me/konsolas/aac/ei
/*    */     //   1268: dup
/*    */     //   1269: sipush #15308
/*    */     //   1272: ldc2_w 4357087012662938533
/*    */     //   1275: lload #9
/*    */     //   1277: lxor
/*    */     //   1278: <illegal opcode> l : (IJ)Ljava/lang/String;
/*    */     //   1283: bipush #15
/*    */     //   1285: lload #11
/*    */     //   1287: sipush #5053
/*    */     //   1290: ldc2_w 9195701203393749991
/*    */     //   1293: lload #9
/*    */     //   1295: lxor
/*    */     //   1296: <illegal opcode> l : (IJ)Ljava/lang/String;
/*    */     //   1301: sipush #29767
/*    */     //   1304: ldc2_w 2197335853401293887
/*    */     //   1307: lload #9
/*    */     //   1309: lxor
/*    */     //   1310: <illegal opcode> l : (IJ)Ljava/lang/String;
/*    */     //   1315: invokespecial <init> : (Ljava/lang/String;IJLjava/lang/String;Ljava/lang/String;)V
/*    */     //   1318: putstatic me/konsolas/aac/ei.PISTON_MOVING : Lme/konsolas/aac/ei;
/*    */     //   1321: new me/konsolas/aac/ei
/*    */     //   1324: dup
/*    */     //   1325: sipush #15899
/*    */     //   1328: ldc2_w 840688616454753865
/*    */     //   1331: lload #9
/*    */     //   1333: lxor
/*    */     //   1334: <illegal opcode> l : (IJ)Ljava/lang/String;
/*    */     //   1339: bipush #16
/*    */     //   1341: lload #11
/*    */     //   1343: sipush #6652
/*    */     //   1346: ldc2_w 1349413017702541718
/*    */     //   1349: lload #9
/*    */     //   1351: lxor
/*    */     //   1352: <illegal opcode> l : (IJ)Ljava/lang/String;
/*    */     //   1357: sipush #22265
/*    */     //   1360: ldc2_w 5575679524824213158
/*    */     //   1363: lload #9
/*    */     //   1365: lxor
/*    */     //   1366: <illegal opcode> l : (IJ)Ljava/lang/String;
/*    */     //   1371: invokespecial <init> : (Ljava/lang/String;IJLjava/lang/String;Ljava/lang/String;)V
/*    */     //   1374: putstatic me/konsolas/aac/ei.COBWEB : Lme/konsolas/aac/ei;
/*    */     //   1377: new me/konsolas/aac/ei
/*    */     //   1380: dup
/*    */     //   1381: sipush #9717
/*    */     //   1384: ldc2_w 3866303919903511936
/*    */     //   1387: lload #9
/*    */     //   1389: lxor
/*    */     //   1390: <illegal opcode> l : (IJ)Ljava/lang/String;
/*    */     //   1395: bipush #17
/*    */     //   1397: lload #11
/*    */     //   1399: sipush #2787
/*    */     //   1402: ldc2_w 5889146372950080151
/*    */     //   1405: lload #9
/*    */     //   1407: lxor
/*    */     //   1408: <illegal opcode> l : (IJ)Ljava/lang/String;
/*    */     //   1413: sipush #10648
/*    */     //   1416: ldc2_w 716215925074074107
/*    */     //   1419: lload #9
/*    */     //   1421: lxor
/*    */     //   1422: <illegal opcode> l : (IJ)Ljava/lang/String;
/*    */     //   1427: invokespecial <init> : (Ljava/lang/String;IJLjava/lang/String;Ljava/lang/String;)V
/*    */     //   1430: putstatic me/konsolas/aac/ei.FIREWORK : Lme/konsolas/aac/ei;
/*    */     //   1433: invokestatic a : ()[Lme/konsolas/aac/ei;
/*    */     //   1436: putstatic me/konsolas/aac/ei.a : [Lme/konsolas/aac/ei;
/*    */     //   1439: ldc org/bukkit/Material
/*    */     //   1441: invokestatic noneOf : (Ljava/lang/Class;)Ljava/util/EnumSet;
/*    */     //   1444: astore #16
/*    */     //   1446: ldc org/bukkit/Material
/*    */     //   1448: invokestatic noneOf : (Ljava/lang/Class;)Ljava/util/EnumSet;
/*    */     //   1451: astore #17
/*    */     //   1453: ldc org/bukkit/Material
/*    */     //   1455: invokestatic noneOf : (Ljava/lang/Class;)Ljava/util/EnumSet;
/*    */     //   1458: astore #18
/*    */     //   1460: ldc org/bukkit/Material
/*    */     //   1462: invokestatic noneOf : (Ljava/lang/Class;)Ljava/util/EnumSet;
/*    */     //   1465: astore #19
/*    */     //   1467: ldc org/bukkit/Material
/*    */     //   1469: invokestatic noneOf : (Ljava/lang/Class;)Ljava/util/EnumSet;
/*    */     //   1472: astore #20
/*    */     //   1474: ldc org/bukkit/Material
/*    */     //   1476: invokestatic noneOf : (Ljava/lang/Class;)Ljava/util/EnumSet;
/*    */     //   1479: astore #21
/*    */     //   1481: ldc org/bukkit/Material
/*    */     //   1483: invokestatic noneOf : (Ljava/lang/Class;)Ljava/util/EnumSet;
/*    */     //   1486: astore #22
/*    */     //   1488: ldc org/bukkit/Material
/*    */     //   1490: invokestatic noneOf : (Ljava/lang/Class;)Ljava/util/EnumSet;
/*    */     //   1493: astore #23
/*    */     //   1495: ldc org/bukkit/Material
/*    */     //   1497: invokestatic noneOf : (Ljava/lang/Class;)Ljava/util/EnumSet;
/*    */     //   1500: astore #24
/*    */     //   1502: ldc org/bukkit/Material
/*    */     //   1504: invokestatic noneOf : (Ljava/lang/Class;)Ljava/util/EnumSet;
/*    */     //   1507: astore #25
/*    */     //   1509: ldc org/bukkit/Material
/*    */     //   1511: invokestatic noneOf : (Ljava/lang/Class;)Ljava/util/EnumSet;
/*    */     //   1514: astore #26
/*    */     //   1516: invokestatic values : ()[Lorg/bukkit/Material;
/*    */     //   1519: astore #27
/*    */     //   1521: aload #27
/*    */     //   1523: arraylength
/*    */     //   1524: istore #28
/*    */     //   1526: iconst_0
/*    */     //   1527: istore #29
/*    */     //   1529: iload #29
/*    */     //   1531: iload #28
/*    */     //   1533: if_icmpge -> 2198
/*    */     //   1536: aload #27
/*    */     //   1538: iload #29
/*    */     //   1540: aaload
/*    */     //   1541: astore #30
/*    */     //   1543: aload #30
/*    */     //   1545: invokevirtual name : ()Ljava/lang/String;
/*    */     //   1548: sipush #1745
/*    */     //   1551: ldc2_w 3041564852451751574
/*    */     //   1554: lload #9
/*    */     //   1556: lxor
/*    */     //   1557: <illegal opcode> l : (IJ)Ljava/lang/String;
/*    */     //   1562: invokevirtual contains : (Ljava/lang/CharSequence;)Z
/*    */     //   1565: ifne -> 1607
/*    */     //   1568: aload #30
/*    */     //   1570: invokevirtual name : ()Ljava/lang/String;
/*    */     //   1573: sipush #7331
/*    */     //   1576: ldc2_w 2814964241875545288
/*    */     //   1579: lload #9
/*    */     //   1581: lxor
/*    */     //   1582: <illegal opcode> l : (IJ)Ljava/lang/String;
/*    */     //   1587: invokevirtual contains : (Ljava/lang/CharSequence;)Z
/*    */     //   1590: ifeq -> 1631
/*    */     //   1593: goto -> 1607
/*    */     //   1596: ldc2_w -48798380848623920
/*    */     //   1599: lload #9
/*    */     //   1601: <illegal opcode> w : (Laacinternal/v;JJ)Laacinternal/v;
/*    */     //   1606: athrow
/*    */     //   1607: aload #16
/*    */     //   1609: aload #30
/*    */     //   1611: invokeinterface add : (Ljava/lang/Object;)Z
/*    */     //   1616: pop
/*    */     //   1617: goto -> 1631
/*    */     //   1620: ldc2_w -48798380848623920
/*    */     //   1623: lload #9
/*    */     //   1625: <illegal opcode> w : (Laacinternal/v;JJ)Laacinternal/v;
/*    */     //   1630: athrow
/*    */     //   1631: aload #30
/*    */     //   1633: invokevirtual name : ()Ljava/lang/String;
/*    */     //   1636: sipush #1693
/*    */     //   1639: ldc2_w 7525743772645668545
/*    */     //   1642: lload #9
/*    */     //   1644: lxor
/*    */     //   1645: <illegal opcode> l : (IJ)Ljava/lang/String;
/*    */     //   1650: invokevirtual contains : (Ljava/lang/CharSequence;)Z
/*    */     //   1653: ifeq -> 1680
/*    */     //   1656: aload #17
/*    */     //   1658: aload #30
/*    */     //   1660: invokeinterface add : (Ljava/lang/Object;)Z
/*    */     //   1665: pop
/*    */     //   1666: goto -> 1680
/*    */     //   1669: ldc2_w -48798380848623920
/*    */     //   1672: lload #9
/*    */     //   1674: <illegal opcode> w : (Laacinternal/v;JJ)Laacinternal/v;
/*    */     //   1679: athrow
/*    */     //   1680: aload #30
/*    */     //   1682: invokevirtual name : ()Ljava/lang/String;
/*    */     //   1685: sipush #4640
/*    */     //   1688: ldc2_w 2838569934394499662
/*    */     //   1691: lload #9
/*    */     //   1693: lxor
/*    */     //   1694: <illegal opcode> l : (IJ)Ljava/lang/String;
/*    */     //   1699: invokevirtual contains : (Ljava/lang/CharSequence;)Z
/*    */     //   1702: ifeq -> 1729
/*    */     //   1705: aload #26
/*    */     //   1707: aload #30
/*    */     //   1709: invokeinterface add : (Ljava/lang/Object;)Z
/*    */     //   1714: pop
/*    */     //   1715: goto -> 1729
/*    */     //   1718: ldc2_w -48798380848623920
/*    */     //   1721: lload #9
/*    */     //   1723: <illegal opcode> w : (Laacinternal/v;JJ)Laacinternal/v;
/*    */     //   1728: athrow
/*    */     //   1729: aload #30
/*    */     //   1731: invokevirtual name : ()Ljava/lang/String;
/*    */     //   1734: sipush #24737
/*    */     //   1737: ldc2_w 5010738215633342679
/*    */     //   1740: lload #9
/*    */     //   1742: lxor
/*    */     //   1743: <illegal opcode> l : (IJ)Ljava/lang/String;
/*    */     //   1748: invokevirtual contains : (Ljava/lang/CharSequence;)Z
/*    */     //   1751: ifeq -> 1778
/*    */     //   1754: aload #26
/*    */     //   1756: aload #30
/*    */     //   1758: invokeinterface add : (Ljava/lang/Object;)Z
/*    */     //   1763: pop
/*    */     //   1764: goto -> 1778
/*    */     //   1767: ldc2_w -48798380848623920
/*    */     //   1770: lload #9
/*    */     //   1772: <illegal opcode> w : (Laacinternal/v;JJ)Laacinternal/v;
/*    */     //   1777: athrow
/*    */     //   1778: aload #30
/*    */     //   1780: invokevirtual name : ()Ljava/lang/String;
/*    */     //   1783: sipush #13054
/*    */     //   1786: ldc2_w 8443794583367713458
/*    */     //   1789: lload #9
/*    */     //   1791: lxor
/*    */     //   1792: <illegal opcode> l : (IJ)Ljava/lang/String;
/*    */     //   1797: invokevirtual contains : (Ljava/lang/CharSequence;)Z
/*    */     //   1800: ifeq -> 1849
/*    */     //   1803: aload #30
/*    */     //   1805: getstatic org/bukkit/Material.BEDROCK : Lorg/bukkit/Material;
/*    */     //   1808: if_acmpeq -> 1849
/*    */     //   1811: goto -> 1825
/*    */     //   1814: ldc2_w -48798380848623920
/*    */     //   1817: lload #9
/*    */     //   1819: <illegal opcode> w : (Laacinternal/v;JJ)Laacinternal/v;
/*    */     //   1824: athrow
/*    */     //   1825: aload #18
/*    */     //   1827: aload #30
/*    */     //   1829: invokeinterface add : (Ljava/lang/Object;)Z
/*    */     //   1834: pop
/*    */     //   1835: goto -> 1849
/*    */     //   1838: ldc2_w -48798380848623920
/*    */     //   1841: lload #9
/*    */     //   1843: <illegal opcode> w : (Laacinternal/v;JJ)Laacinternal/v;
/*    */     //   1848: athrow
/*    */     //   1849: aload #30
/*    */     //   1851: invokevirtual name : ()Ljava/lang/String;
/*    */     //   1854: sipush #30866
/*    */     //   1857: ldc2_w 3530451471160166617
/*    */     //   1860: lload #9
/*    */     //   1862: lxor
/*    */     //   1863: <illegal opcode> l : (IJ)Ljava/lang/String;
/*    */     //   1868: invokevirtual contains : (Ljava/lang/CharSequence;)Z
/*    */     //   1871: ifeq -> 1898
/*    */     //   1874: aload #19
/*    */     //   1876: aload #30
/*    */     //   1878: invokeinterface add : (Ljava/lang/Object;)Z
/*    */     //   1883: pop
/*    */     //   1884: goto -> 1898
/*    */     //   1887: ldc2_w -48798380848623920
/*    */     //   1890: lload #9
/*    */     //   1892: <illegal opcode> w : (Laacinternal/v;JJ)Laacinternal/v;
/*    */     //   1897: athrow
/*    */     //   1898: aload #30
/*    */     //   1900: invokevirtual name : ()Ljava/lang/String;
/*    */     //   1903: sipush #17701
/*    */     //   1906: ldc2_w 7005046265469334851
/*    */     //   1909: lload #9
/*    */     //   1911: lxor
/*    */     //   1912: <illegal opcode> l : (IJ)Ljava/lang/String;
/*    */     //   1917: invokevirtual endsWith : (Ljava/lang/String;)Z
/*    */     //   1920: ifeq -> 1947
/*    */     //   1923: aload #20
/*    */     //   1925: aload #30
/*    */     //   1927: invokeinterface add : (Ljava/lang/Object;)Z
/*    */     //   1932: pop
/*    */     //   1933: goto -> 1947
/*    */     //   1936: ldc2_w -48798380848623920
/*    */     //   1939: lload #9
/*    */     //   1941: <illegal opcode> w : (Laacinternal/v;JJ)Laacinternal/v;
/*    */     //   1946: athrow
/*    */     //   1947: aload #30
/*    */     //   1949: invokevirtual name : ()Ljava/lang/String;
/*    */     //   1952: sipush #31234
/*    */     //   1955: ldc2_w 4432474221052185200
/*    */     //   1958: lload #9
/*    */     //   1960: lxor
/*    */     //   1961: <illegal opcode> l : (IJ)Ljava/lang/String;
/*    */     //   1966: invokevirtual endsWith : (Ljava/lang/String;)Z
/*    */     //   1969: ifeq -> 1996
/*    */     //   1972: aload #21
/*    */     //   1974: aload #30
/*    */     //   1976: invokeinterface add : (Ljava/lang/Object;)Z
/*    */     //   1981: pop
/*    */     //   1982: goto -> 1996
/*    */     //   1985: ldc2_w -48798380848623920
/*    */     //   1988: lload #9
/*    */     //   1990: <illegal opcode> w : (Laacinternal/v;JJ)Laacinternal/v;
/*    */     //   1995: athrow
/*    */     //   1996: aload #30
/*    */     //   1998: invokevirtual name : ()Ljava/lang/String;
/*    */     //   2001: sipush #14016
/*    */     //   2004: ldc2_w 410379305391130269
/*    */     //   2007: lload #9
/*    */     //   2009: lxor
/*    */     //   2010: <illegal opcode> l : (IJ)Ljava/lang/String;
/*    */     //   2015: invokevirtual endsWith : (Ljava/lang/String;)Z
/*    */     //   2018: ifeq -> 2045
/*    */     //   2021: aload #22
/*    */     //   2023: aload #30
/*    */     //   2025: invokeinterface add : (Ljava/lang/Object;)Z
/*    */     //   2030: pop
/*    */     //   2031: goto -> 2045
/*    */     //   2034: ldc2_w -48798380848623920
/*    */     //   2037: lload #9
/*    */     //   2039: <illegal opcode> w : (Laacinternal/v;JJ)Laacinternal/v;
/*    */     //   2044: athrow
/*    */     //   2045: aload #30
/*    */     //   2047: invokevirtual name : ()Ljava/lang/String;
/*    */     //   2050: sipush #7182
/*    */     //   2053: ldc2_w 2862364289870081115
/*    */     //   2056: lload #9
/*    */     //   2058: lxor
/*    */     //   2059: <illegal opcode> l : (IJ)Ljava/lang/String;
/*    */     //   2064: invokevirtual endsWith : (Ljava/lang/String;)Z
/*    */     //   2067: ifeq -> 2094
/*    */     //   2070: aload #23
/*    */     //   2072: aload #30
/*    */     //   2074: invokeinterface add : (Ljava/lang/Object;)Z
/*    */     //   2079: pop
/*    */     //   2080: goto -> 2094
/*    */     //   2083: ldc2_w -48798380848623920
/*    */     //   2086: lload #9
/*    */     //   2088: <illegal opcode> w : (Laacinternal/v;JJ)Laacinternal/v;
/*    */     //   2093: athrow
/*    */     //   2094: aload #30
/*    */     //   2096: invokevirtual name : ()Ljava/lang/String;
/*    */     //   2099: sipush #16416
/*    */     //   2102: ldc2_w 2343384741335691383
/*    */     //   2105: lload #9
/*    */     //   2107: lxor
/*    */     //   2108: <illegal opcode> l : (IJ)Ljava/lang/String;
/*    */     //   2113: invokevirtual contains : (Ljava/lang/CharSequence;)Z
/*    */     //   2116: ifeq -> 2143
/*    */     //   2119: aload #24
/*    */     //   2121: aload #30
/*    */     //   2123: invokeinterface add : (Ljava/lang/Object;)Z
/*    */     //   2128: pop
/*    */     //   2129: goto -> 2143
/*    */     //   2132: ldc2_w -48798380848623920
/*    */     //   2135: lload #9
/*    */     //   2137: <illegal opcode> w : (Laacinternal/v;JJ)Laacinternal/v;
/*    */     //   2142: athrow
/*    */     //   2143: aload #30
/*    */     //   2145: invokevirtual name : ()Ljava/lang/String;
/*    */     //   2148: sipush #4998
/*    */     //   2151: ldc2_w 5020921229152068489
/*    */     //   2154: lload #9
/*    */     //   2156: lxor
/*    */     //   2157: <illegal opcode> l : (IJ)Ljava/lang/String;
/*    */     //   2162: invokevirtual contains : (Ljava/lang/CharSequence;)Z
/*    */     //   2165: ifeq -> 2192
/*    */     //   2168: aload #25
/*    */     //   2170: aload #30
/*    */     //   2172: invokeinterface add : (Ljava/lang/Object;)Z
/*    */     //   2177: pop
/*    */     //   2178: goto -> 2192
/*    */     //   2181: ldc2_w -48798380848623920
/*    */     //   2184: lload #9
/*    */     //   2186: <illegal opcode> w : (Laacinternal/v;JJ)Laacinternal/v;
/*    */     //   2191: athrow
/*    */     //   2192: iinc #29, 1
/*    */     //   2195: goto -> 1529
/*    */     //   2198: aload #16
/*    */     //   2200: invokestatic unmodifiableSet : (Ljava/util/Set;)Ljava/util/Set;
/*    */     //   2203: putstatic me/konsolas/aac/ei.TRAPDOORS : Ljava/util/Set;
/*    */     //   2206: aload #17
/*    */     //   2208: invokestatic unmodifiableSet : (Ljava/util/Set;)Ljava/util/Set;
/*    */     //   2211: putstatic me/konsolas/aac/ei.SPAWN_EGGS : Ljava/util/Set;
/*    */     //   2214: aload #18
/*    */     //   2216: invokestatic unmodifiableSet : (Ljava/util/Set;)Ljava/util/Set;
/*    */     //   2219: putstatic me/konsolas/aac/ei.BEDS : Ljava/util/Set;
/*    */     //   2222: aload #19
/*    */     //   2224: invokestatic unmodifiableSet : (Ljava/util/Set;)Ljava/util/Set;
/*    */     //   2227: putstatic me/konsolas/aac/ei.SHULKER_BOXES : Ljava/util/Set;
/*    */     //   2230: aload #20
/*    */     //   2232: invokestatic unmodifiableSet : (Ljava/util/Set;)Ljava/util/Set;
/*    */     //   2235: putstatic me/konsolas/aac/ei.CHESTS : Ljava/util/Set;
/*    */     //   2238: aload #21
/*    */     //   2240: invokestatic unmodifiableSet : (Ljava/util/Set;)Ljava/util/Set;
/*    */     //   2243: putstatic me/konsolas/aac/ei.WATER : Ljava/util/Set;
/*    */     //   2246: aload #22
/*    */     //   2248: invokestatic unmodifiableSet : (Ljava/util/Set;)Ljava/util/Set;
/*    */     //   2251: putstatic me/konsolas/aac/ei.LAVA : Ljava/util/Set;
/*    */     //   2254: aload #23
/*    */     //   2256: invokestatic unmodifiableSet : (Ljava/util/Set;)Ljava/util/Set;
/*    */     //   2259: putstatic me/konsolas/aac/ei.ICE : Ljava/util/Set;
/*    */     //   2262: aload #24
/*    */     //   2264: invokestatic unmodifiableSet : (Ljava/util/Set;)Ljava/util/Set;
/*    */     //   2267: putstatic me/konsolas/aac/ei.CARPET : Ljava/util/Set;
/*    */     //   2270: aload #25
/*    */     //   2272: invokestatic unmodifiableSet : (Ljava/util/Set;)Ljava/util/Set;
/*    */     //   2275: putstatic me/konsolas/aac/ei.HONEY : Ljava/util/Set;
/*    */     //   2278: aload #26
/*    */     //   2280: invokestatic unmodifiableSet : (Ljava/util/Set;)Ljava/util/Set;
/*    */     //   2283: putstatic me/konsolas/aac/ei.INTERACTABLE : Ljava/util/Set;
/*    */     //   2286: return
/*    */     // Line number table:
/*    */     //   Java source line number -> byte code offset
/*    */     //   #31	-> 476
/*    */     //   #33	-> 531
/*    */     //   #45	-> 586
/*    */     //   #47	-> 632
/*    */     //   #56	-> 678
/*    */     //   #16	-> 724
/*    */     //   #27	-> 779
/*    */     //   #54	-> 835
/*    */     //   #40	-> 891
/*    */     //   #25	-> 947
/*    */     //   #35	-> 994
/*    */     //   #10	-> 1041
/*    */     //   #61	-> 1097
/*    */     //   #1	-> 1153
/*    */     //   #13	-> 1209
/*    */     //   #80	-> 1265
/*    */     //   #46	-> 1321
/*    */     //   #11	-> 1377
/*    */     //   #55	-> 1433
/*    */     //   #72	-> 1439
/*    */     //   #44	-> 1446
/*    */     //   #57	-> 1453
/*    */     //   #6	-> 1460
/*    */     //   #5	-> 1467
/*    */     //   #52	-> 1474
/*    */     //   #67	-> 1481
/*    */     //   #18	-> 1488
/*    */     //   #74	-> 1495
/*    */     //   #3	-> 1502
/*    */     //   #29	-> 1509
/*    */     //   #79	-> 1516
/*    */     //   #19	-> 1543
/*    */     //   #39	-> 1607
/*    */     //   #21	-> 1631
/*    */     //   #20	-> 1680
/*    */     //   #82	-> 1729
/*    */     //   #34	-> 1778
/*    */     //   #24	-> 1849
/*    */     //   #81	-> 1898
/*    */     //   #60	-> 1947
/*    */     //   #38	-> 1996
/*    */     //   #43	-> 2045
/*    */     //   #65	-> 2094
/*    */     //   #26	-> 2143
/*    */     //   #66	-> 2192
/*    */     //   #36	-> 2198
/*    */     //   #41	-> 2206
/*    */     //   #51	-> 2214
/*    */     //   #70	-> 2222
/*    */     //   #58	-> 2230
/*    */     //   #76	-> 2238
/*    */     //   #2	-> 2246
/*    */     //   #62	-> 2254
/*    */     //   #42	-> 2262
/*    */     //   #7	-> 2270
/*    */     //   #71	-> 2278
/*    */     //   #68	-> 2286
/*    */     // Exception table:
/*    */     //   from	to	target	type
/*    */     //   1543	1593	1596	aacinternal/v
/*    */     //   1568	1617	1620	aacinternal/v
/*    */     //   1631	1666	1669	aacinternal/v
/*    */     //   1680	1715	1718	aacinternal/v
/*    */     //   1729	1764	1767	aacinternal/v
/*    */     //   1778	1811	1814	aacinternal/v
/*    */     //   1803	1835	1838	aacinternal/v
/*    */     //   1849	1884	1887	aacinternal/v
/*    */     //   1898	1933	1936	aacinternal/v
/*    */     //   1947	1982	1985	aacinternal/v
/*    */     //   1996	2031	2034	aacinternal/v
/*    */     //   2045	2080	2083	aacinternal/v
/*    */     //   2094	2129	2132	aacinternal/v
/*    */     //   2143	2178	2181	aacinternal/v
/*    */   }
/*    */   
/*    */   private static v a(v paramv) {
/*    */     return paramv;
/*    */   }
/*    */   
/*    */   private static String a(byte[] paramArrayOfbyte) {
/*    */     byte b1 = 0;
/*    */     int i;
/*    */     char[] arrayOfChar = new char[i = paramArrayOfbyte.length];
/*    */     for (byte b2 = 0; b2 < i; b2++) {
/*    */       int j;
/*    */       if ((j = 0xFF & paramArrayOfbyte[b2]) < 192) {
/*    */         arrayOfChar[b1++] = (char)j;
/*    */       } else if (j < 224) {
/*    */         char c = (char)((char)(j & 0x1F) << 6);
/*    */         j = paramArrayOfbyte[++b2];
/*    */         c = (char)(c | (char)(j & 0x3F));
/*    */         arrayOfChar[b1++] = c;
/*    */       } else if (b2 < i - 2) {
/*    */         char c = (char)((char)(j & 0xF) << 12);
/*    */         j = paramArrayOfbyte[++b2];
/*    */         c = (char)(c | (char)(j & 0x3F) << 6);
/*    */         j = paramArrayOfbyte[++b2];
/*    */         c = (char)(c | (char)(j & 0x3F));
/*    */         arrayOfChar[b1++] = c;
/*    */       } 
/*    */     } 
/*    */     return new String(arrayOfChar, 0, b1);
/*    */   }
/*    */   
/*    */   private static String a(int paramInt, long paramLong) {
/*    */     int i = paramInt ^ (int)(paramLong & 0x7FFFL) ^ 0x4FD2;
/*    */     if (f[i] == null) {
/*    */       Object[] arrayOfObject;
/*    */       try {
/*    */         Long long_ = Long.valueOf(Thread.currentThread().getId());
/*    */         arrayOfObject = (Object[])g.get(long_);
/*    */         if (arrayOfObject == null) {
/*    */           arrayOfObject = new Object[3];
/*    */           "畻㰮歂և⢸卍ږ䞑Ҕ塢ꝗ飉ᯜ凯甌萻੝瓗✛".toCharArray()[16] = (char)("畻㰮歂և⢸卍ږ䞑Ҕ塢ꝗ飉ᯜ凯甌萻੝瓗✛".toCharArray()[16] ^ 0x1A1A);
/*    */           arrayOfObject[0] = Cipher.getInstance(dP$dt.X("畻㰮歂և⢸卍ږ䞑Ҕ塢ꝗ飉ᯜ凯甌萻੝瓗✛".toCharArray(), (short)8800, false, false));
/*    */           "趢봇⚹".toCharArray()[2] = (char)("趢봇⚹".toCharArray()[2] ^ 0x45E6);
/*    */           arrayOfObject[1] = SecretKeyFactory.getInstance(dP$dt.X("趢봇⚹".toCharArray(), (short)20053, true, true));
/*    */           arrayOfObject[2] = new IvParameterSpec(new byte[8]);
/*    */           g.put(long_, arrayOfObject);
/*    */         } 
/*    */       } catch (Exception exception) {
/*    */         "偟悅숄㭌匈ｮḥ爂뿠茊晊㰊諗䥂얨ṷ࿎࿏".toCharArray()[2] = (char)("偟悅숄㭌匈ｮḥ爂뿠茊晊㰊諗䥂얨ṷ࿎࿏".toCharArray()[2] ^ 0x6C74);
/*    */         throw new RuntimeException(dP$dt.X("偟悅숄㭌匈ｮḥ爂뿠茊晊㰊諗䥂얨ṷ࿎࿏".toCharArray(), (short)28230, false, true), exception);
/*    */       } 
/*    */       byte[] arrayOfByte1 = new byte[8];
/*    */       arrayOfByte1[0] = (byte)(int)(paramLong >>> 56L);
/*    */       for (byte b = 1; b < 8; b++)
/*    */         arrayOfByte1[b] = (byte)(int)(paramLong << b * 8 >>> 56L); 
/*    */       DESKeySpec dESKeySpec = new DESKeySpec(arrayOfByte1);
/*    */       SecretKey secretKey = ((SecretKeyFactory)arrayOfObject[1]).generateSecret(dESKeySpec);
/*    */       ((Cipher)arrayOfObject[0]).init(2, secretKey, (IvParameterSpec)arrayOfObject[2]);
/*    */       "?⋓迕忲ꀊ걃쿷닱ᢑ".toCharArray()[2] = (char)("?⋓迕忲ꀊ걃쿷닱ᢑ".toCharArray()[2] ^ 0x601A);
/*    */       byte[] arrayOfByte2 = e[i].getBytes(dP$dt.X("?⋓迕忲ꀊ걃쿷닱ᢑ".toCharArray(), (short)1254, true, false));
/*    */       f[i] = a(((Cipher)arrayOfObject[0]).doFinal(arrayOfByte2));
/*    */     } 
/*    */     return f[i];
/*    */   }
/*    */   
/*    */   private static Object a(MethodHandles.Lookup paramLookup, MutableCallSite paramMutableCallSite, String paramString, Object[] paramArrayOfObject) {
/*    */     int i = ((Integer)paramArrayOfObject[0]).intValue();
/*    */     long l = ((Long)paramArrayOfObject[1]).longValue();
/*    */     String str = a(i, l);
/*    */     MethodHandle methodHandle = MethodHandles.constant(String.class, str);
/*    */     paramMutableCallSite.setTarget(MethodHandles.dropArguments(methodHandle, 0, new Class[] { int.class, long.class }));
/*    */     return str;
/*    */   }
/*    */   
/*    */   private static CallSite a(MethodHandles.Lookup paramLookup, String paramString, MethodType paramMethodType) {
/*    */     // Byte code:
/*    */     //   0: new java/lang/invoke/MutableCallSite
/*    */     //   3: dup
/*    */     //   4: aload_2
/*    */     //   5: invokespecial <init> : (Ljava/lang/invoke/MethodType;)V
/*    */     //   8: astore_3
/*    */     //   9: aload_3
/*    */     //   10: ldc_w
/*    */     //   13: ldc_w [Ljava/lang/Object;
/*    */     //   16: aload_2
/*    */     //   17: invokevirtual parameterCount : ()I
/*    */     //   20: invokevirtual asCollector : (Ljava/lang/Class;I)Ljava/lang/invoke/MethodHandle;
/*    */     //   23: iconst_0
/*    */     //   24: iconst_3
/*    */     //   25: anewarray java/lang/Object
/*    */     //   28: dup
/*    */     //   29: iconst_0
/*    */     //   30: aload_0
/*    */     //   31: aastore
/*    */     //   32: dup
/*    */     //   33: iconst_1
/*    */     //   34: aload_3
/*    */     //   35: aastore
/*    */     //   36: dup
/*    */     //   37: iconst_2
/*    */     //   38: aload_1
/*    */     //   39: aastore
/*    */     //   40: invokestatic insertArguments : (Ljava/lang/invoke/MethodHandle;I[Ljava/lang/Object;)Ljava/lang/invoke/MethodHandle;
/*    */     //   43: aload_2
/*    */     //   44: invokestatic explicitCastArguments : (Ljava/lang/invoke/MethodHandle;Ljava/lang/invoke/MethodType;)Ljava/lang/invoke/MethodHandle;
/*    */     //   47: invokevirtual setTarget : (Ljava/lang/invoke/MethodHandle;)V
/*    */     //   50: goto -> 171
/*    */     //   53: astore #4
/*    */     //   55: new java/lang/RuntimeException
/*    */     //   58: dup
/*    */     //   59: new java/lang/StringBuilder
/*    */     //   62: dup
/*    */     //   63: invokespecial <init> : ()V
/*    */     //   66: ldc_w '뽯ᆋ嶱鐪⥛鈒⼀抱쫘ො襕ឿ힟䈵⸷ꎳ⇽'
/*    */     //   69: invokevirtual toCharArray : ()[C
/*    */     //   72: dup
/*    */     //   73: dup
/*    */     //   74: bipush #11
/*    */     //   76: dup_x1
/*    */     //   77: caload
/*    */     //   78: sipush #16255
/*    */     //   81: ixor
/*    */     //   82: i2c
/*    */     //   83: castore
/*    */     //   84: sipush #8177
/*    */     //   87: iconst_0
/*    */     //   88: iconst_0
/*    */     //   89: invokestatic X : (Ljava/lang/Object;SZZ)Ljava/lang/String;
/*    */     //   92: invokevirtual append : (Ljava/lang/String;)Ljava/lang/StringBuilder;
/*    */     //   95: ldc_w '㬹瘤棅纶'
/*    */     //   98: invokevirtual toCharArray : ()[C
/*    */     //   101: dup
/*    */     //   102: dup
/*    */     //   103: iconst_0
/*    */     //   104: dup_x1
/*    */     //   105: caload
/*    */     //   106: sipush #18420
/*    */     //   109: ixor
/*    */     //   110: i2c
/*    */     //   111: castore
/*    */     //   112: sipush #28800
/*    */     //   115: iconst_0
/*    */     //   116: iconst_0
/*    */     //   117: invokestatic X : (Ljava/lang/Object;SZZ)Ljava/lang/String;
/*    */     //   120: invokevirtual append : (Ljava/lang/String;)Ljava/lang/StringBuilder;
/*    */     //   123: aload_1
/*    */     //   124: invokevirtual append : (Ljava/lang/String;)Ljava/lang/StringBuilder;
/*    */     //   127: ldc_w 'ᶑଁ銫䠉'
/*    */     //   130: invokevirtual toCharArray : ()[C
/*    */     //   133: dup
/*    */     //   134: dup
/*    */     //   135: iconst_0
/*    */     //   136: dup_x1
/*    */     //   137: caload
/*    */     //   138: sipush #32296
/*    */     //   141: ixor
/*    */     //   142: i2c
/*    */     //   143: castore
/*    */     //   144: sipush #6441
/*    */     //   147: iconst_1
/*    */     //   148: iconst_1
/*    */     //   149: invokestatic X : (Ljava/lang/Object;SZZ)Ljava/lang/String;
/*    */     //   152: invokevirtual append : (Ljava/lang/String;)Ljava/lang/StringBuilder;
/*    */     //   155: aload_2
/*    */     //   156: invokevirtual toString : ()Ljava/lang/String;
/*    */     //   159: invokevirtual append : (Ljava/lang/String;)Ljava/lang/StringBuilder;
/*    */     //   162: invokevirtual toString : ()Ljava/lang/String;
/*    */     //   165: aload #4
/*    */     //   167: invokespecial <init> : (Ljava/lang/String;Ljava/lang/Throwable;)V
/*    */     //   170: athrow
/*    */     //   171: aload_3
/*    */     //   172: areturn
/*    */     // Exception table:
/*    */     //   from	to	target	type
/*    */     //   9	50	53	java/lang/Exception
/*    */   } }


/* Location:              C:\Users\BukkitBypass\Desktop\MatrixAC\AAC\AAC-spigot-5.2.0.jar!\me\konsolas\aac\ei.class
 * Java compiler version: 8 (52.0)
 * JD-Core Version:       1.1.3
 */