/*     */ package me.konsolas.aac;
/*     */ import java.lang.invoke.MethodHandles;
/*     */ import java.lang.invoke.MutableCallSite;
/*     */ import java.net.Socket;
/*     */ import java.util.List;
/*     */ import javax.crypto.Cipher;
/*     */ import javax.crypto.SecretKey;
/*     */ import javax.crypto.SecretKeyFactory;
/*     */ import javax.crypto.spec.DESKeySpec;
/*     */ import javax.crypto.spec.IvParameterSpec;
/*     */ 
/*     */ public final class el extends eX implements i4 {
/*     */   private void a(long paramLong, lK paramlK) {
/*     */     // Byte code:
/*     */     //   0: getstatic me/konsolas/aac/el.u : J
/*     */     //   3: lload_1
/*     */     //   4: lxor
/*     */     //   5: lstore_1
/*     */     //   6: lload_1
/*     */     //   7: dup2
/*     */     //   8: ldc2_w 86803861510551
/*     */     //   11: lxor
/*     */     //   12: lstore #4
/*     */     //   14: dup2
/*     */     //   15: ldc2_w 37994345221352
/*     */     //   18: lxor
/*     */     //   19: dup2
/*     */     //   20: bipush #48
/*     */     //   22: lushr
/*     */     //   23: l2i
/*     */     //   24: istore #6
/*     */     //   26: dup2
/*     */     //   27: bipush #16
/*     */     //   29: lshl
/*     */     //   30: bipush #48
/*     */     //   32: lushr
/*     */     //   33: l2i
/*     */     //   34: istore #7
/*     */     //   36: dup2
/*     */     //   37: bipush #32
/*     */     //   39: lshl
/*     */     //   40: bipush #32
/*     */     //   42: lushr
/*     */     //   43: l2i
/*     */     //   44: istore #8
/*     */     //   46: pop2
/*     */     //   47: dup2
/*     */     //   48: ldc2_w 78120771446040
/*     */     //   51: lxor
/*     */     //   52: dup2
/*     */     //   53: bipush #32
/*     */     //   55: lushr
/*     */     //   56: l2i
/*     */     //   57: istore #9
/*     */     //   59: dup2
/*     */     //   60: bipush #32
/*     */     //   62: lshl
/*     */     //   63: bipush #48
/*     */     //   65: lushr
/*     */     //   66: l2i
/*     */     //   67: istore #10
/*     */     //   69: dup2
/*     */     //   70: bipush #48
/*     */     //   72: lshl
/*     */     //   73: bipush #48
/*     */     //   75: lushr
/*     */     //   76: l2i
/*     */     //   77: istore #11
/*     */     //   79: pop2
/*     */     //   80: dup2
/*     */     //   81: ldc2_w 30515515242825
/*     */     //   84: lxor
/*     */     //   85: lstore #12
/*     */     //   87: dup2
/*     */     //   88: ldc2_w 95152516696718
/*     */     //   91: lxor
/*     */     //   92: lstore #14
/*     */     //   94: dup2
/*     */     //   95: ldc2_w 62141295652374
/*     */     //   98: lxor
/*     */     //   99: lstore #16
/*     */     //   101: dup2
/*     */     //   102: ldc2_w 131395719637775
/*     */     //   105: lxor
/*     */     //   106: lstore #18
/*     */     //   108: dup2
/*     */     //   109: ldc2_w 135007767679911
/*     */     //   112: lxor
/*     */     //   113: lstore #20
/*     */     //   115: dup2
/*     */     //   116: ldc2_w 15699315445749
/*     */     //   119: lxor
/*     */     //   120: lstore #22
/*     */     //   122: dup2
/*     */     //   123: ldc2_w 15320773079542
/*     */     //   126: lxor
/*     */     //   127: lstore #24
/*     */     //   129: dup2
/*     */     //   130: ldc2_w 46664475165359
/*     */     //   133: lxor
/*     */     //   134: lstore #26
/*     */     //   136: dup2
/*     */     //   137: ldc2_w 86560965536515
/*     */     //   140: lxor
/*     */     //   141: lstore #28
/*     */     //   143: dup2
/*     */     //   144: ldc2_w 7207710717770
/*     */     //   147: lxor
/*     */     //   148: lstore #30
/*     */     //   150: dup2
/*     */     //   151: ldc2_w 118482981788421
/*     */     //   154: lxor
/*     */     //   155: lstore #32
/*     */     //   157: dup2
/*     */     //   158: ldc2_w 18971319060215
/*     */     //   161: lxor
/*     */     //   162: lstore #34
/*     */     //   164: pop2
/*     */     //   165: aload_0
/*     */     //   166: getfield o : Lme/konsolas/aac/hQ;
/*     */     //   169: invokevirtual a : ()Lme/konsolas/aac/jh;
/*     */     //   172: astore #37
/*     */     //   174: ldc2_w 4713569429520454985
/*     */     //   177: lload_1
/*     */     //   178: <illegal opcode> w : (JJ)I
/*     */     //   183: aload #37
/*     */     //   185: invokevirtual a : ()Ljavax/net/ssl/SSLSocketFactory;
/*     */     //   188: astore #38
/*     */     //   190: iconst_0
/*     */     //   191: istore #39
/*     */     //   193: aconst_null
/*     */     //   194: astore #40
/*     */     //   196: istore #36
/*     */     //   198: aload #38
/*     */     //   200: aload_0
/*     */     //   201: getfield r : Ljava/net/Socket;
/*     */     //   204: aload #37
/*     */     //   206: invokevirtual a : ()Lme/konsolas/aac/l6;
/*     */     //   209: invokevirtual d : ()Ljava/lang/String;
/*     */     //   212: aload #37
/*     */     //   214: invokevirtual a : ()Lme/konsolas/aac/l6;
/*     */     //   217: invokevirtual c : ()I
/*     */     //   220: iconst_1
/*     */     //   221: invokevirtual createSocket : (Ljava/net/Socket;Ljava/lang/String;IZ)Ljava/net/Socket;
/*     */     //   224: checkcast javax/net/ssl/SSLSocket
/*     */     //   227: astore #40
/*     */     //   229: aload_3
/*     */     //   230: aload #40
/*     */     //   232: lload #14
/*     */     //   234: invokevirtual a : (Ljavax/net/ssl/SSLSocket;J)Lme/konsolas/aac/kB;
/*     */     //   237: astore #41
/*     */     //   239: iload #36
/*     */     //   241: ifne -> 306
/*     */     //   244: aload #41
/*     */     //   246: invokevirtual b : ()Z
/*     */     //   249: ifeq -> 301
/*     */     //   252: goto -> 265
/*     */     //   255: ldc2_w 4687482058400431050
/*     */     //   258: lload_1
/*     */     //   259: <illegal opcode> w : (Ljava/lang/Throwable;JJ)Ljava/lang/Throwable;
/*     */     //   264: athrow
/*     */     //   265: invokestatic c : ()Lme/konsolas/aac/io;
/*     */     //   268: lload #16
/*     */     //   270: aload #40
/*     */     //   272: aload #37
/*     */     //   274: invokevirtual a : ()Lme/konsolas/aac/l6;
/*     */     //   277: invokevirtual d : ()Ljava/lang/String;
/*     */     //   280: aload #37
/*     */     //   282: invokevirtual b : ()Ljava/util/List;
/*     */     //   285: invokevirtual a : (JLjavax/net/ssl/SSLSocket;Ljava/lang/String;Ljava/util/List;)V
/*     */     //   288: goto -> 301
/*     */     //   291: ldc2_w 4687482058400431050
/*     */     //   294: lload_1
/*     */     //   295: <illegal opcode> w : (Ljava/lang/Throwable;JJ)Ljava/lang/Throwable;
/*     */     //   300: athrow
/*     */     //   301: aload #40
/*     */     //   303: invokevirtual startHandshake : ()V
/*     */     //   306: aload #40
/*     */     //   308: invokevirtual getSession : ()Ljavax/net/ssl/SSLSession;
/*     */     //   311: astore #42
/*     */     //   313: aload #42
/*     */     //   315: lload #24
/*     */     //   317: invokestatic a : (Ljavax/net/ssl/SSLSession;J)Lme/konsolas/aac/it;
/*     */     //   320: astore #43
/*     */     //   322: aload #37
/*     */     //   324: invokevirtual a : ()Ljavax/net/ssl/HostnameVerifier;
/*     */     //   327: aload #37
/*     */     //   329: invokevirtual a : ()Lme/konsolas/aac/l6;
/*     */     //   332: invokevirtual d : ()Ljava/lang/String;
/*     */     //   335: aload #42
/*     */     //   337: invokeinterface verify : (Ljava/lang/String;Ljavax/net/ssl/SSLSession;)Z
/*     */     //   342: lload_1
/*     */     //   343: lconst_0
/*     */     //   344: lcmp
/*     */     //   345: ifle -> 645
/*     */     //   348: iload #36
/*     */     //   350: ifne -> 645
/*     */     //   353: ifne -> 617
/*     */     //   356: goto -> 369
/*     */     //   359: ldc2_w 4687482058400431050
/*     */     //   362: lload_1
/*     */     //   363: <illegal opcode> w : (Ljava/lang/Throwable;JJ)Ljava/lang/Throwable;
/*     */     //   368: athrow
/*     */     //   369: aload #43
/*     */     //   371: invokevirtual b : ()Ljava/util/List;
/*     */     //   374: astore #44
/*     */     //   376: aload #44
/*     */     //   378: iload #36
/*     */     //   380: ifne -> 425
/*     */     //   383: invokeinterface isEmpty : ()Z
/*     */     //   388: ifne -> 556
/*     */     //   391: goto -> 404
/*     */     //   394: ldc2_w 4687482058400431050
/*     */     //   397: lload_1
/*     */     //   398: <illegal opcode> w : (Ljava/lang/Throwable;JJ)Ljava/lang/Throwable;
/*     */     //   403: athrow
/*     */     //   404: aload #44
/*     */     //   406: iconst_0
/*     */     //   407: invokeinterface get : (I)Ljava/lang/Object;
/*     */     //   412: goto -> 425
/*     */     //   415: ldc2_w 4687482058400431050
/*     */     //   418: lload_1
/*     */     //   419: <illegal opcode> w : (Ljava/lang/Throwable;JJ)Ljava/lang/Throwable;
/*     */     //   424: athrow
/*     */     //   425: checkcast java/security/cert/X509Certificate
/*     */     //   428: astore #45
/*     */     //   430: new javax/net/ssl/SSLPeerUnverifiedException
/*     */     //   433: dup
/*     */     //   434: new java/lang/StringBuilder
/*     */     //   437: dup
/*     */     //   438: invokespecial <init> : ()V
/*     */     //   441: sipush #27981
/*     */     //   444: ldc2_w 6552047818509465566
/*     */     //   447: lload_1
/*     */     //   448: lxor
/*     */     //   449: <illegal opcode> a : (IJ)Ljava/lang/String;
/*     */     //   454: invokevirtual append : (Ljava/lang/String;)Ljava/lang/StringBuilder;
/*     */     //   457: aload #37
/*     */     //   459: invokevirtual a : ()Lme/konsolas/aac/l6;
/*     */     //   462: invokevirtual d : ()Ljava/lang/String;
/*     */     //   465: invokevirtual append : (Ljava/lang/String;)Ljava/lang/StringBuilder;
/*     */     //   468: sipush #11230
/*     */     //   471: ldc2_w 315266530325754201
/*     */     //   474: lload_1
/*     */     //   475: lxor
/*     */     //   476: <illegal opcode> a : (IJ)Ljava/lang/String;
/*     */     //   481: invokevirtual append : (Ljava/lang/String;)Ljava/lang/StringBuilder;
/*     */     //   484: lload #20
/*     */     //   486: aload #45
/*     */     //   488: invokestatic a : (JLjava/security/cert/Certificate;)Ljava/lang/String;
/*     */     //   491: invokevirtual append : (Ljava/lang/String;)Ljava/lang/StringBuilder;
/*     */     //   494: sipush #14591
/*     */     //   497: ldc2_w 3731949550644159095
/*     */     //   500: lload_1
/*     */     //   501: lxor
/*     */     //   502: <illegal opcode> a : (IJ)Ljava/lang/String;
/*     */     //   507: invokevirtual append : (Ljava/lang/String;)Ljava/lang/StringBuilder;
/*     */     //   510: aload #45
/*     */     //   512: invokevirtual getSubjectDN : ()Ljava/security/Principal;
/*     */     //   515: invokeinterface getName : ()Ljava/lang/String;
/*     */     //   520: invokevirtual append : (Ljava/lang/String;)Ljava/lang/StringBuilder;
/*     */     //   523: sipush #7081
/*     */     //   526: ldc2_w 5899483233629028647
/*     */     //   529: lload_1
/*     */     //   530: lxor
/*     */     //   531: <illegal opcode> a : (IJ)Ljava/lang/String;
/*     */     //   536: invokevirtual append : (Ljava/lang/String;)Ljava/lang/StringBuilder;
/*     */     //   539: aload #45
/*     */     //   541: lload #18
/*     */     //   543: invokestatic a : (Ljava/security/cert/X509Certificate;J)Ljava/util/List;
/*     */     //   546: invokevirtual append : (Ljava/lang/Object;)Ljava/lang/StringBuilder;
/*     */     //   549: invokevirtual toString : ()Ljava/lang/String;
/*     */     //   552: invokespecial <init> : (Ljava/lang/String;)V
/*     */     //   555: athrow
/*     */     //   556: new javax/net/ssl/SSLPeerUnverifiedException
/*     */     //   559: dup
/*     */     //   560: new java/lang/StringBuilder
/*     */     //   563: dup
/*     */     //   564: invokespecial <init> : ()V
/*     */     //   567: sipush #12946
/*     */     //   570: ldc2_w 8517584412217894927
/*     */     //   573: lload_1
/*     */     //   574: lxor
/*     */     //   575: <illegal opcode> a : (IJ)Ljava/lang/String;
/*     */     //   580: invokevirtual append : (Ljava/lang/String;)Ljava/lang/StringBuilder;
/*     */     //   583: aload #37
/*     */     //   585: invokevirtual a : ()Lme/konsolas/aac/l6;
/*     */     //   588: invokevirtual d : ()Ljava/lang/String;
/*     */     //   591: invokevirtual append : (Ljava/lang/String;)Ljava/lang/StringBuilder;
/*     */     //   594: sipush #16638
/*     */     //   597: ldc2_w 6971175383968225894
/*     */     //   600: lload_1
/*     */     //   601: lxor
/*     */     //   602: <illegal opcode> a : (IJ)Ljava/lang/String;
/*     */     //   607: invokevirtual append : (Ljava/lang/String;)Ljava/lang/StringBuilder;
/*     */     //   610: invokevirtual toString : ()Ljava/lang/String;
/*     */     //   613: invokespecial <init> : (Ljava/lang/String;)V
/*     */     //   616: athrow
/*     */     //   617: aload #37
/*     */     //   619: invokevirtual a : ()Lme/konsolas/aac/mG;
/*     */     //   622: aload #37
/*     */     //   624: invokevirtual a : ()Lme/konsolas/aac/l6;
/*     */     //   627: invokevirtual d : ()Ljava/lang/String;
/*     */     //   630: aload #43
/*     */     //   632: invokevirtual b : ()Ljava/util/List;
/*     */     //   635: lload #30
/*     */     //   637: invokevirtual a : (Ljava/lang/String;Ljava/util/List;J)V
/*     */     //   640: aload #41
/*     */     //   642: invokevirtual b : ()Z
/*     */     //   645: ifeq -> 671
/*     */     //   648: invokestatic c : ()Lme/konsolas/aac/io;
/*     */     //   651: lload #22
/*     */     //   653: aload #40
/*     */     //   655: invokevirtual a : (JLjavax/net/ssl/SSLSocket;)Ljava/lang/String;
/*     */     //   658: goto -> 672
/*     */     //   661: ldc2_w 4687482058400431050
/*     */     //   664: lload_1
/*     */     //   665: <illegal opcode> w : (Ljava/lang/Throwable;JJ)Ljava/lang/Throwable;
/*     */     //   670: athrow
/*     */     //   671: aconst_null
/*     */     //   672: astore #44
/*     */     //   674: aload_0
/*     */     //   675: aload #40
/*     */     //   677: putfield n : Ljava/net/Socket;
/*     */     //   680: aload_0
/*     */     //   681: aload_0
/*     */     //   682: getfield n : Ljava/net/Socket;
/*     */     //   685: lload #34
/*     */     //   687: dup2_x1
/*     */     //   688: pop2
/*     */     //   689: invokestatic a : (JLjava/net/Socket;)Lme/konsolas/aac/hp;
/*     */     //   692: iload #6
/*     */     //   694: i2s
/*     */     //   695: swap
/*     */     //   696: iload #7
/*     */     //   698: i2c
/*     */     //   699: iload #8
/*     */     //   701: invokestatic a : (SLme/konsolas/aac/hp;CI)Lme/konsolas/aac/bX;
/*     */     //   704: putfield h : Lme/konsolas/aac/bX;
/*     */     //   707: aload_0
/*     */     //   708: aload_0
/*     */     //   709: getfield n : Ljava/net/Socket;
/*     */     //   712: lload #12
/*     */     //   714: dup2_x1
/*     */     //   715: pop2
/*     */     //   716: invokestatic a : (JLjava/net/Socket;)Lme/konsolas/aac/gp;
/*     */     //   719: lload #4
/*     */     //   721: invokestatic a : (Lme/konsolas/aac/gp;J)Lme/konsolas/aac/gi;
/*     */     //   724: putfield p : Lme/konsolas/aac/gi;
/*     */     //   727: aload_0
/*     */     //   728: aload #43
/*     */     //   730: putfield b : Lme/konsolas/aac/it;
/*     */     //   733: aload_0
/*     */     //   734: aload #44
/*     */     //   736: iload #36
/*     */     //   738: ifne -> 759
/*     */     //   741: ifnull -> 767
/*     */     //   744: goto -> 757
/*     */     //   747: ldc2_w 4687482058400431050
/*     */     //   750: lload_1
/*     */     //   751: <illegal opcode> w : (Ljava/lang/Throwable;JJ)Ljava/lang/Throwable;
/*     */     //   756: athrow
/*     */     //   757: aload #44
/*     */     //   759: lload #32
/*     */     //   761: invokestatic a : (Ljava/lang/String;J)Lme/konsolas/aac/le;
/*     */     //   764: goto -> 770
/*     */     //   767: getstatic me/konsolas/aac/le.HTTP_1_1 : Lme/konsolas/aac/le;
/*     */     //   770: putfield i : Lme/konsolas/aac/le;
/*     */     //   773: iconst_1
/*     */     //   774: lload_1
/*     */     //   775: lconst_0
/*     */     //   776: lcmp
/*     */     //   777: ifle -> 823
/*     */     //   780: iload #36
/*     */     //   782: ifne -> 823
/*     */     //   785: istore #39
/*     */     //   787: lload_1
/*     */     //   788: lconst_0
/*     */     //   789: lcmp
/*     */     //   790: iflt -> 808
/*     */     //   793: aload #40
/*     */     //   795: ifnull -> 821
/*     */     //   798: invokestatic c : ()Lme/konsolas/aac/io;
/*     */     //   801: lload #26
/*     */     //   803: aload #40
/*     */     //   805: invokevirtual a : (JLjavax/net/ssl/SSLSocket;)V
/*     */     //   808: goto -> 821
/*     */     //   811: ldc2_w 4687482058400431050
/*     */     //   814: lload_1
/*     */     //   815: <illegal opcode> w : (Ljava/lang/Throwable;JJ)Ljava/lang/Throwable;
/*     */     //   820: athrow
/*     */     //   821: iload #39
/*     */     //   823: ifne -> 980
/*     */     //   826: lload #28
/*     */     //   828: aload #40
/*     */     //   830: invokestatic a : (JLjava/net/Socket;)V
/*     */     //   833: goto -> 980
/*     */     //   836: ldc2_w 4687482058400431050
/*     */     //   839: lload_1
/*     */     //   840: <illegal opcode> w : (Ljava/lang/Throwable;JJ)Ljava/lang/Throwable;
/*     */     //   845: athrow
/*     */     //   846: astore #41
/*     */     //   848: aload #41
/*     */     //   850: iload #36
/*     */     //   852: lload_1
/*     */     //   853: lconst_0
/*     */     //   854: lcmp
/*     */     //   855: ifle -> 863
/*     */     //   858: ifne -> 909
/*     */     //   861: iload #9
/*     */     //   863: iload #10
/*     */     //   865: i2c
/*     */     //   866: iload #11
/*     */     //   868: invokestatic a : (Ljava/lang/AssertionError;ICI)Z
/*     */     //   871: ifeq -> 907
/*     */     //   874: goto -> 887
/*     */     //   877: ldc2_w 4687482058400431050
/*     */     //   880: lload_1
/*     */     //   881: <illegal opcode> w : (Ljava/lang/Throwable;JJ)Ljava/lang/Throwable;
/*     */     //   886: athrow
/*     */     //   887: new java/io/IOException
/*     */     //   890: dup
/*     */     //   891: aload #41
/*     */     //   893: invokespecial <init> : (Ljava/lang/Throwable;)V
/*     */     //   896: athrow
/*     */     //   897: ldc2_w 4687482058400431050
/*     */     //   900: lload_1
/*     */     //   901: <illegal opcode> w : (Ljava/lang/Throwable;JJ)Ljava/lang/Throwable;
/*     */     //   906: athrow
/*     */     //   907: aload #41
/*     */     //   909: athrow
/*     */     //   910: astore #46
/*     */     //   912: lload_1
/*     */     //   913: lconst_0
/*     */     //   914: lcmp
/*     */     //   915: iflt -> 946
/*     */     //   918: aload #40
/*     */     //   920: ifnull -> 946
/*     */     //   923: invokestatic c : ()Lme/konsolas/aac/io;
/*     */     //   926: lload #26
/*     */     //   928: aload #40
/*     */     //   930: invokevirtual a : (JLjavax/net/ssl/SSLSocket;)V
/*     */     //   933: goto -> 946
/*     */     //   936: ldc2_w 4687482058400431050
/*     */     //   939: lload_1
/*     */     //   940: <illegal opcode> w : (Ljava/lang/Throwable;JJ)Ljava/lang/Throwable;
/*     */     //   945: athrow
/*     */     //   946: lload_1
/*     */     //   947: lconst_0
/*     */     //   948: lcmp
/*     */     //   949: ifle -> 964
/*     */     //   952: iload #39
/*     */     //   954: ifne -> 977
/*     */     //   957: lload #28
/*     */     //   959: aload #40
/*     */     //   961: invokestatic a : (JLjava/net/Socket;)V
/*     */     //   964: goto -> 977
/*     */     //   967: ldc2_w 4687482058400431050
/*     */     //   970: lload_1
/*     */     //   971: <illegal opcode> w : (Ljava/lang/Throwable;JJ)Ljava/lang/Throwable;
/*     */     //   976: athrow
/*     */     //   977: aload #46
/*     */     //   979: athrow
/*     */     //   980: return
/*     */     // Line number table:
/*     */     //   Java source line number -> byte code offset
/*     */     //   #17	-> 165
/*     */     //   #93	-> 183
/*     */     //   #247	-> 190
/*     */     //   #158	-> 193
/*     */     //   #273	-> 198
/*     */     //   #39	-> 206
/*     */     //   #80	-> 221
/*     */     //   #301	-> 229
/*     */     //   #276	-> 239
/*     */     //   #223	-> 265
/*     */     //   #302	-> 274
/*     */     //   #66	-> 285
/*     */     //   #285	-> 301
/*     */     //   #30	-> 306
/*     */     //   #117	-> 313
/*     */     //   #54	-> 322
/*     */     //   #267	-> 369
/*     */     //   #85	-> 376
/*     */     //   #109	-> 404
/*     */     //   #122	-> 430
/*     */     //   #120	-> 459
/*     */     //   #307	-> 488
/*     */     //   #112	-> 512
/*     */     //   #47	-> 541
/*     */     //   #181	-> 556
/*     */     //   #151	-> 585
/*     */     //   #306	-> 617
/*     */     //   #179	-> 632
/*     */     //   #125	-> 635
/*     */     //   #194	-> 640
/*     */     //   #274	-> 648
/*     */     //   #183	-> 671
/*     */     //   #41	-> 674
/*     */     //   #203	-> 680
/*     */     //   #225	-> 707
/*     */     //   #196	-> 727
/*     */     //   #175	-> 733
/*     */     //   #108	-> 757
/*     */     //   #243	-> 767
/*     */     //   #185	-> 773
/*     */     //   #73	-> 787
/*     */     //   #99	-> 798
/*     */     //   #169	-> 821
/*     */     //   #94	-> 826
/*     */     //   #56	-> 846
/*     */     //   #275	-> 848
/*     */     //   #28	-> 907
/*     */     //   #309	-> 910
/*     */     //   #139	-> 923
/*     */     //   #25	-> 946
/*     */     //   #178	-> 957
/*     */     //   #297	-> 980
/*     */     // Exception table:
/*     */     //   from	to	target	type
/*     */     //   198	787	846	java/lang/AssertionError
/*     */     //   198	787	910	finally
/*     */     //   239	252	255	java/lang/AssertionError
/*     */     //   244	288	291	java/lang/AssertionError
/*     */     //   322	356	359	java/lang/AssertionError
/*     */     //   376	391	394	java/lang/AssertionError
/*     */     //   383	412	415	java/lang/AssertionError
/*     */     //   645	661	661	java/lang/AssertionError
/*     */     //   674	744	747	java/lang/AssertionError
/*     */     //   787	808	811	java/lang/AssertionError
/*     */     //   823	836	836	java/lang/AssertionError
/*     */     //   846	912	910	finally
/*     */     //   848	874	877	java/lang/AssertionError
/*     */     //   861	897	897	java/lang/AssertionError
/*     */     //   912	933	936	java/lang/AssertionError
/*     */     //   946	964	967	java/lang/AssertionError
/*     */   }
/*     */   
/*     */   public void a(long paramLong, cZ paramcZ) {
/*  18 */     int i = (int)((paramLong ^ 0xDAE55C7BC1BL) >>> 32L), j = (int)((paramLong ^ 0xDAE55C7BC1BL) << 32L >>> 48L), k = (int)((paramLong ^ 0xDAE55C7BC1BL) << 48L >>> 48L); paramLong ^ 0xDAE55C7BC1BL; synchronized (this.c) {
/*     */ 
/*     */ 
/*     */ 
/*     */ 
/*     */ 
/*     */ 
/*     */ 
/*     */ 
/*     */ 
/*     */ 
/*     */ 
/*     */ 
/*     */ 
/*     */ 
/*     */ 
/*     */ 
/*     */ 
/*     */ 
/*     */ 
/*     */ 
/*     */ 
/*     */ 
/*     */ 
/*     */ 
/*     */ 
/*     */ 
/*     */ 
/*     */ 
/*     */ 
/*     */ 
/*     */ 
/*     */ 
/*     */ 
/*     */ 
/*     */ 
/*     */ 
/*     */ 
/*     */ 
/*     */ 
/*     */ 
/*     */ 
/*     */ 
/*     */ 
/*     */ 
/*     */ 
/*     */ 
/*     */ 
/*     */ 
/*     */ 
/*     */ 
/*     */ 
/*     */ 
/*     */ 
/*     */ 
/*     */ 
/*     */ 
/*     */ 
/*     */ 
/*     */ 
/*     */ 
/*     */ 
/*     */ 
/*     */ 
/*     */ 
/*     */ 
/*     */ 
/*     */ 
/*     */ 
/*     */ 
/*     */ 
/*     */ 
/*     */ 
/*     */ 
/*     */ 
/*     */ 
/*     */ 
/*     */ 
/*     */ 
/*     */ 
/*     */ 
/*     */ 
/*     */ 
/*     */ 
/*     */ 
/*     */ 
/*     */ 
/*     */ 
/*     */ 
/*     */ 
/*     */ 
/*     */ 
/*     */ 
/*     */ 
/*     */ 
/*     */ 
/*     */ 
/*     */ 
/*     */ 
/*     */ 
/*     */ 
/*     */ 
/*     */ 
/*     */ 
/*     */ 
/*     */ 
/*     */ 
/*     */ 
/*     */ 
/*     */ 
/*     */ 
/*     */ 
/*     */ 
/*     */ 
/*     */ 
/*     */ 
/*     */ 
/*     */ 
/*     */ 
/*     */ 
/*     */ 
/*     */ 
/*     */ 
/*     */ 
/*     */ 
/*     */ 
/*     */ 
/*     */ 
/*     */ 
/*     */ 
/*     */ 
/*     */ 
/*     */ 
/*     */ 
/*     */ 
/*     */ 
/*     */ 
/*     */ 
/*     */ 
/*     */ 
/*     */ 
/*     */ 
/*     */ 
/*     */ 
/*     */ 
/*     */ 
/*     */ 
/*     */ 
/*     */ 
/*     */ 
/*     */ 
/*     */ 
/*     */ 
/*     */ 
/*     */ 
/*     */ 
/*     */ 
/*     */ 
/*     */ 
/*     */ 
/*     */ 
/*     */ 
/*     */ 
/*     */ 
/*     */ 
/*     */ 
/*     */ 
/*     */ 
/*     */ 
/*     */ 
/*     */ 
/*     */ 
/*     */ 
/*     */ 
/*     */ 
/*     */ 
/*     */ 
/*     */ 
/*     */ 
/*     */ 
/*     */ 
/*     */ 
/*     */ 
/*     */ 
/*     */ 
/*     */ 
/*     */ 
/*     */ 
/*     */ 
/*     */ 
/*     */ 
/*     */ 
/*     */       
/* 211 */       this.t = paramcZ.a(i, j, k);
/*     */     } 
/*     */   }
/*     */ 
/*     */ 
/*     */   
/*     */   public it a() {
/*     */     return this.b;
/*     */   }
/*     */ 
/*     */ 
/*     */   
/*     */   public void b(char paramChar, int paramInt, short paramShort) {
/*     */     long l1 = (paramChar << 48L | paramInt << 32L >>> 16L | paramShort << 48L >>> 48L) ^ u, l2 = l1 ^ 0x4626481AF2A7L;
/*     */     eO.a(l2, this.r);
/*     */   }
/*     */ 
/*     */ 
/*     */   
/*     */   private boolean a(int paramInt1, byte paramByte, int paramInt2, List paramList) {
/*     */     // Byte code:
/*     */     //   0: iload_1
/*     */     //   1: i2l
/*     */     //   2: bipush #32
/*     */     //   4: lshl
/*     */     //   5: iload_2
/*     */     //   6: i2l
/*     */     //   7: bipush #56
/*     */     //   9: lshl
/*     */     //   10: bipush #32
/*     */     //   12: lushr
/*     */     //   13: lor
/*     */     //   14: iload_3
/*     */     //   15: i2l
/*     */     //   16: bipush #40
/*     */     //   18: lshl
/*     */     //   19: bipush #40
/*     */     //   21: lushr
/*     */     //   22: lor
/*     */     //   23: getstatic me/konsolas/aac/el.u : J
/*     */     //   26: lxor
/*     */     //   27: lstore #5
/*     */     //   29: ldc2_w -706377108611264520
/*     */     //   32: lload #5
/*     */     //   34: <illegal opcode> w : (JJ)I
/*     */     //   39: iconst_0
/*     */     //   40: istore #8
/*     */     //   42: istore #7
/*     */     //   44: aload #4
/*     */     //   46: invokeinterface size : ()I
/*     */     //   51: istore #9
/*     */     //   53: iload #8
/*     */     //   55: iload #9
/*     */     //   57: if_icmpge -> 225
/*     */     //   60: aload #4
/*     */     //   62: iload #8
/*     */     //   64: invokeinterface get : (I)Ljava/lang/Object;
/*     */     //   69: checkcast me/konsolas/aac/hQ
/*     */     //   72: astore #10
/*     */     //   74: iload #7
/*     */     //   76: iload_3
/*     */     //   77: iflt -> 222
/*     */     //   80: ifeq -> 220
/*     */     //   83: aload #10
/*     */     //   85: invokevirtual a : ()Ljava/net/Proxy;
/*     */     //   88: invokevirtual type : ()Ljava/net/Proxy$Type;
/*     */     //   91: getstatic java/net/Proxy$Type.DIRECT : Ljava/net/Proxy$Type;
/*     */     //   94: if_acmpne -> 217
/*     */     //   97: goto -> 111
/*     */     //   100: ldc2_w -651208586211374031
/*     */     //   103: lload #5
/*     */     //   105: <illegal opcode> w : (Ljava/lang/Throwable;JJ)Ljava/lang/Throwable;
/*     */     //   110: athrow
/*     */     //   111: aload_0
/*     */     //   112: getfield o : Lme/konsolas/aac/hQ;
/*     */     //   115: iload_1
/*     */     //   116: ifle -> 182
/*     */     //   119: iload #7
/*     */     //   121: ifeq -> 182
/*     */     //   124: goto -> 138
/*     */     //   127: ldc2_w -651208586211374031
/*     */     //   130: lload #5
/*     */     //   132: <illegal opcode> w : (Ljava/lang/Throwable;JJ)Ljava/lang/Throwable;
/*     */     //   137: athrow
/*     */     //   138: invokevirtual a : ()Ljava/net/Proxy;
/*     */     //   141: invokevirtual type : ()Ljava/net/Proxy$Type;
/*     */     //   144: getstatic java/net/Proxy$Type.DIRECT : Ljava/net/Proxy$Type;
/*     */     //   147: if_acmpne -> 217
/*     */     //   150: goto -> 164
/*     */     //   153: ldc2_w -651208586211374031
/*     */     //   156: lload #5
/*     */     //   158: <illegal opcode> w : (Ljava/lang/Throwable;JJ)Ljava/lang/Throwable;
/*     */     //   163: athrow
/*     */     //   164: aload_0
/*     */     //   165: getfield o : Lme/konsolas/aac/hQ;
/*     */     //   168: goto -> 182
/*     */     //   171: ldc2_w -651208586211374031
/*     */     //   174: lload #5
/*     */     //   176: <illegal opcode> w : (Ljava/lang/Throwable;JJ)Ljava/lang/Throwable;
/*     */     //   181: athrow
/*     */     //   182: invokevirtual a : ()Ljava/net/InetSocketAddress;
/*     */     //   185: aload #10
/*     */     //   187: invokevirtual a : ()Ljava/net/InetSocketAddress;
/*     */     //   190: invokevirtual equals : (Ljava/lang/Object;)Z
/*     */     //   193: iload #7
/*     */     //   195: ifeq -> 216
/*     */     //   198: ifeq -> 217
/*     */     //   201: goto -> 215
/*     */     //   204: ldc2_w -651208586211374031
/*     */     //   207: lload #5
/*     */     //   209: <illegal opcode> w : (Ljava/lang/Throwable;JJ)Ljava/lang/Throwable;
/*     */     //   214: athrow
/*     */     //   215: iconst_1
/*     */     //   216: ireturn
/*     */     //   217: iinc #8, 1
/*     */     //   220: iload #7
/*     */     //   222: ifne -> 53
/*     */     //   225: iconst_0
/*     */     //   226: ireturn
/*     */     // Line number table:
/*     */     //   Java source line number -> byte code offset
/*     */     //   #40	-> 39
/*     */     //   #49	-> 60
/*     */     //   #46	-> 74
/*     */     //   #3	-> 115
/*     */     //   #190	-> 182
/*     */     //   #82	-> 215
/*     */     //   #198	-> 217
/*     */     //   #1	-> 225
/*     */     // Exception table:
/*     */     //   from	to	target	type
/*     */     //   74	97	100	java/lang/IllegalStateException
/*     */     //   83	124	127	java/lang/IllegalStateException
/*     */     //   111	150	153	java/lang/IllegalStateException
/*     */     //   138	168	171	java/lang/IllegalStateException
/*     */     //   182	201	204	java/lang/IllegalStateException
/*     */   }
/*     */ 
/*     */   
/*     */   public void a(cQ paramcQ, long paramLong) {
/*     */     long l = paramLong ^ 0x1D98FD97EDD0L;
/*     */     paramcQ.a(eb.REFUSED_STREAM, (IOException)null, l);
/*     */   }
/*     */ 
/*     */   
/*     */   static el a(gL paramgL, hQ paramhQ, Socket paramSocket, long paramLong) {
/*     */     el el1 = new el(paramgL, paramhQ);
/*     */     el1.n = paramSocket;
/* 244 */     el1.e = paramLong;
/*     */     return el1;
/*     */   }
/*     */   boolean a(int paramInt, short paramShort, jh paramjh, char paramChar, @Nullable List paramList) { // Byte code:
/*     */     //   0: iload_1
/*     */     //   1: i2l
/*     */     //   2: bipush #32
/*     */     //   4: lshl
/*     */     //   5: iload_2
/*     */     //   6: i2l
/*     */     //   7: bipush #48
/*     */     //   9: lshl
/*     */     //   10: bipush #32
/*     */     //   12: lushr
/*     */     //   13: lor
/*     */     //   14: iload #4
/*     */     //   16: i2l
/*     */     //   17: bipush #48
/*     */     //   19: lshl
/*     */     //   20: bipush #48
/*     */     //   22: lushr
/*     */     //   23: lor
/*     */     //   24: getstatic me/konsolas/aac/el.u : J
/*     */     //   27: lxor
/*     */     //   28: lstore #6
/*     */     //   30: lload #6
/*     */     //   32: dup2
/*     */     //   33: ldc2_w 63305629982811
/*     */     //   36: lxor
/*     */     //   37: lstore #8
/*     */     //   39: dup2
/*     */     //   40: ldc2_w 80842398509472
/*     */     //   43: lxor
/*     */     //   44: lstore #10
/*     */     //   46: dup2
/*     */     //   47: ldc2_w 134256250257623
/*     */     //   50: lxor
/*     */     //   51: dup2
/*     */     //   52: bipush #32
/*     */     //   54: lushr
/*     */     //   55: l2i
/*     */     //   56: istore #12
/*     */     //   58: dup2
/*     */     //   59: bipush #32
/*     */     //   61: lshl
/*     */     //   62: bipush #56
/*     */     //   64: lushr
/*     */     //   65: l2i
/*     */     //   66: istore #13
/*     */     //   68: dup2
/*     */     //   69: bipush #40
/*     */     //   71: lshl
/*     */     //   72: bipush #40
/*     */     //   74: lushr
/*     */     //   75: l2i
/*     */     //   76: istore #14
/*     */     //   78: pop2
/*     */     //   79: dup2
/*     */     //   80: ldc2_w 4879996511126
/*     */     //   83: lxor
/*     */     //   84: lstore #15
/*     */     //   86: pop2
/*     */     //   87: ldc2_w 6130887935838956767
/*     */     //   90: lload #6
/*     */     //   92: <illegal opcode> w : (JJ)I
/*     */     //   97: istore #17
/*     */     //   99: aload_0
/*     */     //   100: getfield g : Ljava/util/List;
/*     */     //   103: invokeinterface size : ()I
/*     */     //   108: iload #17
/*     */     //   110: ifeq -> 179
/*     */     //   113: aload_0
/*     */     //   114: getfield t : I
/*     */     //   117: if_icmpge -> 178
/*     */     //   120: goto -> 134
/*     */     //   123: ldc2_w 6183806118792621846
/*     */     //   126: lload #6
/*     */     //   128: <illegal opcode> w : (Ljava/lang/Throwable;JJ)Ljava/lang/Throwable;
/*     */     //   133: athrow
/*     */     //   134: aload_0
/*     */     //   135: getfield j : Z
/*     */     //   138: iload #17
/*     */     //   140: iload_1
/*     */     //   141: iflt -> 200
/*     */     //   144: ifeq -> 198
/*     */     //   147: goto -> 161
/*     */     //   150: ldc2_w 6183806118792621846
/*     */     //   153: lload #6
/*     */     //   155: <illegal opcode> w : (Ljava/lang/Throwable;JJ)Ljava/lang/Throwable;
/*     */     //   160: athrow
/*     */     //   161: ifeq -> 180
/*     */     //   164: goto -> 178
/*     */     //   167: ldc2_w 6183806118792621846
/*     */     //   170: lload #6
/*     */     //   172: <illegal opcode> w : (Ljava/lang/Throwable;JJ)Ljava/lang/Throwable;
/*     */     //   177: athrow
/*     */     //   178: iconst_0
/*     */     //   179: ireturn
/*     */     //   180: getstatic me/konsolas/aac/dJ.a : Lme/konsolas/aac/dJ;
/*     */     //   183: aload_0
/*     */     //   184: getfield o : Lme/konsolas/aac/hQ;
/*     */     //   187: invokevirtual a : ()Lme/konsolas/aac/jh;
/*     */     //   190: lload #8
/*     */     //   192: dup2_x1
/*     */     //   193: pop2
/*     */     //   194: aload_3
/*     */     //   195: invokevirtual a : (JLme/konsolas/aac/jh;Lme/konsolas/aac/jh;)Z
/*     */     //   198: iload #17
/*     */     //   200: iload #4
/*     */     //   202: iflt -> 263
/*     */     //   205: ifeq -> 261
/*     */     //   208: ifne -> 238
/*     */     //   211: goto -> 225
/*     */     //   214: ldc2_w 6183806118792621846
/*     */     //   217: lload #6
/*     */     //   219: <illegal opcode> w : (Ljava/lang/Throwable;JJ)Ljava/lang/Throwable;
/*     */     //   224: athrow
/*     */     //   225: iconst_0
/*     */     //   226: ireturn
/*     */     //   227: ldc2_w 6183806118792621846
/*     */     //   230: lload #6
/*     */     //   232: <illegal opcode> w : (Ljava/lang/Throwable;JJ)Ljava/lang/Throwable;
/*     */     //   237: athrow
/*     */     //   238: aload_3
/*     */     //   239: invokevirtual a : ()Lme/konsolas/aac/l6;
/*     */     //   242: invokevirtual d : ()Ljava/lang/String;
/*     */     //   245: aload_0
/*     */     //   246: invokevirtual a : ()Lme/konsolas/aac/hQ;
/*     */     //   249: invokevirtual a : ()Lme/konsolas/aac/jh;
/*     */     //   252: invokevirtual a : ()Lme/konsolas/aac/l6;
/*     */     //   255: invokevirtual d : ()Ljava/lang/String;
/*     */     //   258: invokevirtual equals : (Ljava/lang/Object;)Z
/*     */     //   261: iload #17
/*     */     //   263: ifeq -> 284
/*     */     //   266: ifeq -> 285
/*     */     //   269: goto -> 283
/*     */     //   272: ldc2_w 6183806118792621846
/*     */     //   275: lload #6
/*     */     //   277: <illegal opcode> w : (Ljava/lang/Throwable;JJ)Ljava/lang/Throwable;
/*     */     //   282: athrow
/*     */     //   283: iconst_1
/*     */     //   284: ireturn
/*     */     //   285: iload #4
/*     */     //   287: iflt -> 310
/*     */     //   290: aload_0
/*     */     //   291: getfield k : Lme/konsolas/aac/cZ;
/*     */     //   294: ifnonnull -> 310
/*     */     //   297: iconst_0
/*     */     //   298: ireturn
/*     */     //   299: ldc2_w 6183806118792621846
/*     */     //   302: lload #6
/*     */     //   304: <illegal opcode> w : (Ljava/lang/Throwable;JJ)Ljava/lang/Throwable;
/*     */     //   309: athrow
/*     */     //   310: aload #5
/*     */     //   312: ifnull -> 364
/*     */     //   315: aload_0
/*     */     //   316: iload #12
/*     */     //   318: iload #13
/*     */     //   320: i2b
/*     */     //   321: iload #14
/*     */     //   323: aload #5
/*     */     //   325: invokespecial a : (IBILjava/util/List;)Z
/*     */     //   328: iload #17
/*     */     //   330: ifeq -> 365
/*     */     //   333: goto -> 347
/*     */     //   336: ldc2_w 6183806118792621846
/*     */     //   339: lload #6
/*     */     //   341: <illegal opcode> w : (Ljava/lang/Throwable;JJ)Ljava/lang/Throwable;
/*     */     //   346: athrow
/*     */     //   347: ifne -> 366
/*     */     //   350: goto -> 364
/*     */     //   353: ldc2_w 6183806118792621846
/*     */     //   356: lload #6
/*     */     //   358: <illegal opcode> w : (Ljava/lang/Throwable;JJ)Ljava/lang/Throwable;
/*     */     //   363: athrow
/*     */     //   364: iconst_0
/*     */     //   365: ireturn
/*     */     //   366: iload #4
/*     */     //   368: ifle -> 394
/*     */     //   371: aload_3
/*     */     //   372: invokevirtual a : ()Ljavax/net/ssl/HostnameVerifier;
/*     */     //   375: getstatic me/konsolas/aac/jV.a : Lme/konsolas/aac/jV;
/*     */     //   378: if_acmpeq -> 394
/*     */     //   381: iconst_0
/*     */     //   382: ireturn
/*     */     //   383: ldc2_w 6183806118792621846
/*     */     //   386: lload #6
/*     */     //   388: <illegal opcode> w : (Ljava/lang/Throwable;JJ)Ljava/lang/Throwable;
/*     */     //   393: athrow
/*     */     //   394: aload_0
/*     */     //   395: aload_3
/*     */     //   396: invokevirtual a : ()Lme/konsolas/aac/l6;
/*     */     //   399: lload #10
/*     */     //   401: dup2_x1
/*     */     //   402: pop2
/*     */     //   403: invokevirtual a : (JLme/konsolas/aac/l6;)Z
/*     */     //   406: iload #17
/*     */     //   408: ifeq -> 429
/*     */     //   411: ifne -> 430
/*     */     //   414: goto -> 428
/*     */     //   417: ldc2_w 6183806118792621846
/*     */     //   420: lload #6
/*     */     //   422: <illegal opcode> w : (Ljava/lang/Throwable;JJ)Ljava/lang/Throwable;
/*     */     //   427: athrow
/*     */     //   428: iconst_0
/*     */     //   429: ireturn
/*     */     //   430: aload_3
/*     */     //   431: invokevirtual a : ()Lme/konsolas/aac/mG;
/*     */     //   434: aload_3
/*     */     //   435: invokevirtual a : ()Lme/konsolas/aac/l6;
/*     */     //   438: invokevirtual d : ()Ljava/lang/String;
/*     */     //   441: aload_0
/*     */     //   442: invokevirtual a : ()Lme/konsolas/aac/it;
/*     */     //   445: invokevirtual b : ()Ljava/util/List;
/*     */     //   448: lload #15
/*     */     //   450: invokevirtual a : (Ljava/lang/String;Ljava/util/List;J)V
/*     */     //   453: goto -> 460
/*     */     //   456: astore #18
/*     */     //   458: iconst_0
/*     */     //   459: ireturn
/*     */     //   460: iconst_1
/*     */     //   461: ireturn
/*     */     // Line number table:
/*     */     //   Java source line number -> byte code offset
/*     */     //   #50	-> 99
/*     */     //   #129	-> 180
/*     */     //   #62	-> 238
/*     */     //   #23	-> 283
/*     */     //   #295	-> 285
/*     */     //   #250	-> 310
/*     */     //   #193	-> 366
/*     */     //   #235	-> 394
/*     */     //   #157	-> 430
/*     */     //   #218	-> 453
/*     */     //   #111	-> 456
/*     */     //   #37	-> 458
/*     */     //   #281	-> 460
/*     */     // Exception table:
/*     */     //   from	to	target	type
/*     */     //   99	120	123	javax/net/ssl/SSLPeerUnverifiedException
/*     */     //   113	147	150	javax/net/ssl/SSLPeerUnverifiedException
/*     */     //   134	164	167	javax/net/ssl/SSLPeerUnverifiedException
/*     */     //   198	211	214	javax/net/ssl/SSLPeerUnverifiedException
/*     */     //   208	227	227	javax/net/ssl/SSLPeerUnverifiedException
/*     */     //   261	269	272	javax/net/ssl/SSLPeerUnverifiedException
/*     */     //   285	299	299	javax/net/ssl/SSLPeerUnverifiedException
/*     */     //   310	333	336	javax/net/ssl/SSLPeerUnverifiedException
/*     */     //   315	350	353	javax/net/ssl/SSLPeerUnverifiedException
/*     */     //   366	383	383	javax/net/ssl/SSLPeerUnverifiedException
/*     */     //   394	414	417	javax/net/ssl/SSLPeerUnverifiedException
/*     */     //   430	453	456	javax/net/ssl/SSLPeerUnverifiedException }
/*     */   private void a(int paramInt1, long paramLong, int paramInt2, gC paramgC, cv paramcv) { // Byte code:
/*     */     //   0: getstatic me/konsolas/aac/el.u : J
/*     */     //   3: lload_2
/*     */     //   4: lxor
/*     */     //   5: lstore_2
/*     */     //   6: lload_2
/*     */     //   7: dup2
/*     */     //   8: ldc2_w 13841741349635
/*     */     //   11: lxor
/*     */     //   12: lstore #7
/*     */     //   14: dup2
/*     */     //   15: ldc2_w 98563647677405
/*     */     //   18: lxor
/*     */     //   19: lstore #9
/*     */     //   21: dup2
/*     */     //   22: ldc2_w 115625894211594
/*     */     //   25: lxor
/*     */     //   26: lstore #11
/*     */     //   28: dup2
/*     */     //   29: ldc2_w 59201914336930
/*     */     //   32: lxor
/*     */     //   33: dup2
/*     */     //   34: bipush #48
/*     */     //   36: lushr
/*     */     //   37: l2i
/*     */     //   38: istore #13
/*     */     //   40: dup2
/*     */     //   41: bipush #16
/*     */     //   43: lshl
/*     */     //   44: bipush #48
/*     */     //   46: lushr
/*     */     //   47: l2i
/*     */     //   48: istore #14
/*     */     //   50: dup2
/*     */     //   51: bipush #32
/*     */     //   53: lshl
/*     */     //   54: bipush #32
/*     */     //   56: lushr
/*     */     //   57: l2i
/*     */     //   58: istore #15
/*     */     //   60: pop2
/*     */     //   61: dup2
/*     */     //   62: ldc2_w 6696405204157
/*     */     //   65: lxor
/*     */     //   66: lstore #16
/*     */     //   68: pop2
/*     */     //   69: ldc2_w -350188706430931197
/*     */     //   72: lload_2
/*     */     //   73: <illegal opcode> w : (JJ)I
/*     */     //   78: aload_0
/*     */     //   79: getfield o : Lme/konsolas/aac/hQ;
/*     */     //   82: invokevirtual a : ()Ljava/net/Proxy;
/*     */     //   85: astore #19
/*     */     //   87: istore #18
/*     */     //   89: aload_0
/*     */     //   90: getfield o : Lme/konsolas/aac/hQ;
/*     */     //   93: invokevirtual a : ()Lme/konsolas/aac/jh;
/*     */     //   96: astore #20
/*     */     //   98: aload_0
/*     */     //   99: aload #19
/*     */     //   101: invokevirtual type : ()Ljava/net/Proxy$Type;
/*     */     //   104: getstatic java/net/Proxy$Type.DIRECT : Ljava/net/Proxy$Type;
/*     */     //   107: iload #18
/*     */     //   109: ifne -> 149
/*     */     //   112: if_acmpeq -> 152
/*     */     //   115: goto -> 128
/*     */     //   118: ldc2_w -340198453942894208
/*     */     //   121: lload_2
/*     */     //   122: <illegal opcode> w : (Ljava/lang/Throwable;JJ)Ljava/lang/Throwable;
/*     */     //   127: athrow
/*     */     //   128: aload #19
/*     */     //   130: invokevirtual type : ()Ljava/net/Proxy$Type;
/*     */     //   133: getstatic java/net/Proxy$Type.HTTP : Ljava/net/Proxy$Type;
/*     */     //   136: goto -> 149
/*     */     //   139: ldc2_w -340198453942894208
/*     */     //   142: lload_2
/*     */     //   143: <illegal opcode> w : (Ljava/lang/Throwable;JJ)Ljava/lang/Throwable;
/*     */     //   148: athrow
/*     */     //   149: if_acmpne -> 173
/*     */     //   152: aload #20
/*     */     //   154: invokevirtual a : ()Ljavax/net/SocketFactory;
/*     */     //   157: invokevirtual createSocket : ()Ljava/net/Socket;
/*     */     //   160: goto -> 182
/*     */     //   163: ldc2_w -340198453942894208
/*     */     //   166: lload_2
/*     */     //   167: <illegal opcode> w : (Ljava/lang/Throwable;JJ)Ljava/lang/Throwable;
/*     */     //   172: athrow
/*     */     //   173: new java/net/Socket
/*     */     //   176: dup
/*     */     //   177: aload #19
/*     */     //   179: invokespecial <init> : (Ljava/net/Proxy;)V
/*     */     //   182: putfield r : Ljava/net/Socket;
/*     */     //   185: aload #6
/*     */     //   187: aload #5
/*     */     //   189: aload_0
/*     */     //   190: getfield o : Lme/konsolas/aac/hQ;
/*     */     //   193: invokevirtual a : ()Ljava/net/InetSocketAddress;
/*     */     //   196: aload #19
/*     */     //   198: invokevirtual a : (Lme/konsolas/aac/gC;Ljava/net/InetSocketAddress;Ljava/net/Proxy;)V
/*     */     //   201: aload_0
/*     */     //   202: getfield r : Ljava/net/Socket;
/*     */     //   205: iload #4
/*     */     //   207: invokevirtual setSoTimeout : (I)V
/*     */     //   210: invokestatic c : ()Lme/konsolas/aac/io;
/*     */     //   213: aload_0
/*     */     //   214: getfield r : Ljava/net/Socket;
/*     */     //   217: aload_0
/*     */     //   218: getfield o : Lme/konsolas/aac/hQ;
/*     */     //   221: invokevirtual a : ()Ljava/net/InetSocketAddress;
/*     */     //   224: lload #11
/*     */     //   226: iload_1
/*     */     //   227: invokevirtual a : (Ljava/net/Socket;Ljava/net/InetSocketAddress;JI)V
/*     */     //   230: goto -> 291
/*     */     //   233: astore #21
/*     */     //   235: new java/net/ConnectException
/*     */     //   238: dup
/*     */     //   239: new java/lang/StringBuilder
/*     */     //   242: dup
/*     */     //   243: invokespecial <init> : ()V
/*     */     //   246: sipush #20504
/*     */     //   249: ldc2_w 1084967569127026909
/*     */     //   252: lload_2
/*     */     //   253: lxor
/*     */     //   254: <illegal opcode> a : (IJ)Ljava/lang/String;
/*     */     //   259: invokevirtual append : (Ljava/lang/String;)Ljava/lang/StringBuilder;
/*     */     //   262: aload_0
/*     */     //   263: getfield o : Lme/konsolas/aac/hQ;
/*     */     //   266: invokevirtual a : ()Ljava/net/InetSocketAddress;
/*     */     //   269: invokevirtual append : (Ljava/lang/Object;)Ljava/lang/StringBuilder;
/*     */     //   272: invokevirtual toString : ()Ljava/lang/String;
/*     */     //   275: invokespecial <init> : (Ljava/lang/String;)V
/*     */     //   278: astore #22
/*     */     //   280: aload #22
/*     */     //   282: aload #21
/*     */     //   284: invokevirtual initCause : (Ljava/lang/Throwable;)Ljava/lang/Throwable;
/*     */     //   287: pop
/*     */     //   288: aload #22
/*     */     //   290: athrow
/*     */     //   291: aload_0
/*     */     //   292: aload_0
/*     */     //   293: getfield r : Ljava/net/Socket;
/*     */     //   296: lload #16
/*     */     //   298: dup2_x1
/*     */     //   299: pop2
/*     */     //   300: invokestatic a : (JLjava/net/Socket;)Lme/konsolas/aac/hp;
/*     */     //   303: iload #13
/*     */     //   305: i2s
/*     */     //   306: swap
/*     */     //   307: iload #14
/*     */     //   309: i2c
/*     */     //   310: iload #15
/*     */     //   312: invokestatic a : (SLme/konsolas/aac/hp;CI)Lme/konsolas/aac/bX;
/*     */     //   315: putfield h : Lme/konsolas/aac/bX;
/*     */     //   318: aload_0
/*     */     //   319: aload_0
/*     */     //   320: getfield r : Ljava/net/Socket;
/*     */     //   323: lload #7
/*     */     //   325: dup2_x1
/*     */     //   326: pop2
/*     */     //   327: invokestatic a : (JLjava/net/Socket;)Lme/konsolas/aac/gp;
/*     */     //   330: lload #9
/*     */     //   332: invokestatic a : (Lme/konsolas/aac/gp;J)Lme/konsolas/aac/gi;
/*     */     //   335: putfield p : Lme/konsolas/aac/gi;
/*     */     //   338: goto -> 387
/*     */     //   341: astore #21
/*     */     //   343: sipush #10099
/*     */     //   346: ldc2_w 8074410287036319664
/*     */     //   349: lload_2
/*     */     //   350: lxor
/*     */     //   351: <illegal opcode> a : (IJ)Ljava/lang/String;
/*     */     //   356: aload #21
/*     */     //   358: invokevirtual getMessage : ()Ljava/lang/String;
/*     */     //   361: invokevirtual equals : (Ljava/lang/Object;)Z
/*     */     //   364: ifeq -> 387
/*     */     //   367: new java/io/IOException
/*     */     //   370: dup
/*     */     //   371: aload #21
/*     */     //   373: invokespecial <init> : (Ljava/lang/Throwable;)V
/*     */     //   376: athrow
/*     */     //   377: ldc2_w -340198453942894208
/*     */     //   380: lload_2
/*     */     //   381: <illegal opcode> w : (Ljava/lang/Throwable;JJ)Ljava/lang/Throwable;
/*     */     //   386: athrow
/*     */     //   387: return
/*     */     // Line number table:
/*     */     //   Java source line number -> byte code offset
/*     */     //   #58	-> 78
/*     */     //   #145	-> 89
/*     */     //   #288	-> 98
/*     */     //   #188	-> 152
/*     */     //   #29	-> 173
/*     */     //   #277	-> 185
/*     */     //   #271	-> 201
/*     */     //   #55	-> 210
/*     */     //   #272	-> 230
/*     */     //   #214	-> 233
/*     */     //   #187	-> 235
/*     */     //   #31	-> 280
/*     */     //   #216	-> 288
/*     */     //   #239	-> 291
/*     */     //   #83	-> 318
/*     */     //   #153	-> 338
/*     */     //   #72	-> 341
/*     */     //   #256	-> 343
/*     */     //   #280	-> 367
/*     */     //   #110	-> 387
/*     */     // Exception table:
/*     */     //   from	to	target	type
/*     */     //   98	115	118	java/net/ConnectException
/*     */     //   112	136	139	java/net/ConnectException
/*     */     //   149	163	163	java/net/ConnectException
/*     */     //   210	230	233	java/net/ConnectException
/*     */     //   291	338	341	java/lang/NullPointerException
/*     */     //   343	377	377	java/net/ConnectException }
/*     */   private void a(lK paramlK, int paramInt, gC paramgC, cv paramcv, long paramLong, byte paramByte) { // Byte code:
/*     */     //   0: lload #5
/*     */     //   2: bipush #8
/*     */     //   4: lshl
/*     */     //   5: iload #7
/*     */     //   7: i2l
/*     */     //   8: bipush #56
/*     */     //   10: lshl
/*     */     //   11: bipush #56
/*     */     //   13: lushr
/*     */     //   14: lor
/*     */     //   15: getstatic me/konsolas/aac/el.u : J
/*     */     //   18: lxor
/*     */     //   19: lstore #8
/*     */     //   21: lload #8
/*     */     //   23: dup2
/*     */     //   24: ldc2_w 27528097566452
/*     */     //   27: lxor
/*     */     //   28: lstore #10
/*     */     //   30: dup2
/*     */     //   31: ldc2_w 68881205246367
/*     */     //   34: lxor
/*     */     //   35: dup2
/*     */     //   36: bipush #48
/*     */     //   38: lushr
/*     */     //   39: l2i
/*     */     //   40: istore #12
/*     */     //   42: dup2
/*     */     //   43: bipush #16
/*     */     //   45: lshl
/*     */     //   46: bipush #32
/*     */     //   48: lushr
/*     */     //   49: l2i
/*     */     //   50: istore #13
/*     */     //   52: dup2
/*     */     //   53: bipush #48
/*     */     //   55: lshl
/*     */     //   56: bipush #48
/*     */     //   58: lushr
/*     */     //   59: l2i
/*     */     //   60: istore #14
/*     */     //   62: pop2
/*     */     //   63: pop2
/*     */     //   64: ldc2_w -1410279085367707571
/*     */     //   67: lload #8
/*     */     //   69: <illegal opcode> w : (JJ)I
/*     */     //   74: istore #15
/*     */     //   76: aload_0
/*     */     //   77: iload #15
/*     */     //   79: ifne -> 251
/*     */     //   82: getfield o : Lme/konsolas/aac/hQ;
/*     */     //   85: invokevirtual a : ()Lme/konsolas/aac/jh;
/*     */     //   88: invokevirtual a : ()Ljavax/net/ssl/SSLSocketFactory;
/*     */     //   91: ifnonnull -> 227
/*     */     //   94: goto -> 108
/*     */     //   97: ldc2_w -1438600119469287730
/*     */     //   100: lload #8
/*     */     //   102: <illegal opcode> w : (Ljava/lang/Throwable;JJ)Ljava/lang/Throwable;
/*     */     //   107: athrow
/*     */     //   108: iload #7
/*     */     //   110: ifge -> 226
/*     */     //   113: aload_0
/*     */     //   114: iload #15
/*     */     //   116: ifne -> 220
/*     */     //   119: goto -> 133
/*     */     //   122: ldc2_w -1438600119469287730
/*     */     //   125: lload #8
/*     */     //   127: <illegal opcode> w : (Ljava/lang/Throwable;JJ)Ljava/lang/Throwable;
/*     */     //   132: athrow
/*     */     //   133: iload #7
/*     */     //   135: ifge -> 212
/*     */     //   138: getfield o : Lme/konsolas/aac/hQ;
/*     */     //   141: invokevirtual a : ()Lme/konsolas/aac/jh;
/*     */     //   144: invokevirtual b : ()Ljava/util/List;
/*     */     //   147: getstatic me/konsolas/aac/le.H2_PRIOR_KNOWLEDGE : Lme/konsolas/aac/le;
/*     */     //   150: invokeinterface contains : (Ljava/lang/Object;)Z
/*     */     //   155: ifeq -> 211
/*     */     //   158: goto -> 172
/*     */     //   161: ldc2_w -1438600119469287730
/*     */     //   164: lload #8
/*     */     //   166: <illegal opcode> w : (Ljava/lang/Throwable;JJ)Ljava/lang/Throwable;
/*     */     //   171: athrow
/*     */     //   172: aload_0
/*     */     //   173: aload_0
/*     */     //   174: getfield r : Ljava/net/Socket;
/*     */     //   177: putfield n : Ljava/net/Socket;
/*     */     //   180: aload_0
/*     */     //   181: getstatic me/konsolas/aac/le.H2_PRIOR_KNOWLEDGE : Lme/konsolas/aac/le;
/*     */     //   184: putfield i : Lme/konsolas/aac/le;
/*     */     //   187: aload_0
/*     */     //   188: iload #12
/*     */     //   190: i2c
/*     */     //   191: iload_2
/*     */     //   192: iload #13
/*     */     //   194: iload #14
/*     */     //   196: invokespecial a : (CIII)V
/*     */     //   199: return
/*     */     //   200: ldc2_w -1438600119469287730
/*     */     //   203: lload #8
/*     */     //   205: <illegal opcode> w : (Ljava/lang/Throwable;JJ)Ljava/lang/Throwable;
/*     */     //   210: athrow
/*     */     //   211: aload_0
/*     */     //   212: aload_0
/*     */     //   213: getfield r : Ljava/net/Socket;
/*     */     //   216: putfield n : Ljava/net/Socket;
/*     */     //   219: aload_0
/*     */     //   220: getstatic me/konsolas/aac/le.HTTP_1_1 : Lme/konsolas/aac/le;
/*     */     //   223: putfield i : Lme/konsolas/aac/le;
/*     */     //   226: return
/*     */     //   227: aload #4
/*     */     //   229: aload_3
/*     */     //   230: invokevirtual f : (Lme/konsolas/aac/gC;)V
/*     */     //   233: aload_0
/*     */     //   234: lload #10
/*     */     //   236: aload_1
/*     */     //   237: invokespecial a : (JLme/konsolas/aac/lK;)V
/*     */     //   240: aload #4
/*     */     //   242: aload_3
/*     */     //   243: aload_0
/*     */     //   244: getfield b : Lme/konsolas/aac/it;
/*     */     //   247: invokevirtual a : (Lme/konsolas/aac/gC;Lme/konsolas/aac/it;)V
/*     */     //   250: aload_0
/*     */     //   251: iload #15
/*     */     //   253: iload #7
/*     */     //   255: ifgt -> 302
/*     */     //   258: ifne -> 299
/*     */     //   261: getfield i : Lme/konsolas/aac/le;
/*     */     //   264: getstatic me/konsolas/aac/le.HTTP_2 : Lme/konsolas/aac/le;
/*     */     //   267: if_acmpne -> 310
/*     */     //   270: goto -> 284
/*     */     //   273: ldc2_w -1438600119469287730
/*     */     //   276: lload #8
/*     */     //   278: <illegal opcode> w : (Ljava/lang/Throwable;JJ)Ljava/lang/Throwable;
/*     */     //   283: athrow
/*     */     //   284: aload_0
/*     */     //   285: goto -> 299
/*     */     //   288: ldc2_w -1438600119469287730
/*     */     //   291: lload #8
/*     */     //   293: <illegal opcode> w : (Ljava/lang/Throwable;JJ)Ljava/lang/Throwable;
/*     */     //   298: athrow
/*     */     //   299: iload #12
/*     */     //   301: i2c
/*     */     //   302: iload_2
/*     */     //   303: iload #13
/*     */     //   305: iload #14
/*     */     //   307: invokespecial a : (CIII)V
/*     */     //   310: return
/*     */     // Line number table:
/*     */     //   Java source line number -> byte code offset
/*     */     //   #70	-> 76
/*     */     //   #65	-> 108
/*     */     //   #127	-> 172
/*     */     //   #154	-> 180
/*     */     //   #152	-> 187
/*     */     //   #45	-> 199
/*     */     //   #230	-> 211
/*     */     //   #87	-> 219
/*     */     //   #182	-> 226
/*     */     //   #124	-> 227
/*     */     //   #77	-> 233
/*     */     //   #229	-> 240
/*     */     //   #227	-> 250
/*     */     //   #172	-> 284
/*     */     //   #130	-> 310
/*     */     // Exception table:
/*     */     //   from	to	target	type
/*     */     //   76	94	97	java/io/IOException
/*     */     //   82	119	122	java/io/IOException
/*     */     //   108	158	161	java/io/IOException
/*     */     //   133	200	200	java/io/IOException
/*     */     //   251	270	273	java/io/IOException
/*     */     //   261	285	288	java/io/IOException }
/*     */   public void a(int paramInt1, int paramInt2, int paramInt3, long paramLong, int paramInt4, boolean paramBoolean, gC paramgC, cv paramcv) { // Byte code:
/*     */     //   0: getstatic me/konsolas/aac/el.u : J
/*     */     //   3: lload #4
/*     */     //   5: lxor
/*     */     //   6: lstore #4
/*     */     //   8: lload #4
/*     */     //   10: dup2
/*     */     //   11: ldc2_w 35904963040723
/*     */     //   14: lxor
/*     */     //   15: dup2
/*     */     //   16: bipush #32
/*     */     //   18: lushr
/*     */     //   19: l2i
/*     */     //   20: istore #10
/*     */     //   22: dup2
/*     */     //   23: bipush #32
/*     */     //   25: lshl
/*     */     //   26: bipush #48
/*     */     //   28: lushr
/*     */     //   29: l2i
/*     */     //   30: istore #11
/*     */     //   32: dup2
/*     */     //   33: bipush #48
/*     */     //   35: lshl
/*     */     //   36: bipush #48
/*     */     //   38: lushr
/*     */     //   39: l2i
/*     */     //   40: istore #12
/*     */     //   42: pop2
/*     */     //   43: dup2
/*     */     //   44: ldc2_w 58418631565271
/*     */     //   47: lxor
/*     */     //   48: lstore #13
/*     */     //   50: dup2
/*     */     //   51: ldc2_w 65673169062006
/*     */     //   54: lxor
/*     */     //   55: lstore #15
/*     */     //   57: dup2
/*     */     //   58: ldc2_w 32572984095567
/*     */     //   61: lxor
/*     */     //   62: lstore #17
/*     */     //   64: dup2
/*     */     //   65: ldc2_w 90605364396313
/*     */     //   68: lxor
/*     */     //   69: dup2
/*     */     //   70: bipush #8
/*     */     //   72: lushr
/*     */     //   73: lstore #19
/*     */     //   75: dup2
/*     */     //   76: bipush #56
/*     */     //   78: lshl
/*     */     //   79: bipush #56
/*     */     //   81: lushr
/*     */     //   82: l2i
/*     */     //   83: istore #21
/*     */     //   85: pop2
/*     */     //   86: dup2
/*     */     //   87: ldc2_w 51001466659854
/*     */     //   90: lxor
/*     */     //   91: lstore #22
/*     */     //   93: dup2
/*     */     //   94: ldc2_w 6411806270702
/*     */     //   97: lxor
/*     */     //   98: lstore #24
/*     */     //   100: dup2
/*     */     //   101: ldc2_w 32957199111767
/*     */     //   104: lxor
/*     */     //   105: lstore #26
/*     */     //   107: dup2
/*     */     //   108: ldc2_w 25711700303108
/*     */     //   111: lxor
/*     */     //   112: dup2
/*     */     //   113: bipush #32
/*     */     //   115: lushr
/*     */     //   116: l2i
/*     */     //   117: istore #28
/*     */     //   119: dup2
/*     */     //   120: bipush #32
/*     */     //   122: lshl
/*     */     //   123: bipush #48
/*     */     //   125: lushr
/*     */     //   126: l2i
/*     */     //   127: istore #29
/*     */     //   129: dup2
/*     */     //   130: bipush #48
/*     */     //   132: lshl
/*     */     //   133: bipush #48
/*     */     //   135: lushr
/*     */     //   136: l2i
/*     */     //   137: istore #30
/*     */     //   139: pop2
/*     */     //   140: pop2
/*     */     //   141: ldc2_w 1018943300639520750
/*     */     //   144: lload #4
/*     */     //   146: <illegal opcode> w : (JJ)I
/*     */     //   151: istore #31
/*     */     //   153: aload_0
/*     */     //   154: getfield i : Lme/konsolas/aac/le;
/*     */     //   157: ifnull -> 193
/*     */     //   160: new java/lang/IllegalStateException
/*     */     //   163: dup
/*     */     //   164: sipush #23830
/*     */     //   167: ldc2_w 3326091539979585642
/*     */     //   170: lload #4
/*     */     //   172: lxor
/*     */     //   173: <illegal opcode> a : (IJ)Ljava/lang/String;
/*     */     //   178: invokespecial <init> : (Ljava/lang/String;)V
/*     */     //   181: athrow
/*     */     //   182: ldc2_w 1071860516974769191
/*     */     //   185: lload #4
/*     */     //   187: <illegal opcode> w : (Ljava/lang/Throwable;JJ)Ljava/lang/Throwable;
/*     */     //   192: athrow
/*     */     //   193: aconst_null
/*     */     //   194: astore #32
/*     */     //   196: aload_0
/*     */     //   197: getfield o : Lme/konsolas/aac/hQ;
/*     */     //   200: invokevirtual a : ()Lme/konsolas/aac/jh;
/*     */     //   203: invokevirtual a : ()Ljava/util/List;
/*     */     //   206: astore #33
/*     */     //   208: new me/konsolas/aac/lK
/*     */     //   211: dup
/*     */     //   212: aload #33
/*     */     //   214: invokespecial <init> : (Ljava/util/List;)V
/*     */     //   217: astore #34
/*     */     //   219: aload_0
/*     */     //   220: getfield o : Lme/konsolas/aac/hQ;
/*     */     //   223: invokevirtual a : ()Lme/konsolas/aac/jh;
/*     */     //   226: lload #4
/*     */     //   228: lconst_0
/*     */     //   229: lcmp
/*     */     //   230: ifle -> 461
/*     */     //   233: iload #31
/*     */     //   235: ifeq -> 461
/*     */     //   238: invokevirtual a : ()Ljavax/net/ssl/SSLSocketFactory;
/*     */     //   241: ifnonnull -> 440
/*     */     //   244: goto -> 258
/*     */     //   247: ldc2_w 1071860516974769191
/*     */     //   250: lload #4
/*     */     //   252: <illegal opcode> w : (Ljava/lang/Throwable;JJ)Ljava/lang/Throwable;
/*     */     //   257: athrow
/*     */     //   258: aload #33
/*     */     //   260: getstatic me/konsolas/aac/kB.f : Lme/konsolas/aac/kB;
/*     */     //   263: invokeinterface contains : (Ljava/lang/Object;)Z
/*     */     //   268: ifne -> 325
/*     */     //   271: goto -> 285
/*     */     //   274: ldc2_w 1071860516974769191
/*     */     //   277: lload #4
/*     */     //   279: <illegal opcode> w : (Ljava/lang/Throwable;JJ)Ljava/lang/Throwable;
/*     */     //   284: athrow
/*     */     //   285: new me/konsolas/aac/jj
/*     */     //   288: dup
/*     */     //   289: new java/net/UnknownServiceException
/*     */     //   292: dup
/*     */     //   293: sipush #2487
/*     */     //   296: ldc2_w 3076547828099325130
/*     */     //   299: lload #4
/*     */     //   301: lxor
/*     */     //   302: <illegal opcode> a : (IJ)Ljava/lang/String;
/*     */     //   307: invokespecial <init> : (Ljava/lang/String;)V
/*     */     //   310: invokespecial <init> : (Ljava/io/IOException;)V
/*     */     //   313: athrow
/*     */     //   314: ldc2_w 1071860516974769191
/*     */     //   317: lload #4
/*     */     //   319: <illegal opcode> w : (Ljava/lang/Throwable;JJ)Ljava/lang/Throwable;
/*     */     //   324: athrow
/*     */     //   325: aload_0
/*     */     //   326: getfield o : Lme/konsolas/aac/hQ;
/*     */     //   329: invokevirtual a : ()Lme/konsolas/aac/jh;
/*     */     //   332: invokevirtual a : ()Lme/konsolas/aac/l6;
/*     */     //   335: invokevirtual d : ()Ljava/lang/String;
/*     */     //   338: astore #35
/*     */     //   340: invokestatic c : ()Lme/konsolas/aac/io;
/*     */     //   343: lload #13
/*     */     //   345: aload #35
/*     */     //   347: invokevirtual a : (JLjava/lang/String;)Z
/*     */     //   350: lload #4
/*     */     //   352: lconst_0
/*     */     //   353: lcmp
/*     */     //   354: ifle -> 437
/*     */     //   357: ifne -> 435
/*     */     //   360: new me/konsolas/aac/jj
/*     */     //   363: dup
/*     */     //   364: new java/net/UnknownServiceException
/*     */     //   367: dup
/*     */     //   368: new java/lang/StringBuilder
/*     */     //   371: dup
/*     */     //   372: invokespecial <init> : ()V
/*     */     //   375: sipush #26279
/*     */     //   378: ldc2_w 5302557235916633045
/*     */     //   381: lload #4
/*     */     //   383: lxor
/*     */     //   384: <illegal opcode> a : (IJ)Ljava/lang/String;
/*     */     //   389: invokevirtual append : (Ljava/lang/String;)Ljava/lang/StringBuilder;
/*     */     //   392: aload #35
/*     */     //   394: invokevirtual append : (Ljava/lang/String;)Ljava/lang/StringBuilder;
/*     */     //   397: sipush #1237
/*     */     //   400: ldc2_w 5019117755467469243
/*     */     //   403: lload #4
/*     */     //   405: lxor
/*     */     //   406: <illegal opcode> a : (IJ)Ljava/lang/String;
/*     */     //   411: invokevirtual append : (Ljava/lang/String;)Ljava/lang/StringBuilder;
/*     */     //   414: invokevirtual toString : ()Ljava/lang/String;
/*     */     //   417: invokespecial <init> : (Ljava/lang/String;)V
/*     */     //   420: invokespecial <init> : (Ljava/io/IOException;)V
/*     */     //   423: athrow
/*     */     //   424: ldc2_w 1071860516974769191
/*     */     //   427: lload #4
/*     */     //   429: <illegal opcode> w : (Ljava/lang/Throwable;JJ)Ljava/lang/Throwable;
/*     */     //   434: athrow
/*     */     //   435: iload #31
/*     */     //   437: ifne -> 515
/*     */     //   440: aload_0
/*     */     //   441: getfield o : Lme/konsolas/aac/hQ;
/*     */     //   444: invokevirtual a : ()Lme/konsolas/aac/jh;
/*     */     //   447: goto -> 461
/*     */     //   450: ldc2_w 1071860516974769191
/*     */     //   453: lload #4
/*     */     //   455: <illegal opcode> w : (Ljava/lang/Throwable;JJ)Ljava/lang/Throwable;
/*     */     //   460: athrow
/*     */     //   461: invokevirtual b : ()Ljava/util/List;
/*     */     //   464: getstatic me/konsolas/aac/le.H2_PRIOR_KNOWLEDGE : Lme/konsolas/aac/le;
/*     */     //   467: invokeinterface contains : (Ljava/lang/Object;)Z
/*     */     //   472: ifeq -> 515
/*     */     //   475: new me/konsolas/aac/jj
/*     */     //   478: dup
/*     */     //   479: new java/net/UnknownServiceException
/*     */     //   482: dup
/*     */     //   483: sipush #15149
/*     */     //   486: ldc2_w 300093551928553052
/*     */     //   489: lload #4
/*     */     //   491: lxor
/*     */     //   492: <illegal opcode> a : (IJ)Ljava/lang/String;
/*     */     //   497: invokespecial <init> : (Ljava/lang/String;)V
/*     */     //   500: invokespecial <init> : (Ljava/io/IOException;)V
/*     */     //   503: athrow
/*     */     //   504: ldc2_w 1071860516974769191
/*     */     //   507: lload #4
/*     */     //   509: <illegal opcode> w : (Ljava/lang/Throwable;JJ)Ljava/lang/Throwable;
/*     */     //   514: athrow
/*     */     //   515: aload_0
/*     */     //   516: iload #31
/*     */     //   518: lload #4
/*     */     //   520: lconst_0
/*     */     //   521: lcmp
/*     */     //   522: ifle -> 633
/*     */     //   525: ifeq -> 632
/*     */     //   528: getfield o : Lme/konsolas/aac/hQ;
/*     */     //   531: iload #10
/*     */     //   533: iload #11
/*     */     //   535: i2c
/*     */     //   536: iload #12
/*     */     //   538: i2c
/*     */     //   539: invokevirtual a : (ICC)Z
/*     */     //   542: ifeq -> 631
/*     */     //   545: goto -> 559
/*     */     //   548: ldc2_w 1071860516974769191
/*     */     //   551: lload #4
/*     */     //   553: <illegal opcode> w : (Ljava/lang/Throwable;JJ)Ljava/lang/Throwable;
/*     */     //   558: athrow
/*     */     //   559: aload_0
/*     */     //   560: iload_1
/*     */     //   561: iload_2
/*     */     //   562: iload_3
/*     */     //   563: lload #22
/*     */     //   565: aload #8
/*     */     //   567: aload #9
/*     */     //   569: invokespecial a : (IIIJLme/konsolas/aac/gC;Lme/konsolas/aac/cv;)V
/*     */     //   572: lload #4
/*     */     //   574: lconst_0
/*     */     //   575: lcmp
/*     */     //   576: ifle -> 685
/*     */     //   579: aload_0
/*     */     //   580: iload #31
/*     */     //   582: ifeq -> 644
/*     */     //   585: goto -> 599
/*     */     //   588: ldc2_w 1071860516974769191
/*     */     //   591: lload #4
/*     */     //   593: <illegal opcode> w : (Ljava/lang/Throwable;JJ)Ljava/lang/Throwable;
/*     */     //   598: athrow
/*     */     //   599: getfield r : Ljava/net/Socket;
/*     */     //   602: ifnonnull -> 643
/*     */     //   605: goto -> 619
/*     */     //   608: ldc2_w 1071860516974769191
/*     */     //   611: lload #4
/*     */     //   613: <illegal opcode> w : (Ljava/lang/Throwable;JJ)Ljava/lang/Throwable;
/*     */     //   618: athrow
/*     */     //   619: lload #4
/*     */     //   621: lconst_0
/*     */     //   622: lcmp
/*     */     //   623: ifle -> 924
/*     */     //   626: iload #31
/*     */     //   628: ifne -> 924
/*     */     //   631: aload_0
/*     */     //   632: iload_1
/*     */     //   633: lload #26
/*     */     //   635: iload_2
/*     */     //   636: aload #8
/*     */     //   638: aload #9
/*     */     //   640: invokespecial a : (IJILme/konsolas/aac/gC;Lme/konsolas/aac/cv;)V
/*     */     //   643: aload_0
/*     */     //   644: aload #34
/*     */     //   646: iload #6
/*     */     //   648: aload #8
/*     */     //   650: aload #9
/*     */     //   652: lload #19
/*     */     //   654: iload #21
/*     */     //   656: i2b
/*     */     //   657: invokespecial a : (Lme/konsolas/aac/lK;ILme/konsolas/aac/gC;Lme/konsolas/aac/cv;JB)V
/*     */     //   660: aload #9
/*     */     //   662: aload #8
/*     */     //   664: aload_0
/*     */     //   665: getfield o : Lme/konsolas/aac/hQ;
/*     */     //   668: invokevirtual a : ()Ljava/net/InetSocketAddress;
/*     */     //   671: aload_0
/*     */     //   672: getfield o : Lme/konsolas/aac/hQ;
/*     */     //   675: invokevirtual a : ()Ljava/net/Proxy;
/*     */     //   678: aload_0
/*     */     //   679: getfield i : Lme/konsolas/aac/le;
/*     */     //   682: invokevirtual a : (Lme/konsolas/aac/gC;Ljava/net/InetSocketAddress;Ljava/net/Proxy;Lme/konsolas/aac/le;)V
/*     */     //   685: goto -> 924
/*     */     //   688: astore #35
/*     */     //   690: aload_0
/*     */     //   691: getfield n : Ljava/net/Socket;
/*     */     //   694: lload #24
/*     */     //   696: dup2_x1
/*     */     //   697: pop2
/*     */     //   698: invokestatic a : (JLjava/net/Socket;)V
/*     */     //   701: aload_0
/*     */     //   702: getfield r : Ljava/net/Socket;
/*     */     //   705: lload #24
/*     */     //   707: dup2_x1
/*     */     //   708: pop2
/*     */     //   709: invokestatic a : (JLjava/net/Socket;)V
/*     */     //   712: aload_0
/*     */     //   713: aconst_null
/*     */     //   714: putfield n : Ljava/net/Socket;
/*     */     //   717: aload_0
/*     */     //   718: aconst_null
/*     */     //   719: putfield r : Ljava/net/Socket;
/*     */     //   722: aload_0
/*     */     //   723: aconst_null
/*     */     //   724: putfield h : Lme/konsolas/aac/bX;
/*     */     //   727: aload_0
/*     */     //   728: aconst_null
/*     */     //   729: putfield p : Lme/konsolas/aac/gi;
/*     */     //   732: aload_0
/*     */     //   733: aconst_null
/*     */     //   734: putfield b : Lme/konsolas/aac/it;
/*     */     //   737: aload_0
/*     */     //   738: aconst_null
/*     */     //   739: putfield i : Lme/konsolas/aac/le;
/*     */     //   742: aload_0
/*     */     //   743: aconst_null
/*     */     //   744: putfield k : Lme/konsolas/aac/cZ;
/*     */     //   747: aload #9
/*     */     //   749: aload #8
/*     */     //   751: aload_0
/*     */     //   752: getfield o : Lme/konsolas/aac/hQ;
/*     */     //   755: invokevirtual a : ()Ljava/net/InetSocketAddress;
/*     */     //   758: aload_0
/*     */     //   759: getfield o : Lme/konsolas/aac/hQ;
/*     */     //   762: invokevirtual a : ()Ljava/net/Proxy;
/*     */     //   765: aconst_null
/*     */     //   766: aload #35
/*     */     //   768: invokevirtual a : (Lme/konsolas/aac/gC;Ljava/net/InetSocketAddress;Ljava/net/Proxy;Lme/konsolas/aac/le;Ljava/io/IOException;)V
/*     */     //   771: aload #32
/*     */     //   773: iload #31
/*     */     //   775: ifeq -> 834
/*     */     //   778: ifnonnull -> 818
/*     */     //   781: goto -> 795
/*     */     //   784: ldc2_w 1071860516974769191
/*     */     //   787: lload #4
/*     */     //   789: <illegal opcode> w : (Ljava/lang/Throwable;JJ)Ljava/lang/Throwable;
/*     */     //   794: athrow
/*     */     //   795: new me/konsolas/aac/jj
/*     */     //   798: dup
/*     */     //   799: aload #35
/*     */     //   801: invokespecial <init> : (Ljava/io/IOException;)V
/*     */     //   804: astore #32
/*     */     //   806: iload #31
/*     */     //   808: lload #4
/*     */     //   810: lconst_0
/*     */     //   811: lcmp
/*     */     //   812: iflt -> 843
/*     */     //   815: ifne -> 841
/*     */     //   818: aload #32
/*     */     //   820: goto -> 834
/*     */     //   823: ldc2_w 1071860516974769191
/*     */     //   826: lload #4
/*     */     //   828: <illegal opcode> w : (Ljava/lang/Throwable;JJ)Ljava/lang/Throwable;
/*     */     //   833: athrow
/*     */     //   834: lload #15
/*     */     //   836: aload #35
/*     */     //   838: invokevirtual a : (JLjava/io/IOException;)V
/*     */     //   841: iload #7
/*     */     //   843: lload #4
/*     */     //   845: lconst_0
/*     */     //   846: lcmp
/*     */     //   847: ifle -> 895
/*     */     //   850: iload #31
/*     */     //   852: ifeq -> 895
/*     */     //   855: ifeq -> 905
/*     */     //   858: goto -> 872
/*     */     //   861: ldc2_w 1071860516974769191
/*     */     //   864: lload #4
/*     */     //   866: <illegal opcode> w : (Ljava/lang/Throwable;JJ)Ljava/lang/Throwable;
/*     */     //   871: athrow
/*     */     //   872: aload #34
/*     */     //   874: aload #35
/*     */     //   876: lload #17
/*     */     //   878: invokevirtual a : (Ljava/io/IOException;J)Z
/*     */     //   881: goto -> 895
/*     */     //   884: ldc2_w 1071860516974769191
/*     */     //   887: lload #4
/*     */     //   889: <illegal opcode> w : (Ljava/lang/Throwable;JJ)Ljava/lang/Throwable;
/*     */     //   894: athrow
/*     */     //   895: lload #4
/*     */     //   897: lconst_0
/*     */     //   898: lcmp
/*     */     //   899: ifle -> 921
/*     */     //   902: ifne -> 919
/*     */     //   905: aload #32
/*     */     //   907: athrow
/*     */     //   908: ldc2_w 1071860516974769191
/*     */     //   911: lload #4
/*     */     //   913: <illegal opcode> w : (Ljava/lang/Throwable;JJ)Ljava/lang/Throwable;
/*     */     //   918: athrow
/*     */     //   919: iload #31
/*     */     //   921: ifne -> 515
/*     */     //   924: aload_0
/*     */     //   925: iload #31
/*     */     //   927: ifeq -> 1042
/*     */     //   930: getfield o : Lme/konsolas/aac/hQ;
/*     */     //   933: iload #10
/*     */     //   935: iload #11
/*     */     //   937: i2c
/*     */     //   938: iload #12
/*     */     //   940: i2c
/*     */     //   941: invokevirtual a : (ICC)Z
/*     */     //   944: ifeq -> 1041
/*     */     //   947: goto -> 961
/*     */     //   950: ldc2_w 1071860516974769191
/*     */     //   953: lload #4
/*     */     //   955: <illegal opcode> w : (Ljava/lang/Throwable;JJ)Ljava/lang/Throwable;
/*     */     //   960: athrow
/*     */     //   961: aload_0
/*     */     //   962: iload #31
/*     */     //   964: lload #4
/*     */     //   966: lconst_0
/*     */     //   967: lcmp
/*     */     //   968: iflt -> 1044
/*     */     //   971: ifeq -> 1042
/*     */     //   974: goto -> 988
/*     */     //   977: ldc2_w 1071860516974769191
/*     */     //   980: lload #4
/*     */     //   982: <illegal opcode> w : (Ljava/lang/Throwable;JJ)Ljava/lang/Throwable;
/*     */     //   987: athrow
/*     */     //   988: getfield r : Ljava/net/Socket;
/*     */     //   991: ifnonnull -> 1041
/*     */     //   994: goto -> 1008
/*     */     //   997: ldc2_w 1071860516974769191
/*     */     //   1000: lload #4
/*     */     //   1002: <illegal opcode> w : (Ljava/lang/Throwable;JJ)Ljava/lang/Throwable;
/*     */     //   1007: athrow
/*     */     //   1008: new java/net/ProtocolException
/*     */     //   1011: dup
/*     */     //   1012: sipush #19819
/*     */     //   1015: ldc2_w 8403592349975795731
/*     */     //   1018: lload #4
/*     */     //   1020: lxor
/*     */     //   1021: <illegal opcode> a : (IJ)Ljava/lang/String;
/*     */     //   1026: invokespecial <init> : (Ljava/lang/String;)V
/*     */     //   1029: astore #35
/*     */     //   1031: new me/konsolas/aac/jj
/*     */     //   1034: dup
/*     */     //   1035: aload #35
/*     */     //   1037: invokespecial <init> : (Ljava/io/IOException;)V
/*     */     //   1040: athrow
/*     */     //   1041: aload_0
/*     */     //   1042: iload #31
/*     */     //   1044: ifeq -> 1082
/*     */     //   1047: getfield k : Lme/konsolas/aac/cZ;
/*     */     //   1050: ifnull -> 1120
/*     */     //   1053: goto -> 1067
/*     */     //   1056: ldc2_w 1071860516974769191
/*     */     //   1059: lload #4
/*     */     //   1061: <illegal opcode> w : (Ljava/lang/Throwable;JJ)Ljava/lang/Throwable;
/*     */     //   1066: athrow
/*     */     //   1067: aload_0
/*     */     //   1068: goto -> 1082
/*     */     //   1071: ldc2_w 1071860516974769191
/*     */     //   1074: lload #4
/*     */     //   1076: <illegal opcode> w : (Ljava/lang/Throwable;JJ)Ljava/lang/Throwable;
/*     */     //   1081: athrow
/*     */     //   1082: getfield c : Lme/konsolas/aac/gL;
/*     */     //   1085: dup
/*     */     //   1086: astore #35
/*     */     //   1088: monitorenter
/*     */     //   1089: aload_0
/*     */     //   1090: aload_0
/*     */     //   1091: getfield k : Lme/konsolas/aac/cZ;
/*     */     //   1094: iload #28
/*     */     //   1096: iload #29
/*     */     //   1098: iload #30
/*     */     //   1100: invokevirtual a : (III)I
/*     */     //   1103: putfield t : I
/*     */     //   1106: aload #35
/*     */     //   1108: monitorexit
/*     */     //   1109: goto -> 1120
/*     */     //   1112: astore #36
/*     */     //   1114: aload #35
/*     */     //   1116: monitorexit
/*     */     //   1117: aload #36
/*     */     //   1119: athrow
/*     */     //   1120: lload #4
/*     */     //   1122: lconst_0
/*     */     //   1123: lcmp
/*     */     //   1124: iflt -> 1155
/*     */     //   1127: ldc2_w 1069112405623786101
/*     */     //   1130: lload #4
/*     */     //   1132: <illegal opcode> w : (JJ)[Lme/konsolas/aac/aN;
/*     */     //   1137: ifnull -> 1169
/*     */     //   1140: iinc #31, 1
/*     */     //   1143: iload #31
/*     */     //   1145: ldc2_w 1083977801775846991
/*     */     //   1148: lload #4
/*     */     //   1150: <illegal opcode> w : (IJJ)V
/*     */     //   1155: goto -> 1169
/*     */     //   1158: ldc2_w 1071860516974769191
/*     */     //   1161: lload #4
/*     */     //   1163: <illegal opcode> w : (Ljava/lang/Throwable;JJ)Ljava/lang/Throwable;
/*     */     //   1168: athrow
/*     */     //   1169: return
/*     */     // Line number table:
/*     */     //   Java source line number -> byte code offset
/*     */     //   #96	-> 153
/*     */     //   #155	-> 193
/*     */     //   #102	-> 196
/*     */     //   #255	-> 208
/*     */     //   #168	-> 219
/*     */     //   #13	-> 258
/*     */     //   #278	-> 285
/*     */     //   #290	-> 325
/*     */     //   #228	-> 340
/*     */     //   #257	-> 360
/*     */     //   #114	-> 435
/*     */     //   #279	-> 440
/*     */     //   #32	-> 475
/*     */     //   #64	-> 515
/*     */     //   #254	-> 559
/*     */     //   #166	-> 572
/*     */     //   #123	-> 619
/*     */     //   #209	-> 631
/*     */     //   #74	-> 643
/*     */     //   #95	-> 660
/*     */     //   #296	-> 685
/*     */     //   #84	-> 688
/*     */     //   #12	-> 690
/*     */     //   #192	-> 701
/*     */     //   #53	-> 712
/*     */     //   #184	-> 717
/*     */     //   #283	-> 722
/*     */     //   #7	-> 727
/*     */     //   #265	-> 732
/*     */     //   #5	-> 737
/*     */     //   #233	-> 742
/*     */     //   #236	-> 747
/*     */     //   #266	-> 771
/*     */     //   #156	-> 795
/*     */     //   #38	-> 818
/*     */     //   #219	-> 841
/*     */     //   #36	-> 905
/*     */     //   #264	-> 919
/*     */     //   #162	-> 924
/*     */     //   #115	-> 1008
/*     */     //   #221	-> 1031
/*     */     //   #159	-> 1041
/*     */     //   #224	-> 1067
/*     */     //   #57	-> 1089
/*     */     //   #291	-> 1106
/*     */     //   #294	-> 1120
/*     */     // Exception table:
/*     */     //   from	to	target	type
/*     */     //   153	182	182	java/io/IOException
/*     */     //   219	244	247	java/io/IOException
/*     */     //   238	271	274	java/io/IOException
/*     */     //   258	314	314	java/io/IOException
/*     */     //   340	424	424	java/io/IOException
/*     */     //   435	447	450	java/io/IOException
/*     */     //   461	504	504	java/io/IOException
/*     */     //   515	545	548	java/io/IOException
/*     */     //   515	619	688	java/io/IOException
/*     */     //   528	585	588	java/io/IOException
/*     */     //   559	605	608	java/io/IOException
/*     */     //   631	685	688	java/io/IOException
/*     */     //   690	781	784	java/io/IOException
/*     */     //   806	820	823	java/io/IOException
/*     */     //   841	858	861	java/io/IOException
/*     */     //   855	881	884	java/io/IOException
/*     */     //   895	908	908	java/io/IOException
/*     */     //   924	947	950	java/io/IOException
/*     */     //   930	974	977	java/io/IOException
/*     */     //   961	994	997	java/io/IOException
/*     */     //   1042	1053	1056	java/io/IOException
/*     */     //   1047	1068	1071	java/io/IOException
/*     */     //   1089	1109	1112	finally
/*     */     //   1112	1117	1112	finally
/*     */     //   1120	1155	1158	java/io/IOException }
/*     */   void a(short paramShort1, int paramInt, short paramShort2, @Nullable IOException paramIOException) { // Byte code:
/*     */     //   0: iload_1
/*     */     //   1: i2l
/*     */     //   2: bipush #48
/*     */     //   4: lshl
/*     */     //   5: iload_2
/*     */     //   6: i2l
/*     */     //   7: bipush #32
/*     */     //   9: lshl
/*     */     //   10: bipush #16
/*     */     //   12: lushr
/*     */     //   13: lor
/*     */     //   14: iload_3
/*     */     //   15: i2l
/*     */     //   16: bipush #48
/*     */     //   18: lshl
/*     */     //   19: bipush #48
/*     */     //   21: lushr
/*     */     //   22: lor
/*     */     //   23: getstatic me/konsolas/aac/el.u : J
/*     */     //   26: lxor
/*     */     //   27: lstore #5
/*     */     //   29: lload #5
/*     */     //   31: dup2
/*     */     //   32: ldc2_w 73609221904280
/*     */     //   35: lxor
/*     */     //   36: lstore #7
/*     */     //   38: dup2
/*     */     //   39: ldc2_w 27920522535415
/*     */     //   42: lxor
/*     */     //   43: lstore #9
/*     */     //   45: pop2
/*     */     //   46: ldc2_w 9022236187976893695
/*     */     //   49: lload #5
/*     */     //   51: <illegal opcode> w : (JJ)I
/*     */     //   56: istore #11
/*     */     //   58: getstatic me/konsolas/aac/el.m : Z
/*     */     //   61: iload #11
/*     */     //   63: ifeq -> 123
/*     */     //   66: ifne -> 145
/*     */     //   69: goto -> 83
/*     */     //   72: ldc2_w 9075154554854852406
/*     */     //   75: lload #5
/*     */     //   77: <illegal opcode> w : (Ljava/lang/Throwable;JJ)Ljava/lang/Throwable;
/*     */     //   82: athrow
/*     */     //   83: aload_0
/*     */     //   84: getfield c : Lme/konsolas/aac/gL;
/*     */     //   87: iload #11
/*     */     //   89: ifeq -> 149
/*     */     //   92: goto -> 106
/*     */     //   95: ldc2_w 9075154554854852406
/*     */     //   98: lload #5
/*     */     //   100: <illegal opcode> w : (Ljava/lang/Throwable;JJ)Ljava/lang/Throwable;
/*     */     //   105: athrow
/*     */     //   106: invokestatic holdsLock : (Ljava/lang/Object;)Z
/*     */     //   109: goto -> 123
/*     */     //   112: ldc2_w 9075154554854852406
/*     */     //   115: lload #5
/*     */     //   117: <illegal opcode> w : (Ljava/lang/Throwable;JJ)Ljava/lang/Throwable;
/*     */     //   122: athrow
/*     */     //   123: ifeq -> 145
/*     */     //   126: new java/lang/AssertionError
/*     */     //   129: dup
/*     */     //   130: invokespecial <init> : ()V
/*     */     //   133: athrow
/*     */     //   134: ldc2_w 9075154554854852406
/*     */     //   137: lload #5
/*     */     //   139: <illegal opcode> w : (Ljava/lang/Throwable;JJ)Ljava/lang/Throwable;
/*     */     //   144: athrow
/*     */     //   145: aload_0
/*     */     //   146: getfield c : Lme/konsolas/aac/gL;
/*     */     //   149: dup
/*     */     //   150: astore #12
/*     */     //   152: monitorenter
/*     */     //   153: aload #4
/*     */     //   155: instanceof me/konsolas/aac/fF
/*     */     //   158: iload #11
/*     */     //   160: iload_3
/*     */     //   161: ifge -> 390
/*     */     //   164: ifeq -> 388
/*     */     //   167: ifeq -> 368
/*     */     //   170: aload #4
/*     */     //   172: checkcast me/konsolas/aac/fF
/*     */     //   175: getfield a : Lme/konsolas/aac/eb;
/*     */     //   178: astore #13
/*     */     //   180: aload #13
/*     */     //   182: getstatic me/konsolas/aac/eb.REFUSED_STREAM : Lme/konsolas/aac/eb;
/*     */     //   185: iload_2
/*     */     //   186: iflt -> 327
/*     */     //   189: iload #11
/*     */     //   191: ifeq -> 327
/*     */     //   194: if_acmpne -> 308
/*     */     //   197: goto -> 211
/*     */     //   200: ldc2_w 9075154554854852406
/*     */     //   203: lload #5
/*     */     //   205: <illegal opcode> w : (Ljava/lang/Throwable;JJ)Ljava/lang/Throwable;
/*     */     //   210: athrow
/*     */     //   211: aload_0
/*     */     //   212: dup
/*     */     //   213: getfield s : I
/*     */     //   216: iconst_1
/*     */     //   217: iadd
/*     */     //   218: putfield s : I
/*     */     //   221: aload_0
/*     */     //   222: iload #11
/*     */     //   224: iload_1
/*     */     //   225: iflt -> 296
/*     */     //   228: ifeq -> 290
/*     */     //   231: goto -> 245
/*     */     //   234: ldc2_w 9075154554854852406
/*     */     //   237: lload #5
/*     */     //   239: <illegal opcode> w : (Ljava/lang/Throwable;JJ)Ljava/lang/Throwable;
/*     */     //   244: athrow
/*     */     //   245: getfield s : I
/*     */     //   248: iload_3
/*     */     //   249: ifgt -> 365
/*     */     //   252: iconst_1
/*     */     //   253: if_icmple -> 359
/*     */     //   256: goto -> 270
/*     */     //   259: ldc2_w 9075154554854852406
/*     */     //   262: lload #5
/*     */     //   264: <illegal opcode> w : (Ljava/lang/Throwable;JJ)Ljava/lang/Throwable;
/*     */     //   269: athrow
/*     */     //   270: aload_0
/*     */     //   271: iconst_1
/*     */     //   272: putfield j : Z
/*     */     //   275: aload_0
/*     */     //   276: goto -> 290
/*     */     //   279: ldc2_w 9075154554854852406
/*     */     //   282: lload #5
/*     */     //   284: <illegal opcode> w : (Ljava/lang/Throwable;JJ)Ljava/lang/Throwable;
/*     */     //   289: athrow
/*     */     //   290: dup
/*     */     //   291: getfield d : I
/*     */     //   294: iconst_1
/*     */     //   295: iadd
/*     */     //   296: putfield d : I
/*     */     //   299: iload #11
/*     */     //   301: iload_1
/*     */     //   302: iflt -> 365
/*     */     //   305: ifne -> 359
/*     */     //   308: aload #13
/*     */     //   310: getstatic me/konsolas/aac/eb.CANCEL : Lme/konsolas/aac/eb;
/*     */     //   313: goto -> 327
/*     */     //   316: ldc2_w 9075154554854852406
/*     */     //   319: lload #5
/*     */     //   321: <illegal opcode> w : (Ljava/lang/Throwable;JJ)Ljava/lang/Throwable;
/*     */     //   326: athrow
/*     */     //   327: if_acmpeq -> 359
/*     */     //   330: aload_0
/*     */     //   331: iconst_1
/*     */     //   332: putfield j : Z
/*     */     //   335: aload_0
/*     */     //   336: dup
/*     */     //   337: getfield d : I
/*     */     //   340: iconst_1
/*     */     //   341: iadd
/*     */     //   342: putfield d : I
/*     */     //   345: goto -> 359
/*     */     //   348: ldc2_w 9075154554854852406
/*     */     //   351: lload #5
/*     */     //   353: <illegal opcode> w : (Ljava/lang/Throwable;JJ)Ljava/lang/Throwable;
/*     */     //   358: athrow
/*     */     //   359: iload_2
/*     */     //   360: ifle -> 561
/*     */     //   363: iload #11
/*     */     //   365: ifne -> 558
/*     */     //   368: aload_0
/*     */     //   369: lload #7
/*     */     //   371: invokevirtual a : (J)Z
/*     */     //   374: goto -> 388
/*     */     //   377: ldc2_w 9075154554854852406
/*     */     //   380: lload #5
/*     */     //   382: <illegal opcode> w : (Ljava/lang/Throwable;JJ)Ljava/lang/Throwable;
/*     */     //   387: athrow
/*     */     //   388: iload #11
/*     */     //   390: ifeq -> 497
/*     */     //   393: ifeq -> 455
/*     */     //   396: goto -> 410
/*     */     //   399: ldc2_w 9075154554854852406
/*     */     //   402: lload #5
/*     */     //   404: <illegal opcode> w : (Ljava/lang/Throwable;JJ)Ljava/lang/Throwable;
/*     */     //   409: athrow
/*     */     //   410: aload #4
/*     */     //   412: instanceof me/konsolas/aac/R
/*     */     //   415: iload_2
/*     */     //   416: ifle -> 497
/*     */     //   419: iload #11
/*     */     //   421: ifeq -> 497
/*     */     //   424: goto -> 438
/*     */     //   427: ldc2_w 9075154554854852406
/*     */     //   430: lload #5
/*     */     //   432: <illegal opcode> w : (Ljava/lang/Throwable;JJ)Ljava/lang/Throwable;
/*     */     //   437: athrow
/*     */     //   438: ifeq -> 558
/*     */     //   441: goto -> 455
/*     */     //   444: ldc2_w 9075154554854852406
/*     */     //   447: lload #5
/*     */     //   449: <illegal opcode> w : (Ljava/lang/Throwable;JJ)Ljava/lang/Throwable;
/*     */     //   454: athrow
/*     */     //   455: aload_0
/*     */     //   456: iconst_1
/*     */     //   457: putfield j : Z
/*     */     //   460: iload #11
/*     */     //   462: ifeq -> 561
/*     */     //   465: goto -> 479
/*     */     //   468: ldc2_w 9075154554854852406
/*     */     //   471: lload #5
/*     */     //   473: <illegal opcode> w : (Ljava/lang/Throwable;JJ)Ljava/lang/Throwable;
/*     */     //   478: athrow
/*     */     //   479: aload_0
/*     */     //   480: getfield l : I
/*     */     //   483: goto -> 497
/*     */     //   486: ldc2_w 9075154554854852406
/*     */     //   489: lload #5
/*     */     //   491: <illegal opcode> w : (Ljava/lang/Throwable;JJ)Ljava/lang/Throwable;
/*     */     //   496: athrow
/*     */     //   497: ifne -> 558
/*     */     //   500: aload #4
/*     */     //   502: ifnull -> 548
/*     */     //   505: goto -> 519
/*     */     //   508: ldc2_w 9075154554854852406
/*     */     //   511: lload #5
/*     */     //   513: <illegal opcode> w : (Ljava/lang/Throwable;JJ)Ljava/lang/Throwable;
/*     */     //   518: athrow
/*     */     //   519: aload_0
/*     */     //   520: getfield c : Lme/konsolas/aac/gL;
/*     */     //   523: aload_0
/*     */     //   524: getfield o : Lme/konsolas/aac/hQ;
/*     */     //   527: aload #4
/*     */     //   529: lload #9
/*     */     //   531: invokevirtual a : (Lme/konsolas/aac/hQ;Ljava/io/IOException;J)V
/*     */     //   534: goto -> 548
/*     */     //   537: ldc2_w 9075154554854852406
/*     */     //   540: lload #5
/*     */     //   542: <illegal opcode> w : (Ljava/lang/Throwable;JJ)Ljava/lang/Throwable;
/*     */     //   547: athrow
/*     */     //   548: aload_0
/*     */     //   549: dup
/*     */     //   550: getfield d : I
/*     */     //   553: iconst_1
/*     */     //   554: iadd
/*     */     //   555: putfield d : I
/*     */     //   558: aload #12
/*     */     //   560: monitorexit
/*     */     //   561: goto -> 572
/*     */     //   564: astore #14
/*     */     //   566: aload #12
/*     */     //   568: monitorexit
/*     */     //   569: aload #14
/*     */     //   571: athrow
/*     */     //   572: return
/*     */     // Line number table:
/*     */     //   Java source line number -> byte code offset
/*     */     //   #113	-> 58
/*     */     //   #252	-> 145
/*     */     //   #132	-> 153
/*     */     //   #300	-> 170
/*     */     //   #137	-> 180
/*     */     //   #68	-> 211
/*     */     //   #207	-> 221
/*     */     //   #262	-> 270
/*     */     //   #34	-> 275
/*     */     //   #71	-> 308
/*     */     //   #248	-> 330
/*     */     //   #81	-> 335
/*     */     //   #222	-> 359
/*     */     //   #148	-> 455
/*     */     //   #213	-> 460
/*     */     //   #97	-> 500
/*     */     //   #287	-> 519
/*     */     //   #160	-> 548
/*     */     //   #304	-> 558
/*     */     //   #43	-> 572
/*     */     // Exception table:
/*     */     //   from	to	target	type
/*     */     //   58	69	72	java/lang/IllegalStateException
/*     */     //   66	92	95	java/lang/IllegalStateException
/*     */     //   83	109	112	java/lang/IllegalStateException
/*     */     //   123	134	134	java/lang/IllegalStateException
/*     */     //   153	561	564	finally
/*     */     //   180	197	200	java/lang/IllegalStateException
/*     */     //   194	231	234	java/lang/IllegalStateException
/*     */     //   211	256	259	java/lang/IllegalStateException
/*     */     //   245	276	279	java/lang/IllegalStateException
/*     */     //   290	313	316	java/lang/IllegalStateException
/*     */     //   327	345	348	java/lang/IllegalStateException
/*     */     //   359	374	377	java/lang/IllegalStateException
/*     */     //   388	396	399	java/lang/IllegalStateException
/*     */     //   393	424	427	java/lang/IllegalStateException
/*     */     //   410	441	444	java/lang/IllegalStateException
/*     */     //   438	465	468	java/lang/IllegalStateException
/*     */     //   455	483	486	java/lang/IllegalStateException
/*     */     //   497	505	508	java/lang/IllegalStateException
/*     */     //   500	534	537	java/lang/IllegalStateException
/*     */     //   564	569	564	finally }
/*     */   long e = Long.MAX_VALUE; private int t = 1; public boolean a(long paramLong) { // Byte code:
/*     */     //   0: getstatic me/konsolas/aac/el.u : J
/*     */     //   3: lload_1
/*     */     //   4: lxor
/*     */     //   5: lstore_1
/*     */     //   6: aload_0
/*     */     //   7: getfield k : Lme/konsolas/aac/cZ;
/*     */     //   10: ifnull -> 27
/*     */     //   13: iconst_1
/*     */     //   14: goto -> 28
/*     */     //   17: ldc2_w -3919979063001484450
/*     */     //   20: lload_1
/*     */     //   21: <illegal opcode> w : (Ljava/lang/Throwable;JJ)Ljava/lang/Throwable;
/*     */     //   26: athrow
/*     */     //   27: iconst_0
/*     */     //   28: ireturn
/*     */     // Line number table:
/*     */     //   Java source line number -> byte code offset
/*     */     //   #150	-> 6
/*     */     // Exception table:
/*     */     //   from	to	target	type
/*     */     //   6	17	17	java/lang/IllegalStateException } static { long l;
/*     */     byte b1;
/*     */     for (u = nc.a(-3723082453898359964L, -8676973212375075854L, MethodHandles.lookup().lookupClass()).a(27071068435477L), x = new HashMap<>(13), l = u ^ 0x669FE3BF0E98L, "".toCharArray()[6] = (char)("".toCharArray()[6] ^ 0x7419), "".toCharArray()[0] = (char)("".toCharArray()[0] ^ 0x57DA), (new byte[8])[0] = (byte)(int)(l >>> 56L), b1 = 1; b1 < 8; ) {
/*     */       (new byte[8])[b1] = (byte)(int)(l << b1 * 8 >>> 56L);
/*     */       b1++;
/*     */     } 
/*     */     Cipher cipher;
/*     */     (cipher = Cipher.getInstance(hY$g6.H("".toCharArray(), (short)18207, (byte)3, (byte)1))).init(2, SecretKeyFactory.getInstance(hY$g6.H("".toCharArray(), (short)22080, (byte)5, (byte)4)).generateSecret(new DESKeySpec(new byte[8])), new IvParameterSpec(new byte[8]));
/*     */     String[] arrayOfString = new String[36];
/*     */     boolean bool = false;
/*     */     "??????<?????t?????????????????????Q?????????????".toCharArray()[424] = (char)("??????<?????t?????????????????????Q?????????????".toCharArray()[424] ^ 0x7602);
/*     */     String str;
/*     */     int i = (str = hY$g6.H("??????<?????t?????????????????????Q?????????????".toCharArray(), (short)11780, (byte)4, (byte)5)).length();
/*     */     byte b2 = 48;
/*     */     byte b = -1;
/*     */     while (true);
/* 268 */     throw a(-1); } fr a(ec paramec, long paramLong) { paramLong = u ^ paramLong; long l = paramLong ^ 0x3BB8181C7405L; this.n.setSoTimeout(0);
/*     */     a(l);
/*     */     return new fB(this, true, this.h, this.p, paramec); }
/*     */ 
/*     */   
/*     */   public le a() {
/*     */     return this.i;
/*     */   }
/*     */   
/*     */   public void a(long paramLong) {
/*     */     // Byte code:
/*     */     //   0: getstatic me/konsolas/aac/el.u : J
/*     */     //   3: lload_1
/*     */     //   4: lxor
/*     */     //   5: lstore_1
/*     */     //   6: ldc2_w -2765145922089770902
/*     */     //   9: lload_1
/*     */     //   10: <illegal opcode> w : (JJ)I
/*     */     //   15: istore_3
/*     */     //   16: getstatic me/konsolas/aac/el.m : Z
/*     */     //   19: iload_3
/*     */     //   20: ifeq -> 76
/*     */     //   23: ifne -> 97
/*     */     //   26: goto -> 39
/*     */     //   29: ldc2_w -2782034272371481693
/*     */     //   32: lload_1
/*     */     //   33: <illegal opcode> w : (Ljava/lang/Throwable;JJ)Ljava/lang/Throwable;
/*     */     //   38: athrow
/*     */     //   39: aload_0
/*     */     //   40: getfield c : Lme/konsolas/aac/gL;
/*     */     //   43: iload_3
/*     */     //   44: ifeq -> 101
/*     */     //   47: goto -> 60
/*     */     //   50: ldc2_w -2782034272371481693
/*     */     //   53: lload_1
/*     */     //   54: <illegal opcode> w : (Ljava/lang/Throwable;JJ)Ljava/lang/Throwable;
/*     */     //   59: athrow
/*     */     //   60: invokestatic holdsLock : (Ljava/lang/Object;)Z
/*     */     //   63: goto -> 76
/*     */     //   66: ldc2_w -2782034272371481693
/*     */     //   69: lload_1
/*     */     //   70: <illegal opcode> w : (Ljava/lang/Throwable;JJ)Ljava/lang/Throwable;
/*     */     //   75: athrow
/*     */     //   76: ifeq -> 97
/*     */     //   79: new java/lang/AssertionError
/*     */     //   82: dup
/*     */     //   83: invokespecial <init> : ()V
/*     */     //   86: athrow
/*     */     //   87: ldc2_w -2782034272371481693
/*     */     //   90: lload_1
/*     */     //   91: <illegal opcode> w : (Ljava/lang/Throwable;JJ)Ljava/lang/Throwable;
/*     */     //   96: athrow
/*     */     //   97: aload_0
/*     */     //   98: getfield c : Lme/konsolas/aac/gL;
/*     */     //   101: dup
/*     */     //   102: astore #4
/*     */     //   104: monitorenter
/*     */     //   105: aload_0
/*     */     //   106: iconst_1
/*     */     //   107: putfield j : Z
/*     */     //   110: aload #4
/*     */     //   112: monitorexit
/*     */     //   113: goto -> 124
/*     */     //   116: astore #5
/*     */     //   118: aload #4
/*     */     //   120: monitorexit
/*     */     //   121: aload #5
/*     */     //   123: athrow
/*     */     //   124: return
/*     */     // Line number table:
/*     */     //   Java source line number -> byte code offset
/*     */     //   #171	-> 16
/*     */     //   #261	-> 97
/*     */     //   #270	-> 105
/*     */     //   #176	-> 110
/*     */     //   #52	-> 124
/*     */     // Exception table:
/*     */     //   from	to	target	type
/*     */     //   16	26	29	java/lang/IllegalStateException
/*     */     //   23	47	50	java/lang/IllegalStateException
/*     */     //   39	63	66	java/lang/IllegalStateException
/*     */     //   76	87	87	java/lang/IllegalStateException
/*     */     //   105	113	116	finally
/*     */     //   116	121	116	finally
/*     */   }
/*     */   
/*     */   public String toString() {
/*     */     // Byte code:
/*     */     //   0: getstatic me/konsolas/aac/el.u : J
/*     */     //   3: ldc2_w 106730950082362
/*     */     //   6: lxor
/*     */     //   7: lstore_1
/*     */     //   8: ldc2_w 2158221843692538323
/*     */     //   11: lload_1
/*     */     //   12: <illegal opcode> w : (JJ)I
/*     */     //   17: istore_3
/*     */     //   18: new java/lang/StringBuilder
/*     */     //   21: dup
/*     */     //   22: invokespecial <init> : ()V
/*     */     //   25: sipush #30645
/*     */     //   28: ldc2_w 2822565467117384117
/*     */     //   31: lload_1
/*     */     //   32: lxor
/*     */     //   33: <illegal opcode> a : (IJ)Ljava/lang/String;
/*     */     //   38: invokevirtual append : (Ljava/lang/String;)Ljava/lang/StringBuilder;
/*     */     //   41: aload_0
/*     */     //   42: getfield o : Lme/konsolas/aac/hQ;
/*     */     //   45: invokevirtual a : ()Lme/konsolas/aac/jh;
/*     */     //   48: invokevirtual a : ()Lme/konsolas/aac/l6;
/*     */     //   51: invokevirtual d : ()Ljava/lang/String;
/*     */     //   54: invokevirtual append : (Ljava/lang/String;)Ljava/lang/StringBuilder;
/*     */     //   57: ldc_w ''
/*     */     //   60: invokevirtual toCharArray : ()[C
/*     */     //   63: dup
/*     */     //   64: dup
/*     */     //   65: iconst_0
/*     */     //   66: dup_x1
/*     */     //   67: caload
/*     */     //   68: sipush #7283
/*     */     //   71: ixor
/*     */     //   72: i2c
/*     */     //   73: castore
/*     */     //   74: sipush #10307
/*     */     //   77: iconst_1
/*     */     //   78: iconst_4
/*     */     //   79: invokestatic H : (Ljava/lang/Object;SBB)Ljava/lang/String;
/*     */     //   82: invokevirtual append : (Ljava/lang/String;)Ljava/lang/StringBuilder;
/*     */     //   85: aload_0
/*     */     //   86: getfield o : Lme/konsolas/aac/hQ;
/*     */     //   89: invokevirtual a : ()Lme/konsolas/aac/jh;
/*     */     //   92: invokevirtual a : ()Lme/konsolas/aac/l6;
/*     */     //   95: invokevirtual c : ()I
/*     */     //   98: invokevirtual append : (I)Ljava/lang/StringBuilder;
/*     */     //   101: sipush #2575
/*     */     //   104: ldc2_w 6359435206634638355
/*     */     //   107: lload_1
/*     */     //   108: lxor
/*     */     //   109: <illegal opcode> a : (IJ)Ljava/lang/String;
/*     */     //   114: invokevirtual append : (Ljava/lang/String;)Ljava/lang/StringBuilder;
/*     */     //   117: aload_0
/*     */     //   118: getfield o : Lme/konsolas/aac/hQ;
/*     */     //   121: invokevirtual a : ()Ljava/net/Proxy;
/*     */     //   124: invokevirtual append : (Ljava/lang/Object;)Ljava/lang/StringBuilder;
/*     */     //   127: bipush #43
/*     */     //   129: ldc2_w 1434971374788380171
/*     */     //   132: lload_1
/*     */     //   133: lxor
/*     */     //   134: <illegal opcode> a : (IJ)Ljava/lang/String;
/*     */     //   139: invokevirtual append : (Ljava/lang/String;)Ljava/lang/StringBuilder;
/*     */     //   142: aload_0
/*     */     //   143: getfield o : Lme/konsolas/aac/hQ;
/*     */     //   146: invokevirtual a : ()Ljava/net/InetSocketAddress;
/*     */     //   149: invokevirtual append : (Ljava/lang/Object;)Ljava/lang/StringBuilder;
/*     */     //   152: sipush #19122
/*     */     //   155: ldc2_w 225243268019932322
/*     */     //   158: lload_1
/*     */     //   159: lxor
/*     */     //   160: <illegal opcode> a : (IJ)Ljava/lang/String;
/*     */     //   165: invokevirtual append : (Ljava/lang/String;)Ljava/lang/StringBuilder;
/*     */     //   168: aload_0
/*     */     //   169: getfield b : Lme/konsolas/aac/it;
/*     */     //   172: iload_3
/*     */     //   173: ifne -> 209
/*     */     //   176: ifnull -> 215
/*     */     //   179: goto -> 192
/*     */     //   182: ldc2_w 2132231368334387024
/*     */     //   185: lload_1
/*     */     //   186: <illegal opcode> w : (Ljava/lang/Throwable;JJ)Ljava/lang/Throwable;
/*     */     //   191: athrow
/*     */     //   192: aload_0
/*     */     //   193: getfield b : Lme/konsolas/aac/it;
/*     */     //   196: goto -> 209
/*     */     //   199: ldc2_w 2132231368334387024
/*     */     //   202: lload_1
/*     */     //   203: <illegal opcode> w : (Ljava/lang/Throwable;JJ)Ljava/lang/Throwable;
/*     */     //   208: athrow
/*     */     //   209: invokevirtual a : ()Lme/konsolas/aac/fn;
/*     */     //   212: goto -> 228
/*     */     //   215: sipush #21047
/*     */     //   218: ldc2_w 9141165908616827949
/*     */     //   221: lload_1
/*     */     //   222: lxor
/*     */     //   223: <illegal opcode> a : (IJ)Ljava/lang/String;
/*     */     //   228: invokevirtual append : (Ljava/lang/Object;)Ljava/lang/StringBuilder;
/*     */     //   231: sipush #10865
/*     */     //   234: ldc2_w 8426828943370759248
/*     */     //   237: lload_1
/*     */     //   238: lxor
/*     */     //   239: <illegal opcode> a : (IJ)Ljava/lang/String;
/*     */     //   244: invokevirtual append : (Ljava/lang/String;)Ljava/lang/StringBuilder;
/*     */     //   247: aload_0
/*     */     //   248: getfield i : Lme/konsolas/aac/le;
/*     */     //   251: invokevirtual append : (Ljava/lang/Object;)Ljava/lang/StringBuilder;
/*     */     //   254: bipush #125
/*     */     //   256: invokevirtual append : (C)Ljava/lang/StringBuilder;
/*     */     //   259: invokevirtual toString : ()Ljava/lang/String;
/*     */     //   262: areturn
/*     */     // Line number table:
/*     */     //   Java source line number -> byte code offset
/*     */     //   #180	-> 18
/*     */     //   #149	-> 45
/*     */     //   #240	-> 121
/*     */     //   #42	-> 146
/*     */     //   #61	-> 168
/*     */     //   #293	-> 262
/*     */     // Exception table:
/*     */     //   from	to	target	type
/*     */     //   18	179	182	java/lang/IllegalStateException
/*     */     //   176	196	199	java/lang/IllegalStateException
/*     */   }
/*     */   
/*     */   public Socket a() {
/*     */     return this.n;
/*     */   }
/*     */   
/*     */   gq a(gf paramgf, ko paramko, long paramLong) {
/*     */     // Byte code:
/*     */     //   0: getstatic me/konsolas/aac/el.u : J
/*     */     //   3: lload_3
/*     */     //   4: lxor
/*     */     //   5: lstore_3
/*     */     //   6: lload_3
/*     */     //   7: dup2
/*     */     //   8: ldc2_w 50093471711135
/*     */     //   11: lxor
/*     */     //   12: dup2
/*     */     //   13: bipush #48
/*     */     //   15: lushr
/*     */     //   16: l2i
/*     */     //   17: istore #5
/*     */     //   19: dup2
/*     */     //   20: bipush #16
/*     */     //   22: lshl
/*     */     //   23: bipush #32
/*     */     //   25: lushr
/*     */     //   26: l2i
/*     */     //   27: istore #6
/*     */     //   29: dup2
/*     */     //   30: bipush #48
/*     */     //   32: lshl
/*     */     //   33: bipush #48
/*     */     //   35: lushr
/*     */     //   36: l2i
/*     */     //   37: istore #7
/*     */     //   39: pop2
/*     */     //   40: dup2
/*     */     //   41: ldc2_w 76368020083233
/*     */     //   44: lxor
/*     */     //   45: lstore #8
/*     */     //   47: pop2
/*     */     //   48: ldc2_w 155278774457095687
/*     */     //   51: lload_3
/*     */     //   52: <illegal opcode> w : (JJ)I
/*     */     //   57: istore #10
/*     */     //   59: aload_0
/*     */     //   60: iload #10
/*     */     //   62: ifne -> 156
/*     */     //   65: getfield k : Lme/konsolas/aac/cZ;
/*     */     //   68: ifnull -> 117
/*     */     //   71: goto -> 84
/*     */     //   74: ldc2_w 162999634952730756
/*     */     //   77: lload_3
/*     */     //   78: <illegal opcode> w : (Ljava/lang/Throwable;JJ)Ljava/lang/Throwable;
/*     */     //   83: athrow
/*     */     //   84: new me/konsolas/aac/dS
/*     */     //   87: dup
/*     */     //   88: iload #5
/*     */     //   90: i2c
/*     */     //   91: aload_1
/*     */     //   92: aload_0
/*     */     //   93: aload_2
/*     */     //   94: aload_0
/*     */     //   95: getfield k : Lme/konsolas/aac/cZ;
/*     */     //   98: iload #6
/*     */     //   100: iload #7
/*     */     //   102: i2s
/*     */     //   103: invokespecial <init> : (CLme/konsolas/aac/gf;Lme/konsolas/aac/el;Lme/konsolas/aac/ko;Lme/konsolas/aac/cZ;IS)V
/*     */     //   106: areturn
/*     */     //   107: ldc2_w 162999634952730756
/*     */     //   110: lload_3
/*     */     //   111: <illegal opcode> w : (Ljava/lang/Throwable;JJ)Ljava/lang/Throwable;
/*     */     //   116: athrow
/*     */     //   117: aload_0
/*     */     //   118: getfield n : Ljava/net/Socket;
/*     */     //   121: aload_2
/*     */     //   122: invokeinterface a : ()I
/*     */     //   127: invokevirtual setSoTimeout : (I)V
/*     */     //   130: aload_0
/*     */     //   131: getfield h : Lme/konsolas/aac/bX;
/*     */     //   134: invokeinterface a : ()Lme/konsolas/aac/li;
/*     */     //   139: aload_2
/*     */     //   140: invokeinterface a : ()I
/*     */     //   145: i2l
/*     */     //   146: lload #8
/*     */     //   148: getstatic java/util/concurrent/TimeUnit.MILLISECONDS : Ljava/util/concurrent/TimeUnit;
/*     */     //   151: invokevirtual a : (JJLjava/util/concurrent/TimeUnit;)Lme/konsolas/aac/li;
/*     */     //   154: pop
/*     */     //   155: aload_0
/*     */     //   156: getfield p : Lme/konsolas/aac/gi;
/*     */     //   159: invokeinterface a : ()Lme/konsolas/aac/li;
/*     */     //   164: aload_2
/*     */     //   165: invokeinterface c : ()I
/*     */     //   170: i2l
/*     */     //   171: lload #8
/*     */     //   173: getstatic java/util/concurrent/TimeUnit.MILLISECONDS : Ljava/util/concurrent/TimeUnit;
/*     */     //   176: invokevirtual a : (JJLjava/util/concurrent/TimeUnit;)Lme/konsolas/aac/li;
/*     */     //   179: pop
/*     */     //   180: new me/konsolas/aac/iL
/*     */     //   183: dup
/*     */     //   184: aload_1
/*     */     //   185: aload_0
/*     */     //   186: aload_0
/*     */     //   187: getfield h : Lme/konsolas/aac/bX;
/*     */     //   190: aload_0
/*     */     //   191: getfield p : Lme/konsolas/aac/gi;
/*     */     //   194: invokespecial <init> : (Lme/konsolas/aac/gf;Lme/konsolas/aac/el;Lme/konsolas/aac/bX;Lme/konsolas/aac/gi;)V
/*     */     //   197: areturn
/*     */     // Line number table:
/*     */     //   Java source line number -> byte code offset
/*     */     //   #200	-> 59
/*     */     //   #26	-> 84
/*     */     //   #48	-> 117
/*     */     //   #9	-> 130
/*     */     //   #21	-> 155
/*     */     //   #119	-> 180
/*     */     // Exception table:
/*     */     //   from	to	target	type
/*     */     //   59	71	74	java/net/SocketException
/*     */     //   65	107	107	java/net/SocketException
/*     */   }
/*     */   
/*     */   public el(gL paramgL, hQ paramhQ) {
/*     */     this.c = paramgL;
/*     */     this.o = paramhQ;
/*     */   }
/*     */   
/*     */   public hQ a() {
/*     */     return this.o;
/*     */   }
/*     */   
/*     */   private void a(char paramChar, int paramInt1, int paramInt2, int paramInt3) {
/*     */     long l1 = (paramChar << 48L | paramInt2 << 32L >>> 16L | paramInt3 << 48L >>> 48L) ^ u, l2 = l1 ^ 0x603E20423F91L;
/*     */     int i = (int)((l1 ^ 0x1B46F821E8FFL) >>> 32L), j = (int)((l1 ^ 0x1B46F821E8FFL) << 32L >>> 48L), k = (int)((l1 ^ 0x1B46F821E8FFL) << 48L >>> 48L);
/*     */     l1 ^ 0x1B46F821E8FFL;
/*     */     this.n.setSoTimeout(0);
/*     */     this.k = (new f_(true)).a(this.n, this.o.a().a().d(), this.h, this.p).a(this).a(paramInt1).a(l2);
/*     */     this.k.b(i, (short)j, k);
/*     */   }
/*     */   
/*     */   public boolean a(long paramLong, l6 paraml6) {
/*     */     // Byte code:
/*     */     //   0: getstatic me/konsolas/aac/el.u : J
/*     */     //   3: lload_1
/*     */     //   4: lxor
/*     */     //   5: lstore_1
/*     */     //   6: lload_1
/*     */     //   7: dup2
/*     */     //   8: ldc2_w 46267563512829
/*     */     //   11: lxor
/*     */     //   12: lstore #4
/*     */     //   14: pop2
/*     */     //   15: ldc2_w -2313164840802546747
/*     */     //   18: lload_1
/*     */     //   19: <illegal opcode> w : (JJ)I
/*     */     //   24: istore #6
/*     */     //   26: aload_3
/*     */     //   27: invokevirtual c : ()I
/*     */     //   30: iload #6
/*     */     //   32: ifne -> 96
/*     */     //   35: aload_0
/*     */     //   36: getfield o : Lme/konsolas/aac/hQ;
/*     */     //   39: invokevirtual a : ()Lme/konsolas/aac/jh;
/*     */     //   42: invokevirtual a : ()Lme/konsolas/aac/l6;
/*     */     //   45: invokevirtual c : ()I
/*     */     //   48: if_icmpeq -> 76
/*     */     //   51: goto -> 64
/*     */     //   54: ldc2_w -2341517068403808954
/*     */     //   57: lload_1
/*     */     //   58: <illegal opcode> w : (Ljava/lang/Throwable;JJ)Ljava/lang/Throwable;
/*     */     //   63: athrow
/*     */     //   64: iconst_0
/*     */     //   65: ireturn
/*     */     //   66: ldc2_w -2341517068403808954
/*     */     //   69: lload_1
/*     */     //   70: <illegal opcode> w : (Ljava/lang/Throwable;JJ)Ljava/lang/Throwable;
/*     */     //   75: athrow
/*     */     //   76: aload_3
/*     */     //   77: invokevirtual d : ()Ljava/lang/String;
/*     */     //   80: aload_0
/*     */     //   81: getfield o : Lme/konsolas/aac/hQ;
/*     */     //   84: invokevirtual a : ()Lme/konsolas/aac/jh;
/*     */     //   87: invokevirtual a : ()Lme/konsolas/aac/l6;
/*     */     //   90: invokevirtual d : ()Ljava/lang/String;
/*     */     //   93: invokevirtual equals : (Ljava/lang/Object;)Z
/*     */     //   96: iload #6
/*     */     //   98: ifne -> 206
/*     */     //   101: ifne -> 205
/*     */     //   104: goto -> 117
/*     */     //   107: ldc2_w -2341517068403808954
/*     */     //   110: lload_1
/*     */     //   111: <illegal opcode> w : (Ljava/lang/Throwable;JJ)Ljava/lang/Throwable;
/*     */     //   116: athrow
/*     */     //   117: aload_0
/*     */     //   118: getfield b : Lme/konsolas/aac/it;
/*     */     //   121: ifnull -> 203
/*     */     //   124: goto -> 137
/*     */     //   127: ldc2_w -2341517068403808954
/*     */     //   130: lload_1
/*     */     //   131: <illegal opcode> w : (Ljava/lang/Throwable;JJ)Ljava/lang/Throwable;
/*     */     //   136: athrow
/*     */     //   137: getstatic me/konsolas/aac/jV.a : Lme/konsolas/aac/jV;
/*     */     //   140: aload_3
/*     */     //   141: invokevirtual d : ()Ljava/lang/String;
/*     */     //   144: aload_0
/*     */     //   145: getfield b : Lme/konsolas/aac/it;
/*     */     //   148: invokevirtual b : ()Ljava/util/List;
/*     */     //   151: iconst_0
/*     */     //   152: invokeinterface get : (I)Ljava/lang/Object;
/*     */     //   157: checkcast java/security/cert/X509Certificate
/*     */     //   160: lload #4
/*     */     //   162: invokevirtual b : (Ljava/lang/String;Ljava/security/cert/X509Certificate;J)Z
/*     */     //   165: iload #6
/*     */     //   167: ifne -> 200
/*     */     //   170: goto -> 183
/*     */     //   173: ldc2_w -2341517068403808954
/*     */     //   176: lload_1
/*     */     //   177: <illegal opcode> w : (Ljava/lang/Throwable;JJ)Ljava/lang/Throwable;
/*     */     //   182: athrow
/*     */     //   183: ifeq -> 203
/*     */     //   186: goto -> 199
/*     */     //   189: ldc2_w -2341517068403808954
/*     */     //   192: lload_1
/*     */     //   193: <illegal opcode> w : (Ljava/lang/Throwable;JJ)Ljava/lang/Throwable;
/*     */     //   198: athrow
/*     */     //   199: iconst_1
/*     */     //   200: goto -> 204
/*     */     //   203: iconst_0
/*     */     //   204: ireturn
/*     */     //   205: iconst_1
/*     */     //   206: ireturn
/*     */     // Line number table:
/*     */     //   Java source line number -> byte code offset
/*     */     //   #231	-> 26
/*     */     //   #205	-> 64
/*     */     //   #310	-> 76
/*     */     //   #260	-> 117
/*     */     //   #197	-> 141
/*     */     //   #59	-> 160
/*     */     //   #106	-> 205
/*     */     // Exception table:
/*     */     //   from	to	target	type
/*     */     //   26	51	54	java/lang/IllegalStateException
/*     */     //   35	66	66	java/lang/IllegalStateException
/*     */     //   96	104	107	java/lang/IllegalStateException
/*     */     //   101	124	127	java/lang/IllegalStateException
/*     */     //   117	170	173	java/lang/IllegalStateException
/*     */     //   137	186	189	java/lang/IllegalStateException
/*     */   }
/*     */   
/*     */   final List g = new ArrayList();
/*     */   private static final String f;
/*     */   private static final int q = 21;
/*     */   public final gL c;
/*     */   private final hQ o;
/*     */   private Socket r;
/*     */   private Socket n;
/*     */   private it b;
/*     */   private le i;
/*     */   private cZ k;
/*     */   private bX h;
/*     */   private gi p;
/*     */   boolean j;
/*     */   int d;
/*     */   int l;
/*     */   private int s;
/*     */   private static final long u;
/*     */   private static final String[] v;
/*     */   private static final String[] w;
/*     */   private static final Map x;
/*     */   
/*     */   private s a(long paramLong) {
/*     */     // Byte code:
/*     */     //   0: getstatic me/konsolas/aac/el.u : J
/*     */     //   3: lload_1
/*     */     //   4: lxor
/*     */     //   5: lstore_1
/*     */     //   6: lload_1
/*     */     //   7: dup2
/*     */     //   8: ldc2_w 139985614430642
/*     */     //   11: lxor
/*     */     //   12: lstore_3
/*     */     //   13: dup2
/*     */     //   14: ldc2_w 36280727611315
/*     */     //   17: lxor
/*     */     //   18: dup2
/*     */     //   19: bipush #8
/*     */     //   21: lushr
/*     */     //   22: lstore #5
/*     */     //   24: dup2
/*     */     //   25: bipush #56
/*     */     //   27: lshl
/*     */     //   28: bipush #56
/*     */     //   30: lushr
/*     */     //   31: l2i
/*     */     //   32: istore #7
/*     */     //   34: pop2
/*     */     //   35: dup2
/*     */     //   36: ldc2_w 34505409069933
/*     */     //   39: lxor
/*     */     //   40: lstore #8
/*     */     //   42: dup2
/*     */     //   43: ldc2_w 126761933276312
/*     */     //   46: lxor
/*     */     //   47: dup2
/*     */     //   48: bipush #48
/*     */     //   50: lushr
/*     */     //   51: l2i
/*     */     //   52: istore #10
/*     */     //   54: dup2
/*     */     //   55: bipush #16
/*     */     //   57: lshl
/*     */     //   58: bipush #32
/*     */     //   60: lushr
/*     */     //   61: l2i
/*     */     //   62: istore #11
/*     */     //   64: dup2
/*     */     //   65: bipush #48
/*     */     //   67: lshl
/*     */     //   68: bipush #48
/*     */     //   70: lushr
/*     */     //   71: l2i
/*     */     //   72: istore #12
/*     */     //   74: pop2
/*     */     //   75: dup2
/*     */     //   76: ldc2_w 88209683994899
/*     */     //   79: lxor
/*     */     //   80: lstore #13
/*     */     //   82: dup2
/*     */     //   83: ldc2_w 137665360266957
/*     */     //   86: lxor
/*     */     //   87: lstore #15
/*     */     //   89: dup2
/*     */     //   90: ldc2_w 60976325420553
/*     */     //   93: lxor
/*     */     //   94: lstore #17
/*     */     //   96: dup2
/*     */     //   97: ldc2_w 95311607059926
/*     */     //   100: lxor
/*     */     //   101: lstore #19
/*     */     //   103: dup2
/*     */     //   104: ldc2_w 76984955017526
/*     */     //   107: lxor
/*     */     //   108: lstore #21
/*     */     //   110: pop2
/*     */     //   111: ldc2_w 4451373951556764684
/*     */     //   114: lload_1
/*     */     //   115: <illegal opcode> w : (JJ)I
/*     */     //   120: new me/konsolas/aac/k_
/*     */     //   123: dup
/*     */     //   124: lload #17
/*     */     //   126: invokespecial <init> : (J)V
/*     */     //   129: aload_0
/*     */     //   130: getfield o : Lme/konsolas/aac/hQ;
/*     */     //   133: invokevirtual a : ()Lme/konsolas/aac/jh;
/*     */     //   136: invokevirtual a : ()Lme/konsolas/aac/l6;
/*     */     //   139: lload #19
/*     */     //   141: invokevirtual a : (Lme/konsolas/aac/l6;J)Lme/konsolas/aac/k_;
/*     */     //   144: sipush #20967
/*     */     //   147: ldc2_w 6659659573127083889
/*     */     //   150: lload_1
/*     */     //   151: lxor
/*     */     //   152: <illegal opcode> a : (IJ)Ljava/lang/String;
/*     */     //   157: lload #21
/*     */     //   159: aconst_null
/*     */     //   160: invokevirtual a : (Ljava/lang/String;JLme/konsolas/aac/jR;)Lme/konsolas/aac/k_;
/*     */     //   163: sipush #9840
/*     */     //   166: ldc2_w 8564898631169638625
/*     */     //   169: lload_1
/*     */     //   170: lxor
/*     */     //   171: <illegal opcode> a : (IJ)Ljava/lang/String;
/*     */     //   176: aload_0
/*     */     //   177: getfield o : Lme/konsolas/aac/hQ;
/*     */     //   180: invokevirtual a : ()Lme/konsolas/aac/jh;
/*     */     //   183: invokevirtual a : ()Lme/konsolas/aac/l6;
/*     */     //   186: lload_3
/*     */     //   187: iconst_1
/*     */     //   188: invokestatic a : (Lme/konsolas/aac/l6;JZ)Ljava/lang/String;
/*     */     //   191: lload #5
/*     */     //   193: dup2_x1
/*     */     //   194: pop2
/*     */     //   195: iload #7
/*     */     //   197: i2b
/*     */     //   198: swap
/*     */     //   199: invokevirtual a : (Ljava/lang/String;JBLjava/lang/String;)Lme/konsolas/aac/k_;
/*     */     //   202: sipush #5041
/*     */     //   205: ldc2_w 6852439268573033769
/*     */     //   208: lload_1
/*     */     //   209: lxor
/*     */     //   210: <illegal opcode> a : (IJ)Ljava/lang/String;
/*     */     //   215: lload #5
/*     */     //   217: iload #7
/*     */     //   219: i2b
/*     */     //   220: sipush #1454
/*     */     //   223: ldc2_w 775709580715336492
/*     */     //   226: lload_1
/*     */     //   227: lxor
/*     */     //   228: <illegal opcode> a : (IJ)Ljava/lang/String;
/*     */     //   233: invokevirtual a : (Ljava/lang/String;JBLjava/lang/String;)Lme/konsolas/aac/k_;
/*     */     //   236: sipush #11601
/*     */     //   239: ldc2_w 5046876835957148635
/*     */     //   242: lload_1
/*     */     //   243: lxor
/*     */     //   244: <illegal opcode> a : (IJ)Ljava/lang/String;
/*     */     //   249: iload #10
/*     */     //   251: i2s
/*     */     //   252: iload #11
/*     */     //   254: iload #12
/*     */     //   256: i2c
/*     */     //   257: invokestatic a : (SIC)Ljava/lang/String;
/*     */     //   260: lload #5
/*     */     //   262: dup2_x1
/*     */     //   263: pop2
/*     */     //   264: iload #7
/*     */     //   266: i2b
/*     */     //   267: swap
/*     */     //   268: invokevirtual a : (Ljava/lang/String;JBLjava/lang/String;)Lme/konsolas/aac/k_;
/*     */     //   271: lload #8
/*     */     //   273: invokevirtual a : (J)Lme/konsolas/aac/s;
/*     */     //   276: astore #24
/*     */     //   278: istore #23
/*     */     //   280: new me/konsolas/aac/T
/*     */     //   283: dup
/*     */     //   284: invokespecial <init> : ()V
/*     */     //   287: aload #24
/*     */     //   289: invokevirtual a : (Lme/konsolas/aac/s;)Lme/konsolas/aac/T;
/*     */     //   292: getstatic me/konsolas/aac/le.HTTP_1_1 : Lme/konsolas/aac/le;
/*     */     //   295: invokevirtual a : (Lme/konsolas/aac/le;)Lme/konsolas/aac/T;
/*     */     //   298: sipush #407
/*     */     //   301: invokevirtual a : (I)Lme/konsolas/aac/T;
/*     */     //   304: sipush #26339
/*     */     //   307: ldc2_w 1088603990835249248
/*     */     //   310: lload_1
/*     */     //   311: lxor
/*     */     //   312: <illegal opcode> a : (IJ)Ljava/lang/String;
/*     */     //   317: invokevirtual a : (Ljava/lang/String;)Lme/konsolas/aac/T;
/*     */     //   320: getstatic me/konsolas/aac/eO.j : Lme/konsolas/aac/d2;
/*     */     //   323: invokevirtual a : (Lme/konsolas/aac/d2;)Lme/konsolas/aac/T;
/*     */     //   326: ldc2_w -1
/*     */     //   329: invokevirtual b : (J)Lme/konsolas/aac/T;
/*     */     //   332: ldc2_w -1
/*     */     //   335: invokevirtual a : (J)Lme/konsolas/aac/T;
/*     */     //   338: sipush #25563
/*     */     //   341: ldc2_w 3126878021140825429
/*     */     //   344: lload_1
/*     */     //   345: lxor
/*     */     //   346: <illegal opcode> a : (IJ)Ljava/lang/String;
/*     */     //   351: lload #13
/*     */     //   353: sipush #20857
/*     */     //   356: ldc2_w 840105203688863732
/*     */     //   359: lload_1
/*     */     //   360: lxor
/*     */     //   361: <illegal opcode> a : (IJ)Ljava/lang/String;
/*     */     //   366: invokevirtual a : (Ljava/lang/String;JLjava/lang/String;)Lme/konsolas/aac/T;
/*     */     //   369: lload #15
/*     */     //   371: invokevirtual a : (J)Lme/konsolas/aac/H;
/*     */     //   374: astore #25
/*     */     //   376: aload_0
/*     */     //   377: getfield o : Lme/konsolas/aac/hQ;
/*     */     //   380: invokevirtual a : ()Lme/konsolas/aac/jh;
/*     */     //   383: invokevirtual a : ()Lme/konsolas/aac/dp;
/*     */     //   386: aload_0
/*     */     //   387: getfield o : Lme/konsolas/aac/hQ;
/*     */     //   390: aload #25
/*     */     //   392: invokeinterface a : (Lme/konsolas/aac/hQ;Lme/konsolas/aac/H;)Lme/konsolas/aac/s;
/*     */     //   397: astore #26
/*     */     //   399: aload #26
/*     */     //   401: iload #23
/*     */     //   403: ifeq -> 424
/*     */     //   406: ifnull -> 427
/*     */     //   409: goto -> 422
/*     */     //   412: ldc2_w 4396205897821063109
/*     */     //   415: lload_1
/*     */     //   416: <illegal opcode> w : (Ljava/lang/Throwable;JJ)Ljava/lang/Throwable;
/*     */     //   421: athrow
/*     */     //   422: aload #26
/*     */     //   424: goto -> 429
/*     */     //   427: aload #24
/*     */     //   429: areturn
/*     */     // Line number table:
/*     */     //   Java source line number -> byte code offset
/*     */     //   #253	-> 120
/*     */     //   #20	-> 133
/*     */     //   #186	-> 160
/*     */     //   #140	-> 180
/*     */     //   #282	-> 233
/*     */     //   #237	-> 249
/*     */     //   #189	-> 271
/*     */     //   #89	-> 280
/*     */     //   #245	-> 289
/*     */     //   #164	-> 295
/*     */     //   #103	-> 301
/*     */     //   #234	-> 317
/*     */     //   #15	-> 323
/*     */     //   #286	-> 329
/*     */     //   #14	-> 335
/*     */     //   #259	-> 366
/*     */     //   #136	-> 369
/*     */     //   #88	-> 376
/*     */     //   #134	-> 392
/*     */     //   #204	-> 399
/*     */     //   #289	-> 422
/*     */     //   #311	-> 427
/*     */     //   #298	-> 429
/*     */     // Exception table:
/*     */     //   from	to	target	type
/*     */     //   399	409	412	java/io/IOException
/*     */   }
/*     */   
/*     */   private void a(int paramInt1, int paramInt2, int paramInt3, long paramLong, gC paramgC, cv paramcv) {
/*     */     // Byte code:
/*     */     //   0: getstatic me/konsolas/aac/el.u : J
/*     */     //   3: lload #4
/*     */     //   5: lxor
/*     */     //   6: lstore #4
/*     */     //   8: lload #4
/*     */     //   10: dup2
/*     */     //   11: ldc2_w 106336192518080
/*     */     //   14: lxor
/*     */     //   15: dup2
/*     */     //   16: bipush #32
/*     */     //   18: lushr
/*     */     //   19: l2i
/*     */     //   20: istore #8
/*     */     //   22: dup2
/*     */     //   23: bipush #32
/*     */     //   25: lshl
/*     */     //   26: bipush #48
/*     */     //   28: lushr
/*     */     //   29: l2i
/*     */     //   30: istore #9
/*     */     //   32: dup2
/*     */     //   33: bipush #48
/*     */     //   35: lshl
/*     */     //   36: bipush #48
/*     */     //   38: lushr
/*     */     //   39: l2i
/*     */     //   40: istore #10
/*     */     //   42: pop2
/*     */     //   43: dup2
/*     */     //   44: ldc2_w 97772587685868
/*     */     //   47: lxor
/*     */     //   48: lstore #11
/*     */     //   50: dup2
/*     */     //   51: ldc2_w 117063487283984
/*     */     //   54: lxor
/*     */     //   55: lstore #13
/*     */     //   57: dup2
/*     */     //   58: ldc2_w 125732363260329
/*     */     //   61: lxor
/*     */     //   62: lstore #15
/*     */     //   64: pop2
/*     */     //   65: aload_0
/*     */     //   66: lload #11
/*     */     //   68: invokespecial a : (J)Lme/konsolas/aac/s;
/*     */     //   71: astore #18
/*     */     //   73: aload #18
/*     */     //   75: invokevirtual a : ()Lme/konsolas/aac/l6;
/*     */     //   78: astore #19
/*     */     //   80: ldc2_w 709998825923538960
/*     */     //   83: lload #4
/*     */     //   85: <illegal opcode> w : (JJ)I
/*     */     //   90: iconst_0
/*     */     //   91: istore #20
/*     */     //   93: istore #17
/*     */     //   95: iload #20
/*     */     //   97: bipush #21
/*     */     //   99: if_icmpge -> 233
/*     */     //   102: aload_0
/*     */     //   103: iload_1
/*     */     //   104: lload #15
/*     */     //   106: iload_2
/*     */     //   107: aload #6
/*     */     //   109: aload #7
/*     */     //   111: invokespecial a : (IJILme/konsolas/aac/gC;Lme/konsolas/aac/cv;)V
/*     */     //   114: aload_0
/*     */     //   115: iload_2
/*     */     //   116: iload_3
/*     */     //   117: iload #8
/*     */     //   119: iload #9
/*     */     //   121: aload #18
/*     */     //   123: aload #19
/*     */     //   125: iload #10
/*     */     //   127: invokespecial a : (IIIILme/konsolas/aac/s;Lme/konsolas/aac/l6;I)Lme/konsolas/aac/s;
/*     */     //   130: astore #18
/*     */     //   132: iload #17
/*     */     //   134: lload #4
/*     */     //   136: lconst_0
/*     */     //   137: lcmp
/*     */     //   138: iflt -> 230
/*     */     //   141: ifeq -> 228
/*     */     //   144: aload #18
/*     */     //   146: ifnonnull -> 177
/*     */     //   149: goto -> 163
/*     */     //   152: ldc2_w 657082258698548185
/*     */     //   155: lload #4
/*     */     //   157: <illegal opcode> w : (Ljava/lang/Throwable;JJ)Ljava/lang/Throwable;
/*     */     //   162: athrow
/*     */     //   163: goto -> 233
/*     */     //   166: ldc2_w 657082258698548185
/*     */     //   169: lload #4
/*     */     //   171: <illegal opcode> w : (Ljava/lang/Throwable;JJ)Ljava/lang/Throwable;
/*     */     //   176: athrow
/*     */     //   177: aload_0
/*     */     //   178: getfield r : Ljava/net/Socket;
/*     */     //   181: lload #13
/*     */     //   183: dup2_x1
/*     */     //   184: pop2
/*     */     //   185: invokestatic a : (JLjava/net/Socket;)V
/*     */     //   188: aload_0
/*     */     //   189: aconst_null
/*     */     //   190: putfield r : Ljava/net/Socket;
/*     */     //   193: aload_0
/*     */     //   194: aconst_null
/*     */     //   195: putfield p : Lme/konsolas/aac/gi;
/*     */     //   198: aload_0
/*     */     //   199: aconst_null
/*     */     //   200: putfield h : Lme/konsolas/aac/bX;
/*     */     //   203: aload #7
/*     */     //   205: aload #6
/*     */     //   207: aload_0
/*     */     //   208: getfield o : Lme/konsolas/aac/hQ;
/*     */     //   211: invokevirtual a : ()Ljava/net/InetSocketAddress;
/*     */     //   214: aload_0
/*     */     //   215: getfield o : Lme/konsolas/aac/hQ;
/*     */     //   218: invokevirtual a : ()Ljava/net/Proxy;
/*     */     //   221: aconst_null
/*     */     //   222: invokevirtual a : (Lme/konsolas/aac/gC;Ljava/net/InetSocketAddress;Ljava/net/Proxy;Lme/konsolas/aac/le;)V
/*     */     //   225: iinc #20, 1
/*     */     //   228: iload #17
/*     */     //   230: ifne -> 95
/*     */     //   233: lload #4
/*     */     //   235: lconst_0
/*     */     //   236: lcmp
/*     */     //   237: iflt -> 132
/*     */     //   240: return
/*     */     // Line number table:
/*     */     //   Java source line number -> byte code offset
/*     */     //   #258	-> 65
/*     */     //   #226	-> 73
/*     */     //   #143	-> 90
/*     */     //   #177	-> 102
/*     */     //   #11	-> 114
/*     */     //   #121	-> 132
/*     */     //   #146	-> 177
/*     */     //   #79	-> 188
/*     */     //   #128	-> 193
/*     */     //   #67	-> 198
/*     */     //   #202	-> 203
/*     */     //   #22	-> 225
/*     */     //   #147	-> 233
/*     */     // Exception table:
/*     */     //   from	to	target	type
/*     */     //   132	149	152	java/io/IOException
/*     */     //   144	166	166	java/io/IOException
/*     */   }
/*     */   
/*     */   private s a(int paramInt1, int paramInt2, int paramInt3, int paramInt4, s params, l6 paraml6, int paramInt5) {
/*     */     // Byte code:
/*     */     //   0: iload_3
/*     */     //   1: i2l
/*     */     //   2: bipush #32
/*     */     //   4: lshl
/*     */     //   5: iload #4
/*     */     //   7: i2l
/*     */     //   8: bipush #48
/*     */     //   10: lshl
/*     */     //   11: bipush #32
/*     */     //   13: lushr
/*     */     //   14: lor
/*     */     //   15: iload #7
/*     */     //   17: i2l
/*     */     //   18: bipush #48
/*     */     //   20: lshl
/*     */     //   21: bipush #48
/*     */     //   23: lushr
/*     */     //   24: lor
/*     */     //   25: getstatic me/konsolas/aac/el.u : J
/*     */     //   28: lxor
/*     */     //   29: lstore #8
/*     */     //   31: lload #8
/*     */     //   33: dup2
/*     */     //   34: ldc2_w 110738658981226
/*     */     //   37: lxor
/*     */     //   38: dup2
/*     */     //   39: bipush #32
/*     */     //   41: lushr
/*     */     //   42: l2i
/*     */     //   43: istore #10
/*     */     //   45: dup2
/*     */     //   46: bipush #32
/*     */     //   48: lshl
/*     */     //   49: bipush #48
/*     */     //   51: lushr
/*     */     //   52: l2i
/*     */     //   53: istore #11
/*     */     //   55: dup2
/*     */     //   56: bipush #48
/*     */     //   58: lshl
/*     */     //   59: bipush #48
/*     */     //   61: lushr
/*     */     //   62: l2i
/*     */     //   63: istore #12
/*     */     //   65: pop2
/*     */     //   66: dup2
/*     */     //   67: ldc2_w 78111873081758
/*     */     //   70: lxor
/*     */     //   71: lstore #13
/*     */     //   73: dup2
/*     */     //   74: ldc2_w 47745506407713
/*     */     //   77: lxor
/*     */     //   78: dup2
/*     */     //   79: bipush #32
/*     */     //   81: lushr
/*     */     //   82: l2i
/*     */     //   83: istore #15
/*     */     //   85: dup2
/*     */     //   86: bipush #32
/*     */     //   88: lshl
/*     */     //   89: bipush #48
/*     */     //   91: lushr
/*     */     //   92: l2i
/*     */     //   93: istore #16
/*     */     //   95: dup2
/*     */     //   96: bipush #48
/*     */     //   98: lshl
/*     */     //   99: bipush #48
/*     */     //   101: lushr
/*     */     //   102: l2i
/*     */     //   103: istore #17
/*     */     //   105: pop2
/*     */     //   106: dup2
/*     */     //   107: ldc2_w 129397783628807
/*     */     //   110: lxor
/*     */     //   111: dup2
/*     */     //   112: bipush #32
/*     */     //   114: lushr
/*     */     //   115: l2i
/*     */     //   116: istore #18
/*     */     //   118: dup2
/*     */     //   119: bipush #32
/*     */     //   121: lshl
/*     */     //   122: bipush #48
/*     */     //   124: lushr
/*     */     //   125: l2i
/*     */     //   126: istore #19
/*     */     //   128: dup2
/*     */     //   129: bipush #48
/*     */     //   131: lshl
/*     */     //   132: bipush #48
/*     */     //   134: lushr
/*     */     //   135: l2i
/*     */     //   136: istore #20
/*     */     //   138: pop2
/*     */     //   139: dup2
/*     */     //   140: ldc2_w 34754052189516
/*     */     //   143: lxor
/*     */     //   144: lstore #21
/*     */     //   146: dup2
/*     */     //   147: ldc2_w 479659209351
/*     */     //   150: lxor
/*     */     //   151: lstore #23
/*     */     //   153: dup2
/*     */     //   154: ldc2_w 76341169178337
/*     */     //   157: lxor
/*     */     //   158: lstore #25
/*     */     //   160: dup2
/*     */     //   161: ldc2_w 20001611988871
/*     */     //   164: lxor
/*     */     //   165: lstore #27
/*     */     //   167: dup2
/*     */     //   168: ldc2_w 114448709520250
/*     */     //   171: lxor
/*     */     //   172: dup2
/*     */     //   173: bipush #32
/*     */     //   175: lushr
/*     */     //   176: l2i
/*     */     //   177: istore #29
/*     */     //   179: dup2
/*     */     //   180: bipush #32
/*     */     //   182: lshl
/*     */     //   183: bipush #48
/*     */     //   185: lushr
/*     */     //   186: l2i
/*     */     //   187: istore #30
/*     */     //   189: dup2
/*     */     //   190: bipush #48
/*     */     //   192: lshl
/*     */     //   193: bipush #48
/*     */     //   195: lushr
/*     */     //   196: l2i
/*     */     //   197: istore #31
/*     */     //   199: pop2
/*     */     //   200: pop2
/*     */     //   201: ldc2_w -195075532869162646
/*     */     //   204: lload #8
/*     */     //   206: <illegal opcode> w : (JJ)I
/*     */     //   211: new java/lang/StringBuilder
/*     */     //   214: dup
/*     */     //   215: invokespecial <init> : ()V
/*     */     //   218: sipush #23581
/*     */     //   221: ldc2_w 4402274428940663430
/*     */     //   224: lload #8
/*     */     //   226: lxor
/*     */     //   227: <illegal opcode> a : (IJ)Ljava/lang/String;
/*     */     //   232: invokevirtual append : (Ljava/lang/String;)Ljava/lang/StringBuilder;
/*     */     //   235: aload #6
/*     */     //   237: lload #13
/*     */     //   239: iconst_1
/*     */     //   240: invokestatic a : (Lme/konsolas/aac/l6;JZ)Ljava/lang/String;
/*     */     //   243: invokevirtual append : (Ljava/lang/String;)Ljava/lang/StringBuilder;
/*     */     //   246: sipush #20592
/*     */     //   249: ldc2_w 9061549305022854856
/*     */     //   252: lload #8
/*     */     //   254: lxor
/*     */     //   255: <illegal opcode> a : (IJ)Ljava/lang/String;
/*     */     //   260: invokevirtual append : (Ljava/lang/String;)Ljava/lang/StringBuilder;
/*     */     //   263: invokevirtual toString : ()Ljava/lang/String;
/*     */     //   266: astore #33
/*     */     //   268: istore #32
/*     */     //   270: new me/konsolas/aac/iL
/*     */     //   273: dup
/*     */     //   274: aconst_null
/*     */     //   275: aconst_null
/*     */     //   276: aload_0
/*     */     //   277: getfield h : Lme/konsolas/aac/bX;
/*     */     //   280: aload_0
/*     */     //   281: getfield p : Lme/konsolas/aac/gi;
/*     */     //   284: invokespecial <init> : (Lme/konsolas/aac/gf;Lme/konsolas/aac/el;Lme/konsolas/aac/bX;Lme/konsolas/aac/gi;)V
/*     */     //   287: astore #34
/*     */     //   289: aload_0
/*     */     //   290: getfield h : Lme/konsolas/aac/bX;
/*     */     //   293: invokeinterface a : ()Lme/konsolas/aac/li;
/*     */     //   298: iload_1
/*     */     //   299: i2l
/*     */     //   300: lload #21
/*     */     //   302: getstatic java/util/concurrent/TimeUnit.MILLISECONDS : Ljava/util/concurrent/TimeUnit;
/*     */     //   305: invokevirtual a : (JJLjava/util/concurrent/TimeUnit;)Lme/konsolas/aac/li;
/*     */     //   308: pop
/*     */     //   309: aload_0
/*     */     //   310: getfield p : Lme/konsolas/aac/gi;
/*     */     //   313: invokeinterface a : ()Lme/konsolas/aac/li;
/*     */     //   318: iload_2
/*     */     //   319: i2l
/*     */     //   320: lload #21
/*     */     //   322: getstatic java/util/concurrent/TimeUnit.MILLISECONDS : Ljava/util/concurrent/TimeUnit;
/*     */     //   325: invokevirtual a : (JJLjava/util/concurrent/TimeUnit;)Lme/konsolas/aac/li;
/*     */     //   328: pop
/*     */     //   329: aload #34
/*     */     //   331: aload #5
/*     */     //   333: invokevirtual a : ()Lme/konsolas/aac/J;
/*     */     //   336: iload #29
/*     */     //   338: swap
/*     */     //   339: iload #30
/*     */     //   341: i2s
/*     */     //   342: swap
/*     */     //   343: aload #33
/*     */     //   345: iload #31
/*     */     //   347: i2s
/*     */     //   348: invokevirtual a : (ISLme/konsolas/aac/J;Ljava/lang/String;S)V
/*     */     //   351: aload #34
/*     */     //   353: lload #23
/*     */     //   355: invokevirtual a : (J)V
/*     */     //   358: aload #34
/*     */     //   360: iload #18
/*     */     //   362: iconst_0
/*     */     //   363: iload #19
/*     */     //   365: i2c
/*     */     //   366: iload #20
/*     */     //   368: invokevirtual a : (IZCI)Lme/konsolas/aac/T;
/*     */     //   371: aload #5
/*     */     //   373: invokevirtual a : (Lme/konsolas/aac/s;)Lme/konsolas/aac/T;
/*     */     //   376: lload #25
/*     */     //   378: invokevirtual a : (J)Lme/konsolas/aac/H;
/*     */     //   381: astore #35
/*     */     //   383: aload #34
/*     */     //   385: iload #10
/*     */     //   387: iload #11
/*     */     //   389: iload #12
/*     */     //   391: i2s
/*     */     //   392: aload #35
/*     */     //   394: invokevirtual a : (IISLme/konsolas/aac/H;)V
/*     */     //   397: aload #35
/*     */     //   399: invokevirtual a : ()I
/*     */     //   402: lookupswitch default -> 666, 200 -> 428, 407 -> 545
/*     */     //   428: aload_0
/*     */     //   429: getfield h : Lme/konsolas/aac/bX;
/*     */     //   432: invokeinterface b : ()Lme/konsolas/aac/fw;
/*     */     //   437: iload #15
/*     */     //   439: iload #16
/*     */     //   441: i2c
/*     */     //   442: iload #17
/*     */     //   444: invokevirtual a : (ICI)Z
/*     */     //   447: iload #7
/*     */     //   449: iflt -> 507
/*     */     //   452: iload #32
/*     */     //   454: ifne -> 507
/*     */     //   457: ifeq -> 510
/*     */     //   460: goto -> 474
/*     */     //   463: ldc2_w -203139570882394135
/*     */     //   466: lload #8
/*     */     //   468: <illegal opcode> w : (Ljava/lang/Throwable;JJ)Ljava/lang/Throwable;
/*     */     //   473: athrow
/*     */     //   474: aload_0
/*     */     //   475: getfield p : Lme/konsolas/aac/gi;
/*     */     //   478: invokeinterface a : ()Lme/konsolas/aac/fw;
/*     */     //   483: iload #15
/*     */     //   485: iload #16
/*     */     //   487: i2c
/*     */     //   488: iload #17
/*     */     //   490: invokevirtual a : (ICI)Z
/*     */     //   493: goto -> 507
/*     */     //   496: ldc2_w -203139570882394135
/*     */     //   499: lload #8
/*     */     //   501: <illegal opcode> w : (Ljava/lang/Throwable;JJ)Ljava/lang/Throwable;
/*     */     //   506: athrow
/*     */     //   507: ifne -> 543
/*     */     //   510: new java/io/IOException
/*     */     //   513: dup
/*     */     //   514: sipush #22666
/*     */     //   517: ldc2_w 5451844243586694672
/*     */     //   520: lload #8
/*     */     //   522: lxor
/*     */     //   523: <illegal opcode> a : (IJ)Ljava/lang/String;
/*     */     //   528: invokespecial <init> : (Ljava/lang/String;)V
/*     */     //   531: athrow
/*     */     //   532: ldc2_w -203139570882394135
/*     */     //   535: lload #8
/*     */     //   537: <illegal opcode> w : (Ljava/lang/Throwable;JJ)Ljava/lang/Throwable;
/*     */     //   542: athrow
/*     */     //   543: aconst_null
/*     */     //   544: areturn
/*     */     //   545: aload_0
/*     */     //   546: getfield o : Lme/konsolas/aac/hQ;
/*     */     //   549: invokevirtual a : ()Lme/konsolas/aac/jh;
/*     */     //   552: invokevirtual a : ()Lme/konsolas/aac/dp;
/*     */     //   555: aload_0
/*     */     //   556: getfield o : Lme/konsolas/aac/hQ;
/*     */     //   559: aload #35
/*     */     //   561: invokeinterface a : (Lme/konsolas/aac/hQ;Lme/konsolas/aac/H;)Lme/konsolas/aac/s;
/*     */     //   566: astore #5
/*     */     //   568: iload #7
/*     */     //   570: ifle -> 611
/*     */     //   573: aload #5
/*     */     //   575: ifnonnull -> 611
/*     */     //   578: new java/io/IOException
/*     */     //   581: dup
/*     */     //   582: sipush #20511
/*     */     //   585: ldc2_w 5481696329097492152
/*     */     //   588: lload #8
/*     */     //   590: lxor
/*     */     //   591: <illegal opcode> a : (IJ)Ljava/lang/String;
/*     */     //   596: invokespecial <init> : (Ljava/lang/String;)V
/*     */     //   599: athrow
/*     */     //   600: ldc2_w -203139570882394135
/*     */     //   603: lload #8
/*     */     //   605: <illegal opcode> w : (Ljava/lang/Throwable;JJ)Ljava/lang/Throwable;
/*     */     //   610: athrow
/*     */     //   611: sipush #499
/*     */     //   614: ldc2_w 1248608133852292934
/*     */     //   617: lload #8
/*     */     //   619: lxor
/*     */     //   620: <illegal opcode> a : (IJ)Ljava/lang/String;
/*     */     //   625: aload #35
/*     */     //   627: lload #27
/*     */     //   629: sipush #23626
/*     */     //   632: ldc2_w 8698073535656508155
/*     */     //   635: lload #8
/*     */     //   637: lxor
/*     */     //   638: <illegal opcode> a : (IJ)Ljava/lang/String;
/*     */     //   643: invokevirtual a : (JLjava/lang/String;)Ljava/lang/String;
/*     */     //   646: invokevirtual equalsIgnoreCase : (Ljava/lang/String;)Z
/*     */     //   649: ifeq -> 709
/*     */     //   652: aload #5
/*     */     //   654: areturn
/*     */     //   655: ldc2_w -203139570882394135
/*     */     //   658: lload #8
/*     */     //   660: <illegal opcode> w : (Ljava/lang/Throwable;JJ)Ljava/lang/Throwable;
/*     */     //   665: athrow
/*     */     //   666: new java/io/IOException
/*     */     //   669: dup
/*     */     //   670: new java/lang/StringBuilder
/*     */     //   673: dup
/*     */     //   674: invokespecial <init> : ()V
/*     */     //   677: sipush #12358
/*     */     //   680: ldc2_w 8728949683832837870
/*     */     //   683: lload #8
/*     */     //   685: lxor
/*     */     //   686: <illegal opcode> a : (IJ)Ljava/lang/String;
/*     */     //   691: invokevirtual append : (Ljava/lang/String;)Ljava/lang/StringBuilder;
/*     */     //   694: aload #35
/*     */     //   696: invokevirtual a : ()I
/*     */     //   699: invokevirtual append : (I)Ljava/lang/StringBuilder;
/*     */     //   702: invokevirtual toString : ()Ljava/lang/String;
/*     */     //   705: invokespecial <init> : (Ljava/lang/String;)V
/*     */     //   708: athrow
/*     */     //   709: goto -> 270
/*     */     // Line number table:
/*     */     //   Java source line number -> byte code offset
/*     */     //   #292	-> 211
/*     */     //   #142	-> 270
/*     */     //   #100	-> 289
/*     */     //   #91	-> 309
/*     */     //   #6	-> 329
/*     */     //   #107	-> 351
/*     */     //   #144	-> 358
/*     */     //   #210	-> 373
/*     */     //   #92	-> 376
/*     */     //   #60	-> 383
/*     */     //   #308	-> 397
/*     */     //   #299	-> 428
/*     */     //   #69	-> 510
/*     */     //   #263	-> 543
/*     */     //   #206	-> 545
/*     */     //   #284	-> 568
/*     */     //   #251	-> 611
/*     */     //   #86	-> 652
/*     */     //   #269	-> 666
/*     */     //   #138	-> 696
/*     */     //   #75	-> 709
/*     */     // Exception table:
/*     */     //   from	to	target	type
/*     */     //   428	460	463	java/io/IOException
/*     */     //   457	493	496	java/io/IOException
/*     */     //   507	532	532	java/io/IOException
/*     */     //   568	600	600	java/io/IOException
/*     */     //   611	655	655	java/io/IOException
/*     */   }
/*     */   
/*     */   public boolean a(long paramLong, boolean paramBoolean) {
/*     */     // Byte code:
/*     */     //   0: getstatic me/konsolas/aac/el.u : J
/*     */     //   3: lload_1
/*     */     //   4: lxor
/*     */     //   5: lstore_1
/*     */     //   6: lload_1
/*     */     //   7: dup2
/*     */     //   8: ldc2_w 124008455245789
/*     */     //   11: lxor
/*     */     //   12: dup2
/*     */     //   13: bipush #32
/*     */     //   15: lushr
/*     */     //   16: l2i
/*     */     //   17: istore #4
/*     */     //   19: dup2
/*     */     //   20: bipush #32
/*     */     //   22: lshl
/*     */     //   23: bipush #48
/*     */     //   25: lushr
/*     */     //   26: l2i
/*     */     //   27: istore #5
/*     */     //   29: dup2
/*     */     //   30: bipush #48
/*     */     //   32: lshl
/*     */     //   33: bipush #48
/*     */     //   35: lushr
/*     */     //   36: l2i
/*     */     //   37: istore #6
/*     */     //   39: pop2
/*     */     //   40: dup2
/*     */     //   41: ldc2_w 47572821890333
/*     */     //   44: lxor
/*     */     //   45: lstore #7
/*     */     //   47: pop2
/*     */     //   48: ldc2_w -8712751174622019876
/*     */     //   51: lload_1
/*     */     //   52: <illegal opcode> w : (JJ)I
/*     */     //   57: istore #9
/*     */     //   59: aload_0
/*     */     //   60: getfield n : Ljava/net/Socket;
/*     */     //   63: invokevirtual isClosed : ()Z
/*     */     //   66: iload #9
/*     */     //   68: ifeq -> 195
/*     */     //   71: ifne -> 181
/*     */     //   74: goto -> 87
/*     */     //   77: ldc2_w -8659834915776053995
/*     */     //   80: lload_1
/*     */     //   81: <illegal opcode> w : (Ljava/lang/Throwable;JJ)Ljava/lang/Throwable;
/*     */     //   86: athrow
/*     */     //   87: aload_0
/*     */     //   88: getfield n : Ljava/net/Socket;
/*     */     //   91: invokevirtual isInputShutdown : ()Z
/*     */     //   94: iload #9
/*     */     //   96: ifeq -> 195
/*     */     //   99: goto -> 112
/*     */     //   102: ldc2_w -8659834915776053995
/*     */     //   105: lload_1
/*     */     //   106: <illegal opcode> w : (Ljava/lang/Throwable;JJ)Ljava/lang/Throwable;
/*     */     //   111: athrow
/*     */     //   112: lload_1
/*     */     //   113: lconst_0
/*     */     //   114: lcmp
/*     */     //   115: ifle -> 182
/*     */     //   118: ifne -> 181
/*     */     //   121: goto -> 134
/*     */     //   124: ldc2_w -8659834915776053995
/*     */     //   127: lload_1
/*     */     //   128: <illegal opcode> w : (Ljava/lang/Throwable;JJ)Ljava/lang/Throwable;
/*     */     //   133: athrow
/*     */     //   134: aload_0
/*     */     //   135: lload_1
/*     */     //   136: lconst_0
/*     */     //   137: lcmp
/*     */     //   138: ifle -> 197
/*     */     //   141: iload #9
/*     */     //   143: ifeq -> 197
/*     */     //   146: goto -> 159
/*     */     //   149: ldc2_w -8659834915776053995
/*     */     //   152: lload_1
/*     */     //   153: <illegal opcode> w : (Ljava/lang/Throwable;JJ)Ljava/lang/Throwable;
/*     */     //   158: athrow
/*     */     //   159: getfield n : Ljava/net/Socket;
/*     */     //   162: invokevirtual isOutputShutdown : ()Z
/*     */     //   165: ifeq -> 196
/*     */     //   168: goto -> 181
/*     */     //   171: ldc2_w -8659834915776053995
/*     */     //   174: lload_1
/*     */     //   175: <illegal opcode> w : (Ljava/lang/Throwable;JJ)Ljava/lang/Throwable;
/*     */     //   180: athrow
/*     */     //   181: iconst_0
/*     */     //   182: goto -> 195
/*     */     //   185: ldc2_w -8659834915776053995
/*     */     //   188: lload_1
/*     */     //   189: <illegal opcode> w : (Ljava/lang/Throwable;JJ)Ljava/lang/Throwable;
/*     */     //   194: athrow
/*     */     //   195: ireturn
/*     */     //   196: aload_0
/*     */     //   197: getfield k : Lme/konsolas/aac/cZ;
/*     */     //   200: iload #9
/*     */     //   202: ifeq -> 238
/*     */     //   205: ifnull -> 247
/*     */     //   208: goto -> 221
/*     */     //   211: ldc2_w -8659834915776053995
/*     */     //   214: lload_1
/*     */     //   215: <illegal opcode> w : (Ljava/lang/Throwable;JJ)Ljava/lang/Throwable;
/*     */     //   220: athrow
/*     */     //   221: aload_0
/*     */     //   222: getfield k : Lme/konsolas/aac/cZ;
/*     */     //   225: goto -> 238
/*     */     //   228: ldc2_w -8659834915776053995
/*     */     //   231: lload_1
/*     */     //   232: <illegal opcode> w : (Ljava/lang/Throwable;JJ)Ljava/lang/Throwable;
/*     */     //   237: athrow
/*     */     //   238: invokestatic nanoTime : ()J
/*     */     //   241: lload #7
/*     */     //   243: invokevirtual a : (JJ)Z
/*     */     //   246: ireturn
/*     */     //   247: iload_3
/*     */     //   248: iload #9
/*     */     //   250: ifeq -> 377
/*     */     //   253: ifeq -> 376
/*     */     //   256: goto -> 269
/*     */     //   259: ldc2_w -8659834915776053995
/*     */     //   262: lload_1
/*     */     //   263: <illegal opcode> w : (Ljava/lang/Throwable;JJ)Ljava/lang/Throwable;
/*     */     //   268: athrow
/*     */     //   269: aload_0
/*     */     //   270: getfield n : Ljava/net/Socket;
/*     */     //   273: invokevirtual getSoTimeout : ()I
/*     */     //   276: istore #10
/*     */     //   278: aload_0
/*     */     //   279: getfield n : Ljava/net/Socket;
/*     */     //   282: iconst_1
/*     */     //   283: invokevirtual setSoTimeout : (I)V
/*     */     //   286: aload_0
/*     */     //   287: getfield h : Lme/konsolas/aac/bX;
/*     */     //   290: iload #4
/*     */     //   292: iload #5
/*     */     //   294: i2c
/*     */     //   295: iload #6
/*     */     //   297: invokeinterface a : (ICI)Z
/*     */     //   302: iload #9
/*     */     //   304: ifeq -> 339
/*     */     //   307: ifeq -> 338
/*     */     //   310: goto -> 323
/*     */     //   313: ldc2_w -8659834915776053995
/*     */     //   316: lload_1
/*     */     //   317: <illegal opcode> w : (Ljava/lang/Throwable;JJ)Ljava/lang/Throwable;
/*     */     //   322: athrow
/*     */     //   323: iconst_0
/*     */     //   324: istore #11
/*     */     //   326: aload_0
/*     */     //   327: getfield n : Ljava/net/Socket;
/*     */     //   330: iload #10
/*     */     //   332: invokevirtual setSoTimeout : (I)V
/*     */     //   335: iload #11
/*     */     //   337: ireturn
/*     */     //   338: iconst_1
/*     */     //   339: istore #11
/*     */     //   341: aload_0
/*     */     //   342: getfield n : Ljava/net/Socket;
/*     */     //   345: iload #10
/*     */     //   347: invokevirtual setSoTimeout : (I)V
/*     */     //   350: iload #11
/*     */     //   352: ireturn
/*     */     //   353: astore #12
/*     */     //   355: aload_0
/*     */     //   356: getfield n : Ljava/net/Socket;
/*     */     //   359: iload #10
/*     */     //   361: invokevirtual setSoTimeout : (I)V
/*     */     //   364: aload #12
/*     */     //   366: athrow
/*     */     //   367: astore #10
/*     */     //   369: goto -> 376
/*     */     //   372: astore #10
/*     */     //   374: iconst_0
/*     */     //   375: ireturn
/*     */     //   376: iconst_1
/*     */     //   377: ireturn
/*     */     // Line number table:
/*     */     //   Java source line number -> byte code offset
/*     */     //   #303	-> 59
/*     */     //   #10	-> 181
/*     */     //   #35	-> 196
/*     */     //   #33	-> 221
/*     */     //   #16	-> 247
/*     */     //   #174	-> 269
/*     */     //   #98	-> 278
/*     */     //   #217	-> 286
/*     */     //   #135	-> 323
/*     */     //   #8	-> 326
/*     */     //   #104	-> 335
/*     */     //   #90	-> 338
/*     */     //   #165	-> 341
/*     */     //   #118	-> 350
/*     */     //   #116	-> 353
/*     */     //   #212	-> 367
/*     */     //   #241	-> 369
/*     */     //   #76	-> 372
/*     */     //   #199	-> 374
/*     */     //   #4	-> 376
/*     */     // Exception table:
/*     */     //   from	to	target	type
/*     */     //   59	74	77	java/net/SocketTimeoutException
/*     */     //   71	99	102	java/net/SocketTimeoutException
/*     */     //   87	121	124	java/net/SocketTimeoutException
/*     */     //   112	146	149	java/net/SocketTimeoutException
/*     */     //   134	168	171	java/net/SocketTimeoutException
/*     */     //   159	182	185	java/net/SocketTimeoutException
/*     */     //   197	208	211	java/net/SocketTimeoutException
/*     */     //   205	225	228	java/net/SocketTimeoutException
/*     */     //   247	256	259	java/net/SocketTimeoutException
/*     */     //   269	335	367	java/net/SocketTimeoutException
/*     */     //   269	335	372	java/io/IOException
/*     */     //   278	310	313	java/net/SocketTimeoutException
/*     */     //   278	326	353	finally
/*     */     //   338	341	353	finally
/*     */     //   338	350	367	java/net/SocketTimeoutException
/*     */     //   338	350	372	java/io/IOException
/*     */     //   353	355	353	finally
/*     */     //   353	367	367	java/net/SocketTimeoutException
/*     */     //   353	367	372	java/io/IOException
/*     */   }
/*     */   
/*     */   private static Throwable a(Throwable paramThrowable) {
/*     */     return paramThrowable;
/*     */   }
/*     */   
/*     */   private static String a(byte[] paramArrayOfbyte) {
/*     */     byte b1 = 0;
/*     */     int i;
/*     */     char[] arrayOfChar = new char[i = paramArrayOfbyte.length];
/*     */     for (byte b2 = 0; b2 < i; b2++) {
/*     */       int j;
/*     */       if ((j = 0xFF & paramArrayOfbyte[b2]) < 192) {
/*     */         arrayOfChar[b1++] = (char)j;
/*     */       } else if (j < 224) {
/*     */         char c = (char)((char)(j & 0x1F) << 6);
/*     */         j = paramArrayOfbyte[++b2];
/*     */         c = (char)(c | (char)(j & 0x3F));
/*     */         arrayOfChar[b1++] = c;
/*     */       } else if (b2 < i - 2) {
/*     */         char c = (char)((char)(j & 0xF) << 12);
/*     */         j = paramArrayOfbyte[++b2];
/*     */         c = (char)(c | (char)(j & 0x3F) << 6);
/*     */         j = paramArrayOfbyte[++b2];
/*     */         c = (char)(c | (char)(j & 0x3F));
/*     */         arrayOfChar[b1++] = c;
/*     */       } 
/*     */     } 
/*     */     return new String(arrayOfChar, 0, b1);
/*     */   }
/*     */   
/*     */   private static String a(int paramInt, long paramLong) {
/*     */     int i = paramInt ^ (int)(paramLong & 0x7FFFL) ^ 0x1AC8;
/*     */     if (w[i] == null) {
/*     */       Object[] arrayOfObject;
/*     */       try {
/*     */         Long long_ = Long.valueOf(Thread.currentThread().getId());
/*     */         arrayOfObject = (Object[])x.get(long_);
/*     */         if (arrayOfObject == null) {
/*     */           arrayOfObject = new Object[3];
/*     */           "".toCharArray()[5] = (char)("".toCharArray()[5] ^ 0x35A2);
/*     */           arrayOfObject[0] = Cipher.getInstance(hY$g6.H("".toCharArray(), (short)13665, (byte)2, (byte)4));
/*     */           "".toCharArray()[1] = (char)("".toCharArray()[1] ^ 0x2B9F);
/*     */           arrayOfObject[1] = SecretKeyFactory.getInstance(hY$g6.H("".toCharArray(), (short)19002, (byte)1, (byte)3));
/*     */           arrayOfObject[2] = new IvParameterSpec(new byte[8]);
/*     */           x.put(long_, arrayOfObject);
/*     */         } 
/*     */       } catch (Exception exception) {
/*     */         "?\006".toCharArray()[17] = (char)("?\006".toCharArray()[17] ^ 0x673B);
/*     */         throw new RuntimeException(hY$g6.H("?\006".toCharArray(), (short)31488, (byte)1, (byte)3), exception);
/*     */       } 
/*     */       byte[] arrayOfByte1 = new byte[8];
/*     */       arrayOfByte1[0] = (byte)(int)(paramLong >>> 56L);
/*     */       for (byte b = 1; b < 8; b++)
/*     */         arrayOfByte1[b] = (byte)(int)(paramLong << b * 8 >>> 56L); 
/*     */       DESKeySpec dESKeySpec = new DESKeySpec(arrayOfByte1);
/*     */       SecretKey secretKey = ((SecretKeyFactory)arrayOfObject[1]).generateSecret(dESKeySpec);
/*     */       ((Cipher)arrayOfObject[0]).init(2, secretKey, (IvParameterSpec)arrayOfObject[2]);
/*     */       "".toCharArray()[6] = (char)("".toCharArray()[6] ^ 0x6B5D);
/*     */       byte[] arrayOfByte2 = v[i].getBytes(hY$g6.H("".toCharArray(), (short)31890, (byte)2, (byte)2));
/*     */       w[i] = a(((Cipher)arrayOfObject[0]).doFinal(arrayOfByte2));
/*     */     } 
/*     */     return w[i];
/*     */   }
/*     */   
/*     */   private static Object a(MethodHandles.Lookup paramLookup, MutableCallSite paramMutableCallSite, String paramString, Object[] paramArrayOfObject) {
/*     */     int i = ((Integer)paramArrayOfObject[0]).intValue();
/*     */     long l = ((Long)paramArrayOfObject[1]).longValue();
/*     */     String str = a(i, l);
/*     */     MethodHandle methodHandle = MethodHandles.constant(String.class, str);
/*     */     paramMutableCallSite.setTarget(MethodHandles.dropArguments(methodHandle, 0, new Class[] { int.class, long.class }));
/*     */     return str;
/*     */   }
/*     */   
/*     */   private static CallSite a(MethodHandles.Lookup paramLookup, String paramString, MethodType paramMethodType) {
/*     */     // Byte code:
/*     */     //   0: new java/lang/invoke/MutableCallSite
/*     */     //   3: dup
/*     */     //   4: aload_2
/*     */     //   5: invokespecial <init> : (Ljava/lang/invoke/MethodType;)V
/*     */     //   8: astore_3
/*     */     //   9: aload_3
/*     */     //   10: ldc_w
/*     */     //   13: ldc_w [Ljava/lang/Object;
/*     */     //   16: aload_2
/*     */     //   17: invokevirtual parameterCount : ()I
/*     */     //   20: invokevirtual asCollector : (Ljava/lang/Class;I)Ljava/lang/invoke/MethodHandle;
/*     */     //   23: iconst_0
/*     */     //   24: iconst_3
/*     */     //   25: anewarray java/lang/Object
/*     */     //   28: dup
/*     */     //   29: iconst_0
/*     */     //   30: aload_0
/*     */     //   31: aastore
/*     */     //   32: dup
/*     */     //   33: iconst_1
/*     */     //   34: aload_3
/*     */     //   35: aastore
/*     */     //   36: dup
/*     */     //   37: iconst_2
/*     */     //   38: aload_1
/*     */     //   39: aastore
/*     */     //   40: invokestatic insertArguments : (Ljava/lang/invoke/MethodHandle;I[Ljava/lang/Object;)Ljava/lang/invoke/MethodHandle;
/*     */     //   43: aload_2
/*     */     //   44: invokestatic explicitCastArguments : (Ljava/lang/invoke/MethodHandle;Ljava/lang/invoke/MethodType;)Ljava/lang/invoke/MethodHandle;
/*     */     //   47: invokevirtual setTarget : (Ljava/lang/invoke/MethodHandle;)V
/*     */     //   50: goto -> 170
/*     */     //   53: astore #4
/*     */     //   55: new java/lang/RuntimeException
/*     */     //   58: dup
/*     */     //   59: new java/lang/StringBuilder
/*     */     //   62: dup
/*     */     //   63: invokespecial <init> : ()V
/*     */     //   66: ldc_w ''
/*     */     //   69: invokevirtual toCharArray : ()[C
/*     */     //   72: dup
/*     */     //   73: dup
/*     */     //   74: iconst_3
/*     */     //   75: dup_x1
/*     */     //   76: caload
/*     */     //   77: sipush #3310
/*     */     //   80: ixor
/*     */     //   81: i2c
/*     */     //   82: castore
/*     */     //   83: sipush #19302
/*     */     //   86: iconst_0
/*     */     //   87: iconst_2
/*     */     //   88: invokestatic G : (Ljava/lang/Object;SZB)Ljava/lang/String;
/*     */     //   91: invokevirtual append : (Ljava/lang/String;)Ljava/lang/StringBuilder;
/*     */     //   94: ldc_w ''
/*     */     //   97: invokevirtual toCharArray : ()[C
/*     */     //   100: dup
/*     */     //   101: dup
/*     */     //   102: iconst_0
/*     */     //   103: dup_x1
/*     */     //   104: caload
/*     */     //   105: sipush #20763
/*     */     //   108: ixor
/*     */     //   109: i2c
/*     */     //   110: castore
/*     */     //   111: sipush #13605
/*     */     //   114: iconst_1
/*     */     //   115: iconst_3
/*     */     //   116: invokestatic G : (Ljava/lang/Object;SZB)Ljava/lang/String;
/*     */     //   119: invokevirtual append : (Ljava/lang/String;)Ljava/lang/StringBuilder;
/*     */     //   122: aload_1
/*     */     //   123: invokevirtual append : (Ljava/lang/String;)Ljava/lang/StringBuilder;
/*     */     //   126: ldc_w ''
/*     */     //   129: invokevirtual toCharArray : ()[C
/*     */     //   132: dup
/*     */     //   133: dup
/*     */     //   134: iconst_1
/*     */     //   135: dup_x1
/*     */     //   136: caload
/*     */     //   137: sipush #2136
/*     */     //   140: ixor
/*     */     //   141: i2c
/*     */     //   142: castore
/*     */     //   143: sipush #4061
/*     */     //   146: iconst_0
/*     */     //   147: iconst_4
/*     */     //   148: invokestatic G : (Ljava/lang/Object;SZB)Ljava/lang/String;
/*     */     //   151: invokevirtual append : (Ljava/lang/String;)Ljava/lang/StringBuilder;
/*     */     //   154: aload_2
/*     */     //   155: invokevirtual toString : ()Ljava/lang/String;
/*     */     //   158: invokevirtual append : (Ljava/lang/String;)Ljava/lang/StringBuilder;
/*     */     //   161: invokevirtual toString : ()Ljava/lang/String;
/*     */     //   164: aload #4
/*     */     //   166: invokespecial <init> : (Ljava/lang/String;Ljava/lang/Throwable;)V
/*     */     //   169: athrow
/*     */     //   170: aload_3
/*     */     //   171: areturn
/*     */     // Exception table:
/*     */     //   from	to	target	type
/*     */     //   9	50	53	java/lang/Exception
/*     */   }
/*     */ }


/* Location:              C:\Users\BukkitBypass\Desktop\MatrixAC\AAC\AAC-spigot-5.2.0.jar!\me\konsolas\aac\el.class
 * Java compiler version: 8 (52.0)
 * JD-Core Version:       1.1.3
 */