/*     */ package me.konsolas.aac;public final class fd { public static final byte[][] j; public static final byte[][] a; public static final m9 d; private static final int h = 7; private static final int k = 8192;
/*     */   private static final int g = 40;
/*     */   private static final int f = 8;
/*     */   private static final int c = 255;
/*     */   private static final int b = 1;
/*     */   private static final int e = 1024;
/*     */   private static boolean i;
/*     */   private static final long l;
/*     */   
/*  10 */   public static void b(byte[][] paramArrayOfbyte) { f(paramArrayOfbyte, 0L, k.a(paramArrayOfbyte)); }
/*  11 */   private static long a(byte[][] paramArrayOfbyte, long paramLong1, long paramLong2, long paramLong3, g9 paramg9) { int i = paramg9.a(k.a(paramArrayOfbyte, paramLong1), k.a(paramArrayOfbyte, paramLong2));
/*     */ 
/*     */ 
/*     */ 
/*     */ 
/*     */ 
/*     */ 
/*     */ 
/*     */ 
/*     */ 
/*     */ 
/*     */ 
/*     */ 
/*     */ 
/*     */ 
/*     */ 
/*     */ 
/*     */ 
/*     */ 
/*     */ 
/*     */ 
/*     */ 
/*     */ 
/*     */ 
/*     */ 
/*     */ 
/*     */ 
/*     */ 
/*     */ 
/*     */ 
/*     */ 
/*     */ 
/*     */ 
/*     */ 
/*     */ 
/*     */ 
/*     */ 
/*     */ 
/*     */ 
/*     */ 
/*     */ 
/*     */ 
/*     */ 
/*     */ 
/*     */ 
/*     */ 
/*     */ 
/*     */ 
/*     */ 
/*     */ 
/*     */ 
/*     */ 
/*     */ 
/*     */ 
/*     */ 
/*     */ 
/*     */ 
/*     */ 
/*     */ 
/*     */ 
/*     */ 
/*     */ 
/*     */ 
/*     */ 
/*     */ 
/*     */ 
/*     */ 
/*     */ 
/*     */ 
/*     */ 
/*     */ 
/*     */ 
/*     */ 
/*     */ 
/*     */ 
/*     */ 
/*     */ 
/*     */ 
/*     */ 
/*     */ 
/*     */ 
/*     */ 
/*     */ 
/*     */ 
/*     */ 
/*     */ 
/*     */ 
/*     */ 
/*     */ 
/*     */ 
/*     */ 
/*     */ 
/*     */ 
/*     */ 
/*     */ 
/*     */ 
/*     */ 
/*     */ 
/*     */ 
/*     */ 
/*     */ 
/*     */ 
/*     */ 
/*     */ 
/*     */ 
/*     */ 
/*     */ 
/*     */ 
/*     */ 
/*     */ 
/*     */ 
/*     */ 
/*     */ 
/*     */ 
/*     */ 
/*     */ 
/*     */ 
/*     */ 
/*     */ 
/*     */ 
/*     */ 
/*     */ 
/*     */ 
/*     */ 
/*     */ 
/*     */ 
/*     */ 
/*     */ 
/*     */ 
/*     */ 
/*     */ 
/*     */ 
/*     */ 
/*     */ 
/*     */ 
/*     */ 
/*     */ 
/*     */ 
/*     */ 
/*     */ 
/*     */ 
/*     */ 
/*     */ 
/*     */ 
/*     */ 
/*     */ 
/*     */ 
/*     */ 
/*     */ 
/*     */ 
/*     */ 
/*     */ 
/*     */ 
/*     */ 
/*     */ 
/*     */ 
/*     */ 
/*     */ 
/*     */ 
/*     */ 
/*     */ 
/*     */ 
/*     */ 
/*     */ 
/*     */ 
/*     */ 
/*     */ 
/*     */ 
/*     */ 
/*     */ 
/*     */ 
/*     */ 
/*     */ 
/*     */ 
/*     */ 
/*     */ 
/*     */ 
/*     */ 
/*     */ 
/*     */ 
/*     */ 
/*     */ 
/*     */ 
/*     */ 
/*     */ 
/*     */ 
/*     */ 
/*     */ 
/*     */ 
/*     */ 
/*     */ 
/*     */ 
/*     */ 
/*     */ 
/*     */ 
/*     */ 
/*     */ 
/*     */ 
/*     */ 
/*     */ 
/*     */ 
/*     */ 
/*     */ 
/*     */ 
/*     */ 
/*     */ 
/*     */ 
/*     */ 
/*     */ 
/*     */ 
/*     */ 
/*     */ 
/*     */ 
/*     */     
/* 225 */     int j = paramg9.a(k.a(paramArrayOfbyte, paramLong1), k.a(paramArrayOfbyte, paramLong3));
/*     */ 
/*     */ 
/*     */ 
/*     */ 
/*     */ 
/*     */ 
/*     */ 
/*     */ 
/*     */ 
/*     */ 
/*     */ 
/*     */ 
/*     */ 
/*     */ 
/*     */ 
/*     */ 
/*     */ 
/*     */ 
/*     */ 
/*     */ 
/*     */ 
/*     */ 
/*     */ 
/*     */ 
/*     */ 
/*     */ 
/*     */ 
/*     */ 
/*     */ 
/*     */ 
/*     */ 
/*     */ 
/*     */ 
/*     */ 
/*     */ 
/*     */ 
/*     */ 
/*     */ 
/*     */ 
/*     */ 
/*     */ 
/*     */     
/*     */     int k = paramg9.a(k.a(paramArrayOfbyte, paramLong2), k.a(paramArrayOfbyte, paramLong3));
/*     */ 
/*     */ 
/*     */ 
/*     */ 
/*     */ 
/*     */ 
/*     */ 
/*     */ 
/*     */ 
/*     */ 
/*     */ 
/*     */ 
/*     */ 
/*     */ 
/*     */ 
/*     */ 
/*     */ 
/*     */ 
/*     */ 
/*     */ 
/*     */ 
/*     */ 
/*     */ 
/*     */ 
/*     */ 
/*     */ 
/*     */ 
/*     */ 
/*     */ 
/*     */ 
/*     */ 
/*     */ 
/*     */ 
/*     */ 
/*     */ 
/*     */ 
/*     */ 
/*     */ 
/*     */ 
/*     */ 
/*     */ 
/*     */ 
/*     */     
/*     */     try { if (i < 0)
/*     */       { try {
/*     */           try {
/*     */           
/*     */           } catch (IllegalArgumentException illegalArgumentException) {
/*     */             throw a(null);
/*     */           } 
/*     */         } catch (IllegalArgumentException illegalArgumentException) {
/*     */           throw a(null);
/*     */         }  }
/*     */       else
/*     */       { 
/*     */         try { 
/*     */           try {  }
/*     */           catch (IllegalArgumentException illegalArgumentException)
/* 327 */           { throw a(null); }  } catch (IllegalArgumentException illegalArgumentException) { throw a(null); }  }  } catch (IllegalArgumentException illegalArgumentException) { throw a(null); }  return (k > 0) ? paramLong2 : ((j > 0) ? paramLong3 : paramLong1); }
/*     */   @Deprecated
/*     */   public static void a(byte[][] paramArrayOfbyte, long paramLong, byte paramByte) { paramArrayOfbyte[k.b(paramLong)][k.a(paramLong)] = (byte)(paramArrayOfbyte[k.b(paramLong)][k.a(paramLong)] + paramByte); }
/*     */   @Deprecated
/*     */   public static void a(byte[][] paramArrayOfbyte, long paramLong) { paramArrayOfbyte[k.b(paramLong)][k.a(paramLong)] = (byte)(paramArrayOfbyte[k.b(paramLong)][k.a(paramLong)] + 1); }
/*     */   public static long a(byte[][] paramArrayOfbyte, byte paramByte, g9 paramg9) { return a(paramArrayOfbyte, 0L, k.a(paramArrayOfbyte), paramByte, paramg9); }
/*     */   public static byte[][] a(byte[][] paramArrayOfbyte, long paramLong1, long paramLong2, Random paramRandom) { return k.a(paramArrayOfbyte, paramLong1, paramLong2, paramRandom); }
/*     */   @Deprecated
/*     */   public static void a(byte[][] paramArrayOfbyte, byte paramByte) { int i = paramArrayOfbyte.length;
/*     */     try {
/*     */       for (; i-- != 0; Arrays.fill(paramArrayOfbyte[i], paramByte));
/*     */     } catch (IllegalArgumentException illegalArgumentException) {
/*     */       throw a(null);
/*     */     }  }
/*     */   @Deprecated
/*     */   public static long a(byte[][] paramArrayOfbyte) { int i = paramArrayOfbyte.length;
/*     */     
/*     */     try {  }
/*     */     catch (IllegalArgumentException illegalArgumentException)
/* 346 */     { throw a(null); }  return (i == 0) ? 0L : (k.a(i - 1) + (paramArrayOfbyte[i - 1]).length); }
/*     */   private static long b(byte[][] paramArrayOfbyte, long paramLong1, long paramLong2, long paramLong3) { int i = Byte.compare(k.a(paramArrayOfbyte, paramLong1), k.a(paramArrayOfbyte, paramLong2));
/*     */     int j = Byte.compare(k.a(paramArrayOfbyte, paramLong1), k.a(paramArrayOfbyte, paramLong3));
/*     */     int k = Byte.compare(k.a(paramArrayOfbyte, paramLong2), k.a(paramArrayOfbyte, paramLong3));
/*     */     try {
/*     */       if (i < 0) {
/*     */         try {
/*     */           try {
/*     */           
/*     */           } catch (IllegalArgumentException illegalArgumentException) {
/*     */             throw a(null);
/*     */           } 
/*     */         } catch (IllegalArgumentException illegalArgumentException) {
/*     */           throw a(null);
/*     */         } 
/*     */       } else {
/*     */         try {
/*     */           try {
/*     */           
/*     */           } catch (IllegalArgumentException illegalArgumentException) {
/*     */             throw a(null);
/*     */           } 
/*     */         } catch (IllegalArgumentException illegalArgumentException) {
/*     */           throw a(null);
/*     */         } 
/*     */       } 
/*     */     } catch (IllegalArgumentException illegalArgumentException) {
/*     */       throw a(null);
/*     */     } 
/*     */     return (k > 0) ? paramLong2 : ((j > 0) ? paramLong3 : paramLong1); }
/*     */   @Deprecated
/*     */   public static void b(byte[][] paramArrayOfbyte1, byte[][] paramArrayOfbyte2) { // Byte code:
/*     */     //   0: getstatic me/konsolas/aac/fd.l : J
/*     */     //   3: ldc2_w 131619252283381
/*     */     //   6: lxor
/*     */     //   7: lstore_2
/*     */     //   8: aload_0
/*     */     //   9: invokestatic a : ([[B)J
/*     */     //   12: aload_1
/*     */     //   13: invokestatic a : ([[B)J
/*     */     //   16: lcmp
/*     */     //   17: ifeq -> 117
/*     */     //   20: new java/lang/IllegalArgumentException
/*     */     //   23: dup
/*     */     //   24: new java/lang/StringBuilder
/*     */     //   27: dup
/*     */     //   28: invokespecial <init> : ()V
/*     */     //   31: ldc 'ꑨ成㯟꧞᎗奦蟉⫻⠐ᮟᮭ룁붌ꭃꑳ褾䠣慳㎸됐搊'
/*     */     //   33: invokevirtual toCharArray : ()[C
/*     */     //   36: dup
/*     */     //   37: dup
/*     */     //   38: bipush #10
/*     */     //   40: dup_x1
/*     */     //   41: caload
/*     */     //   42: sipush #21906
/*     */     //   45: ixor
/*     */     //   46: i2c
/*     */     //   47: castore
/*     */     //   48: sipush #13843
/*     */     //   51: iconst_1
/*     */     //   52: iconst_1
/*     */     //   53: invokestatic U : (Ljava/lang/Object;SZZ)Ljava/lang/String;
/*     */     //   56: invokevirtual append : (Ljava/lang/String;)Ljava/lang/StringBuilder;
/*     */     //   59: aload_0
/*     */     //   60: invokestatic a : ([[B)J
/*     */     //   63: invokevirtual append : (J)Ljava/lang/StringBuilder;
/*     */     //   66: ldc 'ⴰ⬉赦寧䬭'
/*     */     //   68: invokevirtual toCharArray : ()[C
/*     */     //   71: dup
/*     */     //   72: dup
/*     */     //   73: iconst_0
/*     */     //   74: dup_x1
/*     */     //   75: caload
/*     */     //   76: sipush #29013
/*     */     //   79: ixor
/*     */     //   80: i2c
/*     */     //   81: castore
/*     */     //   82: sipush #3675
/*     */     //   85: iconst_0
/*     */     //   86: iconst_1
/*     */     //   87: invokestatic U : (Ljava/lang/Object;SZZ)Ljava/lang/String;
/*     */     //   90: invokevirtual append : (Ljava/lang/String;)Ljava/lang/StringBuilder;
/*     */     //   93: aload_1
/*     */     //   94: invokestatic a : ([[B)J
/*     */     //   97: invokevirtual append : (J)Ljava/lang/StringBuilder;
/*     */     //   100: invokevirtual toString : ()Ljava/lang/String;
/*     */     //   103: invokespecial <init> : (Ljava/lang/String;)V
/*     */     //   106: athrow
/*     */     //   107: ldc2_w 4911385783321774
/*     */     //   110: lload_2
/*     */     //   111: <illegal opcode> w : (Ljava/lang/IllegalArgumentException;JJ)Ljava/lang/IllegalArgumentException;
/*     */     //   116: athrow
/*     */     //   117: return
/*     */     // Line number table:
/*     */     //   Java source line number -> byte code offset
/*     */     //   #80	-> 8
/*     */     //   #43	-> 117
/*     */     // Exception table:
/*     */     //   from	to	target	type
/*     */     //   8	107	107	java/lang/IllegalArgumentException }
/*     */   public static void a(byte[][] paramArrayOfbyte, long paramLong1, long paramLong2) { // Byte code:
/*     */     //   0: lload_3
/*     */     //   1: lload_1
/*     */     //   2: lsub
/*     */     //   3: lstore #5
/*     */     //   5: lload #5
/*     */     //   7: ldc2_w 7
/*     */     //   10: lcmp
/*     */     //   11: ifge -> 25
/*     */     //   14: aload_0
/*     */     //   15: lload_1
/*     */     //   16: lload_3
/*     */     //   17: invokestatic d : ([[BJJ)V
/*     */     //   20: return
/*     */     //   21: invokestatic a : (Ljava/lang/IllegalArgumentException;)Ljava/lang/IllegalArgumentException;
/*     */     //   24: athrow
/*     */     //   25: lload_1
/*     */     //   26: lload #5
/*     */     //   28: ldc2_w 2
/*     */     //   31: ldiv
/*     */     //   32: ladd
/*     */     //   33: lstore #7
/*     */     //   35: lload #5
/*     */     //   37: ldc2_w 7
/*     */     //   40: lcmp
/*     */     //   41: ifle -> 143
/*     */     //   44: lload_1
/*     */     //   45: lstore #9
/*     */     //   47: lload_3
/*     */     //   48: lconst_1
/*     */     //   49: lsub
/*     */     //   50: lstore #11
/*     */     //   52: lload #5
/*     */     //   54: ldc2_w 40
/*     */     //   57: lcmp
/*     */     //   58: ifle -> 131
/*     */     //   61: lload #5
/*     */     //   63: ldc2_w 8
/*     */     //   66: ldiv
/*     */     //   67: lstore #13
/*     */     //   69: aload_0
/*     */     //   70: lload #9
/*     */     //   72: lload #9
/*     */     //   74: lload #13
/*     */     //   76: ladd
/*     */     //   77: lload #9
/*     */     //   79: ldc2_w 2
/*     */     //   82: lload #13
/*     */     //   84: lmul
/*     */     //   85: ladd
/*     */     //   86: invokestatic b : ([[BJJJ)J
/*     */     //   89: lstore #9
/*     */     //   91: aload_0
/*     */     //   92: lload #7
/*     */     //   94: lload #13
/*     */     //   96: lsub
/*     */     //   97: lload #7
/*     */     //   99: lload #7
/*     */     //   101: lload #13
/*     */     //   103: ladd
/*     */     //   104: invokestatic b : ([[BJJJ)J
/*     */     //   107: lstore #7
/*     */     //   109: aload_0
/*     */     //   110: lload #11
/*     */     //   112: ldc2_w 2
/*     */     //   115: lload #13
/*     */     //   117: lmul
/*     */     //   118: lsub
/*     */     //   119: lload #11
/*     */     //   121: lload #13
/*     */     //   123: lsub
/*     */     //   124: lload #11
/*     */     //   126: invokestatic b : ([[BJJJ)J
/*     */     //   129: lstore #11
/*     */     //   131: aload_0
/*     */     //   132: lload #9
/*     */     //   134: lload #7
/*     */     //   136: lload #11
/*     */     //   138: invokestatic b : ([[BJJJ)J
/*     */     //   141: lstore #7
/*     */     //   143: aload_0
/*     */     //   144: lload #7
/*     */     //   146: invokestatic a : ([[BJ)B
/*     */     //   149: istore #9
/*     */     //   151: lload_1
/*     */     //   152: lstore #10
/*     */     //   154: lload #10
/*     */     //   156: lstore #12
/*     */     //   158: lload_3
/*     */     //   159: lconst_1
/*     */     //   160: lsub
/*     */     //   161: lstore #14
/*     */     //   163: lload #14
/*     */     //   165: lstore #16
/*     */     //   167: lload #12
/*     */     //   169: lload #14
/*     */     //   171: lcmp
/*     */     //   172: ifgt -> 226
/*     */     //   175: aload_0
/*     */     //   176: lload #12
/*     */     //   178: invokestatic a : ([[BJ)B
/*     */     //   181: iload #9
/*     */     //   183: invokestatic compare : (BB)I
/*     */     //   186: dup
/*     */     //   187: istore #18
/*     */     //   189: ifgt -> 226
/*     */     //   192: iload #18
/*     */     //   194: ifne -> 217
/*     */     //   197: goto -> 204
/*     */     //   200: invokestatic a : (Ljava/lang/IllegalArgumentException;)Ljava/lang/IllegalArgumentException;
/*     */     //   203: athrow
/*     */     //   204: aload_0
/*     */     //   205: lload #10
/*     */     //   207: dup2
/*     */     //   208: lconst_1
/*     */     //   209: ladd
/*     */     //   210: lstore #10
/*     */     //   212: lload #12
/*     */     //   214: invokestatic b : ([[BJJ)V
/*     */     //   217: lload #12
/*     */     //   219: lconst_1
/*     */     //   220: ladd
/*     */     //   221: lstore #12
/*     */     //   223: goto -> 167
/*     */     //   226: lload #14
/*     */     //   228: lload #12
/*     */     //   230: lcmp
/*     */     //   231: iflt -> 285
/*     */     //   234: aload_0
/*     */     //   235: lload #14
/*     */     //   237: invokestatic a : ([[BJ)B
/*     */     //   240: iload #9
/*     */     //   242: invokestatic compare : (BB)I
/*     */     //   245: dup
/*     */     //   246: istore #18
/*     */     //   248: iflt -> 285
/*     */     //   251: iload #18
/*     */     //   253: ifne -> 276
/*     */     //   256: goto -> 263
/*     */     //   259: invokestatic a : (Ljava/lang/IllegalArgumentException;)Ljava/lang/IllegalArgumentException;
/*     */     //   262: athrow
/*     */     //   263: aload_0
/*     */     //   264: lload #14
/*     */     //   266: lload #16
/*     */     //   268: dup2
/*     */     //   269: lconst_1
/*     */     //   270: lsub
/*     */     //   271: lstore #16
/*     */     //   273: invokestatic b : ([[BJJ)V
/*     */     //   276: lload #14
/*     */     //   278: lconst_1
/*     */     //   279: lsub
/*     */     //   280: lstore #14
/*     */     //   282: goto -> 226
/*     */     //   285: lload #12
/*     */     //   287: lload #14
/*     */     //   289: lcmp
/*     */     //   290: ifle -> 300
/*     */     //   293: goto -> 321
/*     */     //   296: invokestatic a : (Ljava/lang/IllegalArgumentException;)Ljava/lang/IllegalArgumentException;
/*     */     //   299: athrow
/*     */     //   300: aload_0
/*     */     //   301: lload #12
/*     */     //   303: dup2
/*     */     //   304: lconst_1
/*     */     //   305: ladd
/*     */     //   306: lstore #12
/*     */     //   308: lload #14
/*     */     //   310: dup2
/*     */     //   311: lconst_1
/*     */     //   312: lsub
/*     */     //   313: lstore #14
/*     */     //   315: invokestatic b : ([[BJJ)V
/*     */     //   318: goto -> 167
/*     */     //   321: lload_3
/*     */     //   322: lstore #20
/*     */     //   324: lload #10
/*     */     //   326: lload_1
/*     */     //   327: lsub
/*     */     //   328: lload #12
/*     */     //   330: lload #10
/*     */     //   332: lsub
/*     */     //   333: invokestatic min : (JJ)J
/*     */     //   336: lstore #18
/*     */     //   338: aload_0
/*     */     //   339: lload_1
/*     */     //   340: lload #12
/*     */     //   342: lload #18
/*     */     //   344: lsub
/*     */     //   345: lload #18
/*     */     //   347: invokestatic a : ([[BJJJ)V
/*     */     //   350: lload #16
/*     */     //   352: lload #14
/*     */     //   354: lsub
/*     */     //   355: lload #20
/*     */     //   357: lload #16
/*     */     //   359: lsub
/*     */     //   360: lconst_1
/*     */     //   361: lsub
/*     */     //   362: invokestatic min : (JJ)J
/*     */     //   365: lstore #18
/*     */     //   367: aload_0
/*     */     //   368: lload #12
/*     */     //   370: lload #20
/*     */     //   372: lload #18
/*     */     //   374: lsub
/*     */     //   375: lload #18
/*     */     //   377: invokestatic a : ([[BJJJ)V
/*     */     //   380: lload #12
/*     */     //   382: lload #10
/*     */     //   384: lsub
/*     */     //   385: dup2
/*     */     //   386: lstore #18
/*     */     //   388: lconst_1
/*     */     //   389: lcmp
/*     */     //   390: ifle -> 409
/*     */     //   393: aload_0
/*     */     //   394: lload_1
/*     */     //   395: lload_1
/*     */     //   396: lload #18
/*     */     //   398: ladd
/*     */     //   399: invokestatic a : ([[BJJ)V
/*     */     //   402: goto -> 409
/*     */     //   405: invokestatic a : (Ljava/lang/IllegalArgumentException;)Ljava/lang/IllegalArgumentException;
/*     */     //   408: athrow
/*     */     //   409: lload #16
/*     */     //   411: lload #14
/*     */     //   413: lsub
/*     */     //   414: dup2
/*     */     //   415: lstore #18
/*     */     //   417: lconst_1
/*     */     //   418: lcmp
/*     */     //   419: ifle -> 440
/*     */     //   422: aload_0
/*     */     //   423: lload #20
/*     */     //   425: lload #18
/*     */     //   427: lsub
/*     */     //   428: lload #20
/*     */     //   430: invokestatic a : ([[BJJ)V
/*     */     //   433: goto -> 440
/*     */     //   436: invokestatic a : (Ljava/lang/IllegalArgumentException;)Ljava/lang/IllegalArgumentException;
/*     */     //   439: athrow
/*     */     //   440: return
/*     */     // Line number table:
/*     */     //   Java source line number -> byte code offset
/*     */     //   #84	-> 0
/*     */     //   #305	-> 5
/*     */     //   #68	-> 14
/*     */     //   #368	-> 20
/*     */     //   #81	-> 25
/*     */     //   #154	-> 35
/*     */     //   #325	-> 44
/*     */     //   #308	-> 47
/*     */     //   #312	-> 52
/*     */     //   #76	-> 61
/*     */     //   #365	-> 69
/*     */     //   #152	-> 91
/*     */     //   #109	-> 109
/*     */     //   #398	-> 131
/*     */     //   #173	-> 143
/*     */     //   #38	-> 151
/*     */     //   #343	-> 167
/*     */     //   #100	-> 192
/*     */     //   #124	-> 217
/*     */     //   #364	-> 226
/*     */     //   #16	-> 251
/*     */     //   #204	-> 276
/*     */     //   #274	-> 285
/*     */     //   #51	-> 300
/*     */     //   #148	-> 321
/*     */     //   #218	-> 324
/*     */     //   #332	-> 338
/*     */     //   #247	-> 350
/*     */     //   #389	-> 367
/*     */     //   #66	-> 380
/*     */     //   #394	-> 409
/*     */     //   #195	-> 440
/*     */     // Exception table:
/*     */     //   from	to	target	type
/*     */     //   5	21	21	java/lang/IllegalArgumentException
/*     */     //   189	197	200	java/lang/IllegalArgumentException
/*     */     //   248	256	259	java/lang/IllegalArgumentException
/*     */     //   285	296	296	java/lang/IllegalArgumentException
/*     */     //   388	402	405	java/lang/IllegalArgumentException
/*     */     //   417	433	436	java/lang/IllegalArgumentException }
/*     */   private static void a(byte[][] paramArrayOfbyte, long paramLong1, long paramLong2, long paramLong3) { for (byte b = 0; b < paramLong3; ) {
/*     */       k.b(paramArrayOfbyte, paramLong1, paramLong2);
/*     */       b++;
/*     */       paramLong1++;
/*     */       paramLong2++;
/*     */     }  }
/*     */   public static long a(byte[][] paramArrayOfbyte, long paramLong1, long paramLong2, byte paramByte) {
/*     */     paramLong2--;
/*     */     while (paramLong1 <= paramLong2) {
/*     */       long l = paramLong1 + paramLong2 >>> 1L;
/*     */       byte b = k.a(paramArrayOfbyte, l);
/*     */       if (b < paramByte) {
/*     */         paramLong1 = l + 1L;
/*     */         continue;
/*     */       } 
/*     */       if (b > paramByte) {
/*     */         paramLong2 = l - 1L;
/*     */         continue;
/*     */       } 
/*     */       return l;
/*     */     } 
/*     */     return -(paramLong1 + 1L);
/*     */   } public static void c(byte[][] paramArrayOfbyte) {
/*     */     b(paramArrayOfbyte, 0L, k.a(paramArrayOfbyte));
/*     */   } @Deprecated
/*     */   public static byte[][] c(byte[][] paramArrayOfbyte, long paramLong1, long paramLong2) {
/*     */     long l = a(paramArrayOfbyte);
/*     */     try {
/*     */     
/*     */     } catch (IllegalArgumentException illegalArgumentException) {
/*     */       throw a(null);
/*     */     } 
/*     */     return (paramLong1 > l) ? b(paramArrayOfbyte, Math.max(l + (l >> 1L), paramLong1), paramLong2) : paramArrayOfbyte;
/*     */   } public static long a(byte[][] paramArrayOfbyte, long paramLong1, long paramLong2, byte paramByte, g9 paramg9) { paramLong2--;
/* 413 */     for (; paramLong1 <= paramLong2; b = k.a(paramArrayOfbyte, l), i = paramg9.a(b, paramByte)) { byte b; int i; long l = paramLong1 + paramLong2 >>> 1L; }
/*     */      return -(paramLong1 + 1L); }
/* 415 */   @Deprecated public static void c(byte[][] paramArrayOfbyte, long paramLong, byte paramByte) { paramArrayOfbyte[k.b(paramLong)][k.a(paramLong)] = (byte)(paramArrayOfbyte[k.b(paramLong)][k.a(paramLong)] * paramByte); } private static void a(long[][] paramArrayOflong, byte[][] paramArrayOfbyte1, byte[][] paramArrayOfbyte2, long paramLong1, long paramLong2) { for (long l = paramLong1; ++l < paramLong2; l1 = l, l2 = k.a(paramArrayOflong, l1 - 1L)) { long l1 = k.a(paramArrayOflong, l); continue; }  } private static void d(byte[][] paramArrayOfbyte, long paramLong1, long paramLong2) { for (long l = paramLong1; l < paramLong2 - 1L; l2 = l + 1L) long l2, l1 = l;  } public static void a(byte[][] paramArrayOfbyte1, byte[][] paramArrayOfbyte2, long paramLong1, long paramLong2) { // Byte code:
/*     */     //   0: getstatic me/konsolas/aac/fd.l : J
/*     */     //   3: ldc2_w 65100693272353
/*     */     //   6: lxor
/*     */     //   7: lstore #6
/*     */     //   9: iconst_2
/*     */     //   10: istore #8
/*     */     //   12: aload_0
/*     */     //   13: invokestatic a : ([[B)J
/*     */     //   16: aload_1
/*     */     //   17: invokestatic a : ([[B)J
/*     */     //   20: lcmp
/*     */     //   21: ifeq -> 69
/*     */     //   24: new java/lang/IllegalArgumentException
/*     */     //   27: dup
/*     */     //   28: ldc_w '衮㹴⺧䐉㉗ㆤ쪙袶箳㝒晴Ɇ䪏ꍠ͢ㅫ麗秂'
/*     */     //   31: invokevirtual toCharArray : ()[C
/*     */     //   34: dup
/*     */     //   35: dup
/*     */     //   36: bipush #16
/*     */     //   38: dup_x1
/*     */     //   39: caload
/*     */     //   40: sipush #12505
/*     */     //   43: ixor
/*     */     //   44: i2c
/*     */     //   45: castore
/*     */     //   46: sipush #13233
/*     */     //   49: iconst_0
/*     */     //   50: iconst_0
/*     */     //   51: invokestatic X : (Ljava/lang/Object;SZZ)Ljava/lang/String;
/*     */     //   54: invokespecial <init> : (Ljava/lang/String;)V
/*     */     //   57: athrow
/*     */     //   58: ldc2_w 5820126677858849914
/*     */     //   61: lload #6
/*     */     //   63: <illegal opcode> w : (Ljava/lang/IllegalArgumentException;JJ)Ljava/lang/IllegalArgumentException;
/*     */     //   68: athrow
/*     */     //   69: iconst_1
/*     */     //   70: istore #9
/*     */     //   72: sipush #256
/*     */     //   75: istore #10
/*     */     //   77: sipush #256
/*     */     //   80: newarray long
/*     */     //   82: astore #11
/*     */     //   84: iconst_0
/*     */     //   85: istore #12
/*     */     //   87: sipush #256
/*     */     //   90: newarray long
/*     */     //   92: astore #13
/*     */     //   94: iconst_0
/*     */     //   95: istore #14
/*     */     //   97: sipush #256
/*     */     //   100: newarray int
/*     */     //   102: astore #15
/*     */     //   104: iconst_0
/*     */     //   105: istore #16
/*     */     //   107: aload #11
/*     */     //   109: iload #12
/*     */     //   111: iinc #12, 1
/*     */     //   114: lload_2
/*     */     //   115: lastore
/*     */     //   116: aload #13
/*     */     //   118: iload #14
/*     */     //   120: iinc #14, 1
/*     */     //   123: lload #4
/*     */     //   125: lload_2
/*     */     //   126: lsub
/*     */     //   127: lastore
/*     */     //   128: aload #15
/*     */     //   130: iload #16
/*     */     //   132: iinc #16, 1
/*     */     //   135: iconst_0
/*     */     //   136: iastore
/*     */     //   137: sipush #256
/*     */     //   140: newarray long
/*     */     //   142: astore #17
/*     */     //   144: sipush #256
/*     */     //   147: newarray long
/*     */     //   149: astore #18
/*     */     //   151: lload #4
/*     */     //   153: lload_2
/*     */     //   154: lsub
/*     */     //   155: invokestatic a : (J)[[B
/*     */     //   158: astore #19
/*     */     //   160: iload #12
/*     */     //   162: ifle -> 757
/*     */     //   165: aload #11
/*     */     //   167: iinc #12, -1
/*     */     //   170: iload #12
/*     */     //   172: laload
/*     */     //   173: lstore #20
/*     */     //   175: aload #13
/*     */     //   177: iinc #14, -1
/*     */     //   180: iload #14
/*     */     //   182: laload
/*     */     //   183: lstore #22
/*     */     //   185: aload #15
/*     */     //   187: iinc #16, -1
/*     */     //   190: iload #16
/*     */     //   192: iaload
/*     */     //   193: istore #24
/*     */     //   195: iload #24
/*     */     //   197: iconst_1
/*     */     //   198: irem
/*     */     //   199: ifne -> 219
/*     */     //   202: sipush #128
/*     */     //   205: goto -> 220
/*     */     //   208: ldc2_w 5820126677858849914
/*     */     //   211: lload #6
/*     */     //   213: <illegal opcode> w : (Ljava/lang/IllegalArgumentException;JJ)Ljava/lang/IllegalArgumentException;
/*     */     //   218: athrow
/*     */     //   219: iconst_0
/*     */     //   220: istore #25
/*     */     //   222: lload #22
/*     */     //   224: ldc2_w 40
/*     */     //   227: lcmp
/*     */     //   228: ifge -> 257
/*     */     //   231: aload_0
/*     */     //   232: aload_1
/*     */     //   233: lload #20
/*     */     //   235: lload #20
/*     */     //   237: lload #22
/*     */     //   239: ladd
/*     */     //   240: invokestatic b : ([[B[[BJJ)V
/*     */     //   243: goto -> 160
/*     */     //   246: ldc2_w 5820126677858849914
/*     */     //   249: lload #6
/*     */     //   251: <illegal opcode> w : (Ljava/lang/IllegalArgumentException;JJ)Ljava/lang/IllegalArgumentException;
/*     */     //   256: athrow
/*     */     //   257: iload #24
/*     */     //   259: iconst_1
/*     */     //   260: if_icmpge -> 278
/*     */     //   263: aload_0
/*     */     //   264: goto -> 279
/*     */     //   267: ldc2_w 5820126677858849914
/*     */     //   270: lload #6
/*     */     //   272: <illegal opcode> w : (Ljava/lang/IllegalArgumentException;JJ)Ljava/lang/IllegalArgumentException;
/*     */     //   277: athrow
/*     */     //   278: aload_1
/*     */     //   279: astore #26
/*     */     //   281: iconst_0
/*     */     //   282: iload #24
/*     */     //   284: iconst_1
/*     */     //   285: irem
/*     */     //   286: isub
/*     */     //   287: bipush #8
/*     */     //   289: imul
/*     */     //   290: istore #27
/*     */     //   292: lload #22
/*     */     //   294: lstore #28
/*     */     //   296: lload #28
/*     */     //   298: dup2
/*     */     //   299: lconst_1
/*     */     //   300: lsub
/*     */     //   301: lstore #28
/*     */     //   303: lconst_0
/*     */     //   304: lcmp
/*     */     //   305: ifeq -> 350
/*     */     //   308: aload #19
/*     */     //   310: lload #28
/*     */     //   312: aload #26
/*     */     //   314: lload #20
/*     */     //   316: lload #28
/*     */     //   318: ladd
/*     */     //   319: invokestatic a : ([[BJ)B
/*     */     //   322: iload #27
/*     */     //   324: iushr
/*     */     //   325: sipush #255
/*     */     //   328: iand
/*     */     //   329: iload #25
/*     */     //   331: ixor
/*     */     //   332: i2b
/*     */     //   333: invokestatic b : ([[BJB)V
/*     */     //   336: goto -> 296
/*     */     //   339: ldc2_w 5820126677858849914
/*     */     //   342: lload #6
/*     */     //   344: <illegal opcode> w : (Ljava/lang/IllegalArgumentException;JJ)Ljava/lang/IllegalArgumentException;
/*     */     //   349: athrow
/*     */     //   350: lload #22
/*     */     //   352: lstore #28
/*     */     //   354: lload #28
/*     */     //   356: dup2
/*     */     //   357: lconst_1
/*     */     //   358: lsub
/*     */     //   359: lstore #28
/*     */     //   361: lconst_0
/*     */     //   362: lcmp
/*     */     //   363: ifeq -> 398
/*     */     //   366: aload #17
/*     */     //   368: aload #19
/*     */     //   370: lload #28
/*     */     //   372: invokestatic a : ([[BJ)B
/*     */     //   375: sipush #255
/*     */     //   378: iand
/*     */     //   379: dup2
/*     */     //   380: laload
/*     */     //   381: lconst_1
/*     */     //   382: ladd
/*     */     //   383: lastore
/*     */     //   384: goto -> 354
/*     */     //   387: ldc2_w 5820126677858849914
/*     */     //   390: lload #6
/*     */     //   392: <illegal opcode> w : (Ljava/lang/IllegalArgumentException;JJ)Ljava/lang/IllegalArgumentException;
/*     */     //   397: athrow
/*     */     //   398: iconst_m1
/*     */     //   399: istore #28
/*     */     //   401: lconst_0
/*     */     //   402: lstore #29
/*     */     //   404: iconst_0
/*     */     //   405: istore #31
/*     */     //   407: iload #31
/*     */     //   409: sipush #256
/*     */     //   412: if_icmpge -> 547
/*     */     //   415: aload #17
/*     */     //   417: iload #31
/*     */     //   419: laload
/*     */     //   420: lconst_0
/*     */     //   421: lcmp
/*     */     //   422: ifeq -> 525
/*     */     //   425: goto -> 439
/*     */     //   428: ldc2_w 5820126677858849914
/*     */     //   431: lload #6
/*     */     //   433: <illegal opcode> w : (Ljava/lang/IllegalArgumentException;JJ)Ljava/lang/IllegalArgumentException;
/*     */     //   438: athrow
/*     */     //   439: iload #31
/*     */     //   441: istore #28
/*     */     //   443: iload #24
/*     */     //   445: iconst_1
/*     */     //   446: if_icmpge -> 525
/*     */     //   449: aload #17
/*     */     //   451: iload #31
/*     */     //   453: laload
/*     */     //   454: lconst_1
/*     */     //   455: lcmp
/*     */     //   456: ifle -> 525
/*     */     //   459: goto -> 473
/*     */     //   462: ldc2_w 5820126677858849914
/*     */     //   465: lload #6
/*     */     //   467: <illegal opcode> w : (Ljava/lang/IllegalArgumentException;JJ)Ljava/lang/IllegalArgumentException;
/*     */     //   472: athrow
/*     */     //   473: aload #11
/*     */     //   475: iload #12
/*     */     //   477: iinc #12, 1
/*     */     //   480: lload #29
/*     */     //   482: lload #20
/*     */     //   484: ladd
/*     */     //   485: lastore
/*     */     //   486: aload #13
/*     */     //   488: iload #14
/*     */     //   490: iinc #14, 1
/*     */     //   493: aload #17
/*     */     //   495: iload #31
/*     */     //   497: laload
/*     */     //   498: lastore
/*     */     //   499: aload #15
/*     */     //   501: iload #16
/*     */     //   503: iinc #16, 1
/*     */     //   506: iload #24
/*     */     //   508: iconst_1
/*     */     //   509: iadd
/*     */     //   510: iastore
/*     */     //   511: goto -> 525
/*     */     //   514: ldc2_w 5820126677858849914
/*     */     //   517: lload #6
/*     */     //   519: <illegal opcode> w : (Ljava/lang/IllegalArgumentException;JJ)Ljava/lang/IllegalArgumentException;
/*     */     //   524: athrow
/*     */     //   525: aload #18
/*     */     //   527: iload #31
/*     */     //   529: lload #29
/*     */     //   531: aload #17
/*     */     //   533: iload #31
/*     */     //   535: laload
/*     */     //   536: ladd
/*     */     //   537: dup2
/*     */     //   538: lstore #29
/*     */     //   540: lastore
/*     */     //   541: iinc #31, 1
/*     */     //   544: goto -> 407
/*     */     //   547: lload #22
/*     */     //   549: aload #17
/*     */     //   551: iload #28
/*     */     //   553: laload
/*     */     //   554: lsub
/*     */     //   555: lstore #31
/*     */     //   557: aload #17
/*     */     //   559: iload #28
/*     */     //   561: lconst_0
/*     */     //   562: lastore
/*     */     //   563: iconst_m1
/*     */     //   564: istore #33
/*     */     //   566: lconst_0
/*     */     //   567: lstore #34
/*     */     //   569: lload #34
/*     */     //   571: lload #31
/*     */     //   573: lcmp
/*     */     //   574: ifge -> 754
/*     */     //   577: aload_0
/*     */     //   578: lload #34
/*     */     //   580: lload #20
/*     */     //   582: ladd
/*     */     //   583: invokestatic a : ([[BJ)B
/*     */     //   586: istore #38
/*     */     //   588: aload_1
/*     */     //   589: lload #34
/*     */     //   591: lload #20
/*     */     //   593: ladd
/*     */     //   594: invokestatic a : ([[BJ)B
/*     */     //   597: istore #39
/*     */     //   599: aload #19
/*     */     //   601: lload #34
/*     */     //   603: invokestatic a : ([[BJ)B
/*     */     //   606: sipush #255
/*     */     //   609: iand
/*     */     //   610: istore #33
/*     */     //   612: aload #18
/*     */     //   614: iload #33
/*     */     //   616: dup2
/*     */     //   617: laload
/*     */     //   618: lconst_1
/*     */     //   619: lsub
/*     */     //   620: dup2_x2
/*     */     //   621: lastore
/*     */     //   622: dup2
/*     */     //   623: lstore #36
/*     */     //   625: lload #34
/*     */     //   627: lcmp
/*     */     //   628: ifle -> 713
/*     */     //   631: iload #38
/*     */     //   633: istore #40
/*     */     //   635: iload #33
/*     */     //   637: istore #41
/*     */     //   639: aload_0
/*     */     //   640: lload #36
/*     */     //   642: lload #20
/*     */     //   644: ladd
/*     */     //   645: invokestatic a : ([[BJ)B
/*     */     //   648: istore #38
/*     */     //   650: aload_0
/*     */     //   651: lload #36
/*     */     //   653: lload #20
/*     */     //   655: ladd
/*     */     //   656: iload #40
/*     */     //   658: invokestatic b : ([[BJB)V
/*     */     //   661: iload #39
/*     */     //   663: istore #40
/*     */     //   665: aload_1
/*     */     //   666: lload #36
/*     */     //   668: lload #20
/*     */     //   670: ladd
/*     */     //   671: invokestatic a : ([[BJ)B
/*     */     //   674: istore #39
/*     */     //   676: aload_1
/*     */     //   677: lload #36
/*     */     //   679: lload #20
/*     */     //   681: ladd
/*     */     //   682: iload #40
/*     */     //   684: invokestatic b : ([[BJB)V
/*     */     //   687: aload #19
/*     */     //   689: lload #36
/*     */     //   691: invokestatic a : ([[BJ)B
/*     */     //   694: sipush #255
/*     */     //   697: iand
/*     */     //   698: istore #33
/*     */     //   700: aload #19
/*     */     //   702: lload #36
/*     */     //   704: iload #41
/*     */     //   706: i2b
/*     */     //   707: invokestatic b : ([[BJB)V
/*     */     //   710: goto -> 612
/*     */     //   713: aload_0
/*     */     //   714: lload #34
/*     */     //   716: lload #20
/*     */     //   718: ladd
/*     */     //   719: iload #38
/*     */     //   721: invokestatic b : ([[BJB)V
/*     */     //   724: aload_1
/*     */     //   725: lload #34
/*     */     //   727: lload #20
/*     */     //   729: ladd
/*     */     //   730: iload #39
/*     */     //   732: invokestatic b : ([[BJB)V
/*     */     //   735: lload #34
/*     */     //   737: aload #17
/*     */     //   739: iload #33
/*     */     //   741: laload
/*     */     //   742: ladd
/*     */     //   743: lstore #34
/*     */     //   745: aload #17
/*     */     //   747: iload #33
/*     */     //   749: lconst_0
/*     */     //   750: lastore
/*     */     //   751: goto -> 569
/*     */     //   754: goto -> 160
/*     */     //   757: return
/*     */     // Line number table:
/*     */     //   Java source line number -> byte code offset
/*     */     //   #104	-> 9
/*     */     //   #18	-> 12
/*     */     //   #86	-> 69
/*     */     //   #87	-> 72
/*     */     //   #313	-> 77
/*     */     //   #229	-> 84
/*     */     //   #162	-> 87
/*     */     //   #333	-> 94
/*     */     //   #372	-> 97
/*     */     //   #397	-> 104
/*     */     //   #270	-> 107
/*     */     //   #101	-> 116
/*     */     //   #377	-> 128
/*     */     //   #259	-> 137
/*     */     //   #60	-> 144
/*     */     //   #258	-> 151
/*     */     //   #236	-> 160
/*     */     //   #361	-> 165
/*     */     //   #54	-> 175
/*     */     //   #360	-> 185
/*     */     //   #39	-> 195
/*     */     //   #208	-> 222
/*     */     //   #298	-> 231
/*     */     //   #359	-> 243
/*     */     //   #164	-> 257
/*     */     //   #251	-> 281
/*     */     //   #243	-> 292
/*     */     //   #167	-> 350
/*     */     //   #250	-> 398
/*     */     //   #69	-> 401
/*     */     //   #150	-> 404
/*     */     //   #370	-> 415
/*     */     //   #363	-> 439
/*     */     //   #29	-> 443
/*     */     //   #240	-> 473
/*     */     //   #374	-> 486
/*     */     //   #338	-> 499
/*     */     //   #179	-> 525
/*     */     //   #379	-> 541
/*     */     //   #304	-> 547
/*     */     //   #131	-> 557
/*     */     //   #220	-> 563
/*     */     //   #289	-> 566
/*     */     //   #318	-> 577
/*     */     //   #147	-> 588
/*     */     //   #35	-> 599
/*     */     //   #36	-> 612
/*     */     //   #287	-> 631
/*     */     //   #317	-> 635
/*     */     //   #199	-> 639
/*     */     //   #260	-> 650
/*     */     //   #326	-> 661
/*     */     //   #151	-> 665
/*     */     //   #373	-> 676
/*     */     //   #242	-> 687
/*     */     //   #383	-> 700
/*     */     //   #188	-> 710
/*     */     //   #336	-> 713
/*     */     //   #205	-> 724
/*     */     //   #120	-> 735
/*     */     //   #214	-> 754
/*     */     //   #232	-> 757
/*     */     // Exception table:
/*     */     //   from	to	target	type
/*     */     //   12	58	58	java/lang/IllegalArgumentException
/*     */     //   195	208	208	java/lang/IllegalArgumentException
/*     */     //   222	246	246	java/lang/IllegalArgumentException
/*     */     //   257	267	267	java/lang/IllegalArgumentException
/*     */     //   303	339	339	java/lang/IllegalArgumentException
/*     */     //   361	387	387	java/lang/IllegalArgumentException
/*     */     //   407	425	428	java/lang/IllegalArgumentException
/*     */     //   443	459	462	java/lang/IllegalArgumentException
/*     */     //   449	511	514	java/lang/IllegalArgumentException } public static long a(byte[][] paramArrayOfbyte, byte paramByte) { return a(paramArrayOfbyte, 0L, k.a(paramArrayOfbyte), paramByte); } @Deprecated public static void a(byte[][] paramArrayOfbyte, long paramLong1, long paramLong2, byte paramByte) { k.a(paramArrayOfbyte, paramLong1, paramLong2, paramByte); }
/* 416 */   @Deprecated public static byte a(byte[][] paramArrayOfbyte, long paramLong) { return paramArrayOfbyte[k.b(paramLong)][k.a(paramLong)]; }
/*     */ 
/*     */   
/*     */   @Deprecated
/*     */   public static void a(byte[][] paramArrayOfbyte1, long paramLong1, byte[][] paramArrayOfbyte2, long paramLong2, long paramLong3) {
/*     */     k.a(paramArrayOfbyte1, paramLong1, paramArrayOfbyte2, paramLong2, paramLong3);
/*     */   }
/*     */   
/*     */   public static void b(byte[][] paramArrayOfbyte, g9 paramg9) {
/*     */     b(paramArrayOfbyte, 0L, k.a(paramArrayOfbyte), paramg9);
/*     */   }
/*     */   
/*     */   @Deprecated
/*     */   public static byte[][] a(byte[][] paramArrayOfbyte, long paramLong1, long paramLong2) {
/*     */     return k.b(paramArrayOfbyte, paramLong1, paramLong2);
/*     */   }
/*     */   
/*     */   public static void a(byte[][] paramArrayOfbyte1, byte[][] paramArrayOfbyte2) {
/*     */     a(paramArrayOfbyte1, paramArrayOfbyte2, 0L, k.a(paramArrayOfbyte1));
/*     */   }
/*     */   
/*     */   public static void a(long[][] paramArrayOflong, byte[][] paramArrayOfbyte1, byte[][] paramArrayOfbyte2, boolean paramBoolean) {
/*     */     b(paramArrayOfbyte1, paramArrayOfbyte2);
/*     */     a(paramArrayOflong, paramArrayOfbyte1, paramArrayOfbyte2, 0L, k.a(paramArrayOfbyte1), paramBoolean);
/*     */   }
/*     */   
/*     */   public static void c(byte[][] paramArrayOfbyte, long paramLong1, long paramLong2, g9 paramg9) {
/*     */     ForkJoinPool forkJoinPool = a();
/*     */     try {
/*     */       if (paramLong2 - paramLong1 >= 8192L) {
/*     */         try {
/*     */           if (forkJoinPool.getParallelism() == 1) {
/*     */             b(paramArrayOfbyte, paramLong1, paramLong2, paramg9);
/*     */             return;
/*     */           } 
/*     */         } catch (IllegalArgumentException illegalArgumentException) {
/*     */           throw a(null);
/*     */         } 
/*     */         forkJoinPool.invoke(new iP(paramArrayOfbyte, paramLong1, paramLong2, paramg9));
/*     */         return;
/*     */       } 
/*     */     } catch (IllegalArgumentException illegalArgumentException) {
/*     */       throw a(null);
/*     */     } 
/*     */     b(paramArrayOfbyte, paramLong1, paramLong2, paramg9);
/*     */   }
/*     */   
/*     */   public static void a(long[][] paramArrayOflong, byte[][] paramArrayOfbyte1, byte[][] paramArrayOfbyte2, long paramLong1, long paramLong2, boolean paramBoolean) {
/*     */     // Byte code:
/*     */     //   0: lload #5
/*     */     //   2: lload_3
/*     */     //   3: lsub
/*     */     //   4: ldc2_w 1024
/*     */     //   7: lcmp
/*     */     //   8: ifge -> 25
/*     */     //   11: aload_0
/*     */     //   12: aload_1
/*     */     //   13: aload_2
/*     */     //   14: lload_3
/*     */     //   15: lload #5
/*     */     //   17: invokestatic a : ([[J[[B[[BJJ)V
/*     */     //   20: return
/*     */     //   21: invokestatic a : (Ljava/lang/IllegalArgumentException;)Ljava/lang/IllegalArgumentException;
/*     */     //   24: athrow
/*     */     //   25: iconst_2
/*     */     //   26: istore #8
/*     */     //   28: iconst_1
/*     */     //   29: istore #9
/*     */     //   31: sipush #256
/*     */     //   34: istore #10
/*     */     //   36: iconst_0
/*     */     //   37: istore #11
/*     */     //   39: sipush #256
/*     */     //   42: newarray long
/*     */     //   44: astore #12
/*     */     //   46: sipush #256
/*     */     //   49: newarray long
/*     */     //   51: astore #13
/*     */     //   53: sipush #256
/*     */     //   56: newarray int
/*     */     //   58: astore #14
/*     */     //   60: aload #12
/*     */     //   62: iload #11
/*     */     //   64: lload_3
/*     */     //   65: lastore
/*     */     //   66: aload #13
/*     */     //   68: iload #11
/*     */     //   70: lload #5
/*     */     //   72: lload_3
/*     */     //   73: lsub
/*     */     //   74: lastore
/*     */     //   75: aload #14
/*     */     //   77: iload #11
/*     */     //   79: iinc #11, 1
/*     */     //   82: iconst_0
/*     */     //   83: iastore
/*     */     //   84: sipush #256
/*     */     //   87: newarray long
/*     */     //   89: astore #15
/*     */     //   91: sipush #256
/*     */     //   94: newarray long
/*     */     //   96: astore #16
/*     */     //   98: iload #7
/*     */     //   100: ifeq -> 117
/*     */     //   103: aload_0
/*     */     //   104: invokestatic a : ([[J)J
/*     */     //   107: invokestatic a : (J)[[J
/*     */     //   110: goto -> 118
/*     */     //   113: invokestatic a : (Ljava/lang/IllegalArgumentException;)Ljava/lang/IllegalArgumentException;
/*     */     //   116: athrow
/*     */     //   117: aconst_null
/*     */     //   118: astore #17
/*     */     //   120: iload #11
/*     */     //   122: ifle -> 798
/*     */     //   125: aload #12
/*     */     //   127: iinc #11, -1
/*     */     //   130: iload #11
/*     */     //   132: laload
/*     */     //   133: lstore #18
/*     */     //   135: aload #13
/*     */     //   137: iload #11
/*     */     //   139: laload
/*     */     //   140: lstore #20
/*     */     //   142: aload #14
/*     */     //   144: iload #11
/*     */     //   146: iaload
/*     */     //   147: istore #22
/*     */     //   149: iload #22
/*     */     //   151: iconst_1
/*     */     //   152: irem
/*     */     //   153: ifne -> 166
/*     */     //   156: sipush #128
/*     */     //   159: goto -> 167
/*     */     //   162: invokestatic a : (Ljava/lang/IllegalArgumentException;)Ljava/lang/IllegalArgumentException;
/*     */     //   165: athrow
/*     */     //   166: iconst_0
/*     */     //   167: istore #23
/*     */     //   169: iload #22
/*     */     //   171: iconst_1
/*     */     //   172: if_icmpge -> 183
/*     */     //   175: aload_1
/*     */     //   176: goto -> 184
/*     */     //   179: invokestatic a : (Ljava/lang/IllegalArgumentException;)Ljava/lang/IllegalArgumentException;
/*     */     //   182: athrow
/*     */     //   183: aload_2
/*     */     //   184: astore #24
/*     */     //   186: iconst_0
/*     */     //   187: iload #22
/*     */     //   189: iconst_1
/*     */     //   190: irem
/*     */     //   191: isub
/*     */     //   192: bipush #8
/*     */     //   194: imul
/*     */     //   195: istore #25
/*     */     //   197: lload #18
/*     */     //   199: lload #20
/*     */     //   201: ladd
/*     */     //   202: lstore #26
/*     */     //   204: lload #26
/*     */     //   206: dup2
/*     */     //   207: lconst_1
/*     */     //   208: lsub
/*     */     //   209: lstore #26
/*     */     //   211: lload #18
/*     */     //   213: lcmp
/*     */     //   214: ifeq -> 252
/*     */     //   217: aload #15
/*     */     //   219: aload #24
/*     */     //   221: aload_0
/*     */     //   222: lload #26
/*     */     //   224: invokestatic a : ([[JJ)J
/*     */     //   227: invokestatic a : ([[BJ)B
/*     */     //   230: iload #25
/*     */     //   232: iushr
/*     */     //   233: sipush #255
/*     */     //   236: iand
/*     */     //   237: iload #23
/*     */     //   239: ixor
/*     */     //   240: dup2
/*     */     //   241: laload
/*     */     //   242: lconst_1
/*     */     //   243: ladd
/*     */     //   244: lastore
/*     */     //   245: goto -> 204
/*     */     //   248: invokestatic a : (Ljava/lang/IllegalArgumentException;)Ljava/lang/IllegalArgumentException;
/*     */     //   251: athrow
/*     */     //   252: iconst_m1
/*     */     //   253: istore #26
/*     */     //   255: iload #7
/*     */     //   257: ifeq -> 268
/*     */     //   260: lconst_0
/*     */     //   261: goto -> 270
/*     */     //   264: invokestatic a : (Ljava/lang/IllegalArgumentException;)Ljava/lang/IllegalArgumentException;
/*     */     //   267: athrow
/*     */     //   268: lload #18
/*     */     //   270: lstore #27
/*     */     //   272: iconst_0
/*     */     //   273: istore #29
/*     */     //   275: iload #29
/*     */     //   277: sipush #256
/*     */     //   280: if_icmpge -> 326
/*     */     //   283: aload #15
/*     */     //   285: iload #29
/*     */     //   287: laload
/*     */     //   288: lconst_0
/*     */     //   289: lcmp
/*     */     //   290: ifeq -> 304
/*     */     //   293: goto -> 300
/*     */     //   296: invokestatic a : (Ljava/lang/IllegalArgumentException;)Ljava/lang/IllegalArgumentException;
/*     */     //   299: athrow
/*     */     //   300: iload #29
/*     */     //   302: istore #26
/*     */     //   304: aload #16
/*     */     //   306: iload #29
/*     */     //   308: lload #27
/*     */     //   310: aload #15
/*     */     //   312: iload #29
/*     */     //   314: laload
/*     */     //   315: ladd
/*     */     //   316: dup2
/*     */     //   317: lstore #27
/*     */     //   319: lastore
/*     */     //   320: iinc #29, 1
/*     */     //   323: goto -> 275
/*     */     //   326: iload #7
/*     */     //   328: ifeq -> 550
/*     */     //   331: lload #18
/*     */     //   333: lload #20
/*     */     //   335: ladd
/*     */     //   336: lstore #29
/*     */     //   338: lload #29
/*     */     //   340: dup2
/*     */     //   341: lconst_1
/*     */     //   342: lsub
/*     */     //   343: lstore #29
/*     */     //   345: lload #18
/*     */     //   347: lcmp
/*     */     //   348: ifeq -> 398
/*     */     //   351: aload #17
/*     */     //   353: aload #16
/*     */     //   355: aload #24
/*     */     //   357: aload_0
/*     */     //   358: lload #29
/*     */     //   360: invokestatic a : ([[JJ)J
/*     */     //   363: invokestatic a : ([[BJ)B
/*     */     //   366: iload #25
/*     */     //   368: iushr
/*     */     //   369: sipush #255
/*     */     //   372: iand
/*     */     //   373: iload #23
/*     */     //   375: ixor
/*     */     //   376: dup2
/*     */     //   377: laload
/*     */     //   378: lconst_1
/*     */     //   379: lsub
/*     */     //   380: dup2_x2
/*     */     //   381: lastore
/*     */     //   382: aload_0
/*     */     //   383: lload #29
/*     */     //   385: invokestatic a : ([[JJ)J
/*     */     //   388: invokestatic d : ([[JJJ)V
/*     */     //   391: goto -> 338
/*     */     //   394: invokestatic a : (Ljava/lang/IllegalArgumentException;)Ljava/lang/IllegalArgumentException;
/*     */     //   397: athrow
/*     */     //   398: aload #17
/*     */     //   400: lconst_0
/*     */     //   401: aload_0
/*     */     //   402: lload #18
/*     */     //   404: lload #20
/*     */     //   406: invokestatic a : ([[JJ[[JJJ)V
/*     */     //   409: lload #18
/*     */     //   411: lstore #27
/*     */     //   413: iconst_0
/*     */     //   414: istore #29
/*     */     //   416: iload #29
/*     */     //   418: sipush #256
/*     */     //   421: if_icmpge -> 541
/*     */     //   424: iload #22
/*     */     //   426: iconst_1
/*     */     //   427: if_icmpge -> 525
/*     */     //   430: goto -> 437
/*     */     //   433: invokestatic a : (Ljava/lang/IllegalArgumentException;)Ljava/lang/IllegalArgumentException;
/*     */     //   436: athrow
/*     */     //   437: aload #15
/*     */     //   439: iload #29
/*     */     //   441: laload
/*     */     //   442: lconst_1
/*     */     //   443: lcmp
/*     */     //   444: ifle -> 525
/*     */     //   447: goto -> 454
/*     */     //   450: invokestatic a : (Ljava/lang/IllegalArgumentException;)Ljava/lang/IllegalArgumentException;
/*     */     //   453: athrow
/*     */     //   454: aload #15
/*     */     //   456: iload #29
/*     */     //   458: laload
/*     */     //   459: ldc2_w 1024
/*     */     //   462: lcmp
/*     */     //   463: ifge -> 496
/*     */     //   466: goto -> 473
/*     */     //   469: invokestatic a : (Ljava/lang/IllegalArgumentException;)Ljava/lang/IllegalArgumentException;
/*     */     //   472: athrow
/*     */     //   473: aload_0
/*     */     //   474: aload_1
/*     */     //   475: aload_2
/*     */     //   476: lload #27
/*     */     //   478: lload #27
/*     */     //   480: aload #15
/*     */     //   482: iload #29
/*     */     //   484: laload
/*     */     //   485: ladd
/*     */     //   486: invokestatic a : ([[J[[B[[BJJ)V
/*     */     //   489: goto -> 525
/*     */     //   492: invokestatic a : (Ljava/lang/IllegalArgumentException;)Ljava/lang/IllegalArgumentException;
/*     */     //   495: athrow
/*     */     //   496: aload #12
/*     */     //   498: iload #11
/*     */     //   500: lload #27
/*     */     //   502: lastore
/*     */     //   503: aload #13
/*     */     //   505: iload #11
/*     */     //   507: aload #15
/*     */     //   509: iload #29
/*     */     //   511: laload
/*     */     //   512: lastore
/*     */     //   513: aload #14
/*     */     //   515: iload #11
/*     */     //   517: iinc #11, 1
/*     */     //   520: iload #22
/*     */     //   522: iconst_1
/*     */     //   523: iadd
/*     */     //   524: iastore
/*     */     //   525: lload #27
/*     */     //   527: aload #15
/*     */     //   529: iload #29
/*     */     //   531: laload
/*     */     //   532: ladd
/*     */     //   533: lstore #27
/*     */     //   535: iinc #29, 1
/*     */     //   538: goto -> 416
/*     */     //   541: aload #15
/*     */     //   543: lconst_0
/*     */     //   544: invokestatic fill : ([JJ)V
/*     */     //   547: goto -> 795
/*     */     //   550: lload #18
/*     */     //   552: lload #20
/*     */     //   554: ladd
/*     */     //   555: aload #15
/*     */     //   557: iload #26
/*     */     //   559: laload
/*     */     //   560: lsub
/*     */     //   561: lstore #29
/*     */     //   563: iconst_m1
/*     */     //   564: istore #31
/*     */     //   566: lload #18
/*     */     //   568: lstore #32
/*     */     //   570: lload #32
/*     */     //   572: lload #29
/*     */     //   574: lcmp
/*     */     //   575: ifgt -> 795
/*     */     //   578: aload_0
/*     */     //   579: lload #32
/*     */     //   581: invokestatic a : ([[JJ)J
/*     */     //   584: lstore #36
/*     */     //   586: aload #24
/*     */     //   588: lload #36
/*     */     //   590: invokestatic a : ([[BJ)B
/*     */     //   593: iload #25
/*     */     //   595: iushr
/*     */     //   596: sipush #255
/*     */     //   599: iand
/*     */     //   600: iload #23
/*     */     //   602: ixor
/*     */     //   603: istore #31
/*     */     //   605: lload #32
/*     */     //   607: lload #29
/*     */     //   609: lcmp
/*     */     //   610: ifge -> 682
/*     */     //   613: aload #16
/*     */     //   615: iload #31
/*     */     //   617: dup2
/*     */     //   618: laload
/*     */     //   619: lconst_1
/*     */     //   620: lsub
/*     */     //   621: dup2_x2
/*     */     //   622: lastore
/*     */     //   623: dup2
/*     */     //   624: lstore #34
/*     */     //   626: lload #32
/*     */     //   628: lcmp
/*     */     //   629: ifle -> 674
/*     */     //   632: lload #36
/*     */     //   634: lstore #38
/*     */     //   636: aload_0
/*     */     //   637: lload #34
/*     */     //   639: invokestatic a : ([[JJ)J
/*     */     //   642: lstore #36
/*     */     //   644: aload_0
/*     */     //   645: lload #34
/*     */     //   647: lload #38
/*     */     //   649: invokestatic d : ([[JJJ)V
/*     */     //   652: aload #24
/*     */     //   654: lload #36
/*     */     //   656: invokestatic a : ([[BJ)B
/*     */     //   659: iload #25
/*     */     //   661: iushr
/*     */     //   662: sipush #255
/*     */     //   665: iand
/*     */     //   666: iload #23
/*     */     //   668: ixor
/*     */     //   669: istore #31
/*     */     //   671: goto -> 613
/*     */     //   674: aload_0
/*     */     //   675: lload #32
/*     */     //   677: lload #36
/*     */     //   679: invokestatic d : ([[JJJ)V
/*     */     //   682: iload #22
/*     */     //   684: iconst_1
/*     */     //   685: if_icmpge -> 776
/*     */     //   688: aload #15
/*     */     //   690: iload #31
/*     */     //   692: laload
/*     */     //   693: lconst_1
/*     */     //   694: lcmp
/*     */     //   695: ifle -> 776
/*     */     //   698: goto -> 705
/*     */     //   701: invokestatic a : (Ljava/lang/IllegalArgumentException;)Ljava/lang/IllegalArgumentException;
/*     */     //   704: athrow
/*     */     //   705: aload #15
/*     */     //   707: iload #31
/*     */     //   709: laload
/*     */     //   710: ldc2_w 1024
/*     */     //   713: lcmp
/*     */     //   714: ifge -> 747
/*     */     //   717: goto -> 724
/*     */     //   720: invokestatic a : (Ljava/lang/IllegalArgumentException;)Ljava/lang/IllegalArgumentException;
/*     */     //   723: athrow
/*     */     //   724: aload_0
/*     */     //   725: aload_1
/*     */     //   726: aload_2
/*     */     //   727: lload #32
/*     */     //   729: lload #32
/*     */     //   731: aload #15
/*     */     //   733: iload #31
/*     */     //   735: laload
/*     */     //   736: ladd
/*     */     //   737: invokestatic a : ([[J[[B[[BJJ)V
/*     */     //   740: goto -> 776
/*     */     //   743: invokestatic a : (Ljava/lang/IllegalArgumentException;)Ljava/lang/IllegalArgumentException;
/*     */     //   746: athrow
/*     */     //   747: aload #12
/*     */     //   749: iload #11
/*     */     //   751: lload #32
/*     */     //   753: lastore
/*     */     //   754: aload #13
/*     */     //   756: iload #11
/*     */     //   758: aload #15
/*     */     //   760: iload #31
/*     */     //   762: laload
/*     */     //   763: lastore
/*     */     //   764: aload #14
/*     */     //   766: iload #11
/*     */     //   768: iinc #11, 1
/*     */     //   771: iload #22
/*     */     //   773: iconst_1
/*     */     //   774: iadd
/*     */     //   775: iastore
/*     */     //   776: lload #32
/*     */     //   778: aload #15
/*     */     //   780: iload #31
/*     */     //   782: laload
/*     */     //   783: ladd
/*     */     //   784: lstore #32
/*     */     //   786: aload #15
/*     */     //   788: iload #31
/*     */     //   790: lconst_0
/*     */     //   791: lastore
/*     */     //   792: goto -> 570
/*     */     //   795: goto -> 120
/*     */     //   798: return
/*     */     // Line number table:
/*     */     //   Java source line number -> byte code offset
/*     */     //   #169	-> 0
/*     */     //   #355	-> 11
/*     */     //   #65	-> 20
/*     */     //   #174	-> 25
/*     */     //   #142	-> 28
/*     */     //   #75	-> 31
/*     */     //   #280	-> 36
/*     */     //   #337	-> 39
/*     */     //   #241	-> 46
/*     */     //   #63	-> 53
/*     */     //   #193	-> 60
/*     */     //   #316	-> 66
/*     */     //   #261	-> 75
/*     */     //   #330	-> 84
/*     */     //   #276	-> 91
/*     */     //   #314	-> 98
/*     */     //   #125	-> 120
/*     */     //   #140	-> 125
/*     */     //   #56	-> 135
/*     */     //   #331	-> 142
/*     */     //   #275	-> 149
/*     */     //   #82	-> 169
/*     */     //   #215	-> 186
/*     */     //   #257	-> 197
/*     */     //   #371	-> 252
/*     */     //   #407	-> 255
/*     */     //   #334	-> 272
/*     */     //   #156	-> 283
/*     */     //   #244	-> 304
/*     */     //   #231	-> 320
/*     */     //   #129	-> 326
/*     */     //   #254	-> 331
/*     */     //   #306	-> 398
/*     */     //   #47	-> 409
/*     */     //   #235	-> 413
/*     */     //   #262	-> 424
/*     */     //   #53	-> 454
/*     */     //   #74	-> 496
/*     */     //   #392	-> 503
/*     */     //   #227	-> 513
/*     */     //   #13	-> 525
/*     */     //   #387	-> 535
/*     */     //   #23	-> 541
/*     */     //   #295	-> 550
/*     */     //   #21	-> 563
/*     */     //   #216	-> 566
/*     */     //   #123	-> 578
/*     */     //   #93	-> 586
/*     */     //   #105	-> 605
/*     */     //   #393	-> 613
/*     */     //   #190	-> 632
/*     */     //   #344	-> 636
/*     */     //   #31	-> 644
/*     */     //   #278	-> 652
/*     */     //   #390	-> 671
/*     */     //   #183	-> 674
/*     */     //   #291	-> 682
/*     */     //   #299	-> 705
/*     */     //   #219	-> 747
/*     */     //   #245	-> 754
/*     */     //   #135	-> 764
/*     */     //   #267	-> 776
/*     */     //   #3	-> 795
/*     */     //   #137	-> 798
/*     */     // Exception table:
/*     */     //   from	to	target	type
/*     */     //   0	21	21	java/lang/IllegalArgumentException
/*     */     //   98	113	113	java/lang/IllegalArgumentException
/*     */     //   149	162	162	java/lang/IllegalArgumentException
/*     */     //   169	179	179	java/lang/IllegalArgumentException
/*     */     //   211	248	248	java/lang/IllegalArgumentException
/*     */     //   255	264	264	java/lang/IllegalArgumentException
/*     */     //   275	293	296	java/lang/IllegalArgumentException
/*     */     //   345	394	394	java/lang/IllegalArgumentException
/*     */     //   416	430	433	java/lang/IllegalArgumentException
/*     */     //   424	447	450	java/lang/IllegalArgumentException
/*     */     //   437	466	469	java/lang/IllegalArgumentException
/*     */     //   454	492	492	java/lang/IllegalArgumentException
/*     */     //   682	698	701	java/lang/IllegalArgumentException
/*     */     //   688	717	720	java/lang/IllegalArgumentException
/*     */     //   705	743	743	java/lang/IllegalArgumentException
/*     */   }
/*     */   
/*     */   @Deprecated
/*     */   public static void g(byte[][] paramArrayOfbyte, long paramLong1, long paramLong2) {
/*     */     k.a(a(paramArrayOfbyte), paramLong1, paramLong2);
/*     */   }
/*     */   
/*     */   public static void a(byte[][] paramArrayOfbyte, g9 paramg9) {
/*     */     c(paramArrayOfbyte, 0L, k.a(paramArrayOfbyte), paramg9);
/*     */   }
/*     */   
/*     */   @Deprecated
/*     */   public static byte[][] d(byte[][] paramArrayOfbyte, long paramLong1, long paramLong2) {
/*     */     return k.a(paramArrayOfbyte, paramLong1, paramLong2);
/*     */   }
/*     */   
/*     */   @Deprecated
/*     */   public static byte[][] a(byte[][] paramArrayOfbyte) {
/*     */     return k.b(paramArrayOfbyte);
/*     */   }
/*     */   
/*     */   public static void b(byte[][] paramArrayOfbyte, long paramLong1, long paramLong2) {
/*     */     // Byte code:
/*     */     //   0: iconst_0
/*     */     //   1: istore #5
/*     */     //   3: iconst_1
/*     */     //   4: istore #6
/*     */     //   6: iconst_1
/*     */     //   7: newarray long
/*     */     //   9: astore #7
/*     */     //   11: iconst_0
/*     */     //   12: istore #8
/*     */     //   14: iconst_1
/*     */     //   15: newarray long
/*     */     //   17: astore #9
/*     */     //   19: iconst_0
/*     */     //   20: istore #10
/*     */     //   22: iconst_1
/*     */     //   23: newarray int
/*     */     //   25: astore #11
/*     */     //   27: iconst_0
/*     */     //   28: istore #12
/*     */     //   30: aload #7
/*     */     //   32: iload #8
/*     */     //   34: iinc #8, 1
/*     */     //   37: lload_1
/*     */     //   38: lastore
/*     */     //   39: aload #9
/*     */     //   41: iload #10
/*     */     //   43: iinc #10, 1
/*     */     //   46: lload_3
/*     */     //   47: lload_1
/*     */     //   48: lsub
/*     */     //   49: lastore
/*     */     //   50: aload #11
/*     */     //   52: iload #12
/*     */     //   54: iinc #12, 1
/*     */     //   57: iconst_0
/*     */     //   58: iastore
/*     */     //   59: sipush #256
/*     */     //   62: newarray long
/*     */     //   64: astore #13
/*     */     //   66: sipush #256
/*     */     //   69: newarray long
/*     */     //   71: astore #14
/*     */     //   73: lload_3
/*     */     //   74: lload_1
/*     */     //   75: lsub
/*     */     //   76: invokestatic a : (J)[[B
/*     */     //   79: astore #15
/*     */     //   81: iload #8
/*     */     //   83: ifle -> 554
/*     */     //   86: aload #7
/*     */     //   88: iinc #8, -1
/*     */     //   91: iload #8
/*     */     //   93: laload
/*     */     //   94: lstore #16
/*     */     //   96: aload #9
/*     */     //   98: iinc #10, -1
/*     */     //   101: iload #10
/*     */     //   103: laload
/*     */     //   104: lstore #18
/*     */     //   106: aload #11
/*     */     //   108: iinc #12, -1
/*     */     //   111: iload #12
/*     */     //   113: iaload
/*     */     //   114: istore #20
/*     */     //   116: iload #20
/*     */     //   118: iconst_1
/*     */     //   119: irem
/*     */     //   120: ifne -> 133
/*     */     //   123: sipush #128
/*     */     //   126: goto -> 134
/*     */     //   129: invokestatic a : (Ljava/lang/IllegalArgumentException;)Ljava/lang/IllegalArgumentException;
/*     */     //   132: athrow
/*     */     //   133: iconst_0
/*     */     //   134: istore #21
/*     */     //   136: lload #18
/*     */     //   138: ldc2_w 40
/*     */     //   141: lcmp
/*     */     //   142: ifge -> 163
/*     */     //   145: aload_0
/*     */     //   146: lload #16
/*     */     //   148: lload #16
/*     */     //   150: lload #18
/*     */     //   152: ladd
/*     */     //   153: invokestatic d : ([[BJJ)V
/*     */     //   156: goto -> 81
/*     */     //   159: invokestatic a : (Ljava/lang/IllegalArgumentException;)Ljava/lang/IllegalArgumentException;
/*     */     //   162: athrow
/*     */     //   163: iconst_0
/*     */     //   164: iload #20
/*     */     //   166: iconst_1
/*     */     //   167: irem
/*     */     //   168: isub
/*     */     //   169: bipush #8
/*     */     //   171: imul
/*     */     //   172: istore #22
/*     */     //   174: lload #18
/*     */     //   176: lstore #23
/*     */     //   178: lload #23
/*     */     //   180: dup2
/*     */     //   181: lconst_1
/*     */     //   182: lsub
/*     */     //   183: lstore #23
/*     */     //   185: lconst_0
/*     */     //   186: lcmp
/*     */     //   187: ifeq -> 224
/*     */     //   190: aload #15
/*     */     //   192: lload #23
/*     */     //   194: aload_0
/*     */     //   195: lload #16
/*     */     //   197: lload #23
/*     */     //   199: ladd
/*     */     //   200: invokestatic a : ([[BJ)B
/*     */     //   203: iload #22
/*     */     //   205: iushr
/*     */     //   206: sipush #255
/*     */     //   209: iand
/*     */     //   210: iload #21
/*     */     //   212: ixor
/*     */     //   213: i2b
/*     */     //   214: invokestatic b : ([[BJB)V
/*     */     //   217: goto -> 178
/*     */     //   220: invokestatic a : (Ljava/lang/IllegalArgumentException;)Ljava/lang/IllegalArgumentException;
/*     */     //   223: athrow
/*     */     //   224: lload #18
/*     */     //   226: lstore #23
/*     */     //   228: lload #23
/*     */     //   230: dup2
/*     */     //   231: lconst_1
/*     */     //   232: lsub
/*     */     //   233: lstore #23
/*     */     //   235: lconst_0
/*     */     //   236: lcmp
/*     */     //   237: ifeq -> 265
/*     */     //   240: aload #13
/*     */     //   242: aload #15
/*     */     //   244: lload #23
/*     */     //   246: invokestatic a : ([[BJ)B
/*     */     //   249: sipush #255
/*     */     //   252: iand
/*     */     //   253: dup2
/*     */     //   254: laload
/*     */     //   255: lconst_1
/*     */     //   256: ladd
/*     */     //   257: lastore
/*     */     //   258: goto -> 228
/*     */     //   261: invokestatic a : (Ljava/lang/IllegalArgumentException;)Ljava/lang/IllegalArgumentException;
/*     */     //   264: athrow
/*     */     //   265: iconst_m1
/*     */     //   266: istore #23
/*     */     //   268: lconst_0
/*     */     //   269: lstore #24
/*     */     //   271: iconst_0
/*     */     //   272: istore #26
/*     */     //   274: iload #26
/*     */     //   276: sipush #256
/*     */     //   279: if_icmpge -> 392
/*     */     //   282: aload #13
/*     */     //   284: iload #26
/*     */     //   286: laload
/*     */     //   287: lconst_0
/*     */     //   288: lcmp
/*     */     //   289: ifeq -> 370
/*     */     //   292: goto -> 299
/*     */     //   295: invokestatic a : (Ljava/lang/IllegalArgumentException;)Ljava/lang/IllegalArgumentException;
/*     */     //   298: athrow
/*     */     //   299: iload #26
/*     */     //   301: istore #23
/*     */     //   303: iload #20
/*     */     //   305: ifge -> 370
/*     */     //   308: aload #13
/*     */     //   310: iload #26
/*     */     //   312: laload
/*     */     //   313: lconst_1
/*     */     //   314: lcmp
/*     */     //   315: ifle -> 370
/*     */     //   318: goto -> 325
/*     */     //   321: invokestatic a : (Ljava/lang/IllegalArgumentException;)Ljava/lang/IllegalArgumentException;
/*     */     //   324: athrow
/*     */     //   325: aload #7
/*     */     //   327: iload #8
/*     */     //   329: iinc #8, 1
/*     */     //   332: lload #24
/*     */     //   334: lload #16
/*     */     //   336: ladd
/*     */     //   337: lastore
/*     */     //   338: aload #9
/*     */     //   340: iload #10
/*     */     //   342: iinc #10, 1
/*     */     //   345: aload #13
/*     */     //   347: iload #26
/*     */     //   349: laload
/*     */     //   350: lastore
/*     */     //   351: aload #11
/*     */     //   353: iload #12
/*     */     //   355: iinc #12, 1
/*     */     //   358: iload #20
/*     */     //   360: iconst_1
/*     */     //   361: iadd
/*     */     //   362: iastore
/*     */     //   363: goto -> 370
/*     */     //   366: invokestatic a : (Ljava/lang/IllegalArgumentException;)Ljava/lang/IllegalArgumentException;
/*     */     //   369: athrow
/*     */     //   370: aload #14
/*     */     //   372: iload #26
/*     */     //   374: lload #24
/*     */     //   376: aload #13
/*     */     //   378: iload #26
/*     */     //   380: laload
/*     */     //   381: ladd
/*     */     //   382: dup2
/*     */     //   383: lstore #24
/*     */     //   385: lastore
/*     */     //   386: iinc #26, 1
/*     */     //   389: goto -> 274
/*     */     //   392: lload #18
/*     */     //   394: aload #13
/*     */     //   396: iload #23
/*     */     //   398: laload
/*     */     //   399: lsub
/*     */     //   400: lstore #26
/*     */     //   402: aload #13
/*     */     //   404: iload #23
/*     */     //   406: lconst_0
/*     */     //   407: lastore
/*     */     //   408: iconst_m1
/*     */     //   409: istore #28
/*     */     //   411: lconst_0
/*     */     //   412: lstore #29
/*     */     //   414: lload #29
/*     */     //   416: lload #26
/*     */     //   418: lcmp
/*     */     //   419: ifge -> 551
/*     */     //   422: aload_0
/*     */     //   423: lload #29
/*     */     //   425: lload #16
/*     */     //   427: ladd
/*     */     //   428: invokestatic a : ([[BJ)B
/*     */     //   431: istore #33
/*     */     //   433: aload #15
/*     */     //   435: lload #29
/*     */     //   437: invokestatic a : ([[BJ)B
/*     */     //   440: sipush #255
/*     */     //   443: iand
/*     */     //   444: istore #28
/*     */     //   446: aload #14
/*     */     //   448: iload #28
/*     */     //   450: dup2
/*     */     //   451: laload
/*     */     //   452: lconst_1
/*     */     //   453: lsub
/*     */     //   454: dup2_x2
/*     */     //   455: lastore
/*     */     //   456: dup2
/*     */     //   457: lstore #31
/*     */     //   459: lload #29
/*     */     //   461: lcmp
/*     */     //   462: ifle -> 521
/*     */     //   465: iload #33
/*     */     //   467: istore #34
/*     */     //   469: iload #28
/*     */     //   471: istore #35
/*     */     //   473: aload_0
/*     */     //   474: lload #31
/*     */     //   476: lload #16
/*     */     //   478: ladd
/*     */     //   479: invokestatic a : ([[BJ)B
/*     */     //   482: istore #33
/*     */     //   484: aload #15
/*     */     //   486: lload #31
/*     */     //   488: invokestatic a : ([[BJ)B
/*     */     //   491: sipush #255
/*     */     //   494: iand
/*     */     //   495: istore #28
/*     */     //   497: aload_0
/*     */     //   498: lload #31
/*     */     //   500: lload #16
/*     */     //   502: ladd
/*     */     //   503: iload #34
/*     */     //   505: invokestatic b : ([[BJB)V
/*     */     //   508: aload #15
/*     */     //   510: lload #31
/*     */     //   512: iload #35
/*     */     //   514: i2b
/*     */     //   515: invokestatic b : ([[BJB)V
/*     */     //   518: goto -> 446
/*     */     //   521: aload_0
/*     */     //   522: lload #29
/*     */     //   524: lload #16
/*     */     //   526: ladd
/*     */     //   527: iload #33
/*     */     //   529: invokestatic b : ([[BJB)V
/*     */     //   532: lload #29
/*     */     //   534: aload #13
/*     */     //   536: iload #28
/*     */     //   538: laload
/*     */     //   539: ladd
/*     */     //   540: lstore #29
/*     */     //   542: aload #13
/*     */     //   544: iload #28
/*     */     //   546: lconst_0
/*     */     //   547: lastore
/*     */     //   548: goto -> 414
/*     */     //   551: goto -> 81
/*     */     //   554: return
/*     */     // Line number table:
/*     */     //   Java source line number -> byte code offset
/*     */     //   #189	-> 0
/*     */     //   #102	-> 3
/*     */     //   #111	-> 6
/*     */     //   #300	-> 11
/*     */     //   #177	-> 14
/*     */     //   #324	-> 19
/*     */     //   #212	-> 22
/*     */     //   #107	-> 27
/*     */     //   #399	-> 30
/*     */     //   #369	-> 39
/*     */     //   #200	-> 50
/*     */     //   #271	-> 59
/*     */     //   #41	-> 66
/*     */     //   #103	-> 73
/*     */     //   #58	-> 81
/*     */     //   #5	-> 86
/*     */     //   #384	-> 96
/*     */     //   #237	-> 106
/*     */     //   #352	-> 116
/*     */     //   #294	-> 136
/*     */     //   #264	-> 145
/*     */     //   #158	-> 156
/*     */     //   #286	-> 163
/*     */     //   #246	-> 174
/*     */     //   #217	-> 224
/*     */     //   #95	-> 265
/*     */     //   #7	-> 268
/*     */     //   #228	-> 271
/*     */     //   #85	-> 282
/*     */     //   #209	-> 299
/*     */     //   #285	-> 303
/*     */     //   #269	-> 325
/*     */     //   #57	-> 338
/*     */     //   #108	-> 351
/*     */     //   #238	-> 370
/*     */     //   #2	-> 386
/*     */     //   #127	-> 392
/*     */     //   #249	-> 402
/*     */     //   #17	-> 408
/*     */     //   #180	-> 411
/*     */     //   #253	-> 422
/*     */     //   #77	-> 433
/*     */     //   #356	-> 446
/*     */     //   #181	-> 465
/*     */     //   #233	-> 469
/*     */     //   #110	-> 473
/*     */     //   #301	-> 484
/*     */     //   #221	-> 497
/*     */     //   #283	-> 508
/*     */     //   #168	-> 518
/*     */     //   #417	-> 521
/*     */     //   #282	-> 532
/*     */     //   #61	-> 551
/*     */     //   #115	-> 554
/*     */     // Exception table:
/*     */     //   from	to	target	type
/*     */     //   116	129	129	java/lang/IllegalArgumentException
/*     */     //   136	159	159	java/lang/IllegalArgumentException
/*     */     //   185	220	220	java/lang/IllegalArgumentException
/*     */     //   235	261	261	java/lang/IllegalArgumentException
/*     */     //   274	292	295	java/lang/IllegalArgumentException
/*     */     //   303	318	321	java/lang/IllegalArgumentException
/*     */     //   308	363	366	java/lang/IllegalArgumentException
/*     */   }
/*     */   
/*     */   public static byte[][] a(byte[][] paramArrayOfbyte, Random paramRandom) {
/*     */     return k.a(paramArrayOfbyte, paramRandom);
/*     */   }
/*     */   
/*     */   @Deprecated
/*     */   public static byte[][] b(byte[][] paramArrayOfbyte, long paramLong) {
/*     */     k.a(paramLong);
/*     */     long l = a(paramArrayOfbyte);
/*     */     try {
/*     */       if (paramLong >= l)
/*     */         return paramArrayOfbyte; 
/*     */     } catch (IllegalArgumentException illegalArgumentException) {
/*     */       throw a(null);
/*     */     } 
/*     */     int i = (int)(paramLong + 134217727L >>> 27L);
/*     */     byte[][] arrayOfByte = Arrays.<byte[]>copyOf(paramArrayOfbyte, i);
/*     */     int j = (int)(paramLong & 0x7FFFFFFL);
/*     */     try {
/*     */       if (j != 0)
/*     */         arrayOfByte[i - 1] = dx.d(arrayOfByte[i - 1], j); 
/*     */     } catch (IllegalArgumentException illegalArgumentException) {
/*     */       throw a(null);
/*     */     } 
/*     */     return arrayOfByte;
/*     */   }
/*     */   
/*     */   @Deprecated
/*     */   public static void a(byte[] paramArrayOfbyte, int paramInt, byte[][] paramArrayOfbyte1, long paramLong1, long paramLong2) {
/*     */     k.a(paramArrayOfbyte, paramInt, paramArrayOfbyte1, paramLong1, paramLong2);
/*     */   }
/*     */   
/*     */   private static void a(byte[][] paramArrayOfbyte, long paramLong1, long paramLong2, g9 paramg9) {
/*     */     for (long l = paramLong1; l < paramLong2 - 1L; ) {
/*     */       long l1 = l;
/*     */       long l2 = l + 1L;
/*     */       while (true) {
/*     */         try {
/*     */           if (l2 < paramLong2) {
/*     */             if (paramg9.a(k.a(paramArrayOfbyte, l2), k.a(paramArrayOfbyte, l1)) < 0)
/*     */               l1 = l2; 
/*     */             l2++;
/*     */             continue;
/*     */           } 
/*     */         } catch (IllegalArgumentException illegalArgumentException) {
/*     */           throw a(null);
/*     */         } 
/*     */         try {
/*     */           if (l1 != l)
/*     */             k.b(paramArrayOfbyte, l, l1); 
/*     */         } catch (IllegalArgumentException illegalArgumentException) {
/*     */           throw a(null);
/*     */         } 
/*     */         break;
/*     */       } 
/*     */     } 
/*     */   }
/*     */   
/*     */   @Deprecated
/*     */   public static byte[][] b(byte[][] paramArrayOfbyte, long paramLong1, long paramLong2) {
/*     */     try {
/*     */     
/*     */     } catch (IllegalArgumentException illegalArgumentException) {
/*     */       throw a(null);
/*     */     } 
/*     */     return (paramLong1 > a(paramArrayOfbyte)) ? d(paramArrayOfbyte, paramLong1, paramLong2) : paramArrayOfbyte;
/*     */   }
/*     */   
/*     */   @Deprecated
/*     */   public static byte[][] c(byte[][] paramArrayOfbyte, long paramLong) {
/*     */     return b(paramArrayOfbyte, paramLong, a(paramArrayOfbyte));
/*     */   }
/*     */   
/*     */   @Deprecated
/*     */   public static void b(byte[][] paramArrayOfbyte, long paramLong) {
/*     */     paramArrayOfbyte[k.b(paramLong)][k.a(paramLong)] = (byte)(paramArrayOfbyte[k.b(paramLong)][k.a(paramLong)] - 1);
/*     */   }
/*     */   
/*     */   @Deprecated
/*     */   public static void c(byte[][] paramArrayOfbyte, long paramLong1, long paramLong2) {
/*     */     byte b = paramArrayOfbyte[k.b(paramLong1)][k.a(paramLong1)];
/*     */     paramArrayOfbyte[k.b(paramLong1)][k.a(paramLong1)] = paramArrayOfbyte[k.b(paramLong2)][k.a(paramLong2)];
/*     */     paramArrayOfbyte[k.b(paramLong2)][k.a(paramLong2)] = b;
/*     */   }
/*     */   
/*     */   @Deprecated
/*     */   public static byte[][] d(byte[][] paramArrayOfbyte, long paramLong) {
/*     */     return k.a(paramArrayOfbyte, paramLong);
/*     */   }
/*     */   
/*     */   public static void f(byte[][] paramArrayOfbyte, long paramLong1, long paramLong2) {
/*     */     ForkJoinPool forkJoinPool = a();
/*     */     try {
/*     */       if (paramLong2 - paramLong1 >= 8192L) {
/*     */         try {
/*     */           if (forkJoinPool.getParallelism() == 1) {
/*     */             a(paramArrayOfbyte, paramLong1, paramLong2);
/*     */             return;
/*     */           } 
/*     */         } catch (IllegalArgumentException illegalArgumentException) {
/*     */           throw a(null);
/*     */         } 
/*     */         forkJoinPool.invoke(new ak(paramArrayOfbyte, paramLong1, paramLong2));
/*     */         return;
/*     */       } 
/*     */     } catch (IllegalArgumentException illegalArgumentException) {
/*     */       throw a(null);
/*     */     } 
/*     */     a(paramArrayOfbyte, paramLong1, paramLong2);
/*     */   }
/*     */   
/*     */   @Deprecated
/*     */   public static String a(byte[][] paramArrayOfbyte) {
/*     */     return k.a(paramArrayOfbyte);
/*     */   }
/*     */   
/*     */   private static void b(byte[][] paramArrayOfbyte1, byte[][] paramArrayOfbyte2, long paramLong1, long paramLong2) {
/*     */     // Byte code:
/*     */     //   0: lload_2
/*     */     //   1: lstore #6
/*     */     //   3: lload #6
/*     */     //   5: lload #4
/*     */     //   7: lconst_1
/*     */     //   8: lsub
/*     */     //   9: lcmp
/*     */     //   10: ifge -> 183
/*     */     //   13: lload #6
/*     */     //   15: lstore #8
/*     */     //   17: lload #6
/*     */     //   19: lconst_1
/*     */     //   20: ladd
/*     */     //   21: lstore #10
/*     */     //   23: lload #10
/*     */     //   25: lload #4
/*     */     //   27: lcmp
/*     */     //   28: ifge -> 110
/*     */     //   31: aload_0
/*     */     //   32: lload #10
/*     */     //   34: invokestatic a : ([[BJ)B
/*     */     //   37: aload_0
/*     */     //   38: lload #8
/*     */     //   40: invokestatic a : ([[BJ)B
/*     */     //   43: if_icmplt -> 97
/*     */     //   46: goto -> 53
/*     */     //   49: invokestatic a : (Ljava/lang/IllegalArgumentException;)Ljava/lang/IllegalArgumentException;
/*     */     //   52: athrow
/*     */     //   53: aload_0
/*     */     //   54: lload #10
/*     */     //   56: invokestatic a : ([[BJ)B
/*     */     //   59: aload_0
/*     */     //   60: lload #8
/*     */     //   62: invokestatic a : ([[BJ)B
/*     */     //   65: if_icmpne -> 101
/*     */     //   68: goto -> 75
/*     */     //   71: invokestatic a : (Ljava/lang/IllegalArgumentException;)Ljava/lang/IllegalArgumentException;
/*     */     //   74: athrow
/*     */     //   75: aload_1
/*     */     //   76: lload #10
/*     */     //   78: invokestatic a : ([[BJ)B
/*     */     //   81: aload_1
/*     */     //   82: lload #8
/*     */     //   84: invokestatic a : ([[BJ)B
/*     */     //   87: if_icmpge -> 101
/*     */     //   90: goto -> 97
/*     */     //   93: invokestatic a : (Ljava/lang/IllegalArgumentException;)Ljava/lang/IllegalArgumentException;
/*     */     //   96: athrow
/*     */     //   97: lload #10
/*     */     //   99: lstore #8
/*     */     //   101: lload #10
/*     */     //   103: lconst_1
/*     */     //   104: ladd
/*     */     //   105: lstore #10
/*     */     //   107: goto -> 23
/*     */     //   110: lload #8
/*     */     //   112: lload #6
/*     */     //   114: lcmp
/*     */     //   115: ifeq -> 174
/*     */     //   118: aload_0
/*     */     //   119: lload #6
/*     */     //   121: invokestatic a : ([[BJ)B
/*     */     //   124: istore #10
/*     */     //   126: aload_0
/*     */     //   127: lload #6
/*     */     //   129: aload_0
/*     */     //   130: lload #8
/*     */     //   132: invokestatic a : ([[BJ)B
/*     */     //   135: invokestatic b : ([[BJB)V
/*     */     //   138: aload_0
/*     */     //   139: lload #8
/*     */     //   141: iload #10
/*     */     //   143: invokestatic b : ([[BJB)V
/*     */     //   146: aload_1
/*     */     //   147: lload #6
/*     */     //   149: invokestatic a : ([[BJ)B
/*     */     //   152: istore #10
/*     */     //   154: aload_1
/*     */     //   155: lload #6
/*     */     //   157: aload_1
/*     */     //   158: lload #8
/*     */     //   160: invokestatic a : ([[BJ)B
/*     */     //   163: invokestatic b : ([[BJB)V
/*     */     //   166: aload_1
/*     */     //   167: lload #8
/*     */     //   169: iload #10
/*     */     //   171: invokestatic b : ([[BJB)V
/*     */     //   174: lload #6
/*     */     //   176: lconst_1
/*     */     //   177: ladd
/*     */     //   178: lstore #6
/*     */     //   180: goto -> 3
/*     */     //   183: return
/*     */     // Line number table:
/*     */     //   Java source line number -> byte code offset
/*     */     //   #322	-> 0
/*     */     //   #404	-> 13
/*     */     //   #353	-> 17
/*     */     //   #155	-> 31
/*     */     //   #44	-> 101
/*     */     //   #197	-> 110
/*     */     //   #248	-> 118
/*     */     //   #411	-> 126
/*     */     //   #412	-> 138
/*     */     //   #224	-> 146
/*     */     //   #170	-> 154
/*     */     //   #358	-> 166
/*     */     //   #138	-> 174
/*     */     //   #222	-> 183
/*     */     // Exception table:
/*     */     //   from	to	target	type
/*     */     //   23	46	49	java/lang/IllegalArgumentException
/*     */     //   31	68	71	java/lang/IllegalArgumentException
/*     */     //   53	90	93	java/lang/IllegalArgumentException
/*     */   }
/*     */   
/*     */   @Deprecated
/*     */   public static boolean a(byte[][] paramArrayOfbyte1, byte[][] paramArrayOfbyte2) {
/*     */     return k.a(paramArrayOfbyte1, paramArrayOfbyte2);
/*     */   }
/*     */   
/*     */   @Deprecated
/*     */   public static byte[][] a(byte[][] paramArrayOfbyte, long paramLong) {
/*     */     long l = a(paramArrayOfbyte);
/*     */     try {
/*     */     
/*     */     } catch (IllegalArgumentException illegalArgumentException) {
/*     */       throw a(null);
/*     */     } 
/*     */     return (paramLong > l) ? c(paramArrayOfbyte, paramLong, l) : paramArrayOfbyte;
/*     */   }
/*     */   
/*     */   public static byte[][] a(long paramLong) {
/*     */     try {
/*     */       if (paramLong == 0L)
/*     */         return j; 
/*     */     } catch (IllegalArgumentException illegalArgumentException) {
/*     */       throw a(null);
/*     */     } 
/*     */     k.a(paramLong);
/*     */     int i = (int)(paramLong + 134217727L >>> 27L);
/*     */     byte[][] arrayOfByte = new byte[i][];
/*     */     int j = (int)(paramLong & 0x7FFFFFFL);
/*     */     if (j != 0) {
/*     */       byte b1 = 0;
/*     */       try {
/*     */         while (b1 < i - 1) {
/*     */           arrayOfByte[b1] = new byte[134217728];
/*     */           b1++;
/*     */         } 
/*     */       } catch (IllegalArgumentException illegalArgumentException) {
/*     */         throw a(null);
/*     */       } 
/*     */     } 
/*     */     byte b = 0;
/*     */     try {
/*     */       while (b < i) {
/*     */         arrayOfByte[b] = new byte[134217728];
/*     */         b++;
/*     */       } 
/*     */     } catch (IllegalArgumentException illegalArgumentException) {
/*     */       throw a(null);
/*     */     } 
/*     */     return arrayOfByte;
/*     */   }
/*     */   
/*     */   @Deprecated
/*     */   public static void b(byte[][] paramArrayOfbyte, long paramLong, byte paramByte) {
/*     */     paramArrayOfbyte[k.b(paramLong)][k.a(paramLong)] = paramByte;
/*     */   }
/*     */   
/*     */   public static void a(byte[][] paramArrayOfbyte) {
/*     */     a(paramArrayOfbyte, 0L, k.a(paramArrayOfbyte));
/*     */   }
/*     */   
/*     */   private static ForkJoinPool a() {
/*     */     ForkJoinPool forkJoinPool = ForkJoinTask.getPool();
/*     */     try {
/*     */     
/*     */     } catch (IllegalArgumentException illegalArgumentException) {
/*     */       throw a(null);
/*     */     } 
/*     */     return (forkJoinPool == null) ? ForkJoinPool.commonPool() : forkJoinPool;
/*     */   }
/*     */   
/*     */   @Deprecated
/*     */   public static byte[][] a(byte[] paramArrayOfbyte) {
/*     */     return k.a(paramArrayOfbyte);
/*     */   }
/*     */   
/*     */   @Deprecated
/*     */   public static void e(byte[][] paramArrayOfbyte, long paramLong1, long paramLong2) {
/*     */     k.b(a(paramArrayOfbyte), paramLong1, paramLong2);
/*     */   }
/*     */   
/*     */   public static void b(byte[][] paramArrayOfbyte, long paramLong1, long paramLong2, g9 paramg9) {
/*     */     // Byte code:
/*     */     //   0: lload_3
/*     */     //   1: lload_1
/*     */     //   2: lsub
/*     */     //   3: lstore #6
/*     */     //   5: lload #6
/*     */     //   7: ldc2_w 7
/*     */     //   10: lcmp
/*     */     //   11: ifge -> 27
/*     */     //   14: aload_0
/*     */     //   15: lload_1
/*     */     //   16: lload_3
/*     */     //   17: aload #5
/*     */     //   19: invokestatic a : ([[BJJLme/konsolas/aac/g9;)V
/*     */     //   22: return
/*     */     //   23: invokestatic a : (Ljava/lang/IllegalArgumentException;)Ljava/lang/IllegalArgumentException;
/*     */     //   26: athrow
/*     */     //   27: lload_1
/*     */     //   28: lload #6
/*     */     //   30: ldc2_w 2
/*     */     //   33: ldiv
/*     */     //   34: ladd
/*     */     //   35: lstore #8
/*     */     //   37: lload #6
/*     */     //   39: ldc2_w 7
/*     */     //   42: lcmp
/*     */     //   43: ifle -> 153
/*     */     //   46: lload_1
/*     */     //   47: lstore #10
/*     */     //   49: lload_3
/*     */     //   50: lconst_1
/*     */     //   51: lsub
/*     */     //   52: lstore #12
/*     */     //   54: lload #6
/*     */     //   56: ldc2_w 40
/*     */     //   59: lcmp
/*     */     //   60: ifle -> 139
/*     */     //   63: lload #6
/*     */     //   65: ldc2_w 8
/*     */     //   68: ldiv
/*     */     //   69: lstore #14
/*     */     //   71: aload_0
/*     */     //   72: lload #10
/*     */     //   74: lload #10
/*     */     //   76: lload #14
/*     */     //   78: ladd
/*     */     //   79: lload #10
/*     */     //   81: ldc2_w 2
/*     */     //   84: lload #14
/*     */     //   86: lmul
/*     */     //   87: ladd
/*     */     //   88: aload #5
/*     */     //   90: invokestatic a : ([[BJJJLme/konsolas/aac/g9;)J
/*     */     //   93: lstore #10
/*     */     //   95: aload_0
/*     */     //   96: lload #8
/*     */     //   98: lload #14
/*     */     //   100: lsub
/*     */     //   101: lload #8
/*     */     //   103: lload #8
/*     */     //   105: lload #14
/*     */     //   107: ladd
/*     */     //   108: aload #5
/*     */     //   110: invokestatic a : ([[BJJJLme/konsolas/aac/g9;)J
/*     */     //   113: lstore #8
/*     */     //   115: aload_0
/*     */     //   116: lload #12
/*     */     //   118: ldc2_w 2
/*     */     //   121: lload #14
/*     */     //   123: lmul
/*     */     //   124: lsub
/*     */     //   125: lload #12
/*     */     //   127: lload #14
/*     */     //   129: lsub
/*     */     //   130: lload #12
/*     */     //   132: aload #5
/*     */     //   134: invokestatic a : ([[BJJJLme/konsolas/aac/g9;)J
/*     */     //   137: lstore #12
/*     */     //   139: aload_0
/*     */     //   140: lload #10
/*     */     //   142: lload #8
/*     */     //   144: lload #12
/*     */     //   146: aload #5
/*     */     //   148: invokestatic a : ([[BJJJLme/konsolas/aac/g9;)J
/*     */     //   151: lstore #8
/*     */     //   153: aload_0
/*     */     //   154: lload #8
/*     */     //   156: invokestatic a : ([[BJ)B
/*     */     //   159: istore #10
/*     */     //   161: lload_1
/*     */     //   162: lstore #11
/*     */     //   164: lload #11
/*     */     //   166: lstore #13
/*     */     //   168: lload_3
/*     */     //   169: lconst_1
/*     */     //   170: lsub
/*     */     //   171: lstore #15
/*     */     //   173: lload #15
/*     */     //   175: lstore #17
/*     */     //   177: lload #13
/*     */     //   179: lload #15
/*     */     //   181: lcmp
/*     */     //   182: ifgt -> 240
/*     */     //   185: aload #5
/*     */     //   187: aload_0
/*     */     //   188: lload #13
/*     */     //   190: invokestatic a : ([[BJ)B
/*     */     //   193: iload #10
/*     */     //   195: invokeinterface a : (BB)I
/*     */     //   200: dup
/*     */     //   201: istore #19
/*     */     //   203: ifgt -> 240
/*     */     //   206: iload #19
/*     */     //   208: ifne -> 231
/*     */     //   211: goto -> 218
/*     */     //   214: invokestatic a : (Ljava/lang/IllegalArgumentException;)Ljava/lang/IllegalArgumentException;
/*     */     //   217: athrow
/*     */     //   218: aload_0
/*     */     //   219: lload #11
/*     */     //   221: dup2
/*     */     //   222: lconst_1
/*     */     //   223: ladd
/*     */     //   224: lstore #11
/*     */     //   226: lload #13
/*     */     //   228: invokestatic b : ([[BJJ)V
/*     */     //   231: lload #13
/*     */     //   233: lconst_1
/*     */     //   234: ladd
/*     */     //   235: lstore #13
/*     */     //   237: goto -> 177
/*     */     //   240: lload #15
/*     */     //   242: lload #13
/*     */     //   244: lcmp
/*     */     //   245: iflt -> 303
/*     */     //   248: aload #5
/*     */     //   250: aload_0
/*     */     //   251: lload #15
/*     */     //   253: invokestatic a : ([[BJ)B
/*     */     //   256: iload #10
/*     */     //   258: invokeinterface a : (BB)I
/*     */     //   263: dup
/*     */     //   264: istore #19
/*     */     //   266: iflt -> 303
/*     */     //   269: iload #19
/*     */     //   271: ifne -> 294
/*     */     //   274: goto -> 281
/*     */     //   277: invokestatic a : (Ljava/lang/IllegalArgumentException;)Ljava/lang/IllegalArgumentException;
/*     */     //   280: athrow
/*     */     //   281: aload_0
/*     */     //   282: lload #15
/*     */     //   284: lload #17
/*     */     //   286: dup2
/*     */     //   287: lconst_1
/*     */     //   288: lsub
/*     */     //   289: lstore #17
/*     */     //   291: invokestatic b : ([[BJJ)V
/*     */     //   294: lload #15
/*     */     //   296: lconst_1
/*     */     //   297: lsub
/*     */     //   298: lstore #15
/*     */     //   300: goto -> 240
/*     */     //   303: lload #13
/*     */     //   305: lload #15
/*     */     //   307: lcmp
/*     */     //   308: ifle -> 318
/*     */     //   311: goto -> 339
/*     */     //   314: invokestatic a : (Ljava/lang/IllegalArgumentException;)Ljava/lang/IllegalArgumentException;
/*     */     //   317: athrow
/*     */     //   318: aload_0
/*     */     //   319: lload #13
/*     */     //   321: dup2
/*     */     //   322: lconst_1
/*     */     //   323: ladd
/*     */     //   324: lstore #13
/*     */     //   326: lload #15
/*     */     //   328: dup2
/*     */     //   329: lconst_1
/*     */     //   330: lsub
/*     */     //   331: lstore #15
/*     */     //   333: invokestatic b : ([[BJJ)V
/*     */     //   336: goto -> 177
/*     */     //   339: lload_3
/*     */     //   340: lstore #21
/*     */     //   342: lload #11
/*     */     //   344: lload_1
/*     */     //   345: lsub
/*     */     //   346: lload #13
/*     */     //   348: lload #11
/*     */     //   350: lsub
/*     */     //   351: invokestatic min : (JJ)J
/*     */     //   354: lstore #19
/*     */     //   356: aload_0
/*     */     //   357: lload_1
/*     */     //   358: lload #13
/*     */     //   360: lload #19
/*     */     //   362: lsub
/*     */     //   363: lload #19
/*     */     //   365: invokestatic a : ([[BJJJ)V
/*     */     //   368: lload #17
/*     */     //   370: lload #15
/*     */     //   372: lsub
/*     */     //   373: lload #21
/*     */     //   375: lload #17
/*     */     //   377: lsub
/*     */     //   378: lconst_1
/*     */     //   379: lsub
/*     */     //   380: invokestatic min : (JJ)J
/*     */     //   383: lstore #19
/*     */     //   385: aload_0
/*     */     //   386: lload #13
/*     */     //   388: lload #21
/*     */     //   390: lload #19
/*     */     //   392: lsub
/*     */     //   393: lload #19
/*     */     //   395: invokestatic a : ([[BJJJ)V
/*     */     //   398: lload #13
/*     */     //   400: lload #11
/*     */     //   402: lsub
/*     */     //   403: dup2
/*     */     //   404: lstore #19
/*     */     //   406: lconst_1
/*     */     //   407: lcmp
/*     */     //   408: ifle -> 429
/*     */     //   411: aload_0
/*     */     //   412: lload_1
/*     */     //   413: lload_1
/*     */     //   414: lload #19
/*     */     //   416: ladd
/*     */     //   417: aload #5
/*     */     //   419: invokestatic b : ([[BJJLme/konsolas/aac/g9;)V
/*     */     //   422: goto -> 429
/*     */     //   425: invokestatic a : (Ljava/lang/IllegalArgumentException;)Ljava/lang/IllegalArgumentException;
/*     */     //   428: athrow
/*     */     //   429: lload #17
/*     */     //   431: lload #15
/*     */     //   433: lsub
/*     */     //   434: dup2
/*     */     //   435: lstore #19
/*     */     //   437: lconst_1
/*     */     //   438: lcmp
/*     */     //   439: ifle -> 462
/*     */     //   442: aload_0
/*     */     //   443: lload #21
/*     */     //   445: lload #19
/*     */     //   447: lsub
/*     */     //   448: lload #21
/*     */     //   450: aload #5
/*     */     //   452: invokestatic b : ([[BJJLme/konsolas/aac/g9;)V
/*     */     //   455: goto -> 462
/*     */     //   458: invokestatic a : (Ljava/lang/IllegalArgumentException;)Ljava/lang/IllegalArgumentException;
/*     */     //   461: athrow
/*     */     //   462: return
/*     */     // Line number table:
/*     */     //   Java source line number -> byte code offset
/*     */     //   #409	-> 0
/*     */     //   #201	-> 5
/*     */     //   #362	-> 14
/*     */     //   #382	-> 22
/*     */     //   #290	-> 27
/*     */     //   #388	-> 37
/*     */     //   #182	-> 46
/*     */     //   #15	-> 49
/*     */     //   #96	-> 54
/*     */     //   #30	-> 63
/*     */     //   #252	-> 71
/*     */     //   #8	-> 95
/*     */     //   #385	-> 115
/*     */     //   #266	-> 139
/*     */     //   #348	-> 153
/*     */     //   #159	-> 161
/*     */     //   #45	-> 177
/*     */     //   #94	-> 206
/*     */     //   #378	-> 231
/*     */     //   #191	-> 240
/*     */     //   #176	-> 269
/*     */     //   #206	-> 294
/*     */     //   #1	-> 303
/*     */     //   #132	-> 318
/*     */     //   #166	-> 339
/*     */     //   #194	-> 342
/*     */     //   #112	-> 356
/*     */     //   #342	-> 368
/*     */     //   #230	-> 385
/*     */     //   #122	-> 398
/*     */     //   #172	-> 429
/*     */     //   #375	-> 462
/*     */     // Exception table:
/*     */     //   from	to	target	type
/*     */     //   5	23	23	java/lang/IllegalArgumentException
/*     */     //   203	211	214	java/lang/IllegalArgumentException
/*     */     //   266	274	277	java/lang/IllegalArgumentException
/*     */     //   303	314	314	java/lang/IllegalArgumentException
/*     */     //   406	422	425	java/lang/IllegalArgumentException
/*     */     //   437	455	458	java/lang/IllegalArgumentException
/*     */   }
/*     */   
/*     */   @Deprecated
/*     */   public static void a(byte[][] paramArrayOfbyte, long paramLong, byte[] paramArrayOfbyte1, int paramInt1, int paramInt2) {
/*     */     k.a(paramArrayOfbyte, paramLong, paramArrayOfbyte1, paramInt1, paramInt2);
/*     */   }
/*     */   
/*     */   static {
/*     */     // Byte code:
/*     */     //   0: ldc2_w 1451885046372709612
/*     */     //   3: ldc2_w -9158224567771407754
/*     */     //   6: invokestatic lookup : ()Ljava/lang/invoke/MethodHandles$Lookup;
/*     */     //   9: invokevirtual lookupClass : ()Ljava/lang/Class;
/*     */     //   12: invokestatic a : (JJLjava/lang/Object;)Lme/konsolas/aac/na;
/*     */     //   15: ldc2_w 144997672803155
/*     */     //   18: invokeinterface a : (J)J
/*     */     //   23: putstatic me/konsolas/aac/fd.l : J
/*     */     //   26: getstatic me/konsolas/aac/fd.l : J
/*     */     //   29: ldc2_w 2338918348927
/*     */     //   32: lxor
/*     */     //   33: lstore_0
/*     */     //   34: iconst_0
/*     */     //   35: anewarray [B
/*     */     //   38: putstatic me/konsolas/aac/fd.j : [[B
/*     */     //   41: iconst_1
/*     */     //   42: iconst_0
/*     */     //   43: anewarray [B
/*     */     //   46: putstatic me/konsolas/aac/fd.a : [[B
/*     */     //   49: ldc2_w -7054732043667171778
/*     */     //   52: lload_0
/*     */     //   53: <illegal opcode> w : (ZJJ)V
/*     */     //   58: new me/konsolas/aac/cd
/*     */     //   61: dup
/*     */     //   62: aconst_null
/*     */     //   63: invokespecial <init> : (Lme/konsolas/aac/M;)V
/*     */     //   66: putstatic me/konsolas/aac/fd.d : Lme/konsolas/aac/m9;
/*     */     //   69: return
/*     */     // Line number table:
/*     */     //   Java source line number -> byte code offset
/*     */     //   #310	-> 34
/*     */     //   #9	-> 42
/*     */     //   #273	-> 58
/*     */   }
/*     */   
/*     */   public static void b(boolean paramBoolean) {
/*     */     i = paramBoolean;
/*     */   }
/*     */   
/*     */   public static boolean b() {
/*     */     return i;
/*     */   }
/*     */   
/*     */   public static boolean a() {
/*     */     boolean bool = b();
/*     */     try {
/*     */       if (!bool)
/*     */         return true; 
/*     */     } catch (IllegalArgumentException illegalArgumentException) {
/*     */       throw a(null);
/*     */     } 
/*     */     return false;
/*     */   }
/*     */   
/*     */   private static IllegalArgumentException a(IllegalArgumentException paramIllegalArgumentException) {
/*     */     return paramIllegalArgumentException;
/*     */   } }


/* Location:              C:\Users\BukkitBypass\Desktop\MatrixAC\AAC\AAC-spigot-5.2.0.jar!\me\konsolas\aac\fd.class
 * Java compiler version: 8 (52.0)
 * JD-Core Version:       1.1.3
 */