/*     */ package me.konsolas.aac;public final class fn { static final Comparator I; private static final Map k; public static final fn be; public static final fn az; public static final fn aq; public static final fn i; public static final fn L; public static final fn an; public static final fn E; public static final fn aS; public static final fn M; public static final fn V; public static final fn ai; public static final fn ax; public static final fn aj; public static final fn Z; public static final fn x; public static final fn af; public static final fn ah; public static final fn a4; public static final fn ba; public static final fn aR; public static final fn Y; public static final fn t; public static final fn aA; public static final fn ak; public static final fn X; public static final fn N; public static final fn aL; public static final fn w; public static final fn U; public static final fn ar; public static final fn W; public static final fn s; public static final fn y; public static final fn ao; public static final fn z; public static final fn g; public static final fn e; public static final fn A; public static final fn aw; public static final fn C; public static final fn ab;
/*     */   public static final fn S;
/*     */   public static final fn p;
/*     */   public static final fn aY;
/*     */   public static final fn aK;
/*     */   public static final fn at;
/*     */   public static final fn aZ;
/*     */   public static final fn am;
/*     */   public static final fn d;
/*     */   public static final fn r;
/*     */   public static final fn aN;
/*     */   public static final fn aV;
/*     */   public static final fn a3;
/*     */   public static final fn a1;
/*     */   public static final fn aC;
/*     */   public static final fn ad;
/*     */   public static final fn ae;
/*     */   public static final fn ac;
/*     */   public static final fn H;
/*     */   public static final fn aE;
/*     */   public static final fn n;
/*     */   
/*     */   private static fn a(long paramLong, String paramString, int paramInt) {
/*  24 */     paramLong = cb ^ paramLong; long l = paramLong ^ 0x7888ECC72906L; fn fn1 = new fn(l, paramString);
/*     */ 
/*     */ 
/*     */ 
/*     */ 
/*     */ 
/*     */ 
/*     */ 
/*     */ 
/*     */ 
/*     */ 
/*     */ 
/*     */ 
/*     */ 
/*     */ 
/*     */ 
/*     */ 
/*     */ 
/*     */ 
/*     */ 
/*     */ 
/*     */ 
/*     */ 
/*     */ 
/*     */ 
/*     */ 
/*     */ 
/*     */ 
/*     */ 
/*     */ 
/*     */ 
/*     */ 
/*     */ 
/*     */ 
/*     */ 
/*     */ 
/*     */ 
/*     */ 
/*     */ 
/*     */ 
/*     */ 
/*     */ 
/*     */ 
/*     */ 
/*     */ 
/*     */ 
/*     */ 
/*     */ 
/*     */ 
/*     */ 
/*     */ 
/*     */     
/*  76 */     k.put(paramString, fn1);
/*     */     return fn1;
/*     */   } public static final fn aM; public static final fn bd; public static final fn R; public static final fn ap; public static final fn a7; public static final fn a_; public static final fn aB; public static final fn m; public static final fn aJ; public static final fn u; public static final fn B; public static final fn b; public static final fn a5; public static final fn a6; public static final fn bg; public static final fn aX; public static final fn a0; public static final fn l; public static final fn ay; public static final fn J; public static final fn T; public static final fn al; public static final fn aF; public static final fn aD; public static final fn a8; public static final fn v; public static final fn aT; public static final fn aU; public static final fn o; public static final fn bb; public static final fn F; public static final fn aH; public static final fn j; public static final fn P; public static final fn a2; public static final fn a; public static final fn aO; public static final fn aa; public static final fn O; public static final fn Q; public static final fn aQ; public static final fn aI; public static final fn ag; public static final fn c; public static final fn bc; public static final fn q; public static final fn au; public static final fn as; public static final fn G; public static final fn av; public static final fn aW; public static final fn aP; public static final fn D; public static final fn K; public static final fn f; public static final fn aG; public static final fn h; public static final fn a9; final String bf; private static final long cb; private static final String[] db; private static final String[] eb; private static final Map fb;
/*     */   static List a(String[] paramArrayOfString, long paramLong) {
/*     */     // Byte code:
/*     */     //   0: getstatic me/konsolas/aac/fn.cb : J
/*     */     //   3: lload_1
/*     */     //   4: lxor
/*     */     //   5: lstore_1
/*     */     //   6: lload_1
/*     */     //   7: dup2
/*     */     //   8: ldc2_w 65453096555407
/*     */     //   11: lxor
/*     */     //   12: lstore_3
/*     */     //   13: pop2
/*     */     //   14: new java/util/ArrayList
/*     */     //   17: dup
/*     */     //   18: aload_0
/*     */     //   19: arraylength
/*     */     //   20: invokespecial <init> : (I)V
/*     */     //   23: astore #6
/*     */     //   25: ldc2_w -5911370199374713548
/*     */     //   28: lload_1
/*     */     //   29: <illegal opcode> w : (JJ)[Lme/konsolas/aac/aN;
/*     */     //   34: aload_0
/*     */     //   35: astore #7
/*     */     //   37: astore #5
/*     */     //   39: aload #7
/*     */     //   41: arraylength
/*     */     //   42: istore #8
/*     */     //   44: iconst_0
/*     */     //   45: istore #9
/*     */     //   47: iload #9
/*     */     //   49: iload #8
/*     */     //   51: if_icmpge -> 113
/*     */     //   54: aload #7
/*     */     //   56: iload #9
/*     */     //   58: aaload
/*     */     //   59: astore #10
/*     */     //   61: lload_1
/*     */     //   62: lconst_0
/*     */     //   63: lcmp
/*     */     //   64: ifle -> 89
/*     */     //   67: aload #6
/*     */     //   69: aload #5
/*     */     //   71: ifnonnull -> 118
/*     */     //   74: aload #10
/*     */     //   76: lload_3
/*     */     //   77: invokestatic a : (Ljava/lang/String;J)Lme/konsolas/aac/fn;
/*     */     //   80: invokeinterface add : (Ljava/lang/Object;)Z
/*     */     //   85: pop
/*     */     //   86: iinc #9, 1
/*     */     //   89: aload #5
/*     */     //   91: ifnull -> 47
/*     */     //   94: lload_1
/*     */     //   95: lconst_0
/*     */     //   96: lcmp
/*     */     //   97: ifle -> 61
/*     */     //   100: goto -> 113
/*     */     //   103: ldc2_w -6041008497938347131
/*     */     //   106: lload_1
/*     */     //   107: <illegal opcode> w : (Ljava/lang/NullPointerException;JJ)Ljava/lang/NullPointerException;
/*     */     //   112: athrow
/*     */     //   113: aload #6
/*     */     //   115: invokestatic unmodifiableList : (Ljava/util/List;)Ljava/util/List;
/*     */     //   118: areturn
/*     */     // Line number table:
/*     */     //   Java source line number -> byte code offset
/*     */     //   #58	-> 14
/*     */     //   #51	-> 34
/*     */     //   #39	-> 61
/*     */     //   #141	-> 86
/*     */     //   #48	-> 113
/*     */     // Exception table:
/*     */     //   from	to	target	type
/*     */     //   61	94	103	java/lang/NullPointerException
/*     */   }
/*     */   public static synchronized fn a(String paramString, long paramLong) {
/*     */     // Byte code:
/*     */     //   0: getstatic me/konsolas/aac/fn.cb : J
/*     */     //   3: lload_1
/*     */     //   4: lxor
/*     */     //   5: lstore_1
/*     */     //   6: lload_1
/*     */     //   7: dup2
/*     */     //   8: ldc2_w 15061426511254
/*     */     //   11: lxor
/*     */     //   12: lstore_3
/*     */     //   13: dup2
/*     */     //   14: ldc2_w 70688406191069
/*     */     //   17: lxor
/*     */     //   18: lstore #5
/*     */     //   20: pop2
/*     */     //   21: ldc2_w -7876841436971101587
/*     */     //   24: lload_1
/*     */     //   25: <illegal opcode> w : (JJ)[Lme/konsolas/aac/aN;
/*     */     //   30: getstatic me/konsolas/aac/fn.k : Ljava/util/Map;
/*     */     //   33: aload_0
/*     */     //   34: invokeinterface get : (Ljava/lang/Object;)Ljava/lang/Object;
/*     */     //   39: checkcast me/konsolas/aac/fn
/*     */     //   42: astore #8
/*     */     //   44: astore #7
/*     */     //   46: aload #8
/*     */     //   48: aload #7
/*     */     //   50: ifnonnull -> 136
/*     */     //   53: ifnonnull -> 134
/*     */     //   56: goto -> 69
/*     */     //   59: ldc2_w -7821828229534649124
/*     */     //   62: lload_1
/*     */     //   63: <illegal opcode> w : (Ljava/lang/NullPointerException;JJ)Ljava/lang/NullPointerException;
/*     */     //   68: athrow
/*     */     //   69: getstatic me/konsolas/aac/fn.k : Ljava/util/Map;
/*     */     //   72: aload_0
/*     */     //   73: lload #5
/*     */     //   75: invokestatic a : (Ljava/lang/String;J)Ljava/lang/String;
/*     */     //   78: invokeinterface get : (Ljava/lang/Object;)Ljava/lang/Object;
/*     */     //   83: checkcast me/konsolas/aac/fn
/*     */     //   86: astore #8
/*     */     //   88: aload #8
/*     */     //   90: aload #7
/*     */     //   92: ifnonnull -> 133
/*     */     //   95: ifnonnull -> 122
/*     */     //   98: goto -> 111
/*     */     //   101: ldc2_w -7821828229534649124
/*     */     //   104: lload_1
/*     */     //   105: <illegal opcode> w : (Ljava/lang/NullPointerException;JJ)Ljava/lang/NullPointerException;
/*     */     //   110: athrow
/*     */     //   111: new me/konsolas/aac/fn
/*     */     //   114: dup
/*     */     //   115: lload_3
/*     */     //   116: aload_0
/*     */     //   117: invokespecial <init> : (JLjava/lang/String;)V
/*     */     //   120: astore #8
/*     */     //   122: getstatic me/konsolas/aac/fn.k : Ljava/util/Map;
/*     */     //   125: aload_0
/*     */     //   126: aload #8
/*     */     //   128: invokeinterface put : (Ljava/lang/Object;Ljava/lang/Object;)Ljava/lang/Object;
/*     */     //   133: pop
/*     */     //   134: aload #8
/*     */     //   136: areturn
/*     */     // Line number table:
/*     */     //   Java source line number -> byte code offset
/*     */     //   #68	-> 30
/*     */     //   #2	-> 46
/*     */     //   #60	-> 69
/*     */     //   #125	-> 88
/*     */     //   #42	-> 111
/*     */     //   #41	-> 122
/*     */     //   #22	-> 134
/*     */     // Exception table:
/*     */     //   from	to	target	type
/*     */     //   46	56	59	java/lang/NullPointerException
/*     */     //   88	98	101	java/lang/NullPointerException
/*     */   }
/*     */   public String toString() {
/*  86 */     return this.bf;
/*     */   }
/*     */ 
/*     */ 
/*     */ 
/*     */ 
/*     */ 
/*     */ 
/*     */ 
/*     */ 
/*     */ 
/*     */   
/*     */   public String a() {
/*  99 */     return this.bf;
/*     */   }
/*     */ 
/*     */ 
/*     */ 
/*     */ 
/*     */ 
/*     */ 
/*     */ 
/*     */ 
/*     */   
/*     */   static {
/*     */     byte b1;
/*     */     long l1, l2;
/* 113 */     for (cb = nc.a(1203804521041363066L, 3287607162642033860L, MethodHandles.lookup().lookupClass()).a(209415434112810L), l1 = cb ^ 0x6BFD7D9A184DL, l2 = l1 ^ 0x619DAE3BBE96L, fb = new HashMap<>(13), "䧯磞뇲剧쎋츇귨⫯䈾潂왱퐙髻꣑佋ˀ璅䖰".toCharArray()[12] = (char)("䧯磞뇲剧쎋츇귨⫯䈾潂왱퐙髻꣑佋ˀ璅䖰".toCharArray()[12] ^ 0x5173), "Ϛ낡䉌".toCharArray()[0] = (char)("Ϛ낡䉌".toCharArray()[0] ^ 0x2142), (new byte[8])[0] = (byte)(int)(l1 >>> 56L), b1 = 1; b1 < 8; ) { (new byte[8])[b1] = (byte)(int)(l1 << b1 * 8 >>> 56L); b1++; }  Cipher cipher; (cipher = Cipher.getInstance(dP$dt.X("䧯磞뇲剧쎋츇귨⫯䈾潂왱퐙髻꣑佋ˀ璅䖰".toCharArray(), (short)23093, false, true))).init(2, SecretKeyFactory.getInstance(dP$dt.X("Ϛ낡䉌".toCharArray(), (short)6480, true, false)).generateSecret(new DESKeySpec(new byte[8])), new IvParameterSpec(new byte[8])); String[] arrayOfString = new String[123]; boolean bool = false; "门衫縼≡ꋨ㾭礒ሀ䭊忠썃䡢븍櫐ꦼ狲ί✋옅돼汿퓸粵逜擊蔒⦻ᬝ螇舞셵ⅆꅂ忂⼁ဉ渆㡦韎쨑䯛者䮼Ẏᵒ啕⋂ꇩ䨄徵ಃ挺媂廲愫鑷䭸퟊㐰⮚်凄쒂㬐ڥ졦싦徬圙?ﻟ⸏䄂芚쟑淈঩ᩢ保̓閖銨門起뚄뭂㎷脀멗⛊뿖Ԋ虶俜奷춁廴䖴块譨唣퇪봭콚䄋╡壢栒缼醵斝ሌ谶抄⅟궡㗆珏㩹븮뭃튍猊岘言땶㭚陃ᛑ怣쬸仲먋球⇡햘㣿䉼쑭拓彜텵䂤ڝ盺ᅠ瑸Ꮭ?겸ᯋ횡욕琟䏵艨➉巃ᗓ僰炦ꌯ尳೵ꦯၧ്渻픨♠鱯쪭唥塍䅓ꆞ㈙젡샰ⴉ㟡堲축?ệ?쩛帲潵䋶欈镹诈猇ꉬ궥띈啸➎썛?꿀ﰶ뇏닞淽鋪ᢒ㢎룛䍖쑛ᓵ鮓긤๮䗄냋ꆊ뮡?ꫦ椣镐鼭㫽؄陚῟폼훃讶퀔ℝ⒦쮺?밡ᶷ笈䌜⛒悊葈墅芯䟍쟥㚽鯙䙄⨒?놎㼠௽왔큐ᘷ鈧笇묹띰ᯞ㮏ꭻ小䈖꣍嘇늉Ḑꃫ쓲த?盈밲練㵶怔㽬犝ꖇ㭅鐵䴃ᭅ⇥劂휃塰鿰럪뱤黚㲞頂ឩ뒓⶧๝ࡈ빚轶썵뚙䲊ޣ䨮☌ᠩ䷶췥쨜??欛蠨䰂쟜쐀⡌쉶痼횻鈦꯰ㇼ⸂쏿솄쥶Ꮷ䷧覼켦죃窍䎳嶉ؿ㔌Ꮵ찴『䯳疤藔嗞괄ﹳ䈡㫢䌢在븭렟ĩ᜔ᚆ審ᕆ탪蛶뮑맧蚄ഺ䁷恄瞝䉚롪ꤢѵQ롱譁ܻછｏ㝯ඏ琨礲䭝陖錉எꀳ퐛郮膀ክ뛨쨂剫䵹ឍ⎈质㋽\001䀾铁뷢㯔麉镏ᜋ☔উ흵뒒뺭Ƿ⿰⬧ࢇꋦ剒貨ꜭ嶙渠坸닅鑹퇖ༀᘍ斍슼곉즤㽲餐舚ડƔ泝괟᫹柍匆恞蓷敨垬⮩?謩䇇﬈葢韰挴鼆㌭睨럲䜟ꅴ李䋻ᒈꡅ㗭᧼造屣瀔??穗溫ⷵ箑撓?鬨헻̩ਅ᳝鉋?쏬䷚嫷峍䰏诛܇羾㰲텦킪᭬埍䒍?挡?䗶㑀⻠᚟甊襻僛㔶忏圄藉毶瘂ⴖ橣㘪넵꯺膙䱏뚩죟ꃸⴁ幥㬜믋太䭤磄莈濽Д鎶帀ѓ༢ᗖᳲஒ蜀?왟흛擊ꎉ?貜멂ꤼ杵䏱习閰葨ꨋꖵ썞ฉ穌鲊훡꺅셠抶ਗ휨悜쩴巷铀詁ਾḌ铷랬ఝꕍ屭ꉴ읖댉剀쌫䠃薻慻ﰶ떊뮆傟顩㭬쪭醏ꣽ茧굟몗팋扐␚勉⸿戔⽨篪邏ᯂ뀶䴏⥸픕벣燠袋خ鈾뀁溥䛔턛Ǥ觙將〫௟켣檺ಉל얮퐰ೄ驻㻹冋ᏻꃁ㷩㾭曃誾䨐덝鍉⹆錴薁薍峿햍굹罆┏썢鐔ꞑ䋶觮ꭝꭊ판㐪〤䰘?떅䃃穯㵳꥓蒏吋藥읮努巟濭喆ᅫ뇥?吅角둠ᆒﶓ틄हﰟ魅㫌괖틚Ű邍밶㓜㮓뾙㲄䔤魞䞥겋殝㲹쟥믞⤖瀇罩㍡뇲¡儜䲘晴夰虉衯撡ֶᮧ銋嚝ೆ⁲黭뷝?귱䷩鬵慶ᱵ紿䳖㸹Ꞽ렇ꖣ?찬溠ᘮ향墸荧ޢ⊪춟䑹ਐ칵૴䴤閤熅౸?▝滾쾥緀駀隇㊭ℿ爱蘽椡鯟혉媚뒍?ଌ羰⽅蹭㇭ꡉ葆蓂␜∐就䆠⍗ᄺꈓ襄胣䵼꟞្??སｯ깝묄⛫肰뵦꿢ﰯ䜬穸뵳ꮑꇭ녧䉓㼂썜咐?㊸轤㍑䃁Ὕᘓ뼘턾耣羨͢爷৙棐瞰旵ᓶ螧剻맵䶂ꎠ믒⼥뢩쯈䬙꡸냊瓏嘂眜꾣ो冷諻ﮨ3棖ⱖȧ李?༸壐쎾웵쁝㴎資᎔⥇谇臿㻠耏䜗Αꫮ쯯貥鳡?쁩ꙇ᪄姂貘ﴚ〦騈ㅐ瓌羏釱㈂⑒䁤ྎ犘嵈䨡뀼奣ꑇଌཀ껽븃쌂搜ꝧ㘾ㆹ?揦쑩㞂롫㙠犢ꔿ幃컷䙈泂䷯혲狮腖녕檋穞먡⮈푣킹썽탙?ἢ웙젰﩯驼츀퍣넧⣈?쯝䱙䇘?ᕄ?꧌ᅞ䆙貿벦䃪韍쵬冹냧聤렞ﳷ拁॥㔤络棁䅢끹劍ꌾ⸸ꚗ₊?숳瘾穊唹㮺頻恰䌮栀浚馁媴当悆맓?䒎鏉⭉䦴촤棰ꈅ泥깶뇼毢̋龣⛲鄰鲀創ᙃ࿡溋낥㖊⾕饧즀닿⁬摘覍ꜯ⣧㩕籞脂鯌Ωﺩ意½题䉣㲰넙쬣馩˛ﯓ萲埦ꃽ흉梭犹ݗ奢랲굌凬轒却螭燓鹼枼枰馶팻샫頋?ْ筰散⠪೴㋛酷Ⓦ퉌왑冘䛖짡ﶢ텻?詚Ằ⊒ⱱ䴶葀⭣⃿챬㆟簳䆿4猤䠋ꐖ뤏뱰圗ᤩ水ᾟ濿∻왐㌑㽵ᷞ茆讯◲설⍥଎藗რ傷逵␯鲶鐅ꮄ艜﻿㟽Ẽ赒貳੘訑⮟횖ᗜ⪱ڇ쥷솢꾍쪯삦න⤖搐୪䲏䀑ퟑ뎷徂澂ꢪ箷毝劕庘?릻谞抜侞厸黃⺫ᴺﵑ⫳헯ⶰﺜ庈졆햳漭⋎耘렰푣ቄ䦡뮂䐙Ȝ뉠ǧ垖崐퍤훽ꌝ⇟벀霯萋习檫⪑ѩźꈨ࿁帏狳ᣚᯋ㶦塍柠륅쀕ꘕ萈р蘡龯䂧굿ᕀ眛뱷ᆶ╙챝谈か࣐?䣔茆䝬왩䪬쎡㈤㌯䞘﹋⅄꿦衍꠆?ᡓవ⓪梪崥ⶢ싎热⑍鉌未ٕ嬮㼺ᝂ炕馪◪闖筠ꍪ鶼쮒陒暞?瀙?⤖೫逧ை꟬ժ倭뿉䂢躵楀㗷죬瘓쇰엢赮博յ븝辫㜴썤ꎐ垞ะ࿼淯浘겺쯛㼼诜吏巨쎉믊鸷鶿訄紃ྛ㟆솼แڂ洀౯Қꕉᛅ韀ʙ萏?毛?옠쩇Ὄ颤檔㽈茿轓胇뎰⨏ꕤ떚困퓉ଘ穽慎૛鹌롓꼤歘졟ꖬ頇膇ꙗ봕撝뗦ઑⰥ㲹횼ꪄꈏᬌ蛩좷햅턃ኬ夳亳덯㤫ઌꕟ斾诈ꅣ橔哔곪沱ᓊ͢??欦㆚ŷ༆❇퐖ꟍ?殡뤵襾ㅴ夔퇝㬙❧鉄팾鮈ᗦ鋞簻쌖涖狇卮ﱇ鈷ᑍ晸뚝⚴豁㡉䤚߷?ᆊ趰瘻੗肜鉁醷鬼깘ﱌ姕Ὶ?䘏Ӭ郴騗䯻⿩녝ﴱꈃ᭗劇?哣鍙꫁䅫ؼ?⌜Ꟈ嵲ꂒ椫줉룦믎誕㯸뿉ꊼ煍?ķ쑍ሷ⑂얖挷⦨˶Ꮲ봺ᚢㇳ⣹ꯟ☊筞쯌ᘸ渽⠸ꓣ卹ඎඉ飩粌幹唢띆隹噉?쉔᛫늼㧫꟮퀊芎歁넝㒢?誢뺞㼔翎乙䁻?⌑鿛뎪镂矯?컥蒣兤撤ᭋ쌟沩?麹ᕣ歶䫳۟㛶รᤀᝅﴛ쵩᩻ᘾೂ驒丱㌋?쬉ﰱ瀨ᒐ믎刭岲䡒辭녙좫빩㬕涛㈬呒局徏毵➵모峯㡙厦礲娷칲ﳫ⑗閊泚鋘婏鳑댣鍎᝽馣གﭥ헇ᯙ瘫҆䍾蟄椄詌䤺䂂릃硐譸꽳M㸔뗷魆᥃줃皌?끵疤퐺Ⲭ僷兖丝ၒ笯坎箿衺熅䐕尗䙂䢥싑඙ంᗅתּㆯỊ梨恫昤灣ꐒ?傈洪䗒ჱᆝ杰蚡௡˳늰缘揖垖휗⡖덁⩭᝵䬦빝枆ឣ擘፶὆ˑ䭆䎥껄赣墽镙ಭ克闱ᗰ㹮寞桬ଯỡ㍖୼ꠊ쐁躏硫猶姽䮩斊Ǥ찂旰凷፱熝汽뚊靾ᑐ泡脿㙕볔姂䣳慳ꏠ罼䛌懐鮰⍡㆔䗂?漘勽姹⣴煫ಈ⽤䷕兕ꥀ딈୻㊅៮灉౎ꁼ橉蘚伖귏?䖈⠠㼙ٌ仉栣⎍⿏臀＇㏸ϣ浇뇮∨劥恡텟甹䴘効仢퉛઒塮♕ዷ칝첿犵㜑品栋菚냭쉶ㅿ뽳䀺쮫ᾖ㯰ఛ깜럶꾛뢇ౡ蜎賅덱ଟং䫉蓤䀞혔꾲㒖쎬⪦면앖ʄ짍ᕫ뵨첌ꎼ؉ꊀ摕橷⽺긭䔰?⮈ꭹ묎兾ㄩ衶(婤漱ꛇ㙤㡗庳輣⒃涳泭⚌컽먤心Ỵꄳ뻼靈?鹰ሒ牢勑䊞怆뾸﵏࢕݄☩ᢝ巓蟑佽鑨菹✈飿豹噃Ὸ?熀꘯㚜֚㻸瀚텟腜냈䰕믢凅儠눒淣缺ჴꂽ푑쑴䌫ѯ릞ࣙ㥄空⦧갰份?䉚욣ߨ꟮뒑㺒蠅谗耼추钱闈᫨ꌥꤦ횫冷놊厡鑎뾪㽃ՀϾ⣶䋒납꠶勉훮ꟑ䎚餡忭砻辀埤?⡍ṯ䗻歜诚茻ᄱ蚋ｂꔝ䙞賚嘦눿哯酊?뇴㞢掲퇜쑝ᱺ⽀轈ნ⤹ᘬㆼ?샷朖鲐썉ꓽ쎧꨾䓖鎟浒䮭גͷ力猙ⴋꄬ⭍䕬进쀍㔌曓騗ָఌ吸铠쀔꩜阙텻㱸ⴚ?Ｎൄ腜ᤀ?漧ⷣ㘵⠫ꋤוּ徲輛Ῠ퍮藴꫺᭢䘎⽨쓡䉜㏟늆ꖨ뱄㦱⃻杍族锦꒾廥ꉁ│䶖෣?鹣幠ꯄ耟洌攺悔澏鎸㏕Ⓩ봙Ⴗ᳙䵬貾侪煙睱奴≳칦糯ଡഐ葀ﰋ᷋灥錡缏밓흋凮⼜䏹䢆?䶒꺔璩뛖ﳓꉢ똖㍰젫୛?₲蝛惤馃悠憕죡?㡛ጾ嶊嗴?韲凥櫽⃲㔅物鴅甎쬾䅃犷㠪蠫ἹՉ뺜㋨ஓ☠ﳶ륫䑯陠枻颎餵걞ꎵ뗆І킑築돱鈻ᯓ汫왏ⶱ梫퉕曆菪忠ଈ鍩㜱릾㤘ᅷㇽ걣럷㥌㉋⇙퇌겧鼌칏㭾篾탵⫆氄줰౏?諅䲁?◤⵬푹ᨾ᳴₮㦒ి关룴툩ࢱ设鍟꿸嵬炯?ᢳꡨ旟ꇚ灠⓯豐놁睗ꤠ㗗ඉ觔䔡坿ꇑ콤쒰ః鳱⣬㞊짚£墔耩뵞葁렟ꅭ㫹ᩆ鏽䙽῁ﱙ焜酖숋廃ﾐ溽果擕ꄷ㔬쏡索覆紂浼⸊勍᝟㰳孧蚢䶩顧驤맞쀅矊郬ᕼȰ蠇ㅬ硾锂㗎晈珌쭬鼇?祇䤃憛櫆㬆䠴撚账댅ꚢ?ᒘ僂連皽?崣샚枯䀞걲쳫堋퀿懷ៃ刻?낷渐ヺ䒯뉱㋍覮밷䎀㳸朄᳏昑?ʨ熈克ⷱ⃖蓉葄碓儦韋丒ﳎʏ涝呪댑譝ﺹ햌攻耝擧?삻㋞㷴櫙錰犉똏呫犼橧﹥銧㏊ঈ肌䡐찥✋륜웜俩싳漶㦿ﱕ폊ശ덈嬁큰?ﻬ䤶䧞煉⦺˧弾뉜㪌隆ᆇ뉤腨袄釱㽉쁵ꗻ࿤귧䣺⶜?逹欂ˉ⮅㒐嫇岔⌠⿊ᔵ᪶唑ඇᨱ譯胄䒴䵝⑵햽겯肏뺑髮欎ᡨ牔?忞졙䔠묢眅嬲⒪௓擠⃲뫯⁙㷚⸥먊憨ൕ済谼뻽쓠䃶뤝獵⪹Ϋ뚐骿朐㾟爷뛘⭒鮏婝쵣衠ลᛃ掤ࠏ繓似缤⊠섙ⅅ驯歹繕䗼俜핾৶꒻ꄳ榪㒩꬘馣໼㴨ᮛㅌꊾ躷숂?ᷜ딺㎁떫?淡閆Ⓒ૆䳠힭籇ኻ䋘멝짅芕⋷嗤⠂櫆틔ꞌ胴툜⏅舥䮈Ѷ뜫՜ﾔ䂑瑋樺坹ۋ욨툶宭朞舎炙푨崅⒌퍖᚝逧꥗冀⋼渌჉茨얔답霴㱉Ⴧ屣磞㌀ᢰ⭣떓ᴕụ就ᆅէ빏葺ﷺ꾙쑆콎矀?롔뭪ͱ皒簺䬊帥圮덃䮨쐷篼䜔⿔뙅꾬뽆ੂ쟱㶤魩Ն쒨屗竦↽횠츈殛薬泩噚粓⊁ꌬ܁챻澩㉔倫绍쇫⨉珞尶㿎崪쁛᠄婹Ⱂꀬے〘쀐ꕈ?衅⯍偼㯵햽ଋ⻿﵀ჰ魊隶瓻≊휳웘ᚠ啲뙷罗䃓쉾ル杺쯑덢俅謈?Ⴥఱ欜縳圆ұᢕ䊨?寮㫶⪈꛷ꡜ?顓驘䳘諚켺஧뵵蜎♧㲝甛ᙗ앬?ꐞᆗ䐃랴얗蚛쨠삥䜡쨬Ⓢ﾿艵錛㍩಍司䛦ᗋ⎁䕽횫㬖퐭矲臞澿簾㨊鹭掬㸼퓊䯦㛂늦蟓늳ⷡ簊﫧ⷿ䔽퉌䜈㉈푕䉍㙠会ꋐ锵愧쮇ಸ鵠谢怾臡絘䑅訹菗ͯ朵㈛ⵚ?᭴厉沬ꍓ눈䅐슇㷷퇣ퟑ鉃⛙ᗼ䙂呐孑쇌ष皕䚦잸跛呙紟Ꭺ჊翿暅☎⪭궲녉䤏搀凿>뛵쪧럀竨든쥪甊쉤赓猨颣踒䈬덭쟳?Ԗ￣뮹鞚䑿?䄓⡱⠳켟捴럢ﳃ⭫鶴ꇜ൉䆴?愹뉘㿬?ᵍ橮숮벝꒠䖞樆?ấ堞똉䐦?妡敒칲妦謩ᛕ雛髛緤᝞訌捓Ȓᅄ며ᅻ辋汎晰큘鬱搒蓴빡㽻녮耭跘캩꒜쫝缵墢彸鍆ㅈ꼸讀ꏂ허沲랰ौޮᢖ體兑噤芃ᜨ릠誶݌敒ꦴᗔᢘ龞㳌定侌繀꾴᷒榊䰅䛅얚쩀?ᑆ꒷儕栆묻﹋쌇俽딙ꗏ䟜श︖먺킙럎ꎨᛑ˲⾻齾?ᡇ앎䦧촜略癉ᅄ씃⧰漙䳥瘬僛鴲㙫➬웟ጩ᤬ｑꕞ஝䑼くᄺ⇜?줣对阚?뻊퉩㡂Ⓣ竈沞湳숍巿Ƿឈ齗硇爹ⶠ쳎Ჶꌏ釉욾⢜ꖜᾥ糪隤밐쌵ᇧ⳾ۢ卲㝵婛䔫䠥᪑舅ೇ喎橲疺膌捰샱?잰㌃蘟物遜듎␃恲㐙濉䯺¤嘜蕞߮缒뽐乜⌑딜㵖Ƹ诸r줉虔䇾㎉膠쑪뚜ꬰ춟侮襔뉐&㕼躜襟㍟ꠤ✴哰ʩ旪亚蠆茘?฿჋ڻ㊹ᄻ枆䍭ᗡ霧女覭꒞뚠ꪑ㽔깊冐踪義뭰꜇㪁剭祙﫫쵛뗷㾕Է䘡䡻饻踉＠륆꺨魛趬ྙ殯챱ꊢ幷丁⧅⻖뻲튤奲갰殁め䃰晄䩥獾起ꋢ䕀㥯邉빗七늂㥻妩⎃썥닆鿳箘㠚愦㒦虲臭뫷㠷発욽勈骦⃀殎ﭓ犾Ẅ쟄괼셋↳캌瓽ᨅ繺ﴂ摗劚뤨툜䳸歏ﾩ뗓亖农䊍ಫሙ灇儤昢⋹灵⧡磆䄘栙堝⽶䫐翖?≻歧╙䢊릟잖聡멈轛䘢퍩㬰坸韒臣眜컭暼䋑৛甶霒➂耀넏ᕢ鎦嶅䍱骄隬᏾煺࿈묹ឤ㖡皃増랥έ鲉׮헄鈭㡡웧蕬蟘߿㨃蜔纅뮫踴ꏙḿ蠽뉘﹈㋆ꔛ참훲醊?꫚??麋雎淙敆ﭮ房钃槩ដ毣摿?淪舢ﻤ죋᭝佌뼈첹ໂ㭶삂뤿铡ꦀⰱ薦趏??濉唑姣⾋筀쩬פּ㈇ְ㦬둅毞࿊鐆㶋頵ᆙՐ쭐灯쭫峂鴫郝ꅆᜌ?꯶㜚얺뻌Ꮡ껜徔창烅ᯩ隽갮莡ྡ덴?헚杤ᮗ䩧⾑홹鲪贕겭뽒䃪⍗鬩⣐銩履ꍺኒ䌏씲먷뤷䧳嘧䀸㯞＇?Šꞌ쐱뽸?ꊤ沋磌弃ﵫ뷟罣藦壟썵ₑ圷॔癘㚄╞뿘婳뇽땬㝲爀ﾫ槰ీ鈑ꊡ嫄㽧ḥ巉杄했橜죓ꦚ?౽ᗔힾ禭顪妴ᘽ嗚ᔗ㞠ꗹ൳㒛ꃭ戠鍡쾙뎻匍牎瀇댡鵍ጥㄴ鳗䘮ӵ쮙餶阚䴍퀐᥶䥧矦猃ࠜﶶꅁͦ⵺Ḫ᫣ﾀ춛3ꜝ嚲༠䴲?膲ꦐ㻕鷿ﴃ݆봺㦲Ǡ췮䇅笁炯쿡됲꠸白㱦珔ꠡ덬?᫫꿼֙뺵䒙寂覎媸?㑶뿆?쀡ŝᩞ玁禶낃퀷ठ멵葌箯뱭⳪쭂환ࠀꌗ값剪垛㹨ᷴ䓄ꌆ䛜踟♠ᘥ㺵྆ꎈꚬ鱯味峊◮釁櫟썙蠜＃㍧ꖑꡂ榫롄엗㊓ᆔᨂ뤃蟡癞녲斵峵ළ弨柗煐眦䈣䖥⾈撷㿭ᛈ늨ֽ鈂벗䇫苮ㇷ套ꛙ嫞썩㈇佝㨗ﲔ௔箺頇⧏Ჾꡘ뤱륳䄍?巬葶चउ猣ゅ炤篂᧫࢓갺量K윧돾?ꁯ耳ꗅ䘭⎺䱿嫸䂡顃㱟ꙋ븣皭ᰔᩩ䇍䪶橺럝᡻?ᩌ⿊薧笄䪂殁둄ү᧗棏幮ϧ闂?鶑膵㇯ఉ敝ጊﳪ켯ഹﴯ懦殗ᄔ頫㴛ﯧሣ횡쵱㷂ꄱϮ賄轆ꎕ쵃㴤햒ꄗ澚ဢઋ鶭䃪믪郟ᇜ᷒ଙ鰎墉쁏ꤑऀ㿒됭鋔絾ꂩ⸐鴙⩡鶅㏔ﭰ悉≎뎚侪颒怒뜣ʌ蟃㏵赒?跚칫䈲ꐓ쯼쐼䬰ݑ睦邓꺀蕭⚩祿黟뜣ᕷ棴颩伄襲ী셆⢛툘ꥋ쐜㧢昅ᰫꏫ幁긄爋忚㕭멲攜㚡⑲讑턚㞸ꋆ叙脷炎쬵畳㲁Ꮏ촊塞펈ޠ㓷媠ᅊ㪪昬骑䗂?䉖琫⏚漒„見쨇なꫧ؏쪔廧㻲㕯깉⟆囊掙Ｌ灒銳䇲楑ᡜꡪ웆슖਒籪좎ﶞꈕ⋇઀飪␰洞凞刴鹪䣭듛Ⱞ詭鳁㠦鹙ֈ吗꣡춂動즉苜䣢ꊗ䥞쥅쌵踽ﵸ༵で鸴⋯鴳뜏㤏⿖蓌鏷ꐻﴆ✑碊쩹㳅巄絢퓐駠쬋海ꅗꂋ曩쾤춄ᙯ唜ẹ攗鎽좙ᴇ㋁ΰ㼎噦乼?纋쥃⃕㖂㗿ﯷh説刏릎釮䃘银왿좃쬒蝖⫋鶑෦눏冡㇃풵䲫ﳣᠬ쾋塚᭺⡝ॻ䝸꿘㖝⤤異⥈ᐅ╈㈼᪲Ꮄ儐㨞영′궉㾣쑔歚㷛뻹ꀟ킜짅ꩃ㯇젞뽔↬犪見ꖦḩ峺๕蔲?᝶慲ꏌ㋝㽘ኣꞼ혩蟀狜썁靉鳄褿㜓嘹亍繪胉ᦀꡛ裀ก঳冾⺑េ?茮ᡶㆪ砓٘⇢⯃졊簐嶕쓚૙ਰ獟⣋⺔Ⱈꪎセ쫽?ꬖҲ樹﵂ἄ謡俌긆⻁爿䂫委탄Ꜫ쉆︳⍣㑝䳃훼툗춥᡹ᡸ偿짳疉ꢜ蘌㤼ｯ?싑錬繋咥罛ᕏ욎産￑䭊굙궳ஈ隖⭦ꌨ폃顧ᰀ䖼鞩넁롊䉭͆‗圛轭푯￁건⽘쑵䇓鍌?읾˺顐濋㪎䏴⼵災ⰸᐥ锽寳Ῐ矸㞋껜솓鍛蕂闑㠝ᖷ㣸ύ檷홴἟㱛뙔ꀫ❝ࣨፂ随?ꦀ붱ꠢﳍꐲ〦䎜痌⚐Ԅ㵄ݚ镐⁶颭塦剘㎢繄?롻㦷䈢矴㤄釤⍪랞륽淽㺎䗩᠇嫉௼䓶⯙啤쓕颽曆᫧꟮╇欙␑代窢뙋奥啣㗛⣞簷̲琑㳰蓪֖㕱揾?눌ⅼ♊ꓔ켫愉໅﷦㥙?蓩딸蕇順閜ၲ렫鉾曟⒵姰汑홫?呝᯿闺컒㜞푭朤㐜ﵼ?驊ἓƃ츱න鸽첸げ텸㼢쫑鸨僦㤣⁭⑄⸰퉔싳ꆺ쾖젔⦭៹䌭璼喀빋䌃⌶砙렯?霕㠫鰌粧脼깩䭼햢?吚傳셑熸㜗⠱诫⏁೓䳟姂頮Ŏ꜋ꭥ꼥ᕳ?⹇䐲쓆㬩泠鿊᧚뢶媹ꨠ賉㛽摨鹛뛍锎๭॰䧳䰪껥鐟법﹣㡎晍ꂈƫ釹?섍ý窸ᶌȵ淶츝댷⹭咺ꝡ藟뜧暯?㖌?ඛₜ廂?銕ᙏ뫂喢ᜋ卦울䙇跺붶௖굴ꈀ韏╌㺋ᵺ功㿙虼ᓯ??Ⰼ飤䥱?ᆜሰ⻘䉇绥౤䉸蛗?둒앋㵏㯗䭤폕᳒藹㺸Ț⚼᷍ꊅ覎뫴ꢹ帷鷇퐋Ἕ괍؆逸씷伕鴇⽈ᮼ컸沲ꇂ袐๾浣?鴯㍂ힹ㋭赝敟徽積掍ꨨ턇䫅泒懲ꕰ⅍趃?Ⴚ蠂︅섞צង袿冣慲辪놭ᡕ꽅㢹孾꽄췾䉕埠풀ㄡ땙Ν쫀渢娐ᘡܙꬂ࣐㳧桖乀ꇚ?㷰鄛셉㳎ഽ䳣㧰酢ᓆ촤躲軥?縄ꄗ㕟⅀듴䙈늂Ďઆ驏흲ረ㽁ꉂ뾩⅐䉮ᔏ씆㒦濹䤝㦒㩬鼭♋☎췬ḩ窑׿흎쳾놫ꉢ㊗碥藙㜛좌ᗑ㜃⼫ﲈ쵾ꍼၬ큸⌶蘏ഇ繊廣䕵쥿꾧Ϩ㮚娽휠ⱌ쉈䏇눭黧쯾౤솇訩ﰷ糙ݏⅺ햃羭蓺蛟黩鲂⊇?潀犪啑팜⿴䷵䖮痲썙⮋ⅶ紲벖뇙诗⤮ⰾ羠玚䟙爀欪俔Ⱅ䀰폨炅飒ᘜ䒜敌鹒딐ฉ奔䫺ꪉ㒥䠅攁ⲙᘨ၁뼣⁽?뇞Ⰳ镭鶔㙏롳⣩뤂埂ፘ需勽嶸⿷醆▚↖ꏝ갲᥻뛽揂躵㰢褵帬䍅槼ԍ埸쀂狥้뒲쁬쮳笑尬㯪敳톗榺х̀Ḑㆺ〥咲?锧ꔼ칵찢◭?붖肥ﴯ㛊䓣퉌䡸ꀏ崍遚얐Ꞷጻ꫖螙꼞꺔푆⓳ﮎ᦭ଲᙃ࿹줋?တ进❴䟆ꤲ趒켋ᣇ冾罫崵륆襠ů㶒鑨ൟꇾ淲⺂洴ె鹶뿙꿒褱｣稧朿弭퐌⃆귔ꃻឫ魮ɕ瑒ඎ↞截བྷ⒂먷氄༅ᆼヅ矾홒둼醔䦁荤⨴文怺偕▇໺䈠툱ở眏賔絓禝瘡ᖰᢢ컩흴ђ쾠럈⏍漙ﶺ牫?迅Ǡ觹ΐ飪?劢盢藥笼Ă嘟૎䝿䜃능윎礃瞊뱤䟕䰙밅૞㪢靖픲勈?圣繭읚꼴劽搎﨎Ԗ鞩?탵秣컎컱펣ॄﳚ饰뀟䔋爘Ს륫箟뇞羨툇챁딙󖨻ⓔ䧸㍮ƃ⹾핪?䁝扃䔧⧉鮯虨ꖧ⋽풸쟪盕畚僿儎禥疥䍩獁䩺더㾝Რﾸ䎣ꠜ뤤絻㑲ᴗ垛屍동㶽遼䔭저紪?㙘?葃윭⾼࿹ᖜ㚻架Ἠ㫑⣻烶㋖ၑ鄊㐪곐还?힫眞粷晸劄촜䰈먥Ქ齻뱕벧該﹖껴ਟ丵짘䟄ྕ羏㊊柖צּꀼ贕诜䈌⤜??㵎㒿獰㞂铡씒?┚ၦ⺞鵔햎㡢∿泖挣ᬔ痧ᘬ謎ஒⅡ࣌Ӥ檚ᖄ笢?끉头閿ꥻ꟩넍쉤㖍ⷄ㱣摃靜柼ಗ秝飽塇⇂鋥‴臻薅ꗥࣶ짯Ҕ惎㺻ؗ蝝늱㬱ໞ庬梳蚔ᢖ䳝㬗㨖ヷﴄ灖퍓鬘鯪ᵓ?활ࠖ훌빜⾾䉧瀘盧⃒ꪆ먀ࢫ꺜⻑紫쳿︫陂䉏源흚煮ഡꁇ旳瑇彮幖돛ɼ傟泩쭡㹈돜​걯ꎘ晐褃縲௒ᚐᮽ㗟䓳ﬦڥ彥굄ꦃ쨃呲ᡒ辉뤓诱喀땱禘蚤ㄿ纈ὦౌ猆䷊헿᧚費葷⟌ᤑ烓▘໴祌嚍ᑅ줠꿛웜㐼媳ꌗྥ趰捴ǧŨ໦傰搾뮙﨡䓹腚?殮ڳ䵣璀屦畈쒶䛹䵾䵒蠱韟㗙鞲?⨸䭽坮蘋챁ҋ뮉 ♔ݯݺ핓ᶔᦞ봇䓂룩㡿皑ꌀ皜㣆뭉骑鴉ꗜ鿯떷㘌촉㔆ɔ쎐洐顏吱?坓⼩₺攔팁ؽ䱀금⃂ந଎ㅨᓳꓙ횾캄ᙧ㤟ｲ⾢㶜棿앗틚䏥鶦?ت䴙Ҽ탫슸偫侫㓃ј㰊⏔研椶ᫎ⦦由ɪట裊敖垬ِ䲓⟙溲ӳ轓Ṝ㜫룚₺⥪䣾템?␲뎩蛊⣰欀즤䉏㘆孑ᴂ뛰வݲ톑悦瘭밷腪?볐푞乎煆鬬ﴥ䋢泝┌陵곒⡑螹繖뱷ⲽ⽾ᅧん䶋迵囹㭍큓㭿囀衆◄睟揿栩脋ῦ⡏릖沺䚦䒾䁞ꩦ蠞嵌Ř刵⇄㋏荎畏샏㩁汞ﱶ㠹䇲油잣䕈⪫ೀⱰ鞾䇭䙸Დ㗟膦嚶嬻酰䒓茞띧঄ă沚狩縱᧠멯ꔒ?⿩꺟㱘⮀閝纏鞕ᵝ蝑헎郪暖䃓嘊鬪쩎쯬邠뾺緽轷뱪꽄愢⛘齪鐚ᇶ燐雑쩯칍−෺㰝뤛拌红䗸㖩㑯岥堔鵙咥Ɲ퍫蘗?멀磲锭隣㢼붮飗㿝⚈掿祦??橒?ꤡ㧄ꆛ賢㔘㨑밽囱㣗췿뭒釅啮걷莊歬┸ῼ貮腨໐ᙸዮ輡묉ᨅ㱆櫖锗ퟭ╲売렺♇ಒ良鱬㧊?ꀭ玕㔲⿿?섗䦂ଦ睰㐑掳꺄걥鬟㐈Թ韢঒朤⎷鼻췀Ꝝ贖䙾풲啱퀜쪚ꢻ㗭䆷㜂鲁钤►?檣맯令왾汗폒볝ᲆ趿踯猶?⼌롿蛻冔棼뎤⦫ㇱૉ堬㙦堬鸇聫Ð⣽㽔ᭋ최兽斡?싓䒲銇ෘ迖굞鉭㗓躻실᧌噵㲁镢쭵∫骵疦㪡體걅貸톆曏액軎깉漖蓄ग़⑧ੈ∁朷힮⥋ꇬꩨ庲൪醰늅䬨욈攔퐕䄺瓭䶰ㄴ頹綢禲球ᴣᦩ鐭飩薽摋ꨂ㧖ಶ駢Ṧ噳㌼ㅬᰉ⺡ａ⦇≒缸븧᡿ᦡ蹕യᧃ申썵쾏á䡝촫ᲅ䄭邍౵锈傳꣊ـ촶㋓쀶咯칝ꗤ刄䭋ᓮ䏢嵈풮摶슇ꢾ﹄尵갩覶챐̞㺑팏Ꮅ鑡眢摍ﴡ檜㻺㫱媔秥꟟?㐘씠쩕壅ᙦৈሲ﯊繛夳꓇藋쀙צ撈罌⾷ຏ郋粵䂙ኈ꫞띔橳딎훡ᰛ沰뭼떆❍䍗毳䫔䎸뺒ꤌꋮ艖檻≘쐿?⨖簐ᯈ焚⬞ﯘハ੔܂蓪阉찵ઑ퀮ي㈎➢䤘ာ덝ᬧ瑾梜ꪺ춘Ѣꗋ욟ꖩ戰憏⑶淘谴጑㄰⹬ᗭ溘눔썋襁ﷺ㫿ᣵ⳦߮ἵ⚩竚Ǵ䗓ᯏ鑺鉅䲓䧮䉸岭⪑哗?铻喾㡣룺켬節봣豿㇨毴ᤠだ淃앶䋽譮ອ꣩퀰招አ雐ᅄ⍏쾲틀ତ渉?⧅㻃壏ㆦȑ寡ත慕죱?梦́蚌䅧窡篑뽝睉騮וֹ妆쫙?고䊼匶藧⵫刖覌૭⪻鿟䫮嘰싵뼬ꨘ蜕ᬆ꛳䮖▷뭕둔遚ᶪ캸猣൉Ƽ鍤Ĩ䬫浄໰䉽넳假꺟魝㿓왱㡌枲ꐪ凣쳩⯺폊싟춐騆⯸햠풵⽣岞耯气㨌굁䚸檲諫䟜㘐属杕ꐊ噐ퟣ鮂ཝ졀舐綤薲勻궍쬰⃡逖㱇ꤨ薈?ᷪ勵ﰮ䃘馉ﭽ࿹뽸輦稈ꮬ᧼潦㢞溟竲ዌ燫褌੧瓎衶츠ꮆ⺸됩ᠴ쬣?⯴Ꭵ뵯ꅅ⻨쀂䮔珪돹Ↄ뱭哱ꫪ忻஢ㆍ筳襝眇䣽绶Ḓ?숞怗祹㎫?팭㫡Ϡ책碆蝩쇹쐣筳ᩎ⥩ᗛࡦ㧮拔꾈狌봔芄ᔡ대ﾡ␧᥻얲敠䗚咰䷆걬軀鸫ͦꪾⓍ温튘푂렒㛞쏸冐≰ⓙꐟ?髵虤䛝ᔨ㊗ꚇ鲟盡틛鑍晑㗇躧㥝ཌྷ啶୮?兣氖ꡮ㊿?栖ⷧ楸?ﰢ䮹턭䥅邇檑?쳇에匣懠ࣚᥔ꧶⾣왪볈Դꛏ礊䬟畑駦筂稈怺瘶虝Ѝ謎絇侯똊枷귥赩姧苧ꑶ걊驰콯䤖ꖊ퇈㺿偢텙ၑ೚❉䊎蹇ᬾ簂Ǣ㔏愡䣘캄잍₨羥柴㏾⨝ᗯ휓꺿㮓兜礢꜏샊餢ﷄ魒ঐ?ꊜ㋜능煎얛खꡉ規෢뉀?㞿涯อ뭐ᓘ⪡㴳倜皘묢侨艐ꮸﱧﾷ꺎掶桏᰷┓嬊꣒ೊ?㟟煎鱑⻋皈涏壵舫畬ᇢ 처⪂㜙㷁?뿱?Წ嵏毲᧦쬄扢γ顏劌욡헯畨딎ﮫ䴧䏋饓⇟틗ᵩ岈?逶캔쫱맵ﮈƣ멸匥鯊隝ꃪ﹏첈忄䨅墋ｋ뚤땠♪ⱱp．ᢗ簉羔뾸澊懨뀛漚ꬣ崊엂纘ᖾ뭷䙾底ꦼ䆭렪ᓍോ㘁셹龔饱⾦辗皽秠텖ʾ곪釢偐᝚ﷳ턞惎籏ꎙ퀕쵲咙?皇竍ꋒ젧Ȓ핕ꗿᩈ칒ह쵧䂠鈐콛蛓ⳝ⁃揧㒔糟舠粰?鶷㬁⽡癲엂⹎升㲋쮻﫴杺［ґ엉㲰꘯믉㶎瑆晜孷㹬턧㍝䣷곭瘪䬘뢪吞㊙쒏鸚噗ᮻᆂ↡칦ࣸ튾ᆮᝊ?忘팦㾭ด쁪렳管縌䇮⺡潅⛶㷼ᄡ펪勠﬒缋勯픃ࣺఱ銳띶쩒降ࡿ?鞚ṏ鍀悖졖몘䢇?腤⳺绥魓⽉흀䎃槣搧묤ꥅ᧫켁쉮콴칩㬴◩뼔廇ﴎԩ酦哱谁䷲?鴦傮걜其ᬂꊶ㓣魫З閆江᷇䫠툥呟ꨃ狩㸗⺑⼸빥紇☨瓄쬤ໜ떱쑌䦀‿鉆構葤뢏訐퓆ۧɦ眏搬Ԥⷣ뾀簐栅ᓲ鐽꟢ꜳꏄӰ⼤቗웬杕絙抙㾍䏳ଉ覉랛跰⚏꺡볔柣ฺ晌긵僔ᠸ⼙䄆೬꯬鬾傠桕꿲뭽榎毮촼꣩ᄇ阝၁屜?줟ည娾綐썃驑㚴ꃐ?탽壆䃼짂㲪쫞蘚艵?ꅤ袕ｅ㥮ꈿ闭␱?㶾౾⛯股熐蛀魵㋃월ᨢ͟꜓䋛쇯䭋䟢損괚폹➛첨䳱凳?㗠뒇?ૅ穽蚴ﹼ䆈쉩妢嫖屟峱?繺휤엥텄貊鞼ꏡ穤ἠ홈좗꬯Ềখ䒼ⴜ?捥蕺蕯㉄⏄လ멷웷舨冺㰭?쮺薵ﱽ勲?㪯兌舷␓䧪ퟝ萮䯜".toCharArray()[1542] = (char)("门衫縼≡ꋨ㾭礒ሀ䭊忠썃䡢븍櫐ꦼ狲ί✋옅돼汿퓸粵逜擊蔒⦻ᬝ螇舞셵ⅆꅂ忂⼁ဉ渆㡦韎쨑䯛者䮼Ẏᵒ啕⋂ꇩ䨄徵ಃ挺媂廲愫鑷䭸퟊㐰⮚်凄쒂㬐ڥ졦싦徬圙?ﻟ⸏䄂芚쟑淈঩ᩢ保̓閖銨門起뚄뭂㎷脀멗⛊뿖Ԋ虶俜奷춁廴䖴块譨唣퇪봭콚䄋╡壢栒缼醵斝ሌ谶抄⅟궡㗆珏㩹븮뭃튍猊岘言땶㭚陃ᛑ怣쬸仲먋球⇡햘㣿䉼쑭拓彜텵䂤ڝ盺ᅠ瑸Ꮭ?겸ᯋ횡욕琟䏵艨➉巃ᗓ僰炦ꌯ尳೵ꦯၧ്渻픨♠鱯쪭唥塍䅓ꆞ㈙젡샰ⴉ㟡堲축?ệ?쩛帲潵䋶欈镹诈猇ꉬ궥띈啸➎썛?꿀ﰶ뇏닞淽鋪ᢒ㢎룛䍖쑛ᓵ鮓긤๮䗄냋ꆊ뮡?ꫦ椣镐鼭㫽؄陚῟폼훃讶퀔ℝ⒦쮺?밡ᶷ笈䌜⛒悊葈墅芯䟍쟥㚽鯙䙄⨒?놎㼠௽왔큐ᘷ鈧笇묹띰ᯞ㮏ꭻ小䈖꣍嘇늉Ḑꃫ쓲த?盈밲練㵶怔㽬犝ꖇ㭅鐵䴃ᭅ⇥劂휃塰鿰럪뱤黚㲞頂ឩ뒓⶧๝ࡈ빚轶썵뚙䲊ޣ䨮☌ᠩ䷶췥쨜??欛蠨䰂쟜쐀⡌쉶痼횻鈦꯰ㇼ⸂쏿솄쥶Ꮷ䷧覼켦죃窍䎳嶉ؿ㔌Ꮵ찴『䯳疤藔嗞괄ﹳ䈡㫢䌢在븭렟ĩ᜔ᚆ審ᕆ탪蛶뮑맧蚄ഺ䁷恄瞝䉚롪ꤢѵQ롱譁ܻછｏ㝯ඏ琨礲䭝陖錉எꀳ퐛郮膀ክ뛨쨂剫䵹ឍ⎈质㋽\001䀾铁뷢㯔麉镏ᜋ☔উ흵뒒뺭Ƿ⿰⬧ࢇꋦ剒貨ꜭ嶙渠坸닅鑹퇖ༀᘍ斍슼곉즤㽲餐舚ડƔ泝괟᫹柍匆恞蓷敨垬⮩?謩䇇﬈葢韰挴鼆㌭睨럲䜟ꅴ李䋻ᒈꡅ㗭᧼造屣瀔??穗溫ⷵ箑撓?鬨헻̩ਅ᳝鉋?쏬䷚嫷峍䰏诛܇羾㰲텦킪᭬埍䒍?挡?䗶㑀⻠᚟甊襻僛㔶忏圄藉毶瘂ⴖ橣㘪넵꯺膙䱏뚩죟ꃸⴁ幥㬜믋太䭤磄莈濽Д鎶帀ѓ༢ᗖᳲஒ蜀?왟흛擊ꎉ?貜멂ꤼ杵䏱习閰葨ꨋꖵ썞ฉ穌鲊훡꺅셠抶ਗ휨悜쩴巷铀詁ਾḌ铷랬ఝꕍ屭ꉴ읖댉剀쌫䠃薻慻ﰶ떊뮆傟顩㭬쪭醏ꣽ茧굟몗팋扐␚勉⸿戔⽨篪邏ᯂ뀶䴏⥸픕벣燠袋خ鈾뀁溥䛔턛Ǥ觙將〫௟켣檺ಉל얮퐰ೄ驻㻹冋ᏻꃁ㷩㾭曃誾䨐덝鍉⹆錴薁薍峿햍굹罆┏썢鐔ꞑ䋶觮ꭝꭊ판㐪〤䰘?떅䃃穯㵳꥓蒏吋藥읮努巟濭喆ᅫ뇥?吅角둠ᆒﶓ틄हﰟ魅㫌괖틚Ű邍밶㓜㮓뾙㲄䔤魞䞥겋殝㲹쟥믞⤖瀇罩㍡뇲¡儜䲘晴夰虉衯撡ֶᮧ銋嚝ೆ⁲黭뷝?귱䷩鬵慶ᱵ紿䳖㸹Ꞽ렇ꖣ?찬溠ᘮ향墸荧ޢ⊪춟䑹ਐ칵૴䴤閤熅౸?▝滾쾥緀駀隇㊭ℿ爱蘽椡鯟혉媚뒍?ଌ羰⽅蹭㇭ꡉ葆蓂␜∐就䆠⍗ᄺꈓ襄胣䵼꟞្??སｯ깝묄⛫肰뵦꿢ﰯ䜬穸뵳ꮑꇭ녧䉓㼂썜咐?㊸轤㍑䃁Ὕᘓ뼘턾耣羨͢爷৙棐瞰旵ᓶ螧剻맵䶂ꎠ믒⼥뢩쯈䬙꡸냊瓏嘂眜꾣ो冷諻ﮨ3棖ⱖȧ李?༸壐쎾웵쁝㴎資᎔⥇谇臿㻠耏䜗Αꫮ쯯貥鳡?쁩ꙇ᪄姂貘ﴚ〦騈ㅐ瓌羏釱㈂⑒䁤ྎ犘嵈䨡뀼奣ꑇଌཀ껽븃쌂搜ꝧ㘾ㆹ?揦쑩㞂롫㙠犢ꔿ幃컷䙈泂䷯혲狮腖녕檋穞먡⮈푣킹썽탙?ἢ웙젰﩯驼츀퍣넧⣈?쯝䱙䇘?ᕄ?꧌ᅞ䆙貿벦䃪韍쵬冹냧聤렞ﳷ拁॥㔤络棁䅢끹劍ꌾ⸸ꚗ₊?숳瘾穊唹㮺頻恰䌮栀浚馁媴当悆맓?䒎鏉⭉䦴촤棰ꈅ泥깶뇼毢̋龣⛲鄰鲀創ᙃ࿡溋낥㖊⾕饧즀닿⁬摘覍ꜯ⣧㩕籞脂鯌Ωﺩ意½题䉣㲰넙쬣馩˛ﯓ萲埦ꃽ흉梭犹ݗ奢랲굌凬轒却螭燓鹼枼枰馶팻샫頋?ْ筰散⠪೴㋛酷Ⓦ퉌왑冘䛖짡ﶢ텻?詚Ằ⊒ⱱ䴶葀⭣⃿챬㆟簳䆿4猤䠋ꐖ뤏뱰圗ᤩ水ᾟ濿∻왐㌑㽵ᷞ茆讯◲설⍥଎藗რ傷逵␯鲶鐅ꮄ艜﻿㟽Ẽ赒貳੘訑⮟횖ᗜ⪱ڇ쥷솢꾍쪯삦න⤖搐୪䲏䀑ퟑ뎷徂澂ꢪ箷毝劕庘?릻谞抜侞厸黃⺫ᴺﵑ⫳헯ⶰﺜ庈졆햳漭⋎耘렰푣ቄ䦡뮂䐙Ȝ뉠ǧ垖崐퍤훽ꌝ⇟벀霯萋习檫⪑ѩźꈨ࿁帏狳ᣚᯋ㶦塍柠륅쀕ꘕ萈р蘡龯䂧굿ᕀ眛뱷ᆶ╙챝谈か࣐?䣔茆䝬왩䪬쎡㈤㌯䞘﹋⅄꿦衍꠆?ᡓవ⓪梪崥ⶢ싎热⑍鉌未ٕ嬮㼺ᝂ炕馪◪闖筠ꍪ鶼쮒陒暞?瀙?⤖೫逧ை꟬ժ倭뿉䂢躵楀㗷죬瘓쇰엢赮博յ븝辫㜴썤ꎐ垞ะ࿼淯浘겺쯛㼼诜吏巨쎉믊鸷鶿訄紃ྛ㟆솼แڂ洀౯Қꕉᛅ韀ʙ萏?毛?옠쩇Ὄ颤檔㽈茿轓胇뎰⨏ꕤ떚困퓉ଘ穽慎૛鹌롓꼤歘졟ꖬ頇膇ꙗ봕撝뗦ઑⰥ㲹횼ꪄꈏᬌ蛩좷햅턃ኬ夳亳덯㤫ઌꕟ斾诈ꅣ橔哔곪沱ᓊ͢??欦㆚ŷ༆❇퐖ꟍ?殡뤵襾ㅴ夔퇝㬙❧鉄팾鮈ᗦ鋞簻쌖涖狇卮ﱇ鈷ᑍ晸뚝⚴豁㡉䤚߷?ᆊ趰瘻੗肜鉁醷鬼깘ﱌ姕Ὶ?䘏Ӭ郴騗䯻⿩녝ﴱꈃ᭗劇?哣鍙꫁䅫ؼ?⌜Ꟈ嵲ꂒ椫줉룦믎誕㯸뿉ꊼ煍?ķ쑍ሷ⑂얖挷⦨˶Ꮲ봺ᚢㇳ⣹ꯟ☊筞쯌ᘸ渽⠸ꓣ卹ඎඉ飩粌幹唢띆隹噉?쉔᛫늼㧫꟮퀊芎歁넝㒢?誢뺞㼔翎乙䁻?⌑鿛뎪镂矯?컥蒣兤撤ᭋ쌟沩?麹ᕣ歶䫳۟㛶รᤀᝅﴛ쵩᩻ᘾೂ驒丱㌋?쬉ﰱ瀨ᒐ믎刭岲䡒辭녙좫빩㬕涛㈬呒局徏毵➵모峯㡙厦礲娷칲ﳫ⑗閊泚鋘婏鳑댣鍎᝽馣གﭥ헇ᯙ瘫҆䍾蟄椄詌䤺䂂릃硐譸꽳M㸔뗷魆᥃줃皌?끵疤퐺Ⲭ僷兖丝ၒ笯坎箿衺熅䐕尗䙂䢥싑඙ంᗅתּㆯỊ梨恫昤灣ꐒ?傈洪䗒ჱᆝ杰蚡௡˳늰缘揖垖휗⡖덁⩭᝵䬦빝枆ឣ擘፶὆ˑ䭆䎥껄赣墽镙ಭ克闱ᗰ㹮寞桬ଯỡ㍖୼ꠊ쐁躏硫猶姽䮩斊Ǥ찂旰凷፱熝汽뚊靾ᑐ泡脿㙕볔姂䣳慳ꏠ罼䛌懐鮰⍡㆔䗂?漘勽姹⣴煫ಈ⽤䷕兕ꥀ딈୻㊅៮灉౎ꁼ橉蘚伖귏?䖈⠠㼙ٌ仉栣⎍⿏臀＇㏸ϣ浇뇮∨劥恡텟甹䴘効仢퉛઒塮♕ዷ칝첿犵㜑品栋菚냭쉶ㅿ뽳䀺쮫ᾖ㯰ఛ깜럶꾛뢇ౡ蜎賅덱ଟং䫉蓤䀞혔꾲㒖쎬⪦면앖ʄ짍ᕫ뵨첌ꎼ؉ꊀ摕橷⽺긭䔰?⮈ꭹ묎兾ㄩ衶(婤漱ꛇ㙤㡗庳輣⒃涳泭⚌컽먤心Ỵꄳ뻼靈?鹰ሒ牢勑䊞怆뾸﵏࢕݄☩ᢝ巓蟑佽鑨菹✈飿豹噃Ὸ?熀꘯㚜֚㻸瀚텟腜냈䰕믢凅儠눒淣缺ჴꂽ푑쑴䌫ѯ릞ࣙ㥄空⦧갰份?䉚욣ߨ꟮뒑㺒蠅谗耼추钱闈᫨ꌥꤦ횫冷놊厡鑎뾪㽃ՀϾ⣶䋒납꠶勉훮ꟑ䎚餡忭砻辀埤?⡍ṯ䗻歜诚茻ᄱ蚋ｂꔝ䙞賚嘦눿哯酊?뇴㞢掲퇜쑝ᱺ⽀轈ნ⤹ᘬㆼ?샷朖鲐썉ꓽ쎧꨾䓖鎟浒䮭גͷ力猙ⴋꄬ⭍䕬进쀍㔌曓騗ָఌ吸铠쀔꩜阙텻㱸ⴚ?Ｎൄ腜ᤀ?漧ⷣ㘵⠫ꋤוּ徲輛Ῠ퍮藴꫺᭢䘎⽨쓡䉜㏟늆ꖨ뱄㦱⃻杍族锦꒾廥ꉁ│䶖෣?鹣幠ꯄ耟洌攺悔澏鎸㏕Ⓩ봙Ⴗ᳙䵬貾侪煙睱奴≳칦糯ଡഐ葀ﰋ᷋灥錡缏밓흋凮⼜䏹䢆?䶒꺔璩뛖ﳓꉢ똖㍰젫୛?₲蝛惤馃悠憕죡?㡛ጾ嶊嗴?韲凥櫽⃲㔅物鴅甎쬾䅃犷㠪蠫ἹՉ뺜㋨ஓ☠ﳶ륫䑯陠枻颎餵걞ꎵ뗆І킑築돱鈻ᯓ汫왏ⶱ梫퉕曆菪忠ଈ鍩㜱릾㤘ᅷㇽ걣럷㥌㉋⇙퇌겧鼌칏㭾篾탵⫆氄줰౏?諅䲁?◤⵬푹ᨾ᳴₮㦒ి关룴툩ࢱ设鍟꿸嵬炯?ᢳꡨ旟ꇚ灠⓯豐놁睗ꤠ㗗ඉ觔䔡坿ꇑ콤쒰ః鳱⣬㞊짚£墔耩뵞葁렟ꅭ㫹ᩆ鏽䙽῁ﱙ焜酖숋廃ﾐ溽果擕ꄷ㔬쏡索覆紂浼⸊勍᝟㰳孧蚢䶩顧驤맞쀅矊郬ᕼȰ蠇ㅬ硾锂㗎晈珌쭬鼇?祇䤃憛櫆㬆䠴撚账댅ꚢ?ᒘ僂連皽?崣샚枯䀞걲쳫堋퀿懷ៃ刻?낷渐ヺ䒯뉱㋍覮밷䎀㳸朄᳏昑?ʨ熈克ⷱ⃖蓉葄碓儦韋丒ﳎʏ涝呪댑譝ﺹ햌攻耝擧?삻㋞㷴櫙錰犉똏呫犼橧﹥銧㏊ঈ肌䡐찥✋륜웜俩싳漶㦿ﱕ폊ശ덈嬁큰?ﻬ䤶䧞煉⦺˧弾뉜㪌隆ᆇ뉤腨袄釱㽉쁵ꗻ࿤귧䣺⶜?逹欂ˉ⮅㒐嫇岔⌠⿊ᔵ᪶唑ඇᨱ譯胄䒴䵝⑵햽겯肏뺑髮欎ᡨ牔?忞졙䔠묢眅嬲⒪௓擠⃲뫯⁙㷚⸥먊憨ൕ済谼뻽쓠䃶뤝獵⪹Ϋ뚐骿朐㾟爷뛘⭒鮏婝쵣衠ลᛃ掤ࠏ繓似缤⊠섙ⅅ驯歹繕䗼俜핾৶꒻ꄳ榪㒩꬘馣໼㴨ᮛㅌꊾ躷숂?ᷜ딺㎁떫?淡閆Ⓒ૆䳠힭籇ኻ䋘멝짅芕⋷嗤⠂櫆틔ꞌ胴툜⏅舥䮈Ѷ뜫՜ﾔ䂑瑋樺坹ۋ욨툶宭朞舎炙푨崅⒌퍖᚝逧꥗冀⋼渌჉茨얔답霴㱉Ⴧ屣磞㌀ᢰ⭣떓ᴕụ就ᆅէ빏葺ﷺ꾙쑆콎矀?롔뭪ͱ皒簺䬊帥圮덃䮨쐷篼䜔⿔뙅꾬뽆ੂ쟱㶤魩Ն쒨屗竦↽횠츈殛薬泩噚粓⊁ꌬ܁챻澩㉔倫绍쇫⨉珞尶㿎崪쁛᠄婹Ⱂꀬے〘쀐ꕈ?衅⯍偼㯵햽ଋ⻿﵀ჰ魊隶瓻≊휳웘ᚠ啲뙷罗䃓쉾ル杺쯑덢俅謈?Ⴥఱ欜縳圆ұᢕ䊨?寮㫶⪈꛷ꡜ?顓驘䳘諚켺஧뵵蜎♧㲝甛ᙗ앬?ꐞᆗ䐃랴얗蚛쨠삥䜡쨬Ⓢ﾿艵錛㍩಍司䛦ᗋ⎁䕽횫㬖퐭矲臞澿簾㨊鹭掬㸼퓊䯦㛂늦蟓늳ⷡ簊﫧ⷿ䔽퉌䜈㉈푕䉍㙠会ꋐ锵愧쮇ಸ鵠谢怾臡絘䑅訹菗ͯ朵㈛ⵚ?᭴厉沬ꍓ눈䅐슇㷷퇣ퟑ鉃⛙ᗼ䙂呐孑쇌ष皕䚦잸跛呙紟Ꭺ჊翿暅☎⪭궲녉䤏搀凿>뛵쪧럀竨든쥪甊쉤赓猨颣踒䈬덭쟳?Ԗ￣뮹鞚䑿?䄓⡱⠳켟捴럢ﳃ⭫鶴ꇜ൉䆴?愹뉘㿬?ᵍ橮숮벝꒠䖞樆?ấ堞똉䐦?妡敒칲妦謩ᛕ雛髛緤᝞訌捓Ȓᅄ며ᅻ辋汎晰큘鬱搒蓴빡㽻녮耭跘캩꒜쫝缵墢彸鍆ㅈ꼸讀ꏂ허沲랰ौޮᢖ體兑噤芃ᜨ릠誶݌敒ꦴᗔᢘ龞㳌定侌繀꾴᷒榊䰅䛅얚쩀?ᑆ꒷儕栆묻﹋쌇俽딙ꗏ䟜श︖먺킙럎ꎨᛑ˲⾻齾?ᡇ앎䦧촜略癉ᅄ씃⧰漙䳥瘬僛鴲㙫➬웟ጩ᤬ｑꕞ஝䑼くᄺ⇜?줣对阚?뻊퉩㡂Ⓣ竈沞湳숍巿Ƿឈ齗硇爹ⶠ쳎Ჶꌏ釉욾⢜ꖜᾥ糪隤밐쌵ᇧ⳾ۢ卲㝵婛䔫䠥᪑舅ೇ喎橲疺膌捰샱?잰㌃蘟物遜듎␃恲㐙濉䯺¤嘜蕞߮缒뽐乜⌑딜㵖Ƹ诸r줉虔䇾㎉膠쑪뚜ꬰ춟侮襔뉐&㕼躜襟㍟ꠤ✴哰ʩ旪亚蠆茘?฿჋ڻ㊹ᄻ枆䍭ᗡ霧女覭꒞뚠ꪑ㽔깊冐踪義뭰꜇㪁剭祙﫫쵛뗷㾕Է䘡䡻饻踉＠륆꺨魛趬ྙ殯챱ꊢ幷丁⧅⻖뻲튤奲갰殁め䃰晄䩥獾起ꋢ䕀㥯邉빗七늂㥻妩⎃썥닆鿳箘㠚愦㒦虲臭뫷㠷発욽勈骦⃀殎ﭓ犾Ẅ쟄괼셋↳캌瓽ᨅ繺ﴂ摗劚뤨툜䳸歏ﾩ뗓亖农䊍ಫሙ灇儤昢⋹灵⧡磆䄘栙堝⽶䫐翖?≻歧╙䢊릟잖聡멈轛䘢퍩㬰坸韒臣眜컭暼䋑৛甶霒➂耀넏ᕢ鎦嶅䍱骄隬᏾煺࿈묹ឤ㖡皃増랥έ鲉׮헄鈭㡡웧蕬蟘߿㨃蜔纅뮫踴ꏙḿ蠽뉘﹈㋆ꔛ참훲醊?꫚??麋雎淙敆ﭮ房钃槩ដ毣摿?淪舢ﻤ죋᭝佌뼈첹ໂ㭶삂뤿铡ꦀⰱ薦趏??濉唑姣⾋筀쩬פּ㈇ְ㦬둅毞࿊鐆㶋頵ᆙՐ쭐灯쭫峂鴫郝ꅆᜌ?꯶㜚얺뻌Ꮡ껜徔창烅ᯩ隽갮莡ྡ덴?헚杤ᮗ䩧⾑홹鲪贕겭뽒䃪⍗鬩⣐銩履ꍺኒ䌏씲먷뤷䧳嘧䀸㯞＇?Šꞌ쐱뽸?ꊤ沋磌弃ﵫ뷟罣藦壟썵ₑ圷॔癘㚄╞뿘婳뇽땬㝲爀ﾫ槰ీ鈑ꊡ嫄㽧ḥ巉杄했橜죓ꦚ?౽ᗔힾ禭顪妴ᘽ嗚ᔗ㞠ꗹ൳㒛ꃭ戠鍡쾙뎻匍牎瀇댡鵍ጥㄴ鳗䘮ӵ쮙餶阚䴍퀐᥶䥧矦猃ࠜﶶꅁͦ⵺Ḫ᫣ﾀ춛3ꜝ嚲༠䴲?膲ꦐ㻕鷿ﴃ݆봺㦲Ǡ췮䇅笁炯쿡됲꠸白㱦珔ꠡ덬?᫫꿼֙뺵䒙寂覎媸?㑶뿆?쀡ŝᩞ玁禶낃퀷ठ멵葌箯뱭⳪쭂환ࠀꌗ값剪垛㹨ᷴ䓄ꌆ䛜踟♠ᘥ㺵྆ꎈꚬ鱯味峊◮釁櫟썙蠜＃㍧ꖑꡂ榫롄엗㊓ᆔᨂ뤃蟡癞녲斵峵ළ弨柗煐眦䈣䖥⾈撷㿭ᛈ늨ֽ鈂벗䇫苮ㇷ套ꛙ嫞썩㈇佝㨗ﲔ௔箺頇⧏Ჾꡘ뤱륳䄍?巬葶चउ猣ゅ炤篂᧫࢓갺量K윧돾?ꁯ耳ꗅ䘭⎺䱿嫸䂡顃㱟ꙋ븣皭ᰔᩩ䇍䪶橺럝᡻?ᩌ⿊薧笄䪂殁둄ү᧗棏幮ϧ闂?鶑膵㇯ఉ敝ጊﳪ켯ഹﴯ懦殗ᄔ頫㴛ﯧሣ횡쵱㷂ꄱϮ賄轆ꎕ쵃㴤햒ꄗ澚ဢઋ鶭䃪믪郟ᇜ᷒ଙ鰎墉쁏ꤑऀ㿒됭鋔絾ꂩ⸐鴙⩡鶅㏔ﭰ悉≎뎚侪颒怒뜣ʌ蟃㏵赒?跚칫䈲ꐓ쯼쐼䬰ݑ睦邓꺀蕭⚩祿黟뜣ᕷ棴颩伄襲ী셆⢛툘ꥋ쐜㧢昅ᰫꏫ幁긄爋忚㕭멲攜㚡⑲讑턚㞸ꋆ叙脷炎쬵畳㲁Ꮏ촊塞펈ޠ㓷媠ᅊ㪪昬骑䗂?䉖琫⏚漒„見쨇なꫧ؏쪔廧㻲㕯깉⟆囊掙Ｌ灒銳䇲楑ᡜꡪ웆슖਒籪좎ﶞꈕ⋇઀飪␰洞凞刴鹪䣭듛Ⱞ詭鳁㠦鹙ֈ吗꣡춂動즉苜䣢ꊗ䥞쥅쌵踽ﵸ༵で鸴⋯鴳뜏㤏⿖蓌鏷ꐻﴆ✑碊쩹㳅巄絢퓐駠쬋海ꅗꂋ曩쾤춄ᙯ唜ẹ攗鎽좙ᴇ㋁ΰ㼎噦乼?纋쥃⃕㖂㗿ﯷh説刏릎釮䃘银왿좃쬒蝖⫋鶑෦눏冡㇃풵䲫ﳣᠬ쾋塚᭺⡝ॻ䝸꿘㖝⤤異⥈ᐅ╈㈼᪲Ꮄ儐㨞영′궉㾣쑔歚㷛뻹ꀟ킜짅ꩃ㯇젞뽔↬犪見ꖦḩ峺๕蔲?᝶慲ꏌ㋝㽘ኣꞼ혩蟀狜썁靉鳄褿㜓嘹亍繪胉ᦀꡛ裀ก঳冾⺑េ?茮ᡶㆪ砓٘⇢⯃졊簐嶕쓚૙ਰ獟⣋⺔Ⱈꪎセ쫽?ꬖҲ樹﵂ἄ謡俌긆⻁爿䂫委탄Ꜫ쉆︳⍣㑝䳃훼툗춥᡹ᡸ偿짳疉ꢜ蘌㤼ｯ?싑錬繋咥罛ᕏ욎産￑䭊굙궳ஈ隖⭦ꌨ폃顧ᰀ䖼鞩넁롊䉭͆‗圛轭푯￁건⽘쑵䇓鍌?읾˺顐濋㪎䏴⼵災ⰸᐥ锽寳Ῐ矸㞋껜솓鍛蕂闑㠝ᖷ㣸ύ檷홴἟㱛뙔ꀫ❝ࣨፂ随?ꦀ붱ꠢﳍꐲ〦䎜痌⚐Ԅ㵄ݚ镐⁶颭塦剘㎢繄?롻㦷䈢矴㤄釤⍪랞륽淽㺎䗩᠇嫉௼䓶⯙啤쓕颽曆᫧꟮╇欙␑代窢뙋奥啣㗛⣞簷̲琑㳰蓪֖㕱揾?눌ⅼ♊ꓔ켫愉໅﷦㥙?蓩딸蕇順閜ၲ렫鉾曟⒵姰汑홫?呝᯿闺컒㜞푭朤㐜ﵼ?驊ἓƃ츱න鸽첸げ텸㼢쫑鸨僦㤣⁭⑄⸰퉔싳ꆺ쾖젔⦭៹䌭璼喀빋䌃⌶砙렯?霕㠫鰌粧脼깩䭼햢?吚傳셑熸㜗⠱诫⏁೓䳟姂頮Ŏ꜋ꭥ꼥ᕳ?⹇䐲쓆㬩泠鿊᧚뢶媹ꨠ賉㛽摨鹛뛍锎๭॰䧳䰪껥鐟법﹣㡎晍ꂈƫ釹?섍ý窸ᶌȵ淶츝댷⹭咺ꝡ藟뜧暯?㖌?ඛₜ廂?銕ᙏ뫂喢ᜋ卦울䙇跺붶௖굴ꈀ韏╌㺋ᵺ功㿙虼ᓯ??Ⰼ飤䥱?ᆜሰ⻘䉇绥౤䉸蛗?둒앋㵏㯗䭤폕᳒藹㺸Ț⚼᷍ꊅ覎뫴ꢹ帷鷇퐋Ἕ괍؆逸씷伕鴇⽈ᮼ컸沲ꇂ袐๾浣?鴯㍂ힹ㋭赝敟徽積掍ꨨ턇䫅泒懲ꕰ⅍趃?Ⴚ蠂︅섞צង袿冣慲辪놭ᡕ꽅㢹孾꽄췾䉕埠풀ㄡ땙Ν쫀渢娐ᘡܙꬂ࣐㳧桖乀ꇚ?㷰鄛셉㳎ഽ䳣㧰酢ᓆ촤躲軥?縄ꄗ㕟⅀듴䙈늂Ďઆ驏흲ረ㽁ꉂ뾩⅐䉮ᔏ씆㒦濹䤝㦒㩬鼭♋☎췬ḩ窑׿흎쳾놫ꉢ㊗碥藙㜛좌ᗑ㜃⼫ﲈ쵾ꍼၬ큸⌶蘏ഇ繊廣䕵쥿꾧Ϩ㮚娽휠ⱌ쉈䏇눭黧쯾౤솇訩ﰷ糙ݏⅺ햃羭蓺蛟黩鲂⊇?潀犪啑팜⿴䷵䖮痲썙⮋ⅶ紲벖뇙诗⤮ⰾ羠玚䟙爀欪俔Ⱅ䀰폨炅飒ᘜ䒜敌鹒딐ฉ奔䫺ꪉ㒥䠅攁ⲙᘨ၁뼣⁽?뇞Ⰳ镭鶔㙏롳⣩뤂埂ፘ需勽嶸⿷醆▚↖ꏝ갲᥻뛽揂躵㰢褵帬䍅槼ԍ埸쀂狥้뒲쁬쮳笑尬㯪敳톗榺х̀Ḑㆺ〥咲?锧ꔼ칵찢◭?붖肥ﴯ㛊䓣퉌䡸ꀏ崍遚얐Ꞷጻ꫖螙꼞꺔푆⓳ﮎ᦭ଲᙃ࿹줋?တ进❴䟆ꤲ趒켋ᣇ冾罫崵륆襠ů㶒鑨ൟꇾ淲⺂洴ె鹶뿙꿒褱｣稧朿弭퐌⃆귔ꃻឫ魮ɕ瑒ඎ↞截བྷ⒂먷氄༅ᆼヅ矾홒둼醔䦁荤⨴文怺偕▇໺䈠툱ở眏賔絓禝瘡ᖰᢢ컩흴ђ쾠럈⏍漙ﶺ牫?迅Ǡ觹ΐ飪?劢盢藥笼Ă嘟૎䝿䜃능윎礃瞊뱤䟕䰙밅૞㪢靖픲勈?圣繭읚꼴劽搎﨎Ԗ鞩?탵秣컎컱펣ॄﳚ饰뀟䔋爘Ს륫箟뇞羨툇챁딙󖨻ⓔ䧸㍮ƃ⹾핪?䁝扃䔧⧉鮯虨ꖧ⋽풸쟪盕畚僿儎禥疥䍩獁䩺더㾝Რﾸ䎣ꠜ뤤絻㑲ᴗ垛屍동㶽遼䔭저紪?㙘?葃윭⾼࿹ᖜ㚻架Ἠ㫑⣻烶㋖ၑ鄊㐪곐还?힫眞粷晸劄촜䰈먥Ქ齻뱕벧該﹖껴ਟ丵짘䟄ྕ羏㊊柖צּꀼ贕诜䈌⤜??㵎㒿獰㞂铡씒?┚ၦ⺞鵔햎㡢∿泖挣ᬔ痧ᘬ謎ஒⅡ࣌Ӥ檚ᖄ笢?끉头閿ꥻ꟩넍쉤㖍ⷄ㱣摃靜柼ಗ秝飽塇⇂鋥‴臻薅ꗥࣶ짯Ҕ惎㺻ؗ蝝늱㬱ໞ庬梳蚔ᢖ䳝㬗㨖ヷﴄ灖퍓鬘鯪ᵓ?활ࠖ훌빜⾾䉧瀘盧⃒ꪆ먀ࢫ꺜⻑紫쳿︫陂䉏源흚煮ഡꁇ旳瑇彮幖돛ɼ傟泩쭡㹈돜​걯ꎘ晐褃縲௒ᚐᮽ㗟䓳ﬦڥ彥굄ꦃ쨃呲ᡒ辉뤓诱喀땱禘蚤ㄿ纈ὦౌ猆䷊헿᧚費葷⟌ᤑ烓▘໴祌嚍ᑅ줠꿛웜㐼媳ꌗྥ趰捴ǧŨ໦傰搾뮙﨡䓹腚?殮ڳ䵣璀屦畈쒶䛹䵾䵒蠱韟㗙鞲?⨸䭽坮蘋챁ҋ뮉 ♔ݯݺ핓ᶔᦞ봇䓂룩㡿皑ꌀ皜㣆뭉骑鴉ꗜ鿯떷㘌촉㔆ɔ쎐洐顏吱?坓⼩₺攔팁ؽ䱀금⃂ந଎ㅨᓳꓙ횾캄ᙧ㤟ｲ⾢㶜棿앗틚䏥鶦?ت䴙Ҽ탫슸偫侫㓃ј㰊⏔研椶ᫎ⦦由ɪట裊敖垬ِ䲓⟙溲ӳ轓Ṝ㜫룚₺⥪䣾템?␲뎩蛊⣰欀즤䉏㘆孑ᴂ뛰வݲ톑悦瘭밷腪?볐푞乎煆鬬ﴥ䋢泝┌陵곒⡑螹繖뱷ⲽ⽾ᅧん䶋迵囹㭍큓㭿囀衆◄睟揿栩脋ῦ⡏릖沺䚦䒾䁞ꩦ蠞嵌Ř刵⇄㋏荎畏샏㩁汞ﱶ㠹䇲油잣䕈⪫ೀⱰ鞾䇭䙸Დ㗟膦嚶嬻酰䒓茞띧঄ă沚狩縱᧠멯ꔒ?⿩꺟㱘⮀閝纏鞕ᵝ蝑헎郪暖䃓嘊鬪쩎쯬邠뾺緽轷뱪꽄愢⛘齪鐚ᇶ燐雑쩯칍−෺㰝뤛拌红䗸㖩㑯岥堔鵙咥Ɲ퍫蘗?멀磲锭隣㢼붮飗㿝⚈掿祦??橒?ꤡ㧄ꆛ賢㔘㨑밽囱㣗췿뭒釅啮걷莊歬┸ῼ貮腨໐ᙸዮ輡묉ᨅ㱆櫖锗ퟭ╲売렺♇ಒ良鱬㧊?ꀭ玕㔲⿿?섗䦂ଦ睰㐑掳꺄걥鬟㐈Թ韢঒朤⎷鼻췀Ꝝ贖䙾풲啱퀜쪚ꢻ㗭䆷㜂鲁钤►?檣맯令왾汗폒볝ᲆ趿踯猶?⼌롿蛻冔棼뎤⦫ㇱૉ堬㙦堬鸇聫Ð⣽㽔ᭋ최兽斡?싓䒲銇ෘ迖굞鉭㗓躻실᧌噵㲁镢쭵∫骵疦㪡體걅貸톆曏액軎깉漖蓄ग़⑧ੈ∁朷힮⥋ꇬꩨ庲൪醰늅䬨욈攔퐕䄺瓭䶰ㄴ頹綢禲球ᴣᦩ鐭飩薽摋ꨂ㧖ಶ駢Ṧ噳㌼ㅬᰉ⺡ａ⦇≒缸븧᡿ᦡ蹕യᧃ申썵쾏á䡝촫ᲅ䄭邍౵锈傳꣊ـ촶㋓쀶咯칝ꗤ刄䭋ᓮ䏢嵈풮摶슇ꢾ﹄尵갩覶챐̞㺑팏Ꮅ鑡眢摍ﴡ檜㻺㫱媔秥꟟?㐘씠쩕壅ᙦৈሲ﯊繛夳꓇藋쀙צ撈罌⾷ຏ郋粵䂙ኈ꫞띔橳딎훡ᰛ沰뭼떆❍䍗毳䫔䎸뺒ꤌꋮ艖檻≘쐿?⨖簐ᯈ焚⬞ﯘハ੔܂蓪阉찵ઑ퀮ي㈎➢䤘ာ덝ᬧ瑾梜ꪺ춘Ѣꗋ욟ꖩ戰憏⑶淘谴጑㄰⹬ᗭ溘눔썋襁ﷺ㫿ᣵ⳦߮ἵ⚩竚Ǵ䗓ᯏ鑺鉅䲓䧮䉸岭⪑哗?铻喾㡣룺켬節봣豿㇨毴ᤠだ淃앶䋽譮ອ꣩퀰招አ雐ᅄ⍏쾲틀ତ渉?⧅㻃壏ㆦȑ寡ත慕죱?梦́蚌䅧窡篑뽝睉騮וֹ妆쫙?고䊼匶藧⵫刖覌૭⪻鿟䫮嘰싵뼬ꨘ蜕ᬆ꛳䮖▷뭕둔遚ᶪ캸猣൉Ƽ鍤Ĩ䬫浄໰䉽넳假꺟魝㿓왱㡌枲ꐪ凣쳩⯺폊싟춐騆⯸햠풵⽣岞耯气㨌굁䚸檲諫䟜㘐属杕ꐊ噐ퟣ鮂ཝ졀舐綤薲勻궍쬰⃡逖㱇ꤨ薈?ᷪ勵ﰮ䃘馉ﭽ࿹뽸輦稈ꮬ᧼潦㢞溟竲ዌ燫褌੧瓎衶츠ꮆ⺸됩ᠴ쬣?⯴Ꭵ뵯ꅅ⻨쀂䮔珪돹Ↄ뱭哱ꫪ忻஢ㆍ筳襝眇䣽绶Ḓ?숞怗祹㎫?팭㫡Ϡ책碆蝩쇹쐣筳ᩎ⥩ᗛࡦ㧮拔꾈狌봔芄ᔡ대ﾡ␧᥻얲敠䗚咰䷆걬軀鸫ͦꪾⓍ温튘푂렒㛞쏸冐≰ⓙꐟ?髵虤䛝ᔨ㊗ꚇ鲟盡틛鑍晑㗇躧㥝ཌྷ啶୮?兣氖ꡮ㊿?栖ⷧ楸?ﰢ䮹턭䥅邇檑?쳇에匣懠ࣚᥔ꧶⾣왪볈Դꛏ礊䬟畑駦筂稈怺瘶虝Ѝ謎絇侯똊枷귥赩姧苧ꑶ걊驰콯䤖ꖊ퇈㺿偢텙ၑ೚❉䊎蹇ᬾ簂Ǣ㔏愡䣘캄잍₨羥柴㏾⨝ᗯ휓꺿㮓兜礢꜏샊餢ﷄ魒ঐ?ꊜ㋜능煎얛खꡉ規෢뉀?㞿涯อ뭐ᓘ⪡㴳倜皘묢侨艐ꮸﱧﾷ꺎掶桏᰷┓嬊꣒ೊ?㟟煎鱑⻋皈涏壵舫畬ᇢ 처⪂㜙㷁?뿱?Წ嵏毲᧦쬄扢γ顏劌욡헯畨딎ﮫ䴧䏋饓⇟틗ᵩ岈?逶캔쫱맵ﮈƣ멸匥鯊隝ꃪ﹏첈忄䨅墋ｋ뚤땠♪ⱱp．ᢗ簉羔뾸澊懨뀛漚ꬣ崊엂纘ᖾ뭷䙾底ꦼ䆭렪ᓍോ㘁셹龔饱⾦辗皽秠텖ʾ곪釢偐᝚ﷳ턞惎籏ꎙ퀕쵲咙?皇竍ꋒ젧Ȓ핕ꗿᩈ칒ह쵧䂠鈐콛蛓ⳝ⁃揧㒔糟舠粰?鶷㬁⽡癲엂⹎升㲋쮻﫴杺［ґ엉㲰꘯믉㶎瑆晜孷㹬턧㍝䣷곭瘪䬘뢪吞㊙쒏鸚噗ᮻᆂ↡칦ࣸ튾ᆮᝊ?忘팦㾭ด쁪렳管縌䇮⺡潅⛶㷼ᄡ펪勠﬒缋勯픃ࣺఱ銳띶쩒降ࡿ?鞚ṏ鍀悖졖몘䢇?腤⳺绥魓⽉흀䎃槣搧묤ꥅ᧫켁쉮콴칩㬴◩뼔廇ﴎԩ酦哱谁䷲?鴦傮걜其ᬂꊶ㓣魫З閆江᷇䫠툥呟ꨃ狩㸗⺑⼸빥紇☨瓄쬤ໜ떱쑌䦀‿鉆構葤뢏訐퓆ۧɦ眏搬Ԥⷣ뾀簐栅ᓲ鐽꟢ꜳꏄӰ⼤቗웬杕絙抙㾍䏳ଉ覉랛跰⚏꺡볔柣ฺ晌긵僔ᠸ⼙䄆೬꯬鬾傠桕꿲뭽榎毮촼꣩ᄇ阝၁屜?줟ည娾綐썃驑㚴ꃐ?탽壆䃼짂㲪쫞蘚艵?ꅤ袕ｅ㥮ꈿ闭␱?㶾౾⛯股熐蛀魵㋃월ᨢ͟꜓䋛쇯䭋䟢損괚폹➛첨䳱凳?㗠뒇?ૅ穽蚴ﹼ䆈쉩妢嫖屟峱?繺휤엥텄貊鞼ꏡ穤ἠ홈좗꬯Ềখ䒼ⴜ?捥蕺蕯㉄⏄လ멷웷舨冺㰭?쮺薵ﱽ勲?㪯兌舷␓䧪ퟝ萮䯜".toCharArray()[1542] ^ 0x6A56); String str; int i = (str = dP$dt.X("门衫縼≡ꋨ㾭礒ሀ䭊忠썃䡢븍櫐ꦼ狲ί✋옅돼汿퓸粵逜擊蔒⦻ᬝ螇舞셵ⅆꅂ忂⼁ဉ渆㡦韎쨑䯛者䮼Ẏᵒ啕⋂ꇩ䨄徵ಃ挺媂廲愫鑷䭸퟊㐰⮚်凄쒂㬐ڥ졦싦徬圙?ﻟ⸏䄂芚쟑淈঩ᩢ保̓閖銨門起뚄뭂㎷脀멗⛊뿖Ԋ虶俜奷춁廴䖴块譨唣퇪봭콚䄋╡壢栒缼醵斝ሌ谶抄⅟궡㗆珏㩹븮뭃튍猊岘言땶㭚陃ᛑ怣쬸仲먋球⇡햘㣿䉼쑭拓彜텵䂤ڝ盺ᅠ瑸Ꮭ?겸ᯋ횡욕琟䏵艨➉巃ᗓ僰炦ꌯ尳೵ꦯၧ്渻픨♠鱯쪭唥塍䅓ꆞ㈙젡샰ⴉ㟡堲축?ệ?쩛帲潵䋶欈镹诈猇ꉬ궥띈啸➎썛?꿀ﰶ뇏닞淽鋪ᢒ㢎룛䍖쑛ᓵ鮓긤๮䗄냋ꆊ뮡?ꫦ椣镐鼭㫽؄陚῟폼훃讶퀔ℝ⒦쮺?밡ᶷ笈䌜⛒悊葈墅芯䟍쟥㚽鯙䙄⨒?놎㼠௽왔큐ᘷ鈧笇묹띰ᯞ㮏ꭻ小䈖꣍嘇늉Ḑꃫ쓲த?盈밲練㵶怔㽬犝ꖇ㭅鐵䴃ᭅ⇥劂휃塰鿰럪뱤黚㲞頂ឩ뒓⶧๝ࡈ빚轶썵뚙䲊ޣ䨮☌ᠩ䷶췥쨜??欛蠨䰂쟜쐀⡌쉶痼횻鈦꯰ㇼ⸂쏿솄쥶Ꮷ䷧覼켦죃窍䎳嶉ؿ㔌Ꮵ찴『䯳疤藔嗞괄ﹳ䈡㫢䌢在븭렟ĩ᜔ᚆ審ᕆ탪蛶뮑맧蚄ഺ䁷恄瞝䉚롪ꤢѵQ롱譁ܻછｏ㝯ඏ琨礲䭝陖錉எꀳ퐛郮膀ክ뛨쨂剫䵹ឍ⎈质㋽\001䀾铁뷢㯔麉镏ᜋ☔উ흵뒒뺭Ƿ⿰⬧ࢇꋦ剒貨ꜭ嶙渠坸닅鑹퇖ༀᘍ斍슼곉즤㽲餐舚ડƔ泝괟᫹柍匆恞蓷敨垬⮩?謩䇇﬈葢韰挴鼆㌭睨럲䜟ꅴ李䋻ᒈꡅ㗭᧼造屣瀔??穗溫ⷵ箑撓?鬨헻̩ਅ᳝鉋?쏬䷚嫷峍䰏诛܇羾㰲텦킪᭬埍䒍?挡?䗶㑀⻠᚟甊襻僛㔶忏圄藉毶瘂ⴖ橣㘪넵꯺膙䱏뚩죟ꃸⴁ幥㬜믋太䭤磄莈濽Д鎶帀ѓ༢ᗖᳲஒ蜀?왟흛擊ꎉ?貜멂ꤼ杵䏱习閰葨ꨋꖵ썞ฉ穌鲊훡꺅셠抶ਗ휨悜쩴巷铀詁ਾḌ铷랬ఝꕍ屭ꉴ읖댉剀쌫䠃薻慻ﰶ떊뮆傟顩㭬쪭醏ꣽ茧굟몗팋扐␚勉⸿戔⽨篪邏ᯂ뀶䴏⥸픕벣燠袋خ鈾뀁溥䛔턛Ǥ觙將〫௟켣檺ಉל얮퐰ೄ驻㻹冋ᏻꃁ㷩㾭曃誾䨐덝鍉⹆錴薁薍峿햍굹罆┏썢鐔ꞑ䋶觮ꭝꭊ판㐪〤䰘?떅䃃穯㵳꥓蒏吋藥읮努巟濭喆ᅫ뇥?吅角둠ᆒﶓ틄हﰟ魅㫌괖틚Ű邍밶㓜㮓뾙㲄䔤魞䞥겋殝㲹쟥믞⤖瀇罩㍡뇲¡儜䲘晴夰虉衯撡ֶᮧ銋嚝ೆ⁲黭뷝?귱䷩鬵慶ᱵ紿䳖㸹Ꞽ렇ꖣ?찬溠ᘮ향墸荧ޢ⊪춟䑹ਐ칵૴䴤閤熅౸?▝滾쾥緀駀隇㊭ℿ爱蘽椡鯟혉媚뒍?ଌ羰⽅蹭㇭ꡉ葆蓂␜∐就䆠⍗ᄺꈓ襄胣䵼꟞្??སｯ깝묄⛫肰뵦꿢ﰯ䜬穸뵳ꮑꇭ녧䉓㼂썜咐?㊸轤㍑䃁Ὕᘓ뼘턾耣羨͢爷৙棐瞰旵ᓶ螧剻맵䶂ꎠ믒⼥뢩쯈䬙꡸냊瓏嘂眜꾣ो冷諻ﮨ3棖ⱖȧ李?༸壐쎾웵쁝㴎資᎔⥇谇臿㻠耏䜗Αꫮ쯯貥鳡?쁩ꙇ᪄姂貘ﴚ〦騈ㅐ瓌羏釱㈂⑒䁤ྎ犘嵈䨡뀼奣ꑇଌཀ껽븃쌂搜ꝧ㘾ㆹ?揦쑩㞂롫㙠犢ꔿ幃컷䙈泂䷯혲狮腖녕檋穞먡⮈푣킹썽탙?ἢ웙젰﩯驼츀퍣넧⣈?쯝䱙䇘?ᕄ?꧌ᅞ䆙貿벦䃪韍쵬冹냧聤렞ﳷ拁॥㔤络棁䅢끹劍ꌾ⸸ꚗ₊?숳瘾穊唹㮺頻恰䌮栀浚馁媴当悆맓?䒎鏉⭉䦴촤棰ꈅ泥깶뇼毢̋龣⛲鄰鲀創ᙃ࿡溋낥㖊⾕饧즀닿⁬摘覍ꜯ⣧㩕籞脂鯌Ωﺩ意½题䉣㲰넙쬣馩˛ﯓ萲埦ꃽ흉梭犹ݗ奢랲굌凬轒却螭燓鹼枼枰馶팻샫頋?ْ筰散⠪೴㋛酷Ⓦ퉌왑冘䛖짡ﶢ텻?詚Ằ⊒ⱱ䴶葀⭣⃿챬㆟簳䆿4猤䠋ꐖ뤏뱰圗ᤩ水ᾟ濿∻왐㌑㽵ᷞ茆讯◲설⍥଎藗რ傷逵␯鲶鐅ꮄ艜﻿㟽Ẽ赒貳੘訑⮟횖ᗜ⪱ڇ쥷솢꾍쪯삦න⤖搐୪䲏䀑ퟑ뎷徂澂ꢪ箷毝劕庘?릻谞抜侞厸黃⺫ᴺﵑ⫳헯ⶰﺜ庈졆햳漭⋎耘렰푣ቄ䦡뮂䐙Ȝ뉠ǧ垖崐퍤훽ꌝ⇟벀霯萋习檫⪑ѩźꈨ࿁帏狳ᣚᯋ㶦塍柠륅쀕ꘕ萈р蘡龯䂧굿ᕀ眛뱷ᆶ╙챝谈か࣐?䣔茆䝬왩䪬쎡㈤㌯䞘﹋⅄꿦衍꠆?ᡓవ⓪梪崥ⶢ싎热⑍鉌未ٕ嬮㼺ᝂ炕馪◪闖筠ꍪ鶼쮒陒暞?瀙?⤖೫逧ை꟬ժ倭뿉䂢躵楀㗷죬瘓쇰엢赮博յ븝辫㜴썤ꎐ垞ะ࿼淯浘겺쯛㼼诜吏巨쎉믊鸷鶿訄紃ྛ㟆솼แڂ洀౯Қꕉᛅ韀ʙ萏?毛?옠쩇Ὄ颤檔㽈茿轓胇뎰⨏ꕤ떚困퓉ଘ穽慎૛鹌롓꼤歘졟ꖬ頇膇ꙗ봕撝뗦ઑⰥ㲹횼ꪄꈏᬌ蛩좷햅턃ኬ夳亳덯㤫ઌꕟ斾诈ꅣ橔哔곪沱ᓊ͢??欦㆚ŷ༆❇퐖ꟍ?殡뤵襾ㅴ夔퇝㬙❧鉄팾鮈ᗦ鋞簻쌖涖狇卮ﱇ鈷ᑍ晸뚝⚴豁㡉䤚߷?ᆊ趰瘻੗肜鉁醷鬼깘ﱌ姕Ὶ?䘏Ӭ郴騗䯻⿩녝ﴱꈃ᭗劇?哣鍙꫁䅫ؼ?⌜Ꟈ嵲ꂒ椫줉룦믎誕㯸뿉ꊼ煍?ķ쑍ሷ⑂얖挷⦨˶Ꮲ봺ᚢㇳ⣹ꯟ☊筞쯌ᘸ渽⠸ꓣ卹ඎඉ飩粌幹唢띆隹噉?쉔᛫늼㧫꟮퀊芎歁넝㒢?誢뺞㼔翎乙䁻?⌑鿛뎪镂矯?컥蒣兤撤ᭋ쌟沩?麹ᕣ歶䫳۟㛶รᤀᝅﴛ쵩᩻ᘾೂ驒丱㌋?쬉ﰱ瀨ᒐ믎刭岲䡒辭녙좫빩㬕涛㈬呒局徏毵➵모峯㡙厦礲娷칲ﳫ⑗閊泚鋘婏鳑댣鍎᝽馣གﭥ헇ᯙ瘫҆䍾蟄椄詌䤺䂂릃硐譸꽳M㸔뗷魆᥃줃皌?끵疤퐺Ⲭ僷兖丝ၒ笯坎箿衺熅䐕尗䙂䢥싑඙ంᗅתּㆯỊ梨恫昤灣ꐒ?傈洪䗒ჱᆝ杰蚡௡˳늰缘揖垖휗⡖덁⩭᝵䬦빝枆ឣ擘፶὆ˑ䭆䎥껄赣墽镙ಭ克闱ᗰ㹮寞桬ଯỡ㍖୼ꠊ쐁躏硫猶姽䮩斊Ǥ찂旰凷፱熝汽뚊靾ᑐ泡脿㙕볔姂䣳慳ꏠ罼䛌懐鮰⍡㆔䗂?漘勽姹⣴煫ಈ⽤䷕兕ꥀ딈୻㊅៮灉౎ꁼ橉蘚伖귏?䖈⠠㼙ٌ仉栣⎍⿏臀＇㏸ϣ浇뇮∨劥恡텟甹䴘効仢퉛઒塮♕ዷ칝첿犵㜑品栋菚냭쉶ㅿ뽳䀺쮫ᾖ㯰ఛ깜럶꾛뢇ౡ蜎賅덱ଟং䫉蓤䀞혔꾲㒖쎬⪦면앖ʄ짍ᕫ뵨첌ꎼ؉ꊀ摕橷⽺긭䔰?⮈ꭹ묎兾ㄩ衶(婤漱ꛇ㙤㡗庳輣⒃涳泭⚌컽먤心Ỵꄳ뻼靈?鹰ሒ牢勑䊞怆뾸﵏࢕݄☩ᢝ巓蟑佽鑨菹✈飿豹噃Ὸ?熀꘯㚜֚㻸瀚텟腜냈䰕믢凅儠눒淣缺ჴꂽ푑쑴䌫ѯ릞ࣙ㥄空⦧갰份?䉚욣ߨ꟮뒑㺒蠅谗耼추钱闈᫨ꌥꤦ횫冷놊厡鑎뾪㽃ՀϾ⣶䋒납꠶勉훮ꟑ䎚餡忭砻辀埤?⡍ṯ䗻歜诚茻ᄱ蚋ｂꔝ䙞賚嘦눿哯酊?뇴㞢掲퇜쑝ᱺ⽀轈ნ⤹ᘬㆼ?샷朖鲐썉ꓽ쎧꨾䓖鎟浒䮭גͷ力猙ⴋꄬ⭍䕬进쀍㔌曓騗ָఌ吸铠쀔꩜阙텻㱸ⴚ?Ｎൄ腜ᤀ?漧ⷣ㘵⠫ꋤוּ徲輛Ῠ퍮藴꫺᭢䘎⽨쓡䉜㏟늆ꖨ뱄㦱⃻杍族锦꒾廥ꉁ│䶖෣?鹣幠ꯄ耟洌攺悔澏鎸㏕Ⓩ봙Ⴗ᳙䵬貾侪煙睱奴≳칦糯ଡഐ葀ﰋ᷋灥錡缏밓흋凮⼜䏹䢆?䶒꺔璩뛖ﳓꉢ똖㍰젫୛?₲蝛惤馃悠憕죡?㡛ጾ嶊嗴?韲凥櫽⃲㔅物鴅甎쬾䅃犷㠪蠫ἹՉ뺜㋨ஓ☠ﳶ륫䑯陠枻颎餵걞ꎵ뗆І킑築돱鈻ᯓ汫왏ⶱ梫퉕曆菪忠ଈ鍩㜱릾㤘ᅷㇽ걣럷㥌㉋⇙퇌겧鼌칏㭾篾탵⫆氄줰౏?諅䲁?◤⵬푹ᨾ᳴₮㦒ి关룴툩ࢱ设鍟꿸嵬炯?ᢳꡨ旟ꇚ灠⓯豐놁睗ꤠ㗗ඉ觔䔡坿ꇑ콤쒰ః鳱⣬㞊짚£墔耩뵞葁렟ꅭ㫹ᩆ鏽䙽῁ﱙ焜酖숋廃ﾐ溽果擕ꄷ㔬쏡索覆紂浼⸊勍᝟㰳孧蚢䶩顧驤맞쀅矊郬ᕼȰ蠇ㅬ硾锂㗎晈珌쭬鼇?祇䤃憛櫆㬆䠴撚账댅ꚢ?ᒘ僂連皽?崣샚枯䀞걲쳫堋퀿懷ៃ刻?낷渐ヺ䒯뉱㋍覮밷䎀㳸朄᳏昑?ʨ熈克ⷱ⃖蓉葄碓儦韋丒ﳎʏ涝呪댑譝ﺹ햌攻耝擧?삻㋞㷴櫙錰犉똏呫犼橧﹥銧㏊ঈ肌䡐찥✋륜웜俩싳漶㦿ﱕ폊ശ덈嬁큰?ﻬ䤶䧞煉⦺˧弾뉜㪌隆ᆇ뉤腨袄釱㽉쁵ꗻ࿤귧䣺⶜?逹欂ˉ⮅㒐嫇岔⌠⿊ᔵ᪶唑ඇᨱ譯胄䒴䵝⑵햽겯肏뺑髮欎ᡨ牔?忞졙䔠묢眅嬲⒪௓擠⃲뫯⁙㷚⸥먊憨ൕ済谼뻽쓠䃶뤝獵⪹Ϋ뚐骿朐㾟爷뛘⭒鮏婝쵣衠ลᛃ掤ࠏ繓似缤⊠섙ⅅ驯歹繕䗼俜핾৶꒻ꄳ榪㒩꬘馣໼㴨ᮛㅌꊾ躷숂?ᷜ딺㎁떫?淡閆Ⓒ૆䳠힭籇ኻ䋘멝짅芕⋷嗤⠂櫆틔ꞌ胴툜⏅舥䮈Ѷ뜫՜ﾔ䂑瑋樺坹ۋ욨툶宭朞舎炙푨崅⒌퍖᚝逧꥗冀⋼渌჉茨얔답霴㱉Ⴧ屣磞㌀ᢰ⭣떓ᴕụ就ᆅէ빏葺ﷺ꾙쑆콎矀?롔뭪ͱ皒簺䬊帥圮덃䮨쐷篼䜔⿔뙅꾬뽆ੂ쟱㶤魩Ն쒨屗竦↽횠츈殛薬泩噚粓⊁ꌬ܁챻澩㉔倫绍쇫⨉珞尶㿎崪쁛᠄婹Ⱂꀬے〘쀐ꕈ?衅⯍偼㯵햽ଋ⻿﵀ჰ魊隶瓻≊휳웘ᚠ啲뙷罗䃓쉾ル杺쯑덢俅謈?Ⴥఱ欜縳圆ұᢕ䊨?寮㫶⪈꛷ꡜ?顓驘䳘諚켺஧뵵蜎♧㲝甛ᙗ앬?ꐞᆗ䐃랴얗蚛쨠삥䜡쨬Ⓢ﾿艵錛㍩಍司䛦ᗋ⎁䕽횫㬖퐭矲臞澿簾㨊鹭掬㸼퓊䯦㛂늦蟓늳ⷡ簊﫧ⷿ䔽퉌䜈㉈푕䉍㙠会ꋐ锵愧쮇ಸ鵠谢怾臡絘䑅訹菗ͯ朵㈛ⵚ?᭴厉沬ꍓ눈䅐슇㷷퇣ퟑ鉃⛙ᗼ䙂呐孑쇌ष皕䚦잸跛呙紟Ꭺ჊翿暅☎⪭궲녉䤏搀凿>뛵쪧럀竨든쥪甊쉤赓猨颣踒䈬덭쟳?Ԗ￣뮹鞚䑿?䄓⡱⠳켟捴럢ﳃ⭫鶴ꇜ൉䆴?愹뉘㿬?ᵍ橮숮벝꒠䖞樆?ấ堞똉䐦?妡敒칲妦謩ᛕ雛髛緤᝞訌捓Ȓᅄ며ᅻ辋汎晰큘鬱搒蓴빡㽻녮耭跘캩꒜쫝缵墢彸鍆ㅈ꼸讀ꏂ허沲랰ौޮᢖ體兑噤芃ᜨ릠誶݌敒ꦴᗔᢘ龞㳌定侌繀꾴᷒榊䰅䛅얚쩀?ᑆ꒷儕栆묻﹋쌇俽딙ꗏ䟜श︖먺킙럎ꎨᛑ˲⾻齾?ᡇ앎䦧촜略癉ᅄ씃⧰漙䳥瘬僛鴲㙫➬웟ጩ᤬ｑꕞ஝䑼くᄺ⇜?줣对阚?뻊퉩㡂Ⓣ竈沞湳숍巿Ƿឈ齗硇爹ⶠ쳎Ჶꌏ釉욾⢜ꖜᾥ糪隤밐쌵ᇧ⳾ۢ卲㝵婛䔫䠥᪑舅ೇ喎橲疺膌捰샱?잰㌃蘟物遜듎␃恲㐙濉䯺¤嘜蕞߮缒뽐乜⌑딜㵖Ƹ诸r줉虔䇾㎉膠쑪뚜ꬰ춟侮襔뉐&㕼躜襟㍟ꠤ✴哰ʩ旪亚蠆茘?฿჋ڻ㊹ᄻ枆䍭ᗡ霧女覭꒞뚠ꪑ㽔깊冐踪義뭰꜇㪁剭祙﫫쵛뗷㾕Է䘡䡻饻踉＠륆꺨魛趬ྙ殯챱ꊢ幷丁⧅⻖뻲튤奲갰殁め䃰晄䩥獾起ꋢ䕀㥯邉빗七늂㥻妩⎃썥닆鿳箘㠚愦㒦虲臭뫷㠷発욽勈骦⃀殎ﭓ犾Ẅ쟄괼셋↳캌瓽ᨅ繺ﴂ摗劚뤨툜䳸歏ﾩ뗓亖农䊍ಫሙ灇儤昢⋹灵⧡磆䄘栙堝⽶䫐翖?≻歧╙䢊릟잖聡멈轛䘢퍩㬰坸韒臣眜컭暼䋑৛甶霒➂耀넏ᕢ鎦嶅䍱骄隬᏾煺࿈묹ឤ㖡皃増랥έ鲉׮헄鈭㡡웧蕬蟘߿㨃蜔纅뮫踴ꏙḿ蠽뉘﹈㋆ꔛ참훲醊?꫚??麋雎淙敆ﭮ房钃槩ដ毣摿?淪舢ﻤ죋᭝佌뼈첹ໂ㭶삂뤿铡ꦀⰱ薦趏??濉唑姣⾋筀쩬פּ㈇ְ㦬둅毞࿊鐆㶋頵ᆙՐ쭐灯쭫峂鴫郝ꅆᜌ?꯶㜚얺뻌Ꮡ껜徔창烅ᯩ隽갮莡ྡ덴?헚杤ᮗ䩧⾑홹鲪贕겭뽒䃪⍗鬩⣐銩履ꍺኒ䌏씲먷뤷䧳嘧䀸㯞＇?Šꞌ쐱뽸?ꊤ沋磌弃ﵫ뷟罣藦壟썵ₑ圷॔癘㚄╞뿘婳뇽땬㝲爀ﾫ槰ీ鈑ꊡ嫄㽧ḥ巉杄했橜죓ꦚ?౽ᗔힾ禭顪妴ᘽ嗚ᔗ㞠ꗹ൳㒛ꃭ戠鍡쾙뎻匍牎瀇댡鵍ጥㄴ鳗䘮ӵ쮙餶阚䴍퀐᥶䥧矦猃ࠜﶶꅁͦ⵺Ḫ᫣ﾀ춛3ꜝ嚲༠䴲?膲ꦐ㻕鷿ﴃ݆봺㦲Ǡ췮䇅笁炯쿡됲꠸白㱦珔ꠡ덬?᫫꿼֙뺵䒙寂覎媸?㑶뿆?쀡ŝᩞ玁禶낃퀷ठ멵葌箯뱭⳪쭂환ࠀꌗ값剪垛㹨ᷴ䓄ꌆ䛜踟♠ᘥ㺵྆ꎈꚬ鱯味峊◮釁櫟썙蠜＃㍧ꖑꡂ榫롄엗㊓ᆔᨂ뤃蟡癞녲斵峵ළ弨柗煐眦䈣䖥⾈撷㿭ᛈ늨ֽ鈂벗䇫苮ㇷ套ꛙ嫞썩㈇佝㨗ﲔ௔箺頇⧏Ჾꡘ뤱륳䄍?巬葶चउ猣ゅ炤篂᧫࢓갺量K윧돾?ꁯ耳ꗅ䘭⎺䱿嫸䂡顃㱟ꙋ븣皭ᰔᩩ䇍䪶橺럝᡻?ᩌ⿊薧笄䪂殁둄ү᧗棏幮ϧ闂?鶑膵㇯ఉ敝ጊﳪ켯ഹﴯ懦殗ᄔ頫㴛ﯧሣ횡쵱㷂ꄱϮ賄轆ꎕ쵃㴤햒ꄗ澚ဢઋ鶭䃪믪郟ᇜ᷒ଙ鰎墉쁏ꤑऀ㿒됭鋔絾ꂩ⸐鴙⩡鶅㏔ﭰ悉≎뎚侪颒怒뜣ʌ蟃㏵赒?跚칫䈲ꐓ쯼쐼䬰ݑ睦邓꺀蕭⚩祿黟뜣ᕷ棴颩伄襲ী셆⢛툘ꥋ쐜㧢昅ᰫꏫ幁긄爋忚㕭멲攜㚡⑲讑턚㞸ꋆ叙脷炎쬵畳㲁Ꮏ촊塞펈ޠ㓷媠ᅊ㪪昬骑䗂?䉖琫⏚漒„見쨇なꫧ؏쪔廧㻲㕯깉⟆囊掙Ｌ灒銳䇲楑ᡜꡪ웆슖਒籪좎ﶞꈕ⋇઀飪␰洞凞刴鹪䣭듛Ⱞ詭鳁㠦鹙ֈ吗꣡춂動즉苜䣢ꊗ䥞쥅쌵踽ﵸ༵で鸴⋯鴳뜏㤏⿖蓌鏷ꐻﴆ✑碊쩹㳅巄絢퓐駠쬋海ꅗꂋ曩쾤춄ᙯ唜ẹ攗鎽좙ᴇ㋁ΰ㼎噦乼?纋쥃⃕㖂㗿ﯷh説刏릎釮䃘银왿좃쬒蝖⫋鶑෦눏冡㇃풵䲫ﳣᠬ쾋塚᭺⡝ॻ䝸꿘㖝⤤異⥈ᐅ╈㈼᪲Ꮄ儐㨞영′궉㾣쑔歚㷛뻹ꀟ킜짅ꩃ㯇젞뽔↬犪見ꖦḩ峺๕蔲?᝶慲ꏌ㋝㽘ኣꞼ혩蟀狜썁靉鳄褿㜓嘹亍繪胉ᦀꡛ裀ก঳冾⺑េ?茮ᡶㆪ砓٘⇢⯃졊簐嶕쓚૙ਰ獟⣋⺔Ⱈꪎセ쫽?ꬖҲ樹﵂ἄ謡俌긆⻁爿䂫委탄Ꜫ쉆︳⍣㑝䳃훼툗춥᡹ᡸ偿짳疉ꢜ蘌㤼ｯ?싑錬繋咥罛ᕏ욎産￑䭊굙궳ஈ隖⭦ꌨ폃顧ᰀ䖼鞩넁롊䉭͆‗圛轭푯￁건⽘쑵䇓鍌?읾˺顐濋㪎䏴⼵災ⰸᐥ锽寳Ῐ矸㞋껜솓鍛蕂闑㠝ᖷ㣸ύ檷홴἟㱛뙔ꀫ❝ࣨፂ随?ꦀ붱ꠢﳍꐲ〦䎜痌⚐Ԅ㵄ݚ镐⁶颭塦剘㎢繄?롻㦷䈢矴㤄釤⍪랞륽淽㺎䗩᠇嫉௼䓶⯙啤쓕颽曆᫧꟮╇欙␑代窢뙋奥啣㗛⣞簷̲琑㳰蓪֖㕱揾?눌ⅼ♊ꓔ켫愉໅﷦㥙?蓩딸蕇順閜ၲ렫鉾曟⒵姰汑홫?呝᯿闺컒㜞푭朤㐜ﵼ?驊ἓƃ츱න鸽첸げ텸㼢쫑鸨僦㤣⁭⑄⸰퉔싳ꆺ쾖젔⦭៹䌭璼喀빋䌃⌶砙렯?霕㠫鰌粧脼깩䭼햢?吚傳셑熸㜗⠱诫⏁೓䳟姂頮Ŏ꜋ꭥ꼥ᕳ?⹇䐲쓆㬩泠鿊᧚뢶媹ꨠ賉㛽摨鹛뛍锎๭॰䧳䰪껥鐟법﹣㡎晍ꂈƫ釹?섍ý窸ᶌȵ淶츝댷⹭咺ꝡ藟뜧暯?㖌?ඛₜ廂?銕ᙏ뫂喢ᜋ卦울䙇跺붶௖굴ꈀ韏╌㺋ᵺ功㿙虼ᓯ??Ⰼ飤䥱?ᆜሰ⻘䉇绥౤䉸蛗?둒앋㵏㯗䭤폕᳒藹㺸Ț⚼᷍ꊅ覎뫴ꢹ帷鷇퐋Ἕ괍؆逸씷伕鴇⽈ᮼ컸沲ꇂ袐๾浣?鴯㍂ힹ㋭赝敟徽積掍ꨨ턇䫅泒懲ꕰ⅍趃?Ⴚ蠂︅섞צង袿冣慲辪놭ᡕ꽅㢹孾꽄췾䉕埠풀ㄡ땙Ν쫀渢娐ᘡܙꬂ࣐㳧桖乀ꇚ?㷰鄛셉㳎ഽ䳣㧰酢ᓆ촤躲軥?縄ꄗ㕟⅀듴䙈늂Ďઆ驏흲ረ㽁ꉂ뾩⅐䉮ᔏ씆㒦濹䤝㦒㩬鼭♋☎췬ḩ窑׿흎쳾놫ꉢ㊗碥藙㜛좌ᗑ㜃⼫ﲈ쵾ꍼၬ큸⌶蘏ഇ繊廣䕵쥿꾧Ϩ㮚娽휠ⱌ쉈䏇눭黧쯾౤솇訩ﰷ糙ݏⅺ햃羭蓺蛟黩鲂⊇?潀犪啑팜⿴䷵䖮痲썙⮋ⅶ紲벖뇙诗⤮ⰾ羠玚䟙爀欪俔Ⱅ䀰폨炅飒ᘜ䒜敌鹒딐ฉ奔䫺ꪉ㒥䠅攁ⲙᘨ၁뼣⁽?뇞Ⰳ镭鶔㙏롳⣩뤂埂ፘ需勽嶸⿷醆▚↖ꏝ갲᥻뛽揂躵㰢褵帬䍅槼ԍ埸쀂狥้뒲쁬쮳笑尬㯪敳톗榺х̀Ḑㆺ〥咲?锧ꔼ칵찢◭?붖肥ﴯ㛊䓣퉌䡸ꀏ崍遚얐Ꞷጻ꫖螙꼞꺔푆⓳ﮎ᦭ଲᙃ࿹줋?တ进❴䟆ꤲ趒켋ᣇ冾罫崵륆襠ů㶒鑨ൟꇾ淲⺂洴ె鹶뿙꿒褱｣稧朿弭퐌⃆귔ꃻឫ魮ɕ瑒ඎ↞截བྷ⒂먷氄༅ᆼヅ矾홒둼醔䦁荤⨴文怺偕▇໺䈠툱ở眏賔絓禝瘡ᖰᢢ컩흴ђ쾠럈⏍漙ﶺ牫?迅Ǡ觹ΐ飪?劢盢藥笼Ă嘟૎䝿䜃능윎礃瞊뱤䟕䰙밅૞㪢靖픲勈?圣繭읚꼴劽搎﨎Ԗ鞩?탵秣컎컱펣ॄﳚ饰뀟䔋爘Ს륫箟뇞羨툇챁딙󖨻ⓔ䧸㍮ƃ⹾핪?䁝扃䔧⧉鮯虨ꖧ⋽풸쟪盕畚僿儎禥疥䍩獁䩺더㾝Რﾸ䎣ꠜ뤤絻㑲ᴗ垛屍동㶽遼䔭저紪?㙘?葃윭⾼࿹ᖜ㚻架Ἠ㫑⣻烶㋖ၑ鄊㐪곐还?힫眞粷晸劄촜䰈먥Ქ齻뱕벧該﹖껴ਟ丵짘䟄ྕ羏㊊柖צּꀼ贕诜䈌⤜??㵎㒿獰㞂铡씒?┚ၦ⺞鵔햎㡢∿泖挣ᬔ痧ᘬ謎ஒⅡ࣌Ӥ檚ᖄ笢?끉头閿ꥻ꟩넍쉤㖍ⷄ㱣摃靜柼ಗ秝飽塇⇂鋥‴臻薅ꗥࣶ짯Ҕ惎㺻ؗ蝝늱㬱ໞ庬梳蚔ᢖ䳝㬗㨖ヷﴄ灖퍓鬘鯪ᵓ?활ࠖ훌빜⾾䉧瀘盧⃒ꪆ먀ࢫ꺜⻑紫쳿︫陂䉏源흚煮ഡꁇ旳瑇彮幖돛ɼ傟泩쭡㹈돜​걯ꎘ晐褃縲௒ᚐᮽ㗟䓳ﬦڥ彥굄ꦃ쨃呲ᡒ辉뤓诱喀땱禘蚤ㄿ纈ὦౌ猆䷊헿᧚費葷⟌ᤑ烓▘໴祌嚍ᑅ줠꿛웜㐼媳ꌗྥ趰捴ǧŨ໦傰搾뮙﨡䓹腚?殮ڳ䵣璀屦畈쒶䛹䵾䵒蠱韟㗙鞲?⨸䭽坮蘋챁ҋ뮉 ♔ݯݺ핓ᶔᦞ봇䓂룩㡿皑ꌀ皜㣆뭉骑鴉ꗜ鿯떷㘌촉㔆ɔ쎐洐顏吱?坓⼩₺攔팁ؽ䱀금⃂ந଎ㅨᓳꓙ횾캄ᙧ㤟ｲ⾢㶜棿앗틚䏥鶦?ت䴙Ҽ탫슸偫侫㓃ј㰊⏔研椶ᫎ⦦由ɪట裊敖垬ِ䲓⟙溲ӳ轓Ṝ㜫룚₺⥪䣾템?␲뎩蛊⣰欀즤䉏㘆孑ᴂ뛰வݲ톑悦瘭밷腪?볐푞乎煆鬬ﴥ䋢泝┌陵곒⡑螹繖뱷ⲽ⽾ᅧん䶋迵囹㭍큓㭿囀衆◄睟揿栩脋ῦ⡏릖沺䚦䒾䁞ꩦ蠞嵌Ř刵⇄㋏荎畏샏㩁汞ﱶ㠹䇲油잣䕈⪫ೀⱰ鞾䇭䙸Დ㗟膦嚶嬻酰䒓茞띧঄ă沚狩縱᧠멯ꔒ?⿩꺟㱘⮀閝纏鞕ᵝ蝑헎郪暖䃓嘊鬪쩎쯬邠뾺緽轷뱪꽄愢⛘齪鐚ᇶ燐雑쩯칍−෺㰝뤛拌红䗸㖩㑯岥堔鵙咥Ɲ퍫蘗?멀磲锭隣㢼붮飗㿝⚈掿祦??橒?ꤡ㧄ꆛ賢㔘㨑밽囱㣗췿뭒釅啮걷莊歬┸ῼ貮腨໐ᙸዮ輡묉ᨅ㱆櫖锗ퟭ╲売렺♇ಒ良鱬㧊?ꀭ玕㔲⿿?섗䦂ଦ睰㐑掳꺄걥鬟㐈Թ韢঒朤⎷鼻췀Ꝝ贖䙾풲啱퀜쪚ꢻ㗭䆷㜂鲁钤►?檣맯令왾汗폒볝ᲆ趿踯猶?⼌롿蛻冔棼뎤⦫ㇱૉ堬㙦堬鸇聫Ð⣽㽔ᭋ최兽斡?싓䒲銇ෘ迖굞鉭㗓躻실᧌噵㲁镢쭵∫骵疦㪡體걅貸톆曏액軎깉漖蓄ग़⑧ੈ∁朷힮⥋ꇬꩨ庲൪醰늅䬨욈攔퐕䄺瓭䶰ㄴ頹綢禲球ᴣᦩ鐭飩薽摋ꨂ㧖ಶ駢Ṧ噳㌼ㅬᰉ⺡ａ⦇≒缸븧᡿ᦡ蹕യᧃ申썵쾏á䡝촫ᲅ䄭邍౵锈傳꣊ـ촶㋓쀶咯칝ꗤ刄䭋ᓮ䏢嵈풮摶슇ꢾ﹄尵갩覶챐̞㺑팏Ꮅ鑡眢摍ﴡ檜㻺㫱媔秥꟟?㐘씠쩕壅ᙦৈሲ﯊繛夳꓇藋쀙צ撈罌⾷ຏ郋粵䂙ኈ꫞띔橳딎훡ᰛ沰뭼떆❍䍗毳䫔䎸뺒ꤌꋮ艖檻≘쐿?⨖簐ᯈ焚⬞ﯘハ੔܂蓪阉찵ઑ퀮ي㈎➢䤘ာ덝ᬧ瑾梜ꪺ춘Ѣꗋ욟ꖩ戰憏⑶淘谴጑㄰⹬ᗭ溘눔썋襁ﷺ㫿ᣵ⳦߮ἵ⚩竚Ǵ䗓ᯏ鑺鉅䲓䧮䉸岭⪑哗?铻喾㡣룺켬節봣豿㇨毴ᤠだ淃앶䋽譮ອ꣩퀰招አ雐ᅄ⍏쾲틀ତ渉?⧅㻃壏ㆦȑ寡ත慕죱?梦́蚌䅧窡篑뽝睉騮וֹ妆쫙?고䊼匶藧⵫刖覌૭⪻鿟䫮嘰싵뼬ꨘ蜕ᬆ꛳䮖▷뭕둔遚ᶪ캸猣൉Ƽ鍤Ĩ䬫浄໰䉽넳假꺟魝㿓왱㡌枲ꐪ凣쳩⯺폊싟춐騆⯸햠풵⽣岞耯气㨌굁䚸檲諫䟜㘐属杕ꐊ噐ퟣ鮂ཝ졀舐綤薲勻궍쬰⃡逖㱇ꤨ薈?ᷪ勵ﰮ䃘馉ﭽ࿹뽸輦稈ꮬ᧼潦㢞溟竲ዌ燫褌੧瓎衶츠ꮆ⺸됩ᠴ쬣?⯴Ꭵ뵯ꅅ⻨쀂䮔珪돹Ↄ뱭哱ꫪ忻஢ㆍ筳襝眇䣽绶Ḓ?숞怗祹㎫?팭㫡Ϡ책碆蝩쇹쐣筳ᩎ⥩ᗛࡦ㧮拔꾈狌봔芄ᔡ대ﾡ␧᥻얲敠䗚咰䷆걬軀鸫ͦꪾⓍ温튘푂렒㛞쏸冐≰ⓙꐟ?髵虤䛝ᔨ㊗ꚇ鲟盡틛鑍晑㗇躧㥝ཌྷ啶୮?兣氖ꡮ㊿?栖ⷧ楸?ﰢ䮹턭䥅邇檑?쳇에匣懠ࣚᥔ꧶⾣왪볈Դꛏ礊䬟畑駦筂稈怺瘶虝Ѝ謎絇侯똊枷귥赩姧苧ꑶ걊驰콯䤖ꖊ퇈㺿偢텙ၑ೚❉䊎蹇ᬾ簂Ǣ㔏愡䣘캄잍₨羥柴㏾⨝ᗯ휓꺿㮓兜礢꜏샊餢ﷄ魒ঐ?ꊜ㋜능煎얛खꡉ規෢뉀?㞿涯อ뭐ᓘ⪡㴳倜皘묢侨艐ꮸﱧﾷ꺎掶桏᰷┓嬊꣒ೊ?㟟煎鱑⻋皈涏壵舫畬ᇢ 처⪂㜙㷁?뿱?Წ嵏毲᧦쬄扢γ顏劌욡헯畨딎ﮫ䴧䏋饓⇟틗ᵩ岈?逶캔쫱맵ﮈƣ멸匥鯊隝ꃪ﹏첈忄䨅墋ｋ뚤땠♪ⱱp．ᢗ簉羔뾸澊懨뀛漚ꬣ崊엂纘ᖾ뭷䙾底ꦼ䆭렪ᓍോ㘁셹龔饱⾦辗皽秠텖ʾ곪釢偐᝚ﷳ턞惎籏ꎙ퀕쵲咙?皇竍ꋒ젧Ȓ핕ꗿᩈ칒ह쵧䂠鈐콛蛓ⳝ⁃揧㒔糟舠粰?鶷㬁⽡癲엂⹎升㲋쮻﫴杺［ґ엉㲰꘯믉㶎瑆晜孷㹬턧㍝䣷곭瘪䬘뢪吞㊙쒏鸚噗ᮻᆂ↡칦ࣸ튾ᆮᝊ?忘팦㾭ด쁪렳管縌䇮⺡潅⛶㷼ᄡ펪勠﬒缋勯픃ࣺఱ銳띶쩒降ࡿ?鞚ṏ鍀悖졖몘䢇?腤⳺绥魓⽉흀䎃槣搧묤ꥅ᧫켁쉮콴칩㬴◩뼔廇ﴎԩ酦哱谁䷲?鴦傮걜其ᬂꊶ㓣魫З閆江᷇䫠툥呟ꨃ狩㸗⺑⼸빥紇☨瓄쬤ໜ떱쑌䦀‿鉆構葤뢏訐퓆ۧɦ眏搬Ԥⷣ뾀簐栅ᓲ鐽꟢ꜳꏄӰ⼤቗웬杕絙抙㾍䏳ଉ覉랛跰⚏꺡볔柣ฺ晌긵僔ᠸ⼙䄆೬꯬鬾傠桕꿲뭽榎毮촼꣩ᄇ阝၁屜?줟ည娾綐썃驑㚴ꃐ?탽壆䃼짂㲪쫞蘚艵?ꅤ袕ｅ㥮ꈿ闭␱?㶾౾⛯股熐蛀魵㋃월ᨢ͟꜓䋛쇯䭋䟢損괚폹➛첨䳱凳?㗠뒇?ૅ穽蚴ﹼ䆈쉩妢嫖屟峱?繺휤엥텄貊鞼ꏡ穤ἠ홈좗꬯Ềখ䒼ⴜ?捥蕺蕯㉄⏄လ멷웷舨冺㰭?쮺薵ﱽ勲?㪯兌舷␓䧪ퟝ萮䯜".toCharArray(), (short)15248, false, true)).length(); byte b2 = 64; byte b = -1;
/*     */     while (true);
/*     */   }
/*     */ 
/*     */ 
/*     */ 
/*     */ 
/*     */ 
/*     */ 
/*     */ 
/*     */ 
/*     */ 
/*     */ 
/*     */ 
/*     */ 
/*     */ 
/*     */ 
/*     */ 
/*     */ 
/*     */ 
/*     */ 
/*     */ 
/*     */ 
/*     */ 
/*     */ 
/*     */ 
/*     */ 
/*     */ 
/*     */ 
/*     */ 
/*     */ 
/*     */ 
/*     */ 
/*     */ 
/*     */ 
/*     */ 
/*     */ 
/*     */ 
/*     */ 
/*     */ 
/*     */ 
/*     */   
/*     */   private fn(long paramLong, String paramString) {
/* 156 */     if (paramString == null)
/*     */       throw new NullPointerException(); 
/*     */     this.bf = paramString;
/*     */   }
/*     */   
/*     */   private static String a(String paramString, long paramLong) {
/*     */     // Byte code:
/*     */     //   0: getstatic me/konsolas/aac/fn.cb : J
/*     */     //   3: lload_1
/*     */     //   4: lxor
/*     */     //   5: lstore_1
/*     */     //   6: ldc2_w 5018386378224190822
/*     */     //   9: lload_1
/*     */     //   10: <illegal opcode> w : (JJ)[Lme/konsolas/aac/aN;
/*     */     //   15: astore_3
/*     */     //   16: aload_0
/*     */     //   17: sipush #31480
/*     */     //   20: ldc2_w 4178633224045947559
/*     */     //   23: lload_1
/*     */     //   24: lxor
/*     */     //   25: <illegal opcode> z : (IJ)Ljava/lang/String;
/*     */     //   30: invokevirtual startsWith : (Ljava/lang/String;)Z
/*     */     //   33: aload_3
/*     */     //   34: ifnonnull -> 132
/*     */     //   37: ifeq -> 98
/*     */     //   40: goto -> 53
/*     */     //   43: ldc2_w 4933830873863824343
/*     */     //   46: lload_1
/*     */     //   47: <illegal opcode> w : (Ljava/lang/NullPointerException;JJ)Ljava/lang/NullPointerException;
/*     */     //   52: athrow
/*     */     //   53: new java/lang/StringBuilder
/*     */     //   56: dup
/*     */     //   57: invokespecial <init> : ()V
/*     */     //   60: sipush #29030
/*     */     //   63: ldc2_w 5600329920719118609
/*     */     //   66: lload_1
/*     */     //   67: lxor
/*     */     //   68: <illegal opcode> z : (IJ)Ljava/lang/String;
/*     */     //   73: invokevirtual append : (Ljava/lang/String;)Ljava/lang/StringBuilder;
/*     */     //   76: aload_0
/*     */     //   77: iconst_4
/*     */     //   78: invokevirtual substring : (I)Ljava/lang/String;
/*     */     //   81: invokevirtual append : (Ljava/lang/String;)Ljava/lang/StringBuilder;
/*     */     //   84: invokevirtual toString : ()Ljava/lang/String;
/*     */     //   87: areturn
/*     */     //   88: ldc2_w 4933830873863824343
/*     */     //   91: lload_1
/*     */     //   92: <illegal opcode> w : (Ljava/lang/NullPointerException;JJ)Ljava/lang/NullPointerException;
/*     */     //   97: athrow
/*     */     //   98: aload_0
/*     */     //   99: aload_3
/*     */     //   100: ifnonnull -> 181
/*     */     //   103: sipush #2899
/*     */     //   106: ldc2_w 6776683142350216004
/*     */     //   109: lload_1
/*     */     //   110: lxor
/*     */     //   111: <illegal opcode> z : (IJ)Ljava/lang/String;
/*     */     //   116: invokevirtual startsWith : (Ljava/lang/String;)Z
/*     */     //   119: goto -> 132
/*     */     //   122: ldc2_w 4933830873863824343
/*     */     //   125: lload_1
/*     */     //   126: <illegal opcode> w : (Ljava/lang/NullPointerException;JJ)Ljava/lang/NullPointerException;
/*     */     //   131: athrow
/*     */     //   132: ifeq -> 180
/*     */     //   135: new java/lang/StringBuilder
/*     */     //   138: dup
/*     */     //   139: invokespecial <init> : ()V
/*     */     //   142: sipush #27616
/*     */     //   145: ldc2_w 4088290957709900750
/*     */     //   148: lload_1
/*     */     //   149: lxor
/*     */     //   150: <illegal opcode> z : (IJ)Ljava/lang/String;
/*     */     //   155: invokevirtual append : (Ljava/lang/String;)Ljava/lang/StringBuilder;
/*     */     //   158: aload_0
/*     */     //   159: iconst_4
/*     */     //   160: invokevirtual substring : (I)Ljava/lang/String;
/*     */     //   163: invokevirtual append : (Ljava/lang/String;)Ljava/lang/StringBuilder;
/*     */     //   166: invokevirtual toString : ()Ljava/lang/String;
/*     */     //   169: areturn
/*     */     //   170: ldc2_w 4933830873863824343
/*     */     //   173: lload_1
/*     */     //   174: <illegal opcode> w : (Ljava/lang/NullPointerException;JJ)Ljava/lang/NullPointerException;
/*     */     //   179: athrow
/*     */     //   180: aload_0
/*     */     //   181: areturn
/*     */     // Line number table:
/*     */     //   Java source line number -> byte code offset
/*     */     //   #138	-> 16
/*     */     //   #16	-> 53
/*     */     //   #55	-> 98
/*     */     //   #65	-> 135
/*     */     //   #37	-> 180
/*     */     // Exception table:
/*     */     //   from	to	target	type
/*     */     //   16	40	43	java/lang/NullPointerException
/*     */     //   37	88	88	java/lang/NullPointerException
/*     */     //   98	119	122	java/lang/NullPointerException
/*     */     //   132	170	170	java/lang/NullPointerException
/*     */   }
/*     */   
/*     */   private static NullPointerException a(NullPointerException paramNullPointerException) {
/*     */     return paramNullPointerException;
/*     */   }
/*     */   
/*     */   private static String a(byte[] paramArrayOfbyte) {
/*     */     byte b1 = 0;
/*     */     int i;
/*     */     char[] arrayOfChar = new char[i = paramArrayOfbyte.length];
/*     */     for (byte b2 = 0; b2 < i; b2++) {
/*     */       int j;
/*     */       if ((j = 0xFF & paramArrayOfbyte[b2]) < 192) {
/*     */         arrayOfChar[b1++] = (char)j;
/*     */       } else if (j < 224) {
/*     */         char c = (char)((char)(j & 0x1F) << 6);
/*     */         j = paramArrayOfbyte[++b2];
/*     */         c = (char)(c | (char)(j & 0x3F));
/*     */         arrayOfChar[b1++] = c;
/*     */       } else if (b2 < i - 2) {
/*     */         char c = (char)((char)(j & 0xF) << 12);
/*     */         j = paramArrayOfbyte[++b2];
/*     */         c = (char)(c | (char)(j & 0x3F) << 6);
/*     */         j = paramArrayOfbyte[++b2];
/*     */         c = (char)(c | (char)(j & 0x3F));
/*     */         arrayOfChar[b1++] = c;
/*     */       } 
/*     */     } 
/*     */     return new String(arrayOfChar, 0, b1);
/*     */   }
/*     */   
/*     */   private static String a(int paramInt, long paramLong) {
/*     */     int i = paramInt ^ (int)(paramLong & 0x7FFFL) ^ 0x551A;
/*     */     if (eb[i] == null) {
/*     */       Object[] arrayOfObject;
/*     */       try {
/*     */         Long long_ = Long.valueOf(Thread.currentThread().getId());
/*     */         arrayOfObject = (Object[])fb.get(long_);
/*     */         if (arrayOfObject == null) {
/*     */           arrayOfObject = new Object[3];
/*     */           "⊹䧊옣辬⟂軏?䴯ᜫ盙첖嘇菶뺢꺢Ⴖ㎔᳐뱮⬼".toCharArray()[5] = (char)("⊹䧊옣辬⟂軏?䴯ᜫ盙첖嘇菶뺢꺢Ⴖ㎔᳐뱮⬼".toCharArray()[5] ^ 0x6100);
/*     */           arrayOfObject[0] = Cipher.getInstance(a0$cc.G("⊹䧊옣辬⟂軏?䴯ᜫ盙첖嘇菶뺢꺢Ⴖ㎔᳐뱮⬼".toCharArray(), (short)29456, false, (byte)0));
/*     */           "ႀ홈ˈ".toCharArray()[0] = (char)("ႀ홈ˈ".toCharArray()[0] ^ 0x2FA5);
/*     */           arrayOfObject[1] = SecretKeyFactory.getInstance(a0$cc.G("ႀ홈ˈ".toCharArray(), (short)8712, false, (byte)5));
/*     */           arrayOfObject[2] = new IvParameterSpec(new byte[8]);
/*     */           fb.put(long_, arrayOfObject);
/*     */         } 
/*     */       } catch (Exception exception) {
/*     */         "궵⦊㿓좝ᑷ茞仂鎛䓤零䦊帆ꗺ┽ﰠ⺲媢".toCharArray()[8] = (char)("궵⦊㿓좝ᑷ茞仂鎛䓤零䦊帆ꗺ┽ﰠ⺲媢".toCharArray()[8] ^ 0x7096);
/*     */         throw new RuntimeException(a0$cc.G("궵⦊㿓좝ᑷ茞仂鎛䓤零䦊帆ꗺ┽ﰠ⺲媢".toCharArray(), (short)18627, false, (byte)0), exception);
/*     */       } 
/*     */       byte[] arrayOfByte1 = new byte[8];
/*     */       arrayOfByte1[0] = (byte)(int)(paramLong >>> 56L);
/*     */       for (byte b = 1; b < 8; b++)
/*     */         arrayOfByte1[b] = (byte)(int)(paramLong << b * 8 >>> 56L); 
/*     */       DESKeySpec dESKeySpec = new DESKeySpec(arrayOfByte1);
/*     */       SecretKey secretKey = ((SecretKeyFactory)arrayOfObject[1]).generateSecret(dESKeySpec);
/*     */       ((Cipher)arrayOfObject[0]).init(2, secretKey, (IvParameterSpec)arrayOfObject[2]);
/*     */       "퀜柠昄궠퐯퇴鷏ᐬ?䭷".toCharArray()[5] = (char)("퀜柠昄궠퐯퇴鷏ᐬ?䭷".toCharArray()[5] ^ 0x2C9C);
/*     */       byte[] arrayOfByte2 = db[i].getBytes(a0$cc.G("퀜柠昄궠퐯퇴鷏ᐬ?䭷".toCharArray(), (short)5453, false, (byte)3));
/*     */       eb[i] = a(((Cipher)arrayOfObject[0]).doFinal(arrayOfByte2));
/*     */     } 
/*     */     return eb[i];
/*     */   }
/*     */   
/*     */   private static Object a(MethodHandles.Lookup paramLookup, MutableCallSite paramMutableCallSite, String paramString, Object[] paramArrayOfObject) {
/*     */     int i = ((Integer)paramArrayOfObject[0]).intValue();
/*     */     long l = ((Long)paramArrayOfObject[1]).longValue();
/*     */     String str = a(i, l);
/*     */     MethodHandle methodHandle = MethodHandles.constant(String.class, str);
/*     */     paramMutableCallSite.setTarget(MethodHandles.dropArguments(methodHandle, 0, new Class[] { int.class, long.class }));
/*     */     return str;
/*     */   }
/*     */   
/*     */   private static CallSite a(MethodHandles.Lookup paramLookup, String paramString, MethodType paramMethodType) {
/*     */     // Byte code:
/*     */     //   0: new java/lang/invoke/MutableCallSite
/*     */     //   3: dup
/*     */     //   4: aload_2
/*     */     //   5: invokespecial <init> : (Ljava/lang/invoke/MethodType;)V
/*     */     //   8: astore_3
/*     */     //   9: aload_3
/*     */     //   10: ldc_w
/*     */     //   13: ldc_w [Ljava/lang/Object;
/*     */     //   16: aload_2
/*     */     //   17: invokevirtual parameterCount : ()I
/*     */     //   20: invokevirtual asCollector : (Ljava/lang/Class;I)Ljava/lang/invoke/MethodHandle;
/*     */     //   23: iconst_0
/*     */     //   24: iconst_3
/*     */     //   25: anewarray java/lang/Object
/*     */     //   28: dup
/*     */     //   29: iconst_0
/*     */     //   30: aload_0
/*     */     //   31: aastore
/*     */     //   32: dup
/*     */     //   33: iconst_1
/*     */     //   34: aload_3
/*     */     //   35: aastore
/*     */     //   36: dup
/*     */     //   37: iconst_2
/*     */     //   38: aload_1
/*     */     //   39: aastore
/*     */     //   40: invokestatic insertArguments : (Ljava/lang/invoke/MethodHandle;I[Ljava/lang/Object;)Ljava/lang/invoke/MethodHandle;
/*     */     //   43: aload_2
/*     */     //   44: invokestatic explicitCastArguments : (Ljava/lang/invoke/MethodHandle;Ljava/lang/invoke/MethodType;)Ljava/lang/invoke/MethodHandle;
/*     */     //   47: invokevirtual setTarget : (Ljava/lang/invoke/MethodHandle;)V
/*     */     //   50: goto -> 170
/*     */     //   53: astore #4
/*     */     //   55: new java/lang/RuntimeException
/*     */     //   58: dup
/*     */     //   59: new java/lang/StringBuilder
/*     */     //   62: dup
/*     */     //   63: invokespecial <init> : ()V
/*     */     //   66: ldc_w 'ᒡ桻䈂ೣ䵟懚娋呀镲쳤캁隿㞣䣓ꬢ卉'
/*     */     //   69: invokevirtual toCharArray : ()[C
/*     */     //   72: dup
/*     */     //   73: dup
/*     */     //   74: iconst_1
/*     */     //   75: dup_x1
/*     */     //   76: caload
/*     */     //   77: sipush #24660
/*     */     //   80: ixor
/*     */     //   81: i2c
/*     */     //   82: castore
/*     */     //   83: sipush #21982
/*     */     //   86: iconst_5
/*     */     //   87: iconst_1
/*     */     //   88: invokestatic H : (Ljava/lang/Object;SBB)Ljava/lang/String;
/*     */     //   91: invokevirtual append : (Ljava/lang/String;)Ljava/lang/StringBuilder;
/*     */     //   94: ldc_w '쓂ꬱ䎡㡵'
/*     */     //   97: invokevirtual toCharArray : ()[C
/*     */     //   100: dup
/*     */     //   101: dup
/*     */     //   102: iconst_2
/*     */     //   103: dup_x1
/*     */     //   104: caload
/*     */     //   105: sipush #10402
/*     */     //   108: ixor
/*     */     //   109: i2c
/*     */     //   110: castore
/*     */     //   111: sipush #31270
/*     */     //   114: iconst_1
/*     */     //   115: iconst_3
/*     */     //   116: invokestatic H : (Ljava/lang/Object;SBB)Ljava/lang/String;
/*     */     //   119: invokevirtual append : (Ljava/lang/String;)Ljava/lang/StringBuilder;
/*     */     //   122: aload_1
/*     */     //   123: invokevirtual append : (Ljava/lang/String;)Ljava/lang/StringBuilder;
/*     */     //   126: ldc_w '嵷鰎팋矡'
/*     */     //   129: invokevirtual toCharArray : ()[C
/*     */     //   132: dup
/*     */     //   133: dup
/*     */     //   134: iconst_0
/*     */     //   135: dup_x1
/*     */     //   136: caload
/*     */     //   137: sipush #19969
/*     */     //   140: ixor
/*     */     //   141: i2c
/*     */     //   142: castore
/*     */     //   143: sipush #3972
/*     */     //   146: iconst_2
/*     */     //   147: iconst_2
/*     */     //   148: invokestatic H : (Ljava/lang/Object;SBB)Ljava/lang/String;
/*     */     //   151: invokevirtual append : (Ljava/lang/String;)Ljava/lang/StringBuilder;
/*     */     //   154: aload_2
/*     */     //   155: invokevirtual toString : ()Ljava/lang/String;
/*     */     //   158: invokevirtual append : (Ljava/lang/String;)Ljava/lang/StringBuilder;
/*     */     //   161: invokevirtual toString : ()Ljava/lang/String;
/*     */     //   164: aload #4
/*     */     //   166: invokespecial <init> : (Ljava/lang/String;Ljava/lang/Throwable;)V
/*     */     //   169: athrow
/*     */     //   170: aload_3
/*     */     //   171: areturn
/*     */     // Exception table:
/*     */     //   from	to	target	type
/*     */     //   9	50	53	java/lang/Exception
/*     */   } }


/* Location:              C:\Users\BukkitBypass\Desktop\MatrixAC\AAC\AAC-spigot-5.2.0.jar!\me\konsolas\aac\fn.class
 * Java compiler version: 8 (52.0)
 * JD-Core Version:       1.1.3
 */