/*     */ package me.konsolas.aac;
/*     */ 
/*     */ import java.lang.invoke.CallSite;
/*     */ import java.lang.invoke.MethodHandle;
/*     */ import java.lang.invoke.MethodHandles;
/*     */ import java.lang.invoke.MethodType;
/*     */ import java.lang.invoke.MutableCallSite;
/*     */ import java.util.HashMap;
/*     */ import java.util.List;
/*     */ import java.util.Map;
/*     */ import javax.annotation.Nullable;
/*     */ import javax.crypto.Cipher;
/*     */ import javax.crypto.SecretKey;
/*     */ import javax.crypto.SecretKeyFactory;
/*     */ import javax.crypto.spec.DESKeySpec;
/*     */ import javax.crypto.spec.IvParameterSpec;
/*     */ 
/*     */ 
/*     */ 
/*     */ 
/*     */ 
/*     */ 
/*     */ 
/*     */ 
/*     */ 
/*     */ 
/*     */ 
/*     */ 
/*     */ 
/*     */ 
/*     */ 
/*     */ 
/*     */ 
/*     */ 
/*     */ 
/*     */ 
/*     */ 
/*     */ 
/*     */ 
/*     */ 
/*     */ 
/*     */ 
/*     */ 
/*     */ 
/*     */ 
/*     */ 
/*     */ 
/*     */ 
/*     */ 
/*     */ 
/*     */ 
/*     */ 
/*     */ 
/*     */ 
/*     */ 
/*     */ 
/*     */ 
/*     */ 
/*     */ 
/*     */ 
/*     */ 
/*     */ 
/*     */ 
/*     */ 
/*     */ 
/*     */ 
/*     */ 
/*     */ 
/*     */ 
/*     */ final class fz
/*     */ {
/*     */   private static final String l;
/*     */   private static final String g;
/*     */   private final String i;
/*     */   private final J d;
/*     */   private final String a;
/*     */   private final le j;
/*     */   private final int h;
/*     */   private final String e;
/*     */   private final J b;
/*     */   @Nullable
/*     */   private final it k;
/*     */   private final long f;
/*     */   private final long c;
/*     */   private static final long m;
/*     */   private static final String[] n;
/*     */   private static final String[] o;
/*     */   private static final Map p;
/*     */   
/*     */   fz(hp paramhp, long paramLong) {
/*     */     // Byte code:
/*     */     //   0: getstatic me/konsolas/aac/fz.m : J
/*     */     //   3: lload_2
/*     */     //   4: lxor
/*     */     //   5: lstore_2
/*     */     //   6: lload_2
/*     */     //   7: dup2
/*     */     //   8: ldc2_w 16334660620119
/*     */     //   11: lxor
/*     */     //   12: lstore #4
/*     */     //   14: dup2
/*     */     //   15: ldc2_w 1154953320186
/*     */     //   18: lxor
/*     */     //   19: lstore #6
/*     */     //   21: dup2
/*     */     //   22: ldc2_w 60000357479771
/*     */     //   25: lxor
/*     */     //   26: lstore #8
/*     */     //   28: dup2
/*     */     //   29: ldc2_w 128471167165663
/*     */     //   32: lxor
/*     */     //   33: dup2
/*     */     //   34: bipush #48
/*     */     //   36: lushr
/*     */     //   37: l2i
/*     */     //   38: istore #10
/*     */     //   40: dup2
/*     */     //   41: bipush #16
/*     */     //   43: lshl
/*     */     //   44: bipush #48
/*     */     //   46: lushr
/*     */     //   47: l2i
/*     */     //   48: istore #11
/*     */     //   50: dup2
/*     */     //   51: bipush #32
/*     */     //   53: lshl
/*     */     //   54: bipush #32
/*     */     //   56: lushr
/*     */     //   57: l2i
/*     */     //   58: istore #12
/*     */     //   60: pop2
/*     */     //   61: dup2
/*     */     //   62: ldc2_w 137400802556021
/*     */     //   65: lxor
/*     */     //   66: lstore #13
/*     */     //   68: dup2
/*     */     //   69: ldc2_w 122336353797668
/*     */     //   72: lxor
/*     */     //   73: lstore #15
/*     */     //   75: dup2
/*     */     //   76: ldc2_w 73479107992651
/*     */     //   79: lxor
/*     */     //   80: lstore #17
/*     */     //   82: dup2
/*     */     //   83: ldc2_w 132493643243829
/*     */     //   86: lxor
/*     */     //   87: dup2
/*     */     //   88: bipush #32
/*     */     //   90: lushr
/*     */     //   91: l2i
/*     */     //   92: istore #19
/*     */     //   94: dup2
/*     */     //   95: bipush #32
/*     */     //   97: lshl
/*     */     //   98: bipush #48
/*     */     //   100: lushr
/*     */     //   101: l2i
/*     */     //   102: istore #20
/*     */     //   104: dup2
/*     */     //   105: bipush #48
/*     */     //   107: lshl
/*     */     //   108: bipush #48
/*     */     //   110: lushr
/*     */     //   111: l2i
/*     */     //   112: istore #21
/*     */     //   114: pop2
/*     */     //   115: dup2
/*     */     //   116: ldc2_w 16155682266875
/*     */     //   119: lxor
/*     */     //   120: lstore #22
/*     */     //   122: dup2
/*     */     //   123: ldc2_w 130610128188601
/*     */     //   126: lxor
/*     */     //   127: lstore #24
/*     */     //   129: dup2
/*     */     //   130: ldc2_w 93350808174034
/*     */     //   133: lxor
/*     */     //   134: dup2
/*     */     //   135: bipush #48
/*     */     //   137: lushr
/*     */     //   138: l2i
/*     */     //   139: istore #26
/*     */     //   141: dup2
/*     */     //   142: bipush #16
/*     */     //   144: lshl
/*     */     //   145: bipush #48
/*     */     //   147: lushr
/*     */     //   148: l2i
/*     */     //   149: istore #27
/*     */     //   151: dup2
/*     */     //   152: bipush #32
/*     */     //   154: lshl
/*     */     //   155: bipush #32
/*     */     //   157: lushr
/*     */     //   158: l2i
/*     */     //   159: istore #28
/*     */     //   161: pop2
/*     */     //   162: dup2
/*     */     //   163: ldc2_w 39007148451239
/*     */     //   166: lxor
/*     */     //   167: lstore #29
/*     */     //   169: dup2
/*     */     //   170: ldc2_w 127747158792455
/*     */     //   173: lxor
/*     */     //   174: lstore #31
/*     */     //   176: pop2
/*     */     //   177: ldc2_w 7531041758674970689
/*     */     //   180: lload_2
/*     */     //   181: <illegal opcode> w : (JJ)[Lme/konsolas/aac/aN;
/*     */     //   186: aload_0
/*     */     //   187: invokespecial <init> : ()V
/*     */     //   190: astore #33
/*     */     //   192: iload #10
/*     */     //   194: i2s
/*     */     //   195: aload_1
/*     */     //   196: iload #11
/*     */     //   198: i2c
/*     */     //   199: iload #12
/*     */     //   201: invokestatic a : (SLme/konsolas/aac/hp;CI)Lme/konsolas/aac/bX;
/*     */     //   204: astore #34
/*     */     //   206: aload_0
/*     */     //   207: aload #34
/*     */     //   209: iload #26
/*     */     //   211: i2s
/*     */     //   212: iload #27
/*     */     //   214: i2s
/*     */     //   215: iload #28
/*     */     //   217: invokeinterface b : (SSI)Ljava/lang/String;
/*     */     //   222: putfield i : Ljava/lang/String;
/*     */     //   225: aload_0
/*     */     //   226: aload #34
/*     */     //   228: iload #26
/*     */     //   230: i2s
/*     */     //   231: iload #27
/*     */     //   233: i2s
/*     */     //   234: iload #28
/*     */     //   236: invokeinterface b : (SSI)Ljava/lang/String;
/*     */     //   241: putfield a : Ljava/lang/String;
/*     */     //   244: new me/konsolas/aac/mr
/*     */     //   247: dup
/*     */     //   248: invokespecial <init> : ()V
/*     */     //   251: astore #35
/*     */     //   253: lload #13
/*     */     //   255: aload #34
/*     */     //   257: invokestatic a : (JLme/konsolas/aac/bX;)I
/*     */     //   260: istore #36
/*     */     //   262: iconst_0
/*     */     //   263: istore #37
/*     */     //   265: iload #37
/*     */     //   267: iload #36
/*     */     //   269: if_icmpge -> 333
/*     */     //   272: aload #35
/*     */     //   274: aload #34
/*     */     //   276: iload #26
/*     */     //   278: i2s
/*     */     //   279: iload #27
/*     */     //   281: i2s
/*     */     //   282: iload #28
/*     */     //   284: invokeinterface b : (SSI)Ljava/lang/String;
/*     */     //   289: lload #29
/*     */     //   291: invokevirtual a : (Ljava/lang/String;J)Lme/konsolas/aac/mr;
/*     */     //   294: pop
/*     */     //   295: iinc #37, 1
/*     */     //   298: aload #33
/*     */     //   300: lload_2
/*     */     //   301: lconst_0
/*     */     //   302: lcmp
/*     */     //   303: iflt -> 311
/*     */     //   306: ifnonnull -> 342
/*     */     //   309: aload #33
/*     */     //   311: ifnull -> 265
/*     */     //   314: lload_2
/*     */     //   315: lconst_0
/*     */     //   316: lcmp
/*     */     //   317: iflt -> 298
/*     */     //   320: goto -> 333
/*     */     //   323: ldc2_w 7536792595149072515
/*     */     //   326: lload_2
/*     */     //   327: <illegal opcode> w : (Ljava/lang/Exception;JJ)Ljava/lang/Exception;
/*     */     //   332: athrow
/*     */     //   333: aload_0
/*     */     //   334: aload #35
/*     */     //   336: invokevirtual a : ()Lme/konsolas/aac/J;
/*     */     //   339: putfield d : Lme/konsolas/aac/J;
/*     */     //   342: aload #34
/*     */     //   344: iload #26
/*     */     //   346: i2s
/*     */     //   347: iload #27
/*     */     //   349: i2s
/*     */     //   350: iload #28
/*     */     //   352: invokeinterface b : (SSI)Ljava/lang/String;
/*     */     //   357: lload #24
/*     */     //   359: invokestatic a : (Ljava/lang/String;J)Lme/konsolas/aac/i8;
/*     */     //   362: astore #37
/*     */     //   364: aload_0
/*     */     //   365: aload #37
/*     */     //   367: getfield a : Lme/konsolas/aac/le;
/*     */     //   370: putfield j : Lme/konsolas/aac/le;
/*     */     //   373: aload_0
/*     */     //   374: aload #37
/*     */     //   376: getfield c : I
/*     */     //   379: putfield h : I
/*     */     //   382: aload_0
/*     */     //   383: aload #37
/*     */     //   385: getfield f : Ljava/lang/String;
/*     */     //   388: putfield e : Ljava/lang/String;
/*     */     //   391: new me/konsolas/aac/mr
/*     */     //   394: dup
/*     */     //   395: invokespecial <init> : ()V
/*     */     //   398: astore #38
/*     */     //   400: lload #13
/*     */     //   402: aload #34
/*     */     //   404: invokestatic a : (JLme/konsolas/aac/bX;)I
/*     */     //   407: istore #39
/*     */     //   409: iconst_0
/*     */     //   410: istore #40
/*     */     //   412: iload #40
/*     */     //   414: iload #39
/*     */     //   416: if_icmpge -> 480
/*     */     //   419: lload_2
/*     */     //   420: lconst_0
/*     */     //   421: lcmp
/*     */     //   422: iflt -> 456
/*     */     //   425: aload #38
/*     */     //   427: aload #34
/*     */     //   429: iload #26
/*     */     //   431: i2s
/*     */     //   432: iload #27
/*     */     //   434: i2s
/*     */     //   435: iload #28
/*     */     //   437: invokeinterface b : (SSI)Ljava/lang/String;
/*     */     //   442: lload #29
/*     */     //   444: invokevirtual a : (Ljava/lang/String;J)Lme/konsolas/aac/mr;
/*     */     //   447: aload #33
/*     */     //   449: ifnonnull -> 482
/*     */     //   452: pop
/*     */     //   453: iinc #40, 1
/*     */     //   456: aload #33
/*     */     //   458: ifnull -> 412
/*     */     //   461: lload_2
/*     */     //   462: lconst_0
/*     */     //   463: lcmp
/*     */     //   464: ifle -> 419
/*     */     //   467: goto -> 480
/*     */     //   470: ldc2_w 7536792595149072515
/*     */     //   473: lload_2
/*     */     //   474: <illegal opcode> w : (Ljava/lang/Exception;JJ)Ljava/lang/Exception;
/*     */     //   479: athrow
/*     */     //   480: aload #38
/*     */     //   482: lload #22
/*     */     //   484: getstatic me/konsolas/aac/fz.l : Ljava/lang/String;
/*     */     //   487: invokevirtual a : (JLjava/lang/String;)Ljava/lang/String;
/*     */     //   490: astore #40
/*     */     //   492: aload #38
/*     */     //   494: lload #22
/*     */     //   496: getstatic me/konsolas/aac/fz.g : Ljava/lang/String;
/*     */     //   499: invokevirtual a : (JLjava/lang/String;)Ljava/lang/String;
/*     */     //   502: astore #41
/*     */     //   504: aload #38
/*     */     //   506: lload #15
/*     */     //   508: getstatic me/konsolas/aac/fz.l : Ljava/lang/String;
/*     */     //   511: invokevirtual c : (JLjava/lang/String;)Lme/konsolas/aac/mr;
/*     */     //   514: pop
/*     */     //   515: aload #38
/*     */     //   517: lload #15
/*     */     //   519: getstatic me/konsolas/aac/fz.g : Ljava/lang/String;
/*     */     //   522: invokevirtual c : (JLjava/lang/String;)Lme/konsolas/aac/mr;
/*     */     //   525: pop
/*     */     //   526: aload_0
/*     */     //   527: aload #40
/*     */     //   529: aload #33
/*     */     //   531: ifnonnull -> 552
/*     */     //   534: ifnull -> 558
/*     */     //   537: goto -> 550
/*     */     //   540: ldc2_w 7536792595149072515
/*     */     //   543: lload_2
/*     */     //   544: <illegal opcode> w : (Ljava/lang/Exception;JJ)Ljava/lang/Exception;
/*     */     //   549: athrow
/*     */     //   550: aload #40
/*     */     //   552: invokestatic parseLong : (Ljava/lang/String;)J
/*     */     //   555: goto -> 559
/*     */     //   558: lconst_0
/*     */     //   559: lload_2
/*     */     //   560: lconst_0
/*     */     //   561: lcmp
/*     */     //   562: iflt -> 597
/*     */     //   565: putfield f : J
/*     */     //   568: aload_0
/*     */     //   569: aload #41
/*     */     //   571: aload #33
/*     */     //   573: ifnonnull -> 594
/*     */     //   576: ifnull -> 600
/*     */     //   579: goto -> 592
/*     */     //   582: ldc2_w 7536792595149072515
/*     */     //   585: lload_2
/*     */     //   586: <illegal opcode> w : (Ljava/lang/Exception;JJ)Ljava/lang/Exception;
/*     */     //   591: athrow
/*     */     //   592: aload #41
/*     */     //   594: invokestatic parseLong : (Ljava/lang/String;)J
/*     */     //   597: goto -> 601
/*     */     //   600: lconst_0
/*     */     //   601: lload_2
/*     */     //   602: lconst_0
/*     */     //   603: lcmp
/*     */     //   604: iflt -> 627
/*     */     //   607: putfield c : J
/*     */     //   610: aload_0
/*     */     //   611: aload #38
/*     */     //   613: invokevirtual a : ()Lme/konsolas/aac/J;
/*     */     //   616: putfield b : Lme/konsolas/aac/J;
/*     */     //   619: aload_0
/*     */     //   620: aload #33
/*     */     //   622: ifnonnull -> 931
/*     */     //   625: lload #17
/*     */     //   627: invokespecial a : (J)Z
/*     */     //   630: ifeq -> 917
/*     */     //   633: goto -> 646
/*     */     //   636: ldc2_w 7536792595149072515
/*     */     //   639: lload_2
/*     */     //   640: <illegal opcode> w : (Ljava/lang/Exception;JJ)Ljava/lang/Exception;
/*     */     //   645: athrow
/*     */     //   646: aload #34
/*     */     //   648: iload #26
/*     */     //   650: i2s
/*     */     //   651: iload #27
/*     */     //   653: i2s
/*     */     //   654: iload #28
/*     */     //   656: invokeinterface b : (SSI)Ljava/lang/String;
/*     */     //   661: astore #42
/*     */     //   663: aload #42
/*     */     //   665: aload #33
/*     */     //   667: ifnonnull -> 780
/*     */     //   670: invokevirtual length : ()I
/*     */     //   673: ifle -> 765
/*     */     //   676: goto -> 689
/*     */     //   679: ldc2_w 7536792595149072515
/*     */     //   682: lload_2
/*     */     //   683: <illegal opcode> w : (Ljava/lang/Exception;JJ)Ljava/lang/Exception;
/*     */     //   688: athrow
/*     */     //   689: new java/io/IOException
/*     */     //   692: dup
/*     */     //   693: new java/lang/StringBuilder
/*     */     //   696: dup
/*     */     //   697: invokespecial <init> : ()V
/*     */     //   700: sipush #27627
/*     */     //   703: ldc2_w 3190654872746967041
/*     */     //   706: lload_2
/*     */     //   707: lxor
/*     */     //   708: <illegal opcode> t : (IJ)Ljava/lang/String;
/*     */     //   713: invokevirtual append : (Ljava/lang/String;)Ljava/lang/StringBuilder;
/*     */     //   716: aload #42
/*     */     //   718: invokevirtual append : (Ljava/lang/String;)Ljava/lang/StringBuilder;
/*     */     //   721: ldc '♪䠎'
/*     */     //   723: invokevirtual toCharArray : ()[C
/*     */     //   726: dup
/*     */     //   727: dup
/*     */     //   728: iconst_0
/*     */     //   729: dup_x1
/*     */     //   730: caload
/*     */     //   731: sipush #855
/*     */     //   734: ixor
/*     */     //   735: i2c
/*     */     //   736: castore
/*     */     //   737: sipush #24556
/*     */     //   740: iconst_1
/*     */     //   741: iconst_0
/*     */     //   742: invokestatic X : (Ljava/lang/Object;SZZ)Ljava/lang/String;
/*     */     //   745: invokevirtual append : (Ljava/lang/String;)Ljava/lang/StringBuilder;
/*     */     //   748: invokevirtual toString : ()Ljava/lang/String;
/*     */     //   751: invokespecial <init> : (Ljava/lang/String;)V
/*     */     //   754: athrow
/*     */     //   755: ldc2_w 7536792595149072515
/*     */     //   758: lload_2
/*     */     //   759: <illegal opcode> w : (Ljava/lang/Exception;JJ)Ljava/lang/Exception;
/*     */     //   764: athrow
/*     */     //   765: aload #34
/*     */     //   767: iload #26
/*     */     //   769: i2s
/*     */     //   770: iload #27
/*     */     //   772: i2s
/*     */     //   773: iload #28
/*     */     //   775: invokeinterface b : (SSI)Ljava/lang/String;
/*     */     //   780: astore #43
/*     */     //   782: aload #43
/*     */     //   784: lload #6
/*     */     //   786: invokestatic a : (Ljava/lang/String;J)Lme/konsolas/aac/fn;
/*     */     //   789: astore #44
/*     */     //   791: aload_0
/*     */     //   792: aload #34
/*     */     //   794: lload #4
/*     */     //   796: invokespecial a : (Lme/konsolas/aac/bX;J)Ljava/util/List;
/*     */     //   799: astore #45
/*     */     //   801: aload_0
/*     */     //   802: aload #34
/*     */     //   804: lload #4
/*     */     //   806: invokespecial a : (Lme/konsolas/aac/bX;J)Ljava/util/List;
/*     */     //   809: astore #46
/*     */     //   811: aload #34
/*     */     //   813: aload #33
/*     */     //   815: ifnonnull -> 861
/*     */     //   818: iload #19
/*     */     //   820: iload #20
/*     */     //   822: i2c
/*     */     //   823: iload #21
/*     */     //   825: invokeinterface a : (ICI)Z
/*     */     //   830: ifne -> 884
/*     */     //   833: goto -> 846
/*     */     //   836: ldc2_w 7536792595149072515
/*     */     //   839: lload_2
/*     */     //   840: <illegal opcode> w : (Ljava/lang/Exception;JJ)Ljava/lang/Exception;
/*     */     //   845: athrow
/*     */     //   846: aload #34
/*     */     //   848: goto -> 861
/*     */     //   851: ldc2_w 7536792595149072515
/*     */     //   854: lload_2
/*     */     //   855: <illegal opcode> w : (Ljava/lang/Exception;JJ)Ljava/lang/Exception;
/*     */     //   860: athrow
/*     */     //   861: iload #26
/*     */     //   863: i2s
/*     */     //   864: iload #27
/*     */     //   866: i2s
/*     */     //   867: iload #28
/*     */     //   869: invokeinterface b : (SSI)Ljava/lang/String;
/*     */     //   874: lload #8
/*     */     //   876: dup2_x1
/*     */     //   877: pop2
/*     */     //   878: invokestatic a : (JLjava/lang/String;)Lme/konsolas/aac/iy;
/*     */     //   881: goto -> 887
/*     */     //   884: getstatic me/konsolas/aac/iy.SSL_3_0 : Lme/konsolas/aac/iy;
/*     */     //   887: astore #47
/*     */     //   889: aload_0
/*     */     //   890: aload #47
/*     */     //   892: aload #44
/*     */     //   894: aload #45
/*     */     //   896: aload #46
/*     */     //   898: lload #31
/*     */     //   900: invokestatic a : (Lme/konsolas/aac/iy;Lme/konsolas/aac/fn;Ljava/util/List;Ljava/util/List;J)Lme/konsolas/aac/it;
/*     */     //   903: putfield k : Lme/konsolas/aac/it;
/*     */     //   906: lload_2
/*     */     //   907: lconst_0
/*     */     //   908: lcmp
/*     */     //   909: iflt -> 941
/*     */     //   912: aload #33
/*     */     //   914: ifnull -> 935
/*     */     //   917: aload_0
/*     */     //   918: goto -> 931
/*     */     //   921: ldc2_w 7536792595149072515
/*     */     //   924: lload_2
/*     */     //   925: <illegal opcode> w : (Ljava/lang/Exception;JJ)Ljava/lang/Exception;
/*     */     //   930: athrow
/*     */     //   931: aconst_null
/*     */     //   932: putfield k : Lme/konsolas/aac/it;
/*     */     //   935: aload_1
/*     */     //   936: invokeinterface close : ()V
/*     */     //   941: goto -> 955
/*     */     //   944: astore #48
/*     */     //   946: aload_1
/*     */     //   947: invokeinterface close : ()V
/*     */     //   952: aload #48
/*     */     //   954: athrow
/*     */     //   955: return
/*     */     // Line number table:
/*     */     //   Java source line number -> byte code offset
/*     */     //   #11	-> 186
/*     */     //   #51	-> 192
/*     */     //   #78	-> 206
/*     */     //   #5	-> 225
/*     */     //   #125	-> 244
/*     */     //   #150	-> 253
/*     */     //   #39	-> 262
/*     */     //   #128	-> 272
/*     */     //   #81	-> 295
/*     */     //   #111	-> 333
/*     */     //   #34	-> 342
/*     */     //   #127	-> 364
/*     */     //   #151	-> 373
/*     */     //   #75	-> 382
/*     */     //   #83	-> 391
/*     */     //   #44	-> 400
/*     */     //   #56	-> 409
/*     */     //   #14	-> 419
/*     */     //   #148	-> 453
/*     */     //   #143	-> 480
/*     */     //   #132	-> 492
/*     */     //   #22	-> 504
/*     */     //   #113	-> 515
/*     */     //   #119	-> 526
/*     */     //   #92	-> 550
/*     */     //   #140	-> 558
/*     */     //   #82	-> 568
/*     */     //   #45	-> 592
/*     */     //   #28	-> 600
/*     */     //   #55	-> 610
/*     */     //   #57	-> 619
/*     */     //   #129	-> 646
/*     */     //   #98	-> 663
/*     */     //   #144	-> 689
/*     */     //   #145	-> 765
/*     */     //   #114	-> 782
/*     */     //   #29	-> 791
/*     */     //   #122	-> 801
/*     */     //   #25	-> 811
/*     */     //   #136	-> 846
/*     */     //   #105	-> 884
/*     */     //   #118	-> 889
/*     */     //   #64	-> 906
/*     */     //   #135	-> 917
/*     */     //   #1	-> 935
/*     */     //   #87	-> 941
/*     */     //   #65	-> 944
/*     */     //   #33	-> 955
/*     */     // Exception table:
/*     */     //   from	to	target	type
/*     */     //   192	935	944	finally
/*     */     //   272	314	323	java/io/IOException
/*     */     //   419	461	470	java/io/IOException
/*     */     //   504	537	540	java/io/IOException
/*     */     //   559	579	582	java/io/IOException
/*     */     //   601	633	636	java/io/IOException
/*     */     //   663	676	679	java/io/IOException
/*     */     //   670	755	755	java/io/IOException
/*     */     //   811	833	836	java/io/IOException
/*     */     //   818	848	851	java/io/IOException
/*     */     //   889	918	921	java/io/IOException
/*     */     //   944	946	944	finally
/*     */   }
/*     */   
/*     */   fz(H paramH, short paramShort1, int paramInt, short paramShort2) {
/*  95 */     this.i = paramH.a().a().toString();
/*     */ 
/*     */ 
/*     */ 
/*     */ 
/*     */ 
/*     */ 
/*     */ 
/*     */ 
/*     */ 
/*     */ 
/*     */ 
/*     */ 
/*     */ 
/*     */     
/* 110 */     this.d = gz.a(paramH, l2);
/*     */ 
/*     */ 
/*     */ 
/*     */ 
/*     */ 
/*     */ 
/*     */ 
/*     */ 
/*     */ 
/*     */ 
/*     */ 
/*     */ 
/*     */ 
/*     */ 
/*     */     
/*     */     this.a = paramH.a().a();
/*     */ 
/*     */ 
/*     */ 
/*     */ 
/*     */ 
/*     */ 
/*     */ 
/*     */ 
/*     */ 
/*     */ 
/*     */ 
/*     */ 
/*     */ 
/*     */     
/* 141 */     this.j = paramH.a();
/*     */     this.h = paramH.a();
/*     */     this.e = paramH.a();
/*     */     this.b = paramH.a();
/*     */     this.k = paramH.a();
/*     */     this.f = paramH.a();
/*     */     this.c = paramH.b();
/*     */   }
/*     */   
/*     */   static {
/*     */     byte b1;
/*     */     long l1, l2;
/*     */     for (m = nc.a(-5971985887273882962L, -5054974568853665402L, MethodHandles.lookup().lookupClass()).a(195593588379495L), l1 = m ^ 0x7B5CE36DB5F5L, l2 = l1 ^ 0x579884C5713EL, p = new HashMap<>(13), "锌蚔⌸顟좝螃쫰웶苛ᣮ᪚墇鶏ᗍ⌓恬⇥?䊫".toCharArray()[3] = (char)("锌蚔⌸顟좝螃쫰웶苛ᣮ᪚墇鶏ᗍ⌓恬⇥?䊫".toCharArray()[3] ^ 0x3E1A), "㯧뢟Ú䠠".toCharArray()[0] = (char)("㯧뢟Ú䠠".toCharArray()[0] ^ 0x1134), (new byte[8])[0] = (byte)(int)(l1 >>> 56L), b1 = 1; b1 < 8; ) {
/*     */       (new byte[8])[b1] = (byte)(int)(l1 << b1 * 8 >>> 56L);
/*     */       b1++;
/*     */     } 
/*     */     Cipher cipher;
/*     */     (cipher = Cipher.getInstance(hY$g6.H("锌蚔⌸顟좝螃쫰웶苛ᣮ᪚墇鶏ᗍ⌓恬⇥?䊫".toCharArray(), (short)32177, (byte)2, (byte)3))).init(2, SecretKeyFactory.getInstance(hY$g6.H("㯧뢟Ú䠠".toCharArray(), (short)31597, (byte)4, (byte)3)).generateSecret(new DESKeySpec(new byte[8])), new IvParameterSpec(new byte[8]));
/*     */     String[] arrayOfString = new String[9];
/*     */     boolean bool = false;
/*     */     "둭소㓘鐹僼⤎ᵎꦥ鷸蘧ᎏ䯅蝔풇㡓뿅邸봽?⏌㳅§䉬눩㈙牀쎨茇䐠랊炦濾ဳ䌹욢Ϯ⻠ข䑉ﶙ粅ꮛꥑ鬎삒떷猜릴㾴夫️䦧얘⮐骙ॅ࿱ല擐뻕㐧ᯒ釓嬞귤饍䁆鐴밾簃艎竨숁猖냙쓔툔嶈橊ꅾ禕툟Ⱬ匓墐⣾澿砒坂瑒詼䋶ᵮ귋빘鼻ᓩ챿㓗᰸勘瓫ạ뾙১?扲⟚ࠤ⨠싇一쥖脽ᤄ뀴鲖ハ㱱ﯸ?豘偾阌?酈羪럼჻縖쎽ܛ탹?罧梁ଉ㉬鄧䎚갑衙촵䚨츃ꋞ쏽㻣鄌汿릐螦灙땘ᑟ䡌僡닎痠?晿柉갛甫䏕臫늸?鱜䰑잞槫꜕ᰔ蹎丁ᢷ࿱䃪鱽杩䦥뽕磤䦇".toCharArray()[49] = (char)("둭소㓘鐹僼⤎ᵎꦥ鷸蘧ᎏ䯅蝔풇㡓뿅邸봽?⏌㳅§䉬눩㈙牀쎨茇䐠랊炦濾ဳ䌹욢Ϯ⻠ข䑉ﶙ粅ꮛꥑ鬎삒떷猜릴㾴夫️䦧얘⮐骙ॅ࿱ല擐뻕㐧ᯒ釓嬞귤饍䁆鐴밾簃艎竨숁猖냙쓔툔嶈橊ꅾ禕툟Ⱬ匓墐⣾澿砒坂瑒詼䋶ᵮ귋빘鼻ᓩ챿㓗᰸勘瓫ạ뾙১?扲⟚ࠤ⨠싇一쥖脽ᤄ뀴鲖ハ㱱ﯸ?豘偾阌?酈羪럼჻縖쎽ܛ탹?罧梁ଉ㉬鄧䎚갑衙촵䚨츃ꋞ쏽㻣鄌汿릐螦灙땘ᑟ䡌僡닎痠?晿柉갛甫䏕臫늸?鱜䰑잞槫꜕ᰔ蹎丁ᢷ࿱䃪鱽杩䦥뽕磤䦇".toCharArray()[49] ^ 0x503C);
/*     */     String str;
/*     */     int i = (str = hY$g6.H("둭소㓘鐹僼⤎ᵎꦥ鷸蘧ᎏ䯅蝔풇㡓뿅邸봽?⏌㳅§䉬눩㈙牀쎨茇䐠랊炦濾ဳ䌹욢Ϯ⻠ข䑉ﶙ粅ꮛꥑ鬎삒떷猜릴㾴夫️䦧얘⮐骙ॅ࿱ല擐뻕㐧ᯒ釓嬞귤饍䁆鐴밾簃艎竨숁猖냙쓔툔嶈橊ꅾ禕툟Ⱬ匓墐⣾澿砒坂瑒詼䋶ᵮ귋빘鼻ᓩ챿㓗᰸勘瓫ạ뾙১?扲⟚ࠤ⨠싇一쥖脽ᤄ뀴鲖ハ㱱ﯸ?豘偾阌?酈羪럼჻縖쎽ܛ탹?罧梁ଉ㉬鄧䎚갑衙촵䚨츃ꋞ쏽㻣鄌汿릐螦灙땘ᑟ䡌僡닎痠?晿柉갛甫䏕臫늸?鱜䰑잞槫꜕ᰔ蹎丁ᢷ࿱䃪鱽杩䦥뽕磤䦇".toCharArray(), (short)11552, (byte)1, (byte)1)).length();
/*     */     byte b2 = 16;
/*     */     byte b = -1;
/*     */     while (true);
/*     */   }
/*     */   
/*     */   public void a(long paramLong, dO paramdO) {
/*     */     // Byte code:
/*     */     //   0: getstatic me/konsolas/aac/fz.m : J
/*     */     //   3: lload_1
/*     */     //   4: lxor
/*     */     //   5: lstore_1
/*     */     //   6: lload_1
/*     */     //   7: dup2
/*     */     //   8: ldc2_w 50300185165191
/*     */     //   11: lxor
/*     */     //   12: lstore #4
/*     */     //   14: dup2
/*     */     //   15: ldc2_w 73779269627232
/*     */     //   18: lxor
/*     */     //   19: lstore #6
/*     */     //   21: dup2
/*     */     //   22: ldc2_w 126384039052905
/*     */     //   25: lxor
/*     */     //   26: lstore #8
/*     */     //   28: dup2
/*     */     //   29: ldc2_w 10090820379687
/*     */     //   32: lxor
/*     */     //   33: dup2
/*     */     //   34: bipush #48
/*     */     //   36: lushr
/*     */     //   37: l2i
/*     */     //   38: istore #10
/*     */     //   40: dup2
/*     */     //   41: bipush #16
/*     */     //   43: lshl
/*     */     //   44: bipush #32
/*     */     //   46: lushr
/*     */     //   47: l2i
/*     */     //   48: istore #11
/*     */     //   50: dup2
/*     */     //   51: bipush #48
/*     */     //   53: lshl
/*     */     //   54: bipush #48
/*     */     //   56: lushr
/*     */     //   57: l2i
/*     */     //   58: istore #12
/*     */     //   60: pop2
/*     */     //   61: dup2
/*     */     //   62: ldc2_w 104702056022138
/*     */     //   65: lxor
/*     */     //   66: dup2
/*     */     //   67: bipush #48
/*     */     //   69: lushr
/*     */     //   70: l2i
/*     */     //   71: istore #13
/*     */     //   73: dup2
/*     */     //   74: bipush #16
/*     */     //   76: lshl
/*     */     //   77: bipush #32
/*     */     //   79: lushr
/*     */     //   80: l2i
/*     */     //   81: istore #14
/*     */     //   83: dup2
/*     */     //   84: bipush #48
/*     */     //   86: lshl
/*     */     //   87: bipush #48
/*     */     //   89: lushr
/*     */     //   90: l2i
/*     */     //   91: istore #15
/*     */     //   93: pop2
/*     */     //   94: dup2
/*     */     //   95: ldc2_w 140141287236680
/*     */     //   98: lxor
/*     */     //   99: lstore #16
/*     */     //   101: dup2
/*     */     //   102: ldc2_w 131735184855148
/*     */     //   105: lxor
/*     */     //   106: lstore #18
/*     */     //   108: pop2
/*     */     //   109: ldc2_w -1971284093178944410
/*     */     //   112: lload_1
/*     */     //   113: <illegal opcode> w : (JJ)[Lme/konsolas/aac/aN;
/*     */     //   118: aload_3
/*     */     //   119: lload #16
/*     */     //   121: iconst_0
/*     */     //   122: invokevirtual a : (JI)Lme/konsolas/aac/gp;
/*     */     //   125: lload #4
/*     */     //   127: invokestatic a : (Lme/konsolas/aac/gp;J)Lme/konsolas/aac/gi;
/*     */     //   130: astore #21
/*     */     //   132: astore #20
/*     */     //   134: aload #21
/*     */     //   136: aload_0
/*     */     //   137: getfield i : Ljava/lang/String;
/*     */     //   140: lload #8
/*     */     //   142: invokeinterface a : (Ljava/lang/String;J)Lme/konsolas/aac/gi;
/*     */     //   147: bipush #10
/*     */     //   149: lload #6
/*     */     //   151: invokeinterface d : (IJ)Lme/konsolas/aac/gi;
/*     */     //   156: pop
/*     */     //   157: aload #21
/*     */     //   159: aload_0
/*     */     //   160: getfield a : Ljava/lang/String;
/*     */     //   163: lload #8
/*     */     //   165: invokeinterface a : (Ljava/lang/String;J)Lme/konsolas/aac/gi;
/*     */     //   170: bipush #10
/*     */     //   172: lload #6
/*     */     //   174: invokeinterface d : (IJ)Lme/konsolas/aac/gi;
/*     */     //   179: pop
/*     */     //   180: aload #21
/*     */     //   182: aload_0
/*     */     //   183: getfield d : Lme/konsolas/aac/J;
/*     */     //   186: invokevirtual a : ()I
/*     */     //   189: i2l
/*     */     //   190: iload #10
/*     */     //   192: i2s
/*     */     //   193: dup_x2
/*     */     //   194: pop
/*     */     //   195: iload #11
/*     */     //   197: dup_x2
/*     */     //   198: pop
/*     */     //   199: iload #12
/*     */     //   201: i2s
/*     */     //   202: invokeinterface a : (SIJS)Lme/konsolas/aac/gi;
/*     */     //   207: bipush #10
/*     */     //   209: lload #6
/*     */     //   211: invokeinterface d : (IJ)Lme/konsolas/aac/gi;
/*     */     //   216: pop
/*     */     //   217: iconst_0
/*     */     //   218: istore #22
/*     */     //   220: aload_0
/*     */     //   221: getfield d : Lme/konsolas/aac/J;
/*     */     //   224: invokevirtual a : ()I
/*     */     //   227: istore #23
/*     */     //   229: iload #22
/*     */     //   231: iload #23
/*     */     //   233: if_icmpge -> 338
/*     */     //   236: aload #21
/*     */     //   238: aload_0
/*     */     //   239: getfield d : Lme/konsolas/aac/J;
/*     */     //   242: iload #22
/*     */     //   244: invokevirtual a : (I)Ljava/lang/String;
/*     */     //   247: lload #8
/*     */     //   249: invokeinterface a : (Ljava/lang/String;J)Lme/konsolas/aac/gi;
/*     */     //   254: sipush #9170
/*     */     //   257: ldc2_w 1439488203788878875
/*     */     //   260: lload_1
/*     */     //   261: lxor
/*     */     //   262: <illegal opcode> t : (IJ)Ljava/lang/String;
/*     */     //   267: lload #8
/*     */     //   269: invokeinterface a : (Ljava/lang/String;J)Lme/konsolas/aac/gi;
/*     */     //   274: aload_0
/*     */     //   275: getfield d : Lme/konsolas/aac/J;
/*     */     //   278: iload #22
/*     */     //   280: invokevirtual b : (I)Ljava/lang/String;
/*     */     //   283: lload #8
/*     */     //   285: invokeinterface a : (Ljava/lang/String;J)Lme/konsolas/aac/gi;
/*     */     //   290: bipush #10
/*     */     //   292: lload #6
/*     */     //   294: invokeinterface d : (IJ)Lme/konsolas/aac/gi;
/*     */     //   299: pop
/*     */     //   300: iinc #22, 1
/*     */     //   303: aload #20
/*     */     //   305: lload_1
/*     */     //   306: lconst_0
/*     */     //   307: lcmp
/*     */     //   308: ifle -> 316
/*     */     //   311: ifnonnull -> 421
/*     */     //   314: aload #20
/*     */     //   316: ifnull -> 229
/*     */     //   319: lload_1
/*     */     //   320: lconst_0
/*     */     //   321: lcmp
/*     */     //   322: iflt -> 303
/*     */     //   325: goto -> 338
/*     */     //   328: ldc2_w -1963809179128617820
/*     */     //   331: lload_1
/*     */     //   332: <illegal opcode> w : (Ljava/lang/Exception;JJ)Ljava/lang/Exception;
/*     */     //   337: athrow
/*     */     //   338: aload #21
/*     */     //   340: new me/konsolas/aac/i8
/*     */     //   343: dup
/*     */     //   344: aload_0
/*     */     //   345: getfield j : Lme/konsolas/aac/le;
/*     */     //   348: aload_0
/*     */     //   349: getfield h : I
/*     */     //   352: aload_0
/*     */     //   353: getfield e : Ljava/lang/String;
/*     */     //   356: invokespecial <init> : (Lme/konsolas/aac/le;ILjava/lang/String;)V
/*     */     //   359: invokevirtual toString : ()Ljava/lang/String;
/*     */     //   362: lload #8
/*     */     //   364: invokeinterface a : (Ljava/lang/String;J)Lme/konsolas/aac/gi;
/*     */     //   369: bipush #10
/*     */     //   371: lload #6
/*     */     //   373: invokeinterface d : (IJ)Lme/konsolas/aac/gi;
/*     */     //   378: pop
/*     */     //   379: aload #21
/*     */     //   381: aload_0
/*     */     //   382: getfield b : Lme/konsolas/aac/J;
/*     */     //   385: invokevirtual a : ()I
/*     */     //   388: iconst_2
/*     */     //   389: iadd
/*     */     //   390: i2l
/*     */     //   391: iload #10
/*     */     //   393: i2s
/*     */     //   394: dup_x2
/*     */     //   395: pop
/*     */     //   396: iload #11
/*     */     //   398: dup_x2
/*     */     //   399: pop
/*     */     //   400: iload #12
/*     */     //   402: i2s
/*     */     //   403: invokeinterface a : (SIJS)Lme/konsolas/aac/gi;
/*     */     //   408: bipush #10
/*     */     //   410: lload #6
/*     */     //   412: invokeinterface d : (IJ)Lme/konsolas/aac/gi;
/*     */     //   417: pop
/*     */     //   418: iconst_0
/*     */     //   419: istore #22
/*     */     //   421: aload_0
/*     */     //   422: getfield b : Lme/konsolas/aac/J;
/*     */     //   425: invokevirtual a : ()I
/*     */     //   428: istore #23
/*     */     //   430: iload #22
/*     */     //   432: iload #23
/*     */     //   434: if_icmpge -> 539
/*     */     //   437: aload #21
/*     */     //   439: aload_0
/*     */     //   440: getfield b : Lme/konsolas/aac/J;
/*     */     //   443: iload #22
/*     */     //   445: invokevirtual a : (I)Ljava/lang/String;
/*     */     //   448: lload #8
/*     */     //   450: invokeinterface a : (Ljava/lang/String;J)Lme/konsolas/aac/gi;
/*     */     //   455: sipush #29274
/*     */     //   458: ldc2_w 7750881671644927382
/*     */     //   461: lload_1
/*     */     //   462: lxor
/*     */     //   463: <illegal opcode> t : (IJ)Ljava/lang/String;
/*     */     //   468: lload #8
/*     */     //   470: invokeinterface a : (Ljava/lang/String;J)Lme/konsolas/aac/gi;
/*     */     //   475: aload_0
/*     */     //   476: getfield b : Lme/konsolas/aac/J;
/*     */     //   479: iload #22
/*     */     //   481: invokevirtual b : (I)Ljava/lang/String;
/*     */     //   484: lload #8
/*     */     //   486: invokeinterface a : (Ljava/lang/String;J)Lme/konsolas/aac/gi;
/*     */     //   491: bipush #10
/*     */     //   493: lload #6
/*     */     //   495: invokeinterface d : (IJ)Lme/konsolas/aac/gi;
/*     */     //   500: pop
/*     */     //   501: iinc #22, 1
/*     */     //   504: aload #20
/*     */     //   506: lload_1
/*     */     //   507: lconst_0
/*     */     //   508: lcmp
/*     */     //   509: ifle -> 667
/*     */     //   512: ifnonnull -> 665
/*     */     //   515: aload #20
/*     */     //   517: ifnull -> 430
/*     */     //   520: lload_1
/*     */     //   521: lconst_0
/*     */     //   522: lcmp
/*     */     //   523: iflt -> 504
/*     */     //   526: goto -> 539
/*     */     //   529: ldc2_w -1963809179128617820
/*     */     //   532: lload_1
/*     */     //   533: <illegal opcode> w : (Ljava/lang/Exception;JJ)Ljava/lang/Exception;
/*     */     //   538: athrow
/*     */     //   539: aload #21
/*     */     //   541: getstatic me/konsolas/aac/fz.l : Ljava/lang/String;
/*     */     //   544: lload #8
/*     */     //   546: invokeinterface a : (Ljava/lang/String;J)Lme/konsolas/aac/gi;
/*     */     //   551: sipush #29274
/*     */     //   554: ldc2_w 7750881671644927382
/*     */     //   557: lload_1
/*     */     //   558: lxor
/*     */     //   559: <illegal opcode> t : (IJ)Ljava/lang/String;
/*     */     //   564: lload #8
/*     */     //   566: invokeinterface a : (Ljava/lang/String;J)Lme/konsolas/aac/gi;
/*     */     //   571: aload_0
/*     */     //   572: getfield f : J
/*     */     //   575: iload #10
/*     */     //   577: i2s
/*     */     //   578: dup_x2
/*     */     //   579: pop
/*     */     //   580: iload #11
/*     */     //   582: dup_x2
/*     */     //   583: pop
/*     */     //   584: iload #12
/*     */     //   586: i2s
/*     */     //   587: invokeinterface a : (SIJS)Lme/konsolas/aac/gi;
/*     */     //   592: bipush #10
/*     */     //   594: lload #6
/*     */     //   596: invokeinterface d : (IJ)Lme/konsolas/aac/gi;
/*     */     //   601: pop
/*     */     //   602: aload #21
/*     */     //   604: getstatic me/konsolas/aac/fz.g : Ljava/lang/String;
/*     */     //   607: lload #8
/*     */     //   609: invokeinterface a : (Ljava/lang/String;J)Lme/konsolas/aac/gi;
/*     */     //   614: sipush #29274
/*     */     //   617: ldc2_w 7750881671644927382
/*     */     //   620: lload_1
/*     */     //   621: lxor
/*     */     //   622: <illegal opcode> t : (IJ)Ljava/lang/String;
/*     */     //   627: lload #8
/*     */     //   629: invokeinterface a : (Ljava/lang/String;J)Lme/konsolas/aac/gi;
/*     */     //   634: aload_0
/*     */     //   635: getfield c : J
/*     */     //   638: iload #10
/*     */     //   640: i2s
/*     */     //   641: dup_x2
/*     */     //   642: pop
/*     */     //   643: iload #11
/*     */     //   645: dup_x2
/*     */     //   646: pop
/*     */     //   647: iload #12
/*     */     //   649: i2s
/*     */     //   650: invokeinterface a : (SIJS)Lme/konsolas/aac/gi;
/*     */     //   655: bipush #10
/*     */     //   657: lload #6
/*     */     //   659: invokeinterface d : (IJ)Lme/konsolas/aac/gi;
/*     */     //   664: pop
/*     */     //   665: aload #20
/*     */     //   667: ifnonnull -> 826
/*     */     //   670: aload_0
/*     */     //   671: lload #18
/*     */     //   673: invokespecial a : (J)Z
/*     */     //   676: ifeq -> 819
/*     */     //   679: goto -> 692
/*     */     //   682: ldc2_w -1963809179128617820
/*     */     //   685: lload_1
/*     */     //   686: <illegal opcode> w : (Ljava/lang/Exception;JJ)Ljava/lang/Exception;
/*     */     //   691: athrow
/*     */     //   692: aload #21
/*     */     //   694: bipush #10
/*     */     //   696: lload #6
/*     */     //   698: invokeinterface d : (IJ)Lme/konsolas/aac/gi;
/*     */     //   703: pop
/*     */     //   704: aload #21
/*     */     //   706: aload_0
/*     */     //   707: getfield k : Lme/konsolas/aac/it;
/*     */     //   710: invokevirtual a : ()Lme/konsolas/aac/fn;
/*     */     //   713: invokevirtual a : ()Ljava/lang/String;
/*     */     //   716: lload #8
/*     */     //   718: invokeinterface a : (Ljava/lang/String;J)Lme/konsolas/aac/gi;
/*     */     //   723: bipush #10
/*     */     //   725: lload #6
/*     */     //   727: invokeinterface d : (IJ)Lme/konsolas/aac/gi;
/*     */     //   732: pop
/*     */     //   733: aload_0
/*     */     //   734: iload #13
/*     */     //   736: i2s
/*     */     //   737: iload #14
/*     */     //   739: aload #21
/*     */     //   741: aload_0
/*     */     //   742: getfield k : Lme/konsolas/aac/it;
/*     */     //   745: invokevirtual b : ()Ljava/util/List;
/*     */     //   748: iload #15
/*     */     //   750: i2c
/*     */     //   751: swap
/*     */     //   752: invokespecial a : (SILme/konsolas/aac/gi;CLjava/util/List;)V
/*     */     //   755: aload_0
/*     */     //   756: iload #13
/*     */     //   758: i2s
/*     */     //   759: iload #14
/*     */     //   761: aload #21
/*     */     //   763: aload_0
/*     */     //   764: getfield k : Lme/konsolas/aac/it;
/*     */     //   767: invokevirtual a : ()Ljava/util/List;
/*     */     //   770: iload #15
/*     */     //   772: i2c
/*     */     //   773: swap
/*     */     //   774: invokespecial a : (SILme/konsolas/aac/gi;CLjava/util/List;)V
/*     */     //   777: aload #21
/*     */     //   779: aload_0
/*     */     //   780: getfield k : Lme/konsolas/aac/it;
/*     */     //   783: invokevirtual a : ()Lme/konsolas/aac/iy;
/*     */     //   786: invokevirtual a : ()Ljava/lang/String;
/*     */     //   789: lload #8
/*     */     //   791: invokeinterface a : (Ljava/lang/String;J)Lme/konsolas/aac/gi;
/*     */     //   796: bipush #10
/*     */     //   798: lload #6
/*     */     //   800: invokeinterface d : (IJ)Lme/konsolas/aac/gi;
/*     */     //   805: pop
/*     */     //   806: goto -> 819
/*     */     //   809: ldc2_w -1963809179128617820
/*     */     //   812: lload_1
/*     */     //   813: <illegal opcode> w : (Ljava/lang/Exception;JJ)Ljava/lang/Exception;
/*     */     //   818: athrow
/*     */     //   819: aload #21
/*     */     //   821: invokeinterface close : ()V
/*     */     //   826: return
/*     */     // Line number table:
/*     */     //   Java source line number -> byte code offset
/*     */     //   #24	-> 118
/*     */     //   #93	-> 134
/*     */     //   #139	-> 149
/*     */     //   #73	-> 157
/*     */     //   #103	-> 172
/*     */     //   #27	-> 180
/*     */     //   #52	-> 209
/*     */     //   #138	-> 217
/*     */     //   #85	-> 236
/*     */     //   #32	-> 267
/*     */     //   #133	-> 280
/*     */     //   #106	-> 292
/*     */     //   #134	-> 300
/*     */     //   #97	-> 338
/*     */     //   #76	-> 371
/*     */     //   #86	-> 379
/*     */     //   #94	-> 410
/*     */     //   #88	-> 418
/*     */     //   #123	-> 437
/*     */     //   #30	-> 468
/*     */     //   #61	-> 481
/*     */     //   #10	-> 493
/*     */     //   #46	-> 501
/*     */     //   #16	-> 539
/*     */     //   #66	-> 564
/*     */     //   #53	-> 584
/*     */     //   #96	-> 594
/*     */     //   #112	-> 602
/*     */     //   #130	-> 627
/*     */     //   #131	-> 647
/*     */     //   #121	-> 657
/*     */     //   #9	-> 665
/*     */     //   #108	-> 692
/*     */     //   #59	-> 704
/*     */     //   #49	-> 725
/*     */     //   #41	-> 733
/*     */     //   #71	-> 755
/*     */     //   #137	-> 777
/*     */     //   #67	-> 819
/*     */     //   #7	-> 826
/*     */     // Exception table:
/*     */     //   from	to	target	type
/*     */     //   236	319	328	java/io/IOException
/*     */     //   437	520	529	java/io/IOException
/*     */     //   665	679	682	java/io/IOException
/*     */     //   670	806	809	java/io/IOException
/*     */   }
/*     */   
/*     */   private boolean a(long paramLong) {
/*     */     // Byte code:
/*     */     //   0: getstatic me/konsolas/aac/fz.m : J
/*     */     //   3: lload_1
/*     */     //   4: lxor
/*     */     //   5: lstore_1
/*     */     //   6: aload_0
/*     */     //   7: getfield i : Ljava/lang/String;
/*     */     //   10: sipush #6957
/*     */     //   13: ldc2_w 8384457972148233865
/*     */     //   16: lload_1
/*     */     //   17: lxor
/*     */     //   18: <illegal opcode> t : (IJ)Ljava/lang/String;
/*     */     //   23: invokevirtual startsWith : (Ljava/lang/String;)Z
/*     */     //   26: ireturn
/*     */     // Line number table:
/*     */     //   Java source line number -> byte code offset
/*     */     //   #26	-> 6
/*     */   }
/*     */   
/*     */   private List a(bX parambX, long paramLong) {
/*     */     // Byte code:
/*     */     //   0: getstatic me/konsolas/aac/fz.m : J
/*     */     //   3: lload_2
/*     */     //   4: lxor
/*     */     //   5: lstore_2
/*     */     //   6: lload_2
/*     */     //   7: dup2
/*     */     //   8: ldc2_w 67233706648841
/*     */     //   11: lxor
/*     */     //   12: dup2
/*     */     //   13: bipush #16
/*     */     //   15: lushr
/*     */     //   16: lstore #4
/*     */     //   18: dup2
/*     */     //   19: bipush #48
/*     */     //   21: lshl
/*     */     //   22: bipush #48
/*     */     //   24: lushr
/*     */     //   25: l2i
/*     */     //   26: istore #6
/*     */     //   28: pop2
/*     */     //   29: dup2
/*     */     //   30: ldc2_w 3315770062981
/*     */     //   33: lxor
/*     */     //   34: dup2
/*     */     //   35: bipush #48
/*     */     //   37: lushr
/*     */     //   38: l2i
/*     */     //   39: istore #7
/*     */     //   41: dup2
/*     */     //   42: bipush #16
/*     */     //   44: lshl
/*     */     //   45: bipush #48
/*     */     //   47: lushr
/*     */     //   48: l2i
/*     */     //   49: istore #8
/*     */     //   51: dup2
/*     */     //   52: bipush #32
/*     */     //   54: lshl
/*     */     //   55: bipush #32
/*     */     //   57: lushr
/*     */     //   58: l2i
/*     */     //   59: istore #9
/*     */     //   61: pop2
/*     */     //   62: dup2
/*     */     //   63: ldc2_w 47373230177570
/*     */     //   66: lxor
/*     */     //   67: lstore #10
/*     */     //   69: dup2
/*     */     //   70: ldc2_w 1896188484940
/*     */     //   73: lxor
/*     */     //   74: dup2
/*     */     //   75: bipush #32
/*     */     //   77: lushr
/*     */     //   78: l2i
/*     */     //   79: istore #12
/*     */     //   81: dup2
/*     */     //   82: bipush #32
/*     */     //   84: lshl
/*     */     //   85: bipush #32
/*     */     //   87: lushr
/*     */     //   88: lstore #13
/*     */     //   90: pop2
/*     */     //   91: pop2
/*     */     //   92: ldc2_w 3302534317699050774
/*     */     //   95: lload_2
/*     */     //   96: <illegal opcode> w : (JJ)[Lme/konsolas/aac/aN;
/*     */     //   101: lload #10
/*     */     //   103: aload_1
/*     */     //   104: invokestatic a : (JLme/konsolas/aac/bX;)I
/*     */     //   107: istore #16
/*     */     //   109: astore #15
/*     */     //   111: iload #16
/*     */     //   113: iconst_m1
/*     */     //   114: if_icmpne -> 131
/*     */     //   117: invokestatic emptyList : ()Ljava/util/List;
/*     */     //   120: areturn
/*     */     //   121: ldc2_w 3300935177025285588
/*     */     //   124: lload_2
/*     */     //   125: <illegal opcode> w : (Ljava/lang/Exception;JJ)Ljava/lang/Exception;
/*     */     //   130: athrow
/*     */     //   131: sipush #191
/*     */     //   134: ldc2_w 1014732883772370433
/*     */     //   137: lload_2
/*     */     //   138: lxor
/*     */     //   139: <illegal opcode> t : (IJ)Ljava/lang/String;
/*     */     //   144: invokestatic getInstance : (Ljava/lang/String;)Ljava/security/cert/CertificateFactory;
/*     */     //   147: astore #17
/*     */     //   149: new java/util/ArrayList
/*     */     //   152: dup
/*     */     //   153: iload #16
/*     */     //   155: invokespecial <init> : (I)V
/*     */     //   158: astore #18
/*     */     //   160: iconst_0
/*     */     //   161: istore #19
/*     */     //   163: iload #19
/*     */     //   165: iload #16
/*     */     //   167: if_icmpge -> 271
/*     */     //   170: aload_1
/*     */     //   171: iload #7
/*     */     //   173: i2s
/*     */     //   174: iload #8
/*     */     //   176: i2s
/*     */     //   177: iload #9
/*     */     //   179: invokeinterface b : (SSI)Ljava/lang/String;
/*     */     //   184: astore #20
/*     */     //   186: new me/konsolas/aac/fw
/*     */     //   189: dup
/*     */     //   190: invokespecial <init> : ()V
/*     */     //   193: astore #21
/*     */     //   195: aload #21
/*     */     //   197: aload #20
/*     */     //   199: lload #4
/*     */     //   201: iload #6
/*     */     //   203: i2s
/*     */     //   204: invokestatic b : (Ljava/lang/String;JS)Lme/konsolas/aac/gZ;
/*     */     //   207: iload #12
/*     */     //   209: lload #13
/*     */     //   211: invokevirtual a : (Lme/konsolas/aac/gZ;IJ)Lme/konsolas/aac/fw;
/*     */     //   214: pop
/*     */     //   215: lload_2
/*     */     //   216: lconst_0
/*     */     //   217: lcmp
/*     */     //   218: iflt -> 247
/*     */     //   221: aload #18
/*     */     //   223: aload #15
/*     */     //   225: ifnonnull -> 273
/*     */     //   228: aload #17
/*     */     //   230: aload #21
/*     */     //   232: invokevirtual a : ()Ljava/io/InputStream;
/*     */     //   235: invokevirtual generateCertificate : (Ljava/io/InputStream;)Ljava/security/cert/Certificate;
/*     */     //   238: invokeinterface add : (Ljava/lang/Object;)Z
/*     */     //   243: pop
/*     */     //   244: iinc #19, 1
/*     */     //   247: aload #15
/*     */     //   249: ifnull -> 163
/*     */     //   252: lload_2
/*     */     //   253: lconst_0
/*     */     //   254: lcmp
/*     */     //   255: ifle -> 215
/*     */     //   258: goto -> 271
/*     */     //   261: ldc2_w 3300935177025285588
/*     */     //   264: lload_2
/*     */     //   265: <illegal opcode> w : (Ljava/lang/Exception;JJ)Ljava/lang/Exception;
/*     */     //   270: athrow
/*     */     //   271: aload #18
/*     */     //   273: areturn
/*     */     //   274: astore #17
/*     */     //   276: new java/io/IOException
/*     */     //   279: dup
/*     */     //   280: aload #17
/*     */     //   282: invokevirtual getMessage : ()Ljava/lang/String;
/*     */     //   285: invokespecial <init> : (Ljava/lang/String;)V
/*     */     //   288: athrow
/*     */     // Line number table:
/*     */     //   Java source line number -> byte code offset
/*     */     //   #36	-> 101
/*     */     //   #21	-> 111
/*     */     //   #20	-> 131
/*     */     //   #50	-> 149
/*     */     //   #147	-> 160
/*     */     //   #74	-> 170
/*     */     //   #146	-> 186
/*     */     //   #72	-> 195
/*     */     //   #101	-> 215
/*     */     //   #54	-> 244
/*     */     //   #3	-> 271
/*     */     //   #104	-> 274
/*     */     //   #47	-> 276
/*     */     // Exception table:
/*     */     //   from	to	target	type
/*     */     //   111	121	121	java/security/cert/CertificateException
/*     */     //   131	273	274	java/security/cert/CertificateException
/*     */     //   195	252	261	java/security/cert/CertificateException
/*     */   }
/*     */   
/*     */   private void a(short paramShort, int paramInt, gi paramgi, char paramChar, List paramList) {
/*     */     // Byte code:
/*     */     //   0: iload_1
/*     */     //   1: i2l
/*     */     //   2: bipush #48
/*     */     //   4: lshl
/*     */     //   5: iload_2
/*     */     //   6: i2l
/*     */     //   7: bipush #32
/*     */     //   9: lshl
/*     */     //   10: bipush #16
/*     */     //   12: lushr
/*     */     //   13: lor
/*     */     //   14: iload #4
/*     */     //   16: i2l
/*     */     //   17: bipush #48
/*     */     //   19: lshl
/*     */     //   20: bipush #48
/*     */     //   22: lushr
/*     */     //   23: lor
/*     */     //   24: getstatic me/konsolas/aac/fz.m : J
/*     */     //   27: lxor
/*     */     //   28: lstore #6
/*     */     //   30: lload #6
/*     */     //   32: dup2
/*     */     //   33: ldc2_w 75978254493466
/*     */     //   36: lxor
/*     */     //   37: lstore #8
/*     */     //   39: dup2
/*     */     //   40: ldc2_w 128484423959899
/*     */     //   43: lxor
/*     */     //   44: lstore #10
/*     */     //   46: dup2
/*     */     //   47: ldc2_w 39843001720038
/*     */     //   50: lxor
/*     */     //   51: lstore #12
/*     */     //   53: dup2
/*     */     //   54: ldc2_w 128583002885139
/*     */     //   57: lxor
/*     */     //   58: lstore #14
/*     */     //   60: dup2
/*     */     //   61: ldc2_w 16687830494813
/*     */     //   64: lxor
/*     */     //   65: dup2
/*     */     //   66: bipush #48
/*     */     //   68: lushr
/*     */     //   69: l2i
/*     */     //   70: istore #16
/*     */     //   72: dup2
/*     */     //   73: bipush #16
/*     */     //   75: lshl
/*     */     //   76: bipush #32
/*     */     //   78: lushr
/*     */     //   79: l2i
/*     */     //   80: istore #17
/*     */     //   82: dup2
/*     */     //   83: bipush #48
/*     */     //   85: lshl
/*     */     //   86: bipush #48
/*     */     //   88: lushr
/*     */     //   89: l2i
/*     */     //   90: istore #18
/*     */     //   92: pop2
/*     */     //   93: pop2
/*     */     //   94: ldc2_w 3377296817183403548
/*     */     //   97: lload #6
/*     */     //   99: <illegal opcode> w : (JJ)[Lme/konsolas/aac/aN;
/*     */     //   104: astore #19
/*     */     //   106: aload_3
/*     */     //   107: aload #5
/*     */     //   109: invokeinterface size : ()I
/*     */     //   114: i2l
/*     */     //   115: iload #16
/*     */     //   117: i2s
/*     */     //   118: dup_x2
/*     */     //   119: pop
/*     */     //   120: iload #17
/*     */     //   122: dup_x2
/*     */     //   123: pop
/*     */     //   124: iload #18
/*     */     //   126: i2s
/*     */     //   127: invokeinterface a : (SIJS)Lme/konsolas/aac/gi;
/*     */     //   132: bipush #10
/*     */     //   134: lload #8
/*     */     //   136: invokeinterface d : (IJ)Lme/konsolas/aac/gi;
/*     */     //   141: pop
/*     */     //   142: iconst_0
/*     */     //   143: istore #20
/*     */     //   145: aload #5
/*     */     //   147: invokeinterface size : ()I
/*     */     //   152: istore #21
/*     */     //   154: iload #20
/*     */     //   156: iload #21
/*     */     //   158: if_icmpge -> 248
/*     */     //   161: aload #5
/*     */     //   163: iload #20
/*     */     //   165: invokeinterface get : (I)Ljava/lang/Object;
/*     */     //   170: checkcast java/security/cert/Certificate
/*     */     //   173: invokevirtual getEncoded : ()[B
/*     */     //   176: astore #22
/*     */     //   178: aload #22
/*     */     //   180: lload #10
/*     */     //   182: invokestatic a : ([BJ)Lme/konsolas/aac/gZ;
/*     */     //   185: lload #12
/*     */     //   187: invokevirtual b : (J)Ljava/lang/String;
/*     */     //   190: astore #23
/*     */     //   192: aload_3
/*     */     //   193: aload #23
/*     */     //   195: lload #14
/*     */     //   197: invokeinterface a : (Ljava/lang/String;J)Lme/konsolas/aac/gi;
/*     */     //   202: bipush #10
/*     */     //   204: lload #8
/*     */     //   206: invokeinterface d : (IJ)Lme/konsolas/aac/gi;
/*     */     //   211: pop
/*     */     //   212: iinc #20, 1
/*     */     //   215: aload #19
/*     */     //   217: iload_1
/*     */     //   218: iflt -> 226
/*     */     //   221: ifnonnull -> 266
/*     */     //   224: aload #19
/*     */     //   226: ifnull -> 154
/*     */     //   229: iload #4
/*     */     //   231: iflt -> 215
/*     */     //   234: goto -> 248
/*     */     //   237: ldc2_w 3370139430468054750
/*     */     //   240: lload #6
/*     */     //   242: <illegal opcode> w : (Ljava/lang/Exception;JJ)Ljava/lang/Exception;
/*     */     //   247: athrow
/*     */     //   248: goto -> 266
/*     */     //   251: astore #20
/*     */     //   253: new java/io/IOException
/*     */     //   256: dup
/*     */     //   257: aload #20
/*     */     //   259: invokevirtual getMessage : ()Ljava/lang/String;
/*     */     //   262: invokespecial <init> : (Ljava/lang/String;)V
/*     */     //   265: athrow
/*     */     //   266: return
/*     */     // Line number table:
/*     */     //   Java source line number -> byte code offset
/*     */     //   #79	-> 106
/*     */     //   #4	-> 134
/*     */     //   #15	-> 142
/*     */     //   #117	-> 161
/*     */     //   #89	-> 178
/*     */     //   #91	-> 192
/*     */     //   #42	-> 204
/*     */     //   #109	-> 212
/*     */     //   #120	-> 248
/*     */     //   #2	-> 251
/*     */     //   #17	-> 253
/*     */     //   #8	-> 266
/*     */     // Exception table:
/*     */     //   from	to	target	type
/*     */     //   106	248	251	java/security/cert/CertificateEncodingException
/*     */     //   192	229	237	java/security/cert/CertificateEncodingException
/*     */   }
/*     */   
/*     */   public H a(long paramLong, kW paramkW) {
/*     */     // Byte code:
/*     */     //   0: getstatic me/konsolas/aac/fz.m : J
/*     */     //   3: lload_1
/*     */     //   4: lxor
/*     */     //   5: lstore_1
/*     */     //   6: lload_1
/*     */     //   7: dup2
/*     */     //   8: ldc2_w 100230278139108
/*     */     //   11: lxor
/*     */     //   12: lstore #4
/*     */     //   14: dup2
/*     */     //   15: ldc2_w 137759856423962
/*     */     //   18: lxor
/*     */     //   19: lstore #6
/*     */     //   21: dup2
/*     */     //   22: ldc2_w 34221947974074
/*     */     //   25: lxor
/*     */     //   26: lstore #8
/*     */     //   28: dup2
/*     */     //   29: ldc2_w 93864192872830
/*     */     //   32: lxor
/*     */     //   33: lstore #10
/*     */     //   35: dup2
/*     */     //   36: ldc2_w 75802151378341
/*     */     //   39: lxor
/*     */     //   40: dup2
/*     */     //   41: bipush #32
/*     */     //   43: lushr
/*     */     //   44: l2i
/*     */     //   45: istore #12
/*     */     //   47: dup2
/*     */     //   48: bipush #32
/*     */     //   50: lshl
/*     */     //   51: bipush #48
/*     */     //   53: lushr
/*     */     //   54: l2i
/*     */     //   55: istore #13
/*     */     //   57: dup2
/*     */     //   58: bipush #48
/*     */     //   60: lshl
/*     */     //   61: bipush #48
/*     */     //   63: lushr
/*     */     //   64: l2i
/*     */     //   65: istore #14
/*     */     //   67: pop2
/*     */     //   68: dup2
/*     */     //   69: ldc2_w 7745264462676
/*     */     //   72: lxor
/*     */     //   73: lstore #15
/*     */     //   75: dup2
/*     */     //   76: ldc2_w 39784970808897
/*     */     //   79: lxor
/*     */     //   80: lstore #17
/*     */     //   82: pop2
/*     */     //   83: aload_0
/*     */     //   84: getfield b : Lme/konsolas/aac/J;
/*     */     //   87: iload #12
/*     */     //   89: iload #13
/*     */     //   91: i2c
/*     */     //   92: iload #14
/*     */     //   94: i2c
/*     */     //   95: sipush #31192
/*     */     //   98: ldc2_w 8879163474543538554
/*     */     //   101: lload_1
/*     */     //   102: lxor
/*     */     //   103: <illegal opcode> t : (IJ)Ljava/lang/String;
/*     */     //   108: invokevirtual a : (ICCLjava/lang/String;)Ljava/lang/String;
/*     */     //   111: astore #19
/*     */     //   113: aload_0
/*     */     //   114: getfield b : Lme/konsolas/aac/J;
/*     */     //   117: iload #12
/*     */     //   119: iload #13
/*     */     //   121: i2c
/*     */     //   122: iload #14
/*     */     //   124: i2c
/*     */     //   125: sipush #5653
/*     */     //   128: ldc2_w 3094505813760974514
/*     */     //   131: lload_1
/*     */     //   132: lxor
/*     */     //   133: <illegal opcode> t : (IJ)Ljava/lang/String;
/*     */     //   138: invokevirtual a : (ICCLjava/lang/String;)Ljava/lang/String;
/*     */     //   141: astore #20
/*     */     //   143: new me/konsolas/aac/k_
/*     */     //   146: dup
/*     */     //   147: lload #10
/*     */     //   149: invokespecial <init> : (J)V
/*     */     //   152: aload_0
/*     */     //   153: getfield i : Ljava/lang/String;
/*     */     //   156: lload #15
/*     */     //   158: dup2_x1
/*     */     //   159: pop2
/*     */     //   160: invokevirtual a : (JLjava/lang/String;)Lme/konsolas/aac/k_;
/*     */     //   163: aload_0
/*     */     //   164: getfield a : Ljava/lang/String;
/*     */     //   167: lload #17
/*     */     //   169: aconst_null
/*     */     //   170: invokevirtual a : (Ljava/lang/String;JLme/konsolas/aac/jR;)Lme/konsolas/aac/k_;
/*     */     //   173: aload_0
/*     */     //   174: getfield d : Lme/konsolas/aac/J;
/*     */     //   177: invokevirtual a : (Lme/konsolas/aac/J;)Lme/konsolas/aac/k_;
/*     */     //   180: lload #6
/*     */     //   182: invokevirtual a : (J)Lme/konsolas/aac/s;
/*     */     //   185: astore #21
/*     */     //   187: new me/konsolas/aac/T
/*     */     //   190: dup
/*     */     //   191: invokespecial <init> : ()V
/*     */     //   194: aload #21
/*     */     //   196: invokevirtual a : (Lme/konsolas/aac/s;)Lme/konsolas/aac/T;
/*     */     //   199: aload_0
/*     */     //   200: getfield j : Lme/konsolas/aac/le;
/*     */     //   203: invokevirtual a : (Lme/konsolas/aac/le;)Lme/konsolas/aac/T;
/*     */     //   206: aload_0
/*     */     //   207: getfield h : I
/*     */     //   210: invokevirtual a : (I)Lme/konsolas/aac/T;
/*     */     //   213: aload_0
/*     */     //   214: getfield e : Ljava/lang/String;
/*     */     //   217: invokevirtual a : (Ljava/lang/String;)Lme/konsolas/aac/T;
/*     */     //   220: aload_0
/*     */     //   221: getfield b : Lme/konsolas/aac/J;
/*     */     //   224: invokevirtual a : (Lme/konsolas/aac/J;)Lme/konsolas/aac/T;
/*     */     //   227: new me/konsolas/aac/d9
/*     */     //   230: dup
/*     */     //   231: lload #4
/*     */     //   233: aload_3
/*     */     //   234: aload #19
/*     */     //   236: aload #20
/*     */     //   238: invokespecial <init> : (JLme/konsolas/aac/kW;Ljava/lang/String;Ljava/lang/String;)V
/*     */     //   241: invokevirtual a : (Lme/konsolas/aac/d2;)Lme/konsolas/aac/T;
/*     */     //   244: aload_0
/*     */     //   245: getfield k : Lme/konsolas/aac/it;
/*     */     //   248: invokevirtual a : (Lme/konsolas/aac/it;)Lme/konsolas/aac/T;
/*     */     //   251: aload_0
/*     */     //   252: getfield f : J
/*     */     //   255: invokevirtual b : (J)Lme/konsolas/aac/T;
/*     */     //   258: aload_0
/*     */     //   259: getfield c : J
/*     */     //   262: invokevirtual a : (J)Lme/konsolas/aac/T;
/*     */     //   265: lload #8
/*     */     //   267: invokevirtual a : (J)Lme/konsolas/aac/H;
/*     */     //   270: areturn
/*     */     // Line number table:
/*     */     //   Java source line number -> byte code offset
/*     */     //   #107	-> 83
/*     */     //   #23	-> 113
/*     */     //   #12	-> 143
/*     */     //   #70	-> 160
/*     */     //   #37	-> 170
/*     */     //   #124	-> 177
/*     */     //   #58	-> 180
/*     */     //   #100	-> 187
/*     */     //   #149	-> 196
/*     */     //   #90	-> 203
/*     */     //   #63	-> 210
/*     */     //   #142	-> 217
/*     */     //   #68	-> 224
/*     */     //   #84	-> 241
/*     */     //   #69	-> 248
/*     */     //   #115	-> 255
/*     */     //   #60	-> 262
/*     */     //   #35	-> 265
/*     */     //   #116	-> 270
/*     */   }
/*     */   
/*     */   public boolean a(s params, H paramH, long paramLong) {
/*     */     // Byte code:
/*     */     //   0: getstatic me/konsolas/aac/fz.m : J
/*     */     //   3: lload_3
/*     */     //   4: lxor
/*     */     //   5: lstore_3
/*     */     //   6: lload_3
/*     */     //   7: dup2
/*     */     //   8: ldc2_w 75826488104524
/*     */     //   11: lxor
/*     */     //   12: lstore #5
/*     */     //   14: pop2
/*     */     //   15: ldc2_w -2833049981763463060
/*     */     //   18: lload_3
/*     */     //   19: <illegal opcode> w : (JJ)[Lme/konsolas/aac/aN;
/*     */     //   24: astore #7
/*     */     //   26: aload_0
/*     */     //   27: getfield i : Ljava/lang/String;
/*     */     //   30: aload_1
/*     */     //   31: invokevirtual a : ()Lme/konsolas/aac/l6;
/*     */     //   34: invokevirtual toString : ()Ljava/lang/String;
/*     */     //   37: invokevirtual equals : (Ljava/lang/Object;)Z
/*     */     //   40: aload #7
/*     */     //   42: ifnonnull -> 85
/*     */     //   45: ifeq -> 161
/*     */     //   48: goto -> 61
/*     */     //   51: ldc2_w -2831270521149318994
/*     */     //   54: lload_3
/*     */     //   55: <illegal opcode> w : (Ljava/lang/Exception;JJ)Ljava/lang/Exception;
/*     */     //   60: athrow
/*     */     //   61: aload_0
/*     */     //   62: getfield a : Ljava/lang/String;
/*     */     //   65: aload_1
/*     */     //   66: invokevirtual a : ()Ljava/lang/String;
/*     */     //   69: invokevirtual equals : (Ljava/lang/Object;)Z
/*     */     //   72: goto -> 85
/*     */     //   75: ldc2_w -2831270521149318994
/*     */     //   78: lload_3
/*     */     //   79: <illegal opcode> w : (Ljava/lang/Exception;JJ)Ljava/lang/Exception;
/*     */     //   84: athrow
/*     */     //   85: aload #7
/*     */     //   87: lload_3
/*     */     //   88: lconst_0
/*     */     //   89: lcmp
/*     */     //   90: ifle -> 138
/*     */     //   93: ifnonnull -> 136
/*     */     //   96: ifeq -> 161
/*     */     //   99: goto -> 112
/*     */     //   102: ldc2_w -2831270521149318994
/*     */     //   105: lload_3
/*     */     //   106: <illegal opcode> w : (Ljava/lang/Exception;JJ)Ljava/lang/Exception;
/*     */     //   111: athrow
/*     */     //   112: lload #5
/*     */     //   114: aload_2
/*     */     //   115: aload_0
/*     */     //   116: getfield d : Lme/konsolas/aac/J;
/*     */     //   119: aload_1
/*     */     //   120: invokestatic a : (JLme/konsolas/aac/H;Lme/konsolas/aac/J;Lme/konsolas/aac/s;)Z
/*     */     //   123: goto -> 136
/*     */     //   126: ldc2_w -2831270521149318994
/*     */     //   129: lload_3
/*     */     //   130: <illegal opcode> w : (Ljava/lang/Exception;JJ)Ljava/lang/Exception;
/*     */     //   135: athrow
/*     */     //   136: aload #7
/*     */     //   138: ifnonnull -> 158
/*     */     //   141: ifeq -> 161
/*     */     //   144: goto -> 157
/*     */     //   147: ldc2_w -2831270521149318994
/*     */     //   150: lload_3
/*     */     //   151: <illegal opcode> w : (Ljava/lang/Exception;JJ)Ljava/lang/Exception;
/*     */     //   156: athrow
/*     */     //   157: iconst_1
/*     */     //   158: goto -> 162
/*     */     //   161: iconst_0
/*     */     //   162: ireturn
/*     */     // Line number table:
/*     */     //   Java source line number -> byte code offset
/*     */     //   #126	-> 26
/*     */     //   #48	-> 66
/*     */     //   #19	-> 120
/*     */     //   #102	-> 162
/*     */     // Exception table:
/*     */     //   from	to	target	type
/*     */     //   26	48	51	aacinternal/v
/*     */     //   45	72	75	aacinternal/v
/*     */     //   85	99	102	aacinternal/v
/*     */     //   96	123	126	aacinternal/v
/*     */     //   136	144	147	aacinternal/v
/*     */   }
/*     */   
/*     */   private static Exception a(Exception paramException) {
/*     */     return paramException;
/*     */   }
/*     */   
/*     */   private static String a(byte[] paramArrayOfbyte) {
/*     */     byte b1 = 0;
/*     */     int i;
/*     */     char[] arrayOfChar = new char[i = paramArrayOfbyte.length];
/*     */     for (byte b2 = 0; b2 < i; b2++) {
/*     */       int j;
/*     */       if ((j = 0xFF & paramArrayOfbyte[b2]) < 192) {
/*     */         arrayOfChar[b1++] = (char)j;
/*     */       } else if (j < 224) {
/*     */         char c = (char)((char)(j & 0x1F) << 6);
/*     */         j = paramArrayOfbyte[++b2];
/*     */         c = (char)(c | (char)(j & 0x3F));
/*     */         arrayOfChar[b1++] = c;
/*     */       } else if (b2 < i - 2) {
/*     */         char c = (char)((char)(j & 0xF) << 12);
/*     */         j = paramArrayOfbyte[++b2];
/*     */         c = (char)(c | (char)(j & 0x3F) << 6);
/*     */         j = paramArrayOfbyte[++b2];
/*     */         c = (char)(c | (char)(j & 0x3F));
/*     */         arrayOfChar[b1++] = c;
/*     */       } 
/*     */     } 
/*     */     return new String(arrayOfChar, 0, b1);
/*     */   }
/*     */   
/*     */   private static String a(int paramInt, long paramLong) {
/*     */     int i = paramInt ^ (int)(paramLong & 0x7FFFL) ^ 0x4389;
/*     */     if (o[i] == null) {
/*     */       Object[] arrayOfObject;
/*     */       try {
/*     */         Long long_ = Long.valueOf(Thread.currentThread().getId());
/*     */         arrayOfObject = (Object[])p.get(long_);
/*     */         if (arrayOfObject == null) {
/*     */           arrayOfObject = new Object[3];
/*     */           "?ㇶ룻圏驫撝껝΋?껿≘ꄧ슩﯌殾갲毖".toCharArray()[17] = (char)("?ㇶ룻圏驫撝껝΋?껿≘ꄧ슩﯌殾갲毖".toCharArray()[17] ^ 0x61AE);
/*     */           arrayOfObject[0] = Cipher.getInstance(da$gx.U("?ㇶ룻圏驫撝껝΋?껿≘ꄧ슩﯌殾갲毖".toCharArray(), (short)24441, false, false));
/*     */           "敳弟帆瀠".toCharArray()[0] = (char)("敳弟帆瀠".toCharArray()[0] ^ 0x69BE);
/*     */           arrayOfObject[1] = SecretKeyFactory.getInstance(da$gx.U("敳弟帆瀠".toCharArray(), (short)21166, false, false));
/*     */           arrayOfObject[2] = new IvParameterSpec(new byte[8]);
/*     */           p.put(long_, arrayOfObject);
/*     */         } 
/*     */       } catch (Exception exception) {
/*     */         "勆贚ĕ㠠瘭叴ᛖ賟뒻⬠︵惸於诈惶峺ś₩".toCharArray()[5] = (char)("勆贚ĕ㠠瘭叴ᛖ賟뒻⬠︵惸於诈惶峺ś₩".toCharArray()[5] ^ 0x56AF);
/*     */         throw new RuntimeException(da$gx.U("勆贚ĕ㠠瘭叴ᛖ賟뒻⬠︵惸於诈惶峺ś₩".toCharArray(), (short)31863, false, true), exception);
/*     */       } 
/*     */       byte[] arrayOfByte1 = new byte[8];
/*     */       arrayOfByte1[0] = (byte)(int)(paramLong >>> 56L);
/*     */       for (byte b = 1; b < 8; b++)
/*     */         arrayOfByte1[b] = (byte)(int)(paramLong << b * 8 >>> 56L); 
/*     */       DESKeySpec dESKeySpec = new DESKeySpec(arrayOfByte1);
/*     */       SecretKey secretKey = ((SecretKeyFactory)arrayOfObject[1]).generateSecret(dESKeySpec);
/*     */       ((Cipher)arrayOfObject[0]).init(2, secretKey, (IvParameterSpec)arrayOfObject[2]);
/*     */       "ଧ︿躬䵲싮愉槵쯹쉲㨆".toCharArray()[7] = (char)("ଧ︿躬䵲싮愉槵쯹쉲㨆".toCharArray()[7] ^ 0x71FA);
/*     */       byte[] arrayOfByte2 = n[i].getBytes(da$gx.U("ଧ︿躬䵲싮愉槵쯹쉲㨆".toCharArray(), (short)16248, false, false));
/*     */       o[i] = a(((Cipher)arrayOfObject[0]).doFinal(arrayOfByte2));
/*     */     } 
/*     */     return o[i];
/*     */   }
/*     */   
/*     */   private static Object a(MethodHandles.Lookup paramLookup, MutableCallSite paramMutableCallSite, String paramString, Object[] paramArrayOfObject) {
/*     */     int i = ((Integer)paramArrayOfObject[0]).intValue();
/*     */     long l = ((Long)paramArrayOfObject[1]).longValue();
/*     */     String str = a(i, l);
/*     */     MethodHandle methodHandle = MethodHandles.constant(String.class, str);
/*     */     paramMutableCallSite.setTarget(MethodHandles.dropArguments(methodHandle, 0, new Class[] { int.class, long.class }));
/*     */     return str;
/*     */   }
/*     */   
/*     */   private static CallSite a(MethodHandles.Lookup paramLookup, String paramString, MethodType paramMethodType) {
/*     */     // Byte code:
/*     */     //   0: new java/lang/invoke/MutableCallSite
/*     */     //   3: dup
/*     */     //   4: aload_2
/*     */     //   5: invokespecial <init> : (Ljava/lang/invoke/MethodType;)V
/*     */     //   8: astore_3
/*     */     //   9: aload_3
/*     */     //   10: ldc_w
/*     */     //   13: ldc_w [Ljava/lang/Object;
/*     */     //   16: aload_2
/*     */     //   17: invokevirtual parameterCount : ()I
/*     */     //   20: invokevirtual asCollector : (Ljava/lang/Class;I)Ljava/lang/invoke/MethodHandle;
/*     */     //   23: iconst_0
/*     */     //   24: iconst_3
/*     */     //   25: anewarray java/lang/Object
/*     */     //   28: dup
/*     */     //   29: iconst_0
/*     */     //   30: aload_0
/*     */     //   31: aastore
/*     */     //   32: dup
/*     */     //   33: iconst_1
/*     */     //   34: aload_3
/*     */     //   35: aastore
/*     */     //   36: dup
/*     */     //   37: iconst_2
/*     */     //   38: aload_1
/*     */     //   39: aastore
/*     */     //   40: invokestatic insertArguments : (Ljava/lang/invoke/MethodHandle;I[Ljava/lang/Object;)Ljava/lang/invoke/MethodHandle;
/*     */     //   43: aload_2
/*     */     //   44: invokestatic explicitCastArguments : (Ljava/lang/invoke/MethodHandle;Ljava/lang/invoke/MethodType;)Ljava/lang/invoke/MethodHandle;
/*     */     //   47: invokevirtual setTarget : (Ljava/lang/invoke/MethodHandle;)V
/*     */     //   50: goto -> 171
/*     */     //   53: astore #4
/*     */     //   55: new java/lang/RuntimeException
/*     */     //   58: dup
/*     */     //   59: new java/lang/StringBuilder
/*     */     //   62: dup
/*     */     //   63: invokespecial <init> : ()V
/*     */     //   66: ldc_w '㢵㜱꡹維鄕ゃ狼ᆘ⽉?셚滴♫쳝꣡'
/*     */     //   69: invokevirtual toCharArray : ()[C
/*     */     //   72: dup
/*     */     //   73: dup
/*     */     //   74: bipush #6
/*     */     //   76: dup_x1
/*     */     //   77: caload
/*     */     //   78: sipush #14338
/*     */     //   81: ixor
/*     */     //   82: i2c
/*     */     //   83: castore
/*     */     //   84: sipush #9724
/*     */     //   87: iconst_1
/*     */     //   88: iconst_1
/*     */     //   89: invokestatic X : (Ljava/lang/Object;SZZ)Ljava/lang/String;
/*     */     //   92: invokevirtual append : (Ljava/lang/String;)Ljava/lang/StringBuilder;
/*     */     //   95: ldc_w '䷘뙚ᶇ'
/*     */     //   98: invokevirtual toCharArray : ()[C
/*     */     //   101: dup
/*     */     //   102: dup
/*     */     //   103: iconst_0
/*     */     //   104: dup_x1
/*     */     //   105: caload
/*     */     //   106: sipush #29346
/*     */     //   109: ixor
/*     */     //   110: i2c
/*     */     //   111: castore
/*     */     //   112: sipush #13831
/*     */     //   115: iconst_0
/*     */     //   116: iconst_1
/*     */     //   117: invokestatic X : (Ljava/lang/Object;SZZ)Ljava/lang/String;
/*     */     //   120: invokevirtual append : (Ljava/lang/String;)Ljava/lang/StringBuilder;
/*     */     //   123: aload_1
/*     */     //   124: invokevirtual append : (Ljava/lang/String;)Ljava/lang/StringBuilder;
/*     */     //   127: ldc_w '䫦⸥㴓೺'
/*     */     //   130: invokevirtual toCharArray : ()[C
/*     */     //   133: dup
/*     */     //   134: dup
/*     */     //   135: iconst_2
/*     */     //   136: dup_x1
/*     */     //   137: caload
/*     */     //   138: sipush #7065
/*     */     //   141: ixor
/*     */     //   142: i2c
/*     */     //   143: castore
/*     */     //   144: sipush #23925
/*     */     //   147: iconst_1
/*     */     //   148: iconst_0
/*     */     //   149: invokestatic X : (Ljava/lang/Object;SZZ)Ljava/lang/String;
/*     */     //   152: invokevirtual append : (Ljava/lang/String;)Ljava/lang/StringBuilder;
/*     */     //   155: aload_2
/*     */     //   156: invokevirtual toString : ()Ljava/lang/String;
/*     */     //   159: invokevirtual append : (Ljava/lang/String;)Ljava/lang/StringBuilder;
/*     */     //   162: invokevirtual toString : ()Ljava/lang/String;
/*     */     //   165: aload #4
/*     */     //   167: invokespecial <init> : (Ljava/lang/String;Ljava/lang/Throwable;)V
/*     */     //   170: athrow
/*     */     //   171: aload_3
/*     */     //   172: areturn
/*     */     // Exception table:
/*     */     //   from	to	target	type
/*     */     //   9	50	53	java/lang/Exception
/*     */   }
/*     */ }


/* Location:              C:\Users\BukkitBypass\Desktop\MatrixAC\AAC\AAC-spigot-5.2.0.jar!\me\konsolas\aac\fz.class
 * Java compiler version: 8 (52.0)
 * JD-Core Version:       1.1.3
 */