/*    */ package me.konsolas.aac;public class gf implements Cloneable, ap, bb { static final List o; static final List j; final jT f; @Nullable final Proxy B; final List x; final List C; final List k; final List h; final fD z; final ProxySelector q; final iD c; @Nullable final hW l; @Nullable
/*  2 */   final bC n; final SocketFactory g; final SSLSocketFactory s; final gK p; final HostnameVerifier b; final mG D; final dp u; final dp e; final e_ y; final k4 a; final boolean m; final boolean d; final boolean r; final int t; final int w; final int v; final int A; final int i; private static final long E; private static final String[] F; private static final String[] G; private static final Map H; public int d() { return this.w; } public List d() {
/*  3 */     return this.x;
/*    */   }
/*    */   static { long l;
/*    */     byte b1;
/*  7 */     for (E = nc.a(-2324522191813003530L, 4815630274305314664L, MethodHandles.lookup().lookupClass()).a(99508314984578L), H = new HashMap<>(13), l = E ^ 0x261F37638A74L, "ꂖ組퓞拯榹橥진赓ﱍᯰ￟矾郓㇞??䟊᤭".toCharArray()[11] = (char)("ꂖ組퓞拯榹橥진赓ﱍᯰ￟矾郓㇞??䟊᤭".toCharArray()[11] ^ 0x6AB4), "⹦慥먑㥵".toCharArray()[2] = (char)("⹦慥먑㥵".toCharArray()[2] ^ 0x1F2A), (new byte[8])[0] = (byte)(int)(l >>> 56L), b1 = 1; b1 < 8; ) { (new byte[8])[b1] = (byte)(int)(l << b1 * 8 >>> 56L); b1++; }  Cipher cipher; (cipher = Cipher.getInstance(fW$gy.A("ꂖ組퓞拯榹橥진赓ﱍᯰ￟矾郓㇞??䟊᤭".toCharArray(), (short)24025, true, 3))).init(2, SecretKeyFactory.getInstance(fW$gy.A("⹦慥먑㥵".toCharArray(), (short)16999, false, 0)).generateSecret(new DESKeySpec(new byte[8])), new IvParameterSpec(new byte[8])); String[] arrayOfString = new String[3]; boolean bool = false; "ᦘ뚫絑焝奜㝳殌?옘ͻ聾硠忖?ꆥ쯸嬊湡哦⑆冠칟軹츔ꚮ攱僊㯾鄷㭨늟ᮥƝ甎㦋全Ḛ䰧⼘荗踥봂湥⑜惊겻煶톌觍ᦵ?耹鑈᝿頓쳚択ۼꀃꍻ﵄蛬鈠ꁤ妾퀄섺欐䳷瘱ໜ뵋쑶홹ᒉ뎪Κ剺ἓ쾳?鷺릷䴰肹Ᏹト퇁ლ络픮鷵㤭䓾䡸⩨᷃㋕斑㣚賺㕕䬕狤帕疠?ᆗㅌ".toCharArray()[12] = (char)("ᦘ뚫絑焝奜㝳殌?옘ͻ聾硠忖?ꆥ쯸嬊湡哦⑆冠칟軹츔ꚮ攱僊㯾鄷㭨늟ᮥƝ甎㦋全Ḛ䰧⼘荗踥봂湥⑜惊겻煶톌觍ᦵ?耹鑈᝿頓쳚択ۼꀃꍻ﵄蛬鈠ꁤ妾퀄섺欐䳷瘱ໜ뵋쑶홹ᒉ뎪Κ剺ἓ쾳?鷺릷䴰肹Ᏹト퇁ლ络픮鷵㤭䓾䡸⩨᷃㋕斑㣚賺㕕䬕狤帕疠?ᆗㅌ".toCharArray()[12] ^ 0xA68); String str; int i = (str = fW$gy.A("ᦘ뚫絑焝奜㝳殌?옘ͻ聾硠忖?ꆥ쯸嬊湡哦⑆冠칟軹츔ꚮ攱僊㯾鄷㭨늟ᮥƝ甎㦋全Ḛ䰧⼘荗踥봂湥⑜惊겻煶톌觍ᦵ?耹鑈᝿頓쳚択ۼꀃꍻ﵄蛬鈠ꁤ妾퀄섺欐䳷瘱ໜ뵋쑶홹ᒉ뎪Κ剺ἓ쾳?鷺릷䴰肹Ᏹト퇁ლ络픮鷵㤭䓾䡸⩨᷃㋕斑㣚賺㕕䬕狤帕疠?ᆗㅌ".toCharArray(), (short)20662, true, 3)).length(); byte b2 = 40; byte b = -1;
/*  8 */     while (true); } public k4 a() { return this.a; }
/*    */ 
/*    */ 
/*    */   
/*    */   public gC a(long paramLong, s params) {
/* 13 */     int i = (int)((paramLong ^ 0x569513F5B920L) >>> 48L), j = (int)((paramLong ^ 0x569513F5B920L) << 16L >>> 32L), k = (int)((paramLong ^ 0x569513F5B920L) << 48L >>> 48L); paramLong ^ 0x569513F5B920L; return bL.a((char)i, this, j, params, (short)k, false);
/*    */   }
/*    */ 
/*    */ 
/*    */   
/*    */   @Nullable
/*    */   public Proxy a() {
/* 20 */     return this.B;
/*    */   }
/*    */   public int a() { return this.i; }
/*    */   public int c() { return this.v; } public int e() { return this.A; } public e_ a() { return this.y; } @Nullable bC a(long paramLong) { // Byte code:
/*    */     //   0: getstatic me/konsolas/aac/gf.E : J
/*    */     //   3: lload_1
/*    */     //   4: lxor
/*    */     //   5: lstore_1
/*    */     //   6: ldc2_w -466127297230210747
/*    */     //   9: lload_1
/*    */     //   10: <illegal opcode> w : (JJ)[Lme/konsolas/aac/aN;
/*    */     //   15: astore_3
/*    */     //   16: aload_0
/*    */     //   17: aload_3
/*    */     //   18: ifnonnull -> 61
/*    */     //   21: getfield l : Lme/konsolas/aac/hW;
/*    */     //   24: ifnull -> 60
/*    */     //   27: goto -> 40
/*    */     //   30: ldc2_w -550049670498527665
/*    */     //   33: lload_1
/*    */     //   34: <illegal opcode> w : (Ljava/lang/IllegalStateException;JJ)Ljava/lang/IllegalStateException;
/*    */     //   39: athrow
/*    */     //   40: aload_0
/*    */     //   41: getfield l : Lme/konsolas/aac/hW;
/*    */     //   44: getfield k : Lme/konsolas/aac/bC;
/*    */     //   47: goto -> 64
/*    */     //   50: ldc2_w -550049670498527665
/*    */     //   53: lload_1
/*    */     //   54: <illegal opcode> w : (Ljava/lang/IllegalStateException;JJ)Ljava/lang/IllegalStateException;
/*    */     //   59: athrow
/*    */     //   60: aload_0
/*    */     //   61: getfield n : Lme/konsolas/aac/bC;
/*    */     //   64: areturn
/*    */     // Line number table:
/*    */     //   Java source line number -> byte code offset
/*    */     //   #37	-> 16
/*    */     // Exception table:
/*    */     //   from	to	target	type
/*    */     //   16	27	30	java/lang/IllegalStateException
/*    */     //   21	50	50	java/lang/IllegalStateException } public List b() { return this.h; } public List c() { return this.k; } public boolean a() { return this.m; } gf(gI paramgI, long paramLong) { // Byte code:
/*    */     //   0: getstatic me/konsolas/aac/gf.E : J
/*    */     //   3: lload_2
/*    */     //   4: lxor
/*    */     //   5: lstore_2
/*    */     //   6: lload_2
/*    */     //   7: dup2
/*    */     //   8: ldc2_w 136313057430809
/*    */     //   11: lxor
/*    */     //   12: lstore #4
/*    */     //   14: dup2
/*    */     //   15: ldc2_w 136258841727242
/*    */     //   18: lxor
/*    */     //   19: lstore #6
/*    */     //   21: dup2
/*    */     //   22: ldc2_w 14997688384144
/*    */     //   25: lxor
/*    */     //   26: lstore #8
/*    */     //   28: dup2
/*    */     //   29: ldc2_w 84528476421939
/*    */     //   32: lxor
/*    */     //   33: lstore #10
/*    */     //   35: dup2
/*    */     //   36: ldc2_w 125625206356763
/*    */     //   39: lxor
/*    */     //   40: lstore #12
/*    */     //   42: pop2
/*    */     //   43: ldc2_w -2813656150403131343
/*    */     //   46: lload_2
/*    */     //   47: <illegal opcode> w : (JJ)[Lme/konsolas/aac/aN;
/*    */     //   52: aload_0
/*    */     //   53: invokespecial <init> : ()V
/*    */     //   56: aload_0
/*    */     //   57: aload_1
/*    */     //   58: getfield f : Lme/konsolas/aac/jT;
/*    */     //   61: putfield f : Lme/konsolas/aac/jT;
/*    */     //   64: aload_0
/*    */     //   65: aload_1
/*    */     //   66: getfield u : Ljava/net/Proxy;
/*    */     //   69: putfield B : Ljava/net/Proxy;
/*    */     //   72: aload_0
/*    */     //   73: aload_1
/*    */     //   74: getfield y : Ljava/util/List;
/*    */     //   77: putfield x : Ljava/util/List;
/*    */     //   80: aload_0
/*    */     //   81: aload_1
/*    */     //   82: getfield i : Ljava/util/List;
/*    */     //   85: putfield C : Ljava/util/List;
/*    */     //   88: aload_0
/*    */     //   89: aload_1
/*    */     //   90: getfield k : Ljava/util/List;
/*    */     //   93: invokestatic a : (Ljava/util/List;)Ljava/util/List;
/*    */     //   96: putfield k : Ljava/util/List;
/*    */     //   99: astore #14
/*    */     //   101: aload_0
/*    */     //   102: aload_1
/*    */     //   103: getfield A : Ljava/util/List;
/*    */     //   106: invokestatic a : (Ljava/util/List;)Ljava/util/List;
/*    */     //   109: putfield h : Ljava/util/List;
/*    */     //   112: aload_0
/*    */     //   113: aload_1
/*    */     //   114: getfield l : Lme/konsolas/aac/fD;
/*    */     //   117: putfield z : Lme/konsolas/aac/fD;
/*    */     //   120: aload_0
/*    */     //   121: aload_1
/*    */     //   122: getfield n : Ljava/net/ProxySelector;
/*    */     //   125: putfield q : Ljava/net/ProxySelector;
/*    */     //   128: aload_0
/*    */     //   129: aload_1
/*    */     //   130: getfield x : Lme/konsolas/aac/iD;
/*    */     //   133: putfield c : Lme/konsolas/aac/iD;
/*    */     //   136: aload_0
/*    */     //   137: aload_1
/*    */     //   138: getfield d : Lme/konsolas/aac/hW;
/*    */     //   141: putfield l : Lme/konsolas/aac/hW;
/*    */     //   144: aload_0
/*    */     //   145: aload_1
/*    */     //   146: getfield z : Lme/konsolas/aac/bC;
/*    */     //   149: putfield n : Lme/konsolas/aac/bC;
/*    */     //   152: aload_0
/*    */     //   153: aload_1
/*    */     //   154: getfield e : Ljavax/net/SocketFactory;
/*    */     //   157: putfield g : Ljavax/net/SocketFactory;
/*    */     //   160: iconst_0
/*    */     //   161: istore #15
/*    */     //   163: aload_0
/*    */     //   164: getfield C : Ljava/util/List;
/*    */     //   167: invokeinterface iterator : ()Ljava/util/Iterator;
/*    */     //   172: astore #16
/*    */     //   174: aload #16
/*    */     //   176: invokeinterface hasNext : ()Z
/*    */     //   181: ifeq -> 313
/*    */     //   184: aload #16
/*    */     //   186: invokeinterface next : ()Ljava/lang/Object;
/*    */     //   191: checkcast me/konsolas/aac/kB
/*    */     //   194: astore #17
/*    */     //   196: iload #15
/*    */     //   198: aload #14
/*    */     //   200: lload_2
/*    */     //   201: lconst_0
/*    */     //   202: lcmp
/*    */     //   203: iflt -> 604
/*    */     //   206: ifnonnull -> 596
/*    */     //   209: aload #14
/*    */     //   211: ifnonnull -> 283
/*    */     //   214: goto -> 227
/*    */     //   217: ldc2_w -2798479541758625989
/*    */     //   220: lload_2
/*    */     //   221: <illegal opcode> w : (Ljava/lang/IllegalStateException;JJ)Ljava/lang/IllegalStateException;
/*    */     //   226: athrow
/*    */     //   227: ifne -> 282
/*    */     //   230: goto -> 243
/*    */     //   233: ldc2_w -2798479541758625989
/*    */     //   236: lload_2
/*    */     //   237: <illegal opcode> w : (Ljava/lang/IllegalStateException;JJ)Ljava/lang/IllegalStateException;
/*    */     //   242: athrow
/*    */     //   243: aload #17
/*    */     //   245: invokevirtual a : ()Z
/*    */     //   248: aload #14
/*    */     //   250: ifnonnull -> 283
/*    */     //   253: goto -> 266
/*    */     //   256: ldc2_w -2798479541758625989
/*    */     //   259: lload_2
/*    */     //   260: <illegal opcode> w : (Ljava/lang/IllegalStateException;JJ)Ljava/lang/IllegalStateException;
/*    */     //   265: athrow
/*    */     //   266: ifeq -> 286
/*    */     //   269: goto -> 282
/*    */     //   272: ldc2_w -2798479541758625989
/*    */     //   275: lload_2
/*    */     //   276: <illegal opcode> w : (Ljava/lang/IllegalStateException;JJ)Ljava/lang/IllegalStateException;
/*    */     //   281: athrow
/*    */     //   282: iconst_1
/*    */     //   283: goto -> 287
/*    */     //   286: iconst_0
/*    */     //   287: istore #15
/*    */     //   289: aload #14
/*    */     //   291: ifnull -> 174
/*    */     //   294: iconst_4
/*    */     //   295: anewarray me/konsolas/aac/aN
/*    */     //   298: lload_2
/*    */     //   299: lconst_0
/*    */     //   300: lcmp
/*    */     //   301: ifle -> 191
/*    */     //   304: ldc2_w -2791729710542356332
/*    */     //   307: lload_2
/*    */     //   308: <illegal opcode> w : ([Lme/konsolas/aac/aN;JJ)V
/*    */     //   313: lload_2
/*    */     //   314: lconst_0
/*    */     //   315: lcmp
/*    */     //   316: ifle -> 360
/*    */     //   319: aload_1
/*    */     //   320: getfield h : Ljavax/net/ssl/SSLSocketFactory;
/*    */     //   323: ifnonnull -> 344
/*    */     //   326: iload #15
/*    */     //   328: ifne -> 384
/*    */     //   331: goto -> 344
/*    */     //   334: ldc2_w -2798479541758625989
/*    */     //   337: lload_2
/*    */     //   338: <illegal opcode> w : (Ljava/lang/IllegalStateException;JJ)Ljava/lang/IllegalStateException;
/*    */     //   343: athrow
/*    */     //   344: aload_0
/*    */     //   345: aload_1
/*    */     //   346: getfield h : Ljavax/net/ssl/SSLSocketFactory;
/*    */     //   349: putfield s : Ljavax/net/ssl/SSLSocketFactory;
/*    */     //   352: aload_0
/*    */     //   353: aload_1
/*    */     //   354: getfield q : Lme/konsolas/aac/gK;
/*    */     //   357: putfield p : Lme/konsolas/aac/gK;
/*    */     //   360: lload_2
/*    */     //   361: lconst_0
/*    */     //   362: lcmp
/*    */     //   363: ifle -> 413
/*    */     //   366: aload #14
/*    */     //   368: ifnull -> 413
/*    */     //   371: goto -> 384
/*    */     //   374: ldc2_w -2798479541758625989
/*    */     //   377: lload_2
/*    */     //   378: <illegal opcode> w : (Ljava/lang/IllegalStateException;JJ)Ljava/lang/IllegalStateException;
/*    */     //   383: athrow
/*    */     //   384: lload #4
/*    */     //   386: invokestatic a : (J)Ljavax/net/ssl/X509TrustManager;
/*    */     //   389: astore #16
/*    */     //   391: aload_0
/*    */     //   392: lload #6
/*    */     //   394: aload #16
/*    */     //   396: invokestatic a : (JLjavax/net/ssl/X509TrustManager;)Ljavax/net/ssl/SSLSocketFactory;
/*    */     //   399: putfield s : Ljavax/net/ssl/SSLSocketFactory;
/*    */     //   402: aload_0
/*    */     //   403: lload #8
/*    */     //   405: aload #16
/*    */     //   407: invokestatic a : (JLjavax/net/ssl/X509TrustManager;)Lme/konsolas/aac/gK;
/*    */     //   410: putfield p : Lme/konsolas/aac/gK;
/*    */     //   413: aload_0
/*    */     //   414: aload #14
/*    */     //   416: ifnonnull -> 587
/*    */     //   419: getfield s : Ljavax/net/ssl/SSLSocketFactory;
/*    */     //   422: ifnull -> 465
/*    */     //   425: goto -> 438
/*    */     //   428: ldc2_w -2798479541758625989
/*    */     //   431: lload_2
/*    */     //   432: <illegal opcode> w : (Ljava/lang/IllegalStateException;JJ)Ljava/lang/IllegalStateException;
/*    */     //   437: athrow
/*    */     //   438: invokestatic c : ()Lme/konsolas/aac/io;
/*    */     //   441: aload_0
/*    */     //   442: getfield s : Ljavax/net/ssl/SSLSocketFactory;
/*    */     //   445: lload #12
/*    */     //   447: dup2_x1
/*    */     //   448: pop2
/*    */     //   449: invokevirtual a : (JLjavax/net/ssl/SSLSocketFactory;)V
/*    */     //   452: goto -> 465
/*    */     //   455: ldc2_w -2798479541758625989
/*    */     //   458: lload_2
/*    */     //   459: <illegal opcode> w : (Ljava/lang/IllegalStateException;JJ)Ljava/lang/IllegalStateException;
/*    */     //   464: athrow
/*    */     //   465: aload_0
/*    */     //   466: aload_1
/*    */     //   467: getfield j : Ljavax/net/ssl/HostnameVerifier;
/*    */     //   470: putfield b : Ljavax/net/ssl/HostnameVerifier;
/*    */     //   473: aload_0
/*    */     //   474: aload_1
/*    */     //   475: getfield r : Lme/konsolas/aac/mG;
/*    */     //   478: aload_0
/*    */     //   479: getfield p : Lme/konsolas/aac/gK;
/*    */     //   482: lload #10
/*    */     //   484: invokevirtual a : (Lme/konsolas/aac/gK;J)Lme/konsolas/aac/mG;
/*    */     //   487: putfield D : Lme/konsolas/aac/mG;
/*    */     //   490: aload_0
/*    */     //   491: aload_1
/*    */     //   492: getfield t : Lme/konsolas/aac/dp;
/*    */     //   495: putfield u : Lme/konsolas/aac/dp;
/*    */     //   498: aload_0
/*    */     //   499: aload_1
/*    */     //   500: getfield c : Lme/konsolas/aac/dp;
/*    */     //   503: putfield e : Lme/konsolas/aac/dp;
/*    */     //   506: aload_0
/*    */     //   507: aload_1
/*    */     //   508: getfield w : Lme/konsolas/aac/e_;
/*    */     //   511: putfield y : Lme/konsolas/aac/e_;
/*    */     //   514: aload_0
/*    */     //   515: aload_1
/*    */     //   516: getfield p : Lme/konsolas/aac/k4;
/*    */     //   519: putfield a : Lme/konsolas/aac/k4;
/*    */     //   522: aload_0
/*    */     //   523: aload_1
/*    */     //   524: getfield g : Z
/*    */     //   527: putfield m : Z
/*    */     //   530: aload_0
/*    */     //   531: aload_1
/*    */     //   532: getfield B : Z
/*    */     //   535: putfield d : Z
/*    */     //   538: aload_0
/*    */     //   539: aload_1
/*    */     //   540: getfield s : Z
/*    */     //   543: putfield r : Z
/*    */     //   546: aload_0
/*    */     //   547: aload_1
/*    */     //   548: getfield o : I
/*    */     //   551: putfield t : I
/*    */     //   554: aload_0
/*    */     //   555: aload_1
/*    */     //   556: getfield v : I
/*    */     //   559: putfield w : I
/*    */     //   562: aload_0
/*    */     //   563: aload_1
/*    */     //   564: getfield a : I
/*    */     //   567: putfield v : I
/*    */     //   570: aload_0
/*    */     //   571: aload_1
/*    */     //   572: getfield b : I
/*    */     //   575: putfield A : I
/*    */     //   578: aload_0
/*    */     //   579: aload_1
/*    */     //   580: getfield m : I
/*    */     //   583: putfield i : I
/*    */     //   586: aload_0
/*    */     //   587: getfield k : Ljava/util/List;
/*    */     //   590: aconst_null
/*    */     //   591: invokeinterface contains : (Ljava/lang/Object;)Z
/*    */     //   596: lload_2
/*    */     //   597: lconst_0
/*    */     //   598: lcmp
/*    */     //   599: iflt -> 684
/*    */     //   602: aload #14
/*    */     //   604: ifnonnull -> 684
/*    */     //   607: ifeq -> 674
/*    */     //   610: goto -> 623
/*    */     //   613: ldc2_w -2798479541758625989
/*    */     //   616: lload_2
/*    */     //   617: <illegal opcode> w : (Ljava/lang/IllegalStateException;JJ)Ljava/lang/IllegalStateException;
/*    */     //   622: athrow
/*    */     //   623: new java/lang/IllegalStateException
/*    */     //   626: dup
/*    */     //   627: new java/lang/StringBuilder
/*    */     //   630: dup
/*    */     //   631: invokespecial <init> : ()V
/*    */     //   634: sipush #220
/*    */     //   637: ldc2_w 897550988454530313
/*    */     //   640: lload_2
/*    */     //   641: lxor
/*    */     //   642: <illegal opcode> t : (IJ)Ljava/lang/String;
/*    */     //   647: invokevirtual append : (Ljava/lang/String;)Ljava/lang/StringBuilder;
/*    */     //   650: aload_0
/*    */     //   651: getfield k : Ljava/util/List;
/*    */     //   654: invokevirtual append : (Ljava/lang/Object;)Ljava/lang/StringBuilder;
/*    */     //   657: invokevirtual toString : ()Ljava/lang/String;
/*    */     //   660: invokespecial <init> : (Ljava/lang/String;)V
/*    */     //   663: athrow
/*    */     //   664: ldc2_w -2798479541758625989
/*    */     //   667: lload_2
/*    */     //   668: <illegal opcode> w : (Ljava/lang/IllegalStateException;JJ)Ljava/lang/IllegalStateException;
/*    */     //   673: athrow
/*    */     //   674: aload_0
/*    */     //   675: getfield h : Ljava/util/List;
/*    */     //   678: aconst_null
/*    */     //   679: invokeinterface contains : (Ljava/lang/Object;)Z
/*    */     //   684: ifeq -> 738
/*    */     //   687: new java/lang/IllegalStateException
/*    */     //   690: dup
/*    */     //   691: new java/lang/StringBuilder
/*    */     //   694: dup
/*    */     //   695: invokespecial <init> : ()V
/*    */     //   698: sipush #3756
/*    */     //   701: ldc2_w 7474831057518625659
/*    */     //   704: lload_2
/*    */     //   705: lxor
/*    */     //   706: <illegal opcode> t : (IJ)Ljava/lang/String;
/*    */     //   711: invokevirtual append : (Ljava/lang/String;)Ljava/lang/StringBuilder;
/*    */     //   714: aload_0
/*    */     //   715: getfield h : Ljava/util/List;
/*    */     //   718: invokevirtual append : (Ljava/lang/Object;)Ljava/lang/StringBuilder;
/*    */     //   721: invokevirtual toString : ()Ljava/lang/String;
/*    */     //   724: invokespecial <init> : (Ljava/lang/String;)V
/*    */     //   727: athrow
/*    */     //   728: ldc2_w -2798479541758625989
/*    */     //   731: lload_2
/*    */     //   732: <illegal opcode> w : (Ljava/lang/IllegalStateException;JJ)Ljava/lang/IllegalStateException;
/*    */     //   737: athrow
/*    */     //   738: return
/*    */     // Line number table:
/*    */     //   Java source line number -> byte code offset
/*    */     //   #43	-> 52
/*    */     //   #78	-> 56
/*    */     //   #36	-> 64
/*    */     //   #28	-> 72
/*    */     //   #75	-> 80
/*    */     //   #84	-> 88
/*    */     //   #49	-> 101
/*    */     //   #16	-> 112
/*    */     //   #4	-> 120
/*    */     //   #21	-> 128
/*    */     //   #15	-> 136
/*    */     //   #10	-> 144
/*    */     //   #87	-> 152
/*    */     //   #83	-> 160
/*    */     //   #11	-> 163
/*    */     //   #6	-> 196
/*    */     //   #76	-> 289
/*    */     //   #70	-> 313
/*    */     //   #22	-> 344
/*    */     //   #44	-> 352
/*    */     //   #53	-> 384
/*    */     //   #55	-> 391
/*    */     //   #12	-> 402
/*    */     //   #17	-> 413
/*    */     //   #73	-> 438
/*    */     //   #58	-> 465
/*    */     //   #38	-> 473
/*    */     //   #45	-> 490
/*    */     //   #14	-> 498
/*    */     //   #80	-> 506
/*    */     //   #30	-> 514
/*    */     //   #42	-> 522
/*    */     //   #67	-> 530
/*    */     //   #47	-> 538
/*    */     //   #9	-> 546
/*    */     //   #46	-> 554
/*    */     //   #31	-> 562
/*    */     //   #19	-> 570
/*    */     //   #60	-> 578
/*    */     //   #24	-> 586
/*    */     //   #1	-> 623
/*    */     //   #74	-> 674
/*    */     //   #25	-> 687
/*    */     //   #27	-> 738
/*    */     // Exception table:
/*    */     //   from	to	target	type
/*    */     //   196	214	217	java/lang/IllegalStateException
/*    */     //   209	230	233	java/lang/IllegalStateException
/*    */     //   227	253	256	java/lang/IllegalStateException
/*    */     //   243	269	272	java/lang/IllegalStateException
/*    */     //   313	331	334	java/lang/IllegalStateException
/*    */     //   326	371	374	java/lang/IllegalStateException
/*    */     //   413	425	428	java/lang/IllegalStateException
/*    */     //   419	452	455	java/lang/IllegalStateException
/*    */     //   596	610	613	java/lang/IllegalStateException
/*    */     //   607	664	664	java/lang/IllegalStateException
/* 23 */     //   684	728	728	java/lang/IllegalStateException } public k3 a(long paramLong, s params, jn paramjn) { long l1 = paramLong ^ 0x6FE8B4FCA2ABL, l2 = paramLong ^ 0x788BD3E565B9L, l3 = this.i; Random random = new Random(); dw dw = new dw(params, paramjn, l2, random, l3);
/*    */ 
/*    */ 
/*    */ 
/*    */ 
/*    */ 
/*    */ 
/*    */ 
/*    */ 
/*    */ 
/*    */ 
/*    */ 
/*    */ 
/*    */ 
/*    */ 
/*    */ 
/*    */ 
/*    */ 
/*    */ 
/*    */ 
/*    */ 
/*    */ 
/*    */ 
/*    */ 
/*    */ 
/*    */ 
/*    */ 
/*    */ 
/*    */ 
/*    */ 
/*    */ 
/*    */ 
/*    */ 
/*    */ 
/*    */ 
/*    */ 
/*    */ 
/*    */ 
/*    */ 
/*    */ 
/*    */     
/* 64 */     dw.a(this, l1); return dw; }
/* 65 */   public List a() { return this.C; } public SocketFactory a() { return this.g; } public iD a() { return this.c; } public HostnameVerifier a() { return this.b; } public gf(long paramLong) { this(new gI(l1), l2); } @Nullable public hW a() { return this.l; } public jT a() { return this.f; } public int b() { return this.t; } public mG a() { return this.D; } public boolean b() { return this.d; } public dp b() {
/* 66 */     return this.u;
/*    */   } public boolean c() {
/* 68 */     return this.r;
/*    */   } private static SSLSocketFactory a(long paramLong, X509TrustManager paramX509TrustManager) {
/*    */     // Byte code:
/*    */     //   0: getstatic me/konsolas/aac/gf.E : J
/*    */     //   3: lload_0
/*    */     //   4: lxor
/*    */     //   5: lstore_0
/*    */     //   6: lload_0
/*    */     //   7: dup2
/*    */     //   8: ldc2_w 67743186474426
/*    */     //   11: lxor
/*    */     //   12: lstore_3
/*    */     //   13: pop2
/*    */     //   14: invokestatic c : ()Lme/konsolas/aac/io;
/*    */     //   17: lload_3
/*    */     //   18: invokevirtual a : (J)Ljavax/net/ssl/SSLContext;
/*    */     //   21: astore #5
/*    */     //   23: aload #5
/*    */     //   25: aconst_null
/*    */     //   26: iconst_1
/*    */     //   27: anewarray javax/net/ssl/TrustManager
/*    */     //   30: dup
/*    */     //   31: iconst_0
/*    */     //   32: aload_2
/*    */     //   33: aastore
/*    */     //   34: aconst_null
/*    */     //   35: invokevirtual init : ([Ljavax/net/ssl/KeyManager;[Ljavax/net/ssl/TrustManager;Ljava/security/SecureRandom;)V
/*    */     //   38: aload #5
/*    */     //   40: invokevirtual getSocketFactory : ()Ljavax/net/ssl/SSLSocketFactory;
/*    */     //   43: areturn
/*    */     //   44: astore #5
/*    */     //   46: new java/lang/AssertionError
/*    */     //   49: dup
/*    */     //   50: sipush #29206
/*    */     //   53: ldc2_w 3903622432966696297
/*    */     //   56: lload_0
/*    */     //   57: lxor
/*    */     //   58: <illegal opcode> t : (IJ)Ljava/lang/String;
/*    */     //   63: aload #5
/*    */     //   65: invokespecial <init> : (Ljava/lang/String;Ljava/lang/Throwable;)V
/*    */     //   68: athrow
/*    */     // Line number table:
/*    */     //   Java source line number -> byte code offset
/*    */     //   #71	-> 14
/*    */     //   #81	-> 23
/*    */     //   #5	-> 38
/*    */     //   #50	-> 44
/*    */     //   #69	-> 46
/*    */     // Exception table:
/*    */     //   from	to	target	type
/*    */     //   14	43	44	java/security/GeneralSecurityException
/*    */   } public SSLSocketFactory a() {
/* 72 */     return this.s;
/*    */   }
/*    */ 
/*    */   
/*    */   public ProxySelector a() {
/* 77 */     return this.q;
/*    */   } public gI a(long paramLong) {
/* 79 */     paramLong = E ^ paramLong; long l = paramLong ^ 0x2BDACC58A632L; return new gI(this, l);
/*    */   }
/*    */ 
/*    */   
/*    */   public dp a()
/*    */   {
/* 85 */     return this.e; } public fD a() {
/* 86 */     return this.z;
/*    */   }
/*    */   
/*    */   private static IllegalStateException a(IllegalStateException paramIllegalStateException) {
/*    */     return paramIllegalStateException;
/*    */   }
/*    */   
/*    */   private static String a(byte[] paramArrayOfbyte) {
/*    */     byte b1 = 0;
/*    */     int i;
/*    */     char[] arrayOfChar = new char[i = paramArrayOfbyte.length];
/*    */     for (byte b2 = 0; b2 < i; b2++) {
/*    */       int j;
/*    */       if ((j = 0xFF & paramArrayOfbyte[b2]) < 192) {
/*    */         arrayOfChar[b1++] = (char)j;
/*    */       } else if (j < 224) {
/*    */         char c = (char)((char)(j & 0x1F) << 6);
/*    */         j = paramArrayOfbyte[++b2];
/*    */         c = (char)(c | (char)(j & 0x3F));
/*    */         arrayOfChar[b1++] = c;
/*    */       } else if (b2 < i - 2) {
/*    */         char c = (char)((char)(j & 0xF) << 12);
/*    */         j = paramArrayOfbyte[++b2];
/*    */         c = (char)(c | (char)(j & 0x3F) << 6);
/*    */         j = paramArrayOfbyte[++b2];
/*    */         c = (char)(c | (char)(j & 0x3F));
/*    */         arrayOfChar[b1++] = c;
/*    */       } 
/*    */     } 
/*    */     return new String(arrayOfChar, 0, b1);
/*    */   }
/*    */   
/*    */   private static String a(int paramInt, long paramLong) {
/*    */     int i = paramInt ^ (int)(paramLong & 0x7FFFL) ^ 0x55C2;
/*    */     if (G[i] == null) {
/*    */       Object[] arrayOfObject;
/*    */       try {
/*    */         Long long_ = Long.valueOf(Thread.currentThread().getId());
/*    */         arrayOfObject = (Object[])H.get(long_);
/*    */         if (arrayOfObject == null) {
/*    */           arrayOfObject = new Object[3];
/*    */           "站㼹졄ᰂ１ᙩ৛弽꽞ቴ謻뫴椎ㄑ?痔顯甝".toCharArray()[14] = (char)("站㼹졄ᰂ１ᙩ৛弽꽞ቴ謻뫴椎ㄑ?痔顯甝".toCharArray()[14] ^ 0x4C49);
/*    */           arrayOfObject[0] = Cipher.getInstance(da$gx.U("站㼹졄ᰂ１ᙩ৛弽꽞ቴ謻뫴椎ㄑ?痔顯甝".toCharArray(), (short)1659, true, false));
/*    */           "ⅷ௱䪼✰".toCharArray()[1] = (char)("ⅷ௱䪼✰".toCharArray()[1] ^ 0x76B7);
/*    */           arrayOfObject[1] = SecretKeyFactory.getInstance(da$gx.U("ⅷ௱䪼✰".toCharArray(), (short)25325, false, false));
/*    */           arrayOfObject[2] = new IvParameterSpec(new byte[8]);
/*    */           H.put(long_, arrayOfObject);
/*    */         } 
/*    */       } catch (Exception exception) {
/*    */         "≵떾溞孟庡詑ᛋ쬺ࡣ뫼廾ᮕꇲ몸焢ዩ彑⹯܏".toCharArray()[0] = (char)("≵떾溞孟庡詑ᛋ쬺ࡣ뫼廾ᮕꇲ몸焢ዩ彑⹯܏".toCharArray()[0] ^ 0x285B);
/*    */         throw new RuntimeException(da$gx.U("≵떾溞孟庡詑ᛋ쬺ࡣ뫼廾ᮕꇲ몸焢ዩ彑⹯܏".toCharArray(), (short)3386, true, false), exception);
/*    */       } 
/*    */       byte[] arrayOfByte1 = new byte[8];
/*    */       arrayOfByte1[0] = (byte)(int)(paramLong >>> 56L);
/*    */       for (byte b = 1; b < 8; b++)
/*    */         arrayOfByte1[b] = (byte)(int)(paramLong << b * 8 >>> 56L); 
/*    */       DESKeySpec dESKeySpec = new DESKeySpec(arrayOfByte1);
/*    */       SecretKey secretKey = ((SecretKeyFactory)arrayOfObject[1]).generateSecret(dESKeySpec);
/*    */       ((Cipher)arrayOfObject[0]).init(2, secretKey, (IvParameterSpec)arrayOfObject[2]);
/*    */       "뢠펵힗ఝ⍆픜鯾瑋ᕕ".toCharArray()[3] = (char)("뢠펵힗ఝ⍆픜鯾瑋ᕕ".toCharArray()[3] ^ 0x7CB4);
/*    */       byte[] arrayOfByte2 = F[i].getBytes(da$gx.U("뢠펵힗ఝ⍆픜鯾瑋ᕕ".toCharArray(), (short)1616, true, false));
/*    */       G[i] = a(((Cipher)arrayOfObject[0]).doFinal(arrayOfByte2));
/*    */     } 
/*    */     return G[i];
/*    */   }
/*    */   
/*    */   private static Object a(MethodHandles.Lookup paramLookup, MutableCallSite paramMutableCallSite, String paramString, Object[] paramArrayOfObject) {
/*    */     int i = ((Integer)paramArrayOfObject[0]).intValue();
/*    */     long l = ((Long)paramArrayOfObject[1]).longValue();
/*    */     String str = a(i, l);
/*    */     MethodHandle methodHandle = MethodHandles.constant(String.class, str);
/*    */     paramMutableCallSite.setTarget(MethodHandles.dropArguments(methodHandle, 0, new Class[] { int.class, long.class }));
/*    */     return str;
/*    */   }
/*    */   
/*    */   private static CallSite a(MethodHandles.Lookup paramLookup, String paramString, MethodType paramMethodType) {
/*    */     // Byte code:
/*    */     //   0: new java/lang/invoke/MutableCallSite
/*    */     //   3: dup
/*    */     //   4: aload_2
/*    */     //   5: invokespecial <init> : (Ljava/lang/invoke/MethodType;)V
/*    */     //   8: astore_3
/*    */     //   9: aload_3
/*    */     //   10: ldc_w
/*    */     //   13: ldc_w [Ljava/lang/Object;
/*    */     //   16: aload_2
/*    */     //   17: invokevirtual parameterCount : ()I
/*    */     //   20: invokevirtual asCollector : (Ljava/lang/Class;I)Ljava/lang/invoke/MethodHandle;
/*    */     //   23: iconst_0
/*    */     //   24: iconst_3
/*    */     //   25: anewarray java/lang/Object
/*    */     //   28: dup
/*    */     //   29: iconst_0
/*    */     //   30: aload_0
/*    */     //   31: aastore
/*    */     //   32: dup
/*    */     //   33: iconst_1
/*    */     //   34: aload_3
/*    */     //   35: aastore
/*    */     //   36: dup
/*    */     //   37: iconst_2
/*    */     //   38: aload_1
/*    */     //   39: aastore
/*    */     //   40: invokestatic insertArguments : (Ljava/lang/invoke/MethodHandle;I[Ljava/lang/Object;)Ljava/lang/invoke/MethodHandle;
/*    */     //   43: aload_2
/*    */     //   44: invokestatic explicitCastArguments : (Ljava/lang/invoke/MethodHandle;Ljava/lang/invoke/MethodType;)Ljava/lang/invoke/MethodHandle;
/*    */     //   47: invokevirtual setTarget : (Ljava/lang/invoke/MethodHandle;)V
/*    */     //   50: goto -> 170
/*    */     //   53: astore #4
/*    */     //   55: new java/lang/RuntimeException
/*    */     //   58: dup
/*    */     //   59: new java/lang/StringBuilder
/*    */     //   62: dup
/*    */     //   63: invokespecial <init> : ()V
/*    */     //   66: ldc_w '៷櫠꫘⓷뗵丷굃낐ꈦH⏝ਫ਼죈䙙퐑⥑䐦戺'
/*    */     //   69: invokevirtual toCharArray : ()[C
/*    */     //   72: dup
/*    */     //   73: dup
/*    */     //   74: iconst_3
/*    */     //   75: dup_x1
/*    */     //   76: caload
/*    */     //   77: sipush #10846
/*    */     //   80: ixor
/*    */     //   81: i2c
/*    */     //   82: castore
/*    */     //   83: sipush #2950
/*    */     //   86: iconst_1
/*    */     //   87: iconst_0
/*    */     //   88: invokestatic A : (Ljava/lang/Object;SZI)Ljava/lang/String;
/*    */     //   91: invokevirtual append : (Ljava/lang/String;)Ljava/lang/StringBuilder;
/*    */     //   94: ldc_w '兦ꛝ䥅'
/*    */     //   97: invokevirtual toCharArray : ()[C
/*    */     //   100: dup
/*    */     //   101: dup
/*    */     //   102: iconst_2
/*    */     //   103: dup_x1
/*    */     //   104: caload
/*    */     //   105: sipush #12499
/*    */     //   108: ixor
/*    */     //   109: i2c
/*    */     //   110: castore
/*    */     //   111: sipush #28939
/*    */     //   114: iconst_0
/*    */     //   115: iconst_3
/*    */     //   116: invokestatic A : (Ljava/lang/Object;SZI)Ljava/lang/String;
/*    */     //   119: invokevirtual append : (Ljava/lang/String;)Ljava/lang/StringBuilder;
/*    */     //   122: aload_1
/*    */     //   123: invokevirtual append : (Ljava/lang/String;)Ljava/lang/StringBuilder;
/*    */     //   126: ldc_w '덕㒉駡璖'
/*    */     //   129: invokevirtual toCharArray : ()[C
/*    */     //   132: dup
/*    */     //   133: dup
/*    */     //   134: iconst_0
/*    */     //   135: dup_x1
/*    */     //   136: caload
/*    */     //   137: sipush #8433
/*    */     //   140: ixor
/*    */     //   141: i2c
/*    */     //   142: castore
/*    */     //   143: sipush #20869
/*    */     //   146: iconst_0
/*    */     //   147: iconst_2
/*    */     //   148: invokestatic A : (Ljava/lang/Object;SZI)Ljava/lang/String;
/*    */     //   151: invokevirtual append : (Ljava/lang/String;)Ljava/lang/StringBuilder;
/*    */     //   154: aload_2
/*    */     //   155: invokevirtual toString : ()Ljava/lang/String;
/*    */     //   158: invokevirtual append : (Ljava/lang/String;)Ljava/lang/StringBuilder;
/*    */     //   161: invokevirtual toString : ()Ljava/lang/String;
/*    */     //   164: aload #4
/*    */     //   166: invokespecial <init> : (Ljava/lang/String;Ljava/lang/Throwable;)V
/*    */     //   169: athrow
/*    */     //   170: aload_3
/*    */     //   171: areturn
/*    */     // Exception table:
/*    */     //   from	to	target	type
/*    */     //   9	50	53	java/lang/Exception
/*    */   } }


/* Location:              C:\Users\BukkitBypass\Desktop\MatrixAC\AAC\AAC-spigot-5.2.0.jar!\me\konsolas\aac\gf.class
 * Java compiler version: 8 (52.0)
 * JD-Core Version:       1.1.3
 */