/*     */ package me.konsolas.aac;
/*     */ public final class gz {
/*     */   private static final gZ c;
/*     */   private static final gZ d;
/*     */   private static boolean b;
/*     */   private static final long a;
/*     */   
/*     */   private static String a(char paramChar, int paramInt) {
/*   9 */     char[] arrayOfChar = new char[paramInt];
/*     */ 
/*     */ 
/*     */ 
/*     */ 
/*     */ 
/*     */ 
/*     */ 
/*     */ 
/*     */ 
/*     */ 
/*     */ 
/*     */     
/*  22 */     Arrays.fill(arrayOfChar, paramChar);
/*     */ 
/*     */ 
/*     */ 
/*     */ 
/*     */ 
/*     */ 
/*     */ 
/*     */ 
/*     */ 
/*     */ 
/*     */ 
/*     */ 
/*     */ 
/*     */ 
/*     */ 
/*     */ 
/*     */ 
/*     */ 
/*     */ 
/*     */ 
/*     */ 
/*     */ 
/*     */ 
/*     */ 
/*     */ 
/*     */ 
/*     */ 
/*     */ 
/*     */ 
/*     */ 
/*     */ 
/*     */ 
/*     */ 
/*     */ 
/*     */ 
/*     */ 
/*     */ 
/*     */ 
/*     */ 
/*     */ 
/*     */ 
/*     */     
/*  65 */     return new String(arrayOfChar);
/*     */   } private static final String[] e; private static final String[] f; private static final Map g; public static boolean a(long paramLong, H paramH, J paramJ, s params) {
/*     */     // Byte code:
/*     */     //   0: getstatic me/konsolas/aac/gz.a : J
/*     */     //   3: lload_0
/*     */     //   4: lxor
/*     */     //   5: lstore_0
/*     */     //   6: lload_0
/*     */     //   7: dup2
/*     */     //   8: ldc2_w 106672634128568
/*     */     //   11: lxor
/*     */     //   12: lstore #5
/*     */     //   14: dup2
/*     */     //   15: ldc2_w 101247659050958
/*     */     //   18: lxor
/*     */     //   19: lstore #7
/*     */     //   21: dup2
/*     */     //   22: ldc2_w 13116813596185
/*     */     //   25: lxor
/*     */     //   26: lstore #9
/*     */     //   28: pop2
/*     */     //   29: ldc2_w -6311265462169290938
/*     */     //   32: lload_0
/*     */     //   33: <illegal opcode> w : (JJ)Z
/*     */     //   38: lload #5
/*     */     //   40: aload_2
/*     */     //   41: invokestatic a : (JLme/konsolas/aac/H;)Ljava/util/Set;
/*     */     //   44: invokeinterface iterator : ()Ljava/util/Iterator;
/*     */     //   49: astore #12
/*     */     //   51: istore #11
/*     */     //   53: aload #12
/*     */     //   55: invokeinterface hasNext : ()Z
/*     */     //   60: ifeq -> 147
/*     */     //   63: aload #12
/*     */     //   65: invokeinterface next : ()Ljava/lang/Object;
/*     */     //   70: checkcast java/lang/String
/*     */     //   73: astore #13
/*     */     //   75: aload_3
/*     */     //   76: aload #13
/*     */     //   78: lload #7
/*     */     //   80: invokevirtual a : (Ljava/lang/String;J)Ljava/util/List;
/*     */     //   83: aload #4
/*     */     //   85: aload #13
/*     */     //   87: lload #9
/*     */     //   89: invokevirtual a : (Ljava/lang/String;J)Ljava/util/List;
/*     */     //   92: invokestatic equals : (Ljava/lang/Object;Ljava/lang/Object;)Z
/*     */     //   95: iload #11
/*     */     //   97: lload_0
/*     */     //   98: lconst_0
/*     */     //   99: lcmp
/*     */     //   100: iflt -> 108
/*     */     //   103: ifne -> 148
/*     */     //   106: iload #11
/*     */     //   108: ifne -> 141
/*     */     //   111: goto -> 124
/*     */     //   114: ldc2_w -6202328445095188301
/*     */     //   117: lload_0
/*     */     //   118: <illegal opcode> w : (Ljava/lang/Exception;JJ)Ljava/lang/Exception;
/*     */     //   123: athrow
/*     */     //   124: ifne -> 142
/*     */     //   127: goto -> 140
/*     */     //   130: ldc2_w -6202328445095188301
/*     */     //   133: lload_0
/*     */     //   134: <illegal opcode> w : (Ljava/lang/Exception;JJ)Ljava/lang/Exception;
/*     */     //   139: athrow
/*     */     //   140: iconst_0
/*     */     //   141: ireturn
/*     */     //   142: iload #11
/*     */     //   144: ifeq -> 53
/*     */     //   147: iconst_1
/*     */     //   148: ireturn
/*     */     // Line number table:
/*     */     //   Java source line number -> byte code offset
/*     */     //   #4	-> 38
/*     */     //   #27	-> 75
/*     */     //   #74	-> 142
/*     */     //   #16	-> 147
/*     */     // Exception table:
/*     */     //   from	to	target	type
/*     */     //   75	111	114	java/lang/NumberFormatException
/*     */     //   106	127	130	java/lang/NumberFormatException
/*     */   } public static J a(J paramJ1, J paramJ2, long paramLong) {
/*     */     // Byte code:
/*     */     //   0: getstatic me/konsolas/aac/gz.a : J
/*     */     //   3: lload_2
/*     */     //   4: lxor
/*     */     //   5: lstore_2
/*     */     //   6: lload_2
/*     */     //   7: dup2
/*     */     //   8: ldc2_w 60001723839762
/*     */     //   11: lxor
/*     */     //   12: lstore #4
/*     */     //   14: dup2
/*     */     //   15: ldc2_w 88640126820200
/*     */     //   18: lxor
/*     */     //   19: lstore #6
/*     */     //   21: pop2
/*     */     //   22: ldc2_w -8171800609077463284
/*     */     //   25: lload_2
/*     */     //   26: <illegal opcode> w : (JJ)Z
/*     */     //   31: lload #4
/*     */     //   33: aload_1
/*     */     //   34: invokestatic a : (JLme/konsolas/aac/J;)Ljava/util/Set;
/*     */     //   37: astore #9
/*     */     //   39: istore #8
/*     */     //   41: aload #9
/*     */     //   43: invokeinterface isEmpty : ()Z
/*     */     //   48: ifeq -> 65
/*     */     //   51: getstatic me/konsolas/aac/eO.i : Lme/konsolas/aac/J;
/*     */     //   54: areturn
/*     */     //   55: ldc2_w -8118348082828554742
/*     */     //   58: lload_2
/*     */     //   59: <illegal opcode> w : (Ljava/lang/Exception;JJ)Ljava/lang/Exception;
/*     */     //   64: athrow
/*     */     //   65: new me/konsolas/aac/mr
/*     */     //   68: dup
/*     */     //   69: invokespecial <init> : ()V
/*     */     //   72: astore #10
/*     */     //   74: iconst_0
/*     */     //   75: istore #11
/*     */     //   77: aload_0
/*     */     //   78: invokevirtual a : ()I
/*     */     //   81: istore #12
/*     */     //   83: iload #11
/*     */     //   85: iload #12
/*     */     //   87: if_icmpge -> 182
/*     */     //   90: aload_0
/*     */     //   91: iload #8
/*     */     //   93: lload_2
/*     */     //   94: lconst_0
/*     */     //   95: lcmp
/*     */     //   96: iflt -> 104
/*     */     //   99: ifeq -> 187
/*     */     //   102: iload #11
/*     */     //   104: invokevirtual a : (I)Ljava/lang/String;
/*     */     //   107: astore #13
/*     */     //   109: iload #8
/*     */     //   111: lload_2
/*     */     //   112: lconst_0
/*     */     //   113: lcmp
/*     */     //   114: iflt -> 179
/*     */     //   117: ifeq -> 177
/*     */     //   120: aload #9
/*     */     //   122: aload #13
/*     */     //   124: invokeinterface contains : (Ljava/lang/Object;)Z
/*     */     //   129: ifeq -> 174
/*     */     //   132: goto -> 145
/*     */     //   135: ldc2_w -8118348082828554742
/*     */     //   138: lload_2
/*     */     //   139: <illegal opcode> w : (Ljava/lang/Exception;JJ)Ljava/lang/Exception;
/*     */     //   144: athrow
/*     */     //   145: aload #10
/*     */     //   147: aload #13
/*     */     //   149: aload_0
/*     */     //   150: iload #11
/*     */     //   152: invokevirtual b : (I)Ljava/lang/String;
/*     */     //   155: lload #6
/*     */     //   157: invokevirtual d : (Ljava/lang/String;Ljava/lang/String;J)Lme/konsolas/aac/mr;
/*     */     //   160: pop
/*     */     //   161: goto -> 174
/*     */     //   164: ldc2_w -8118348082828554742
/*     */     //   167: lload_2
/*     */     //   168: <illegal opcode> w : (Ljava/lang/Exception;JJ)Ljava/lang/Exception;
/*     */     //   173: athrow
/*     */     //   174: iinc #11, 1
/*     */     //   177: iload #8
/*     */     //   179: ifne -> 83
/*     */     //   182: aload #10
/*     */     //   184: invokevirtual a : ()Lme/konsolas/aac/J;
/*     */     //   187: areturn
/*     */     // Line number table:
/*     */     //   Java source line number -> byte code offset
/*     */     //   #5	-> 31
/*     */     //   #147	-> 41
/*     */     //   #88	-> 65
/*     */     //   #17	-> 74
/*     */     //   #76	-> 90
/*     */     //   #157	-> 109
/*     */     //   #158	-> 145
/*     */     //   #151	-> 174
/*     */     //   #149	-> 182
/*     */     // Exception table:
/*     */     //   from	to	target	type
/*     */     //   41	55	55	java/lang/NumberFormatException
/*     */     //   109	132	135	java/lang/NumberFormatException
/*     */     //   120	161	164	java/lang/NumberFormatException
/*     */   } private static Set a(long paramLong, H paramH) {
/*     */     paramLong = a ^ paramLong;
/*     */     long l = paramLong ^ 0x4D04C1D9C09L;
/*     */     return a(l, paramH.a());
/*     */   } public static boolean a(J paramJ, long paramLong) {
/*     */     paramLong = a ^ paramLong;
/*     */     long l = paramLong ^ 0x3EC3B0EFF211L;
/*     */     "谬㰑".toCharArray()[0] = (char)("谬㰑".toCharArray()[0] ^ 0x2437);
/*     */     return a(l, paramJ).contains(fW$gy.A("谬㰑".toCharArray(), (short)3248, false, 1));
/*     */   } private static boolean a(long paramLong, fw paramfw) {
/*     */     // Byte code:
/*     */     //   0: getstatic me/konsolas/aac/gz.a : J
/*     */     //   3: lload_0
/*     */     //   4: lxor
/*     */     //   5: lstore_0
/*     */     //   6: lload_0
/*     */     //   7: dup2
/*     */     //   8: ldc2_w 75184460658475
/*     */     //   11: lxor
/*     */     //   12: dup2
/*     */     //   13: bipush #32
/*     */     //   15: lushr
/*     */     //   16: l2i
/*     */     //   17: istore_3
/*     */     //   18: dup2
/*     */     //   19: bipush #32
/*     */     //   21: lshl
/*     */     //   22: bipush #48
/*     */     //   24: lushr
/*     */     //   25: l2i
/*     */     //   26: istore #4
/*     */     //   28: dup2
/*     */     //   29: bipush #48
/*     */     //   31: lshl
/*     */     //   32: bipush #48
/*     */     //   34: lushr
/*     */     //   35: l2i
/*     */     //   36: istore #5
/*     */     //   38: pop2
/*     */     //   39: dup2
/*     */     //   40: ldc2_w 68240592238329
/*     */     //   43: lxor
/*     */     //   44: lstore #6
/*     */     //   46: dup2
/*     */     //   47: ldc2_w 34972189261896
/*     */     //   50: lxor
/*     */     //   51: lstore #8
/*     */     //   53: pop2
/*     */     //   54: ldc2_w -68497352469946333
/*     */     //   57: lload_0
/*     */     //   58: <illegal opcode> w : (JJ)Z
/*     */     //   63: iconst_0
/*     */     //   64: istore #11
/*     */     //   66: istore #10
/*     */     //   68: aload_2
/*     */     //   69: iload_3
/*     */     //   70: iload #4
/*     */     //   72: i2c
/*     */     //   73: iload #5
/*     */     //   75: invokevirtual a : (ICI)Z
/*     */     //   78: ifne -> 273
/*     */     //   81: aload_2
/*     */     //   82: lconst_0
/*     */     //   83: lload #8
/*     */     //   85: invokevirtual a : (JJ)B
/*     */     //   88: istore #12
/*     */     //   90: iload #12
/*     */     //   92: iload #10
/*     */     //   94: lload_0
/*     */     //   95: lconst_0
/*     */     //   96: lcmp
/*     */     //   97: ifle -> 105
/*     */     //   100: ifne -> 275
/*     */     //   103: bipush #44
/*     */     //   105: lload_0
/*     */     //   106: lconst_0
/*     */     //   107: lcmp
/*     */     //   108: ifle -> 201
/*     */     //   111: iload #10
/*     */     //   113: ifne -> 201
/*     */     //   116: goto -> 129
/*     */     //   119: ldc2_w -105376479293947946
/*     */     //   122: lload_0
/*     */     //   123: <illegal opcode> w : (Ljava/lang/Exception;JJ)Ljava/lang/Exception;
/*     */     //   128: athrow
/*     */     //   129: if_icmpne -> 166
/*     */     //   132: goto -> 145
/*     */     //   135: ldc2_w -105376479293947946
/*     */     //   138: lload_0
/*     */     //   139: <illegal opcode> w : (Ljava/lang/Exception;JJ)Ljava/lang/Exception;
/*     */     //   144: athrow
/*     */     //   145: aload_2
/*     */     //   146: lload #6
/*     */     //   148: invokevirtual a : (J)B
/*     */     //   151: pop
/*     */     //   152: iconst_1
/*     */     //   153: istore #11
/*     */     //   155: iload #10
/*     */     //   157: lload_0
/*     */     //   158: lconst_0
/*     */     //   159: lcmp
/*     */     //   160: iflt -> 270
/*     */     //   163: ifeq -> 268
/*     */     //   166: iload #12
/*     */     //   168: iload #10
/*     */     //   170: ifne -> 267
/*     */     //   173: goto -> 186
/*     */     //   176: ldc2_w -105376479293947946
/*     */     //   179: lload_0
/*     */     //   180: <illegal opcode> w : (Ljava/lang/Exception;JJ)Ljava/lang/Exception;
/*     */     //   185: athrow
/*     */     //   186: bipush #32
/*     */     //   188: goto -> 201
/*     */     //   191: ldc2_w -105376479293947946
/*     */     //   194: lload_0
/*     */     //   195: <illegal opcode> w : (Ljava/lang/Exception;JJ)Ljava/lang/Exception;
/*     */     //   200: athrow
/*     */     //   201: lload_0
/*     */     //   202: lconst_0
/*     */     //   203: lcmp
/*     */     //   204: iflt -> 214
/*     */     //   207: if_icmpeq -> 248
/*     */     //   210: iload #12
/*     */     //   212: iload #10
/*     */     //   214: ifne -> 275
/*     */     //   217: goto -> 230
/*     */     //   220: ldc2_w -105376479293947946
/*     */     //   223: lload_0
/*     */     //   224: <illegal opcode> w : (Ljava/lang/Exception;JJ)Ljava/lang/Exception;
/*     */     //   229: athrow
/*     */     //   230: bipush #9
/*     */     //   232: if_icmpne -> 273
/*     */     //   235: goto -> 248
/*     */     //   238: ldc2_w -105376479293947946
/*     */     //   241: lload_0
/*     */     //   242: <illegal opcode> w : (Ljava/lang/Exception;JJ)Ljava/lang/Exception;
/*     */     //   247: athrow
/*     */     //   248: aload_2
/*     */     //   249: lload #6
/*     */     //   251: invokevirtual a : (J)B
/*     */     //   254: goto -> 267
/*     */     //   257: ldc2_w -105376479293947946
/*     */     //   260: lload_0
/*     */     //   261: <illegal opcode> w : (Ljava/lang/Exception;JJ)Ljava/lang/Exception;
/*     */     //   266: athrow
/*     */     //   267: pop
/*     */     //   268: iload #10
/*     */     //   270: ifeq -> 68
/*     */     //   273: iload #11
/*     */     //   275: ireturn
/*     */     // Line number table:
/*     */     //   Java source line number -> byte code offset
/*     */     //   #24	-> 63
/*     */     //   #13	-> 68
/*     */     //   #52	-> 81
/*     */     //   #108	-> 90
/*     */     //   #112	-> 145
/*     */     //   #28	-> 152
/*     */     //   #81	-> 166
/*     */     //   #131	-> 248
/*     */     //   #8	-> 268
/*     */     //   #119	-> 273
/*     */     // Exception table:
/*     */     //   from	to	target	type
/*     */     //   90	116	119	java/lang/NumberFormatException
/*     */     //   103	132	135	java/lang/NumberFormatException
/*     */     //   155	173	176	java/lang/NumberFormatException
/*     */     //   166	188	191	java/lang/NumberFormatException
/*     */     //   201	217	220	java/lang/NumberFormatException
/*     */     //   210	235	238	java/lang/NumberFormatException
/*     */     //   230	254	257	java/lang/NumberFormatException
/*     */   } public static Set a(long paramLong, J paramJ) {
/*     */     // Byte code:
/*     */     //   0: getstatic me/konsolas/aac/gz.a : J
/*     */     //   3: lload_0
/*     */     //   4: lxor
/*     */     //   5: lstore_0
/*     */     //   6: invokestatic emptySet : ()Ljava/util/Set;
/*     */     //   9: astore #4
/*     */     //   11: iconst_0
/*     */     //   12: istore #5
/*     */     //   14: ldc2_w -2533129290722163721
/*     */     //   17: lload_0
/*     */     //   18: <illegal opcode> w : (JJ)Z
/*     */     //   23: aload_2
/*     */     //   24: invokevirtual a : ()I
/*     */     //   27: istore #6
/*     */     //   29: istore_3
/*     */     //   30: iload #5
/*     */     //   32: iload #6
/*     */     //   34: if_icmpge -> 237
/*     */     //   37: sipush #1897
/*     */     //   40: lload_0
/*     */     //   41: lconst_0
/*     */     //   42: lcmp
/*     */     //   43: iflt -> 69
/*     */     //   46: ldc2_w 388704157832460041
/*     */     //   49: lload_0
/*     */     //   50: lxor
/*     */     //   51: <illegal opcode> l : (IJ)Ljava/lang/String;
/*     */     //   56: iload_3
/*     */     //   57: ifne -> 104
/*     */     //   60: aload_2
/*     */     //   61: iload #5
/*     */     //   63: invokevirtual a : (I)Ljava/lang/String;
/*     */     //   66: invokevirtual equalsIgnoreCase : (Ljava/lang/String;)Z
/*     */     //   69: ifne -> 98
/*     */     //   72: goto -> 85
/*     */     //   75: ldc2_w -2495694620627330046
/*     */     //   78: lload_0
/*     */     //   79: <illegal opcode> w : (Ljava/lang/Exception;JJ)Ljava/lang/Exception;
/*     */     //   84: athrow
/*     */     //   85: goto -> 230
/*     */     //   88: ldc2_w -2495694620627330046
/*     */     //   91: lload_0
/*     */     //   92: <illegal opcode> w : (Ljava/lang/Exception;JJ)Ljava/lang/Exception;
/*     */     //   97: athrow
/*     */     //   98: aload_2
/*     */     //   99: iload #5
/*     */     //   101: invokevirtual b : (I)Ljava/lang/String;
/*     */     //   104: astore #7
/*     */     //   106: aload #4
/*     */     //   108: invokeinterface isEmpty : ()Z
/*     */     //   113: ifeq -> 128
/*     */     //   116: new java/util/TreeSet
/*     */     //   119: dup
/*     */     //   120: getstatic java/lang/String.CASE_INSENSITIVE_ORDER : Ljava/util/Comparator;
/*     */     //   123: invokespecial <init> : (Ljava/util/Comparator;)V
/*     */     //   126: astore #4
/*     */     //   128: aload #7
/*     */     //   130: ldc 'ㅙ⋒'
/*     */     //   132: invokevirtual toCharArray : ()[C
/*     */     //   135: dup
/*     */     //   136: dup
/*     */     //   137: iconst_0
/*     */     //   138: dup_x1
/*     */     //   139: caload
/*     */     //   140: sipush #16780
/*     */     //   143: ixor
/*     */     //   144: i2c
/*     */     //   145: castore
/*     */     //   146: sipush #8044
/*     */     //   149: iconst_0
/*     */     //   150: iconst_0
/*     */     //   151: invokestatic A : (Ljava/lang/Object;SZI)Ljava/lang/String;
/*     */     //   154: invokevirtual split : (Ljava/lang/String;)[Ljava/lang/String;
/*     */     //   157: astore #8
/*     */     //   159: aload #8
/*     */     //   161: arraylength
/*     */     //   162: istore #9
/*     */     //   164: iconst_0
/*     */     //   165: istore #10
/*     */     //   167: iload #10
/*     */     //   169: iload #9
/*     */     //   171: if_icmpge -> 230
/*     */     //   174: aload #8
/*     */     //   176: iload #10
/*     */     //   178: aaload
/*     */     //   179: astore #11
/*     */     //   181: aload #4
/*     */     //   183: aload #11
/*     */     //   185: invokevirtual trim : ()Ljava/lang/String;
/*     */     //   188: invokeinterface add : (Ljava/lang/Object;)Z
/*     */     //   193: pop
/*     */     //   194: iinc #10, 1
/*     */     //   197: iload_3
/*     */     //   198: lload_0
/*     */     //   199: lconst_0
/*     */     //   200: lcmp
/*     */     //   201: ifle -> 234
/*     */     //   204: ifne -> 233
/*     */     //   207: iload_3
/*     */     //   208: ifeq -> 167
/*     */     //   211: lload_0
/*     */     //   212: lconst_0
/*     */     //   213: lcmp
/*     */     //   214: ifle -> 197
/*     */     //   217: goto -> 230
/*     */     //   220: ldc2_w -2495694620627330046
/*     */     //   223: lload_0
/*     */     //   224: <illegal opcode> w : (Ljava/lang/Exception;JJ)Ljava/lang/Exception;
/*     */     //   229: athrow
/*     */     //   230: iinc #5, 1
/*     */     //   233: iload_3
/*     */     //   234: ifeq -> 30
/*     */     //   237: lload_0
/*     */     //   238: lconst_0
/*     */     //   239: lcmp
/*     */     //   240: iflt -> 37
/*     */     //   243: aload #4
/*     */     //   245: areturn
/*     */     // Line number table:
/*     */     //   Java source line number -> byte code offset
/*     */     //   #37	-> 6
/*     */     //   #69	-> 11
/*     */     //   #90	-> 37
/*     */     //   #127	-> 98
/*     */     //   #139	-> 106
/*     */     //   #85	-> 116
/*     */     //   #133	-> 128
/*     */     //   #30	-> 181
/*     */     //   #51	-> 194
/*     */     //   #43	-> 230
/*     */     //   #94	-> 237
/*     */     // Exception table:
/*     */     //   from	to	target	type
/*     */     //   37	72	75	java/lang/NumberFormatException
/*     */     //   60	88	88	java/lang/NumberFormatException
/*     */     //   181	211	220	java/lang/NumberFormatException
/*     */   } public static List a(long paramLong, J paramJ, byte paramByte, String paramString) {
/*     */     // Byte code:
/*     */     //   0: lload_0
/*     */     //   1: bipush #8
/*     */     //   3: lshl
/*     */     //   4: iload_3
/*     */     //   5: i2l
/*     */     //   6: bipush #56
/*     */     //   8: lshl
/*     */     //   9: bipush #56
/*     */     //   11: lushr
/*     */     //   12: lor
/*     */     //   13: getstatic me/konsolas/aac/gz.a : J
/*     */     //   16: lxor
/*     */     //   17: lstore #5
/*     */     //   19: lload #5
/*     */     //   21: dup2
/*     */     //   22: ldc2_w 73431061150960
/*     */     //   25: lxor
/*     */     //   26: lstore #7
/*     */     //   28: dup2
/*     */     //   29: ldc2_w 112560238351036
/*     */     //   32: lxor
/*     */     //   33: lstore #9
/*     */     //   35: pop2
/*     */     //   36: ldc2_w -1982785631450260000
/*     */     //   39: lload #5
/*     */     //   41: <illegal opcode> w : (JJ)Z
/*     */     //   46: new java/util/ArrayList
/*     */     //   49: dup
/*     */     //   50: invokespecial <init> : ()V
/*     */     //   53: astore #12
/*     */     //   55: istore #11
/*     */     //   57: iconst_0
/*     */     //   58: istore #13
/*     */     //   60: iload #13
/*     */     //   62: aload_2
/*     */     //   63: invokevirtual a : ()I
/*     */     //   66: if_icmpge -> 126
/*     */     //   69: aload #4
/*     */     //   71: aload_2
/*     */     //   72: iload #13
/*     */     //   74: invokevirtual a : (I)Ljava/lang/String;
/*     */     //   77: invokevirtual equalsIgnoreCase : (Ljava/lang/String;)Z
/*     */     //   80: iload_3
/*     */     //   81: iflt -> 123
/*     */     //   84: ifeq -> 118
/*     */     //   87: new me/konsolas/aac/fw
/*     */     //   90: dup
/*     */     //   91: invokespecial <init> : ()V
/*     */     //   94: aload_2
/*     */     //   95: iload #13
/*     */     //   97: invokevirtual b : (I)Ljava/lang/String;
/*     */     //   100: lload #9
/*     */     //   102: dup2_x1
/*     */     //   103: pop2
/*     */     //   104: invokevirtual a : (JLjava/lang/String;)Lme/konsolas/aac/fw;
/*     */     //   107: astore #14
/*     */     //   109: aload #12
/*     */     //   111: lload #7
/*     */     //   113: aload #14
/*     */     //   115: invokestatic a : (Ljava/util/List;JLme/konsolas/aac/fw;)V
/*     */     //   118: iinc #13, 1
/*     */     //   121: iload #11
/*     */     //   123: ifne -> 60
/*     */     //   126: iload_3
/*     */     //   127: ifle -> 121
/*     */     //   130: aload #12
/*     */     //   132: areturn
/*     */     // Line number table:
/*     */     //   Java source line number -> byte code offset
/*     */     //   #41	-> 46
/*     */     //   #63	-> 57
/*     */     //   #19	-> 69
/*     */     //   #40	-> 87
/*     */     //   #46	-> 109
/*     */     //   #3	-> 118
/*     */     //   #47	-> 126
/*     */   } public static int a(String paramString, long paramLong, int paramInt) {
/*     */     // Byte code:
/*     */     //   0: getstatic me/konsolas/aac/gz.a : J
/*     */     //   3: lload_1
/*     */     //   4: lxor
/*     */     //   5: lstore_1
/*     */     //   6: ldc2_w 6405154222412800376
/*     */     //   9: lload_1
/*     */     //   10: <illegal opcode> w : (JJ)Z
/*     */     //   15: istore #4
/*     */     //   17: aload_0
/*     */     //   18: invokestatic parseLong : (Ljava/lang/String;)J
/*     */     //   21: lstore #5
/*     */     //   23: lload #5
/*     */     //   25: ldc2_w 2147483647
/*     */     //   28: lcmp
/*     */     //   29: iload #4
/*     */     //   31: ifeq -> 58
/*     */     //   34: ifle -> 54
/*     */     //   37: goto -> 50
/*     */     //   40: ldc2_w 6422579600644642942
/*     */     //   43: lload_1
/*     */     //   44: <illegal opcode> w : (Ljava/lang/Exception;JJ)Ljava/lang/Exception;
/*     */     //   49: athrow
/*     */     //   50: ldc_w 2147483647
/*     */     //   53: ireturn
/*     */     //   54: lload #5
/*     */     //   56: lconst_0
/*     */     //   57: lcmp
/*     */     //   58: iload #4
/*     */     //   60: ifeq -> 84
/*     */     //   63: ifge -> 81
/*     */     //   66: goto -> 79
/*     */     //   69: ldc2_w 6422579600644642942
/*     */     //   72: lload_1
/*     */     //   73: <illegal opcode> w : (Ljava/lang/Exception;JJ)Ljava/lang/Exception;
/*     */     //   78: athrow
/*     */     //   79: iconst_0
/*     */     //   80: ireturn
/*     */     //   81: lload #5
/*     */     //   83: l2i
/*     */     //   84: ireturn
/*     */     //   85: astore #5
/*     */     //   87: iload_3
/*     */     //   88: ireturn
/*     */     // Line number table:
/*     */     //   Java source line number -> byte code offset
/*     */     //   #44	-> 17
/*     */     //   #15	-> 23
/*     */     //   #73	-> 50
/*     */     //   #39	-> 54
/*     */     //   #148	-> 79
/*     */     //   #20	-> 81
/*     */     //   #115	-> 85
/*     */     //   #129	-> 87
/*     */     // Exception table:
/*     */     //   from	to	target	type
/*     */     //   17	53	85	java/lang/NumberFormatException
/*     */     //   23	37	40	java/lang/NumberFormatException
/*     */     //   54	80	85	java/lang/NumberFormatException
/*     */     //   58	66	69	java/lang/NumberFormatException
/*     */     //   81	84	85	java/lang/NumberFormatException
/*     */   } public static boolean a(long paramLong, H paramH) {
/*     */     paramLong = a ^ paramLong;
/*     */     long l = paramLong ^ 0x2ABC0F5A2D4BL;
/*     */     return a(paramH.a(), l);
/*     */   } public static int b(String paramString, int paramInt1, char paramChar1, char paramChar2, int paramInt2) {
/*     */     // Byte code:
/*     */     //   0: iload_2
/*     */     //   1: i2l
/*     */     //   2: bipush #48
/*     */     //   4: lshl
/*     */     //   5: iload_3
/*     */     //   6: i2l
/*     */     //   7: bipush #48
/*     */     //   9: lshl
/*     */     //   10: bipush #16
/*     */     //   12: lushr
/*     */     //   13: lor
/*     */     //   14: iload #4
/*     */     //   16: i2l
/*     */     //   17: bipush #32
/*     */     //   19: lshl
/*     */     //   20: bipush #32
/*     */     //   22: lushr
/*     */     //   23: lor
/*     */     //   24: getstatic me/konsolas/aac/gz.a : J
/*     */     //   27: lxor
/*     */     //   28: lstore #5
/*     */     //   30: ldc2_w 5581635786196898394
/*     */     //   33: lload #5
/*     */     //   35: <illegal opcode> w : (JJ)Z
/*     */     //   40: istore #7
/*     */     //   42: iload_1
/*     */     //   43: aload_0
/*     */     //   44: invokevirtual length : ()I
/*     */     //   47: if_icmpge -> 174
/*     */     //   50: aload_0
/*     */     //   51: iload_1
/*     */     //   52: invokevirtual charAt : (I)C
/*     */     //   55: istore #8
/*     */     //   57: iload #7
/*     */     //   59: iload #4
/*     */     //   61: ifge -> 171
/*     */     //   64: ifne -> 169
/*     */     //   67: iload #8
/*     */     //   69: iload #7
/*     */     //   71: ifne -> 175
/*     */     //   74: goto -> 88
/*     */     //   77: ldc2_w 5544197839034650031
/*     */     //   80: lload #5
/*     */     //   82: <illegal opcode> w : (Ljava/lang/Exception;JJ)Ljava/lang/Exception;
/*     */     //   87: athrow
/*     */     //   88: bipush #32
/*     */     //   90: if_icmpeq -> 152
/*     */     //   93: goto -> 107
/*     */     //   96: ldc2_w 5544197839034650031
/*     */     //   99: lload #5
/*     */     //   101: <illegal opcode> w : (Ljava/lang/Exception;JJ)Ljava/lang/Exception;
/*     */     //   106: athrow
/*     */     //   107: iload #4
/*     */     //   109: ifgt -> 155
/*     */     //   112: iload #8
/*     */     //   114: bipush #9
/*     */     //   116: if_icmpeq -> 152
/*     */     //   119: goto -> 133
/*     */     //   122: ldc2_w 5544197839034650031
/*     */     //   125: lload #5
/*     */     //   127: <illegal opcode> w : (Ljava/lang/Exception;JJ)Ljava/lang/Exception;
/*     */     //   132: athrow
/*     */     //   133: iload #7
/*     */     //   135: ifeq -> 174
/*     */     //   138: goto -> 152
/*     */     //   141: ldc2_w 5544197839034650031
/*     */     //   144: lload #5
/*     */     //   146: <illegal opcode> w : (Ljava/lang/Exception;JJ)Ljava/lang/Exception;
/*     */     //   151: athrow
/*     */     //   152: iinc #1, 1
/*     */     //   155: goto -> 169
/*     */     //   158: ldc2_w 5544197839034650031
/*     */     //   161: lload #5
/*     */     //   163: <illegal opcode> w : (Ljava/lang/Exception;JJ)Ljava/lang/Exception;
/*     */     //   168: athrow
/*     */     //   169: iload #7
/*     */     //   171: ifeq -> 42
/*     */     //   174: iload_1
/*     */     //   175: ireturn
/*     */     // Line number table:
/*     */     //   Java source line number -> byte code offset
/*     */     //   #58	-> 42
/*     */     //   #10	-> 50
/*     */     //   #143	-> 57
/*     */     //   #114	-> 133
/*     */     //   #56	-> 152
/*     */     //   #45	-> 174
/*     */     // Exception table:
/*     */     //   from	to	target	type
/*     */     //   57	74	77	java/lang/NumberFormatException
/*     */     //   67	93	96	java/lang/NumberFormatException
/*     */     //   88	119	122	java/lang/NumberFormatException
/*     */     //   107	138	141	java/lang/NumberFormatException
/*     */     //   133	155	158	java/lang/NumberFormatException
/*     */   } public static int a(String paramString1, int paramInt, long paramLong, String paramString2) {
/*     */     // Byte code:
/*     */     //   0: getstatic me/konsolas/aac/gz.a : J
/*     */     //   3: lload_2
/*     */     //   4: lxor
/*     */     //   5: lstore_2
/*     */     //   6: ldc2_w -3065676706647487909
/*     */     //   9: lload_2
/*     */     //   10: <illegal opcode> w : (JJ)Z
/*     */     //   15: istore #5
/*     */     //   17: iload_1
/*     */     //   18: aload_0
/*     */     //   19: invokevirtual length : ()I
/*     */     //   22: if_icmpge -> 108
/*     */     //   25: aload #4
/*     */     //   27: aload_0
/*     */     //   28: iload_1
/*     */     //   29: invokevirtual charAt : (I)C
/*     */     //   32: invokevirtual indexOf : (I)I
/*     */     //   35: iload #5
/*     */     //   37: lload_2
/*     */     //   38: lconst_0
/*     */     //   39: lcmp
/*     */     //   40: iflt -> 47
/*     */     //   43: ifne -> 109
/*     */     //   46: iconst_m1
/*     */     //   47: if_icmpeq -> 81
/*     */     //   50: goto -> 63
/*     */     //   53: ldc2_w -3102555847768697426
/*     */     //   56: lload_2
/*     */     //   57: <illegal opcode> w : (Ljava/lang/Exception;JJ)Ljava/lang/Exception;
/*     */     //   62: athrow
/*     */     //   63: iload #5
/*     */     //   65: ifeq -> 108
/*     */     //   68: goto -> 81
/*     */     //   71: ldc2_w -3102555847768697426
/*     */     //   74: lload_2
/*     */     //   75: <illegal opcode> w : (Ljava/lang/Exception;JJ)Ljava/lang/Exception;
/*     */     //   80: athrow
/*     */     //   81: iinc #1, 1
/*     */     //   84: iload #5
/*     */     //   86: ifeq -> 17
/*     */     //   89: lload_2
/*     */     //   90: lconst_0
/*     */     //   91: lcmp
/*     */     //   92: iflt -> 25
/*     */     //   95: goto -> 108
/*     */     //   98: ldc2_w -3102555847768697426
/*     */     //   101: lload_2
/*     */     //   102: <illegal opcode> w : (Ljava/lang/Exception;JJ)Ljava/lang/Exception;
/*     */     //   107: athrow
/*     */     //   108: iload_1
/*     */     //   109: ireturn
/*     */     // Line number table:
/*     */     //   Java source line number -> byte code offset
/*     */     //   #62	-> 17
/*     */     //   #159	-> 25
/*     */     //   #21	-> 63
/*     */     //   #75	-> 81
/*     */     //   #38	-> 108
/*     */     // Exception table:
/*     */     //   from	to	target	type
/*     */     //   25	50	53	java/lang/NumberFormatException
/*     */     //   46	68	71	java/lang/NumberFormatException
/*     */     //   63	89	98	java/lang/NumberFormatException
/*     */   } private static int a(long paramLong, fw paramfw, byte paramByte) {
/*     */     // Byte code:
/*     */     //   0: getstatic me/konsolas/aac/gz.a : J
/*     */     //   3: lload_0
/*     */     //   4: lxor
/*     */     //   5: lstore_0
/*     */     //   6: lload_0
/*     */     //   7: dup2
/*     */     //   8: ldc2_w 98850230539829
/*     */     //   11: lxor
/*     */     //   12: dup2
/*     */     //   13: bipush #32
/*     */     //   15: lushr
/*     */     //   16: l2i
/*     */     //   17: istore #4
/*     */     //   19: dup2
/*     */     //   20: bipush #32
/*     */     //   22: lshl
/*     */     //   23: bipush #48
/*     */     //   25: lushr
/*     */     //   26: l2i
/*     */     //   27: istore #5
/*     */     //   29: dup2
/*     */     //   30: bipush #48
/*     */     //   32: lshl
/*     */     //   33: bipush #48
/*     */     //   35: lushr
/*     */     //   36: l2i
/*     */     //   37: istore #6
/*     */     //   39: pop2
/*     */     //   40: dup2
/*     */     //   41: ldc2_w 39130972231655
/*     */     //   44: lxor
/*     */     //   45: lstore #7
/*     */     //   47: dup2
/*     */     //   48: ldc2_w 2512473710934
/*     */     //   51: lxor
/*     */     //   52: lstore #9
/*     */     //   54: pop2
/*     */     //   55: ldc2_w -7056371493914541763
/*     */     //   58: lload_0
/*     */     //   59: <illegal opcode> w : (JJ)Z
/*     */     //   64: iconst_0
/*     */     //   65: istore #12
/*     */     //   67: istore #11
/*     */     //   69: aload_2
/*     */     //   70: iload #4
/*     */     //   72: iload #5
/*     */     //   74: i2c
/*     */     //   75: iload #6
/*     */     //   77: invokevirtual a : (ICI)Z
/*     */     //   80: ifne -> 170
/*     */     //   83: aload_2
/*     */     //   84: lconst_0
/*     */     //   85: lload #9
/*     */     //   87: invokevirtual a : (JJ)B
/*     */     //   90: iload #11
/*     */     //   92: lload_0
/*     */     //   93: lconst_0
/*     */     //   94: lcmp
/*     */     //   95: iflt -> 103
/*     */     //   98: ifne -> 172
/*     */     //   101: iload #11
/*     */     //   103: ifne -> 172
/*     */     //   106: goto -> 119
/*     */     //   109: ldc2_w -6946875951234818360
/*     */     //   112: lload_0
/*     */     //   113: <illegal opcode> w : (Ljava/lang/Exception;JJ)Ljava/lang/Exception;
/*     */     //   118: athrow
/*     */     //   119: iload_3
/*     */     //   120: if_icmpne -> 170
/*     */     //   123: goto -> 136
/*     */     //   126: ldc2_w -6946875951234818360
/*     */     //   129: lload_0
/*     */     //   130: <illegal opcode> w : (Ljava/lang/Exception;JJ)Ljava/lang/Exception;
/*     */     //   135: athrow
/*     */     //   136: iinc #12, 1
/*     */     //   139: aload_2
/*     */     //   140: lload #7
/*     */     //   142: invokevirtual a : (J)B
/*     */     //   145: pop
/*     */     //   146: iload #11
/*     */     //   148: ifeq -> 69
/*     */     //   151: lload_0
/*     */     //   152: lconst_0
/*     */     //   153: lcmp
/*     */     //   154: iflt -> 170
/*     */     //   157: goto -> 170
/*     */     //   160: ldc2_w -6946875951234818360
/*     */     //   163: lload_0
/*     */     //   164: <illegal opcode> w : (Ljava/lang/Exception;JJ)Ljava/lang/Exception;
/*     */     //   169: athrow
/*     */     //   170: iload #12
/*     */     //   172: ireturn
/*     */     // Line number table:
/*     */     //   Java source line number -> byte code offset
/*     */     //   #79	-> 64
/*     */     //   #93	-> 69
/*     */     //   #144	-> 136
/*     */     //   #54	-> 139
/*     */     //   #130	-> 170
/*     */     // Exception table:
/*     */     //   from	to	target	type
/*     */     //   83	106	109	java/lang/NumberFormatException
/*     */     //   101	123	126	java/lang/NumberFormatException
/*     */     //   119	151	160	java/lang/NumberFormatException
/*     */   } private static long a(String paramString, long paramLong) {
/*     */     // Byte code:
/*     */     //   0: getstatic me/konsolas/aac/gz.a : J
/*     */     //   3: lload_1
/*     */     //   4: lxor
/*     */     //   5: lstore_1
/*     */     //   6: ldc2_w 8946913690634347270
/*     */     //   9: lload_1
/*     */     //   10: <illegal opcode> w : (JJ)Z
/*     */     //   15: istore_3
/*     */     //   16: aload_0
/*     */     //   17: iload_3
/*     */     //   18: ifne -> 52
/*     */     //   21: ifnonnull -> 51
/*     */     //   24: goto -> 37
/*     */     //   27: ldc2_w 9055846298920369395
/*     */     //   30: lload_1
/*     */     //   31: <illegal opcode> w : (Ljava/lang/Exception;JJ)Ljava/lang/Exception;
/*     */     //   36: athrow
/*     */     //   37: ldc2_w -1
/*     */     //   40: lreturn
/*     */     //   41: ldc2_w 9055846298920369395
/*     */     //   44: lload_1
/*     */     //   45: <illegal opcode> w : (Ljava/lang/Exception;JJ)Ljava/lang/Exception;
/*     */     //   50: athrow
/*     */     //   51: aload_0
/*     */     //   52: invokestatic parseLong : (Ljava/lang/String;)J
/*     */     //   55: lreturn
/*     */     //   56: astore #4
/*     */     //   58: ldc2_w -1
/*     */     //   61: lreturn
/*     */     // Line number table:
/*     */     //   Java source line number -> byte code offset
/*     */     //   #84	-> 16
/*     */     //   #70	-> 51
/*     */     //   #80	-> 56
/*     */     //   #124	-> 58
/*     */     // Exception table:
/*     */     //   from	to	target	type
/*     */     //   16	24	27	java/lang/NumberFormatException
/*     */     //   21	41	41	java/lang/NumberFormatException
/*     */     //   51	55	56	java/lang/NumberFormatException
/*     */   }
/*     */   private static String b(long paramLong, fw paramfw) {
/*     */     // Byte code:
/*     */     //   0: getstatic me/konsolas/aac/gz.a : J
/*     */     //   3: lload_0
/*     */     //   4: lxor
/*     */     //   5: lstore_0
/*     */     //   6: lload_0
/*     */     //   7: dup2
/*     */     //   8: ldc2_w 95142635424739
/*     */     //   11: lxor
/*     */     //   12: lstore_3
/*     */     //   13: dup2
/*     */     //   14: ldc2_w 113386257357393
/*     */     //   17: lxor
/*     */     //   18: lstore #5
/*     */     //   20: dup2
/*     */     //   21: ldc2_w 140230233179944
/*     */     //   24: lxor
/*     */     //   25: lstore #7
/*     */     //   27: dup2
/*     */     //   28: ldc2_w 103732009578905
/*     */     //   31: lxor
/*     */     //   32: lstore #9
/*     */     //   34: dup2
/*     */     //   35: ldc2_w 29641209047912
/*     */     //   38: lxor
/*     */     //   39: lstore #11
/*     */     //   41: pop2
/*     */     //   42: ldc2_w -3559291805421488383
/*     */     //   45: lload_0
/*     */     //   46: <illegal opcode> w : (JJ)Z
/*     */     //   51: istore #13
/*     */     //   53: aload_2
/*     */     //   54: iload #13
/*     */     //   56: ifeq -> 107
/*     */     //   59: lload #7
/*     */     //   61: invokevirtual a : (J)B
/*     */     //   64: bipush #34
/*     */     //   66: if_icmpeq -> 100
/*     */     //   69: goto -> 82
/*     */     //   72: ldc2_w -3505804645358465529
/*     */     //   75: lload_0
/*     */     //   76: <illegal opcode> w : (Ljava/lang/Exception;JJ)Ljava/lang/Exception;
/*     */     //   81: athrow
/*     */     //   82: new java/lang/IllegalArgumentException
/*     */     //   85: dup
/*     */     //   86: invokespecial <init> : ()V
/*     */     //   89: athrow
/*     */     //   90: ldc2_w -3505804645358465529
/*     */     //   93: lload_0
/*     */     //   94: <illegal opcode> w : (Ljava/lang/Exception;JJ)Ljava/lang/Exception;
/*     */     //   99: athrow
/*     */     //   100: new me/konsolas/aac/fw
/*     */     //   103: dup
/*     */     //   104: invokespecial <init> : ()V
/*     */     //   107: astore #14
/*     */     //   109: aload_2
/*     */     //   110: lload #5
/*     */     //   112: getstatic me/konsolas/aac/gz.c : Lme/konsolas/aac/gZ;
/*     */     //   115: invokevirtual b : (JLme/konsolas/aac/gZ;)J
/*     */     //   118: lstore #15
/*     */     //   120: lload #15
/*     */     //   122: ldc2_w -1
/*     */     //   125: lcmp
/*     */     //   126: ifne -> 165
/*     */     //   129: aconst_null
/*     */     //   130: lload_0
/*     */     //   131: lconst_0
/*     */     //   132: lcmp
/*     */     //   133: iflt -> 267
/*     */     //   136: iload #13
/*     */     //   138: ifeq -> 267
/*     */     //   141: goto -> 154
/*     */     //   144: ldc2_w -3505804645358465529
/*     */     //   147: lload_0
/*     */     //   148: <illegal opcode> w : (Ljava/lang/Exception;JJ)Ljava/lang/Exception;
/*     */     //   153: athrow
/*     */     //   154: areturn
/*     */     //   155: ldc2_w -3505804645358465529
/*     */     //   158: lload_0
/*     */     //   159: <illegal opcode> w : (Ljava/lang/Exception;JJ)Ljava/lang/Exception;
/*     */     //   164: athrow
/*     */     //   165: aload_2
/*     */     //   166: lload #15
/*     */     //   168: lload #9
/*     */     //   170: invokevirtual a : (JJ)B
/*     */     //   173: iload #13
/*     */     //   175: lload_0
/*     */     //   176: lconst_0
/*     */     //   177: lcmp
/*     */     //   178: ifle -> 247
/*     */     //   181: ifeq -> 245
/*     */     //   184: bipush #34
/*     */     //   186: if_icmpne -> 236
/*     */     //   189: goto -> 202
/*     */     //   192: ldc2_w -3505804645358465529
/*     */     //   195: lload_0
/*     */     //   196: <illegal opcode> w : (Ljava/lang/Exception;JJ)Ljava/lang/Exception;
/*     */     //   201: athrow
/*     */     //   202: aload #14
/*     */     //   204: lload_3
/*     */     //   205: aload_2
/*     */     //   206: lload #15
/*     */     //   208: invokevirtual b : (JLme/konsolas/aac/fw;J)V
/*     */     //   211: aload_2
/*     */     //   212: lload #7
/*     */     //   214: invokevirtual a : (J)B
/*     */     //   217: pop
/*     */     //   218: aload #14
/*     */     //   220: lload #11
/*     */     //   222: invokevirtual c : (J)Ljava/lang/String;
/*     */     //   225: areturn
/*     */     //   226: ldc2_w -3505804645358465529
/*     */     //   229: lload_0
/*     */     //   230: <illegal opcode> w : (Ljava/lang/Exception;JJ)Ljava/lang/Exception;
/*     */     //   235: athrow
/*     */     //   236: aload_2
/*     */     //   237: invokevirtual f : ()J
/*     */     //   240: lload #15
/*     */     //   242: lconst_1
/*     */     //   243: ladd
/*     */     //   244: lcmp
/*     */     //   245: iload #13
/*     */     //   247: ifeq -> 283
/*     */     //   250: ifne -> 268
/*     */     //   253: goto -> 266
/*     */     //   256: ldc2_w -3505804645358465529
/*     */     //   259: lload_0
/*     */     //   260: <illegal opcode> w : (Ljava/lang/Exception;JJ)Ljava/lang/Exception;
/*     */     //   265: athrow
/*     */     //   266: aconst_null
/*     */     //   267: areturn
/*     */     //   268: aload #14
/*     */     //   270: lload_3
/*     */     //   271: aload_2
/*     */     //   272: lload #15
/*     */     //   274: invokevirtual b : (JLme/konsolas/aac/fw;J)V
/*     */     //   277: aload_2
/*     */     //   278: lload #7
/*     */     //   280: invokevirtual a : (J)B
/*     */     //   283: pop
/*     */     //   284: aload #14
/*     */     //   286: lload_3
/*     */     //   287: aload_2
/*     */     //   288: lconst_1
/*     */     //   289: invokevirtual b : (JLme/konsolas/aac/fw;J)V
/*     */     //   292: goto -> 109
/*     */     // Line number table:
/*     */     //   Java source line number -> byte code offset
/*     */     //   #99	-> 53
/*     */     //   #7	-> 100
/*     */     //   #122	-> 109
/*     */     //   #137	-> 120
/*     */     //   #67	-> 165
/*     */     //   #142	-> 202
/*     */     //   #1	-> 211
/*     */     //   #113	-> 218
/*     */     //   #18	-> 236
/*     */     //   #2	-> 268
/*     */     //   #98	-> 277
/*     */     //   #118	-> 284
/*     */     //   #72	-> 292
/*     */     // Exception table:
/*     */     //   from	to	target	type
/*     */     //   53	69	72	java/lang/NumberFormatException
/*     */     //   59	90	90	java/lang/NumberFormatException
/*     */     //   120	141	144	java/lang/NumberFormatException
/*     */     //   129	155	155	java/lang/NumberFormatException
/*     */     //   165	189	192	java/lang/NumberFormatException
/*     */     //   184	226	226	java/lang/NumberFormatException
/*     */     //   245	253	256	java/lang/NumberFormatException
/*     */   }
/*     */   private static String a(fw paramfw, char paramChar, short paramShort, int paramInt) {
/*     */     // Byte code:
/*     */     //   0: iload_1
/*     */     //   1: i2l
/*     */     //   2: bipush #48
/*     */     //   4: lshl
/*     */     //   5: iload_2
/*     */     //   6: i2l
/*     */     //   7: bipush #48
/*     */     //   9: lshl
/*     */     //   10: bipush #16
/*     */     //   12: lushr
/*     */     //   13: lor
/*     */     //   14: iload_3
/*     */     //   15: i2l
/*     */     //   16: bipush #32
/*     */     //   18: lshl
/*     */     //   19: bipush #32
/*     */     //   21: lushr
/*     */     //   22: lor
/*     */     //   23: getstatic me/konsolas/aac/gz.a : J
/*     */     //   26: lxor
/*     */     //   27: lstore #4
/*     */     //   29: lload #4
/*     */     //   31: dup2
/*     */     //   32: ldc2_w 34916288521339
/*     */     //   35: lxor
/*     */     //   36: lstore #6
/*     */     //   38: dup2
/*     */     //   39: ldc2_w 121230853524916
/*     */     //   42: lxor
/*     */     //   43: lstore #8
/*     */     //   45: pop2
/*     */     //   46: ldc2_w 3528463940762316760
/*     */     //   49: lload #4
/*     */     //   51: <illegal opcode> w : (JJ)Z
/*     */     //   56: istore #10
/*     */     //   58: aload_0
/*     */     //   59: lload #6
/*     */     //   61: getstatic me/konsolas/aac/gz.d : Lme/konsolas/aac/gZ;
/*     */     //   64: invokevirtual b : (JLme/konsolas/aac/gZ;)J
/*     */     //   67: lstore #11
/*     */     //   69: lload #11
/*     */     //   71: ldc2_w -1
/*     */     //   74: lcmp
/*     */     //   75: iload #10
/*     */     //   77: ifne -> 107
/*     */     //   80: ifne -> 103
/*     */     //   83: goto -> 97
/*     */     //   86: ldc2_w 3563079449971814445
/*     */     //   89: lload #4
/*     */     //   91: <illegal opcode> w : (Ljava/lang/Exception;JJ)Ljava/lang/Exception;
/*     */     //   96: athrow
/*     */     //   97: aload_0
/*     */     //   98: invokevirtual f : ()J
/*     */     //   101: lstore #11
/*     */     //   103: lload #11
/*     */     //   105: lconst_0
/*     */     //   106: lcmp
/*     */     //   107: ifeq -> 132
/*     */     //   110: aload_0
/*     */     //   111: lload #11
/*     */     //   113: lload #8
/*     */     //   115: invokevirtual b : (JJ)Ljava/lang/String;
/*     */     //   118: goto -> 133
/*     */     //   121: ldc2_w 3563079449971814445
/*     */     //   124: lload #4
/*     */     //   126: <illegal opcode> w : (Ljava/lang/Exception;JJ)Ljava/lang/Exception;
/*     */     //   131: athrow
/*     */     //   132: aconst_null
/*     */     //   133: areturn
/*     */     //   134: astore #11
/*     */     //   136: new java/lang/AssertionError
/*     */     //   139: dup
/*     */     //   140: invokespecial <init> : ()V
/*     */     //   143: athrow
/*     */     // Line number table:
/*     */     //   Java source line number -> byte code offset
/*     */     //   #100	-> 58
/*     */     //   #83	-> 69
/*     */     //   #57	-> 103
/*     */     //   #71	-> 110
/*     */     //   #150	-> 132
/*     */     //   #91	-> 133
/*     */     //   #26	-> 134
/*     */     //   #134	-> 136
/*     */     // Exception table:
/*     */     //   from	to	target	type
/*     */     //   58	133	134	java/io/EOFException
/*     */     //   69	83	86	java/io/EOFException
/*     */     //   107	121	121	java/io/EOFException
/*     */   }
/*     */   public static long a(J paramJ, long paramLong) {
/*     */     // Byte code:
/*     */     //   0: getstatic me/konsolas/aac/gz.a : J
/*     */     //   3: lload_1
/*     */     //   4: lxor
/*     */     //   5: lstore_1
/*     */     //   6: lload_1
/*     */     //   7: dup2
/*     */     //   8: ldc2_w 25323096788404
/*     */     //   11: lxor
/*     */     //   12: lstore_3
/*     */     //   13: dup2
/*     */     //   14: ldc2_w 126570349298047
/*     */     //   17: lxor
/*     */     //   18: dup2
/*     */     //   19: bipush #32
/*     */     //   21: lushr
/*     */     //   22: l2i
/*     */     //   23: istore #5
/*     */     //   25: dup2
/*     */     //   26: bipush #32
/*     */     //   28: lshl
/*     */     //   29: bipush #48
/*     */     //   31: lushr
/*     */     //   32: l2i
/*     */     //   33: istore #6
/*     */     //   35: dup2
/*     */     //   36: bipush #48
/*     */     //   38: lshl
/*     */     //   39: bipush #48
/*     */     //   41: lushr
/*     */     //   42: l2i
/*     */     //   43: istore #7
/*     */     //   45: pop2
/*     */     //   46: pop2
/*     */     //   47: aload_0
/*     */     //   48: iload #5
/*     */     //   50: iload #6
/*     */     //   52: i2c
/*     */     //   53: iload #7
/*     */     //   55: i2c
/*     */     //   56: sipush #25421
/*     */     //   59: ldc2_w 4630238084716534133
/*     */     //   62: lload_1
/*     */     //   63: lxor
/*     */     //   64: <illegal opcode> l : (IJ)Ljava/lang/String;
/*     */     //   69: invokevirtual a : (ICCLjava/lang/String;)Ljava/lang/String;
/*     */     //   72: lload_3
/*     */     //   73: invokestatic a : (Ljava/lang/String;J)J
/*     */     //   76: lreturn
/*     */     // Line number table:
/*     */     //   Java source line number -> byte code offset
/*     */     //   #101	-> 47
/*     */   }
/*     */   public static boolean b(H paramH, long paramLong) {
/*     */     // Byte code:
/*     */     //   0: getstatic me/konsolas/aac/gz.a : J
/*     */     //   3: lload_1
/*     */     //   4: lxor
/*     */     //   5: lstore_1
/*     */     //   6: lload_1
/*     */     //   7: dup2
/*     */     //   8: ldc2_w 89362434062651
/*     */     //   11: lxor
/*     */     //   12: lstore_3
/*     */     //   13: dup2
/*     */     //   14: ldc2_w 51011097035475
/*     */     //   17: lxor
/*     */     //   18: lstore #5
/*     */     //   20: pop2
/*     */     //   21: ldc2_w 4617817123783326094
/*     */     //   24: lload_1
/*     */     //   25: <illegal opcode> w : (JJ)Z
/*     */     //   30: istore #7
/*     */     //   32: aload_0
/*     */     //   33: invokevirtual a : ()Lme/konsolas/aac/s;
/*     */     //   36: invokevirtual a : ()Ljava/lang/String;
/*     */     //   39: sipush #18914
/*     */     //   42: ldc2_w 8501501898893387018
/*     */     //   45: lload_1
/*     */     //   46: lxor
/*     */     //   47: <illegal opcode> l : (IJ)Ljava/lang/String;
/*     */     //   52: invokevirtual equals : (Ljava/lang/Object;)Z
/*     */     //   55: iload #7
/*     */     //   57: ifeq -> 92
/*     */     //   60: ifeq -> 88
/*     */     //   63: goto -> 76
/*     */     //   66: ldc2_w 4744529009743233160
/*     */     //   69: lload_1
/*     */     //   70: <illegal opcode> w : (Ljava/lang/Exception;JJ)Ljava/lang/Exception;
/*     */     //   75: athrow
/*     */     //   76: iconst_0
/*     */     //   77: ireturn
/*     */     //   78: ldc2_w 4744529009743233160
/*     */     //   81: lload_1
/*     */     //   82: <illegal opcode> w : (Ljava/lang/Exception;JJ)Ljava/lang/Exception;
/*     */     //   87: athrow
/*     */     //   88: aload_0
/*     */     //   89: invokevirtual a : ()I
/*     */     //   92: istore #8
/*     */     //   94: iload #8
/*     */     //   96: bipush #100
/*     */     //   98: lload_1
/*     */     //   99: lconst_0
/*     */     //   100: lcmp
/*     */     //   101: ifle -> 200
/*     */     //   104: iload #7
/*     */     //   106: ifeq -> 200
/*     */     //   109: if_icmplt -> 164
/*     */     //   112: goto -> 125
/*     */     //   115: ldc2_w 4744529009743233160
/*     */     //   118: lload_1
/*     */     //   119: <illegal opcode> w : (Ljava/lang/Exception;JJ)Ljava/lang/Exception;
/*     */     //   124: athrow
/*     */     //   125: iload #8
/*     */     //   127: iload #7
/*     */     //   129: ifeq -> 275
/*     */     //   132: goto -> 145
/*     */     //   135: ldc2_w 4744529009743233160
/*     */     //   138: lload_1
/*     */     //   139: <illegal opcode> w : (Ljava/lang/Exception;JJ)Ljava/lang/Exception;
/*     */     //   144: athrow
/*     */     //   145: sipush #200
/*     */     //   148: if_icmplt -> 266
/*     */     //   151: goto -> 164
/*     */     //   154: ldc2_w 4744529009743233160
/*     */     //   157: lload_1
/*     */     //   158: <illegal opcode> w : (Ljava/lang/Exception;JJ)Ljava/lang/Exception;
/*     */     //   163: athrow
/*     */     //   164: iload #8
/*     */     //   166: iload #7
/*     */     //   168: ifeq -> 275
/*     */     //   171: goto -> 184
/*     */     //   174: ldc2_w 4744529009743233160
/*     */     //   177: lload_1
/*     */     //   178: <illegal opcode> w : (Ljava/lang/Exception;JJ)Ljava/lang/Exception;
/*     */     //   183: athrow
/*     */     //   184: sipush #204
/*     */     //   187: goto -> 200
/*     */     //   190: ldc2_w 4744529009743233160
/*     */     //   193: lload_1
/*     */     //   194: <illegal opcode> w : (Ljava/lang/Exception;JJ)Ljava/lang/Exception;
/*     */     //   199: athrow
/*     */     //   200: lload_1
/*     */     //   201: lconst_0
/*     */     //   202: lcmp
/*     */     //   203: ifle -> 213
/*     */     //   206: if_icmpeq -> 266
/*     */     //   209: iload #8
/*     */     //   211: iload #7
/*     */     //   213: lload_1
/*     */     //   214: lconst_0
/*     */     //   215: lcmp
/*     */     //   216: ifle -> 277
/*     */     //   219: ifeq -> 275
/*     */     //   222: goto -> 235
/*     */     //   225: ldc2_w 4744529009743233160
/*     */     //   228: lload_1
/*     */     //   229: <illegal opcode> w : (Ljava/lang/Exception;JJ)Ljava/lang/Exception;
/*     */     //   234: athrow
/*     */     //   235: sipush #304
/*     */     //   238: if_icmpeq -> 266
/*     */     //   241: goto -> 254
/*     */     //   244: ldc2_w 4744529009743233160
/*     */     //   247: lload_1
/*     */     //   248: <illegal opcode> w : (Ljava/lang/Exception;JJ)Ljava/lang/Exception;
/*     */     //   253: athrow
/*     */     //   254: iconst_1
/*     */     //   255: ireturn
/*     */     //   256: ldc2_w 4744529009743233160
/*     */     //   259: lload_1
/*     */     //   260: <illegal opcode> w : (Ljava/lang/Exception;JJ)Ljava/lang/Exception;
/*     */     //   265: athrow
/*     */     //   266: aload_0
/*     */     //   267: lload_3
/*     */     //   268: invokestatic a : (Lme/konsolas/aac/H;J)J
/*     */     //   271: ldc2_w -1
/*     */     //   274: lcmp
/*     */     //   275: iload #7
/*     */     //   277: ifeq -> 366
/*     */     //   280: ifne -> 365
/*     */     //   283: goto -> 296
/*     */     //   286: ldc2_w 4744529009743233160
/*     */     //   289: lload_1
/*     */     //   290: <illegal opcode> w : (Ljava/lang/Exception;JJ)Ljava/lang/Exception;
/*     */     //   295: athrow
/*     */     //   296: sipush #20359
/*     */     //   299: ldc2_w 2682971188924670830
/*     */     //   302: lload_1
/*     */     //   303: lxor
/*     */     //   304: <illegal opcode> l : (IJ)Ljava/lang/String;
/*     */     //   309: aload_0
/*     */     //   310: lload #5
/*     */     //   312: sipush #849
/*     */     //   315: ldc2_w 1136889870507945917
/*     */     //   318: lload_1
/*     */     //   319: lxor
/*     */     //   320: <illegal opcode> l : (IJ)Ljava/lang/String;
/*     */     //   325: invokevirtual a : (JLjava/lang/String;)Ljava/lang/String;
/*     */     //   328: invokevirtual equalsIgnoreCase : (Ljava/lang/String;)Z
/*     */     //   331: iload #7
/*     */     //   333: ifeq -> 368
/*     */     //   336: goto -> 349
/*     */     //   339: ldc2_w 4744529009743233160
/*     */     //   342: lload_1
/*     */     //   343: <illegal opcode> w : (Ljava/lang/Exception;JJ)Ljava/lang/Exception;
/*     */     //   348: athrow
/*     */     //   349: ifeq -> 367
/*     */     //   352: goto -> 365
/*     */     //   355: ldc2_w 4744529009743233160
/*     */     //   358: lload_1
/*     */     //   359: <illegal opcode> w : (Ljava/lang/Exception;JJ)Ljava/lang/Exception;
/*     */     //   364: athrow
/*     */     //   365: iconst_1
/*     */     //   366: ireturn
/*     */     //   367: iconst_0
/*     */     //   368: ireturn
/*     */     // Line number table:
/*     */     //   Java source line number -> byte code offset
/*     */     //   #102	-> 32
/*     */     //   #154	-> 76
/*     */     //   #121	-> 88
/*     */     //   #117	-> 94
/*     */     //   #49	-> 254
/*     */     //   #135	-> 266
/*     */     //   #32	-> 325
/*     */     //   #59	-> 365
/*     */     //   #120	-> 367
/*     */     // Exception table:
/*     */     //   from	to	target	type
/*     */     //   32	63	66	java/lang/NumberFormatException
/*     */     //   60	78	78	java/lang/NumberFormatException
/*     */     //   94	112	115	java/lang/NumberFormatException
/*     */     //   109	132	135	java/lang/NumberFormatException
/*     */     //   125	151	154	java/lang/NumberFormatException
/*     */     //   145	171	174	java/lang/NumberFormatException
/*     */     //   164	187	190	java/lang/NumberFormatException
/*     */     //   200	222	225	java/lang/NumberFormatException
/*     */     //   209	241	244	java/lang/NumberFormatException
/*     */     //   235	256	256	java/lang/NumberFormatException
/*     */     //   275	283	286	java/lang/NumberFormatException
/*     */     //   280	336	339	java/lang/NumberFormatException
/*     */     //   296	352	355	java/lang/NumberFormatException
/*     */   }
/*     */   public static void a(iD paramiD, l6 paraml6, long paramLong, J paramJ) {
/*     */     // Byte code:
/*     */     //   0: getstatic me/konsolas/aac/gz.a : J
/*     */     //   3: lload_2
/*     */     //   4: lxor
/*     */     //   5: lstore_2
/*     */     //   6: lload_2
/*     */     //   7: dup2
/*     */     //   8: ldc2_w 110850138763044
/*     */     //   11: lxor
/*     */     //   12: dup2
/*     */     //   13: bipush #32
/*     */     //   15: lushr
/*     */     //   16: l2i
/*     */     //   17: istore #5
/*     */     //   19: dup2
/*     */     //   20: bipush #32
/*     */     //   22: lshl
/*     */     //   23: bipush #48
/*     */     //   25: lushr
/*     */     //   26: l2i
/*     */     //   27: istore #6
/*     */     //   29: dup2
/*     */     //   30: bipush #48
/*     */     //   32: lshl
/*     */     //   33: bipush #48
/*     */     //   35: lushr
/*     */     //   36: l2i
/*     */     //   37: istore #7
/*     */     //   39: pop2
/*     */     //   40: pop2
/*     */     //   41: ldc2_w 7501577882425227061
/*     */     //   44: lload_2
/*     */     //   45: <illegal opcode> w : (JJ)Z
/*     */     //   50: istore #8
/*     */     //   52: aload_0
/*     */     //   53: getstatic me/konsolas/aac/iD.a : Lme/konsolas/aac/iD;
/*     */     //   56: if_acmpne -> 70
/*     */     //   59: return
/*     */     //   60: ldc2_w 7611070129360087232
/*     */     //   63: lload_2
/*     */     //   64: <illegal opcode> w : (Ljava/lang/Exception;JJ)Ljava/lang/Exception;
/*     */     //   69: athrow
/*     */     //   70: iload #5
/*     */     //   72: aload_1
/*     */     //   73: iload #6
/*     */     //   75: i2c
/*     */     //   76: aload #4
/*     */     //   78: iload #7
/*     */     //   80: invokestatic a : (ILme/konsolas/aac/l6;CLme/konsolas/aac/J;I)Ljava/util/List;
/*     */     //   83: astore #9
/*     */     //   85: iload #8
/*     */     //   87: lload_2
/*     */     //   88: lconst_0
/*     */     //   89: lcmp
/*     */     //   90: ifle -> 103
/*     */     //   93: ifne -> 139
/*     */     //   96: aload #9
/*     */     //   98: invokeinterface isEmpty : ()Z
/*     */     //   103: ifeq -> 130
/*     */     //   106: goto -> 119
/*     */     //   109: ldc2_w 7611070129360087232
/*     */     //   112: lload_2
/*     */     //   113: <illegal opcode> w : (Ljava/lang/Exception;JJ)Ljava/lang/Exception;
/*     */     //   118: athrow
/*     */     //   119: return
/*     */     //   120: ldc2_w 7611070129360087232
/*     */     //   123: lload_2
/*     */     //   124: <illegal opcode> w : (Ljava/lang/Exception;JJ)Ljava/lang/Exception;
/*     */     //   129: athrow
/*     */     //   130: aload_0
/*     */     //   131: aload_1
/*     */     //   132: aload #9
/*     */     //   134: invokeinterface a : (Lme/konsolas/aac/l6;Ljava/util/List;)V
/*     */     //   139: return
/*     */     // Line number table:
/*     */     //   Java source line number -> byte code offset
/*     */     //   #107	-> 52
/*     */     //   #55	-> 70
/*     */     //   #29	-> 85
/*     */     //   #60	-> 130
/*     */     //   #110	-> 139
/*     */     // Exception table:
/*     */     //   from	to	target	type
/*     */     //   52	60	60	java/lang/NumberFormatException
/*     */     //   85	106	109	java/lang/NumberFormatException
/*     */     //   96	120	120	java/lang/NumberFormatException
/*     */   }
/*     */   public static J a(H paramH, long paramLong) {
/* 116 */     paramLong = a ^ paramLong; long l = paramLong ^ 0x70C0E16396D8L; J j1 = paramH.b().a().a();
/*     */ 
/*     */ 
/*     */ 
/*     */ 
/*     */ 
/*     */ 
/*     */ 
/*     */ 
/*     */ 
/*     */ 
/*     */ 
/*     */ 
/*     */ 
/*     */ 
/*     */ 
/*     */ 
/*     */ 
/*     */ 
/*     */ 
/*     */ 
/*     */     
/* 138 */     J j2 = paramH.a();
/*     */     return a(j1, j2, l);
/*     */   }
/*     */   
/*     */   public static long a(H paramH, long paramLong) {
/*     */     paramLong = a ^ paramLong;
/*     */     long l = paramLong ^ 0x8F413B2FEEL;
/*     */     return a(paramH.a(), l);
/*     */   }
/*     */   
/*     */   private static void a(List paramList, long paramLong, fw paramfw) {
/*     */     // Byte code:
/*     */     //   0: getstatic me/konsolas/aac/gz.a : J
/*     */     //   3: lload_1
/*     */     //   4: lxor
/*     */     //   5: lstore_1
/*     */     //   6: lload_1
/*     */     //   7: dup2
/*     */     //   8: ldc2_w 99074450810939
/*     */     //   11: lxor
/*     */     //   12: dup2
/*     */     //   13: bipush #48
/*     */     //   15: lushr
/*     */     //   16: l2i
/*     */     //   17: istore #4
/*     */     //   19: dup2
/*     */     //   20: bipush #16
/*     */     //   22: lshl
/*     */     //   23: bipush #48
/*     */     //   25: lushr
/*     */     //   26: l2i
/*     */     //   27: istore #5
/*     */     //   29: dup2
/*     */     //   30: bipush #32
/*     */     //   32: lshl
/*     */     //   33: bipush #32
/*     */     //   35: lushr
/*     */     //   36: l2i
/*     */     //   37: istore #6
/*     */     //   39: pop2
/*     */     //   40: dup2
/*     */     //   41: ldc2_w 77201177081841
/*     */     //   44: lxor
/*     */     //   45: dup2
/*     */     //   46: bipush #32
/*     */     //   48: lushr
/*     */     //   49: l2i
/*     */     //   50: istore #7
/*     */     //   52: dup2
/*     */     //   53: bipush #32
/*     */     //   55: lshl
/*     */     //   56: bipush #48
/*     */     //   58: lushr
/*     */     //   59: l2i
/*     */     //   60: istore #8
/*     */     //   62: dup2
/*     */     //   63: bipush #48
/*     */     //   65: lshl
/*     */     //   66: bipush #48
/*     */     //   68: lushr
/*     */     //   69: l2i
/*     */     //   70: istore #9
/*     */     //   72: pop2
/*     */     //   73: dup2
/*     */     //   74: ldc2_w 63882478375123
/*     */     //   77: lxor
/*     */     //   78: lstore #10
/*     */     //   80: dup2
/*     */     //   81: ldc2_w 109249663510464
/*     */     //   84: lxor
/*     */     //   85: lstore #12
/*     */     //   87: dup2
/*     */     //   88: ldc2_w 38232961881617
/*     */     //   91: lxor
/*     */     //   92: lstore #14
/*     */     //   94: dup2
/*     */     //   95: ldc2_w 139478133098206
/*     */     //   98: lxor
/*     */     //   99: lstore #16
/*     */     //   101: dup2
/*     */     //   102: ldc2_w 32544766984338
/*     */     //   105: lxor
/*     */     //   106: lstore #18
/*     */     //   108: pop2
/*     */     //   109: ldc2_w 9192296794920781322
/*     */     //   112: lload_1
/*     */     //   113: <illegal opcode> w : (JJ)Z
/*     */     //   118: aconst_null
/*     */     //   119: astore #21
/*     */     //   121: istore #20
/*     */     //   123: aload #21
/*     */     //   125: ifnonnull -> 203
/*     */     //   128: lload #12
/*     */     //   130: aload_3
/*     */     //   131: invokestatic a : (JLme/konsolas/aac/fw;)Z
/*     */     //   134: pop
/*     */     //   135: aload_3
/*     */     //   136: iload #4
/*     */     //   138: i2c
/*     */     //   139: iload #5
/*     */     //   141: i2s
/*     */     //   142: iload #6
/*     */     //   144: invokestatic a : (Lme/konsolas/aac/fw;CSI)Ljava/lang/String;
/*     */     //   147: astore #21
/*     */     //   149: aload #21
/*     */     //   151: lload_1
/*     */     //   152: lconst_0
/*     */     //   153: lcmp
/*     */     //   154: ifle -> 205
/*     */     //   157: iload #20
/*     */     //   159: lload_1
/*     */     //   160: lconst_0
/*     */     //   161: lcmp
/*     */     //   162: ifle -> 170
/*     */     //   165: ifeq -> 205
/*     */     //   168: iload #20
/*     */     //   170: ifeq -> 205
/*     */     //   173: goto -> 186
/*     */     //   176: ldc2_w 9102798429757456140
/*     */     //   179: lload_1
/*     */     //   180: <illegal opcode> w : (Ljava/lang/Exception;JJ)Ljava/lang/Exception;
/*     */     //   185: athrow
/*     */     //   186: ifnonnull -> 203
/*     */     //   189: goto -> 202
/*     */     //   192: ldc2_w 9102798429757456140
/*     */     //   195: lload_1
/*     */     //   196: <illegal opcode> w : (Ljava/lang/Exception;JJ)Ljava/lang/Exception;
/*     */     //   201: athrow
/*     */     //   202: return
/*     */     //   203: aload #21
/*     */     //   205: astore #22
/*     */     //   207: lload #12
/*     */     //   209: aload_3
/*     */     //   210: invokestatic a : (JLme/konsolas/aac/fw;)Z
/*     */     //   213: istore #23
/*     */     //   215: aload_3
/*     */     //   216: iload #20
/*     */     //   218: lload_1
/*     */     //   219: lconst_0
/*     */     //   220: lcmp
/*     */     //   221: iflt -> 328
/*     */     //   224: ifeq -> 326
/*     */     //   227: iload #4
/*     */     //   229: i2c
/*     */     //   230: iload #5
/*     */     //   232: i2s
/*     */     //   233: iload #6
/*     */     //   235: invokestatic a : (Lme/konsolas/aac/fw;CSI)Ljava/lang/String;
/*     */     //   238: astore #21
/*     */     //   240: lload_1
/*     */     //   241: lconst_0
/*     */     //   242: lcmp
/*     */     //   243: ifle -> 251
/*     */     //   246: aload #21
/*     */     //   248: ifnonnull -> 325
/*     */     //   251: lload_1
/*     */     //   252: lconst_0
/*     */     //   253: lcmp
/*     */     //   254: iflt -> 324
/*     */     //   257: aload_3
/*     */     //   258: iload #7
/*     */     //   260: iload #8
/*     */     //   262: i2c
/*     */     //   263: iload #9
/*     */     //   265: invokevirtual a : (ICI)Z
/*     */     //   268: iload #20
/*     */     //   270: ifeq -> 323
/*     */     //   273: goto -> 286
/*     */     //   276: ldc2_w 9102798429757456140
/*     */     //   279: lload_1
/*     */     //   280: <illegal opcode> w : (Ljava/lang/Exception;JJ)Ljava/lang/Exception;
/*     */     //   285: athrow
/*     */     //   286: ifne -> 303
/*     */     //   289: goto -> 302
/*     */     //   292: ldc2_w 9102798429757456140
/*     */     //   295: lload_1
/*     */     //   296: <illegal opcode> w : (Ljava/lang/Exception;JJ)Ljava/lang/Exception;
/*     */     //   301: athrow
/*     */     //   302: return
/*     */     //   303: aload_0
/*     */     //   304: new me/konsolas/aac/d0
/*     */     //   307: dup
/*     */     //   308: aload #22
/*     */     //   310: invokestatic emptyMap : ()Ljava/util/Map;
/*     */     //   313: lload #10
/*     */     //   315: invokespecial <init> : (Ljava/lang/String;Ljava/util/Map;J)V
/*     */     //   318: invokeinterface add : (Ljava/lang/Object;)Z
/*     */     //   323: pop
/*     */     //   324: return
/*     */     //   325: aload_3
/*     */     //   326: bipush #61
/*     */     //   328: lload #16
/*     */     //   330: dup2_x2
/*     */     //   331: pop2
/*     */     //   332: invokestatic a : (JLme/konsolas/aac/fw;B)I
/*     */     //   335: istore #24
/*     */     //   337: lload #12
/*     */     //   339: aload_3
/*     */     //   340: invokestatic a : (JLme/konsolas/aac/fw;)Z
/*     */     //   343: istore #25
/*     */     //   345: iload #23
/*     */     //   347: iload #20
/*     */     //   349: lload_1
/*     */     //   350: lconst_0
/*     */     //   351: lcmp
/*     */     //   352: iflt -> 378
/*     */     //   355: ifeq -> 376
/*     */     //   358: ifne -> 514
/*     */     //   361: goto -> 374
/*     */     //   364: ldc2_w 9102798429757456140
/*     */     //   367: lload_1
/*     */     //   368: <illegal opcode> w : (Ljava/lang/Exception;JJ)Ljava/lang/Exception;
/*     */     //   373: athrow
/*     */     //   374: iload #25
/*     */     //   376: iload #20
/*     */     //   378: ifeq -> 507
/*     */     //   381: ifne -> 448
/*     */     //   384: goto -> 397
/*     */     //   387: ldc2_w 9102798429757456140
/*     */     //   390: lload_1
/*     */     //   391: <illegal opcode> w : (Ljava/lang/Exception;JJ)Ljava/lang/Exception;
/*     */     //   396: athrow
/*     */     //   397: lload_1
/*     */     //   398: lconst_0
/*     */     //   399: lcmp
/*     */     //   400: iflt -> 508
/*     */     //   403: aload_3
/*     */     //   404: iload #7
/*     */     //   406: iload #8
/*     */     //   408: i2c
/*     */     //   409: iload #9
/*     */     //   411: invokevirtual a : (ICI)Z
/*     */     //   414: iload #20
/*     */     //   416: ifeq -> 507
/*     */     //   419: goto -> 432
/*     */     //   422: ldc2_w 9102798429757456140
/*     */     //   425: lload_1
/*     */     //   426: <illegal opcode> w : (Ljava/lang/Exception;JJ)Ljava/lang/Exception;
/*     */     //   431: athrow
/*     */     //   432: ifeq -> 514
/*     */     //   435: goto -> 448
/*     */     //   438: ldc2_w 9102798429757456140
/*     */     //   441: lload_1
/*     */     //   442: <illegal opcode> w : (Ljava/lang/Exception;JJ)Ljava/lang/Exception;
/*     */     //   447: athrow
/*     */     //   448: aload_0
/*     */     //   449: new me/konsolas/aac/d0
/*     */     //   452: dup
/*     */     //   453: aload #22
/*     */     //   455: aconst_null
/*     */     //   456: new java/lang/StringBuilder
/*     */     //   459: dup
/*     */     //   460: invokespecial <init> : ()V
/*     */     //   463: aload #21
/*     */     //   465: invokevirtual append : (Ljava/lang/String;)Ljava/lang/StringBuilder;
/*     */     //   468: bipush #61
/*     */     //   470: iload #24
/*     */     //   472: invokestatic a : (CI)Ljava/lang/String;
/*     */     //   475: invokevirtual append : (Ljava/lang/String;)Ljava/lang/StringBuilder;
/*     */     //   478: invokevirtual toString : ()Ljava/lang/String;
/*     */     //   481: invokestatic singletonMap : (Ljava/lang/Object;Ljava/lang/Object;)Ljava/util/Map;
/*     */     //   484: lload #10
/*     */     //   486: invokespecial <init> : (Ljava/lang/String;Ljava/util/Map;J)V
/*     */     //   489: invokeinterface add : (Ljava/lang/Object;)Z
/*     */     //   494: goto -> 507
/*     */     //   497: ldc2_w 9102798429757456140
/*     */     //   500: lload_1
/*     */     //   501: <illegal opcode> w : (Ljava/lang/Exception;JJ)Ljava/lang/Exception;
/*     */     //   506: athrow
/*     */     //   507: pop
/*     */     //   508: aconst_null
/*     */     //   509: astore #21
/*     */     //   511: goto -> 123
/*     */     //   514: new java/util/LinkedHashMap
/*     */     //   517: dup
/*     */     //   518: invokespecial <init> : ()V
/*     */     //   521: astore #26
/*     */     //   523: iload #24
/*     */     //   525: lload #16
/*     */     //   527: aload_3
/*     */     //   528: bipush #61
/*     */     //   530: invokestatic a : (JLme/konsolas/aac/fw;B)I
/*     */     //   533: iadd
/*     */     //   534: istore #24
/*     */     //   536: aload #21
/*     */     //   538: ifnonnull -> 628
/*     */     //   541: aload_3
/*     */     //   542: iload #4
/*     */     //   544: i2c
/*     */     //   545: iload #5
/*     */     //   547: i2s
/*     */     //   548: iload #6
/*     */     //   550: invokestatic a : (Lme/konsolas/aac/fw;CSI)Ljava/lang/String;
/*     */     //   553: astore #21
/*     */     //   555: lload #12
/*     */     //   557: aload_3
/*     */     //   558: invokestatic a : (JLme/konsolas/aac/fw;)Z
/*     */     //   561: iload #20
/*     */     //   563: lload_1
/*     */     //   564: lconst_0
/*     */     //   565: lcmp
/*     */     //   566: ifle -> 632
/*     */     //   569: lload_1
/*     */     //   570: lconst_0
/*     */     //   571: lcmp
/*     */     //   572: iflt -> 632
/*     */     //   575: ifeq -> 630
/*     */     //   578: iload #20
/*     */     //   580: ifeq -> 626
/*     */     //   583: goto -> 596
/*     */     //   586: ldc2_w 9102798429757456140
/*     */     //   589: lload_1
/*     */     //   590: <illegal opcode> w : (Ljava/lang/Exception;JJ)Ljava/lang/Exception;
/*     */     //   595: athrow
/*     */     //   596: ifeq -> 618
/*     */     //   599: goto -> 612
/*     */     //   602: ldc2_w 9102798429757456140
/*     */     //   605: lload_1
/*     */     //   606: <illegal opcode> w : (Ljava/lang/Exception;JJ)Ljava/lang/Exception;
/*     */     //   611: athrow
/*     */     //   612: lload_1
/*     */     //   613: lconst_0
/*     */     //   614: lcmp
/*     */     //   615: ifge -> 981
/*     */     //   618: lload #16
/*     */     //   620: aload_3
/*     */     //   621: bipush #61
/*     */     //   623: invokestatic a : (JLme/konsolas/aac/fw;B)I
/*     */     //   626: istore #24
/*     */     //   628: iload #24
/*     */     //   630: iload #20
/*     */     //   632: lload_1
/*     */     //   633: lconst_0
/*     */     //   634: lcmp
/*     */     //   635: ifle -> 667
/*     */     //   638: ifeq -> 665
/*     */     //   641: ifne -> 663
/*     */     //   644: goto -> 657
/*     */     //   647: ldc2_w 9102798429757456140
/*     */     //   650: lload_1
/*     */     //   651: <illegal opcode> w : (Ljava/lang/Exception;JJ)Ljava/lang/Exception;
/*     */     //   656: athrow
/*     */     //   657: lload_1
/*     */     //   658: lconst_0
/*     */     //   659: lcmp
/*     */     //   660: ifgt -> 981
/*     */     //   663: iload #24
/*     */     //   665: iload #20
/*     */     //   667: lload_1
/*     */     //   668: lconst_0
/*     */     //   669: lcmp
/*     */     //   670: iflt -> 718
/*     */     //   673: ifeq -> 710
/*     */     //   676: iconst_1
/*     */     //   677: if_icmple -> 704
/*     */     //   680: goto -> 693
/*     */     //   683: ldc2_w 9102798429757456140
/*     */     //   686: lload_1
/*     */     //   687: <illegal opcode> w : (Ljava/lang/Exception;JJ)Ljava/lang/Exception;
/*     */     //   692: athrow
/*     */     //   693: return
/*     */     //   694: ldc2_w 9102798429757456140
/*     */     //   697: lload_1
/*     */     //   698: <illegal opcode> w : (Ljava/lang/Exception;JJ)Ljava/lang/Exception;
/*     */     //   703: athrow
/*     */     //   704: lload #12
/*     */     //   706: aload_3
/*     */     //   707: invokestatic a : (JLme/konsolas/aac/fw;)Z
/*     */     //   710: lload_1
/*     */     //   711: lconst_0
/*     */     //   712: lcmp
/*     */     //   713: ifle -> 773
/*     */     //   716: iload #20
/*     */     //   718: ifeq -> 773
/*     */     //   721: ifeq -> 738
/*     */     //   724: goto -> 737
/*     */     //   727: ldc2_w 9102798429757456140
/*     */     //   730: lload_1
/*     */     //   731: <illegal opcode> w : (Ljava/lang/Exception;JJ)Ljava/lang/Exception;
/*     */     //   736: athrow
/*     */     //   737: return
/*     */     //   738: aload_3
/*     */     //   739: iload #20
/*     */     //   741: lload_1
/*     */     //   742: lconst_0
/*     */     //   743: lcmp
/*     */     //   744: ifle -> 752
/*     */     //   747: ifeq -> 845
/*     */     //   750: iload #7
/*     */     //   752: iload #8
/*     */     //   754: i2c
/*     */     //   755: iload #9
/*     */     //   757: invokevirtual a : (ICI)Z
/*     */     //   760: goto -> 773
/*     */     //   763: ldc2_w 9102798429757456140
/*     */     //   766: lload_1
/*     */     //   767: <illegal opcode> w : (Ljava/lang/Exception;JJ)Ljava/lang/Exception;
/*     */     //   772: athrow
/*     */     //   773: ifne -> 844
/*     */     //   776: aload_3
/*     */     //   777: iload #20
/*     */     //   779: lload_1
/*     */     //   780: lconst_0
/*     */     //   781: lcmp
/*     */     //   782: ifle -> 848
/*     */     //   785: ifeq -> 845
/*     */     //   788: goto -> 801
/*     */     //   791: ldc2_w 9102798429757456140
/*     */     //   794: lload_1
/*     */     //   795: <illegal opcode> w : (Ljava/lang/Exception;JJ)Ljava/lang/Exception;
/*     */     //   800: athrow
/*     */     //   801: lconst_0
/*     */     //   802: lload #18
/*     */     //   804: invokevirtual a : (JJ)B
/*     */     //   807: bipush #34
/*     */     //   809: if_icmpne -> 844
/*     */     //   812: goto -> 825
/*     */     //   815: ldc2_w 9102798429757456140
/*     */     //   818: lload_1
/*     */     //   819: <illegal opcode> w : (Ljava/lang/Exception;JJ)Ljava/lang/Exception;
/*     */     //   824: athrow
/*     */     //   825: lload #14
/*     */     //   827: aload_3
/*     */     //   828: invokestatic b : (JLme/konsolas/aac/fw;)Ljava/lang/String;
/*     */     //   831: goto -> 856
/*     */     //   834: ldc2_w 9102798429757456140
/*     */     //   837: lload_1
/*     */     //   838: <illegal opcode> w : (Ljava/lang/Exception;JJ)Ljava/lang/Exception;
/*     */     //   843: athrow
/*     */     //   844: aload_3
/*     */     //   845: iload #4
/*     */     //   847: i2c
/*     */     //   848: iload #5
/*     */     //   850: i2s
/*     */     //   851: iload #6
/*     */     //   853: invokestatic a : (Lme/konsolas/aac/fw;CSI)Ljava/lang/String;
/*     */     //   856: astore #27
/*     */     //   858: aload #27
/*     */     //   860: iload #20
/*     */     //   862: ifeq -> 896
/*     */     //   865: ifnonnull -> 882
/*     */     //   868: goto -> 881
/*     */     //   871: ldc2_w 9102798429757456140
/*     */     //   874: lload_1
/*     */     //   875: <illegal opcode> w : (Ljava/lang/Exception;JJ)Ljava/lang/Exception;
/*     */     //   880: athrow
/*     */     //   881: return
/*     */     //   882: aload #26
/*     */     //   884: aload #21
/*     */     //   886: aload #27
/*     */     //   888: invokeinterface put : (Ljava/lang/Object;Ljava/lang/Object;)Ljava/lang/Object;
/*     */     //   893: checkcast java/lang/String
/*     */     //   896: astore #28
/*     */     //   898: aconst_null
/*     */     //   899: astore #21
/*     */     //   901: lload_1
/*     */     //   902: lconst_0
/*     */     //   903: lcmp
/*     */     //   904: ifle -> 923
/*     */     //   907: aload #28
/*     */     //   909: ifnull -> 923
/*     */     //   912: return
/*     */     //   913: ldc2_w 9102798429757456140
/*     */     //   916: lload_1
/*     */     //   917: <illegal opcode> w : (Ljava/lang/Exception;JJ)Ljava/lang/Exception;
/*     */     //   922: athrow
/*     */     //   923: lload #12
/*     */     //   925: aload_3
/*     */     //   926: invokestatic a : (JLme/konsolas/aac/fw;)Z
/*     */     //   929: iload #20
/*     */     //   931: ifeq -> 974
/*     */     //   934: ifne -> 978
/*     */     //   937: goto -> 950
/*     */     //   940: ldc2_w 9102798429757456140
/*     */     //   943: lload_1
/*     */     //   944: <illegal opcode> w : (Ljava/lang/Exception;JJ)Ljava/lang/Exception;
/*     */     //   949: athrow
/*     */     //   950: aload_3
/*     */     //   951: iload #7
/*     */     //   953: iload #8
/*     */     //   955: i2c
/*     */     //   956: iload #9
/*     */     //   958: invokevirtual a : (ICI)Z
/*     */     //   961: goto -> 974
/*     */     //   964: ldc2_w 9102798429757456140
/*     */     //   967: lload_1
/*     */     //   968: <illegal opcode> w : (Ljava/lang/Exception;JJ)Ljava/lang/Exception;
/*     */     //   973: athrow
/*     */     //   974: ifne -> 978
/*     */     //   977: return
/*     */     //   978: goto -> 536
/*     */     //   981: aload_0
/*     */     //   982: new me/konsolas/aac/d0
/*     */     //   985: dup
/*     */     //   986: aload #22
/*     */     //   988: aload #26
/*     */     //   990: lload #10
/*     */     //   992: invokespecial <init> : (Ljava/lang/String;Ljava/util/Map;J)V
/*     */     //   995: invokeinterface add : (Ljava/lang/Object;)Z
/*     */     //   1000: pop
/*     */     //   1001: goto -> 123
/*     */     // Line number table:
/*     */     //   Java source line number -> byte code offset
/*     */     //   #156	-> 118
/*     */     //   #109	-> 123
/*     */     //   #132	-> 128
/*     */     //   #86	-> 135
/*     */     //   #136	-> 149
/*     */     //   #141	-> 203
/*     */     //   #66	-> 207
/*     */     //   #87	-> 215
/*     */     //   #14	-> 240
/*     */     //   #77	-> 251
/*     */     //   #103	-> 303
/*     */     //   #155	-> 324
/*     */     //   #53	-> 325
/*     */     //   #36	-> 337
/*     */     //   #78	-> 345
/*     */     //   #61	-> 448
/*     */     //   #82	-> 472
/*     */     //   #89	-> 481
/*     */     //   #31	-> 508
/*     */     //   #105	-> 511
/*     */     //   #153	-> 514
/*     */     //   #125	-> 523
/*     */     //   #97	-> 536
/*     */     //   #50	-> 541
/*     */     //   #111	-> 555
/*     */     //   #152	-> 618
/*     */     //   #68	-> 628
/*     */     //   #146	-> 663
/*     */     //   #92	-> 704
/*     */     //   #140	-> 738
/*     */     //   #35	-> 825
/*     */     //   #106	-> 844
/*     */     //   #6	-> 858
/*     */     //   #96	-> 882
/*     */     //   #95	-> 898
/*     */     //   #42	-> 901
/*     */     //   #25	-> 923
/*     */     //   #145	-> 978
/*     */     //   #64	-> 981
/*     */     //   #104	-> 1001
/*     */     // Exception table:
/*     */     //   from	to	target	type
/*     */     //   149	173	176	java/lang/NumberFormatException
/*     */     //   168	189	192	java/lang/NumberFormatException
/*     */     //   240	273	276	java/lang/NumberFormatException
/*     */     //   251	289	292	java/lang/NumberFormatException
/*     */     //   345	361	364	java/lang/NumberFormatException
/*     */     //   376	384	387	java/lang/NumberFormatException
/*     */     //   381	419	422	java/lang/NumberFormatException
/*     */     //   397	435	438	java/lang/NumberFormatException
/*     */     //   432	494	497	java/lang/NumberFormatException
/*     */     //   555	583	586	java/lang/NumberFormatException
/*     */     //   578	599	602	java/lang/NumberFormatException
/*     */     //   630	644	647	java/lang/NumberFormatException
/*     */     //   665	680	683	java/lang/NumberFormatException
/*     */     //   676	694	694	java/lang/NumberFormatException
/*     */     //   710	724	727	java/lang/NumberFormatException
/*     */     //   738	760	763	java/lang/NumberFormatException
/*     */     //   773	788	791	java/lang/NumberFormatException
/*     */     //   776	812	815	java/lang/NumberFormatException
/*     */     //   801	834	834	java/lang/NumberFormatException
/*     */     //   858	868	871	java/lang/NumberFormatException
/*     */     //   901	913	913	java/lang/NumberFormatException
/*     */     //   923	937	940	java/lang/NumberFormatException
/*     */     //   934	961	964	java/lang/NumberFormatException
/*     */   }
/*     */   
/*     */   static {
/*     */     // Byte code:
/*     */     //   0: ldc2_w -2816058572808659638
/*     */     //   3: ldc2_w -5833997027506835070
/*     */     //   6: invokestatic lookup : ()Ljava/lang/invoke/MethodHandles$Lookup;
/*     */     //   9: invokevirtual lookupClass : ()Ljava/lang/Class;
/*     */     //   12: invokestatic a : (JJLjava/lang/Object;)Lme/konsolas/aac/na;
/*     */     //   15: ldc2_w 121695313169525
/*     */     //   18: invokeinterface a : (J)J
/*     */     //   23: putstatic me/konsolas/aac/gz.a : J
/*     */     //   26: getstatic me/konsolas/aac/gz.a : J
/*     */     //   29: ldc2_w 32446744673612
/*     */     //   32: lxor
/*     */     //   33: lstore #9
/*     */     //   35: lload #9
/*     */     //   37: dup2
/*     */     //   38: ldc2_w 46957792865912
/*     */     //   41: lxor
/*     */     //   42: lstore #11
/*     */     //   44: pop2
/*     */     //   45: iconst_0
/*     */     //   46: new java/util/HashMap
/*     */     //   49: dup
/*     */     //   50: bipush #13
/*     */     //   52: invokespecial <init> : (I)V
/*     */     //   55: putstatic me/konsolas/aac/gz.g : Ljava/util/Map;
/*     */     //   58: ldc2_w -7283132161874930234
/*     */     //   61: lload #9
/*     */     //   63: <illegal opcode> w : (ZJJ)V
/*     */     //   68: ldc_w '??宿⸩?咔㊗ⷜ䩭ꊁ면⁴냴م೫㻳'
/*     */     //   71: invokevirtual toCharArray : ()[C
/*     */     //   74: dup
/*     */     //   75: dup
/*     */     //   76: bipush #11
/*     */     //   78: dup_x1
/*     */     //   79: caload
/*     */     //   80: sipush #18030
/*     */     //   83: ixor
/*     */     //   84: i2c
/*     */     //   85: castore
/*     */     //   86: sipush #8701
/*     */     //   89: iconst_3
/*     */     //   90: iconst_5
/*     */     //   91: invokestatic H : (Ljava/lang/Object;SBB)Ljava/lang/String;
/*     */     //   94: invokestatic getInstance : (Ljava/lang/String;)Ljavax/crypto/Cipher;
/*     */     //   97: dup
/*     */     //   98: astore_0
/*     */     //   99: iconst_2
/*     */     //   100: ldc_w '훰༵੄'
/*     */     //   103: invokevirtual toCharArray : ()[C
/*     */     //   106: dup
/*     */     //   107: dup
/*     */     //   108: iconst_0
/*     */     //   109: dup_x1
/*     */     //   110: caload
/*     */     //   111: sipush #24340
/*     */     //   114: ixor
/*     */     //   115: i2c
/*     */     //   116: castore
/*     */     //   117: sipush #31591
/*     */     //   120: iconst_5
/*     */     //   121: iconst_1
/*     */     //   122: invokestatic H : (Ljava/lang/Object;SBB)Ljava/lang/String;
/*     */     //   125: invokestatic getInstance : (Ljava/lang/String;)Ljavax/crypto/SecretKeyFactory;
/*     */     //   128: bipush #8
/*     */     //   130: newarray byte
/*     */     //   132: dup
/*     */     //   133: iconst_0
/*     */     //   134: lload #9
/*     */     //   136: bipush #56
/*     */     //   138: lushr
/*     */     //   139: l2i
/*     */     //   140: i2b
/*     */     //   141: bastore
/*     */     //   142: iconst_1
/*     */     //   143: istore_1
/*     */     //   144: iload_1
/*     */     //   145: bipush #8
/*     */     //   147: if_icmpge -> 171
/*     */     //   150: dup
/*     */     //   151: iload_1
/*     */     //   152: lload #9
/*     */     //   154: iload_1
/*     */     //   155: bipush #8
/*     */     //   157: imul
/*     */     //   158: lshl
/*     */     //   159: bipush #56
/*     */     //   161: lushr
/*     */     //   162: l2i
/*     */     //   163: i2b
/*     */     //   164: bastore
/*     */     //   165: iinc #1, 1
/*     */     //   168: goto -> 144
/*     */     //   171: new javax/crypto/spec/DESKeySpec
/*     */     //   174: dup_x1
/*     */     //   175: swap
/*     */     //   176: invokespecial <init> : ([B)V
/*     */     //   179: invokevirtual generateSecret : (Ljava/security/spec/KeySpec;)Ljavax/crypto/SecretKey;
/*     */     //   182: new javax/crypto/spec/IvParameterSpec
/*     */     //   185: dup
/*     */     //   186: bipush #8
/*     */     //   188: newarray byte
/*     */     //   190: invokespecial <init> : ([B)V
/*     */     //   193: invokevirtual init : (ILjava/security/Key;Ljava/security/spec/AlgorithmParameterSpec;)V
/*     */     //   196: bipush #7
/*     */     //   198: anewarray java/lang/String
/*     */     //   201: astore #7
/*     */     //   203: iconst_0
/*     */     //   204: istore #5
/*     */     //   206: ldc_w 'ᲃ誃宆呟磫䰇?䌆⻃贫輍䪍蔛炗鞈ꨯ鮊颒쭍ܱ䅈㨣પ摲屛鼉䂲邺䫃ջ쳯샬뀘ᅣ㸖⃼웂蒃놯뎷瓙䠷喚㪡뒺籸䑉⾡ﾘ鵍䚴룃㑯헍ი猫贀紼į쉾繥患ᕇ焵⎄ㅊ᭼힎諄瞇⛕訆碁꺻ꅐꋉ﫸膌摣㓓੹◊砠֣㔷祘ﱕ䳻䔧趖挺ᄏ츸ấሢⱼ塷硭⨭棚恐엎ᷖ'
/*     */     //   209: invokevirtual toCharArray : ()[C
/*     */     //   212: dup
/*     */     //   213: dup
/*     */     //   214: bipush #74
/*     */     //   216: dup_x1
/*     */     //   217: caload
/*     */     //   218: sipush #23486
/*     */     //   221: ixor
/*     */     //   222: i2c
/*     */     //   223: castore
/*     */     //   224: sipush #10422
/*     */     //   227: iconst_4
/*     */     //   228: iconst_1
/*     */     //   229: invokestatic H : (Ljava/lang/Object;SBB)Ljava/lang/String;
/*     */     //   232: dup
/*     */     //   233: astore #4
/*     */     //   235: invokevirtual length : ()I
/*     */     //   238: istore #6
/*     */     //   240: bipush #16
/*     */     //   242: istore_3
/*     */     //   243: iconst_m1
/*     */     //   244: istore_2
/*     */     //   245: iinc #2, 1
/*     */     //   248: aload #4
/*     */     //   250: iload_2
/*     */     //   251: dup
/*     */     //   252: iload_3
/*     */     //   253: iadd
/*     */     //   254: invokevirtual substring : (II)Ljava/lang/String;
/*     */     //   257: iconst_m1
/*     */     //   258: goto -> 392
/*     */     //   261: aload #7
/*     */     //   263: swap
/*     */     //   264: iload #5
/*     */     //   266: iinc #5, 1
/*     */     //   269: swap
/*     */     //   270: aastore
/*     */     //   271: iload_2
/*     */     //   272: iload_3
/*     */     //   273: iadd
/*     */     //   274: dup
/*     */     //   275: istore_2
/*     */     //   276: iload #6
/*     */     //   278: if_icmpge -> 291
/*     */     //   281: aload #4
/*     */     //   283: iload_2
/*     */     //   284: invokevirtual charAt : (I)C
/*     */     //   287: istore_3
/*     */     //   288: goto -> 245
/*     */     //   291: ldc_w 'ʴ⎖ཫ赜㮃齪ꔨѐ⢨餢囧墋ఠᆛ倦㩐븷皟⻀ㅵ蔉ຍᠮ粸闫᧥篠ꁺ熏犤뾚鼘섫읲ᆖ鮟?훗떇ǡ嵟'
/*     */     //   294: invokevirtual toCharArray : ()[C
/*     */     //   297: dup
/*     */     //   298: dup
/*     */     //   299: bipush #7
/*     */     //   301: dup_x1
/*     */     //   302: caload
/*     */     //   303: sipush #31632
/*     */     //   306: ixor
/*     */     //   307: i2c
/*     */     //   308: castore
/*     */     //   309: sipush #25522
/*     */     //   312: iconst_5
/*     */     //   313: iconst_4
/*     */     //   314: invokestatic H : (Ljava/lang/Object;SBB)Ljava/lang/String;
/*     */     //   317: dup
/*     */     //   318: astore #4
/*     */     //   320: invokevirtual length : ()I
/*     */     //   323: istore #6
/*     */     //   325: bipush #32
/*     */     //   327: istore_3
/*     */     //   328: iconst_m1
/*     */     //   329: istore_2
/*     */     //   330: iinc #2, 1
/*     */     //   333: aload #4
/*     */     //   335: iload_2
/*     */     //   336: dup
/*     */     //   337: iload_3
/*     */     //   338: iadd
/*     */     //   339: invokevirtual substring : (II)Ljava/lang/String;
/*     */     //   342: iconst_0
/*     */     //   343: goto -> 392
/*     */     //   346: aload #7
/*     */     //   348: swap
/*     */     //   349: iload #5
/*     */     //   351: iinc #5, 1
/*     */     //   354: swap
/*     */     //   355: aastore
/*     */     //   356: iload_2
/*     */     //   357: iload_3
/*     */     //   358: iadd
/*     */     //   359: dup
/*     */     //   360: istore_2
/*     */     //   361: iload #6
/*     */     //   363: if_icmpge -> 376
/*     */     //   366: aload #4
/*     */     //   368: iload_2
/*     */     //   369: invokevirtual charAt : (I)C
/*     */     //   372: istore_3
/*     */     //   373: goto -> 330
/*     */     //   376: aload #7
/*     */     //   378: putstatic me/konsolas/aac/gz.e : [Ljava/lang/String;
/*     */     //   381: bipush #7
/*     */     //   383: anewarray java/lang/String
/*     */     //   386: putstatic me/konsolas/aac/gz.f : [Ljava/lang/String;
/*     */     //   389: goto -> 456
/*     */     //   392: swap
/*     */     //   393: ldc_w 'ᗳꒃ䍾㺪⮋㪶橋邧㜩ғ⿕'
/*     */     //   396: invokevirtual toCharArray : ()[C
/*     */     //   399: dup
/*     */     //   400: dup
/*     */     //   401: bipush #9
/*     */     //   403: dup_x1
/*     */     //   404: caload
/*     */     //   405: sipush #26811
/*     */     //   408: ixor
/*     */     //   409: i2c
/*     */     //   410: castore
/*     */     //   411: sipush #23518
/*     */     //   414: iconst_3
/*     */     //   415: iconst_3
/*     */     //   416: invokestatic H : (Ljava/lang/Object;SBB)Ljava/lang/String;
/*     */     //   419: invokevirtual getBytes : (Ljava/lang/String;)[B
/*     */     //   422: aload_0
/*     */     //   423: swap
/*     */     //   424: invokevirtual doFinal : ([B)[B
/*     */     //   427: astore #8
/*     */     //   429: aload #8
/*     */     //   431: invokestatic a : ([B)Ljava/lang/String;
/*     */     //   434: invokevirtual intern : ()Ljava/lang/String;
/*     */     //   437: swap
/*     */     //   438: tableswitch default -> 261, 0 -> 346
/*     */     //   456: sipush #18353
/*     */     //   459: ldc2_w 1986403830095065131
/*     */     //   462: lload #9
/*     */     //   464: lxor
/*     */     //   465: <illegal opcode> l : (IJ)Ljava/lang/String;
/*     */     //   470: lload #11
/*     */     //   472: invokestatic a : (Ljava/lang/String;J)Lme/konsolas/aac/gZ;
/*     */     //   475: putstatic me/konsolas/aac/gz.c : Lme/konsolas/aac/gZ;
/*     */     //   478: sipush #24918
/*     */     //   481: ldc2_w 3270892198101292745
/*     */     //   484: lload #9
/*     */     //   486: lxor
/*     */     //   487: <illegal opcode> l : (IJ)Ljava/lang/String;
/*     */     //   492: lload #11
/*     */     //   494: invokestatic a : (Ljava/lang/String;J)Lme/konsolas/aac/gZ;
/*     */     //   497: putstatic me/konsolas/aac/gz.d : Lme/konsolas/aac/gZ;
/*     */     //   500: return
/*     */     // Line number table:
/*     */     //   Java source line number -> byte code offset
/*     */     //   #33	-> 456
/*     */     //   #34	-> 478
/*     */   }
/*     */   
/*     */   public static void b(boolean paramBoolean) {
/*     */     b = paramBoolean;
/*     */   }
/*     */   
/*     */   public static boolean b() {
/*     */     return b;
/*     */   }
/*     */   
/*     */   public static boolean c() {
/*     */     boolean bool = b();
/*     */     try {
/*     */       if (!bool)
/*     */         return true; 
/*     */     } catch (NumberFormatException numberFormatException) {
/*     */       throw a(null);
/*     */     } 
/*     */     return false;
/*     */   }
/*     */   
/*     */   private static Exception a(Exception paramException) {
/*     */     return paramException;
/*     */   }
/*     */   
/*     */   private static String a(byte[] paramArrayOfbyte) {
/*     */     byte b1 = 0;
/*     */     int i;
/*     */     char[] arrayOfChar = new char[i = paramArrayOfbyte.length];
/*     */     for (byte b2 = 0; b2 < i; b2++) {
/*     */       int j;
/*     */       if ((j = 0xFF & paramArrayOfbyte[b2]) < 192) {
/*     */         arrayOfChar[b1++] = (char)j;
/*     */       } else if (j < 224) {
/*     */         char c = (char)((char)(j & 0x1F) << 6);
/*     */         j = paramArrayOfbyte[++b2];
/*     */         c = (char)(c | (char)(j & 0x3F));
/*     */         arrayOfChar[b1++] = c;
/*     */       } else if (b2 < i - 2) {
/*     */         char c = (char)((char)(j & 0xF) << 12);
/*     */         j = paramArrayOfbyte[++b2];
/*     */         c = (char)(c | (char)(j & 0x3F) << 6);
/*     */         j = paramArrayOfbyte[++b2];
/*     */         c = (char)(c | (char)(j & 0x3F));
/*     */         arrayOfChar[b1++] = c;
/*     */       } 
/*     */     } 
/*     */     return new String(arrayOfChar, 0, b1);
/*     */   }
/*     */   
/*     */   private static String a(int paramInt, long paramLong) {
/*     */     int i = paramInt ^ (int)(paramLong & 0x7FFFL) ^ 0x6DCF;
/*     */     if (f[i] == null) {
/*     */       Object[] arrayOfObject;
/*     */       try {
/*     */         Long long_ = Long.valueOf(Thread.currentThread().getId());
/*     */         arrayOfObject = (Object[])g.get(long_);
/*     */         if (arrayOfObject == null) {
/*     */           arrayOfObject = new Object[3];
/*     */           "ϊ㦇?튖귰ₒ⧵ቨ숯♫剆᫅꩙⹇è쥽禈ଖ".toCharArray()[19] = (char)("ϊ㦇?튖귰ₒ⧵ቨ숯♫剆᫅꩙⹇è쥽禈ଖ".toCharArray()[19] ^ 0x5D11);
/*     */           arrayOfObject[0] = Cipher.getInstance(dP$dt.X("ϊ㦇?튖귰ₒ⧵ቨ숯♫剆᫅꩙⹇è쥽禈ଖ".toCharArray(), (short)26227, false, false));
/*     */           "ꪏ郪珼".toCharArray()[1] = (char)("ꪏ郪珼".toCharArray()[1] ^ 0x6B8A);
/*     */           arrayOfObject[1] = SecretKeyFactory.getInstance(dP$dt.X("ꪏ郪珼".toCharArray(), (short)21108, true, true));
/*     */           arrayOfObject[2] = new IvParameterSpec(new byte[8]);
/*     */           g.put(long_, arrayOfObject);
/*     */         } 
/*     */       } catch (Exception exception) {
/*     */         "ぼ릱왡뢆䣕즉ኢ꧵鸿鹍齠텒䱧ꭗ\032".toCharArray()[0] = (char)("ぼ릱왡뢆䣕즉ኢ꧵鸿鹍齠텒䱧ꭗ\032".toCharArray()[0] ^ 0x75CD);
/*     */         throw new RuntimeException(dP$dt.X("ぼ릱왡뢆䣕즉ኢ꧵鸿鹍齠텒䱧ꭗ\032".toCharArray(), (short)5325, true, false), exception);
/*     */       } 
/*     */       byte[] arrayOfByte1 = new byte[8];
/*     */       arrayOfByte1[0] = (byte)(int)(paramLong >>> 56L);
/*     */       for (byte b = 1; b < 8; b++)
/*     */         arrayOfByte1[b] = (byte)(int)(paramLong << b * 8 >>> 56L); 
/*     */       DESKeySpec dESKeySpec = new DESKeySpec(arrayOfByte1);
/*     */       SecretKey secretKey = ((SecretKeyFactory)arrayOfObject[1]).generateSecret(dESKeySpec);
/*     */       ((Cipher)arrayOfObject[0]).init(2, secretKey, (IvParameterSpec)arrayOfObject[2]);
/*     */       "䃝ⷛ看￱൒㯗뤲殤㫖襤婒".toCharArray()[4] = (char)("䃝ⷛ看￱൒㯗뤲殤㫖襤婒".toCharArray()[4] ^ 0x1408);
/*     */       byte[] arrayOfByte2 = e[i].getBytes(dP$dt.X("䃝ⷛ看￱൒㯗뤲殤㫖襤婒".toCharArray(), (short)21093, true, false));
/*     */       f[i] = a(((Cipher)arrayOfObject[0]).doFinal(arrayOfByte2));
/*     */     } 
/*     */     return f[i];
/*     */   }
/*     */   
/*     */   private static Object a(MethodHandles.Lookup paramLookup, MutableCallSite paramMutableCallSite, String paramString, Object[] paramArrayOfObject) {
/*     */     int i = ((Integer)paramArrayOfObject[0]).intValue();
/*     */     long l = ((Long)paramArrayOfObject[1]).longValue();
/*     */     String str = a(i, l);
/*     */     MethodHandle methodHandle = MethodHandles.constant(String.class, str);
/*     */     paramMutableCallSite.setTarget(MethodHandles.dropArguments(methodHandle, 0, new Class[] { int.class, long.class }));
/*     */     return str;
/*     */   }
/*     */   
/*     */   private static CallSite a(MethodHandles.Lookup paramLookup, String paramString, MethodType paramMethodType) {
/*     */     // Byte code:
/*     */     //   0: new java/lang/invoke/MutableCallSite
/*     */     //   3: dup
/*     */     //   4: aload_2
/*     */     //   5: invokespecial <init> : (Ljava/lang/invoke/MethodType;)V
/*     */     //   8: astore_3
/*     */     //   9: aload_3
/*     */     //   10: ldc_w
/*     */     //   13: ldc_w [Ljava/lang/Object;
/*     */     //   16: aload_2
/*     */     //   17: invokevirtual parameterCount : ()I
/*     */     //   20: invokevirtual asCollector : (Ljava/lang/Class;I)Ljava/lang/invoke/MethodHandle;
/*     */     //   23: iconst_0
/*     */     //   24: iconst_3
/*     */     //   25: anewarray java/lang/Object
/*     */     //   28: dup
/*     */     //   29: iconst_0
/*     */     //   30: aload_0
/*     */     //   31: aastore
/*     */     //   32: dup
/*     */     //   33: iconst_1
/*     */     //   34: aload_3
/*     */     //   35: aastore
/*     */     //   36: dup
/*     */     //   37: iconst_2
/*     */     //   38: aload_1
/*     */     //   39: aastore
/*     */     //   40: invokestatic insertArguments : (Ljava/lang/invoke/MethodHandle;I[Ljava/lang/Object;)Ljava/lang/invoke/MethodHandle;
/*     */     //   43: aload_2
/*     */     //   44: invokestatic explicitCastArguments : (Ljava/lang/invoke/MethodHandle;Ljava/lang/invoke/MethodType;)Ljava/lang/invoke/MethodHandle;
/*     */     //   47: invokevirtual setTarget : (Ljava/lang/invoke/MethodHandle;)V
/*     */     //   50: goto -> 171
/*     */     //   53: astore #4
/*     */     //   55: new java/lang/RuntimeException
/*     */     //   58: dup
/*     */     //   59: new java/lang/StringBuilder
/*     */     //   62: dup
/*     */     //   63: invokespecial <init> : ()V
/*     */     //   66: ldc_w '羞ڏⳡ?뤽㫇慔ᵀ꿙Ṱ쭙꣊時婗㩬﷼뚎冥'
/*     */     //   69: invokevirtual toCharArray : ()[C
/*     */     //   72: dup
/*     */     //   73: dup
/*     */     //   74: bipush #17
/*     */     //   76: dup_x1
/*     */     //   77: caload
/*     */     //   78: sipush #23671
/*     */     //   81: ixor
/*     */     //   82: i2c
/*     */     //   83: castore
/*     */     //   84: sipush #2087
/*     */     //   87: iconst_1
/*     */     //   88: iconst_1
/*     */     //   89: invokestatic G : (Ljava/lang/Object;SZB)Ljava/lang/String;
/*     */     //   92: invokevirtual append : (Ljava/lang/String;)Ljava/lang/StringBuilder;
/*     */     //   95: ldc_w '旹㰊璍ᠠ'
/*     */     //   98: invokevirtual toCharArray : ()[C
/*     */     //   101: dup
/*     */     //   102: dup
/*     */     //   103: iconst_2
/*     */     //   104: dup_x1
/*     */     //   105: caload
/*     */     //   106: sipush #12865
/*     */     //   109: ixor
/*     */     //   110: i2c
/*     */     //   111: castore
/*     */     //   112: sipush #11250
/*     */     //   115: iconst_1
/*     */     //   116: iconst_3
/*     */     //   117: invokestatic G : (Ljava/lang/Object;SZB)Ljava/lang/String;
/*     */     //   120: invokevirtual append : (Ljava/lang/String;)Ljava/lang/StringBuilder;
/*     */     //   123: aload_1
/*     */     //   124: invokevirtual append : (Ljava/lang/String;)Ljava/lang/StringBuilder;
/*     */     //   127: ldc_w '䡺澕豲∱'
/*     */     //   130: invokevirtual toCharArray : ()[C
/*     */     //   133: dup
/*     */     //   134: dup
/*     */     //   135: iconst_1
/*     */     //   136: dup_x1
/*     */     //   137: caload
/*     */     //   138: sipush #19816
/*     */     //   141: ixor
/*     */     //   142: i2c
/*     */     //   143: castore
/*     */     //   144: sipush #9914
/*     */     //   147: iconst_0
/*     */     //   148: iconst_5
/*     */     //   149: invokestatic G : (Ljava/lang/Object;SZB)Ljava/lang/String;
/*     */     //   152: invokevirtual append : (Ljava/lang/String;)Ljava/lang/StringBuilder;
/*     */     //   155: aload_2
/*     */     //   156: invokevirtual toString : ()Ljava/lang/String;
/*     */     //   159: invokevirtual append : (Ljava/lang/String;)Ljava/lang/StringBuilder;
/*     */     //   162: invokevirtual toString : ()Ljava/lang/String;
/*     */     //   165: aload #4
/*     */     //   167: invokespecial <init> : (Ljava/lang/String;Ljava/lang/Throwable;)V
/*     */     //   170: athrow
/*     */     //   171: aload_3
/*     */     //   172: areturn
/*     */     // Exception table:
/*     */     //   from	to	target	type
/*     */     //   9	50	53	java/lang/Exception
/*     */   }
/*     */ }


/* Location:              C:\Users\BukkitBypass\Desktop\MatrixAC\AAC\AAC-spigot-5.2.0.jar!\me\konsolas\aac\gz.class
 * Java compiler version: 8 (52.0)
 * JD-Core Version:       1.1.3
 */