/*     */ package me.konsolas.aac;public final class hr { public static final int[][] h; public static final int[][] d; public static final AtomicIntegerArray[] j; public static final m9 e; private static final int g = 7; private static final int f = 8192; private static final int i = 40; private static final int k = 8; private static final int c = 255; private static final int a = 4; private static final int b = 1024;
/*     */   @Deprecated
/*     */   public static int[][] c(int[][] paramArrayOfint, long paramLong1, long paramLong2) {
/*   4 */     long l = a(paramArrayOfint);
/*     */ 
/*     */ 
/*     */ 
/*     */ 
/*     */ 
/*     */ 
/*     */ 
/*     */ 
/*     */ 
/*     */ 
/*     */ 
/*     */ 
/*     */ 
/*     */ 
/*     */ 
/*     */ 
/*     */ 
/*     */ 
/*     */ 
/*     */ 
/*     */ 
/*     */     
/*     */     try {  }
/*     */     catch (IllegalArgumentException illegalArgumentException)
/*  29 */     { throw a(null); }  return (paramLong1 > l) ? b(paramArrayOfint, Math.max(l + (l >> 1L), paramLong1), paramLong2) : paramArrayOfint;
/*     */   }
/*     */ 
/*     */ 
/*     */ 
/*     */ 
/*     */ 
/*     */ 
/*     */ 
/*     */ 
/*     */ 
/*     */ 
/*     */ 
/*     */ 
/*     */ 
/*     */ 
/*     */ 
/*     */ 
/*     */ 
/*     */ 
/*     */ 
/*     */ 
/*     */ 
/*     */ 
/*     */ 
/*     */ 
/*     */ 
/*     */ 
/*     */ 
/*     */ 
/*     */ 
/*     */ 
/*     */ 
/*     */ 
/*     */ 
/*     */ 
/*     */ 
/*     */ 
/*     */ 
/*     */ 
/*     */ 
/*     */ 
/*     */ 
/*     */ 
/*     */ 
/*     */ 
/*     */ 
/*     */ 
/*     */ 
/*     */ 
/*     */ 
/*     */ 
/*     */ 
/*     */ 
/*     */ 
/*     */ 
/*     */ 
/*     */ 
/*     */ 
/*     */ 
/*     */ 
/*     */ 
/*     */ 
/*     */ 
/*     */ 
/*     */ 
/*     */ 
/*     */ 
/*     */ 
/*     */ 
/*     */ 
/*     */ 
/*     */ 
/*     */ 
/*     */ 
/*     */ 
/*     */ 
/*     */ 
/*     */ 
/*     */ 
/*     */ 
/*     */ 
/*     */ 
/*     */ 
/*     */ 
/*     */ 
/*     */ 
/*     */ 
/*     */ 
/*     */ 
/*     */ 
/*     */ 
/*     */ 
/*     */ 
/*     */ 
/*     */ 
/*     */ 
/*     */ 
/*     */ 
/*     */ 
/*     */ 
/*     */ 
/*     */ 
/*     */ 
/*     */ 
/*     */ 
/*     */ 
/*     */ 
/*     */ 
/*     */ 
/*     */ 
/*     */ 
/*     */ 
/*     */ 
/*     */ 
/*     */ 
/*     */ 
/*     */ 
/*     */ 
/*     */ 
/*     */ 
/*     */ 
/*     */ 
/*     */ 
/*     */ 
/*     */ 
/*     */ 
/*     */ 
/*     */ 
/*     */ 
/*     */ 
/*     */ 
/*     */ 
/*     */ 
/*     */ 
/*     */ 
/*     */ 
/*     */ 
/*     */ 
/*     */ 
/*     */ 
/*     */ 
/*     */ 
/*     */ 
/*     */ 
/*     */ 
/*     */ 
/*     */ 
/*     */ 
/*     */ 
/*     */ 
/*     */ 
/*     */ 
/*     */ 
/*     */ 
/*     */ 
/*     */ 
/*     */ 
/*     */   
/*     */   public static void a(int[][] paramArrayOfint) {
/*     */     e(paramArrayOfint, 0L, k.a(paramArrayOfint));
/*     */   }
/*     */ 
/*     */ 
/*     */ 
/*     */ 
/*     */ 
/*     */ 
/*     */ 
/*     */ 
/*     */ 
/*     */ 
/*     */ 
/*     */ 
/*     */ 
/*     */ 
/*     */ 
/*     */ 
/*     */ 
/*     */ 
/*     */ 
/*     */ 
/*     */ 
/*     */ 
/*     */ 
/*     */ 
/*     */ 
/*     */ 
/*     */ 
/*     */ 
/*     */ 
/*     */ 
/*     */ 
/*     */ 
/*     */ 
/*     */ 
/*     */ 
/*     */ 
/*     */ 
/*     */ 
/*     */ 
/*     */ 
/*     */ 
/*     */ 
/*     */ 
/*     */ 
/*     */ 
/*     */ 
/*     */ 
/*     */ 
/*     */ 
/*     */ 
/*     */ 
/*     */ 
/*     */ 
/*     */ 
/*     */ 
/*     */ 
/*     */ 
/*     */ 
/*     */ 
/*     */ 
/*     */ 
/*     */ 
/*     */ 
/*     */ 
/*     */ 
/*     */ 
/*     */ 
/*     */ 
/*     */ 
/*     */ 
/*     */ 
/*     */ 
/*     */ 
/*     */ 
/*     */ 
/*     */ 
/*     */ 
/*     */ 
/*     */ 
/*     */ 
/*     */ 
/*     */ 
/*     */ 
/*     */ 
/*     */ 
/*     */ 
/*     */ 
/*     */ 
/*     */ 
/*     */ 
/*     */ 
/*     */ 
/*     */ 
/*     */ 
/*     */ 
/*     */ 
/*     */ 
/*     */ 
/*     */ 
/*     */ 
/*     */ 
/*     */ 
/*     */ 
/*     */ 
/*     */ 
/*     */ 
/*     */ 
/*     */ 
/*     */ 
/*     */ 
/*     */ 
/*     */ 
/*     */ 
/*     */ 
/*     */ 
/*     */ 
/*     */ 
/*     */ 
/*     */ 
/*     */ 
/*     */ 
/*     */ 
/*     */ 
/*     */ 
/*     */ 
/*     */ 
/*     */ 
/*     */ 
/*     */ 
/*     */ 
/*     */ 
/*     */ 
/*     */ 
/*     */ 
/*     */ 
/*     */ 
/*     */ 
/*     */ 
/*     */ 
/*     */ 
/*     */ 
/*     */ 
/*     */ 
/*     */ 
/*     */ 
/*     */ 
/*     */ 
/*     */ 
/*     */ 
/*     */ 
/*     */ 
/*     */ 
/*     */ 
/*     */ 
/*     */ 
/*     */ 
/*     */   
/*     */   public static long a(int[][] paramArrayOfint, long paramLong1, long paramLong2, int paramInt) {
/*     */     paramLong2--;
/* 350 */     for (; paramLong1 <= paramLong2; i = k.a(paramArrayOfint, l)) {
/*     */       int i;
/*     */       long l = paramLong1 + paramLong2 >>> 1L;
/*     */     } 
/*     */     return -(paramLong1 + 1L);
/*     */   }
/*     */ 
/*     */ 
/*     */ 
/*     */ 
/*     */ 
/*     */ 
/*     */ 
/*     */ 
/*     */ 
/*     */ 
/*     */ 
/*     */ 
/*     */ 
/*     */ 
/*     */ 
/*     */ 
/*     */ 
/*     */ 
/*     */ 
/*     */ 
/*     */ 
/*     */ 
/*     */ 
/*     */ 
/*     */ 
/*     */ 
/*     */ 
/*     */ 
/*     */ 
/*     */ 
/*     */ 
/*     */ 
/*     */ 
/*     */ 
/*     */ 
/*     */ 
/*     */   
/*     */   private static ForkJoinPool a() {
/*     */     ForkJoinPool forkJoinPool = ForkJoinTask.getPool();
/*     */     
/*     */     try {  }
/*     */     catch (IllegalArgumentException illegalArgumentException)
/* 398 */     { throw a(null); }  return (forkJoinPool == null) ? ForkJoinPool.commonPool() : forkJoinPool;
/*     */   }
/*     */   @Deprecated public static int[][] c(int[][] paramArrayOfint, long paramLong) { return b(paramArrayOfint, paramLong, a(paramArrayOfint)); }
/*     */   public static void e(int[][] paramArrayOfint, long paramLong1, long paramLong2) { ForkJoinPool forkJoinPool = a(); try { if (paramLong2 - paramLong1 >= 8192L) { try { if (forkJoinPool.getParallelism() == 1) { g(paramArrayOfint, paramLong1, paramLong2); return; }  } catch (IllegalArgumentException illegalArgumentException) { throw a(null); }  forkJoinPool.invoke(new dm(paramArrayOfint, paramLong1, paramLong2)); return; }  } catch (IllegalArgumentException illegalArgumentException) { throw a(null); }  g(paramArrayOfint, paramLong1, paramLong2); }
/*     */   @Deprecated public static int[][] b(int[][] paramArrayOfint, long paramLong1, long paramLong2) { try {  } catch (IllegalArgumentException illegalArgumentException) { throw a(null); }  return (paramLong1 > a(paramArrayOfint)) ? a(paramArrayOfint, paramLong1, paramLong2) : paramArrayOfint; }
/*     */   public static void g(int[][] paramArrayOfint, long paramLong1, long paramLong2) { // Byte code:
/*     */     //   0: lload_3
/*     */     //   1: lload_1
/*     */     //   2: lsub
/*     */     //   3: lstore #5
/*     */     //   5: lload #5
/*     */     //   7: ldc2_w 7
/*     */     //   10: lcmp
/*     */     //   11: ifge -> 25
/*     */     //   14: aload_0
/*     */     //   15: lload_1
/*     */     //   16: lload_3
/*     */     //   17: invokestatic f : ([[IJJ)V
/*     */     //   20: return
/*     */     //   21: invokestatic a : (Ljava/lang/IllegalArgumentException;)Ljava/lang/IllegalArgumentException;
/*     */     //   24: athrow
/*     */     //   25: lload_1
/*     */     //   26: lload #5
/*     */     //   28: ldc2_w 2
/*     */     //   31: ldiv
/*     */     //   32: ladd
/*     */     //   33: lstore #7
/*     */     //   35: lload #5
/*     */     //   37: ldc2_w 7
/*     */     //   40: lcmp
/*     */     //   41: ifle -> 143
/*     */     //   44: lload_1
/*     */     //   45: lstore #9
/*     */     //   47: lload_3
/*     */     //   48: lconst_1
/*     */     //   49: lsub
/*     */     //   50: lstore #11
/*     */     //   52: lload #5
/*     */     //   54: ldc2_w 40
/*     */     //   57: lcmp
/*     */     //   58: ifle -> 131
/*     */     //   61: lload #5
/*     */     //   63: ldc2_w 8
/*     */     //   66: ldiv
/*     */     //   67: lstore #13
/*     */     //   69: aload_0
/*     */     //   70: lload #9
/*     */     //   72: lload #9
/*     */     //   74: lload #13
/*     */     //   76: ladd
/*     */     //   77: lload #9
/*     */     //   79: ldc2_w 2
/*     */     //   82: lload #13
/*     */     //   84: lmul
/*     */     //   85: ladd
/*     */     //   86: invokestatic b : ([[IJJJ)J
/*     */     //   89: lstore #9
/*     */     //   91: aload_0
/*     */     //   92: lload #7
/*     */     //   94: lload #13
/*     */     //   96: lsub
/*     */     //   97: lload #7
/*     */     //   99: lload #7
/*     */     //   101: lload #13
/*     */     //   103: ladd
/*     */     //   104: invokestatic b : ([[IJJJ)J
/*     */     //   107: lstore #7
/*     */     //   109: aload_0
/*     */     //   110: lload #11
/*     */     //   112: ldc2_w 2
/*     */     //   115: lload #13
/*     */     //   117: lmul
/*     */     //   118: lsub
/*     */     //   119: lload #11
/*     */     //   121: lload #13
/*     */     //   123: lsub
/*     */     //   124: lload #11
/*     */     //   126: invokestatic b : ([[IJJJ)J
/*     */     //   129: lstore #11
/*     */     //   131: aload_0
/*     */     //   132: lload #9
/*     */     //   134: lload #7
/*     */     //   136: lload #11
/*     */     //   138: invokestatic b : ([[IJJJ)J
/*     */     //   141: lstore #7
/*     */     //   143: aload_0
/*     */     //   144: lload #7
/*     */     //   146: invokestatic a : ([[IJ)I
/*     */     //   149: istore #9
/*     */     //   151: lload_1
/*     */     //   152: lstore #10
/*     */     //   154: lload #10
/*     */     //   156: lstore #12
/*     */     //   158: lload_3
/*     */     //   159: lconst_1
/*     */     //   160: lsub
/*     */     //   161: lstore #14
/*     */     //   163: lload #14
/*     */     //   165: lstore #16
/*     */     //   167: lload #12
/*     */     //   169: lload #14
/*     */     //   171: lcmp
/*     */     //   172: ifgt -> 226
/*     */     //   175: aload_0
/*     */     //   176: lload #12
/*     */     //   178: invokestatic a : ([[IJ)I
/*     */     //   181: iload #9
/*     */     //   183: invokestatic compare : (II)I
/*     */     //   186: dup
/*     */     //   187: istore #18
/*     */     //   189: ifgt -> 226
/*     */     //   192: iload #18
/*     */     //   194: ifne -> 217
/*     */     //   197: goto -> 204
/*     */     //   200: invokestatic a : (Ljava/lang/IllegalArgumentException;)Ljava/lang/IllegalArgumentException;
/*     */     //   203: athrow
/*     */     //   204: aload_0
/*     */     //   205: lload #10
/*     */     //   207: dup2
/*     */     //   208: lconst_1
/*     */     //   209: ladd
/*     */     //   210: lstore #10
/*     */     //   212: lload #12
/*     */     //   214: invokestatic a : ([[IJJ)V
/*     */     //   217: lload #12
/*     */     //   219: lconst_1
/*     */     //   220: ladd
/*     */     //   221: lstore #12
/*     */     //   223: goto -> 167
/*     */     //   226: lload #14
/*     */     //   228: lload #12
/*     */     //   230: lcmp
/*     */     //   231: iflt -> 285
/*     */     //   234: aload_0
/*     */     //   235: lload #14
/*     */     //   237: invokestatic a : ([[IJ)I
/*     */     //   240: iload #9
/*     */     //   242: invokestatic compare : (II)I
/*     */     //   245: dup
/*     */     //   246: istore #18
/*     */     //   248: iflt -> 285
/*     */     //   251: iload #18
/*     */     //   253: ifne -> 276
/*     */     //   256: goto -> 263
/*     */     //   259: invokestatic a : (Ljava/lang/IllegalArgumentException;)Ljava/lang/IllegalArgumentException;
/*     */     //   262: athrow
/*     */     //   263: aload_0
/*     */     //   264: lload #14
/*     */     //   266: lload #16
/*     */     //   268: dup2
/*     */     //   269: lconst_1
/*     */     //   270: lsub
/*     */     //   271: lstore #16
/*     */     //   273: invokestatic a : ([[IJJ)V
/*     */     //   276: lload #14
/*     */     //   278: lconst_1
/*     */     //   279: lsub
/*     */     //   280: lstore #14
/*     */     //   282: goto -> 226
/*     */     //   285: lload #12
/*     */     //   287: lload #14
/*     */     //   289: lcmp
/*     */     //   290: ifle -> 300
/*     */     //   293: goto -> 321
/*     */     //   296: invokestatic a : (Ljava/lang/IllegalArgumentException;)Ljava/lang/IllegalArgumentException;
/*     */     //   299: athrow
/*     */     //   300: aload_0
/*     */     //   301: lload #12
/*     */     //   303: dup2
/*     */     //   304: lconst_1
/*     */     //   305: ladd
/*     */     //   306: lstore #12
/*     */     //   308: lload #14
/*     */     //   310: dup2
/*     */     //   311: lconst_1
/*     */     //   312: lsub
/*     */     //   313: lstore #14
/*     */     //   315: invokestatic a : ([[IJJ)V
/*     */     //   318: goto -> 167
/*     */     //   321: lload_3
/*     */     //   322: lstore #20
/*     */     //   324: lload #10
/*     */     //   326: lload_1
/*     */     //   327: lsub
/*     */     //   328: lload #12
/*     */     //   330: lload #10
/*     */     //   332: lsub
/*     */     //   333: invokestatic min : (JJ)J
/*     */     //   336: lstore #18
/*     */     //   338: aload_0
/*     */     //   339: lload_1
/*     */     //   340: lload #12
/*     */     //   342: lload #18
/*     */     //   344: lsub
/*     */     //   345: lload #18
/*     */     //   347: invokestatic b : ([[IJJJ)V
/*     */     //   350: lload #16
/*     */     //   352: lload #14
/*     */     //   354: lsub
/*     */     //   355: lload #20
/*     */     //   357: lload #16
/*     */     //   359: lsub
/*     */     //   360: lconst_1
/*     */     //   361: lsub
/*     */     //   362: invokestatic min : (JJ)J
/*     */     //   365: lstore #18
/*     */     //   367: aload_0
/*     */     //   368: lload #12
/*     */     //   370: lload #20
/*     */     //   372: lload #18
/*     */     //   374: lsub
/*     */     //   375: lload #18
/*     */     //   377: invokestatic b : ([[IJJJ)V
/*     */     //   380: lload #12
/*     */     //   382: lload #10
/*     */     //   384: lsub
/*     */     //   385: dup2
/*     */     //   386: lstore #18
/*     */     //   388: lconst_1
/*     */     //   389: lcmp
/*     */     //   390: ifle -> 409
/*     */     //   393: aload_0
/*     */     //   394: lload_1
/*     */     //   395: lload_1
/*     */     //   396: lload #18
/*     */     //   398: ladd
/*     */     //   399: invokestatic g : ([[IJJ)V
/*     */     //   402: goto -> 409
/*     */     //   405: invokestatic a : (Ljava/lang/IllegalArgumentException;)Ljava/lang/IllegalArgumentException;
/*     */     //   408: athrow
/*     */     //   409: lload #16
/*     */     //   411: lload #14
/*     */     //   413: lsub
/*     */     //   414: dup2
/*     */     //   415: lstore #18
/*     */     //   417: lconst_1
/*     */     //   418: lcmp
/*     */     //   419: ifle -> 440
/*     */     //   422: aload_0
/*     */     //   423: lload #20
/*     */     //   425: lload #18
/*     */     //   427: lsub
/*     */     //   428: lload #20
/*     */     //   430: invokestatic g : ([[IJJ)V
/*     */     //   433: goto -> 440
/*     */     //   436: invokestatic a : (Ljava/lang/IllegalArgumentException;)Ljava/lang/IllegalArgumentException;
/*     */     //   439: athrow
/*     */     //   440: return
/*     */     // Line number table:
/*     */     //   Java source line number -> byte code offset
/*     */     //   #80	-> 0
/*     */     //   #421	-> 5
/*     */     //   #319	-> 14
/*     */     //   #264	-> 20
/*     */     //   #348	-> 25
/*     */     //   #183	-> 35
/*     */     //   #393	-> 44
/*     */     //   #298	-> 47
/*     */     //   #270	-> 52
/*     */     //   #82	-> 61
/*     */     //   #20	-> 69
/*     */     //   #170	-> 91
/*     */     //   #218	-> 109
/*     */     //   #224	-> 131
/*     */     //   #103	-> 143
/*     */     //   #57	-> 151
/*     */     //   #396	-> 167
/*     */     //   #84	-> 192
/*     */     //   #268	-> 217
/*     */     //   #34	-> 226
/*     */     //   #272	-> 251
/*     */     //   #70	-> 276
/*     */     //   #142	-> 285
/*     */     //   #334	-> 300
/*     */     //   #189	-> 321
/*     */     //   #40	-> 324
/*     */     //   #324	-> 338
/*     */     //   #367	-> 350
/*     */     //   #244	-> 367
/*     */     //   #369	-> 380
/*     */     //   #247	-> 409
/*     */     //   #50	-> 440
/*     */     // Exception table:
/*     */     //   from	to	target	type
/*     */     //   5	21	21	java/lang/IllegalArgumentException
/*     */     //   189	197	200	java/lang/IllegalArgumentException
/*     */     //   248	256	259	java/lang/IllegalArgumentException
/*     */     //   285	296	296	java/lang/IllegalArgumentException
/*     */     //   388	402	405	java/lang/IllegalArgumentException
/*     */     //   417	433	436	java/lang/IllegalArgumentException }
/*     */   @Deprecated public static void a(int[] paramArrayOfint, int paramInt, int[][] paramArrayOfint1, long paramLong1, long paramLong2) { k.a(paramArrayOfint, paramInt, paramArrayOfint1, paramLong1, paramLong2); }
/*     */   @Deprecated public static void b(int[][] paramArrayOfint, long paramLong1, long paramLong2) { int i = paramArrayOfint[k.b(paramLong1)][k.a(paramLong1)]; paramArrayOfint[k.b(paramLong1)][k.a(paramLong1)] = paramArrayOfint[k.b(paramLong2)][k.a(paramLong2)]; paramArrayOfint[k.b(paramLong2)][k.a(paramLong2)] = i; }
/*     */   @Deprecated public static void b(int[][] paramArrayOfint, long paramLong, int paramInt) { paramArrayOfint[k.b(paramLong)][k.a(paramLong)] = paramArrayOfint[k.b(paramLong)][k.a(paramLong)] + paramInt; }
/*     */   public static long a(int[][] paramArrayOfint, int paramInt) { return a(paramArrayOfint, 0L, k.a(paramArrayOfint), paramInt); }
/*     */   @Deprecated public static void a(int[][] paramArrayOfint, long paramLong) { paramArrayOfint[k.b(paramLong)][k.a(paramLong)] = paramArrayOfint[k.b(paramLong)][k.a(paramLong)] - 1; }
/*     */   @Deprecated public static String a(int[][] paramArrayOfint) { return k.a(paramArrayOfint); }
/*     */   @Deprecated public static long a(int[][] paramArrayOfint) { int i = paramArrayOfint.length; try {  } catch (IllegalArgumentException illegalArgumentException) { throw a(null); }  return (i == 0) ? 0L : (k.a(i - 1) + (paramArrayOfint[i - 1]).length); }
/*     */   @Deprecated public static void c(int[][] paramArrayOfint, long paramLong, int paramInt) { paramArrayOfint[k.b(paramLong)][k.a(paramLong)] = paramInt; }
/*     */   private static void a(long[][] paramArrayOflong, int[][] paramArrayOfint1, int[][] paramArrayOfint2, long paramLong1, long paramLong2) { // Byte code:
/*     */     //   0: lload_3
/*     */     //   1: lstore #7
/*     */     //   3: lload #7
/*     */     //   5: lconst_1
/*     */     //   6: ladd
/*     */     //   7: dup2
/*     */     //   8: lstore #7
/*     */     //   10: lload #5
/*     */     //   12: lcmp
/*     */     //   13: ifge -> 159
/*     */     //   16: aload_0
/*     */     //   17: lload #7
/*     */     //   19: invokestatic a : ([[JJ)J
/*     */     //   22: lstore #9
/*     */     //   24: lload #7
/*     */     //   26: lstore #11
/*     */     //   28: aload_0
/*     */     //   29: lload #11
/*     */     //   31: lconst_1
/*     */     //   32: lsub
/*     */     //   33: invokestatic a : ([[JJ)J
/*     */     //   36: lstore #13
/*     */     //   38: aload_1
/*     */     //   39: lload #9
/*     */     //   41: invokestatic a : ([[IJ)I
/*     */     //   44: aload_1
/*     */     //   45: lload #13
/*     */     //   47: invokestatic a : ([[IJ)I
/*     */     //   50: if_icmplt -> 97
/*     */     //   53: aload_1
/*     */     //   54: lload #9
/*     */     //   56: invokestatic a : ([[IJ)I
/*     */     //   59: aload_1
/*     */     //   60: lload #13
/*     */     //   62: invokestatic a : ([[IJ)I
/*     */     //   65: if_icmpne -> 148
/*     */     //   68: goto -> 75
/*     */     //   71: invokestatic a : (Ljava/lang/IllegalArgumentException;)Ljava/lang/IllegalArgumentException;
/*     */     //   74: athrow
/*     */     //   75: aload_2
/*     */     //   76: lload #9
/*     */     //   78: invokestatic a : ([[IJ)I
/*     */     //   81: aload_2
/*     */     //   82: lload #13
/*     */     //   84: invokestatic a : ([[IJ)I
/*     */     //   87: if_icmpge -> 148
/*     */     //   90: goto -> 97
/*     */     //   93: invokestatic a : (Ljava/lang/IllegalArgumentException;)Ljava/lang/IllegalArgumentException;
/*     */     //   96: athrow
/*     */     //   97: aload_0
/*     */     //   98: lload #11
/*     */     //   100: lload #13
/*     */     //   102: invokestatic d : ([[JJJ)V
/*     */     //   105: lload_3
/*     */     //   106: lload #11
/*     */     //   108: lconst_1
/*     */     //   109: lsub
/*     */     //   110: lcmp
/*     */     //   111: ifne -> 130
/*     */     //   114: goto -> 121
/*     */     //   117: invokestatic a : (Ljava/lang/IllegalArgumentException;)Ljava/lang/IllegalArgumentException;
/*     */     //   120: athrow
/*     */     //   121: lload #11
/*     */     //   123: lconst_1
/*     */     //   124: lsub
/*     */     //   125: lstore #11
/*     */     //   127: goto -> 148
/*     */     //   130: aload_0
/*     */     //   131: lload #11
/*     */     //   133: lconst_1
/*     */     //   134: lsub
/*     */     //   135: dup2
/*     */     //   136: lstore #11
/*     */     //   138: lconst_1
/*     */     //   139: lsub
/*     */     //   140: invokestatic a : ([[JJ)J
/*     */     //   143: lstore #13
/*     */     //   145: goto -> 38
/*     */     //   148: aload_0
/*     */     //   149: lload #11
/*     */     //   151: lload #9
/*     */     //   153: invokestatic d : ([[JJJ)V
/*     */     //   156: goto -> 3
/*     */     //   159: return
/*     */     // Line number table:
/*     */     //   Java source line number -> byte code offset
/*     */     //   #156	-> 0
/*     */     //   #187	-> 16
/*     */     //   #195	-> 24
/*     */     //   #147	-> 28
/*     */     //   #24	-> 97
/*     */     //   #209	-> 105
/*     */     //   #152	-> 121
/*     */     //   #100	-> 127
/*     */     //   #271	-> 130
/*     */     //   #98	-> 148
/*     */     //   #91	-> 156
/*     */     //   #285	-> 159
/*     */     // Exception table:
/*     */     //   from	to	target	type
/*     */     //   38	68	71	java/lang/IllegalArgumentException
/*     */     //   53	90	93	java/lang/IllegalArgumentException
/*     */     //   75	114	117	java/lang/IllegalArgumentException }
/* 413 */   @Deprecated public static int[][] a(int[][] paramArrayOfint, long paramLong) { return k.b(paramArrayOfint, paramLong); } @Deprecated public static void a(int[][] paramArrayOfint, long paramLong, int paramInt) { paramArrayOfint[k.b(paramLong)][k.a(paramLong)] = paramArrayOfint[k.b(paramLong)][k.a(paramLong)] * paramInt; } public static void b(int[][] paramArrayOfint, kx paramkx) { c(paramArrayOfint, 0L, k.a(paramArrayOfint), paramkx); } @Deprecated public static void d(int[][] paramArrayOfint, long paramLong1, long paramLong2) { k.b(a(paramArrayOfint), paramLong1, paramLong2); } public static long a(int[][] paramArrayOfint, int paramInt, kx paramkx) { return a(paramArrayOfint, 0L, k.a(paramArrayOfint), paramInt, paramkx); } private static void b(int[][] paramArrayOfint, long paramLong1, long paramLong2, long paramLong3) { for (byte b = 0; b < paramLong3; ) { k.a(paramArrayOfint, paramLong1, paramLong2); b++; paramLong1++; paramLong2++; }  } public static void c(int[][] paramArrayOfint) { c(paramArrayOfint, 0L, k.a(paramArrayOfint)); } @Deprecated public static int[][] d(int[][] paramArrayOfint, long paramLong) { k.a(paramLong); long l = a(paramArrayOfint); try { if (paramLong >= l) return paramArrayOfint;  } catch (IllegalArgumentException illegalArgumentException) { throw a(null); }  int i = (int)(paramLong + 134217727L >>> 27L); int[][] arrayOfInt = Arrays.<int[]>copyOf(paramArrayOfint, i); int j = (int)(paramLong & 0x7FFFFFFL); try { if (j != 0) arrayOfInt[i - 1] = fG.d(arrayOfInt[i - 1], j);  } catch (IllegalArgumentException illegalArgumentException) { throw a(null); }  return arrayOfInt; }
/*     */   @Deprecated public static void a(int[][] paramArrayOfint, int paramInt) { int i = paramArrayOfint.length; try { for (; i-- != 0; Arrays.fill(paramArrayOfint[i], paramInt)); } catch (IllegalArgumentException illegalArgumentException) { throw a(null); }  }
/*     */   public static void a(int[][] paramArrayOfint1, int[][] paramArrayOfint2, long paramLong1, long paramLong2) { // Byte code:
/*     */     //   0: getstatic me/konsolas/aac/hr.l : J
/*     */     //   3: ldc2_w 90349393411689
/*     */     //   6: lxor
/*     */     //   7: lstore #6
/*     */     //   9: iconst_2
/*     */     //   10: istore #8
/*     */     //   12: aload_0
/*     */     //   13: invokestatic a : ([[I)J
/*     */     //   16: aload_1
/*     */     //   17: invokestatic a : ([[I)J
/*     */     //   20: lcmp
/*     */     //   21: ifeq -> 69
/*     */     //   24: new java/lang/IllegalArgumentException
/*     */     //   27: dup
/*     */     //   28: ldc_w 'ྞ赧㢨䌺읆嶉䗟悄䨚㦌ọൔ姱ꯦ쪸䎎✎'
/*     */     //   31: invokevirtual toCharArray : ()[C
/*     */     //   34: dup
/*     */     //   35: dup
/*     */     //   36: bipush #15
/*     */     //   38: dup_x1
/*     */     //   39: caload
/*     */     //   40: sipush #27018
/*     */     //   43: ixor
/*     */     //   44: i2c
/*     */     //   45: castore
/*     */     //   46: sipush #24593
/*     */     //   49: iconst_0
/*     */     //   50: iconst_3
/*     */     //   51: invokestatic G : (Ljava/lang/Object;SZB)Ljava/lang/String;
/*     */     //   54: invokespecial <init> : (Ljava/lang/String;)V
/*     */     //   57: athrow
/*     */     //   58: ldc2_w 675553672313641591
/*     */     //   61: lload #6
/*     */     //   63: <illegal opcode> w : (Ljava/lang/IllegalArgumentException;JJ)Ljava/lang/IllegalArgumentException;
/*     */     //   68: athrow
/*     */     //   69: bipush #7
/*     */     //   71: istore #9
/*     */     //   73: sipush #1786
/*     */     //   76: istore #10
/*     */     //   78: sipush #1786
/*     */     //   81: newarray long
/*     */     //   83: astore #11
/*     */     //   85: iconst_0
/*     */     //   86: istore #12
/*     */     //   88: sipush #1786
/*     */     //   91: newarray long
/*     */     //   93: astore #13
/*     */     //   95: iconst_0
/*     */     //   96: istore #14
/*     */     //   98: sipush #1786
/*     */     //   101: newarray int
/*     */     //   103: astore #15
/*     */     //   105: iconst_0
/*     */     //   106: istore #16
/*     */     //   108: aload #11
/*     */     //   110: iload #12
/*     */     //   112: iinc #12, 1
/*     */     //   115: lload_2
/*     */     //   116: lastore
/*     */     //   117: aload #13
/*     */     //   119: iload #14
/*     */     //   121: iinc #14, 1
/*     */     //   124: lload #4
/*     */     //   126: lload_2
/*     */     //   127: lsub
/*     */     //   128: lastore
/*     */     //   129: aload #15
/*     */     //   131: iload #16
/*     */     //   133: iinc #16, 1
/*     */     //   136: iconst_0
/*     */     //   137: iastore
/*     */     //   138: sipush #256
/*     */     //   141: newarray long
/*     */     //   143: astore #17
/*     */     //   145: sipush #256
/*     */     //   148: newarray long
/*     */     //   150: astore #18
/*     */     //   152: lload #4
/*     */     //   154: lload_2
/*     */     //   155: lsub
/*     */     //   156: invokestatic a : (J)[[B
/*     */     //   159: astore #19
/*     */     //   161: iload #12
/*     */     //   163: ifle -> 759
/*     */     //   166: aload #11
/*     */     //   168: iinc #12, -1
/*     */     //   171: iload #12
/*     */     //   173: laload
/*     */     //   174: lstore #20
/*     */     //   176: aload #13
/*     */     //   178: iinc #14, -1
/*     */     //   181: iload #14
/*     */     //   183: laload
/*     */     //   184: lstore #22
/*     */     //   186: aload #15
/*     */     //   188: iinc #16, -1
/*     */     //   191: iload #16
/*     */     //   193: iaload
/*     */     //   194: istore #24
/*     */     //   196: iload #24
/*     */     //   198: iconst_4
/*     */     //   199: irem
/*     */     //   200: ifne -> 220
/*     */     //   203: sipush #128
/*     */     //   206: goto -> 221
/*     */     //   209: ldc2_w 675553672313641591
/*     */     //   212: lload #6
/*     */     //   214: <illegal opcode> w : (Ljava/lang/IllegalArgumentException;JJ)Ljava/lang/IllegalArgumentException;
/*     */     //   219: athrow
/*     */     //   220: iconst_0
/*     */     //   221: istore #25
/*     */     //   223: lload #22
/*     */     //   225: ldc2_w 40
/*     */     //   228: lcmp
/*     */     //   229: ifge -> 258
/*     */     //   232: aload_0
/*     */     //   233: aload_1
/*     */     //   234: lload #20
/*     */     //   236: lload #20
/*     */     //   238: lload #22
/*     */     //   240: ladd
/*     */     //   241: invokestatic b : ([[I[[IJJ)V
/*     */     //   244: goto -> 161
/*     */     //   247: ldc2_w 675553672313641591
/*     */     //   250: lload #6
/*     */     //   252: <illegal opcode> w : (Ljava/lang/IllegalArgumentException;JJ)Ljava/lang/IllegalArgumentException;
/*     */     //   257: athrow
/*     */     //   258: iload #24
/*     */     //   260: iconst_4
/*     */     //   261: if_icmpge -> 279
/*     */     //   264: aload_0
/*     */     //   265: goto -> 280
/*     */     //   268: ldc2_w 675553672313641591
/*     */     //   271: lload #6
/*     */     //   273: <illegal opcode> w : (Ljava/lang/IllegalArgumentException;JJ)Ljava/lang/IllegalArgumentException;
/*     */     //   278: athrow
/*     */     //   279: aload_1
/*     */     //   280: astore #26
/*     */     //   282: iconst_3
/*     */     //   283: iload #24
/*     */     //   285: iconst_4
/*     */     //   286: irem
/*     */     //   287: isub
/*     */     //   288: bipush #8
/*     */     //   290: imul
/*     */     //   291: istore #27
/*     */     //   293: lload #22
/*     */     //   295: lstore #28
/*     */     //   297: lload #28
/*     */     //   299: dup2
/*     */     //   300: lconst_1
/*     */     //   301: lsub
/*     */     //   302: lstore #28
/*     */     //   304: lconst_0
/*     */     //   305: lcmp
/*     */     //   306: ifeq -> 351
/*     */     //   309: aload #19
/*     */     //   311: lload #28
/*     */     //   313: aload #26
/*     */     //   315: lload #20
/*     */     //   317: lload #28
/*     */     //   319: ladd
/*     */     //   320: invokestatic a : ([[IJ)I
/*     */     //   323: iload #27
/*     */     //   325: iushr
/*     */     //   326: sipush #255
/*     */     //   329: iand
/*     */     //   330: iload #25
/*     */     //   332: ixor
/*     */     //   333: i2b
/*     */     //   334: invokestatic b : ([[BJB)V
/*     */     //   337: goto -> 297
/*     */     //   340: ldc2_w 675553672313641591
/*     */     //   343: lload #6
/*     */     //   345: <illegal opcode> w : (Ljava/lang/IllegalArgumentException;JJ)Ljava/lang/IllegalArgumentException;
/*     */     //   350: athrow
/*     */     //   351: lload #22
/*     */     //   353: lstore #28
/*     */     //   355: lload #28
/*     */     //   357: dup2
/*     */     //   358: lconst_1
/*     */     //   359: lsub
/*     */     //   360: lstore #28
/*     */     //   362: lconst_0
/*     */     //   363: lcmp
/*     */     //   364: ifeq -> 399
/*     */     //   367: aload #17
/*     */     //   369: aload #19
/*     */     //   371: lload #28
/*     */     //   373: invokestatic a : ([[BJ)B
/*     */     //   376: sipush #255
/*     */     //   379: iand
/*     */     //   380: dup2
/*     */     //   381: laload
/*     */     //   382: lconst_1
/*     */     //   383: ladd
/*     */     //   384: lastore
/*     */     //   385: goto -> 355
/*     */     //   388: ldc2_w 675553672313641591
/*     */     //   391: lload #6
/*     */     //   393: <illegal opcode> w : (Ljava/lang/IllegalArgumentException;JJ)Ljava/lang/IllegalArgumentException;
/*     */     //   398: athrow
/*     */     //   399: iconst_m1
/*     */     //   400: istore #28
/*     */     //   402: lconst_0
/*     */     //   403: lstore #29
/*     */     //   405: iconst_0
/*     */     //   406: istore #31
/*     */     //   408: iload #31
/*     */     //   410: sipush #256
/*     */     //   413: if_icmpge -> 549
/*     */     //   416: aload #17
/*     */     //   418: iload #31
/*     */     //   420: laload
/*     */     //   421: lconst_0
/*     */     //   422: lcmp
/*     */     //   423: ifeq -> 527
/*     */     //   426: goto -> 440
/*     */     //   429: ldc2_w 675553672313641591
/*     */     //   432: lload #6
/*     */     //   434: <illegal opcode> w : (Ljava/lang/IllegalArgumentException;JJ)Ljava/lang/IllegalArgumentException;
/*     */     //   439: athrow
/*     */     //   440: iload #31
/*     */     //   442: istore #28
/*     */     //   444: iload #24
/*     */     //   446: bipush #7
/*     */     //   448: if_icmpge -> 527
/*     */     //   451: aload #17
/*     */     //   453: iload #31
/*     */     //   455: laload
/*     */     //   456: lconst_1
/*     */     //   457: lcmp
/*     */     //   458: ifle -> 527
/*     */     //   461: goto -> 475
/*     */     //   464: ldc2_w 675553672313641591
/*     */     //   467: lload #6
/*     */     //   469: <illegal opcode> w : (Ljava/lang/IllegalArgumentException;JJ)Ljava/lang/IllegalArgumentException;
/*     */     //   474: athrow
/*     */     //   475: aload #11
/*     */     //   477: iload #12
/*     */     //   479: iinc #12, 1
/*     */     //   482: lload #29
/*     */     //   484: lload #20
/*     */     //   486: ladd
/*     */     //   487: lastore
/*     */     //   488: aload #13
/*     */     //   490: iload #14
/*     */     //   492: iinc #14, 1
/*     */     //   495: aload #17
/*     */     //   497: iload #31
/*     */     //   499: laload
/*     */     //   500: lastore
/*     */     //   501: aload #15
/*     */     //   503: iload #16
/*     */     //   505: iinc #16, 1
/*     */     //   508: iload #24
/*     */     //   510: iconst_1
/*     */     //   511: iadd
/*     */     //   512: iastore
/*     */     //   513: goto -> 527
/*     */     //   516: ldc2_w 675553672313641591
/*     */     //   519: lload #6
/*     */     //   521: <illegal opcode> w : (Ljava/lang/IllegalArgumentException;JJ)Ljava/lang/IllegalArgumentException;
/*     */     //   526: athrow
/*     */     //   527: aload #18
/*     */     //   529: iload #31
/*     */     //   531: lload #29
/*     */     //   533: aload #17
/*     */     //   535: iload #31
/*     */     //   537: laload
/*     */     //   538: ladd
/*     */     //   539: dup2
/*     */     //   540: lstore #29
/*     */     //   542: lastore
/*     */     //   543: iinc #31, 1
/*     */     //   546: goto -> 408
/*     */     //   549: lload #22
/*     */     //   551: aload #17
/*     */     //   553: iload #28
/*     */     //   555: laload
/*     */     //   556: lsub
/*     */     //   557: lstore #31
/*     */     //   559: aload #17
/*     */     //   561: iload #28
/*     */     //   563: lconst_0
/*     */     //   564: lastore
/*     */     //   565: iconst_m1
/*     */     //   566: istore #33
/*     */     //   568: lconst_0
/*     */     //   569: lstore #34
/*     */     //   571: lload #34
/*     */     //   573: lload #31
/*     */     //   575: lcmp
/*     */     //   576: ifge -> 756
/*     */     //   579: aload_0
/*     */     //   580: lload #34
/*     */     //   582: lload #20
/*     */     //   584: ladd
/*     */     //   585: invokestatic a : ([[IJ)I
/*     */     //   588: istore #38
/*     */     //   590: aload_1
/*     */     //   591: lload #34
/*     */     //   593: lload #20
/*     */     //   595: ladd
/*     */     //   596: invokestatic a : ([[IJ)I
/*     */     //   599: istore #39
/*     */     //   601: aload #19
/*     */     //   603: lload #34
/*     */     //   605: invokestatic a : ([[BJ)B
/*     */     //   608: sipush #255
/*     */     //   611: iand
/*     */     //   612: istore #33
/*     */     //   614: aload #18
/*     */     //   616: iload #33
/*     */     //   618: dup2
/*     */     //   619: laload
/*     */     //   620: lconst_1
/*     */     //   621: lsub
/*     */     //   622: dup2_x2
/*     */     //   623: lastore
/*     */     //   624: dup2
/*     */     //   625: lstore #36
/*     */     //   627: lload #34
/*     */     //   629: lcmp
/*     */     //   630: ifle -> 715
/*     */     //   633: iload #38
/*     */     //   635: istore #40
/*     */     //   637: iload #33
/*     */     //   639: istore #41
/*     */     //   641: aload_0
/*     */     //   642: lload #36
/*     */     //   644: lload #20
/*     */     //   646: ladd
/*     */     //   647: invokestatic a : ([[IJ)I
/*     */     //   650: istore #38
/*     */     //   652: aload_0
/*     */     //   653: lload #36
/*     */     //   655: lload #20
/*     */     //   657: ladd
/*     */     //   658: iload #40
/*     */     //   660: invokestatic c : ([[IJI)V
/*     */     //   663: iload #39
/*     */     //   665: istore #40
/*     */     //   667: aload_1
/*     */     //   668: lload #36
/*     */     //   670: lload #20
/*     */     //   672: ladd
/*     */     //   673: invokestatic a : ([[IJ)I
/*     */     //   676: istore #39
/*     */     //   678: aload_1
/*     */     //   679: lload #36
/*     */     //   681: lload #20
/*     */     //   683: ladd
/*     */     //   684: iload #40
/*     */     //   686: invokestatic c : ([[IJI)V
/*     */     //   689: aload #19
/*     */     //   691: lload #36
/*     */     //   693: invokestatic a : ([[BJ)B
/*     */     //   696: sipush #255
/*     */     //   699: iand
/*     */     //   700: istore #33
/*     */     //   702: aload #19
/*     */     //   704: lload #36
/*     */     //   706: iload #41
/*     */     //   708: i2b
/*     */     //   709: invokestatic b : ([[BJB)V
/*     */     //   712: goto -> 614
/*     */     //   715: aload_0
/*     */     //   716: lload #34
/*     */     //   718: lload #20
/*     */     //   720: ladd
/*     */     //   721: iload #38
/*     */     //   723: invokestatic c : ([[IJI)V
/*     */     //   726: aload_1
/*     */     //   727: lload #34
/*     */     //   729: lload #20
/*     */     //   731: ladd
/*     */     //   732: iload #39
/*     */     //   734: invokestatic c : ([[IJI)V
/*     */     //   737: lload #34
/*     */     //   739: aload #17
/*     */     //   741: iload #33
/*     */     //   743: laload
/*     */     //   744: ladd
/*     */     //   745: lstore #34
/*     */     //   747: aload #17
/*     */     //   749: iload #33
/*     */     //   751: lconst_0
/*     */     //   752: lastore
/*     */     //   753: goto -> 571
/*     */     //   756: goto -> 161
/*     */     //   759: return
/*     */     // Line number table:
/*     */     //   Java source line number -> byte code offset
/*     */     //   #251	-> 9
/*     */     //   #408	-> 12
/*     */     //   #395	-> 69
/*     */     //   #327	-> 73
/*     */     //   #402	-> 78
/*     */     //   #165	-> 85
/*     */     //   #383	-> 88
/*     */     //   #380	-> 95
/*     */     //   #293	-> 98
/*     */     //   #31	-> 105
/*     */     //   #237	-> 108
/*     */     //   #379	-> 117
/*     */     //   #323	-> 129
/*     */     //   #423	-> 138
/*     */     //   #131	-> 145
/*     */     //   #104	-> 152
/*     */     //   #352	-> 161
/*     */     //   #208	-> 166
/*     */     //   #149	-> 176
/*     */     //   #220	-> 186
/*     */     //   #287	-> 196
/*     */     //   #418	-> 223
/*     */     //   #76	-> 232
/*     */     //   #361	-> 244
/*     */     //   #97	-> 258
/*     */     //   #226	-> 282
/*     */     //   #286	-> 293
/*     */     //   #140	-> 351
/*     */     //   #94	-> 399
/*     */     //   #30	-> 402
/*     */     //   #114	-> 405
/*     */     //   #357	-> 416
/*     */     //   #5	-> 440
/*     */     //   #227	-> 444
/*     */     //   #239	-> 475
/*     */     //   #136	-> 488
/*     */     //   #349	-> 501
/*     */     //   #154	-> 527
/*     */     //   #414	-> 543
/*     */     //   #27	-> 549
/*     */     //   #321	-> 559
/*     */     //   #381	-> 565
/*     */     //   #304	-> 568
/*     */     //   #384	-> 579
/*     */     //   #290	-> 590
/*     */     //   #39	-> 601
/*     */     //   #303	-> 614
/*     */     //   #376	-> 633
/*     */     //   #292	-> 637
/*     */     //   #56	-> 641
/*     */     //   #60	-> 652
/*     */     //   #248	-> 663
/*     */     //   #46	-> 667
/*     */     //   #49	-> 678
/*     */     //   #409	-> 689
/*     */     //   #331	-> 702
/*     */     //   #343	-> 712
/*     */     //   #305	-> 715
/*     */     //   #106	-> 726
/*     */     //   #260	-> 737
/*     */     //   #10	-> 756
/*     */     //   #166	-> 759
/*     */     // Exception table:
/*     */     //   from	to	target	type
/*     */     //   12	58	58	java/lang/IllegalArgumentException
/*     */     //   196	209	209	java/lang/IllegalArgumentException
/*     */     //   223	247	247	java/lang/IllegalArgumentException
/*     */     //   258	268	268	java/lang/IllegalArgumentException
/*     */     //   304	340	340	java/lang/IllegalArgumentException
/*     */     //   362	388	388	java/lang/IllegalArgumentException
/*     */     //   408	426	429	java/lang/IllegalArgumentException
/*     */     //   444	461	464	java/lang/IllegalArgumentException
/*     */     //   451	513	516	java/lang/IllegalArgumentException }
/*     */   @Deprecated public static int[][] d(int[][] paramArrayOfint, long paramLong1, long paramLong2) { return k.b(paramArrayOfint, paramLong1, paramLong2); }
/*     */   @Deprecated public static void b(int[][] paramArrayOfint, long paramLong) { paramArrayOfint[k.b(paramLong)][k.a(paramLong)] = paramArrayOfint[k.b(paramLong)][k.a(paramLong)] + 1; }
/*     */   private static long b(int[][] paramArrayOfint, long paramLong1, long paramLong2, long paramLong3, kx paramkx) { int i = paramkx.a(k.a(paramArrayOfint, paramLong1), k.a(paramArrayOfint, paramLong2)); int j = paramkx.a(k.a(paramArrayOfint, paramLong1), k.a(paramArrayOfint, paramLong3)); int k = paramkx.a(k.a(paramArrayOfint, paramLong2), k.a(paramArrayOfint, paramLong3)); try { if (i < 0) { try { try {  } catch (IllegalArgumentException illegalArgumentException) { throw a(null); }  } catch (IllegalArgumentException illegalArgumentException) { throw a(null); }  } else { try { try {  } catch (IllegalArgumentException illegalArgumentException) { throw a(null); }  } catch (IllegalArgumentException illegalArgumentException) { throw a(null); }  }  } catch (IllegalArgumentException illegalArgumentException) { throw a(null); }  return (k > 0) ? paramLong2 : ((j > 0) ? paramLong3 : paramLong1); }
/*     */   @Deprecated public static void a(int[][] paramArrayOfint1, long paramLong1, int[][] paramArrayOfint2, long paramLong2, long paramLong3) { k.a(paramArrayOfint1, paramLong1, paramArrayOfint2, paramLong2, paramLong3); }
/*     */   @Deprecated public static void a(int[][] paramArrayOfint1, int[][] paramArrayOfint2) { // Byte code:
/*     */     //   0: getstatic me/konsolas/aac/hr.l : J
/*     */     //   3: ldc2_w 80239931296314
/*     */     //   6: lxor
/*     */     //   7: lstore_2
/*     */     //   8: aload_0
/*     */     //   9: invokestatic a : ([[I)J
/*     */     //   12: aload_1
/*     */     //   13: invokestatic a : ([[I)J
/*     */     //   16: lcmp
/*     */     //   17: ifeq -> 116
/*     */     //   20: new java/lang/IllegalArgumentException
/*     */     //   23: dup
/*     */     //   24: new java/lang/StringBuilder
/*     */     //   27: dup
/*     */     //   28: invokespecial <init> : ()V
/*     */     //   31: ldc 'ﭽ㖖埶댆㵎졼岝ꓰ⌤됈賰䦷䇍蝰뿅疺䳜ਉᲆ腗䍘'
/*     */     //   33: invokevirtual toCharArray : ()[C
/*     */     //   36: dup
/*     */     //   37: dup
/*     */     //   38: iconst_1
/*     */     //   39: dup_x1
/*     */     //   40: caload
/*     */     //   41: sipush #14630
/*     */     //   44: ixor
/*     */     //   45: i2c
/*     */     //   46: castore
/*     */     //   47: sipush #7459
/*     */     //   50: iconst_1
/*     */     //   51: iconst_0
/*     */     //   52: invokestatic A : (Ljava/lang/Object;SZI)Ljava/lang/String;
/*     */     //   55: invokevirtual append : (Ljava/lang/String;)Ljava/lang/StringBuilder;
/*     */     //   58: aload_0
/*     */     //   59: invokestatic a : ([[I)J
/*     */     //   62: invokevirtual append : (J)Ljava/lang/StringBuilder;
/*     */     //   65: ldc '껉Ꮥ硏X䴨'
/*     */     //   67: invokevirtual toCharArray : ()[C
/*     */     //   70: dup
/*     */     //   71: dup
/*     */     //   72: iconst_2
/*     */     //   73: dup_x1
/*     */     //   74: caload
/*     */     //   75: sipush #18652
/*     */     //   78: ixor
/*     */     //   79: i2c
/*     */     //   80: castore
/*     */     //   81: sipush #3941
/*     */     //   84: iconst_0
/*     */     //   85: iconst_2
/*     */     //   86: invokestatic A : (Ljava/lang/Object;SZI)Ljava/lang/String;
/*     */     //   89: invokevirtual append : (Ljava/lang/String;)Ljava/lang/StringBuilder;
/*     */     //   92: aload_1
/*     */     //   93: invokestatic a : ([[I)J
/*     */     //   96: invokevirtual append : (J)Ljava/lang/StringBuilder;
/*     */     //   99: invokevirtual toString : ()Ljava/lang/String;
/*     */     //   102: invokespecial <init> : (Ljava/lang/String;)V
/*     */     //   105: athrow
/*     */     //   106: ldc2_w -201792638581281244
/*     */     //   109: lload_2
/*     */     //   110: <illegal opcode> w : (Ljava/lang/IllegalArgumentException;JJ)Ljava/lang/IllegalArgumentException;
/*     */     //   115: athrow
/*     */     //   116: return
/*     */     // Line number table:
/*     */     //   Java source line number -> byte code offset
/*     */     //   #274	-> 8
/*     */     //   #77	-> 116
/*     */     // Exception table:
/*     */     //   from	to	target	type
/* 420 */     //   8	106	106	java/lang/IllegalArgumentException } private static void f(int[][] paramArrayOfint, long paramLong1, long paramLong2) { for (long l = paramLong1; l < paramLong2 - 1L; l2 = l + 1L) long l2, l1 = l;  } private static void b(int[][] paramArrayOfint, long paramLong1, long paramLong2, kx paramkx) { for (long l = paramLong1; l < paramLong2 - 1L; l2 = l + 1L) long l2, l1 = l;  } public static void a(int[][] paramArrayOfint, long paramLong1, long paramLong2, kx paramkx) { ForkJoinPool forkJoinPool = a(); try { if (paramLong2 - paramLong1 >= 8192L) { try { if (forkJoinPool.getParallelism() == 1) { c(paramArrayOfint, paramLong1, paramLong2, paramkx); return; }  } catch (IllegalArgumentException illegalArgumentException) { throw a(null); }  forkJoinPool.invoke(new mh(paramArrayOfint, paramLong1, paramLong2, paramkx)); return; }  } catch (IllegalArgumentException illegalArgumentException) { throw a(null); }  c(paramArrayOfint, paramLong1, paramLong2, paramkx); } public static AtomicIntegerArray[] a(long paramLong) { try { if (paramLong == 0L) return j;  } catch (IllegalArgumentException illegalArgumentException) { throw a(null); }  k.a(paramLong); int i = (int)(paramLong + 134217727L >>> 27L); AtomicIntegerArray[] arrayOfAtomicIntegerArray = new AtomicIntegerArray[i]; int j = (int)(paramLong & 0x7FFFFFFL); if (j != 0) { byte b = 0; try { while (b < i - 1) { arrayOfAtomicIntegerArray[b] = new AtomicIntegerArray(134217728); b++; }  } catch (IllegalArgumentException illegalArgumentException) { throw a(null); }  arrayOfAtomicIntegerArray[i - 1] = new AtomicIntegerArray(j); } else { byte b = 0; try { while (b < i) { arrayOfAtomicIntegerArray[b] = new AtomicIntegerArray(134217728); b++; }  } catch (IllegalArgumentException illegalArgumentException) { throw a(null); }  }  return arrayOfAtomicIntegerArray; } @Deprecated public static int[][] a(int[] paramArrayOfint) { return k.a(paramArrayOfint); } public static void a(long[][] paramArrayOflong, int[][] paramArrayOfint1, int[][] paramArrayOfint2, boolean paramBoolean) { a(paramArrayOfint1, paramArrayOfint2); a(paramArrayOflong, paramArrayOfint1, paramArrayOfint2, 0L, k.a(paramArrayOfint1), paramBoolean); } private static final long l = nc.a(-6026992237493464206L, 2513333703456038744L, MethodHandles.lookup().lookupClass()).a(111208984845129L); static { h = new int[0][]; d = new int[0][]; j = new AtomicIntegerArray[0]; e = new dC(null); } @Deprecated public static int[][] b(int[][] paramArrayOfint, long paramLong) { long l = a(paramArrayOfint); try {  } catch (IllegalArgumentException illegalArgumentException) { throw a(null); }  return (paramLong > l) ? c(paramArrayOfint, paramLong, l) : paramArrayOfint; } public static void a(int[][] paramArrayOfint, kx paramkx) { a(paramArrayOfint, 0L, k.a(paramArrayOfint), paramkx); }
/*     */   public static int[][] a(int[][] paramArrayOfint, Random paramRandom) { return k.a(paramArrayOfint, paramRandom); }
/*     */   @Deprecated public static void a(int[][] paramArrayOfint, long paramLong, int[] paramArrayOfint1, int paramInt1, int paramInt2) { k.a(paramArrayOfint, paramLong, paramArrayOfint1, paramInt1, paramInt2); }
/*     */   @Deprecated public static int[][] a(int[][] paramArrayOfint) { return k.b(paramArrayOfint); }
/*     */   private static long b(int[][] paramArrayOfint, long paramLong1, long paramLong2, long paramLong3) { int i = Integer.compare(k.a(paramArrayOfint, paramLong1), k.a(paramArrayOfint, paramLong2)); int j = Integer.compare(k.a(paramArrayOfint, paramLong1), k.a(paramArrayOfint, paramLong3)); int k = Integer.compare(k.a(paramArrayOfint, paramLong2), k.a(paramArrayOfint, paramLong3)); try { if (i < 0) { try { try {  } catch (IllegalArgumentException illegalArgumentException) { throw a(null); }  } catch (IllegalArgumentException illegalArgumentException) { throw a(null); }  } else { try { try {  } catch (IllegalArgumentException illegalArgumentException) { throw a(null); }  } catch (IllegalArgumentException illegalArgumentException) { throw a(null); }  }  } catch (IllegalArgumentException illegalArgumentException) { throw a(null); }  return (k > 0) ? paramLong2 : ((j > 0) ? paramLong3 : paramLong1); }
/*     */   @Deprecated public static void a(int[][] paramArrayOfint, long paramLong1, long paramLong2) { k.a(a(paramArrayOfint), paramLong1, paramLong2); }
/* 426 */   public static int[][] a(int[][] paramArrayOfint, long paramLong1, long paramLong2, Random paramRandom) { return k.a(paramArrayOfint, paramLong1, paramLong2, paramRandom); }
/*     */ 
/*     */   
/*     */   @Deprecated
/*     */   public static int a(int[][] paramArrayOfint, long paramLong) {
/*     */     return paramArrayOfint[k.b(paramLong)][k.a(paramLong)];
/*     */   }
/*     */   
/*     */   public static void c(int[][] paramArrayOfint, long paramLong1, long paramLong2, kx paramkx) {
/*     */     // Byte code:
/*     */     //   0: lload_3
/*     */     //   1: lload_1
/*     */     //   2: lsub
/*     */     //   3: lstore #6
/*     */     //   5: lload #6
/*     */     //   7: ldc2_w 7
/*     */     //   10: lcmp
/*     */     //   11: ifge -> 27
/*     */     //   14: aload_0
/*     */     //   15: lload_1
/*     */     //   16: lload_3
/*     */     //   17: aload #5
/*     */     //   19: invokestatic b : ([[IJJLme/konsolas/aac/kx;)V
/*     */     //   22: return
/*     */     //   23: invokestatic a : (Ljava/lang/IllegalArgumentException;)Ljava/lang/IllegalArgumentException;
/*     */     //   26: athrow
/*     */     //   27: lload_1
/*     */     //   28: lload #6
/*     */     //   30: ldc2_w 2
/*     */     //   33: ldiv
/*     */     //   34: ladd
/*     */     //   35: lstore #8
/*     */     //   37: lload #6
/*     */     //   39: ldc2_w 7
/*     */     //   42: lcmp
/*     */     //   43: ifle -> 153
/*     */     //   46: lload_1
/*     */     //   47: lstore #10
/*     */     //   49: lload_3
/*     */     //   50: lconst_1
/*     */     //   51: lsub
/*     */     //   52: lstore #12
/*     */     //   54: lload #6
/*     */     //   56: ldc2_w 40
/*     */     //   59: lcmp
/*     */     //   60: ifle -> 139
/*     */     //   63: lload #6
/*     */     //   65: ldc2_w 8
/*     */     //   68: ldiv
/*     */     //   69: lstore #14
/*     */     //   71: aload_0
/*     */     //   72: lload #10
/*     */     //   74: lload #10
/*     */     //   76: lload #14
/*     */     //   78: ladd
/*     */     //   79: lload #10
/*     */     //   81: ldc2_w 2
/*     */     //   84: lload #14
/*     */     //   86: lmul
/*     */     //   87: ladd
/*     */     //   88: aload #5
/*     */     //   90: invokestatic b : ([[IJJJLme/konsolas/aac/kx;)J
/*     */     //   93: lstore #10
/*     */     //   95: aload_0
/*     */     //   96: lload #8
/*     */     //   98: lload #14
/*     */     //   100: lsub
/*     */     //   101: lload #8
/*     */     //   103: lload #8
/*     */     //   105: lload #14
/*     */     //   107: ladd
/*     */     //   108: aload #5
/*     */     //   110: invokestatic b : ([[IJJJLme/konsolas/aac/kx;)J
/*     */     //   113: lstore #8
/*     */     //   115: aload_0
/*     */     //   116: lload #12
/*     */     //   118: ldc2_w 2
/*     */     //   121: lload #14
/*     */     //   123: lmul
/*     */     //   124: lsub
/*     */     //   125: lload #12
/*     */     //   127: lload #14
/*     */     //   129: lsub
/*     */     //   130: lload #12
/*     */     //   132: aload #5
/*     */     //   134: invokestatic b : ([[IJJJLme/konsolas/aac/kx;)J
/*     */     //   137: lstore #12
/*     */     //   139: aload_0
/*     */     //   140: lload #10
/*     */     //   142: lload #8
/*     */     //   144: lload #12
/*     */     //   146: aload #5
/*     */     //   148: invokestatic b : ([[IJJJLme/konsolas/aac/kx;)J
/*     */     //   151: lstore #8
/*     */     //   153: aload_0
/*     */     //   154: lload #8
/*     */     //   156: invokestatic a : ([[IJ)I
/*     */     //   159: istore #10
/*     */     //   161: lload_1
/*     */     //   162: lstore #11
/*     */     //   164: lload #11
/*     */     //   166: lstore #13
/*     */     //   168: lload_3
/*     */     //   169: lconst_1
/*     */     //   170: lsub
/*     */     //   171: lstore #15
/*     */     //   173: lload #15
/*     */     //   175: lstore #17
/*     */     //   177: lload #13
/*     */     //   179: lload #15
/*     */     //   181: lcmp
/*     */     //   182: ifgt -> 240
/*     */     //   185: aload #5
/*     */     //   187: aload_0
/*     */     //   188: lload #13
/*     */     //   190: invokestatic a : ([[IJ)I
/*     */     //   193: iload #10
/*     */     //   195: invokeinterface a : (II)I
/*     */     //   200: dup
/*     */     //   201: istore #19
/*     */     //   203: ifgt -> 240
/*     */     //   206: iload #19
/*     */     //   208: ifne -> 231
/*     */     //   211: goto -> 218
/*     */     //   214: invokestatic a : (Ljava/lang/IllegalArgumentException;)Ljava/lang/IllegalArgumentException;
/*     */     //   217: athrow
/*     */     //   218: aload_0
/*     */     //   219: lload #11
/*     */     //   221: dup2
/*     */     //   222: lconst_1
/*     */     //   223: ladd
/*     */     //   224: lstore #11
/*     */     //   226: lload #13
/*     */     //   228: invokestatic a : ([[IJJ)V
/*     */     //   231: lload #13
/*     */     //   233: lconst_1
/*     */     //   234: ladd
/*     */     //   235: lstore #13
/*     */     //   237: goto -> 177
/*     */     //   240: lload #15
/*     */     //   242: lload #13
/*     */     //   244: lcmp
/*     */     //   245: iflt -> 303
/*     */     //   248: aload #5
/*     */     //   250: aload_0
/*     */     //   251: lload #15
/*     */     //   253: invokestatic a : ([[IJ)I
/*     */     //   256: iload #10
/*     */     //   258: invokeinterface a : (II)I
/*     */     //   263: dup
/*     */     //   264: istore #19
/*     */     //   266: iflt -> 303
/*     */     //   269: iload #19
/*     */     //   271: ifne -> 294
/*     */     //   274: goto -> 281
/*     */     //   277: invokestatic a : (Ljava/lang/IllegalArgumentException;)Ljava/lang/IllegalArgumentException;
/*     */     //   280: athrow
/*     */     //   281: aload_0
/*     */     //   282: lload #15
/*     */     //   284: lload #17
/*     */     //   286: dup2
/*     */     //   287: lconst_1
/*     */     //   288: lsub
/*     */     //   289: lstore #17
/*     */     //   291: invokestatic a : ([[IJJ)V
/*     */     //   294: lload #15
/*     */     //   296: lconst_1
/*     */     //   297: lsub
/*     */     //   298: lstore #15
/*     */     //   300: goto -> 240
/*     */     //   303: lload #13
/*     */     //   305: lload #15
/*     */     //   307: lcmp
/*     */     //   308: ifle -> 318
/*     */     //   311: goto -> 339
/*     */     //   314: invokestatic a : (Ljava/lang/IllegalArgumentException;)Ljava/lang/IllegalArgumentException;
/*     */     //   317: athrow
/*     */     //   318: aload_0
/*     */     //   319: lload #13
/*     */     //   321: dup2
/*     */     //   322: lconst_1
/*     */     //   323: ladd
/*     */     //   324: lstore #13
/*     */     //   326: lload #15
/*     */     //   328: dup2
/*     */     //   329: lconst_1
/*     */     //   330: lsub
/*     */     //   331: lstore #15
/*     */     //   333: invokestatic a : ([[IJJ)V
/*     */     //   336: goto -> 177
/*     */     //   339: lload_3
/*     */     //   340: lstore #21
/*     */     //   342: lload #11
/*     */     //   344: lload_1
/*     */     //   345: lsub
/*     */     //   346: lload #13
/*     */     //   348: lload #11
/*     */     //   350: lsub
/*     */     //   351: invokestatic min : (JJ)J
/*     */     //   354: lstore #19
/*     */     //   356: aload_0
/*     */     //   357: lload_1
/*     */     //   358: lload #13
/*     */     //   360: lload #19
/*     */     //   362: lsub
/*     */     //   363: lload #19
/*     */     //   365: invokestatic b : ([[IJJJ)V
/*     */     //   368: lload #17
/*     */     //   370: lload #15
/*     */     //   372: lsub
/*     */     //   373: lload #21
/*     */     //   375: lload #17
/*     */     //   377: lsub
/*     */     //   378: lconst_1
/*     */     //   379: lsub
/*     */     //   380: invokestatic min : (JJ)J
/*     */     //   383: lstore #19
/*     */     //   385: aload_0
/*     */     //   386: lload #13
/*     */     //   388: lload #21
/*     */     //   390: lload #19
/*     */     //   392: lsub
/*     */     //   393: lload #19
/*     */     //   395: invokestatic b : ([[IJJJ)V
/*     */     //   398: lload #13
/*     */     //   400: lload #11
/*     */     //   402: lsub
/*     */     //   403: dup2
/*     */     //   404: lstore #19
/*     */     //   406: lconst_1
/*     */     //   407: lcmp
/*     */     //   408: ifle -> 429
/*     */     //   411: aload_0
/*     */     //   412: lload_1
/*     */     //   413: lload_1
/*     */     //   414: lload #19
/*     */     //   416: ladd
/*     */     //   417: aload #5
/*     */     //   419: invokestatic c : ([[IJJLme/konsolas/aac/kx;)V
/*     */     //   422: goto -> 429
/*     */     //   425: invokestatic a : (Ljava/lang/IllegalArgumentException;)Ljava/lang/IllegalArgumentException;
/*     */     //   428: athrow
/*     */     //   429: lload #17
/*     */     //   431: lload #15
/*     */     //   433: lsub
/*     */     //   434: dup2
/*     */     //   435: lstore #19
/*     */     //   437: lconst_1
/*     */     //   438: lcmp
/*     */     //   439: ifle -> 462
/*     */     //   442: aload_0
/*     */     //   443: lload #21
/*     */     //   445: lload #19
/*     */     //   447: lsub
/*     */     //   448: lload #21
/*     */     //   450: aload #5
/*     */     //   452: invokestatic c : ([[IJJLme/konsolas/aac/kx;)V
/*     */     //   455: goto -> 462
/*     */     //   458: invokestatic a : (Ljava/lang/IllegalArgumentException;)Ljava/lang/IllegalArgumentException;
/*     */     //   461: athrow
/*     */     //   462: return
/*     */     // Line number table:
/*     */     //   Java source line number -> byte code offset
/*     */     //   #339	-> 0
/*     */     //   #163	-> 5
/*     */     //   #160	-> 14
/*     */     //   #315	-> 22
/*     */     //   #81	-> 27
/*     */     //   #194	-> 37
/*     */     //   #19	-> 46
/*     */     //   #355	-> 49
/*     */     //   #288	-> 54
/*     */     //   #74	-> 63
/*     */     //   #22	-> 71
/*     */     //   #422	-> 95
/*     */     //   #141	-> 115
/*     */     //   #66	-> 139
/*     */     //   #256	-> 153
/*     */     //   #164	-> 161
/*     */     //   #109	-> 177
/*     */     //   #289	-> 206
/*     */     //   #105	-> 231
/*     */     //   #310	-> 240
/*     */     //   #73	-> 269
/*     */     //   #150	-> 294
/*     */     //   #203	-> 303
/*     */     //   #87	-> 318
/*     */     //   #12	-> 339
/*     */     //   #16	-> 342
/*     */     //   #116	-> 356
/*     */     //   #366	-> 368
/*     */     //   #262	-> 385
/*     */     //   #405	-> 398
/*     */     //   #72	-> 429
/*     */     //   #221	-> 462
/*     */     // Exception table:
/*     */     //   from	to	target	type
/*     */     //   5	23	23	java/lang/IllegalArgumentException
/*     */     //   203	211	214	java/lang/IllegalArgumentException
/*     */     //   266	274	277	java/lang/IllegalArgumentException
/*     */     //   303	314	314	java/lang/IllegalArgumentException
/*     */     //   406	422	425	java/lang/IllegalArgumentException
/*     */     //   437	455	458	java/lang/IllegalArgumentException
/*     */   }
/*     */   
/*     */   @Deprecated
/*     */   public static boolean a(int[][] paramArrayOfint1, int[][] paramArrayOfint2) {
/*     */     return k.a(paramArrayOfint1, paramArrayOfint2);
/*     */   }
/*     */   
/*     */   public static void b(int[][] paramArrayOfint1, int[][] paramArrayOfint2) {
/*     */     a(paramArrayOfint1, paramArrayOfint2, 0L, k.a(paramArrayOfint1));
/*     */   }
/*     */   
/*     */   @Deprecated
/*     */   public static int[][] a(int[][] paramArrayOfint, long paramLong1, long paramLong2) {
/*     */     return k.c(paramArrayOfint, paramLong1, paramLong2);
/*     */   }
/*     */   
/*     */   public static void b(int[][] paramArrayOfint) {
/*     */     g(paramArrayOfint, 0L, k.a(paramArrayOfint));
/*     */   }
/*     */   
/*     */   public static long a(int[][] paramArrayOfint, long paramLong1, long paramLong2, int paramInt, kx paramkx) {
/*     */     paramLong2--;
/*     */     for (; paramLong1 <= paramLong2; i = k.a(paramArrayOfint, l)) {
/*     */       int i;
/*     */       long l = paramLong1 + paramLong2 >>> 1L;
/*     */     } 
/*     */     return -(paramLong1 + 1L);
/*     */   }
/*     */   
/*     */   private static void b(int[][] paramArrayOfint1, int[][] paramArrayOfint2, long paramLong1, long paramLong2) {
/*     */     long l;
/*     */     for (l = paramLong1; l < paramLong2 - 1L; ) {
/*     */       continue;
/*     */       l1 = l;
/*     */       l2 = l + 1L;
/*     */       while (true) {
/*     */         if (l1 != l) {
/*     */           int i = k.a(paramArrayOfint1, l);
/*     */           k.c(paramArrayOfint1, l, k.a(paramArrayOfint1, l1));
/*     */         } 
/*     */         break;
/*     */       } 
/*     */       l++;
/*     */     } 
/*     */   }
/*     */   
/*     */   public static int[][] a(long paramLong) {
/*     */     try {
/*     */       if (paramLong == 0L)
/*     */         return h; 
/*     */     } catch (IllegalArgumentException illegalArgumentException) {
/*     */       throw a(null);
/*     */     } 
/*     */     k.a(paramLong);
/*     */     int i = (int)(paramLong + 134217727L >>> 27L);
/*     */     int[][] arrayOfInt = new int[i][];
/*     */     int j = (int)(paramLong & 0x7FFFFFFL);
/*     */     if (j != 0) {
/*     */       byte b = 0;
/*     */       try {
/*     */         while (b < i - 1) {
/*     */           arrayOfInt[b] = new int[134217728];
/*     */           b++;
/*     */         } 
/*     */       } catch (IllegalArgumentException illegalArgumentException) {
/*     */         throw a(null);
/*     */       } 
/*     */       arrayOfInt[i - 1] = new int[j];
/*     */     } else {
/*     */       byte b = 0;
/*     */       try {
/*     */         while (b < i) {
/*     */           arrayOfInt[b] = new int[134217728];
/*     */           b++;
/*     */         } 
/*     */       } catch (IllegalArgumentException illegalArgumentException) {
/*     */         throw a(null);
/*     */       } 
/*     */     } 
/*     */     return arrayOfInt;
/*     */   }
/*     */   
/*     */   @Deprecated
/*     */   public static void a(int[][] paramArrayOfint, long paramLong1, long paramLong2, int paramInt) {
/*     */     k.a(paramArrayOfint, paramLong1, paramLong2, paramInt);
/*     */   }
/*     */   
/*     */   public static void a(long[][] paramArrayOflong, int[][] paramArrayOfint1, int[][] paramArrayOfint2, long paramLong1, long paramLong2, boolean paramBoolean) {
/*     */     // Byte code:
/*     */     //   0: lload #5
/*     */     //   2: lload_3
/*     */     //   3: lsub
/*     */     //   4: ldc2_w 1024
/*     */     //   7: lcmp
/*     */     //   8: ifge -> 25
/*     */     //   11: aload_0
/*     */     //   12: aload_1
/*     */     //   13: aload_2
/*     */     //   14: lload_3
/*     */     //   15: lload #5
/*     */     //   17: invokestatic a : ([[J[[I[[IJJ)V
/*     */     //   20: return
/*     */     //   21: invokestatic a : (Ljava/lang/IllegalArgumentException;)Ljava/lang/IllegalArgumentException;
/*     */     //   24: athrow
/*     */     //   25: iconst_2
/*     */     //   26: istore #8
/*     */     //   28: bipush #7
/*     */     //   30: istore #9
/*     */     //   32: sipush #1786
/*     */     //   35: istore #10
/*     */     //   37: iconst_0
/*     */     //   38: istore #11
/*     */     //   40: sipush #1786
/*     */     //   43: newarray long
/*     */     //   45: astore #12
/*     */     //   47: sipush #1786
/*     */     //   50: newarray long
/*     */     //   52: astore #13
/*     */     //   54: sipush #1786
/*     */     //   57: newarray int
/*     */     //   59: astore #14
/*     */     //   61: aload #12
/*     */     //   63: iload #11
/*     */     //   65: lload_3
/*     */     //   66: lastore
/*     */     //   67: aload #13
/*     */     //   69: iload #11
/*     */     //   71: lload #5
/*     */     //   73: lload_3
/*     */     //   74: lsub
/*     */     //   75: lastore
/*     */     //   76: aload #14
/*     */     //   78: iload #11
/*     */     //   80: iinc #11, 1
/*     */     //   83: iconst_0
/*     */     //   84: iastore
/*     */     //   85: sipush #256
/*     */     //   88: newarray long
/*     */     //   90: astore #15
/*     */     //   92: sipush #256
/*     */     //   95: newarray long
/*     */     //   97: astore #16
/*     */     //   99: iload #7
/*     */     //   101: ifeq -> 118
/*     */     //   104: aload_0
/*     */     //   105: invokestatic a : ([[J)J
/*     */     //   108: invokestatic a : (J)[[J
/*     */     //   111: goto -> 119
/*     */     //   114: invokestatic a : (Ljava/lang/IllegalArgumentException;)Ljava/lang/IllegalArgumentException;
/*     */     //   117: athrow
/*     */     //   118: aconst_null
/*     */     //   119: astore #17
/*     */     //   121: iload #11
/*     */     //   123: ifle -> 801
/*     */     //   126: aload #12
/*     */     //   128: iinc #11, -1
/*     */     //   131: iload #11
/*     */     //   133: laload
/*     */     //   134: lstore #18
/*     */     //   136: aload #13
/*     */     //   138: iload #11
/*     */     //   140: laload
/*     */     //   141: lstore #20
/*     */     //   143: aload #14
/*     */     //   145: iload #11
/*     */     //   147: iaload
/*     */     //   148: istore #22
/*     */     //   150: iload #22
/*     */     //   152: iconst_4
/*     */     //   153: irem
/*     */     //   154: ifne -> 167
/*     */     //   157: sipush #128
/*     */     //   160: goto -> 168
/*     */     //   163: invokestatic a : (Ljava/lang/IllegalArgumentException;)Ljava/lang/IllegalArgumentException;
/*     */     //   166: athrow
/*     */     //   167: iconst_0
/*     */     //   168: istore #23
/*     */     //   170: iload #22
/*     */     //   172: iconst_4
/*     */     //   173: if_icmpge -> 184
/*     */     //   176: aload_1
/*     */     //   177: goto -> 185
/*     */     //   180: invokestatic a : (Ljava/lang/IllegalArgumentException;)Ljava/lang/IllegalArgumentException;
/*     */     //   183: athrow
/*     */     //   184: aload_2
/*     */     //   185: astore #24
/*     */     //   187: iconst_3
/*     */     //   188: iload #22
/*     */     //   190: iconst_4
/*     */     //   191: irem
/*     */     //   192: isub
/*     */     //   193: bipush #8
/*     */     //   195: imul
/*     */     //   196: istore #25
/*     */     //   198: lload #18
/*     */     //   200: lload #20
/*     */     //   202: ladd
/*     */     //   203: lstore #26
/*     */     //   205: lload #26
/*     */     //   207: dup2
/*     */     //   208: lconst_1
/*     */     //   209: lsub
/*     */     //   210: lstore #26
/*     */     //   212: lload #18
/*     */     //   214: lcmp
/*     */     //   215: ifeq -> 253
/*     */     //   218: aload #15
/*     */     //   220: aload #24
/*     */     //   222: aload_0
/*     */     //   223: lload #26
/*     */     //   225: invokestatic a : ([[JJ)J
/*     */     //   228: invokestatic a : ([[IJ)I
/*     */     //   231: iload #25
/*     */     //   233: iushr
/*     */     //   234: sipush #255
/*     */     //   237: iand
/*     */     //   238: iload #23
/*     */     //   240: ixor
/*     */     //   241: dup2
/*     */     //   242: laload
/*     */     //   243: lconst_1
/*     */     //   244: ladd
/*     */     //   245: lastore
/*     */     //   246: goto -> 205
/*     */     //   249: invokestatic a : (Ljava/lang/IllegalArgumentException;)Ljava/lang/IllegalArgumentException;
/*     */     //   252: athrow
/*     */     //   253: iconst_m1
/*     */     //   254: istore #26
/*     */     //   256: iload #7
/*     */     //   258: ifeq -> 269
/*     */     //   261: lconst_0
/*     */     //   262: goto -> 271
/*     */     //   265: invokestatic a : (Ljava/lang/IllegalArgumentException;)Ljava/lang/IllegalArgumentException;
/*     */     //   268: athrow
/*     */     //   269: lload #18
/*     */     //   271: lstore #27
/*     */     //   273: iconst_0
/*     */     //   274: istore #29
/*     */     //   276: iload #29
/*     */     //   278: sipush #256
/*     */     //   281: if_icmpge -> 327
/*     */     //   284: aload #15
/*     */     //   286: iload #29
/*     */     //   288: laload
/*     */     //   289: lconst_0
/*     */     //   290: lcmp
/*     */     //   291: ifeq -> 305
/*     */     //   294: goto -> 301
/*     */     //   297: invokestatic a : (Ljava/lang/IllegalArgumentException;)Ljava/lang/IllegalArgumentException;
/*     */     //   300: athrow
/*     */     //   301: iload #29
/*     */     //   303: istore #26
/*     */     //   305: aload #16
/*     */     //   307: iload #29
/*     */     //   309: lload #27
/*     */     //   311: aload #15
/*     */     //   313: iload #29
/*     */     //   315: laload
/*     */     //   316: ladd
/*     */     //   317: dup2
/*     */     //   318: lstore #27
/*     */     //   320: lastore
/*     */     //   321: iinc #29, 1
/*     */     //   324: goto -> 276
/*     */     //   327: iload #7
/*     */     //   329: ifeq -> 552
/*     */     //   332: lload #18
/*     */     //   334: lload #20
/*     */     //   336: ladd
/*     */     //   337: lstore #29
/*     */     //   339: lload #29
/*     */     //   341: dup2
/*     */     //   342: lconst_1
/*     */     //   343: lsub
/*     */     //   344: lstore #29
/*     */     //   346: lload #18
/*     */     //   348: lcmp
/*     */     //   349: ifeq -> 399
/*     */     //   352: aload #17
/*     */     //   354: aload #16
/*     */     //   356: aload #24
/*     */     //   358: aload_0
/*     */     //   359: lload #29
/*     */     //   361: invokestatic a : ([[JJ)J
/*     */     //   364: invokestatic a : ([[IJ)I
/*     */     //   367: iload #25
/*     */     //   369: iushr
/*     */     //   370: sipush #255
/*     */     //   373: iand
/*     */     //   374: iload #23
/*     */     //   376: ixor
/*     */     //   377: dup2
/*     */     //   378: laload
/*     */     //   379: lconst_1
/*     */     //   380: lsub
/*     */     //   381: dup2_x2
/*     */     //   382: lastore
/*     */     //   383: aload_0
/*     */     //   384: lload #29
/*     */     //   386: invokestatic a : ([[JJ)J
/*     */     //   389: invokestatic d : ([[JJJ)V
/*     */     //   392: goto -> 339
/*     */     //   395: invokestatic a : (Ljava/lang/IllegalArgumentException;)Ljava/lang/IllegalArgumentException;
/*     */     //   398: athrow
/*     */     //   399: aload #17
/*     */     //   401: lconst_0
/*     */     //   402: aload_0
/*     */     //   403: lload #18
/*     */     //   405: lload #20
/*     */     //   407: invokestatic a : ([[JJ[[JJJ)V
/*     */     //   410: lload #18
/*     */     //   412: lstore #27
/*     */     //   414: iconst_0
/*     */     //   415: istore #29
/*     */     //   417: iload #29
/*     */     //   419: sipush #256
/*     */     //   422: if_icmpge -> 543
/*     */     //   425: iload #22
/*     */     //   427: bipush #7
/*     */     //   429: if_icmpge -> 527
/*     */     //   432: goto -> 439
/*     */     //   435: invokestatic a : (Ljava/lang/IllegalArgumentException;)Ljava/lang/IllegalArgumentException;
/*     */     //   438: athrow
/*     */     //   439: aload #15
/*     */     //   441: iload #29
/*     */     //   443: laload
/*     */     //   444: lconst_1
/*     */     //   445: lcmp
/*     */     //   446: ifle -> 527
/*     */     //   449: goto -> 456
/*     */     //   452: invokestatic a : (Ljava/lang/IllegalArgumentException;)Ljava/lang/IllegalArgumentException;
/*     */     //   455: athrow
/*     */     //   456: aload #15
/*     */     //   458: iload #29
/*     */     //   460: laload
/*     */     //   461: ldc2_w 1024
/*     */     //   464: lcmp
/*     */     //   465: ifge -> 498
/*     */     //   468: goto -> 475
/*     */     //   471: invokestatic a : (Ljava/lang/IllegalArgumentException;)Ljava/lang/IllegalArgumentException;
/*     */     //   474: athrow
/*     */     //   475: aload_0
/*     */     //   476: aload_1
/*     */     //   477: aload_2
/*     */     //   478: lload #27
/*     */     //   480: lload #27
/*     */     //   482: aload #15
/*     */     //   484: iload #29
/*     */     //   486: laload
/*     */     //   487: ladd
/*     */     //   488: invokestatic a : ([[J[[I[[IJJ)V
/*     */     //   491: goto -> 527
/*     */     //   494: invokestatic a : (Ljava/lang/IllegalArgumentException;)Ljava/lang/IllegalArgumentException;
/*     */     //   497: athrow
/*     */     //   498: aload #12
/*     */     //   500: iload #11
/*     */     //   502: lload #27
/*     */     //   504: lastore
/*     */     //   505: aload #13
/*     */     //   507: iload #11
/*     */     //   509: aload #15
/*     */     //   511: iload #29
/*     */     //   513: laload
/*     */     //   514: lastore
/*     */     //   515: aload #14
/*     */     //   517: iload #11
/*     */     //   519: iinc #11, 1
/*     */     //   522: iload #22
/*     */     //   524: iconst_1
/*     */     //   525: iadd
/*     */     //   526: iastore
/*     */     //   527: lload #27
/*     */     //   529: aload #15
/*     */     //   531: iload #29
/*     */     //   533: laload
/*     */     //   534: ladd
/*     */     //   535: lstore #27
/*     */     //   537: iinc #29, 1
/*     */     //   540: goto -> 417
/*     */     //   543: aload #15
/*     */     //   545: lconst_0
/*     */     //   546: invokestatic fill : ([JJ)V
/*     */     //   549: goto -> 798
/*     */     //   552: lload #18
/*     */     //   554: lload #20
/*     */     //   556: ladd
/*     */     //   557: aload #15
/*     */     //   559: iload #26
/*     */     //   561: laload
/*     */     //   562: lsub
/*     */     //   563: lstore #29
/*     */     //   565: iconst_m1
/*     */     //   566: istore #31
/*     */     //   568: lload #18
/*     */     //   570: lstore #32
/*     */     //   572: lload #32
/*     */     //   574: lload #29
/*     */     //   576: lcmp
/*     */     //   577: ifgt -> 798
/*     */     //   580: aload_0
/*     */     //   581: lload #32
/*     */     //   583: invokestatic a : ([[JJ)J
/*     */     //   586: lstore #36
/*     */     //   588: aload #24
/*     */     //   590: lload #36
/*     */     //   592: invokestatic a : ([[IJ)I
/*     */     //   595: iload #25
/*     */     //   597: iushr
/*     */     //   598: sipush #255
/*     */     //   601: iand
/*     */     //   602: iload #23
/*     */     //   604: ixor
/*     */     //   605: istore #31
/*     */     //   607: lload #32
/*     */     //   609: lload #29
/*     */     //   611: lcmp
/*     */     //   612: ifge -> 684
/*     */     //   615: aload #16
/*     */     //   617: iload #31
/*     */     //   619: dup2
/*     */     //   620: laload
/*     */     //   621: lconst_1
/*     */     //   622: lsub
/*     */     //   623: dup2_x2
/*     */     //   624: lastore
/*     */     //   625: dup2
/*     */     //   626: lstore #34
/*     */     //   628: lload #32
/*     */     //   630: lcmp
/*     */     //   631: ifle -> 676
/*     */     //   634: lload #36
/*     */     //   636: lstore #38
/*     */     //   638: aload_0
/*     */     //   639: lload #34
/*     */     //   641: invokestatic a : ([[JJ)J
/*     */     //   644: lstore #36
/*     */     //   646: aload_0
/*     */     //   647: lload #34
/*     */     //   649: lload #38
/*     */     //   651: invokestatic d : ([[JJJ)V
/*     */     //   654: aload #24
/*     */     //   656: lload #36
/*     */     //   658: invokestatic a : ([[IJ)I
/*     */     //   661: iload #25
/*     */     //   663: iushr
/*     */     //   664: sipush #255
/*     */     //   667: iand
/*     */     //   668: iload #23
/*     */     //   670: ixor
/*     */     //   671: istore #31
/*     */     //   673: goto -> 615
/*     */     //   676: aload_0
/*     */     //   677: lload #32
/*     */     //   679: lload #36
/*     */     //   681: invokestatic d : ([[JJJ)V
/*     */     //   684: iload #22
/*     */     //   686: bipush #7
/*     */     //   688: if_icmpge -> 779
/*     */     //   691: aload #15
/*     */     //   693: iload #31
/*     */     //   695: laload
/*     */     //   696: lconst_1
/*     */     //   697: lcmp
/*     */     //   698: ifle -> 779
/*     */     //   701: goto -> 708
/*     */     //   704: invokestatic a : (Ljava/lang/IllegalArgumentException;)Ljava/lang/IllegalArgumentException;
/*     */     //   707: athrow
/*     */     //   708: aload #15
/*     */     //   710: iload #31
/*     */     //   712: laload
/*     */     //   713: ldc2_w 1024
/*     */     //   716: lcmp
/*     */     //   717: ifge -> 750
/*     */     //   720: goto -> 727
/*     */     //   723: invokestatic a : (Ljava/lang/IllegalArgumentException;)Ljava/lang/IllegalArgumentException;
/*     */     //   726: athrow
/*     */     //   727: aload_0
/*     */     //   728: aload_1
/*     */     //   729: aload_2
/*     */     //   730: lload #32
/*     */     //   732: lload #32
/*     */     //   734: aload #15
/*     */     //   736: iload #31
/*     */     //   738: laload
/*     */     //   739: ladd
/*     */     //   740: invokestatic a : ([[J[[I[[IJJ)V
/*     */     //   743: goto -> 779
/*     */     //   746: invokestatic a : (Ljava/lang/IllegalArgumentException;)Ljava/lang/IllegalArgumentException;
/*     */     //   749: athrow
/*     */     //   750: aload #12
/*     */     //   752: iload #11
/*     */     //   754: lload #32
/*     */     //   756: lastore
/*     */     //   757: aload #13
/*     */     //   759: iload #11
/*     */     //   761: aload #15
/*     */     //   763: iload #31
/*     */     //   765: laload
/*     */     //   766: lastore
/*     */     //   767: aload #14
/*     */     //   769: iload #11
/*     */     //   771: iinc #11, 1
/*     */     //   774: iload #22
/*     */     //   776: iconst_1
/*     */     //   777: iadd
/*     */     //   778: iastore
/*     */     //   779: lload #32
/*     */     //   781: aload #15
/*     */     //   783: iload #31
/*     */     //   785: laload
/*     */     //   786: ladd
/*     */     //   787: lstore #32
/*     */     //   789: aload #15
/*     */     //   791: iload #31
/*     */     //   793: lconst_0
/*     */     //   794: lastore
/*     */     //   795: goto -> 572
/*     */     //   798: goto -> 121
/*     */     //   801: return
/*     */     // Line number table:
/*     */     //   Java source line number -> byte code offset
/*     */     //   #412	-> 0
/*     */     //   #363	-> 11
/*     */     //   #391	-> 20
/*     */     //   #8	-> 25
/*     */     //   #129	-> 28
/*     */     //   #291	-> 32
/*     */     //   #219	-> 37
/*     */     //   #404	-> 40
/*     */     //   #113	-> 47
/*     */     //   #377	-> 54
/*     */     //   #394	-> 61
/*     */     //   #68	-> 67
/*     */     //   #316	-> 76
/*     */     //   #284	-> 85
/*     */     //   #65	-> 92
/*     */     //   #123	-> 99
/*     */     //   #61	-> 121
/*     */     //   #45	-> 126
/*     */     //   #397	-> 136
/*     */     //   #78	-> 143
/*     */     //   #214	-> 150
/*     */     //   #388	-> 170
/*     */     //   #282	-> 187
/*     */     //   #17	-> 198
/*     */     //   #71	-> 253
/*     */     //   #1	-> 256
/*     */     //   #204	-> 273
/*     */     //   #213	-> 284
/*     */     //   #144	-> 305
/*     */     //   #101	-> 321
/*     */     //   #90	-> 327
/*     */     //   #9	-> 332
/*     */     //   #307	-> 399
/*     */     //   #417	-> 410
/*     */     //   #158	-> 414
/*     */     //   #41	-> 425
/*     */     //   #313	-> 456
/*     */     //   #143	-> 498
/*     */     //   #283	-> 505
/*     */     //   #48	-> 515
/*     */     //   #11	-> 527
/*     */     //   #14	-> 537
/*     */     //   #253	-> 543
/*     */     //   #119	-> 552
/*     */     //   #211	-> 565
/*     */     //   #232	-> 568
/*     */     //   #241	-> 580
/*     */     //   #54	-> 588
/*     */     //   #216	-> 607
/*     */     //   #157	-> 615
/*     */     //   #222	-> 634
/*     */     //   #229	-> 638
/*     */     //   #177	-> 646
/*     */     //   #199	-> 654
/*     */     //   #125	-> 673
/*     */     //   #252	-> 676
/*     */     //   #111	-> 684
/*     */     //   #400	-> 708
/*     */     //   #407	-> 750
/*     */     //   #126	-> 757
/*     */     //   #28	-> 767
/*     */     //   #358	-> 779
/*     */     //   #7	-> 798
/*     */     //   #127	-> 801
/*     */     // Exception table:
/*     */     //   from	to	target	type
/*     */     //   0	21	21	java/lang/IllegalArgumentException
/*     */     //   99	114	114	java/lang/IllegalArgumentException
/*     */     //   150	163	163	java/lang/IllegalArgumentException
/*     */     //   170	180	180	java/lang/IllegalArgumentException
/*     */     //   212	249	249	java/lang/IllegalArgumentException
/*     */     //   256	265	265	java/lang/IllegalArgumentException
/*     */     //   276	294	297	java/lang/IllegalArgumentException
/*     */     //   346	395	395	java/lang/IllegalArgumentException
/*     */     //   417	432	435	java/lang/IllegalArgumentException
/*     */     //   425	449	452	java/lang/IllegalArgumentException
/*     */     //   439	468	471	java/lang/IllegalArgumentException
/*     */     //   456	494	494	java/lang/IllegalArgumentException
/*     */     //   684	701	704	java/lang/IllegalArgumentException
/*     */     //   691	720	723	java/lang/IllegalArgumentException
/*     */     //   708	746	746	java/lang/IllegalArgumentException
/*     */   }
/*     */   
/*     */   public static void c(int[][] paramArrayOfint, long paramLong1, long paramLong2) {
/*     */     // Byte code:
/*     */     //   0: iconst_3
/*     */     //   1: istore #5
/*     */     //   3: sipush #766
/*     */     //   6: istore #6
/*     */     //   8: sipush #766
/*     */     //   11: newarray long
/*     */     //   13: astore #7
/*     */     //   15: iconst_0
/*     */     //   16: istore #8
/*     */     //   18: sipush #766
/*     */     //   21: newarray long
/*     */     //   23: astore #9
/*     */     //   25: iconst_0
/*     */     //   26: istore #10
/*     */     //   28: sipush #766
/*     */     //   31: newarray int
/*     */     //   33: astore #11
/*     */     //   35: iconst_0
/*     */     //   36: istore #12
/*     */     //   38: aload #7
/*     */     //   40: iload #8
/*     */     //   42: iinc #8, 1
/*     */     //   45: lload_1
/*     */     //   46: lastore
/*     */     //   47: aload #9
/*     */     //   49: iload #10
/*     */     //   51: iinc #10, 1
/*     */     //   54: lload_3
/*     */     //   55: lload_1
/*     */     //   56: lsub
/*     */     //   57: lastore
/*     */     //   58: aload #11
/*     */     //   60: iload #12
/*     */     //   62: iinc #12, 1
/*     */     //   65: iconst_0
/*     */     //   66: iastore
/*     */     //   67: sipush #256
/*     */     //   70: newarray long
/*     */     //   72: astore #13
/*     */     //   74: sipush #256
/*     */     //   77: newarray long
/*     */     //   79: astore #14
/*     */     //   81: lload_3
/*     */     //   82: lload_1
/*     */     //   83: lsub
/*     */     //   84: invokestatic a : (J)[[B
/*     */     //   87: astore #15
/*     */     //   89: iload #8
/*     */     //   91: ifle -> 563
/*     */     //   94: aload #7
/*     */     //   96: iinc #8, -1
/*     */     //   99: iload #8
/*     */     //   101: laload
/*     */     //   102: lstore #16
/*     */     //   104: aload #9
/*     */     //   106: iinc #10, -1
/*     */     //   109: iload #10
/*     */     //   111: laload
/*     */     //   112: lstore #18
/*     */     //   114: aload #11
/*     */     //   116: iinc #12, -1
/*     */     //   119: iload #12
/*     */     //   121: iaload
/*     */     //   122: istore #20
/*     */     //   124: iload #20
/*     */     //   126: iconst_4
/*     */     //   127: irem
/*     */     //   128: ifne -> 141
/*     */     //   131: sipush #128
/*     */     //   134: goto -> 142
/*     */     //   137: invokestatic a : (Ljava/lang/IllegalArgumentException;)Ljava/lang/IllegalArgumentException;
/*     */     //   140: athrow
/*     */     //   141: iconst_0
/*     */     //   142: istore #21
/*     */     //   144: lload #18
/*     */     //   146: ldc2_w 40
/*     */     //   149: lcmp
/*     */     //   150: ifge -> 171
/*     */     //   153: aload_0
/*     */     //   154: lload #16
/*     */     //   156: lload #16
/*     */     //   158: lload #18
/*     */     //   160: ladd
/*     */     //   161: invokestatic f : ([[IJJ)V
/*     */     //   164: goto -> 89
/*     */     //   167: invokestatic a : (Ljava/lang/IllegalArgumentException;)Ljava/lang/IllegalArgumentException;
/*     */     //   170: athrow
/*     */     //   171: iconst_3
/*     */     //   172: iload #20
/*     */     //   174: iconst_4
/*     */     //   175: irem
/*     */     //   176: isub
/*     */     //   177: bipush #8
/*     */     //   179: imul
/*     */     //   180: istore #22
/*     */     //   182: lload #18
/*     */     //   184: lstore #23
/*     */     //   186: lload #23
/*     */     //   188: dup2
/*     */     //   189: lconst_1
/*     */     //   190: lsub
/*     */     //   191: lstore #23
/*     */     //   193: lconst_0
/*     */     //   194: lcmp
/*     */     //   195: ifeq -> 232
/*     */     //   198: aload #15
/*     */     //   200: lload #23
/*     */     //   202: aload_0
/*     */     //   203: lload #16
/*     */     //   205: lload #23
/*     */     //   207: ladd
/*     */     //   208: invokestatic a : ([[IJ)I
/*     */     //   211: iload #22
/*     */     //   213: iushr
/*     */     //   214: sipush #255
/*     */     //   217: iand
/*     */     //   218: iload #21
/*     */     //   220: ixor
/*     */     //   221: i2b
/*     */     //   222: invokestatic b : ([[BJB)V
/*     */     //   225: goto -> 186
/*     */     //   228: invokestatic a : (Ljava/lang/IllegalArgumentException;)Ljava/lang/IllegalArgumentException;
/*     */     //   231: athrow
/*     */     //   232: lload #18
/*     */     //   234: lstore #23
/*     */     //   236: lload #23
/*     */     //   238: dup2
/*     */     //   239: lconst_1
/*     */     //   240: lsub
/*     */     //   241: lstore #23
/*     */     //   243: lconst_0
/*     */     //   244: lcmp
/*     */     //   245: ifeq -> 273
/*     */     //   248: aload #13
/*     */     //   250: aload #15
/*     */     //   252: lload #23
/*     */     //   254: invokestatic a : ([[BJ)B
/*     */     //   257: sipush #255
/*     */     //   260: iand
/*     */     //   261: dup2
/*     */     //   262: laload
/*     */     //   263: lconst_1
/*     */     //   264: ladd
/*     */     //   265: lastore
/*     */     //   266: goto -> 236
/*     */     //   269: invokestatic a : (Ljava/lang/IllegalArgumentException;)Ljava/lang/IllegalArgumentException;
/*     */     //   272: athrow
/*     */     //   273: iconst_m1
/*     */     //   274: istore #23
/*     */     //   276: lconst_0
/*     */     //   277: lstore #24
/*     */     //   279: iconst_0
/*     */     //   280: istore #26
/*     */     //   282: iload #26
/*     */     //   284: sipush #256
/*     */     //   287: if_icmpge -> 401
/*     */     //   290: aload #13
/*     */     //   292: iload #26
/*     */     //   294: laload
/*     */     //   295: lconst_0
/*     */     //   296: lcmp
/*     */     //   297: ifeq -> 379
/*     */     //   300: goto -> 307
/*     */     //   303: invokestatic a : (Ljava/lang/IllegalArgumentException;)Ljava/lang/IllegalArgumentException;
/*     */     //   306: athrow
/*     */     //   307: iload #26
/*     */     //   309: istore #23
/*     */     //   311: iload #20
/*     */     //   313: iconst_3
/*     */     //   314: if_icmpge -> 379
/*     */     //   317: aload #13
/*     */     //   319: iload #26
/*     */     //   321: laload
/*     */     //   322: lconst_1
/*     */     //   323: lcmp
/*     */     //   324: ifle -> 379
/*     */     //   327: goto -> 334
/*     */     //   330: invokestatic a : (Ljava/lang/IllegalArgumentException;)Ljava/lang/IllegalArgumentException;
/*     */     //   333: athrow
/*     */     //   334: aload #7
/*     */     //   336: iload #8
/*     */     //   338: iinc #8, 1
/*     */     //   341: lload #24
/*     */     //   343: lload #16
/*     */     //   345: ladd
/*     */     //   346: lastore
/*     */     //   347: aload #9
/*     */     //   349: iload #10
/*     */     //   351: iinc #10, 1
/*     */     //   354: aload #13
/*     */     //   356: iload #26
/*     */     //   358: laload
/*     */     //   359: lastore
/*     */     //   360: aload #11
/*     */     //   362: iload #12
/*     */     //   364: iinc #12, 1
/*     */     //   367: iload #20
/*     */     //   369: iconst_1
/*     */     //   370: iadd
/*     */     //   371: iastore
/*     */     //   372: goto -> 379
/*     */     //   375: invokestatic a : (Ljava/lang/IllegalArgumentException;)Ljava/lang/IllegalArgumentException;
/*     */     //   378: athrow
/*     */     //   379: aload #14
/*     */     //   381: iload #26
/*     */     //   383: lload #24
/*     */     //   385: aload #13
/*     */     //   387: iload #26
/*     */     //   389: laload
/*     */     //   390: ladd
/*     */     //   391: dup2
/*     */     //   392: lstore #24
/*     */     //   394: lastore
/*     */     //   395: iinc #26, 1
/*     */     //   398: goto -> 282
/*     */     //   401: lload #18
/*     */     //   403: aload #13
/*     */     //   405: iload #23
/*     */     //   407: laload
/*     */     //   408: lsub
/*     */     //   409: lstore #26
/*     */     //   411: aload #13
/*     */     //   413: iload #23
/*     */     //   415: lconst_0
/*     */     //   416: lastore
/*     */     //   417: iconst_m1
/*     */     //   418: istore #28
/*     */     //   420: lconst_0
/*     */     //   421: lstore #29
/*     */     //   423: lload #29
/*     */     //   425: lload #26
/*     */     //   427: lcmp
/*     */     //   428: ifge -> 560
/*     */     //   431: aload_0
/*     */     //   432: lload #29
/*     */     //   434: lload #16
/*     */     //   436: ladd
/*     */     //   437: invokestatic a : ([[IJ)I
/*     */     //   440: istore #33
/*     */     //   442: aload #15
/*     */     //   444: lload #29
/*     */     //   446: invokestatic a : ([[BJ)B
/*     */     //   449: sipush #255
/*     */     //   452: iand
/*     */     //   453: istore #28
/*     */     //   455: aload #14
/*     */     //   457: iload #28
/*     */     //   459: dup2
/*     */     //   460: laload
/*     */     //   461: lconst_1
/*     */     //   462: lsub
/*     */     //   463: dup2_x2
/*     */     //   464: lastore
/*     */     //   465: dup2
/*     */     //   466: lstore #31
/*     */     //   468: lload #29
/*     */     //   470: lcmp
/*     */     //   471: ifle -> 530
/*     */     //   474: iload #33
/*     */     //   476: istore #34
/*     */     //   478: iload #28
/*     */     //   480: istore #35
/*     */     //   482: aload_0
/*     */     //   483: lload #31
/*     */     //   485: lload #16
/*     */     //   487: ladd
/*     */     //   488: invokestatic a : ([[IJ)I
/*     */     //   491: istore #33
/*     */     //   493: aload #15
/*     */     //   495: lload #31
/*     */     //   497: invokestatic a : ([[BJ)B
/*     */     //   500: sipush #255
/*     */     //   503: iand
/*     */     //   504: istore #28
/*     */     //   506: aload_0
/*     */     //   507: lload #31
/*     */     //   509: lload #16
/*     */     //   511: ladd
/*     */     //   512: iload #34
/*     */     //   514: invokestatic c : ([[IJI)V
/*     */     //   517: aload #15
/*     */     //   519: lload #31
/*     */     //   521: iload #35
/*     */     //   523: i2b
/*     */     //   524: invokestatic b : ([[BJB)V
/*     */     //   527: goto -> 455
/*     */     //   530: aload_0
/*     */     //   531: lload #29
/*     */     //   533: lload #16
/*     */     //   535: ladd
/*     */     //   536: iload #33
/*     */     //   538: invokestatic c : ([[IJI)V
/*     */     //   541: lload #29
/*     */     //   543: aload #13
/*     */     //   545: iload #28
/*     */     //   547: laload
/*     */     //   548: ladd
/*     */     //   549: lstore #29
/*     */     //   551: aload #13
/*     */     //   553: iload #28
/*     */     //   555: lconst_0
/*     */     //   556: lastore
/*     */     //   557: goto -> 423
/*     */     //   560: goto -> 89
/*     */     //   563: return
/*     */     // Line number table:
/*     */     //   Java source line number -> byte code offset
/*     */     //   #416	-> 0
/*     */     //   #236	-> 3
/*     */     //   #15	-> 8
/*     */     //   #206	-> 15
/*     */     //   #64	-> 18
/*     */     //   #258	-> 25
/*     */     //   #134	-> 28
/*     */     //   #107	-> 35
/*     */     //   #311	-> 38
/*     */     //   #330	-> 47
/*     */     //   #42	-> 58
/*     */     //   #386	-> 67
/*     */     //   #273	-> 74
/*     */     //   #21	-> 81
/*     */     //   #26	-> 89
/*     */     //   #79	-> 94
/*     */     //   #387	-> 104
/*     */     //   #53	-> 114
/*     */     //   #354	-> 124
/*     */     //   #132	-> 144
/*     */     //   #200	-> 153
/*     */     //   #385	-> 164
/*     */     //   #294	-> 171
/*     */     //   #151	-> 182
/*     */     //   #419	-> 232
/*     */     //   #335	-> 273
/*     */     //   #238	-> 276
/*     */     //   #389	-> 279
/*     */     //   #168	-> 290
/*     */     //   #205	-> 307
/*     */     //   #59	-> 311
/*     */     //   #425	-> 334
/*     */     //   #368	-> 347
/*     */     //   #230	-> 360
/*     */     //   #240	-> 379
/*     */     //   #182	-> 395
/*     */     //   #6	-> 401
/*     */     //   #122	-> 411
/*     */     //   #193	-> 417
/*     */     //   #250	-> 420
/*     */     //   #342	-> 431
/*     */     //   #281	-> 442
/*     */     //   #255	-> 455
/*     */     //   #341	-> 474
/*     */     //   #118	-> 478
/*     */     //   #44	-> 482
/*     */     //   #35	-> 493
/*     */     //   #427	-> 506
/*     */     //   #188	-> 517
/*     */     //   #130	-> 527
/*     */     //   #146	-> 530
/*     */     //   #302	-> 541
/*     */     //   #308	-> 560
/*     */     //   #55	-> 563
/*     */     // Exception table:
/*     */     //   from	to	target	type
/*     */     //   124	137	137	java/lang/IllegalArgumentException
/*     */     //   144	167	167	java/lang/IllegalArgumentException
/*     */     //   193	228	228	java/lang/IllegalArgumentException
/*     */     //   243	269	269	java/lang/IllegalArgumentException
/*     */     //   282	300	303	java/lang/IllegalArgumentException
/*     */     //   311	327	330	java/lang/IllegalArgumentException
/*     */     //   317	372	375	java/lang/IllegalArgumentException
/*     */   }
/*     */   
/*     */   private static IllegalArgumentException a(IllegalArgumentException paramIllegalArgumentException) {
/*     */     return paramIllegalArgumentException;
/*     */   } }


/* Location:              C:\Users\BukkitBypass\Desktop\MatrixAC\AAC\AAC-spigot-5.2.0.jar!\me\konsolas\aac\hr.class
 * Java compiler version: 8 (52.0)
 * JD-Core Version:       1.1.3
 */