/*    */ package me.konsolas.aac;public final class i8 {
/*    */   public i8(le paramle, int paramInt, String paramString) {
/*  3 */     this.a = paramle;
/*    */ 
/*    */ 
/*    */ 
/*    */ 
/*    */ 
/*    */ 
/*    */ 
/*    */ 
/*    */ 
/*    */ 
/*    */ 
/*    */ 
/*    */ 
/*    */ 
/*    */ 
/*    */ 
/*    */ 
/*    */ 
/*    */ 
/*    */ 
/*    */     
/* 25 */     this.c = paramInt;
/*    */ 
/*    */ 
/*    */ 
/*    */ 
/*    */ 
/*    */ 
/*    */ 
/*    */ 
/*    */ 
/*    */     
/* 36 */     this.f = paramString;
/*    */   }
/*    */   
/*    */   public static final int e = 307;
/*    */   public static final int b = 308;
/*    */   public static final int d = 100;
/*    */   public final le a;
/*    */   public final int c;
/*    */   public final String f;
/*    */   private static final long g = nc.a(6460255938994205082L, 8454257341097136748L, MethodHandles.lookup().lookupClass()).a(189968656268107L);
/*    */   private static final String[] h;
/*    */   private static final String[] i;
/*    */   private static final Map j = new HashMap<>(13);
/*    */   
/*    */   public static i8 a(String paramString, long paramLong) {
/*    */     // Byte code:
/*    */     //   0: getstatic me/konsolas/aac/i8.g : J
/*    */     //   3: lload_1
/*    */     //   4: lxor
/*    */     //   5: lstore_1
/*    */     //   6: ldc2_w -6584585546552624207
/*    */     //   9: lload_1
/*    */     //   10: <illegal opcode> w : (JJ)Z
/*    */     //   15: istore_3
/*    */     //   16: aload_0
/*    */     //   17: sipush #8692
/*    */     //   20: ldc2_w 5658924622675443275
/*    */     //   23: lload_1
/*    */     //   24: lxor
/*    */     //   25: <illegal opcode> n : (IJ)Ljava/lang/String;
/*    */     //   30: invokevirtual startsWith : (Ljava/lang/String;)Z
/*    */     //   33: iload_3
/*    */     //   34: ifne -> 367
/*    */     //   37: ifeq -> 337
/*    */     //   40: goto -> 53
/*    */     //   43: ldc2_w -6553778050885493585
/*    */     //   46: lload_1
/*    */     //   47: <illegal opcode> w : (Ljava/lang/NumberFormatException;JJ)Ljava/lang/NumberFormatException;
/*    */     //   52: athrow
/*    */     //   53: aload_0
/*    */     //   54: invokevirtual length : ()I
/*    */     //   57: bipush #9
/*    */     //   59: iload_3
/*    */     //   60: lload_1
/*    */     //   61: lconst_0
/*    */     //   62: lcmp
/*    */     //   63: ifle -> 120
/*    */     //   66: ifne -> 119
/*    */     //   69: goto -> 82
/*    */     //   72: ldc2_w -6553778050885493585
/*    */     //   75: lload_1
/*    */     //   76: <illegal opcode> w : (Ljava/lang/NumberFormatException;JJ)Ljava/lang/NumberFormatException;
/*    */     //   81: athrow
/*    */     //   82: if_icmplt -> 139
/*    */     //   85: goto -> 98
/*    */     //   88: ldc2_w -6553778050885493585
/*    */     //   91: lload_1
/*    */     //   92: <illegal opcode> w : (Ljava/lang/NumberFormatException;JJ)Ljava/lang/NumberFormatException;
/*    */     //   97: athrow
/*    */     //   98: aload_0
/*    */     //   99: bipush #8
/*    */     //   101: invokevirtual charAt : (I)C
/*    */     //   104: bipush #32
/*    */     //   106: goto -> 119
/*    */     //   109: ldc2_w -6553778050885493585
/*    */     //   112: lload_1
/*    */     //   113: <illegal opcode> w : (Ljava/lang/NumberFormatException;JJ)Ljava/lang/NumberFormatException;
/*    */     //   118: athrow
/*    */     //   119: iload_3
/*    */     //   120: ifne -> 195
/*    */     //   123: if_icmpeq -> 187
/*    */     //   126: goto -> 139
/*    */     //   129: ldc2_w -6553778050885493585
/*    */     //   132: lload_1
/*    */     //   133: <illegal opcode> w : (Ljava/lang/NumberFormatException;JJ)Ljava/lang/NumberFormatException;
/*    */     //   138: athrow
/*    */     //   139: new java/net/ProtocolException
/*    */     //   142: dup
/*    */     //   143: new java/lang/StringBuilder
/*    */     //   146: dup
/*    */     //   147: invokespecial <init> : ()V
/*    */     //   150: sipush #11119
/*    */     //   153: ldc2_w 2660660078047360210
/*    */     //   156: lload_1
/*    */     //   157: lxor
/*    */     //   158: <illegal opcode> n : (IJ)Ljava/lang/String;
/*    */     //   163: invokevirtual append : (Ljava/lang/String;)Ljava/lang/StringBuilder;
/*    */     //   166: aload_0
/*    */     //   167: invokevirtual append : (Ljava/lang/String;)Ljava/lang/StringBuilder;
/*    */     //   170: invokevirtual toString : ()Ljava/lang/String;
/*    */     //   173: invokespecial <init> : (Ljava/lang/String;)V
/*    */     //   176: athrow
/*    */     //   177: ldc2_w -6553778050885493585
/*    */     //   180: lload_1
/*    */     //   181: <illegal opcode> w : (Ljava/lang/NumberFormatException;JJ)Ljava/lang/NumberFormatException;
/*    */     //   186: athrow
/*    */     //   187: aload_0
/*    */     //   188: bipush #7
/*    */     //   190: invokevirtual charAt : (I)C
/*    */     //   193: bipush #48
/*    */     //   195: isub
/*    */     //   196: istore #6
/*    */     //   198: bipush #9
/*    */     //   200: istore #4
/*    */     //   202: iload #6
/*    */     //   204: iload_3
/*    */     //   205: lload_1
/*    */     //   206: lconst_0
/*    */     //   207: lcmp
/*    */     //   208: iflt -> 261
/*    */     //   211: ifne -> 260
/*    */     //   214: ifne -> 245
/*    */     //   217: goto -> 230
/*    */     //   220: ldc2_w -6553778050885493585
/*    */     //   223: lload_1
/*    */     //   224: <illegal opcode> w : (Ljava/lang/NumberFormatException;JJ)Ljava/lang/NumberFormatException;
/*    */     //   229: athrow
/*    */     //   230: getstatic me/konsolas/aac/le.HTTP_1_0 : Lme/konsolas/aac/le;
/*    */     //   233: astore #5
/*    */     //   235: iload_3
/*    */     //   236: lload_1
/*    */     //   237: lconst_0
/*    */     //   238: lcmp
/*    */     //   239: ifle -> 328
/*    */     //   242: ifeq -> 327
/*    */     //   245: iload #6
/*    */     //   247: goto -> 260
/*    */     //   250: ldc2_w -6553778050885493585
/*    */     //   253: lload_1
/*    */     //   254: <illegal opcode> w : (Ljava/lang/NumberFormatException;JJ)Ljava/lang/NumberFormatException;
/*    */     //   259: athrow
/*    */     //   260: iconst_1
/*    */     //   261: if_icmpne -> 279
/*    */     //   264: getstatic me/konsolas/aac/le.HTTP_1_1 : Lme/konsolas/aac/le;
/*    */     //   267: astore #5
/*    */     //   269: iload_3
/*    */     //   270: lload_1
/*    */     //   271: lconst_0
/*    */     //   272: lcmp
/*    */     //   273: iflt -> 328
/*    */     //   276: ifeq -> 327
/*    */     //   279: new java/net/ProtocolException
/*    */     //   282: dup
/*    */     //   283: new java/lang/StringBuilder
/*    */     //   286: dup
/*    */     //   287: invokespecial <init> : ()V
/*    */     //   290: sipush #20292
/*    */     //   293: ldc2_w 1485727079902318840
/*    */     //   296: lload_1
/*    */     //   297: lxor
/*    */     //   298: <illegal opcode> n : (IJ)Ljava/lang/String;
/*    */     //   303: invokevirtual append : (Ljava/lang/String;)Ljava/lang/StringBuilder;
/*    */     //   306: aload_0
/*    */     //   307: invokevirtual append : (Ljava/lang/String;)Ljava/lang/StringBuilder;
/*    */     //   310: invokevirtual toString : ()Ljava/lang/String;
/*    */     //   313: invokespecial <init> : (Ljava/lang/String;)V
/*    */     //   316: athrow
/*    */     //   317: ldc2_w -6553778050885493585
/*    */     //   320: lload_1
/*    */     //   321: <illegal opcode> w : (Ljava/lang/NumberFormatException;JJ)Ljava/lang/NumberFormatException;
/*    */     //   326: athrow
/*    */     //   327: iload_3
/*    */     //   328: lload_1
/*    */     //   329: lconst_0
/*    */     //   330: lcmp
/*    */     //   331: iflt -> 440
/*    */     //   334: ifeq -> 436
/*    */     //   337: aload_0
/*    */     //   338: sipush #29051
/*    */     //   341: ldc2_w 2365525269454401217
/*    */     //   344: lload_1
/*    */     //   345: lxor
/*    */     //   346: <illegal opcode> n : (IJ)Ljava/lang/String;
/*    */     //   351: invokevirtual startsWith : (Ljava/lang/String;)Z
/*    */     //   354: goto -> 367
/*    */     //   357: ldc2_w -6553778050885493585
/*    */     //   360: lload_1
/*    */     //   361: <illegal opcode> w : (Ljava/lang/NumberFormatException;JJ)Ljava/lang/NumberFormatException;
/*    */     //   366: athrow
/*    */     //   367: ifeq -> 388
/*    */     //   370: getstatic me/konsolas/aac/le.HTTP_1_0 : Lme/konsolas/aac/le;
/*    */     //   373: astore #5
/*    */     //   375: iconst_4
/*    */     //   376: istore #4
/*    */     //   378: iload_3
/*    */     //   379: lload_1
/*    */     //   380: lconst_0
/*    */     //   381: lcmp
/*    */     //   382: ifle -> 440
/*    */     //   385: ifeq -> 436
/*    */     //   388: new java/net/ProtocolException
/*    */     //   391: dup
/*    */     //   392: new java/lang/StringBuilder
/*    */     //   395: dup
/*    */     //   396: invokespecial <init> : ()V
/*    */     //   399: sipush #20292
/*    */     //   402: ldc2_w 1485727079902318840
/*    */     //   405: lload_1
/*    */     //   406: lxor
/*    */     //   407: <illegal opcode> n : (IJ)Ljava/lang/String;
/*    */     //   412: invokevirtual append : (Ljava/lang/String;)Ljava/lang/StringBuilder;
/*    */     //   415: aload_0
/*    */     //   416: invokevirtual append : (Ljava/lang/String;)Ljava/lang/StringBuilder;
/*    */     //   419: invokevirtual toString : ()Ljava/lang/String;
/*    */     //   422: invokespecial <init> : (Ljava/lang/String;)V
/*    */     //   425: athrow
/*    */     //   426: ldc2_w -6553778050885493585
/*    */     //   429: lload_1
/*    */     //   430: <illegal opcode> w : (Ljava/lang/NumberFormatException;JJ)Ljava/lang/NumberFormatException;
/*    */     //   435: athrow
/*    */     //   436: aload_0
/*    */     //   437: invokevirtual length : ()I
/*    */     //   440: iload_3
/*    */     //   441: lload_1
/*    */     //   442: lconst_0
/*    */     //   443: lcmp
/*    */     //   444: iflt -> 454
/*    */     //   447: ifne -> 531
/*    */     //   450: iload #4
/*    */     //   452: iconst_3
/*    */     //   453: iadd
/*    */     //   454: if_icmpge -> 518
/*    */     //   457: goto -> 470
/*    */     //   460: ldc2_w -6553778050885493585
/*    */     //   463: lload_1
/*    */     //   464: <illegal opcode> w : (Ljava/lang/NumberFormatException;JJ)Ljava/lang/NumberFormatException;
/*    */     //   469: athrow
/*    */     //   470: new java/net/ProtocolException
/*    */     //   473: dup
/*    */     //   474: new java/lang/StringBuilder
/*    */     //   477: dup
/*    */     //   478: invokespecial <init> : ()V
/*    */     //   481: sipush #20292
/*    */     //   484: ldc2_w 1485727079902318840
/*    */     //   487: lload_1
/*    */     //   488: lxor
/*    */     //   489: <illegal opcode> n : (IJ)Ljava/lang/String;
/*    */     //   494: invokevirtual append : (Ljava/lang/String;)Ljava/lang/StringBuilder;
/*    */     //   497: aload_0
/*    */     //   498: invokevirtual append : (Ljava/lang/String;)Ljava/lang/StringBuilder;
/*    */     //   501: invokevirtual toString : ()Ljava/lang/String;
/*    */     //   504: invokespecial <init> : (Ljava/lang/String;)V
/*    */     //   507: athrow
/*    */     //   508: ldc2_w -6553778050885493585
/*    */     //   511: lload_1
/*    */     //   512: <illegal opcode> w : (Ljava/lang/NumberFormatException;JJ)Ljava/lang/NumberFormatException;
/*    */     //   517: athrow
/*    */     //   518: aload_0
/*    */     //   519: iload #4
/*    */     //   521: iload #4
/*    */     //   523: iconst_3
/*    */     //   524: iadd
/*    */     //   525: invokevirtual substring : (II)Ljava/lang/String;
/*    */     //   528: invokestatic parseInt : (Ljava/lang/String;)I
/*    */     //   531: istore #6
/*    */     //   533: goto -> 576
/*    */     //   536: astore #7
/*    */     //   538: new java/net/ProtocolException
/*    */     //   541: dup
/*    */     //   542: new java/lang/StringBuilder
/*    */     //   545: dup
/*    */     //   546: invokespecial <init> : ()V
/*    */     //   549: sipush #20292
/*    */     //   552: ldc2_w 1485727079902318840
/*    */     //   555: lload_1
/*    */     //   556: lxor
/*    */     //   557: <illegal opcode> n : (IJ)Ljava/lang/String;
/*    */     //   562: invokevirtual append : (Ljava/lang/String;)Ljava/lang/StringBuilder;
/*    */     //   565: aload_0
/*    */     //   566: invokevirtual append : (Ljava/lang/String;)Ljava/lang/StringBuilder;
/*    */     //   569: invokevirtual toString : ()Ljava/lang/String;
/*    */     //   572: invokespecial <init> : (Ljava/lang/String;)V
/*    */     //   575: athrow
/*    */     //   576: ldc ''
/*    */     //   578: astore #7
/*    */     //   580: aload_0
/*    */     //   581: invokevirtual length : ()I
/*    */     //   584: iload #4
/*    */     //   586: iconst_3
/*    */     //   587: iadd
/*    */     //   588: lload_1
/*    */     //   589: lconst_0
/*    */     //   590: lcmp
/*    */     //   591: ifle -> 660
/*    */     //   594: iload_3
/*    */     //   595: ifne -> 660
/*    */     //   598: if_icmple -> 721
/*    */     //   601: goto -> 614
/*    */     //   604: ldc2_w -6553778050885493585
/*    */     //   607: lload_1
/*    */     //   608: <illegal opcode> w : (Ljava/lang/NumberFormatException;JJ)Ljava/lang/NumberFormatException;
/*    */     //   613: athrow
/*    */     //   614: aload_0
/*    */     //   615: lload_1
/*    */     //   616: lconst_0
/*    */     //   617: lcmp
/*    */     //   618: ifle -> 719
/*    */     //   621: iload #4
/*    */     //   623: iconst_3
/*    */     //   624: iadd
/*    */     //   625: iload_3
/*    */     //   626: ifne -> 716
/*    */     //   629: goto -> 642
/*    */     //   632: ldc2_w -6553778050885493585
/*    */     //   635: lload_1
/*    */     //   636: <illegal opcode> w : (Ljava/lang/NumberFormatException;JJ)Ljava/lang/NumberFormatException;
/*    */     //   641: athrow
/*    */     //   642: invokevirtual charAt : (I)C
/*    */     //   645: bipush #32
/*    */     //   647: goto -> 660
/*    */     //   650: ldc2_w -6553778050885493585
/*    */     //   653: lload_1
/*    */     //   654: <illegal opcode> w : (Ljava/lang/NumberFormatException;JJ)Ljava/lang/NumberFormatException;
/*    */     //   659: athrow
/*    */     //   660: if_icmpeq -> 711
/*    */     //   663: new java/net/ProtocolException
/*    */     //   666: dup
/*    */     //   667: new java/lang/StringBuilder
/*    */     //   670: dup
/*    */     //   671: invokespecial <init> : ()V
/*    */     //   674: sipush #20292
/*    */     //   677: ldc2_w 1485727079902318840
/*    */     //   680: lload_1
/*    */     //   681: lxor
/*    */     //   682: <illegal opcode> n : (IJ)Ljava/lang/String;
/*    */     //   687: invokevirtual append : (Ljava/lang/String;)Ljava/lang/StringBuilder;
/*    */     //   690: aload_0
/*    */     //   691: invokevirtual append : (Ljava/lang/String;)Ljava/lang/StringBuilder;
/*    */     //   694: invokevirtual toString : ()Ljava/lang/String;
/*    */     //   697: invokespecial <init> : (Ljava/lang/String;)V
/*    */     //   700: athrow
/*    */     //   701: ldc2_w -6553778050885493585
/*    */     //   704: lload_1
/*    */     //   705: <illegal opcode> w : (Ljava/lang/NumberFormatException;JJ)Ljava/lang/NumberFormatException;
/*    */     //   710: athrow
/*    */     //   711: aload_0
/*    */     //   712: iload #4
/*    */     //   714: iconst_4
/*    */     //   715: iadd
/*    */     //   716: invokevirtual substring : (I)Ljava/lang/String;
/*    */     //   719: astore #7
/*    */     //   721: new me/konsolas/aac/i8
/*    */     //   724: dup
/*    */     //   725: aload #5
/*    */     //   727: iload #6
/*    */     //   729: aload #7
/*    */     //   731: invokespecial <init> : (Lme/konsolas/aac/le;ILjava/lang/String;)V
/*    */     //   734: areturn
/*    */     // Line number table:
/*    */     //   Java source line number -> byte code offset
/*    */     //   #9	-> 16
/*    */     //   #16	-> 53
/*    */     //   #4	-> 139
/*    */     //   #29	-> 187
/*    */     //   #35	-> 198
/*    */     //   #7	-> 202
/*    */     //   #26	-> 230
/*    */     //   #31	-> 245
/*    */     //   #27	-> 264
/*    */     //   #33	-> 279
/*    */     //   #5	-> 327
/*    */     //   #38	-> 370
/*    */     //   #21	-> 375
/*    */     //   #18	-> 388
/*    */     //   #17	-> 436
/*    */     //   #34	-> 470
/*    */     //   #1	-> 518
/*    */     //   #23	-> 533
/*    */     //   #20	-> 536
/*    */     //   #10	-> 538
/*    */     //   #13	-> 576
/*    */     //   #37	-> 580
/*    */     //   #19	-> 614
/*    */     //   #15	-> 663
/*    */     //   #2	-> 711
/*    */     //   #22	-> 721
/*    */     // Exception table:
/*    */     //   from	to	target	type
/*    */     //   16	40	43	java/lang/NumberFormatException
/*    */     //   37	69	72	java/lang/NumberFormatException
/*    */     //   53	85	88	java/lang/NumberFormatException
/*    */     //   82	106	109	java/lang/NumberFormatException
/*    */     //   119	126	129	java/lang/NumberFormatException
/*    */     //   123	177	177	java/lang/NumberFormatException
/*    */     //   202	217	220	java/lang/NumberFormatException
/*    */     //   235	247	250	java/lang/NumberFormatException
/*    */     //   269	317	317	java/lang/NumberFormatException
/*    */     //   327	354	357	java/lang/NumberFormatException
/*    */     //   378	426	426	java/lang/NumberFormatException
/*    */     //   436	457	460	java/lang/NumberFormatException
/*    */     //   450	508	508	java/lang/NumberFormatException
/*    */     //   518	533	536	java/lang/NumberFormatException
/*    */     //   580	601	604	java/lang/NumberFormatException
/*    */     //   598	629	632	java/lang/NumberFormatException
/*    */     //   614	647	650	java/lang/NumberFormatException
/*    */     //   660	701	701	java/lang/NumberFormatException
/*    */   }
/*    */   
/*    */   public String toString() {
/*    */     // Byte code:
/*    */     //   0: getstatic me/konsolas/aac/i8.g : J
/*    */     //   3: ldc2_w 45849005118983
/*    */     //   6: lxor
/*    */     //   7: lstore_1
/*    */     //   8: ldc2_w 7946476819627635048
/*    */     //   11: lload_1
/*    */     //   12: <illegal opcode> w : (JJ)Z
/*    */     //   17: new java/lang/StringBuilder
/*    */     //   20: dup
/*    */     //   21: invokespecial <init> : ()V
/*    */     //   24: astore #4
/*    */     //   26: istore_3
/*    */     //   27: aload #4
/*    */     //   29: aload_0
/*    */     //   30: getfield a : Lme/konsolas/aac/le;
/*    */     //   33: getstatic me/konsolas/aac/le.HTTP_1_0 : Lme/konsolas/aac/le;
/*    */     //   36: if_acmpne -> 65
/*    */     //   39: sipush #28453
/*    */     //   42: ldc2_w 8436038667095046727
/*    */     //   45: lload_1
/*    */     //   46: lxor
/*    */     //   47: <illegal opcode> n : (IJ)Ljava/lang/String;
/*    */     //   52: goto -> 78
/*    */     //   55: ldc2_w 8058374955701573238
/*    */     //   58: lload_1
/*    */     //   59: <illegal opcode> w : (Ljava/lang/NumberFormatException;JJ)Ljava/lang/NumberFormatException;
/*    */     //   64: athrow
/*    */     //   65: sipush #14580
/*    */     //   68: ldc2_w 5268466090342034835
/*    */     //   71: lload_1
/*    */     //   72: lxor
/*    */     //   73: <illegal opcode> n : (IJ)Ljava/lang/String;
/*    */     //   78: invokevirtual append : (Ljava/lang/String;)Ljava/lang/StringBuilder;
/*    */     //   81: pop
/*    */     //   82: aload #4
/*    */     //   84: bipush #32
/*    */     //   86: invokevirtual append : (C)Ljava/lang/StringBuilder;
/*    */     //   89: aload_0
/*    */     //   90: getfield c : I
/*    */     //   93: invokevirtual append : (I)Ljava/lang/StringBuilder;
/*    */     //   96: pop
/*    */     //   97: aload_0
/*    */     //   98: getfield f : Ljava/lang/String;
/*    */     //   101: iload_3
/*    */     //   102: ifne -> 154
/*    */     //   105: ifnull -> 149
/*    */     //   108: goto -> 121
/*    */     //   111: ldc2_w 8058374955701573238
/*    */     //   114: lload_1
/*    */     //   115: <illegal opcode> w : (Ljava/lang/NumberFormatException;JJ)Ljava/lang/NumberFormatException;
/*    */     //   120: athrow
/*    */     //   121: aload #4
/*    */     //   123: bipush #32
/*    */     //   125: invokevirtual append : (C)Ljava/lang/StringBuilder;
/*    */     //   128: aload_0
/*    */     //   129: getfield f : Ljava/lang/String;
/*    */     //   132: invokevirtual append : (Ljava/lang/String;)Ljava/lang/StringBuilder;
/*    */     //   135: pop
/*    */     //   136: goto -> 149
/*    */     //   139: ldc2_w 8058374955701573238
/*    */     //   142: lload_1
/*    */     //   143: <illegal opcode> w : (Ljava/lang/NumberFormatException;JJ)Ljava/lang/NumberFormatException;
/*    */     //   148: athrow
/*    */     //   149: aload #4
/*    */     //   151: invokevirtual toString : ()Ljava/lang/String;
/*    */     //   154: areturn
/*    */     // Line number table:
/*    */     //   Java source line number -> byte code offset
/*    */     //   #24	-> 17
/*    */     //   #8	-> 27
/*    */     //   #12	-> 82
/*    */     //   #14	-> 97
/*    */     //   #6	-> 121
/*    */     //   #32	-> 149
/*    */     // Exception table:
/*    */     //   from	to	target	type
/*    */     //   27	55	55	java/lang/NumberFormatException
/*    */     //   78	108	111	java/lang/NumberFormatException
/*    */     //   105	136	139	java/lang/NumberFormatException
/*    */   }
/*    */   
/*    */   public static i8 a(H paramH) {
/*    */     return new i8(paramH.a(), paramH.a(), paramH.a());
/*    */   }
/*    */   
/*    */   static {
/*    */     long l = g ^ 0x39C788845895L;
/*    */     "䔧쵘탸뷤梽༑阖ஜ軅囪᣾喎苈炧䣟ݶἫ왲ꡐ姉毀".toCharArray()[1] = (char)("䔧쵘탸뷤梽༑阖ஜ軅囪᣾喎苈炧䣟ݶἫ왲ꡐ姉毀".toCharArray()[1] ^ 0x414C);
/*    */     "ዯꔁ?ૹ".toCharArray()[2] = (char)("ዯꔁ?ૹ".toCharArray()[2] ^ 0x1186);
/*    */     (new byte[8])[0] = (byte)(int)(l >>> 56L);
/*    */     for (byte b1 = 1; b1 < 8; b1++)
/*    */       (new byte[8])[b1] = (byte)(int)(l << b1 * 8 >>> 56L); 
/*    */     Cipher cipher;
/*    */     (cipher = Cipher.getInstance(da$gx.U("䔧쵘탸뷤梽༑阖ஜ軅囪᣾喎苈炧䣟ݶἫ왲ꡐ姉毀".toCharArray(), (short)11847, true, true))).init(2, SecretKeyFactory.getInstance(da$gx.U("ዯꔁ?ૹ".toCharArray(), (short)27431, false, false)).generateSecret(new DESKeySpec(new byte[8])), new IvParameterSpec(new byte[8]));
/*    */     String[] arrayOfString = new String[6];
/*    */     boolean bool = false;
/*    */     "簺컑⋝繊ﮤ겐ៃꬌљ肏鯏ꅐ륭쫵昷⤘㫘阑ﳀᶏ⫀碀郀ᦈ⽯鈱?譞ᠡﭕ줊뇌횁䚊ဩ엻鰸꘧㮀揗汃睯謯亦诞ᨻ휢挟揫ᚂ꡵ൊ☖?떶⽾ឭ핖䇌㢅꘺䒎挼ﱓ?䑷彀㌊묠ꂾ?룢৶ᜰ먣鍏ﴐ玗㢔츣ݿƫꝘ揍퓝왱溷铸立볋㿩뺘꿛褙섘긿ꑣ㏀贇૗篵걙餘ޅꠎ层ꏋ驼媜뱶盻♸Ⰹ剄ꏴߪ敵젼帳ᛧ鋦乬섗⁈趛靈픞魗鈡䘸ཥܣ㓫⸜⠨킺쿠↞鍫㷕".toCharArray()[30] = (char)("簺컑⋝繊ﮤ겐ៃꬌљ肏鯏ꅐ륭쫵昷⤘㫘阑ﳀᶏ⫀碀郀ᦈ⽯鈱?譞ᠡﭕ줊뇌횁䚊ဩ엻鰸꘧㮀揗汃睯謯亦诞ᨻ휢挟揫ᚂ꡵ൊ☖?떶⽾ឭ핖䇌㢅꘺䒎挼ﱓ?䑷彀㌊묠ꂾ?룢৶ᜰ먣鍏ﴐ玗㢔츣ݿƫꝘ揍퓝왱溷铸立볋㿩뺘꿛褙섘긿ꑣ㏀贇૗篵걙餘ޅꠎ层ꏋ驼媜뱶盻♸Ⰹ剄ꏴߪ敵젼帳ᛧ鋦乬섗⁈趛靈픞魗鈡䘸ཥܣ㓫⸜⠨킺쿠↞鍫㷕".toCharArray()[30] ^ 0x5A4B);
/*    */     String str;
/*    */     int i = (str = da$gx.U("簺컑⋝繊ﮤ겐ៃꬌљ肏鯏ꅐ륭쫵昷⤘㫘阑ﳀᶏ⫀碀郀ᦈ⽯鈱?譞ᠡﭕ줊뇌횁䚊ဩ엻鰸꘧㮀揗汃睯謯亦诞ᨻ휢挟揫ᚂ꡵ൊ☖?떶⽾ឭ핖䇌㢅꘺䒎挼ﱓ?䑷彀㌊묠ꂾ?룢৶ᜰ먣鍏ﴐ玗㢔츣ݿƫꝘ揍퓝왱溷铸立볋㿩뺘꿛褙섘긿ꑣ㏀贇૗篵걙餘ޅꠎ层ꏋ驼媜뱶盻♸Ⰹ剄ꏴߪ敵젼帳ᛧ鋦乬섗⁈趛靈픞魗鈡䘸ཥܣ㓫⸜⠨킺쿠↞鍫㷕".toCharArray(), (short)9244, false, true)).length();
/*    */     byte b2 = 32;
/*    */     byte b = -1;
/*    */     while (true);
/*    */   }
/*    */   
/*    */   private static NumberFormatException a(NumberFormatException paramNumberFormatException) {
/*    */     return paramNumberFormatException;
/*    */   }
/*    */   
/*    */   private static String a(byte[] paramArrayOfbyte) {
/*    */     byte b1 = 0;
/*    */     int i;
/*    */     char[] arrayOfChar = new char[i = paramArrayOfbyte.length];
/*    */     for (byte b2 = 0; b2 < i; b2++) {
/*    */       int j;
/*    */       if ((j = 0xFF & paramArrayOfbyte[b2]) < 192) {
/*    */         arrayOfChar[b1++] = (char)j;
/*    */       } else if (j < 224) {
/*    */         char c = (char)((char)(j & 0x1F) << 6);
/*    */         j = paramArrayOfbyte[++b2];
/*    */         c = (char)(c | (char)(j & 0x3F));
/*    */         arrayOfChar[b1++] = c;
/*    */       } else if (b2 < i - 2) {
/*    */         char c = (char)((char)(j & 0xF) << 12);
/*    */         j = paramArrayOfbyte[++b2];
/*    */         c = (char)(c | (char)(j & 0x3F) << 6);
/*    */         j = paramArrayOfbyte[++b2];
/*    */         c = (char)(c | (char)(j & 0x3F));
/*    */         arrayOfChar[b1++] = c;
/*    */       } 
/*    */     } 
/*    */     return new String(arrayOfChar, 0, b1);
/*    */   }
/*    */   
/*    */   private static String a(int paramInt, long paramLong) {
/*    */     int i = paramInt ^ (int)(paramLong & 0x7FFFL) ^ 0x7A55;
/*    */     if (i[i] == null) {
/*    */       Object[] arrayOfObject;
/*    */       try {
/*    */         Long long_ = Long.valueOf(Thread.currentThread().getId());
/*    */         arrayOfObject = (Object[])j.get(long_);
/*    */         if (arrayOfObject == null) {
/*    */           arrayOfObject = new Object[3];
/*    */           "湡ร簖䭌ꎭ褷斳䎿≐᪃齻㲤㙢注杢㽐".toCharArray()[17] = (char)("湡ร簖䭌ꎭ褷斳䎿≐᪃齻㲤㙢注杢㽐".toCharArray()[17] ^ 0x3805);
/*    */           arrayOfObject[0] = Cipher.getInstance(fW$gy.A("湡ร簖䭌ꎭ褷斳䎿≐᪃齻㲤㙢注杢㽐".toCharArray(), (short)18905, true, 1));
/*    */           "樷ﮑﱜ㾰".toCharArray()[1] = (char)("樷ﮑﱜ㾰".toCharArray()[1] ^ 0x454B);
/*    */           arrayOfObject[1] = SecretKeyFactory.getInstance(fW$gy.A("樷ﮑﱜ㾰".toCharArray(), (short)14677, true, 3));
/*    */           arrayOfObject[2] = new IvParameterSpec(new byte[8]);
/*    */           j.put(long_, arrayOfObject);
/*    */         } 
/*    */       } catch (Exception exception) {
/*    */         "썚ﻻ拞쫕✼Β๡蒭ⱡឃ龉᜺๱개握薤䤖ᰖ".toCharArray()[0] = (char)("썚ﻻ拞쫕✼Β๡蒭ⱡឃ龉᜺๱개握薤䤖ᰖ".toCharArray()[0] ^ 0x3B7);
/*    */         throw new RuntimeException(fW$gy.A("썚ﻻ拞쫕✼Β๡蒭ⱡឃ龉᜺๱개握薤䤖ᰖ".toCharArray(), (short)14073, true, 2), exception);
/*    */       } 
/*    */       byte[] arrayOfByte1 = new byte[8];
/*    */       arrayOfByte1[0] = (byte)(int)(paramLong >>> 56L);
/*    */       for (byte b = 1; b < 8; b++)
/*    */         arrayOfByte1[b] = (byte)(int)(paramLong << b * 8 >>> 56L); 
/*    */       DESKeySpec dESKeySpec = new DESKeySpec(arrayOfByte1);
/*    */       SecretKey secretKey = ((SecretKeyFactory)arrayOfObject[1]).generateSecret(dESKeySpec);
/*    */       ((Cipher)arrayOfObject[0]).init(2, secretKey, (IvParameterSpec)arrayOfObject[2]);
/*    */       "ဍ؝庾塑댡።黮蔄犛鉆堺".toCharArray()[7] = (char)("ဍ؝庾塑댡።黮蔄犛鉆堺".toCharArray()[7] ^ 0x15EA);
/*    */       byte[] arrayOfByte2 = h[i].getBytes(fW$gy.A("ဍ؝庾塑댡።黮蔄犛鉆堺".toCharArray(), (short)8056, false, 5));
/*    */       i[i] = a(((Cipher)arrayOfObject[0]).doFinal(arrayOfByte2));
/*    */     } 
/*    */     return i[i];
/*    */   }
/*    */   
/*    */   private static Object a(MethodHandles.Lookup paramLookup, MutableCallSite paramMutableCallSite, String paramString, Object[] paramArrayOfObject) {
/*    */     int i = ((Integer)paramArrayOfObject[0]).intValue();
/*    */     long l = ((Long)paramArrayOfObject[1]).longValue();
/*    */     String str = a(i, l);
/*    */     MethodHandle methodHandle = MethodHandles.constant(String.class, str);
/*    */     paramMutableCallSite.setTarget(MethodHandles.dropArguments(methodHandle, 0, new Class[] { int.class, long.class }));
/*    */     return str;
/*    */   }
/*    */   
/*    */   private static CallSite a(MethodHandles.Lookup paramLookup, String paramString, MethodType paramMethodType) {
/*    */     // Byte code:
/*    */     //   0: new java/lang/invoke/MutableCallSite
/*    */     //   3: dup
/*    */     //   4: aload_2
/*    */     //   5: invokespecial <init> : (Ljava/lang/invoke/MethodType;)V
/*    */     //   8: astore_3
/*    */     //   9: aload_3
/*    */     //   10: ldc_w
/*    */     //   13: ldc_w [Ljava/lang/Object;
/*    */     //   16: aload_2
/*    */     //   17: invokevirtual parameterCount : ()I
/*    */     //   20: invokevirtual asCollector : (Ljava/lang/Class;I)Ljava/lang/invoke/MethodHandle;
/*    */     //   23: iconst_0
/*    */     //   24: iconst_3
/*    */     //   25: anewarray java/lang/Object
/*    */     //   28: dup
/*    */     //   29: iconst_0
/*    */     //   30: aload_0
/*    */     //   31: aastore
/*    */     //   32: dup
/*    */     //   33: iconst_1
/*    */     //   34: aload_3
/*    */     //   35: aastore
/*    */     //   36: dup
/*    */     //   37: iconst_2
/*    */     //   38: aload_1
/*    */     //   39: aastore
/*    */     //   40: invokestatic insertArguments : (Ljava/lang/invoke/MethodHandle;I[Ljava/lang/Object;)Ljava/lang/invoke/MethodHandle;
/*    */     //   43: aload_2
/*    */     //   44: invokestatic explicitCastArguments : (Ljava/lang/invoke/MethodHandle;Ljava/lang/invoke/MethodType;)Ljava/lang/invoke/MethodHandle;
/*    */     //   47: invokevirtual setTarget : (Ljava/lang/invoke/MethodHandle;)V
/*    */     //   50: goto -> 171
/*    */     //   53: astore #4
/*    */     //   55: new java/lang/RuntimeException
/*    */     //   58: dup
/*    */     //   59: new java/lang/StringBuilder
/*    */     //   62: dup
/*    */     //   63: invokespecial <init> : ()V
/*    */     //   66: ldc_w '혯愍ꇍ쭑걃⌭쒩栳៻䊅?늼?쳊耛л騀剑'
/*    */     //   69: invokevirtual toCharArray : ()[C
/*    */     //   72: dup
/*    */     //   73: dup
/*    */     //   74: bipush #14
/*    */     //   76: dup_x1
/*    */     //   77: caload
/*    */     //   78: sipush #3525
/*    */     //   81: ixor
/*    */     //   82: i2c
/*    */     //   83: castore
/*    */     //   84: sipush #28842
/*    */     //   87: iconst_3
/*    */     //   88: iconst_4
/*    */     //   89: invokestatic H : (Ljava/lang/Object;SBB)Ljava/lang/String;
/*    */     //   92: invokevirtual append : (Ljava/lang/String;)Ljava/lang/StringBuilder;
/*    */     //   95: ldc_w 'ٺꄉ}'
/*    */     //   98: invokevirtual toCharArray : ()[C
/*    */     //   101: dup
/*    */     //   102: dup
/*    */     //   103: iconst_2
/*    */     //   104: dup_x1
/*    */     //   105: caload
/*    */     //   106: sipush #3084
/*    */     //   109: ixor
/*    */     //   110: i2c
/*    */     //   111: castore
/*    */     //   112: sipush #9877
/*    */     //   115: iconst_0
/*    */     //   116: iconst_5
/*    */     //   117: invokestatic H : (Ljava/lang/Object;SBB)Ljava/lang/String;
/*    */     //   120: invokevirtual append : (Ljava/lang/String;)Ljava/lang/StringBuilder;
/*    */     //   123: aload_1
/*    */     //   124: invokevirtual append : (Ljava/lang/String;)Ljava/lang/StringBuilder;
/*    */     //   127: ldc_w '萨ॎ착⹈'
/*    */     //   130: invokevirtual toCharArray : ()[C
/*    */     //   133: dup
/*    */     //   134: dup
/*    */     //   135: iconst_0
/*    */     //   136: dup_x1
/*    */     //   137: caload
/*    */     //   138: sipush #16328
/*    */     //   141: ixor
/*    */     //   142: i2c
/*    */     //   143: castore
/*    */     //   144: sipush #18902
/*    */     //   147: iconst_2
/*    */     //   148: iconst_2
/*    */     //   149: invokestatic H : (Ljava/lang/Object;SBB)Ljava/lang/String;
/*    */     //   152: invokevirtual append : (Ljava/lang/String;)Ljava/lang/StringBuilder;
/*    */     //   155: aload_2
/*    */     //   156: invokevirtual toString : ()Ljava/lang/String;
/*    */     //   159: invokevirtual append : (Ljava/lang/String;)Ljava/lang/StringBuilder;
/*    */     //   162: invokevirtual toString : ()Ljava/lang/String;
/*    */     //   165: aload #4
/*    */     //   167: invokespecial <init> : (Ljava/lang/String;Ljava/lang/Throwable;)V
/*    */     //   170: athrow
/*    */     //   171: aload_3
/*    */     //   172: areturn
/*    */     // Exception table:
/*    */     //   from	to	target	type
/*    */     //   9	50	53	java/lang/Exception
/*    */   }
/*    */ }


/* Location:              C:\Users\BukkitBypass\Desktop\MatrixAC\AAC\AAC-spigot-5.2.0.jar!\me\konsolas\aac\i8.class
 * Java compiler version: 8 (52.0)
 * JD-Core Version:       1.1.3
 */