/*    */ package me.konsolas.aac;
/*    */ 
/*    */ 
/*    */ public class io {
/*    */   private static final io c;
/*    */   public static final int d = 4;
/*    */   public static final int a = 5;
/*    */   private static final Logger b;
/*    */   
/* 10 */   public String toString() { return getClass().getSimpleName(); } private static final long o; private static final String[] p; private static final String[] q; private static final Map r; public mV a(X509TrustManager paramX509TrustManager, long paramLong) {
/* 11 */     int i = (int)((paramLong ^ 0x29886733B0EBL) >>> 56L), j = (int)((paramLong ^ 0x29886733B0EBL) << 8L >>> 32L), k = (int)((paramLong ^ 0x29886733B0EBL) << 40L >>> 40L); paramLong ^ 0x29886733B0EBL; return new dB((byte)i, j, paramX509TrustManager.getAcceptedIssuers(), k); } public static io c() {
/* 12 */     return c;
/*    */   }
/*    */   public void a(long paramLong, SSLSocketFactory paramSSLSocketFactory) {}
/*    */   @Nullable
/*    */   protected X509TrustManager a(SSLSocketFactory paramSSLSocketFactory, long paramLong) {
/*    */     // Byte code:
/*    */     //   0: lload_2
/*    */     //   1: dup2
/*    */     //   2: ldc2_w 133981168253026
/*    */     //   5: lxor
/*    */     //   6: lstore #4
/*    */     //   8: pop2
/*    */     //   9: ldc2_w 2638576176100422325
/*    */     //   12: lload_2
/*    */     //   13: <illegal opcode> w : (JJ)I
/*    */     //   18: istore #6
/*    */     //   20: sipush #23200
/*    */     //   23: ldc2_w 4743780593069339731
/*    */     //   26: lload_2
/*    */     //   27: lxor
/*    */     //   28: <illegal opcode> l : (IJ)Ljava/lang/String;
/*    */     //   33: invokestatic forName : (Ljava/lang/String;)Ljava/lang/Class;
/*    */     //   36: astore #7
/*    */     //   38: lload #4
/*    */     //   40: aload_1
/*    */     //   41: aload #7
/*    */     //   43: sipush #28210
/*    */     //   46: ldc2_w 4397068695235723462
/*    */     //   49: lload_2
/*    */     //   50: lxor
/*    */     //   51: <illegal opcode> l : (IJ)Ljava/lang/String;
/*    */     //   56: invokestatic a : (JLjava/lang/Object;Ljava/lang/Class;Ljava/lang/String;)Ljava/lang/Object;
/*    */     //   59: astore #8
/*    */     //   61: aload #8
/*    */     //   63: iload #6
/*    */     //   65: ifeq -> 108
/*    */     //   68: ifnonnull -> 86
/*    */     //   71: goto -> 84
/*    */     //   74: ldc2_w 2679948816192118925
/*    */     //   77: lload_2
/*    */     //   78: <illegal opcode> w : (Ljava/lang/Exception;JJ)Ljava/lang/Exception;
/*    */     //   83: athrow
/*    */     //   84: aconst_null
/*    */     //   85: areturn
/*    */     //   86: lload #4
/*    */     //   88: aload #8
/*    */     //   90: ldc javax/net/ssl/X509TrustManager
/*    */     //   92: sipush #9710
/*    */     //   95: ldc2_w 1235620576004393748
/*    */     //   98: lload_2
/*    */     //   99: lxor
/*    */     //   100: <illegal opcode> l : (IJ)Ljava/lang/String;
/*    */     //   105: invokestatic a : (JLjava/lang/Object;Ljava/lang/Class;Ljava/lang/String;)Ljava/lang/Object;
/*    */     //   108: checkcast javax/net/ssl/X509TrustManager
/*    */     //   111: areturn
/*    */     //   112: astore #7
/*    */     //   114: aconst_null
/*    */     //   115: areturn
/*    */     // Line number table:
/*    */     //   Java source line number -> byte code offset
/*    */     //   #22	-> 20
/*    */     //   #79	-> 38
/*    */     //   #17	-> 61
/*    */     //   #39	-> 86
/*    */     //   #49	-> 112
/*    */     //   #76	-> 114
/*    */     // Exception table:
/*    */     //   from	to	target	type
/*    */     //   20	85	112	java/lang/ClassNotFoundException
/*    */     //   61	71	74	java/lang/ClassNotFoundException
/*    */     //   86	111	112	java/lang/ClassNotFoundException
/*    */   }
/*    */   
/*    */   public static boolean b(short paramShort, int paramInt, char paramChar) {
/*    */     // Byte code:
/*    */     //   0: iload_0
/*    */     //   1: i2l
/*    */     //   2: bipush #48
/*    */     //   4: lshl
/*    */     //   5: iload_1
/*    */     //   6: i2l
/*    */     //   7: bipush #32
/*    */     //   9: lshl
/*    */     //   10: bipush #16
/*    */     //   12: lushr
/*    */     //   13: lor
/*    */     //   14: iload_2
/*    */     //   15: i2l
/*    */     //   16: bipush #48
/*    */     //   18: lshl
/*    */     //   19: bipush #48
/*    */     //   21: lushr
/*    */     //   22: lor
/*    */     //   23: getstatic me/konsolas/aac/io.o : J
/*    */     //   26: lxor
/*    */     //   27: lstore_3
/*    */     //   28: sipush #16506
/*    */     //   31: ldc2_w 8780964012288701428
/*    */     //   34: lload_3
/*    */     //   35: lxor
/*    */     //   36: <illegal opcode> l : (IJ)Ljava/lang/String;
/*    */     //   41: sipush #19611
/*    */     //   44: ldc2_w 6297762708244954906
/*    */     //   47: lload_3
/*    */     //   48: lxor
/*    */     //   49: <illegal opcode> l : (IJ)Ljava/lang/String;
/*    */     //   54: aconst_null
/*    */     //   55: invokestatic a : (Ljava/lang/String;Ljava/lang/String;)Ljava/lang/String;
/*    */     //   58: invokevirtual equals : (Ljava/lang/Object;)Z
/*    */     //   61: ifeq -> 76
/*    */     //   64: iconst_1
/*    */     //   65: ireturn
/*    */     //   66: ldc2_w 8667270423184571892
/*    */     //   69: lload_3
/*    */     //   70: <illegal opcode> w : (Ljava/lang/Exception;JJ)Ljava/lang/Exception;
/*    */     //   75: athrow
/*    */     //   76: invokestatic getProviders : ()[Ljava/security/Provider;
/*    */     //   79: iconst_0
/*    */     //   80: aaload
/*    */     //   81: invokevirtual getName : ()Ljava/lang/String;
/*    */     //   84: astore #5
/*    */     //   86: sipush #18430
/*    */     //   89: ldc2_w 2600459362203432047
/*    */     //   92: lload_3
/*    */     //   93: lxor
/*    */     //   94: <illegal opcode> l : (IJ)Ljava/lang/String;
/*    */     //   99: aload #5
/*    */     //   101: invokevirtual equals : (Ljava/lang/Object;)Z
/*    */     //   104: ireturn
/*    */     // Line number table:
/*    */     //   Java source line number -> byte code offset
/*    */     //   #26	-> 28
/*    */     //   #4	-> 64
/*    */     //   #7	-> 76
/*    */     //   #91	-> 94
/*    */     // Exception table:
/*    */     //   from	to	target	type
/*    */     //   28	66	66	java/lang/IllegalStateException
/*    */   }
/*    */   
/*    */   private static io a(long paramLong) {
/*    */     // Byte code:
/*    */     //   0: getstatic me/konsolas/aac/io.o : J
/*    */     //   3: lload_0
/*    */     //   4: lxor
/*    */     //   5: lstore_0
/*    */     //   6: lload_0
/*    */     //   7: dup2
/*    */     //   8: ldc2_w 99997397025203
/*    */     //   11: lxor
/*    */     //   12: lstore_2
/*    */     //   13: dup2
/*    */     //   14: ldc2_w 25064469950137
/*    */     //   17: lxor
/*    */     //   18: lstore #4
/*    */     //   20: dup2
/*    */     //   21: ldc2_w 80858867949623
/*    */     //   24: lxor
/*    */     //   25: lstore #6
/*    */     //   27: pop2
/*    */     //   28: lload #6
/*    */     //   30: invokestatic a : (J)Z
/*    */     //   33: ifeq -> 52
/*    */     //   36: lload #4
/*    */     //   38: invokestatic d : (J)Lme/konsolas/aac/io;
/*    */     //   41: areturn
/*    */     //   42: ldc2_w -4830668668546598582
/*    */     //   45: lload_0
/*    */     //   46: <illegal opcode> w : (Ljava/lang/Exception;JJ)Ljava/lang/Exception;
/*    */     //   51: athrow
/*    */     //   52: lload_2
/*    */     //   53: invokestatic b : (J)Lme/konsolas/aac/io;
/*    */     //   56: areturn
/*    */     // Line number table:
/*    */     //   Java source line number -> byte code offset
/*    */     //   #29	-> 28
/*    */     //   #93	-> 36
/*    */     //   #25	-> 52
/*    */     // Exception table:
/*    */     //   from	to	target	type
/*    */     //   28	42	42	java/lang/IllegalStateException
/*    */   }
/*    */   
/*    */   @Nullable
/*    */   public String a(long paramLong, SSLSocket paramSSLSocket) {
/* 30 */     return null;
/*    */   }
/*    */ 
/*    */   
/*    */   public void a(long paramLong, SSLSocket paramSSLSocket) {}
/*    */ 
/*    */   
/*    */   public String a(long paramLong) {
/*    */     // Byte code:
/*    */     //   0: getstatic me/konsolas/aac/io.o : J
/*    */     //   3: lload_1
/*    */     //   4: lxor
/*    */     //   5: lstore_1
/*    */     //   6: sipush #15832
/*    */     //   9: ldc2_w 1513452897669608906
/*    */     //   12: lload_1
/*    */     //   13: lxor
/*    */     //   14: <illegal opcode> l : (IJ)Ljava/lang/String;
/*    */     //   19: areturn
/*    */     // Line number table:
/*    */     //   Java source line number -> byte code offset
/*    */     //   #40	-> 6
/*    */   }
/*    */ 
/*    */   
/*    */   public void a(int paramInt1, int paramInt2, char paramChar, String paramString, short paramShort, @Nullable Throwable paramThrowable) {
/*    */     // Byte code:
/*    */     //   0: iload_2
/*    */     //   1: i2l
/*    */     //   2: bipush #32
/*    */     //   4: lshl
/*    */     //   5: iload_3
/*    */     //   6: i2l
/*    */     //   7: bipush #48
/*    */     //   9: lshl
/*    */     //   10: bipush #32
/*    */     //   12: lushr
/*    */     //   13: lor
/*    */     //   14: iload #5
/*    */     //   16: i2l
/*    */     //   17: bipush #48
/*    */     //   19: lshl
/*    */     //   20: bipush #48
/*    */     //   22: lushr
/*    */     //   23: lor
/*    */     //   24: lstore #7
/*    */     //   26: iload_1
/*    */     //   27: iconst_5
/*    */     //   28: if_icmpne -> 48
/*    */     //   31: getstatic java/util/logging/Level.WARNING : Ljava/util/logging/Level;
/*    */     //   34: goto -> 51
/*    */     //   37: ldc2_w 846810691363540604
/*    */     //   40: lload #7
/*    */     //   42: <illegal opcode> w : (Ljava/lang/Exception;JJ)Ljava/lang/Exception;
/*    */     //   47: athrow
/*    */     //   48: getstatic java/util/logging/Level.INFO : Ljava/util/logging/Level;
/*    */     //   51: astore #9
/*    */     //   53: getstatic me/konsolas/aac/io.b : Ljava/util/logging/Logger;
/*    */     //   56: aload #9
/*    */     //   58: aload #4
/*    */     //   60: aload #6
/*    */     //   62: invokevirtual log : (Ljava/util/logging/Level;Ljava/lang/String;Ljava/lang/Throwable;)V
/*    */     //   65: return
/*    */     // Line number table:
/*    */     //   Java source line number -> byte code offset
/*    */     //   #46	-> 26
/*    */     //   #35	-> 53
/*    */     //   #55	-> 65
/*    */     // Exception table:
/*    */     //   from	to	target	type
/*    */     //   26	37	37	java/lang/IllegalStateException
/*    */   }
/*    */ 
/*    */   
/*    */   public SSLContext a(long paramLong) {
/*    */     // Byte code:
/*    */     //   0: sipush #9029
/*    */     //   3: ldc2_w 8784812170759816950
/*    */     //   6: lload_1
/*    */     //   7: lxor
/*    */     //   8: <illegal opcode> l : (IJ)Ljava/lang/String;
/*    */     //   13: invokestatic getInstance : (Ljava/lang/String;)Ljavax/net/ssl/SSLContext;
/*    */     //   16: areturn
/*    */     //   17: astore_3
/*    */     //   18: new java/lang/IllegalStateException
/*    */     //   21: dup
/*    */     //   22: sipush #6265
/*    */     //   25: ldc2_w 7079800171734465986
/*    */     //   28: lload_1
/*    */     //   29: lxor
/*    */     //   30: <illegal opcode> l : (IJ)Ljava/lang/String;
/*    */     //   35: aload_3
/*    */     //   36: invokespecial <init> : (Ljava/lang/String;Ljava/lang/Throwable;)V
/*    */     //   39: athrow
/*    */     // Line number table:
/*    */     //   Java source line number -> byte code offset
/*    */     //   #51	-> 0
/*    */     //   #82	-> 17
/*    */     //   #62	-> 18
/*    */     // Exception table:
/*    */     //   from	to	target	type
/*    */     //   0	16	17	java/security/NoSuchAlgorithmException
/*    */   }
/*    */ 
/*    */   
/*    */   public void a(long paramLong, SSLSocket paramSSLSocket, @Nullable String paramString, List paramList) {}
/*    */   
/*    */   static {
/*    */     byte b1;
/*    */     long l1, l2;
/* 57 */     for (o = nc.a(8239131356815388694L, -3419654453152234624L, MethodHandles.lookup().lookupClass()).a(13407591440947L), l1 = o ^ 0x63E1716CC6E7L, l2 = l1 ^ 0xD7A83567B64L, r = new HashMap<>(13), "曱邹덮⒝刦◱唭儤ﱨ떿瓵묊蛓테℩췾?彫の㏆".toCharArray()[12] = (char)("曱邹덮⒝刦◱唭儤ﱨ떿瓵묊蛓테℩췾?彫の㏆".toCharArray()[12] ^ 0x53F4), "ﭽ앞㓒".toCharArray()[1] = (char)("ﭽ앞㓒".toCharArray()[1] ^ 0x3D18), (new byte[8])[0] = (byte)(int)(l1 >>> 56L), b1 = 1; b1 < 8; ) { (new byte[8])[b1] = (byte)(int)(l1 << b1 * 8 >>> 56L); b1++; }  Cipher cipher; (cipher = Cipher.getInstance(fW$gy.A("曱邹덮⒝刦◱唭儤ﱨ떿瓵묊蛓테℩췾?彫の㏆".toCharArray(), (short)22034, true, 5))).init(2, SecretKeyFactory.getInstance(fW$gy.A("ﭽ앞㓒".toCharArray(), (short)24547, true, 3)).generateSecret(new DESKeySpec(new byte[8])), new IvParameterSpec(new byte[8])); String[] arrayOfString = new String[17]; boolean bool = false; "诱᳟⁡ ₚ컃鑔쀮立ꈍ顐읣ᬺ춖벋譑菾䳛⌴䓠Ꚕꨀ扭䰾쬴펄晛屺?ꝅ錞鷵ۓ蹏볿㍼되鲵䖿?ㅦﷁ鮊ꞷႳￗ䢤긮຿農秉ㆿ홏都歉ķ迊?檀鳋龠⮃饥맿栦ㅈ깵쾱왣꟎␻餏ꐔ㥽?虝ᆕ鹴Ｉ枆ﴲꨨ⸛삽ᖪ㤣㱩낍梗肯䈉㿚魙㔦雽쫥럍牨㗍줍♿뵧꣤맲틤겜岙Ⱏ洞駚럳⏗讋ڵ䟑扞袙듪䬛찁謰탮獇罒ί毗Ｘꬥ糹叮諐蹧휣ሷ饲癨뇮嵇䕧䁭斓섃फ蕃섢툫᭄꿲ए篹똯㰾੘ꪟ匐┇㛰埽㾼萕푊瘾鉎嚙ꛦ륈䩅僽崫꣮?䞝㽂쏖⫭➩嵤И첥딛肻႖葈㐾㬏쬈蠈범慡♅㹵确㋵?轄袯昧ꃠ荺ﾱ縻딝㉯벍焮핒ሦѕ䤤㘰众雚ꀝ栒峰⽘ࡏ笑ꌯ梥恹螼硒ԁꎦ径渨뒼馜黖ꏙᙔ?ᄠ㇍䑛苲킒鄪膥꿠楰ẇᏔ䅕⌯탏蘦伾ࣨ♍陻ﲗ茕??ɶ❉踆䪴渤⥊?봿厴アᖎ⮅⺺ꆼ鏬㥍﩮囻የ쩷ጊ䱣쐯Ω듯볻ﶥ嬨ⷷ殤쯗헝䬟ﮎꧤ㔫㼚蚛扪䕷禟柫鸽㝏艖侓⤡娮냽犊吔줴⣮䗱⡯ﮌꤹ✭ㅪ止렺?ǖ绩鐾㶞፜읩돚折뮘곋矨ꄰ풅좗嶠绣?晴厏삯ª⊚桭䅦頇ꑯㅞ?ﳹ㊷랢竚똸倆枍죡⴯㜆ᛓꓴ넱ꕕꪒ驼ε䦇砛璊鬡낝減㑓?Ď쎇容鲜鲭䄫읭怤ᭃ܌캡ᙃጾꌖ跡ᎊ含쿙愥諦谬㎊ꔍ㎜꼙䖊嘞ꈺ庴ぞ??⇨璲臘壨貕霢嬐娆찬d퓲奋뙶┚롫㚪檩폶⺛∫ݓ弜۠첼喭裭ꮱ?虔灵䐆?䌡窙澕楹⧒м鋻꧳齆び窝댯⿝铛蓎泠黄ꚤ웙ᔆ涊ڎ篚㿁⾽㭿吀ባ譮䙤?Ꮸ䑪䰲숲㜎℁깭㆙맓♊呎켥擈榐?窟ꯁ睢⺽ՠ満琚䉺଎ό黄㶳ᮿ￠냊횳뜯蠼ᖲ⁚⡍섦䥥氟细퀒諿퓉⊨渚쭅㴆꾚뚕ā煰쉆蛌㖧ᗟ콫呔鶐?錨???힤㖥㎽솶큎䟴腖輇꘻蹃띲?ឩ䗁『昱莍탩斨ⅲ訽紳෌膖엢럙愉䤵瓮ᥡӵ褗ꪑ⛭㷜뺧噚珉⇶봈㦹좄騄씵怷홋涀韆桉︼ᛔ쒾ㄪ㼊轭?괰㛲凇唥珕㑐✥㐮诔?蚵﮸倁颪ϩᤉ唲谰䝧牷鹴ǳ꽘圀ޑￔຐ͝?툡끯ꘙΎ鿏ꦒଵꁉᜪꋉὈ".toCharArray()[150] = (char)("诱᳟⁡ ₚ컃鑔쀮立ꈍ顐읣ᬺ춖벋譑菾䳛⌴䓠Ꚕꨀ扭䰾쬴펄晛屺?ꝅ錞鷵ۓ蹏볿㍼되鲵䖿?ㅦﷁ鮊ꞷႳￗ䢤긮຿農秉ㆿ홏都歉ķ迊?檀鳋龠⮃饥맿栦ㅈ깵쾱왣꟎␻餏ꐔ㥽?虝ᆕ鹴Ｉ枆ﴲꨨ⸛삽ᖪ㤣㱩낍梗肯䈉㿚魙㔦雽쫥럍牨㗍줍♿뵧꣤맲틤겜岙Ⱏ洞駚럳⏗讋ڵ䟑扞袙듪䬛찁謰탮獇罒ί毗Ｘꬥ糹叮諐蹧휣ሷ饲癨뇮嵇䕧䁭斓섃फ蕃섢툫᭄꿲ए篹똯㰾੘ꪟ匐┇㛰埽㾼萕푊瘾鉎嚙ꛦ륈䩅僽崫꣮?䞝㽂쏖⫭➩嵤И첥딛肻႖葈㐾㬏쬈蠈범慡♅㹵确㋵?轄袯昧ꃠ荺ﾱ縻딝㉯벍焮핒ሦѕ䤤㘰众雚ꀝ栒峰⽘ࡏ笑ꌯ梥恹螼硒ԁꎦ径渨뒼馜黖ꏙᙔ?ᄠ㇍䑛苲킒鄪膥꿠楰ẇᏔ䅕⌯탏蘦伾ࣨ♍陻ﲗ茕??ɶ❉踆䪴渤⥊?봿厴アᖎ⮅⺺ꆼ鏬㥍﩮囻የ쩷ጊ䱣쐯Ω듯볻ﶥ嬨ⷷ殤쯗헝䬟ﮎꧤ㔫㼚蚛扪䕷禟柫鸽㝏艖侓⤡娮냽犊吔줴⣮䗱⡯ﮌꤹ✭ㅪ止렺?ǖ绩鐾㶞፜읩돚折뮘곋矨ꄰ풅좗嶠绣?晴厏삯ª⊚桭䅦頇ꑯㅞ?ﳹ㊷랢竚똸倆枍죡⴯㜆ᛓꓴ넱ꕕꪒ驼ε䦇砛璊鬡낝減㑓?Ď쎇容鲜鲭䄫읭怤ᭃ܌캡ᙃጾꌖ跡ᎊ含쿙愥諦谬㎊ꔍ㎜꼙䖊嘞ꈺ庴ぞ??⇨璲臘壨貕霢嬐娆찬d퓲奋뙶┚롫㚪檩폶⺛∫ݓ弜۠첼喭裭ꮱ?虔灵䐆?䌡窙澕楹⧒м鋻꧳齆び窝댯⿝铛蓎泠黄ꚤ웙ᔆ涊ڎ篚㿁⾽㭿吀ባ譮䙤?Ꮸ䑪䰲숲㜎℁깭㆙맓♊呎켥擈榐?窟ꯁ睢⺽ՠ満琚䉺଎ό黄㶳ᮿ￠냊횳뜯蠼ᖲ⁚⡍섦䥥氟细퀒諿퓉⊨渚쭅㴆꾚뚕ā煰쉆蛌㖧ᗟ콫呔鶐?錨???힤㖥㎽솶큎䟴腖輇꘻蹃띲?ឩ䗁『昱莍탩斨ⅲ訽紳෌膖엢럙愉䤵瓮ᥡӵ褗ꪑ⛭㷜뺧噚珉⇶봈㦹좄騄씵怷홋涀韆桉︼ᛔ쒾ㄪ㼊轭?괰㛲凇唥珕㑐✥㐮诔?蚵﮸倁颪ϩᤉ唲谰䝧牷鹴ǳ꽘圀ޑￔຐ͝?툡끯ꘙΎ鿏ꦒଵꁉᜪꋉὈ".toCharArray()[150] ^ 0x39C6); String str; int i = (str = fW$gy.A("诱᳟⁡ ₚ컃鑔쀮立ꈍ顐읣ᬺ춖벋譑菾䳛⌴䓠Ꚕꨀ扭䰾쬴펄晛屺?ꝅ錞鷵ۓ蹏볿㍼되鲵䖿?ㅦﷁ鮊ꞷႳￗ䢤긮຿農秉ㆿ홏都歉ķ迊?檀鳋龠⮃饥맿栦ㅈ깵쾱왣꟎␻餏ꐔ㥽?虝ᆕ鹴Ｉ枆ﴲꨨ⸛삽ᖪ㤣㱩낍梗肯䈉㿚魙㔦雽쫥럍牨㗍줍♿뵧꣤맲틤겜岙Ⱏ洞駚럳⏗讋ڵ䟑扞袙듪䬛찁謰탮獇罒ί毗Ｘꬥ糹叮諐蹧휣ሷ饲癨뇮嵇䕧䁭斓섃फ蕃섢툫᭄꿲ए篹똯㰾੘ꪟ匐┇㛰埽㾼萕푊瘾鉎嚙ꛦ륈䩅僽崫꣮?䞝㽂쏖⫭➩嵤И첥딛肻႖葈㐾㬏쬈蠈범慡♅㹵确㋵?轄袯昧ꃠ荺ﾱ縻딝㉯벍焮핒ሦѕ䤤㘰众雚ꀝ栒峰⽘ࡏ笑ꌯ梥恹螼硒ԁꎦ径渨뒼馜黖ꏙᙔ?ᄠ㇍䑛苲킒鄪膥꿠楰ẇᏔ䅕⌯탏蘦伾ࣨ♍陻ﲗ茕??ɶ❉踆䪴渤⥊?봿厴アᖎ⮅⺺ꆼ鏬㥍﩮囻የ쩷ጊ䱣쐯Ω듯볻ﶥ嬨ⷷ殤쯗헝䬟ﮎꧤ㔫㼚蚛扪䕷禟柫鸽㝏艖侓⤡娮냽犊吔줴⣮䗱⡯ﮌꤹ✭ㅪ止렺?ǖ绩鐾㶞፜읩돚折뮘곋矨ꄰ풅좗嶠绣?晴厏삯ª⊚桭䅦頇ꑯㅞ?ﳹ㊷랢竚똸倆枍죡⴯㜆ᛓꓴ넱ꕕꪒ驼ε䦇砛璊鬡낝減㑓?Ď쎇容鲜鲭䄫읭怤ᭃ܌캡ᙃጾꌖ跡ᎊ含쿙愥諦谬㎊ꔍ㎜꼙䖊嘞ꈺ庴ぞ??⇨璲臘壨貕霢嬐娆찬d퓲奋뙶┚롫㚪檩폶⺛∫ݓ弜۠첼喭裭ꮱ?虔灵䐆?䌡窙澕楹⧒м鋻꧳齆び窝댯⿝铛蓎泠黄ꚤ웙ᔆ涊ڎ篚㿁⾽㭿吀ባ譮䙤?Ꮸ䑪䰲숲㜎℁깭㆙맓♊呎켥擈榐?窟ꯁ睢⺽ՠ満琚䉺଎ό黄㶳ᮿ￠냊횳뜯蠼ᖲ⁚⡍섦䥥氟细퀒諿퓉⊨渚쭅㴆꾚뚕ā煰쉆蛌㖧ᗟ콫呔鶐?錨???힤㖥㎽솶큎䟴腖輇꘻蹃띲?ឩ䗁『昱莍탩斨ⅲ訽紳෌膖엢럙愉䤵瓮ᥡӵ褗ꪑ⛭㷜뺧噚珉⇶봈㦹좄騄씵怷홋涀韆桉︼ᛔ쒾ㄪ㼊轭?괰㛲凇唥珕㑐✥㐮诔?蚵﮸倁颪ϩᤉ唲谰䝧牷鹴ǳ꽘圀ޑￔຐ͝?툡끯ꘙΎ鿏ꦒଵꁉᜪꋉὈ".toCharArray(), (short)18459, false, 5)).length(); byte b2 = 32; byte b = -1;
/*    */     while (true);
/*    */   }
/*    */   public void a(String paramString, long paramLong, Object paramObject) {
/*    */     // Byte code:
/*    */     //   0: lload_2
/*    */     //   1: dup2
/*    */     //   2: ldc2_w 123844225552030
/*    */     //   5: lxor
/*    */     //   6: dup2
/*    */     //   7: bipush #32
/*    */     //   9: lushr
/*    */     //   10: l2i
/*    */     //   11: istore #5
/*    */     //   13: dup2
/*    */     //   14: bipush #32
/*    */     //   16: lshl
/*    */     //   17: bipush #48
/*    */     //   19: lushr
/*    */     //   20: l2i
/*    */     //   21: istore #6
/*    */     //   23: dup2
/*    */     //   24: bipush #48
/*    */     //   26: lshl
/*    */     //   27: bipush #48
/*    */     //   29: lushr
/*    */     //   30: l2i
/*    */     //   31: istore #7
/*    */     //   33: pop2
/*    */     //   34: pop2
/*    */     //   35: ldc2_w 4967757663609967322
/*    */     //   38: lload_2
/*    */     //   39: <illegal opcode> w : (JJ)I
/*    */     //   44: istore #8
/*    */     //   46: iload #8
/*    */     //   48: ifeq -> 119
/*    */     //   51: aload #4
/*    */     //   53: ifnonnull -> 100
/*    */     //   56: goto -> 69
/*    */     //   59: ldc2_w 4998443034168803554
/*    */     //   62: lload_2
/*    */     //   63: <illegal opcode> w : (Ljava/lang/Exception;JJ)Ljava/lang/Exception;
/*    */     //   68: athrow
/*    */     //   69: new java/lang/StringBuilder
/*    */     //   72: dup
/*    */     //   73: invokespecial <init> : ()V
/*    */     //   76: aload_1
/*    */     //   77: invokevirtual append : (Ljava/lang/String;)Ljava/lang/StringBuilder;
/*    */     //   80: sipush #26619
/*    */     //   83: ldc2_w 6987476348706318689
/*    */     //   86: lload_2
/*    */     //   87: lxor
/*    */     //   88: <illegal opcode> l : (IJ)Ljava/lang/String;
/*    */     //   93: invokevirtual append : (Ljava/lang/String;)Ljava/lang/StringBuilder;
/*    */     //   96: invokevirtual toString : ()Ljava/lang/String;
/*    */     //   99: astore_1
/*    */     //   100: aload_0
/*    */     //   101: iconst_5
/*    */     //   102: iload #5
/*    */     //   104: iload #6
/*    */     //   106: i2c
/*    */     //   107: aload_1
/*    */     //   108: iload #7
/*    */     //   110: i2s
/*    */     //   111: aload #4
/*    */     //   113: checkcast java/lang/Throwable
/*    */     //   116: invokevirtual a : (IICLjava/lang/String;SLjava/lang/Throwable;)V
/*    */     //   119: return
/*    */     // Line number table:
/*    */     //   Java source line number -> byte code offset
/*    */     //   #59	-> 46
/*    */     //   #84	-> 69
/*    */     //   #75	-> 100
/*    */     //   #69	-> 119
/*    */     // Exception table:
/*    */     //   from	to	target	type
/*    */     //   46	56	59	java/lang/IllegalStateException
/*    */   }
/*    */   private static io b(long paramLong) {
/*    */     // Byte code:
/*    */     //   0: getstatic me/konsolas/aac/io.o : J
/*    */     //   3: lload_0
/*    */     //   4: lxor
/*    */     //   5: lstore_0
/*    */     //   6: lload_0
/*    */     //   7: dup2
/*    */     //   8: ldc2_w 11019557913869
/*    */     //   11: lxor
/*    */     //   12: dup2
/*    */     //   13: bipush #48
/*    */     //   15: lushr
/*    */     //   16: l2i
/*    */     //   17: istore_2
/*    */     //   18: dup2
/*    */     //   19: bipush #16
/*    */     //   21: lshl
/*    */     //   22: bipush #32
/*    */     //   24: lushr
/*    */     //   25: l2i
/*    */     //   26: istore_3
/*    */     //   27: dup2
/*    */     //   28: bipush #48
/*    */     //   30: lshl
/*    */     //   31: bipush #48
/*    */     //   33: lushr
/*    */     //   34: l2i
/*    */     //   35: istore #4
/*    */     //   37: pop2
/*    */     //   38: dup2
/*    */     //   39: ldc2_w 17603855694461
/*    */     //   42: lxor
/*    */     //   43: lstore #5
/*    */     //   45: pop2
/*    */     //   46: iload_2
/*    */     //   47: i2s
/*    */     //   48: iload_3
/*    */     //   49: iload #4
/*    */     //   51: i2c
/*    */     //   52: invokestatic b : (SIC)Z
/*    */     //   55: ifeq -> 89
/*    */     //   58: lload #5
/*    */     //   60: invokestatic a : (J)Lme/konsolas/aac/ii;
/*    */     //   63: astore #7
/*    */     //   65: aload #7
/*    */     //   67: lload_0
/*    */     //   68: lconst_0
/*    */     //   69: lcmp
/*    */     //   70: ifle -> 78
/*    */     //   73: ifnull -> 89
/*    */     //   76: aload #7
/*    */     //   78: areturn
/*    */     //   79: ldc2_w -1070417217502710631
/*    */     //   82: lload_0
/*    */     //   83: <illegal opcode> w : (Ljava/lang/Exception;JJ)Ljava/lang/Exception;
/*    */     //   88: athrow
/*    */     //   89: invokestatic a : ()Lme/konsolas/aac/iG;
/*    */     //   92: astore #7
/*    */     //   94: aload #7
/*    */     //   96: lload_0
/*    */     //   97: lconst_0
/*    */     //   98: lcmp
/*    */     //   99: iflt -> 121
/*    */     //   102: ifnull -> 118
/*    */     //   105: aload #7
/*    */     //   107: areturn
/*    */     //   108: ldc2_w -1070417217502710631
/*    */     //   111: lload_0
/*    */     //   112: <illegal opcode> w : (Ljava/lang/Exception;JJ)Ljava/lang/Exception;
/*    */     //   117: athrow
/*    */     //   118: invokestatic e : ()Lme/konsolas/aac/io;
/*    */     //   121: astore #8
/*    */     //   123: aload #8
/*    */     //   125: lload_0
/*    */     //   126: lconst_0
/*    */     //   127: lcmp
/*    */     //   128: iflt -> 154
/*    */     //   131: ifnull -> 147
/*    */     //   134: aload #8
/*    */     //   136: areturn
/*    */     //   137: ldc2_w -1070417217502710631
/*    */     //   140: lload_0
/*    */     //   141: <illegal opcode> w : (Ljava/lang/Exception;JJ)Ljava/lang/Exception;
/*    */     //   146: athrow
/*    */     //   147: new me/konsolas/aac/io
/*    */     //   150: dup
/*    */     //   151: invokespecial <init> : ()V
/*    */     //   154: areturn
/*    */     // Line number table:
/*    */     //   Java source line number -> byte code offset
/*    */     //   #60	-> 46
/*    */     //   #65	-> 58
/*    */     //   #2	-> 65
/*    */     //   #16	-> 76
/*    */     //   #83	-> 89
/*    */     //   #67	-> 94
/*    */     //   #37	-> 105
/*    */     //   #90	-> 118
/*    */     //   #44	-> 123
/*    */     //   #6	-> 134
/*    */     //   #23	-> 147
/*    */     // Exception table:
/*    */     //   from	to	target	type
/*    */     //   65	79	79	java/lang/IllegalStateException
/*    */     //   94	108	108	java/lang/IllegalStateException
/*    */     //   123	137	137	java/lang/IllegalStateException
/*    */   }
/*    */   @Nullable
/*    */   public Object a(long paramLong, String paramString) {
/*    */     // Byte code:
/*    */     //   0: getstatic me/konsolas/aac/io.b : Ljava/util/logging/Logger;
/*    */     //   3: getstatic java/util/logging/Level.FINE : Ljava/util/logging/Level;
/*    */     //   6: invokevirtual isLoggable : (Ljava/util/logging/Level;)Z
/*    */     //   9: ifeq -> 31
/*    */     //   12: new java/lang/Throwable
/*    */     //   15: dup
/*    */     //   16: aload_3
/*    */     //   17: invokespecial <init> : (Ljava/lang/String;)V
/*    */     //   20: areturn
/*    */     //   21: ldc2_w -4501853127416888262
/*    */     //   24: lload_1
/*    */     //   25: <illegal opcode> w : (Ljava/lang/Exception;JJ)Ljava/lang/Exception;
/*    */     //   30: athrow
/*    */     //   31: aconst_null
/*    */     //   32: areturn
/*    */     // Line number table:
/*    */     //   Java source line number -> byte code offset
/*    */     //   #61	-> 0
/*    */     //   #21	-> 12
/*    */     //   #24	-> 31
/*    */     // Exception table:
/*    */     //   from	to	target	type
/*    */     //   0	21	21	java/lang/IllegalStateException
/*    */   }
/*    */   
/*    */   public gK a(long paramLong, X509TrustManager paramX509TrustManager) {
/* 72 */     long l = paramLong ^ 0x7F5A802375B1L; return new g2(a(paramX509TrustManager, l));
/*    */   }
/*    */   public static boolean a(long paramLong) {
/*    */     // Byte code:
/*    */     //   0: getstatic me/konsolas/aac/io.o : J
/*    */     //   3: lload_0
/*    */     //   4: lxor
/*    */     //   5: lstore_0
/*    */     //   6: sipush #21839
/*    */     //   9: ldc2_w 1001146714673516067
/*    */     //   12: lload_0
/*    */     //   13: lxor
/*    */     //   14: <illegal opcode> l : (IJ)Ljava/lang/String;
/*    */     //   19: sipush #9909
/*    */     //   22: ldc2_w 943827332581621214
/*    */     //   25: lload_0
/*    */     //   26: lxor
/*    */     //   27: <illegal opcode> l : (IJ)Ljava/lang/String;
/*    */     //   32: invokestatic getProperty : (Ljava/lang/String;)Ljava/lang/String;
/*    */     //   35: invokevirtual equals : (Ljava/lang/Object;)Z
/*    */     //   38: ireturn
/*    */     // Line number table:
/*    */     //   Java source line number -> byte code offset
/*    */     //   #80	-> 6
/*    */   }
/*    */   
/*    */   @Nullable
/*    */   static Object a(long paramLong, Object paramObject, Class paramClass, String paramString) {
/*    */     // Byte code:
/*    */     //   0: getstatic me/konsolas/aac/io.o : J
/*    */     //   3: lload_0
/*    */     //   4: lxor
/*    */     //   5: lstore_0
/*    */     //   6: lload_0
/*    */     //   7: dup2
/*    */     //   8: ldc2_w 74443321134176
/*    */     //   11: lxor
/*    */     //   12: lstore #5
/*    */     //   14: pop2
/*    */     //   15: ldc2_w -3360188640855854276
/*    */     //   18: lload_0
/*    */     //   19: <illegal opcode> w : (JJ)I
/*    */     //   24: aload_2
/*    */     //   25: invokevirtual getClass : ()Ljava/lang/Class;
/*    */     //   28: astore #8
/*    */     //   30: istore #7
/*    */     //   32: aload #8
/*    */     //   34: iload #7
/*    */     //   36: ifne -> 59
/*    */     //   39: ldc java/lang/Object
/*    */     //   41: if_acmpeq -> 155
/*    */     //   44: goto -> 57
/*    */     //   47: ldc2_w -3372301867620313969
/*    */     //   50: lload_0
/*    */     //   51: <illegal opcode> w : (Ljava/lang/Exception;JJ)Ljava/lang/Exception;
/*    */     //   56: athrow
/*    */     //   57: aload #8
/*    */     //   59: aload #4
/*    */     //   61: invokevirtual getDeclaredField : (Ljava/lang/String;)Ljava/lang/reflect/Field;
/*    */     //   64: astore #9
/*    */     //   66: aload #9
/*    */     //   68: iconst_1
/*    */     //   69: invokevirtual setAccessible : (Z)V
/*    */     //   72: aload #9
/*    */     //   74: aload_2
/*    */     //   75: invokevirtual get : (Ljava/lang/Object;)Ljava/lang/Object;
/*    */     //   78: astore #10
/*    */     //   80: aload_3
/*    */     //   81: lload_0
/*    */     //   82: lconst_0
/*    */     //   83: lcmp
/*    */     //   84: ifle -> 121
/*    */     //   87: aload #10
/*    */     //   89: iload #7
/*    */     //   91: ifne -> 118
/*    */     //   94: invokevirtual isInstance : (Ljava/lang/Object;)Z
/*    */     //   97: ifne -> 115
/*    */     //   100: goto -> 113
/*    */     //   103: ldc2_w -3372301867620313969
/*    */     //   106: lload_0
/*    */     //   107: <illegal opcode> w : (Ljava/lang/Exception;JJ)Ljava/lang/Exception;
/*    */     //   112: athrow
/*    */     //   113: aconst_null
/*    */     //   114: areturn
/*    */     //   115: aload_3
/*    */     //   116: aload #10
/*    */     //   118: invokevirtual cast : (Ljava/lang/Object;)Ljava/lang/Object;
/*    */     //   121: areturn
/*    */     //   122: astore #9
/*    */     //   124: goto -> 137
/*    */     //   127: astore #9
/*    */     //   129: new java/lang/AssertionError
/*    */     //   132: dup
/*    */     //   133: invokespecial <init> : ()V
/*    */     //   136: athrow
/*    */     //   137: aload #8
/*    */     //   139: invokevirtual getSuperclass : ()Ljava/lang/Class;
/*    */     //   142: astore #8
/*    */     //   144: lload_0
/*    */     //   145: lconst_0
/*    */     //   146: lcmp
/*    */     //   147: ifle -> 155
/*    */     //   150: iload #7
/*    */     //   152: ifeq -> 32
/*    */     //   155: aload #4
/*    */     //   157: iload #7
/*    */     //   159: lload_0
/*    */     //   160: lconst_0
/*    */     //   161: lcmp
/*    */     //   162: iflt -> 227
/*    */     //   165: ifne -> 225
/*    */     //   168: sipush #4096
/*    */     //   171: ldc2_w 4442002312719862525
/*    */     //   174: lload_0
/*    */     //   175: lxor
/*    */     //   176: <illegal opcode> l : (IJ)Ljava/lang/String;
/*    */     //   181: invokevirtual equals : (Ljava/lang/Object;)Z
/*    */     //   184: ifne -> 270
/*    */     //   187: goto -> 200
/*    */     //   190: ldc2_w -3372301867620313969
/*    */     //   193: lload_0
/*    */     //   194: <illegal opcode> w : (Ljava/lang/Exception;JJ)Ljava/lang/Exception;
/*    */     //   199: athrow
/*    */     //   200: lload #5
/*    */     //   202: aload_2
/*    */     //   203: ldc java/lang/Object
/*    */     //   205: sipush #3364
/*    */     //   208: ldc2_w 1786616687412418516
/*    */     //   211: lload_0
/*    */     //   212: lxor
/*    */     //   213: <illegal opcode> l : (IJ)Ljava/lang/String;
/*    */     //   218: invokestatic a : (JLjava/lang/Object;Ljava/lang/Class;Ljava/lang/String;)Ljava/lang/Object;
/*    */     //   221: astore #8
/*    */     //   223: aload #8
/*    */     //   225: iload #7
/*    */     //   227: ifne -> 269
/*    */     //   230: ifnull -> 270
/*    */     //   233: goto -> 246
/*    */     //   236: ldc2_w -3372301867620313969
/*    */     //   239: lload_0
/*    */     //   240: <illegal opcode> w : (Ljava/lang/Exception;JJ)Ljava/lang/Exception;
/*    */     //   245: athrow
/*    */     //   246: lload #5
/*    */     //   248: aload #8
/*    */     //   250: aload_3
/*    */     //   251: aload #4
/*    */     //   253: invokestatic a : (JLjava/lang/Object;Ljava/lang/Class;Ljava/lang/String;)Ljava/lang/Object;
/*    */     //   256: goto -> 269
/*    */     //   259: ldc2_w -3372301867620313969
/*    */     //   262: lload_0
/*    */     //   263: <illegal opcode> w : (Ljava/lang/Exception;JJ)Ljava/lang/Exception;
/*    */     //   268: athrow
/*    */     //   269: areturn
/*    */     //   270: aconst_null
/*    */     //   271: areturn
/*    */     // Line number table:
/*    */     //   Java source line number -> byte code offset
/*    */     //   #81	-> 24
/*    */     //   #87	-> 57
/*    */     //   #73	-> 66
/*    */     //   #14	-> 72
/*    */     //   #8	-> 80
/*    */     //   #78	-> 115
/*    */     //   #50	-> 122
/*    */     //   #34	-> 124
/*    */     //   #52	-> 127
/*    */     //   #92	-> 129
/*    */     //   #45	-> 137
/*    */     //   #19	-> 155
/*    */     //   #48	-> 200
/*    */     //   #54	-> 223
/*    */     //   #41	-> 270
/*    */     // Exception table:
/*    */     //   from	to	target	type
/*    */     //   32	44	47	java/lang/NoSuchFieldException
/*    */     //   57	114	122	java/lang/NoSuchFieldException
/*    */     //   57	114	127	java/lang/IllegalAccessException
/*    */     //   80	100	103	java/lang/NoSuchFieldException
/*    */     //   115	121	122	java/lang/NoSuchFieldException
/*    */     //   115	121	127	java/lang/IllegalAccessException
/*    */     //   155	187	190	java/lang/NoSuchFieldException
/*    */     //   225	233	236	java/lang/NoSuchFieldException
/*    */     //   230	256	259	java/lang/NoSuchFieldException
/*    */   }
/*    */   
/*    */   private static io d(long paramLong) {
/*    */     // Byte code:
/*    */     //   0: getstatic me/konsolas/aac/io.o : J
/*    */     //   3: lload_0
/*    */     //   4: lxor
/*    */     //   5: lstore_0
/*    */     //   6: lload_0
/*    */     //   7: dup2
/*    */     //   8: ldc2_w 49254236155415
/*    */     //   11: lxor
/*    */     //   12: dup2
/*    */     //   13: bipush #32
/*    */     //   15: lushr
/*    */     //   16: l2i
/*    */     //   17: istore_2
/*    */     //   18: dup2
/*    */     //   19: bipush #32
/*    */     //   21: lshl
/*    */     //   22: bipush #48
/*    */     //   24: lushr
/*    */     //   25: l2i
/*    */     //   26: istore_3
/*    */     //   27: dup2
/*    */     //   28: bipush #48
/*    */     //   30: lshl
/*    */     //   31: bipush #48
/*    */     //   33: lushr
/*    */     //   34: l2i
/*    */     //   35: istore #4
/*    */     //   37: pop2
/*    */     //   38: dup2
/*    */     //   39: ldc2_w 117324374131713
/*    */     //   42: lxor
/*    */     //   43: dup2
/*    */     //   44: bipush #48
/*    */     //   46: lushr
/*    */     //   47: l2i
/*    */     //   48: istore #5
/*    */     //   50: dup2
/*    */     //   51: bipush #16
/*    */     //   53: lshl
/*    */     //   54: bipush #32
/*    */     //   56: lushr
/*    */     //   57: l2i
/*    */     //   58: istore #6
/*    */     //   60: dup2
/*    */     //   61: bipush #48
/*    */     //   63: lshl
/*    */     //   64: bipush #48
/*    */     //   66: lushr
/*    */     //   67: l2i
/*    */     //   68: istore #7
/*    */     //   70: pop2
/*    */     //   71: pop2
/*    */     //   72: iload #5
/*    */     //   74: i2s
/*    */     //   75: iload #6
/*    */     //   77: iload #7
/*    */     //   79: i2s
/*    */     //   80: invokestatic f : (SIS)Lme/konsolas/aac/io;
/*    */     //   83: astore #8
/*    */     //   85: aload #8
/*    */     //   87: ifnull -> 103
/*    */     //   90: aload #8
/*    */     //   92: areturn
/*    */     //   93: ldc2_w 2175046274050300819
/*    */     //   96: lload_0
/*    */     //   97: <illegal opcode> w : (Ljava/lang/Exception;JJ)Ljava/lang/Exception;
/*    */     //   102: athrow
/*    */     //   103: iload_2
/*    */     //   104: iload_3
/*    */     //   105: i2c
/*    */     //   106: iload #4
/*    */     //   108: invokestatic e : (ICI)Lme/konsolas/aac/io;
/*    */     //   111: astore #9
/*    */     //   113: aload #9
/*    */     //   115: lload_0
/*    */     //   116: lconst_0
/*    */     //   117: lcmp
/*    */     //   118: iflt -> 157
/*    */     //   121: ifnonnull -> 155
/*    */     //   124: new java/lang/NullPointerException
/*    */     //   127: dup
/*    */     //   128: sipush #1911
/*    */     //   131: ldc2_w 5158546267505644191
/*    */     //   134: lload_0
/*    */     //   135: lxor
/*    */     //   136: <illegal opcode> l : (IJ)Ljava/lang/String;
/*    */     //   141: invokespecial <init> : (Ljava/lang/String;)V
/*    */     //   144: athrow
/*    */     //   145: ldc2_w 2175046274050300819
/*    */     //   148: lload_0
/*    */     //   149: <illegal opcode> w : (Ljava/lang/Exception;JJ)Ljava/lang/Exception;
/*    */     //   154: athrow
/*    */     //   155: aload #9
/*    */     //   157: areturn
/*    */     // Line number table:
/*    */     //   Java source line number -> byte code offset
/*    */     //   #86	-> 72
/*    */     //   #77	-> 85
/*    */     //   #66	-> 90
/*    */     //   #47	-> 103
/*    */     //   #58	-> 113
/*    */     //   #1	-> 124
/*    */     //   #13	-> 155
/*    */     // Exception table:
/*    */     //   from	to	target	type
/*    */     //   85	93	93	java/lang/IllegalStateException
/*    */     //   113	145	145	java/lang/IllegalStateException
/*    */   }
/*    */   
/*    */   public boolean a(long paramLong, String paramString) {
/* 88 */     return true;
/*    */   } public static List a(List paramList, long paramLong) {
/*    */     // Byte code:
/*    */     //   0: getstatic me/konsolas/aac/io.o : J
/*    */     //   3: lload_1
/*    */     //   4: lxor
/*    */     //   5: lstore_1
/*    */     //   6: ldc2_w -7332368667252574116
/*    */     //   9: lload_1
/*    */     //   10: <illegal opcode> w : (JJ)I
/*    */     //   15: new java/util/ArrayList
/*    */     //   18: dup
/*    */     //   19: aload_0
/*    */     //   20: invokeinterface size : ()I
/*    */     //   25: invokespecial <init> : (I)V
/*    */     //   28: astore #4
/*    */     //   30: istore_3
/*    */     //   31: iconst_0
/*    */     //   32: istore #5
/*    */     //   34: aload_0
/*    */     //   35: invokeinterface size : ()I
/*    */     //   40: istore #6
/*    */     //   42: iload #5
/*    */     //   44: iload #6
/*    */     //   46: if_icmpge -> 103
/*    */     //   49: aload_0
/*    */     //   50: iload #5
/*    */     //   52: invokeinterface get : (I)Ljava/lang/Object;
/*    */     //   57: checkcast me/konsolas/aac/le
/*    */     //   60: astore #7
/*    */     //   62: aload #7
/*    */     //   64: getstatic me/konsolas/aac/le.HTTP_1_0 : Lme/konsolas/aac/le;
/*    */     //   67: if_acmpne -> 83
/*    */     //   70: goto -> 96
/*    */     //   73: ldc2_w -7326465019450384401
/*    */     //   76: lload_1
/*    */     //   77: <illegal opcode> w : (Ljava/lang/Exception;JJ)Ljava/lang/Exception;
/*    */     //   82: athrow
/*    */     //   83: aload #4
/*    */     //   85: aload #7
/*    */     //   87: invokevirtual toString : ()Ljava/lang/String;
/*    */     //   90: invokeinterface add : (Ljava/lang/Object;)Z
/*    */     //   95: pop
/*    */     //   96: iinc #5, 1
/*    */     //   99: iload_3
/*    */     //   100: ifeq -> 42
/*    */     //   103: aload #4
/*    */     //   105: lload_1
/*    */     //   106: lconst_0
/*    */     //   107: lcmp
/*    */     //   108: iflt -> 57
/*    */     //   111: areturn
/*    */     // Line number table:
/*    */     //   Java source line number -> byte code offset
/*    */     //   #89	-> 15
/*    */     //   #32	-> 31
/*    */     //   #74	-> 49
/*    */     //   #43	-> 62
/*    */     //   #5	-> 83
/*    */     //   #18	-> 96
/*    */     //   #27	-> 103
/*    */     // Exception table:
/*    */     //   from	to	target	type
/*    */     //   62	73	73	java/lang/IllegalStateException
/*    */   } static byte[] a(List paramList, long paramLong) {
/*    */     // Byte code:
/*    */     //   0: getstatic me/konsolas/aac/io.o : J
/*    */     //   3: lload_1
/*    */     //   4: lxor
/*    */     //   5: lstore_1
/*    */     //   6: lload_1
/*    */     //   7: dup2
/*    */     //   8: ldc2_w 98284035562988
/*    */     //   11: lxor
/*    */     //   12: lstore_3
/*    */     //   13: dup2
/*    */     //   14: ldc2_w 72789869096388
/*    */     //   17: lxor
/*    */     //   18: lstore #5
/*    */     //   20: dup2
/*    */     //   21: ldc2_w 119544751033402
/*    */     //   24: lxor
/*    */     //   25: lstore #7
/*    */     //   27: pop2
/*    */     //   28: ldc2_w 6568855359681493323
/*    */     //   31: lload_1
/*    */     //   32: <illegal opcode> w : (JJ)I
/*    */     //   37: new me/konsolas/aac/fw
/*    */     //   40: dup
/*    */     //   41: invokespecial <init> : ()V
/*    */     //   44: astore #10
/*    */     //   46: iconst_0
/*    */     //   47: istore #11
/*    */     //   49: aload_0
/*    */     //   50: invokeinterface size : ()I
/*    */     //   55: istore #12
/*    */     //   57: istore #9
/*    */     //   59: iload #11
/*    */     //   61: iload #12
/*    */     //   63: if_icmpge -> 156
/*    */     //   66: aload_0
/*    */     //   67: iload #11
/*    */     //   69: invokeinterface get : (I)Ljava/lang/Object;
/*    */     //   74: checkcast me/konsolas/aac/le
/*    */     //   77: astore #13
/*    */     //   79: iload #9
/*    */     //   81: ifne -> 133
/*    */     //   84: aload #13
/*    */     //   86: getstatic me/konsolas/aac/le.HTTP_1_0 : Lme/konsolas/aac/le;
/*    */     //   89: if_acmpne -> 118
/*    */     //   92: goto -> 105
/*    */     //   95: ldc2_w 6576478452543479544
/*    */     //   98: lload_1
/*    */     //   99: <illegal opcode> w : (Ljava/lang/Exception;JJ)Ljava/lang/Exception;
/*    */     //   104: athrow
/*    */     //   105: goto -> 148
/*    */     //   108: ldc2_w 6576478452543479544
/*    */     //   111: lload_1
/*    */     //   112: <illegal opcode> w : (Ljava/lang/Exception;JJ)Ljava/lang/Exception;
/*    */     //   117: athrow
/*    */     //   118: aload #10
/*    */     //   120: aload #13
/*    */     //   122: invokevirtual toString : ()Ljava/lang/String;
/*    */     //   125: invokevirtual length : ()I
/*    */     //   128: lload_3
/*    */     //   129: invokevirtual a : (IJ)Lme/konsolas/aac/fw;
/*    */     //   132: pop
/*    */     //   133: aload #10
/*    */     //   135: aload #13
/*    */     //   137: invokevirtual toString : ()Ljava/lang/String;
/*    */     //   140: lload #5
/*    */     //   142: dup2_x1
/*    */     //   143: pop2
/*    */     //   144: invokevirtual a : (JLjava/lang/String;)Lme/konsolas/aac/fw;
/*    */     //   147: pop
/*    */     //   148: iinc #11, 1
/*    */     //   151: iload #9
/*    */     //   153: ifeq -> 59
/*    */     //   156: aload #10
/*    */     //   158: lload #7
/*    */     //   160: invokevirtual a : (J)[B
/*    */     //   163: lload_1
/*    */     //   164: lconst_0
/*    */     //   165: lcmp
/*    */     //   166: iflt -> 74
/*    */     //   169: areturn
/*    */     // Line number table:
/*    */     //   Java source line number -> byte code offset
/*    */     //   #94	-> 37
/*    */     //   #64	-> 46
/*    */     //   #53	-> 66
/*    */     //   #31	-> 79
/*    */     //   #28	-> 118
/*    */     //   #9	-> 133
/*    */     //   #70	-> 148
/*    */     //   #71	-> 156
/*    */     // Exception table:
/*    */     //   from	to	target	type
/*    */     //   79	92	95	java/lang/IllegalStateException
/*    */     //   84	108	108	java/lang/IllegalStateException
/*    */   }
/*    */   public void a(Socket paramSocket, InetSocketAddress paramInetSocketAddress, long paramLong, int paramInt) {
/* 95 */     paramSocket.connect(paramInetSocketAddress, paramInt);
/*    */   }
/*    */   
/*    */   public gK a(long paramLong, SSLSocketFactory paramSSLSocketFactory) {
/*    */     // Byte code:
/*    */     //   0: getstatic me/konsolas/aac/io.o : J
/*    */     //   3: lload_1
/*    */     //   4: lxor
/*    */     //   5: lstore_1
/*    */     //   6: lload_1
/*    */     //   7: dup2
/*    */     //   8: ldc2_w 43394070176855
/*    */     //   11: lxor
/*    */     //   12: lstore #4
/*    */     //   14: dup2
/*    */     //   15: ldc2_w 91313770337425
/*    */     //   18: lxor
/*    */     //   19: lstore #6
/*    */     //   21: pop2
/*    */     //   22: aload_0
/*    */     //   23: aload_3
/*    */     //   24: lload #4
/*    */     //   26: invokevirtual a : (Ljavax/net/ssl/SSLSocketFactory;J)Ljavax/net/ssl/X509TrustManager;
/*    */     //   29: astore #8
/*    */     //   31: aload #8
/*    */     //   33: ifnonnull -> 109
/*    */     //   36: new java/lang/IllegalStateException
/*    */     //   39: dup
/*    */     //   40: new java/lang/StringBuilder
/*    */     //   43: dup
/*    */     //   44: invokespecial <init> : ()V
/*    */     //   47: sipush #3522
/*    */     //   50: ldc2_w 6719945451741546347
/*    */     //   53: lload_1
/*    */     //   54: lxor
/*    */     //   55: <illegal opcode> l : (IJ)Ljava/lang/String;
/*    */     //   60: invokevirtual append : (Ljava/lang/String;)Ljava/lang/StringBuilder;
/*    */     //   63: invokestatic c : ()Lme/konsolas/aac/io;
/*    */     //   66: invokevirtual append : (Ljava/lang/Object;)Ljava/lang/StringBuilder;
/*    */     //   69: sipush #21401
/*    */     //   72: ldc2_w 5169809619041048894
/*    */     //   75: lload_1
/*    */     //   76: lxor
/*    */     //   77: <illegal opcode> l : (IJ)Ljava/lang/String;
/*    */     //   82: invokevirtual append : (Ljava/lang/String;)Ljava/lang/StringBuilder;
/*    */     //   85: aload_3
/*    */     //   86: invokevirtual getClass : ()Ljava/lang/Class;
/*    */     //   89: invokevirtual append : (Ljava/lang/Object;)Ljava/lang/StringBuilder;
/*    */     //   92: invokevirtual toString : ()Ljava/lang/String;
/*    */     //   95: invokespecial <init> : (Ljava/lang/String;)V
/*    */     //   98: athrow
/*    */     //   99: ldc2_w 4712507148796380378
/*    */     //   102: lload_1
/*    */     //   103: <illegal opcode> w : (Ljava/lang/Exception;JJ)Ljava/lang/Exception;
/*    */     //   108: athrow
/*    */     //   109: aload_0
/*    */     //   110: lload #6
/*    */     //   112: aload #8
/*    */     //   114: invokevirtual a : (JLjavax/net/ssl/X509TrustManager;)Lme/konsolas/aac/gK;
/*    */     //   117: areturn
/*    */     // Line number table:
/*    */     //   Java source line number -> byte code offset
/*    */     //   #96	-> 22
/*    */     //   #63	-> 31
/*    */     //   #85	-> 36
/*    */     //   #68	-> 63
/*    */     //   #3	-> 86
/*    */     //   #42	-> 109
/*    */     // Exception table:
/*    */     //   from	to	target	type
/*    */     //   31	99	99	java/lang/IllegalStateException
/*    */   }
/*    */   
/*    */   private static Exception b(Exception paramException) {
/*    */     return paramException;
/*    */   }
/*    */   
/*    */   private static String a(byte[] paramArrayOfbyte) {
/*    */     byte b1 = 0;
/*    */     int i;
/*    */     char[] arrayOfChar = new char[i = paramArrayOfbyte.length];
/*    */     for (byte b2 = 0; b2 < i; b2++) {
/*    */       int j;
/*    */       if ((j = 0xFF & paramArrayOfbyte[b2]) < 192) {
/*    */         arrayOfChar[b1++] = (char)j;
/*    */       } else if (j < 224) {
/*    */         char c = (char)((char)(j & 0x1F) << 6);
/*    */         j = paramArrayOfbyte[++b2];
/*    */         c = (char)(c | (char)(j & 0x3F));
/*    */         arrayOfChar[b1++] = c;
/*    */       } else if (b2 < i - 2) {
/*    */         char c = (char)((char)(j & 0xF) << 12);
/*    */         j = paramArrayOfbyte[++b2];
/*    */         c = (char)(c | (char)(j & 0x3F) << 6);
/*    */         j = paramArrayOfbyte[++b2];
/*    */         c = (char)(c | (char)(j & 0x3F));
/*    */         arrayOfChar[b1++] = c;
/*    */       } 
/*    */     } 
/*    */     return new String(arrayOfChar, 0, b1);
/*    */   }
/*    */   
/*    */   private static String a(int paramInt, long paramLong) {
/*    */     int i = paramInt ^ (int)(paramLong & 0x7FFFL) ^ 0x4ABC;
/*    */     if (q[i] == null) {
/*    */       Object[] arrayOfObject;
/*    */       try {
/*    */         Long long_ = Long.valueOf(Thread.currentThread().getId());
/*    */         arrayOfObject = (Object[])r.get(long_);
/*    */         if (arrayOfObject == null) {
/*    */           arrayOfObject = new Object[3];
/*    */           "┓홽呴ﵼ?䢡겕᛽ꆅ쓘猼⒖殭귣ԫ⭁셒鑁⥛흙ᜯ".toCharArray()[10] = (char)("┓홽呴ﵼ?䢡겕᛽ꆅ쓘猼⒖殭귣ԫ⭁셒鑁⥛흙ᜯ".toCharArray()[10] ^ 0x4FBC);
/*    */           arrayOfObject[0] = Cipher.getInstance(a0$cc.G("┓홽呴ﵼ?䢡겕᛽ꆅ쓘猼⒖殭귣ԫ⭁셒鑁⥛흙ᜯ".toCharArray(), (short)18133, false, (byte)4));
/*    */           "壚귙峷旸".toCharArray()[2] = (char)("壚귙峷旸".toCharArray()[2] ^ 0x12ED);
/*    */           arrayOfObject[1] = SecretKeyFactory.getInstance(a0$cc.G("壚귙峷旸".toCharArray(), (short)31131, false, (byte)5));
/*    */           arrayOfObject[2] = new IvParameterSpec(new byte[8]);
/*    */           r.put(long_, arrayOfObject);
/*    */         } 
/*    */       } catch (Exception exception) {
/*    */         "홈鿹妽㾝⌙뗶닭譺ꬆ☨ᥐ㢑ㅓꍪﹸꦑ｝Ļ".toCharArray()[5] = (char)("홈鿹妽㾝⌙뗶닭譺ꬆ☨ᥐ㢑ㅓꍪﹸꦑ｝Ļ".toCharArray()[5] ^ 0x780F);
/*    */         throw new RuntimeException(a0$cc.G("홈鿹妽㾝⌙뗶닭譺ꬆ☨ᥐ㢑ㅓꍪﹸꦑ｝Ļ".toCharArray(), (short)21334, true, (byte)1), exception);
/*    */       } 
/*    */       byte[] arrayOfByte1 = new byte[8];
/*    */       arrayOfByte1[0] = (byte)(int)(paramLong >>> 56L);
/*    */       for (byte b = 1; b < 8; b++)
/*    */         arrayOfByte1[b] = (byte)(int)(paramLong << b * 8 >>> 56L); 
/*    */       DESKeySpec dESKeySpec = new DESKeySpec(arrayOfByte1);
/*    */       SecretKey secretKey = ((SecretKeyFactory)arrayOfObject[1]).generateSecret(dESKeySpec);
/*    */       ((Cipher)arrayOfObject[0]).init(2, secretKey, (IvParameterSpec)arrayOfObject[2]);
/*    */       "﹅戯ଢ଼鉰뱜⏫埊ᗀ羔涹".toCharArray()[4] = (char)("﹅戯ଢ଼鉰뱜⏫埊ᗀ羔涹".toCharArray()[4] ^ 0x18F2);
/*    */       byte[] arrayOfByte2 = p[i].getBytes(a0$cc.G("﹅戯ଢ଼鉰뱜⏫埊ᗀ羔涹".toCharArray(), (short)1763, true, (byte)3));
/*    */       q[i] = a(((Cipher)arrayOfObject[0]).doFinal(arrayOfByte2));
/*    */     } 
/*    */     return q[i];
/*    */   }
/*    */   
/*    */   private static Object a(MethodHandles.Lookup paramLookup, MutableCallSite paramMutableCallSite, String paramString, Object[] paramArrayOfObject) {
/*    */     int i = ((Integer)paramArrayOfObject[0]).intValue();
/*    */     long l = ((Long)paramArrayOfObject[1]).longValue();
/*    */     String str = a(i, l);
/*    */     MethodHandle methodHandle = MethodHandles.constant(String.class, str);
/*    */     paramMutableCallSite.setTarget(MethodHandles.dropArguments(methodHandle, 0, new Class[] { int.class, long.class }));
/*    */     return str;
/*    */   }
/*    */   
/*    */   private static CallSite a(MethodHandles.Lookup paramLookup, String paramString, MethodType paramMethodType) {
/*    */     // Byte code:
/*    */     //   0: new java/lang/invoke/MutableCallSite
/*    */     //   3: dup
/*    */     //   4: aload_2
/*    */     //   5: invokespecial <init> : (Ljava/lang/invoke/MethodType;)V
/*    */     //   8: astore_3
/*    */     //   9: aload_3
/*    */     //   10: ldc_w
/*    */     //   13: ldc_w [Ljava/lang/Object;
/*    */     //   16: aload_2
/*    */     //   17: invokevirtual parameterCount : ()I
/*    */     //   20: invokevirtual asCollector : (Ljava/lang/Class;I)Ljava/lang/invoke/MethodHandle;
/*    */     //   23: iconst_0
/*    */     //   24: iconst_3
/*    */     //   25: anewarray java/lang/Object
/*    */     //   28: dup
/*    */     //   29: iconst_0
/*    */     //   30: aload_0
/*    */     //   31: aastore
/*    */     //   32: dup
/*    */     //   33: iconst_1
/*    */     //   34: aload_3
/*    */     //   35: aastore
/*    */     //   36: dup
/*    */     //   37: iconst_2
/*    */     //   38: aload_1
/*    */     //   39: aastore
/*    */     //   40: invokestatic insertArguments : (Ljava/lang/invoke/MethodHandle;I[Ljava/lang/Object;)Ljava/lang/invoke/MethodHandle;
/*    */     //   43: aload_2
/*    */     //   44: invokestatic explicitCastArguments : (Ljava/lang/invoke/MethodHandle;Ljava/lang/invoke/MethodType;)Ljava/lang/invoke/MethodHandle;
/*    */     //   47: invokevirtual setTarget : (Ljava/lang/invoke/MethodHandle;)V
/*    */     //   50: goto -> 170
/*    */     //   53: astore #4
/*    */     //   55: new java/lang/RuntimeException
/*    */     //   58: dup
/*    */     //   59: new java/lang/StringBuilder
/*    */     //   62: dup
/*    */     //   63: invokespecial <init> : ()V
/*    */     //   66: ldc_w '樳ꑅ?㸕ᾱ᤾崕㘝뫲藯꧍?䡐ퟩオ耀剖'
/*    */     //   69: invokevirtual toCharArray : ()[C
/*    */     //   72: dup
/*    */     //   73: dup
/*    */     //   74: iconst_0
/*    */     //   75: dup_x1
/*    */     //   76: caload
/*    */     //   77: sipush #13667
/*    */     //   80: ixor
/*    */     //   81: i2c
/*    */     //   82: castore
/*    */     //   83: sipush #6878
/*    */     //   86: iconst_1
/*    */     //   87: iconst_5
/*    */     //   88: invokestatic A : (Ljava/lang/Object;SZI)Ljava/lang/String;
/*    */     //   91: invokevirtual append : (Ljava/lang/String;)Ljava/lang/StringBuilder;
/*    */     //   94: ldc_w '깦띋꺉⯢'
/*    */     //   97: invokevirtual toCharArray : ()[C
/*    */     //   100: dup
/*    */     //   101: dup
/*    */     //   102: iconst_2
/*    */     //   103: dup_x1
/*    */     //   104: caload
/*    */     //   105: sipush #23013
/*    */     //   108: ixor
/*    */     //   109: i2c
/*    */     //   110: castore
/*    */     //   111: sipush #26013
/*    */     //   114: iconst_1
/*    */     //   115: iconst_1
/*    */     //   116: invokestatic A : (Ljava/lang/Object;SZI)Ljava/lang/String;
/*    */     //   119: invokevirtual append : (Ljava/lang/String;)Ljava/lang/StringBuilder;
/*    */     //   122: aload_1
/*    */     //   123: invokevirtual append : (Ljava/lang/String;)Ljava/lang/StringBuilder;
/*    */     //   126: ldc_w '쀨ꌗʸ'
/*    */     //   129: invokevirtual toCharArray : ()[C
/*    */     //   132: dup
/*    */     //   133: dup
/*    */     //   134: iconst_2
/*    */     //   135: dup_x1
/*    */     //   136: caload
/*    */     //   137: sipush #2873
/*    */     //   140: ixor
/*    */     //   141: i2c
/*    */     //   142: castore
/*    */     //   143: sipush #15370
/*    */     //   146: iconst_0
/*    */     //   147: iconst_5
/*    */     //   148: invokestatic A : (Ljava/lang/Object;SZI)Ljava/lang/String;
/*    */     //   151: invokevirtual append : (Ljava/lang/String;)Ljava/lang/StringBuilder;
/*    */     //   154: aload_2
/*    */     //   155: invokevirtual toString : ()Ljava/lang/String;
/*    */     //   158: invokevirtual append : (Ljava/lang/String;)Ljava/lang/StringBuilder;
/*    */     //   161: invokevirtual toString : ()Ljava/lang/String;
/*    */     //   164: aload #4
/*    */     //   166: invokespecial <init> : (Ljava/lang/String;Ljava/lang/Throwable;)V
/*    */     //   169: athrow
/*    */     //   170: aload_3
/*    */     //   171: areturn
/*    */     // Exception table:
/*    */     //   from	to	target	type
/*    */     //   9	50	53	java/lang/Exception
/*    */   }
/*    */ }


/* Location:              C:\Users\BukkitBypass\Desktop\MatrixAC\AAC\AAC-spigot-5.2.0.jar!\me\konsolas\aac\io.class
 * Java compiler version: 8 (52.0)
 * JD-Core Version:       1.1.3
 */