/*    */ package me.konsolas.aac;public final class it { private final iy c; private final fn a;
/*    */   public List a() {
/*  3 */     return this.d;
/*    */   }
/*    */   private final List b; private final List d; private static final long e = nc.a(3160921870881766962L, -8029176685877284658L, MethodHandles.lookup().lookupClass()).a(271448168128766L); private static final String[] f;
/*    */   private static final String[] g;
/*    */   private static final Map h = new HashMap<>(13);
/*    */   
/*    */   public fn a() {
/* 10 */     return this.a;
/*    */   }
/*    */ 
/*    */ 
/*    */ 
/*    */ 
/*    */ 
/*    */ 
/*    */ 
/*    */ 
/*    */   
/*    */   public iy a() {
/* 22 */     return this.c;
/*    */   }
/*    */   
/*    */   @Nullable
/*    */   public Principal a(long paramLong) {
/*    */     // Byte code:
/*    */     //   0: getstatic me/konsolas/aac/it.e : J
/*    */     //   3: lload_1
/*    */     //   4: lxor
/*    */     //   5: lstore_1
/*    */     //   6: ldc2_w -3242438834575846462
/*    */     //   9: lload_1
/*    */     //   10: <illegal opcode> w : (JJ)[Lme/konsolas/aac/aN;
/*    */     //   15: astore_3
/*    */     //   16: aload_0
/*    */     //   17: getfield d : Ljava/util/List;
/*    */     //   20: aload_3
/*    */     //   21: ifnonnull -> 68
/*    */     //   24: invokeinterface isEmpty : ()Z
/*    */     //   29: ifne -> 77
/*    */     //   32: goto -> 45
/*    */     //   35: ldc2_w -3227973170713586443
/*    */     //   38: lload_1
/*    */     //   39: <illegal opcode> w : (Ljava/lang/Exception;JJ)Ljava/lang/Exception;
/*    */     //   44: athrow
/*    */     //   45: aload_0
/*    */     //   46: getfield d : Ljava/util/List;
/*    */     //   49: iconst_0
/*    */     //   50: invokeinterface get : (I)Ljava/lang/Object;
/*    */     //   55: goto -> 68
/*    */     //   58: ldc2_w -3227973170713586443
/*    */     //   61: lload_1
/*    */     //   62: <illegal opcode> w : (Ljava/lang/Exception;JJ)Ljava/lang/Exception;
/*    */     //   67: athrow
/*    */     //   68: checkcast java/security/cert/X509Certificate
/*    */     //   71: invokevirtual getSubjectX500Principal : ()Ljavax/security/auth/x500/X500Principal;
/*    */     //   74: goto -> 78
/*    */     //   77: aconst_null
/*    */     //   78: areturn
/*    */     // Line number table:
/*    */     //   Java source line number -> byte code offset
/*    */     //   #27	-> 16
/*    */     //   #28	-> 45
/*    */     //   #34	-> 77
/*    */     //   #49	-> 78
/*    */     // Exception table:
/*    */     //   from	to	target	type
/*    */     //   16	32	35	java/lang/IllegalStateException
/*    */     //   24	55	58	java/lang/IllegalStateException
/*    */   }
/*    */   
/*    */   public int hashCode() {
/* 31 */     int i = 17;
/*    */ 
/*    */ 
/*    */ 
/*    */ 
/*    */ 
/*    */ 
/*    */ 
/*    */ 
/*    */ 
/*    */ 
/*    */ 
/*    */ 
/*    */ 
/*    */ 
/*    */ 
/*    */ 
/*    */ 
/*    */ 
/*    */ 
/*    */ 
/*    */ 
/*    */ 
/*    */ 
/*    */ 
/*    */ 
/*    */ 
/*    */ 
/*    */     
/* 60 */     i = 31 * i + this.c.hashCode(); i = 31 * i + this.a.hashCode(); i = 31 * i + this.b.hashCode();
/*    */     i = 31 * i + this.d.hashCode();
/*    */     return i;
/*    */   } public static it a(iy paramiy, fn paramfn, List paramList1, List paramList2, long paramLong) { // Byte code:
/*    */     //   0: getstatic me/konsolas/aac/it.e : J
/*    */     //   3: lload #4
/*    */     //   5: lxor
/*    */     //   6: lstore #4
/*    */     //   8: aload_0
/*    */     //   9: ifnonnull -> 45
/*    */     //   12: new java/lang/NullPointerException
/*    */     //   15: dup
/*    */     //   16: sipush #19721
/*    */     //   19: ldc2_w 5705168659722350555
/*    */     //   22: lload #4
/*    */     //   24: lxor
/*    */     //   25: <illegal opcode> s : (IJ)Ljava/lang/String;
/*    */     //   30: invokespecial <init> : (Ljava/lang/String;)V
/*    */     //   33: athrow
/*    */     //   34: ldc2_w -8900263350821305411
/*    */     //   37: lload #4
/*    */     //   39: <illegal opcode> w : (Ljava/lang/Exception;JJ)Ljava/lang/Exception;
/*    */     //   44: athrow
/*    */     //   45: aload_1
/*    */     //   46: ifnonnull -> 81
/*    */     //   49: new java/lang/NullPointerException
/*    */     //   52: dup
/*    */     //   53: bipush #98
/*    */     //   55: ldc2_w 403321506358354617
/*    */     //   58: lload #4
/*    */     //   60: lxor
/*    */     //   61: <illegal opcode> s : (IJ)Ljava/lang/String;
/*    */     //   66: invokespecial <init> : (Ljava/lang/String;)V
/*    */     //   69: athrow
/*    */     //   70: ldc2_w -8900263350821305411
/*    */     //   73: lload #4
/*    */     //   75: <illegal opcode> w : (Ljava/lang/Exception;JJ)Ljava/lang/Exception;
/*    */     //   80: athrow
/*    */     //   81: new me/konsolas/aac/it
/*    */     //   84: dup
/*    */     //   85: aload_0
/*    */     //   86: aload_1
/*    */     //   87: aload_2
/*    */     //   88: invokestatic a : (Ljava/util/List;)Ljava/util/List;
/*    */     //   91: aload_3
/*    */     //   92: invokestatic a : (Ljava/util/List;)Ljava/util/List;
/*    */     //   95: invokespecial <init> : (Lme/konsolas/aac/iy;Lme/konsolas/aac/fn;Ljava/util/List;Ljava/util/List;)V
/*    */     //   98: areturn
/*    */     // Line number table:
/*    */     //   Java source line number -> byte code offset
/*    */     //   #33	-> 8
/*    */     //   #29	-> 45
/*    */     //   #6	-> 81
/*    */     //   #37	-> 92
/*    */     //   #30	-> 98
/*    */     // Exception table:
/*    */     //   from	to	target	type
/*    */     //   8	34	34	java/lang/IllegalStateException
/*    */     //   45	70	70	java/lang/IllegalStateException } public boolean equals(@Nullable Object paramObject) { // Byte code:
/*    */     //   0: getstatic me/konsolas/aac/it.e : J
/*    */     //   3: ldc2_w 133413009544594
/*    */     //   6: lxor
/*    */     //   7: lstore_2
/*    */     //   8: ldc2_w 6970037209969156216
/*    */     //   11: lload_2
/*    */     //   12: <illegal opcode> w : (JJ)[Lme/konsolas/aac/aN;
/*    */     //   17: astore #4
/*    */     //   19: aload_1
/*    */     //   20: aload #4
/*    */     //   22: ifnonnull -> 57
/*    */     //   25: instanceof me/konsolas/aac/it
/*    */     //   28: ifne -> 56
/*    */     //   31: goto -> 44
/*    */     //   34: ldc2_w 6956354321746995023
/*    */     //   37: lload_2
/*    */     //   38: <illegal opcode> w : (Ljava/lang/Exception;JJ)Ljava/lang/Exception;
/*    */     //   43: athrow
/*    */     //   44: iconst_0
/*    */     //   45: ireturn
/*    */     //   46: ldc2_w 6956354321746995023
/*    */     //   49: lload_2
/*    */     //   50: <illegal opcode> w : (Ljava/lang/Exception;JJ)Ljava/lang/Exception;
/*    */     //   55: athrow
/*    */     //   56: aload_1
/*    */     //   57: checkcast me/konsolas/aac/it
/*    */     //   60: astore #5
/*    */     //   62: aload_0
/*    */     //   63: getfield c : Lme/konsolas/aac/iy;
/*    */     //   66: aload #5
/*    */     //   68: getfield c : Lme/konsolas/aac/iy;
/*    */     //   71: invokevirtual equals : (Ljava/lang/Object;)Z
/*    */     //   74: aload #4
/*    */     //   76: ifnonnull -> 120
/*    */     //   79: ifeq -> 241
/*    */     //   82: goto -> 95
/*    */     //   85: ldc2_w 6956354321746995023
/*    */     //   88: lload_2
/*    */     //   89: <illegal opcode> w : (Ljava/lang/Exception;JJ)Ljava/lang/Exception;
/*    */     //   94: athrow
/*    */     //   95: aload_0
/*    */     //   96: getfield a : Lme/konsolas/aac/fn;
/*    */     //   99: aload #5
/*    */     //   101: getfield a : Lme/konsolas/aac/fn;
/*    */     //   104: invokevirtual equals : (Ljava/lang/Object;)Z
/*    */     //   107: goto -> 120
/*    */     //   110: ldc2_w 6956354321746995023
/*    */     //   113: lload_2
/*    */     //   114: <illegal opcode> w : (Ljava/lang/Exception;JJ)Ljava/lang/Exception;
/*    */     //   119: athrow
/*    */     //   120: aload #4
/*    */     //   122: ifnonnull -> 168
/*    */     //   125: ifeq -> 241
/*    */     //   128: goto -> 141
/*    */     //   131: ldc2_w 6956354321746995023
/*    */     //   134: lload_2
/*    */     //   135: <illegal opcode> w : (Ljava/lang/Exception;JJ)Ljava/lang/Exception;
/*    */     //   140: athrow
/*    */     //   141: aload_0
/*    */     //   142: getfield b : Ljava/util/List;
/*    */     //   145: aload #5
/*    */     //   147: getfield b : Ljava/util/List;
/*    */     //   150: invokeinterface equals : (Ljava/lang/Object;)Z
/*    */     //   155: goto -> 168
/*    */     //   158: ldc2_w 6956354321746995023
/*    */     //   161: lload_2
/*    */     //   162: <illegal opcode> w : (Ljava/lang/Exception;JJ)Ljava/lang/Exception;
/*    */     //   167: athrow
/*    */     //   168: aload #4
/*    */     //   170: ifnonnull -> 216
/*    */     //   173: ifeq -> 241
/*    */     //   176: goto -> 189
/*    */     //   179: ldc2_w 6956354321746995023
/*    */     //   182: lload_2
/*    */     //   183: <illegal opcode> w : (Ljava/lang/Exception;JJ)Ljava/lang/Exception;
/*    */     //   188: athrow
/*    */     //   189: aload_0
/*    */     //   190: getfield d : Ljava/util/List;
/*    */     //   193: aload #5
/*    */     //   195: getfield d : Ljava/util/List;
/*    */     //   198: invokeinterface equals : (Ljava/lang/Object;)Z
/*    */     //   203: goto -> 216
/*    */     //   206: ldc2_w 6956354321746995023
/*    */     //   209: lload_2
/*    */     //   210: <illegal opcode> w : (Ljava/lang/Exception;JJ)Ljava/lang/Exception;
/*    */     //   215: athrow
/*    */     //   216: aload #4
/*    */     //   218: ifnonnull -> 238
/*    */     //   221: ifeq -> 241
/*    */     //   224: goto -> 237
/*    */     //   227: ldc2_w 6956354321746995023
/*    */     //   230: lload_2
/*    */     //   231: <illegal opcode> w : (Ljava/lang/Exception;JJ)Ljava/lang/Exception;
/*    */     //   236: athrow
/*    */     //   237: iconst_1
/*    */     //   238: goto -> 242
/*    */     //   241: iconst_0
/*    */     //   242: ireturn
/*    */     // Line number table:
/*    */     //   Java source line number -> byte code offset
/*    */     //   #35	-> 19
/*    */     //   #18	-> 56
/*    */     //   #42	-> 62
/*    */     //   #61	-> 104
/*    */     //   #32	-> 150
/*    */     //   #52	-> 198
/*    */     //   #13	-> 242
/*    */     // Exception table:
/*    */     //   from	to	target	type
/*    */     //   19	31	34	java/lang/IllegalStateException
/*    */     //   25	46	46	java/lang/IllegalStateException
/*    */     //   62	82	85	java/lang/IllegalStateException
/*    */     //   79	107	110	java/lang/IllegalStateException
/*    */     //   120	128	131	java/lang/IllegalStateException
/*    */     //   125	155	158	java/lang/IllegalStateException
/*    */     //   168	176	179	java/lang/IllegalStateException
/*    */     //   173	203	206	java/lang/IllegalStateException
/*    */     //   216	224	227	java/lang/IllegalStateException }
/* 64 */   private it(iy paramiy, fn paramfn, List paramList1, List paramList2) { this.c = paramiy;
/*    */     this.a = paramfn;
/*    */     this.b = paramList1;
/*    */     this.d = paramList2; }
/*    */ 
/*    */   
/*    */   private List a(long paramLong, List paramList) {
/*    */     // Byte code:
/*    */     //   0: getstatic me/konsolas/aac/it.e : J
/*    */     //   3: lload_1
/*    */     //   4: lxor
/*    */     //   5: lstore_1
/*    */     //   6: ldc2_w 9042021776214752697
/*    */     //   9: lload_1
/*    */     //   10: <illegal opcode> w : (JJ)[Lme/konsolas/aac/aN;
/*    */     //   15: new java/util/ArrayList
/*    */     //   18: dup
/*    */     //   19: invokespecial <init> : ()V
/*    */     //   22: astore #5
/*    */     //   24: astore #4
/*    */     //   26: aload_3
/*    */     //   27: invokeinterface iterator : ()Ljava/util/Iterator;
/*    */     //   32: astore #6
/*    */     //   34: aload #6
/*    */     //   36: invokeinterface hasNext : ()Z
/*    */     //   41: ifeq -> 152
/*    */     //   44: aload #6
/*    */     //   46: invokeinterface next : ()Ljava/lang/Object;
/*    */     //   51: checkcast java/security/cert/Certificate
/*    */     //   54: astore #7
/*    */     //   56: aload #7
/*    */     //   58: instanceof java/security/cert/X509Certificate
/*    */     //   61: aload #4
/*    */     //   63: ifnonnull -> 146
/*    */     //   66: ifeq -> 123
/*    */     //   69: goto -> 82
/*    */     //   72: ldc2_w 9027696804743658126
/*    */     //   75: lload_1
/*    */     //   76: <illegal opcode> w : (Ljava/lang/Exception;JJ)Ljava/lang/Exception;
/*    */     //   81: athrow
/*    */     //   82: aload #5
/*    */     //   84: aload #7
/*    */     //   86: checkcast java/security/cert/X509Certificate
/*    */     //   89: invokevirtual getSubjectDN : ()Ljava/security/Principal;
/*    */     //   92: invokestatic valueOf : (Ljava/lang/Object;)Ljava/lang/String;
/*    */     //   95: invokevirtual add : (Ljava/lang/Object;)Z
/*    */     //   98: pop
/*    */     //   99: aload #4
/*    */     //   101: lload_1
/*    */     //   102: lconst_0
/*    */     //   103: lcmp
/*    */     //   104: iflt -> 149
/*    */     //   107: ifnull -> 147
/*    */     //   110: goto -> 123
/*    */     //   113: ldc2_w 9027696804743658126
/*    */     //   116: lload_1
/*    */     //   117: <illegal opcode> w : (Ljava/lang/Exception;JJ)Ljava/lang/Exception;
/*    */     //   122: athrow
/*    */     //   123: aload #5
/*    */     //   125: aload #7
/*    */     //   127: invokevirtual getType : ()Ljava/lang/String;
/*    */     //   130: invokevirtual add : (Ljava/lang/Object;)Z
/*    */     //   133: goto -> 146
/*    */     //   136: ldc2_w 9027696804743658126
/*    */     //   139: lload_1
/*    */     //   140: <illegal opcode> w : (Ljava/lang/Exception;JJ)Ljava/lang/Exception;
/*    */     //   145: athrow
/*    */     //   146: pop
/*    */     //   147: aload #4
/*    */     //   149: ifnull -> 34
/*    */     //   152: aload #5
/*    */     //   154: lload_1
/*    */     //   155: lconst_0
/*    */     //   156: lcmp
/*    */     //   157: ifle -> 51
/*    */     //   160: areturn
/*    */     // Line number table:
/*    */     //   Java source line number -> byte code offset
/*    */     //   #38	-> 15
/*    */     //   #63	-> 26
/*    */     //   #19	-> 56
/*    */     //   #59	-> 82
/*    */     //   #20	-> 123
/*    */     //   #68	-> 147
/*    */     //   #2	-> 152
/*    */     // Exception table:
/*    */     //   from	to	target	type
/*    */     //   56	69	72	java/lang/IllegalStateException
/*    */     //   66	110	113	java/lang/IllegalStateException
/*    */     //   82	133	136	java/lang/IllegalStateException
/*    */   }
/*    */   
/*    */   @Nullable
/*    */   public Principal b(long paramLong) {
/*    */     // Byte code:
/*    */     //   0: getstatic me/konsolas/aac/it.e : J
/*    */     //   3: lload_1
/*    */     //   4: lxor
/*    */     //   5: lstore_1
/*    */     //   6: ldc2_w 4805532456648196722
/*    */     //   9: lload_1
/*    */     //   10: <illegal opcode> w : (JJ)[Lme/konsolas/aac/aN;
/*    */     //   15: astore_3
/*    */     //   16: aload_0
/*    */     //   17: getfield b : Ljava/util/List;
/*    */     //   20: aload_3
/*    */     //   21: ifnonnull -> 68
/*    */     //   24: invokeinterface isEmpty : ()Z
/*    */     //   29: ifne -> 77
/*    */     //   32: goto -> 45
/*    */     //   35: ldc2_w 4792897359521285445
/*    */     //   38: lload_1
/*    */     //   39: <illegal opcode> w : (Ljava/lang/Exception;JJ)Ljava/lang/Exception;
/*    */     //   44: athrow
/*    */     //   45: aload_0
/*    */     //   46: getfield b : Ljava/util/List;
/*    */     //   49: iconst_0
/*    */     //   50: invokeinterface get : (I)Ljava/lang/Object;
/*    */     //   55: goto -> 68
/*    */     //   58: ldc2_w 4792897359521285445
/*    */     //   61: lload_1
/*    */     //   62: <illegal opcode> w : (Ljava/lang/Exception;JJ)Ljava/lang/Exception;
/*    */     //   67: athrow
/*    */     //   68: checkcast java/security/cert/X509Certificate
/*    */     //   71: invokevirtual getSubjectX500Principal : ()Ljavax/security/auth/x500/X500Principal;
/*    */     //   74: goto -> 78
/*    */     //   77: aconst_null
/*    */     //   78: areturn
/*    */     // Line number table:
/*    */     //   Java source line number -> byte code offset
/*    */     //   #43	-> 16
/*    */     //   #66	-> 45
/*    */     //   #57	-> 77
/*    */     //   #26	-> 78
/*    */     // Exception table:
/*    */     //   from	to	target	type
/*    */     //   16	32	35	java/lang/IllegalStateException
/*    */     //   24	55	58	java/lang/IllegalStateException
/*    */   }
/*    */   
/*    */   public static it a(SSLSession paramSSLSession, long paramLong) {
/*    */     // Byte code:
/*    */     //   0: getstatic me/konsolas/aac/it.e : J
/*    */     //   3: lload_1
/*    */     //   4: lxor
/*    */     //   5: lstore_1
/*    */     //   6: lload_1
/*    */     //   7: dup2
/*    */     //   8: ldc2_w 1245745068791
/*    */     //   11: lxor
/*    */     //   12: lstore_3
/*    */     //   13: dup2
/*    */     //   14: ldc2_w 60194224232790
/*    */     //   17: lxor
/*    */     //   18: lstore #5
/*    */     //   20: pop2
/*    */     //   21: ldc2_w 4940064764959147084
/*    */     //   24: lload_1
/*    */     //   25: <illegal opcode> w : (JJ)[Lme/konsolas/aac/aN;
/*    */     //   30: aload_0
/*    */     //   31: invokeinterface getCipherSuite : ()Ljava/lang/String;
/*    */     //   36: astore #8
/*    */     //   38: astore #7
/*    */     //   40: aload #8
/*    */     //   42: aload #7
/*    */     //   44: ifnonnull -> 107
/*    */     //   47: ifnonnull -> 94
/*    */     //   50: goto -> 63
/*    */     //   53: ldc2_w 4953333097167618939
/*    */     //   56: lload_1
/*    */     //   57: <illegal opcode> w : (Ljava/lang/Exception;JJ)Ljava/lang/Exception;
/*    */     //   62: athrow
/*    */     //   63: new java/lang/IllegalStateException
/*    */     //   66: dup
/*    */     //   67: sipush #15194
/*    */     //   70: ldc2_w 9118777484209166662
/*    */     //   73: lload_1
/*    */     //   74: lxor
/*    */     //   75: <illegal opcode> s : (IJ)Ljava/lang/String;
/*    */     //   80: invokespecial <init> : (Ljava/lang/String;)V
/*    */     //   83: athrow
/*    */     //   84: ldc2_w 4953333097167618939
/*    */     //   87: lload_1
/*    */     //   88: <illegal opcode> w : (Ljava/lang/Exception;JJ)Ljava/lang/Exception;
/*    */     //   93: athrow
/*    */     //   94: sipush #4671
/*    */     //   97: ldc2_w 5650194464706113568
/*    */     //   100: lload_1
/*    */     //   101: lxor
/*    */     //   102: <illegal opcode> s : (IJ)Ljava/lang/String;
/*    */     //   107: aload #7
/*    */     //   109: ifnonnull -> 166
/*    */     //   112: aload #8
/*    */     //   114: invokevirtual equals : (Ljava/lang/Object;)Z
/*    */     //   117: ifeq -> 164
/*    */     //   120: goto -> 133
/*    */     //   123: ldc2_w 4953333097167618939
/*    */     //   126: lload_1
/*    */     //   127: <illegal opcode> w : (Ljava/lang/Exception;JJ)Ljava/lang/Exception;
/*    */     //   132: athrow
/*    */     //   133: new java/io/IOException
/*    */     //   136: dup
/*    */     //   137: sipush #21062
/*    */     //   140: ldc2_w 1399800456576069716
/*    */     //   143: lload_1
/*    */     //   144: lxor
/*    */     //   145: <illegal opcode> s : (IJ)Ljava/lang/String;
/*    */     //   150: invokespecial <init> : (Ljava/lang/String;)V
/*    */     //   153: athrow
/*    */     //   154: ldc2_w 4953333097167618939
/*    */     //   157: lload_1
/*    */     //   158: <illegal opcode> w : (Ljava/lang/Exception;JJ)Ljava/lang/Exception;
/*    */     //   163: athrow
/*    */     //   164: aload #8
/*    */     //   166: lload_3
/*    */     //   167: invokestatic a : (Ljava/lang/String;J)Lme/konsolas/aac/fn;
/*    */     //   170: astore #9
/*    */     //   172: aload_0
/*    */     //   173: invokeinterface getProtocol : ()Ljava/lang/String;
/*    */     //   178: astore #10
/*    */     //   180: aload #10
/*    */     //   182: aload #7
/*    */     //   184: lload_1
/*    */     //   185: lconst_0
/*    */     //   186: lcmp
/*    */     //   187: ifle -> 255
/*    */     //   190: ifnonnull -> 253
/*    */     //   193: ifnonnull -> 240
/*    */     //   196: goto -> 209
/*    */     //   199: ldc2_w 4953333097167618939
/*    */     //   202: lload_1
/*    */     //   203: <illegal opcode> w : (Ljava/lang/Exception;JJ)Ljava/lang/Exception;
/*    */     //   208: athrow
/*    */     //   209: new java/lang/IllegalStateException
/*    */     //   212: dup
/*    */     //   213: sipush #22897
/*    */     //   216: ldc2_w 4611932896505330530
/*    */     //   219: lload_1
/*    */     //   220: lxor
/*    */     //   221: <illegal opcode> s : (IJ)Ljava/lang/String;
/*    */     //   226: invokespecial <init> : (Ljava/lang/String;)V
/*    */     //   229: athrow
/*    */     //   230: ldc2_w 4953333097167618939
/*    */     //   233: lload_1
/*    */     //   234: <illegal opcode> w : (Ljava/lang/Exception;JJ)Ljava/lang/Exception;
/*    */     //   239: athrow
/*    */     //   240: sipush #17272
/*    */     //   243: ldc2_w 7580039722115064169
/*    */     //   246: lload_1
/*    */     //   247: lxor
/*    */     //   248: <illegal opcode> s : (IJ)Ljava/lang/String;
/*    */     //   253: aload #7
/*    */     //   255: ifnonnull -> 312
/*    */     //   258: aload #10
/*    */     //   260: invokevirtual equals : (Ljava/lang/Object;)Z
/*    */     //   263: ifeq -> 310
/*    */     //   266: goto -> 279
/*    */     //   269: ldc2_w 4953333097167618939
/*    */     //   272: lload_1
/*    */     //   273: <illegal opcode> w : (Ljava/lang/Exception;JJ)Ljava/lang/Exception;
/*    */     //   278: athrow
/*    */     //   279: new java/io/IOException
/*    */     //   282: dup
/*    */     //   283: sipush #29880
/*    */     //   286: ldc2_w 2508244338329310886
/*    */     //   289: lload_1
/*    */     //   290: lxor
/*    */     //   291: <illegal opcode> s : (IJ)Ljava/lang/String;
/*    */     //   296: invokespecial <init> : (Ljava/lang/String;)V
/*    */     //   299: athrow
/*    */     //   300: ldc2_w 4953333097167618939
/*    */     //   303: lload_1
/*    */     //   304: <illegal opcode> w : (Ljava/lang/Exception;JJ)Ljava/lang/Exception;
/*    */     //   309: athrow
/*    */     //   310: aload #10
/*    */     //   312: lload #5
/*    */     //   314: dup2_x1
/*    */     //   315: pop2
/*    */     //   316: invokestatic a : (JLjava/lang/String;)Lme/konsolas/aac/iy;
/*    */     //   319: astore #11
/*    */     //   321: aload_0
/*    */     //   322: invokeinterface getPeerCertificates : ()[Ljava/security/cert/Certificate;
/*    */     //   327: astore #12
/*    */     //   329: goto -> 337
/*    */     //   332: astore #13
/*    */     //   334: aconst_null
/*    */     //   335: astore #12
/*    */     //   337: aload #12
/*    */     //   339: aload #7
/*    */     //   341: ifnonnull -> 362
/*    */     //   344: ifnull -> 368
/*    */     //   347: goto -> 360
/*    */     //   350: ldc2_w 4953333097167618939
/*    */     //   353: lload_1
/*    */     //   354: <illegal opcode> w : (Ljava/lang/Exception;JJ)Ljava/lang/Exception;
/*    */     //   359: athrow
/*    */     //   360: aload #12
/*    */     //   362: invokestatic a : ([Ljava/lang/Object;)Ljava/util/List;
/*    */     //   365: goto -> 371
/*    */     //   368: invokestatic emptyList : ()Ljava/util/List;
/*    */     //   371: astore #13
/*    */     //   373: aload_0
/*    */     //   374: invokeinterface getLocalCertificates : ()[Ljava/security/cert/Certificate;
/*    */     //   379: astore #14
/*    */     //   381: aload #14
/*    */     //   383: aload #7
/*    */     //   385: ifnonnull -> 406
/*    */     //   388: ifnull -> 412
/*    */     //   391: goto -> 404
/*    */     //   394: ldc2_w 4953333097167618939
/*    */     //   397: lload_1
/*    */     //   398: <illegal opcode> w : (Ljava/lang/Exception;JJ)Ljava/lang/Exception;
/*    */     //   403: athrow
/*    */     //   404: aload #14
/*    */     //   406: invokestatic a : ([Ljava/lang/Object;)Ljava/util/List;
/*    */     //   409: goto -> 415
/*    */     //   412: invokestatic emptyList : ()Ljava/util/List;
/*    */     //   415: astore #15
/*    */     //   417: new me/konsolas/aac/it
/*    */     //   420: dup
/*    */     //   421: aload #11
/*    */     //   423: aload #9
/*    */     //   425: aload #13
/*    */     //   427: aload #15
/*    */     //   429: invokespecial <init> : (Lme/konsolas/aac/iy;Lme/konsolas/aac/fn;Ljava/util/List;Ljava/util/List;)V
/*    */     //   432: areturn
/*    */     // Line number table:
/*    */     //   Java source line number -> byte code offset
/*    */     //   #44	-> 30
/*    */     //   #17	-> 40
/*    */     //   #46	-> 94
/*    */     //   #9	-> 133
/*    */     //   #7	-> 164
/*    */     //   #11	-> 172
/*    */     //   #1	-> 180
/*    */     //   #21	-> 240
/*    */     //   #67	-> 310
/*    */     //   #16	-> 321
/*    */     //   #25	-> 329
/*    */     //   #55	-> 332
/*    */     //   #62	-> 334
/*    */     //   #36	-> 337
/*    */     //   #41	-> 360
/*    */     //   #45	-> 368
/*    */     //   #24	-> 373
/*    */     //   #40	-> 381
/*    */     //   #4	-> 404
/*    */     //   #54	-> 412
/*    */     //   #53	-> 417
/*    */     // Exception table:
/*    */     //   from	to	target	type
/*    */     //   40	50	53	javax/net/ssl/SSLPeerUnverifiedException
/*    */     //   47	84	84	javax/net/ssl/SSLPeerUnverifiedException
/*    */     //   107	120	123	javax/net/ssl/SSLPeerUnverifiedException
/*    */     //   112	154	154	javax/net/ssl/SSLPeerUnverifiedException
/*    */     //   180	196	199	javax/net/ssl/SSLPeerUnverifiedException
/*    */     //   193	230	230	javax/net/ssl/SSLPeerUnverifiedException
/*    */     //   253	266	269	javax/net/ssl/SSLPeerUnverifiedException
/*    */     //   258	300	300	javax/net/ssl/SSLPeerUnverifiedException
/*    */     //   321	329	332	javax/net/ssl/SSLPeerUnverifiedException
/*    */     //   337	347	350	javax/net/ssl/SSLPeerUnverifiedException
/*    */     //   381	391	394	javax/net/ssl/SSLPeerUnverifiedException
/*    */   }
/*    */   
/*    */   public List b() {
/*    */     return this.b;
/*    */   }
/*    */   
/*    */   public String toString() {
/*    */     // Byte code:
/*    */     //   0: getstatic me/konsolas/aac/it.e : J
/*    */     //   3: ldc2_w 30144924636274
/*    */     //   6: lxor
/*    */     //   7: lstore_1
/*    */     //   8: lload_1
/*    */     //   9: dup2
/*    */     //   10: ldc2_w 5102554851821
/*    */     //   13: lxor
/*    */     //   14: lstore_3
/*    */     //   15: pop2
/*    */     //   16: new java/lang/StringBuilder
/*    */     //   19: dup
/*    */     //   20: invokespecial <init> : ()V
/*    */     //   23: sipush #273
/*    */     //   26: ldc2_w 1768502876626323152
/*    */     //   29: lload_1
/*    */     //   30: lxor
/*    */     //   31: <illegal opcode> s : (IJ)Ljava/lang/String;
/*    */     //   36: invokevirtual append : (Ljava/lang/String;)Ljava/lang/StringBuilder;
/*    */     //   39: aload_0
/*    */     //   40: getfield c : Lme/konsolas/aac/iy;
/*    */     //   43: invokevirtual append : (Ljava/lang/Object;)Ljava/lang/StringBuilder;
/*    */     //   46: sipush #7617
/*    */     //   49: ldc2_w 2011823885273864707
/*    */     //   52: lload_1
/*    */     //   53: lxor
/*    */     //   54: <illegal opcode> s : (IJ)Ljava/lang/String;
/*    */     //   59: invokevirtual append : (Ljava/lang/String;)Ljava/lang/StringBuilder;
/*    */     //   62: aload_0
/*    */     //   63: getfield a : Lme/konsolas/aac/fn;
/*    */     //   66: invokevirtual append : (Ljava/lang/Object;)Ljava/lang/StringBuilder;
/*    */     //   69: sipush #3833
/*    */     //   72: ldc2_w 8879969766650480957
/*    */     //   75: lload_1
/*    */     //   76: lxor
/*    */     //   77: <illegal opcode> s : (IJ)Ljava/lang/String;
/*    */     //   82: invokevirtual append : (Ljava/lang/String;)Ljava/lang/StringBuilder;
/*    */     //   85: aload_0
/*    */     //   86: aload_0
/*    */     //   87: getfield b : Ljava/util/List;
/*    */     //   90: lload_3
/*    */     //   91: dup2_x1
/*    */     //   92: pop2
/*    */     //   93: invokespecial a : (JLjava/util/List;)Ljava/util/List;
/*    */     //   96: invokevirtual append : (Ljava/lang/Object;)Ljava/lang/StringBuilder;
/*    */     //   99: sipush #5115
/*    */     //   102: ldc2_w 116762979199063096
/*    */     //   105: lload_1
/*    */     //   106: lxor
/*    */     //   107: <illegal opcode> s : (IJ)Ljava/lang/String;
/*    */     //   112: invokevirtual append : (Ljava/lang/String;)Ljava/lang/StringBuilder;
/*    */     //   115: aload_0
/*    */     //   116: aload_0
/*    */     //   117: getfield d : Ljava/util/List;
/*    */     //   120: lload_3
/*    */     //   121: dup2_x1
/*    */     //   122: pop2
/*    */     //   123: invokespecial a : (JLjava/util/List;)Ljava/util/List;
/*    */     //   126: invokevirtual append : (Ljava/lang/Object;)Ljava/lang/StringBuilder;
/*    */     //   129: bipush #125
/*    */     //   131: invokevirtual append : (C)Ljava/lang/StringBuilder;
/*    */     //   134: invokevirtual toString : ()Ljava/lang/String;
/*    */     //   137: areturn
/*    */     // Line number table:
/*    */     //   Java source line number -> byte code offset
/*    */     //   #65	-> 16
/*    */     //   #15	-> 93
/*    */     //   #23	-> 123
/*    */     //   #14	-> 137
/*    */   }
/*    */   
/*    */   static {
/*    */     long l = e ^ 0xCB61F9E8D7BL;
/*    */     "ଯঀ햜腆ࠜぐݭ뼆ᕺ?㙷兀ᎅ?왊⻯퀰쏋ꉫ䬰".toCharArray()[5] = (char)("ଯঀ햜腆ࠜぐݭ뼆ᕺ?㙷兀ᎅ?왊⻯퀰쏋ꉫ䬰".toCharArray()[5] ^ 0x2F62);
/*    */     "븐苇ᯡĳ".toCharArray()[1] = (char)("븐苇ᯡĳ".toCharArray()[1] ^ 0xE1D);
/*    */     (new byte[8])[0] = (byte)(int)(l >>> 56L);
/*    */     for (byte b1 = 1; b1 < 8; b1++)
/*    */       (new byte[8])[b1] = (byte)(int)(l << b1 * 8 >>> 56L); 
/*    */     Cipher cipher;
/*    */     (cipher = Cipher.getInstance(dP$dt.X("ଯঀ햜腆ࠜぐݭ뼆ᕺ?㙷兀ᎅ?왊⻯퀰쏋ꉫ䬰".toCharArray(), (short)25561, true, false))).init(2, SecretKeyFactory.getInstance(dP$dt.X("븐苇ᯡĳ".toCharArray(), (short)6734, false, true)).generateSecret(new DESKeySpec(new byte[8])), new IvParameterSpec(new byte[8]));
/*    */     String[] arrayOfString = new String[12];
/*    */     boolean bool = false;
/*    */     "噔쩕࠹뗈䐫膪驵ᝲㅲ찠ﱥ㤐䈥ꀚꖯ澍畵㮪᤹蔷乌컎냸۝㊛럥ᷝ?瑩䦲ꖠ㯈喓퐪튵⦭柔㼋礶ᗀ깪ꮜꙈ៎Ϣ掰㺦劕䋐企ᖻ쎘攄홌⃻Í旦玼꾚齗⟿腕㘔㗥㢳놏㒎譋샅鹬缜媻ڪ줼㢏㖞ⵢṆ鿯ᛊ닞脪탄ᧁ㤽?꫚ⶅ崗ᠤ餪?롕哳ﶬఈᱶ閿앏㑾㪡椴赉啕䞉繙卆?㨵ᅡ轊?瘥瑮駗퍏ⷉ笐ึ?穴锉⠳휯?艃⋑퐯ᩒ뾫ퟤᒌ䒡?덓꽒洟⅐ꀳ䦃◚᯵楯㠠㓬⨬ҁ﫡쎒?糜Ꝥ?אָ熻䛉螄ﱣ݋즒勿בֿ൜襥蘧숣成⇙닇縯꘷?齂?᣹䵉婷ﻅ꿣ᒕ?埉롯使ࠩ鼩쥉揓ธ凾¸䓰溆갹度䂫㟜㶿?쌧཯엄甩ꎪ㗾ｭ﹐㌌튋و䡃ڰ↵꧙䱇ಫ懭製ᝩဎ㈶戧쵅ൗ㶯렞牐᮷普蹖켍踔뜺䷎?㚢杧粞?䛯싙ӫ㛤卜븉ᙕ䠎䰤ꂑ쟀ʖ䍴㡀뭻햧ᑌઁ쓍殉뭯ᚖ⪘䍜빙偈缍용ﲎ墖拟⫢툿啚ᵅ杈細ᔥ벞햏⦋锪⮊쯽ﾮ滈อ굥룰鮊Ფ嚘非⭢纽࿳넶줰㈵ꍑ滩躦炈譠땪ᰛ쌅辻㘓頵?泅ﾳ?퐇뭈⺜뼨۾褪䷀?礳ㄭꘪ睬渹浰켛ꬅ玢㴎꼅๘丆ᴆ䜆齨䭘謚됱ᰳ立嚓騨㘢洉ᤙᭃ뻻떼씿?魣ㄙ?赯毻㝜".toCharArray()[385] = (char)("噔쩕࠹뗈䐫膪驵ᝲㅲ찠ﱥ㤐䈥ꀚꖯ澍畵㮪᤹蔷乌컎냸۝㊛럥ᷝ?瑩䦲ꖠ㯈喓퐪튵⦭柔㼋礶ᗀ깪ꮜꙈ៎Ϣ掰㺦劕䋐企ᖻ쎘攄홌⃻Í旦玼꾚齗⟿腕㘔㗥㢳놏㒎譋샅鹬缜媻ڪ줼㢏㖞ⵢṆ鿯ᛊ닞脪탄ᧁ㤽?꫚ⶅ崗ᠤ餪?롕哳ﶬఈᱶ閿앏㑾㪡椴赉啕䞉繙卆?㨵ᅡ轊?瘥瑮駗퍏ⷉ笐ึ?穴锉⠳휯?艃⋑퐯ᩒ뾫ퟤᒌ䒡?덓꽒洟⅐ꀳ䦃◚᯵楯㠠㓬⨬ҁ﫡쎒?糜Ꝥ?אָ熻䛉螄ﱣ݋즒勿בֿ൜襥蘧숣成⇙닇縯꘷?齂?᣹䵉婷ﻅ꿣ᒕ?埉롯使ࠩ鼩쥉揓ธ凾¸䓰溆갹度䂫㟜㶿?쌧཯엄甩ꎪ㗾ｭ﹐㌌튋و䡃ڰ↵꧙䱇ಫ懭製ᝩဎ㈶戧쵅ൗ㶯렞牐᮷普蹖켍踔뜺䷎?㚢杧粞?䛯싙ӫ㛤卜븉ᙕ䠎䰤ꂑ쟀ʖ䍴㡀뭻햧ᑌઁ쓍殉뭯ᚖ⪘䍜빙偈缍용ﲎ墖拟⫢툿啚ᵅ杈細ᔥ벞햏⦋锪⮊쯽ﾮ滈อ굥룰鮊Ფ嚘非⭢纽࿳넶줰㈵ꍑ滩躦炈譠땪ᰛ쌅辻㘓頵?泅ﾳ?퐇뭈⺜뼨۾褪䷀?礳ㄭꘪ睬渹浰켛ꬅ玢㴎꼅๘丆ᴆ䜆齨䭘謚됱ᰳ立嚓騨㘢洉ᤙᭃ뻻떼씿?魣ㄙ?赯毻㝜".toCharArray()[385] ^ 0x62A9);
/*    */     String str;
/*    */     int i = (str = dP$dt.X("噔쩕࠹뗈䐫膪驵ᝲㅲ찠ﱥ㤐䈥ꀚꖯ澍畵㮪᤹蔷乌컎냸۝㊛럥ᷝ?瑩䦲ꖠ㯈喓퐪튵⦭柔㼋礶ᗀ깪ꮜꙈ៎Ϣ掰㺦劕䋐企ᖻ쎘攄홌⃻Í旦玼꾚齗⟿腕㘔㗥㢳놏㒎譋샅鹬缜媻ڪ줼㢏㖞ⵢṆ鿯ᛊ닞脪탄ᧁ㤽?꫚ⶅ崗ᠤ餪?롕哳ﶬఈᱶ閿앏㑾㪡椴赉啕䞉繙卆?㨵ᅡ轊?瘥瑮駗퍏ⷉ笐ึ?穴锉⠳휯?艃⋑퐯ᩒ뾫ퟤᒌ䒡?덓꽒洟⅐ꀳ䦃◚᯵楯㠠㓬⨬ҁ﫡쎒?糜Ꝥ?אָ熻䛉螄ﱣ݋즒勿בֿ൜襥蘧숣成⇙닇縯꘷?齂?᣹䵉婷ﻅ꿣ᒕ?埉롯使ࠩ鼩쥉揓ธ凾¸䓰溆갹度䂫㟜㶿?쌧཯엄甩ꎪ㗾ｭ﹐㌌튋و䡃ڰ↵꧙䱇ಫ懭製ᝩဎ㈶戧쵅ൗ㶯렞牐᮷普蹖켍踔뜺䷎?㚢杧粞?䛯싙ӫ㛤卜븉ᙕ䠎䰤ꂑ쟀ʖ䍴㡀뭻햧ᑌઁ쓍殉뭯ᚖ⪘䍜빙偈缍용ﲎ墖拟⫢툿啚ᵅ杈細ᔥ벞햏⦋锪⮊쯽ﾮ滈อ굥룰鮊Ფ嚘非⭢纽࿳넶줰㈵ꍑ滩躦炈譠땪ᰛ쌅辻㘓頵?泅ﾳ?퐇뭈⺜뼨۾褪䷀?礳ㄭꘪ睬渹浰켛ꬅ玢㴎꼅๘丆ᴆ䜆齨䭘謚됱ᰳ立嚓騨㘢洉ᤙᭃ뻻떼씿?魣ㄙ?赯毻㝜".toCharArray(), (short)29039, true, false)).length();
/*    */     byte b2 = 40;
/*    */     byte b = -1;
/*    */     while (true);
/*    */   }
/*    */   
/*    */   private static Exception a(Exception paramException) {
/*    */     return paramException;
/*    */   }
/*    */   
/*    */   private static String a(byte[] paramArrayOfbyte) {
/*    */     byte b1 = 0;
/*    */     int i;
/*    */     char[] arrayOfChar = new char[i = paramArrayOfbyte.length];
/*    */     for (byte b2 = 0; b2 < i; b2++) {
/*    */       int j;
/*    */       if ((j = 0xFF & paramArrayOfbyte[b2]) < 192) {
/*    */         arrayOfChar[b1++] = (char)j;
/*    */       } else if (j < 224) {
/*    */         char c = (char)((char)(j & 0x1F) << 6);
/*    */         j = paramArrayOfbyte[++b2];
/*    */         c = (char)(c | (char)(j & 0x3F));
/*    */         arrayOfChar[b1++] = c;
/*    */       } else if (b2 < i - 2) {
/*    */         char c = (char)((char)(j & 0xF) << 12);
/*    */         j = paramArrayOfbyte[++b2];
/*    */         c = (char)(c | (char)(j & 0x3F) << 6);
/*    */         j = paramArrayOfbyte[++b2];
/*    */         c = (char)(c | (char)(j & 0x3F));
/*    */         arrayOfChar[b1++] = c;
/*    */       } 
/*    */     } 
/*    */     return new String(arrayOfChar, 0, b1);
/*    */   }
/*    */   
/*    */   private static String a(int paramInt, long paramLong) {
/*    */     int i = paramInt ^ (int)(paramLong & 0x7FFFL) ^ 0x667E;
/*    */     if (g[i] == null) {
/*    */       Object[] arrayOfObject;
/*    */       try {
/*    */         Long long_ = Long.valueOf(Thread.currentThread().getId());
/*    */         arrayOfObject = (Object[])h.get(long_);
/*    */         if (arrayOfObject == null) {
/*    */           arrayOfObject = new Object[3];
/*    */           "知쯔Ꟍㄸḫᖵ鎡Რ㰜ꕮ魮끩⿍뤀첃㖅㈉ꋆ勳".toCharArray()[8] = (char)("知쯔Ꟍㄸḫᖵ鎡Რ㰜ꕮ魮끩⿍뤀첃㖅㈉ꋆ勳".toCharArray()[8] ^ 0x4DB6);
/*    */           arrayOfObject[0] = Cipher.getInstance(da$gx.U("知쯔Ꟍㄸḫᖵ鎡Რ㰜ꕮ魮끩⿍뤀첃㖅㈉ꋆ勳".toCharArray(), (short)26301, false, false));
/*    */           "䳿?肱秵".toCharArray()[2] = (char)("䳿?肱秵".toCharArray()[2] ^ 0xD47);
/*    */           arrayOfObject[1] = SecretKeyFactory.getInstance(da$gx.U("䳿?肱秵".toCharArray(), (short)22708, false, true));
/*    */           arrayOfObject[2] = new IvParameterSpec(new byte[8]);
/*    */           h.put(long_, arrayOfObject);
/*    */         } 
/*    */       } catch (Exception exception) {
/*    */         "떵뢅뻶犽料劣免땗ꢗᏫꘙ雉濫倌䑲ଏ".toCharArray()[11] = (char)("떵뢅뻶犽料劣免땗ꢗᏫꘙ雉濫倌䑲ଏ".toCharArray()[11] ^ 0x7A38);
/*    */         throw new RuntimeException(da$gx.U("떵뢅뻶犽料劣免땗ꢗᏫꘙ雉濫倌䑲ଏ".toCharArray(), (short)16331, true, true), exception);
/*    */       } 
/*    */       byte[] arrayOfByte1 = new byte[8];
/*    */       arrayOfByte1[0] = (byte)(int)(paramLong >>> 56L);
/*    */       for (byte b = 1; b < 8; b++)
/*    */         arrayOfByte1[b] = (byte)(int)(paramLong << b * 8 >>> 56L); 
/*    */       DESKeySpec dESKeySpec = new DESKeySpec(arrayOfByte1);
/*    */       SecretKey secretKey = ((SecretKeyFactory)arrayOfObject[1]).generateSecret(dESKeySpec);
/*    */       ((Cipher)arrayOfObject[0]).init(2, secretKey, (IvParameterSpec)arrayOfObject[2]);
/*    */       "䬠缪䭬К⥠騱ᑔ逖?伩".toCharArray()[0] = (char)("䬠缪䭬К⥠騱ᑔ逖?伩".toCharArray()[0] ^ 0x2405);
/*    */       byte[] arrayOfByte2 = f[i].getBytes(da$gx.U("䬠缪䭬К⥠騱ᑔ逖?伩".toCharArray(), (short)26681, false, true));
/*    */       g[i] = a(((Cipher)arrayOfObject[0]).doFinal(arrayOfByte2));
/*    */     } 
/*    */     return g[i];
/*    */   }
/*    */   
/*    */   private static Object a(MethodHandles.Lookup paramLookup, MutableCallSite paramMutableCallSite, String paramString, Object[] paramArrayOfObject) {
/*    */     int i = ((Integer)paramArrayOfObject[0]).intValue();
/*    */     long l = ((Long)paramArrayOfObject[1]).longValue();
/*    */     String str = a(i, l);
/*    */     MethodHandle methodHandle = MethodHandles.constant(String.class, str);
/*    */     paramMutableCallSite.setTarget(MethodHandles.dropArguments(methodHandle, 0, new Class[] { int.class, long.class }));
/*    */     return str;
/*    */   }
/*    */   
/*    */   private static CallSite a(MethodHandles.Lookup paramLookup, String paramString, MethodType paramMethodType) {
/*    */     // Byte code:
/*    */     //   0: new java/lang/invoke/MutableCallSite
/*    */     //   3: dup
/*    */     //   4: aload_2
/*    */     //   5: invokespecial <init> : (Ljava/lang/invoke/MethodType;)V
/*    */     //   8: astore_3
/*    */     //   9: aload_3
/*    */     //   10: ldc_w
/*    */     //   13: ldc_w [Ljava/lang/Object;
/*    */     //   16: aload_2
/*    */     //   17: invokevirtual parameterCount : ()I
/*    */     //   20: invokevirtual asCollector : (Ljava/lang/Class;I)Ljava/lang/invoke/MethodHandle;
/*    */     //   23: iconst_0
/*    */     //   24: iconst_3
/*    */     //   25: anewarray java/lang/Object
/*    */     //   28: dup
/*    */     //   29: iconst_0
/*    */     //   30: aload_0
/*    */     //   31: aastore
/*    */     //   32: dup
/*    */     //   33: iconst_1
/*    */     //   34: aload_3
/*    */     //   35: aastore
/*    */     //   36: dup
/*    */     //   37: iconst_2
/*    */     //   38: aload_1
/*    */     //   39: aastore
/*    */     //   40: invokestatic insertArguments : (Ljava/lang/invoke/MethodHandle;I[Ljava/lang/Object;)Ljava/lang/invoke/MethodHandle;
/*    */     //   43: aload_2
/*    */     //   44: invokestatic explicitCastArguments : (Ljava/lang/invoke/MethodHandle;Ljava/lang/invoke/MethodType;)Ljava/lang/invoke/MethodHandle;
/*    */     //   47: invokevirtual setTarget : (Ljava/lang/invoke/MethodHandle;)V
/*    */     //   50: goto -> 171
/*    */     //   53: astore #4
/*    */     //   55: new java/lang/RuntimeException
/*    */     //   58: dup
/*    */     //   59: new java/lang/StringBuilder
/*    */     //   62: dup
/*    */     //   63: invokespecial <init> : ()V
/*    */     //   66: ldc_w '팗祌僄ᝠᗞ⾗뎥뿘긶褓ၠ΁㆕悮ˈ'
/*    */     //   69: invokevirtual toCharArray : ()[C
/*    */     //   72: dup
/*    */     //   73: dup
/*    */     //   74: bipush #8
/*    */     //   76: dup_x1
/*    */     //   77: caload
/*    */     //   78: sipush #19962
/*    */     //   81: ixor
/*    */     //   82: i2c
/*    */     //   83: castore
/*    */     //   84: sipush #10286
/*    */     //   87: iconst_1
/*    */     //   88: iconst_0
/*    */     //   89: invokestatic G : (Ljava/lang/Object;SZB)Ljava/lang/String;
/*    */     //   92: invokevirtual append : (Ljava/lang/String;)Ljava/lang/StringBuilder;
/*    */     //   95: ldc_w '끚끍⒉娓'
/*    */     //   98: invokevirtual toCharArray : ()[C
/*    */     //   101: dup
/*    */     //   102: dup
/*    */     //   103: iconst_2
/*    */     //   104: dup_x1
/*    */     //   105: caload
/*    */     //   106: sipush #20983
/*    */     //   109: ixor
/*    */     //   110: i2c
/*    */     //   111: castore
/*    */     //   112: sipush #11025
/*    */     //   115: iconst_1
/*    */     //   116: iconst_3
/*    */     //   117: invokestatic G : (Ljava/lang/Object;SZB)Ljava/lang/String;
/*    */     //   120: invokevirtual append : (Ljava/lang/String;)Ljava/lang/StringBuilder;
/*    */     //   123: aload_1
/*    */     //   124: invokevirtual append : (Ljava/lang/String;)Ljava/lang/StringBuilder;
/*    */     //   127: ldc_w '첓ჾ䲋⿀'
/*    */     //   130: invokevirtual toCharArray : ()[C
/*    */     //   133: dup
/*    */     //   134: dup
/*    */     //   135: iconst_0
/*    */     //   136: dup_x1
/*    */     //   137: caload
/*    */     //   138: sipush #3594
/*    */     //   141: ixor
/*    */     //   142: i2c
/*    */     //   143: castore
/*    */     //   144: sipush #9461
/*    */     //   147: iconst_0
/*    */     //   148: iconst_1
/*    */     //   149: invokestatic G : (Ljava/lang/Object;SZB)Ljava/lang/String;
/*    */     //   152: invokevirtual append : (Ljava/lang/String;)Ljava/lang/StringBuilder;
/*    */     //   155: aload_2
/*    */     //   156: invokevirtual toString : ()Ljava/lang/String;
/*    */     //   159: invokevirtual append : (Ljava/lang/String;)Ljava/lang/StringBuilder;
/*    */     //   162: invokevirtual toString : ()Ljava/lang/String;
/*    */     //   165: aload #4
/*    */     //   167: invokespecial <init> : (Ljava/lang/String;Ljava/lang/Throwable;)V
/*    */     //   170: athrow
/*    */     //   171: aload_3
/*    */     //   172: areturn
/*    */     // Exception table:
/*    */     //   from	to	target	type
/*    */     //   9	50	53	java/lang/Exception
/*    */   } }


/* Location:              C:\Users\BukkitBypass\Desktop\MatrixAC\AAC\AAC-spigot-5.2.0.jar!\me\konsolas\aac\it.class
 * Java compiler version: 8 (52.0)
 * JD-Core Version:       1.1.3
 */