/*    */ package me.konsolas.aac;
/*    */ 
/*    */ import javax.crypto.Cipher;
/*    */ 
/*    */ public enum iy {
/*    */   public static final iy TLS_1_3;
/*    */   public static final iy TLS_1_2;
/*    */   public static final iy TLS_1_1;
/*    */   public static final iy TLS_1_0;
/*    */   public static final iy SSL_3_0;
/*    */   
/* 12 */   public String a() { return this.a; } final String a; private static final long c; private static final String[] d; private static final String[] e; private static final Map f; static { byte b1; long l;
/* 13 */     for (c = nc.a(4709593509741019844L, 5290917342236290014L, MethodHandles.lookup().lookupClass()).a(68450281814713L), l = c ^ 0x5E06A9E0342EL, f = new HashMap<>(13), "썲⍎幗滇骹台曹礜ꀮ莒់ꮷ了战燚乗".toCharArray()[7] = (char)("썲⍎幗滇骹台曹礜ꀮ莒់ꮷ了战燚乗".toCharArray()[7] ^ 0x3DF2), "裆蒨ζ".toCharArray()[1] = (char)("裆蒨ζ".toCharArray()[1] ^ 0x5E54), (new byte[8])[0] = (byte)(int)(l >>> 56L), b1 = 1; b1 < 8; ) { (new byte[8])[b1] = (byte)(int)(l << b1 * 8 >>> 56L); b1++; }  Cipher cipher; (cipher = Cipher.getInstance(fW$gy.A("썲⍎幗滇骹台曹礜ꀮ莒់ꮷ了战燚乗".toCharArray(), (short)25896, true, 0))).init(2, SecretKeyFactory.getInstance(fW$gy.A("裆蒨ζ".toCharArray(), (short)29014, false, 2)).generateSecret(new DESKeySpec(new byte[8])), new IvParameterSpec(new byte[8])); String[] arrayOfString = new String[16]; boolean bool = false; "퓂뷡᪷雱퀗혔풲멚揣ꥰ꼃?銂갡곺꧚⭹䐀゗梻쬨╥?쮗䡩峀骙墱悳沋뗡夎鏲ㄶᗪ⚥ἄ셐슍殏鈏ѿ帠嬢蹦虒帏㢑ʹ攌鯦蜇ι患᠃ܻ繭臕釹䋽䱃痔逵뿫?钓仔⊯⃽忪έ㊦뤞潌ꗚ⡥ↂ밎䮗⌻粕ᓣ凶奤ϊ奵⩴韢ᄯ堫⢻收끫Ợ䠄๏뢒쨗놭ﱐ졒쓡Ꮓ䷉鲌좝㍙⵵秌궍㞻웕큚罞ꃆ䄣립⇭禞㔑頉뻷ᴵ쭶螏艤ꛀ??斕̿圭䋊埓ᓄី亐퉻ʈਧ绠몂̚틔烱摧扱쇙ꖪ⑖혹ꃺ軤烮⏅뫤⺎ᗵ䍀꿤쒓⧪湿쎛ᵗ訷忸鿵珓鄝藃ﶃ㟀첿튿氲ൠ㦖∨纱蘸誓삨볰드芨ㄧ煭觥◛ꩃ㷼?鿅醃晫퀓뉬쪬뒏ᖧ巶㚯᪻䔪慵ꁒᆂ檊錫翔὿覮窛遼鍦쟐낰뒱尯幓㱠剬绵茒؄樄ﶔ먡͏ꧣ菋ꪵᷜ贂戭틉睒刟?潝琗龕榷핀醛슭ó፦滮".toCharArray()[234] = (char)("퓂뷡᪷雱퀗혔풲멚揣ꥰ꼃?銂갡곺꧚⭹䐀゗梻쬨╥?쮗䡩峀骙墱悳沋뗡夎鏲ㄶᗪ⚥ἄ셐슍殏鈏ѿ帠嬢蹦虒帏㢑ʹ攌鯦蜇ι患᠃ܻ繭臕釹䋽䱃痔逵뿫?钓仔⊯⃽忪έ㊦뤞潌ꗚ⡥ↂ밎䮗⌻粕ᓣ凶奤ϊ奵⩴韢ᄯ堫⢻收끫Ợ䠄๏뢒쨗놭ﱐ졒쓡Ꮓ䷉鲌좝㍙⵵秌궍㞻웕큚罞ꃆ䄣립⇭禞㔑頉뻷ᴵ쭶螏艤ꛀ??斕̿圭䋊埓ᓄី亐퉻ʈਧ绠몂̚틔烱摧扱쇙ꖪ⑖혹ꃺ軤烮⏅뫤⺎ᗵ䍀꿤쒓⧪湿쎛ᵗ訷忸鿵珓鄝藃ﶃ㟀첿튿氲ൠ㦖∨纱蘸誓삨볰드芨ㄧ煭觥◛ꩃ㷼?鿅醃晫퀓뉬쪬뒏ᖧ巶㚯᪻䔪慵ꁒᆂ檊錫翔὿覮窛遼鍦쟐낰뒱尯幓㱠剬绵茒؄樄ﶔ먡͏ꧣ菋ꪵᷜ贂戭틉睒刟?潝琗龕榷핀醛슭ó፦滮".toCharArray()[234] ^ 0x5C48); String str; int i = (str = fW$gy.A("퓂뷡᪷雱퀗혔풲멚揣ꥰ꼃?銂갡곺꧚⭹䐀゗梻쬨╥?쮗䡩峀骙墱悳沋뗡夎鏲ㄶᗪ⚥ἄ셐슍殏鈏ѿ帠嬢蹦虒帏㢑ʹ攌鯦蜇ι患᠃ܻ繭臕釹䋽䱃痔逵뿫?钓仔⊯⃽忪έ㊦뤞潌ꗚ⡥ↂ밎䮗⌻粕ᓣ凶奤ϊ奵⩴韢ᄯ堫⢻收끫Ợ䠄๏뢒쨗놭ﱐ졒쓡Ꮓ䷉鲌좝㍙⵵秌궍㞻웕큚罞ꃆ䄣립⇭禞㔑頉뻷ᴵ쭶螏艤ꛀ??斕̿圭䋊埓ᓄី亐퉻ʈਧ绠몂̚틔烱摧扱쇙ꖪ⑖혹ꃺ軤烮⏅뫤⺎ᗵ䍀꿤쒓⧪湿쎛ᵗ訷忸鿵珓鄝藃ﶃ㟀첿튿氲ൠ㦖∨纱蘸誓삨볰드芨ㄧ煭觥◛ꩃ㷼?鿅醃晫퀓뉬쪬뒏ᖧ巶㚯᪻䔪慵ꁒᆂ檊錫翔὿覮窛遼鍦쟐낰뒱尯幓㱠剬绵茒؄樄ﶔ먡͏ꧣ菋ꪵᷜ贂戭틉睒刟?潝琗龕榷핀醛슭ó፦滮".toCharArray(), (short)11690, false, 2)).length(); byte b2 = 16; byte b = -1;
/*    */     while (true); }
/*    */    public static iy a(long paramLong, String paramString) {
/*    */     // Byte code:
/*    */     //   0: getstatic me/konsolas/aac/iy.c : J
/*    */     //   3: lload_0
/*    */     //   4: lxor
/*    */     //   5: lstore_0
/*    */     //   6: aload_2
/*    */     //   7: astore #4
/*    */     //   9: ldc2_w 7370331664368232074
/*    */     //   12: lload_0
/*    */     //   13: <illegal opcode> w : (JJ)[Lme/konsolas/aac/aN;
/*    */     //   18: iconst_m1
/*    */     //   19: istore #5
/*    */     //   21: astore_3
/*    */     //   22: aload #4
/*    */     //   24: invokevirtual hashCode : ()I
/*    */     //   27: aload_3
/*    */     //   28: ifnonnull -> 408
/*    */     //   31: lookupswitch default -> 406, -503070503 -> 218, -503070502 -> 154, -503070501 -> 90, 79201641 -> 346, 79923350 -> 282
/*    */     //   80: ldc2_w 7476527200299539363
/*    */     //   83: lload_0
/*    */     //   84: <illegal opcode> w : (Ljava/lang/IllegalArgumentException;JJ)Ljava/lang/IllegalArgumentException;
/*    */     //   89: athrow
/*    */     //   90: aload #4
/*    */     //   92: sipush #10099
/*    */     //   95: ldc2_w 7070828538863146786
/*    */     //   98: lload_0
/*    */     //   99: lxor
/*    */     //   100: <illegal opcode> w : (IJ)Ljava/lang/String;
/*    */     //   105: invokevirtual equals : (Ljava/lang/Object;)Z
/*    */     //   108: aload_3
/*    */     //   109: ifnonnull -> 408
/*    */     //   112: goto -> 125
/*    */     //   115: ldc2_w 7476527200299539363
/*    */     //   118: lload_0
/*    */     //   119: <illegal opcode> w : (Ljava/lang/IllegalArgumentException;JJ)Ljava/lang/IllegalArgumentException;
/*    */     //   124: athrow
/*    */     //   125: ifeq -> 406
/*    */     //   128: goto -> 141
/*    */     //   131: ldc2_w 7476527200299539363
/*    */     //   134: lload_0
/*    */     //   135: <illegal opcode> w : (Ljava/lang/IllegalArgumentException;JJ)Ljava/lang/IllegalArgumentException;
/*    */     //   140: athrow
/*    */     //   141: iconst_0
/*    */     //   142: istore #5
/*    */     //   144: lload_0
/*    */     //   145: lconst_0
/*    */     //   146: lcmp
/*    */     //   147: iflt -> 154
/*    */     //   150: aload_3
/*    */     //   151: ifnull -> 406
/*    */     //   154: aload #4
/*    */     //   156: sipush #30144
/*    */     //   159: ldc2_w 4164053657026135448
/*    */     //   162: lload_0
/*    */     //   163: lxor
/*    */     //   164: <illegal opcode> w : (IJ)Ljava/lang/String;
/*    */     //   169: invokevirtual equals : (Ljava/lang/Object;)Z
/*    */     //   172: aload_3
/*    */     //   173: ifnonnull -> 408
/*    */     //   176: goto -> 189
/*    */     //   179: ldc2_w 7476527200299539363
/*    */     //   182: lload_0
/*    */     //   183: <illegal opcode> w : (Ljava/lang/IllegalArgumentException;JJ)Ljava/lang/IllegalArgumentException;
/*    */     //   188: athrow
/*    */     //   189: ifeq -> 406
/*    */     //   192: goto -> 205
/*    */     //   195: ldc2_w 7476527200299539363
/*    */     //   198: lload_0
/*    */     //   199: <illegal opcode> w : (Ljava/lang/IllegalArgumentException;JJ)Ljava/lang/IllegalArgumentException;
/*    */     //   204: athrow
/*    */     //   205: iconst_1
/*    */     //   206: istore #5
/*    */     //   208: lload_0
/*    */     //   209: lconst_0
/*    */     //   210: lcmp
/*    */     //   211: ifle -> 218
/*    */     //   214: aload_3
/*    */     //   215: ifnull -> 406
/*    */     //   218: aload #4
/*    */     //   220: sipush #19233
/*    */     //   223: ldc2_w 6205732582369344373
/*    */     //   226: lload_0
/*    */     //   227: lxor
/*    */     //   228: <illegal opcode> w : (IJ)Ljava/lang/String;
/*    */     //   233: invokevirtual equals : (Ljava/lang/Object;)Z
/*    */     //   236: aload_3
/*    */     //   237: ifnonnull -> 408
/*    */     //   240: goto -> 253
/*    */     //   243: ldc2_w 7476527200299539363
/*    */     //   246: lload_0
/*    */     //   247: <illegal opcode> w : (Ljava/lang/IllegalArgumentException;JJ)Ljava/lang/IllegalArgumentException;
/*    */     //   252: athrow
/*    */     //   253: ifeq -> 406
/*    */     //   256: goto -> 269
/*    */     //   259: ldc2_w 7476527200299539363
/*    */     //   262: lload_0
/*    */     //   263: <illegal opcode> w : (Ljava/lang/IllegalArgumentException;JJ)Ljava/lang/IllegalArgumentException;
/*    */     //   268: athrow
/*    */     //   269: iconst_2
/*    */     //   270: istore #5
/*    */     //   272: lload_0
/*    */     //   273: lconst_0
/*    */     //   274: lcmp
/*    */     //   275: iflt -> 282
/*    */     //   278: aload_3
/*    */     //   279: ifnull -> 406
/*    */     //   282: aload #4
/*    */     //   284: sipush #9553
/*    */     //   287: ldc2_w 5957606258192471302
/*    */     //   290: lload_0
/*    */     //   291: lxor
/*    */     //   292: <illegal opcode> w : (IJ)Ljava/lang/String;
/*    */     //   297: invokevirtual equals : (Ljava/lang/Object;)Z
/*    */     //   300: aload_3
/*    */     //   301: ifnonnull -> 408
/*    */     //   304: goto -> 317
/*    */     //   307: ldc2_w 7476527200299539363
/*    */     //   310: lload_0
/*    */     //   311: <illegal opcode> w : (Ljava/lang/IllegalArgumentException;JJ)Ljava/lang/IllegalArgumentException;
/*    */     //   316: athrow
/*    */     //   317: ifeq -> 406
/*    */     //   320: goto -> 333
/*    */     //   323: ldc2_w 7476527200299539363
/*    */     //   326: lload_0
/*    */     //   327: <illegal opcode> w : (Ljava/lang/IllegalArgumentException;JJ)Ljava/lang/IllegalArgumentException;
/*    */     //   332: athrow
/*    */     //   333: iconst_3
/*    */     //   334: istore #5
/*    */     //   336: lload_0
/*    */     //   337: lconst_0
/*    */     //   338: lcmp
/*    */     //   339: iflt -> 346
/*    */     //   342: aload_3
/*    */     //   343: ifnull -> 406
/*    */     //   346: aload #4
/*    */     //   348: sipush #19334
/*    */     //   351: ldc2_w 7738247099551923161
/*    */     //   354: lload_0
/*    */     //   355: lxor
/*    */     //   356: <illegal opcode> w : (IJ)Ljava/lang/String;
/*    */     //   361: invokevirtual equals : (Ljava/lang/Object;)Z
/*    */     //   364: lload_0
/*    */     //   365: lconst_0
/*    */     //   366: lcmp
/*    */     //   367: iflt -> 408
/*    */     //   370: aload_3
/*    */     //   371: ifnonnull -> 408
/*    */     //   374: goto -> 387
/*    */     //   377: ldc2_w 7476527200299539363
/*    */     //   380: lload_0
/*    */     //   381: <illegal opcode> w : (Ljava/lang/IllegalArgumentException;JJ)Ljava/lang/IllegalArgumentException;
/*    */     //   386: athrow
/*    */     //   387: ifeq -> 406
/*    */     //   390: goto -> 403
/*    */     //   393: ldc2_w 7476527200299539363
/*    */     //   396: lload_0
/*    */     //   397: <illegal opcode> w : (Ljava/lang/IllegalArgumentException;JJ)Ljava/lang/IllegalArgumentException;
/*    */     //   402: athrow
/*    */     //   403: iconst_4
/*    */     //   404: istore #5
/*    */     //   406: iload #5
/*    */     //   408: tableswitch default -> 474, 0 -> 444, 1 -> 458, 2 -> 462, 3 -> 466, 4 -> 470
/*    */     //   444: getstatic me/konsolas/aac/iy.TLS_1_3 : Lme/konsolas/aac/iy;
/*    */     //   447: areturn
/*    */     //   448: ldc2_w 7476527200299539363
/*    */     //   451: lload_0
/*    */     //   452: <illegal opcode> w : (Ljava/lang/IllegalArgumentException;JJ)Ljava/lang/IllegalArgumentException;
/*    */     //   457: athrow
/*    */     //   458: getstatic me/konsolas/aac/iy.TLS_1_2 : Lme/konsolas/aac/iy;
/*    */     //   461: areturn
/*    */     //   462: getstatic me/konsolas/aac/iy.TLS_1_1 : Lme/konsolas/aac/iy;
/*    */     //   465: areturn
/*    */     //   466: getstatic me/konsolas/aac/iy.TLS_1_0 : Lme/konsolas/aac/iy;
/*    */     //   469: areturn
/*    */     //   470: getstatic me/konsolas/aac/iy.SSL_3_0 : Lme/konsolas/aac/iy;
/*    */     //   473: areturn
/*    */     //   474: new java/lang/IllegalArgumentException
/*    */     //   477: dup
/*    */     //   478: new java/lang/StringBuilder
/*    */     //   481: dup
/*    */     //   482: invokespecial <init> : ()V
/*    */     //   485: sipush #1533
/*    */     //   488: ldc2_w 138840407382062504
/*    */     //   491: lload_0
/*    */     //   492: lxor
/*    */     //   493: <illegal opcode> w : (IJ)Ljava/lang/String;
/*    */     //   498: invokevirtual append : (Ljava/lang/String;)Ljava/lang/StringBuilder;
/*    */     //   501: aload_2
/*    */     //   502: invokevirtual append : (Ljava/lang/String;)Ljava/lang/StringBuilder;
/*    */     //   505: invokevirtual toString : ()Ljava/lang/String;
/*    */     //   508: invokespecial <init> : (Ljava/lang/String;)V
/*    */     //   511: athrow
/*    */     // Line number table:
/*    */     //   Java source line number -> byte code offset
/*    */     //   #14	-> 6
/*    */     //   #17	-> 444
/*    */     //   #20	-> 458
/*    */     //   #7	-> 462
/*    */     //   #23	-> 466
/*    */     //   #22	-> 470
/*    */     //   #1	-> 474
/*    */     // Exception table:
/*    */     //   from	to	target	type
/*    */     //   22	80	80	java/lang/IllegalArgumentException
/*    */     //   31	112	115	java/lang/IllegalArgumentException
/*    */     //   90	128	131	java/lang/IllegalArgumentException
/*    */     //   144	176	179	java/lang/IllegalArgumentException
/*    */     //   154	192	195	java/lang/IllegalArgumentException
/*    */     //   208	240	243	java/lang/IllegalArgumentException
/*    */     //   218	256	259	java/lang/IllegalArgumentException
/*    */     //   272	304	307	java/lang/IllegalArgumentException
/*    */     //   282	320	323	java/lang/IllegalArgumentException
/*    */     //   336	374	377	java/lang/IllegalArgumentException
/*    */     //   346	390	393	java/lang/IllegalArgumentException
/*    */     //   408	448	448	java/lang/IllegalArgumentException
/*    */   } iy(String paramString1) {
/* 18 */     this.a = paramString1;
/*    */   }
/*    */   
/*    */   static List a(String[] paramArrayOfString, long paramLong) {
/*    */     // Byte code:
/*    */     //   0: getstatic me/konsolas/aac/iy.c : J
/*    */     //   3: lload_1
/*    */     //   4: lxor
/*    */     //   5: lstore_1
/*    */     //   6: lload_1
/*    */     //   7: dup2
/*    */     //   8: ldc2_w 130663967651366
/*    */     //   11: lxor
/*    */     //   12: lstore_3
/*    */     //   13: pop2
/*    */     //   14: ldc2_w 7781906604003846972
/*    */     //   17: lload_1
/*    */     //   18: <illegal opcode> w : (JJ)[Lme/konsolas/aac/aN;
/*    */     //   23: new java/util/ArrayList
/*    */     //   26: dup
/*    */     //   27: aload_0
/*    */     //   28: arraylength
/*    */     //   29: invokespecial <init> : (I)V
/*    */     //   32: astore #6
/*    */     //   34: astore #5
/*    */     //   36: aload_0
/*    */     //   37: astore #7
/*    */     //   39: aload #7
/*    */     //   41: arraylength
/*    */     //   42: istore #8
/*    */     //   44: iconst_0
/*    */     //   45: istore #9
/*    */     //   47: iload #9
/*    */     //   49: iload #8
/*    */     //   51: if_icmpge -> 113
/*    */     //   54: aload #7
/*    */     //   56: iload #9
/*    */     //   58: aaload
/*    */     //   59: astore #10
/*    */     //   61: lload_1
/*    */     //   62: lconst_0
/*    */     //   63: lcmp
/*    */     //   64: ifle -> 89
/*    */     //   67: aload #6
/*    */     //   69: aload #5
/*    */     //   71: ifnonnull -> 118
/*    */     //   74: lload_3
/*    */     //   75: aload #10
/*    */     //   77: invokestatic a : (JLjava/lang/String;)Lme/konsolas/aac/iy;
/*    */     //   80: invokeinterface add : (Ljava/lang/Object;)Z
/*    */     //   85: pop
/*    */     //   86: iinc #9, 1
/*    */     //   89: aload #5
/*    */     //   91: ifnull -> 47
/*    */     //   94: lload_1
/*    */     //   95: lconst_0
/*    */     //   96: lcmp
/*    */     //   97: ifle -> 61
/*    */     //   100: goto -> 113
/*    */     //   103: ldc2_w 7671805731619165717
/*    */     //   106: lload_1
/*    */     //   107: <illegal opcode> w : (Ljava/lang/IllegalArgumentException;JJ)Ljava/lang/IllegalArgumentException;
/*    */     //   112: athrow
/*    */     //   113: aload #6
/*    */     //   115: invokestatic unmodifiableList : (Ljava/util/List;)Ljava/util/List;
/*    */     //   118: areturn
/*    */     // Line number table:
/*    */     //   Java source line number -> byte code offset
/*    */     //   #21	-> 23
/*    */     //   #16	-> 36
/*    */     //   #3	-> 61
/*    */     //   #9	-> 86
/*    */     //   #19	-> 113
/*    */     // Exception table:
/*    */     //   from	to	target	type
/*    */     //   61	94	103	java/lang/IllegalArgumentException
/*    */   }
/*    */   
/*    */   private static IllegalArgumentException a(IllegalArgumentException paramIllegalArgumentException) {
/*    */     return paramIllegalArgumentException;
/*    */   }
/*    */   
/*    */   private static String a(byte[] paramArrayOfbyte) {
/*    */     byte b1 = 0;
/*    */     int i;
/*    */     char[] arrayOfChar = new char[i = paramArrayOfbyte.length];
/*    */     for (byte b2 = 0; b2 < i; b2++) {
/*    */       int j;
/*    */       if ((j = 0xFF & paramArrayOfbyte[b2]) < 192) {
/*    */         arrayOfChar[b1++] = (char)j;
/*    */       } else if (j < 224) {
/*    */         char c = (char)((char)(j & 0x1F) << 6);
/*    */         j = paramArrayOfbyte[++b2];
/*    */         c = (char)(c | (char)(j & 0x3F));
/*    */         arrayOfChar[b1++] = c;
/*    */       } else if (b2 < i - 2) {
/*    */         char c = (char)((char)(j & 0xF) << 12);
/*    */         j = paramArrayOfbyte[++b2];
/*    */         c = (char)(c | (char)(j & 0x3F) << 6);
/*    */         j = paramArrayOfbyte[++b2];
/*    */         c = (char)(c | (char)(j & 0x3F));
/*    */         arrayOfChar[b1++] = c;
/*    */       } 
/*    */     } 
/*    */     return new String(arrayOfChar, 0, b1);
/*    */   }
/*    */   
/*    */   private static String a(int paramInt, long paramLong) {
/*    */     int i = paramInt ^ (int)(paramLong & 0x7FFFL) ^ 0x16FE;
/*    */     if (e[i] == null) {
/*    */       Object[] arrayOfObject;
/*    */       try {
/*    */         Long long_ = Long.valueOf(Thread.currentThread().getId());
/*    */         arrayOfObject = (Object[])f.get(long_);
/*    */         if (arrayOfObject == null) {
/*    */           arrayOfObject = new Object[3];
/*    */           "亟黴榖⟝튍ꎩ虿챉橉쬀籲찴稊ﱄ꥕㔨䕡㥄힖엛⻊".toCharArray()[0] = (char)("亟黴榖⟝튍ꎩ虿챉橉쬀籲찴稊ﱄ꥕㔨䕡㥄힖엛⻊".toCharArray()[0] ^ 0x1D74);
/*    */           arrayOfObject[0] = Cipher.getInstance(a0$cc.G("亟黴榖⟝튍ꎩ虿챉橉쬀籲찴稊ﱄ꥕㔨䕡㥄힖엛⻊".toCharArray(), (short)17028, false, (byte)4));
/*    */           "묐윘礈䭧".toCharArray()[1] = (char)("묐윘礈䭧".toCharArray()[1] ^ 0x6AE2);
/*    */           arrayOfObject[1] = SecretKeyFactory.getInstance(a0$cc.G("묐윘礈䭧".toCharArray(), (short)11360, false, (byte)4));
/*    */           arrayOfObject[2] = new IvParameterSpec(new byte[8]);
/*    */           f.put(long_, arrayOfObject);
/*    */         } 
/*    */       } catch (Exception exception) {
/*    */         "귎ꌘຠ䏧隍漤禮ẚ䈹ꀹ盇枥ᙂ⵷ᱠ籲".toCharArray()[14] = (char)("귎ꌘຠ䏧隍漤禮ẚ䈹ꀹ盇枥ᙂ⵷ᱠ籲".toCharArray()[14] ^ 0x45C6);
/*    */         throw new RuntimeException(a0$cc.G("귎ꌘຠ䏧隍漤禮ẚ䈹ꀹ盇枥ᙂ⵷ᱠ籲".toCharArray(), (short)19864, false, (byte)5), exception);
/*    */       } 
/*    */       byte[] arrayOfByte1 = new byte[8];
/*    */       arrayOfByte1[0] = (byte)(int)(paramLong >>> 56L);
/*    */       for (byte b = 1; b < 8; b++)
/*    */         arrayOfByte1[b] = (byte)(int)(paramLong << b * 8 >>> 56L); 
/*    */       DESKeySpec dESKeySpec = new DESKeySpec(arrayOfByte1);
/*    */       SecretKey secretKey = ((SecretKeyFactory)arrayOfObject[1]).generateSecret(dESKeySpec);
/*    */       ((Cipher)arrayOfObject[0]).init(2, secretKey, (IvParameterSpec)arrayOfObject[2]);
/*    */       "ꬿ曶㺆写䬭澫궾귁篙".toCharArray()[7] = (char)("ꬿ曶㺆写䬭澫궾귁篙".toCharArray()[7] ^ 0x5487);
/*    */       byte[] arrayOfByte2 = d[i].getBytes(a0$cc.G("ꬿ曶㺆写䬭澫궾귁篙".toCharArray(), (short)6812, false, (byte)2));
/*    */       e[i] = a(((Cipher)arrayOfObject[0]).doFinal(arrayOfByte2));
/*    */     } 
/*    */     return e[i];
/*    */   }
/*    */   
/*    */   private static Object a(MethodHandles.Lookup paramLookup, MutableCallSite paramMutableCallSite, String paramString, Object[] paramArrayOfObject) {
/*    */     int i = ((Integer)paramArrayOfObject[0]).intValue();
/*    */     long l = ((Long)paramArrayOfObject[1]).longValue();
/*    */     String str = a(i, l);
/*    */     MethodHandle methodHandle = MethodHandles.constant(String.class, str);
/*    */     paramMutableCallSite.setTarget(MethodHandles.dropArguments(methodHandle, 0, new Class[] { int.class, long.class }));
/*    */     return str;
/*    */   }
/*    */   
/*    */   private static CallSite a(MethodHandles.Lookup paramLookup, String paramString, MethodType paramMethodType) {
/*    */     // Byte code:
/*    */     //   0: new java/lang/invoke/MutableCallSite
/*    */     //   3: dup
/*    */     //   4: aload_2
/*    */     //   5: invokespecial <init> : (Ljava/lang/invoke/MethodType;)V
/*    */     //   8: astore_3
/*    */     //   9: aload_3
/*    */     //   10: ldc_w
/*    */     //   13: ldc_w [Ljava/lang/Object;
/*    */     //   16: aload_2
/*    */     //   17: invokevirtual parameterCount : ()I
/*    */     //   20: invokevirtual asCollector : (Ljava/lang/Class;I)Ljava/lang/invoke/MethodHandle;
/*    */     //   23: iconst_0
/*    */     //   24: iconst_3
/*    */     //   25: anewarray java/lang/Object
/*    */     //   28: dup
/*    */     //   29: iconst_0
/*    */     //   30: aload_0
/*    */     //   31: aastore
/*    */     //   32: dup
/*    */     //   33: iconst_1
/*    */     //   34: aload_3
/*    */     //   35: aastore
/*    */     //   36: dup
/*    */     //   37: iconst_2
/*    */     //   38: aload_1
/*    */     //   39: aastore
/*    */     //   40: invokestatic insertArguments : (Ljava/lang/invoke/MethodHandle;I[Ljava/lang/Object;)Ljava/lang/invoke/MethodHandle;
/*    */     //   43: aload_2
/*    */     //   44: invokestatic explicitCastArguments : (Ljava/lang/invoke/MethodHandle;Ljava/lang/invoke/MethodType;)Ljava/lang/invoke/MethodHandle;
/*    */     //   47: invokevirtual setTarget : (Ljava/lang/invoke/MethodHandle;)V
/*    */     //   50: goto -> 170
/*    */     //   53: astore #4
/*    */     //   55: new java/lang/RuntimeException
/*    */     //   58: dup
/*    */     //   59: new java/lang/StringBuilder
/*    */     //   62: dup
/*    */     //   63: invokespecial <init> : ()V
/*    */     //   66: ldc_w '㜜覱꟯隄㚯닎褜鲥ﲥ竪薦匩뮣Ᏸ擫⡧'
/*    */     //   69: invokevirtual toCharArray : ()[C
/*    */     //   72: dup
/*    */     //   73: dup
/*    */     //   74: iconst_0
/*    */     //   75: dup_x1
/*    */     //   76: caload
/*    */     //   77: sipush #20350
/*    */     //   80: ixor
/*    */     //   81: i2c
/*    */     //   82: castore
/*    */     //   83: sipush #31133
/*    */     //   86: iconst_0
/*    */     //   87: iconst_4
/*    */     //   88: invokestatic A : (Ljava/lang/Object;SZI)Ljava/lang/String;
/*    */     //   91: invokevirtual append : (Ljava/lang/String;)Ljava/lang/StringBuilder;
/*    */     //   94: ldc_w '糃ි䆿㘞'
/*    */     //   97: invokevirtual toCharArray : ()[C
/*    */     //   100: dup
/*    */     //   101: dup
/*    */     //   102: iconst_0
/*    */     //   103: dup_x1
/*    */     //   104: caload
/*    */     //   105: sipush #2553
/*    */     //   108: ixor
/*    */     //   109: i2c
/*    */     //   110: castore
/*    */     //   111: sipush #8704
/*    */     //   114: iconst_1
/*    */     //   115: iconst_0
/*    */     //   116: invokestatic A : (Ljava/lang/Object;SZI)Ljava/lang/String;
/*    */     //   119: invokevirtual append : (Ljava/lang/String;)Ljava/lang/StringBuilder;
/*    */     //   122: aload_1
/*    */     //   123: invokevirtual append : (Ljava/lang/String;)Ljava/lang/StringBuilder;
/*    */     //   126: ldc_w '⋉䢢牋'
/*    */     //   129: invokevirtual toCharArray : ()[C
/*    */     //   132: dup
/*    */     //   133: dup
/*    */     //   134: iconst_2
/*    */     //   135: dup_x1
/*    */     //   136: caload
/*    */     //   137: sipush #6449
/*    */     //   140: ixor
/*    */     //   141: i2c
/*    */     //   142: castore
/*    */     //   143: sipush #28847
/*    */     //   146: iconst_1
/*    */     //   147: iconst_0
/*    */     //   148: invokestatic A : (Ljava/lang/Object;SZI)Ljava/lang/String;
/*    */     //   151: invokevirtual append : (Ljava/lang/String;)Ljava/lang/StringBuilder;
/*    */     //   154: aload_2
/*    */     //   155: invokevirtual toString : ()Ljava/lang/String;
/*    */     //   158: invokevirtual append : (Ljava/lang/String;)Ljava/lang/StringBuilder;
/*    */     //   161: invokevirtual toString : ()Ljava/lang/String;
/*    */     //   164: aload #4
/*    */     //   166: invokespecial <init> : (Ljava/lang/String;Ljava/lang/Throwable;)V
/*    */     //   169: athrow
/*    */     //   170: aload_3
/*    */     //   171: areturn
/*    */     // Exception table:
/*    */     //   from	to	target	type
/*    */     //   9	50	53	java/lang/Exception
/*    */   }
/*    */ }


/* Location:              C:\Users\BukkitBypass\Desktop\MatrixAC\AAC\AAC-spigot-5.2.0.jar!\me\konsolas\aac\iy.class
 * Java compiler version: 8 (52.0)
 * JD-Core Version:       1.1.3
 */