/*     */ package me.konsolas.aac;
/*     */ import java.util.Arrays;
/*     */ import java.util.Random;
/*     */ import java.util.concurrent.ExecutorCompletionService;
/*     */ import java.util.concurrent.ForkJoinPool;
/*     */ import java.util.concurrent.LinkedBlockingQueue;
/*     */ import java.util.concurrent.atomic.AtomicInteger;
/*     */ 
/*     */ public final class j {
/*     */   public static final short[] e;
/*     */   public static final short[] l;
/*     */   private static final int o = 16;
/*     */   private static final int k = 8192;
/*     */   private static final int j = 128;
/*     */   private static final int a = 16;
/*     */   private static final int b = 8;
/*     */   private static final int g = 255;
/*     */   private static final int f = 2;
/*     */   private static final int d = 1024;
/*     */   private static final int i = 1024;
/*     */   static final int h = 1000;
/*     */   protected static final fm c;
/*     */   public static final m9 m;
/*     */   private static aN[] n;
/*     */   private static final long p;
/*     */   
/*     */   public static void d(int[] paramArrayOfint, short[] paramArrayOfshort, int paramInt1, int paramInt2) {
/*     */     // Byte code:
/*     */     //   0: iload_3
/*     */     //   1: iload_2
/*     */     //   2: isub
/*     */     //   3: istore #4
/*     */     //   5: iload #4
/*     */     //   7: bipush #16
/*     */     //   9: if_icmpge -> 24
/*     */     //   12: aload_0
/*     */     //   13: aload_1
/*     */     //   14: iload_2
/*     */     //   15: iload_3
/*     */     //   16: invokestatic b : ([I[SII)V
/*     */     //   19: return
/*     */     //   20: invokestatic a : (Ljava/lang/Exception;)Ljava/lang/Exception;
/*     */     //   23: athrow
/*     */     //   24: iload_2
/*     */     //   25: iload #4
/*     */     //   27: iconst_2
/*     */     //   28: idiv
/*     */     //   29: iadd
/*     */     //   30: istore #5
/*     */     //   32: iload_2
/*     */     //   33: istore #6
/*     */     //   35: iload_3
/*     */     //   36: iconst_1
/*     */     //   37: isub
/*     */     //   38: istore #7
/*     */     //   40: iload #4
/*     */     //   42: sipush #128
/*     */     //   45: if_icmple -> 116
/*     */     //   48: iload #4
/*     */     //   50: bipush #8
/*     */     //   52: idiv
/*     */     //   53: istore #8
/*     */     //   55: aload_0
/*     */     //   56: aload_1
/*     */     //   57: iload #6
/*     */     //   59: iload #6
/*     */     //   61: iload #8
/*     */     //   63: iadd
/*     */     //   64: iload #6
/*     */     //   66: iconst_2
/*     */     //   67: iload #8
/*     */     //   69: imul
/*     */     //   70: iadd
/*     */     //   71: invokestatic a : ([I[SIII)I
/*     */     //   74: istore #6
/*     */     //   76: aload_0
/*     */     //   77: aload_1
/*     */     //   78: iload #5
/*     */     //   80: iload #8
/*     */     //   82: isub
/*     */     //   83: iload #5
/*     */     //   85: iload #5
/*     */     //   87: iload #8
/*     */     //   89: iadd
/*     */     //   90: invokestatic a : ([I[SIII)I
/*     */     //   93: istore #5
/*     */     //   95: aload_0
/*     */     //   96: aload_1
/*     */     //   97: iload #7
/*     */     //   99: iconst_2
/*     */     //   100: iload #8
/*     */     //   102: imul
/*     */     //   103: isub
/*     */     //   104: iload #7
/*     */     //   106: iload #8
/*     */     //   108: isub
/*     */     //   109: iload #7
/*     */     //   111: invokestatic a : ([I[SIII)I
/*     */     //   114: istore #7
/*     */     //   116: aload_0
/*     */     //   117: aload_1
/*     */     //   118: iload #6
/*     */     //   120: iload #5
/*     */     //   122: iload #7
/*     */     //   124: invokestatic a : ([I[SIII)I
/*     */     //   127: istore #5
/*     */     //   129: aload_1
/*     */     //   130: aload_0
/*     */     //   131: iload #5
/*     */     //   133: iaload
/*     */     //   134: saload
/*     */     //   135: istore #8
/*     */     //   137: iload_2
/*     */     //   138: istore #9
/*     */     //   140: iload #9
/*     */     //   142: istore #10
/*     */     //   144: iload_3
/*     */     //   145: iconst_1
/*     */     //   146: isub
/*     */     //   147: istore #11
/*     */     //   149: iload #11
/*     */     //   151: istore #12
/*     */     //   153: iload #10
/*     */     //   155: iload #11
/*     */     //   157: if_icmpgt -> 213
/*     */     //   160: aload_1
/*     */     //   161: aload_0
/*     */     //   162: iload #10
/*     */     //   164: iaload
/*     */     //   165: saload
/*     */     //   166: iload #8
/*     */     //   168: invokestatic compare : (SS)I
/*     */     //   171: dup
/*     */     //   172: istore #13
/*     */     //   174: ifgt -> 213
/*     */     //   177: iload #13
/*     */     //   179: ifne -> 207
/*     */     //   182: goto -> 189
/*     */     //   185: invokestatic a : (Ljava/lang/Exception;)Ljava/lang/Exception;
/*     */     //   188: athrow
/*     */     //   189: aload_0
/*     */     //   190: iload #9
/*     */     //   192: iinc #9, 1
/*     */     //   195: iload #10
/*     */     //   197: invokestatic g : ([III)V
/*     */     //   200: goto -> 207
/*     */     //   203: invokestatic a : (Ljava/lang/Exception;)Ljava/lang/Exception;
/*     */     //   206: athrow
/*     */     //   207: iinc #10, 1
/*     */     //   210: goto -> 153
/*     */     //   213: iload #11
/*     */     //   215: iload #10
/*     */     //   217: if_icmplt -> 273
/*     */     //   220: aload_1
/*     */     //   221: aload_0
/*     */     //   222: iload #11
/*     */     //   224: iaload
/*     */     //   225: saload
/*     */     //   226: iload #8
/*     */     //   228: invokestatic compare : (SS)I
/*     */     //   231: dup
/*     */     //   232: istore #13
/*     */     //   234: iflt -> 273
/*     */     //   237: iload #13
/*     */     //   239: ifne -> 267
/*     */     //   242: goto -> 249
/*     */     //   245: invokestatic a : (Ljava/lang/Exception;)Ljava/lang/Exception;
/*     */     //   248: athrow
/*     */     //   249: aload_0
/*     */     //   250: iload #11
/*     */     //   252: iload #12
/*     */     //   254: iinc #12, -1
/*     */     //   257: invokestatic g : ([III)V
/*     */     //   260: goto -> 267
/*     */     //   263: invokestatic a : (Ljava/lang/Exception;)Ljava/lang/Exception;
/*     */     //   266: athrow
/*     */     //   267: iinc #11, -1
/*     */     //   270: goto -> 213
/*     */     //   273: iload #10
/*     */     //   275: iload #11
/*     */     //   277: if_icmple -> 287
/*     */     //   280: goto -> 304
/*     */     //   283: invokestatic a : (Ljava/lang/Exception;)Ljava/lang/Exception;
/*     */     //   286: athrow
/*     */     //   287: aload_0
/*     */     //   288: iload #10
/*     */     //   290: iinc #10, 1
/*     */     //   293: iload #11
/*     */     //   295: iinc #11, -1
/*     */     //   298: invokestatic g : ([III)V
/*     */     //   301: goto -> 153
/*     */     //   304: iload #9
/*     */     //   306: iload_2
/*     */     //   307: isub
/*     */     //   308: iload #10
/*     */     //   310: iload #9
/*     */     //   312: isub
/*     */     //   313: invokestatic min : (II)I
/*     */     //   316: istore #13
/*     */     //   318: aload_0
/*     */     //   319: iload_2
/*     */     //   320: iload #10
/*     */     //   322: iload #13
/*     */     //   324: isub
/*     */     //   325: iload #13
/*     */     //   327: invokestatic b : ([IIII)V
/*     */     //   330: iload #12
/*     */     //   332: iload #11
/*     */     //   334: isub
/*     */     //   335: iload_3
/*     */     //   336: iload #12
/*     */     //   338: isub
/*     */     //   339: iconst_1
/*     */     //   340: isub
/*     */     //   341: invokestatic min : (II)I
/*     */     //   344: istore #13
/*     */     //   346: aload_0
/*     */     //   347: iload #10
/*     */     //   349: iload_3
/*     */     //   350: iload #13
/*     */     //   352: isub
/*     */     //   353: iload #13
/*     */     //   355: invokestatic b : ([IIII)V
/*     */     //   358: iload #10
/*     */     //   360: iload #9
/*     */     //   362: isub
/*     */     //   363: dup
/*     */     //   364: istore #13
/*     */     //   366: iconst_1
/*     */     //   367: if_icmple -> 387
/*     */     //   370: aload_0
/*     */     //   371: aload_1
/*     */     //   372: iload_2
/*     */     //   373: iload_2
/*     */     //   374: iload #13
/*     */     //   376: iadd
/*     */     //   377: invokestatic d : ([I[SII)V
/*     */     //   380: goto -> 387
/*     */     //   383: invokestatic a : (Ljava/lang/Exception;)Ljava/lang/Exception;
/*     */     //   386: athrow
/*     */     //   387: iload #12
/*     */     //   389: iload #11
/*     */     //   391: isub
/*     */     //   392: dup
/*     */     //   393: istore #13
/*     */     //   395: iconst_1
/*     */     //   396: if_icmple -> 416
/*     */     //   399: aload_0
/*     */     //   400: aload_1
/*     */     //   401: iload_3
/*     */     //   402: iload #13
/*     */     //   404: isub
/*     */     //   405: iload_3
/*     */     //   406: invokestatic d : ([I[SII)V
/*     */     //   409: goto -> 416
/*     */     //   412: invokestatic a : (Ljava/lang/Exception;)Ljava/lang/Exception;
/*     */     //   415: athrow
/*     */     //   416: return
/*     */     // Line number table:
/*     */     //   Java source line number -> byte code offset
/*     */     //   #17	-> 0
/*     */     //   #299	-> 5
/*     */     //   #71	-> 12
/*     */     //   #598	-> 19
/*     */     //   #818	-> 24
/*     */     //   #275	-> 32
/*     */     //   #274	-> 35
/*     */     //   #476	-> 40
/*     */     //   #278	-> 48
/*     */     //   #68	-> 55
/*     */     //   #318	-> 76
/*     */     //   #567	-> 95
/*     */     //   #252	-> 116
/*     */     //   #179	-> 129
/*     */     //   #480	-> 137
/*     */     //   #289	-> 153
/*     */     //   #245	-> 177
/*     */     //   #38	-> 207
/*     */     //   #755	-> 213
/*     */     //   #232	-> 237
/*     */     //   #530	-> 267
/*     */     //   #749	-> 273
/*     */     //   #739	-> 287
/*     */     //   #575	-> 304
/*     */     //   #610	-> 318
/*     */     //   #262	-> 330
/*     */     //   #885	-> 346
/*     */     //   #261	-> 358
/*     */     //   #666	-> 387
/*     */     //   #521	-> 416
/*     */     // Exception table:
/*     */     //   from	to	target	type
/*     */     //   5	20	20	java/lang/IllegalArgumentException
/*     */     //   174	182	185	java/lang/IllegalArgumentException
/*     */     //   177	200	203	java/lang/IllegalArgumentException
/*     */     //   234	242	245	java/lang/IllegalArgumentException
/*     */     //   237	260	263	java/lang/IllegalArgumentException
/*     */     //   273	283	283	java/lang/IllegalArgumentException
/*     */     //   366	380	383	java/lang/IllegalArgumentException
/*     */     //   395	409	412	java/lang/IllegalArgumentException
/*     */   }
/*     */   
/*     */   public static void d(short[] paramArrayOfshort, int paramInt1, int paramInt2, ad paramad) {
/*  32 */     ForkJoinPool forkJoinPool = a();
/*     */ 
/*     */ 
/*     */ 
/*     */ 
/*     */ 
/*     */ 
/*     */ 
/*     */ 
/*     */ 
/*     */ 
/*     */ 
/*     */ 
/*     */ 
/*     */ 
/*     */ 
/*     */ 
/*     */ 
/*     */ 
/*     */ 
/*     */ 
/*     */ 
/*     */ 
/*     */ 
/*     */ 
/*     */ 
/*     */ 
/*     */ 
/*     */ 
/*     */ 
/*     */ 
/*     */ 
/*     */ 
/*     */ 
/*     */ 
/*     */ 
/*     */ 
/*     */ 
/*     */ 
/*     */ 
/*     */ 
/*     */ 
/*     */ 
/*     */ 
/*     */ 
/*     */ 
/*     */ 
/*     */ 
/*     */ 
/*     */ 
/*     */ 
/*     */ 
/*     */ 
/*     */ 
/*     */ 
/*     */ 
/*     */ 
/*     */ 
/*     */ 
/*     */ 
/*     */ 
/*     */ 
/*     */ 
/*     */ 
/*     */ 
/*     */ 
/*     */ 
/*     */ 
/*     */ 
/*     */ 
/*     */ 
/*     */ 
/*     */ 
/*     */ 
/*     */ 
/*     */ 
/*     */ 
/*     */ 
/*     */ 
/*     */ 
/*     */ 
/*     */ 
/*     */ 
/*     */ 
/*     */ 
/*     */ 
/*     */ 
/*     */ 
/*     */ 
/*     */ 
/*     */ 
/*     */ 
/*     */ 
/*     */ 
/*     */ 
/*     */ 
/*     */ 
/*     */ 
/*     */ 
/*     */ 
/*     */ 
/*     */ 
/*     */ 
/*     */ 
/*     */ 
/*     */ 
/*     */ 
/*     */ 
/*     */ 
/*     */ 
/*     */ 
/*     */ 
/*     */ 
/*     */ 
/*     */ 
/*     */ 
/*     */ 
/*     */ 
/*     */ 
/*     */ 
/*     */ 
/*     */ 
/*     */ 
/*     */ 
/*     */ 
/*     */ 
/*     */ 
/*     */ 
/*     */ 
/*     */ 
/*     */ 
/*     */ 
/*     */ 
/*     */ 
/*     */ 
/*     */ 
/*     */ 
/*     */ 
/*     */ 
/*     */ 
/*     */ 
/*     */ 
/*     */ 
/*     */ 
/*     */ 
/*     */ 
/*     */ 
/*     */ 
/*     */ 
/*     */ 
/*     */ 
/*     */ 
/*     */ 
/*     */ 
/*     */ 
/*     */ 
/*     */ 
/*     */ 
/*     */ 
/*     */ 
/*     */ 
/*     */ 
/*     */ 
/*     */ 
/*     */ 
/*     */ 
/*     */ 
/*     */ 
/*     */ 
/*     */ 
/*     */ 
/*     */ 
/*     */ 
/*     */ 
/*     */ 
/*     */ 
/*     */ 
/*     */ 
/*     */ 
/*     */ 
/*     */ 
/*     */ 
/*     */ 
/*     */ 
/*     */ 
/*     */ 
/*     */ 
/*     */ 
/*     */ 
/*     */ 
/*     */ 
/*     */ 
/*     */ 
/*     */ 
/*     */ 
/*     */ 
/*     */ 
/*     */ 
/*     */ 
/*     */ 
/*     */ 
/*     */ 
/*     */ 
/*     */ 
/*     */ 
/*     */ 
/*     */ 
/*     */ 
/*     */ 
/*     */ 
/*     */ 
/*     */ 
/*     */ 
/*     */ 
/*     */ 
/*     */ 
/*     */ 
/*     */ 
/*     */ 
/*     */ 
/*     */ 
/*     */ 
/*     */ 
/*     */ 
/*     */ 
/*     */ 
/*     */ 
/*     */ 
/*     */ 
/*     */ 
/*     */ 
/*     */ 
/*     */ 
/*     */ 
/*     */ 
/*     */ 
/*     */ 
/*     */ 
/*     */ 
/*     */ 
/*     */ 
/*     */ 
/*     */ 
/*     */ 
/*     */ 
/*     */ 
/*     */ 
/*     */ 
/*     */ 
/*     */ 
/*     */ 
/*     */ 
/*     */ 
/*     */ 
/*     */ 
/*     */ 
/*     */ 
/*     */ 
/*     */ 
/*     */ 
/*     */ 
/*     */ 
/*     */ 
/*     */ 
/*     */ 
/*     */ 
/*     */ 
/*     */ 
/*     */ 
/*     */ 
/*     */ 
/*     */ 
/*     */ 
/*     */ 
/*     */ 
/*     */ 
/*     */ 
/*     */ 
/*     */ 
/*     */ 
/*     */ 
/*     */ 
/*     */ 
/*     */ 
/*     */ 
/*     */ 
/*     */ 
/*     */ 
/*     */ 
/*     */ 
/*     */ 
/*     */ 
/*     */ 
/*     */ 
/*     */ 
/*     */ 
/*     */ 
/*     */ 
/*     */ 
/*     */ 
/*     */ 
/*     */ 
/*     */ 
/*     */ 
/*     */ 
/*     */ 
/*     */ 
/*     */ 
/*     */ 
/*     */ 
/*     */ 
/*     */ 
/*     */ 
/*     */ 
/*     */ 
/*     */ 
/*     */ 
/*     */ 
/*     */ 
/*     */ 
/*     */ 
/*     */ 
/*     */ 
/*     */ 
/*     */ 
/*     */ 
/*     */ 
/*     */ 
/*     */ 
/*     */ 
/*     */ 
/*     */ 
/*     */ 
/*     */ 
/*     */ 
/*     */ 
/*     */ 
/*     */ 
/*     */ 
/*     */ 
/*     */ 
/*     */ 
/*     */ 
/*     */ 
/*     */ 
/*     */ 
/*     */ 
/*     */ 
/*     */ 
/*     */ 
/*     */ 
/*     */ 
/*     */ 
/*     */ 
/*     */ 
/*     */ 
/*     */ 
/*     */ 
/*     */ 
/*     */ 
/*     */ 
/*     */ 
/*     */ 
/*     */ 
/*     */ 
/*     */ 
/*     */ 
/*     */ 
/*     */ 
/*     */ 
/*     */ 
/*     */ 
/*     */ 
/*     */ 
/*     */ 
/*     */ 
/*     */ 
/*     */ 
/*     */ 
/*     */ 
/*     */ 
/*     */ 
/*     */ 
/*     */ 
/*     */ 
/*     */ 
/*     */ 
/*     */ 
/*     */ 
/*     */ 
/*     */ 
/*     */ 
/*     */ 
/*     */ 
/*     */ 
/*     */ 
/*     */ 
/*     */ 
/*     */ 
/*     */ 
/*     */ 
/*     */ 
/*     */ 
/*     */ 
/*     */ 
/*     */ 
/*     */ 
/*     */ 
/*     */ 
/*     */ 
/*     */ 
/*     */ 
/*     */ 
/*     */ 
/*     */ 
/*     */ 
/*     */ 
/*     */ 
/*     */ 
/*     */ 
/*     */ 
/*     */ 
/*     */ 
/*     */ 
/*     */ 
/*     */ 
/*     */ 
/*     */ 
/*     */ 
/*     */ 
/*     */ 
/*     */ 
/*     */ 
/*     */ 
/*     */ 
/*     */ 
/*     */ 
/*     */ 
/*     */ 
/*     */ 
/*     */ 
/*     */ 
/*     */ 
/*     */ 
/*     */ 
/*     */ 
/*     */ 
/*     */ 
/*     */ 
/*     */ 
/*     */ 
/*     */ 
/*     */ 
/*     */ 
/*     */ 
/*     */ 
/*     */ 
/*     */ 
/*     */ 
/*     */ 
/*     */ 
/*     */ 
/*     */ 
/*     */ 
/*     */ 
/*     */ 
/*     */ 
/*     */ 
/*     */ 
/*     */ 
/*     */ 
/*     */ 
/*     */ 
/*     */ 
/*     */ 
/*     */ 
/*     */ 
/*     */ 
/*     */ 
/*     */ 
/*     */ 
/*     */ 
/*     */ 
/*     */ 
/*     */ 
/*     */ 
/*     */ 
/*     */ 
/*     */ 
/*     */ 
/*     */ 
/*     */ 
/*     */ 
/*     */ 
/*     */ 
/*     */ 
/*     */ 
/*     */ 
/*     */ 
/*     */ 
/*     */ 
/*     */ 
/*     */ 
/*     */ 
/*     */ 
/*     */ 
/*     */ 
/*     */ 
/*     */ 
/*     */ 
/*     */ 
/*     */ 
/*     */ 
/*     */ 
/*     */ 
/*     */ 
/*     */ 
/*     */ 
/*     */ 
/*     */ 
/*     */ 
/*     */ 
/*     */ 
/*     */ 
/*     */ 
/*     */ 
/*     */ 
/*     */ 
/*     */ 
/*     */ 
/*     */ 
/*     */ 
/*     */ 
/*     */ 
/*     */ 
/*     */ 
/*     */ 
/*     */ 
/*     */ 
/*     */ 
/*     */ 
/*     */ 
/*     */ 
/*     */ 
/*     */ 
/*     */ 
/*     */ 
/*     */ 
/*     */ 
/*     */ 
/*     */ 
/*     */ 
/*     */ 
/*     */ 
/*     */ 
/*     */ 
/*     */ 
/*     */ 
/*     */ 
/*     */ 
/*     */ 
/*     */ 
/*     */ 
/*     */ 
/*     */ 
/*     */ 
/*     */ 
/*     */ 
/*     */ 
/*     */ 
/*     */ 
/*     */ 
/*     */ 
/*     */ 
/*     */ 
/*     */ 
/*     */ 
/*     */ 
/*     */ 
/*     */ 
/*     */ 
/*     */ 
/*     */ 
/*     */ 
/*     */ 
/*     */ 
/*     */ 
/*     */ 
/*     */ 
/*     */ 
/*     */ 
/*     */ 
/*     */ 
/*     */ 
/*     */ 
/*     */ 
/*     */ 
/*     */ 
/*     */ 
/*     */ 
/*     */ 
/*     */ 
/*     */ 
/*     */ 
/*     */ 
/*     */ 
/*     */ 
/*     */ 
/*     */ 
/*     */ 
/*     */ 
/*     */ 
/*     */ 
/*     */ 
/*     */ 
/*     */ 
/*     */ 
/*     */ 
/*     */ 
/*     */ 
/*     */ 
/*     */ 
/*     */ 
/*     */ 
/*     */ 
/*     */ 
/*     */ 
/*     */ 
/*     */     
/* 661 */     try { if (paramInt2 - paramInt1 >= 8192) { try { if (forkJoinPool.getParallelism() == 1) { g(paramArrayOfshort, paramInt1, paramInt2, paramad); return; }  } catch (IllegalArgumentException illegalArgumentException) { throw a(null); }  forkJoinPool.invoke(new cj(paramArrayOfshort, paramInt1, paramInt2, paramad)); return; }  } catch (IllegalArgumentException illegalArgumentException) { throw a(null); }  g(paramArrayOfshort, paramInt1, paramInt2, paramad);
/*     */   }
/*     */ 
/*     */ 
/*     */ 
/*     */ 
/*     */ 
/*     */ 
/*     */ 
/*     */ 
/*     */ 
/*     */ 
/*     */ 
/*     */ 
/*     */ 
/*     */ 
/*     */ 
/*     */ 
/*     */ 
/*     */ 
/*     */ 
/*     */ 
/*     */ 
/*     */ 
/*     */ 
/*     */ 
/*     */ 
/*     */ 
/*     */ 
/*     */ 
/*     */ 
/*     */ 
/*     */ 
/*     */ 
/*     */ 
/*     */ 
/*     */ 
/*     */ 
/*     */ 
/*     */ 
/*     */   
/*     */   public static void c(short[] paramArrayOfshort, ad paramad) {
/*     */     f(paramArrayOfshort, 0, paramArrayOfshort.length, paramad);
/*     */   }
/*     */ 
/*     */ 
/*     */ 
/*     */ 
/*     */ 
/*     */ 
/*     */ 
/*     */ 
/*     */ 
/*     */ 
/*     */ 
/*     */ 
/*     */ 
/*     */ 
/*     */ 
/*     */ 
/*     */ 
/*     */ 
/*     */ 
/*     */ 
/*     */ 
/*     */ 
/*     */ 
/*     */ 
/*     */ 
/*     */ 
/*     */ 
/*     */ 
/*     */ 
/*     */ 
/*     */ 
/*     */ 
/*     */ 
/*     */ 
/*     */ 
/*     */ 
/*     */ 
/*     */ 
/*     */   
/*     */   public static void a(short[] paramArrayOfshort1, int paramInt1, int paramInt2, ad paramad, short[] paramArrayOfshort2) {
/*     */     // Byte code:
/*     */     //   0: iload_2
/*     */     //   1: iload_1
/*     */     //   2: isub
/*     */     //   3: istore #5
/*     */     //   5: iload #5
/*     */     //   7: bipush #16
/*     */     //   9: if_icmpge -> 24
/*     */     //   12: aload_0
/*     */     //   13: iload_1
/*     */     //   14: iload_2
/*     */     //   15: aload_3
/*     */     //   16: invokestatic e : ([SIILme/konsolas/aac/ad;)V
/*     */     //   19: return
/*     */     //   20: invokestatic a : (Ljava/lang/Exception;)Ljava/lang/Exception;
/*     */     //   23: athrow
/*     */     //   24: aload #4
/*     */     //   26: ifnonnull -> 36
/*     */     //   29: aload_0
/*     */     //   30: iload_2
/*     */     //   31: invokestatic copyOf : ([SI)[S
/*     */     //   34: astore #4
/*     */     //   36: iload_1
/*     */     //   37: iload_2
/*     */     //   38: iadd
/*     */     //   39: iconst_1
/*     */     //   40: iushr
/*     */     //   41: istore #6
/*     */     //   43: aload #4
/*     */     //   45: iload_1
/*     */     //   46: iload #6
/*     */     //   48: aload_3
/*     */     //   49: aload_0
/*     */     //   50: invokestatic a : ([SIILme/konsolas/aac/ad;[S)V
/*     */     //   53: aload #4
/*     */     //   55: iload #6
/*     */     //   57: iload_2
/*     */     //   58: aload_3
/*     */     //   59: aload_0
/*     */     //   60: invokestatic a : ([SIILme/konsolas/aac/ad;[S)V
/*     */     //   63: aload_3
/*     */     //   64: aload #4
/*     */     //   66: iload #6
/*     */     //   68: iconst_1
/*     */     //   69: isub
/*     */     //   70: saload
/*     */     //   71: aload #4
/*     */     //   73: iload #6
/*     */     //   75: saload
/*     */     //   76: invokeinterface a : (SS)I
/*     */     //   81: ifgt -> 99
/*     */     //   84: aload #4
/*     */     //   86: iload_1
/*     */     //   87: aload_0
/*     */     //   88: iload_1
/*     */     //   89: iload #5
/*     */     //   91: invokestatic arraycopy : (Ljava/lang/Object;ILjava/lang/Object;II)V
/*     */     //   94: return
/*     */     //   95: invokestatic a : (Ljava/lang/Exception;)Ljava/lang/Exception;
/*     */     //   98: athrow
/*     */     //   99: iload_1
/*     */     //   100: istore #7
/*     */     //   102: iload_1
/*     */     //   103: istore #8
/*     */     //   105: iload #6
/*     */     //   107: istore #9
/*     */     //   109: iload #7
/*     */     //   111: iload_2
/*     */     //   112: if_icmpge -> 205
/*     */     //   115: iload #9
/*     */     //   117: iload_2
/*     */     //   118: if_icmpge -> 168
/*     */     //   121: goto -> 128
/*     */     //   124: invokestatic a : (Ljava/lang/Exception;)Ljava/lang/Exception;
/*     */     //   127: athrow
/*     */     //   128: iload #8
/*     */     //   130: iload #6
/*     */     //   132: if_icmpge -> 187
/*     */     //   135: goto -> 142
/*     */     //   138: invokestatic a : (Ljava/lang/Exception;)Ljava/lang/Exception;
/*     */     //   141: athrow
/*     */     //   142: aload_3
/*     */     //   143: aload #4
/*     */     //   145: iload #8
/*     */     //   147: saload
/*     */     //   148: aload #4
/*     */     //   150: iload #9
/*     */     //   152: saload
/*     */     //   153: invokeinterface a : (SS)I
/*     */     //   158: ifgt -> 187
/*     */     //   161: goto -> 168
/*     */     //   164: invokestatic a : (Ljava/lang/Exception;)Ljava/lang/Exception;
/*     */     //   167: athrow
/*     */     //   168: aload_0
/*     */     //   169: iload #7
/*     */     //   171: aload #4
/*     */     //   173: iload #8
/*     */     //   175: iinc #8, 1
/*     */     //   178: saload
/*     */     //   179: sastore
/*     */     //   180: goto -> 199
/*     */     //   183: invokestatic a : (Ljava/lang/Exception;)Ljava/lang/Exception;
/*     */     //   186: athrow
/*     */     //   187: aload_0
/*     */     //   188: iload #7
/*     */     //   190: aload #4
/*     */     //   192: iload #9
/*     */     //   194: iinc #9, 1
/*     */     //   197: saload
/*     */     //   198: sastore
/*     */     //   199: iinc #7, 1
/*     */     //   202: goto -> 109
/*     */     //   205: return
/*     */     // Line number table:
/*     */     //   Java source line number -> byte code offset
/*     */     //   #40	-> 0
/*     */     //   #466	-> 5
/*     */     //   #103	-> 12
/*     */     //   #937	-> 19
/*     */     //   #871	-> 24
/*     */     //   #64	-> 36
/*     */     //   #715	-> 43
/*     */     //   #859	-> 53
/*     */     //   #643	-> 63
/*     */     //   #611	-> 84
/*     */     //   #196	-> 94
/*     */     //   #713	-> 99
/*     */     //   #535	-> 115
/*     */     //   #689	-> 187
/*     */     //   #619	-> 199
/*     */     //   #409	-> 205
/*     */     // Exception table:
/*     */     //   from	to	target	type
/*     */     //   5	20	20	java/lang/IllegalArgumentException
/*     */     //   43	95	95	java/lang/IllegalArgumentException
/*     */     //   109	121	124	java/lang/IllegalArgumentException
/*     */     //   115	135	138	java/lang/IllegalArgumentException
/*     */     //   128	161	164	java/lang/IllegalArgumentException
/*     */     //   142	183	183	java/lang/IllegalArgumentException
/*     */   }
/*     */ 
/*     */ 
/*     */ 
/*     */ 
/*     */ 
/*     */ 
/*     */ 
/*     */ 
/*     */ 
/*     */ 
/*     */ 
/*     */ 
/*     */ 
/*     */ 
/*     */ 
/*     */ 
/*     */ 
/*     */ 
/*     */ 
/*     */ 
/*     */ 
/*     */ 
/*     */ 
/*     */ 
/*     */ 
/*     */ 
/*     */ 
/*     */ 
/*     */ 
/*     */ 
/*     */ 
/*     */ 
/*     */ 
/*     */ 
/*     */ 
/*     */ 
/*     */ 
/*     */ 
/*     */   
/*     */   public static void e(short[] paramArrayOfshort, int paramInt1, int paramInt2) {
/*     */     l(paramArrayOfshort, paramInt1, paramInt2);
/*     */   }
/*     */ 
/*     */ 
/*     */ 
/*     */ 
/*     */ 
/*     */ 
/*     */ 
/*     */ 
/*     */ 
/*     */ 
/*     */ 
/*     */ 
/*     */ 
/*     */ 
/*     */ 
/*     */ 
/*     */ 
/*     */ 
/*     */ 
/*     */ 
/*     */ 
/*     */ 
/*     */ 
/*     */ 
/*     */ 
/*     */ 
/*     */ 
/*     */ 
/*     */ 
/*     */ 
/*     */ 
/*     */ 
/*     */ 
/*     */ 
/*     */ 
/*     */ 
/*     */ 
/*     */   
/*     */   private static int a(short[] paramArrayOfshort, int paramInt1, int paramInt2, int paramInt3, ad paramad) {
/*     */     int i = paramad.a(paramArrayOfshort[paramInt1], paramArrayOfshort[paramInt2]);
/*     */     int k = paramad.a(paramArrayOfshort[paramInt1], paramArrayOfshort[paramInt3]);
/*     */     int m = paramad.a(paramArrayOfshort[paramInt2], paramArrayOfshort[paramInt3]);
/*     */     try {
/* 832 */       if (i < 0) {
/*     */         try {
/*     */           try {
/*     */           
/*     */           } catch (IllegalArgumentException illegalArgumentException) {
/*     */             throw a(null);
/*     */           } 
/*     */         } catch (IllegalArgumentException illegalArgumentException) {
/*     */           throw a(null);
/*     */         } 
/*     */       } else {
/*     */         try {
/*     */           try {
/*     */           
/*     */           } catch (IllegalArgumentException illegalArgumentException) {
/*     */             throw a(null);
/*     */           } 
/*     */         } catch (IllegalArgumentException illegalArgumentException) {
/*     */           throw a(null);
/*     */         } 
/*     */       } 
/*     */     } catch (IllegalArgumentException illegalArgumentException) {
/*     */       throw a(null);
/*     */     } 
/*     */     return (m > 0) ? paramInt2 : ((k > 0) ? paramInt3 : paramInt1);
/*     */   } @Deprecated
/*     */   public static void a(short[] paramArrayOfshort, int paramInt1, int paramInt2, short paramShort) {
/*     */     try {
/*     */       j(paramArrayOfshort, paramInt1, paramInt2);
/*     */       if (paramInt1 == 0) {
/*     */         try {
/*     */           for (; paramInt2-- != 0; paramArrayOfshort[paramInt2] = paramShort);
/*     */         } catch (IllegalArgumentException illegalArgumentException) {
/*     */           throw a(null);
/*     */         } 
/*     */       } else {
/*     */         int i = paramInt1;
/*     */         try {
/*     */           while (i < paramInt2) {
/*     */             paramArrayOfshort[i] = paramShort;
/*     */             i++;
/*     */           } 
/*     */         } catch (IllegalArgumentException illegalArgumentException) {
/*     */           throw a(null);
/*     */         } 
/*     */       } 
/*     */     } catch (IllegalArgumentException illegalArgumentException) {
/*     */       throw a(null);
/*     */     } 
/*     */   } public static void b(int[] paramArrayOfint, short[] paramArrayOfshort, boolean paramBoolean) {
/*     */     b(paramArrayOfint, paramArrayOfshort, 0, paramArrayOfshort.length, paramBoolean);
/*     */   } public static void a(short[] paramArrayOfshort, int paramInt1, int paramInt2, int paramInt3) {
/*     */     byte b = 0;
/*     */     try {
/*     */       while (b < paramInt3) {
/*     */         c(paramArrayOfshort, paramInt1, paramInt2);
/*     */         b++;
/*     */         paramInt1++;
/*     */         paramInt2++;
/*     */       } 
/*     */     } catch (IllegalArgumentException illegalArgumentException) {
/*     */       throw a(null);
/*     */     } 
/*     */   }
/*     */   public static int a(short[] paramArrayOfshort, short paramShort, ad paramad) {
/*     */     return a(paramArrayOfshort, 0, paramArrayOfshort.length, paramShort, paramad);
/*     */   }
/*     */   public static void f(short[] paramArrayOfshort1, short[] paramArrayOfshort2, int paramInt1, int paramInt2) {
/*     */     // Byte code:
/*     */     //   0: getstatic me/konsolas/aac/j.p : J
/*     */     //   3: ldc2_w 83825224850496
/*     */     //   6: lxor
/*     */     //   7: lstore #4
/*     */     //   9: invokestatic a : ()Ljava/util/concurrent/ForkJoinPool;
/*     */     //   12: astore #6
/*     */     //   14: iload_3
/*     */     //   15: iload_2
/*     */     //   16: isub
/*     */     //   17: sipush #1024
/*     */     //   20: if_icmplt -> 46
/*     */     //   23: aload #6
/*     */     //   25: invokevirtual getParallelism : ()I
/*     */     //   28: iconst_1
/*     */     //   29: if_icmpne -> 65
/*     */     //   32: goto -> 46
/*     */     //   35: ldc2_w -5633221985221754363
/*     */     //   38: lload #4
/*     */     //   40: <illegal opcode> w : (Ljava/lang/Exception;JJ)Ljava/lang/Exception;
/*     */     //   45: athrow
/*     */     //   46: aload_0
/*     */     //   47: aload_1
/*     */     //   48: iload_2
/*     */     //   49: iload_3
/*     */     //   50: invokestatic a : ([S[SII)V
/*     */     //   53: return
/*     */     //   54: ldc2_w -5633221985221754363
/*     */     //   57: lload #4
/*     */     //   59: <illegal opcode> w : (Ljava/lang/Exception;JJ)Ljava/lang/Exception;
/*     */     //   64: athrow
/*     */     //   65: iconst_2
/*     */     //   66: istore #7
/*     */     //   68: aload_0
/*     */     //   69: arraylength
/*     */     //   70: aload_1
/*     */     //   71: arraylength
/*     */     //   72: if_icmpeq -> 119
/*     */     //   75: new java/lang/IllegalArgumentException
/*     */     //   78: dup
/*     */     //   79: ldc_w '㮫ꦻㅖᤴ偩햓뢊爦䱕롟쯘᳋?䱁ऎ頜ꠈ逘扞'
/*     */     //   82: invokevirtual toCharArray : ()[C
/*     */     //   85: dup
/*     */     //   86: dup
/*     */     //   87: iconst_1
/*     */     //   88: dup_x1
/*     */     //   89: caload
/*     */     //   90: sipush #19276
/*     */     //   93: ixor
/*     */     //   94: i2c
/*     */     //   95: castore
/*     */     //   96: sipush #13738
/*     */     //   99: iconst_1
/*     */     //   100: iconst_1
/*     */     //   101: invokestatic X : (Ljava/lang/Object;SZZ)Ljava/lang/String;
/*     */     //   104: invokespecial <init> : (Ljava/lang/String;)V
/*     */     //   107: athrow
/*     */     //   108: ldc2_w -5633221985221754363
/*     */     //   111: lload #4
/*     */     //   113: <illegal opcode> w : (Ljava/lang/Exception;JJ)Ljava/lang/Exception;
/*     */     //   118: athrow
/*     */     //   119: iconst_3
/*     */     //   120: istore #8
/*     */     //   122: new java/util/concurrent/LinkedBlockingQueue
/*     */     //   125: dup
/*     */     //   126: invokespecial <init> : ()V
/*     */     //   129: astore #9
/*     */     //   131: aload #9
/*     */     //   133: new me/konsolas/aac/fm
/*     */     //   136: dup
/*     */     //   137: iload_2
/*     */     //   138: iload_3
/*     */     //   139: iload_2
/*     */     //   140: isub
/*     */     //   141: iconst_0
/*     */     //   142: invokespecial <init> : (III)V
/*     */     //   145: invokevirtual add : (Ljava/lang/Object;)Z
/*     */     //   148: pop
/*     */     //   149: new java/util/concurrent/atomic/AtomicInteger
/*     */     //   152: dup
/*     */     //   153: iconst_1
/*     */     //   154: invokespecial <init> : (I)V
/*     */     //   157: astore #10
/*     */     //   159: aload #6
/*     */     //   161: invokevirtual getParallelism : ()I
/*     */     //   164: istore #11
/*     */     //   166: new java/util/concurrent/ExecutorCompletionService
/*     */     //   169: dup
/*     */     //   170: aload #6
/*     */     //   172: invokespecial <init> : (Ljava/util/concurrent/Executor;)V
/*     */     //   175: astore #12
/*     */     //   177: iload #11
/*     */     //   179: istore #13
/*     */     //   181: iload #13
/*     */     //   183: iinc #13, -1
/*     */     //   186: ifeq -> 222
/*     */     //   189: aload #12
/*     */     //   191: aload #10
/*     */     //   193: iload #11
/*     */     //   195: aload #9
/*     */     //   197: aload_0
/*     */     //   198: aload_1
/*     */     //   199: <illegal opcode> call : (Ljava/util/concurrent/atomic/AtomicInteger;ILjava/util/concurrent/LinkedBlockingQueue;[S[S)Ljava/util/concurrent/Callable;
/*     */     //   204: invokevirtual submit : (Ljava/util/concurrent/Callable;)Ljava/util/concurrent/Future;
/*     */     //   207: pop
/*     */     //   208: goto -> 181
/*     */     //   211: ldc2_w -5633221985221754363
/*     */     //   214: lload #4
/*     */     //   216: <illegal opcode> w : (Ljava/lang/Exception;JJ)Ljava/lang/Exception;
/*     */     //   221: athrow
/*     */     //   222: aconst_null
/*     */     //   223: astore #13
/*     */     //   225: iload #11
/*     */     //   227: istore #14
/*     */     //   229: iload #14
/*     */     //   231: iinc #14, -1
/*     */     //   234: ifeq -> 263
/*     */     //   237: aload #12
/*     */     //   239: invokevirtual take : ()Ljava/util/concurrent/Future;
/*     */     //   242: invokeinterface get : ()Ljava/lang/Object;
/*     */     //   247: pop
/*     */     //   248: goto -> 229
/*     */     //   251: astore #15
/*     */     //   253: aload #15
/*     */     //   255: invokevirtual getCause : ()Ljava/lang/Throwable;
/*     */     //   258: astore #13
/*     */     //   260: goto -> 229
/*     */     //   263: aload #13
/*     */     //   265: ifnull -> 319
/*     */     //   268: aload #13
/*     */     //   270: instanceof java/lang/RuntimeException
/*     */     //   273: ifeq -> 309
/*     */     //   276: goto -> 290
/*     */     //   279: ldc2_w -5633221985221754363
/*     */     //   282: lload #4
/*     */     //   284: <illegal opcode> w : (Ljava/lang/Exception;JJ)Ljava/lang/Exception;
/*     */     //   289: athrow
/*     */     //   290: aload #13
/*     */     //   292: checkcast java/lang/RuntimeException
/*     */     //   295: goto -> 318
/*     */     //   298: ldc2_w -5633221985221754363
/*     */     //   301: lload #4
/*     */     //   303: <illegal opcode> w : (Ljava/lang/Exception;JJ)Ljava/lang/Exception;
/*     */     //   308: athrow
/*     */     //   309: new java/lang/RuntimeException
/*     */     //   312: dup
/*     */     //   313: aload #13
/*     */     //   315: invokespecial <init> : (Ljava/lang/Throwable;)V
/*     */     //   318: athrow
/*     */     //   319: return
/*     */     // Line number table:
/*     */     //   Java source line number -> byte code offset
/*     */     //   #75	-> 9
/*     */     //   #163	-> 14
/*     */     //   #214	-> 46
/*     */     //   #735	-> 53
/*     */     //   #901	-> 65
/*     */     //   #421	-> 68
/*     */     //   #520	-> 119
/*     */     //   #382	-> 122
/*     */     //   #359	-> 131
/*     */     //   #125	-> 149
/*     */     //   #351	-> 159
/*     */     //   #556	-> 166
/*     */     //   #113	-> 177
/*     */     //   #104	-> 222
/*     */     //   #246	-> 225
/*     */     //   #444	-> 237
/*     */     //   #263	-> 248
/*     */     //   #646	-> 251
/*     */     //   #603	-> 253
/*     */     //   #562	-> 260
/*     */     //   #397	-> 263
/*     */     //   #827	-> 319
/*     */     // Exception table:
/*     */     //   from	to	target	type
/*     */     //   14	32	35	java/lang/Exception
/*     */     //   23	54	54	java/lang/Exception
/*     */     //   68	108	108	java/lang/Exception
/*     */     //   181	211	211	java/lang/Exception
/*     */     //   237	248	251	java/lang/Exception
/*     */     //   263	276	279	java/lang/Exception
/*     */     //   268	298	298	java/lang/Exception
/*     */   }
/*     */   public static void e(short[] paramArrayOfshort1, short[] paramArrayOfshort2, int paramInt1, int paramInt2) { ForkJoinPool forkJoinPool = a();
/*     */     
/*     */     try { if (paramInt2 - paramInt1 >= 8192)
/*     */       { try {
/*     */           if (forkJoinPool.getParallelism() == 1) {
/*     */             a(paramArrayOfshort1, paramArrayOfshort2, paramInt1, paramInt2);
/*     */             return;
/*     */           } 
/*     */         } catch (IllegalArgumentException illegalArgumentException) {
/*     */           throw a(null);
/*     */         } 
/* 913 */         forkJoinPool.invoke(new ku(paramArrayOfshort1, paramArrayOfshort2, paramInt1, paramInt2)); return; }  } catch (IllegalArgumentException illegalArgumentException) { throw a(null); }  a(paramArrayOfshort1, paramArrayOfshort2, paramInt1, paramInt2); }
/*     */   private static void a(short[] paramArrayOfshort1, short[] paramArrayOfshort2, int paramInt1, int paramInt2, int paramInt3) { byte b = 0; try { while (b < paramInt3) { g(paramArrayOfshort1, paramArrayOfshort2, paramInt1, paramInt2); b++; paramInt1++; paramInt2++; }  } catch (IllegalArgumentException illegalArgumentException) { throw a(null); }  }
/*     */   public static void e(short[] paramArrayOfshort) { h(paramArrayOfshort, 0, paramArrayOfshort.length); }
/*     */   public static int a(short[] paramArrayOfshort, short paramShort) { return a(paramArrayOfshort, 0, paramArrayOfshort.length, paramShort); }
/*     */   public static void b(short[] paramArrayOfshort, int paramInt1, int paramInt2) { a(paramArrayOfshort, paramInt1, paramInt2, (short[])null); }
/*     */   public static int a(short[] paramArrayOfshort, int paramInt1, int paramInt2, short paramShort, ad paramad) { paramInt2--; while (paramInt1 <= paramInt2) { int i = paramInt1 + paramInt2 >>> 1; short s = paramArrayOfshort[i]; int k = paramad.a(s, paramShort); if (k < 0) paramInt1 = i + 1;  }  return -(paramInt1 + 1); }
/*     */   public static void d(short[] paramArrayOfshort, ad paramad) { c(paramArrayOfshort, 0, paramArrayOfshort.length, paramad); }
/*     */   private static void e(short[] paramArrayOfshort, int paramInt1, int paramInt2, ad paramad) { for (int i = paramInt1; ++i < paramInt2; paramArrayOfshort[k] = s1) { short s1 = paramArrayOfshort[i]; int k = i; short s2 = paramArrayOfshort[k - 1]; while (true) { try { if (paramad.a(s1, s2) < 0) { try { paramArrayOfshort[k] = s2; if (paramInt1 == k - 1) { k--; break; }  } catch (IllegalArgumentException illegalArgumentException) { throw a(null); }  s2 = paramArrayOfshort[--k - 1]; }  } catch (IllegalArgumentException illegalArgumentException) { throw a(null); }  break; }  }  } public static void a(short[] paramArrayOfshort, ad paramad) { d(paramArrayOfshort, 0, paramArrayOfshort.length, paramad); } @Deprecated public static boolean a(short[] paramArrayOfshort1, short[] paramArrayOfshort2) { int i = paramArrayOfshort1.length; try { if (i != paramArrayOfshort2.length) return false;  } catch (IllegalArgumentException illegalArgumentException) { throw a(null); }  while (i-- != 0) { if (paramArrayOfshort1[i] != paramArrayOfshort2[i]) return false;  }  return true; } public static short[] a(short[] paramArrayOfshort, int paramInt1, int paramInt2, Random paramRandom) { for (int i = paramInt2 - paramInt1; i-- != 0; paramArrayOfshort[paramInt1 + k] = s) { int k = paramRandom.nextInt(i + 1); short s = paramArrayOfshort[paramInt1 + i]; paramArrayOfshort[paramInt1 + i] = paramArrayOfshort[paramInt1 + k]; }  return paramArrayOfshort; } public static short[] b(short[] paramArrayOfshort) { return (short[])paramArrayOfshort.clone(); } public static void g(short[] paramArrayOfshort, int paramInt1, int paramInt2, ad paramad) { int i = paramInt2 - paramInt1; try { if (i < 16) { b(paramArrayOfshort, paramInt1, paramInt2, paramad); return; }  } catch (IllegalArgumentException illegalArgumentException) { throw a(null); }  int k = paramInt1 + i / 2; int m = paramInt1; int n = paramInt2 - 1; if (i > 128) { int i6 = i / 8; m = a(paramArrayOfshort, m, m + i6, m + 2 * i6, paramad); k = a(paramArrayOfshort, k - i6, k, k + i6, paramad); n = a(paramArrayOfshort, n - 2 * i6, n - i6, n, paramad); }  k = a(paramArrayOfshort, m, k, n, paramad); short s = paramArrayOfshort[k]; int i1 = paramInt1, i2 = i1, i3 = paramInt2 - 1, i4 = i3; for (;; c(paramArrayOfshort, i2++, i3--)) { if (i2 <= i3) { int i6; try { if ((i6 = paramad.a(paramArrayOfshort[i2], s)) <= 0) { try { if (i6 == 0) c(paramArrayOfshort, i1++, i2);  } catch (IllegalArgumentException illegalArgumentException) { throw a(null); }  i2++; }  } catch (IllegalArgumentException illegalArgumentException) { throw a(null); }  }  continue; while (i3 >= i2) { int i6; try { if ((i6 = paramad.a(paramArrayOfshort[i3], s)) >= 0) { try { if (i6 == 0) c(paramArrayOfshort, i3, i4--);  } catch (IllegalArgumentException illegalArgumentException) { throw a(null); }  i3--; }  } catch (IllegalArgumentException illegalArgumentException) { throw a(null); }  }  try { if (i2 > i3) break;  } catch (IllegalArgumentException illegalArgumentException) { throw a(null); }  }  int i5 = Math.min(i1 - paramInt1, i2 - i1); a(paramArrayOfshort, paramInt1, i2 - i5, i5); i5 = Math.min(i4 - i3, paramInt2 - i4 - 1); a(paramArrayOfshort, i2, paramInt2 - i5, i5); try { if ((i5 = i2 - i1) > 1) g(paramArrayOfshort, paramInt1, paramInt1 + i5, paramad);  } catch (IllegalArgumentException illegalArgumentException) { throw a(null); }  try { if ((i5 = i4 - i3) > 1) g(paramArrayOfshort, paramInt2 - i5, paramInt2, paramad);  } catch (IllegalArgumentException illegalArgumentException) { throw a(null); }  } public static void b(int[] paramArrayOfint, short[] paramArrayOfshort) { c(paramArrayOfint, paramArrayOfshort, 0, paramArrayOfshort.length); } private static ForkJoinPool a() { ForkJoinPool forkJoinPool = ForkJoinTask.getPool(); try {  } catch (IllegalArgumentException illegalArgumentException) { throw a(null); }  return (forkJoinPool == null) ? ForkJoinPool.commonPool() : forkJoinPool; } private static int b(short[] paramArrayOfshort, int paramInt1, int paramInt2, int paramInt3) { int i = Short.compare(paramArrayOfshort[paramInt1], paramArrayOfshort[paramInt2]); int k = Short.compare(paramArrayOfshort[paramInt1], paramArrayOfshort[paramInt3]); int m = Short.compare(paramArrayOfshort[paramInt2], paramArrayOfshort[paramInt3]); try { if (i < 0) { try { try {  } catch (IllegalArgumentException illegalArgumentException) { throw a(null); }  } catch (IllegalArgumentException illegalArgumentException) { throw a(null); }  } else { try { try {  } catch (IllegalArgumentException illegalArgumentException) { throw a(null); }  } catch (IllegalArgumentException illegalArgumentException) { throw a(null); }  }  } catch (IllegalArgumentException illegalArgumentException) { throw a(null); }  return (m > 0) ? paramInt2 : ((k > 0) ? paramInt3 : paramInt1); } public static void i(short[] paramArrayOfshort, int paramInt1, int paramInt2) { // Byte code:
/*     */     //   0: iload_2
/*     */     //   1: iload_1
/*     */     //   2: isub
/*     */     //   3: istore_3
/*     */     //   4: iload_3
/*     */     //   5: bipush #16
/*     */     //   7: if_icmpge -> 21
/*     */     //   10: aload_0
/*     */     //   11: iload_1
/*     */     //   12: iload_2
/*     */     //   13: invokestatic d : ([SII)V
/*     */     //   16: return
/*     */     //   17: invokestatic a : (Ljava/lang/Exception;)Ljava/lang/Exception;
/*     */     //   20: athrow
/*     */     //   21: iload_1
/*     */     //   22: iload_3
/*     */     //   23: iconst_2
/*     */     //   24: idiv
/*     */     //   25: iadd
/*     */     //   26: istore #4
/*     */     //   28: iload_1
/*     */     //   29: istore #5
/*     */     //   31: iload_2
/*     */     //   32: iconst_1
/*     */     //   33: isub
/*     */     //   34: istore #6
/*     */     //   36: iload_3
/*     */     //   37: sipush #128
/*     */     //   40: if_icmple -> 107
/*     */     //   43: iload_3
/*     */     //   44: bipush #8
/*     */     //   46: idiv
/*     */     //   47: istore #7
/*     */     //   49: aload_0
/*     */     //   50: iload #5
/*     */     //   52: iload #5
/*     */     //   54: iload #7
/*     */     //   56: iadd
/*     */     //   57: iload #5
/*     */     //   59: iconst_2
/*     */     //   60: iload #7
/*     */     //   62: imul
/*     */     //   63: iadd
/*     */     //   64: invokestatic b : ([SIII)I
/*     */     //   67: istore #5
/*     */     //   69: aload_0
/*     */     //   70: iload #4
/*     */     //   72: iload #7
/*     */     //   74: isub
/*     */     //   75: iload #4
/*     */     //   77: iload #4
/*     */     //   79: iload #7
/*     */     //   81: iadd
/*     */     //   82: invokestatic b : ([SIII)I
/*     */     //   85: istore #4
/*     */     //   87: aload_0
/*     */     //   88: iload #6
/*     */     //   90: iconst_2
/*     */     //   91: iload #7
/*     */     //   93: imul
/*     */     //   94: isub
/*     */     //   95: iload #6
/*     */     //   97: iload #7
/*     */     //   99: isub
/*     */     //   100: iload #6
/*     */     //   102: invokestatic b : ([SIII)I
/*     */     //   105: istore #6
/*     */     //   107: aload_0
/*     */     //   108: iload #5
/*     */     //   110: iload #4
/*     */     //   112: iload #6
/*     */     //   114: invokestatic b : ([SIII)I
/*     */     //   117: istore #4
/*     */     //   119: aload_0
/*     */     //   120: iload #4
/*     */     //   122: saload
/*     */     //   123: istore #7
/*     */     //   125: iload_1
/*     */     //   126: istore #8
/*     */     //   128: iload #8
/*     */     //   130: istore #9
/*     */     //   132: iload_2
/*     */     //   133: iconst_1
/*     */     //   134: isub
/*     */     //   135: istore #10
/*     */     //   137: iload #10
/*     */     //   139: istore #11
/*     */     //   141: iload #9
/*     */     //   143: iload #10
/*     */     //   145: if_icmpgt -> 199
/*     */     //   148: aload_0
/*     */     //   149: iload #9
/*     */     //   151: saload
/*     */     //   152: iload #7
/*     */     //   154: invokestatic compare : (SS)I
/*     */     //   157: dup
/*     */     //   158: istore #12
/*     */     //   160: ifgt -> 199
/*     */     //   163: iload #12
/*     */     //   165: ifne -> 193
/*     */     //   168: goto -> 175
/*     */     //   171: invokestatic a : (Ljava/lang/Exception;)Ljava/lang/Exception;
/*     */     //   174: athrow
/*     */     //   175: aload_0
/*     */     //   176: iload #8
/*     */     //   178: iinc #8, 1
/*     */     //   181: iload #9
/*     */     //   183: invokestatic c : ([SII)V
/*     */     //   186: goto -> 193
/*     */     //   189: invokestatic a : (Ljava/lang/Exception;)Ljava/lang/Exception;
/*     */     //   192: athrow
/*     */     //   193: iinc #9, 1
/*     */     //   196: goto -> 141
/*     */     //   199: iload #10
/*     */     //   201: iload #9
/*     */     //   203: if_icmplt -> 257
/*     */     //   206: aload_0
/*     */     //   207: iload #10
/*     */     //   209: saload
/*     */     //   210: iload #7
/*     */     //   212: invokestatic compare : (SS)I
/*     */     //   215: dup
/*     */     //   216: istore #12
/*     */     //   218: iflt -> 257
/*     */     //   221: iload #12
/*     */     //   223: ifne -> 251
/*     */     //   226: goto -> 233
/*     */     //   229: invokestatic a : (Ljava/lang/Exception;)Ljava/lang/Exception;
/*     */     //   232: athrow
/*     */     //   233: aload_0
/*     */     //   234: iload #10
/*     */     //   236: iload #11
/*     */     //   238: iinc #11, -1
/*     */     //   241: invokestatic c : ([SII)V
/*     */     //   244: goto -> 251
/*     */     //   247: invokestatic a : (Ljava/lang/Exception;)Ljava/lang/Exception;
/*     */     //   250: athrow
/*     */     //   251: iinc #10, -1
/*     */     //   254: goto -> 199
/*     */     //   257: iload #9
/*     */     //   259: iload #10
/*     */     //   261: if_icmple -> 271
/*     */     //   264: goto -> 288
/*     */     //   267: invokestatic a : (Ljava/lang/Exception;)Ljava/lang/Exception;
/*     */     //   270: athrow
/*     */     //   271: aload_0
/*     */     //   272: iload #9
/*     */     //   274: iinc #9, 1
/*     */     //   277: iload #10
/*     */     //   279: iinc #10, -1
/*     */     //   282: invokestatic c : ([SII)V
/*     */     //   285: goto -> 141
/*     */     //   288: iload #8
/*     */     //   290: iload_1
/*     */     //   291: isub
/*     */     //   292: iload #9
/*     */     //   294: iload #8
/*     */     //   296: isub
/*     */     //   297: invokestatic min : (II)I
/*     */     //   300: istore #12
/*     */     //   302: aload_0
/*     */     //   303: iload_1
/*     */     //   304: iload #9
/*     */     //   306: iload #12
/*     */     //   308: isub
/*     */     //   309: iload #12
/*     */     //   311: invokestatic a : ([SIII)V
/*     */     //   314: iload #11
/*     */     //   316: iload #10
/*     */     //   318: isub
/*     */     //   319: iload_2
/*     */     //   320: iload #11
/*     */     //   322: isub
/*     */     //   323: iconst_1
/*     */     //   324: isub
/*     */     //   325: invokestatic min : (II)I
/*     */     //   328: istore #12
/*     */     //   330: aload_0
/*     */     //   331: iload #9
/*     */     //   333: iload_2
/*     */     //   334: iload #12
/*     */     //   336: isub
/*     */     //   337: iload #12
/*     */     //   339: invokestatic a : ([SIII)V
/*     */     //   342: iload #9
/*     */     //   344: iload #8
/*     */     //   346: isub
/*     */     //   347: dup
/*     */     //   348: istore #12
/*     */     //   350: iconst_1
/*     */     //   351: if_icmple -> 370
/*     */     //   354: aload_0
/*     */     //   355: iload_1
/*     */     //   356: iload_1
/*     */     //   357: iload #12
/*     */     //   359: iadd
/*     */     //   360: invokestatic i : ([SII)V
/*     */     //   363: goto -> 370
/*     */     //   366: invokestatic a : (Ljava/lang/Exception;)Ljava/lang/Exception;
/*     */     //   369: athrow
/*     */     //   370: iload #11
/*     */     //   372: iload #10
/*     */     //   374: isub
/*     */     //   375: dup
/*     */     //   376: istore #12
/*     */     //   378: iconst_1
/*     */     //   379: if_icmple -> 398
/*     */     //   382: aload_0
/*     */     //   383: iload_2
/*     */     //   384: iload #12
/*     */     //   386: isub
/*     */     //   387: iload_2
/*     */     //   388: invokestatic i : ([SII)V
/*     */     //   391: goto -> 398
/*     */     //   394: invokestatic a : (Ljava/lang/Exception;)Ljava/lang/Exception;
/*     */     //   397: athrow
/*     */     //   398: return
/*     */     // Line number table:
/*     */     //   Java source line number -> byte code offset
/*     */     //   #291	-> 0
/*     */     //   #614	-> 4
/*     */     //   #914	-> 10
/*     */     //   #873	-> 16
/*     */     //   #679	-> 21
/*     */     //   #773	-> 28
/*     */     //   #577	-> 31
/*     */     //   #555	-> 36
/*     */     //   #912	-> 43
/*     */     //   #518	-> 49
/*     */     //   #811	-> 69
/*     */     //   #462	-> 87
/*     */     //   #379	-> 107
/*     */     //   #62	-> 119
/*     */     //   #551	-> 125
/*     */     //   #681	-> 141
/*     */     //   #331	-> 163
/*     */     //   #742	-> 193
/*     */     //   #3	-> 199
/*     */     //   #612	-> 221
/*     */     //   #42	-> 251
/*     */     //   #407	-> 257
/*     */     //   #626	-> 271
/*     */     //   #202	-> 288
/*     */     //   #146	-> 302
/*     */     //   #692	-> 314
/*     */     //   #16	-> 330
/*     */     //   #188	-> 342
/*     */     //   #15	-> 370
/*     */     //   #805	-> 398
/*     */     // Exception table:
/*     */     //   from	to	target	type
/*     */     //   4	17	17	java/lang/IllegalArgumentException
/*     */     //   160	168	171	java/lang/IllegalArgumentException
/*     */     //   163	186	189	java/lang/IllegalArgumentException
/*     */     //   218	226	229	java/lang/IllegalArgumentException
/*     */     //   221	244	247	java/lang/IllegalArgumentException
/*     */     //   257	267	267	java/lang/IllegalArgumentException
/*     */     //   350	363	366	java/lang/IllegalArgumentException
/* 920 */     //   378	391	394	java/lang/IllegalArgumentException } public static void g(short[] paramArrayOfshort) { i(paramArrayOfshort, 0, paramArrayOfshort.length); } public static void a(int[] paramArrayOfint, short[] paramArrayOfshort1, short[] paramArrayOfshort2, int paramInt1, int paramInt2, boolean paramBoolean) { try { if (paramInt2 - paramInt1 < 1024) { a(paramArrayOfint, paramArrayOfshort1, paramArrayOfshort2, paramInt1, paramInt2); return; }  } catch (IllegalArgumentException illegalArgumentException) { throw a(null); }  byte b1 = 2; byte b2 = 3; char c = '˾'; byte b3 = 0; int[] arrayOfInt1 = new int[766]; int[] arrayOfInt2 = new int[766]; int[] arrayOfInt3 = new int[766]; arrayOfInt1[b3] = paramInt1; arrayOfInt2[b3] = paramInt2 - paramInt1; arrayOfInt3[b3++] = 0; int[] arrayOfInt4 = new int[256]; int[] arrayOfInt5 = new int[256]; try {  } catch (IllegalArgumentException illegalArgumentException) { throw a(null); }  int[] arrayOfInt6 = paramBoolean ? new int[paramArrayOfint.length] : null; while (b3 > 0) { int i = arrayOfInt1[--b3]; int k = arrayOfInt2[b3]; int m = arrayOfInt3[b3]; try {  } catch (IllegalArgumentException illegalArgumentException) { throw a(null); }  boolean bool = (m % 2 == 0) ? true : false; try {  } catch (IllegalArgumentException illegalArgumentException) { throw a(null); }  short[] arrayOfShort = (m < 2) ? paramArrayOfshort1 : paramArrayOfshort2; int n = (1 - m % 2) * 8; int i1 = i + k; }  } public static void a(short[] paramArrayOfshort, int paramInt1, int paramInt2, ad paramad) { c(paramArrayOfshort, paramInt1, paramInt2, paramad); } public static void c(short[] paramArrayOfshort, int paramInt1, int paramInt2, ad paramad) { a(paramArrayOfshort, paramInt1, paramInt2, paramad, (short[])null); } private static int a(int[] paramArrayOfint, short[] paramArrayOfshort, int paramInt1, int paramInt2, int paramInt3) { short s1 = paramArrayOfshort[paramArrayOfint[paramInt1]]; short s2 = paramArrayOfshort[paramArrayOfint[paramInt2]]; short s3 = paramArrayOfshort[paramArrayOfint[paramInt3]]; int i = Short.compare(s1, s2); int k = Short.compare(s1, s3); int m = Short.compare(s2, s3); try { if (i < 0) { try { try {  } catch (IllegalArgumentException illegalArgumentException) { throw a(null); }  } catch (IllegalArgumentException illegalArgumentException) { throw a(null); }  } else { try { try {  } catch (IllegalArgumentException illegalArgumentException) { throw a(null); }  } catch (IllegalArgumentException illegalArgumentException) { throw a(null); }  }  } catch (IllegalArgumentException illegalArgumentException) { throw a(null); }  return (m > 0) ? paramInt2 : ((k > 0) ? paramInt3 : paramInt1); } public static void g(short[] paramArrayOfshort, int paramInt1, int paramInt2) { aL.a(paramArrayOfshort.length, paramInt1, paramInt2); } public static short[] d(short[] paramArrayOfshort, int paramInt1, int paramInt2) { if (paramInt1 > paramArrayOfshort.length) { int i = (int)Math.max(Math.min(paramArrayOfshort.length + (paramArrayOfshort.length >> 1), 2147483639L), paramInt1); short[] arrayOfShort = new short[i]; System.arraycopy(paramArrayOfshort, 0, arrayOfShort, 0, paramInt2); return arrayOfShort; }  return paramArrayOfshort; } private static int b(short[] paramArrayOfshort1, short[] paramArrayOfshort2, int paramInt1, int paramInt2, int paramInt3) { try {  } catch (IllegalArgumentException illegalArgumentException) { throw a(null); }  int i, k = ((i = Short.compare(paramArrayOfshort1[paramInt1], paramArrayOfshort1[paramInt2])) == 0) ? Short.compare(paramArrayOfshort2[paramInt1], paramArrayOfshort2[paramInt2]) : i; try {  } catch (IllegalArgumentException illegalArgumentException) { throw a(null); }  int m = ((i = Short.compare(paramArrayOfshort1[paramInt1], paramArrayOfshort1[paramInt3])) == 0) ? Short.compare(paramArrayOfshort2[paramInt1], paramArrayOfshort2[paramInt3]) : i; try {  } catch (IllegalArgumentException illegalArgumentException) { throw a(null); }  int n = ((i = Short.compare(paramArrayOfshort1[paramInt2], paramArrayOfshort1[paramInt3])) == 0) ? Short.compare(paramArrayOfshort2[paramInt2], paramArrayOfshort2[paramInt3]) : i; try { if (k < 0) { try { try {  } catch (IllegalArgumentException illegalArgumentException) { throw a(null); }  } catch (IllegalArgumentException illegalArgumentException) { throw a(null); }  } else { try { try {  } catch (IllegalArgumentException illegalArgumentException) { throw a(null); }  } catch (IllegalArgumentException illegalArgumentException) { throw a(null); }  }  } catch (IllegalArgumentException illegalArgumentException) { throw a(null); }  return (n > 0) ? paramInt2 : ((m > 0) ? paramInt3 : paramInt1); } public static void b(short[] paramArrayOfshort) { a(paramArrayOfshort, 0, paramArrayOfshort.length); } @Deprecated public static void a(short[] paramArrayOfshort, short paramShort) { int i = paramArrayOfshort.length; try { for (; i-- != 0; paramArrayOfshort[i] = paramShort); } catch (IllegalArgumentException illegalArgumentException) { throw a(null); }  } public static short[] b(short[] paramArrayOfshort, int paramInt) { return d(paramArrayOfshort, paramInt, paramArrayOfshort.length); } private static void a(int[] paramArrayOfint, short[] paramArrayOfshort1, short[] paramArrayOfshort2, int paramInt1, int paramInt2) { for (int i = paramInt1; ++i < paramInt2; paramArrayOfint[m] = k) { int k = paramArrayOfint[i]; int m = i; int n = paramArrayOfint[m - 1]; for (;; n = paramArrayOfint[--m - 1]) { try { if (paramArrayOfshort1[k] >= paramArrayOfshort1[n]) { try { if (paramArrayOfshort1[k] == paramArrayOfshort1[n]) try { if (paramArrayOfshort2[k] < paramArrayOfshort2[n]) continue;  } catch (IllegalArgumentException illegalArgumentException) { throw a(null); }   } catch (IllegalArgumentException illegalArgumentException) { throw a(null); }  break; }  } catch (IllegalArgumentException illegalArgumentException) { throw a(null); }  continue; try { paramArrayOfint[m] = n; if (paramInt1 == m - 1) { m--; break; }  } catch (IllegalArgumentException illegalArgumentException) { throw a(null); }  }  }  }
/*     */   public static void f(short[] paramArrayOfshort, int paramInt1, int paramInt2, ad paramad) { g(paramArrayOfshort, paramInt1, paramInt2, paramad); }
/*     */   public static void f(short[] paramArrayOfshort, int paramInt1, int paramInt2) { try { if (paramInt2 - paramInt1 < 1024) { i(paramArrayOfshort, paramInt1, paramInt2); return; }  } catch (IllegalArgumentException illegalArgumentException) { throw a(null); }  boolean bool = true; char c = 'Ā'; byte b = 0; int[] arrayOfInt1 = new int[256]; int[] arrayOfInt2 = new int[256]; int[] arrayOfInt3 = new int[256]; arrayOfInt1[b] = paramInt1; arrayOfInt2[b] = paramInt2 - paramInt1; arrayOfInt3[b++] = 0; int[] arrayOfInt4 = new int[256]; int[] arrayOfInt5 = new int[256]; while (b > 0) { int i = arrayOfInt1[--b]; int k = arrayOfInt2[b]; int m = arrayOfInt3[b]; try {  } catch (IllegalArgumentException illegalArgumentException) { throw a(null); }  }  }
/*     */   public static short[] a(short[] paramArrayOfshort, int paramInt) { return c(paramArrayOfshort, paramInt, paramArrayOfshort.length); }
/*     */   public static void a(int[] paramArrayOfint, short[] paramArrayOfshort, int paramInt1, int paramInt2) { // Byte code:
/*     */     //   0: iload_2
/*     */     //   1: istore #4
/*     */     //   3: iload_2
/*     */     //   4: iconst_1
/*     */     //   5: iadd
/*     */     //   6: istore #5
/*     */     //   8: iload #5
/*     */     //   10: iload_3
/*     */     //   11: if_icmpge -> 77
/*     */     //   14: aload_1
/*     */     //   15: aload_0
/*     */     //   16: iload #5
/*     */     //   18: iaload
/*     */     //   19: saload
/*     */     //   20: aload_1
/*     */     //   21: aload_0
/*     */     //   22: iload #4
/*     */     //   24: iaload
/*     */     //   25: saload
/*     */     //   26: if_icmpeq -> 71
/*     */     //   29: goto -> 36
/*     */     //   32: invokestatic a : (Ljava/lang/Exception;)Ljava/lang/Exception;
/*     */     //   35: athrow
/*     */     //   36: iload #5
/*     */     //   38: iload #4
/*     */     //   40: isub
/*     */     //   41: iconst_1
/*     */     //   42: if_icmple -> 67
/*     */     //   45: goto -> 52
/*     */     //   48: invokestatic a : (Ljava/lang/Exception;)Ljava/lang/Exception;
/*     */     //   51: athrow
/*     */     //   52: aload_0
/*     */     //   53: iload #4
/*     */     //   55: iload #5
/*     */     //   57: invokestatic k : ([III)V
/*     */     //   60: goto -> 67
/*     */     //   63: invokestatic a : (Ljava/lang/Exception;)Ljava/lang/Exception;
/*     */     //   66: athrow
/*     */     //   67: iload #5
/*     */     //   69: istore #4
/*     */     //   71: iinc #5, 1
/*     */     //   74: goto -> 8
/*     */     //   77: iload_3
/*     */     //   78: iload #4
/*     */     //   80: isub
/*     */     //   81: iconst_1
/*     */     //   82: if_icmple -> 99
/*     */     //   85: aload_0
/*     */     //   86: iload #4
/*     */     //   88: iload_3
/*     */     //   89: invokestatic k : ([III)V
/*     */     //   92: goto -> 99
/*     */     //   95: invokestatic a : (Ljava/lang/Exception;)Ljava/lang/Exception;
/*     */     //   98: athrow
/*     */     //   99: return
/*     */     // Line number table:
/*     */     //   Java source line number -> byte code offset
/*     */     //   #468	-> 0
/*     */     //   #120	-> 3
/*     */     //   #381	-> 14
/*     */     //   #99	-> 36
/*     */     //   #205	-> 67
/*     */     //   #228	-> 71
/*     */     //   #222	-> 77
/*     */     //   #416	-> 99
/*     */     // Exception table:
/*     */     //   from	to	target	type
/*     */     //   8	29	32	java/lang/IllegalArgumentException
/*     */     //   14	45	48	java/lang/IllegalArgumentException
/*     */     //   36	60	63	java/lang/IllegalArgumentException
/*     */     //   77	92	95	java/lang/IllegalArgumentException }
/*     */   public static short[] d(short[] paramArrayOfshort, int paramInt) { try { if (paramInt == paramArrayOfshort.length) return paramArrayOfshort;  } catch (IllegalArgumentException illegalArgumentException) { throw a(null); }  try { if (paramInt < paramArrayOfshort.length) return c(paramArrayOfshort, paramInt);  } catch (IllegalArgumentException illegalArgumentException) { throw a(null); }  return a(paramArrayOfshort, paramInt); }
/*     */   public static void a(int[] paramArrayOfint, short[] paramArrayOfshort) { d(paramArrayOfint, paramArrayOfshort, 0, paramArrayOfshort.length); }
/*     */   private static void k(short[] paramArrayOfshort, int paramInt1, int paramInt2) { for (int i = paramInt1; ++i < paramInt2; s2 = paramArrayOfshort[k - 1]) { short s2, s1 = paramArrayOfshort[i]; int k = i; }  }
/*     */   public static void c(short[] paramArrayOfshort) { l(paramArrayOfshort, 0, paramArrayOfshort.length); }
/*     */   public static void b(short[] paramArrayOfshort, ad paramad) { g(paramArrayOfshort, 0, paramArrayOfshort.length, paramad); }
/*     */   public static void c(short[] paramArrayOfshort, int paramInt1, int paramInt2) { short s = paramArrayOfshort[paramInt1]; paramArrayOfshort[paramInt1] = paramArrayOfshort[paramInt2]; paramArrayOfshort[paramInt2] = s; }
/*     */   public static void a(int[] paramArrayOfint, short[] paramArrayOfshort, int paramInt1, int paramInt2, boolean paramBoolean) { try { if (paramInt2 - paramInt1 < 1024) { b(paramArrayOfint, paramArrayOfshort, paramInt1, paramInt2); return; }  } catch (IllegalArgumentException illegalArgumentException) { throw a(null); }  boolean bool = true; char c = 'Ā'; byte b = 0; int[] arrayOfInt1 = new int[256]; int[] arrayOfInt2 = new int[256]; int[] arrayOfInt3 = new int[256]; arrayOfInt1[b] = paramInt1; arrayOfInt2[b] = paramInt2 - paramInt1; arrayOfInt3[b++] = 0; int[] arrayOfInt4 = new int[256]; int[] arrayOfInt5 = new int[256]; try {  } catch (IllegalArgumentException illegalArgumentException) { throw a(null); }  int[] arrayOfInt6 = paramBoolean ? new int[paramArrayOfint.length] : null; while (b > 0) { int i = arrayOfInt1[--b]; int k = arrayOfInt2[b]; int m = arrayOfInt3[b]; try {  } catch (IllegalArgumentException illegalArgumentException) { throw a(null); }  }  }
/*     */   public static void j(short[] paramArrayOfshort, int paramInt1, int paramInt2) { aL.b(paramArrayOfshort.length, paramInt1, paramInt2); }
/*     */   private static void b(short[] paramArrayOfshort, int paramInt1, int paramInt2, ad paramad) { for (int i = paramInt1; i < paramInt2 - 1; ) { int k = i; int m = i + 1; while (true) { try { if (m < paramInt2) { if (paramad.a(paramArrayOfshort[m], paramArrayOfshort[k]) < 0) k = m;  m++; continue; }  } catch (IllegalArgumentException illegalArgumentException) { throw a(null); }  if (k != i) { m = paramArrayOfshort[i]; paramArrayOfshort[i] = paramArrayOfshort[k]; paramArrayOfshort[k] = m; }  break; }  }  }
/*     */   private static void a(short[][] paramArrayOfshort, int paramInt1, int paramInt2, int paramInt3) { int i = paramArrayOfshort.length; int k = paramInt3 / 2; for (int m = paramInt1; m < paramInt2 - 1; ) { continue; n = m; for (int i1 = m + 1; i1 < paramInt2; i1++) { int i2 = k; while (true) { try { if (i2 < i) { if (paramArrayOfshort[i2][i1] < paramArrayOfshort[i2][n]) { n = i1; break; }  try { if (paramArrayOfshort[i2][i1] > paramArrayOfshort[i2][n]) break;  } catch (IllegalArgumentException illegalArgumentException) { throw a(null); }  }  } catch (IllegalArgumentException illegalArgumentException) { throw a(null); }  break; }  }  }  }
/*     */   public static void b(short[] paramArrayOfshort1, short[] paramArrayOfshort2) { e(paramArrayOfshort1, paramArrayOfshort2); a(paramArrayOfshort1, paramArrayOfshort2, 0, paramArrayOfshort1.length); }
/*     */   public static void a(short[] paramArrayOfshort1, int paramInt1, int paramInt2, short[] paramArrayOfshort2) { // Byte code:
/*     */     //   0: iload_2
/*     */     //   1: iload_1
/*     */     //   2: isub
/*     */     //   3: istore #4
/*     */     //   5: iload #4
/*     */     //   7: bipush #16
/*     */     //   9: if_icmpge -> 23
/*     */     //   12: aload_0
/*     */     //   13: iload_1
/*     */     //   14: iload_2
/*     */     //   15: invokestatic k : ([SII)V
/*     */     //   18: return
/*     */     //   19: invokestatic a : (Ljava/lang/Exception;)Ljava/lang/Exception;
/*     */     //   22: athrow
/*     */     //   23: aload_3
/*     */     //   24: ifnonnull -> 33
/*     */     //   27: aload_0
/*     */     //   28: iload_2
/*     */     //   29: invokestatic copyOf : ([SI)[S
/*     */     //   32: astore_3
/*     */     //   33: iload_1
/*     */     //   34: iload_2
/*     */     //   35: iadd
/*     */     //   36: iconst_1
/*     */     //   37: iushr
/*     */     //   38: istore #5
/*     */     //   40: aload_3
/*     */     //   41: iload_1
/*     */     //   42: iload #5
/*     */     //   44: aload_0
/*     */     //   45: invokestatic a : ([SII[S)V
/*     */     //   48: aload_3
/*     */     //   49: iload #5
/*     */     //   51: iload_2
/*     */     //   52: aload_0
/*     */     //   53: invokestatic a : ([SII[S)V
/*     */     //   56: aload_3
/*     */     //   57: iload #5
/*     */     //   59: iconst_1
/*     */     //   60: isub
/*     */     //   61: saload
/*     */     //   62: aload_3
/*     */     //   63: iload #5
/*     */     //   65: saload
/*     */     //   66: if_icmpgt -> 83
/*     */     //   69: aload_3
/*     */     //   70: iload_1
/*     */     //   71: aload_0
/*     */     //   72: iload_1
/*     */     //   73: iload #4
/*     */     //   75: invokestatic arraycopy : (Ljava/lang/Object;ILjava/lang/Object;II)V
/*     */     //   78: return
/*     */     //   79: invokestatic a : (Ljava/lang/Exception;)Ljava/lang/Exception;
/*     */     //   82: athrow
/*     */     //   83: iload_1
/*     */     //   84: istore #6
/*     */     //   86: iload_1
/*     */     //   87: istore #7
/*     */     //   89: iload #5
/*     */     //   91: istore #8
/*     */     //   93: iload #6
/*     */     //   95: iload_2
/*     */     //   96: if_icmpge -> 179
/*     */     //   99: iload #8
/*     */     //   101: iload_2
/*     */     //   102: if_icmpge -> 144
/*     */     //   105: goto -> 112
/*     */     //   108: invokestatic a : (Ljava/lang/Exception;)Ljava/lang/Exception;
/*     */     //   111: athrow
/*     */     //   112: iload #7
/*     */     //   114: iload #5
/*     */     //   116: if_icmpge -> 162
/*     */     //   119: goto -> 126
/*     */     //   122: invokestatic a : (Ljava/lang/Exception;)Ljava/lang/Exception;
/*     */     //   125: athrow
/*     */     //   126: aload_3
/*     */     //   127: iload #7
/*     */     //   129: saload
/*     */     //   130: aload_3
/*     */     //   131: iload #8
/*     */     //   133: saload
/*     */     //   134: if_icmpgt -> 162
/*     */     //   137: goto -> 144
/*     */     //   140: invokestatic a : (Ljava/lang/Exception;)Ljava/lang/Exception;
/*     */     //   143: athrow
/*     */     //   144: aload_0
/*     */     //   145: iload #6
/*     */     //   147: aload_3
/*     */     //   148: iload #7
/*     */     //   150: iinc #7, 1
/*     */     //   153: saload
/*     */     //   154: sastore
/*     */     //   155: goto -> 173
/*     */     //   158: invokestatic a : (Ljava/lang/Exception;)Ljava/lang/Exception;
/*     */     //   161: athrow
/*     */     //   162: aload_0
/*     */     //   163: iload #6
/*     */     //   165: aload_3
/*     */     //   166: iload #8
/*     */     //   168: iinc #8, 1
/*     */     //   171: saload
/*     */     //   172: sastore
/*     */     //   173: iinc #6, 1
/*     */     //   176: goto -> 93
/*     */     //   179: return
/*     */     // Line number table:
/*     */     //   Java source line number -> byte code offset
/*     */     //   #604	-> 0
/*     */     //   #797	-> 5
/*     */     //   #271	-> 12
/*     */     //   #581	-> 18
/*     */     //   #454	-> 23
/*     */     //   #804	-> 33
/*     */     //   #400	-> 40
/*     */     //   #574	-> 48
/*     */     //   #121	-> 56
/*     */     //   #815	-> 69
/*     */     //   #613	-> 78
/*     */     //   #934	-> 83
/*     */     //   #60	-> 99
/*     */     //   #226	-> 162
/*     */     //   #509	-> 173
/*     */     //   #174	-> 179
/*     */     // Exception table:
/*     */     //   from	to	target	type
/*     */     //   5	19	19	java/lang/IllegalArgumentException
/*     */     //   40	79	79	java/lang/IllegalArgumentException
/*     */     //   93	105	108	java/lang/IllegalArgumentException
/*     */     //   99	119	122	java/lang/IllegalArgumentException
/*     */     //   112	137	140	java/lang/IllegalArgumentException
/* 936 */     //   126	158	158	java/lang/IllegalArgumentException } public static void c(int[] paramArrayOfint, short[] paramArrayOfshort, int paramInt1, int paramInt2) { ForkJoinPool forkJoinPool = a(); try { if (paramInt2 - paramInt1 >= 8192) { try { if (forkJoinPool.getParallelism() == 1) { d(paramArrayOfint, paramArrayOfshort, paramInt1, paramInt2); return; }  } catch (IllegalArgumentException illegalArgumentException) { throw a(null); }  forkJoinPool.invoke(new am(paramArrayOfint, paramArrayOfshort, paramInt1, paramInt2)); return; }  } catch (IllegalArgumentException illegalArgumentException) { throw a(null); }  d(paramArrayOfint, paramArrayOfshort, paramInt1, paramInt2); } public static int a(short[] paramArrayOfshort, int paramInt1, int paramInt2, short paramShort) { paramInt2--; while (paramInt1 <= paramInt2) { int i = paramInt1 + paramInt2 >>> 1; short s = paramArrayOfshort[i]; if (s < paramShort) paramInt1 = i + 1;  }  return -(paramInt1 + 1); } public static void c(int[] paramArrayOfint, short[] paramArrayOfshort) { a(paramArrayOfint, paramArrayOfshort, 0, paramArrayOfint.length); } public static short[] b(short[] paramArrayOfshort, int paramInt1, int paramInt2) { short[] arrayOfShort = new short[paramInt1]; System.arraycopy(paramArrayOfshort, 0, arrayOfShort, 0, paramInt2); return arrayOfShort; } public static short[] a(short[] paramArrayOfshort, Random paramRandom) { for (int i = paramArrayOfshort.length; i-- != 0; paramArrayOfshort[i] = paramArrayOfshort[k]) { int k = paramRandom.nextInt(i + 1); short s = paramArrayOfshort[i]; }  return paramArrayOfshort; } private static void d(short[] paramArrayOfshort, int paramInt1, int paramInt2) { for (int i = paramInt1; i < paramInt2 - 1; m = i + 1) int m, k = i;  } public static void a(int[] paramArrayOfint, short[] paramArrayOfshort, boolean paramBoolean) { a(paramArrayOfint, paramArrayOfshort, 0, paramArrayOfint.length, paramBoolean); } public static short[] a(short[] paramArrayOfshort, int paramInt1, int paramInt2) { try { g(paramArrayOfshort, paramInt1, paramInt2); } catch (IllegalArgumentException illegalArgumentException) { throw a(null); }  short[] arrayOfShort = (paramInt2 == 0) ? e : new short[paramInt2]; System.arraycopy(paramArrayOfshort, paramInt1, arrayOfShort, 0, paramInt2); return arrayOfShort; }
/*     */   public static void a(short[] paramArrayOfshort) { f(paramArrayOfshort, 0, paramArrayOfshort.length); }
/*     */   public static void b(int[] paramArrayOfint, short[] paramArrayOfshort, int paramInt1, int paramInt2, boolean paramBoolean) { ForkJoinPool forkJoinPool = a(); try { if (paramInt2 - paramInt1 >= 1024) try { if (forkJoinPool.getParallelism() != 1) { boolean bool = true; LinkedBlockingQueue<fm> linkedBlockingQueue = new LinkedBlockingQueue(); linkedBlockingQueue.add(new fm(paramInt1, paramInt2 - paramInt1, 0)); AtomicInteger atomicInteger = new AtomicInteger(1); int i = forkJoinPool.getParallelism(); ExecutorCompletionService executorCompletionService = new ExecutorCompletionService(forkJoinPool); try {  } catch (Exception exception) { throw a(null); }  int[] arrayOfInt = paramBoolean ? new int[paramArrayOfint.length] : null; int k = i; try { for (; k-- != 0; executorCompletionService.submit(() -> { int[] arrayOfInt1 = new int[256]; int[] arrayOfInt2 = new int[256]; while (true) { if (paramAtomicInteger.get() == 0) { int i4 = paramInt; try { while (i4-- != 0) paramLinkedBlockingQueue.add(c);  } catch (Exception exception) { throw a(null); }  }  fm fm1 = paramLinkedBlockingQueue.take(); try { if (fm1 == c) return null;  } catch (Exception exception) { throw a(null); }  int i = fm1.a; int k = fm1.c; int m = fm1.b; try {  } catch (Exception exception) { throw a(null); }  boolean bool = (m % 2 == 0) ? true : false; int n = (1 - m % 2) * 8; int i1 = i + k; try { while (i1-- != i) arrayOfInt1[paramArrayOfshort[paramArrayOfint1[i1]] >>> n & 0xFF ^ bool] = arrayOfInt1[paramArrayOfshort[paramArrayOfint1[i1]] >>> n & 0xFF ^ bool] + 1;  } catch (Exception exception) { throw a(null); }  i1 = -1; int i2 = 0; int i3 = i; while (true) { try { if (i2 < 256) { if (arrayOfInt1[i2] != 0) i1 = i2;  arrayOfInt2[i2] = i3 += arrayOfInt1[i2]; i2++; continue; }  } catch (Exception exception) { throw a(null); }  if (paramBoolean) { i2 = i + k; try { while (i2-- != i) { arrayOfInt2[paramArrayOfshort[paramArrayOfint1[i2]] >>> n & 0xFF ^ bool] = arrayOfInt2[paramArrayOfshort[paramArrayOfint1[i2]] >>> n & 0xFF ^ bool] - 1; paramArrayOfint2[arrayOfInt2[paramArrayOfshort[paramArrayOfint1[i2]] >>> n & 0xFF ^ bool] - 1] = paramArrayOfint1[i2]; }  } catch (Exception exception) { throw a(null); }  System.arraycopy(paramArrayOfint2, i, paramArrayOfint1, i, k); i2 = 0; i3 = i; while (true) { try { if (i2 <= i1) { try { if (m < 1) try { if (arrayOfInt1[i2] > 1) try { if (arrayOfInt1[i2] < 1024) { a(paramArrayOfint1, paramArrayOfshort, i3, i3 + arrayOfInt1[i2], paramBoolean); } else { paramAtomicInteger.incrementAndGet(); paramLinkedBlockingQueue.add(new fm(i3, arrayOfInt1[i2], m + 1)); }  } catch (Exception exception) { throw a(null); }   } catch (Exception exception) { throw a(null); }   } catch (Exception exception) { throw a(null); }  i3 += arrayOfInt1[i2]; i2++; continue; }  } catch (Exception exception) { throw a(null); }  break; }  Arrays.fill(arrayOfInt1, 0); break; }  i2 = i + k - arrayOfInt1[i1]; i3 = i; int i4 = -1; while (i3 <= i2) { int i5 = paramArrayOfint1[i3]; i4 = paramArrayOfshort[i5] >>> n & 0xFF ^ bool; if (i3 < i2) { arrayOfInt2[i4] = arrayOfInt2[i4] - 1; int i6; while ((i6 = arrayOfInt2[i4] - 1) > i3) { int i7 = i5; i5 = paramArrayOfint1[i6]; paramArrayOfint1[i6] = i7; i4 = paramArrayOfshort[i5] >>> n & 0xFF ^ bool; }  paramArrayOfint1[i3] = i5; }  }  paramAtomicInteger.decrementAndGet(); }  paramAtomicInteger.decrementAndGet(); }  })); } catch (Exception exception) { throw a(null); }  Throwable throwable = null; for (int m = i; m-- != 0;) { try { executorCompletionService.take().get(); } catch (Exception exception) { throwable = exception.getCause(); }  }  try { if (throwable != null) { try {  } catch (Exception exception) { throw a(null); }  throw (throwable instanceof RuntimeException) ? (RuntimeException)throwable : new RuntimeException(throwable); }  } catch (Exception exception) { throw a(null); }  return; }  a(paramArrayOfint, paramArrayOfshort, paramInt1, paramInt2, paramBoolean); return; } catch (Exception exception) { throw a(null); }   } catch (Exception exception) { throw a(null); }  a(paramArrayOfint, paramArrayOfshort, paramInt1, paramInt2, paramBoolean); }
/*     */   public static void e(short[] paramArrayOfshort1, short[] paramArrayOfshort2) { // Byte code:
/*     */     //   0: getstatic me/konsolas/aac/j.p : J
/*     */     //   3: ldc2_w 51936100167789
/*     */     //   6: lxor
/*     */     //   7: lstore_2
/*     */     //   8: aload_0
/*     */     //   9: arraylength
/*     */     //   10: aload_1
/*     */     //   11: arraylength
/*     */     //   12: if_icmpeq -> 108
/*     */     //   15: new java/lang/IllegalArgumentException
/*     */     //   18: dup
/*     */     //   19: new java/lang/StringBuilder
/*     */     //   22: dup
/*     */     //   23: invokespecial <init> : ()V
/*     */     //   26: ldc 'ꀼ̩葯?⁡秎尘붐껜㇚杶膤럟톰♕檭へ㧩埢㙬'
/*     */     //   28: invokevirtual toCharArray : ()[C
/*     */     //   31: dup
/*     */     //   32: dup
/*     */     //   33: bipush #9
/*     */     //   35: dup_x1
/*     */     //   36: caload
/*     */     //   37: sipush #30332
/*     */     //   40: ixor
/*     */     //   41: i2c
/*     */     //   42: castore
/*     */     //   43: sipush #13899
/*     */     //   46: iconst_0
/*     */     //   47: iconst_0
/*     */     //   48: invokestatic A : (Ljava/lang/Object;SZI)Ljava/lang/String;
/*     */     //   51: invokevirtual append : (Ljava/lang/String;)Ljava/lang/StringBuilder;
/*     */     //   54: aload_0
/*     */     //   55: arraylength
/*     */     //   56: invokevirtual append : (I)Ljava/lang/StringBuilder;
/*     */     //   59: ldc '꛵黋㆑扣'
/*     */     //   61: invokevirtual toCharArray : ()[C
/*     */     //   64: dup
/*     */     //   65: dup
/*     */     //   66: iconst_3
/*     */     //   67: dup_x1
/*     */     //   68: caload
/*     */     //   69: sipush #2781
/*     */     //   72: ixor
/*     */     //   73: i2c
/*     */     //   74: castore
/*     */     //   75: sipush #17398
/*     */     //   78: iconst_0
/*     */     //   79: iconst_1
/*     */     //   80: invokestatic A : (Ljava/lang/Object;SZI)Ljava/lang/String;
/*     */     //   83: invokevirtual append : (Ljava/lang/String;)Ljava/lang/StringBuilder;
/*     */     //   86: aload_1
/*     */     //   87: arraylength
/*     */     //   88: invokevirtual append : (I)Ljava/lang/StringBuilder;
/*     */     //   91: invokevirtual toString : ()Ljava/lang/String;
/*     */     //   94: invokespecial <init> : (Ljava/lang/String;)V
/*     */     //   97: athrow
/*     */     //   98: ldc2_w -7061743781348708824
/*     */     //   101: lload_2
/*     */     //   102: <illegal opcode> w : (Ljava/lang/Exception;JJ)Ljava/lang/Exception;
/*     */     //   107: athrow
/*     */     //   108: return
/*     */     // Line number table:
/*     */     //   Java source line number -> byte code offset
/*     */     //   #702	-> 8
/*     */     //   #926	-> 108
/*     */     // Exception table:
/*     */     //   from	to	target	type
/*     */     //   8	98	98	java/lang/IllegalArgumentException }
/*     */   public static void c(short[] paramArrayOfshort1, short[] paramArrayOfshort2) { e(paramArrayOfshort1, paramArrayOfshort2); e(paramArrayOfshort1, paramArrayOfshort2, 0, paramArrayOfshort1.length); }
/*     */   public static short[] e(short[] paramArrayOfshort, int paramInt1, int paramInt2) { int i = paramInt2 - paramInt1; for (int k = i / 2; k-- != 0; paramArrayOfshort[paramInt1 + i - k - 1] = paramArrayOfshort[paramInt1 + k], paramArrayOfshort[paramInt1 + k] = s) short s = paramArrayOfshort[paramInt1 + i - k - 1];  return paramArrayOfshort; }
/*     */   private static void c(short[] paramArrayOfshort1, short[] paramArrayOfshort2, int paramInt1, int paramInt2) { for (int i = paramInt1; i < paramInt2 - 1; ) { continue; k = i; for (int m = i + 1; m < paramInt2;); }  }
/*     */   public static void b(short[] paramArrayOfshort1, short[] paramArrayOfshort2, int paramInt1, int paramInt2) { try { if (paramInt2 - paramInt1 < 1024) { c(paramArrayOfshort1, paramArrayOfshort2, paramInt1, paramInt2); return; }  } catch (IllegalArgumentException illegalArgumentException) { throw a(null); }  byte b1 = 2; byte b2 = 3; char c = '˾'; byte b3 = 0; int[] arrayOfInt1 = new int[766]; int[] arrayOfInt2 = new int[766]; int[] arrayOfInt3 = new int[766]; arrayOfInt1[b3] = paramInt1; arrayOfInt2[b3] = paramInt2 - paramInt1; arrayOfInt3[b3++] = 0; int[] arrayOfInt4 = new int[256]; int[] arrayOfInt5 = new int[256]; while (b3 > 0) { int i = arrayOfInt1[--b3]; int k = arrayOfInt2[b3]; int m = arrayOfInt3[b3]; try {  } catch (IllegalArgumentException illegalArgumentException) { throw a(null); }  boolean bool = (m % 2 == 0) ? true : false; try {  } catch (IllegalArgumentException illegalArgumentException) { throw a(null); }  short[] arrayOfShort = (m < 2) ? paramArrayOfshort1 : paramArrayOfshort2; int n = (1 - m % 2) * 8; int i1 = i + k; try { for (; i1-- != i; arrayOfInt4[arrayOfShort[i1] >>> n & 0xFF ^ bool] = arrayOfInt4[arrayOfShort[i1] >>> n & 0xFF ^ bool] + 1); } catch (IllegalArgumentException illegalArgumentException) { throw a(null); }  i1 = -1; int i2 = 0, i3 = i; while (true) { try { if (i2 < 256) { if (arrayOfInt4[i2] != 0) i1 = i2;  arrayOfInt5[i2] = i3 += arrayOfInt4[i2]; i2++; continue; }  } catch (IllegalArgumentException illegalArgumentException) { throw a(null); }  break; }  i2 = i + k - arrayOfInt4[i1]; int i4; for (i3 = i, i4 = -1; i3 <= i2; ) { continue; s1 = paramArrayOfshort1[i3]; s2 = paramArrayOfshort2[i3]; i4 = arrayOfShort[i3] >>> n & 0xFF ^ bool; }  }  }
/* 944 */   private static void g(short[] paramArrayOfshort1, short[] paramArrayOfshort2, int paramInt1, int paramInt2) { short s1 = paramArrayOfshort1[paramInt1]; short s2 = paramArrayOfshort2[paramInt1]; paramArrayOfshort1[paramInt1] = paramArrayOfshort1[paramInt2];
/*     */     paramArrayOfshort2[paramInt1] = paramArrayOfshort2[paramInt2];
/* 946 */     paramArrayOfshort1[paramInt2] = s1; paramArrayOfshort2[paramInt2] = s2; } public static void a(short[] paramArrayOfshort1, short[] paramArrayOfshort2, int paramInt1, int paramInt2) { // Byte code:
/*     */     //   0: iload_3
/*     */     //   1: iload_2
/*     */     //   2: isub
/*     */     //   3: istore #4
/*     */     //   5: iload #4
/*     */     //   7: bipush #16
/*     */     //   9: if_icmpge -> 24
/*     */     //   12: aload_0
/*     */     //   13: aload_1
/*     */     //   14: iload_2
/*     */     //   15: iload_3
/*     */     //   16: invokestatic c : ([S[SII)V
/*     */     //   19: return
/*     */     //   20: invokestatic a : (Ljava/lang/Exception;)Ljava/lang/Exception;
/*     */     //   23: athrow
/*     */     //   24: iload_2
/*     */     //   25: iload #4
/*     */     //   27: iconst_2
/*     */     //   28: idiv
/*     */     //   29: iadd
/*     */     //   30: istore #5
/*     */     //   32: iload_2
/*     */     //   33: istore #6
/*     */     //   35: iload_3
/*     */     //   36: iconst_1
/*     */     //   37: isub
/*     */     //   38: istore #7
/*     */     //   40: iload #4
/*     */     //   42: sipush #128
/*     */     //   45: if_icmple -> 116
/*     */     //   48: iload #4
/*     */     //   50: bipush #8
/*     */     //   52: idiv
/*     */     //   53: istore #8
/*     */     //   55: aload_0
/*     */     //   56: aload_1
/*     */     //   57: iload #6
/*     */     //   59: iload #6
/*     */     //   61: iload #8
/*     */     //   63: iadd
/*     */     //   64: iload #6
/*     */     //   66: iconst_2
/*     */     //   67: iload #8
/*     */     //   69: imul
/*     */     //   70: iadd
/*     */     //   71: invokestatic b : ([S[SIII)I
/*     */     //   74: istore #6
/*     */     //   76: aload_0
/*     */     //   77: aload_1
/*     */     //   78: iload #5
/*     */     //   80: iload #8
/*     */     //   82: isub
/*     */     //   83: iload #5
/*     */     //   85: iload #5
/*     */     //   87: iload #8
/*     */     //   89: iadd
/*     */     //   90: invokestatic b : ([S[SIII)I
/*     */     //   93: istore #5
/*     */     //   95: aload_0
/*     */     //   96: aload_1
/*     */     //   97: iload #7
/*     */     //   99: iconst_2
/*     */     //   100: iload #8
/*     */     //   102: imul
/*     */     //   103: isub
/*     */     //   104: iload #7
/*     */     //   106: iload #8
/*     */     //   108: isub
/*     */     //   109: iload #7
/*     */     //   111: invokestatic b : ([S[SIII)I
/*     */     //   114: istore #7
/*     */     //   116: aload_0
/*     */     //   117: aload_1
/*     */     //   118: iload #6
/*     */     //   120: iload #5
/*     */     //   122: iload #7
/*     */     //   124: invokestatic b : ([S[SIII)I
/*     */     //   127: istore #5
/*     */     //   129: aload_0
/*     */     //   130: iload #5
/*     */     //   132: saload
/*     */     //   133: istore #8
/*     */     //   135: aload_1
/*     */     //   136: iload #5
/*     */     //   138: saload
/*     */     //   139: istore #9
/*     */     //   141: iload_2
/*     */     //   142: istore #10
/*     */     //   144: iload #10
/*     */     //   146: istore #11
/*     */     //   148: iload_3
/*     */     //   149: iconst_1
/*     */     //   150: isub
/*     */     //   151: istore #12
/*     */     //   153: iload #12
/*     */     //   155: istore #13
/*     */     //   157: iload #11
/*     */     //   159: iload #12
/*     */     //   161: if_icmpgt -> 240
/*     */     //   164: aload_0
/*     */     //   165: iload #11
/*     */     //   167: saload
/*     */     //   168: iload #8
/*     */     //   170: invokestatic compare : (SS)I
/*     */     //   173: dup
/*     */     //   174: istore #15
/*     */     //   176: ifne -> 195
/*     */     //   179: aload_1
/*     */     //   180: iload #11
/*     */     //   182: saload
/*     */     //   183: iload #9
/*     */     //   185: invokestatic compare : (SS)I
/*     */     //   188: goto -> 197
/*     */     //   191: invokestatic a : (Ljava/lang/Exception;)Ljava/lang/Exception;
/*     */     //   194: athrow
/*     */     //   195: iload #15
/*     */     //   197: dup
/*     */     //   198: istore #14
/*     */     //   200: ifgt -> 240
/*     */     //   203: iload #14
/*     */     //   205: ifne -> 234
/*     */     //   208: goto -> 215
/*     */     //   211: invokestatic a : (Ljava/lang/Exception;)Ljava/lang/Exception;
/*     */     //   214: athrow
/*     */     //   215: aload_0
/*     */     //   216: aload_1
/*     */     //   217: iload #10
/*     */     //   219: iinc #10, 1
/*     */     //   222: iload #11
/*     */     //   224: invokestatic g : ([S[SII)V
/*     */     //   227: goto -> 234
/*     */     //   230: invokestatic a : (Ljava/lang/Exception;)Ljava/lang/Exception;
/*     */     //   233: athrow
/*     */     //   234: iinc #11, 1
/*     */     //   237: goto -> 157
/*     */     //   240: iload #12
/*     */     //   242: iload #11
/*     */     //   244: if_icmplt -> 323
/*     */     //   247: aload_0
/*     */     //   248: iload #12
/*     */     //   250: saload
/*     */     //   251: iload #8
/*     */     //   253: invokestatic compare : (SS)I
/*     */     //   256: dup
/*     */     //   257: istore #15
/*     */     //   259: ifne -> 278
/*     */     //   262: aload_1
/*     */     //   263: iload #12
/*     */     //   265: saload
/*     */     //   266: iload #9
/*     */     //   268: invokestatic compare : (SS)I
/*     */     //   271: goto -> 280
/*     */     //   274: invokestatic a : (Ljava/lang/Exception;)Ljava/lang/Exception;
/*     */     //   277: athrow
/*     */     //   278: iload #15
/*     */     //   280: dup
/*     */     //   281: istore #14
/*     */     //   283: iflt -> 323
/*     */     //   286: iload #14
/*     */     //   288: ifne -> 317
/*     */     //   291: goto -> 298
/*     */     //   294: invokestatic a : (Ljava/lang/Exception;)Ljava/lang/Exception;
/*     */     //   297: athrow
/*     */     //   298: aload_0
/*     */     //   299: aload_1
/*     */     //   300: iload #12
/*     */     //   302: iload #13
/*     */     //   304: iinc #13, -1
/*     */     //   307: invokestatic g : ([S[SII)V
/*     */     //   310: goto -> 317
/*     */     //   313: invokestatic a : (Ljava/lang/Exception;)Ljava/lang/Exception;
/*     */     //   316: athrow
/*     */     //   317: iinc #12, -1
/*     */     //   320: goto -> 240
/*     */     //   323: iload #11
/*     */     //   325: iload #12
/*     */     //   327: if_icmple -> 337
/*     */     //   330: goto -> 355
/*     */     //   333: invokestatic a : (Ljava/lang/Exception;)Ljava/lang/Exception;
/*     */     //   336: athrow
/*     */     //   337: aload_0
/*     */     //   338: aload_1
/*     */     //   339: iload #11
/*     */     //   341: iinc #11, 1
/*     */     //   344: iload #12
/*     */     //   346: iinc #12, -1
/*     */     //   349: invokestatic g : ([S[SII)V
/*     */     //   352: goto -> 157
/*     */     //   355: iload #10
/*     */     //   357: iload_2
/*     */     //   358: isub
/*     */     //   359: iload #11
/*     */     //   361: iload #10
/*     */     //   363: isub
/*     */     //   364: invokestatic min : (II)I
/*     */     //   367: istore #14
/*     */     //   369: aload_0
/*     */     //   370: aload_1
/*     */     //   371: iload_2
/*     */     //   372: iload #11
/*     */     //   374: iload #14
/*     */     //   376: isub
/*     */     //   377: iload #14
/*     */     //   379: invokestatic a : ([S[SIII)V
/*     */     //   382: iload #13
/*     */     //   384: iload #12
/*     */     //   386: isub
/*     */     //   387: iload_3
/*     */     //   388: iload #13
/*     */     //   390: isub
/*     */     //   391: iconst_1
/*     */     //   392: isub
/*     */     //   393: invokestatic min : (II)I
/*     */     //   396: istore #14
/*     */     //   398: aload_0
/*     */     //   399: aload_1
/*     */     //   400: iload #11
/*     */     //   402: iload_3
/*     */     //   403: iload #14
/*     */     //   405: isub
/*     */     //   406: iload #14
/*     */     //   408: invokestatic a : ([S[SIII)V
/*     */     //   411: iload #11
/*     */     //   413: iload #10
/*     */     //   415: isub
/*     */     //   416: dup
/*     */     //   417: istore #14
/*     */     //   419: iconst_1
/*     */     //   420: if_icmple -> 440
/*     */     //   423: aload_0
/*     */     //   424: aload_1
/*     */     //   425: iload_2
/*     */     //   426: iload_2
/*     */     //   427: iload #14
/*     */     //   429: iadd
/*     */     //   430: invokestatic a : ([S[SII)V
/*     */     //   433: goto -> 440
/*     */     //   436: invokestatic a : (Ljava/lang/Exception;)Ljava/lang/Exception;
/*     */     //   439: athrow
/*     */     //   440: iload #13
/*     */     //   442: iload #12
/*     */     //   444: isub
/*     */     //   445: dup
/*     */     //   446: istore #14
/*     */     //   448: iconst_1
/*     */     //   449: if_icmple -> 469
/*     */     //   452: aload_0
/*     */     //   453: aload_1
/*     */     //   454: iload_3
/*     */     //   455: iload #14
/*     */     //   457: isub
/*     */     //   458: iload_3
/*     */     //   459: invokestatic a : ([S[SII)V
/*     */     //   462: goto -> 469
/*     */     //   465: invokestatic a : (Ljava/lang/Exception;)Ljava/lang/Exception;
/*     */     //   468: athrow
/*     */     //   469: return
/*     */     // Line number table:
/*     */     //   Java source line number -> byte code offset
/*     */     //   #770	-> 0
/*     */     //   #295	-> 5
/*     */     //   #851	-> 12
/*     */     //   #453	-> 19
/*     */     //   #855	-> 24
/*     */     //   #18	-> 32
/*     */     //   #705	-> 35
/*     */     //   #267	-> 40
/*     */     //   #527	-> 48
/*     */     //   #846	-> 55
/*     */     //   #434	-> 76
/*     */     //   #131	-> 95
/*     */     //   #630	-> 116
/*     */     //   #697	-> 129
/*     */     //   #734	-> 141
/*     */     //   #906	-> 157
/*     */     //   #417	-> 203
/*     */     //   #927	-> 234
/*     */     //   #695	-> 240
/*     */     //   #371	-> 286
/*     */     //   #357	-> 317
/*     */     //   #589	-> 323
/*     */     //   #667	-> 337
/*     */     //   #768	-> 355
/*     */     //   #20	-> 369
/*     */     //   #282	-> 382
/*     */     //   #119	-> 398
/*     */     //   #513	-> 411
/*     */     //   #161	-> 440
/*     */     //   #819	-> 469
/*     */     // Exception table:
/*     */     //   from	to	target	type
/*     */     //   5	20	20	java/lang/IllegalArgumentException
/*     */     //   176	191	191	java/lang/IllegalArgumentException
/*     */     //   200	208	211	java/lang/IllegalArgumentException
/*     */     //   203	227	230	java/lang/IllegalArgumentException
/*     */     //   259	274	274	java/lang/IllegalArgumentException
/*     */     //   283	291	294	java/lang/IllegalArgumentException
/*     */     //   286	310	313	java/lang/IllegalArgumentException
/*     */     //   323	333	333	java/lang/IllegalArgumentException
/*     */     //   419	433	436	java/lang/IllegalArgumentException
/*     */     //   448	462	465	java/lang/IllegalArgumentException } public static void a(short[][] paramArrayOfshort, int paramInt1, int paramInt2) { // Byte code:
/*     */     //   0: getstatic me/konsolas/aac/j.p : J
/*     */     //   3: ldc2_w 115999855116224
/*     */     //   6: lxor
/*     */     //   7: lstore_3
/*     */     //   8: iload_2
/*     */     //   9: iload_1
/*     */     //   10: isub
/*     */     //   11: sipush #1024
/*     */     //   14: if_icmpge -> 35
/*     */     //   17: aload_0
/*     */     //   18: iload_1
/*     */     //   19: iload_2
/*     */     //   20: iconst_0
/*     */     //   21: invokestatic a : ([[SIII)V
/*     */     //   24: return
/*     */     //   25: ldc2_w -3291317903432375931
/*     */     //   28: lload_3
/*     */     //   29: <illegal opcode> w : (Ljava/lang/Exception;JJ)Ljava/lang/Exception;
/*     */     //   34: athrow
/*     */     //   35: aload_0
/*     */     //   36: arraylength
/*     */     //   37: istore #5
/*     */     //   39: iconst_2
/*     */     //   40: iload #5
/*     */     //   42: imul
/*     */     //   43: iconst_1
/*     */     //   44: isub
/*     */     //   45: istore #6
/*     */     //   47: iload #5
/*     */     //   49: istore #7
/*     */     //   51: aload_0
/*     */     //   52: iconst_0
/*     */     //   53: aaload
/*     */     //   54: arraylength
/*     */     //   55: istore #8
/*     */     //   57: iload #7
/*     */     //   59: iinc #7, -1
/*     */     //   62: ifeq -> 155
/*     */     //   65: aload_0
/*     */     //   66: iload #7
/*     */     //   68: aaload
/*     */     //   69: arraylength
/*     */     //   70: iload #8
/*     */     //   72: if_icmpeq -> 57
/*     */     //   75: new java/lang/IllegalArgumentException
/*     */     //   78: dup
/*     */     //   79: new java/lang/StringBuilder
/*     */     //   82: dup
/*     */     //   83: invokespecial <init> : ()V
/*     */     //   86: ldc_w '?峏镔?㊗坳Ɤ斀묏∼픢䛠솣扲江얈羠뗧罟'
/*     */     //   89: invokevirtual toCharArray : ()[C
/*     */     //   92: dup
/*     */     //   93: dup
/*     */     //   94: iconst_3
/*     */     //   95: dup_x1
/*     */     //   96: caload
/*     */     //   97: sipush #18699
/*     */     //   100: ixor
/*     */     //   101: i2c
/*     */     //   102: castore
/*     */     //   103: sipush #14363
/*     */     //   106: iconst_0
/*     */     //   107: iconst_1
/*     */     //   108: invokestatic G : (Ljava/lang/Object;SZB)Ljava/lang/String;
/*     */     //   111: invokevirtual append : (Ljava/lang/String;)Ljava/lang/StringBuilder;
/*     */     //   114: iload #7
/*     */     //   116: invokevirtual append : (I)Ljava/lang/StringBuilder;
/*     */     //   119: ldc_w '鉛舽㓗ⰾ讓ജ釗欤죹ﰛ漼篂ṍ셏쨿搪罩輬㖱?퐵濋ℐ蔪ፊ䓝ᮡ⩦誙?䱈싗?ἅ蒓׃﹞納흱ᚖ㤠肘븸˙᷶갏ᮎ'
/*     */     //   122: invokevirtual toCharArray : ()[C
/*     */     //   125: dup
/*     */     //   126: dup
/*     */     //   127: bipush #11
/*     */     //   129: dup_x1
/*     */     //   130: caload
/*     */     //   131: sipush #12421
/*     */     //   134: ixor
/*     */     //   135: i2c
/*     */     //   136: castore
/*     */     //   137: sipush #15427
/*     */     //   140: iconst_0
/*     */     //   141: iconst_0
/*     */     //   142: invokestatic G : (Ljava/lang/Object;SZB)Ljava/lang/String;
/*     */     //   145: invokevirtual append : (Ljava/lang/String;)Ljava/lang/StringBuilder;
/*     */     //   148: invokevirtual toString : ()Ljava/lang/String;
/*     */     //   151: invokespecial <init> : (Ljava/lang/String;)V
/*     */     //   154: athrow
/*     */     //   155: sipush #255
/*     */     //   158: iload #5
/*     */     //   160: iconst_2
/*     */     //   161: imul
/*     */     //   162: iconst_1
/*     */     //   163: isub
/*     */     //   164: imul
/*     */     //   165: iconst_1
/*     */     //   166: iadd
/*     */     //   167: istore #7
/*     */     //   169: iconst_0
/*     */     //   170: istore #8
/*     */     //   172: iload #7
/*     */     //   174: newarray int
/*     */     //   176: astore #9
/*     */     //   178: iload #7
/*     */     //   180: newarray int
/*     */     //   182: astore #10
/*     */     //   184: iload #7
/*     */     //   186: newarray int
/*     */     //   188: astore #11
/*     */     //   190: aload #9
/*     */     //   192: iload #8
/*     */     //   194: iload_1
/*     */     //   195: iastore
/*     */     //   196: aload #10
/*     */     //   198: iload #8
/*     */     //   200: iload_2
/*     */     //   201: iload_1
/*     */     //   202: isub
/*     */     //   203: iastore
/*     */     //   204: aload #11
/*     */     //   206: iload #8
/*     */     //   208: iinc #8, 1
/*     */     //   211: iconst_0
/*     */     //   212: iastore
/*     */     //   213: sipush #256
/*     */     //   216: newarray int
/*     */     //   218: astore #12
/*     */     //   220: sipush #256
/*     */     //   223: newarray int
/*     */     //   225: astore #13
/*     */     //   227: iload #5
/*     */     //   229: newarray short
/*     */     //   231: astore #14
/*     */     //   233: iload #8
/*     */     //   235: ifle -> 765
/*     */     //   238: aload #9
/*     */     //   240: iinc #8, -1
/*     */     //   243: iload #8
/*     */     //   245: iaload
/*     */     //   246: istore #15
/*     */     //   248: aload #10
/*     */     //   250: iload #8
/*     */     //   252: iaload
/*     */     //   253: istore #16
/*     */     //   255: aload #11
/*     */     //   257: iload #8
/*     */     //   259: iaload
/*     */     //   260: istore #17
/*     */     //   262: iload #17
/*     */     //   264: iconst_2
/*     */     //   265: irem
/*     */     //   266: ifne -> 285
/*     */     //   269: sipush #128
/*     */     //   272: goto -> 286
/*     */     //   275: ldc2_w -3291317903432375931
/*     */     //   278: lload_3
/*     */     //   279: <illegal opcode> w : (Ljava/lang/Exception;JJ)Ljava/lang/Exception;
/*     */     //   284: athrow
/*     */     //   285: iconst_0
/*     */     //   286: istore #18
/*     */     //   288: aload_0
/*     */     //   289: iload #17
/*     */     //   291: iconst_2
/*     */     //   292: idiv
/*     */     //   293: aaload
/*     */     //   294: astore #19
/*     */     //   296: iconst_1
/*     */     //   297: iload #17
/*     */     //   299: iconst_2
/*     */     //   300: irem
/*     */     //   301: isub
/*     */     //   302: bipush #8
/*     */     //   304: imul
/*     */     //   305: istore #20
/*     */     //   307: iload #15
/*     */     //   309: iload #16
/*     */     //   311: iadd
/*     */     //   312: istore #21
/*     */     //   314: iload #21
/*     */     //   316: iinc #21, -1
/*     */     //   319: iload #15
/*     */     //   321: if_icmpeq -> 359
/*     */     //   324: aload #12
/*     */     //   326: aload #19
/*     */     //   328: iload #21
/*     */     //   330: saload
/*     */     //   331: iload #20
/*     */     //   333: iushr
/*     */     //   334: sipush #255
/*     */     //   337: iand
/*     */     //   338: iload #18
/*     */     //   340: ixor
/*     */     //   341: dup2
/*     */     //   342: iaload
/*     */     //   343: iconst_1
/*     */     //   344: iadd
/*     */     //   345: iastore
/*     */     //   346: goto -> 314
/*     */     //   349: ldc2_w -3291317903432375931
/*     */     //   352: lload_3
/*     */     //   353: <illegal opcode> w : (Ljava/lang/Exception;JJ)Ljava/lang/Exception;
/*     */     //   358: athrow
/*     */     //   359: iconst_m1
/*     */     //   360: istore #21
/*     */     //   362: iconst_0
/*     */     //   363: istore #22
/*     */     //   365: iload #15
/*     */     //   367: istore #23
/*     */     //   369: iload #22
/*     */     //   371: sipush #256
/*     */     //   374: if_icmpge -> 424
/*     */     //   377: aload #12
/*     */     //   379: iload #22
/*     */     //   381: iaload
/*     */     //   382: ifeq -> 402
/*     */     //   385: goto -> 398
/*     */     //   388: ldc2_w -3291317903432375931
/*     */     //   391: lload_3
/*     */     //   392: <illegal opcode> w : (Ljava/lang/Exception;JJ)Ljava/lang/Exception;
/*     */     //   397: athrow
/*     */     //   398: iload #22
/*     */     //   400: istore #21
/*     */     //   402: aload #13
/*     */     //   404: iload #22
/*     */     //   406: iload #23
/*     */     //   408: aload #12
/*     */     //   410: iload #22
/*     */     //   412: iaload
/*     */     //   413: iadd
/*     */     //   414: dup
/*     */     //   415: istore #23
/*     */     //   417: iastore
/*     */     //   418: iinc #22, 1
/*     */     //   421: goto -> 369
/*     */     //   424: iload #15
/*     */     //   426: iload #16
/*     */     //   428: iadd
/*     */     //   429: aload #12
/*     */     //   431: iload #21
/*     */     //   433: iaload
/*     */     //   434: isub
/*     */     //   435: istore #22
/*     */     //   437: iload #15
/*     */     //   439: istore #23
/*     */     //   441: iconst_m1
/*     */     //   442: istore #24
/*     */     //   444: iload #23
/*     */     //   446: iload #22
/*     */     //   448: if_icmpgt -> 762
/*     */     //   451: iload #5
/*     */     //   453: istore #26
/*     */     //   455: iload #26
/*     */     //   457: iinc #26, -1
/*     */     //   460: ifeq -> 488
/*     */     //   463: aload #14
/*     */     //   465: iload #26
/*     */     //   467: aload_0
/*     */     //   468: iload #26
/*     */     //   470: aaload
/*     */     //   471: iload #23
/*     */     //   473: saload
/*     */     //   474: sastore
/*     */     //   475: goto -> 455
/*     */     //   478: ldc2_w -3291317903432375931
/*     */     //   481: lload_3
/*     */     //   482: <illegal opcode> w : (Ljava/lang/Exception;JJ)Ljava/lang/Exception;
/*     */     //   487: athrow
/*     */     //   488: aload #19
/*     */     //   490: iload #23
/*     */     //   492: saload
/*     */     //   493: iload #20
/*     */     //   495: iushr
/*     */     //   496: sipush #255
/*     */     //   499: iand
/*     */     //   500: iload #18
/*     */     //   502: ixor
/*     */     //   503: istore #24
/*     */     //   505: iload #23
/*     */     //   507: iload #22
/*     */     //   509: if_icmpge -> 630
/*     */     //   512: aload #13
/*     */     //   514: iload #24
/*     */     //   516: dup2
/*     */     //   517: iaload
/*     */     //   518: iconst_1
/*     */     //   519: isub
/*     */     //   520: dup_x2
/*     */     //   521: iastore
/*     */     //   522: dup
/*     */     //   523: istore #25
/*     */     //   525: iload #23
/*     */     //   527: if_icmple -> 593
/*     */     //   530: aload #19
/*     */     //   532: iload #25
/*     */     //   534: saload
/*     */     //   535: iload #20
/*     */     //   537: iushr
/*     */     //   538: sipush #255
/*     */     //   541: iand
/*     */     //   542: iload #18
/*     */     //   544: ixor
/*     */     //   545: istore #24
/*     */     //   547: iload #5
/*     */     //   549: istore #26
/*     */     //   551: iload #26
/*     */     //   553: iinc #26, -1
/*     */     //   556: ifeq -> 590
/*     */     //   559: aload #14
/*     */     //   561: iload #26
/*     */     //   563: saload
/*     */     //   564: istore #27
/*     */     //   566: aload #14
/*     */     //   568: iload #26
/*     */     //   570: aload_0
/*     */     //   571: iload #26
/*     */     //   573: aaload
/*     */     //   574: iload #25
/*     */     //   576: saload
/*     */     //   577: sastore
/*     */     //   578: aload_0
/*     */     //   579: iload #26
/*     */     //   581: aaload
/*     */     //   582: iload #25
/*     */     //   584: iload #27
/*     */     //   586: sastore
/*     */     //   587: goto -> 551
/*     */     //   590: goto -> 512
/*     */     //   593: iload #5
/*     */     //   595: istore #26
/*     */     //   597: iload #26
/*     */     //   599: iinc #26, -1
/*     */     //   602: ifeq -> 630
/*     */     //   605: aload_0
/*     */     //   606: iload #26
/*     */     //   608: aaload
/*     */     //   609: iload #23
/*     */     //   611: aload #14
/*     */     //   613: iload #26
/*     */     //   615: saload
/*     */     //   616: sastore
/*     */     //   617: goto -> 597
/*     */     //   620: ldc2_w -3291317903432375931
/*     */     //   623: lload_3
/*     */     //   624: <illegal opcode> w : (Ljava/lang/Exception;JJ)Ljava/lang/Exception;
/*     */     //   629: athrow
/*     */     //   630: iload #17
/*     */     //   632: iload #6
/*     */     //   634: if_icmpge -> 743
/*     */     //   637: aload #12
/*     */     //   639: iload #24
/*     */     //   641: iaload
/*     */     //   642: iconst_1
/*     */     //   643: if_icmple -> 743
/*     */     //   646: goto -> 659
/*     */     //   649: ldc2_w -3291317903432375931
/*     */     //   652: lload_3
/*     */     //   653: <illegal opcode> w : (Ljava/lang/Exception;JJ)Ljava/lang/Exception;
/*     */     //   658: athrow
/*     */     //   659: aload #12
/*     */     //   661: iload #24
/*     */     //   663: iaload
/*     */     //   664: sipush #1024
/*     */     //   667: if_icmpge -> 714
/*     */     //   670: goto -> 683
/*     */     //   673: ldc2_w -3291317903432375931
/*     */     //   676: lload_3
/*     */     //   677: <illegal opcode> w : (Ljava/lang/Exception;JJ)Ljava/lang/Exception;
/*     */     //   682: athrow
/*     */     //   683: aload_0
/*     */     //   684: iload #23
/*     */     //   686: iload #23
/*     */     //   688: aload #12
/*     */     //   690: iload #24
/*     */     //   692: iaload
/*     */     //   693: iadd
/*     */     //   694: iload #17
/*     */     //   696: iconst_1
/*     */     //   697: iadd
/*     */     //   698: invokestatic a : ([[SIII)V
/*     */     //   701: goto -> 743
/*     */     //   704: ldc2_w -3291317903432375931
/*     */     //   707: lload_3
/*     */     //   708: <illegal opcode> w : (Ljava/lang/Exception;JJ)Ljava/lang/Exception;
/*     */     //   713: athrow
/*     */     //   714: aload #9
/*     */     //   716: iload #8
/*     */     //   718: iload #23
/*     */     //   720: iastore
/*     */     //   721: aload #10
/*     */     //   723: iload #8
/*     */     //   725: aload #12
/*     */     //   727: iload #24
/*     */     //   729: iaload
/*     */     //   730: iastore
/*     */     //   731: aload #11
/*     */     //   733: iload #8
/*     */     //   735: iinc #8, 1
/*     */     //   738: iload #17
/*     */     //   740: iconst_1
/*     */     //   741: iadd
/*     */     //   742: iastore
/*     */     //   743: iload #23
/*     */     //   745: aload #12
/*     */     //   747: iload #24
/*     */     //   749: iaload
/*     */     //   750: iadd
/*     */     //   751: istore #23
/*     */     //   753: aload #12
/*     */     //   755: iload #24
/*     */     //   757: iconst_0
/*     */     //   758: iastore
/*     */     //   759: goto -> 444
/*     */     //   762: goto -> 233
/*     */     //   765: return
/*     */     // Line number table:
/*     */     //   Java source line number -> byte code offset
/*     */     //   #772	-> 8
/*     */     //   #635	-> 17
/*     */     //   #220	-> 24
/*     */     //   #347	-> 35
/*     */     //   #194	-> 39
/*     */     //   #904	-> 47
/*     */     //   #436	-> 155
/*     */     //   #440	-> 169
/*     */     //   #147	-> 172
/*     */     //   #870	-> 178
/*     */     //   #544	-> 184
/*     */     //   #65	-> 190
/*     */     //   #703	-> 196
/*     */     //   #883	-> 204
/*     */     //   #503	-> 213
/*     */     //   #140	-> 220
/*     */     //   #155	-> 227
/*     */     //   #464	-> 233
/*     */     //   #548	-> 238
/*     */     //   #512	-> 248
/*     */     //   #173	-> 255
/*     */     //   #932	-> 262
/*     */     //   #327	-> 288
/*     */     //   #922	-> 296
/*     */     //   #366	-> 307
/*     */     //   #117	-> 359
/*     */     //   #394	-> 362
/*     */     //   #517	-> 377
/*     */     //   #428	-> 402
/*     */     //   #579	-> 418
/*     */     //   #320	-> 424
/*     */     //   #750	-> 437
/*     */     //   #100	-> 451
/*     */     //   #177	-> 488
/*     */     //   #823	-> 505
/*     */     //   #72	-> 512
/*     */     //   #930	-> 530
/*     */     //   #148	-> 547
/*     */     //   #87	-> 559
/*     */     //   #26	-> 566
/*     */     //   #353	-> 578
/*     */     //   #158	-> 587
/*     */     //   #50	-> 593
/*     */     //   #167	-> 630
/*     */     //   #640	-> 659
/*     */     //   #774	-> 714
/*     */     //   #315	-> 721
/*     */     //   #511	-> 731
/*     */     //   #101	-> 743
/*     */     //   #135	-> 762
/*     */     //   #344	-> 765
/*     */     // Exception table:
/*     */     //   from	to	target	type
/*     */     //   8	25	25	java/lang/IllegalArgumentException
/*     */     //   262	275	275	java/lang/IllegalArgumentException
/*     */     //   314	349	349	java/lang/IllegalArgumentException
/*     */     //   369	385	388	java/lang/IllegalArgumentException
/*     */     //   455	478	478	java/lang/IllegalArgumentException
/*     */     //   597	620	620	java/lang/IllegalArgumentException
/*     */     //   630	646	649	java/lang/IllegalArgumentException
/*     */     //   637	670	673	java/lang/IllegalArgumentException
/*     */     //   659	704	704	java/lang/IllegalArgumentException } public static void h(short[] paramArrayOfshort, int paramInt1, int paramInt2) { ForkJoinPool forkJoinPool = a(); try { if (paramInt2 - paramInt1 >= 8192) { try { if (forkJoinPool.getParallelism() == 1) { i(paramArrayOfshort, paramInt1, paramInt2); return; }  } catch (IllegalArgumentException illegalArgumentException) { throw a(null); }  forkJoinPool.invoke(new eu(paramArrayOfshort, paramInt1, paramInt2)); return; }  } catch (IllegalArgumentException illegalArgumentException) { throw a(null); }  i(paramArrayOfshort, paramInt1, paramInt2); } public static void a(short[] paramArrayOfshort, int paramInt1, int paramInt2) { ForkJoinPool forkJoinPool = a(); try { if (paramInt2 - paramInt1 >= 1024) try { if (forkJoinPool.getParallelism() != 1) { boolean bool = true; LinkedBlockingQueue<fm> linkedBlockingQueue = new LinkedBlockingQueue(); linkedBlockingQueue.add(new fm(paramInt1, paramInt2 - paramInt1, 0)); AtomicInteger atomicInteger = new AtomicInteger(1); int i = forkJoinPool.getParallelism(); ExecutorCompletionService executorCompletionService = new ExecutorCompletionService(forkJoinPool); int k = i; try { for (; k-- != 0; executorCompletionService.submit(() -> { int[] arrayOfInt1 = new int[256]; int[] arrayOfInt2 = new int[256]; while (true) { if (paramAtomicInteger.get() == 0) { int i5 = paramInt; try { while (i5-- != 0) paramLinkedBlockingQueue.add(c);  } catch (Exception exception) { throw a(null); }  }  fm fm1 = paramLinkedBlockingQueue.take(); try { if (fm1 == c) return null;  } catch (Exception exception) { throw a(null); }  int i = fm1.a; int k = fm1.c; int m = fm1.b; try {  } catch (Exception exception) { throw a(null); }  boolean bool = (m % 2 == 0) ? true : false; int n = (1 - m % 2) * 8; int i1 = i + k; try { while (i1-- != i) arrayOfInt1[paramArrayOfshort[i1] >>> n & 0xFF ^ bool] = arrayOfInt1[paramArrayOfshort[i1] >>> n & 0xFF ^ bool] + 1;  } catch (Exception exception) { throw a(null); }  i1 = -1; int i2 = 0; int i3 = i; while (true) { try { if (i2 < 256) { if (arrayOfInt1[i2] != 0) i1 = i2;  arrayOfInt2[i2] = i3 += arrayOfInt1[i2]; i2++; continue; }  } catch (Exception exception) { throw a(null); }  break; }  i2 = i + k - arrayOfInt1[i1]; i3 = i; for (int i4 = -1; i3 <= i2; i4 = SYNTHETIC_LOCAL_VARIABLE_17 >>> n & 0xFF ^ bool) { short s = paramArrayOfshort[i3]; continue; }  paramAtomicInteger.decrementAndGet(); }  })); } catch (Exception exception) { throw a(null); }  Throwable throwable = null; for (int m = i; m-- != 0;) { try { executorCompletionService.take().get(); } catch (Exception exception) { throwable = exception.getCause(); }  }  try { if (throwable != null) { try {  } catch (Exception exception) { throw a(null); }  throw (throwable instanceof RuntimeException) ? (RuntimeException)throwable : new RuntimeException(throwable); }  } catch (Exception exception) { throw a(null); }  return; }  i(paramArrayOfshort, paramInt1, paramInt2); return; } catch (Exception exception) { throw a(null); }   } catch (Exception exception) { throw a(null); }  i(paramArrayOfshort, paramInt1, paramInt2); } public static void d(short[] paramArrayOfshort1, short[] paramArrayOfshort2) { e(paramArrayOfshort1, paramArrayOfshort2); f(paramArrayOfshort1, paramArrayOfshort2, 0, paramArrayOfshort1.length); } public static void e(short[] paramArrayOfshort, ad paramad) { a(paramArrayOfshort, 0, paramArrayOfshort.length, paramad); } public static void a(int[] paramArrayOfint, short[] paramArrayOfshort1, short[] paramArrayOfshort2, boolean paramBoolean) { e(paramArrayOfshort1, paramArrayOfshort2); a(paramArrayOfint, paramArrayOfshort1, paramArrayOfshort2, 0, paramArrayOfshort1.length, paramBoolean); } public static short[] c(short[] paramArrayOfshort, int paramInt) { try { if (paramInt >= paramArrayOfshort.length) return paramArrayOfshort;  } catch (IllegalArgumentException illegalArgumentException) { throw a(null); }  try {  } catch (IllegalArgumentException illegalArgumentException) { throw a(null); }  short[] arrayOfShort = (paramInt == 0) ? e : new short[paramInt]; System.arraycopy(paramArrayOfshort, 0, arrayOfShort, 0, paramInt); return arrayOfShort; } public static void d(short[] paramArrayOfshort) { e(paramArrayOfshort, 0, paramArrayOfshort.length); } public static short[] a(short[] paramArrayOfshort) { int i = paramArrayOfshort.length; for (int k = i / 2; k-- != 0; paramArrayOfshort[i - k - 1] = paramArrayOfshort[k], paramArrayOfshort[k] = s) short s = paramArrayOfshort[i - k - 1];  return paramArrayOfshort; } public static void a(short[][] paramArrayOfshort) { a(paramArrayOfshort, 0, (paramArrayOfshort[0]).length); } public static void f(short[] paramArrayOfshort) { b(paramArrayOfshort, 0, paramArrayOfshort.length); }
/* 947 */   private static void b(int[] paramArrayOfint, short[] paramArrayOfshort, int paramInt1, int paramInt2) { for (int i = paramInt1; ++i < paramInt2; m = i) int m, k = paramArrayOfint[i];  }
/*     */ 
/*     */   
/*     */   public static short[] c(short[] paramArrayOfshort, int paramInt1, int paramInt2) {
/*     */     try {
/*     */     
/*     */     } catch (IllegalArgumentException illegalArgumentException) {
/*     */       throw a(null);
/*     */     } 
/*     */     return (paramInt1 > paramArrayOfshort.length) ? b(paramArrayOfshort, paramInt1, paramInt2) : paramArrayOfshort;
/*     */   }
/*     */   
/*     */   public static void l(short[] paramArrayOfshort, int paramInt1, int paramInt2) {
/*     */     try {
/*     */       if (paramInt2 - paramInt1 >= 1000) {
/*     */         f(paramArrayOfshort, paramInt1, paramInt2);
/*     */       } else {
/*     */         i(paramArrayOfshort, paramInt1, paramInt2);
/*     */       } 
/*     */     } catch (IllegalArgumentException illegalArgumentException) {
/*     */       throw a(null);
/*     */     } 
/*     */   }
/*     */   
/*     */   public static void a(short[] paramArrayOfshort1, short[] paramArrayOfshort2) {
/*     */     e(paramArrayOfshort1, paramArrayOfshort2);
/*     */     b(paramArrayOfshort1, paramArrayOfshort2, 0, paramArrayOfshort1.length);
/*     */   }
/*     */   
/*     */   static {
/*     */     // Byte code:
/*     */     //   0: ldc2_w -708042881121058954
/*     */     //   3: ldc2_w 999670039722916598
/*     */     //   6: invokestatic lookup : ()Ljava/lang/invoke/MethodHandles$Lookup;
/*     */     //   9: invokevirtual lookupClass : ()Ljava/lang/Class;
/*     */     //   12: invokestatic a : (JJLjava/lang/Object;)Lme/konsolas/aac/na;
/*     */     //   15: ldc2_w 148899525561342
/*     */     //   18: invokeinterface a : (J)J
/*     */     //   23: putstatic me/konsolas/aac/j.p : J
/*     */     //   26: getstatic me/konsolas/aac/j.p : J
/*     */     //   29: ldc2_w 103368866586938
/*     */     //   32: lxor
/*     */     //   33: lstore_0
/*     */     //   34: iconst_1
/*     */     //   35: anewarray me/konsolas/aac/aN
/*     */     //   38: iconst_0
/*     */     //   39: newarray short
/*     */     //   41: putstatic me/konsolas/aac/j.e : [S
/*     */     //   44: ldc2_w 5504870565856992854
/*     */     //   47: lload_0
/*     */     //   48: <illegal opcode> w : ([Lme/konsolas/aac/aN;JJ)V
/*     */     //   53: iconst_0
/*     */     //   54: newarray short
/*     */     //   56: putstatic me/konsolas/aac/j.l : [S
/*     */     //   59: new me/konsolas/aac/fm
/*     */     //   62: dup
/*     */     //   63: iconst_m1
/*     */     //   64: iconst_m1
/*     */     //   65: iconst_m1
/*     */     //   66: invokespecial <init> : (III)V
/*     */     //   69: putstatic me/konsolas/aac/j.c : Lme/konsolas/aac/fm;
/*     */     //   72: new me/konsolas/aac/dF
/*     */     //   75: dup
/*     */     //   76: aconst_null
/*     */     //   77: invokespecial <init> : (Lme/konsolas/aac/h9;)V
/*     */     //   80: putstatic me/konsolas/aac/j.m : Lme/konsolas/aac/m9;
/*     */     //   83: return
/*     */     // Line number table:
/*     */     //   Java source line number -> byte code offset
/*     */     //   #634	-> 38
/*     */     //   #828	-> 53
/*     */     //   #370	-> 59
/*     */     //   #741	-> 72
/*     */   }
/*     */   
/*     */   public static void b(aN[] paramArrayOfaN) {
/*     */     n = paramArrayOfaN;
/*     */   }
/*     */   
/*     */   public static aN[] b() {
/*     */     return n;
/*     */   }
/*     */   
/*     */   private static Exception a(Exception paramException) {
/*     */     return paramException;
/*     */   }
/*     */ }


/* Location:              C:\Users\BukkitBypass\Desktop\MatrixAC\AAC\AAC-spigot-5.2.0.jar!\me\konsolas\aac\j.class
 * Java compiler version: 8 (52.0)
 * JD-Core Version:       1.1.3
 */