/*     */ package me.konsolas.aac;
/*     */ 
/*     */ import java.lang.invoke.CallSite;
/*     */ import java.lang.invoke.MethodHandle;
/*     */ import java.lang.invoke.MethodHandles;
/*     */ import java.lang.invoke.MethodType;
/*     */ import java.lang.invoke.MutableCallSite;
/*     */ import java.util.ArrayList;
/*     */ import java.util.HashMap;
/*     */ import java.util.List;
/*     */ import java.util.Map;
/*     */ import javax.annotation.Nullable;
/*     */ import javax.crypto.Cipher;
/*     */ import javax.crypto.SecretKey;
/*     */ import javax.crypto.SecretKeyFactory;
/*     */ import javax.crypto.spec.DESKeySpec;
/*     */ import javax.crypto.spec.IvParameterSpec;
/*     */ 
/*     */ 
/*     */ 
/*     */ 
/*     */ 
/*     */ 
/*     */ 
/*     */ 
/*     */ 
/*     */ 
/*     */ 
/*     */ 
/*     */ 
/*     */ 
/*     */ 
/*     */ 
/*     */ 
/*     */ 
/*     */ 
/*     */ 
/*     */ 
/*     */ 
/*     */ 
/*     */ 
/*     */ 
/*     */ 
/*     */ 
/*     */ 
/*     */ 
/*     */ 
/*     */ 
/*     */ 
/*     */ 
/*     */ 
/*     */ 
/*     */ 
/*     */ 
/*     */ 
/*     */ 
/*     */ 
/*     */ 
/*     */ 
/*     */ 
/*     */ 
/*     */ 
/*     */ 
/*     */ 
/*     */ 
/*     */ 
/*     */ 
/*     */ 
/*     */ 
/*     */ 
/*     */ 
/*     */ 
/*     */ 
/*     */ 
/*     */ 
/*     */ 
/*     */ 
/*     */ 
/*     */ 
/*     */ 
/*     */ 
/*     */ 
/*     */ 
/*     */ 
/*     */ 
/*     */ 
/*     */ 
/*     */ 
/*     */ 
/*     */ 
/*     */ 
/*     */ 
/*     */ 
/*     */ 
/*     */ 
/*     */ 
/*     */ 
/*     */ 
/*     */ 
/*     */ 
/*     */ 
/*     */ 
/*     */ 
/*     */ 
/*     */ 
/*     */ 
/*     */ 
/*     */ 
/*     */ 
/*     */ 
/*     */ 
/*     */ 
/*     */ 
/*     */ 
/*     */ 
/*     */ 
/*     */ 
/*     */ 
/*     */ 
/*     */ 
/*     */ 
/*     */ 
/*     */ 
/*     */ 
/*     */ 
/*     */ 
/*     */ 
/*     */ 
/*     */ 
/*     */ 
/*     */ 
/*     */ 
/*     */ 
/*     */ 
/*     */ public final class j5
/*     */ {
/*     */   @Nullable
/*     */   String c;
/*     */   String f;
/*     */   String a;
/*     */   @Nullable
/*     */   String g;
/*     */   int e;
/*     */   final List i;
/*     */   @Nullable
/*     */   List h;
/*     */   @Nullable
/*     */   String d;
/*     */   static final String b;
/*     */   private static final long j = nc.a(6990140874675363584L, -4725435796143959594L, MethodHandles.lookup().lookupClass()).a(56930498390531L);
/*     */   private static final String[] k;
/*     */   private static final String[] l;
/*     */   private static final Map m = new HashMap<>(13);
/*     */   
/*     */   public j5 b(String paramString, long paramLong) {
/*     */     // Byte code:
/*     */     //   0: getstatic me/konsolas/aac/j5.j : J
/*     */     //   3: lload_2
/*     */     //   4: lxor
/*     */     //   5: lstore_2
/*     */     //   6: lload_2
/*     */     //   7: dup2
/*     */     //   8: ldc2_w 84785872740338
/*     */     //   11: lxor
/*     */     //   12: lstore #4
/*     */     //   14: pop2
/*     */     //   15: ldc2_w -781100811426007574
/*     */     //   18: lload_2
/*     */     //   19: <illegal opcode> w : (JJ)[Lme/konsolas/aac/aN;
/*     */     //   24: astore #6
/*     */     //   26: aload #6
/*     */     //   28: ifnonnull -> 106
/*     */     //   31: aload_1
/*     */     //   32: ifnonnull -> 79
/*     */     //   35: goto -> 48
/*     */     //   38: ldc2_w -792602371005652207
/*     */     //   41: lload_2
/*     */     //   42: <illegal opcode> w : (Ljava/lang/RuntimeException;JJ)Ljava/lang/RuntimeException;
/*     */     //   47: athrow
/*     */     //   48: new java/lang/NullPointerException
/*     */     //   51: dup
/*     */     //   52: sipush #13435
/*     */     //   55: ldc2_w 5907240348809179827
/*     */     //   58: lload_2
/*     */     //   59: lxor
/*     */     //   60: <illegal opcode> c : (IJ)Ljava/lang/String;
/*     */     //   65: invokespecial <init> : (Ljava/lang/String;)V
/*     */     //   68: athrow
/*     */     //   69: ldc2_w -792602371005652207
/*     */     //   72: lload_2
/*     */     //   73: <illegal opcode> w : (Ljava/lang/RuntimeException;JJ)Ljava/lang/RuntimeException;
/*     */     //   78: athrow
/*     */     //   79: aload_0
/*     */     //   80: aload_1
/*     */     //   81: sipush #4000
/*     */     //   84: ldc2_w 2612718143662983533
/*     */     //   87: lload_2
/*     */     //   88: lxor
/*     */     //   89: <illegal opcode> c : (IJ)Ljava/lang/String;
/*     */     //   94: lload #4
/*     */     //   96: iconst_0
/*     */     //   97: iconst_0
/*     */     //   98: iconst_0
/*     */     //   99: iconst_1
/*     */     //   100: invokestatic a : (Ljava/lang/String;Ljava/lang/String;JZZZZ)Ljava/lang/String;
/*     */     //   103: putfield a : Ljava/lang/String;
/*     */     //   106: aload_0
/*     */     //   107: areturn
/*     */     // Line number table:
/*     */     //   Java source line number -> byte code offset
/*     */     //   #1	-> 26
/*     */     //   #121	-> 79
/*     */     //   #277	-> 106
/*     */     // Exception table:
/*     */     //   from	to	target	type
/*     */     //   26	35	38	java/lang/NullPointerException
/*     */     //   31	69	69	java/lang/NullPointerException
/*     */   }
/*     */   
/*     */   private boolean b(String paramString, long paramLong) {
/*     */     // Byte code:
/*     */     //   0: getstatic me/konsolas/aac/j5.j : J
/*     */     //   3: lload_2
/*     */     //   4: lxor
/*     */     //   5: lstore_2
/*     */     //   6: ldc2_w -6120972475910149169
/*     */     //   9: lload_2
/*     */     //   10: <illegal opcode> w : (JJ)[Lme/konsolas/aac/aN;
/*     */     //   15: astore #4
/*     */     //   17: aload_1
/*     */     //   18: sipush #6357
/*     */     //   21: ldc2_w 5291325320969895956
/*     */     //   24: lload_2
/*     */     //   25: lxor
/*     */     //   26: <illegal opcode> c : (IJ)Ljava/lang/String;
/*     */     //   31: invokevirtual equals : (Ljava/lang/Object;)Z
/*     */     //   34: aload #4
/*     */     //   36: ifnonnull -> 209
/*     */     //   39: ifne -> 208
/*     */     //   42: goto -> 55
/*     */     //   45: ldc2_w -6114468471325377228
/*     */     //   48: lload_2
/*     */     //   49: <illegal opcode> w : (Ljava/lang/RuntimeException;JJ)Ljava/lang/RuntimeException;
/*     */     //   54: athrow
/*     */     //   55: aload_1
/*     */     //   56: sipush #3637
/*     */     //   59: ldc2_w 2293076645904176858
/*     */     //   62: lload_2
/*     */     //   63: lxor
/*     */     //   64: <illegal opcode> c : (IJ)Ljava/lang/String;
/*     */     //   69: invokevirtual equalsIgnoreCase : (Ljava/lang/String;)Z
/*     */     //   72: aload #4
/*     */     //   74: ifnonnull -> 209
/*     */     //   77: goto -> 90
/*     */     //   80: ldc2_w -6114468471325377228
/*     */     //   83: lload_2
/*     */     //   84: <illegal opcode> w : (Ljava/lang/RuntimeException;JJ)Ljava/lang/RuntimeException;
/*     */     //   89: athrow
/*     */     //   90: ifne -> 208
/*     */     //   93: goto -> 106
/*     */     //   96: ldc2_w -6114468471325377228
/*     */     //   99: lload_2
/*     */     //   100: <illegal opcode> w : (Ljava/lang/RuntimeException;JJ)Ljava/lang/RuntimeException;
/*     */     //   105: athrow
/*     */     //   106: aload_1
/*     */     //   107: sipush #5448
/*     */     //   110: ldc2_w 5376652265889648046
/*     */     //   113: lload_2
/*     */     //   114: lxor
/*     */     //   115: <illegal opcode> c : (IJ)Ljava/lang/String;
/*     */     //   120: invokevirtual equalsIgnoreCase : (Ljava/lang/String;)Z
/*     */     //   123: aload #4
/*     */     //   125: ifnonnull -> 209
/*     */     //   128: goto -> 141
/*     */     //   131: ldc2_w -6114468471325377228
/*     */     //   134: lload_2
/*     */     //   135: <illegal opcode> w : (Ljava/lang/RuntimeException;JJ)Ljava/lang/RuntimeException;
/*     */     //   140: athrow
/*     */     //   141: ifne -> 208
/*     */     //   144: goto -> 157
/*     */     //   147: ldc2_w -6114468471325377228
/*     */     //   150: lload_2
/*     */     //   151: <illegal opcode> w : (Ljava/lang/RuntimeException;JJ)Ljava/lang/RuntimeException;
/*     */     //   156: athrow
/*     */     //   157: aload_1
/*     */     //   158: sipush #27894
/*     */     //   161: ldc2_w 2264593739064914991
/*     */     //   164: lload_2
/*     */     //   165: lxor
/*     */     //   166: <illegal opcode> c : (IJ)Ljava/lang/String;
/*     */     //   171: invokevirtual equalsIgnoreCase : (Ljava/lang/String;)Z
/*     */     //   174: aload #4
/*     */     //   176: ifnonnull -> 209
/*     */     //   179: goto -> 192
/*     */     //   182: ldc2_w -6114468471325377228
/*     */     //   185: lload_2
/*     */     //   186: <illegal opcode> w : (Ljava/lang/RuntimeException;JJ)Ljava/lang/RuntimeException;
/*     */     //   191: athrow
/*     */     //   192: ifeq -> 212
/*     */     //   195: goto -> 208
/*     */     //   198: ldc2_w -6114468471325377228
/*     */     //   201: lload_2
/*     */     //   202: <illegal opcode> w : (Ljava/lang/RuntimeException;JJ)Ljava/lang/RuntimeException;
/*     */     //   207: athrow
/*     */     //   208: iconst_1
/*     */     //   209: goto -> 213
/*     */     //   212: iconst_0
/*     */     //   213: ireturn
/*     */     // Line number table:
/*     */     //   Java source line number -> byte code offset
/*     */     //   #7	-> 17
/*     */     //   #150	-> 69
/*     */     //   #78	-> 120
/*     */     //   #308	-> 171
/*     */     //   #100	-> 213
/*     */     // Exception table:
/*     */     //   from	to	target	type
/*     */     //   17	42	45	java/lang/NullPointerException
/*     */     //   39	77	80	java/lang/NullPointerException
/*     */     //   55	93	96	java/lang/NullPointerException
/*     */     //   90	128	131	java/lang/NullPointerException
/*     */     //   106	144	147	java/lang/NullPointerException
/*     */     //   141	179	182	java/lang/NullPointerException
/*     */     //   157	195	198	java/lang/NullPointerException
/*     */   }
/*     */   
/*     */   public j5 m(long paramLong, String paramString) {
/*     */     // Byte code:
/*     */     //   0: getstatic me/konsolas/aac/j5.j : J
/*     */     //   3: lload_1
/*     */     //   4: lxor
/*     */     //   5: lstore_1
/*     */     //   6: lload_1
/*     */     //   7: dup2
/*     */     //   8: ldc2_w 52772595201149
/*     */     //   11: lxor
/*     */     //   12: lstore #4
/*     */     //   14: pop2
/*     */     //   15: ldc2_w 2208903540006919781
/*     */     //   18: lload_1
/*     */     //   19: <illegal opcode> w : (JJ)[Lme/konsolas/aac/aN;
/*     */     //   24: astore #6
/*     */     //   26: aload #6
/*     */     //   28: ifnonnull -> 106
/*     */     //   31: aload_3
/*     */     //   32: ifnonnull -> 79
/*     */     //   35: goto -> 48
/*     */     //   38: ldc2_w 2202118055977978014
/*     */     //   41: lload_1
/*     */     //   42: <illegal opcode> w : (Ljava/lang/RuntimeException;JJ)Ljava/lang/RuntimeException;
/*     */     //   47: athrow
/*     */     //   48: new java/lang/NullPointerException
/*     */     //   51: dup
/*     */     //   52: sipush #13482
/*     */     //   55: ldc2_w 8007326097147058646
/*     */     //   58: lload_1
/*     */     //   59: lxor
/*     */     //   60: <illegal opcode> c : (IJ)Ljava/lang/String;
/*     */     //   65: invokespecial <init> : (Ljava/lang/String;)V
/*     */     //   68: athrow
/*     */     //   69: ldc2_w 2202118055977978014
/*     */     //   72: lload_1
/*     */     //   73: <illegal opcode> w : (Ljava/lang/RuntimeException;JJ)Ljava/lang/RuntimeException;
/*     */     //   78: athrow
/*     */     //   79: aload_0
/*     */     //   80: aload_3
/*     */     //   81: sipush #4000
/*     */     //   84: ldc2_w 2612755929377661666
/*     */     //   87: lload_1
/*     */     //   88: lxor
/*     */     //   89: <illegal opcode> c : (IJ)Ljava/lang/String;
/*     */     //   94: lload #4
/*     */     //   96: iconst_1
/*     */     //   97: iconst_0
/*     */     //   98: iconst_0
/*     */     //   99: iconst_1
/*     */     //   100: invokestatic a : (Ljava/lang/String;Ljava/lang/String;JZZZZ)Ljava/lang/String;
/*     */     //   103: putfield f : Ljava/lang/String;
/*     */     //   106: aload_0
/*     */     //   107: areturn
/*     */     // Line number table:
/*     */     //   Java source line number -> byte code offset
/*     */     //   #11	-> 26
/*     */     //   #204	-> 79
/*     */     //   #179	-> 106
/*     */     // Exception table:
/*     */     //   from	to	target	type
/*     */     //   26	35	38	java/lang/NullPointerException
/*     */     //   31	69	69	java/lang/NullPointerException
/*     */   }
/*     */   
/*     */   private boolean a(long paramLong, String paramString) {
/*     */     // Byte code:
/*     */     //   0: getstatic me/konsolas/aac/j5.j : J
/*     */     //   3: lload_1
/*     */     //   4: lxor
/*     */     //   5: lstore_1
/*     */     //   6: ldc2_w -8010785776936316911
/*     */     //   9: lload_1
/*     */     //   10: <illegal opcode> w : (JJ)[Lme/konsolas/aac/aN;
/*     */     //   15: astore #4
/*     */     //   17: aload_3
/*     */     //   18: ldc_w '൏卫'
/*     */     //   21: invokevirtual toCharArray : ()[C
/*     */     //   24: dup
/*     */     //   25: dup
/*     */     //   26: iconst_0
/*     */     //   27: dup_x1
/*     */     //   28: caload
/*     */     //   29: sipush #10780
/*     */     //   32: ixor
/*     */     //   33: i2c
/*     */     //   34: castore
/*     */     //   35: sipush #22779
/*     */     //   38: iconst_1
/*     */     //   39: iconst_1
/*     */     //   40: invokestatic X : (Ljava/lang/Object;SZZ)Ljava/lang/String;
/*     */     //   43: invokevirtual equals : (Ljava/lang/Object;)Z
/*     */     //   46: aload #4
/*     */     //   48: ifnonnull -> 119
/*     */     //   51: ifne -> 118
/*     */     //   54: goto -> 67
/*     */     //   57: ldc2_w -7999769097325246742
/*     */     //   60: lload_1
/*     */     //   61: <illegal opcode> w : (Ljava/lang/RuntimeException;JJ)Ljava/lang/RuntimeException;
/*     */     //   66: athrow
/*     */     //   67: aload_3
/*     */     //   68: sipush #20488
/*     */     //   71: ldc2_w 3027582561113584419
/*     */     //   74: lload_1
/*     */     //   75: lxor
/*     */     //   76: <illegal opcode> c : (IJ)Ljava/lang/String;
/*     */     //   81: invokevirtual equalsIgnoreCase : (Ljava/lang/String;)Z
/*     */     //   84: aload #4
/*     */     //   86: ifnonnull -> 119
/*     */     //   89: goto -> 102
/*     */     //   92: ldc2_w -7999769097325246742
/*     */     //   95: lload_1
/*     */     //   96: <illegal opcode> w : (Ljava/lang/RuntimeException;JJ)Ljava/lang/RuntimeException;
/*     */     //   101: athrow
/*     */     //   102: ifeq -> 122
/*     */     //   105: goto -> 118
/*     */     //   108: ldc2_w -7999769097325246742
/*     */     //   111: lload_1
/*     */     //   112: <illegal opcode> w : (Ljava/lang/RuntimeException;JJ)Ljava/lang/RuntimeException;
/*     */     //   117: athrow
/*     */     //   118: iconst_1
/*     */     //   119: goto -> 123
/*     */     //   122: iconst_0
/*     */     //   123: ireturn
/*     */     // Line number table:
/*     */     //   Java source line number -> byte code offset
/*     */     //   #13	-> 17
/*     */     // Exception table:
/*     */     //   from	to	target	type
/*     */     //   17	54	57	java/lang/NullPointerException
/*     */     //   51	89	92	java/lang/NullPointerException
/*     */     //   67	105	108	java/lang/NullPointerException
/*     */   }
/*     */   
/*     */   public j5 l(String paramString, long paramLong) {
/*     */     // Byte code:
/*     */     //   0: getstatic me/konsolas/aac/j5.j : J
/*     */     //   3: lload_2
/*     */     //   4: lxor
/*     */     //   5: lstore_2
/*     */     //   6: lload_2
/*     */     //   7: dup2
/*     */     //   8: ldc2_w 105385657803477
/*     */     //   11: lxor
/*     */     //   12: lstore #4
/*     */     //   14: pop2
/*     */     //   15: ldc2_w -860310418602986291
/*     */     //   18: lload_2
/*     */     //   19: <illegal opcode> w : (JJ)[Lme/konsolas/aac/aN;
/*     */     //   24: astore #6
/*     */     //   26: aload_1
/*     */     //   27: aload #6
/*     */     //   29: ifnonnull -> 90
/*     */     //   32: ifnonnull -> 79
/*     */     //   35: goto -> 48
/*     */     //   38: ldc2_w -853585374295596490
/*     */     //   41: lload_2
/*     */     //   42: <illegal opcode> w : (Ljava/lang/RuntimeException;JJ)Ljava/lang/RuntimeException;
/*     */     //   47: athrow
/*     */     //   48: new java/lang/NullPointerException
/*     */     //   51: dup
/*     */     //   52: sipush #28785
/*     */     //   55: ldc2_w 7177922798263138176
/*     */     //   58: lload_2
/*     */     //   59: lxor
/*     */     //   60: <illegal opcode> c : (IJ)Ljava/lang/String;
/*     */     //   65: invokespecial <init> : (Ljava/lang/String;)V
/*     */     //   68: athrow
/*     */     //   69: ldc2_w -853585374295596490
/*     */     //   72: lload_2
/*     */     //   73: <illegal opcode> w : (Ljava/lang/RuntimeException;JJ)Ljava/lang/RuntimeException;
/*     */     //   78: athrow
/*     */     //   79: lload #4
/*     */     //   81: aload_1
/*     */     //   82: iconst_0
/*     */     //   83: aload_1
/*     */     //   84: invokevirtual length : ()I
/*     */     //   87: invokestatic a : (JLjava/lang/String;II)Ljava/lang/String;
/*     */     //   90: astore #7
/*     */     //   92: aload #6
/*     */     //   94: ifnonnull -> 169
/*     */     //   97: aload #7
/*     */     //   99: ifnonnull -> 163
/*     */     //   102: goto -> 115
/*     */     //   105: ldc2_w -853585374295596490
/*     */     //   108: lload_2
/*     */     //   109: <illegal opcode> w : (Ljava/lang/RuntimeException;JJ)Ljava/lang/RuntimeException;
/*     */     //   114: athrow
/*     */     //   115: new java/lang/IllegalArgumentException
/*     */     //   118: dup
/*     */     //   119: new java/lang/StringBuilder
/*     */     //   122: dup
/*     */     //   123: invokespecial <init> : ()V
/*     */     //   126: sipush #21367
/*     */     //   129: ldc2_w 372803466071823498
/*     */     //   132: lload_2
/*     */     //   133: lxor
/*     */     //   134: <illegal opcode> c : (IJ)Ljava/lang/String;
/*     */     //   139: invokevirtual append : (Ljava/lang/String;)Ljava/lang/StringBuilder;
/*     */     //   142: aload_1
/*     */     //   143: invokevirtual append : (Ljava/lang/String;)Ljava/lang/StringBuilder;
/*     */     //   146: invokevirtual toString : ()Ljava/lang/String;
/*     */     //   149: invokespecial <init> : (Ljava/lang/String;)V
/*     */     //   152: athrow
/*     */     //   153: ldc2_w -853585374295596490
/*     */     //   156: lload_2
/*     */     //   157: <illegal opcode> w : (Ljava/lang/RuntimeException;JJ)Ljava/lang/RuntimeException;
/*     */     //   162: athrow
/*     */     //   163: aload_0
/*     */     //   164: aload #7
/*     */     //   166: putfield g : Ljava/lang/String;
/*     */     //   169: aload_0
/*     */     //   170: areturn
/*     */     // Line number table:
/*     */     //   Java source line number -> byte code offset
/*     */     //   #22	-> 26
/*     */     //   #324	-> 79
/*     */     //   #197	-> 92
/*     */     //   #278	-> 163
/*     */     //   #271	-> 169
/*     */     // Exception table:
/*     */     //   from	to	target	type
/*     */     //   26	35	38	java/lang/NullPointerException
/*     */     //   32	69	69	java/lang/NullPointerException
/*     */     //   92	102	105	java/lang/NullPointerException
/*     */     //   97	153	153	java/lang/NullPointerException
/*     */   }
/*     */   
/*     */   public j5 d(String paramString1, @Nullable String paramString2, long paramLong) {
/*     */     // Byte code:
/*     */     //   0: getstatic me/konsolas/aac/j5.j : J
/*     */     //   3: lload_3
/*     */     //   4: lxor
/*     */     //   5: lstore_3
/*     */     //   6: lload_3
/*     */     //   7: dup2
/*     */     //   8: ldc2_w 67414318444503
/*     */     //   11: lxor
/*     */     //   12: lstore #5
/*     */     //   14: pop2
/*     */     //   15: ldc2_w -8859274534013008433
/*     */     //   18: lload_3
/*     */     //   19: <illegal opcode> w : (JJ)[Lme/konsolas/aac/aN;
/*     */     //   24: astore #7
/*     */     //   26: aload_1
/*     */     //   27: ifnonnull -> 61
/*     */     //   30: new java/lang/NullPointerException
/*     */     //   33: dup
/*     */     //   34: sipush #10843
/*     */     //   37: ldc2_w 2059128746900085943
/*     */     //   40: lload_3
/*     */     //   41: lxor
/*     */     //   42: <illegal opcode> c : (IJ)Ljava/lang/String;
/*     */     //   47: invokespecial <init> : (Ljava/lang/String;)V
/*     */     //   50: athrow
/*     */     //   51: ldc2_w -8852550627474009292
/*     */     //   54: lload_3
/*     */     //   55: <illegal opcode> w : (Ljava/lang/RuntimeException;JJ)Ljava/lang/RuntimeException;
/*     */     //   60: athrow
/*     */     //   61: aload_0
/*     */     //   62: getfield h : Ljava/util/List;
/*     */     //   65: lload_3
/*     */     //   66: lconst_0
/*     */     //   67: lcmp
/*     */     //   68: iflt -> 153
/*     */     //   71: aload #7
/*     */     //   73: ifnonnull -> 153
/*     */     //   76: ifnonnull -> 116
/*     */     //   79: goto -> 92
/*     */     //   82: ldc2_w -8852550627474009292
/*     */     //   85: lload_3
/*     */     //   86: <illegal opcode> w : (Ljava/lang/RuntimeException;JJ)Ljava/lang/RuntimeException;
/*     */     //   91: athrow
/*     */     //   92: aload_0
/*     */     //   93: new java/util/ArrayList
/*     */     //   96: dup
/*     */     //   97: invokespecial <init> : ()V
/*     */     //   100: putfield h : Ljava/util/List;
/*     */     //   103: goto -> 116
/*     */     //   106: ldc2_w -8852550627474009292
/*     */     //   109: lload_3
/*     */     //   110: <illegal opcode> w : (Ljava/lang/RuntimeException;JJ)Ljava/lang/RuntimeException;
/*     */     //   115: athrow
/*     */     //   116: aload_0
/*     */     //   117: getfield h : Ljava/util/List;
/*     */     //   120: aload_1
/*     */     //   121: sipush #12245
/*     */     //   124: ldc2_w 2444677949127743766
/*     */     //   127: lload_3
/*     */     //   128: lxor
/*     */     //   129: <illegal opcode> c : (IJ)Ljava/lang/String;
/*     */     //   134: lload #5
/*     */     //   136: iconst_1
/*     */     //   137: iconst_0
/*     */     //   138: iconst_1
/*     */     //   139: iconst_1
/*     */     //   140: invokestatic a : (Ljava/lang/String;Ljava/lang/String;JZZZZ)Ljava/lang/String;
/*     */     //   143: invokeinterface add : (Ljava/lang/Object;)Z
/*     */     //   148: pop
/*     */     //   149: aload_0
/*     */     //   150: getfield h : Ljava/util/List;
/*     */     //   153: aload_2
/*     */     //   154: aload #7
/*     */     //   156: ifnonnull -> 211
/*     */     //   159: ifnull -> 214
/*     */     //   162: goto -> 175
/*     */     //   165: ldc2_w -8852550627474009292
/*     */     //   168: lload_3
/*     */     //   169: <illegal opcode> w : (Ljava/lang/RuntimeException;JJ)Ljava/lang/RuntimeException;
/*     */     //   174: athrow
/*     */     //   175: aload_2
/*     */     //   176: sipush #3836
/*     */     //   179: ldc2_w 1847386578541738043
/*     */     //   182: lload_3
/*     */     //   183: lxor
/*     */     //   184: <illegal opcode> c : (IJ)Ljava/lang/String;
/*     */     //   189: lload #5
/*     */     //   191: iconst_1
/*     */     //   192: iconst_0
/*     */     //   193: iconst_1
/*     */     //   194: iconst_1
/*     */     //   195: invokestatic a : (Ljava/lang/String;Ljava/lang/String;JZZZZ)Ljava/lang/String;
/*     */     //   198: goto -> 211
/*     */     //   201: ldc2_w -8852550627474009292
/*     */     //   204: lload_3
/*     */     //   205: <illegal opcode> w : (Ljava/lang/RuntimeException;JJ)Ljava/lang/RuntimeException;
/*     */     //   210: athrow
/*     */     //   211: goto -> 215
/*     */     //   214: aconst_null
/*     */     //   215: invokeinterface add : (Ljava/lang/Object;)Z
/*     */     //   220: pop
/*     */     //   221: aload_0
/*     */     //   222: areturn
/*     */     // Line number table:
/*     */     //   Java source line number -> byte code offset
/*     */     //   #33	-> 26
/*     */     //   #120	-> 61
/*     */     //   #136	-> 116
/*     */     //   #46	-> 140
/*     */     //   #326	-> 143
/*     */     //   #174	-> 149
/*     */     //   #168	-> 175
/*     */     //   #309	-> 214
/*     */     //   #209	-> 215
/*     */     //   #238	-> 221
/*     */     // Exception table:
/*     */     //   from	to	target	type
/*     */     //   26	51	51	java/lang/NullPointerException
/*     */     //   61	79	82	java/lang/NullPointerException
/*     */     //   76	103	106	java/lang/NullPointerException
/*     */     //   153	162	165	java/lang/NullPointerException
/*     */     //   159	198	201	java/lang/NullPointerException
/*     */   }
/*     */   
/*     */   public j5 b(int paramInt, long paramLong) {
/*     */     // Byte code:
/*     */     //   0: getstatic me/konsolas/aac/j5.j : J
/*     */     //   3: lload_2
/*     */     //   4: lxor
/*     */     //   5: lstore_2
/*     */     //   6: ldc2_w 7338024123619370263
/*     */     //   9: lload_2
/*     */     //   10: <illegal opcode> w : (JJ)[Lme/konsolas/aac/aN;
/*     */     //   15: astore #4
/*     */     //   17: iload_1
/*     */     //   18: aload #4
/*     */     //   20: ifnonnull -> 40
/*     */     //   23: ifle -> 45
/*     */     //   26: goto -> 39
/*     */     //   29: ldc2_w 7349033101553169388
/*     */     //   32: lload_2
/*     */     //   33: <illegal opcode> w : (Ljava/lang/RuntimeException;JJ)Ljava/lang/RuntimeException;
/*     */     //   38: athrow
/*     */     //   39: iload_1
/*     */     //   40: ldc 65535
/*     */     //   42: if_icmple -> 93
/*     */     //   45: new java/lang/IllegalArgumentException
/*     */     //   48: dup
/*     */     //   49: new java/lang/StringBuilder
/*     */     //   52: dup
/*     */     //   53: invokespecial <init> : ()V
/*     */     //   56: sipush #1067
/*     */     //   59: ldc2_w 628191513352213002
/*     */     //   62: lload_2
/*     */     //   63: lxor
/*     */     //   64: <illegal opcode> c : (IJ)Ljava/lang/String;
/*     */     //   69: invokevirtual append : (Ljava/lang/String;)Ljava/lang/StringBuilder;
/*     */     //   72: iload_1
/*     */     //   73: invokevirtual append : (I)Ljava/lang/StringBuilder;
/*     */     //   76: invokevirtual toString : ()Ljava/lang/String;
/*     */     //   79: invokespecial <init> : (Ljava/lang/String;)V
/*     */     //   82: athrow
/*     */     //   83: ldc2_w 7349033101553169388
/*     */     //   86: lload_2
/*     */     //   87: <illegal opcode> w : (Ljava/lang/RuntimeException;JJ)Ljava/lang/RuntimeException;
/*     */     //   92: athrow
/*     */     //   93: aload_0
/*     */     //   94: iload_1
/*     */     //   95: putfield e : I
/*     */     //   98: aload_0
/*     */     //   99: areturn
/*     */     // Line number table:
/*     */     //   Java source line number -> byte code offset
/*     */     //   #43	-> 17
/*     */     //   #75	-> 93
/*     */     //   #192	-> 98
/*     */     // Exception table:
/*     */     //   from	to	target	type
/*     */     //   17	26	29	java/lang/NullPointerException
/*     */     //   40	83	83	java/lang/NullPointerException
/*     */   }
/*     */   
/*     */   public j5 d(long paramLong, String paramString) {
/*     */     // Byte code:
/*     */     //   0: getstatic me/konsolas/aac/j5.j : J
/*     */     //   3: lload_1
/*     */     //   4: lxor
/*     */     //   5: lstore_1
/*     */     //   6: ldc2_w -8020133472870166416
/*     */     //   9: lload_1
/*     */     //   10: <illegal opcode> w : (JJ)[Lme/konsolas/aac/aN;
/*     */     //   15: astore #4
/*     */     //   17: aload_3
/*     */     //   18: aload #4
/*     */     //   20: ifnonnull -> 71
/*     */     //   23: ifnonnull -> 70
/*     */     //   26: goto -> 39
/*     */     //   29: ldc2_w -8027059689652550005
/*     */     //   32: lload_1
/*     */     //   33: <illegal opcode> w : (Ljava/lang/RuntimeException;JJ)Ljava/lang/RuntimeException;
/*     */     //   38: athrow
/*     */     //   39: new java/lang/NullPointerException
/*     */     //   42: dup
/*     */     //   43: sipush #21412
/*     */     //   46: ldc2_w 3045549318995685576
/*     */     //   49: lload_1
/*     */     //   50: lxor
/*     */     //   51: <illegal opcode> c : (IJ)Ljava/lang/String;
/*     */     //   56: invokespecial <init> : (Ljava/lang/String;)V
/*     */     //   59: athrow
/*     */     //   60: ldc2_w -8027059689652550005
/*     */     //   63: lload_1
/*     */     //   64: <illegal opcode> w : (Ljava/lang/RuntimeException;JJ)Ljava/lang/RuntimeException;
/*     */     //   69: athrow
/*     */     //   70: aload_3
/*     */     //   71: sipush #15102
/*     */     //   74: ldc2_w 931823466324122003
/*     */     //   77: lload_1
/*     */     //   78: lxor
/*     */     //   79: <illegal opcode> c : (IJ)Ljava/lang/String;
/*     */     //   84: invokevirtual equalsIgnoreCase : (Ljava/lang/String;)Z
/*     */     //   87: lload_1
/*     */     //   88: lconst_0
/*     */     //   89: lcmp
/*     */     //   90: iflt -> 185
/*     */     //   93: aload #4
/*     */     //   95: ifnonnull -> 185
/*     */     //   98: ifeq -> 155
/*     */     //   101: goto -> 114
/*     */     //   104: ldc2_w -8027059689652550005
/*     */     //   107: lload_1
/*     */     //   108: <illegal opcode> w : (Ljava/lang/RuntimeException;JJ)Ljava/lang/RuntimeException;
/*     */     //   113: athrow
/*     */     //   114: aload_0
/*     */     //   115: lload_1
/*     */     //   116: lconst_0
/*     */     //   117: lcmp
/*     */     //   118: ifle -> 278
/*     */     //   121: sipush #12480
/*     */     //   124: ldc2_w 7891789348867527556
/*     */     //   127: lload_1
/*     */     //   128: lxor
/*     */     //   129: <illegal opcode> c : (IJ)Ljava/lang/String;
/*     */     //   134: putfield c : Ljava/lang/String;
/*     */     //   137: aload #4
/*     */     //   139: ifnull -> 277
/*     */     //   142: goto -> 155
/*     */     //   145: ldc2_w -8027059689652550005
/*     */     //   148: lload_1
/*     */     //   149: <illegal opcode> w : (Ljava/lang/RuntimeException;JJ)Ljava/lang/RuntimeException;
/*     */     //   154: athrow
/*     */     //   155: aload_3
/*     */     //   156: sipush #14011
/*     */     //   159: ldc2_w 5598885220074902992
/*     */     //   162: lload_1
/*     */     //   163: lxor
/*     */     //   164: <illegal opcode> c : (IJ)Ljava/lang/String;
/*     */     //   169: invokevirtual equalsIgnoreCase : (Ljava/lang/String;)Z
/*     */     //   172: goto -> 185
/*     */     //   175: ldc2_w -8027059689652550005
/*     */     //   178: lload_1
/*     */     //   179: <illegal opcode> w : (Ljava/lang/RuntimeException;JJ)Ljava/lang/RuntimeException;
/*     */     //   184: athrow
/*     */     //   185: ifeq -> 229
/*     */     //   188: aload_0
/*     */     //   189: lload_1
/*     */     //   190: lconst_0
/*     */     //   191: lcmp
/*     */     //   192: ifle -> 278
/*     */     //   195: sipush #24884
/*     */     //   198: ldc2_w 4532635020220334707
/*     */     //   201: lload_1
/*     */     //   202: lxor
/*     */     //   203: <illegal opcode> c : (IJ)Ljava/lang/String;
/*     */     //   208: putfield c : Ljava/lang/String;
/*     */     //   211: aload #4
/*     */     //   213: ifnull -> 277
/*     */     //   216: goto -> 229
/*     */     //   219: ldc2_w -8027059689652550005
/*     */     //   222: lload_1
/*     */     //   223: <illegal opcode> w : (Ljava/lang/RuntimeException;JJ)Ljava/lang/RuntimeException;
/*     */     //   228: athrow
/*     */     //   229: new java/lang/IllegalArgumentException
/*     */     //   232: dup
/*     */     //   233: new java/lang/StringBuilder
/*     */     //   236: dup
/*     */     //   237: invokespecial <init> : ()V
/*     */     //   240: sipush #23310
/*     */     //   243: ldc2_w 5656135801871972459
/*     */     //   246: lload_1
/*     */     //   247: lxor
/*     */     //   248: <illegal opcode> c : (IJ)Ljava/lang/String;
/*     */     //   253: invokevirtual append : (Ljava/lang/String;)Ljava/lang/StringBuilder;
/*     */     //   256: aload_3
/*     */     //   257: invokevirtual append : (Ljava/lang/String;)Ljava/lang/StringBuilder;
/*     */     //   260: invokevirtual toString : ()Ljava/lang/String;
/*     */     //   263: invokespecial <init> : (Ljava/lang/String;)V
/*     */     //   266: athrow
/*     */     //   267: ldc2_w -8027059689652550005
/*     */     //   270: lload_1
/*     */     //   271: <illegal opcode> w : (Ljava/lang/RuntimeException;JJ)Ljava/lang/RuntimeException;
/*     */     //   276: athrow
/*     */     //   277: aload_0
/*     */     //   278: areturn
/*     */     // Line number table:
/*     */     //   Java source line number -> byte code offset
/*     */     //   #47	-> 17
/*     */     //   #56	-> 39
/*     */     //   #287	-> 70
/*     */     //   #2	-> 114
/*     */     //   #258	-> 155
/*     */     //   #23	-> 188
/*     */     //   #314	-> 229
/*     */     //   #255	-> 277
/*     */     // Exception table:
/*     */     //   from	to	target	type
/*     */     //   17	26	29	java/lang/NullPointerException
/*     */     //   23	60	60	java/lang/NullPointerException
/*     */     //   71	101	104	java/lang/NullPointerException
/*     */     //   98	142	145	java/lang/NullPointerException
/*     */     //   114	172	175	java/lang/NullPointerException
/*     */     //   185	216	219	java/lang/NullPointerException
/*     */     //   188	267	267	java/lang/NullPointerException
/*     */   }
/*     */   
/*     */   public j5 p(String paramString, int paramInt1, int paramInt2) {
/*     */     // Byte code:
/*     */     //   0: iload_2
/*     */     //   1: i2l
/*     */     //   2: bipush #32
/*     */     //   4: lshl
/*     */     //   5: iload_3
/*     */     //   6: i2l
/*     */     //   7: bipush #32
/*     */     //   9: lshl
/*     */     //   10: bipush #32
/*     */     //   12: lushr
/*     */     //   13: lor
/*     */     //   14: getstatic me/konsolas/aac/j5.j : J
/*     */     //   17: lxor
/*     */     //   18: lstore #4
/*     */     //   20: lload #4
/*     */     //   22: dup2
/*     */     //   23: ldc2_w 29369362683625
/*     */     //   26: lxor
/*     */     //   27: lstore #6
/*     */     //   29: pop2
/*     */     //   30: ldc2_w 8949689685472673009
/*     */     //   33: lload #4
/*     */     //   35: <illegal opcode> w : (JJ)[Lme/konsolas/aac/aN;
/*     */     //   40: astore #8
/*     */     //   42: aload #8
/*     */     //   44: ifnonnull -> 126
/*     */     //   47: aload_1
/*     */     //   48: ifnonnull -> 98
/*     */     //   51: goto -> 65
/*     */     //   54: ldc2_w 8942825036779022858
/*     */     //   57: lload #4
/*     */     //   59: <illegal opcode> w : (Ljava/lang/RuntimeException;JJ)Ljava/lang/RuntimeException;
/*     */     //   64: athrow
/*     */     //   65: new java/lang/NullPointerException
/*     */     //   68: dup
/*     */     //   69: sipush #30285
/*     */     //   72: ldc2_w 9031676991765936550
/*     */     //   75: lload #4
/*     */     //   77: lxor
/*     */     //   78: <illegal opcode> c : (IJ)Ljava/lang/String;
/*     */     //   83: invokespecial <init> : (Ljava/lang/String;)V
/*     */     //   86: athrow
/*     */     //   87: ldc2_w 8942825036779022858
/*     */     //   90: lload #4
/*     */     //   92: <illegal opcode> w : (Ljava/lang/RuntimeException;JJ)Ljava/lang/RuntimeException;
/*     */     //   97: athrow
/*     */     //   98: aload_0
/*     */     //   99: aload_1
/*     */     //   100: sipush #4000
/*     */     //   103: ldc2_w 2612768268745539702
/*     */     //   106: lload #4
/*     */     //   108: lxor
/*     */     //   109: <illegal opcode> c : (IJ)Ljava/lang/String;
/*     */     //   114: lload #6
/*     */     //   116: iconst_0
/*     */     //   117: iconst_0
/*     */     //   118: iconst_0
/*     */     //   119: iconst_1
/*     */     //   120: invokestatic a : (Ljava/lang/String;Ljava/lang/String;JZZZZ)Ljava/lang/String;
/*     */     //   123: putfield f : Ljava/lang/String;
/*     */     //   126: aload_0
/*     */     //   127: areturn
/*     */     // Line number table:
/*     */     //   Java source line number -> byte code offset
/*     */     //   #50	-> 42
/*     */     //   #127	-> 98
/*     */     //   #115	-> 126
/*     */     // Exception table:
/*     */     //   from	to	target	type
/*     */     //   42	51	54	java/lang/NullPointerException
/*     */     //   47	87	87	java/lang/NullPointerException
/*     */   }
/*     */   
/*     */   private j5 a(String paramString, boolean paramBoolean, long paramLong) {
/*     */     // Byte code:
/*     */     //   0: getstatic me/konsolas/aac/j5.j : J
/*     */     //   3: lload_3
/*     */     //   4: lxor
/*     */     //   5: lstore_3
/*     */     //   6: lload_3
/*     */     //   7: dup2
/*     */     //   8: ldc2_w 6370973606188
/*     */     //   11: lxor
/*     */     //   12: lstore #5
/*     */     //   14: dup2
/*     */     //   15: ldc2_w 8545896829886
/*     */     //   18: lxor
/*     */     //   19: lstore #7
/*     */     //   21: pop2
/*     */     //   22: ldc2_w -6489495642855267022
/*     */     //   25: lload_3
/*     */     //   26: <illegal opcode> w : (JJ)[Lme/konsolas/aac/aN;
/*     */     //   31: iconst_0
/*     */     //   32: istore #10
/*     */     //   34: astore #9
/*     */     //   36: lload #5
/*     */     //   38: aload_1
/*     */     //   39: iload #10
/*     */     //   41: aload_1
/*     */     //   42: invokevirtual length : ()I
/*     */     //   45: sipush #19201
/*     */     //   48: ldc2_w 5896241400817524004
/*     */     //   51: lload_3
/*     */     //   52: lxor
/*     */     //   53: <illegal opcode> c : (IJ)Ljava/lang/String;
/*     */     //   58: invokestatic a : (JLjava/lang/String;IILjava/lang/String;)I
/*     */     //   61: istore #11
/*     */     //   63: iload #11
/*     */     //   65: aload_1
/*     */     //   66: invokevirtual length : ()I
/*     */     //   69: if_icmpge -> 76
/*     */     //   72: iconst_1
/*     */     //   73: goto -> 77
/*     */     //   76: iconst_0
/*     */     //   77: istore #12
/*     */     //   79: aload_0
/*     */     //   80: aload_1
/*     */     //   81: iload #10
/*     */     //   83: iload #11
/*     */     //   85: iload #12
/*     */     //   87: iload_2
/*     */     //   88: lload #7
/*     */     //   90: invokespecial a : (Ljava/lang/String;IIZZJ)V
/*     */     //   93: iload #11
/*     */     //   95: iconst_1
/*     */     //   96: iadd
/*     */     //   97: istore #10
/*     */     //   99: iload #10
/*     */     //   101: aload_1
/*     */     //   102: invokevirtual length : ()I
/*     */     //   105: if_icmple -> 36
/*     */     //   108: aload_0
/*     */     //   109: lload_3
/*     */     //   110: lconst_0
/*     */     //   111: lcmp
/*     */     //   112: iflt -> 80
/*     */     //   115: aload #9
/*     */     //   117: ifnonnull -> 80
/*     */     //   120: areturn
/*     */     // Line number table:
/*     */     //   Java source line number -> byte code offset
/*     */     //   #63	-> 31
/*     */     //   #212	-> 36
/*     */     //   #64	-> 63
/*     */     //   #74	-> 79
/*     */     //   #55	-> 93
/*     */     //   #291	-> 99
/*     */     //   #297	-> 108
/*     */   }
/*     */   
/*     */   public j5 k(String paramString, long paramLong) {
/*     */     // Byte code:
/*     */     //   0: getstatic me/konsolas/aac/j5.j : J
/*     */     //   3: lload_2
/*     */     //   4: lxor
/*     */     //   5: lstore_2
/*     */     //   6: lload_2
/*     */     //   7: dup2
/*     */     //   8: ldc2_w 108340844996964
/*     */     //   11: lxor
/*     */     //   12: lstore #4
/*     */     //   14: pop2
/*     */     //   15: ldc2_w 2245830929368686568
/*     */     //   18: lload_2
/*     */     //   19: <illegal opcode> w : (JJ)[Lme/konsolas/aac/aN;
/*     */     //   24: astore #6
/*     */     //   26: aload #6
/*     */     //   28: ifnonnull -> 93
/*     */     //   31: aload_1
/*     */     //   32: ifnonnull -> 79
/*     */     //   35: goto -> 48
/*     */     //   38: ldc2_w 2234401074304157971
/*     */     //   41: lload_2
/*     */     //   42: <illegal opcode> w : (Ljava/lang/RuntimeException;JJ)Ljava/lang/RuntimeException;
/*     */     //   47: athrow
/*     */     //   48: new java/lang/NullPointerException
/*     */     //   51: dup
/*     */     //   52: sipush #17289
/*     */     //   55: ldc2_w 7929242058027282264
/*     */     //   58: lload_2
/*     */     //   59: lxor
/*     */     //   60: <illegal opcode> c : (IJ)Ljava/lang/String;
/*     */     //   65: invokespecial <init> : (Ljava/lang/String;)V
/*     */     //   68: athrow
/*     */     //   69: ldc2_w 2234401074304157971
/*     */     //   72: lload_2
/*     */     //   73: <illegal opcode> w : (Ljava/lang/RuntimeException;JJ)Ljava/lang/RuntimeException;
/*     */     //   78: athrow
/*     */     //   79: aload_0
/*     */     //   80: aload_1
/*     */     //   81: iconst_0
/*     */     //   82: aload_1
/*     */     //   83: invokevirtual length : ()I
/*     */     //   86: iconst_0
/*     */     //   87: iconst_1
/*     */     //   88: lload #4
/*     */     //   90: invokespecial a : (Ljava/lang/String;IIZZJ)V
/*     */     //   93: aload_0
/*     */     //   94: areturn
/*     */     // Line number table:
/*     */     //   Java source line number -> byte code offset
/*     */     //   #65	-> 26
/*     */     //   #280	-> 48
/*     */     //   #230	-> 79
/*     */     //   #141	-> 93
/*     */     // Exception table:
/*     */     //   from	to	target	type
/*     */     //   26	35	38	java/lang/NullPointerException
/*     */     //   31	69	69	java/lang/NullPointerException
/*     */   }
/*     */   
/*     */   public j5 o(byte paramByte, int paramInt1, String paramString, int paramInt2) {
/*     */     // Byte code:
/*     */     //   0: iload_1
/*     */     //   1: i2l
/*     */     //   2: bipush #56
/*     */     //   4: lshl
/*     */     //   5: iload_2
/*     */     //   6: i2l
/*     */     //   7: bipush #32
/*     */     //   9: lshl
/*     */     //   10: bipush #8
/*     */     //   12: lushr
/*     */     //   13: lor
/*     */     //   14: iload #4
/*     */     //   16: i2l
/*     */     //   17: bipush #40
/*     */     //   19: lshl
/*     */     //   20: bipush #40
/*     */     //   22: lushr
/*     */     //   23: lor
/*     */     //   24: getstatic me/konsolas/aac/j5.j : J
/*     */     //   27: lxor
/*     */     //   28: lstore #5
/*     */     //   30: lload #5
/*     */     //   32: dup2
/*     */     //   33: ldc2_w 85245363445663
/*     */     //   36: lxor
/*     */     //   37: dup2
/*     */     //   38: bipush #48
/*     */     //   40: lushr
/*     */     //   41: l2i
/*     */     //   42: istore #7
/*     */     //   44: dup2
/*     */     //   45: bipush #16
/*     */     //   47: lshl
/*     */     //   48: bipush #48
/*     */     //   50: lushr
/*     */     //   51: l2i
/*     */     //   52: istore #8
/*     */     //   54: dup2
/*     */     //   55: bipush #32
/*     */     //   57: lshl
/*     */     //   58: bipush #32
/*     */     //   60: lushr
/*     */     //   61: l2i
/*     */     //   62: istore #9
/*     */     //   64: pop2
/*     */     //   65: dup2
/*     */     //   66: ldc2_w 75385366919056
/*     */     //   69: lxor
/*     */     //   70: lstore #10
/*     */     //   72: pop2
/*     */     //   73: ldc2_w 6722450925475683720
/*     */     //   76: lload #5
/*     */     //   78: <illegal opcode> w : (JJ)[Lme/konsolas/aac/aN;
/*     */     //   83: astore #12
/*     */     //   85: aload_3
/*     */     //   86: ifnonnull -> 122
/*     */     //   89: new java/lang/NullPointerException
/*     */     //   92: dup
/*     */     //   93: sipush #31608
/*     */     //   96: ldc2_w 8498853092869035489
/*     */     //   99: lload #5
/*     */     //   101: lxor
/*     */     //   102: <illegal opcode> c : (IJ)Ljava/lang/String;
/*     */     //   107: invokespecial <init> : (Ljava/lang/String;)V
/*     */     //   110: athrow
/*     */     //   111: ldc2_w 6728964825562794867
/*     */     //   114: lload #5
/*     */     //   116: <illegal opcode> w : (Ljava/lang/RuntimeException;JJ)Ljava/lang/RuntimeException;
/*     */     //   121: athrow
/*     */     //   122: aload_0
/*     */     //   123: aload #12
/*     */     //   125: ifnonnull -> 198
/*     */     //   128: getfield h : Ljava/util/List;
/*     */     //   131: ifnonnull -> 161
/*     */     //   134: goto -> 148
/*     */     //   137: ldc2_w 6728964825562794867
/*     */     //   140: lload #5
/*     */     //   142: <illegal opcode> w : (Ljava/lang/RuntimeException;JJ)Ljava/lang/RuntimeException;
/*     */     //   147: athrow
/*     */     //   148: aload_0
/*     */     //   149: areturn
/*     */     //   150: ldc2_w 6728964825562794867
/*     */     //   153: lload #5
/*     */     //   155: <illegal opcode> w : (Ljava/lang/RuntimeException;JJ)Ljava/lang/RuntimeException;
/*     */     //   160: athrow
/*     */     //   161: aload_0
/*     */     //   162: aload_3
/*     */     //   163: sipush #3836
/*     */     //   166: ldc2_w 1847396749149806716
/*     */     //   169: lload #5
/*     */     //   171: lxor
/*     */     //   172: <illegal opcode> c : (IJ)Ljava/lang/String;
/*     */     //   177: lload #10
/*     */     //   179: iconst_1
/*     */     //   180: iconst_0
/*     */     //   181: iconst_1
/*     */     //   182: iconst_1
/*     */     //   183: invokestatic a : (Ljava/lang/String;Ljava/lang/String;JZZZZ)Ljava/lang/String;
/*     */     //   186: iload #7
/*     */     //   188: i2c
/*     */     //   189: iload #8
/*     */     //   191: i2c
/*     */     //   192: iload #9
/*     */     //   194: invokespecial a : (Ljava/lang/String;CCI)V
/*     */     //   197: aload_0
/*     */     //   198: areturn
/*     */     // Line number table:
/*     */     //   Java source line number -> byte code offset
/*     */     //   #73	-> 85
/*     */     //   #188	-> 122
/*     */     //   #69	-> 161
/*     */     //   #138	-> 183
/*     */     //   #161	-> 186
/*     */     //   #317	-> 197
/*     */     // Exception table:
/*     */     //   from	to	target	type
/*     */     //   85	111	111	java/lang/NullPointerException
/*     */     //   122	134	137	java/lang/NullPointerException
/*     */     //   128	150	150	java/lang/NullPointerException
/*     */   }
/*     */   
/*     */   private void a(String paramString, int paramInt1, int paramInt2, boolean paramBoolean1, boolean paramBoolean2, long paramLong) {
/*     */     // Byte code:
/*     */     //   0: getstatic me/konsolas/aac/j5.j : J
/*     */     //   3: lload #6
/*     */     //   5: lxor
/*     */     //   6: lstore #6
/*     */     //   8: lload #6
/*     */     //   10: dup2
/*     */     //   11: ldc2_w 125997196492660
/*     */     //   14: lxor
/*     */     //   15: lstore #8
/*     */     //   17: dup2
/*     */     //   18: ldc2_w 83627385515739
/*     */     //   21: lxor
/*     */     //   22: dup2
/*     */     //   23: bipush #32
/*     */     //   25: lushr
/*     */     //   26: l2i
/*     */     //   27: istore #10
/*     */     //   29: dup2
/*     */     //   30: bipush #32
/*     */     //   32: lshl
/*     */     //   33: bipush #32
/*     */     //   35: lushr
/*     */     //   36: lstore #11
/*     */     //   38: pop2
/*     */     //   39: dup2
/*     */     //   40: ldc2_w 89174845302429
/*     */     //   43: lxor
/*     */     //   44: lstore #13
/*     */     //   46: dup2
/*     */     //   47: ldc2_w 77152215178563
/*     */     //   50: lxor
/*     */     //   51: lstore #15
/*     */     //   53: pop2
/*     */     //   54: ldc2_w -8665214492820928644
/*     */     //   57: lload #6
/*     */     //   59: <illegal opcode> w : (JJ)[Lme/konsolas/aac/aN;
/*     */     //   64: iload #10
/*     */     //   66: aload_1
/*     */     //   67: iload_2
/*     */     //   68: iload_3
/*     */     //   69: sipush #2555
/*     */     //   72: ldc2_w 2980178720500710784
/*     */     //   75: lload #6
/*     */     //   77: lxor
/*     */     //   78: <illegal opcode> c : (IJ)Ljava/lang/String;
/*     */     //   83: iload #5
/*     */     //   85: iconst_0
/*     */     //   86: iconst_0
/*     */     //   87: iconst_1
/*     */     //   88: aconst_null
/*     */     //   89: lload #11
/*     */     //   91: invokestatic a : (ILjava/lang/String;IILjava/lang/String;ZZZZLjava/nio/charset/Charset;J)Ljava/lang/String;
/*     */     //   94: astore #18
/*     */     //   96: astore #17
/*     */     //   98: aload_0
/*     */     //   99: lload #13
/*     */     //   101: aload #18
/*     */     //   103: invokespecial a : (JLjava/lang/String;)Z
/*     */     //   106: aload #17
/*     */     //   108: ifnonnull -> 137
/*     */     //   111: ifeq -> 129
/*     */     //   114: goto -> 128
/*     */     //   117: ldc2_w -8676714712736853625
/*     */     //   120: lload #6
/*     */     //   122: <illegal opcode> w : (Ljava/lang/RuntimeException;JJ)Ljava/lang/RuntimeException;
/*     */     //   127: athrow
/*     */     //   128: return
/*     */     //   129: aload_0
/*     */     //   130: aload #18
/*     */     //   132: lload #15
/*     */     //   134: invokespecial b : (Ljava/lang/String;J)Z
/*     */     //   137: aload #17
/*     */     //   139: lload #6
/*     */     //   141: lconst_0
/*     */     //   142: lcmp
/*     */     //   143: ifle -> 212
/*     */     //   146: ifnonnull -> 210
/*     */     //   149: ifeq -> 184
/*     */     //   152: goto -> 166
/*     */     //   155: ldc2_w -8676714712736853625
/*     */     //   158: lload #6
/*     */     //   160: <illegal opcode> w : (Ljava/lang/RuntimeException;JJ)Ljava/lang/RuntimeException;
/*     */     //   165: athrow
/*     */     //   166: aload_0
/*     */     //   167: lload #8
/*     */     //   169: invokespecial a : (J)V
/*     */     //   172: return
/*     */     //   173: ldc2_w -8676714712736853625
/*     */     //   176: lload #6
/*     */     //   178: <illegal opcode> w : (Ljava/lang/RuntimeException;JJ)Ljava/lang/RuntimeException;
/*     */     //   183: athrow
/*     */     //   184: aload_0
/*     */     //   185: getfield i : Ljava/util/List;
/*     */     //   188: aload_0
/*     */     //   189: getfield i : Ljava/util/List;
/*     */     //   192: invokeinterface size : ()I
/*     */     //   197: iconst_1
/*     */     //   198: isub
/*     */     //   199: invokeinterface get : (I)Ljava/lang/Object;
/*     */     //   204: checkcast java/lang/String
/*     */     //   207: invokevirtual isEmpty : ()Z
/*     */     //   210: aload #17
/*     */     //   212: ifnonnull -> 306
/*     */     //   215: ifeq -> 281
/*     */     //   218: goto -> 232
/*     */     //   221: ldc2_w -8676714712736853625
/*     */     //   224: lload #6
/*     */     //   226: <illegal opcode> w : (Ljava/lang/RuntimeException;JJ)Ljava/lang/RuntimeException;
/*     */     //   231: athrow
/*     */     //   232: aload_0
/*     */     //   233: getfield i : Ljava/util/List;
/*     */     //   236: aload_0
/*     */     //   237: getfield i : Ljava/util/List;
/*     */     //   240: invokeinterface size : ()I
/*     */     //   245: iconst_1
/*     */     //   246: isub
/*     */     //   247: aload #18
/*     */     //   249: invokeinterface set : (ILjava/lang/Object;)Ljava/lang/Object;
/*     */     //   254: pop
/*     */     //   255: lload #6
/*     */     //   257: lconst_0
/*     */     //   258: lcmp
/*     */     //   259: iflt -> 307
/*     */     //   262: aload #17
/*     */     //   264: ifnull -> 307
/*     */     //   267: goto -> 281
/*     */     //   270: ldc2_w -8676714712736853625
/*     */     //   273: lload #6
/*     */     //   275: <illegal opcode> w : (Ljava/lang/RuntimeException;JJ)Ljava/lang/RuntimeException;
/*     */     //   280: athrow
/*     */     //   281: aload_0
/*     */     //   282: getfield i : Ljava/util/List;
/*     */     //   285: aload #18
/*     */     //   287: invokeinterface add : (Ljava/lang/Object;)Z
/*     */     //   292: goto -> 306
/*     */     //   295: ldc2_w -8676714712736853625
/*     */     //   298: lload #6
/*     */     //   300: <illegal opcode> w : (Ljava/lang/RuntimeException;JJ)Ljava/lang/RuntimeException;
/*     */     //   305: athrow
/*     */     //   306: pop
/*     */     //   307: iload #4
/*     */     //   309: aload #17
/*     */     //   311: ifnonnull -> 356
/*     */     //   314: ifeq -> 357
/*     */     //   317: goto -> 331
/*     */     //   320: ldc2_w -8676714712736853625
/*     */     //   323: lload #6
/*     */     //   325: <illegal opcode> w : (Ljava/lang/RuntimeException;JJ)Ljava/lang/RuntimeException;
/*     */     //   330: athrow
/*     */     //   331: aload_0
/*     */     //   332: getfield i : Ljava/util/List;
/*     */     //   335: ldc ''
/*     */     //   337: invokeinterface add : (Ljava/lang/Object;)Z
/*     */     //   342: goto -> 356
/*     */     //   345: ldc2_w -8676714712736853625
/*     */     //   348: lload #6
/*     */     //   350: <illegal opcode> w : (Ljava/lang/RuntimeException;JJ)Ljava/lang/RuntimeException;
/*     */     //   355: athrow
/*     */     //   356: pop
/*     */     //   357: return
/*     */     // Line number table:
/*     */     //   Java source line number -> byte code offset
/*     */     //   #95	-> 64
/*     */     //   #282	-> 98
/*     */     //   #110	-> 128
/*     */     //   #39	-> 129
/*     */     //   #93	-> 166
/*     */     //   #117	-> 172
/*     */     //   #86	-> 184
/*     */     //   #299	-> 232
/*     */     //   #87	-> 281
/*     */     //   #148	-> 307
/*     */     //   #206	-> 331
/*     */     //   #21	-> 357
/*     */     // Exception table:
/*     */     //   from	to	target	type
/*     */     //   98	114	117	java/lang/NullPointerException
/*     */     //   137	152	155	java/lang/NullPointerException
/*     */     //   149	173	173	java/lang/NullPointerException
/*     */     //   210	218	221	java/lang/NullPointerException
/*     */     //   215	267	270	java/lang/NullPointerException
/*     */     //   232	292	295	java/lang/NullPointerException
/*     */     //   307	317	320	java/lang/NullPointerException
/*     */     //   314	342	345	java/lang/NullPointerException
/*     */   }
/*     */   
/*     */   public j5() {
/* 208 */     this.f = "";
/*     */     this.a = "";
/*     */     this.e = -1;
/*     */     this.i = new ArrayList();
/*     */     this.i.add(""); } public j5 b(String paramString1, @Nullable String paramString2, int paramInt1, int paramInt2, char paramChar) {
/*     */     long l1 = (paramInt1 << 32L | paramInt2 << 48L >>> 32L | paramChar << 48L >>> 48L) ^ j;
/*     */     int i = (int)((l1 ^ 0x62285ACB9F6L) >>> 56L), j = (int)((l1 ^ 0x62285ACB9F6L) << 8L >>> 32L), k = (int)((l1 ^ 0x62285ACB9F6L) << 40L >>> 40L);
/*     */     l1 ^ 0x62285ACB9F6L;
/*     */     long l2 = l1 ^ 0x7FE29D2861B1L;
/*     */     o((byte)i, j, paramString1, k);
/*     */     d(paramString1, paramString2, l2);
/* 219 */     return this;
/*     */   }
/*     */   private void a(String paramString, char paramChar1, char paramChar2, int paramInt) {
/*     */     // Byte code:
/*     */     //   0: iload_2
/*     */     //   1: i2l
/*     */     //   2: bipush #48
/*     */     //   4: lshl
/*     */     //   5: iload_3
/*     */     //   6: i2l
/*     */     //   7: bipush #48
/*     */     //   9: lshl
/*     */     //   10: bipush #16
/*     */     //   12: lushr
/*     */     //   13: lor
/*     */     //   14: iload #4
/*     */     //   16: i2l
/*     */     //   17: bipush #32
/*     */     //   19: lshl
/*     */     //   20: bipush #32
/*     */     //   22: lushr
/*     */     //   23: lor
/*     */     //   24: getstatic me/konsolas/aac/j5.j : J
/*     */     //   27: lxor
/*     */     //   28: lstore #5
/*     */     //   30: ldc2_w 3685611843045962727
/*     */     //   33: lload #5
/*     */     //   35: <illegal opcode> w : (JJ)[Lme/konsolas/aac/aN;
/*     */     //   40: aload_0
/*     */     //   41: getfield h : Ljava/util/List;
/*     */     //   44: invokeinterface size : ()I
/*     */     //   49: iconst_2
/*     */     //   50: isub
/*     */     //   51: istore #8
/*     */     //   53: astore #7
/*     */     //   55: iload #8
/*     */     //   57: iflt -> 201
/*     */     //   60: aload_1
/*     */     //   61: aload_0
/*     */     //   62: getfield h : Ljava/util/List;
/*     */     //   65: iload #8
/*     */     //   67: invokeinterface get : (I)Ljava/lang/Object;
/*     */     //   72: invokevirtual equals : (Ljava/lang/Object;)Z
/*     */     //   75: iload_3
/*     */     //   76: iflt -> 173
/*     */     //   79: aload #7
/*     */     //   81: ifnonnull -> 173
/*     */     //   84: ifeq -> 193
/*     */     //   87: goto -> 101
/*     */     //   90: ldc2_w 3678606182383592732
/*     */     //   93: lload #5
/*     */     //   95: <illegal opcode> w : (Ljava/lang/RuntimeException;JJ)Ljava/lang/RuntimeException;
/*     */     //   100: athrow
/*     */     //   101: aload_0
/*     */     //   102: getfield h : Ljava/util/List;
/*     */     //   105: iload #8
/*     */     //   107: iconst_1
/*     */     //   108: iadd
/*     */     //   109: invokeinterface remove : (I)Ljava/lang/Object;
/*     */     //   114: pop
/*     */     //   115: aload_0
/*     */     //   116: getfield h : Ljava/util/List;
/*     */     //   119: iload #8
/*     */     //   121: invokeinterface remove : (I)Ljava/lang/Object;
/*     */     //   126: pop
/*     */     //   127: aload #7
/*     */     //   129: iload_2
/*     */     //   130: iflt -> 198
/*     */     //   133: ifnonnull -> 196
/*     */     //   136: goto -> 150
/*     */     //   139: ldc2_w 3678606182383592732
/*     */     //   142: lload #5
/*     */     //   144: <illegal opcode> w : (Ljava/lang/RuntimeException;JJ)Ljava/lang/RuntimeException;
/*     */     //   149: athrow
/*     */     //   150: aload_0
/*     */     //   151: getfield h : Ljava/util/List;
/*     */     //   154: invokeinterface isEmpty : ()Z
/*     */     //   159: goto -> 173
/*     */     //   162: ldc2_w 3678606182383592732
/*     */     //   165: lload #5
/*     */     //   167: <illegal opcode> w : (Ljava/lang/RuntimeException;JJ)Ljava/lang/RuntimeException;
/*     */     //   172: athrow
/*     */     //   173: ifeq -> 193
/*     */     //   176: aload_0
/*     */     //   177: aconst_null
/*     */     //   178: putfield h : Ljava/util/List;
/*     */     //   181: return
/*     */     //   182: ldc2_w 3678606182383592732
/*     */     //   185: lload #5
/*     */     //   187: <illegal opcode> w : (Ljava/lang/RuntimeException;JJ)Ljava/lang/RuntimeException;
/*     */     //   192: athrow
/*     */     //   193: iinc #8, -2
/*     */     //   196: aload #7
/*     */     //   198: ifnull -> 55
/*     */     //   201: iload_3
/*     */     //   202: ifle -> 60
/*     */     //   205: return
/*     */     // Line number table:
/*     */     //   Java source line number -> byte code offset
/*     */     //   #98	-> 40
/*     */     //   #135	-> 60
/*     */     //   #231	-> 101
/*     */     //   #88	-> 115
/*     */     //   #154	-> 127
/*     */     //   #321	-> 176
/*     */     //   #229	-> 181
/*     */     //   #260	-> 193
/*     */     //   #54	-> 201
/*     */     // Exception table:
/*     */     //   from	to	target	type
/*     */     //   60	87	90	java/lang/NullPointerException
/*     */     //   84	136	139	java/lang/NullPointerException
/*     */     //   101	159	162	java/lang/NullPointerException
/*     */     //   173	182	182	java/lang/NullPointerException
/*     */   }
/*     */   public j5 h(long paramLong, @Nullable String paramString) {
/*     */     // Byte code:
/*     */     //   0: getstatic me/konsolas/aac/j5.j : J
/*     */     //   3: lload_1
/*     */     //   4: lxor
/*     */     //   5: lstore_1
/*     */     //   6: lload_1
/*     */     //   7: dup2
/*     */     //   8: ldc2_w 110877872581055
/*     */     //   11: lxor
/*     */     //   12: dup2
/*     */     //   13: bipush #32
/*     */     //   15: lushr
/*     */     //   16: l2i
/*     */     //   17: istore #4
/*     */     //   19: dup2
/*     */     //   20: bipush #32
/*     */     //   22: lshl
/*     */     //   23: bipush #32
/*     */     //   25: lushr
/*     */     //   26: l2i
/*     */     //   27: istore #5
/*     */     //   29: pop2
/*     */     //   30: dup2
/*     */     //   31: ldc2_w 55018746687319
/*     */     //   34: lxor
/*     */     //   35: lstore #6
/*     */     //   37: pop2
/*     */     //   38: ldc2_w 5011811381744715087
/*     */     //   41: lload_1
/*     */     //   42: <illegal opcode> w : (JJ)[Lme/konsolas/aac/aN;
/*     */     //   47: astore #9
/*     */     //   49: aload_0
/*     */     //   50: aload_3
/*     */     //   51: aload #9
/*     */     //   53: ifnonnull -> 108
/*     */     //   56: ifnull -> 122
/*     */     //   59: goto -> 72
/*     */     //   62: ldc2_w 5018526492730774452
/*     */     //   65: lload_1
/*     */     //   66: <illegal opcode> w : (Ljava/lang/RuntimeException;JJ)Ljava/lang/RuntimeException;
/*     */     //   71: athrow
/*     */     //   72: aload_3
/*     */     //   73: sipush #23940
/*     */     //   76: ldc2_w 7294998028346452990
/*     */     //   79: lload_1
/*     */     //   80: lxor
/*     */     //   81: <illegal opcode> c : (IJ)Ljava/lang/String;
/*     */     //   86: lload #6
/*     */     //   88: iconst_0
/*     */     //   89: iconst_0
/*     */     //   90: iconst_1
/*     */     //   91: iconst_1
/*     */     //   92: invokestatic a : (Ljava/lang/String;Ljava/lang/String;JZZZZ)Ljava/lang/String;
/*     */     //   95: goto -> 108
/*     */     //   98: ldc2_w 5018526492730774452
/*     */     //   101: lload_1
/*     */     //   102: <illegal opcode> w : (Ljava/lang/RuntimeException;JJ)Ljava/lang/RuntimeException;
/*     */     //   107: athrow
/*     */     //   108: astore #8
/*     */     //   110: iload #4
/*     */     //   112: aload #8
/*     */     //   114: iload #5
/*     */     //   116: invokestatic b : (ILjava/lang/String;I)Ljava/util/List;
/*     */     //   119: goto -> 123
/*     */     //   122: aconst_null
/*     */     //   123: putfield h : Ljava/util/List;
/*     */     //   126: aload_0
/*     */     //   127: areturn
/*     */     // Line number table:
/*     */     //   Java source line number -> byte code offset
/*     */     //   #171	-> 49
/*     */     //   #186	-> 72
/*     */     //   #210	-> 122
/*     */     //   #58	-> 126
/*     */     // Exception table:
/*     */     //   from	to	target	type
/*     */     //   49	59	62	java/lang/NullPointerException
/*     */     //   56	95	98	java/lang/NullPointerException
/*     */   }
/*     */   public j5 c(String paramString1, @Nullable String paramString2, long paramLong) {
/*     */     paramLong = j ^ paramLong;
/*     */     long l1 = paramLong ^ 0xE480D8CB056L, l2 = paramLong ^ 0x29570F098110L;
/*     */     i(l2, paramString1);
/*     */     a(paramString1, paramString2, l1);
/*     */     return this;
/*     */   }
/*     */   
/*     */   public j5 a(long paramLong, String paramString) {
/*     */     // Byte code:
/*     */     //   0: getstatic me/konsolas/aac/j5.j : J
/*     */     //   3: lload_1
/*     */     //   4: lxor
/*     */     //   5: lstore_1
/*     */     //   6: lload_1
/*     */     //   7: dup2
/*     */     //   8: ldc2_w 99935428781811
/*     */     //   11: lxor
/*     */     //   12: lstore #4
/*     */     //   14: pop2
/*     */     //   15: ldc2_w 1206387704643981439
/*     */     //   18: lload_1
/*     */     //   19: <illegal opcode> w : (JJ)[Lme/konsolas/aac/aN;
/*     */     //   24: astore #6
/*     */     //   26: aload #6
/*     */     //   28: ifnonnull -> 93
/*     */     //   31: aload_3
/*     */     //   32: ifnonnull -> 79
/*     */     //   35: goto -> 48
/*     */     //   38: ldc2_w 1194887240716224132
/*     */     //   41: lload_1
/*     */     //   42: <illegal opcode> w : (Ljava/lang/RuntimeException;JJ)Ljava/lang/RuntimeException;
/*     */     //   47: athrow
/*     */     //   48: new java/lang/NullPointerException
/*     */     //   51: dup
/*     */     //   52: sipush #16706
/*     */     //   55: ldc2_w 8339573735354835506
/*     */     //   58: lload_1
/*     */     //   59: lxor
/*     */     //   60: <illegal opcode> c : (IJ)Ljava/lang/String;
/*     */     //   65: invokespecial <init> : (Ljava/lang/String;)V
/*     */     //   68: athrow
/*     */     //   69: ldc2_w 1194887240716224132
/*     */     //   72: lload_1
/*     */     //   73: <illegal opcode> w : (Ljava/lang/RuntimeException;JJ)Ljava/lang/RuntimeException;
/*     */     //   78: athrow
/*     */     //   79: aload_0
/*     */     //   80: aload_3
/*     */     //   81: iconst_0
/*     */     //   82: aload_3
/*     */     //   83: invokevirtual length : ()I
/*     */     //   86: iconst_0
/*     */     //   87: iconst_0
/*     */     //   88: lload #4
/*     */     //   90: invokespecial a : (Ljava/lang/String;IIZZJ)V
/*     */     //   93: aload_0
/*     */     //   94: areturn
/*     */     // Line number table:
/*     */     //   Java source line number -> byte code offset
/*     */     //   #184	-> 26
/*     */     //   #102	-> 79
/*     */     //   #12	-> 93
/*     */     // Exception table:
/*     */     //   from	to	target	type
/*     */     //   26	35	38	java/lang/NullPointerException
/*     */     //   31	69	69	java/lang/NullPointerException
/*     */   }
/*     */   
/*     */   private void a(long paramLong) {
/*     */     // Byte code:
/*     */     //   0: getstatic me/konsolas/aac/j5.j : J
/*     */     //   3: lload_1
/*     */     //   4: lxor
/*     */     //   5: lstore_1
/*     */     //   6: ldc2_w 665084987630684664
/*     */     //   9: lload_1
/*     */     //   10: <illegal opcode> w : (JJ)[Lme/konsolas/aac/aN;
/*     */     //   15: aload_0
/*     */     //   16: getfield i : Ljava/util/List;
/*     */     //   19: aload_0
/*     */     //   20: getfield i : Ljava/util/List;
/*     */     //   23: invokeinterface size : ()I
/*     */     //   28: iconst_1
/*     */     //   29: isub
/*     */     //   30: invokeinterface remove : (I)Ljava/lang/Object;
/*     */     //   35: checkcast java/lang/String
/*     */     //   38: astore #4
/*     */     //   40: astore_3
/*     */     //   41: aload #4
/*     */     //   43: invokevirtual isEmpty : ()Z
/*     */     //   46: aload_3
/*     */     //   47: ifnonnull -> 178
/*     */     //   50: ifeq -> 154
/*     */     //   53: goto -> 66
/*     */     //   56: ldc2_w 653655133066993411
/*     */     //   59: lload_1
/*     */     //   60: <illegal opcode> w : (Ljava/lang/RuntimeException;JJ)Ljava/lang/RuntimeException;
/*     */     //   65: athrow
/*     */     //   66: aload_0
/*     */     //   67: getfield i : Ljava/util/List;
/*     */     //   70: invokeinterface isEmpty : ()Z
/*     */     //   75: aload_3
/*     */     //   76: ifnonnull -> 178
/*     */     //   79: goto -> 92
/*     */     //   82: ldc2_w 653655133066993411
/*     */     //   85: lload_1
/*     */     //   86: <illegal opcode> w : (Ljava/lang/RuntimeException;JJ)Ljava/lang/RuntimeException;
/*     */     //   91: athrow
/*     */     //   92: lload_1
/*     */     //   93: lconst_0
/*     */     //   94: lcmp
/*     */     //   95: iflt -> 165
/*     */     //   98: ifne -> 154
/*     */     //   101: goto -> 114
/*     */     //   104: ldc2_w 653655133066993411
/*     */     //   107: lload_1
/*     */     //   108: <illegal opcode> w : (Ljava/lang/RuntimeException;JJ)Ljava/lang/RuntimeException;
/*     */     //   113: athrow
/*     */     //   114: aload_0
/*     */     //   115: getfield i : Ljava/util/List;
/*     */     //   118: aload_0
/*     */     //   119: getfield i : Ljava/util/List;
/*     */     //   122: invokeinterface size : ()I
/*     */     //   127: iconst_1
/*     */     //   128: isub
/*     */     //   129: ldc ''
/*     */     //   131: invokeinterface set : (ILjava/lang/Object;)Ljava/lang/Object;
/*     */     //   136: pop
/*     */     //   137: aload_3
/*     */     //   138: ifnull -> 179
/*     */     //   141: goto -> 154
/*     */     //   144: ldc2_w 653655133066993411
/*     */     //   147: lload_1
/*     */     //   148: <illegal opcode> w : (Ljava/lang/RuntimeException;JJ)Ljava/lang/RuntimeException;
/*     */     //   153: athrow
/*     */     //   154: aload_0
/*     */     //   155: getfield i : Ljava/util/List;
/*     */     //   158: ldc ''
/*     */     //   160: invokeinterface add : (Ljava/lang/Object;)Z
/*     */     //   165: goto -> 178
/*     */     //   168: ldc2_w 653655133066993411
/*     */     //   171: lload_1
/*     */     //   172: <illegal opcode> w : (Ljava/lang/RuntimeException;JJ)Ljava/lang/RuntimeException;
/*     */     //   177: athrow
/*     */     //   178: pop
/*     */     //   179: return
/*     */     // Line number table:
/*     */     //   Java source line number -> byte code offset
/*     */     //   #196	-> 15
/*     */     //   #15	-> 41
/*     */     //   #109	-> 114
/*     */     //   #235	-> 154
/*     */     //   #252	-> 179
/*     */     // Exception table:
/*     */     //   from	to	target	type
/*     */     //   41	53	56	java/lang/NullPointerException
/*     */     //   50	79	82	java/lang/NullPointerException
/*     */     //   66	101	104	java/lang/NullPointerException
/*     */     //   92	141	144	java/lang/NullPointerException
/*     */     //   114	165	168	java/lang/NullPointerException
/*     */   }
/*     */   
/*     */   public l6 a(long paramLong) {
/*     */     // Byte code:
/*     */     //   0: getstatic me/konsolas/aac/j5.j : J
/*     */     //   3: lload_1
/*     */     //   4: lxor
/*     */     //   5: lstore_1
/*     */     //   6: lload_1
/*     */     //   7: dup2
/*     */     //   8: ldc2_w 67326619444786
/*     */     //   11: lxor
/*     */     //   12: lstore_3
/*     */     //   13: pop2
/*     */     //   14: ldc2_w -1194901492086018136
/*     */     //   17: lload_1
/*     */     //   18: <illegal opcode> w : (JJ)[Lme/konsolas/aac/aN;
/*     */     //   23: astore #5
/*     */     //   25: aload_0
/*     */     //   26: getfield c : Ljava/lang/String;
/*     */     //   29: aload #5
/*     */     //   31: ifnonnull -> 85
/*     */     //   34: ifnonnull -> 81
/*     */     //   37: goto -> 50
/*     */     //   40: ldc2_w -1206331618137114285
/*     */     //   43: lload_1
/*     */     //   44: <illegal opcode> w : (Ljava/lang/RuntimeException;JJ)Ljava/lang/RuntimeException;
/*     */     //   49: athrow
/*     */     //   50: new java/lang/IllegalStateException
/*     */     //   53: dup
/*     */     //   54: sipush #25310
/*     */     //   57: ldc2_w 6889561619433586269
/*     */     //   60: lload_1
/*     */     //   61: lxor
/*     */     //   62: <illegal opcode> c : (IJ)Ljava/lang/String;
/*     */     //   67: invokespecial <init> : (Ljava/lang/String;)V
/*     */     //   70: athrow
/*     */     //   71: ldc2_w -1206331618137114285
/*     */     //   74: lload_1
/*     */     //   75: <illegal opcode> w : (Ljava/lang/RuntimeException;JJ)Ljava/lang/RuntimeException;
/*     */     //   80: athrow
/*     */     //   81: aload_0
/*     */     //   82: getfield g : Ljava/lang/String;
/*     */     //   85: ifnonnull -> 119
/*     */     //   88: new java/lang/IllegalStateException
/*     */     //   91: dup
/*     */     //   92: sipush #12781
/*     */     //   95: ldc2_w 7410200009551588686
/*     */     //   98: lload_1
/*     */     //   99: lxor
/*     */     //   100: <illegal opcode> c : (IJ)Ljava/lang/String;
/*     */     //   105: invokespecial <init> : (Ljava/lang/String;)V
/*     */     //   108: athrow
/*     */     //   109: ldc2_w -1206331618137114285
/*     */     //   112: lload_1
/*     */     //   113: <illegal opcode> w : (Ljava/lang/RuntimeException;JJ)Ljava/lang/RuntimeException;
/*     */     //   118: athrow
/*     */     //   119: new me/konsolas/aac/l6
/*     */     //   122: dup
/*     */     //   123: lload_3
/*     */     //   124: aload_0
/*     */     //   125: invokespecial <init> : (JLme/konsolas/aac/j5;)V
/*     */     //   128: areturn
/*     */     // Line number table:
/*     */     //   Java source line number -> byte code offset
/*     */     //   #201	-> 25
/*     */     //   #263	-> 81
/*     */     //   #241	-> 119
/*     */     // Exception table:
/*     */     //   from	to	target	type
/*     */     //   25	37	40	java/lang/NullPointerException
/*     */     //   34	71	71	java/lang/NullPointerException
/*     */     //   85	109	109	java/lang/NullPointerException
/*     */   }
/*     */   
/*     */   @Nullable
/*     */   private static String a(long paramLong, String paramString, int paramInt1, int paramInt2) {
/* 249 */     paramLong = j ^ paramLong; long l1 = paramLong ^ 0x175310561806L; int i = (int)((paramLong ^ 0x35D19759297DL) >>> 48L); long l2 = (paramLong ^ 0x35D19759297DL) << 16L >>> 16L; paramLong ^ 0x35D19759297DL; String str = l6.a((short)i, paramString, paramInt1, paramInt2, l2, false);
/*     */     return eO.a(l1, str);
/*     */   }
/*     */   
/*     */   public j5 g(long paramLong, String paramString) {
/*     */     // Byte code:
/*     */     //   0: getstatic me/konsolas/aac/j5.j : J
/*     */     //   3: lload_1
/*     */     //   4: lxor
/*     */     //   5: lstore_1
/*     */     //   6: lload_1
/*     */     //   7: dup2
/*     */     //   8: ldc2_w 10812073669807
/*     */     //   11: lxor
/*     */     //   12: lstore #4
/*     */     //   14: pop2
/*     */     //   15: aload_3
/*     */     //   16: ifnonnull -> 50
/*     */     //   19: new java/lang/NullPointerException
/*     */     //   22: dup
/*     */     //   23: sipush #26038
/*     */     //   26: ldc2_w 7597268871344223953
/*     */     //   29: lload_1
/*     */     //   30: lxor
/*     */     //   31: <illegal opcode> c : (IJ)Ljava/lang/String;
/*     */     //   36: invokespecial <init> : (Ljava/lang/String;)V
/*     */     //   39: athrow
/*     */     //   40: ldc2_w -2267822032433416554
/*     */     //   43: lload_1
/*     */     //   44: <illegal opcode> w : (Ljava/lang/RuntimeException;JJ)Ljava/lang/RuntimeException;
/*     */     //   49: athrow
/*     */     //   50: aload_0
/*     */     //   51: aload_3
/*     */     //   52: iconst_1
/*     */     //   53: lload #4
/*     */     //   55: invokespecial a : (Ljava/lang/String;ZJ)Lme/konsolas/aac/j5;
/*     */     //   58: areturn
/*     */     // Line number table:
/*     */     //   Java source line number -> byte code offset
/*     */     //   #211	-> 15
/*     */     //   #220	-> 19
/*     */     //   #108	-> 50
/*     */     // Exception table:
/*     */     //   from	to	target	type
/*     */     //   15	40	40	java/lang/NullPointerException
/*     */   }
/*     */   
/*     */   private static int d(long paramLong, String paramString, int paramInt1, int paramInt2) {
/*     */     // Byte code:
/*     */     //   0: getstatic me/konsolas/aac/j5.j : J
/*     */     //   3: lload_0
/*     */     //   4: lxor
/*     */     //   5: lstore_0
/*     */     //   6: ldc2_w 8534244762143585965
/*     */     //   9: lload_0
/*     */     //   10: <illegal opcode> w : (JJ)[Lme/konsolas/aac/aN;
/*     */     //   15: iload_3
/*     */     //   16: istore #6
/*     */     //   18: astore #5
/*     */     //   20: iload #6
/*     */     //   22: iload #4
/*     */     //   24: if_icmpge -> 182
/*     */     //   27: aload_2
/*     */     //   28: iload #6
/*     */     //   30: invokevirtual charAt : (I)C
/*     */     //   33: aload #5
/*     */     //   35: lload_0
/*     */     //   36: lconst_0
/*     */     //   37: lcmp
/*     */     //   38: iflt -> 46
/*     */     //   41: ifnonnull -> 190
/*     */     //   44: aload #5
/*     */     //   46: ifnonnull -> 124
/*     */     //   49: goto -> 62
/*     */     //   52: ldc2_w 8522885005208445014
/*     */     //   55: lload_0
/*     */     //   56: <illegal opcode> w : (Ljava/lang/RuntimeException;JJ)Ljava/lang/RuntimeException;
/*     */     //   61: athrow
/*     */     //   62: lload_0
/*     */     //   63: lconst_0
/*     */     //   64: lcmp
/*     */     //   65: ifle -> 111
/*     */     //   68: lookupswitch default -> 174, 58 -> 171, 91 -> 106
/*     */     //   96: ldc2_w 8522885005208445014
/*     */     //   99: lload_0
/*     */     //   100: <illegal opcode> w : (Ljava/lang/RuntimeException;JJ)Ljava/lang/RuntimeException;
/*     */     //   105: athrow
/*     */     //   106: iinc #6, 1
/*     */     //   109: iload #6
/*     */     //   111: goto -> 124
/*     */     //   114: ldc2_w 8522885005208445014
/*     */     //   117: lload_0
/*     */     //   118: <illegal opcode> w : (Ljava/lang/RuntimeException;JJ)Ljava/lang/RuntimeException;
/*     */     //   123: athrow
/*     */     //   124: iload #4
/*     */     //   126: lload_0
/*     */     //   127: lconst_0
/*     */     //   128: lcmp
/*     */     //   129: iflt -> 143
/*     */     //   132: if_icmpge -> 174
/*     */     //   135: aload_2
/*     */     //   136: iload #6
/*     */     //   138: invokevirtual charAt : (I)C
/*     */     //   141: bipush #93
/*     */     //   143: if_icmpne -> 106
/*     */     //   146: lload_0
/*     */     //   147: lconst_0
/*     */     //   148: lcmp
/*     */     //   149: ifle -> 177
/*     */     //   152: goto -> 165
/*     */     //   155: ldc2_w 8522885005208445014
/*     */     //   158: lload_0
/*     */     //   159: <illegal opcode> w : (Ljava/lang/RuntimeException;JJ)Ljava/lang/RuntimeException;
/*     */     //   164: athrow
/*     */     //   165: lload_0
/*     */     //   166: lconst_0
/*     */     //   167: lcmp
/*     */     //   168: ifgt -> 174
/*     */     //   171: iload #6
/*     */     //   173: ireturn
/*     */     //   174: iinc #6, 1
/*     */     //   177: aload #5
/*     */     //   179: ifnull -> 20
/*     */     //   182: lload_0
/*     */     //   183: lconst_0
/*     */     //   184: lcmp
/*     */     //   185: ifle -> 27
/*     */     //   188: iload #4
/*     */     //   190: ireturn
/*     */     // Line number table:
/*     */     //   Java source line number -> byte code offset
/*     */     //   #217	-> 15
/*     */     //   #240	-> 27
/*     */     //   #123	-> 106
/*     */     //   #178	-> 135
/*     */     //   #129	-> 171
/*     */     //   #189	-> 174
/*     */     //   #60	-> 182
/*     */     // Exception table:
/*     */     //   from	to	target	type
/*     */     //   27	49	52	java/lang/NullPointerException
/*     */     //   44	96	96	java/lang/NullPointerException
/*     */     //   62	111	114	java/lang/NullPointerException
/*     */     //   124	146	155	java/lang/NullPointerException
/*     */   }
/*     */   
/*     */   public j5 c(long paramLong, @Nullable String paramString) {
/*     */     // Byte code:
/*     */     //   0: getstatic me/konsolas/aac/j5.j : J
/*     */     //   3: lload_1
/*     */     //   4: lxor
/*     */     //   5: lstore_1
/*     */     //   6: lload_1
/*     */     //   7: dup2
/*     */     //   8: ldc2_w 32672274243922
/*     */     //   11: lxor
/*     */     //   12: dup2
/*     */     //   13: bipush #32
/*     */     //   15: lushr
/*     */     //   16: l2i
/*     */     //   17: istore #4
/*     */     //   19: dup2
/*     */     //   20: bipush #32
/*     */     //   22: lshl
/*     */     //   23: bipush #32
/*     */     //   25: lushr
/*     */     //   26: l2i
/*     */     //   27: istore #5
/*     */     //   29: pop2
/*     */     //   30: dup2
/*     */     //   31: ldc2_w 82922189334458
/*     */     //   34: lxor
/*     */     //   35: lstore #6
/*     */     //   37: pop2
/*     */     //   38: ldc2_w -3647635849956373086
/*     */     //   41: lload_1
/*     */     //   42: <illegal opcode> w : (JJ)[Lme/konsolas/aac/aN;
/*     */     //   47: astore #9
/*     */     //   49: aload_0
/*     */     //   50: aload_3
/*     */     //   51: aload #9
/*     */     //   53: ifnonnull -> 108
/*     */     //   56: ifnull -> 122
/*     */     //   59: goto -> 72
/*     */     //   62: ldc2_w -3654642365884048551
/*     */     //   65: lload_1
/*     */     //   66: <illegal opcode> w : (Ljava/lang/RuntimeException;JJ)Ljava/lang/RuntimeException;
/*     */     //   71: athrow
/*     */     //   72: aload_3
/*     */     //   73: sipush #23940
/*     */     //   76: ldc2_w 7295113890843222803
/*     */     //   79: lload_1
/*     */     //   80: lxor
/*     */     //   81: <illegal opcode> c : (IJ)Ljava/lang/String;
/*     */     //   86: lload #6
/*     */     //   88: iconst_1
/*     */     //   89: iconst_0
/*     */     //   90: iconst_1
/*     */     //   91: iconst_1
/*     */     //   92: invokestatic a : (Ljava/lang/String;Ljava/lang/String;JZZZZ)Ljava/lang/String;
/*     */     //   95: goto -> 108
/*     */     //   98: ldc2_w -3654642365884048551
/*     */     //   101: lload_1
/*     */     //   102: <illegal opcode> w : (Ljava/lang/RuntimeException;JJ)Ljava/lang/RuntimeException;
/*     */     //   107: athrow
/*     */     //   108: astore #8
/*     */     //   110: iload #4
/*     */     //   112: aload #8
/*     */     //   114: iload #5
/*     */     //   116: invokestatic b : (ILjava/lang/String;I)Ljava/util/List;
/*     */     //   119: goto -> 123
/*     */     //   122: aconst_null
/*     */     //   123: putfield h : Ljava/util/List;
/*     */     //   126: aload_0
/*     */     //   127: areturn
/*     */     // Line number table:
/*     */     //   Java source line number -> byte code offset
/*     */     //   #223	-> 49
/*     */     //   #316	-> 72
/*     */     //   #144	-> 92
/*     */     //   #85	-> 108
/*     */     //   #199	-> 122
/*     */     //   #190	-> 126
/*     */     // Exception table:
/*     */     //   from	to	target	type
/*     */     //   49	59	62	java/lang/NullPointerException
/*     */     //   56	95	98	java/lang/NullPointerException
/*     */   }
/*     */   
/*     */   public j5 a(long paramLong, int paramInt) {
/*     */     // Byte code:
/*     */     //   0: getstatic me/konsolas/aac/j5.j : J
/*     */     //   3: lload_1
/*     */     //   4: lxor
/*     */     //   5: lstore_1
/*     */     //   6: ldc2_w -3440816542753697539
/*     */     //   9: lload_1
/*     */     //   10: <illegal opcode> w : (JJ)[Lme/konsolas/aac/aN;
/*     */     //   15: aload_0
/*     */     //   16: getfield i : Ljava/util/List;
/*     */     //   19: iload_3
/*     */     //   20: invokeinterface remove : (I)Ljava/lang/Object;
/*     */     //   25: pop
/*     */     //   26: astore #4
/*     */     //   28: aload_0
/*     */     //   29: aload #4
/*     */     //   31: ifnonnull -> 84
/*     */     //   34: getfield i : Ljava/util/List;
/*     */     //   37: invokeinterface isEmpty : ()Z
/*     */     //   42: ifeq -> 83
/*     */     //   45: goto -> 58
/*     */     //   48: ldc2_w -3452247496961735162
/*     */     //   51: lload_1
/*     */     //   52: <illegal opcode> w : (Ljava/lang/RuntimeException;JJ)Ljava/lang/RuntimeException;
/*     */     //   57: athrow
/*     */     //   58: aload_0
/*     */     //   59: getfield i : Ljava/util/List;
/*     */     //   62: ldc ''
/*     */     //   64: invokeinterface add : (Ljava/lang/Object;)Z
/*     */     //   69: pop
/*     */     //   70: goto -> 83
/*     */     //   73: ldc2_w -3452247496961735162
/*     */     //   76: lload_1
/*     */     //   77: <illegal opcode> w : (Ljava/lang/RuntimeException;JJ)Ljava/lang/RuntimeException;
/*     */     //   82: athrow
/*     */     //   83: aload_0
/*     */     //   84: areturn
/*     */     // Line number table:
/*     */     //   Java source line number -> byte code offset
/*     */     //   #226	-> 15
/*     */     //   #181	-> 28
/*     */     //   #305	-> 58
/*     */     //   #82	-> 83
/*     */     // Exception table:
/*     */     //   from	to	target	type
/*     */     //   28	45	48	java/lang/NullPointerException
/*     */     //   34	70	73	java/lang/NullPointerException
/*     */   }
/*     */   
/*     */   public j5 e(long paramLong, String paramString) {
/*     */     // Byte code:
/*     */     //   0: getstatic me/konsolas/aac/j5.j : J
/*     */     //   3: lload_1
/*     */     //   4: lxor
/*     */     //   5: lstore_1
/*     */     //   6: lload_1
/*     */     //   7: dup2
/*     */     //   8: ldc2_w 97163399107391
/*     */     //   11: lxor
/*     */     //   12: lstore #4
/*     */     //   14: pop2
/*     */     //   15: aload_3
/*     */     //   16: ifnonnull -> 50
/*     */     //   19: new java/lang/NullPointerException
/*     */     //   22: dup
/*     */     //   23: sipush #32709
/*     */     //   26: ldc2_w 8954876501377289020
/*     */     //   29: lload_1
/*     */     //   30: lxor
/*     */     //   31: <illegal opcode> c : (IJ)Ljava/lang/String;
/*     */     //   36: invokespecial <init> : (Ljava/lang/String;)V
/*     */     //   39: athrow
/*     */     //   40: ldc2_w 510950112259510534
/*     */     //   43: lload_1
/*     */     //   44: <illegal opcode> w : (Ljava/lang/RuntimeException;JJ)Ljava/lang/RuntimeException;
/*     */     //   49: athrow
/*     */     //   50: aload_0
/*     */     //   51: aload_3
/*     */     //   52: iconst_0
/*     */     //   53: lload #4
/*     */     //   55: invokespecial a : (Ljava/lang/String;ZJ)Lme/konsolas/aac/j5;
/*     */     //   58: areturn
/*     */     // Line number table:
/*     */     //   Java source line number -> byte code offset
/*     */     //   #228	-> 15
/*     */     //   #225	-> 50
/*     */     // Exception table:
/*     */     //   from	to	target	type
/*     */     //   15	40	40	java/lang/NullPointerException
/*     */   }
/*     */   
/*     */   public j5 q(@Nullable String paramString, long paramLong) {
/*     */     // Byte code:
/*     */     //   0: getstatic me/konsolas/aac/j5.j : J
/*     */     //   3: lload_2
/*     */     //   4: lxor
/*     */     //   5: lstore_2
/*     */     //   6: lload_2
/*     */     //   7: dup2
/*     */     //   8: ldc2_w 124617739056143
/*     */     //   11: lxor
/*     */     //   12: lstore #4
/*     */     //   14: pop2
/*     */     //   15: ldc2_w -2389787727413584361
/*     */     //   18: lload_2
/*     */     //   19: <illegal opcode> w : (JJ)[Lme/konsolas/aac/aN;
/*     */     //   24: astore #6
/*     */     //   26: aload_0
/*     */     //   27: aload_1
/*     */     //   28: aload #6
/*     */     //   30: ifnonnull -> 74
/*     */     //   33: ifnull -> 77
/*     */     //   36: goto -> 49
/*     */     //   39: ldc2_w -2378709716440102676
/*     */     //   42: lload_2
/*     */     //   43: <illegal opcode> w : (Ljava/lang/RuntimeException;JJ)Ljava/lang/RuntimeException;
/*     */     //   48: athrow
/*     */     //   49: aload_1
/*     */     //   50: ldc ''
/*     */     //   52: lload #4
/*     */     //   54: iconst_0
/*     */     //   55: iconst_0
/*     */     //   56: iconst_0
/*     */     //   57: iconst_0
/*     */     //   58: invokestatic a : (Ljava/lang/String;Ljava/lang/String;JZZZZ)Ljava/lang/String;
/*     */     //   61: goto -> 74
/*     */     //   64: ldc2_w -2378709716440102676
/*     */     //   67: lload_2
/*     */     //   68: <illegal opcode> w : (Ljava/lang/RuntimeException;JJ)Ljava/lang/RuntimeException;
/*     */     //   73: athrow
/*     */     //   74: goto -> 78
/*     */     //   77: aconst_null
/*     */     //   78: putfield d : Ljava/lang/String;
/*     */     //   81: aload_0
/*     */     //   82: areturn
/*     */     // Line number table:
/*     */     //   Java source line number -> byte code offset
/*     */     //   #237	-> 26
/*     */     //   #177	-> 49
/*     */     //   #203	-> 77
/*     */     //   #233	-> 81
/*     */     // Exception table:
/*     */     //   from	to	target	type
/*     */     //   26	36	39	java/lang/NullPointerException
/*     */     //   33	61	64	java/lang/NullPointerException
/*     */   }
/*     */   
/*     */   private static int b(String paramString, int paramInt1, long paramLong, int paramInt2) {
/*     */     // Byte code:
/*     */     //   0: getstatic me/konsolas/aac/j5.j : J
/*     */     //   3: lload_2
/*     */     //   4: lxor
/*     */     //   5: lstore_2
/*     */     //   6: lload_2
/*     */     //   7: dup2
/*     */     //   8: ldc2_w 64201421783093
/*     */     //   11: lxor
/*     */     //   12: dup2
/*     */     //   13: bipush #32
/*     */     //   15: lushr
/*     */     //   16: l2i
/*     */     //   17: istore #5
/*     */     //   19: dup2
/*     */     //   20: bipush #32
/*     */     //   22: lshl
/*     */     //   23: bipush #32
/*     */     //   25: lushr
/*     */     //   26: lstore #6
/*     */     //   28: pop2
/*     */     //   29: pop2
/*     */     //   30: ldc2_w 7588722873783314834
/*     */     //   33: lload_2
/*     */     //   34: <illegal opcode> w : (JJ)[Lme/konsolas/aac/aN;
/*     */     //   39: astore #8
/*     */     //   41: iload #5
/*     */     //   43: aload_0
/*     */     //   44: iload_1
/*     */     //   45: iload #4
/*     */     //   47: ldc ''
/*     */     //   49: iconst_0
/*     */     //   50: iconst_0
/*     */     //   51: iconst_0
/*     */     //   52: iconst_1
/*     */     //   53: aconst_null
/*     */     //   54: lload #6
/*     */     //   56: invokestatic a : (ILjava/lang/String;IILjava/lang/String;ZZZZLjava/nio/charset/Charset;J)Ljava/lang/String;
/*     */     //   59: astore #9
/*     */     //   61: aload #9
/*     */     //   63: invokestatic parseInt : (Ljava/lang/String;)I
/*     */     //   66: istore #10
/*     */     //   68: iload #10
/*     */     //   70: aload #8
/*     */     //   72: ifnonnull -> 133
/*     */     //   75: ifle -> 132
/*     */     //   78: goto -> 91
/*     */     //   81: ldc2_w 7599942687529238377
/*     */     //   84: lload_2
/*     */     //   85: <illegal opcode> w : (Ljava/lang/RuntimeException;JJ)Ljava/lang/RuntimeException;
/*     */     //   90: athrow
/*     */     //   91: iload #10
/*     */     //   93: aload #8
/*     */     //   95: ifnonnull -> 133
/*     */     //   98: goto -> 111
/*     */     //   101: ldc2_w 7599942687529238377
/*     */     //   104: lload_2
/*     */     //   105: <illegal opcode> w : (Ljava/lang/RuntimeException;JJ)Ljava/lang/RuntimeException;
/*     */     //   110: athrow
/*     */     //   111: ldc 65535
/*     */     //   113: if_icmpgt -> 132
/*     */     //   116: goto -> 129
/*     */     //   119: ldc2_w 7599942687529238377
/*     */     //   122: lload_2
/*     */     //   123: <illegal opcode> w : (Ljava/lang/RuntimeException;JJ)Ljava/lang/RuntimeException;
/*     */     //   128: athrow
/*     */     //   129: iload #10
/*     */     //   131: ireturn
/*     */     //   132: iconst_m1
/*     */     //   133: ireturn
/*     */     //   134: astore #9
/*     */     //   136: iconst_m1
/*     */     //   137: ireturn
/*     */     // Line number table:
/*     */     //   Java source line number -> byte code offset
/*     */     //   #261	-> 41
/*     */     //   #307	-> 61
/*     */     //   #111	-> 68
/*     */     //   #284	-> 132
/*     */     //   #106	-> 134
/*     */     //   #48	-> 136
/*     */     // Exception table:
/*     */     //   from	to	target	type
/*     */     //   41	131	134	java/lang/NumberFormatException
/*     */     //   68	78	81	java/lang/NumberFormatException
/*     */     //   75	98	101	java/lang/NumberFormatException
/*     */     //   91	116	119	java/lang/NumberFormatException
/*     */     //   132	133	134	java/lang/NumberFormatException
/*     */   }
/*     */   
/*     */   private static int a(String paramString, int paramInt1, int paramInt2, long paramLong) {
/*     */     // Byte code:
/*     */     //   0: getstatic me/konsolas/aac/j5.j : J
/*     */     //   3: lload_3
/*     */     //   4: lxor
/*     */     //   5: lstore_3
/*     */     //   6: ldc2_w 415608139088790790
/*     */     //   9: lload_3
/*     */     //   10: <illegal opcode> w : (JJ)[Lme/konsolas/aac/aN;
/*     */     //   15: astore #5
/*     */     //   17: iload_2
/*     */     //   18: iload_1
/*     */     //   19: isub
/*     */     //   20: aload #5
/*     */     //   22: ifnonnull -> 59
/*     */     //   25: iconst_2
/*     */     //   26: if_icmpge -> 54
/*     */     //   29: goto -> 42
/*     */     //   32: ldc2_w 426836745038566397
/*     */     //   35: lload_3
/*     */     //   36: <illegal opcode> w : (Ljava/lang/RuntimeException;JJ)Ljava/lang/RuntimeException;
/*     */     //   41: athrow
/*     */     //   42: iconst_m1
/*     */     //   43: ireturn
/*     */     //   44: ldc2_w 426836745038566397
/*     */     //   47: lload_3
/*     */     //   48: <illegal opcode> w : (Ljava/lang/RuntimeException;JJ)Ljava/lang/RuntimeException;
/*     */     //   53: athrow
/*     */     //   54: aload_0
/*     */     //   55: iload_1
/*     */     //   56: invokevirtual charAt : (I)C
/*     */     //   59: istore #6
/*     */     //   61: iload #6
/*     */     //   63: bipush #97
/*     */     //   65: lload_3
/*     */     //   66: lconst_0
/*     */     //   67: lcmp
/*     */     //   68: iflt -> 165
/*     */     //   71: aload #5
/*     */     //   73: ifnonnull -> 165
/*     */     //   76: if_icmplt -> 130
/*     */     //   79: goto -> 92
/*     */     //   82: ldc2_w 426836745038566397
/*     */     //   85: lload_3
/*     */     //   86: <illegal opcode> w : (Ljava/lang/RuntimeException;JJ)Ljava/lang/RuntimeException;
/*     */     //   91: athrow
/*     */     //   92: iload #6
/*     */     //   94: bipush #122
/*     */     //   96: aload #5
/*     */     //   98: ifnonnull -> 222
/*     */     //   101: goto -> 114
/*     */     //   104: ldc2_w 426836745038566397
/*     */     //   107: lload_3
/*     */     //   108: <illegal opcode> w : (Ljava/lang/RuntimeException;JJ)Ljava/lang/RuntimeException;
/*     */     //   113: athrow
/*     */     //   114: if_icmple -> 220
/*     */     //   117: goto -> 130
/*     */     //   120: ldc2_w 426836745038566397
/*     */     //   123: lload_3
/*     */     //   124: <illegal opcode> w : (Ljava/lang/RuntimeException;JJ)Ljava/lang/RuntimeException;
/*     */     //   129: athrow
/*     */     //   130: iload #6
/*     */     //   132: aload #5
/*     */     //   134: ifnonnull -> 219
/*     */     //   137: goto -> 150
/*     */     //   140: ldc2_w 426836745038566397
/*     */     //   143: lload_3
/*     */     //   144: <illegal opcode> w : (Ljava/lang/RuntimeException;JJ)Ljava/lang/RuntimeException;
/*     */     //   149: athrow
/*     */     //   150: bipush #65
/*     */     //   152: goto -> 165
/*     */     //   155: ldc2_w 426836745038566397
/*     */     //   158: lload_3
/*     */     //   159: <illegal opcode> w : (Ljava/lang/RuntimeException;JJ)Ljava/lang/RuntimeException;
/*     */     //   164: athrow
/*     */     //   165: lload_3
/*     */     //   166: lconst_0
/*     */     //   167: lcmp
/*     */     //   168: iflt -> 184
/*     */     //   171: if_icmplt -> 218
/*     */     //   174: iload #6
/*     */     //   176: lload_3
/*     */     //   177: lconst_0
/*     */     //   178: lcmp
/*     */     //   179: ifle -> 223
/*     */     //   182: bipush #90
/*     */     //   184: aload #5
/*     */     //   186: ifnonnull -> 222
/*     */     //   189: goto -> 202
/*     */     //   192: ldc2_w 426836745038566397
/*     */     //   195: lload_3
/*     */     //   196: <illegal opcode> w : (Ljava/lang/RuntimeException;JJ)Ljava/lang/RuntimeException;
/*     */     //   201: athrow
/*     */     //   202: if_icmple -> 220
/*     */     //   205: goto -> 218
/*     */     //   208: ldc2_w 426836745038566397
/*     */     //   211: lload_3
/*     */     //   212: <illegal opcode> w : (Ljava/lang/RuntimeException;JJ)Ljava/lang/RuntimeException;
/*     */     //   217: athrow
/*     */     //   218: iconst_m1
/*     */     //   219: ireturn
/*     */     //   220: iload_1
/*     */     //   221: iconst_1
/*     */     //   222: iadd
/*     */     //   223: istore #7
/*     */     //   225: iload #7
/*     */     //   227: iload_2
/*     */     //   228: if_icmpge -> 713
/*     */     //   231: aload_0
/*     */     //   232: iload #7
/*     */     //   234: invokevirtual charAt : (I)C
/*     */     //   237: istore #8
/*     */     //   239: iload #8
/*     */     //   241: aload #5
/*     */     //   243: ifnonnull -> 714
/*     */     //   246: bipush #97
/*     */     //   248: aload #5
/*     */     //   250: ifnonnull -> 349
/*     */     //   253: goto -> 266
/*     */     //   256: ldc2_w 426836745038566397
/*     */     //   259: lload_3
/*     */     //   260: <illegal opcode> w : (Ljava/lang/RuntimeException;JJ)Ljava/lang/RuntimeException;
/*     */     //   265: athrow
/*     */     //   266: lload_3
/*     */     //   267: lconst_0
/*     */     //   268: lcmp
/*     */     //   269: iflt -> 336
/*     */     //   272: if_icmplt -> 332
/*     */     //   275: goto -> 288
/*     */     //   278: ldc2_w 426836745038566397
/*     */     //   281: lload_3
/*     */     //   282: <illegal opcode> w : (Ljava/lang/RuntimeException;JJ)Ljava/lang/RuntimeException;
/*     */     //   287: athrow
/*     */     //   288: iload #8
/*     */     //   290: bipush #122
/*     */     //   292: aload #5
/*     */     //   294: lload_3
/*     */     //   295: lconst_0
/*     */     //   296: lcmp
/*     */     //   297: ifle -> 351
/*     */     //   300: ifnonnull -> 349
/*     */     //   303: goto -> 316
/*     */     //   306: ldc2_w 426836745038566397
/*     */     //   309: lload_3
/*     */     //   310: <illegal opcode> w : (Ljava/lang/RuntimeException;JJ)Ljava/lang/RuntimeException;
/*     */     //   315: athrow
/*     */     //   316: if_icmple -> 705
/*     */     //   319: goto -> 332
/*     */     //   322: ldc2_w 426836745038566397
/*     */     //   325: lload_3
/*     */     //   326: <illegal opcode> w : (Ljava/lang/RuntimeException;JJ)Ljava/lang/RuntimeException;
/*     */     //   331: athrow
/*     */     //   332: iload #8
/*     */     //   334: bipush #65
/*     */     //   336: goto -> 349
/*     */     //   339: ldc2_w 426836745038566397
/*     */     //   342: lload_3
/*     */     //   343: <illegal opcode> w : (Ljava/lang/RuntimeException;JJ)Ljava/lang/RuntimeException;
/*     */     //   348: athrow
/*     */     //   349: aload #5
/*     */     //   351: ifnonnull -> 431
/*     */     //   354: if_icmplt -> 414
/*     */     //   357: goto -> 370
/*     */     //   360: ldc2_w 426836745038566397
/*     */     //   363: lload_3
/*     */     //   364: <illegal opcode> w : (Ljava/lang/RuntimeException;JJ)Ljava/lang/RuntimeException;
/*     */     //   369: athrow
/*     */     //   370: iload #8
/*     */     //   372: bipush #90
/*     */     //   374: aload #5
/*     */     //   376: lload_3
/*     */     //   377: lconst_0
/*     */     //   378: lcmp
/*     */     //   379: ifle -> 433
/*     */     //   382: ifnonnull -> 431
/*     */     //   385: goto -> 398
/*     */     //   388: ldc2_w 426836745038566397
/*     */     //   391: lload_3
/*     */     //   392: <illegal opcode> w : (Ljava/lang/RuntimeException;JJ)Ljava/lang/RuntimeException;
/*     */     //   397: athrow
/*     */     //   398: if_icmple -> 705
/*     */     //   401: goto -> 414
/*     */     //   404: ldc2_w 426836745038566397
/*     */     //   407: lload_3
/*     */     //   408: <illegal opcode> w : (Ljava/lang/RuntimeException;JJ)Ljava/lang/RuntimeException;
/*     */     //   413: athrow
/*     */     //   414: iload #8
/*     */     //   416: bipush #48
/*     */     //   418: goto -> 431
/*     */     //   421: ldc2_w 426836745038566397
/*     */     //   424: lload_3
/*     */     //   425: <illegal opcode> w : (Ljava/lang/RuntimeException;JJ)Ljava/lang/RuntimeException;
/*     */     //   430: athrow
/*     */     //   431: aload #5
/*     */     //   433: ifnonnull -> 513
/*     */     //   436: if_icmplt -> 496
/*     */     //   439: goto -> 452
/*     */     //   442: ldc2_w 426836745038566397
/*     */     //   445: lload_3
/*     */     //   446: <illegal opcode> w : (Ljava/lang/RuntimeException;JJ)Ljava/lang/RuntimeException;
/*     */     //   451: athrow
/*     */     //   452: iload #8
/*     */     //   454: bipush #57
/*     */     //   456: aload #5
/*     */     //   458: lload_3
/*     */     //   459: lconst_0
/*     */     //   460: lcmp
/*     */     //   461: iflt -> 515
/*     */     //   464: ifnonnull -> 513
/*     */     //   467: goto -> 480
/*     */     //   470: ldc2_w 426836745038566397
/*     */     //   473: lload_3
/*     */     //   474: <illegal opcode> w : (Ljava/lang/RuntimeException;JJ)Ljava/lang/RuntimeException;
/*     */     //   479: athrow
/*     */     //   480: if_icmple -> 705
/*     */     //   483: goto -> 496
/*     */     //   486: ldc2_w 426836745038566397
/*     */     //   489: lload_3
/*     */     //   490: <illegal opcode> w : (Ljava/lang/RuntimeException;JJ)Ljava/lang/RuntimeException;
/*     */     //   495: athrow
/*     */     //   496: iload #8
/*     */     //   498: bipush #43
/*     */     //   500: goto -> 513
/*     */     //   503: ldc2_w 426836745038566397
/*     */     //   506: lload_3
/*     */     //   507: <illegal opcode> w : (Ljava/lang/RuntimeException;JJ)Ljava/lang/RuntimeException;
/*     */     //   512: athrow
/*     */     //   513: aload #5
/*     */     //   515: lload_3
/*     */     //   516: lconst_0
/*     */     //   517: lcmp
/*     */     //   518: ifle -> 559
/*     */     //   521: ifnonnull -> 557
/*     */     //   524: if_icmpeq -> 705
/*     */     //   527: goto -> 540
/*     */     //   530: ldc2_w 426836745038566397
/*     */     //   533: lload_3
/*     */     //   534: <illegal opcode> w : (Ljava/lang/RuntimeException;JJ)Ljava/lang/RuntimeException;
/*     */     //   539: athrow
/*     */     //   540: iload #8
/*     */     //   542: bipush #45
/*     */     //   544: goto -> 557
/*     */     //   547: ldc2_w 426836745038566397
/*     */     //   550: lload_3
/*     */     //   551: <illegal opcode> w : (Ljava/lang/RuntimeException;JJ)Ljava/lang/RuntimeException;
/*     */     //   556: athrow
/*     */     //   557: aload #5
/*     */     //   559: lload_3
/*     */     //   560: lconst_0
/*     */     //   561: lcmp
/*     */     //   562: ifle -> 609
/*     */     //   565: ifnonnull -> 601
/*     */     //   568: if_icmpeq -> 705
/*     */     //   571: goto -> 584
/*     */     //   574: ldc2_w 426836745038566397
/*     */     //   577: lload_3
/*     */     //   578: <illegal opcode> w : (Ljava/lang/RuntimeException;JJ)Ljava/lang/RuntimeException;
/*     */     //   583: athrow
/*     */     //   584: iload #8
/*     */     //   586: bipush #46
/*     */     //   588: goto -> 601
/*     */     //   591: ldc2_w 426836745038566397
/*     */     //   594: lload_3
/*     */     //   595: <illegal opcode> w : (Ljava/lang/RuntimeException;JJ)Ljava/lang/RuntimeException;
/*     */     //   600: athrow
/*     */     //   601: lload_3
/*     */     //   602: lconst_0
/*     */     //   603: lcmp
/*     */     //   604: iflt -> 687
/*     */     //   607: aload #5
/*     */     //   609: ifnonnull -> 687
/*     */     //   612: if_icmpne -> 652
/*     */     //   615: goto -> 628
/*     */     //   618: ldc2_w 426836745038566397
/*     */     //   621: lload_3
/*     */     //   622: <illegal opcode> w : (Ljava/lang/RuntimeException;JJ)Ljava/lang/RuntimeException;
/*     */     //   627: athrow
/*     */     //   628: aload #5
/*     */     //   630: lload_3
/*     */     //   631: lconst_0
/*     */     //   632: lcmp
/*     */     //   633: ifle -> 710
/*     */     //   636: ifnull -> 705
/*     */     //   639: goto -> 652
/*     */     //   642: ldc2_w 426836745038566397
/*     */     //   645: lload_3
/*     */     //   646: <illegal opcode> w : (Ljava/lang/RuntimeException;JJ)Ljava/lang/RuntimeException;
/*     */     //   651: athrow
/*     */     //   652: iload #8
/*     */     //   654: aload #5
/*     */     //   656: ifnonnull -> 704
/*     */     //   659: goto -> 672
/*     */     //   662: ldc2_w 426836745038566397
/*     */     //   665: lload_3
/*     */     //   666: <illegal opcode> w : (Ljava/lang/RuntimeException;JJ)Ljava/lang/RuntimeException;
/*     */     //   671: athrow
/*     */     //   672: bipush #58
/*     */     //   674: goto -> 687
/*     */     //   677: ldc2_w 426836745038566397
/*     */     //   680: lload_3
/*     */     //   681: <illegal opcode> w : (Ljava/lang/RuntimeException;JJ)Ljava/lang/RuntimeException;
/*     */     //   686: athrow
/*     */     //   687: if_icmpne -> 703
/*     */     //   690: iload #7
/*     */     //   692: ireturn
/*     */     //   693: ldc2_w 426836745038566397
/*     */     //   696: lload_3
/*     */     //   697: <illegal opcode> w : (Ljava/lang/RuntimeException;JJ)Ljava/lang/RuntimeException;
/*     */     //   702: athrow
/*     */     //   703: iconst_m1
/*     */     //   704: ireturn
/*     */     //   705: iinc #7, 1
/*     */     //   708: aload #5
/*     */     //   710: ifnull -> 225
/*     */     //   713: iconst_m1
/*     */     //   714: ireturn
/*     */     // Line number table:
/*     */     //   Java source line number -> byte code offset
/*     */     //   #265	-> 17
/*     */     //   #318	-> 54
/*     */     //   #269	-> 61
/*     */     //   #83	-> 220
/*     */     //   #213	-> 231
/*     */     //   #4	-> 239
/*     */     //   #41	-> 628
/*     */     //   #330	-> 652
/*     */     //   #61	-> 690
/*     */     //   #162	-> 703
/*     */     //   #183	-> 705
/*     */     //   #163	-> 713
/*     */     // Exception table:
/*     */     //   from	to	target	type
/*     */     //   17	29	32	java/lang/NullPointerException
/*     */     //   25	44	44	java/lang/NullPointerException
/*     */     //   61	79	82	java/lang/NullPointerException
/*     */     //   76	101	104	java/lang/NullPointerException
/*     */     //   92	117	120	java/lang/NullPointerException
/*     */     //   114	137	140	java/lang/NullPointerException
/*     */     //   130	152	155	java/lang/NullPointerException
/*     */     //   165	189	192	java/lang/NullPointerException
/*     */     //   174	205	208	java/lang/NullPointerException
/*     */     //   239	253	256	java/lang/NullPointerException
/*     */     //   246	275	278	java/lang/NullPointerException
/*     */     //   266	303	306	java/lang/NullPointerException
/*     */     //   288	319	322	java/lang/NullPointerException
/*     */     //   316	336	339	java/lang/NullPointerException
/*     */     //   349	357	360	java/lang/NullPointerException
/*     */     //   354	385	388	java/lang/NullPointerException
/*     */     //   370	401	404	java/lang/NullPointerException
/*     */     //   398	418	421	java/lang/NullPointerException
/*     */     //   431	439	442	java/lang/NullPointerException
/*     */     //   436	467	470	java/lang/NullPointerException
/*     */     //   452	483	486	java/lang/NullPointerException
/*     */     //   480	500	503	java/lang/NullPointerException
/*     */     //   513	527	530	java/lang/NullPointerException
/*     */     //   524	544	547	java/lang/NullPointerException
/*     */     //   557	571	574	java/lang/NullPointerException
/*     */     //   568	588	591	java/lang/NullPointerException
/*     */     //   601	615	618	java/lang/NullPointerException
/*     */     //   612	639	642	java/lang/NullPointerException
/*     */     //   628	659	662	java/lang/NullPointerException
/*     */     //   652	674	677	java/lang/NullPointerException
/*     */     //   687	693	693	java/lang/NullPointerException
/*     */   }
/*     */   
/*     */   private void a(String paramString, long paramLong, int paramInt1, int paramInt2) {
/*     */     // Byte code:
/*     */     //   0: getstatic me/konsolas/aac/j5.j : J
/*     */     //   3: lload_2
/*     */     //   4: lxor
/*     */     //   5: lstore_2
/*     */     //   6: lload_2
/*     */     //   7: dup2
/*     */     //   8: ldc2_w 115727636731161
/*     */     //   11: lxor
/*     */     //   12: lstore #6
/*     */     //   14: dup2
/*     */     //   15: ldc2_w 117983088666507
/*     */     //   18: lxor
/*     */     //   19: lstore #8
/*     */     //   21: pop2
/*     */     //   22: ldc2_w 5892329627708903687
/*     */     //   25: lload_2
/*     */     //   26: <illegal opcode> w : (JJ)[Lme/konsolas/aac/aN;
/*     */     //   31: astore #10
/*     */     //   33: iload #4
/*     */     //   35: aload #10
/*     */     //   37: ifnonnull -> 75
/*     */     //   40: iload #5
/*     */     //   42: if_icmpne -> 69
/*     */     //   45: goto -> 58
/*     */     //   48: ldc2_w 5903416705461569532
/*     */     //   51: lload_2
/*     */     //   52: <illegal opcode> w : (Ljava/lang/RuntimeException;JJ)Ljava/lang/RuntimeException;
/*     */     //   57: athrow
/*     */     //   58: return
/*     */     //   59: ldc2_w 5903416705461569532
/*     */     //   62: lload_2
/*     */     //   63: <illegal opcode> w : (Ljava/lang/RuntimeException;JJ)Ljava/lang/RuntimeException;
/*     */     //   68: athrow
/*     */     //   69: aload_1
/*     */     //   70: iload #4
/*     */     //   72: invokevirtual charAt : (I)C
/*     */     //   75: istore #11
/*     */     //   77: iload #11
/*     */     //   79: aload #10
/*     */     //   81: ifnonnull -> 179
/*     */     //   84: bipush #47
/*     */     //   86: if_icmpeq -> 146
/*     */     //   89: goto -> 102
/*     */     //   92: ldc2_w 5903416705461569532
/*     */     //   95: lload_2
/*     */     //   96: <illegal opcode> w : (Ljava/lang/RuntimeException;JJ)Ljava/lang/RuntimeException;
/*     */     //   101: athrow
/*     */     //   102: iload #11
/*     */     //   104: lload_2
/*     */     //   105: lconst_0
/*     */     //   106: lcmp
/*     */     //   107: ifle -> 179
/*     */     //   110: aload #10
/*     */     //   112: ifnonnull -> 179
/*     */     //   115: goto -> 128
/*     */     //   118: ldc2_w 5903416705461569532
/*     */     //   121: lload_2
/*     */     //   122: <illegal opcode> w : (Ljava/lang/RuntimeException;JJ)Ljava/lang/RuntimeException;
/*     */     //   127: athrow
/*     */     //   128: bipush #92
/*     */     //   130: if_icmpne -> 194
/*     */     //   133: goto -> 146
/*     */     //   136: ldc2_w 5903416705461569532
/*     */     //   139: lload_2
/*     */     //   140: <illegal opcode> w : (Ljava/lang/RuntimeException;JJ)Ljava/lang/RuntimeException;
/*     */     //   145: athrow
/*     */     //   146: aload_0
/*     */     //   147: getfield i : Ljava/util/List;
/*     */     //   150: invokeinterface clear : ()V
/*     */     //   155: aload_0
/*     */     //   156: getfield i : Ljava/util/List;
/*     */     //   159: ldc ''
/*     */     //   161: invokeinterface add : (Ljava/lang/Object;)Z
/*     */     //   166: goto -> 179
/*     */     //   169: ldc2_w 5903416705461569532
/*     */     //   172: lload_2
/*     */     //   173: <illegal opcode> w : (Ljava/lang/RuntimeException;JJ)Ljava/lang/RuntimeException;
/*     */     //   178: athrow
/*     */     //   179: lload_2
/*     */     //   180: lconst_0
/*     */     //   181: lcmp
/*     */     //   182: ifle -> 232
/*     */     //   185: pop
/*     */     //   186: iinc #4, 1
/*     */     //   189: aload #10
/*     */     //   191: ifnull -> 230
/*     */     //   194: aload_0
/*     */     //   195: getfield i : Ljava/util/List;
/*     */     //   198: aload_0
/*     */     //   199: getfield i : Ljava/util/List;
/*     */     //   202: invokeinterface size : ()I
/*     */     //   207: iconst_1
/*     */     //   208: isub
/*     */     //   209: ldc ''
/*     */     //   211: invokeinterface set : (ILjava/lang/Object;)Ljava/lang/Object;
/*     */     //   216: pop
/*     */     //   217: goto -> 230
/*     */     //   220: ldc2_w 5903416705461569532
/*     */     //   223: lload_2
/*     */     //   224: <illegal opcode> w : (Ljava/lang/RuntimeException;JJ)Ljava/lang/RuntimeException;
/*     */     //   229: athrow
/*     */     //   230: iload #4
/*     */     //   232: istore #12
/*     */     //   234: iload #12
/*     */     //   236: iload #5
/*     */     //   238: if_icmpge -> 361
/*     */     //   241: lload #6
/*     */     //   243: aload_1
/*     */     //   244: iload #12
/*     */     //   246: iload #5
/*     */     //   248: sipush #24537
/*     */     //   251: ldc2_w 313865161558916607
/*     */     //   254: lload_2
/*     */     //   255: lxor
/*     */     //   256: <illegal opcode> c : (IJ)Ljava/lang/String;
/*     */     //   261: invokestatic a : (JLjava/lang/String;IILjava/lang/String;)I
/*     */     //   264: istore #13
/*     */     //   266: iload #13
/*     */     //   268: aload #10
/*     */     //   270: ifnonnull -> 305
/*     */     //   273: iload #5
/*     */     //   275: if_icmpge -> 308
/*     */     //   278: goto -> 291
/*     */     //   281: ldc2_w 5903416705461569532
/*     */     //   284: lload_2
/*     */     //   285: <illegal opcode> w : (Ljava/lang/RuntimeException;JJ)Ljava/lang/RuntimeException;
/*     */     //   290: athrow
/*     */     //   291: iconst_1
/*     */     //   292: goto -> 305
/*     */     //   295: ldc2_w 5903416705461569532
/*     */     //   298: lload_2
/*     */     //   299: <illegal opcode> w : (Ljava/lang/RuntimeException;JJ)Ljava/lang/RuntimeException;
/*     */     //   304: athrow
/*     */     //   305: goto -> 309
/*     */     //   308: iconst_0
/*     */     //   309: istore #14
/*     */     //   311: aload_0
/*     */     //   312: aload_1
/*     */     //   313: iload #12
/*     */     //   315: iload #13
/*     */     //   317: iload #14
/*     */     //   319: iconst_1
/*     */     //   320: lload #8
/*     */     //   322: invokespecial a : (Ljava/lang/String;IIZZJ)V
/*     */     //   325: iload #13
/*     */     //   327: istore #12
/*     */     //   329: lload_2
/*     */     //   330: lconst_0
/*     */     //   331: lcmp
/*     */     //   332: ifle -> 343
/*     */     //   335: iload #14
/*     */     //   337: ifeq -> 356
/*     */     //   340: iinc #12, 1
/*     */     //   343: goto -> 356
/*     */     //   346: ldc2_w 5903416705461569532
/*     */     //   349: lload_2
/*     */     //   350: <illegal opcode> w : (Ljava/lang/RuntimeException;JJ)Ljava/lang/RuntimeException;
/*     */     //   355: athrow
/*     */     //   356: aload #10
/*     */     //   358: ifnull -> 234
/*     */     //   361: return
/*     */     // Line number table:
/*     */     //   Java source line number -> byte code offset
/*     */     //   #268	-> 33
/*     */     //   #262	-> 58
/*     */     //   #77	-> 69
/*     */     //   #71	-> 77
/*     */     //   #236	-> 146
/*     */     //   #253	-> 155
/*     */     //   #191	-> 186
/*     */     //   #222	-> 194
/*     */     //   #315	-> 230
/*     */     //   #296	-> 241
/*     */     //   #180	-> 266
/*     */     //   #288	-> 311
/*     */     //   #89	-> 325
/*     */     //   #164	-> 329
/*     */     //   #8	-> 356
/*     */     //   #3	-> 361
/*     */     // Exception table:
/*     */     //   from	to	target	type
/*     */     //   33	45	48	java/lang/NullPointerException
/*     */     //   40	59	59	java/lang/NullPointerException
/*     */     //   77	89	92	java/lang/NullPointerException
/*     */     //   84	115	118	java/lang/NullPointerException
/*     */     //   102	133	136	java/lang/NullPointerException
/*     */     //   128	166	169	java/lang/NullPointerException
/*     */     //   179	217	220	java/lang/NullPointerException
/*     */     //   266	278	281	java/lang/NullPointerException
/*     */     //   273	292	295	java/lang/NullPointerException
/*     */     //   329	343	346	java/lang/NullPointerException
/*     */   }
/*     */   
/*     */   private static int c(long paramLong, String paramString, int paramInt1, int paramInt2) {
/*     */     // Byte code:
/*     */     //   0: getstatic me/konsolas/aac/j5.j : J
/*     */     //   3: lload_0
/*     */     //   4: lxor
/*     */     //   5: lstore_0
/*     */     //   6: ldc2_w 4682482255585034297
/*     */     //   9: lload_0
/*     */     //   10: <illegal opcode> w : (JJ)[Lme/konsolas/aac/aN;
/*     */     //   15: iconst_0
/*     */     //   16: istore #6
/*     */     //   18: astore #5
/*     */     //   20: iload_3
/*     */     //   21: iload #4
/*     */     //   23: if_icmpge -> 144
/*     */     //   26: aload_2
/*     */     //   27: iload_3
/*     */     //   28: invokevirtual charAt : (I)C
/*     */     //   31: istore #7
/*     */     //   33: aload #5
/*     */     //   35: lload_0
/*     */     //   36: lconst_0
/*     */     //   37: lcmp
/*     */     //   38: iflt -> 141
/*     */     //   41: ifnonnull -> 139
/*     */     //   44: iload #7
/*     */     //   46: aload #5
/*     */     //   48: ifnonnull -> 146
/*     */     //   51: goto -> 64
/*     */     //   54: ldc2_w 4671183246527747778
/*     */     //   57: lload_0
/*     */     //   58: <illegal opcode> w : (Ljava/lang/RuntimeException;JJ)Ljava/lang/RuntimeException;
/*     */     //   63: athrow
/*     */     //   64: bipush #92
/*     */     //   66: if_icmpeq -> 120
/*     */     //   69: goto -> 82
/*     */     //   72: ldc2_w 4671183246527747778
/*     */     //   75: lload_0
/*     */     //   76: <illegal opcode> w : (Ljava/lang/RuntimeException;JJ)Ljava/lang/RuntimeException;
/*     */     //   81: athrow
/*     */     //   82: iload #7
/*     */     //   84: aload #5
/*     */     //   86: ifnonnull -> 146
/*     */     //   89: goto -> 102
/*     */     //   92: ldc2_w 4671183246527747778
/*     */     //   95: lload_0
/*     */     //   96: <illegal opcode> w : (Ljava/lang/RuntimeException;JJ)Ljava/lang/RuntimeException;
/*     */     //   101: athrow
/*     */     //   102: bipush #47
/*     */     //   104: if_icmpne -> 144
/*     */     //   107: goto -> 120
/*     */     //   110: ldc2_w 4671183246527747778
/*     */     //   113: lload_0
/*     */     //   114: <illegal opcode> w : (Ljava/lang/RuntimeException;JJ)Ljava/lang/RuntimeException;
/*     */     //   119: athrow
/*     */     //   120: iinc #6, 1
/*     */     //   123: iinc #3, 1
/*     */     //   126: goto -> 139
/*     */     //   129: ldc2_w 4671183246527747778
/*     */     //   132: lload_0
/*     */     //   133: <illegal opcode> w : (Ljava/lang/RuntimeException;JJ)Ljava/lang/RuntimeException;
/*     */     //   138: athrow
/*     */     //   139: aload #5
/*     */     //   141: ifnull -> 20
/*     */     //   144: iload #6
/*     */     //   146: ireturn
/*     */     // Line number table:
/*     */     //   Java source line number -> byte code offset
/*     */     //   #270	-> 15
/*     */     //   #310	-> 20
/*     */     //   #35	-> 26
/*     */     //   #322	-> 33
/*     */     //   #215	-> 120
/*     */     //   #119	-> 123
/*     */     //   #16	-> 139
/*     */     //   #216	-> 144
/*     */     // Exception table:
/*     */     //   from	to	target	type
/*     */     //   33	51	54	java/lang/NullPointerException
/*     */     //   44	69	72	java/lang/NullPointerException
/*     */     //   64	89	92	java/lang/NullPointerException
/*     */     //   82	107	110	java/lang/NullPointerException
/*     */     //   102	126	129	java/lang/NullPointerException
/*     */   }
/*     */   
/*     */   j5 a(@Nullable l6 paraml6, long paramLong, String paramString) {
/*     */     // Byte code:
/*     */     //   0: getstatic me/konsolas/aac/j5.j : J
/*     */     //   3: lload_2
/*     */     //   4: lxor
/*     */     //   5: lstore_2
/*     */     //   6: lload_2
/*     */     //   7: dup2
/*     */     //   8: ldc2_w 140181144769804
/*     */     //   11: lxor
/*     */     //   12: lstore #5
/*     */     //   14: dup2
/*     */     //   15: ldc2_w 1004352119003
/*     */     //   18: lxor
/*     */     //   19: lstore #7
/*     */     //   21: dup2
/*     */     //   22: ldc2_w 128145564744871
/*     */     //   25: lxor
/*     */     //   26: lstore #9
/*     */     //   28: dup2
/*     */     //   29: ldc2_w 33405315386722
/*     */     //   32: lxor
/*     */     //   33: dup2
/*     */     //   34: bipush #32
/*     */     //   36: lushr
/*     */     //   37: l2i
/*     */     //   38: istore #11
/*     */     //   40: dup2
/*     */     //   41: bipush #32
/*     */     //   43: lshl
/*     */     //   44: bipush #32
/*     */     //   46: lushr
/*     */     //   47: lstore #12
/*     */     //   49: pop2
/*     */     //   50: dup2
/*     */     //   51: ldc2_w 11805244472514
/*     */     //   54: lxor
/*     */     //   55: dup2
/*     */     //   56: bipush #56
/*     */     //   58: lushr
/*     */     //   59: l2i
/*     */     //   60: istore #14
/*     */     //   62: dup2
/*     */     //   63: bipush #8
/*     */     //   65: lshl
/*     */     //   66: bipush #32
/*     */     //   68: lushr
/*     */     //   69: l2i
/*     */     //   70: istore #15
/*     */     //   72: dup2
/*     */     //   73: bipush #40
/*     */     //   75: lshl
/*     */     //   76: bipush #40
/*     */     //   78: lushr
/*     */     //   79: l2i
/*     */     //   80: istore #16
/*     */     //   82: pop2
/*     */     //   83: dup2
/*     */     //   84: ldc2_w 126261440008243
/*     */     //   87: lxor
/*     */     //   88: lstore #17
/*     */     //   90: dup2
/*     */     //   91: ldc2_w 93472519078846
/*     */     //   94: lxor
/*     */     //   95: dup2
/*     */     //   96: bipush #32
/*     */     //   98: lushr
/*     */     //   99: l2i
/*     */     //   100: istore #19
/*     */     //   102: dup2
/*     */     //   103: bipush #32
/*     */     //   105: lshl
/*     */     //   106: bipush #48
/*     */     //   108: lushr
/*     */     //   109: l2i
/*     */     //   110: istore #20
/*     */     //   112: dup2
/*     */     //   113: bipush #48
/*     */     //   115: lshl
/*     */     //   116: bipush #48
/*     */     //   118: lushr
/*     */     //   119: l2i
/*     */     //   120: istore #21
/*     */     //   122: pop2
/*     */     //   123: dup2
/*     */     //   124: ldc2_w 100043328349734
/*     */     //   127: lxor
/*     */     //   128: lstore #22
/*     */     //   130: dup2
/*     */     //   131: ldc2_w 72387675530136
/*     */     //   134: lxor
/*     */     //   135: lstore #24
/*     */     //   137: dup2
/*     */     //   138: ldc2_w 135767955794772
/*     */     //   141: lxor
/*     */     //   142: lstore #26
/*     */     //   144: dup2
/*     */     //   145: ldc2_w 84049836831285
/*     */     //   148: lxor
/*     */     //   149: dup2
/*     */     //   150: bipush #48
/*     */     //   152: lushr
/*     */     //   153: l2i
/*     */     //   154: istore #28
/*     */     //   156: dup2
/*     */     //   157: bipush #16
/*     */     //   159: lshl
/*     */     //   160: bipush #16
/*     */     //   162: lushr
/*     */     //   163: lstore #29
/*     */     //   165: pop2
/*     */     //   166: dup2
/*     */     //   167: ldc2_w 5730513918103
/*     */     //   170: lxor
/*     */     //   171: lstore #31
/*     */     //   173: dup2
/*     */     //   174: ldc2_w 79202848852021
/*     */     //   177: lxor
/*     */     //   178: dup2
/*     */     //   179: bipush #32
/*     */     //   181: lushr
/*     */     //   182: l2i
/*     */     //   183: istore #33
/*     */     //   185: dup2
/*     */     //   186: bipush #32
/*     */     //   188: lshl
/*     */     //   189: bipush #32
/*     */     //   191: lushr
/*     */     //   192: l2i
/*     */     //   193: istore #34
/*     */     //   195: pop2
/*     */     //   196: dup2
/*     */     //   197: ldc2_w 62813216736306
/*     */     //   200: lxor
/*     */     //   201: lstore #35
/*     */     //   203: dup2
/*     */     //   204: ldc2_w 110881083142877
/*     */     //   207: lxor
/*     */     //   208: lstore #37
/*     */     //   210: dup2
/*     */     //   211: ldc2_w 113120562218087
/*     */     //   214: lxor
/*     */     //   215: lstore #39
/*     */     //   217: dup2
/*     */     //   218: ldc2_w 64691083636575
/*     */     //   221: lxor
/*     */     //   222: lstore #41
/*     */     //   224: dup2
/*     */     //   225: ldc2_w 139774755940998
/*     */     //   228: lxor
/*     */     //   229: lstore #43
/*     */     //   231: pop2
/*     */     //   232: ldc2_w -2015454038338181947
/*     */     //   235: lload_2
/*     */     //   236: <illegal opcode> w : (JJ)[Lme/konsolas/aac/aN;
/*     */     //   241: aload #4
/*     */     //   243: lload #39
/*     */     //   245: iconst_0
/*     */     //   246: aload #4
/*     */     //   248: invokevirtual length : ()I
/*     */     //   251: invokestatic a : (Ljava/lang/String;JII)I
/*     */     //   254: istore #46
/*     */     //   256: astore #45
/*     */     //   258: aload #4
/*     */     //   260: iload #14
/*     */     //   262: i2b
/*     */     //   263: iload #46
/*     */     //   265: aload #4
/*     */     //   267: invokevirtual length : ()I
/*     */     //   270: iload #15
/*     */     //   272: iload #16
/*     */     //   274: invokestatic b : (Ljava/lang/String;BIIII)I
/*     */     //   277: istore #47
/*     */     //   279: aload #4
/*     */     //   281: iload #46
/*     */     //   283: iload #47
/*     */     //   285: lload #17
/*     */     //   287: invokestatic a : (Ljava/lang/String;IIJ)I
/*     */     //   290: istore #48
/*     */     //   292: iload #48
/*     */     //   294: aload #45
/*     */     //   296: ifnonnull -> 353
/*     */     //   299: iconst_m1
/*     */     //   300: if_icmpeq -> 625
/*     */     //   303: goto -> 316
/*     */     //   306: ldc2_w -2004295767480307138
/*     */     //   309: lload_2
/*     */     //   310: <illegal opcode> w : (Ljava/lang/RuntimeException;JJ)Ljava/lang/RuntimeException;
/*     */     //   315: athrow
/*     */     //   316: aload #4
/*     */     //   318: iconst_1
/*     */     //   319: iload #46
/*     */     //   321: sipush #23777
/*     */     //   324: ldc2_w 8999951470233570057
/*     */     //   327: lload_2
/*     */     //   328: lxor
/*     */     //   329: <illegal opcode> c : (IJ)Ljava/lang/String;
/*     */     //   334: iconst_0
/*     */     //   335: bipush #6
/*     */     //   337: invokevirtual regionMatches : (ZILjava/lang/String;II)Z
/*     */     //   340: goto -> 353
/*     */     //   343: ldc2_w -2004295767480307138
/*     */     //   346: lload_2
/*     */     //   347: <illegal opcode> w : (Ljava/lang/RuntimeException;JJ)Ljava/lang/RuntimeException;
/*     */     //   352: athrow
/*     */     //   353: aload #45
/*     */     //   355: lload_2
/*     */     //   356: lconst_0
/*     */     //   357: lcmp
/*     */     //   358: ifle -> 467
/*     */     //   361: ifnonnull -> 465
/*     */     //   364: ifeq -> 429
/*     */     //   367: goto -> 380
/*     */     //   370: ldc2_w -2004295767480307138
/*     */     //   373: lload_2
/*     */     //   374: <illegal opcode> w : (Ljava/lang/RuntimeException;JJ)Ljava/lang/RuntimeException;
/*     */     //   379: athrow
/*     */     //   380: aload_0
/*     */     //   381: sipush #24884
/*     */     //   384: ldc2_w 4532679144107538118
/*     */     //   387: lload_2
/*     */     //   388: lxor
/*     */     //   389: <illegal opcode> c : (IJ)Ljava/lang/String;
/*     */     //   394: putfield c : Ljava/lang/String;
/*     */     //   397: iload #46
/*     */     //   399: sipush #14693
/*     */     //   402: ldc2_w 8281462902501912242
/*     */     //   405: lload_2
/*     */     //   406: lxor
/*     */     //   407: <illegal opcode> c : (IJ)Ljava/lang/String;
/*     */     //   412: invokevirtual length : ()I
/*     */     //   415: iadd
/*     */     //   416: lload_2
/*     */     //   417: lconst_0
/*     */     //   418: lcmp
/*     */     //   419: ifle -> 693
/*     */     //   422: istore #46
/*     */     //   424: aload #45
/*     */     //   426: ifnull -> 692
/*     */     //   429: aload #4
/*     */     //   431: iconst_1
/*     */     //   432: iload #46
/*     */     //   434: sipush #12951
/*     */     //   437: ldc2_w 1232933437190088018
/*     */     //   440: lload_2
/*     */     //   441: lxor
/*     */     //   442: <illegal opcode> c : (IJ)Ljava/lang/String;
/*     */     //   447: iconst_0
/*     */     //   448: iconst_5
/*     */     //   449: invokevirtual regionMatches : (ZILjava/lang/String;II)Z
/*     */     //   452: goto -> 465
/*     */     //   455: ldc2_w -2004295767480307138
/*     */     //   458: lload_2
/*     */     //   459: <illegal opcode> w : (Ljava/lang/RuntimeException;JJ)Ljava/lang/RuntimeException;
/*     */     //   464: athrow
/*     */     //   465: aload #45
/*     */     //   467: ifnonnull -> 535
/*     */     //   470: ifeq -> 542
/*     */     //   473: goto -> 486
/*     */     //   476: ldc2_w -2004295767480307138
/*     */     //   479: lload_2
/*     */     //   480: <illegal opcode> w : (Ljava/lang/RuntimeException;JJ)Ljava/lang/RuntimeException;
/*     */     //   485: athrow
/*     */     //   486: aload_0
/*     */     //   487: sipush #12480
/*     */     //   490: ldc2_w 7891763099422074673
/*     */     //   493: lload_2
/*     */     //   494: lxor
/*     */     //   495: <illegal opcode> c : (IJ)Ljava/lang/String;
/*     */     //   500: putfield c : Ljava/lang/String;
/*     */     //   503: iload #46
/*     */     //   505: sipush #10339
/*     */     //   508: ldc2_w 1390447194558807946
/*     */     //   511: lload_2
/*     */     //   512: lxor
/*     */     //   513: <illegal opcode> c : (IJ)Ljava/lang/String;
/*     */     //   518: invokevirtual length : ()I
/*     */     //   521: iadd
/*     */     //   522: goto -> 535
/*     */     //   525: ldc2_w -2004295767480307138
/*     */     //   528: lload_2
/*     */     //   529: <illegal opcode> w : (Ljava/lang/RuntimeException;JJ)Ljava/lang/RuntimeException;
/*     */     //   534: athrow
/*     */     //   535: istore #46
/*     */     //   537: aload #45
/*     */     //   539: ifnull -> 692
/*     */     //   542: new java/lang/IllegalArgumentException
/*     */     //   545: dup
/*     */     //   546: new java/lang/StringBuilder
/*     */     //   549: dup
/*     */     //   550: invokespecial <init> : ()V
/*     */     //   553: sipush #9691
/*     */     //   556: ldc2_w 196733905010078267
/*     */     //   559: lload_2
/*     */     //   560: lxor
/*     */     //   561: <illegal opcode> c : (IJ)Ljava/lang/String;
/*     */     //   566: invokevirtual append : (Ljava/lang/String;)Ljava/lang/StringBuilder;
/*     */     //   569: aload #4
/*     */     //   571: iconst_0
/*     */     //   572: iload #48
/*     */     //   574: invokevirtual substring : (II)Ljava/lang/String;
/*     */     //   577: invokevirtual append : (Ljava/lang/String;)Ljava/lang/StringBuilder;
/*     */     //   580: ldc_w '믉᫡'
/*     */     //   583: invokevirtual toCharArray : ()[C
/*     */     //   586: dup
/*     */     //   587: dup
/*     */     //   588: iconst_0
/*     */     //   589: dup_x1
/*     */     //   590: caload
/*     */     //   591: sipush #5622
/*     */     //   594: ixor
/*     */     //   595: i2c
/*     */     //   596: castore
/*     */     //   597: sipush #32549
/*     */     //   600: iconst_1
/*     */     //   601: iconst_1
/*     */     //   602: invokestatic U : (Ljava/lang/Object;SZZ)Ljava/lang/String;
/*     */     //   605: invokevirtual append : (Ljava/lang/String;)Ljava/lang/StringBuilder;
/*     */     //   608: invokevirtual toString : ()Ljava/lang/String;
/*     */     //   611: invokespecial <init> : (Ljava/lang/String;)V
/*     */     //   614: athrow
/*     */     //   615: ldc2_w -2004295767480307138
/*     */     //   618: lload_2
/*     */     //   619: <illegal opcode> w : (Ljava/lang/RuntimeException;JJ)Ljava/lang/RuntimeException;
/*     */     //   624: athrow
/*     */     //   625: lload_2
/*     */     //   626: lconst_0
/*     */     //   627: lcmp
/*     */     //   628: iflt -> 643
/*     */     //   631: aload_1
/*     */     //   632: ifnull -> 661
/*     */     //   635: aload_0
/*     */     //   636: aload_1
/*     */     //   637: getfield m : Ljava/lang/String;
/*     */     //   640: putfield c : Ljava/lang/String;
/*     */     //   643: aload #45
/*     */     //   645: ifnull -> 692
/*     */     //   648: goto -> 661
/*     */     //   651: ldc2_w -2004295767480307138
/*     */     //   654: lload_2
/*     */     //   655: <illegal opcode> w : (Ljava/lang/RuntimeException;JJ)Ljava/lang/RuntimeException;
/*     */     //   660: athrow
/*     */     //   661: new java/lang/IllegalArgumentException
/*     */     //   664: dup
/*     */     //   665: sipush #6687
/*     */     //   668: ldc2_w 2679928145295609285
/*     */     //   671: lload_2
/*     */     //   672: lxor
/*     */     //   673: <illegal opcode> c : (IJ)Ljava/lang/String;
/*     */     //   678: invokespecial <init> : (Ljava/lang/String;)V
/*     */     //   681: athrow
/*     */     //   682: ldc2_w -2004295767480307138
/*     */     //   685: lload_2
/*     */     //   686: <illegal opcode> w : (Ljava/lang/RuntimeException;JJ)Ljava/lang/RuntimeException;
/*     */     //   691: athrow
/*     */     //   692: iconst_0
/*     */     //   693: istore #49
/*     */     //   695: iconst_0
/*     */     //   696: istore #50
/*     */     //   698: lload #5
/*     */     //   700: aload #4
/*     */     //   702: iload #46
/*     */     //   704: iload #47
/*     */     //   706: invokestatic c : (JLjava/lang/String;II)I
/*     */     //   709: istore #51
/*     */     //   711: iload #51
/*     */     //   713: lload_2
/*     */     //   714: lconst_0
/*     */     //   715: lcmp
/*     */     //   716: iflt -> 838
/*     */     //   719: iconst_2
/*     */     //   720: aload #45
/*     */     //   722: ifnonnull -> 837
/*     */     //   725: if_icmpge -> 820
/*     */     //   728: goto -> 741
/*     */     //   731: ldc2_w -2004295767480307138
/*     */     //   734: lload_2
/*     */     //   735: <illegal opcode> w : (Ljava/lang/RuntimeException;JJ)Ljava/lang/RuntimeException;
/*     */     //   740: athrow
/*     */     //   741: aload_1
/*     */     //   742: lload_2
/*     */     //   743: lconst_0
/*     */     //   744: lcmp
/*     */     //   745: ifle -> 783
/*     */     //   748: aload #45
/*     */     //   750: ifnonnull -> 783
/*     */     //   753: goto -> 766
/*     */     //   756: ldc2_w -2004295767480307138
/*     */     //   759: lload_2
/*     */     //   760: <illegal opcode> w : (Ljava/lang/RuntimeException;JJ)Ljava/lang/RuntimeException;
/*     */     //   765: athrow
/*     */     //   766: ifnull -> 820
/*     */     //   769: goto -> 782
/*     */     //   772: ldc2_w -2004295767480307138
/*     */     //   775: lload_2
/*     */     //   776: <illegal opcode> w : (Ljava/lang/RuntimeException;JJ)Ljava/lang/RuntimeException;
/*     */     //   781: athrow
/*     */     //   782: aload_1
/*     */     //   783: getfield m : Ljava/lang/String;
/*     */     //   786: aload_0
/*     */     //   787: getfield c : Ljava/lang/String;
/*     */     //   790: invokevirtual equals : (Ljava/lang/Object;)Z
/*     */     //   793: lload_2
/*     */     //   794: lconst_0
/*     */     //   795: lcmp
/*     */     //   796: iflt -> 1719
/*     */     //   799: aload #45
/*     */     //   801: ifnonnull -> 1719
/*     */     //   804: ifne -> 1632
/*     */     //   807: goto -> 820
/*     */     //   810: ldc2_w -2004295767480307138
/*     */     //   813: lload_2
/*     */     //   814: <illegal opcode> w : (Ljava/lang/RuntimeException;JJ)Ljava/lang/RuntimeException;
/*     */     //   819: athrow
/*     */     //   820: iload #46
/*     */     //   822: iload #51
/*     */     //   824: goto -> 837
/*     */     //   827: ldc2_w -2004295767480307138
/*     */     //   830: lload_2
/*     */     //   831: <illegal opcode> w : (Ljava/lang/RuntimeException;JJ)Ljava/lang/RuntimeException;
/*     */     //   836: athrow
/*     */     //   837: iadd
/*     */     //   838: istore #46
/*     */     //   840: lload #7
/*     */     //   842: aload #4
/*     */     //   844: iload #46
/*     */     //   846: iload #47
/*     */     //   848: sipush #557
/*     */     //   851: ldc2_w 6481370373220177377
/*     */     //   854: lload_2
/*     */     //   855: lxor
/*     */     //   856: <illegal opcode> c : (IJ)Ljava/lang/String;
/*     */     //   861: invokestatic a : (JLjava/lang/String;IILjava/lang/String;)I
/*     */     //   864: istore #52
/*     */     //   866: iload #52
/*     */     //   868: iload #47
/*     */     //   870: if_icmpeq -> 898
/*     */     //   873: aload #4
/*     */     //   875: iload #52
/*     */     //   877: invokevirtual charAt : (I)C
/*     */     //   880: aload #45
/*     */     //   882: ifnonnull -> 899
/*     */     //   885: goto -> 899
/*     */     //   888: ldc2_w -2004295767480307138
/*     */     //   891: lload_2
/*     */     //   892: <illegal opcode> w : (Ljava/lang/RuntimeException;JJ)Ljava/lang/RuntimeException;
/*     */     //   897: athrow
/*     */     //   898: iconst_m1
/*     */     //   899: istore #53
/*     */     //   901: iload #53
/*     */     //   903: aload #45
/*     */     //   905: lload_2
/*     */     //   906: lconst_0
/*     */     //   907: lcmp
/*     */     //   908: ifle -> 986
/*     */     //   911: ifnonnull -> 984
/*     */     //   914: lookupswitch default -> 1608, -1 -> 1314, 35 -> 1314, 47 -> 1314, 63 -> 1314, 64 -> 982, 92 -> 1314
/*     */     //   972: ldc2_w -2004295767480307138
/*     */     //   975: lload_2
/*     */     //   976: <illegal opcode> w : (Ljava/lang/RuntimeException;JJ)Ljava/lang/RuntimeException;
/*     */     //   981: athrow
/*     */     //   982: iload #50
/*     */     //   984: aload #45
/*     */     //   986: ifnonnull -> 1031
/*     */     //   989: ifne -> 1213
/*     */     //   992: goto -> 1005
/*     */     //   995: ldc2_w -2004295767480307138
/*     */     //   998: lload_2
/*     */     //   999: <illegal opcode> w : (Ljava/lang/RuntimeException;JJ)Ljava/lang/RuntimeException;
/*     */     //   1004: athrow
/*     */     //   1005: aload #4
/*     */     //   1007: iload #46
/*     */     //   1009: lload #41
/*     */     //   1011: iload #52
/*     */     //   1013: bipush #58
/*     */     //   1015: invokestatic a : (Ljava/lang/String;IJIC)I
/*     */     //   1018: goto -> 1031
/*     */     //   1021: ldc2_w -2004295767480307138
/*     */     //   1024: lload_2
/*     */     //   1025: <illegal opcode> w : (Ljava/lang/RuntimeException;JJ)Ljava/lang/RuntimeException;
/*     */     //   1030: athrow
/*     */     //   1031: istore #54
/*     */     //   1033: iload #11
/*     */     //   1035: aload #4
/*     */     //   1037: iload #46
/*     */     //   1039: iload #54
/*     */     //   1041: sipush #10887
/*     */     //   1044: ldc2_w 5718312742119816570
/*     */     //   1047: lload_2
/*     */     //   1048: lxor
/*     */     //   1049: <illegal opcode> c : (IJ)Ljava/lang/String;
/*     */     //   1054: iconst_1
/*     */     //   1055: iconst_0
/*     */     //   1056: iconst_0
/*     */     //   1057: iconst_1
/*     */     //   1058: aconst_null
/*     */     //   1059: lload #12
/*     */     //   1061: invokestatic a : (ILjava/lang/String;IILjava/lang/String;ZZZZLjava/nio/charset/Charset;J)Ljava/lang/String;
/*     */     //   1064: astore #55
/*     */     //   1066: aload_0
/*     */     //   1067: iload #49
/*     */     //   1069: ifeq -> 1123
/*     */     //   1072: new java/lang/StringBuilder
/*     */     //   1075: dup
/*     */     //   1076: invokespecial <init> : ()V
/*     */     //   1079: aload_0
/*     */     //   1080: getfield f : Ljava/lang/String;
/*     */     //   1083: invokevirtual append : (Ljava/lang/String;)Ljava/lang/StringBuilder;
/*     */     //   1086: sipush #443
/*     */     //   1089: ldc2_w 337557514428913272
/*     */     //   1092: lload_2
/*     */     //   1093: lxor
/*     */     //   1094: <illegal opcode> c : (IJ)Ljava/lang/String;
/*     */     //   1099: invokevirtual append : (Ljava/lang/String;)Ljava/lang/StringBuilder;
/*     */     //   1102: aload #55
/*     */     //   1104: invokevirtual append : (Ljava/lang/String;)Ljava/lang/StringBuilder;
/*     */     //   1107: invokevirtual toString : ()Ljava/lang/String;
/*     */     //   1110: goto -> 1125
/*     */     //   1113: ldc2_w -2004295767480307138
/*     */     //   1116: lload_2
/*     */     //   1117: <illegal opcode> w : (Ljava/lang/RuntimeException;JJ)Ljava/lang/RuntimeException;
/*     */     //   1122: athrow
/*     */     //   1123: aload #55
/*     */     //   1125: putfield f : Ljava/lang/String;
/*     */     //   1128: lload_2
/*     */     //   1129: lconst_0
/*     */     //   1130: lcmp
/*     */     //   1131: iflt -> 1202
/*     */     //   1134: iload #54
/*     */     //   1136: aload #45
/*     */     //   1138: ifnonnull -> 1200
/*     */     //   1141: iload #52
/*     */     //   1143: if_icmpeq -> 1199
/*     */     //   1146: goto -> 1159
/*     */     //   1149: ldc2_w -2004295767480307138
/*     */     //   1152: lload_2
/*     */     //   1153: <illegal opcode> w : (Ljava/lang/RuntimeException;JJ)Ljava/lang/RuntimeException;
/*     */     //   1158: athrow
/*     */     //   1159: iconst_1
/*     */     //   1160: istore #50
/*     */     //   1162: aload_0
/*     */     //   1163: iload #11
/*     */     //   1165: aload #4
/*     */     //   1167: iload #54
/*     */     //   1169: iconst_1
/*     */     //   1170: iadd
/*     */     //   1171: iload #52
/*     */     //   1173: sipush #4000
/*     */     //   1176: ldc2_w 2612772258817972290
/*     */     //   1179: lload_2
/*     */     //   1180: lxor
/*     */     //   1181: <illegal opcode> c : (IJ)Ljava/lang/String;
/*     */     //   1186: iconst_1
/*     */     //   1187: iconst_0
/*     */     //   1188: iconst_0
/*     */     //   1189: iconst_1
/*     */     //   1190: aconst_null
/*     */     //   1191: lload #12
/*     */     //   1193: invokestatic a : (ILjava/lang/String;IILjava/lang/String;ZZZZLjava/nio/charset/Charset;J)Ljava/lang/String;
/*     */     //   1196: putfield a : Ljava/lang/String;
/*     */     //   1199: iconst_1
/*     */     //   1200: istore #49
/*     */     //   1202: aload #45
/*     */     //   1204: lload_2
/*     */     //   1205: lconst_0
/*     */     //   1206: lcmp
/*     */     //   1207: iflt -> 1305
/*     */     //   1210: ifnull -> 1297
/*     */     //   1213: aload_0
/*     */     //   1214: new java/lang/StringBuilder
/*     */     //   1217: dup
/*     */     //   1218: invokespecial <init> : ()V
/*     */     //   1221: aload_0
/*     */     //   1222: getfield a : Ljava/lang/String;
/*     */     //   1225: invokevirtual append : (Ljava/lang/String;)Ljava/lang/StringBuilder;
/*     */     //   1228: sipush #20155
/*     */     //   1231: ldc2_w 3043769883080382808
/*     */     //   1234: lload_2
/*     */     //   1235: lxor
/*     */     //   1236: <illegal opcode> c : (IJ)Ljava/lang/String;
/*     */     //   1241: invokevirtual append : (Ljava/lang/String;)Ljava/lang/StringBuilder;
/*     */     //   1244: iload #11
/*     */     //   1246: aload #4
/*     */     //   1248: iload #46
/*     */     //   1250: iload #52
/*     */     //   1252: sipush #4000
/*     */     //   1255: ldc2_w 2612772258817972290
/*     */     //   1258: lload_2
/*     */     //   1259: lxor
/*     */     //   1260: <illegal opcode> c : (IJ)Ljava/lang/String;
/*     */     //   1265: iconst_1
/*     */     //   1266: iconst_0
/*     */     //   1267: iconst_0
/*     */     //   1268: iconst_1
/*     */     //   1269: aconst_null
/*     */     //   1270: lload #12
/*     */     //   1272: invokestatic a : (ILjava/lang/String;IILjava/lang/String;ZZZZLjava/nio/charset/Charset;J)Ljava/lang/String;
/*     */     //   1275: invokevirtual append : (Ljava/lang/String;)Ljava/lang/StringBuilder;
/*     */     //   1278: invokevirtual toString : ()Ljava/lang/String;
/*     */     //   1281: putfield a : Ljava/lang/String;
/*     */     //   1284: goto -> 1297
/*     */     //   1287: ldc2_w -2004295767480307138
/*     */     //   1290: lload_2
/*     */     //   1291: <illegal opcode> w : (Ljava/lang/RuntimeException;JJ)Ljava/lang/RuntimeException;
/*     */     //   1296: athrow
/*     */     //   1297: iload #52
/*     */     //   1299: iconst_1
/*     */     //   1300: iadd
/*     */     //   1301: istore #46
/*     */     //   1303: aload #45
/*     */     //   1305: lload_2
/*     */     //   1306: lconst_0
/*     */     //   1307: lcmp
/*     */     //   1308: iflt -> 1610
/*     */     //   1311: ifnull -> 1608
/*     */     //   1314: lload #24
/*     */     //   1316: aload #4
/*     */     //   1318: iload #46
/*     */     //   1320: iload #52
/*     */     //   1322: invokestatic d : (JLjava/lang/String;II)I
/*     */     //   1325: istore #54
/*     */     //   1327: aload #45
/*     */     //   1329: ifnonnull -> 1509
/*     */     //   1332: iload #54
/*     */     //   1334: iconst_1
/*     */     //   1335: iadd
/*     */     //   1336: iload #52
/*     */     //   1338: if_icmpge -> 1494
/*     */     //   1341: goto -> 1354
/*     */     //   1344: ldc2_w -2004295767480307138
/*     */     //   1347: lload_2
/*     */     //   1348: <illegal opcode> w : (Ljava/lang/RuntimeException;JJ)Ljava/lang/RuntimeException;
/*     */     //   1353: athrow
/*     */     //   1354: aload_0
/*     */     //   1355: lload #37
/*     */     //   1357: aload #4
/*     */     //   1359: iload #46
/*     */     //   1361: iload #54
/*     */     //   1363: invokestatic a : (JLjava/lang/String;II)Ljava/lang/String;
/*     */     //   1366: putfield g : Ljava/lang/String;
/*     */     //   1369: aload_0
/*     */     //   1370: aload #4
/*     */     //   1372: iload #54
/*     */     //   1374: iconst_1
/*     */     //   1375: iadd
/*     */     //   1376: lload #9
/*     */     //   1378: iload #52
/*     */     //   1380: invokestatic b : (Ljava/lang/String;IJI)I
/*     */     //   1383: putfield e : I
/*     */     //   1386: aload_0
/*     */     //   1387: lload_2
/*     */     //   1388: lconst_0
/*     */     //   1389: lcmp
/*     */     //   1390: ifle -> 1526
/*     */     //   1393: aload #45
/*     */     //   1395: ifnonnull -> 1526
/*     */     //   1398: goto -> 1411
/*     */     //   1401: ldc2_w -2004295767480307138
/*     */     //   1404: lload_2
/*     */     //   1405: <illegal opcode> w : (Ljava/lang/RuntimeException;JJ)Ljava/lang/RuntimeException;
/*     */     //   1410: athrow
/*     */     //   1411: getfield e : I
/*     */     //   1414: iconst_m1
/*     */     //   1415: if_icmpne -> 1525
/*     */     //   1418: goto -> 1431
/*     */     //   1421: ldc2_w -2004295767480307138
/*     */     //   1424: lload_2
/*     */     //   1425: <illegal opcode> w : (Ljava/lang/RuntimeException;JJ)Ljava/lang/RuntimeException;
/*     */     //   1430: athrow
/*     */     //   1431: new java/lang/IllegalArgumentException
/*     */     //   1434: dup
/*     */     //   1435: new java/lang/StringBuilder
/*     */     //   1438: dup
/*     */     //   1439: invokespecial <init> : ()V
/*     */     //   1442: sipush #1939
/*     */     //   1445: ldc2_w 7849249221554573403
/*     */     //   1448: lload_2
/*     */     //   1449: lxor
/*     */     //   1450: <illegal opcode> c : (IJ)Ljava/lang/String;
/*     */     //   1455: invokevirtual append : (Ljava/lang/String;)Ljava/lang/StringBuilder;
/*     */     //   1458: aload #4
/*     */     //   1460: iload #54
/*     */     //   1462: iconst_1
/*     */     //   1463: iadd
/*     */     //   1464: iload #52
/*     */     //   1466: invokevirtual substring : (II)Ljava/lang/String;
/*     */     //   1469: invokevirtual append : (Ljava/lang/String;)Ljava/lang/StringBuilder;
/*     */     //   1472: bipush #34
/*     */     //   1474: invokevirtual append : (C)Ljava/lang/StringBuilder;
/*     */     //   1477: invokevirtual toString : ()Ljava/lang/String;
/*     */     //   1480: invokespecial <init> : (Ljava/lang/String;)V
/*     */     //   1483: athrow
/*     */     //   1484: ldc2_w -2004295767480307138
/*     */     //   1487: lload_2
/*     */     //   1488: <illegal opcode> w : (Ljava/lang/RuntimeException;JJ)Ljava/lang/RuntimeException;
/*     */     //   1493: athrow
/*     */     //   1494: aload_0
/*     */     //   1495: lload #37
/*     */     //   1497: aload #4
/*     */     //   1499: iload #46
/*     */     //   1501: iload #54
/*     */     //   1503: invokestatic a : (JLjava/lang/String;II)Ljava/lang/String;
/*     */     //   1506: putfield g : Ljava/lang/String;
/*     */     //   1509: aload_0
/*     */     //   1510: aload_0
/*     */     //   1511: getfield c : Ljava/lang/String;
/*     */     //   1514: iload #28
/*     */     //   1516: i2s
/*     */     //   1517: lload #29
/*     */     //   1519: invokestatic a : (Ljava/lang/String;SJ)I
/*     */     //   1522: putfield e : I
/*     */     //   1525: aload_0
/*     */     //   1526: getfield g : Ljava/lang/String;
/*     */     //   1529: ifnonnull -> 1593
/*     */     //   1532: new java/lang/IllegalArgumentException
/*     */     //   1535: dup
/*     */     //   1536: new java/lang/StringBuilder
/*     */     //   1539: dup
/*     */     //   1540: invokespecial <init> : ()V
/*     */     //   1543: sipush #614
/*     */     //   1546: ldc2_w 4922129280378672519
/*     */     //   1549: lload_2
/*     */     //   1550: lxor
/*     */     //   1551: <illegal opcode> c : (IJ)Ljava/lang/String;
/*     */     //   1556: invokevirtual append : (Ljava/lang/String;)Ljava/lang/StringBuilder;
/*     */     //   1559: aload #4
/*     */     //   1561: iload #46
/*     */     //   1563: iload #54
/*     */     //   1565: invokevirtual substring : (II)Ljava/lang/String;
/*     */     //   1568: invokevirtual append : (Ljava/lang/String;)Ljava/lang/StringBuilder;
/*     */     //   1571: bipush #34
/*     */     //   1573: invokevirtual append : (C)Ljava/lang/StringBuilder;
/*     */     //   1576: invokevirtual toString : ()Ljava/lang/String;
/*     */     //   1579: invokespecial <init> : (Ljava/lang/String;)V
/*     */     //   1582: athrow
/*     */     //   1583: ldc2_w -2004295767480307138
/*     */     //   1586: lload_2
/*     */     //   1587: <illegal opcode> w : (Ljava/lang/RuntimeException;JJ)Ljava/lang/RuntimeException;
/*     */     //   1592: athrow
/*     */     //   1593: iload #52
/*     */     //   1595: istore #46
/*     */     //   1597: aload #45
/*     */     //   1599: lload_2
/*     */     //   1600: lconst_0
/*     */     //   1601: lcmp
/*     */     //   1602: ifle -> 1610
/*     */     //   1605: ifnull -> 1806
/*     */     //   1608: aload #45
/*     */     //   1610: ifnull -> 840
/*     */     //   1613: lload_2
/*     */     //   1614: lconst_0
/*     */     //   1615: lcmp
/*     */     //   1616: ifle -> 873
/*     */     //   1619: goto -> 1632
/*     */     //   1622: ldc2_w -2004295767480307138
/*     */     //   1625: lload_2
/*     */     //   1626: <illegal opcode> w : (Ljava/lang/RuntimeException;JJ)Ljava/lang/RuntimeException;
/*     */     //   1631: athrow
/*     */     //   1632: aload_0
/*     */     //   1633: aload_1
/*     */     //   1634: lload #43
/*     */     //   1636: invokevirtual j : (J)Ljava/lang/String;
/*     */     //   1639: putfield f : Ljava/lang/String;
/*     */     //   1642: aload_0
/*     */     //   1643: aload_1
/*     */     //   1644: lload #26
/*     */     //   1646: invokevirtual b : (J)Ljava/lang/String;
/*     */     //   1649: putfield a : Ljava/lang/String;
/*     */     //   1652: aload_0
/*     */     //   1653: aload_1
/*     */     //   1654: getfield k : Ljava/lang/String;
/*     */     //   1657: putfield g : Ljava/lang/String;
/*     */     //   1660: aload_0
/*     */     //   1661: aload_1
/*     */     //   1662: getfield s : I
/*     */     //   1665: putfield e : I
/*     */     //   1668: aload_0
/*     */     //   1669: getfield i : Ljava/util/List;
/*     */     //   1672: invokeinterface clear : ()V
/*     */     //   1677: lload_2
/*     */     //   1678: lconst_0
/*     */     //   1679: lcmp
/*     */     //   1680: ifle -> 1704
/*     */     //   1683: aload_0
/*     */     //   1684: aload #45
/*     */     //   1686: ifnonnull -> 1805
/*     */     //   1689: getfield i : Ljava/util/List;
/*     */     //   1692: aload_1
/*     */     //   1693: lload #22
/*     */     //   1695: invokevirtual a : (J)Ljava/util/List;
/*     */     //   1698: invokeinterface addAll : (Ljava/util/Collection;)Z
/*     */     //   1703: pop
/*     */     //   1704: iload #46
/*     */     //   1706: goto -> 1719
/*     */     //   1709: ldc2_w -2004295767480307138
/*     */     //   1712: lload_2
/*     */     //   1713: <illegal opcode> w : (Ljava/lang/RuntimeException;JJ)Ljava/lang/RuntimeException;
/*     */     //   1718: athrow
/*     */     //   1719: lload_2
/*     */     //   1720: lconst_0
/*     */     //   1721: lcmp
/*     */     //   1722: iflt -> 1737
/*     */     //   1725: iload #47
/*     */     //   1727: if_icmpeq -> 1773
/*     */     //   1730: aload #4
/*     */     //   1732: iload #46
/*     */     //   1734: invokevirtual charAt : (I)C
/*     */     //   1737: aload #45
/*     */     //   1739: ifnonnull -> 1830
/*     */     //   1742: goto -> 1755
/*     */     //   1745: ldc2_w -2004295767480307138
/*     */     //   1748: lload_2
/*     */     //   1749: <illegal opcode> w : (Ljava/lang/RuntimeException;JJ)Ljava/lang/RuntimeException;
/*     */     //   1754: athrow
/*     */     //   1755: bipush #35
/*     */     //   1757: if_icmpne -> 1806
/*     */     //   1760: goto -> 1773
/*     */     //   1763: ldc2_w -2004295767480307138
/*     */     //   1766: lload_2
/*     */     //   1767: <illegal opcode> w : (Ljava/lang/RuntimeException;JJ)Ljava/lang/RuntimeException;
/*     */     //   1772: athrow
/*     */     //   1773: aload_0
/*     */     //   1774: aload_1
/*     */     //   1775: iload #19
/*     */     //   1777: iload #20
/*     */     //   1779: i2s
/*     */     //   1780: iload #21
/*     */     //   1782: invokevirtual i : (ISI)Ljava/lang/String;
/*     */     //   1785: lload #31
/*     */     //   1787: dup2_x1
/*     */     //   1788: pop2
/*     */     //   1789: invokevirtual c : (JLjava/lang/String;)Lme/konsolas/aac/j5;
/*     */     //   1792: goto -> 1805
/*     */     //   1795: ldc2_w -2004295767480307138
/*     */     //   1798: lload_2
/*     */     //   1799: <illegal opcode> w : (Ljava/lang/RuntimeException;JJ)Ljava/lang/RuntimeException;
/*     */     //   1804: athrow
/*     */     //   1805: pop
/*     */     //   1806: lload #7
/*     */     //   1808: aload #4
/*     */     //   1810: iload #46
/*     */     //   1812: iload #47
/*     */     //   1814: sipush #20808
/*     */     //   1817: ldc2_w 7081681256323532431
/*     */     //   1820: lload_2
/*     */     //   1821: lxor
/*     */     //   1822: <illegal opcode> c : (IJ)Ljava/lang/String;
/*     */     //   1827: invokestatic a : (JLjava/lang/String;IILjava/lang/String;)I
/*     */     //   1830: istore #52
/*     */     //   1832: aload_0
/*     */     //   1833: aload #4
/*     */     //   1835: lload #35
/*     */     //   1837: iload #46
/*     */     //   1839: iload #52
/*     */     //   1841: invokespecial a : (Ljava/lang/String;JII)V
/*     */     //   1844: iload #52
/*     */     //   1846: istore #46
/*     */     //   1848: iload #46
/*     */     //   1850: iload #47
/*     */     //   1852: aload #45
/*     */     //   1854: ifnonnull -> 1990
/*     */     //   1857: if_icmpge -> 1986
/*     */     //   1860: goto -> 1873
/*     */     //   1863: ldc2_w -2004295767480307138
/*     */     //   1866: lload_2
/*     */     //   1867: <illegal opcode> w : (Ljava/lang/RuntimeException;JJ)Ljava/lang/RuntimeException;
/*     */     //   1872: athrow
/*     */     //   1873: aload #4
/*     */     //   1875: iload #46
/*     */     //   1877: invokevirtual charAt : (I)C
/*     */     //   1880: bipush #63
/*     */     //   1882: aload #45
/*     */     //   1884: lload_2
/*     */     //   1885: lconst_0
/*     */     //   1886: lcmp
/*     */     //   1887: ifle -> 1998
/*     */     //   1890: ifnonnull -> 1990
/*     */     //   1893: goto -> 1906
/*     */     //   1896: ldc2_w -2004295767480307138
/*     */     //   1899: lload_2
/*     */     //   1900: <illegal opcode> w : (Ljava/lang/RuntimeException;JJ)Ljava/lang/RuntimeException;
/*     */     //   1905: athrow
/*     */     //   1906: if_icmpne -> 1986
/*     */     //   1909: goto -> 1922
/*     */     //   1912: ldc2_w -2004295767480307138
/*     */     //   1915: lload_2
/*     */     //   1916: <illegal opcode> w : (Ljava/lang/RuntimeException;JJ)Ljava/lang/RuntimeException;
/*     */     //   1921: athrow
/*     */     //   1922: aload #4
/*     */     //   1924: iload #46
/*     */     //   1926: lload #41
/*     */     //   1928: iload #47
/*     */     //   1930: bipush #35
/*     */     //   1932: invokestatic a : (Ljava/lang/String;IJIC)I
/*     */     //   1935: istore #53
/*     */     //   1937: aload_0
/*     */     //   1938: iload #11
/*     */     //   1940: aload #4
/*     */     //   1942: iload #46
/*     */     //   1944: iconst_1
/*     */     //   1945: iadd
/*     */     //   1946: iload #53
/*     */     //   1948: sipush #24554
/*     */     //   1951: ldc2_w 2324225893770840119
/*     */     //   1954: lload_2
/*     */     //   1955: lxor
/*     */     //   1956: <illegal opcode> c : (IJ)Ljava/lang/String;
/*     */     //   1961: iconst_1
/*     */     //   1962: iconst_0
/*     */     //   1963: iconst_1
/*     */     //   1964: iconst_1
/*     */     //   1965: aconst_null
/*     */     //   1966: lload #12
/*     */     //   1968: invokestatic a : (ILjava/lang/String;IILjava/lang/String;ZZZZLjava/nio/charset/Charset;J)Ljava/lang/String;
/*     */     //   1971: iload #33
/*     */     //   1973: swap
/*     */     //   1974: iload #34
/*     */     //   1976: invokestatic b : (ILjava/lang/String;I)Ljava/util/List;
/*     */     //   1979: putfield h : Ljava/util/List;
/*     */     //   1982: iload #53
/*     */     //   1984: istore #46
/*     */     //   1986: iload #46
/*     */     //   1988: iload #47
/*     */     //   1990: lload_2
/*     */     //   1991: lconst_0
/*     */     //   1992: lcmp
/*     */     //   1993: iflt -> 2039
/*     */     //   1996: aload #45
/*     */     //   1998: ifnonnull -> 2039
/*     */     //   2001: if_icmpge -> 2081
/*     */     //   2004: goto -> 2017
/*     */     //   2007: ldc2_w -2004295767480307138
/*     */     //   2010: lload_2
/*     */     //   2011: <illegal opcode> w : (Ljava/lang/RuntimeException;JJ)Ljava/lang/RuntimeException;
/*     */     //   2016: athrow
/*     */     //   2017: aload #4
/*     */     //   2019: iload #46
/*     */     //   2021: invokevirtual charAt : (I)C
/*     */     //   2024: bipush #35
/*     */     //   2026: goto -> 2039
/*     */     //   2029: ldc2_w -2004295767480307138
/*     */     //   2032: lload_2
/*     */     //   2033: <illegal opcode> w : (Ljava/lang/RuntimeException;JJ)Ljava/lang/RuntimeException;
/*     */     //   2038: athrow
/*     */     //   2039: if_icmpne -> 2081
/*     */     //   2042: aload_0
/*     */     //   2043: iload #11
/*     */     //   2045: aload #4
/*     */     //   2047: iload #46
/*     */     //   2049: iconst_1
/*     */     //   2050: iadd
/*     */     //   2051: iload #47
/*     */     //   2053: ldc ''
/*     */     //   2055: iconst_1
/*     */     //   2056: iconst_0
/*     */     //   2057: iconst_0
/*     */     //   2058: iconst_0
/*     */     //   2059: aconst_null
/*     */     //   2060: lload #12
/*     */     //   2062: invokestatic a : (ILjava/lang/String;IILjava/lang/String;ZZZZLjava/nio/charset/Charset;J)Ljava/lang/String;
/*     */     //   2065: putfield d : Ljava/lang/String;
/*     */     //   2068: goto -> 2081
/*     */     //   2071: ldc2_w -2004295767480307138
/*     */     //   2074: lload_2
/*     */     //   2075: <illegal opcode> w : (Ljava/lang/RuntimeException;JJ)Ljava/lang/RuntimeException;
/*     */     //   2080: athrow
/*     */     //   2081: aload_0
/*     */     //   2082: areturn
/*     */     // Line number table:
/*     */     //   Java source line number -> byte code offset
/*     */     //   #272	-> 241
/*     */     //   #142	-> 258
/*     */     //   #122	-> 279
/*     */     //   #137	-> 292
/*     */     //   #302	-> 316
/*     */     //   #234	-> 380
/*     */     //   #27	-> 397
/*     */     //   #9	-> 429
/*     */     //   #319	-> 486
/*     */     //   #107	-> 503
/*     */     //   #328	-> 542
/*     */     //   #40	-> 574
/*     */     //   #18	-> 625
/*     */     //   #333	-> 635
/*     */     //   #36	-> 661
/*     */     //   #128	-> 692
/*     */     //   #159	-> 695
/*     */     //   #10	-> 698
/*     */     //   #334	-> 711
/*     */     //   #25	-> 820
/*     */     //   #152	-> 840
/*     */     //   #34	-> 866
/*     */     //   #140	-> 873
/*     */     //   #259	-> 898
/*     */     //   #329	-> 901
/*     */     //   #133	-> 982
/*     */     //   #113	-> 1005
/*     */     //   #200	-> 1033
/*     */     //   #84	-> 1066
/*     */     //   #14	-> 1072
/*     */     //   #114	-> 1123
/*     */     //   #157	-> 1128
/*     */     //   #17	-> 1159
/*     */     //   #185	-> 1162
/*     */     //   #254	-> 1199
/*     */     //   #247	-> 1202
/*     */     //   #94	-> 1213
/*     */     //   #6	-> 1297
/*     */     //   #250	-> 1303
/*     */     //   #31	-> 1314
/*     */     //   #155	-> 1327
/*     */     //   #337	-> 1354
/*     */     //   #292	-> 1369
/*     */     //   #81	-> 1386
/*     */     //   #79	-> 1431
/*     */     //   #124	-> 1466
/*     */     //   #51	-> 1494
/*     */     //   #320	-> 1509
/*     */     //   #52	-> 1525
/*     */     //   #232	-> 1532
/*     */     //   #323	-> 1565
/*     */     //   #53	-> 1593
/*     */     //   #19	-> 1597
/*     */     //   #38	-> 1608
/*     */     //   #311	-> 1632
/*     */     //   #256	-> 1642
/*     */     //   #295	-> 1652
/*     */     //   #62	-> 1660
/*     */     //   #166	-> 1668
/*     */     //   #67	-> 1677
/*     */     //   #103	-> 1704
/*     */     //   #293	-> 1773
/*     */     //   #336	-> 1806
/*     */     //   #266	-> 1832
/*     */     //   #112	-> 1844
/*     */     //   #273	-> 1848
/*     */     //   #97	-> 1922
/*     */     //   #243	-> 1937
/*     */     //   #44	-> 1982
/*     */     //   #198	-> 1986
/*     */     //   #156	-> 2042
/*     */     //   #221	-> 2081
/*     */     // Exception table:
/*     */     //   from	to	target	type
/*     */     //   292	303	306	java/lang/NullPointerException
/*     */     //   299	340	343	java/lang/NullPointerException
/*     */     //   353	367	370	java/lang/NullPointerException
/*     */     //   424	452	455	java/lang/NullPointerException
/*     */     //   465	473	476	java/lang/NullPointerException
/*     */     //   470	522	525	java/lang/NullPointerException
/*     */     //   537	615	615	java/lang/NullPointerException
/*     */     //   625	648	651	java/lang/NullPointerException
/*     */     //   635	682	682	java/lang/NullPointerException
/*     */     //   711	728	731	java/lang/NullPointerException
/*     */     //   725	753	756	java/lang/NullPointerException
/*     */     //   741	769	772	java/lang/NullPointerException
/*     */     //   783	807	810	java/lang/NullPointerException
/*     */     //   804	824	827	java/lang/NullPointerException
/*     */     //   873	888	888	java/lang/NullPointerException
/*     */     //   901	972	972	java/lang/NullPointerException
/*     */     //   984	992	995	java/lang/NullPointerException
/*     */     //   989	1018	1021	java/lang/NullPointerException
/*     */     //   1066	1113	1113	java/lang/NullPointerException
/*     */     //   1125	1146	1149	java/lang/NullPointerException
/*     */     //   1202	1284	1287	java/lang/NullPointerException
/*     */     //   1327	1341	1344	java/lang/NullPointerException
/*     */     //   1332	1398	1401	java/lang/NullPointerException
/*     */     //   1354	1418	1421	java/lang/NullPointerException
/*     */     //   1411	1484	1484	java/lang/NullPointerException
/*     */     //   1526	1583	1583	java/lang/NullPointerException
/*     */     //   1597	1613	1622	java/lang/NullPointerException
/*     */     //   1632	1706	1709	java/lang/NullPointerException
/*     */     //   1719	1742	1745	java/lang/NullPointerException
/*     */     //   1730	1760	1763	java/lang/NullPointerException
/*     */     //   1755	1792	1795	java/lang/NullPointerException
/*     */     //   1848	1860	1863	java/lang/NullPointerException
/*     */     //   1857	1893	1896	java/lang/NullPointerException
/*     */     //   1873	1909	1912	java/lang/NullPointerException
/*     */     //   1990	2004	2007	java/lang/NullPointerException
/*     */     //   2001	2026	2029	java/lang/NullPointerException
/*     */     //   2039	2068	2071	java/lang/NullPointerException
/*     */   }
/*     */   
/*     */   public j5 a(String paramString1, @Nullable String paramString2, long paramLong) {
/*     */     // Byte code:
/*     */     //   0: getstatic me/konsolas/aac/j5.j : J
/*     */     //   3: lload_3
/*     */     //   4: lxor
/*     */     //   5: lstore_3
/*     */     //   6: lload_3
/*     */     //   7: dup2
/*     */     //   8: ldc2_w 87639497889673
/*     */     //   11: lxor
/*     */     //   12: lstore #5
/*     */     //   14: pop2
/*     */     //   15: ldc2_w -4804221109666923119
/*     */     //   18: lload_3
/*     */     //   19: <illegal opcode> w : (JJ)[Lme/konsolas/aac/aN;
/*     */     //   24: astore #7
/*     */     //   26: aload_1
/*     */     //   27: ifnonnull -> 61
/*     */     //   30: new java/lang/NullPointerException
/*     */     //   33: dup
/*     */     //   34: sipush #23688
/*     */     //   37: ldc2_w 8407848488506888758
/*     */     //   40: lload_3
/*     */     //   41: lxor
/*     */     //   42: <illegal opcode> c : (IJ)Ljava/lang/String;
/*     */     //   47: invokespecial <init> : (Ljava/lang/String;)V
/*     */     //   50: athrow
/*     */     //   51: ldc2_w -4793203300610397334
/*     */     //   54: lload_3
/*     */     //   55: <illegal opcode> w : (Ljava/lang/RuntimeException;JJ)Ljava/lang/RuntimeException;
/*     */     //   60: athrow
/*     */     //   61: aload_0
/*     */     //   62: getfield h : Ljava/util/List;
/*     */     //   65: lload_3
/*     */     //   66: lconst_0
/*     */     //   67: lcmp
/*     */     //   68: ifle -> 153
/*     */     //   71: aload #7
/*     */     //   73: ifnonnull -> 153
/*     */     //   76: ifnonnull -> 116
/*     */     //   79: goto -> 92
/*     */     //   82: ldc2_w -4793203300610397334
/*     */     //   85: lload_3
/*     */     //   86: <illegal opcode> w : (Ljava/lang/RuntimeException;JJ)Ljava/lang/RuntimeException;
/*     */     //   91: athrow
/*     */     //   92: aload_0
/*     */     //   93: new java/util/ArrayList
/*     */     //   96: dup
/*     */     //   97: invokespecial <init> : ()V
/*     */     //   100: putfield h : Ljava/util/List;
/*     */     //   103: goto -> 116
/*     */     //   106: ldc2_w -4793203300610397334
/*     */     //   109: lload_3
/*     */     //   110: <illegal opcode> w : (Ljava/lang/RuntimeException;JJ)Ljava/lang/RuntimeException;
/*     */     //   115: athrow
/*     */     //   116: aload_0
/*     */     //   117: getfield h : Ljava/util/List;
/*     */     //   120: aload_1
/*     */     //   121: sipush #18666
/*     */     //   124: ldc2_w 6384129275345667710
/*     */     //   127: lload_3
/*     */     //   128: lxor
/*     */     //   129: <illegal opcode> c : (IJ)Ljava/lang/String;
/*     */     //   134: lload #5
/*     */     //   136: iconst_0
/*     */     //   137: iconst_0
/*     */     //   138: iconst_1
/*     */     //   139: iconst_1
/*     */     //   140: invokestatic a : (Ljava/lang/String;Ljava/lang/String;JZZZZ)Ljava/lang/String;
/*     */     //   143: invokeinterface add : (Ljava/lang/Object;)Z
/*     */     //   148: pop
/*     */     //   149: aload_0
/*     */     //   150: getfield h : Ljava/util/List;
/*     */     //   153: aload_2
/*     */     //   154: aload #7
/*     */     //   156: ifnonnull -> 211
/*     */     //   159: ifnull -> 214
/*     */     //   162: goto -> 175
/*     */     //   165: ldc2_w -4793203300610397334
/*     */     //   168: lload_3
/*     */     //   169: <illegal opcode> w : (Ljava/lang/RuntimeException;JJ)Ljava/lang/RuntimeException;
/*     */     //   174: athrow
/*     */     //   175: aload_2
/*     */     //   176: sipush #17700
/*     */     //   179: ldc2_w 936211347951684507
/*     */     //   182: lload_3
/*     */     //   183: lxor
/*     */     //   184: <illegal opcode> c : (IJ)Ljava/lang/String;
/*     */     //   189: lload #5
/*     */     //   191: iconst_0
/*     */     //   192: iconst_0
/*     */     //   193: iconst_1
/*     */     //   194: iconst_1
/*     */     //   195: invokestatic a : (Ljava/lang/String;Ljava/lang/String;JZZZZ)Ljava/lang/String;
/*     */     //   198: goto -> 211
/*     */     //   201: ldc2_w -4793203300610397334
/*     */     //   204: lload_3
/*     */     //   205: <illegal opcode> w : (Ljava/lang/RuntimeException;JJ)Ljava/lang/RuntimeException;
/*     */     //   210: athrow
/*     */     //   211: goto -> 215
/*     */     //   214: aconst_null
/*     */     //   215: invokeinterface add : (Ljava/lang/Object;)Z
/*     */     //   220: pop
/*     */     //   221: aload_0
/*     */     //   222: areturn
/*     */     // Line number table:
/*     */     //   Java source line number -> byte code offset
/*     */     //   #274	-> 26
/*     */     //   #116	-> 61
/*     */     //   #251	-> 116
/*     */     //   #91	-> 140
/*     */     //   #153	-> 143
/*     */     //   #193	-> 149
/*     */     //   #325	-> 175
/*     */     //   #218	-> 214
/*     */     //   #264	-> 215
/*     */     //   #182	-> 221
/*     */     // Exception table:
/*     */     //   from	to	target	type
/*     */     //   26	51	51	java/lang/NullPointerException
/*     */     //   61	79	82	java/lang/NullPointerException
/*     */     //   76	103	106	java/lang/NullPointerException
/*     */     //   153	162	165	java/lang/NullPointerException
/*     */     //   159	198	201	java/lang/NullPointerException
/*     */   }
/*     */   
/*     */   public String toString() {
/*     */     // Byte code:
/*     */     //   0: getstatic me/konsolas/aac/j5.j : J
/*     */     //   3: ldc2_w 95276725422497
/*     */     //   6: lxor
/*     */     //   7: lstore_1
/*     */     //   8: lload_1
/*     */     //   9: dup2
/*     */     //   10: ldc2_w 79497953734279
/*     */     //   13: lxor
/*     */     //   14: dup2
/*     */     //   15: bipush #48
/*     */     //   17: lushr
/*     */     //   18: l2i
/*     */     //   19: istore_3
/*     */     //   20: dup2
/*     */     //   21: bipush #16
/*     */     //   23: lshl
/*     */     //   24: bipush #16
/*     */     //   26: lushr
/*     */     //   27: lstore #4
/*     */     //   29: pop2
/*     */     //   30: dup2
/*     */     //   31: ldc2_w 29127892753202
/*     */     //   34: lxor
/*     */     //   35: lstore #6
/*     */     //   37: dup2
/*     */     //   38: ldc2_w 624776530211
/*     */     //   41: lxor
/*     */     //   42: lstore #8
/*     */     //   44: dup2
/*     */     //   45: ldc2_w 126103898168252
/*     */     //   48: lxor
/*     */     //   49: lstore #10
/*     */     //   51: pop2
/*     */     //   52: ldc2_w -525321340939798409
/*     */     //   55: lload_1
/*     */     //   56: <illegal opcode> w : (JJ)[Lme/konsolas/aac/aN;
/*     */     //   61: new java/lang/StringBuilder
/*     */     //   64: dup
/*     */     //   65: invokespecial <init> : ()V
/*     */     //   68: astore #13
/*     */     //   70: astore #12
/*     */     //   72: aload #12
/*     */     //   74: ifnonnull -> 139
/*     */     //   77: aload_0
/*     */     //   78: getfield c : Ljava/lang/String;
/*     */     //   81: ifnull -> 144
/*     */     //   84: goto -> 97
/*     */     //   87: ldc2_w -532186019430895988
/*     */     //   90: lload_1
/*     */     //   91: <illegal opcode> w : (Ljava/lang/RuntimeException;JJ)Ljava/lang/RuntimeException;
/*     */     //   96: athrow
/*     */     //   97: aload #13
/*     */     //   99: aload_0
/*     */     //   100: getfield c : Ljava/lang/String;
/*     */     //   103: invokevirtual append : (Ljava/lang/String;)Ljava/lang/StringBuilder;
/*     */     //   106: pop
/*     */     //   107: aload #13
/*     */     //   109: sipush #11903
/*     */     //   112: ldc2_w 2952501449821988107
/*     */     //   115: lload_1
/*     */     //   116: lxor
/*     */     //   117: <illegal opcode> c : (IJ)Ljava/lang/String;
/*     */     //   122: invokevirtual append : (Ljava/lang/String;)Ljava/lang/StringBuilder;
/*     */     //   125: pop
/*     */     //   126: goto -> 139
/*     */     //   129: ldc2_w -532186019430895988
/*     */     //   132: lload_1
/*     */     //   133: <illegal opcode> w : (Ljava/lang/RuntimeException;JJ)Ljava/lang/RuntimeException;
/*     */     //   138: athrow
/*     */     //   139: aload #12
/*     */     //   141: ifnull -> 176
/*     */     //   144: aload #13
/*     */     //   146: sipush #14227
/*     */     //   149: ldc2_w 6540832735290932464
/*     */     //   152: lload_1
/*     */     //   153: lxor
/*     */     //   154: <illegal opcode> c : (IJ)Ljava/lang/String;
/*     */     //   159: invokevirtual append : (Ljava/lang/String;)Ljava/lang/StringBuilder;
/*     */     //   162: pop
/*     */     //   163: goto -> 176
/*     */     //   166: ldc2_w -532186019430895988
/*     */     //   169: lload_1
/*     */     //   170: <illegal opcode> w : (Ljava/lang/RuntimeException;JJ)Ljava/lang/RuntimeException;
/*     */     //   175: athrow
/*     */     //   176: aload_0
/*     */     //   177: getfield f : Ljava/lang/String;
/*     */     //   180: invokevirtual isEmpty : ()Z
/*     */     //   183: aload #12
/*     */     //   185: ifnonnull -> 293
/*     */     //   188: ifeq -> 245
/*     */     //   191: goto -> 204
/*     */     //   194: ldc2_w -532186019430895988
/*     */     //   197: lload_1
/*     */     //   198: <illegal opcode> w : (Ljava/lang/RuntimeException;JJ)Ljava/lang/RuntimeException;
/*     */     //   203: athrow
/*     */     //   204: aload_0
/*     */     //   205: getfield a : Ljava/lang/String;
/*     */     //   208: aload #12
/*     */     //   210: ifnonnull -> 357
/*     */     //   213: goto -> 226
/*     */     //   216: ldc2_w -532186019430895988
/*     */     //   219: lload_1
/*     */     //   220: <illegal opcode> w : (Ljava/lang/RuntimeException;JJ)Ljava/lang/RuntimeException;
/*     */     //   225: athrow
/*     */     //   226: invokevirtual isEmpty : ()Z
/*     */     //   229: ifne -> 335
/*     */     //   232: goto -> 245
/*     */     //   235: ldc2_w -532186019430895988
/*     */     //   238: lload_1
/*     */     //   239: <illegal opcode> w : (Ljava/lang/RuntimeException;JJ)Ljava/lang/RuntimeException;
/*     */     //   244: athrow
/*     */     //   245: aload #13
/*     */     //   247: aload_0
/*     */     //   248: getfield f : Ljava/lang/String;
/*     */     //   251: invokevirtual append : (Ljava/lang/String;)Ljava/lang/StringBuilder;
/*     */     //   254: aload #12
/*     */     //   256: ifnonnull -> 334
/*     */     //   259: goto -> 272
/*     */     //   262: ldc2_w -532186019430895988
/*     */     //   265: lload_1
/*     */     //   266: <illegal opcode> w : (Ljava/lang/RuntimeException;JJ)Ljava/lang/RuntimeException;
/*     */     //   271: athrow
/*     */     //   272: pop
/*     */     //   273: aload_0
/*     */     //   274: getfield a : Ljava/lang/String;
/*     */     //   277: invokevirtual isEmpty : ()Z
/*     */     //   280: goto -> 293
/*     */     //   283: ldc2_w -532186019430895988
/*     */     //   286: lload_1
/*     */     //   287: <illegal opcode> w : (Ljava/lang/RuntimeException;JJ)Ljava/lang/RuntimeException;
/*     */     //   292: athrow
/*     */     //   293: ifne -> 327
/*     */     //   296: aload #13
/*     */     //   298: bipush #58
/*     */     //   300: invokevirtual append : (C)Ljava/lang/StringBuilder;
/*     */     //   303: pop
/*     */     //   304: aload #13
/*     */     //   306: aload_0
/*     */     //   307: getfield a : Ljava/lang/String;
/*     */     //   310: invokevirtual append : (Ljava/lang/String;)Ljava/lang/StringBuilder;
/*     */     //   313: pop
/*     */     //   314: goto -> 327
/*     */     //   317: ldc2_w -532186019430895988
/*     */     //   320: lload_1
/*     */     //   321: <illegal opcode> w : (Ljava/lang/RuntimeException;JJ)Ljava/lang/RuntimeException;
/*     */     //   326: athrow
/*     */     //   327: aload #13
/*     */     //   329: bipush #64
/*     */     //   331: invokevirtual append : (C)Ljava/lang/StringBuilder;
/*     */     //   334: pop
/*     */     //   335: aload_0
/*     */     //   336: aload #12
/*     */     //   338: ifnonnull -> 454
/*     */     //   341: getfield g : Ljava/lang/String;
/*     */     //   344: goto -> 357
/*     */     //   347: ldc2_w -532186019430895988
/*     */     //   350: lload_1
/*     */     //   351: <illegal opcode> w : (Ljava/lang/RuntimeException;JJ)Ljava/lang/RuntimeException;
/*     */     //   356: athrow
/*     */     //   357: ifnull -> 453
/*     */     //   360: aload_0
/*     */     //   361: getfield g : Ljava/lang/String;
/*     */     //   364: bipush #58
/*     */     //   366: invokevirtual indexOf : (I)I
/*     */     //   369: iconst_m1
/*     */     //   370: if_icmpeq -> 430
/*     */     //   373: goto -> 386
/*     */     //   376: ldc2_w -532186019430895988
/*     */     //   379: lload_1
/*     */     //   380: <illegal opcode> w : (Ljava/lang/RuntimeException;JJ)Ljava/lang/RuntimeException;
/*     */     //   385: athrow
/*     */     //   386: aload #13
/*     */     //   388: bipush #91
/*     */     //   390: invokevirtual append : (C)Ljava/lang/StringBuilder;
/*     */     //   393: pop
/*     */     //   394: aload #13
/*     */     //   396: aload_0
/*     */     //   397: getfield g : Ljava/lang/String;
/*     */     //   400: invokevirtual append : (Ljava/lang/String;)Ljava/lang/StringBuilder;
/*     */     //   403: pop
/*     */     //   404: aload #13
/*     */     //   406: bipush #93
/*     */     //   408: invokevirtual append : (C)Ljava/lang/StringBuilder;
/*     */     //   411: pop
/*     */     //   412: aload #12
/*     */     //   414: ifnull -> 453
/*     */     //   417: goto -> 430
/*     */     //   420: ldc2_w -532186019430895988
/*     */     //   423: lload_1
/*     */     //   424: <illegal opcode> w : (Ljava/lang/RuntimeException;JJ)Ljava/lang/RuntimeException;
/*     */     //   429: athrow
/*     */     //   430: aload #13
/*     */     //   432: aload_0
/*     */     //   433: getfield g : Ljava/lang/String;
/*     */     //   436: invokevirtual append : (Ljava/lang/String;)Ljava/lang/StringBuilder;
/*     */     //   439: pop
/*     */     //   440: goto -> 453
/*     */     //   443: ldc2_w -532186019430895988
/*     */     //   446: lload_1
/*     */     //   447: <illegal opcode> w : (Ljava/lang/RuntimeException;JJ)Ljava/lang/RuntimeException;
/*     */     //   452: athrow
/*     */     //   453: aload_0
/*     */     //   454: getfield e : I
/*     */     //   457: aload #12
/*     */     //   459: ifnonnull -> 536
/*     */     //   462: iconst_m1
/*     */     //   463: if_icmpne -> 517
/*     */     //   466: goto -> 479
/*     */     //   469: ldc2_w -532186019430895988
/*     */     //   472: lload_1
/*     */     //   473: <illegal opcode> w : (Ljava/lang/RuntimeException;JJ)Ljava/lang/RuntimeException;
/*     */     //   478: athrow
/*     */     //   479: aload_0
/*     */     //   480: aload #12
/*     */     //   482: ifnonnull -> 633
/*     */     //   485: goto -> 498
/*     */     //   488: ldc2_w -532186019430895988
/*     */     //   491: lload_1
/*     */     //   492: <illegal opcode> w : (Ljava/lang/RuntimeException;JJ)Ljava/lang/RuntimeException;
/*     */     //   497: athrow
/*     */     //   498: getfield c : Ljava/lang/String;
/*     */     //   501: ifnull -> 621
/*     */     //   504: goto -> 517
/*     */     //   507: ldc2_w -532186019430895988
/*     */     //   510: lload_1
/*     */     //   511: <illegal opcode> w : (Ljava/lang/RuntimeException;JJ)Ljava/lang/RuntimeException;
/*     */     //   516: athrow
/*     */     //   517: aload_0
/*     */     //   518: lload #8
/*     */     //   520: invokevirtual a : (J)I
/*     */     //   523: goto -> 536
/*     */     //   526: ldc2_w -532186019430895988
/*     */     //   529: lload_1
/*     */     //   530: <illegal opcode> w : (Ljava/lang/RuntimeException;JJ)Ljava/lang/RuntimeException;
/*     */     //   535: athrow
/*     */     //   536: istore #14
/*     */     //   538: aload #12
/*     */     //   540: ifnonnull -> 613
/*     */     //   543: aload_0
/*     */     //   544: getfield c : Ljava/lang/String;
/*     */     //   547: ifnull -> 592
/*     */     //   550: goto -> 563
/*     */     //   553: ldc2_w -532186019430895988
/*     */     //   556: lload_1
/*     */     //   557: <illegal opcode> w : (Ljava/lang/RuntimeException;JJ)Ljava/lang/RuntimeException;
/*     */     //   562: athrow
/*     */     //   563: iload #14
/*     */     //   565: aload_0
/*     */     //   566: getfield c : Ljava/lang/String;
/*     */     //   569: iload_3
/*     */     //   570: i2s
/*     */     //   571: lload #4
/*     */     //   573: invokestatic a : (Ljava/lang/String;SJ)I
/*     */     //   576: if_icmpeq -> 621
/*     */     //   579: goto -> 592
/*     */     //   582: ldc2_w -532186019430895988
/*     */     //   585: lload_1
/*     */     //   586: <illegal opcode> w : (Ljava/lang/RuntimeException;JJ)Ljava/lang/RuntimeException;
/*     */     //   591: athrow
/*     */     //   592: aload #13
/*     */     //   594: bipush #58
/*     */     //   596: invokevirtual append : (C)Ljava/lang/StringBuilder;
/*     */     //   599: pop
/*     */     //   600: goto -> 613
/*     */     //   603: ldc2_w -532186019430895988
/*     */     //   606: lload_1
/*     */     //   607: <illegal opcode> w : (Ljava/lang/RuntimeException;JJ)Ljava/lang/RuntimeException;
/*     */     //   612: athrow
/*     */     //   613: aload #13
/*     */     //   615: iload #14
/*     */     //   617: invokevirtual append : (I)Ljava/lang/StringBuilder;
/*     */     //   620: pop
/*     */     //   621: lload #10
/*     */     //   623: aload #13
/*     */     //   625: aload_0
/*     */     //   626: getfield i : Ljava/util/List;
/*     */     //   629: invokestatic a : (JLjava/lang/StringBuilder;Ljava/util/List;)V
/*     */     //   632: aload_0
/*     */     //   633: aload #12
/*     */     //   635: ifnonnull -> 692
/*     */     //   638: getfield h : Ljava/util/List;
/*     */     //   641: ifnull -> 691
/*     */     //   644: goto -> 657
/*     */     //   647: ldc2_w -532186019430895988
/*     */     //   650: lload_1
/*     */     //   651: <illegal opcode> w : (Ljava/lang/RuntimeException;JJ)Ljava/lang/RuntimeException;
/*     */     //   656: athrow
/*     */     //   657: aload #13
/*     */     //   659: bipush #63
/*     */     //   661: invokevirtual append : (C)Ljava/lang/StringBuilder;
/*     */     //   664: pop
/*     */     //   665: aload #13
/*     */     //   667: aload_0
/*     */     //   668: getfield h : Ljava/util/List;
/*     */     //   671: lload #6
/*     */     //   673: dup2_x1
/*     */     //   674: pop2
/*     */     //   675: invokestatic b : (Ljava/lang/StringBuilder;JLjava/util/List;)V
/*     */     //   678: goto -> 691
/*     */     //   681: ldc2_w -532186019430895988
/*     */     //   684: lload_1
/*     */     //   685: <illegal opcode> w : (Ljava/lang/RuntimeException;JJ)Ljava/lang/RuntimeException;
/*     */     //   690: athrow
/*     */     //   691: aload_0
/*     */     //   692: getfield d : Ljava/lang/String;
/*     */     //   695: aload #12
/*     */     //   697: ifnonnull -> 752
/*     */     //   700: ifnull -> 747
/*     */     //   703: goto -> 716
/*     */     //   706: ldc2_w -532186019430895988
/*     */     //   709: lload_1
/*     */     //   710: <illegal opcode> w : (Ljava/lang/RuntimeException;JJ)Ljava/lang/RuntimeException;
/*     */     //   715: athrow
/*     */     //   716: aload #13
/*     */     //   718: bipush #35
/*     */     //   720: invokevirtual append : (C)Ljava/lang/StringBuilder;
/*     */     //   723: pop
/*     */     //   724: aload #13
/*     */     //   726: aload_0
/*     */     //   727: getfield d : Ljava/lang/String;
/*     */     //   730: invokevirtual append : (Ljava/lang/String;)Ljava/lang/StringBuilder;
/*     */     //   733: pop
/*     */     //   734: goto -> 747
/*     */     //   737: ldc2_w -532186019430895988
/*     */     //   740: lload_1
/*     */     //   741: <illegal opcode> w : (Ljava/lang/RuntimeException;JJ)Ljava/lang/RuntimeException;
/*     */     //   746: athrow
/*     */     //   747: aload #13
/*     */     //   749: invokevirtual toString : ()Ljava/lang/String;
/*     */     //   752: areturn
/*     */     // Line number table:
/*     */     //   Java source line number -> byte code offset
/*     */     //   #275	-> 61
/*     */     //   #246	-> 72
/*     */     //   #257	-> 97
/*     */     //   #37	-> 107
/*     */     //   #42	-> 144
/*     */     //   #298	-> 176
/*     */     //   #285	-> 245
/*     */     //   #160	-> 273
/*     */     //   #104	-> 296
/*     */     //   #202	-> 304
/*     */     //   #118	-> 327
/*     */     //   #132	-> 335
/*     */     //   #244	-> 360
/*     */     //   #32	-> 386
/*     */     //   #28	-> 394
/*     */     //   #332	-> 404
/*     */     //   #26	-> 430
/*     */     //   #301	-> 453
/*     */     //   #327	-> 517
/*     */     //   #130	-> 538
/*     */     //   #57	-> 592
/*     */     //   #239	-> 613
/*     */     //   #92	-> 621
/*     */     //   #227	-> 632
/*     */     //   #175	-> 657
/*     */     //   #283	-> 665
/*     */     //   #300	-> 691
/*     */     //   #105	-> 716
/*     */     //   #5	-> 724
/*     */     //   #59	-> 747
/*     */     // Exception table:
/*     */     //   from	to	target	type
/*     */     //   72	84	87	java/lang/NullPointerException
/*     */     //   77	126	129	java/lang/NullPointerException
/*     */     //   139	163	166	java/lang/NullPointerException
/*     */     //   176	191	194	java/lang/NullPointerException
/*     */     //   188	213	216	java/lang/NullPointerException
/*     */     //   204	232	235	java/lang/NullPointerException
/*     */     //   226	259	262	java/lang/NullPointerException
/*     */     //   245	280	283	java/lang/NullPointerException
/*     */     //   293	314	317	java/lang/NullPointerException
/*     */     //   335	344	347	java/lang/NullPointerException
/*     */     //   357	373	376	java/lang/NullPointerException
/*     */     //   360	417	420	java/lang/NullPointerException
/*     */     //   386	440	443	java/lang/NullPointerException
/*     */     //   454	466	469	java/lang/NullPointerException
/*     */     //   462	485	488	java/lang/NullPointerException
/*     */     //   479	504	507	java/lang/NullPointerException
/*     */     //   498	523	526	java/lang/NullPointerException
/*     */     //   538	550	553	java/lang/NullPointerException
/*     */     //   543	579	582	java/lang/NullPointerException
/*     */     //   563	600	603	java/lang/NullPointerException
/*     */     //   633	644	647	java/lang/NullPointerException
/*     */     //   638	678	681	java/lang/NullPointerException
/*     */     //   692	703	706	java/lang/NullPointerException
/*     */     //   700	734	737	java/lang/NullPointerException
/*     */   }
/*     */   
/*     */   public j5 f(long paramLong, String paramString) {
/*     */     // Byte code:
/*     */     //   0: getstatic me/konsolas/aac/j5.j : J
/*     */     //   3: lload_1
/*     */     //   4: lxor
/*     */     //   5: lstore_1
/*     */     //   6: lload_1
/*     */     //   7: dup2
/*     */     //   8: ldc2_w 92244857331317
/*     */     //   11: lxor
/*     */     //   12: lstore #4
/*     */     //   14: pop2
/*     */     //   15: ldc2_w 8408191962146501741
/*     */     //   18: lload_1
/*     */     //   19: <illegal opcode> w : (JJ)[Lme/konsolas/aac/aN;
/*     */     //   24: astore #6
/*     */     //   26: aload #6
/*     */     //   28: ifnonnull -> 106
/*     */     //   31: aload_3
/*     */     //   32: ifnonnull -> 79
/*     */     //   35: goto -> 48
/*     */     //   38: ldc2_w 8396682977109926550
/*     */     //   41: lload_1
/*     */     //   42: <illegal opcode> w : (Ljava/lang/RuntimeException;JJ)Ljava/lang/RuntimeException;
/*     */     //   47: athrow
/*     */     //   48: new java/lang/NullPointerException
/*     */     //   51: dup
/*     */     //   52: sipush #19828
/*     */     //   55: ldc2_w 1285839202444298801
/*     */     //   58: lload_1
/*     */     //   59: lxor
/*     */     //   60: <illegal opcode> c : (IJ)Ljava/lang/String;
/*     */     //   65: invokespecial <init> : (Ljava/lang/String;)V
/*     */     //   68: athrow
/*     */     //   69: ldc2_w 8396682977109926550
/*     */     //   72: lload_1
/*     */     //   73: <illegal opcode> w : (Ljava/lang/RuntimeException;JJ)Ljava/lang/RuntimeException;
/*     */     //   78: athrow
/*     */     //   79: aload_0
/*     */     //   80: aload_3
/*     */     //   81: sipush #4000
/*     */     //   84: ldc2_w 2612690001664116970
/*     */     //   87: lload_1
/*     */     //   88: lxor
/*     */     //   89: <illegal opcode> c : (IJ)Ljava/lang/String;
/*     */     //   94: lload #4
/*     */     //   96: iconst_1
/*     */     //   97: iconst_0
/*     */     //   98: iconst_0
/*     */     //   99: iconst_1
/*     */     //   100: invokestatic a : (Ljava/lang/String;Ljava/lang/String;JZZZZ)Ljava/lang/String;
/*     */     //   103: putfield a : Ljava/lang/String;
/*     */     //   106: aload_0
/*     */     //   107: areturn
/*     */     // Line number table:
/*     */     //   Java source line number -> byte code offset
/*     */     //   #276	-> 26
/*     */     //   #242	-> 79
/*     */     //   #72	-> 106
/*     */     // Exception table:
/*     */     //   from	to	target	type
/*     */     //   26	35	38	java/lang/NullPointerException
/*     */     //   31	69	69	java/lang/NullPointerException
/*     */   }
/*     */   
/*     */   public j5 a(int paramInt, String paramString, long paramLong) {
/*     */     // Byte code:
/*     */     //   0: getstatic me/konsolas/aac/j5.j : J
/*     */     //   3: lload_3
/*     */     //   4: lxor
/*     */     //   5: lstore_3
/*     */     //   6: lload_3
/*     */     //   7: dup2
/*     */     //   8: ldc2_w 89515930018107
/*     */     //   11: lxor
/*     */     //   12: dup2
/*     */     //   13: bipush #32
/*     */     //   15: lushr
/*     */     //   16: l2i
/*     */     //   17: istore #5
/*     */     //   19: dup2
/*     */     //   20: bipush #32
/*     */     //   22: lshl
/*     */     //   23: bipush #32
/*     */     //   25: lushr
/*     */     //   26: lstore #6
/*     */     //   28: pop2
/*     */     //   29: dup2
/*     */     //   30: ldc2_w 84111219009917
/*     */     //   33: lxor
/*     */     //   34: lstore #8
/*     */     //   36: dup2
/*     */     //   37: ldc2_w 100392441451171
/*     */     //   40: lxor
/*     */     //   41: lstore #10
/*     */     //   43: pop2
/*     */     //   44: ldc2_w 603170300115880092
/*     */     //   47: lload_3
/*     */     //   48: <illegal opcode> w : (JJ)[Lme/konsolas/aac/aN;
/*     */     //   53: astore #12
/*     */     //   55: aload_2
/*     */     //   56: aload #12
/*     */     //   58: ifnonnull -> 139
/*     */     //   61: ifnonnull -> 108
/*     */     //   64: goto -> 77
/*     */     //   67: ldc2_w 609675442328477287
/*     */     //   70: lload_3
/*     */     //   71: <illegal opcode> w : (Ljava/lang/RuntimeException;JJ)Ljava/lang/RuntimeException;
/*     */     //   76: athrow
/*     */     //   77: new java/lang/NullPointerException
/*     */     //   80: dup
/*     */     //   81: sipush #15780
/*     */     //   84: ldc2_w 6828694643223021059
/*     */     //   87: lload_3
/*     */     //   88: lxor
/*     */     //   89: <illegal opcode> c : (IJ)Ljava/lang/String;
/*     */     //   94: invokespecial <init> : (Ljava/lang/String;)V
/*     */     //   97: athrow
/*     */     //   98: ldc2_w 609675442328477287
/*     */     //   101: lload_3
/*     */     //   102: <illegal opcode> w : (Ljava/lang/RuntimeException;JJ)Ljava/lang/RuntimeException;
/*     */     //   107: athrow
/*     */     //   108: iload #5
/*     */     //   110: aload_2
/*     */     //   111: iconst_0
/*     */     //   112: aload_2
/*     */     //   113: invokevirtual length : ()I
/*     */     //   116: sipush #2555
/*     */     //   119: ldc2_w 2980157705369547360
/*     */     //   122: lload_3
/*     */     //   123: lxor
/*     */     //   124: <illegal opcode> c : (IJ)Ljava/lang/String;
/*     */     //   129: iconst_1
/*     */     //   130: iconst_0
/*     */     //   131: iconst_0
/*     */     //   132: iconst_1
/*     */     //   133: aconst_null
/*     */     //   134: lload #6
/*     */     //   136: invokestatic a : (ILjava/lang/String;IILjava/lang/String;ZZZZLjava/nio/charset/Charset;J)Ljava/lang/String;
/*     */     //   139: astore #13
/*     */     //   141: aload_0
/*     */     //   142: getfield i : Ljava/util/List;
/*     */     //   145: iload_1
/*     */     //   146: aload #13
/*     */     //   148: invokeinterface set : (ILjava/lang/Object;)Ljava/lang/Object;
/*     */     //   153: pop
/*     */     //   154: aload_0
/*     */     //   155: lload #8
/*     */     //   157: aload #13
/*     */     //   159: invokespecial a : (JLjava/lang/String;)Z
/*     */     //   162: lload_3
/*     */     //   163: lconst_0
/*     */     //   164: lcmp
/*     */     //   165: iflt -> 228
/*     */     //   168: aload #12
/*     */     //   170: ifnonnull -> 228
/*     */     //   173: ifne -> 231
/*     */     //   176: goto -> 189
/*     */     //   179: ldc2_w 609675442328477287
/*     */     //   182: lload_3
/*     */     //   183: <illegal opcode> w : (Ljava/lang/RuntimeException;JJ)Ljava/lang/RuntimeException;
/*     */     //   188: athrow
/*     */     //   189: aload_0
/*     */     //   190: aload #12
/*     */     //   192: ifnonnull -> 280
/*     */     //   195: goto -> 208
/*     */     //   198: ldc2_w 609675442328477287
/*     */     //   201: lload_3
/*     */     //   202: <illegal opcode> w : (Ljava/lang/RuntimeException;JJ)Ljava/lang/RuntimeException;
/*     */     //   207: athrow
/*     */     //   208: aload #13
/*     */     //   210: lload #10
/*     */     //   212: invokespecial b : (Ljava/lang/String;J)Z
/*     */     //   215: goto -> 228
/*     */     //   218: ldc2_w 609675442328477287
/*     */     //   221: lload_3
/*     */     //   222: <illegal opcode> w : (Ljava/lang/RuntimeException;JJ)Ljava/lang/RuntimeException;
/*     */     //   227: athrow
/*     */     //   228: ifeq -> 279
/*     */     //   231: new java/lang/IllegalArgumentException
/*     */     //   234: dup
/*     */     //   235: new java/lang/StringBuilder
/*     */     //   238: dup
/*     */     //   239: invokespecial <init> : ()V
/*     */     //   242: sipush #19576
/*     */     //   245: ldc2_w 7189103748986189787
/*     */     //   248: lload_3
/*     */     //   249: lxor
/*     */     //   250: <illegal opcode> c : (IJ)Ljava/lang/String;
/*     */     //   255: invokevirtual append : (Ljava/lang/String;)Ljava/lang/StringBuilder;
/*     */     //   258: aload_2
/*     */     //   259: invokevirtual append : (Ljava/lang/String;)Ljava/lang/StringBuilder;
/*     */     //   262: invokevirtual toString : ()Ljava/lang/String;
/*     */     //   265: invokespecial <init> : (Ljava/lang/String;)V
/*     */     //   268: athrow
/*     */     //   269: ldc2_w 609675442328477287
/*     */     //   272: lload_3
/*     */     //   273: <illegal opcode> w : (Ljava/lang/RuntimeException;JJ)Ljava/lang/RuntimeException;
/*     */     //   278: athrow
/*     */     //   279: aload_0
/*     */     //   280: areturn
/*     */     // Line number table:
/*     */     //   Java source line number -> byte code offset
/*     */     //   #279	-> 55
/*     */     //   #143	-> 77
/*     */     //   #126	-> 108
/*     */     //   #90	-> 141
/*     */     //   #224	-> 154
/*     */     //   #194	-> 231
/*     */     //   #286	-> 279
/*     */     // Exception table:
/*     */     //   from	to	target	type
/*     */     //   55	64	67	java/lang/NullPointerException
/*     */     //   61	98	98	java/lang/NullPointerException
/*     */     //   141	176	179	java/lang/NullPointerException
/*     */     //   173	195	198	java/lang/NullPointerException
/*     */     //   189	215	218	java/lang/NullPointerException
/*     */     //   228	269	269	java/lang/NullPointerException
/*     */   }
/*     */   
/*     */   public j5 j(char paramChar, int paramInt1, String paramString, int paramInt2) {
/*     */     // Byte code:
/*     */     //   0: iload_1
/*     */     //   1: i2l
/*     */     //   2: bipush #48
/*     */     //   4: lshl
/*     */     //   5: iload_2
/*     */     //   6: i2l
/*     */     //   7: bipush #32
/*     */     //   9: lshl
/*     */     //   10: bipush #16
/*     */     //   12: lushr
/*     */     //   13: lor
/*     */     //   14: iload #4
/*     */     //   16: i2l
/*     */     //   17: bipush #48
/*     */     //   19: lshl
/*     */     //   20: bipush #48
/*     */     //   22: lushr
/*     */     //   23: lor
/*     */     //   24: getstatic me/konsolas/aac/j5.j : J
/*     */     //   27: lxor
/*     */     //   28: lstore #5
/*     */     //   30: lload #5
/*     */     //   32: dup2
/*     */     //   33: ldc2_w 20367212063924
/*     */     //   36: lxor
/*     */     //   37: lstore #7
/*     */     //   39: pop2
/*     */     //   40: ldc2_w -3710543209589257149
/*     */     //   43: lload #5
/*     */     //   45: <illegal opcode> w : (JJ)[Lme/konsolas/aac/aN;
/*     */     //   50: astore #9
/*     */     //   52: aload_3
/*     */     //   53: aload #9
/*     */     //   55: ifnonnull -> 109
/*     */     //   58: ifnonnull -> 108
/*     */     //   61: goto -> 75
/*     */     //   64: ldc2_w -3699315424382657864
/*     */     //   67: lload #5
/*     */     //   69: <illegal opcode> w : (Ljava/lang/RuntimeException;JJ)Ljava/lang/RuntimeException;
/*     */     //   74: athrow
/*     */     //   75: new java/lang/NullPointerException
/*     */     //   78: dup
/*     */     //   79: sipush #9015
/*     */     //   82: ldc2_w 1504338547096591429
/*     */     //   85: lload #5
/*     */     //   87: lxor
/*     */     //   88: <illegal opcode> c : (IJ)Ljava/lang/String;
/*     */     //   93: invokespecial <init> : (Ljava/lang/String;)V
/*     */     //   96: athrow
/*     */     //   97: ldc2_w -3699315424382657864
/*     */     //   100: lload #5
/*     */     //   102: <illegal opcode> w : (Ljava/lang/RuntimeException;JJ)Ljava/lang/RuntimeException;
/*     */     //   107: athrow
/*     */     //   108: aload_3
/*     */     //   109: ldc_w '⇔▿'
/*     */     //   112: invokevirtual toCharArray : ()[C
/*     */     //   115: dup
/*     */     //   116: dup
/*     */     //   117: iconst_0
/*     */     //   118: dup_x1
/*     */     //   119: caload
/*     */     //   120: sipush #3273
/*     */     //   123: ixor
/*     */     //   124: i2c
/*     */     //   125: castore
/*     */     //   126: sipush #22230
/*     */     //   129: iconst_1
/*     */     //   130: iconst_5
/*     */     //   131: invokestatic A : (Ljava/lang/Object;SZI)Ljava/lang/String;
/*     */     //   134: invokevirtual startsWith : (Ljava/lang/String;)Z
/*     */     //   137: ifne -> 190
/*     */     //   140: new java/lang/IllegalArgumentException
/*     */     //   143: dup
/*     */     //   144: new java/lang/StringBuilder
/*     */     //   147: dup
/*     */     //   148: invokespecial <init> : ()V
/*     */     //   151: sipush #32384
/*     */     //   154: ldc2_w 8698749306966753747
/*     */     //   157: lload #5
/*     */     //   159: lxor
/*     */     //   160: <illegal opcode> c : (IJ)Ljava/lang/String;
/*     */     //   165: invokevirtual append : (Ljava/lang/String;)Ljava/lang/StringBuilder;
/*     */     //   168: aload_3
/*     */     //   169: invokevirtual append : (Ljava/lang/String;)Ljava/lang/StringBuilder;
/*     */     //   172: invokevirtual toString : ()Ljava/lang/String;
/*     */     //   175: invokespecial <init> : (Ljava/lang/String;)V
/*     */     //   178: athrow
/*     */     //   179: ldc2_w -3699315424382657864
/*     */     //   182: lload #5
/*     */     //   184: <illegal opcode> w : (Ljava/lang/RuntimeException;JJ)Ljava/lang/RuntimeException;
/*     */     //   189: athrow
/*     */     //   190: aload_0
/*     */     //   191: aload_3
/*     */     //   192: lload #7
/*     */     //   194: iconst_0
/*     */     //   195: aload_3
/*     */     //   196: invokevirtual length : ()I
/*     */     //   199: invokespecial a : (Ljava/lang/String;JII)V
/*     */     //   202: aload_0
/*     */     //   203: areturn
/*     */     // Line number table:
/*     */     //   Java source line number -> byte code offset
/*     */     //   #289	-> 52
/*     */     //   #248	-> 108
/*     */     //   #20	-> 140
/*     */     //   #281	-> 190
/*     */     //   #70	-> 202
/*     */     // Exception table:
/*     */     //   from	to	target	type
/*     */     //   52	61	64	java/lang/NullPointerException
/*     */     //   58	97	97	java/lang/NullPointerException
/*     */     //   109	179	179	java/lang/NullPointerException
/*     */   }
/*     */   
/*     */   public j5 i(long paramLong, String paramString) {
/*     */     // Byte code:
/*     */     //   0: getstatic me/konsolas/aac/j5.j : J
/*     */     //   3: lload_1
/*     */     //   4: lxor
/*     */     //   5: lstore_1
/*     */     //   6: lload_1
/*     */     //   7: dup2
/*     */     //   8: ldc2_w 107466897067712
/*     */     //   11: lxor
/*     */     //   12: dup2
/*     */     //   13: bipush #48
/*     */     //   15: lushr
/*     */     //   16: l2i
/*     */     //   17: istore #4
/*     */     //   19: dup2
/*     */     //   20: bipush #16
/*     */     //   22: lshl
/*     */     //   23: bipush #48
/*     */     //   25: lushr
/*     */     //   26: l2i
/*     */     //   27: istore #5
/*     */     //   29: dup2
/*     */     //   30: bipush #32
/*     */     //   32: lshl
/*     */     //   33: bipush #32
/*     */     //   35: lushr
/*     */     //   36: l2i
/*     */     //   37: istore #6
/*     */     //   39: pop2
/*     */     //   40: dup2
/*     */     //   41: ldc2_w 115080086087375
/*     */     //   44: lxor
/*     */     //   45: lstore #7
/*     */     //   47: pop2
/*     */     //   48: ldc2_w -8352526642155123497
/*     */     //   51: lload_1
/*     */     //   52: <illegal opcode> w : (JJ)[Lme/konsolas/aac/aN;
/*     */     //   57: astore #9
/*     */     //   59: aload_3
/*     */     //   60: ifnonnull -> 94
/*     */     //   63: new java/lang/NullPointerException
/*     */     //   66: dup
/*     */     //   67: sipush #11115
/*     */     //   70: ldc2_w 1476310584161358998
/*     */     //   73: lload_1
/*     */     //   74: lxor
/*     */     //   75: <illegal opcode> c : (IJ)Ljava/lang/String;
/*     */     //   80: invokespecial <init> : (Ljava/lang/String;)V
/*     */     //   83: athrow
/*     */     //   84: ldc2_w -8341447294806779348
/*     */     //   87: lload_1
/*     */     //   88: <illegal opcode> w : (Ljava/lang/RuntimeException;JJ)Ljava/lang/RuntimeException;
/*     */     //   93: athrow
/*     */     //   94: aload_0
/*     */     //   95: aload #9
/*     */     //   97: ifnonnull -> 133
/*     */     //   100: getfield h : Ljava/util/List;
/*     */     //   103: ifnonnull -> 134
/*     */     //   106: goto -> 119
/*     */     //   109: ldc2_w -8341447294806779348
/*     */     //   112: lload_1
/*     */     //   113: <illegal opcode> w : (Ljava/lang/RuntimeException;JJ)Ljava/lang/RuntimeException;
/*     */     //   118: athrow
/*     */     //   119: aload_0
/*     */     //   120: goto -> 133
/*     */     //   123: ldc2_w -8341447294806779348
/*     */     //   126: lload_1
/*     */     //   127: <illegal opcode> w : (Ljava/lang/RuntimeException;JJ)Ljava/lang/RuntimeException;
/*     */     //   132: athrow
/*     */     //   133: areturn
/*     */     //   134: aload_3
/*     */     //   135: sipush #17700
/*     */     //   138: ldc2_w 936238951748647645
/*     */     //   141: lload_1
/*     */     //   142: lxor
/*     */     //   143: <illegal opcode> c : (IJ)Ljava/lang/String;
/*     */     //   148: lload #7
/*     */     //   150: iconst_0
/*     */     //   151: iconst_0
/*     */     //   152: iconst_1
/*     */     //   153: iconst_1
/*     */     //   154: invokestatic a : (Ljava/lang/String;Ljava/lang/String;JZZZZ)Ljava/lang/String;
/*     */     //   157: astore #10
/*     */     //   159: aload_0
/*     */     //   160: aload #10
/*     */     //   162: iload #4
/*     */     //   164: i2c
/*     */     //   165: iload #5
/*     */     //   167: i2c
/*     */     //   168: iload #6
/*     */     //   170: invokespecial a : (Ljava/lang/String;CCI)V
/*     */     //   173: aload_0
/*     */     //   174: areturn
/*     */     // Line number table:
/*     */     //   Java source line number -> byte code offset
/*     */     //   #294	-> 59
/*     */     //   #24	-> 94
/*     */     //   #45	-> 134
/*     */     //   #147	-> 159
/*     */     //   #149	-> 173
/*     */     // Exception table:
/*     */     //   from	to	target	type
/*     */     //   59	84	84	java/lang/NullPointerException
/*     */     //   94	106	109	java/lang/NullPointerException
/*     */     //   100	120	123	java/lang/NullPointerException
/*     */   }
/*     */   
/*     */   int a(long paramLong) {
/*     */     // Byte code:
/*     */     //   0: getstatic me/konsolas/aac/j5.j : J
/*     */     //   3: lload_1
/*     */     //   4: lxor
/*     */     //   5: lstore_1
/*     */     //   6: lload_1
/*     */     //   7: dup2
/*     */     //   8: ldc2_w 26753469224532
/*     */     //   11: lxor
/*     */     //   12: dup2
/*     */     //   13: bipush #48
/*     */     //   15: lushr
/*     */     //   16: l2i
/*     */     //   17: istore_3
/*     */     //   18: dup2
/*     */     //   19: bipush #16
/*     */     //   21: lshl
/*     */     //   22: bipush #16
/*     */     //   24: lushr
/*     */     //   25: lstore #4
/*     */     //   27: pop2
/*     */     //   28: pop2
/*     */     //   29: ldc2_w -9194381082364706652
/*     */     //   32: lload_1
/*     */     //   33: <illegal opcode> w : (JJ)[Lme/konsolas/aac/aN;
/*     */     //   38: astore #6
/*     */     //   40: aload_0
/*     */     //   41: aload #6
/*     */     //   43: ifnonnull -> 84
/*     */     //   46: getfield e : I
/*     */     //   49: iconst_m1
/*     */     //   50: if_icmpeq -> 83
/*     */     //   53: goto -> 66
/*     */     //   56: ldc2_w -9201386502906898849
/*     */     //   59: lload_1
/*     */     //   60: <illegal opcode> w : (Ljava/lang/RuntimeException;JJ)Ljava/lang/RuntimeException;
/*     */     //   65: athrow
/*     */     //   66: aload_0
/*     */     //   67: getfield e : I
/*     */     //   70: goto -> 94
/*     */     //   73: ldc2_w -9201386502906898849
/*     */     //   76: lload_1
/*     */     //   77: <illegal opcode> w : (Ljava/lang/RuntimeException;JJ)Ljava/lang/RuntimeException;
/*     */     //   82: athrow
/*     */     //   83: aload_0
/*     */     //   84: getfield c : Ljava/lang/String;
/*     */     //   87: iload_3
/*     */     //   88: i2s
/*     */     //   89: lload #4
/*     */     //   91: invokestatic a : (Ljava/lang/String;SJ)I
/*     */     //   94: ireturn
/*     */     // Line number table:
/*     */     //   Java source line number -> byte code offset
/*     */     //   #304	-> 40
/*     */     // Exception table:
/*     */     //   from	to	target	type
/*     */     //   40	53	56	java/lang/NullPointerException
/*     */     //   46	73	73	java/lang/NullPointerException
/*     */   }
/*     */   
/*     */   public j5 b(int paramInt, long paramLong, String paramString) {
/*     */     // Byte code:
/*     */     //   0: getstatic me/konsolas/aac/j5.j : J
/*     */     //   3: lload_2
/*     */     //   4: lxor
/*     */     //   5: lstore_2
/*     */     //   6: lload_2
/*     */     //   7: dup2
/*     */     //   8: ldc2_w 57795636342543
/*     */     //   11: lxor
/*     */     //   12: dup2
/*     */     //   13: bipush #32
/*     */     //   15: lushr
/*     */     //   16: l2i
/*     */     //   17: istore #5
/*     */     //   19: dup2
/*     */     //   20: bipush #32
/*     */     //   22: lshl
/*     */     //   23: bipush #32
/*     */     //   25: lushr
/*     */     //   26: lstore #6
/*     */     //   28: pop2
/*     */     //   29: dup2
/*     */     //   30: ldc2_w 45652251699017
/*     */     //   33: lxor
/*     */     //   34: lstore #8
/*     */     //   36: dup2
/*     */     //   37: ldc2_w 68947020209303
/*     */     //   40: lxor
/*     */     //   41: lstore #10
/*     */     //   43: pop2
/*     */     //   44: ldc2_w 5074010641750247080
/*     */     //   47: lload_2
/*     */     //   48: <illegal opcode> w : (JJ)[Lme/konsolas/aac/aN;
/*     */     //   53: astore #12
/*     */     //   55: aload #4
/*     */     //   57: aload #12
/*     */     //   59: ifnonnull -> 142
/*     */     //   62: ifnonnull -> 109
/*     */     //   65: goto -> 78
/*     */     //   68: ldc2_w 5062720459560112211
/*     */     //   71: lload_2
/*     */     //   72: <illegal opcode> w : (Ljava/lang/RuntimeException;JJ)Ljava/lang/RuntimeException;
/*     */     //   77: athrow
/*     */     //   78: new java/lang/NullPointerException
/*     */     //   81: dup
/*     */     //   82: sipush #19107
/*     */     //   85: ldc2_w 5999113677913063225
/*     */     //   88: lload_2
/*     */     //   89: lxor
/*     */     //   90: <illegal opcode> c : (IJ)Ljava/lang/String;
/*     */     //   95: invokespecial <init> : (Ljava/lang/String;)V
/*     */     //   98: athrow
/*     */     //   99: ldc2_w 5062720459560112211
/*     */     //   102: lload_2
/*     */     //   103: <illegal opcode> w : (Ljava/lang/RuntimeException;JJ)Ljava/lang/RuntimeException;
/*     */     //   108: athrow
/*     */     //   109: iload #5
/*     */     //   111: aload #4
/*     */     //   113: iconst_0
/*     */     //   114: aload #4
/*     */     //   116: invokevirtual length : ()I
/*     */     //   119: sipush #16188
/*     */     //   122: ldc2_w 4480620987643005607
/*     */     //   125: lload_2
/*     */     //   126: lxor
/*     */     //   127: <illegal opcode> c : (IJ)Ljava/lang/String;
/*     */     //   132: iconst_0
/*     */     //   133: iconst_0
/*     */     //   134: iconst_0
/*     */     //   135: iconst_1
/*     */     //   136: aconst_null
/*     */     //   137: lload #6
/*     */     //   139: invokestatic a : (ILjava/lang/String;IILjava/lang/String;ZZZZLjava/nio/charset/Charset;J)Ljava/lang/String;
/*     */     //   142: astore #13
/*     */     //   144: aload_0
/*     */     //   145: lload #8
/*     */     //   147: aload #13
/*     */     //   149: invokespecial a : (JLjava/lang/String;)Z
/*     */     //   152: lload_2
/*     */     //   153: lconst_0
/*     */     //   154: lcmp
/*     */     //   155: ifle -> 218
/*     */     //   158: aload #12
/*     */     //   160: ifnonnull -> 218
/*     */     //   163: ifne -> 221
/*     */     //   166: goto -> 179
/*     */     //   169: ldc2_w 5062720459560112211
/*     */     //   172: lload_2
/*     */     //   173: <illegal opcode> w : (Ljava/lang/RuntimeException;JJ)Ljava/lang/RuntimeException;
/*     */     //   178: athrow
/*     */     //   179: aload_0
/*     */     //   180: aload #12
/*     */     //   182: ifnonnull -> 284
/*     */     //   185: goto -> 198
/*     */     //   188: ldc2_w 5062720459560112211
/*     */     //   191: lload_2
/*     */     //   192: <illegal opcode> w : (Ljava/lang/RuntimeException;JJ)Ljava/lang/RuntimeException;
/*     */     //   197: athrow
/*     */     //   198: aload #13
/*     */     //   200: lload #10
/*     */     //   202: invokespecial b : (Ljava/lang/String;J)Z
/*     */     //   205: goto -> 218
/*     */     //   208: ldc2_w 5062720459560112211
/*     */     //   211: lload_2
/*     */     //   212: <illegal opcode> w : (Ljava/lang/RuntimeException;JJ)Ljava/lang/RuntimeException;
/*     */     //   217: athrow
/*     */     //   218: ifeq -> 270
/*     */     //   221: new java/lang/IllegalArgumentException
/*     */     //   224: dup
/*     */     //   225: new java/lang/StringBuilder
/*     */     //   228: dup
/*     */     //   229: invokespecial <init> : ()V
/*     */     //   232: sipush #12715
/*     */     //   235: ldc2_w 6201125822353179650
/*     */     //   238: lload_2
/*     */     //   239: lxor
/*     */     //   240: <illegal opcode> c : (IJ)Ljava/lang/String;
/*     */     //   245: invokevirtual append : (Ljava/lang/String;)Ljava/lang/StringBuilder;
/*     */     //   248: aload #4
/*     */     //   250: invokevirtual append : (Ljava/lang/String;)Ljava/lang/StringBuilder;
/*     */     //   253: invokevirtual toString : ()Ljava/lang/String;
/*     */     //   256: invokespecial <init> : (Ljava/lang/String;)V
/*     */     //   259: athrow
/*     */     //   260: ldc2_w 5062720459560112211
/*     */     //   263: lload_2
/*     */     //   264: <illegal opcode> w : (Ljava/lang/RuntimeException;JJ)Ljava/lang/RuntimeException;
/*     */     //   269: athrow
/*     */     //   270: aload_0
/*     */     //   271: getfield i : Ljava/util/List;
/*     */     //   274: iload_1
/*     */     //   275: aload #13
/*     */     //   277: invokeinterface set : (ILjava/lang/Object;)Ljava/lang/Object;
/*     */     //   282: pop
/*     */     //   283: aload_0
/*     */     //   284: areturn
/*     */     // Line number table:
/*     */     //   Java source line number -> byte code offset
/*     */     //   #306	-> 55
/*     */     //   #158	-> 109
/*     */     //   #145	-> 144
/*     */     //   #169	-> 221
/*     */     //   #80	-> 270
/*     */     //   #165	-> 283
/*     */     // Exception table:
/*     */     //   from	to	target	type
/*     */     //   55	65	68	java/lang/NullPointerException
/*     */     //   62	99	99	java/lang/NullPointerException
/*     */     //   144	166	169	java/lang/NullPointerException
/*     */     //   163	185	188	java/lang/NullPointerException
/*     */     //   179	205	208	java/lang/NullPointerException
/*     */     //   218	260	260	java/lang/NullPointerException
/*     */   }
/*     */   
/*     */   j5 a(long paramLong) {
/*     */     // Byte code:
/*     */     //   0: getstatic me/konsolas/aac/j5.j : J
/*     */     //   3: lload_1
/*     */     //   4: lxor
/*     */     //   5: lstore_1
/*     */     //   6: lload_1
/*     */     //   7: dup2
/*     */     //   8: ldc2_w 129863151958330
/*     */     //   11: lxor
/*     */     //   12: lstore_3
/*     */     //   13: pop2
/*     */     //   14: ldc2_w -3179325884419550430
/*     */     //   17: lload_1
/*     */     //   18: <illegal opcode> w : (JJ)[Lme/konsolas/aac/aN;
/*     */     //   23: iconst_0
/*     */     //   24: istore #6
/*     */     //   26: astore #5
/*     */     //   28: aload_0
/*     */     //   29: getfield i : Ljava/util/List;
/*     */     //   32: invokeinterface size : ()I
/*     */     //   37: istore #7
/*     */     //   39: iload #6
/*     */     //   41: iload #7
/*     */     //   43: if_icmpge -> 135
/*     */     //   46: aload_0
/*     */     //   47: getfield i : Ljava/util/List;
/*     */     //   50: iload #6
/*     */     //   52: invokeinterface get : (I)Ljava/lang/Object;
/*     */     //   57: checkcast java/lang/String
/*     */     //   60: astore #8
/*     */     //   62: aload_0
/*     */     //   63: getfield i : Ljava/util/List;
/*     */     //   66: iload #6
/*     */     //   68: aload #8
/*     */     //   70: sipush #922
/*     */     //   73: ldc2_w 5199142318895539077
/*     */     //   76: lload_1
/*     */     //   77: lxor
/*     */     //   78: <illegal opcode> c : (IJ)Ljava/lang/String;
/*     */     //   83: lload_3
/*     */     //   84: iconst_1
/*     */     //   85: iconst_1
/*     */     //   86: iconst_0
/*     */     //   87: iconst_1
/*     */     //   88: invokestatic a : (Ljava/lang/String;Ljava/lang/String;JZZZZ)Ljava/lang/String;
/*     */     //   91: invokeinterface set : (ILjava/lang/Object;)Ljava/lang/Object;
/*     */     //   96: pop
/*     */     //   97: iinc #6, 1
/*     */     //   100: aload #5
/*     */     //   102: lload_1
/*     */     //   103: lconst_0
/*     */     //   104: lcmp
/*     */     //   105: iflt -> 113
/*     */     //   108: ifnonnull -> 312
/*     */     //   111: aload #5
/*     */     //   113: ifnull -> 39
/*     */     //   116: lload_1
/*     */     //   117: lconst_0
/*     */     //   118: lcmp
/*     */     //   119: ifle -> 100
/*     */     //   122: goto -> 135
/*     */     //   125: ldc2_w -3186253479923792423
/*     */     //   128: lload_1
/*     */     //   129: <illegal opcode> w : (Ljava/lang/RuntimeException;JJ)Ljava/lang/RuntimeException;
/*     */     //   134: athrow
/*     */     //   135: aload_0
/*     */     //   136: aload #5
/*     */     //   138: lload_1
/*     */     //   139: lconst_0
/*     */     //   140: lcmp
/*     */     //   141: iflt -> 315
/*     */     //   144: ifnonnull -> 313
/*     */     //   147: getfield h : Ljava/util/List;
/*     */     //   150: ifnull -> 312
/*     */     //   153: goto -> 166
/*     */     //   156: ldc2_w -3186253479923792423
/*     */     //   159: lload_1
/*     */     //   160: <illegal opcode> w : (Ljava/lang/RuntimeException;JJ)Ljava/lang/RuntimeException;
/*     */     //   165: athrow
/*     */     //   166: iconst_0
/*     */     //   167: istore #6
/*     */     //   169: aload_0
/*     */     //   170: getfield h : Ljava/util/List;
/*     */     //   173: invokeinterface size : ()I
/*     */     //   178: istore #7
/*     */     //   180: iload #6
/*     */     //   182: iload #7
/*     */     //   184: if_icmpge -> 312
/*     */     //   187: aload_0
/*     */     //   188: getfield h : Ljava/util/List;
/*     */     //   191: iload #6
/*     */     //   193: invokeinterface get : (I)Ljava/lang/Object;
/*     */     //   198: checkcast java/lang/String
/*     */     //   201: astore #8
/*     */     //   203: aload #5
/*     */     //   205: lload_1
/*     */     //   206: lconst_0
/*     */     //   207: lcmp
/*     */     //   208: ifle -> 309
/*     */     //   211: ifnonnull -> 307
/*     */     //   214: aload #8
/*     */     //   216: lload_1
/*     */     //   217: lconst_0
/*     */     //   218: lcmp
/*     */     //   219: ifle -> 334
/*     */     //   222: aload #5
/*     */     //   224: ifnonnull -> 334
/*     */     //   227: goto -> 240
/*     */     //   230: ldc2_w -3186253479923792423
/*     */     //   233: lload_1
/*     */     //   234: <illegal opcode> w : (Ljava/lang/RuntimeException;JJ)Ljava/lang/RuntimeException;
/*     */     //   239: athrow
/*     */     //   240: ifnull -> 304
/*     */     //   243: goto -> 256
/*     */     //   246: ldc2_w -3186253479923792423
/*     */     //   249: lload_1
/*     */     //   250: <illegal opcode> w : (Ljava/lang/RuntimeException;JJ)Ljava/lang/RuntimeException;
/*     */     //   255: athrow
/*     */     //   256: aload_0
/*     */     //   257: getfield h : Ljava/util/List;
/*     */     //   260: iload #6
/*     */     //   262: aload #8
/*     */     //   264: sipush #29044
/*     */     //   267: ldc2_w 2091084486355931461
/*     */     //   270: lload_1
/*     */     //   271: lxor
/*     */     //   272: <illegal opcode> c : (IJ)Ljava/lang/String;
/*     */     //   277: lload_3
/*     */     //   278: iconst_1
/*     */     //   279: iconst_1
/*     */     //   280: iconst_1
/*     */     //   281: iconst_1
/*     */     //   282: invokestatic a : (Ljava/lang/String;Ljava/lang/String;JZZZZ)Ljava/lang/String;
/*     */     //   285: invokeinterface set : (ILjava/lang/Object;)Ljava/lang/Object;
/*     */     //   290: pop
/*     */     //   291: goto -> 304
/*     */     //   294: ldc2_w -3186253479923792423
/*     */     //   297: lload_1
/*     */     //   298: <illegal opcode> w : (Ljava/lang/RuntimeException;JJ)Ljava/lang/RuntimeException;
/*     */     //   303: athrow
/*     */     //   304: iinc #6, 1
/*     */     //   307: aload #5
/*     */     //   309: ifnull -> 180
/*     */     //   312: aload_0
/*     */     //   313: aload #5
/*     */     //   315: ifnonnull -> 380
/*     */     //   318: getfield d : Ljava/lang/String;
/*     */     //   321: goto -> 334
/*     */     //   324: ldc2_w -3186253479923792423
/*     */     //   327: lload_1
/*     */     //   328: <illegal opcode> w : (Ljava/lang/RuntimeException;JJ)Ljava/lang/RuntimeException;
/*     */     //   333: athrow
/*     */     //   334: ifnull -> 379
/*     */     //   337: aload_0
/*     */     //   338: aload_0
/*     */     //   339: getfield d : Ljava/lang/String;
/*     */     //   342: sipush #14777
/*     */     //   345: ldc2_w 2448047545150183845
/*     */     //   348: lload_1
/*     */     //   349: lxor
/*     */     //   350: <illegal opcode> c : (IJ)Ljava/lang/String;
/*     */     //   355: lload_3
/*     */     //   356: iconst_1
/*     */     //   357: iconst_1
/*     */     //   358: iconst_0
/*     */     //   359: iconst_0
/*     */     //   360: invokestatic a : (Ljava/lang/String;Ljava/lang/String;JZZZZ)Ljava/lang/String;
/*     */     //   363: putfield d : Ljava/lang/String;
/*     */     //   366: goto -> 379
/*     */     //   369: ldc2_w -3186253479923792423
/*     */     //   372: lload_1
/*     */     //   373: <illegal opcode> w : (Ljava/lang/RuntimeException;JJ)Ljava/lang/RuntimeException;
/*     */     //   378: athrow
/*     */     //   379: aload_0
/*     */     //   380: areturn
/*     */     // Line number table:
/*     */     //   Java source line number -> byte code offset
/*     */     //   #312	-> 23
/*     */     //   #125	-> 46
/*     */     //   #335	-> 62
/*     */     //   #267	-> 88
/*     */     //   #245	-> 91
/*     */     //   #167	-> 97
/*     */     //   #176	-> 135
/*     */     //   #303	-> 166
/*     */     //   #66	-> 187
/*     */     //   #134	-> 203
/*     */     //   #101	-> 256
/*     */     //   #187	-> 282
/*     */     //   #30	-> 285
/*     */     //   #290	-> 304
/*     */     //   #313	-> 312
/*     */     //   #195	-> 337
/*     */     //   #214	-> 379
/*     */     // Exception table:
/*     */     //   from	to	target	type
/*     */     //   62	116	125	java/lang/NullPointerException
/*     */     //   135	153	156	java/lang/NullPointerException
/*     */     //   203	227	230	java/lang/NullPointerException
/*     */     //   214	243	246	java/lang/NullPointerException
/*     */     //   240	291	294	java/lang/NullPointerException
/*     */     //   313	321	324	java/lang/NullPointerException
/*     */     //   334	366	369	java/lang/NullPointerException
/*     */   }
/*     */   
/*     */   public j5 n(@Nullable String paramString, long paramLong) {
/*     */     // Byte code:
/*     */     //   0: getstatic me/konsolas/aac/j5.j : J
/*     */     //   3: lload_2
/*     */     //   4: lxor
/*     */     //   5: lstore_2
/*     */     //   6: lload_2
/*     */     //   7: dup2
/*     */     //   8: ldc2_w 27279261951688
/*     */     //   11: lxor
/*     */     //   12: lstore #4
/*     */     //   14: pop2
/*     */     //   15: ldc2_w -8353424003246158640
/*     */     //   18: lload_2
/*     */     //   19: <illegal opcode> w : (JJ)[Lme/konsolas/aac/aN;
/*     */     //   24: astore #6
/*     */     //   26: aload_0
/*     */     //   27: aload_1
/*     */     //   28: aload #6
/*     */     //   30: ifnonnull -> 74
/*     */     //   33: ifnull -> 77
/*     */     //   36: goto -> 49
/*     */     //   39: ldc2_w -8342274528441329109
/*     */     //   42: lload_2
/*     */     //   43: <illegal opcode> w : (Ljava/lang/RuntimeException;JJ)Ljava/lang/RuntimeException;
/*     */     //   48: athrow
/*     */     //   49: aload_1
/*     */     //   50: ldc ''
/*     */     //   52: lload #4
/*     */     //   54: iconst_1
/*     */     //   55: iconst_0
/*     */     //   56: iconst_0
/*     */     //   57: iconst_0
/*     */     //   58: invokestatic a : (Ljava/lang/String;Ljava/lang/String;JZZZZ)Ljava/lang/String;
/*     */     //   61: goto -> 74
/*     */     //   64: ldc2_w -8342274528441329109
/*     */     //   67: lload_2
/*     */     //   68: <illegal opcode> w : (Ljava/lang/RuntimeException;JJ)Ljava/lang/RuntimeException;
/*     */     //   73: athrow
/*     */     //   74: goto -> 78
/*     */     //   77: aconst_null
/*     */     //   78: putfield d : Ljava/lang/String;
/*     */     //   81: aload_0
/*     */     //   82: areturn
/*     */     // Line number table:
/*     */     //   Java source line number -> byte code offset
/*     */     //   #331	-> 26
/*     */     //   #49	-> 49
/*     */     //   #205	-> 77
/*     */     //   #146	-> 81
/*     */     // Exception table:
/*     */     //   from	to	target	type
/*     */     //   26	36	39	java/lang/NullPointerException
/*     */     //   33	61	64	java/lang/NullPointerException
/*     */   }
/*     */   
/*     */   static {
/*     */     long l = j ^ 0x549AD6DAD3FAL;
/*     */     "퀣?︠쉖ﴛ?﫭驖⪧횗ㆩ삱㖤톯쇩ῨߩΕ齅㸠".toCharArray()[8] = (char)("퀣?︠쉖ﴛ?﫭驖⪧횗ㆩ삱㖤톯쇩ῨߩΕ齅㸠".toCharArray()[8] ^ 0x7E8B);
/*     */     "❇瓻ğ嫢".toCharArray()[1] = (char)("❇瓻ğ嫢".toCharArray()[1] ^ 0x1BE9);
/*     */     (new byte[8])[0] = (byte)(int)(l >>> 56L);
/*     */     for (byte b1 = 1; b1 < 8; b1++)
/*     */       (new byte[8])[b1] = (byte)(int)(l << b1 * 8 >>> 56L); 
/*     */     Cipher cipher;
/*     */     (cipher = Cipher.getInstance(dP$dt.X("퀣?︠쉖ﴛ?﫭驖⪧횗ㆩ삱㖤톯쇩ῨߩΕ齅㸠".toCharArray(), (short)23665, true, false))).init(2, SecretKeyFactory.getInstance(dP$dt.X("❇瓻ğ嫢".toCharArray(), (short)11203, false, false)).generateSecret(new DESKeySpec(new byte[8])), new IvParameterSpec(new byte[8]));
/*     */     String[] arrayOfString = new String[64];
/*     */     boolean bool = false;
/*     */     "诅塬樂衜䤨⳵࿅蜾觰왛ꊤⲷ퓶⚜衺葩勻偿흖䮴쨍ऊ虔⭲㐣訊⿧⍭㹮Ꮓ豋ﲣ瞞㪋㜲಑猤挼壛᧘뎉䜟㔪?삌ꨘ屶矣*纯珉㼛鳊閽뱏鞡룝솀㖛䘾徂賡ꮛ혳蚶鴬遨蘱趿褁㏁駙놻痎晇Tۗ覔ഝካꊀ퉊砍矬蹳⦍侭횧ử쓏᠇盩ѵ೓議ᕻ꼼ꢌꇲ蒝膰㒇羈谏㇅鐵視曦蠎?ꖶ表㴎䢠鷷婓忩罡ᔀꄛো꫶ᢁ?ᅩ៓⟈킦鱹횁尐쑀舙蒱뚐乽煵寿굉띘ꓚ篧薡᷂怫궔䛂焷蕿䦮䠊ꃒ좊堗䕨탛멌倄銜艋䧢ᔥ曔ꔚ欞슘檿뭔鿌┬谏ಳ쏺䆥帆豊陾呼쥷暚뀶⟛?둯舧櫥ᇆ嘩䊁鱔慮揰끸બ쯜캔撩鋮⏝ხ岠㹭ꨨ띸苰ᨒ䍋礜೴ᰑ㫏ᕚ⽬嗃䚩軷Ⳡ薈돓漢낋வ뛐ခ⥸斣慈轟六㕊?ﻐ鄟﷣酅뿞녫鄒蒡䊢ꚑ蘬肌荭㧱녣眇뤏閈ള䖑䧾譳ᢡ鱦័?㤇妛斡陚뷛銯찠쀣ࢢᱶ䜢繨绾梷뤢㘺䑛恃忄릹㯟瞐⼈஽⍗喨Ē䃬篳댷甍맬暭欦計섯㗚鼍ṓ짘鐒˵ꃀ⼜ஜż艤ྙﻄ㠳ᵑ?硒圉︅⒛ᮘ⻇孺人鈚捤媟뼳콯뚠㳦ᆊ쭭螌உච쫖豀肣ꎅ븜㦌曭࿢ṱ䆜牌ꊽﾹꆉ?≤頮ᾓ騌͎ꭗ祮鴊䙓̩뽵ʻ᫾መ碭?⨾姭퓰졙꬀죳㉔玲逯圛郂皣ꚱඞ쁧쐠슎헩켎／塜͍掯컀囋쏀⻚椊薹좷皖൵闦軉旴酦榛㌓ꞛ⯌ௌ痀?짍魄獮狰췡?欦߅᧷樾㍪餢銜?ጻ韔⅐罁⪄ഊ驂헹盧ࣹ毧斲Ԭ硩שּׁᘁ沺ⓠ蒂꪿ꀨ뗢쭉尟탬帀轢㮳⒂外⶝忝廢椿㌬ঙཬ吏뽌⥲룽䌧ᕣ䚇ꝝ樏䩩?㣪췛威㊕㖘႞懚逪槃٘䰸༼ΐ㞆㳚닊པ疝솊誥ꢮἁꙏ숁쏜쁾ꃚᢆỻ 岍＂碹럩쒶⸵犟梘虭撳䥚ꉥ琦搙גּ?फ़⸙뽚䴱ꢺ턍ꊂ膎餢閥珉ꏦ艽ꓧ࿨뜮⒤?멮꣘鉲鑇㷆褭?嶑毊䃒⥔闞媌榼䵱ۗㅬ챆韛ԑ甘夺汵?숥簨ᯘ阈䵇⡃蓧珹罿꓃跟⼮黆핖⡫౮넅梜m흙蠌⿧蛞鹭襗?簿뺅ꄦ惯즟镒斉톛닚깞無␸?鞗⮤駐퇍괓嫿痉❑峤뗍噉̌旁簶偱띄Ḇﲻ휌졦㇧렭㹦ᙘ♙娿닟莲ⰾ攏⊔?틍관藃졝賳쫴ㄣ폸祜৮ꕽ띗⥞馗ᄥ䵿Ꚃ挲Π꿛઴瞜놄ﰃ䴁战醗龎練愤뉾狹〬᪅ㅃ螔棷姉錬噏쟚洞鏺?퍖맢⵰줃覇戩坰ꑭⱉ鞚駙玷댁驥韇봓듦쵊歬ﳤ昙⩂䍛궫ᜓ娑᜕汃惘멕ᜡ㮅ᲁꓬ헙岑俺荻冧?Ƈꆀჽ삒薧씨䂗햑뺖턁⦢熆㔈ⲥ⠈?劶䒞뼧菸뛸⯐⅕隃鸵밁࠿⊡嬣⫕ࣆ貈녫杆㗭苎응懕烯ശ३喒앍줟ꕸࡒ맂먹뽎ﷶ嶕㔼蝖䈂乍㨱᤹魇ࠁ⋽ﯭ䍓겾ᆛቍ龡ꥣ旮뿃▼㭭ב謦胖럳?卐?辔缗䂦૙曪ꃽ穨㧆檂䯃䜻ὗœ委ꃽ靼ꓟ?蔸ἢ﮶䟎뚏ᅬ㼁尶䐜곞?錿㍆✎䦽ቐ뾌鰸㻮ᛇ洋嵒夗뚑?ꤓ윬핵鰓埧ﾘ癐躀?珶ؾ죍枦닱䜳ԇ⋕᛽汃꺶ڢ묎攮ힶ偪赗肝ⴄḔ㦴⹊赡莮?뀄龻⒬㟚Ꙃ굃嫊꿓啌熇⽔者겚뛠䄤䜄ञ뒳းࠎ퐌윷㞡䝍垂馺幣ｦ㣳첮弿褤❟ꈹ漅쯁㧸䤉?魑謔蟂騷ᷛ蟆聁ꏆᱦꦓ੦邩?ﶧ᭘⩀髐֡䏐掗듩爔䠨ᖗ冾員倽鼩裢缏뒽䲄괖뫞暂犖ꏾݞ쥷ኟ늃賈兕럙햀쉴畞쯛ኅ㘂婀⤞㻚첄䁠䮴김蔪咥๐䇬苹搂炚泍偰쳁䆫ᰀᎧᵚ㟎狴쀮彖?异㜱牃韔郪䂵箽?芏໬㡯塇᪇꽤ဲ׫楦뇯覶匳쁮쵿ಁᆷ廦䞿ﳚ㴳?䈞劯棩閤૿ࣚ諭う䚎液꽭䪔໴ꠐ쬓﫡◎搓唁ﺦ倬䭄酿궟ꘗ掁䠢഼낙՝瑌맓ಢៜ풥䦹젼ꕁ钧稬ႎ긓玣?⦒룺ൊ觫끽⭞홥浯泄緜썥ਲ਼쒪쫡璗檖湠펟糜䨫ဪ菰嵿員ﬆ煪溨◙㫫댔쏉⩉诿氈鉶祢磝逩椂딟㽘喦뙊腮⡨욹〦鞍Ɣ氰᩿継髒豲ワ靪ꄟ伴䥿뀆Ꙫ?盢찝碫?㈿蛲섀徥礊鹙䶉끰ꗵ고?㳐莢冻⥅줃?쬅㧐瓴ꔧ漆㲝㎆膍潎᪙券믣㔷箅ᖲ웣서Ｃ뺪娑灭蚕逴뷻慅瑈봠ꌥ童楂侼⏣ㅮꩃ⶞챜ܚᵕ=✺幊겠럺叼෵탓谗死䄴톄촩秲鲉蜘䓒嬲퐯ⵎ桤И᮶竧Ꭺ퉅噡䳽⼭⅍킧젞ꠜ쥿⦩纂炝낍힏Ꞑ㭰⤼⋸橔᥿묩㮱궟륮᠘跄軸଴뭉揹⟖셷⨕赙汿은⮀螙ፃ冺伷⊖⶞蜄㭘ꪩ옯촤쵯ӵ띯꥓甫됫઱틏䯐쪶퉡觟侨鬦⺿퓏睕?ұ褲嵊Ḧよ喈퉼Ξ테揞䚦蒜㎽Ⴇ䅲䨎㐂ⷄ䋑쁖䁃騍῾廐眠⑿쵍;羻㐞㔀ବ网⁄쟲䏧箬삤헺셀ퟠ꺝盙盉?獉ꕩ쬇柾滑纝踙鞫?섘簅쯸帶嬸떃怔纃礜暛걝♞ώ뵾ဪɭꝋ醼ꕒ䓸Ꮰᩢ綘ᆾ㱸⛿旪Ћ핃蟳֚袢ﱕØ㤕窈궹?兗缊֔絩圖ﶬנּ䲕洍຾꽤튫ሥꫜ࿌Ỽ༲툌돮㕟⣂৐⍦⹽偡겧솲쩰䱴ݴ逪墴훧왇쿔쨖ꁃ呕ང쁳딞괻२䭑汥㏨釂ᙍ﨔痣輣䭾ઓ곙扼?努陖꤬⣑낳ⓩ쬧ꪲ쾏꛾꫊똁튎雨骰鈷逵⩾碝輽㳔ሱ漜끾೒滬?㒾⚍榨㖀ཐ蓘酻唋馜㒚⇩ㆦⳫ䭄樹뷝뛅⩪휻풝쥜ཿ侈큘韾潶䇣䛖獻뉩ꌞᅰ?ۈ乫匇ꚕ袵ꀒₚ퇇띣퐿偏嚋㟱꯽䟯群溮촁㓳㾐蘆亠嫳鮛䓤㣑น၊艙愐Ǳ呏떔甦橽욊᫱卦즼㽾踉?멬畕ꂮ?綑飰ᦁ䦔ᣮͶ넦㺄狡逡憊鱝?믖⍁擲❂ꪤؤ㝍轶ﮁ눨Ｇ參?멪貌䆹ᡶ졮㺣畚㯋齃偶㜌᣶ࠁ蘡荋伍㬓윈흽％抺䵹恧몗쬸罣楹꬀䛩칆촩ȑ暞≢㸓뇙愗臉끆䗜벘㳈澋◚뚐칸굺䡌쐅굶캦㔼싊蓮⣕鶦䳖斉骇踅﬜呇艛?옜튙违舊煙침贒?⛌幆ꁟႸᯃ췸靳俥䓝㙬綂躩䀉꿋㚜ٳ鯌毀䵩⇔惍ݚ뤅ា儖껊揶䌪?긠愔⮹얾ﲳ䡳澞≕뜀愦㡚٥졅昲嵡㡈쑬ꎃꖢ췠⫮緪冘Ǫ鵤蘉ဂ⽤궼耑ꖜ㴰ꡋ싕ᩝ耭缅墔䈢嵕崲襳죑﷤㎶杷ᨶ䙎揈მ䟟䌧뀀㭁?嶀㸞쯺給襛嘌걄❵嗮༙孛ϖ硳튞߼酑ᒻ❝呄酴ᯯ仒ು蓵듮繠䚪䯢ᦞ㍠꫎⮟ഠ飝콜䧃樯头愺씟핷蛧ԧસ❰簝㡺蘜쐷손鐙趺戾ؽ⚔绖ꗞ밾醭གྷ询㰆␼赁쐴⬋䇼肘?ꎙ뒤ꃎꇵ砚衻稜柑珱풭ɔ?ᇈ嫎ꈙܲ廋訴͉ﾁꖮ묢䡯ꉖ뢡䮗溒퓡긁闗ᣕᝋ潌蹤䳂괌?侸칒滅⠕铎嘷嫞⬯풫ꉲ빎㽛紂潖ס༩츜?ﻔ：੓愇ᒒ睕῾咏筌叀ﶦ戙咺绘䰏荁฾嚞蟔￠࣒ဘ埬쭱琮ᤘ鐻ỵ缿眓ᮡ羈鈎쮇猪?븃?㹩".toCharArray()[645] = (char)("诅塬樂衜䤨⳵࿅蜾觰왛ꊤⲷ퓶⚜衺葩勻偿흖䮴쨍ऊ虔⭲㐣訊⿧⍭㹮Ꮓ豋ﲣ瞞㪋㜲಑猤挼壛᧘뎉䜟㔪?삌ꨘ屶矣*纯珉㼛鳊閽뱏鞡룝솀㖛䘾徂賡ꮛ혳蚶鴬遨蘱趿褁㏁駙놻痎晇Tۗ覔ഝካꊀ퉊砍矬蹳⦍侭횧ử쓏᠇盩ѵ೓議ᕻ꼼ꢌꇲ蒝膰㒇羈谏㇅鐵視曦蠎?ꖶ表㴎䢠鷷婓忩罡ᔀꄛো꫶ᢁ?ᅩ៓⟈킦鱹횁尐쑀舙蒱뚐乽煵寿굉띘ꓚ篧薡᷂怫궔䛂焷蕿䦮䠊ꃒ좊堗䕨탛멌倄銜艋䧢ᔥ曔ꔚ欞슘檿뭔鿌┬谏ಳ쏺䆥帆豊陾呼쥷暚뀶⟛?둯舧櫥ᇆ嘩䊁鱔慮揰끸બ쯜캔撩鋮⏝ხ岠㹭ꨨ띸苰ᨒ䍋礜೴ᰑ㫏ᕚ⽬嗃䚩軷Ⳡ薈돓漢낋வ뛐ခ⥸斣慈轟六㕊?ﻐ鄟﷣酅뿞녫鄒蒡䊢ꚑ蘬肌荭㧱녣眇뤏閈ള䖑䧾譳ᢡ鱦័?㤇妛斡陚뷛銯찠쀣ࢢᱶ䜢繨绾梷뤢㘺䑛恃忄릹㯟瞐⼈஽⍗喨Ē䃬篳댷甍맬暭欦計섯㗚鼍ṓ짘鐒˵ꃀ⼜ஜż艤ྙﻄ㠳ᵑ?硒圉︅⒛ᮘ⻇孺人鈚捤媟뼳콯뚠㳦ᆊ쭭螌உච쫖豀肣ꎅ븜㦌曭࿢ṱ䆜牌ꊽﾹꆉ?≤頮ᾓ騌͎ꭗ祮鴊䙓̩뽵ʻ᫾መ碭?⨾姭퓰졙꬀죳㉔玲逯圛郂皣ꚱඞ쁧쐠슎헩켎／塜͍掯컀囋쏀⻚椊薹좷皖൵闦軉旴酦榛㌓ꞛ⯌ௌ痀?짍魄獮狰췡?欦߅᧷樾㍪餢銜?ጻ韔⅐罁⪄ഊ驂헹盧ࣹ毧斲Ԭ硩שּׁᘁ沺ⓠ蒂꪿ꀨ뗢쭉尟탬帀轢㮳⒂外⶝忝廢椿㌬ঙཬ吏뽌⥲룽䌧ᕣ䚇ꝝ樏䩩?㣪췛威㊕㖘႞懚逪槃٘䰸༼ΐ㞆㳚닊པ疝솊誥ꢮἁꙏ숁쏜쁾ꃚᢆỻ 岍＂碹럩쒶⸵犟梘虭撳䥚ꉥ琦搙גּ?फ़⸙뽚䴱ꢺ턍ꊂ膎餢閥珉ꏦ艽ꓧ࿨뜮⒤?멮꣘鉲鑇㷆褭?嶑毊䃒⥔闞媌榼䵱ۗㅬ챆韛ԑ甘夺汵?숥簨ᯘ阈䵇⡃蓧珹罿꓃跟⼮黆핖⡫౮넅梜m흙蠌⿧蛞鹭襗?簿뺅ꄦ惯즟镒斉톛닚깞無␸?鞗⮤駐퇍괓嫿痉❑峤뗍噉̌旁簶偱띄Ḇﲻ휌졦㇧렭㹦ᙘ♙娿닟莲ⰾ攏⊔?틍관藃졝賳쫴ㄣ폸祜৮ꕽ띗⥞馗ᄥ䵿Ꚃ挲Π꿛઴瞜놄ﰃ䴁战醗龎練愤뉾狹〬᪅ㅃ螔棷姉錬噏쟚洞鏺?퍖맢⵰줃覇戩坰ꑭⱉ鞚駙玷댁驥韇봓듦쵊歬ﳤ昙⩂䍛궫ᜓ娑᜕汃惘멕ᜡ㮅ᲁꓬ헙岑俺荻冧?Ƈꆀჽ삒薧씨䂗햑뺖턁⦢熆㔈ⲥ⠈?劶䒞뼧菸뛸⯐⅕隃鸵밁࠿⊡嬣⫕ࣆ貈녫杆㗭苎응懕烯ശ३喒앍줟ꕸࡒ맂먹뽎ﷶ嶕㔼蝖䈂乍㨱᤹魇ࠁ⋽ﯭ䍓겾ᆛቍ龡ꥣ旮뿃▼㭭ב謦胖럳?卐?辔缗䂦૙曪ꃽ穨㧆檂䯃䜻ὗœ委ꃽ靼ꓟ?蔸ἢ﮶䟎뚏ᅬ㼁尶䐜곞?錿㍆✎䦽ቐ뾌鰸㻮ᛇ洋嵒夗뚑?ꤓ윬핵鰓埧ﾘ癐躀?珶ؾ죍枦닱䜳ԇ⋕᛽汃꺶ڢ묎攮ힶ偪赗肝ⴄḔ㦴⹊赡莮?뀄龻⒬㟚Ꙃ굃嫊꿓啌熇⽔者겚뛠䄤䜄ञ뒳းࠎ퐌윷㞡䝍垂馺幣ｦ㣳첮弿褤❟ꈹ漅쯁㧸䤉?魑謔蟂騷ᷛ蟆聁ꏆᱦꦓ੦邩?ﶧ᭘⩀髐֡䏐掗듩爔䠨ᖗ冾員倽鼩裢缏뒽䲄괖뫞暂犖ꏾݞ쥷ኟ늃賈兕럙햀쉴畞쯛ኅ㘂婀⤞㻚첄䁠䮴김蔪咥๐䇬苹搂炚泍偰쳁䆫ᰀᎧᵚ㟎狴쀮彖?异㜱牃韔郪䂵箽?芏໬㡯塇᪇꽤ဲ׫楦뇯覶匳쁮쵿ಁᆷ廦䞿ﳚ㴳?䈞劯棩閤૿ࣚ諭う䚎液꽭䪔໴ꠐ쬓﫡◎搓唁ﺦ倬䭄酿궟ꘗ掁䠢഼낙՝瑌맓ಢៜ풥䦹젼ꕁ钧稬ႎ긓玣?⦒룺ൊ觫끽⭞홥浯泄緜썥ਲ਼쒪쫡璗檖湠펟糜䨫ဪ菰嵿員ﬆ煪溨◙㫫댔쏉⩉诿氈鉶祢磝逩椂딟㽘喦뙊腮⡨욹〦鞍Ɣ氰᩿継髒豲ワ靪ꄟ伴䥿뀆Ꙫ?盢찝碫?㈿蛲섀徥礊鹙䶉끰ꗵ고?㳐莢冻⥅줃?쬅㧐瓴ꔧ漆㲝㎆膍潎᪙券믣㔷箅ᖲ웣서Ｃ뺪娑灭蚕逴뷻慅瑈봠ꌥ童楂侼⏣ㅮꩃ⶞챜ܚᵕ=✺幊겠럺叼෵탓谗死䄴톄촩秲鲉蜘䓒嬲퐯ⵎ桤И᮶竧Ꭺ퉅噡䳽⼭⅍킧젞ꠜ쥿⦩纂炝낍힏Ꞑ㭰⤼⋸橔᥿묩㮱궟륮᠘跄軸଴뭉揹⟖셷⨕赙汿은⮀螙ፃ冺伷⊖⶞蜄㭘ꪩ옯촤쵯ӵ띯꥓甫됫઱틏䯐쪶퉡觟侨鬦⺿퓏睕?ұ褲嵊Ḧよ喈퉼Ξ테揞䚦蒜㎽Ⴇ䅲䨎㐂ⷄ䋑쁖䁃騍῾廐眠⑿쵍;羻㐞㔀ବ网⁄쟲䏧箬삤헺셀ퟠ꺝盙盉?獉ꕩ쬇柾滑纝踙鞫?섘簅쯸帶嬸떃怔纃礜暛걝♞ώ뵾ဪɭꝋ醼ꕒ䓸Ꮰᩢ綘ᆾ㱸⛿旪Ћ핃蟳֚袢ﱕØ㤕窈궹?兗缊֔絩圖ﶬנּ䲕洍຾꽤튫ሥꫜ࿌Ỽ༲툌돮㕟⣂৐⍦⹽偡겧솲쩰䱴ݴ逪墴훧왇쿔쨖ꁃ呕ང쁳딞괻२䭑汥㏨釂ᙍ﨔痣輣䭾ઓ곙扼?努陖꤬⣑낳ⓩ쬧ꪲ쾏꛾꫊똁튎雨骰鈷逵⩾碝輽㳔ሱ漜끾೒滬?㒾⚍榨㖀ཐ蓘酻唋馜㒚⇩ㆦⳫ䭄樹뷝뛅⩪휻풝쥜ཿ侈큘韾潶䇣䛖獻뉩ꌞᅰ?ۈ乫匇ꚕ袵ꀒₚ퇇띣퐿偏嚋㟱꯽䟯群溮촁㓳㾐蘆亠嫳鮛䓤㣑น၊艙愐Ǳ呏떔甦橽욊᫱卦즼㽾踉?멬畕ꂮ?綑飰ᦁ䦔ᣮͶ넦㺄狡逡憊鱝?믖⍁擲❂ꪤؤ㝍轶ﮁ눨Ｇ參?멪貌䆹ᡶ졮㺣畚㯋齃偶㜌᣶ࠁ蘡荋伍㬓윈흽％抺䵹恧몗쬸罣楹꬀䛩칆촩ȑ暞≢㸓뇙愗臉끆䗜벘㳈澋◚뚐칸굺䡌쐅굶캦㔼싊蓮⣕鶦䳖斉骇踅﬜呇艛?옜튙违舊煙침贒?⛌幆ꁟႸᯃ췸靳俥䓝㙬綂躩䀉꿋㚜ٳ鯌毀䵩⇔惍ݚ뤅ា儖껊揶䌪?긠愔⮹얾ﲳ䡳澞≕뜀愦㡚٥졅昲嵡㡈쑬ꎃꖢ췠⫮緪冘Ǫ鵤蘉ဂ⽤궼耑ꖜ㴰ꡋ싕ᩝ耭缅墔䈢嵕崲襳죑﷤㎶杷ᨶ䙎揈მ䟟䌧뀀㭁?嶀㸞쯺給襛嘌걄❵嗮༙孛ϖ硳튞߼酑ᒻ❝呄酴ᯯ仒ು蓵듮繠䚪䯢ᦞ㍠꫎⮟ഠ飝콜䧃樯头愺씟핷蛧ԧસ❰簝㡺蘜쐷손鐙趺戾ؽ⚔绖ꗞ밾醭གྷ询㰆␼赁쐴⬋䇼肘?ꎙ뒤ꃎꇵ砚衻稜柑珱풭ɔ?ᇈ嫎ꈙܲ廋訴͉ﾁꖮ묢䡯ꉖ뢡䮗溒퓡긁闗ᣕᝋ潌蹤䳂괌?侸칒滅⠕铎嘷嫞⬯풫ꉲ빎㽛紂潖ס༩츜?ﻔ：੓愇ᒒ睕῾咏筌叀ﶦ戙咺绘䰏荁฾嚞蟔￠࣒ဘ埬쭱琮ᤘ鐻ỵ缿眓ᮡ羈鈎쮇猪?븃?㹩".toCharArray()[645] ^ 0x62C6);
/*     */     String str;
/*     */     int i = (str = dP$dt.X("诅塬樂衜䤨⳵࿅蜾觰왛ꊤⲷ퓶⚜衺葩勻偿흖䮴쨍ऊ虔⭲㐣訊⿧⍭㹮Ꮓ豋ﲣ瞞㪋㜲಑猤挼壛᧘뎉䜟㔪?삌ꨘ屶矣*纯珉㼛鳊閽뱏鞡룝솀㖛䘾徂賡ꮛ혳蚶鴬遨蘱趿褁㏁駙놻痎晇Tۗ覔ഝካꊀ퉊砍矬蹳⦍侭횧ử쓏᠇盩ѵ೓議ᕻ꼼ꢌꇲ蒝膰㒇羈谏㇅鐵視曦蠎?ꖶ表㴎䢠鷷婓忩罡ᔀꄛো꫶ᢁ?ᅩ៓⟈킦鱹횁尐쑀舙蒱뚐乽煵寿굉띘ꓚ篧薡᷂怫궔䛂焷蕿䦮䠊ꃒ좊堗䕨탛멌倄銜艋䧢ᔥ曔ꔚ欞슘檿뭔鿌┬谏ಳ쏺䆥帆豊陾呼쥷暚뀶⟛?둯舧櫥ᇆ嘩䊁鱔慮揰끸બ쯜캔撩鋮⏝ხ岠㹭ꨨ띸苰ᨒ䍋礜೴ᰑ㫏ᕚ⽬嗃䚩軷Ⳡ薈돓漢낋வ뛐ခ⥸斣慈轟六㕊?ﻐ鄟﷣酅뿞녫鄒蒡䊢ꚑ蘬肌荭㧱녣眇뤏閈ള䖑䧾譳ᢡ鱦័?㤇妛斡陚뷛銯찠쀣ࢢᱶ䜢繨绾梷뤢㘺䑛恃忄릹㯟瞐⼈஽⍗喨Ē䃬篳댷甍맬暭欦計섯㗚鼍ṓ짘鐒˵ꃀ⼜ஜż艤ྙﻄ㠳ᵑ?硒圉︅⒛ᮘ⻇孺人鈚捤媟뼳콯뚠㳦ᆊ쭭螌உච쫖豀肣ꎅ븜㦌曭࿢ṱ䆜牌ꊽﾹꆉ?≤頮ᾓ騌͎ꭗ祮鴊䙓̩뽵ʻ᫾መ碭?⨾姭퓰졙꬀죳㉔玲逯圛郂皣ꚱඞ쁧쐠슎헩켎／塜͍掯컀囋쏀⻚椊薹좷皖൵闦軉旴酦榛㌓ꞛ⯌ௌ痀?짍魄獮狰췡?欦߅᧷樾㍪餢銜?ጻ韔⅐罁⪄ഊ驂헹盧ࣹ毧斲Ԭ硩שּׁᘁ沺ⓠ蒂꪿ꀨ뗢쭉尟탬帀轢㮳⒂外⶝忝廢椿㌬ঙཬ吏뽌⥲룽䌧ᕣ䚇ꝝ樏䩩?㣪췛威㊕㖘႞懚逪槃٘䰸༼ΐ㞆㳚닊པ疝솊誥ꢮἁꙏ숁쏜쁾ꃚᢆỻ 岍＂碹럩쒶⸵犟梘虭撳䥚ꉥ琦搙גּ?फ़⸙뽚䴱ꢺ턍ꊂ膎餢閥珉ꏦ艽ꓧ࿨뜮⒤?멮꣘鉲鑇㷆褭?嶑毊䃒⥔闞媌榼䵱ۗㅬ챆韛ԑ甘夺汵?숥簨ᯘ阈䵇⡃蓧珹罿꓃跟⼮黆핖⡫౮넅梜m흙蠌⿧蛞鹭襗?簿뺅ꄦ惯즟镒斉톛닚깞無␸?鞗⮤駐퇍괓嫿痉❑峤뗍噉̌旁簶偱띄Ḇﲻ휌졦㇧렭㹦ᙘ♙娿닟莲ⰾ攏⊔?틍관藃졝賳쫴ㄣ폸祜৮ꕽ띗⥞馗ᄥ䵿Ꚃ挲Π꿛઴瞜놄ﰃ䴁战醗龎練愤뉾狹〬᪅ㅃ螔棷姉錬噏쟚洞鏺?퍖맢⵰줃覇戩坰ꑭⱉ鞚駙玷댁驥韇봓듦쵊歬ﳤ昙⩂䍛궫ᜓ娑᜕汃惘멕ᜡ㮅ᲁꓬ헙岑俺荻冧?Ƈꆀჽ삒薧씨䂗햑뺖턁⦢熆㔈ⲥ⠈?劶䒞뼧菸뛸⯐⅕隃鸵밁࠿⊡嬣⫕ࣆ貈녫杆㗭苎응懕烯ശ३喒앍줟ꕸࡒ맂먹뽎ﷶ嶕㔼蝖䈂乍㨱᤹魇ࠁ⋽ﯭ䍓겾ᆛቍ龡ꥣ旮뿃▼㭭ב謦胖럳?卐?辔缗䂦૙曪ꃽ穨㧆檂䯃䜻ὗœ委ꃽ靼ꓟ?蔸ἢ﮶䟎뚏ᅬ㼁尶䐜곞?錿㍆✎䦽ቐ뾌鰸㻮ᛇ洋嵒夗뚑?ꤓ윬핵鰓埧ﾘ癐躀?珶ؾ죍枦닱䜳ԇ⋕᛽汃꺶ڢ묎攮ힶ偪赗肝ⴄḔ㦴⹊赡莮?뀄龻⒬㟚Ꙃ굃嫊꿓啌熇⽔者겚뛠䄤䜄ञ뒳းࠎ퐌윷㞡䝍垂馺幣ｦ㣳첮弿褤❟ꈹ漅쯁㧸䤉?魑謔蟂騷ᷛ蟆聁ꏆᱦꦓ੦邩?ﶧ᭘⩀髐֡䏐掗듩爔䠨ᖗ冾員倽鼩裢缏뒽䲄괖뫞暂犖ꏾݞ쥷ኟ늃賈兕럙햀쉴畞쯛ኅ㘂婀⤞㻚첄䁠䮴김蔪咥๐䇬苹搂炚泍偰쳁䆫ᰀᎧᵚ㟎狴쀮彖?异㜱牃韔郪䂵箽?芏໬㡯塇᪇꽤ဲ׫楦뇯覶匳쁮쵿ಁᆷ廦䞿ﳚ㴳?䈞劯棩閤૿ࣚ諭う䚎液꽭䪔໴ꠐ쬓﫡◎搓唁ﺦ倬䭄酿궟ꘗ掁䠢഼낙՝瑌맓ಢៜ풥䦹젼ꕁ钧稬ႎ긓玣?⦒룺ൊ觫끽⭞홥浯泄緜썥ਲ਼쒪쫡璗檖湠펟糜䨫ဪ菰嵿員ﬆ煪溨◙㫫댔쏉⩉诿氈鉶祢磝逩椂딟㽘喦뙊腮⡨욹〦鞍Ɣ氰᩿継髒豲ワ靪ꄟ伴䥿뀆Ꙫ?盢찝碫?㈿蛲섀徥礊鹙䶉끰ꗵ고?㳐莢冻⥅줃?쬅㧐瓴ꔧ漆㲝㎆膍潎᪙券믣㔷箅ᖲ웣서Ｃ뺪娑灭蚕逴뷻慅瑈봠ꌥ童楂侼⏣ㅮꩃ⶞챜ܚᵕ=✺幊겠럺叼෵탓谗死䄴톄촩秲鲉蜘䓒嬲퐯ⵎ桤И᮶竧Ꭺ퉅噡䳽⼭⅍킧젞ꠜ쥿⦩纂炝낍힏Ꞑ㭰⤼⋸橔᥿묩㮱궟륮᠘跄軸଴뭉揹⟖셷⨕赙汿은⮀螙ፃ冺伷⊖⶞蜄㭘ꪩ옯촤쵯ӵ띯꥓甫됫઱틏䯐쪶퉡觟侨鬦⺿퓏睕?ұ褲嵊Ḧよ喈퉼Ξ테揞䚦蒜㎽Ⴇ䅲䨎㐂ⷄ䋑쁖䁃騍῾廐眠⑿쵍;羻㐞㔀ବ网⁄쟲䏧箬삤헺셀ퟠ꺝盙盉?獉ꕩ쬇柾滑纝踙鞫?섘簅쯸帶嬸떃怔纃礜暛걝♞ώ뵾ဪɭꝋ醼ꕒ䓸Ꮰᩢ綘ᆾ㱸⛿旪Ћ핃蟳֚袢ﱕØ㤕窈궹?兗缊֔絩圖ﶬנּ䲕洍຾꽤튫ሥꫜ࿌Ỽ༲툌돮㕟⣂৐⍦⹽偡겧솲쩰䱴ݴ逪墴훧왇쿔쨖ꁃ呕ང쁳딞괻२䭑汥㏨釂ᙍ﨔痣輣䭾ઓ곙扼?努陖꤬⣑낳ⓩ쬧ꪲ쾏꛾꫊똁튎雨骰鈷逵⩾碝輽㳔ሱ漜끾೒滬?㒾⚍榨㖀ཐ蓘酻唋馜㒚⇩ㆦⳫ䭄樹뷝뛅⩪휻풝쥜ཿ侈큘韾潶䇣䛖獻뉩ꌞᅰ?ۈ乫匇ꚕ袵ꀒₚ퇇띣퐿偏嚋㟱꯽䟯群溮촁㓳㾐蘆亠嫳鮛䓤㣑น၊艙愐Ǳ呏떔甦橽욊᫱卦즼㽾踉?멬畕ꂮ?綑飰ᦁ䦔ᣮͶ넦㺄狡逡憊鱝?믖⍁擲❂ꪤؤ㝍轶ﮁ눨Ｇ參?멪貌䆹ᡶ졮㺣畚㯋齃偶㜌᣶ࠁ蘡荋伍㬓윈흽％抺䵹恧몗쬸罣楹꬀䛩칆촩ȑ暞≢㸓뇙愗臉끆䗜벘㳈澋◚뚐칸굺䡌쐅굶캦㔼싊蓮⣕鶦䳖斉骇踅﬜呇艛?옜튙违舊煙침贒?⛌幆ꁟႸᯃ췸靳俥䓝㙬綂躩䀉꿋㚜ٳ鯌毀䵩⇔惍ݚ뤅ា儖껊揶䌪?긠愔⮹얾ﲳ䡳澞≕뜀愦㡚٥졅昲嵡㡈쑬ꎃꖢ췠⫮緪冘Ǫ鵤蘉ဂ⽤궼耑ꖜ㴰ꡋ싕ᩝ耭缅墔䈢嵕崲襳죑﷤㎶杷ᨶ䙎揈მ䟟䌧뀀㭁?嶀㸞쯺給襛嘌걄❵嗮༙孛ϖ硳튞߼酑ᒻ❝呄酴ᯯ仒ು蓵듮繠䚪䯢ᦞ㍠꫎⮟ഠ飝콜䧃樯头愺씟핷蛧ԧસ❰簝㡺蘜쐷손鐙趺戾ؽ⚔绖ꗞ밾醭གྷ询㰆␼赁쐴⬋䇼肘?ꎙ뒤ꃎꇵ砚衻稜柑珱풭ɔ?ᇈ嫎ꈙܲ廋訴͉ﾁꖮ묢䡯ꉖ뢡䮗溒퓡긁闗ᣕᝋ潌蹤䳂괌?侸칒滅⠕铎嘷嫞⬯풫ꉲ빎㽛紂潖ס༩츜?ﻔ：੓愇ᒒ睕῾咏筌叀ﶦ戙咺绘䰏荁฾嚞蟔￠࣒ဘ埬쭱琮ᤘ鐻ỵ缿眓ᮡ羈鈎쮇猪?븃?㹩".toCharArray(), (short)5804, false, false)).length();
/*     */     byte b2 = 24;
/*     */     byte b = -1;
/*     */     while (true);
/*     */   }
/*     */   
/*     */   private static RuntimeException a(RuntimeException paramRuntimeException) {
/*     */     return paramRuntimeException;
/*     */   }
/*     */   
/*     */   private static String a(byte[] paramArrayOfbyte) {
/*     */     byte b1 = 0;
/*     */     int i;
/*     */     char[] arrayOfChar = new char[i = paramArrayOfbyte.length];
/*     */     for (byte b2 = 0; b2 < i; b2++) {
/*     */       int j;
/*     */       if ((j = 0xFF & paramArrayOfbyte[b2]) < 192) {
/*     */         arrayOfChar[b1++] = (char)j;
/*     */       } else if (j < 224) {
/*     */         char c = (char)((char)(j & 0x1F) << 6);
/*     */         j = paramArrayOfbyte[++b2];
/*     */         c = (char)(c | (char)(j & 0x3F));
/*     */         arrayOfChar[b1++] = c;
/*     */       } else if (b2 < i - 2) {
/*     */         char c = (char)((char)(j & 0xF) << 12);
/*     */         j = paramArrayOfbyte[++b2];
/*     */         c = (char)(c | (char)(j & 0x3F) << 6);
/*     */         j = paramArrayOfbyte[++b2];
/*     */         c = (char)(c | (char)(j & 0x3F));
/*     */         arrayOfChar[b1++] = c;
/*     */       } 
/*     */     } 
/*     */     return new String(arrayOfChar, 0, b1);
/*     */   }
/*     */   
/*     */   private static String a(int paramInt, long paramLong) {
/*     */     int i = paramInt ^ (int)(paramLong & 0x7FFFL) ^ 0x730D;
/*     */     if (l[i] == null) {
/*     */       Object[] arrayOfObject;
/*     */       try {
/*     */         Long long_ = Long.valueOf(Thread.currentThread().getId());
/*     */         arrayOfObject = (Object[])m.get(long_);
/*     */         if (arrayOfObject == null) {
/*     */           arrayOfObject = new Object[3];
/*     */           "䀶諅詶鯰꯺Е겗푥䌢ლ礭?鮕揊償ạ㾃ヾ⎄褡姿".toCharArray()[0] = (char)("䀶諅詶鯰꯺Е겗푥䌢ლ礭?鮕揊償ạ㾃ヾ⎄褡姿".toCharArray()[0] ^ 0x38EE);
/*     */           arrayOfObject[0] = Cipher.getInstance(hY$g6.H("䀶諅詶鯰꯺Е겗푥䌢ლ礭?鮕揊償ạ㾃ヾ⎄褡姿".toCharArray(), (short)24193, (byte)1, (byte)5));
/*     */           "䎌씤졫㷼".toCharArray()[0] = (char)("䎌씤졫㷼".toCharArray()[0] ^ 0x1952);
/*     */           arrayOfObject[1] = SecretKeyFactory.getInstance(hY$g6.H("䎌씤졫㷼".toCharArray(), (short)31263, (byte)3, (byte)2));
/*     */           arrayOfObject[2] = new IvParameterSpec(new byte[8]);
/*     */           m.put(long_, arrayOfObject);
/*     */         } 
/*     */       } catch (Exception exception) {
/*     */         "১᱄ꁋ狳콼絤곢ﱇ铹罾苵ᛇ禖曯헔꺿宸瀲慯".toCharArray()[13] = (char)("১᱄ꁋ狳콼絤곢ﱇ铹罾苵ᛇ禖曯헔꺿宸瀲慯".toCharArray()[13] ^ 0x231A);
/*     */         throw new RuntimeException(hY$g6.H("১᱄ꁋ狳콼絤곢ﱇ铹罾苵ᛇ禖曯헔꺿宸瀲慯".toCharArray(), (short)9882, (byte)1, (byte)0), exception);
/*     */       } 
/*     */       byte[] arrayOfByte1 = new byte[8];
/*     */       arrayOfByte1[0] = (byte)(int)(paramLong >>> 56L);
/*     */       for (byte b = 1; b < 8; b++)
/*     */         arrayOfByte1[b] = (byte)(int)(paramLong << b * 8 >>> 56L); 
/*     */       DESKeySpec dESKeySpec = new DESKeySpec(arrayOfByte1);
/*     */       SecretKey secretKey = ((SecretKeyFactory)arrayOfObject[1]).generateSecret(dESKeySpec);
/*     */       ((Cipher)arrayOfObject[0]).init(2, secretKey, (IvParameterSpec)arrayOfObject[2]);
/*     */       "좼?됖Ⅿ묢弣?᣾唓丢䢢".toCharArray()[7] = (char)("좼?됖Ⅿ묢弣?᣾唓丢䢢".toCharArray()[7] ^ 0x2429);
/*     */       byte[] arrayOfByte2 = k[i].getBytes(hY$g6.H("좼?됖Ⅿ묢弣?᣾唓丢䢢".toCharArray(), (short)13609, (byte)1, (byte)2));
/*     */       l[i] = a(((Cipher)arrayOfObject[0]).doFinal(arrayOfByte2));
/*     */     } 
/*     */     return l[i];
/*     */   }
/*     */   
/*     */   private static Object a(MethodHandles.Lookup paramLookup, MutableCallSite paramMutableCallSite, String paramString, Object[] paramArrayOfObject) {
/*     */     int i = ((Integer)paramArrayOfObject[0]).intValue();
/*     */     long l = ((Long)paramArrayOfObject[1]).longValue();
/*     */     String str = a(i, l);
/*     */     MethodHandle methodHandle = MethodHandles.constant(String.class, str);
/*     */     paramMutableCallSite.setTarget(MethodHandles.dropArguments(methodHandle, 0, new Class[] { int.class, long.class }));
/*     */     return str;
/*     */   }
/*     */   
/*     */   private static CallSite a(MethodHandles.Lookup paramLookup, String paramString, MethodType paramMethodType) {
/*     */     // Byte code:
/*     */     //   0: new java/lang/invoke/MutableCallSite
/*     */     //   3: dup
/*     */     //   4: aload_2
/*     */     //   5: invokespecial <init> : (Ljava/lang/invoke/MethodType;)V
/*     */     //   8: astore_3
/*     */     //   9: aload_3
/*     */     //   10: ldc_w
/*     */     //   13: ldc_w [Ljava/lang/Object;
/*     */     //   16: aload_2
/*     */     //   17: invokevirtual parameterCount : ()I
/*     */     //   20: invokevirtual asCollector : (Ljava/lang/Class;I)Ljava/lang/invoke/MethodHandle;
/*     */     //   23: iconst_0
/*     */     //   24: iconst_3
/*     */     //   25: anewarray java/lang/Object
/*     */     //   28: dup
/*     */     //   29: iconst_0
/*     */     //   30: aload_0
/*     */     //   31: aastore
/*     */     //   32: dup
/*     */     //   33: iconst_1
/*     */     //   34: aload_3
/*     */     //   35: aastore
/*     */     //   36: dup
/*     */     //   37: iconst_2
/*     */     //   38: aload_1
/*     */     //   39: aastore
/*     */     //   40: invokestatic insertArguments : (Ljava/lang/invoke/MethodHandle;I[Ljava/lang/Object;)Ljava/lang/invoke/MethodHandle;
/*     */     //   43: aload_2
/*     */     //   44: invokestatic explicitCastArguments : (Ljava/lang/invoke/MethodHandle;Ljava/lang/invoke/MethodType;)Ljava/lang/invoke/MethodHandle;
/*     */     //   47: invokevirtual setTarget : (Ljava/lang/invoke/MethodHandle;)V
/*     */     //   50: goto -> 170
/*     */     //   53: astore #4
/*     */     //   55: new java/lang/RuntimeException
/*     */     //   58: dup
/*     */     //   59: new java/lang/StringBuilder
/*     */     //   62: dup
/*     */     //   63: invokespecial <init> : ()V
/*     */     //   66: ldc_w '贖缌褎싡桅飴覰졏妄湹༖媗쳋谦鼳愻万'
/*     */     //   69: invokevirtual toCharArray : ()[C
/*     */     //   72: dup
/*     */     //   73: dup
/*     */     //   74: iconst_3
/*     */     //   75: dup_x1
/*     */     //   76: caload
/*     */     //   77: sipush #12584
/*     */     //   80: ixor
/*     */     //   81: i2c
/*     */     //   82: castore
/*     */     //   83: sipush #28610
/*     */     //   86: iconst_2
/*     */     //   87: iconst_3
/*     */     //   88: invokestatic H : (Ljava/lang/Object;SBB)Ljava/lang/String;
/*     */     //   91: invokevirtual append : (Ljava/lang/String;)Ljava/lang/StringBuilder;
/*     */     //   94: ldc_w '菌┵ऌ'
/*     */     //   97: invokevirtual toCharArray : ()[C
/*     */     //   100: dup
/*     */     //   101: dup
/*     */     //   102: iconst_0
/*     */     //   103: dup_x1
/*     */     //   104: caload
/*     */     //   105: sipush #25042
/*     */     //   108: ixor
/*     */     //   109: i2c
/*     */     //   110: castore
/*     */     //   111: sipush #5321
/*     */     //   114: iconst_3
/*     */     //   115: iconst_5
/*     */     //   116: invokestatic H : (Ljava/lang/Object;SBB)Ljava/lang/String;
/*     */     //   119: invokevirtual append : (Ljava/lang/String;)Ljava/lang/StringBuilder;
/*     */     //   122: aload_1
/*     */     //   123: invokevirtual append : (Ljava/lang/String;)Ljava/lang/StringBuilder;
/*     */     //   126: ldc_w '甡㢋ꕃ掣'
/*     */     //   129: invokevirtual toCharArray : ()[C
/*     */     //   132: dup
/*     */     //   133: dup
/*     */     //   134: iconst_2
/*     */     //   135: dup_x1
/*     */     //   136: caload
/*     */     //   137: sipush #29213
/*     */     //   140: ixor
/*     */     //   141: i2c
/*     */     //   142: castore
/*     */     //   143: sipush #9975
/*     */     //   146: iconst_2
/*     */     //   147: iconst_3
/*     */     //   148: invokestatic H : (Ljava/lang/Object;SBB)Ljava/lang/String;
/*     */     //   151: invokevirtual append : (Ljava/lang/String;)Ljava/lang/StringBuilder;
/*     */     //   154: aload_2
/*     */     //   155: invokevirtual toString : ()Ljava/lang/String;
/*     */     //   158: invokevirtual append : (Ljava/lang/String;)Ljava/lang/StringBuilder;
/*     */     //   161: invokevirtual toString : ()Ljava/lang/String;
/*     */     //   164: aload #4
/*     */     //   166: invokespecial <init> : (Ljava/lang/String;Ljava/lang/Throwable;)V
/*     */     //   169: athrow
/*     */     //   170: aload_3
/*     */     //   171: areturn
/*     */     // Exception table:
/*     */     //   from	to	target	type
/*     */     //   9	50	53	java/lang/Exception
/*     */   }
/*     */ }


/* Location:              C:\Users\BukkitBypass\Desktop\MatrixAC\AAC\AAC-spigot-5.2.0.jar!\me\konsolas\aac\j5.class
 * Java compiler version: 8 (52.0)
 * JD-Core Version:       1.1.3
 */