/*    */ package me.konsolas.aac;
/*    */ 
/*    */ import java.lang.invoke.CallSite;
/*    */ import java.lang.invoke.MethodHandle;
/*    */ import java.lang.invoke.MethodHandles;
/*    */ import java.lang.invoke.MethodType;
/*    */ import java.lang.invoke.MutableCallSite;
/*    */ import java.util.HashMap;
/*    */ import java.util.Map;
/*    */ import javax.annotation.Nullable;
/*    */ import javax.crypto.Cipher;
/*    */ import javax.crypto.SecretKey;
/*    */ import javax.crypto.SecretKeyFactory;
/*    */ import javax.crypto.spec.DESKeySpec;
/*    */ import javax.crypto.spec.IvParameterSpec;
/*    */ 
/*    */ 
/*    */ 
/*    */ 
/*    */ 
/*    */ 
/*    */ 
/*    */ 
/*    */ 
/*    */ 
/*    */ 
/*    */ 
/*    */ 
/*    */ 
/*    */ 
/*    */ 
/*    */ 
/*    */ 
/*    */ 
/*    */ 
/*    */ 
/*    */ 
/*    */ 
/*    */ 
/*    */ 
/*    */ 
/*    */ 
/*    */ 
/*    */ 
/*    */ 
/*    */ 
/*    */ 
/*    */ 
/*    */ 
/*    */ 
/*    */ 
/*    */ 
/*    */ 
/*    */ 
/*    */ 
/*    */ 
/*    */ 
/*    */ 
/*    */ 
/*    */ 
/*    */ 
/*    */ 
/*    */ 
/*    */ public final class j8
/*    */   implements ki
/*    */ {
/*    */   @Nullable
/*    */   final bC a;
/*    */   private static final long b = nc.a(7879694114208479186L, 6425045841669909112L, MethodHandles.lookup().lookupClass()).a(107637005437214L);
/*    */   private static final String[] c;
/*    */   private static final String[] d;
/*    */   private static final Map e = new HashMap<>(13);
/*    */   
/*    */   static boolean b(long paramLong, String paramString) {
/*    */     // Byte code:
/*    */     //   0: getstatic me/konsolas/aac/j8.b : J
/*    */     //   3: lload_0
/*    */     //   4: lxor
/*    */     //   5: lstore_0
/*    */     //   6: ldc2_w -4406195024497971779
/*    */     //   9: lload_0
/*    */     //   10: <illegal opcode> w : (JJ)[Ljava/lang/String;
/*    */     //   15: astore_3
/*    */     //   16: sipush #15326
/*    */     //   19: ldc2_w 2270929701725726950
/*    */     //   22: lload_0
/*    */     //   23: lxor
/*    */     //   24: <illegal opcode> r : (IJ)Ljava/lang/String;
/*    */     //   29: aload_2
/*    */     //   30: invokevirtual equalsIgnoreCase : (Ljava/lang/String;)Z
/*    */     //   33: aload_3
/*    */     //   34: ifnonnull -> 83
/*    */     //   37: ifne -> 443
/*    */     //   40: goto -> 53
/*    */     //   43: ldc2_w -4402608370881539546
/*    */     //   46: lload_0
/*    */     //   47: <illegal opcode> w : (Ljava/lang/Exception;JJ)Ljava/lang/Exception;
/*    */     //   52: athrow
/*    */     //   53: sipush #31218
/*    */     //   56: ldc2_w 680597211509893837
/*    */     //   59: lload_0
/*    */     //   60: lxor
/*    */     //   61: <illegal opcode> r : (IJ)Ljava/lang/String;
/*    */     //   66: aload_2
/*    */     //   67: invokevirtual equalsIgnoreCase : (Ljava/lang/String;)Z
/*    */     //   70: goto -> 83
/*    */     //   73: ldc2_w -4402608370881539546
/*    */     //   76: lload_0
/*    */     //   77: <illegal opcode> w : (Ljava/lang/Exception;JJ)Ljava/lang/Exception;
/*    */     //   82: athrow
/*    */     //   83: aload_3
/*    */     //   84: lload_0
/*    */     //   85: lconst_0
/*    */     //   86: lcmp
/*    */     //   87: ifle -> 140
/*    */     //   90: ifnonnull -> 139
/*    */     //   93: ifne -> 443
/*    */     //   96: goto -> 109
/*    */     //   99: ldc2_w -4402608370881539546
/*    */     //   102: lload_0
/*    */     //   103: <illegal opcode> w : (Ljava/lang/Exception;JJ)Ljava/lang/Exception;
/*    */     //   108: athrow
/*    */     //   109: sipush #6486
/*    */     //   112: ldc2_w 1803917688444308066
/*    */     //   115: lload_0
/*    */     //   116: lxor
/*    */     //   117: <illegal opcode> r : (IJ)Ljava/lang/String;
/*    */     //   122: aload_2
/*    */     //   123: invokevirtual equalsIgnoreCase : (Ljava/lang/String;)Z
/*    */     //   126: goto -> 139
/*    */     //   129: ldc2_w -4402608370881539546
/*    */     //   132: lload_0
/*    */     //   133: <illegal opcode> w : (Ljava/lang/Exception;JJ)Ljava/lang/Exception;
/*    */     //   138: athrow
/*    */     //   139: aload_3
/*    */     //   140: lload_0
/*    */     //   141: lconst_0
/*    */     //   142: lcmp
/*    */     //   143: iflt -> 196
/*    */     //   146: ifnonnull -> 195
/*    */     //   149: ifne -> 443
/*    */     //   152: goto -> 165
/*    */     //   155: ldc2_w -4402608370881539546
/*    */     //   158: lload_0
/*    */     //   159: <illegal opcode> w : (Ljava/lang/Exception;JJ)Ljava/lang/Exception;
/*    */     //   164: athrow
/*    */     //   165: sipush #17297
/*    */     //   168: ldc2_w 5401620395924656294
/*    */     //   171: lload_0
/*    */     //   172: lxor
/*    */     //   173: <illegal opcode> r : (IJ)Ljava/lang/String;
/*    */     //   178: aload_2
/*    */     //   179: invokevirtual equalsIgnoreCase : (Ljava/lang/String;)Z
/*    */     //   182: goto -> 195
/*    */     //   185: ldc2_w -4402608370881539546
/*    */     //   188: lload_0
/*    */     //   189: <illegal opcode> w : (Ljava/lang/Exception;JJ)Ljava/lang/Exception;
/*    */     //   194: athrow
/*    */     //   195: aload_3
/*    */     //   196: lload_0
/*    */     //   197: lconst_0
/*    */     //   198: lcmp
/*    */     //   199: ifle -> 252
/*    */     //   202: ifnonnull -> 251
/*    */     //   205: ifne -> 443
/*    */     //   208: goto -> 221
/*    */     //   211: ldc2_w -4402608370881539546
/*    */     //   214: lload_0
/*    */     //   215: <illegal opcode> w : (Ljava/lang/Exception;JJ)Ljava/lang/Exception;
/*    */     //   220: athrow
/*    */     //   221: sipush #22526
/*    */     //   224: ldc2_w 6649505900806603970
/*    */     //   227: lload_0
/*    */     //   228: lxor
/*    */     //   229: <illegal opcode> r : (IJ)Ljava/lang/String;
/*    */     //   234: aload_2
/*    */     //   235: invokevirtual equalsIgnoreCase : (Ljava/lang/String;)Z
/*    */     //   238: goto -> 251
/*    */     //   241: ldc2_w -4402608370881539546
/*    */     //   244: lload_0
/*    */     //   245: <illegal opcode> w : (Ljava/lang/Exception;JJ)Ljava/lang/Exception;
/*    */     //   250: athrow
/*    */     //   251: aload_3
/*    */     //   252: lload_0
/*    */     //   253: lconst_0
/*    */     //   254: lcmp
/*    */     //   255: iflt -> 308
/*    */     //   258: ifnonnull -> 307
/*    */     //   261: ifne -> 443
/*    */     //   264: goto -> 277
/*    */     //   267: ldc2_w -4402608370881539546
/*    */     //   270: lload_0
/*    */     //   271: <illegal opcode> w : (Ljava/lang/Exception;JJ)Ljava/lang/Exception;
/*    */     //   276: athrow
/*    */     //   277: sipush #19708
/*    */     //   280: ldc2_w 5866430885012381646
/*    */     //   283: lload_0
/*    */     //   284: lxor
/*    */     //   285: <illegal opcode> r : (IJ)Ljava/lang/String;
/*    */     //   290: aload_2
/*    */     //   291: invokevirtual equalsIgnoreCase : (Ljava/lang/String;)Z
/*    */     //   294: goto -> 307
/*    */     //   297: ldc2_w -4402608370881539546
/*    */     //   300: lload_0
/*    */     //   301: <illegal opcode> w : (Ljava/lang/Exception;JJ)Ljava/lang/Exception;
/*    */     //   306: athrow
/*    */     //   307: aload_3
/*    */     //   308: lload_0
/*    */     //   309: lconst_0
/*    */     //   310: lcmp
/*    */     //   311: ifle -> 364
/*    */     //   314: ifnonnull -> 363
/*    */     //   317: ifne -> 443
/*    */     //   320: goto -> 333
/*    */     //   323: ldc2_w -4402608370881539546
/*    */     //   326: lload_0
/*    */     //   327: <illegal opcode> w : (Ljava/lang/Exception;JJ)Ljava/lang/Exception;
/*    */     //   332: athrow
/*    */     //   333: sipush #14225
/*    */     //   336: ldc2_w 3895632126588970148
/*    */     //   339: lload_0
/*    */     //   340: lxor
/*    */     //   341: <illegal opcode> r : (IJ)Ljava/lang/String;
/*    */     //   346: aload_2
/*    */     //   347: invokevirtual equalsIgnoreCase : (Ljava/lang/String;)Z
/*    */     //   350: goto -> 363
/*    */     //   353: ldc2_w -4402608370881539546
/*    */     //   356: lload_0
/*    */     //   357: <illegal opcode> w : (Ljava/lang/Exception;JJ)Ljava/lang/Exception;
/*    */     //   362: athrow
/*    */     //   363: aload_3
/*    */     //   364: lload_0
/*    */     //   365: lconst_0
/*    */     //   366: lcmp
/*    */     //   367: ifle -> 420
/*    */     //   370: ifnonnull -> 419
/*    */     //   373: ifne -> 443
/*    */     //   376: goto -> 389
/*    */     //   379: ldc2_w -4402608370881539546
/*    */     //   382: lload_0
/*    */     //   383: <illegal opcode> w : (Ljava/lang/Exception;JJ)Ljava/lang/Exception;
/*    */     //   388: athrow
/*    */     //   389: sipush #6583
/*    */     //   392: ldc2_w 9072384789021575815
/*    */     //   395: lload_0
/*    */     //   396: lxor
/*    */     //   397: <illegal opcode> r : (IJ)Ljava/lang/String;
/*    */     //   402: aload_2
/*    */     //   403: invokevirtual equalsIgnoreCase : (Ljava/lang/String;)Z
/*    */     //   406: goto -> 419
/*    */     //   409: ldc2_w -4402608370881539546
/*    */     //   412: lload_0
/*    */     //   413: <illegal opcode> w : (Ljava/lang/Exception;JJ)Ljava/lang/Exception;
/*    */     //   418: athrow
/*    */     //   419: aload_3
/*    */     //   420: ifnonnull -> 440
/*    */     //   423: ifne -> 443
/*    */     //   426: goto -> 439
/*    */     //   429: ldc2_w -4402608370881539546
/*    */     //   432: lload_0
/*    */     //   433: <illegal opcode> w : (Ljava/lang/Exception;JJ)Ljava/lang/Exception;
/*    */     //   438: athrow
/*    */     //   439: iconst_1
/*    */     //   440: goto -> 444
/*    */     //   443: iconst_0
/*    */     //   444: ireturn
/*    */     // Line number table:
/*    */     //   Java source line number -> byte code offset
/*    */     //   #3	-> 16
/*    */     //   #23	-> 67
/*    */     //   #65	-> 123
/*    */     //   #63	-> 179
/*    */     //   #8	-> 235
/*    */     //   #69	-> 291
/*    */     //   #7	-> 347
/*    */     //   #44	-> 403
/*    */     //   #42	-> 444
/*    */     // Exception table:
/*    */     //   from	to	target	type
/*    */     //   16	40	43	aacinternal/v
/*    */     //   37	70	73	aacinternal/v
/*    */     //   83	96	99	aacinternal/v
/*    */     //   93	126	129	aacinternal/v
/*    */     //   139	152	155	aacinternal/v
/*    */     //   149	182	185	aacinternal/v
/*    */     //   195	208	211	aacinternal/v
/*    */     //   205	238	241	aacinternal/v
/*    */     //   251	264	267	aacinternal/v
/*    */     //   261	294	297	aacinternal/v
/*    */     //   307	320	323	aacinternal/v
/*    */     //   317	350	353	aacinternal/v
/*    */     //   363	376	379	aacinternal/v
/*    */     //   373	406	409	aacinternal/v
/*    */     //   419	426	429	aacinternal/v
/*    */   }
/*    */   
/*    */   public j8(@Nullable bC parambC) {
/* 79 */     this.a = parambC;
/*    */   }
/*    */   
/*    */   static boolean a(String paramString, long paramLong) {
/*    */     // Byte code:
/*    */     //   0: getstatic me/konsolas/aac/j8.b : J
/*    */     //   3: lload_1
/*    */     //   4: lxor
/*    */     //   5: lstore_1
/*    */     //   6: ldc2_w 6392404335371679697
/*    */     //   9: lload_1
/*    */     //   10: <illegal opcode> w : (JJ)[Ljava/lang/String;
/*    */     //   15: astore_3
/*    */     //   16: sipush #18104
/*    */     //   19: ldc2_w 6232659134819143650
/*    */     //   22: lload_1
/*    */     //   23: lxor
/*    */     //   24: <illegal opcode> r : (IJ)Ljava/lang/String;
/*    */     //   29: aload_0
/*    */     //   30: invokevirtual equalsIgnoreCase : (Ljava/lang/String;)Z
/*    */     //   33: aload_3
/*    */     //   34: ifnonnull -> 154
/*    */     //   37: ifne -> 153
/*    */     //   40: goto -> 53
/*    */     //   43: ldc2_w 6380094499023702090
/*    */     //   46: lload_1
/*    */     //   47: <illegal opcode> w : (Ljava/lang/Exception;JJ)Ljava/lang/Exception;
/*    */     //   52: athrow
/*    */     //   53: sipush #13802
/*    */     //   56: ldc2_w 7475834922552556735
/*    */     //   59: lload_1
/*    */     //   60: lxor
/*    */     //   61: <illegal opcode> r : (IJ)Ljava/lang/String;
/*    */     //   66: aload_0
/*    */     //   67: invokevirtual equalsIgnoreCase : (Ljava/lang/String;)Z
/*    */     //   70: aload_3
/*    */     //   71: ifnonnull -> 154
/*    */     //   74: goto -> 87
/*    */     //   77: ldc2_w 6380094499023702090
/*    */     //   80: lload_1
/*    */     //   81: <illegal opcode> w : (Ljava/lang/Exception;JJ)Ljava/lang/Exception;
/*    */     //   86: athrow
/*    */     //   87: ifne -> 153
/*    */     //   90: goto -> 103
/*    */     //   93: ldc2_w 6380094499023702090
/*    */     //   96: lload_1
/*    */     //   97: <illegal opcode> w : (Ljava/lang/Exception;JJ)Ljava/lang/Exception;
/*    */     //   102: athrow
/*    */     //   103: sipush #24097
/*    */     //   106: ldc2_w 2465953420297049968
/*    */     //   109: lload_1
/*    */     //   110: lxor
/*    */     //   111: <illegal opcode> r : (IJ)Ljava/lang/String;
/*    */     //   116: aload_0
/*    */     //   117: invokevirtual equalsIgnoreCase : (Ljava/lang/String;)Z
/*    */     //   120: aload_3
/*    */     //   121: ifnonnull -> 154
/*    */     //   124: goto -> 137
/*    */     //   127: ldc2_w 6380094499023702090
/*    */     //   130: lload_1
/*    */     //   131: <illegal opcode> w : (Ljava/lang/Exception;JJ)Ljava/lang/Exception;
/*    */     //   136: athrow
/*    */     //   137: ifeq -> 157
/*    */     //   140: goto -> 153
/*    */     //   143: ldc2_w 6380094499023702090
/*    */     //   146: lload_1
/*    */     //   147: <illegal opcode> w : (Ljava/lang/Exception;JJ)Ljava/lang/Exception;
/*    */     //   152: athrow
/*    */     //   153: iconst_1
/*    */     //   154: goto -> 158
/*    */     //   157: iconst_0
/*    */     //   158: ireturn
/*    */     // Line number table:
/*    */     //   Java source line number -> byte code offset
/*    */     //   #37	-> 16
/*    */     //   #49	-> 67
/*    */     //   #81	-> 117
/*    */     //   #17	-> 158
/*    */     // Exception table:
/*    */     //   from	to	target	type
/*    */     //   16	40	43	aacinternal/v
/*    */     //   37	74	77	aacinternal/v
/*    */     //   53	90	93	aacinternal/v
/*    */     //   87	124	127	aacinternal/v
/*    */     //   103	140	143	aacinternal/v
/*    */   }
/*    */   
/*    */   public H a(long paramLong, ko paramko) {
/*    */     // Byte code:
/*    */     //   0: lload_1
/*    */     //   1: dup2
/*    */     //   2: ldc2_w 80654356364680
/*    */     //   5: lxor
/*    */     //   6: lstore #4
/*    */     //   8: dup2
/*    */     //   9: ldc2_w 46836476704883
/*    */     //   12: lxor
/*    */     //   13: lstore #6
/*    */     //   15: dup2
/*    */     //   16: ldc2_w 40685407614583
/*    */     //   19: lxor
/*    */     //   20: lstore #8
/*    */     //   22: dup2
/*    */     //   23: ldc2_w 55808603974920
/*    */     //   26: lxor
/*    */     //   27: lstore #10
/*    */     //   29: dup2
/*    */     //   30: ldc2_w 67652849686771
/*    */     //   33: lxor
/*    */     //   34: lstore #12
/*    */     //   36: dup2
/*    */     //   37: ldc2_w 132767887783896
/*    */     //   40: lxor
/*    */     //   41: dup2
/*    */     //   42: bipush #48
/*    */     //   44: lushr
/*    */     //   45: l2i
/*    */     //   46: istore #14
/*    */     //   48: dup2
/*    */     //   49: bipush #16
/*    */     //   51: lshl
/*    */     //   52: bipush #32
/*    */     //   54: lushr
/*    */     //   55: l2i
/*    */     //   56: istore #15
/*    */     //   58: dup2
/*    */     //   59: bipush #48
/*    */     //   61: lshl
/*    */     //   62: bipush #48
/*    */     //   64: lushr
/*    */     //   65: l2i
/*    */     //   66: istore #16
/*    */     //   68: pop2
/*    */     //   69: dup2
/*    */     //   70: ldc2_w 108072258430063
/*    */     //   73: lxor
/*    */     //   74: lstore #17
/*    */     //   76: dup2
/*    */     //   77: ldc2_w 70333938907896
/*    */     //   80: lxor
/*    */     //   81: dup2
/*    */     //   82: bipush #48
/*    */     //   84: lushr
/*    */     //   85: l2i
/*    */     //   86: istore #19
/*    */     //   88: dup2
/*    */     //   89: bipush #16
/*    */     //   91: lshl
/*    */     //   92: bipush #48
/*    */     //   94: lushr
/*    */     //   95: l2i
/*    */     //   96: istore #20
/*    */     //   98: dup2
/*    */     //   99: bipush #32
/*    */     //   101: lshl
/*    */     //   102: bipush #32
/*    */     //   104: lushr
/*    */     //   105: l2i
/*    */     //   106: istore #21
/*    */     //   108: pop2
/*    */     //   109: dup2
/*    */     //   110: ldc2_w 87909747225374
/*    */     //   113: lxor
/*    */     //   114: lstore #22
/*    */     //   116: dup2
/*    */     //   117: ldc2_w 93801688454164
/*    */     //   120: lxor
/*    */     //   121: lstore #24
/*    */     //   123: dup2
/*    */     //   124: ldc2_w 110142469404905
/*    */     //   127: lxor
/*    */     //   128: lstore #26
/*    */     //   130: dup2
/*    */     //   131: ldc2_w 139100027516957
/*    */     //   134: lxor
/*    */     //   135: lstore #28
/*    */     //   137: dup2
/*    */     //   138: ldc2_w 55495277320439
/*    */     //   141: lxor
/*    */     //   142: dup2
/*    */     //   143: bipush #32
/*    */     //   145: lushr
/*    */     //   146: l2i
/*    */     //   147: istore #30
/*    */     //   149: dup2
/*    */     //   150: bipush #32
/*    */     //   152: lshl
/*    */     //   153: bipush #48
/*    */     //   155: lushr
/*    */     //   156: l2i
/*    */     //   157: istore #31
/*    */     //   159: dup2
/*    */     //   160: bipush #48
/*    */     //   162: lshl
/*    */     //   163: bipush #48
/*    */     //   165: lushr
/*    */     //   166: l2i
/*    */     //   167: istore #32
/*    */     //   169: pop2
/*    */     //   170: dup2
/*    */     //   171: ldc2_w 90212784976332
/*    */     //   174: lxor
/*    */     //   175: lstore #33
/*    */     //   177: dup2
/*    */     //   178: ldc2_w 123956286709911
/*    */     //   181: lxor
/*    */     //   182: lstore #35
/*    */     //   184: dup2
/*    */     //   185: ldc2_w 114955140348984
/*    */     //   188: lxor
/*    */     //   189: lstore #37
/*    */     //   191: dup2
/*    */     //   192: ldc2_w 1250055110467
/*    */     //   195: lxor
/*    */     //   196: lstore #39
/*    */     //   198: dup2
/*    */     //   199: ldc2_w 92152558739220
/*    */     //   202: lxor
/*    */     //   203: lstore #41
/*    */     //   205: pop2
/*    */     //   206: ldc2_w 6596761318067533035
/*    */     //   209: lload_1
/*    */     //   210: <illegal opcode> w : (JJ)[Ljava/lang/String;
/*    */     //   215: astore #43
/*    */     //   217: aload_0
/*    */     //   218: getfield a : Lme/konsolas/aac/bC;
/*    */     //   221: aload #43
/*    */     //   223: ifnonnull -> 259
/*    */     //   226: ifnull -> 280
/*    */     //   229: goto -> 242
/*    */     //   232: ldc2_w 6606957179036912496
/*    */     //   235: lload_1
/*    */     //   236: <illegal opcode> w : (Ljava/lang/Exception;JJ)Ljava/lang/Exception;
/*    */     //   241: athrow
/*    */     //   242: aload_0
/*    */     //   243: getfield a : Lme/konsolas/aac/bC;
/*    */     //   246: goto -> 259
/*    */     //   249: ldc2_w 6606957179036912496
/*    */     //   252: lload_1
/*    */     //   253: <illegal opcode> w : (Ljava/lang/Exception;JJ)Ljava/lang/Exception;
/*    */     //   258: athrow
/*    */     //   259: aload_3
/*    */     //   260: invokeinterface a : ()Lme/konsolas/aac/s;
/*    */     //   265: iload #30
/*    */     //   267: iload #31
/*    */     //   269: iload #32
/*    */     //   271: i2s
/*    */     //   272: invokeinterface a : (Lme/konsolas/aac/s;IIS)Lme/konsolas/aac/H;
/*    */     //   277: goto -> 281
/*    */     //   280: aconst_null
/*    */     //   281: astore #44
/*    */     //   283: invokestatic currentTimeMillis : ()J
/*    */     //   286: lstore #45
/*    */     //   288: new me/konsolas/aac/dD
/*    */     //   291: dup
/*    */     //   292: lload #45
/*    */     //   294: aload_3
/*    */     //   295: invokeinterface a : ()Lme/konsolas/aac/s;
/*    */     //   300: lload #12
/*    */     //   302: dup2_x1
/*    */     //   303: pop2
/*    */     //   304: aload #44
/*    */     //   306: invokespecial <init> : (JJLme/konsolas/aac/s;Lme/konsolas/aac/H;)V
/*    */     //   309: lload #4
/*    */     //   311: invokevirtual b : (J)Lme/konsolas/aac/a3;
/*    */     //   314: astore #47
/*    */     //   316: aload #47
/*    */     //   318: getfield b : Lme/konsolas/aac/s;
/*    */     //   321: astore #48
/*    */     //   323: aload #47
/*    */     //   325: getfield a : Lme/konsolas/aac/H;
/*    */     //   328: astore #49
/*    */     //   330: aload_0
/*    */     //   331: getfield a : Lme/konsolas/aac/bC;
/*    */     //   334: aload #43
/*    */     //   336: ifnonnull -> 372
/*    */     //   339: ifnull -> 381
/*    */     //   342: goto -> 355
/*    */     //   345: ldc2_w 6606957179036912496
/*    */     //   348: lload_1
/*    */     //   349: <illegal opcode> w : (Ljava/lang/Exception;JJ)Ljava/lang/Exception;
/*    */     //   354: athrow
/*    */     //   355: aload_0
/*    */     //   356: getfield a : Lme/konsolas/aac/bC;
/*    */     //   359: goto -> 372
/*    */     //   362: ldc2_w 6606957179036912496
/*    */     //   365: lload_1
/*    */     //   366: <illegal opcode> w : (Ljava/lang/Exception;JJ)Ljava/lang/Exception;
/*    */     //   371: athrow
/*    */     //   372: aload #47
/*    */     //   374: lload #6
/*    */     //   376: invokeinterface a : (Lme/konsolas/aac/a3;J)V
/*    */     //   381: aload #44
/*    */     //   383: aload #43
/*    */     //   385: lload_1
/*    */     //   386: lconst_0
/*    */     //   387: lcmp
/*    */     //   388: iflt -> 414
/*    */     //   391: ifnonnull -> 412
/*    */     //   394: ifnull -> 445
/*    */     //   397: goto -> 410
/*    */     //   400: ldc2_w 6606957179036912496
/*    */     //   403: lload_1
/*    */     //   404: <illegal opcode> w : (Ljava/lang/Exception;JJ)Ljava/lang/Exception;
/*    */     //   409: athrow
/*    */     //   410: aload #49
/*    */     //   412: aload #43
/*    */     //   414: ifnonnull -> 435
/*    */     //   417: ifnonnull -> 445
/*    */     //   420: goto -> 433
/*    */     //   423: ldc2_w 6606957179036912496
/*    */     //   426: lload_1
/*    */     //   427: <illegal opcode> w : (Ljava/lang/Exception;JJ)Ljava/lang/Exception;
/*    */     //   432: athrow
/*    */     //   433: aload #44
/*    */     //   435: invokevirtual a : ()Lme/konsolas/aac/d2;
/*    */     //   438: lload #39
/*    */     //   440: dup2_x1
/*    */     //   441: pop2
/*    */     //   442: invokestatic a : (JLjava/io/Closeable;)V
/*    */     //   445: aload #48
/*    */     //   447: lload_1
/*    */     //   448: lconst_0
/*    */     //   449: lcmp
/*    */     //   450: iflt -> 593
/*    */     //   453: aload #43
/*    */     //   455: ifnonnull -> 593
/*    */     //   458: ifnonnull -> 591
/*    */     //   461: goto -> 474
/*    */     //   464: ldc2_w 6606957179036912496
/*    */     //   467: lload_1
/*    */     //   468: <illegal opcode> w : (Ljava/lang/Exception;JJ)Ljava/lang/Exception;
/*    */     //   473: athrow
/*    */     //   474: aload #49
/*    */     //   476: aload #43
/*    */     //   478: ifnonnull -> 590
/*    */     //   481: goto -> 494
/*    */     //   484: ldc2_w 6606957179036912496
/*    */     //   487: lload_1
/*    */     //   488: <illegal opcode> w : (Ljava/lang/Exception;JJ)Ljava/lang/Exception;
/*    */     //   493: athrow
/*    */     //   494: ifnonnull -> 591
/*    */     //   497: goto -> 510
/*    */     //   500: ldc2_w 6606957179036912496
/*    */     //   503: lload_1
/*    */     //   504: <illegal opcode> w : (Ljava/lang/Exception;JJ)Ljava/lang/Exception;
/*    */     //   509: athrow
/*    */     //   510: new me/konsolas/aac/T
/*    */     //   513: dup
/*    */     //   514: invokespecial <init> : ()V
/*    */     //   517: aload_3
/*    */     //   518: invokeinterface a : ()Lme/konsolas/aac/s;
/*    */     //   523: invokevirtual a : (Lme/konsolas/aac/s;)Lme/konsolas/aac/T;
/*    */     //   526: getstatic me/konsolas/aac/le.HTTP_1_1 : Lme/konsolas/aac/le;
/*    */     //   529: invokevirtual a : (Lme/konsolas/aac/le;)Lme/konsolas/aac/T;
/*    */     //   532: sipush #504
/*    */     //   535: invokevirtual a : (I)Lme/konsolas/aac/T;
/*    */     //   538: sipush #29387
/*    */     //   541: ldc2_w 4524500319388121251
/*    */     //   544: lload_1
/*    */     //   545: lxor
/*    */     //   546: <illegal opcode> r : (IJ)Ljava/lang/String;
/*    */     //   551: invokevirtual a : (Ljava/lang/String;)Lme/konsolas/aac/T;
/*    */     //   554: getstatic me/konsolas/aac/eO.j : Lme/konsolas/aac/d2;
/*    */     //   557: invokevirtual a : (Lme/konsolas/aac/d2;)Lme/konsolas/aac/T;
/*    */     //   560: ldc2_w -1
/*    */     //   563: invokevirtual b : (J)Lme/konsolas/aac/T;
/*    */     //   566: invokestatic currentTimeMillis : ()J
/*    */     //   569: invokevirtual a : (J)Lme/konsolas/aac/T;
/*    */     //   572: lload #35
/*    */     //   574: invokevirtual a : (J)Lme/konsolas/aac/H;
/*    */     //   577: goto -> 590
/*    */     //   580: ldc2_w 6606957179036912496
/*    */     //   583: lload_1
/*    */     //   584: <illegal opcode> w : (Ljava/lang/Exception;JJ)Ljava/lang/Exception;
/*    */     //   589: athrow
/*    */     //   590: areturn
/*    */     //   591: aload #48
/*    */     //   593: ifnonnull -> 631
/*    */     //   596: aload #49
/*    */     //   598: invokevirtual a : ()Lme/konsolas/aac/T;
/*    */     //   601: aload #49
/*    */     //   603: lload #22
/*    */     //   605: invokestatic a : (Lme/konsolas/aac/H;J)Lme/konsolas/aac/H;
/*    */     //   608: lload #17
/*    */     //   610: dup2_x1
/*    */     //   611: pop2
/*    */     //   612: invokevirtual b : (JLme/konsolas/aac/H;)Lme/konsolas/aac/T;
/*    */     //   615: lload #35
/*    */     //   617: invokevirtual a : (J)Lme/konsolas/aac/H;
/*    */     //   620: areturn
/*    */     //   621: ldc2_w 6606957179036912496
/*    */     //   624: lload_1
/*    */     //   625: <illegal opcode> w : (Ljava/lang/Exception;JJ)Ljava/lang/Exception;
/*    */     //   630: athrow
/*    */     //   631: aconst_null
/*    */     //   632: astore #50
/*    */     //   634: aload_3
/*    */     //   635: iload #14
/*    */     //   637: i2c
/*    */     //   638: aload #48
/*    */     //   640: iload #15
/*    */     //   642: iload #16
/*    */     //   644: invokeinterface a : (CLme/konsolas/aac/s;II)Lme/konsolas/aac/H;
/*    */     //   649: astore #50
/*    */     //   651: aload #50
/*    */     //   653: aload #43
/*    */     //   655: ifnonnull -> 812
/*    */     //   658: ifnonnull -> 810
/*    */     //   661: goto -> 674
/*    */     //   664: ldc2_w 6606957179036912496
/*    */     //   667: lload_1
/*    */     //   668: <illegal opcode> w : (Ljava/lang/Exception;JJ)Ljava/lang/Exception;
/*    */     //   673: athrow
/*    */     //   674: aload #44
/*    */     //   676: aload #43
/*    */     //   678: lload_1
/*    */     //   679: lconst_0
/*    */     //   680: lcmp
/*    */     //   681: ifle -> 814
/*    */     //   684: ifnonnull -> 812
/*    */     //   687: goto -> 700
/*    */     //   690: ldc2_w 6606957179036912496
/*    */     //   693: lload_1
/*    */     //   694: <illegal opcode> w : (Ljava/lang/Exception;JJ)Ljava/lang/Exception;
/*    */     //   699: athrow
/*    */     //   700: ifnull -> 810
/*    */     //   703: goto -> 716
/*    */     //   706: ldc2_w 6606957179036912496
/*    */     //   709: lload_1
/*    */     //   710: <illegal opcode> w : (Ljava/lang/Exception;JJ)Ljava/lang/Exception;
/*    */     //   715: athrow
/*    */     //   716: aload #44
/*    */     //   718: invokevirtual a : ()Lme/konsolas/aac/d2;
/*    */     //   721: lload #39
/*    */     //   723: dup2_x1
/*    */     //   724: pop2
/*    */     //   725: invokestatic a : (JLjava/io/Closeable;)V
/*    */     //   728: goto -> 810
/*    */     //   731: ldc2_w 6606957179036912496
/*    */     //   734: lload_1
/*    */     //   735: <illegal opcode> w : (Ljava/lang/Exception;JJ)Ljava/lang/Exception;
/*    */     //   740: athrow
/*    */     //   741: astore #51
/*    */     //   743: aload #50
/*    */     //   745: aload #43
/*    */     //   747: lload_1
/*    */     //   748: lconst_0
/*    */     //   749: lcmp
/*    */     //   750: iflt -> 776
/*    */     //   753: ifnonnull -> 774
/*    */     //   756: ifnonnull -> 807
/*    */     //   759: goto -> 772
/*    */     //   762: ldc2_w 6606957179036912496
/*    */     //   765: lload_1
/*    */     //   766: <illegal opcode> w : (Ljava/lang/Exception;JJ)Ljava/lang/Exception;
/*    */     //   771: athrow
/*    */     //   772: aload #44
/*    */     //   774: aload #43
/*    */     //   776: ifnonnull -> 797
/*    */     //   779: ifnull -> 807
/*    */     //   782: goto -> 795
/*    */     //   785: ldc2_w 6606957179036912496
/*    */     //   788: lload_1
/*    */     //   789: <illegal opcode> w : (Ljava/lang/Exception;JJ)Ljava/lang/Exception;
/*    */     //   794: athrow
/*    */     //   795: aload #44
/*    */     //   797: invokevirtual a : ()Lme/konsolas/aac/d2;
/*    */     //   800: lload #39
/*    */     //   802: dup2_x1
/*    */     //   803: pop2
/*    */     //   804: invokestatic a : (JLjava/io/Closeable;)V
/*    */     //   807: aload #51
/*    */     //   809: athrow
/*    */     //   810: aload #49
/*    */     //   812: aload #43
/*    */     //   814: ifnonnull -> 1034
/*    */     //   817: ifnull -> 996
/*    */     //   820: goto -> 833
/*    */     //   823: ldc2_w 6606957179036912496
/*    */     //   826: lload_1
/*    */     //   827: <illegal opcode> w : (Ljava/lang/Exception;JJ)Ljava/lang/Exception;
/*    */     //   832: athrow
/*    */     //   833: aload #50
/*    */     //   835: aload #43
/*    */     //   837: ifnonnull -> 986
/*    */     //   840: goto -> 853
/*    */     //   843: ldc2_w 6606957179036912496
/*    */     //   846: lload_1
/*    */     //   847: <illegal opcode> w : (Ljava/lang/Exception;JJ)Ljava/lang/Exception;
/*    */     //   852: athrow
/*    */     //   853: invokevirtual a : ()I
/*    */     //   856: sipush #304
/*    */     //   859: if_icmpne -> 984
/*    */     //   862: goto -> 875
/*    */     //   865: ldc2_w 6606957179036912496
/*    */     //   868: lload_1
/*    */     //   869: <illegal opcode> w : (Ljava/lang/Exception;JJ)Ljava/lang/Exception;
/*    */     //   874: athrow
/*    */     //   875: aload #49
/*    */     //   877: invokevirtual a : ()Lme/konsolas/aac/T;
/*    */     //   880: aload #49
/*    */     //   882: invokevirtual a : ()Lme/konsolas/aac/J;
/*    */     //   885: aload #50
/*    */     //   887: invokevirtual a : ()Lme/konsolas/aac/J;
/*    */     //   890: lload #41
/*    */     //   892: invokestatic a : (Lme/konsolas/aac/J;Lme/konsolas/aac/J;J)Lme/konsolas/aac/J;
/*    */     //   895: invokevirtual a : (Lme/konsolas/aac/J;)Lme/konsolas/aac/T;
/*    */     //   898: aload #50
/*    */     //   900: invokevirtual a : ()J
/*    */     //   903: invokevirtual b : (J)Lme/konsolas/aac/T;
/*    */     //   906: aload #50
/*    */     //   908: invokevirtual b : ()J
/*    */     //   911: invokevirtual a : (J)Lme/konsolas/aac/T;
/*    */     //   914: aload #49
/*    */     //   916: lload #22
/*    */     //   918: invokestatic a : (Lme/konsolas/aac/H;J)Lme/konsolas/aac/H;
/*    */     //   921: lload #17
/*    */     //   923: dup2_x1
/*    */     //   924: pop2
/*    */     //   925: invokevirtual b : (JLme/konsolas/aac/H;)Lme/konsolas/aac/T;
/*    */     //   928: aload #50
/*    */     //   930: lload #22
/*    */     //   932: invokestatic a : (Lme/konsolas/aac/H;J)Lme/konsolas/aac/H;
/*    */     //   935: lload #8
/*    */     //   937: dup2_x1
/*    */     //   938: pop2
/*    */     //   939: invokevirtual a : (JLme/konsolas/aac/H;)Lme/konsolas/aac/T;
/*    */     //   942: lload #35
/*    */     //   944: invokevirtual a : (J)Lme/konsolas/aac/H;
/*    */     //   947: astore #51
/*    */     //   949: aload #50
/*    */     //   951: invokevirtual a : ()Lme/konsolas/aac/d2;
/*    */     //   954: invokevirtual close : ()V
/*    */     //   957: aload_0
/*    */     //   958: getfield a : Lme/konsolas/aac/bC;
/*    */     //   961: invokeinterface a : ()V
/*    */     //   966: aload_0
/*    */     //   967: getfield a : Lme/konsolas/aac/bC;
/*    */     //   970: aload #49
/*    */     //   972: lload #28
/*    */     //   974: aload #51
/*    */     //   976: invokeinterface a : (Lme/konsolas/aac/H;JLme/konsolas/aac/H;)V
/*    */     //   981: aload #51
/*    */     //   983: areturn
/*    */     //   984: aload #49
/*    */     //   986: invokevirtual a : ()Lme/konsolas/aac/d2;
/*    */     //   989: lload #39
/*    */     //   991: dup2_x1
/*    */     //   992: pop2
/*    */     //   993: invokestatic a : (JLjava/io/Closeable;)V
/*    */     //   996: aload #50
/*    */     //   998: invokevirtual a : ()Lme/konsolas/aac/T;
/*    */     //   1001: aload #49
/*    */     //   1003: lload #22
/*    */     //   1005: invokestatic a : (Lme/konsolas/aac/H;J)Lme/konsolas/aac/H;
/*    */     //   1008: lload #17
/*    */     //   1010: dup2_x1
/*    */     //   1011: pop2
/*    */     //   1012: invokevirtual b : (JLme/konsolas/aac/H;)Lme/konsolas/aac/T;
/*    */     //   1015: aload #50
/*    */     //   1017: lload #22
/*    */     //   1019: invokestatic a : (Lme/konsolas/aac/H;J)Lme/konsolas/aac/H;
/*    */     //   1022: lload #8
/*    */     //   1024: dup2_x1
/*    */     //   1025: pop2
/*    */     //   1026: invokevirtual a : (JLme/konsolas/aac/H;)Lme/konsolas/aac/T;
/*    */     //   1029: lload #35
/*    */     //   1031: invokevirtual a : (J)Lme/konsolas/aac/H;
/*    */     //   1034: astore #51
/*    */     //   1036: lload_1
/*    */     //   1037: lconst_0
/*    */     //   1038: lcmp
/*    */     //   1039: ifle -> 1049
/*    */     //   1042: aload_0
/*    */     //   1043: getfield a : Lme/konsolas/aac/bC;
/*    */     //   1046: ifnull -> 1214
/*    */     //   1049: aload #51
/*    */     //   1051: lload #37
/*    */     //   1053: invokestatic b : (Lme/konsolas/aac/H;J)Z
/*    */     //   1056: aload #43
/*    */     //   1058: ifnonnull -> 1183
/*    */     //   1061: goto -> 1074
/*    */     //   1064: ldc2_w 6606957179036912496
/*    */     //   1067: lload_1
/*    */     //   1068: <illegal opcode> w : (Ljava/lang/Exception;JJ)Ljava/lang/Exception;
/*    */     //   1073: athrow
/*    */     //   1074: ifeq -> 1171
/*    */     //   1077: goto -> 1090
/*    */     //   1080: ldc2_w 6606957179036912496
/*    */     //   1083: lload_1
/*    */     //   1084: <illegal opcode> w : (Ljava/lang/Exception;JJ)Ljava/lang/Exception;
/*    */     //   1089: athrow
/*    */     //   1090: aload #51
/*    */     //   1092: lload #33
/*    */     //   1094: aload #48
/*    */     //   1096: invokestatic a : (Lme/konsolas/aac/H;JLme/konsolas/aac/s;)Z
/*    */     //   1099: lload_1
/*    */     //   1100: lconst_0
/*    */     //   1101: lcmp
/*    */     //   1102: ifle -> 1183
/*    */     //   1105: aload #43
/*    */     //   1107: ifnonnull -> 1183
/*    */     //   1110: goto -> 1123
/*    */     //   1113: ldc2_w 6606957179036912496
/*    */     //   1116: lload_1
/*    */     //   1117: <illegal opcode> w : (Ljava/lang/Exception;JJ)Ljava/lang/Exception;
/*    */     //   1122: athrow
/*    */     //   1123: ifeq -> 1171
/*    */     //   1126: goto -> 1139
/*    */     //   1129: ldc2_w 6606957179036912496
/*    */     //   1132: lload_1
/*    */     //   1133: <illegal opcode> w : (Ljava/lang/Exception;JJ)Ljava/lang/Exception;
/*    */     //   1138: athrow
/*    */     //   1139: aload_0
/*    */     //   1140: getfield a : Lme/konsolas/aac/bC;
/*    */     //   1143: aload #51
/*    */     //   1145: iload #19
/*    */     //   1147: i2s
/*    */     //   1148: iload #20
/*    */     //   1150: i2s
/*    */     //   1151: iload #21
/*    */     //   1153: invokeinterface a : (Lme/konsolas/aac/H;SSI)Lme/konsolas/aac/iA;
/*    */     //   1158: astore #52
/*    */     //   1160: aload_0
/*    */     //   1161: aload #52
/*    */     //   1163: aload #51
/*    */     //   1165: lload #24
/*    */     //   1167: invokespecial a : (Lme/konsolas/aac/iA;Lme/konsolas/aac/H;J)Lme/konsolas/aac/H;
/*    */     //   1170: areturn
/*    */     //   1171: aload #48
/*    */     //   1173: invokevirtual a : ()Ljava/lang/String;
/*    */     //   1176: lload #26
/*    */     //   1178: dup2_x1
/*    */     //   1179: pop2
/*    */     //   1180: invokestatic c : (JLjava/lang/String;)Z
/*    */     //   1183: ifeq -> 1214
/*    */     //   1186: aload_0
/*    */     //   1187: getfield a : Lme/konsolas/aac/bC;
/*    */     //   1190: aload #48
/*    */     //   1192: lload #10
/*    */     //   1194: invokeinterface a : (Lme/konsolas/aac/s;J)V
/*    */     //   1199: goto -> 1214
/*    */     //   1202: ldc2_w 6606957179036912496
/*    */     //   1205: lload_1
/*    */     //   1206: <illegal opcode> w : (Ljava/lang/Exception;JJ)Ljava/lang/Exception;
/*    */     //   1211: athrow
/*    */     //   1212: astore #52
/*    */     //   1214: aload #51
/*    */     //   1216: areturn
/*    */     // Line number table:
/*    */     //   Java source line number -> byte code offset
/*    */     //   #57	-> 217
/*    */     //   #48	-> 242
/*    */     //   #86	-> 280
/*    */     //   #34	-> 283
/*    */     //   #6	-> 288
/*    */     //   #39	-> 316
/*    */     //   #73	-> 323
/*    */     //   #24	-> 330
/*    */     //   #102	-> 355
/*    */     //   #25	-> 381
/*    */     //   #83	-> 433
/*    */     //   #71	-> 445
/*    */     //   #32	-> 510
/*    */     //   #10	-> 518
/*    */     //   #78	-> 529
/*    */     //   #99	-> 535
/*    */     //   #11	-> 551
/*    */     //   #21	-> 557
/*    */     //   #14	-> 563
/*    */     //   #46	-> 566
/*    */     //   #89	-> 572
/*    */     //   #100	-> 590
/*    */     //   #50	-> 591
/*    */     //   #27	-> 596
/*    */     //   #45	-> 603
/*    */     //   #66	-> 615
/*    */     //   #54	-> 620
/*    */     //   #68	-> 631
/*    */     //   #88	-> 634
/*    */     //   #26	-> 651
/*    */     //   #19	-> 716
/*    */     //   #22	-> 741
/*    */     //   #97	-> 795
/*    */     //   #20	-> 810
/*    */     //   #47	-> 833
/*    */     //   #74	-> 875
/*    */     //   #75	-> 882
/*    */     //   #82	-> 900
/*    */     //   #77	-> 908
/*    */     //   #58	-> 916
/*    */     //   #51	-> 930
/*    */     //   #18	-> 942
/*    */     //   #62	-> 949
/*    */     //   #29	-> 957
/*    */     //   #93	-> 966
/*    */     //   #92	-> 981
/*    */     //   #12	-> 984
/*    */     //   #55	-> 996
/*    */     //   #59	-> 1003
/*    */     //   #36	-> 1017
/*    */     //   #60	-> 1029
/*    */     //   #40	-> 1036
/*    */     //   #84	-> 1049
/*    */     //   #2	-> 1139
/*    */     //   #52	-> 1160
/*    */     //   #80	-> 1171
/*    */     //   #94	-> 1186
/*    */     //   #105	-> 1199
/*    */     //   #98	-> 1212
/*    */     //   #41	-> 1214
/*    */     // Exception table:
/*    */     //   from	to	target	type
/*    */     //   217	229	232	java/io/IOException
/*    */     //   226	246	249	java/io/IOException
/*    */     //   330	342	345	java/io/IOException
/*    */     //   339	359	362	java/io/IOException
/*    */     //   381	397	400	java/io/IOException
/*    */     //   412	420	423	java/io/IOException
/*    */     //   445	461	464	java/io/IOException
/*    */     //   458	481	484	java/io/IOException
/*    */     //   474	497	500	java/io/IOException
/*    */     //   494	577	580	java/io/IOException
/*    */     //   593	621	621	java/io/IOException
/*    */     //   634	651	741	finally
/*    */     //   651	661	664	java/io/IOException
/*    */     //   658	687	690	java/io/IOException
/*    */     //   674	703	706	java/io/IOException
/*    */     //   700	731	731	java/io/IOException
/*    */     //   741	743	741	finally
/*    */     //   743	759	762	java/io/IOException
/*    */     //   774	782	785	java/io/IOException
/*    */     //   812	820	823	java/io/IOException
/*    */     //   817	840	843	java/io/IOException
/*    */     //   833	862	865	java/io/IOException
/*    */     //   1036	1061	1064	java/io/IOException
/*    */     //   1049	1077	1080	java/io/IOException
/*    */     //   1074	1110	1113	java/io/IOException
/*    */     //   1090	1126	1129	java/io/IOException
/*    */     //   1183	1202	1202	aacinternal/v
/*    */     //   1186	1199	1212	java/io/IOException
/*    */   }
/*    */   
/*    */   private static H a(H paramH, long paramLong) {
/*    */     // Byte code:
/*    */     //   0: getstatic me/konsolas/aac/j8.b : J
/*    */     //   3: lload_1
/*    */     //   4: lxor
/*    */     //   5: lstore_1
/*    */     //   6: lload_1
/*    */     //   7: dup2
/*    */     //   8: ldc2_w 112566271839803
/*    */     //   11: lxor
/*    */     //   12: lstore_3
/*    */     //   13: pop2
/*    */     //   14: ldc2_w 3828184664761801287
/*    */     //   17: lload_1
/*    */     //   18: <illegal opcode> w : (JJ)[Ljava/lang/String;
/*    */     //   23: astore #5
/*    */     //   25: aload_0
/*    */     //   26: aload #5
/*    */     //   28: ifnonnull -> 48
/*    */     //   31: ifnull -> 100
/*    */     //   34: goto -> 47
/*    */     //   37: ldc2_w 3827134240831317468
/*    */     //   40: lload_1
/*    */     //   41: <illegal opcode> w : (Ljava/lang/Exception;JJ)Ljava/lang/Exception;
/*    */     //   46: athrow
/*    */     //   47: aload_0
/*    */     //   48: aload #5
/*    */     //   50: ifnonnull -> 97
/*    */     //   53: invokevirtual a : ()Lme/konsolas/aac/d2;
/*    */     //   56: ifnull -> 100
/*    */     //   59: goto -> 72
/*    */     //   62: ldc2_w 3827134240831317468
/*    */     //   65: lload_1
/*    */     //   66: <illegal opcode> w : (Ljava/lang/Exception;JJ)Ljava/lang/Exception;
/*    */     //   71: athrow
/*    */     //   72: aload_0
/*    */     //   73: invokevirtual a : ()Lme/konsolas/aac/T;
/*    */     //   76: aconst_null
/*    */     //   77: invokevirtual a : (Lme/konsolas/aac/d2;)Lme/konsolas/aac/T;
/*    */     //   80: lload_3
/*    */     //   81: invokevirtual a : (J)Lme/konsolas/aac/H;
/*    */     //   84: goto -> 97
/*    */     //   87: ldc2_w 3827134240831317468
/*    */     //   90: lload_1
/*    */     //   91: <illegal opcode> w : (Ljava/lang/Exception;JJ)Ljava/lang/Exception;
/*    */     //   96: athrow
/*    */     //   97: goto -> 101
/*    */     //   100: aload_0
/*    */     //   101: areturn
/*    */     // Line number table:
/*    */     //   Java source line number -> byte code offset
/*    */     //   #67	-> 25
/*    */     //   #103	-> 72
/*    */     //   #108	-> 100
/*    */     //   #43	-> 101
/*    */     // Exception table:
/*    */     //   from	to	target	type
/*    */     //   25	34	37	aacinternal/v
/*    */     //   48	59	62	aacinternal/v
/*    */     //   53	84	87	aacinternal/v
/*    */   }
/*    */   
/*    */   private static J a(J paramJ1, J paramJ2, long paramLong) {
/*    */     // Byte code:
/*    */     //   0: getstatic me/konsolas/aac/j8.b : J
/*    */     //   3: lload_2
/*    */     //   4: lxor
/*    */     //   5: lstore_2
/*    */     //   6: lload_2
/*    */     //   7: dup2
/*    */     //   8: ldc2_w 93903580191790
/*    */     //   11: lxor
/*    */     //   12: lstore #4
/*    */     //   14: dup2
/*    */     //   15: ldc2_w 37065536343598
/*    */     //   18: lxor
/*    */     //   19: dup2
/*    */     //   20: bipush #32
/*    */     //   22: lushr
/*    */     //   23: l2i
/*    */     //   24: istore #6
/*    */     //   26: dup2
/*    */     //   27: bipush #32
/*    */     //   29: lshl
/*    */     //   30: bipush #48
/*    */     //   32: lushr
/*    */     //   33: l2i
/*    */     //   34: istore #7
/*    */     //   36: dup2
/*    */     //   37: bipush #48
/*    */     //   39: lshl
/*    */     //   40: bipush #48
/*    */     //   42: lushr
/*    */     //   43: l2i
/*    */     //   44: istore #8
/*    */     //   46: pop2
/*    */     //   47: dup2
/*    */     //   48: ldc2_w 61848170841666
/*    */     //   51: lxor
/*    */     //   52: lstore #9
/*    */     //   54: pop2
/*    */     //   55: ldc2_w 1813382266831746637
/*    */     //   58: lload_2
/*    */     //   59: <illegal opcode> w : (JJ)[Ljava/lang/String;
/*    */     //   64: new me/konsolas/aac/mr
/*    */     //   67: dup
/*    */     //   68: invokespecial <init> : ()V
/*    */     //   71: astore #12
/*    */     //   73: astore #11
/*    */     //   75: iconst_0
/*    */     //   76: istore #13
/*    */     //   78: aload_0
/*    */     //   79: invokevirtual a : ()I
/*    */     //   82: istore #14
/*    */     //   84: iload #13
/*    */     //   86: iload #14
/*    */     //   88: if_icmpge -> 435
/*    */     //   91: aload_0
/*    */     //   92: iload #13
/*    */     //   94: invokevirtual a : (I)Ljava/lang/String;
/*    */     //   97: astore #15
/*    */     //   99: aload_0
/*    */     //   100: iload #13
/*    */     //   102: invokevirtual b : (I)Ljava/lang/String;
/*    */     //   105: astore #16
/*    */     //   107: sipush #10053
/*    */     //   110: ldc2_w 6583868701622775686
/*    */     //   113: lload_2
/*    */     //   114: lxor
/*    */     //   115: <illegal opcode> r : (IJ)Ljava/lang/String;
/*    */     //   120: aload #15
/*    */     //   122: invokevirtual equalsIgnoreCase : (Ljava/lang/String;)Z
/*    */     //   125: aload #11
/*    */     //   127: lload_2
/*    */     //   128: lconst_0
/*    */     //   129: lcmp
/*    */     //   130: ifle -> 138
/*    */     //   133: ifnonnull -> 448
/*    */     //   136: aload #11
/*    */     //   138: ifnonnull -> 296
/*    */     //   141: goto -> 154
/*    */     //   144: ldc2_w 1807819678076766678
/*    */     //   147: lload_2
/*    */     //   148: <illegal opcode> w : (Ljava/lang/Exception;JJ)Ljava/lang/Exception;
/*    */     //   153: athrow
/*    */     //   154: lload_2
/*    */     //   155: lconst_0
/*    */     //   156: lcmp
/*    */     //   157: ifle -> 283
/*    */     //   160: ifeq -> 276
/*    */     //   163: goto -> 176
/*    */     //   166: ldc2_w 1807819678076766678
/*    */     //   169: lload_2
/*    */     //   170: <illegal opcode> w : (Ljava/lang/Exception;JJ)Ljava/lang/Exception;
/*    */     //   175: athrow
/*    */     //   176: aload #16
/*    */     //   178: ldc_w '㪦'
/*    */     //   181: invokevirtual toCharArray : ()[C
/*    */     //   184: dup
/*    */     //   185: dup
/*    */     //   186: iconst_0
/*    */     //   187: dup_x1
/*    */     //   188: caload
/*    */     //   189: sipush #19030
/*    */     //   192: ixor
/*    */     //   193: i2c
/*    */     //   194: castore
/*    */     //   195: sipush #11906
/*    */     //   198: iconst_2
/*    */     //   199: iconst_2
/*    */     //   200: invokestatic H : (Ljava/lang/Object;SBB)Ljava/lang/String;
/*    */     //   203: invokevirtual startsWith : (Ljava/lang/String;)Z
/*    */     //   206: aload #11
/*    */     //   208: lload_2
/*    */     //   209: lconst_0
/*    */     //   210: lcmp
/*    */     //   211: ifle -> 304
/*    */     //   214: ifnonnull -> 296
/*    */     //   217: goto -> 230
/*    */     //   220: ldc2_w 1807819678076766678
/*    */     //   223: lload_2
/*    */     //   224: <illegal opcode> w : (Ljava/lang/Exception;JJ)Ljava/lang/Exception;
/*    */     //   229: athrow
/*    */     //   230: lload_2
/*    */     //   231: lconst_0
/*    */     //   232: lcmp
/*    */     //   233: ifle -> 283
/*    */     //   236: ifeq -> 276
/*    */     //   239: goto -> 252
/*    */     //   242: ldc2_w 1807819678076766678
/*    */     //   245: lload_2
/*    */     //   246: <illegal opcode> w : (Ljava/lang/Exception;JJ)Ljava/lang/Exception;
/*    */     //   251: athrow
/*    */     //   252: aload #11
/*    */     //   254: lload_2
/*    */     //   255: lconst_0
/*    */     //   256: lcmp
/*    */     //   257: ifle -> 432
/*    */     //   260: ifnull -> 427
/*    */     //   263: goto -> 276
/*    */     //   266: ldc2_w 1807819678076766678
/*    */     //   269: lload_2
/*    */     //   270: <illegal opcode> w : (Ljava/lang/Exception;JJ)Ljava/lang/Exception;
/*    */     //   275: athrow
/*    */     //   276: aload #15
/*    */     //   278: lload #4
/*    */     //   280: invokestatic a : (Ljava/lang/String;J)Z
/*    */     //   283: goto -> 296
/*    */     //   286: ldc2_w 1807819678076766678
/*    */     //   289: lload_2
/*    */     //   290: <illegal opcode> w : (Ljava/lang/Exception;JJ)Ljava/lang/Exception;
/*    */     //   295: athrow
/*    */     //   296: lload_2
/*    */     //   297: lconst_0
/*    */     //   298: lcmp
/*    */     //   299: iflt -> 369
/*    */     //   302: aload #11
/*    */     //   304: ifnonnull -> 369
/*    */     //   307: ifne -> 402
/*    */     //   310: goto -> 323
/*    */     //   313: ldc2_w 1807819678076766678
/*    */     //   316: lload_2
/*    */     //   317: <illegal opcode> w : (Ljava/lang/Exception;JJ)Ljava/lang/Exception;
/*    */     //   322: athrow
/*    */     //   323: aload #15
/*    */     //   325: lload_2
/*    */     //   326: lconst_0
/*    */     //   327: lcmp
/*    */     //   328: ifle -> 399
/*    */     //   331: aload #11
/*    */     //   333: ifnonnull -> 399
/*    */     //   336: goto -> 349
/*    */     //   339: ldc2_w 1807819678076766678
/*    */     //   342: lload_2
/*    */     //   343: <illegal opcode> w : (Ljava/lang/Exception;JJ)Ljava/lang/Exception;
/*    */     //   348: athrow
/*    */     //   349: lload #9
/*    */     //   351: dup2_x1
/*    */     //   352: pop2
/*    */     //   353: invokestatic b : (JLjava/lang/String;)Z
/*    */     //   356: goto -> 369
/*    */     //   359: ldc2_w 1807819678076766678
/*    */     //   362: lload_2
/*    */     //   363: <illegal opcode> w : (Ljava/lang/Exception;JJ)Ljava/lang/Exception;
/*    */     //   368: athrow
/*    */     //   369: ifeq -> 402
/*    */     //   372: aload_1
/*    */     //   373: iload #6
/*    */     //   375: iload #7
/*    */     //   377: i2c
/*    */     //   378: iload #8
/*    */     //   380: i2c
/*    */     //   381: aload #15
/*    */     //   383: invokevirtual a : (ICCLjava/lang/String;)Ljava/lang/String;
/*    */     //   386: goto -> 399
/*    */     //   389: ldc2_w 1807819678076766678
/*    */     //   392: lload_2
/*    */     //   393: <illegal opcode> w : (Ljava/lang/Exception;JJ)Ljava/lang/Exception;
/*    */     //   398: athrow
/*    */     //   399: ifnonnull -> 427
/*    */     //   402: getstatic me/konsolas/aac/dJ.a : Lme/konsolas/aac/dJ;
/*    */     //   405: aload #12
/*    */     //   407: aload #15
/*    */     //   409: aload #16
/*    */     //   411: invokevirtual a : (Lme/konsolas/aac/mr;Ljava/lang/String;Ljava/lang/String;)V
/*    */     //   414: goto -> 427
/*    */     //   417: ldc2_w 1807819678076766678
/*    */     //   420: lload_2
/*    */     //   421: <illegal opcode> w : (Ljava/lang/Exception;JJ)Ljava/lang/Exception;
/*    */     //   426: athrow
/*    */     //   427: iinc #13, 1
/*    */     //   430: aload #11
/*    */     //   432: ifnull -> 84
/*    */     //   435: iconst_0
/*    */     //   436: istore #13
/*    */     //   438: aload_1
/*    */     //   439: lload_2
/*    */     //   440: lconst_0
/*    */     //   441: lcmp
/*    */     //   442: ifle -> 92
/*    */     //   445: invokevirtual a : ()I
/*    */     //   448: istore #14
/*    */     //   450: iload #13
/*    */     //   452: iload #14
/*    */     //   454: if_icmpge -> 564
/*    */     //   457: aload_1
/*    */     //   458: aload #11
/*    */     //   460: ifnonnull -> 569
/*    */     //   463: iload #13
/*    */     //   465: invokevirtual a : (I)Ljava/lang/String;
/*    */     //   468: astore #15
/*    */     //   470: aload #11
/*    */     //   472: lload_2
/*    */     //   473: lconst_0
/*    */     //   474: lcmp
/*    */     //   475: iflt -> 561
/*    */     //   478: ifnonnull -> 559
/*    */     //   481: aload #15
/*    */     //   483: lload #4
/*    */     //   485: invokestatic a : (Ljava/lang/String;J)Z
/*    */     //   488: ifne -> 556
/*    */     //   491: goto -> 504
/*    */     //   494: ldc2_w 1807819678076766678
/*    */     //   497: lload_2
/*    */     //   498: <illegal opcode> w : (Ljava/lang/Exception;JJ)Ljava/lang/Exception;
/*    */     //   503: athrow
/*    */     //   504: lload #9
/*    */     //   506: aload #15
/*    */     //   508: invokestatic b : (JLjava/lang/String;)Z
/*    */     //   511: ifeq -> 556
/*    */     //   514: goto -> 527
/*    */     //   517: ldc2_w 1807819678076766678
/*    */     //   520: lload_2
/*    */     //   521: <illegal opcode> w : (Ljava/lang/Exception;JJ)Ljava/lang/Exception;
/*    */     //   526: athrow
/*    */     //   527: getstatic me/konsolas/aac/dJ.a : Lme/konsolas/aac/dJ;
/*    */     //   530: aload #12
/*    */     //   532: aload #15
/*    */     //   534: aload_1
/*    */     //   535: iload #13
/*    */     //   537: invokevirtual b : (I)Ljava/lang/String;
/*    */     //   540: invokevirtual a : (Lme/konsolas/aac/mr;Ljava/lang/String;Ljava/lang/String;)V
/*    */     //   543: goto -> 556
/*    */     //   546: ldc2_w 1807819678076766678
/*    */     //   549: lload_2
/*    */     //   550: <illegal opcode> w : (Ljava/lang/Exception;JJ)Ljava/lang/Exception;
/*    */     //   555: athrow
/*    */     //   556: iinc #13, 1
/*    */     //   559: aload #11
/*    */     //   561: ifnull -> 450
/*    */     //   564: aload #12
/*    */     //   566: invokevirtual a : ()Lme/konsolas/aac/J;
/*    */     //   569: areturn
/*    */     // Line number table:
/*    */     //   Java source line number -> byte code offset
/*    */     //   #70	-> 64
/*    */     //   #107	-> 75
/*    */     //   #53	-> 91
/*    */     //   #90	-> 99
/*    */     //   #109	-> 107
/*    */     //   #104	-> 252
/*    */     //   #95	-> 276
/*    */     //   #87	-> 325
/*    */     //   #30	-> 383
/*    */     //   #56	-> 402
/*    */     //   #28	-> 427
/*    */     //   #16	-> 435
/*    */     //   #13	-> 457
/*    */     //   #61	-> 470
/*    */     //   #76	-> 527
/*    */     //   #9	-> 556
/*    */     //   #5	-> 564
/*    */     // Exception table:
/*    */     //   from	to	target	type
/*    */     //   107	141	144	aacinternal/v
/*    */     //   136	163	166	aacinternal/v
/*    */     //   154	217	220	aacinternal/v
/*    */     //   176	239	242	aacinternal/v
/*    */     //   230	263	266	aacinternal/v
/*    */     //   252	283	286	aacinternal/v
/*    */     //   296	310	313	aacinternal/v
/*    */     //   307	336	339	aacinternal/v
/*    */     //   323	356	359	aacinternal/v
/*    */     //   369	386	389	aacinternal/v
/*    */     //   399	414	417	aacinternal/v
/*    */     //   470	491	494	aacinternal/v
/*    */     //   481	514	517	aacinternal/v
/*    */     //   504	543	546	aacinternal/v
/*    */   }
/*    */   
/*    */   private H a(iA paramiA, H paramH, long paramLong) {
/*    */     // Byte code:
/*    */     //   0: getstatic me/konsolas/aac/j8.b : J
/*    */     //   3: lload_3
/*    */     //   4: lxor
/*    */     //   5: lstore_3
/*    */     //   6: lload_3
/*    */     //   7: dup2
/*    */     //   8: ldc2_w 126431571429988
/*    */     //   11: lxor
/*    */     //   12: lstore #5
/*    */     //   14: dup2
/*    */     //   15: ldc2_w 62664597915843
/*    */     //   18: lxor
/*    */     //   19: lstore #7
/*    */     //   21: dup2
/*    */     //   22: ldc2_w 137280538093873
/*    */     //   25: lxor
/*    */     //   26: lstore #9
/*    */     //   28: dup2
/*    */     //   29: ldc2_w 47852127146071
/*    */     //   32: lxor
/*    */     //   33: lstore #11
/*    */     //   35: dup2
/*    */     //   36: ldc2_w 33541593276187
/*    */     //   39: lxor
/*    */     //   40: dup2
/*    */     //   41: bipush #48
/*    */     //   43: lushr
/*    */     //   44: l2i
/*    */     //   45: istore #13
/*    */     //   47: dup2
/*    */     //   48: bipush #16
/*    */     //   50: lshl
/*    */     //   51: bipush #48
/*    */     //   53: lushr
/*    */     //   54: l2i
/*    */     //   55: istore #14
/*    */     //   57: dup2
/*    */     //   58: bipush #32
/*    */     //   60: lshl
/*    */     //   61: bipush #32
/*    */     //   63: lushr
/*    */     //   64: l2i
/*    */     //   65: istore #15
/*    */     //   67: pop2
/*    */     //   68: pop2
/*    */     //   69: ldc2_w -7914395676662219443
/*    */     //   72: lload_3
/*    */     //   73: <illegal opcode> w : (JJ)[Ljava/lang/String;
/*    */     //   78: astore #16
/*    */     //   80: aload_1
/*    */     //   81: aload #16
/*    */     //   83: ifnonnull -> 115
/*    */     //   86: ifnonnull -> 114
/*    */     //   89: goto -> 102
/*    */     //   92: ldc2_w -7919952767866862890
/*    */     //   95: lload_3
/*    */     //   96: <illegal opcode> w : (Ljava/lang/Exception;JJ)Ljava/lang/Exception;
/*    */     //   101: athrow
/*    */     //   102: aload_2
/*    */     //   103: areturn
/*    */     //   104: ldc2_w -7919952767866862890
/*    */     //   107: lload_3
/*    */     //   108: <illegal opcode> w : (Ljava/lang/Exception;JJ)Ljava/lang/Exception;
/*    */     //   113: athrow
/*    */     //   114: aload_1
/*    */     //   115: invokeinterface a : ()Lme/konsolas/aac/gp;
/*    */     //   120: astore #17
/*    */     //   122: aload #17
/*    */     //   124: ifnonnull -> 139
/*    */     //   127: aload_2
/*    */     //   128: areturn
/*    */     //   129: ldc2_w -7919952767866862890
/*    */     //   132: lload_3
/*    */     //   133: <illegal opcode> w : (Ljava/lang/Exception;JJ)Ljava/lang/Exception;
/*    */     //   138: athrow
/*    */     //   139: aload_2
/*    */     //   140: invokevirtual a : ()Lme/konsolas/aac/d2;
/*    */     //   143: invokevirtual a : ()Lme/konsolas/aac/bX;
/*    */     //   146: astore #18
/*    */     //   148: aload #17
/*    */     //   150: lload #5
/*    */     //   152: invokestatic a : (Lme/konsolas/aac/gp;J)Lme/konsolas/aac/gi;
/*    */     //   155: astore #19
/*    */     //   157: new me/konsolas/aac/lh
/*    */     //   160: dup
/*    */     //   161: aload_0
/*    */     //   162: aload #18
/*    */     //   164: aload_1
/*    */     //   165: aload #19
/*    */     //   167: invokespecial <init> : (Lme/konsolas/aac/j8;Lme/konsolas/aac/bX;Lme/konsolas/aac/iA;Lme/konsolas/aac/gi;)V
/*    */     //   170: astore #20
/*    */     //   172: aload_2
/*    */     //   173: lload #11
/*    */     //   175: sipush #28071
/*    */     //   178: ldc2_w 8403712906441551462
/*    */     //   181: lload_3
/*    */     //   182: lxor
/*    */     //   183: <illegal opcode> r : (IJ)Ljava/lang/String;
/*    */     //   188: invokevirtual a : (JLjava/lang/String;)Ljava/lang/String;
/*    */     //   191: astore #21
/*    */     //   193: aload_2
/*    */     //   194: invokevirtual a : ()Lme/konsolas/aac/d2;
/*    */     //   197: lload #7
/*    */     //   199: invokevirtual a : (J)J
/*    */     //   202: lstore #22
/*    */     //   204: aload_2
/*    */     //   205: invokevirtual a : ()Lme/konsolas/aac/T;
/*    */     //   208: new me/konsolas/aac/dQ
/*    */     //   211: dup
/*    */     //   212: aload #21
/*    */     //   214: lload #22
/*    */     //   216: iload #13
/*    */     //   218: i2s
/*    */     //   219: aload #20
/*    */     //   221: iload #14
/*    */     //   223: i2c
/*    */     //   224: iload #15
/*    */     //   226: invokestatic a : (SLme/konsolas/aac/hp;CI)Lme/konsolas/aac/bX;
/*    */     //   229: invokespecial <init> : (Ljava/lang/String;JLme/konsolas/aac/bX;)V
/*    */     //   232: invokevirtual a : (Lme/konsolas/aac/d2;)Lme/konsolas/aac/T;
/*    */     //   235: lload #9
/*    */     //   237: invokevirtual a : (J)Lme/konsolas/aac/H;
/*    */     //   240: areturn
/*    */     // Line number table:
/*    */     //   Java source line number -> byte code offset
/*    */     //   #85	-> 80
/*    */     //   #38	-> 114
/*    */     //   #1	-> 122
/*    */     //   #72	-> 139
/*    */     //   #91	-> 148
/*    */     //   #101	-> 157
/*    */     //   #35	-> 172
/*    */     //   #4	-> 193
/*    */     //   #64	-> 204
/*    */     //   #106	-> 221
/*    */     //   #31	-> 235
/*    */     //   #96	-> 240
/*    */     // Exception table:
/*    */     //   from	to	target	type
/*    */     //   80	89	92	java/io/IOException
/*    */     //   86	104	104	java/io/IOException
/*    */     //   122	129	129	java/io/IOException
/*    */   }
/*    */   
/*    */   static {
/*    */     long l = b ^ 0x47249885EE8CL;
/*    */     "秣ꚁ劙뉺官覆맨唕䋁ㄝ溮쑌?ࡅ⫥榔즔?㊁◯".toCharArray()[9] = (char)("秣ꚁ劙뉺官覆맨唕䋁ㄝ溮쑌?ࡅ⫥榔즔?㊁◯".toCharArray()[9] ^ 0x5205);
/*    */     "꾇Ⲁ톥ᾛ".toCharArray()[1] = (char)("꾇Ⲁ톥ᾛ".toCharArray()[1] ^ 0xB64);
/*    */     (new byte[8])[0] = (byte)(int)(l >>> 56L);
/*    */     for (byte b1 = 1; b1 < 8; b1++)
/*    */       (new byte[8])[b1] = (byte)(int)(l << b1 * 8 >>> 56L); 
/*    */     Cipher cipher;
/*    */     (cipher = Cipher.getInstance(dP$dt.X("秣ꚁ劙뉺官覆맨唕䋁ㄝ溮쑌?ࡅ⫥榔즔?㊁◯".toCharArray(), (short)3926, false, false))).init(2, SecretKeyFactory.getInstance(dP$dt.X("꾇Ⲁ톥ᾛ".toCharArray(), (short)27805, false, false)).generateSecret(new DESKeySpec(new byte[8])), new IvParameterSpec(new byte[8]));
/*    */     String[] arrayOfString = new String[14];
/*    */     boolean bool = false;
/*    */     "뗞띥帞‡鎬咀ヱ?ᑘ?ᱼ蚊픋灴ᶎ◨漇鵶࿤ⰹ돛倳믨ﻤ铎㨵撦ᨇ灆㩊ࠋ옸䡶辮쮧穘폋?ꚴ捆躛䔐㙪쮱믆痙뢹쭸ꀃ明줗脛蕙쒕㐼ہ㹪氋䒘ᚉ䫐≺䱔舀뿬쿷?줧⁸꞊㔕鑳骟⨼頨勵⺤㩂肶ꮭ?㤚挻㞟龊岒禧?縏꟬哝ꆨ灍鴓Ɽ쑳蒧彷ꏜᓎሲ䱭쿪璵껭矂歐꩝鑷直怜뵐엵纵䦖᪂쪴Ⓥ䅭ᖗꭩ箌截牟ꦼ侏脃嚊⠑明㽊礙뱱솈땅ې펫红嵮㽒ᣛ⭽돽ᄳ챘雨둧完㤥ﺐ➦斔쥙଩ሉҷ罏쮳瀠貰샂쥢鎱ꛤ짜狈樤옷ჱ⻑꼞刮ﰄ뮋㍋닚双诩⾿컙䖷輊輇傜畘඄晃?囤덺ʜ⟶揹䯒ᡢᛧ஛赣዗֞퇴뜫ₐ븸ㅝ㔇῵冎ꇦ飑笇㥼耏য়怋㕌ㅕ縁疼킯펁毉鬸ฏ聪ጆ瞶燜⮻㵚ᗇࡄ᥸鐺輒趚꓏㨆늱隭嚃?媤弗鶟䜔搆?츄㸄곲ʨ擶筸睉䂇ᨗ勖Ꙇ﷕⋚℮签왑✂屩疔箞ஞṿᓀ㥰룪廓⽩屠쏑돋瞇첩츩굟构彇鏗哔뇦?꠵ᇀ杮ग쌱驔ᖯ縀?킆龵麧岖ܖ䄿븛䦖祣偈๖痀脢䜊趠덆爳톩逖搳檭쨊峏ꛁ澈窑禿㶳쓩✜읚⸎믕酹㿈䝀퇫閹䍖蜵᫠㇈?ኚ䢙噎ǳ蔀蛔㹼ⅵ틩째?닔포湙".toCharArray()[126] = (char)("뗞띥帞‡鎬咀ヱ?ᑘ?ᱼ蚊픋灴ᶎ◨漇鵶࿤ⰹ돛倳믨ﻤ铎㨵撦ᨇ灆㩊ࠋ옸䡶辮쮧穘폋?ꚴ捆躛䔐㙪쮱믆痙뢹쭸ꀃ明줗脛蕙쒕㐼ہ㹪氋䒘ᚉ䫐≺䱔舀뿬쿷?줧⁸꞊㔕鑳骟⨼頨勵⺤㩂肶ꮭ?㤚挻㞟龊岒禧?縏꟬哝ꆨ灍鴓Ɽ쑳蒧彷ꏜᓎሲ䱭쿪璵껭矂歐꩝鑷直怜뵐엵纵䦖᪂쪴Ⓥ䅭ᖗꭩ箌截牟ꦼ侏脃嚊⠑明㽊礙뱱솈땅ې펫红嵮㽒ᣛ⭽돽ᄳ챘雨둧完㤥ﺐ➦斔쥙଩ሉҷ罏쮳瀠貰샂쥢鎱ꛤ짜狈樤옷ჱ⻑꼞刮ﰄ뮋㍋닚双诩⾿컙䖷輊輇傜畘඄晃?囤덺ʜ⟶揹䯒ᡢᛧ஛赣዗֞퇴뜫ₐ븸ㅝ㔇῵冎ꇦ飑笇㥼耏য়怋㕌ㅕ縁疼킯펁毉鬸ฏ聪ጆ瞶燜⮻㵚ᗇࡄ᥸鐺輒趚꓏㨆늱隭嚃?媤弗鶟䜔搆?츄㸄곲ʨ擶筸睉䂇ᨗ勖Ꙇ﷕⋚℮签왑✂屩疔箞ஞṿᓀ㥰룪廓⽩屠쏑돋瞇첩츩굟构彇鏗哔뇦?꠵ᇀ杮ग쌱驔ᖯ縀?킆龵麧岖ܖ䄿븛䦖祣偈๖痀脢䜊趠덆爳톩逖搳檭쨊峏ꛁ澈窑禿㶳쓩✜읚⸎믕酹㿈䝀퇫閹䍖蜵᫠㇈?ኚ䢙噎ǳ蔀蛔㹼ⅵ틩째?닔포湙".toCharArray()[126] ^ 0x4290);
/*    */     String str;
/*    */     int i = (str = dP$dt.X("뗞띥帞‡鎬咀ヱ?ᑘ?ᱼ蚊픋灴ᶎ◨漇鵶࿤ⰹ돛倳믨ﻤ铎㨵撦ᨇ灆㩊ࠋ옸䡶辮쮧穘폋?ꚴ捆躛䔐㙪쮱믆痙뢹쭸ꀃ明줗脛蕙쒕㐼ہ㹪氋䒘ᚉ䫐≺䱔舀뿬쿷?줧⁸꞊㔕鑳骟⨼頨勵⺤㩂肶ꮭ?㤚挻㞟龊岒禧?縏꟬哝ꆨ灍鴓Ɽ쑳蒧彷ꏜᓎሲ䱭쿪璵껭矂歐꩝鑷直怜뵐엵纵䦖᪂쪴Ⓥ䅭ᖗꭩ箌截牟ꦼ侏脃嚊⠑明㽊礙뱱솈땅ې펫红嵮㽒ᣛ⭽돽ᄳ챘雨둧完㤥ﺐ➦斔쥙଩ሉҷ罏쮳瀠貰샂쥢鎱ꛤ짜狈樤옷ჱ⻑꼞刮ﰄ뮋㍋닚双诩⾿컙䖷輊輇傜畘඄晃?囤덺ʜ⟶揹䯒ᡢᛧ஛赣዗֞퇴뜫ₐ븸ㅝ㔇῵冎ꇦ飑笇㥼耏য়怋㕌ㅕ縁疼킯펁毉鬸ฏ聪ጆ瞶燜⮻㵚ᗇࡄ᥸鐺輒趚꓏㨆늱隭嚃?媤弗鶟䜔搆?츄㸄곲ʨ擶筸睉䂇ᨗ勖Ꙇ﷕⋚℮签왑✂屩疔箞ஞṿᓀ㥰룪廓⽩屠쏑돋瞇첩츩굟构彇鏗哔뇦?꠵ᇀ杮ग쌱驔ᖯ縀?킆龵麧岖ܖ䄿븛䦖祣偈๖痀脢䜊趠덆爳톩逖搳檭쨊峏ꛁ澈窑禿㶳쓩✜읚⸎믕酹㿈䝀퇫閹䍖蜵᫠㇈?ኚ䢙噎ǳ蔀蛔㹼ⅵ틩째?닔포湙".toCharArray(), (short)7386, false, false)).length();
/*    */     byte b2 = 40;
/*    */     byte b = -1;
/*    */     while (true);
/*    */   }
/*    */   
/*    */   private static Exception a(Exception paramException) {
/*    */     return paramException;
/*    */   }
/*    */   
/*    */   private static String a(byte[] paramArrayOfbyte) {
/*    */     byte b1 = 0;
/*    */     int i;
/*    */     char[] arrayOfChar = new char[i = paramArrayOfbyte.length];
/*    */     for (byte b2 = 0; b2 < i; b2++) {
/*    */       int j;
/*    */       if ((j = 0xFF & paramArrayOfbyte[b2]) < 192) {
/*    */         arrayOfChar[b1++] = (char)j;
/*    */       } else if (j < 224) {
/*    */         char c = (char)((char)(j & 0x1F) << 6);
/*    */         j = paramArrayOfbyte[++b2];
/*    */         c = (char)(c | (char)(j & 0x3F));
/*    */         arrayOfChar[b1++] = c;
/*    */       } else if (b2 < i - 2) {
/*    */         char c = (char)((char)(j & 0xF) << 12);
/*    */         j = paramArrayOfbyte[++b2];
/*    */         c = (char)(c | (char)(j & 0x3F) << 6);
/*    */         j = paramArrayOfbyte[++b2];
/*    */         c = (char)(c | (char)(j & 0x3F));
/*    */         arrayOfChar[b1++] = c;
/*    */       } 
/*    */     } 
/*    */     return new String(arrayOfChar, 0, b1);
/*    */   }
/*    */   
/*    */   private static String a(int paramInt, long paramLong) {
/*    */     int i = paramInt ^ (int)(paramLong & 0x7FFFL) ^ 0x1067;
/*    */     if (d[i] == null) {
/*    */       Object[] arrayOfObject;
/*    */       try {
/*    */         Long long_ = Long.valueOf(Thread.currentThread().getId());
/*    */         arrayOfObject = (Object[])e.get(long_);
/*    */         if (arrayOfObject == null) {
/*    */           arrayOfObject = new Object[3];
/*    */           "摍蛥??쓓嬮푑?㐟斻䑈囝❘Ⴆ寨₤઒⍛".toCharArray()[5] = (char)("摍蛥??쓓嬮푑?㐟斻䑈囝❘Ⴆ寨₤઒⍛".toCharArray()[5] ^ 0x538B);
/*    */           arrayOfObject[0] = Cipher.getInstance(da$gx.U("摍蛥??쓓嬮푑?㐟斻䑈囝❘Ⴆ寨₤઒⍛".toCharArray(), (short)10742, true, false));
/*    */           "⨣羆㔞ᨁ".toCharArray()[0] = (char)("⨣羆㔞ᨁ".toCharArray()[0] ^ 0x32A6);
/*    */           arrayOfObject[1] = SecretKeyFactory.getInstance(da$gx.U("⨣羆㔞ᨁ".toCharArray(), (short)15500, true, false));
/*    */           arrayOfObject[2] = new IvParameterSpec(new byte[8]);
/*    */           e.put(long_, arrayOfObject);
/*    */         } 
/*    */       } catch (Exception exception) {
/*    */         "꭫쉡뽚౥珚氡誇⑓磵똀䧽喪㒳仫桳钸쯙䔇".toCharArray()[6] = (char)("꭫쉡뽚౥珚氡誇⑓磵똀䧽喪㒳仫桳钸쯙䔇".toCharArray()[6] ^ 0x5C5A);
/*    */         throw new RuntimeException(da$gx.U("꭫쉡뽚౥珚氡誇⑓磵똀䧽喪㒳仫桳钸쯙䔇".toCharArray(), (short)27036, false, false), exception);
/*    */       } 
/*    */       byte[] arrayOfByte1 = new byte[8];
/*    */       arrayOfByte1[0] = (byte)(int)(paramLong >>> 56L);
/*    */       for (byte b = 1; b < 8; b++)
/*    */         arrayOfByte1[b] = (byte)(int)(paramLong << b * 8 >>> 56L); 
/*    */       DESKeySpec dESKeySpec = new DESKeySpec(arrayOfByte1);
/*    */       SecretKey secretKey = ((SecretKeyFactory)arrayOfObject[1]).generateSecret(dESKeySpec);
/*    */       ((Cipher)arrayOfObject[0]).init(2, secretKey, (IvParameterSpec)arrayOfObject[2]);
/*    */       "憯 텦ⴛ爋鰿駤帔咧矎".toCharArray()[2] = (char)("憯 텦ⴛ爋鰿駤帔咧矎".toCharArray()[2] ^ 0x478D);
/*    */       byte[] arrayOfByte2 = c[i].getBytes(da$gx.U("憯 텦ⴛ爋鰿駤帔咧矎".toCharArray(), (short)20161, true, false));
/*    */       d[i] = a(((Cipher)arrayOfObject[0]).doFinal(arrayOfByte2));
/*    */     } 
/*    */     return d[i];
/*    */   }
/*    */   
/*    */   private static Object a(MethodHandles.Lookup paramLookup, MutableCallSite paramMutableCallSite, String paramString, Object[] paramArrayOfObject) {
/*    */     int i = ((Integer)paramArrayOfObject[0]).intValue();
/*    */     long l = ((Long)paramArrayOfObject[1]).longValue();
/*    */     String str = a(i, l);
/*    */     MethodHandle methodHandle = MethodHandles.constant(String.class, str);
/*    */     paramMutableCallSite.setTarget(MethodHandles.dropArguments(methodHandle, 0, new Class[] { int.class, long.class }));
/*    */     return str;
/*    */   }
/*    */   
/*    */   private static CallSite a(MethodHandles.Lookup paramLookup, String paramString, MethodType paramMethodType) {
/*    */     // Byte code:
/*    */     //   0: new java/lang/invoke/MutableCallSite
/*    */     //   3: dup
/*    */     //   4: aload_2
/*    */     //   5: invokespecial <init> : (Ljava/lang/invoke/MethodType;)V
/*    */     //   8: astore_3
/*    */     //   9: aload_3
/*    */     //   10: ldc_w
/*    */     //   13: ldc_w [Ljava/lang/Object;
/*    */     //   16: aload_2
/*    */     //   17: invokevirtual parameterCount : ()I
/*    */     //   20: invokevirtual asCollector : (Ljava/lang/Class;I)Ljava/lang/invoke/MethodHandle;
/*    */     //   23: iconst_0
/*    */     //   24: iconst_3
/*    */     //   25: anewarray java/lang/Object
/*    */     //   28: dup
/*    */     //   29: iconst_0
/*    */     //   30: aload_0
/*    */     //   31: aastore
/*    */     //   32: dup
/*    */     //   33: iconst_1
/*    */     //   34: aload_3
/*    */     //   35: aastore
/*    */     //   36: dup
/*    */     //   37: iconst_2
/*    */     //   38: aload_1
/*    */     //   39: aastore
/*    */     //   40: invokestatic insertArguments : (Ljava/lang/invoke/MethodHandle;I[Ljava/lang/Object;)Ljava/lang/invoke/MethodHandle;
/*    */     //   43: aload_2
/*    */     //   44: invokestatic explicitCastArguments : (Ljava/lang/invoke/MethodHandle;Ljava/lang/invoke/MethodType;)Ljava/lang/invoke/MethodHandle;
/*    */     //   47: invokevirtual setTarget : (Ljava/lang/invoke/MethodHandle;)V
/*    */     //   50: goto -> 171
/*    */     //   53: astore #4
/*    */     //   55: new java/lang/RuntimeException
/*    */     //   58: dup
/*    */     //   59: new java/lang/StringBuilder
/*    */     //   62: dup
/*    */     //   63: invokespecial <init> : ()V
/*    */     //   66: ldc_w '쟓氛൒ㆳ谋屳㭇䃳ꟗ꧛ㄓ溏笖鲗瞠냝ꉗ䬪'
/*    */     //   69: invokevirtual toCharArray : ()[C
/*    */     //   72: dup
/*    */     //   73: dup
/*    */     //   74: bipush #16
/*    */     //   76: dup_x1
/*    */     //   77: caload
/*    */     //   78: sipush #6394
/*    */     //   81: ixor
/*    */     //   82: i2c
/*    */     //   83: castore
/*    */     //   84: sipush #24749
/*    */     //   87: iconst_1
/*    */     //   88: iconst_5
/*    */     //   89: invokestatic A : (Ljava/lang/Object;SZI)Ljava/lang/String;
/*    */     //   92: invokevirtual append : (Ljava/lang/String;)Ljava/lang/StringBuilder;
/*    */     //   95: ldc_w 'ퟶ鸦睞簥'
/*    */     //   98: invokevirtual toCharArray : ()[C
/*    */     //   101: dup
/*    */     //   102: dup
/*    */     //   103: iconst_1
/*    */     //   104: dup_x1
/*    */     //   105: caload
/*    */     //   106: sipush #4392
/*    */     //   109: ixor
/*    */     //   110: i2c
/*    */     //   111: castore
/*    */     //   112: sipush #14654
/*    */     //   115: iconst_1
/*    */     //   116: iconst_2
/*    */     //   117: invokestatic A : (Ljava/lang/Object;SZI)Ljava/lang/String;
/*    */     //   120: invokevirtual append : (Ljava/lang/String;)Ljava/lang/StringBuilder;
/*    */     //   123: aload_1
/*    */     //   124: invokevirtual append : (Ljava/lang/String;)Ljava/lang/StringBuilder;
/*    */     //   127: ldc_w '噈貍࿃'
/*    */     //   130: invokevirtual toCharArray : ()[C
/*    */     //   133: dup
/*    */     //   134: dup
/*    */     //   135: iconst_2
/*    */     //   136: dup_x1
/*    */     //   137: caload
/*    */     //   138: sipush #29362
/*    */     //   141: ixor
/*    */     //   142: i2c
/*    */     //   143: castore
/*    */     //   144: sipush #14639
/*    */     //   147: iconst_1
/*    */     //   148: iconst_0
/*    */     //   149: invokestatic A : (Ljava/lang/Object;SZI)Ljava/lang/String;
/*    */     //   152: invokevirtual append : (Ljava/lang/String;)Ljava/lang/StringBuilder;
/*    */     //   155: aload_2
/*    */     //   156: invokevirtual toString : ()Ljava/lang/String;
/*    */     //   159: invokevirtual append : (Ljava/lang/String;)Ljava/lang/StringBuilder;
/*    */     //   162: invokevirtual toString : ()Ljava/lang/String;
/*    */     //   165: aload #4
/*    */     //   167: invokespecial <init> : (Ljava/lang/String;Ljava/lang/Throwable;)V
/*    */     //   170: athrow
/*    */     //   171: aload_3
/*    */     //   172: areturn
/*    */     // Exception table:
/*    */     //   from	to	target	type
/*    */     //   9	50	53	java/lang/Exception
/*    */   }
/*    */ }


/* Location:              C:\Users\BukkitBypass\Desktop\MatrixAC\AAC\AAC-spigot-5.2.0.jar!\me\konsolas\aac\j8.class
 * Java compiler version: 8 (52.0)
 * JD-Core Version:       1.1.3
 */