/*     */ package me.konsolas.aac;
/*     */ 
/*     */ import java.io.Closeable;
/*     */ import java.io.IOException;
/*     */ import java.lang.invoke.CallSite;
/*     */ import java.lang.invoke.MethodHandle;
/*     */ import java.lang.invoke.MethodHandles;
/*     */ import java.lang.invoke.MethodType;
/*     */ import java.lang.invoke.MutableCallSite;
/*     */ import java.util.HashMap;
/*     */ import java.util.List;
/*     */ import java.util.Map;
/*     */ import java.util.logging.Logger;
/*     */ import javax.crypto.Cipher;
/*     */ import javax.crypto.SecretKey;
/*     */ import javax.crypto.SecretKeyFactory;
/*     */ import javax.crypto.spec.DESKeySpec;
/*     */ import javax.crypto.spec.IvParameterSpec;
/*     */ 
/*     */ 
/*     */ 
/*     */ 
/*     */ 
/*     */ 
/*     */ 
/*     */ 
/*     */ 
/*     */ 
/*     */ 
/*     */ 
/*     */ 
/*     */ 
/*     */ 
/*     */ 
/*     */ 
/*     */ 
/*     */ 
/*     */ 
/*     */ 
/*     */ 
/*     */ 
/*     */ 
/*     */ 
/*     */ 
/*     */ 
/*     */ 
/*     */ 
/*     */ 
/*     */ 
/*     */ 
/*     */ 
/*     */ 
/*     */ 
/*     */ 
/*     */ 
/*     */ 
/*     */ 
/*     */ 
/*     */ 
/*     */ 
/*     */ 
/*     */ 
/*     */ 
/*     */ 
/*     */ 
/*     */ 
/*     */ 
/*     */ 
/*     */ 
/*     */ 
/*     */ 
/*     */ 
/*     */ 
/*     */ 
/*     */ 
/*     */ 
/*     */ 
/*     */ 
/*     */ 
/*     */ 
/*     */ 
/*     */ 
/*     */ 
/*     */ 
/*     */ 
/*     */ 
/*     */ 
/*     */ 
/*     */ 
/*     */ 
/*     */ 
/*     */ 
/*     */ 
/*     */ 
/*     */ 
/*     */ final class ja
/*     */   implements Closeable
/*     */ {
/*     */   private static final Logger f;
/*     */   private final gi d;
/*     */   private final boolean e;
/*     */   private final fw b;
/*     */   private int a;
/*     */   private boolean g;
/*     */   final jk c;
/*     */   private static final long h;
/*     */   private static final String[] i;
/*     */   private static final String[] j;
/*     */   private static final Map k;
/*     */   
/*     */   public synchronized void a(boolean paramBoolean, int paramInt1, int paramInt2, long paramLong) {
/*     */     // Byte code:
/*     */     //   0: getstatic me/konsolas/aac/ja.h : J
/*     */     //   3: lload #4
/*     */     //   5: lxor
/*     */     //   6: lstore #4
/*     */     //   8: lload #4
/*     */     //   10: dup2
/*     */     //   11: ldc2_w 54944273052967
/*     */     //   14: lxor
/*     */     //   15: lstore #6
/*     */     //   17: dup2
/*     */     //   18: ldc2_w 42841010584994
/*     */     //   21: lxor
/*     */     //   22: dup2
/*     */     //   23: bipush #32
/*     */     //   25: lushr
/*     */     //   26: l2i
/*     */     //   27: istore #8
/*     */     //   29: dup2
/*     */     //   30: bipush #32
/*     */     //   32: lshl
/*     */     //   33: bipush #48
/*     */     //   35: lushr
/*     */     //   36: l2i
/*     */     //   37: istore #9
/*     */     //   39: dup2
/*     */     //   40: bipush #48
/*     */     //   42: lshl
/*     */     //   43: bipush #48
/*     */     //   45: lushr
/*     */     //   46: l2i
/*     */     //   47: istore #10
/*     */     //   49: pop2
/*     */     //   50: pop2
/*     */     //   51: ldc2_w 422223656975851994
/*     */     //   54: lload #4
/*     */     //   56: <illegal opcode> w : (JJ)[Lme/konsolas/aac/aN;
/*     */     //   61: astore #11
/*     */     //   63: aload_0
/*     */     //   64: getfield g : Z
/*     */     //   67: aload #11
/*     */     //   69: ifnull -> 124
/*     */     //   72: ifeq -> 122
/*     */     //   75: goto -> 89
/*     */     //   78: ldc2_w 431212123025120769
/*     */     //   81: lload #4
/*     */     //   83: <illegal opcode> w : (Ljava/io/IOException;JJ)Ljava/io/IOException;
/*     */     //   88: athrow
/*     */     //   89: new java/io/IOException
/*     */     //   92: dup
/*     */     //   93: sipush #13637
/*     */     //   96: ldc2_w 5050812445478395781
/*     */     //   99: lload #4
/*     */     //   101: lxor
/*     */     //   102: <illegal opcode> f : (IJ)Ljava/lang/String;
/*     */     //   107: invokespecial <init> : (Ljava/lang/String;)V
/*     */     //   110: athrow
/*     */     //   111: ldc2_w 431212123025120769
/*     */     //   114: lload #4
/*     */     //   116: <illegal opcode> w : (Ljava/io/IOException;JJ)Ljava/io/IOException;
/*     */     //   121: athrow
/*     */     //   122: bipush #8
/*     */     //   124: istore #12
/*     */     //   126: bipush #6
/*     */     //   128: istore #13
/*     */     //   130: iload_1
/*     */     //   131: aload #11
/*     */     //   133: ifnull -> 154
/*     */     //   136: ifeq -> 157
/*     */     //   139: goto -> 153
/*     */     //   142: ldc2_w 431212123025120769
/*     */     //   145: lload #4
/*     */     //   147: <illegal opcode> w : (Ljava/io/IOException;JJ)Ljava/io/IOException;
/*     */     //   152: athrow
/*     */     //   153: iconst_1
/*     */     //   154: goto -> 158
/*     */     //   157: iconst_0
/*     */     //   158: istore #14
/*     */     //   160: iconst_0
/*     */     //   161: istore #15
/*     */     //   163: aload_0
/*     */     //   164: iload #15
/*     */     //   166: iload #12
/*     */     //   168: iload #8
/*     */     //   170: iload #13
/*     */     //   172: iload #9
/*     */     //   174: i2s
/*     */     //   175: iload #14
/*     */     //   177: iload #10
/*     */     //   179: i2s
/*     */     //   180: invokevirtual a : (IIIBSBS)V
/*     */     //   183: aload_0
/*     */     //   184: getfield d : Lme/konsolas/aac/gi;
/*     */     //   187: lload #6
/*     */     //   189: iload_2
/*     */     //   190: invokeinterface c : (JI)Lme/konsolas/aac/gi;
/*     */     //   195: pop
/*     */     //   196: aload_0
/*     */     //   197: getfield d : Lme/konsolas/aac/gi;
/*     */     //   200: lload #6
/*     */     //   202: iload_3
/*     */     //   203: invokeinterface c : (JI)Lme/konsolas/aac/gi;
/*     */     //   208: pop
/*     */     //   209: aload_0
/*     */     //   210: getfield d : Lme/konsolas/aac/gi;
/*     */     //   213: invokeinterface flush : ()V
/*     */     //   218: return
/*     */     // Line number table:
/*     */     //   Java source line number -> byte code offset
/*     */     //   #5	-> 63
/*     */     //   #128	-> 122
/*     */     //   #57	-> 126
/*     */     //   #77	-> 130
/*     */     //   #119	-> 160
/*     */     //   #109	-> 163
/*     */     //   #32	-> 183
/*     */     //   #116	-> 196
/*     */     //   #131	-> 209
/*     */     //   #72	-> 218
/*     */     // Exception table:
/*     */     //   from	to	target	type
/*     */     //   63	75	78	java/io/IOException
/*     */     //   72	111	111	java/io/IOException
/*     */     //   130	139	142	java/io/IOException
/*     */   }
/*     */   
/*     */   public synchronized void a(char paramChar, int paramInt1, int paramInt2, boolean paramBoolean, int paramInt3, fw paramfw, int paramInt4) {
/*     */     // Byte code:
/*     */     //   0: iload_1
/*     */     //   1: i2l
/*     */     //   2: bipush #48
/*     */     //   4: lshl
/*     */     //   5: iload_2
/*     */     //   6: i2l
/*     */     //   7: bipush #32
/*     */     //   9: lshl
/*     */     //   10: bipush #16
/*     */     //   12: lushr
/*     */     //   13: lor
/*     */     //   14: iload_3
/*     */     //   15: i2l
/*     */     //   16: bipush #48
/*     */     //   18: lshl
/*     */     //   19: bipush #48
/*     */     //   21: lushr
/*     */     //   22: lor
/*     */     //   23: getstatic me/konsolas/aac/ja.h : J
/*     */     //   26: lxor
/*     */     //   27: lstore #8
/*     */     //   29: lload #8
/*     */     //   31: dup2
/*     */     //   32: ldc2_w 44685435391727
/*     */     //   35: lxor
/*     */     //   36: dup2
/*     */     //   37: bipush #48
/*     */     //   39: lushr
/*     */     //   40: l2i
/*     */     //   41: istore #10
/*     */     //   43: dup2
/*     */     //   44: bipush #16
/*     */     //   46: lshl
/*     */     //   47: bipush #32
/*     */     //   49: lushr
/*     */     //   50: l2i
/*     */     //   51: istore #11
/*     */     //   53: dup2
/*     */     //   54: bipush #48
/*     */     //   56: lshl
/*     */     //   57: bipush #48
/*     */     //   59: lushr
/*     */     //   60: l2i
/*     */     //   61: istore #12
/*     */     //   63: pop2
/*     */     //   64: pop2
/*     */     //   65: ldc2_w -801270583490309913
/*     */     //   68: lload #8
/*     */     //   70: <illegal opcode> w : (JJ)[Lme/konsolas/aac/aN;
/*     */     //   75: astore #13
/*     */     //   77: aload_0
/*     */     //   78: getfield g : Z
/*     */     //   81: aload #13
/*     */     //   83: ifnull -> 137
/*     */     //   86: ifeq -> 136
/*     */     //   89: goto -> 103
/*     */     //   92: ldc2_w -808779107963113668
/*     */     //   95: lload #8
/*     */     //   97: <illegal opcode> w : (Ljava/io/IOException;JJ)Ljava/io/IOException;
/*     */     //   102: athrow
/*     */     //   103: new java/io/IOException
/*     */     //   106: dup
/*     */     //   107: sipush #13637
/*     */     //   110: ldc2_w 5050872345510833848
/*     */     //   113: lload #8
/*     */     //   115: lxor
/*     */     //   116: <illegal opcode> f : (IJ)Ljava/lang/String;
/*     */     //   121: invokespecial <init> : (Ljava/lang/String;)V
/*     */     //   124: athrow
/*     */     //   125: ldc2_w -808779107963113668
/*     */     //   128: lload #8
/*     */     //   130: <illegal opcode> w : (Ljava/io/IOException;JJ)Ljava/io/IOException;
/*     */     //   135: athrow
/*     */     //   136: iconst_0
/*     */     //   137: istore #14
/*     */     //   139: aload #13
/*     */     //   141: ifnull -> 190
/*     */     //   144: iload #4
/*     */     //   146: ifeq -> 170
/*     */     //   149: goto -> 163
/*     */     //   152: ldc2_w -808779107963113668
/*     */     //   155: lload #8
/*     */     //   157: <illegal opcode> w : (Ljava/io/IOException;JJ)Ljava/io/IOException;
/*     */     //   162: athrow
/*     */     //   163: iload #14
/*     */     //   165: iconst_1
/*     */     //   166: ior
/*     */     //   167: i2b
/*     */     //   168: istore #14
/*     */     //   170: aload_0
/*     */     //   171: iload #10
/*     */     //   173: i2c
/*     */     //   174: iload #5
/*     */     //   176: iload #11
/*     */     //   178: iload #14
/*     */     //   180: aload #6
/*     */     //   182: iload #12
/*     */     //   184: i2s
/*     */     //   185: iload #7
/*     */     //   187: invokevirtual a : (CIIBLme/konsolas/aac/fw;SI)V
/*     */     //   190: return
/*     */     // Line number table:
/*     */     //   Java source line number -> byte code offset
/*     */     //   #6	-> 77
/*     */     //   #123	-> 136
/*     */     //   #2	-> 139
/*     */     //   #47	-> 170
/*     */     //   #65	-> 190
/*     */     // Exception table:
/*     */     //   from	to	target	type
/*     */     //   77	89	92	java/io/IOException
/*     */     //   86	125	125	java/io/IOException
/*     */     //   139	149	152	java/io/IOException
/*     */   }
/*     */   
/*     */   ja(gi paramgi, boolean paramBoolean) {
/* 120 */     this.d = paramgi;
/*     */     this.e = paramBoolean;
/*     */     this.b = new fw();
/*     */     this.c = new jk(this.b);
/*     */     this.a = 16384;
/*     */   }
/*     */   
/*     */   public synchronized void b(dM paramdM, long paramLong) {
/*     */     // Byte code:
/*     */     //   0: getstatic me/konsolas/aac/ja.h : J
/*     */     //   3: lload_2
/*     */     //   4: lxor
/*     */     //   5: lstore_2
/*     */     //   6: lload_2
/*     */     //   7: dup2
/*     */     //   8: ldc2_w 109319903412362
/*     */     //   11: lxor
/*     */     //   12: dup2
/*     */     //   13: bipush #48
/*     */     //   15: lushr
/*     */     //   16: l2i
/*     */     //   17: istore #4
/*     */     //   19: dup2
/*     */     //   20: bipush #16
/*     */     //   22: lshl
/*     */     //   23: bipush #16
/*     */     //   25: lushr
/*     */     //   26: lstore #5
/*     */     //   28: pop2
/*     */     //   29: dup2
/*     */     //   30: ldc2_w 7175152493888
/*     */     //   33: lxor
/*     */     //   34: dup2
/*     */     //   35: bipush #32
/*     */     //   37: lushr
/*     */     //   38: l2i
/*     */     //   39: istore #7
/*     */     //   41: dup2
/*     */     //   42: bipush #32
/*     */     //   44: lshl
/*     */     //   45: bipush #48
/*     */     //   47: lushr
/*     */     //   48: l2i
/*     */     //   49: istore #8
/*     */     //   51: dup2
/*     */     //   52: bipush #48
/*     */     //   54: lshl
/*     */     //   55: bipush #48
/*     */     //   57: lushr
/*     */     //   58: l2i
/*     */     //   59: istore #9
/*     */     //   61: pop2
/*     */     //   62: dup2
/*     */     //   63: ldc2_w 129231351057208
/*     */     //   66: lxor
/*     */     //   67: lstore #10
/*     */     //   69: dup2
/*     */     //   70: ldc2_w 83964304697148
/*     */     //   73: lxor
/*     */     //   74: lstore #12
/*     */     //   76: pop2
/*     */     //   77: ldc2_w -2504517759647205064
/*     */     //   80: lload_2
/*     */     //   81: <illegal opcode> w : (JJ)[Lme/konsolas/aac/aN;
/*     */     //   86: astore #14
/*     */     //   88: aload_0
/*     */     //   89: getfield g : Z
/*     */     //   92: aload #14
/*     */     //   94: ifnull -> 170
/*     */     //   97: ifeq -> 144
/*     */     //   100: goto -> 113
/*     */     //   103: ldc2_w -2514739961897629981
/*     */     //   106: lload_2
/*     */     //   107: <illegal opcode> w : (Ljava/io/IOException;JJ)Ljava/io/IOException;
/*     */     //   112: athrow
/*     */     //   113: new java/io/IOException
/*     */     //   116: dup
/*     */     //   117: sipush #13637
/*     */     //   120: ldc2_w 5050847835549943655
/*     */     //   123: lload_2
/*     */     //   124: lxor
/*     */     //   125: <illegal opcode> f : (IJ)Ljava/lang/String;
/*     */     //   130: invokespecial <init> : (Ljava/lang/String;)V
/*     */     //   133: athrow
/*     */     //   134: ldc2_w -2514739961897629981
/*     */     //   137: lload_2
/*     */     //   138: <illegal opcode> w : (Ljava/io/IOException;JJ)Ljava/io/IOException;
/*     */     //   143: athrow
/*     */     //   144: aload_0
/*     */     //   145: aload_1
/*     */     //   146: aload_0
/*     */     //   147: getfield a : I
/*     */     //   150: iload #4
/*     */     //   152: i2c
/*     */     //   153: swap
/*     */     //   154: lload #5
/*     */     //   156: dup2_x1
/*     */     //   157: pop2
/*     */     //   158: invokevirtual a : (CJI)I
/*     */     //   161: putfield a : I
/*     */     //   164: aload_1
/*     */     //   165: lload #10
/*     */     //   167: invokevirtual b : (J)I
/*     */     //   170: aload #14
/*     */     //   172: ifnull -> 223
/*     */     //   175: iconst_m1
/*     */     //   176: if_icmpeq -> 222
/*     */     //   179: goto -> 192
/*     */     //   182: ldc2_w -2514739961897629981
/*     */     //   185: lload_2
/*     */     //   186: <illegal opcode> w : (Ljava/io/IOException;JJ)Ljava/io/IOException;
/*     */     //   191: athrow
/*     */     //   192: aload_0
/*     */     //   193: getfield c : Lme/konsolas/aac/jk;
/*     */     //   196: aload_1
/*     */     //   197: lload #10
/*     */     //   199: invokevirtual b : (J)I
/*     */     //   202: lload #12
/*     */     //   204: dup2_x1
/*     */     //   205: pop2
/*     */     //   206: invokevirtual a : (JI)V
/*     */     //   209: goto -> 222
/*     */     //   212: ldc2_w -2514739961897629981
/*     */     //   215: lload_2
/*     */     //   216: <illegal opcode> w : (Ljava/io/IOException;JJ)Ljava/io/IOException;
/*     */     //   221: athrow
/*     */     //   222: iconst_0
/*     */     //   223: istore #15
/*     */     //   225: iconst_4
/*     */     //   226: istore #16
/*     */     //   228: iconst_1
/*     */     //   229: istore #17
/*     */     //   231: iconst_0
/*     */     //   232: istore #18
/*     */     //   234: aload_0
/*     */     //   235: iload #18
/*     */     //   237: iload #15
/*     */     //   239: iload #7
/*     */     //   241: iload #16
/*     */     //   243: iload #8
/*     */     //   245: i2s
/*     */     //   246: iload #17
/*     */     //   248: iload #9
/*     */     //   250: i2s
/*     */     //   251: invokevirtual a : (IIIBSBS)V
/*     */     //   254: aload_0
/*     */     //   255: getfield d : Lme/konsolas/aac/gi;
/*     */     //   258: invokeinterface flush : ()V
/*     */     //   263: return
/*     */     // Line number table:
/*     */     //   Java source line number -> byte code offset
/*     */     //   #39	-> 88
/*     */     //   #22	-> 144
/*     */     //   #50	-> 164
/*     */     //   #147	-> 192
/*     */     //   #49	-> 222
/*     */     //   #17	-> 225
/*     */     //   #79	-> 228
/*     */     //   #138	-> 231
/*     */     //   #3	-> 234
/*     */     //   #20	-> 254
/*     */     //   #73	-> 263
/*     */     // Exception table:
/*     */     //   from	to	target	type
/*     */     //   88	100	103	java/io/IOException
/*     */     //   97	134	134	java/io/IOException
/*     */     //   170	179	182	java/io/IOException
/*     */     //   175	209	212	java/io/IOException
/*     */   }
/*     */   
/*     */   private static void a(gi paramgi, int paramInt, long paramLong) {
/* 132 */     paramLong = h ^ paramLong; long l = paramLong ^ 0x258BE2B8FD6L; paramgi.d(paramInt >>> 16 & 0xFF, l);
/*     */     paramgi.d(paramInt >>> 8 & 0xFF, l);
/*     */     paramgi.d(paramInt & 0xFF, l);
/*     */   }
/*     */   
/*     */   public synchronized void a(long paramLong, boolean paramBoolean, int paramInt, List paramList) {
/*     */     // Byte code:
/*     */     //   0: getstatic me/konsolas/aac/ja.h : J
/*     */     //   3: lload_1
/*     */     //   4: lxor
/*     */     //   5: lstore_1
/*     */     //   6: lload_1
/*     */     //   7: dup2
/*     */     //   8: ldc2_w 104512493458588
/*     */     //   11: lxor
/*     */     //   12: lstore #6
/*     */     //   14: dup2
/*     */     //   15: ldc2_w 121706227706799
/*     */     //   18: lxor
/*     */     //   19: lstore #8
/*     */     //   21: dup2
/*     */     //   22: ldc2_w 113147065832994
/*     */     //   25: lxor
/*     */     //   26: dup2
/*     */     //   27: bipush #32
/*     */     //   29: lushr
/*     */     //   30: l2i
/*     */     //   31: istore #10
/*     */     //   33: dup2
/*     */     //   34: bipush #32
/*     */     //   36: lshl
/*     */     //   37: bipush #48
/*     */     //   39: lushr
/*     */     //   40: l2i
/*     */     //   41: istore #11
/*     */     //   43: dup2
/*     */     //   44: bipush #48
/*     */     //   46: lshl
/*     */     //   47: bipush #48
/*     */     //   49: lushr
/*     */     //   50: l2i
/*     */     //   51: istore #12
/*     */     //   53: pop2
/*     */     //   54: dup2
/*     */     //   55: ldc2_w 129274136688255
/*     */     //   58: lxor
/*     */     //   59: lstore #13
/*     */     //   61: pop2
/*     */     //   62: ldc2_w 3340626608524544602
/*     */     //   65: lload_1
/*     */     //   66: <illegal opcode> w : (JJ)[Lme/konsolas/aac/aN;
/*     */     //   71: astore #15
/*     */     //   73: aload_0
/*     */     //   74: aload #15
/*     */     //   76: ifnull -> 141
/*     */     //   79: getfield g : Z
/*     */     //   82: ifeq -> 129
/*     */     //   85: goto -> 98
/*     */     //   88: ldc2_w 3349474409027745153
/*     */     //   91: lload_1
/*     */     //   92: <illegal opcode> w : (Ljava/io/IOException;JJ)Ljava/io/IOException;
/*     */     //   97: athrow
/*     */     //   98: new java/io/IOException
/*     */     //   101: dup
/*     */     //   102: sipush #13637
/*     */     //   105: ldc2_w 5050882871775048709
/*     */     //   108: lload_1
/*     */     //   109: lxor
/*     */     //   110: <illegal opcode> f : (IJ)Ljava/lang/String;
/*     */     //   115: invokespecial <init> : (Ljava/lang/String;)V
/*     */     //   118: athrow
/*     */     //   119: ldc2_w 3349474409027745153
/*     */     //   122: lload_1
/*     */     //   123: <illegal opcode> w : (Ljava/io/IOException;JJ)Ljava/io/IOException;
/*     */     //   128: athrow
/*     */     //   129: aload_0
/*     */     //   130: getfield c : Lme/konsolas/aac/jk;
/*     */     //   133: aload #5
/*     */     //   135: lload #13
/*     */     //   137: invokevirtual a : (Ljava/util/List;J)V
/*     */     //   140: aload_0
/*     */     //   141: getfield b : Lme/konsolas/aac/fw;
/*     */     //   144: invokevirtual f : ()J
/*     */     //   147: lstore #16
/*     */     //   149: aload_0
/*     */     //   150: getfield a : I
/*     */     //   153: i2l
/*     */     //   154: lload #16
/*     */     //   156: invokestatic min : (JJ)J
/*     */     //   159: l2i
/*     */     //   160: istore #18
/*     */     //   162: iconst_1
/*     */     //   163: istore #19
/*     */     //   165: lload #16
/*     */     //   167: iload #18
/*     */     //   169: i2l
/*     */     //   170: lcmp
/*     */     //   171: aload #15
/*     */     //   173: ifnull -> 193
/*     */     //   176: ifne -> 196
/*     */     //   179: goto -> 192
/*     */     //   182: ldc2_w 3349474409027745153
/*     */     //   185: lload_1
/*     */     //   186: <illegal opcode> w : (Ljava/io/IOException;JJ)Ljava/io/IOException;
/*     */     //   191: athrow
/*     */     //   192: iconst_4
/*     */     //   193: goto -> 197
/*     */     //   196: iconst_0
/*     */     //   197: istore #20
/*     */     //   199: iload_3
/*     */     //   200: aload #15
/*     */     //   202: ifnull -> 298
/*     */     //   205: ifeq -> 228
/*     */     //   208: goto -> 221
/*     */     //   211: ldc2_w 3349474409027745153
/*     */     //   214: lload_1
/*     */     //   215: <illegal opcode> w : (Ljava/io/IOException;JJ)Ljava/io/IOException;
/*     */     //   220: athrow
/*     */     //   221: iload #20
/*     */     //   223: iconst_1
/*     */     //   224: ior
/*     */     //   225: i2b
/*     */     //   226: istore #20
/*     */     //   228: aload_0
/*     */     //   229: iload #4
/*     */     //   231: iload #18
/*     */     //   233: iload #10
/*     */     //   235: iload #19
/*     */     //   237: iload #11
/*     */     //   239: i2s
/*     */     //   240: iload #20
/*     */     //   242: iload #12
/*     */     //   244: i2s
/*     */     //   245: invokevirtual a : (IIIBSBS)V
/*     */     //   248: lload_1
/*     */     //   249: lconst_0
/*     */     //   250: lcmp
/*     */     //   251: ifle -> 279
/*     */     //   254: aload_0
/*     */     //   255: aload #15
/*     */     //   257: ifnull -> 302
/*     */     //   260: getfield d : Lme/konsolas/aac/gi;
/*     */     //   263: aload_0
/*     */     //   264: getfield b : Lme/konsolas/aac/fw;
/*     */     //   267: lload #8
/*     */     //   269: dup2_x1
/*     */     //   270: pop2
/*     */     //   271: iload #18
/*     */     //   273: i2l
/*     */     //   274: invokeinterface b : (JLme/konsolas/aac/fw;J)V
/*     */     //   279: lload #16
/*     */     //   281: iload #18
/*     */     //   283: i2l
/*     */     //   284: lcmp
/*     */     //   285: goto -> 298
/*     */     //   288: ldc2_w 3349474409027745153
/*     */     //   291: lload_1
/*     */     //   292: <illegal opcode> w : (Ljava/io/IOException;JJ)Ljava/io/IOException;
/*     */     //   297: athrow
/*     */     //   298: ifle -> 315
/*     */     //   301: aload_0
/*     */     //   302: lload #6
/*     */     //   304: iload #4
/*     */     //   306: lload #16
/*     */     //   308: iload #18
/*     */     //   310: i2l
/*     */     //   311: lsub
/*     */     //   312: invokespecial b : (JIJ)V
/*     */     //   315: return
/*     */     // Line number table:
/*     */     //   Java source line number -> byte code offset
/*     */     //   #44	-> 73
/*     */     //   #33	-> 129
/*     */     //   #143	-> 140
/*     */     //   #140	-> 149
/*     */     //   #100	-> 162
/*     */     //   #125	-> 165
/*     */     //   #141	-> 199
/*     */     //   #19	-> 228
/*     */     //   #4	-> 248
/*     */     //   #18	-> 279
/*     */     //   #10	-> 315
/*     */     // Exception table:
/*     */     //   from	to	target	type
/*     */     //   73	85	88	java/io/IOException
/*     */     //   79	119	119	java/io/IOException
/*     */     //   165	179	182	java/io/IOException
/*     */     //   199	208	211	java/io/IOException
/*     */     //   228	285	288	java/io/IOException
/*     */   }
/*     */   
/*     */   public synchronized void a(char paramChar, int paramInt1, int paramInt2, dM paramdM) {
/*     */     // Byte code:
/*     */     //   0: iload_1
/*     */     //   1: i2l
/*     */     //   2: bipush #48
/*     */     //   4: lshl
/*     */     //   5: iload_2
/*     */     //   6: i2l
/*     */     //   7: bipush #32
/*     */     //   9: lshl
/*     */     //   10: bipush #16
/*     */     //   12: lushr
/*     */     //   13: lor
/*     */     //   14: iload_3
/*     */     //   15: i2l
/*     */     //   16: bipush #48
/*     */     //   18: lshl
/*     */     //   19: bipush #48
/*     */     //   21: lushr
/*     */     //   22: lor
/*     */     //   23: getstatic me/konsolas/aac/ja.h : J
/*     */     //   26: lxor
/*     */     //   27: lstore #5
/*     */     //   29: lload #5
/*     */     //   31: dup2
/*     */     //   32: ldc2_w 105981391040172
/*     */     //   35: lxor
/*     */     //   36: lstore #7
/*     */     //   38: dup2
/*     */     //   39: ldc2_w 52980018791037
/*     */     //   42: lxor
/*     */     //   43: lstore #9
/*     */     //   45: dup2
/*     */     //   46: ldc2_w 131313021314601
/*     */     //   49: lxor
/*     */     //   50: dup2
/*     */     //   51: bipush #32
/*     */     //   53: lushr
/*     */     //   54: l2i
/*     */     //   55: istore #11
/*     */     //   57: dup2
/*     */     //   58: bipush #32
/*     */     //   60: lshl
/*     */     //   61: bipush #48
/*     */     //   63: lushr
/*     */     //   64: l2i
/*     */     //   65: istore #12
/*     */     //   67: dup2
/*     */     //   68: bipush #48
/*     */     //   70: lshl
/*     */     //   71: bipush #48
/*     */     //   73: lushr
/*     */     //   74: l2i
/*     */     //   75: istore #13
/*     */     //   77: pop2
/*     */     //   78: dup2
/*     */     //   79: ldc2_w 99433324169955
/*     */     //   82: lxor
/*     */     //   83: dup2
/*     */     //   84: bipush #48
/*     */     //   86: lushr
/*     */     //   87: l2i
/*     */     //   88: istore #14
/*     */     //   90: dup2
/*     */     //   91: bipush #16
/*     */     //   93: lshl
/*     */     //   94: bipush #48
/*     */     //   96: lushr
/*     */     //   97: l2i
/*     */     //   98: istore #15
/*     */     //   100: dup2
/*     */     //   101: bipush #32
/*     */     //   103: lshl
/*     */     //   104: bipush #32
/*     */     //   106: lushr
/*     */     //   107: l2i
/*     */     //   108: istore #16
/*     */     //   110: pop2
/*     */     //   111: pop2
/*     */     //   112: ldc2_w -2425369033533212079
/*     */     //   115: lload #5
/*     */     //   117: <illegal opcode> w : (JJ)[Lme/konsolas/aac/aN;
/*     */     //   122: astore #17
/*     */     //   124: aload_0
/*     */     //   125: getfield g : Z
/*     */     //   128: aload #17
/*     */     //   130: ifnull -> 191
/*     */     //   133: ifeq -> 183
/*     */     //   136: goto -> 150
/*     */     //   139: ldc2_w -2418247460984207990
/*     */     //   142: lload #5
/*     */     //   144: <illegal opcode> w : (Ljava/io/IOException;JJ)Ljava/io/IOException;
/*     */     //   149: athrow
/*     */     //   150: new java/io/IOException
/*     */     //   153: dup
/*     */     //   154: sipush #13637
/*     */     //   157: ldc2_w 5050864719478801422
/*     */     //   160: lload #5
/*     */     //   162: lxor
/*     */     //   163: <illegal opcode> f : (IJ)Ljava/lang/String;
/*     */     //   168: invokespecial <init> : (Ljava/lang/String;)V
/*     */     //   171: athrow
/*     */     //   172: ldc2_w -2418247460984207990
/*     */     //   175: lload #5
/*     */     //   177: <illegal opcode> w : (Ljava/io/IOException;JJ)Ljava/io/IOException;
/*     */     //   182: athrow
/*     */     //   183: aload #4
/*     */     //   185: invokevirtual c : ()I
/*     */     //   188: bipush #6
/*     */     //   190: imul
/*     */     //   191: istore #18
/*     */     //   193: iconst_4
/*     */     //   194: istore #19
/*     */     //   196: iconst_0
/*     */     //   197: istore #20
/*     */     //   199: iconst_0
/*     */     //   200: istore #21
/*     */     //   202: aload_0
/*     */     //   203: iload #21
/*     */     //   205: iload #18
/*     */     //   207: iload #11
/*     */     //   209: iload #19
/*     */     //   211: iload #12
/*     */     //   213: i2s
/*     */     //   214: iload #20
/*     */     //   216: iload #13
/*     */     //   218: i2s
/*     */     //   219: invokevirtual a : (IIIBSBS)V
/*     */     //   222: iconst_0
/*     */     //   223: istore #22
/*     */     //   225: iload #22
/*     */     //   227: bipush #10
/*     */     //   229: if_icmpge -> 419
/*     */     //   232: aload #17
/*     */     //   234: ifnull -> 432
/*     */     //   237: aload #4
/*     */     //   239: iload #14
/*     */     //   241: i2c
/*     */     //   242: iload #15
/*     */     //   244: i2c
/*     */     //   245: iload #22
/*     */     //   247: iload #16
/*     */     //   249: invokevirtual a : (CCII)Z
/*     */     //   252: aload #17
/*     */     //   254: ifnull -> 294
/*     */     //   257: goto -> 271
/*     */     //   260: ldc2_w -2418247460984207990
/*     */     //   263: lload #5
/*     */     //   265: <illegal opcode> w : (Ljava/io/IOException;JJ)Ljava/io/IOException;
/*     */     //   270: athrow
/*     */     //   271: ifne -> 292
/*     */     //   274: goto -> 288
/*     */     //   277: ldc2_w -2418247460984207990
/*     */     //   280: lload #5
/*     */     //   282: <illegal opcode> w : (Ljava/io/IOException;JJ)Ljava/io/IOException;
/*     */     //   287: athrow
/*     */     //   288: iload_3
/*     */     //   289: ifge -> 411
/*     */     //   292: iload #22
/*     */     //   294: istore #23
/*     */     //   296: iload #23
/*     */     //   298: iconst_4
/*     */     //   299: aload #17
/*     */     //   301: ifnull -> 370
/*     */     //   304: if_icmpne -> 333
/*     */     //   307: goto -> 321
/*     */     //   310: ldc2_w -2418247460984207990
/*     */     //   313: lload #5
/*     */     //   315: <illegal opcode> w : (Ljava/io/IOException;JJ)Ljava/io/IOException;
/*     */     //   320: athrow
/*     */     //   321: iconst_3
/*     */     //   322: istore #23
/*     */     //   324: iload_2
/*     */     //   325: ifle -> 390
/*     */     //   328: aload #17
/*     */     //   330: ifnonnull -> 376
/*     */     //   333: iload #23
/*     */     //   335: aload #17
/*     */     //   337: ifnull -> 374
/*     */     //   340: goto -> 354
/*     */     //   343: ldc2_w -2418247460984207990
/*     */     //   346: lload #5
/*     */     //   348: <illegal opcode> w : (Ljava/io/IOException;JJ)Ljava/io/IOException;
/*     */     //   353: athrow
/*     */     //   354: bipush #7
/*     */     //   356: goto -> 370
/*     */     //   359: ldc2_w -2418247460984207990
/*     */     //   362: lload #5
/*     */     //   364: <illegal opcode> w : (Ljava/io/IOException;JJ)Ljava/io/IOException;
/*     */     //   369: athrow
/*     */     //   370: if_icmpne -> 376
/*     */     //   373: iconst_4
/*     */     //   374: istore #23
/*     */     //   376: aload_0
/*     */     //   377: getfield d : Lme/konsolas/aac/gi;
/*     */     //   380: lload #9
/*     */     //   382: iload #23
/*     */     //   384: invokeinterface e : (JI)Lme/konsolas/aac/gi;
/*     */     //   389: pop
/*     */     //   390: aload_0
/*     */     //   391: getfield d : Lme/konsolas/aac/gi;
/*     */     //   394: aload #4
/*     */     //   396: iload #22
/*     */     //   398: invokevirtual b : (I)I
/*     */     //   401: lload #7
/*     */     //   403: dup2_x1
/*     */     //   404: pop2
/*     */     //   405: invokeinterface c : (JI)Lme/konsolas/aac/gi;
/*     */     //   410: pop
/*     */     //   411: iinc #22, 1
/*     */     //   414: aload #17
/*     */     //   416: ifnonnull -> 225
/*     */     //   419: aload_0
/*     */     //   420: getfield d : Lme/konsolas/aac/gi;
/*     */     //   423: invokeinterface flush : ()V
/*     */     //   428: iload_2
/*     */     //   429: iflt -> 232
/*     */     //   432: return
/*     */     // Line number table:
/*     */     //   Java source line number -> byte code offset
/*     */     //   #51	-> 124
/*     */     //   #137	-> 183
/*     */     //   #136	-> 193
/*     */     //   #117	-> 196
/*     */     //   #118	-> 199
/*     */     //   #28	-> 202
/*     */     //   #60	-> 222
/*     */     //   #7	-> 232
/*     */     //   #85	-> 292
/*     */     //   #124	-> 296
/*     */     //   #96	-> 321
/*     */     //   #130	-> 333
/*     */     //   #56	-> 373
/*     */     //   #55	-> 376
/*     */     //   #103	-> 390
/*     */     //   #53	-> 411
/*     */     //   #40	-> 419
/*     */     //   #63	-> 432
/*     */     // Exception table:
/*     */     //   from	to	target	type
/*     */     //   124	136	139	java/io/IOException
/*     */     //   133	172	172	java/io/IOException
/*     */     //   232	257	260	java/io/IOException
/*     */     //   237	274	277	java/io/IOException
/*     */     //   296	307	310	java/io/IOException
/*     */     //   324	340	343	java/io/IOException
/*     */     //   333	356	359	java/io/IOException
/*     */   }
/*     */   
/*     */   public synchronized void a(int paramInt, long paramLong, eb parameb) {
/*     */     // Byte code:
/*     */     //   0: getstatic me/konsolas/aac/ja.h : J
/*     */     //   3: lload_2
/*     */     //   4: lxor
/*     */     //   5: lstore_2
/*     */     //   6: lload_2
/*     */     //   7: dup2
/*     */     //   8: ldc2_w 63963952712164
/*     */     //   11: lxor
/*     */     //   12: lstore #5
/*     */     //   14: dup2
/*     */     //   15: ldc2_w 49627314848097
/*     */     //   18: lxor
/*     */     //   19: dup2
/*     */     //   20: bipush #32
/*     */     //   22: lushr
/*     */     //   23: l2i
/*     */     //   24: istore #7
/*     */     //   26: dup2
/*     */     //   27: bipush #32
/*     */     //   29: lshl
/*     */     //   30: bipush #48
/*     */     //   32: lushr
/*     */     //   33: l2i
/*     */     //   34: istore #8
/*     */     //   36: dup2
/*     */     //   37: bipush #48
/*     */     //   39: lshl
/*     */     //   40: bipush #48
/*     */     //   42: lushr
/*     */     //   43: l2i
/*     */     //   44: istore #9
/*     */     //   46: pop2
/*     */     //   47: pop2
/*     */     //   48: ldc2_w -5107361280763536103
/*     */     //   51: lload_2
/*     */     //   52: <illegal opcode> w : (JJ)[Lme/konsolas/aac/aN;
/*     */     //   57: astore #10
/*     */     //   59: aload_0
/*     */     //   60: getfield g : Z
/*     */     //   63: aload #10
/*     */     //   65: ifnull -> 120
/*     */     //   68: ifeq -> 115
/*     */     //   71: goto -> 84
/*     */     //   74: ldc2_w -5100059463938759998
/*     */     //   77: lload_2
/*     */     //   78: <illegal opcode> w : (Ljava/io/IOException;JJ)Ljava/io/IOException;
/*     */     //   83: athrow
/*     */     //   84: new java/io/IOException
/*     */     //   87: dup
/*     */     //   88: sipush #13637
/*     */     //   91: ldc2_w 5050818854353249094
/*     */     //   94: lload_2
/*     */     //   95: lxor
/*     */     //   96: <illegal opcode> f : (IJ)Ljava/lang/String;
/*     */     //   101: invokespecial <init> : (Ljava/lang/String;)V
/*     */     //   104: athrow
/*     */     //   105: ldc2_w -5100059463938759998
/*     */     //   108: lload_2
/*     */     //   109: <illegal opcode> w : (Ljava/io/IOException;JJ)Ljava/io/IOException;
/*     */     //   114: athrow
/*     */     //   115: aload #4
/*     */     //   117: getfield httpCode : I
/*     */     //   120: aload #10
/*     */     //   122: ifnull -> 161
/*     */     //   125: iconst_m1
/*     */     //   126: if_icmpne -> 160
/*     */     //   129: goto -> 142
/*     */     //   132: ldc2_w -5100059463938759998
/*     */     //   135: lload_2
/*     */     //   136: <illegal opcode> w : (Ljava/io/IOException;JJ)Ljava/io/IOException;
/*     */     //   141: athrow
/*     */     //   142: new java/lang/IllegalArgumentException
/*     */     //   145: dup
/*     */     //   146: invokespecial <init> : ()V
/*     */     //   149: athrow
/*     */     //   150: ldc2_w -5100059463938759998
/*     */     //   153: lload_2
/*     */     //   154: <illegal opcode> w : (Ljava/io/IOException;JJ)Ljava/io/IOException;
/*     */     //   159: athrow
/*     */     //   160: iconst_4
/*     */     //   161: istore #11
/*     */     //   163: iconst_3
/*     */     //   164: istore #12
/*     */     //   166: iconst_0
/*     */     //   167: istore #13
/*     */     //   169: aload_0
/*     */     //   170: iload_1
/*     */     //   171: iload #11
/*     */     //   173: iload #7
/*     */     //   175: iload #12
/*     */     //   177: iload #8
/*     */     //   179: i2s
/*     */     //   180: iload #13
/*     */     //   182: iload #9
/*     */     //   184: i2s
/*     */     //   185: invokevirtual a : (IIIBSBS)V
/*     */     //   188: aload_0
/*     */     //   189: getfield d : Lme/konsolas/aac/gi;
/*     */     //   192: aload #4
/*     */     //   194: getfield httpCode : I
/*     */     //   197: lload #5
/*     */     //   199: dup2_x1
/*     */     //   200: pop2
/*     */     //   201: invokeinterface c : (JI)Lme/konsolas/aac/gi;
/*     */     //   206: pop
/*     */     //   207: aload_0
/*     */     //   208: getfield d : Lme/konsolas/aac/gi;
/*     */     //   211: invokeinterface flush : ()V
/*     */     //   216: return
/*     */     // Line number table:
/*     */     //   Java source line number -> byte code offset
/*     */     //   #52	-> 59
/*     */     //   #105	-> 115
/*     */     //   #26	-> 160
/*     */     //   #46	-> 163
/*     */     //   #35	-> 166
/*     */     //   #82	-> 169
/*     */     //   #59	-> 188
/*     */     //   #145	-> 207
/*     */     //   #88	-> 216
/*     */     // Exception table:
/*     */     //   from	to	target	type
/*     */     //   59	71	74	java/io/IOException
/*     */     //   68	105	105	java/io/IOException
/*     */     //   120	129	132	java/io/IOException
/*     */     //   125	150	150	java/io/IOException
/*     */   }
/*     */   
/*     */   public synchronized void a(int paramInt1, int paramInt2, short paramShort) {
/*     */     // Byte code:
/*     */     //   0: iload_1
/*     */     //   1: i2l
/*     */     //   2: bipush #32
/*     */     //   4: lshl
/*     */     //   5: iload_2
/*     */     //   6: i2l
/*     */     //   7: bipush #48
/*     */     //   9: lshl
/*     */     //   10: bipush #32
/*     */     //   12: lushr
/*     */     //   13: lor
/*     */     //   14: iload_3
/*     */     //   15: i2l
/*     */     //   16: bipush #48
/*     */     //   18: lshl
/*     */     //   19: bipush #48
/*     */     //   21: lushr
/*     */     //   22: lor
/*     */     //   23: getstatic me/konsolas/aac/ja.h : J
/*     */     //   26: lxor
/*     */     //   27: lstore #4
/*     */     //   29: lload #4
/*     */     //   31: dup2
/*     */     //   32: ldc2_w 74385794435887
/*     */     //   35: lxor
/*     */     //   36: lstore #6
/*     */     //   38: dup2
/*     */     //   39: ldc2_w 76991953572808
/*     */     //   42: lxor
/*     */     //   43: dup2
/*     */     //   44: bipush #48
/*     */     //   46: lushr
/*     */     //   47: l2i
/*     */     //   48: istore #8
/*     */     //   50: dup2
/*     */     //   51: bipush #16
/*     */     //   53: lshl
/*     */     //   54: bipush #32
/*     */     //   56: lushr
/*     */     //   57: l2i
/*     */     //   58: istore #9
/*     */     //   60: dup2
/*     */     //   61: bipush #48
/*     */     //   63: lshl
/*     */     //   64: bipush #48
/*     */     //   66: lushr
/*     */     //   67: l2i
/*     */     //   68: istore #10
/*     */     //   70: pop2
/*     */     //   71: dup2
/*     */     //   72: ldc2_w 124348765797635
/*     */     //   75: lxor
/*     */     //   76: lstore #11
/*     */     //   78: pop2
/*     */     //   79: ldc2_w -1007572480058976766
/*     */     //   82: lload #4
/*     */     //   84: <illegal opcode> w : (JJ)[Lme/konsolas/aac/aN;
/*     */     //   89: astore #13
/*     */     //   91: aload_0
/*     */     //   92: getfield g : Z
/*     */     //   95: aload #13
/*     */     //   97: ifnull -> 154
/*     */     //   100: ifeq -> 150
/*     */     //   103: goto -> 117
/*     */     //   106: ldc2_w -998795112724108839
/*     */     //   109: lload #4
/*     */     //   111: <illegal opcode> w : (Ljava/io/IOException;JJ)Ljava/io/IOException;
/*     */     //   116: athrow
/*     */     //   117: new java/io/IOException
/*     */     //   120: dup
/*     */     //   121: sipush #13637
/*     */     //   124: ldc2_w 5050926824196106333
/*     */     //   127: lload #4
/*     */     //   129: lxor
/*     */     //   130: <illegal opcode> f : (IJ)Ljava/lang/String;
/*     */     //   135: invokespecial <init> : (Ljava/lang/String;)V
/*     */     //   138: athrow
/*     */     //   139: ldc2_w -998795112724108839
/*     */     //   142: lload #4
/*     */     //   144: <illegal opcode> w : (Ljava/io/IOException;JJ)Ljava/io/IOException;
/*     */     //   149: athrow
/*     */     //   150: aload_0
/*     */     //   151: getfield e : Z
/*     */     //   154: aload #13
/*     */     //   156: ifnull -> 205
/*     */     //   159: ifne -> 177
/*     */     //   162: goto -> 176
/*     */     //   165: ldc2_w -998795112724108839
/*     */     //   168: lload #4
/*     */     //   170: <illegal opcode> w : (Ljava/io/IOException;JJ)Ljava/io/IOException;
/*     */     //   175: athrow
/*     */     //   176: return
/*     */     //   177: getstatic me/konsolas/aac/ja.f : Ljava/util/logging/Logger;
/*     */     //   180: aload #13
/*     */     //   182: ifnull -> 211
/*     */     //   185: getstatic java/util/logging/Level.FINE : Ljava/util/logging/Level;
/*     */     //   188: invokevirtual isLoggable : (Ljava/util/logging/Level;)Z
/*     */     //   191: goto -> 205
/*     */     //   194: ldc2_w -998795112724108839
/*     */     //   197: lload #4
/*     */     //   199: <illegal opcode> w : (Ljava/io/IOException;JJ)Ljava/io/IOException;
/*     */     //   204: athrow
/*     */     //   205: ifeq -> 246
/*     */     //   208: getstatic me/konsolas/aac/ja.f : Ljava/util/logging/Logger;
/*     */     //   211: sipush #20497
/*     */     //   214: ldc2_w 7959952778904800520
/*     */     //   217: lload #4
/*     */     //   219: lxor
/*     */     //   220: <illegal opcode> f : (IJ)Ljava/lang/String;
/*     */     //   225: iconst_1
/*     */     //   226: anewarray java/lang/Object
/*     */     //   229: dup
/*     */     //   230: iconst_0
/*     */     //   231: getstatic me/konsolas/aac/cx.c : Lme/konsolas/aac/gZ;
/*     */     //   234: lload #11
/*     */     //   236: invokevirtual d : (J)Ljava/lang/String;
/*     */     //   239: aastore
/*     */     //   240: invokestatic a : (Ljava/lang/String;[Ljava/lang/Object;)Ljava/lang/String;
/*     */     //   243: invokevirtual fine : (Ljava/lang/String;)V
/*     */     //   246: aload_0
/*     */     //   247: getfield d : Lme/konsolas/aac/gi;
/*     */     //   250: getstatic me/konsolas/aac/cx.c : Lme/konsolas/aac/gZ;
/*     */     //   253: lload #6
/*     */     //   255: invokevirtual b : (J)[B
/*     */     //   258: iload #8
/*     */     //   260: i2c
/*     */     //   261: swap
/*     */     //   262: iload #9
/*     */     //   264: swap
/*     */     //   265: iload #10
/*     */     //   267: i2c
/*     */     //   268: invokeinterface a : (CI[BC)Lme/konsolas/aac/gi;
/*     */     //   273: pop
/*     */     //   274: aload_0
/*     */     //   275: getfield d : Lme/konsolas/aac/gi;
/*     */     //   278: invokeinterface flush : ()V
/*     */     //   283: return
/*     */     // Line number table:
/*     */     //   Java source line number -> byte code offset
/*     */     //   #69	-> 91
/*     */     //   #115	-> 150
/*     */     //   #129	-> 177
/*     */     //   #107	-> 208
/*     */     //   #93	-> 246
/*     */     //   #74	-> 274
/*     */     //   #54	-> 283
/*     */     // Exception table:
/*     */     //   from	to	target	type
/*     */     //   91	103	106	java/io/IOException
/*     */     //   100	139	139	java/io/IOException
/*     */     //   154	162	165	java/io/IOException
/*     */     //   177	191	194	java/io/IOException
/*     */   }
/*     */   
/*     */   public synchronized void a(short paramShort, int paramInt1, int paramInt2, char paramChar, List paramList, int paramInt3) {
/*     */     // Byte code:
/*     */     //   0: iload_1
/*     */     //   1: i2l
/*     */     //   2: bipush #48
/*     */     //   4: lshl
/*     */     //   5: iload #4
/*     */     //   7: i2l
/*     */     //   8: bipush #48
/*     */     //   10: lshl
/*     */     //   11: bipush #16
/*     */     //   13: lushr
/*     */     //   14: lor
/*     */     //   15: iload #6
/*     */     //   17: i2l
/*     */     //   18: bipush #32
/*     */     //   20: lshl
/*     */     //   21: bipush #32
/*     */     //   23: lushr
/*     */     //   24: lor
/*     */     //   25: getstatic me/konsolas/aac/ja.h : J
/*     */     //   28: lxor
/*     */     //   29: lstore #7
/*     */     //   31: lload #7
/*     */     //   33: dup2
/*     */     //   34: ldc2_w 104370442800151
/*     */     //   37: lxor
/*     */     //   38: lstore #9
/*     */     //   40: dup2
/*     */     //   41: ldc2_w 123175524009516
/*     */     //   44: lxor
/*     */     //   45: lstore #11
/*     */     //   47: dup2
/*     */     //   48: ldc2_w 72268448184607
/*     */     //   51: lxor
/*     */     //   52: lstore #13
/*     */     //   54: dup2
/*     */     //   55: ldc2_w 81237796193426
/*     */     //   58: lxor
/*     */     //   59: dup2
/*     */     //   60: bipush #32
/*     */     //   62: lushr
/*     */     //   63: l2i
/*     */     //   64: istore #15
/*     */     //   66: dup2
/*     */     //   67: bipush #32
/*     */     //   69: lshl
/*     */     //   70: bipush #48
/*     */     //   72: lushr
/*     */     //   73: l2i
/*     */     //   74: istore #16
/*     */     //   76: dup2
/*     */     //   77: bipush #48
/*     */     //   79: lshl
/*     */     //   80: bipush #48
/*     */     //   82: lushr
/*     */     //   83: l2i
/*     */     //   84: istore #17
/*     */     //   86: pop2
/*     */     //   87: dup2
/*     */     //   88: ldc2_w 99610050192591
/*     */     //   91: lxor
/*     */     //   92: lstore #18
/*     */     //   94: pop2
/*     */     //   95: ldc2_w -4833377001248892694
/*     */     //   98: lload #7
/*     */     //   100: <illegal opcode> w : (JJ)[Lme/konsolas/aac/aN;
/*     */     //   105: astore #20
/*     */     //   107: aload_0
/*     */     //   108: aload #20
/*     */     //   110: ifnull -> 178
/*     */     //   113: getfield g : Z
/*     */     //   116: ifeq -> 166
/*     */     //   119: goto -> 133
/*     */     //   122: ldc2_w -4842611840581458127
/*     */     //   125: lload #7
/*     */     //   127: <illegal opcode> w : (Ljava/io/IOException;JJ)Ljava/io/IOException;
/*     */     //   132: athrow
/*     */     //   133: new java/io/IOException
/*     */     //   136: dup
/*     */     //   137: sipush #13637
/*     */     //   140: ldc2_w 5050919184160466613
/*     */     //   143: lload #7
/*     */     //   145: lxor
/*     */     //   146: <illegal opcode> f : (IJ)Ljava/lang/String;
/*     */     //   151: invokespecial <init> : (Ljava/lang/String;)V
/*     */     //   154: athrow
/*     */     //   155: ldc2_w -4842611840581458127
/*     */     //   158: lload #7
/*     */     //   160: <illegal opcode> w : (Ljava/io/IOException;JJ)Ljava/io/IOException;
/*     */     //   165: athrow
/*     */     //   166: aload_0
/*     */     //   167: getfield c : Lme/konsolas/aac/jk;
/*     */     //   170: aload #5
/*     */     //   172: lload #18
/*     */     //   174: invokevirtual a : (Ljava/util/List;J)V
/*     */     //   177: aload_0
/*     */     //   178: getfield b : Lme/konsolas/aac/fw;
/*     */     //   181: invokevirtual f : ()J
/*     */     //   184: lstore #21
/*     */     //   186: aload_0
/*     */     //   187: getfield a : I
/*     */     //   190: iconst_4
/*     */     //   191: isub
/*     */     //   192: i2l
/*     */     //   193: lload #21
/*     */     //   195: invokestatic min : (JJ)J
/*     */     //   198: l2i
/*     */     //   199: istore #23
/*     */     //   201: iconst_5
/*     */     //   202: istore #24
/*     */     //   204: lload #21
/*     */     //   206: iload #23
/*     */     //   208: i2l
/*     */     //   209: lcmp
/*     */     //   210: aload #20
/*     */     //   212: ifnull -> 233
/*     */     //   215: ifne -> 236
/*     */     //   218: goto -> 232
/*     */     //   221: ldc2_w -4842611840581458127
/*     */     //   224: lload #7
/*     */     //   226: <illegal opcode> w : (Ljava/io/IOException;JJ)Ljava/io/IOException;
/*     */     //   231: athrow
/*     */     //   232: iconst_4
/*     */     //   233: goto -> 237
/*     */     //   236: iconst_0
/*     */     //   237: istore #25
/*     */     //   239: aload_0
/*     */     //   240: iload_2
/*     */     //   241: iload #23
/*     */     //   243: iconst_4
/*     */     //   244: iadd
/*     */     //   245: iload #15
/*     */     //   247: iload #24
/*     */     //   249: iload #16
/*     */     //   251: i2s
/*     */     //   252: iload #25
/*     */     //   254: iload #17
/*     */     //   256: i2s
/*     */     //   257: invokevirtual a : (IIIBSBS)V
/*     */     //   260: aload_0
/*     */     //   261: getfield d : Lme/konsolas/aac/gi;
/*     */     //   264: iload_3
/*     */     //   265: ldc 2147483647
/*     */     //   267: iand
/*     */     //   268: lload #9
/*     */     //   270: dup2_x1
/*     */     //   271: pop2
/*     */     //   272: invokeinterface c : (JI)Lme/konsolas/aac/gi;
/*     */     //   277: pop
/*     */     //   278: iload_1
/*     */     //   279: iflt -> 307
/*     */     //   282: aload_0
/*     */     //   283: aload #20
/*     */     //   285: ifnull -> 345
/*     */     //   288: getfield d : Lme/konsolas/aac/gi;
/*     */     //   291: aload_0
/*     */     //   292: getfield b : Lme/konsolas/aac/fw;
/*     */     //   295: lload #13
/*     */     //   297: dup2_x1
/*     */     //   298: pop2
/*     */     //   299: iload #23
/*     */     //   301: i2l
/*     */     //   302: invokeinterface b : (JLme/konsolas/aac/fw;J)V
/*     */     //   307: lload #21
/*     */     //   309: iload #23
/*     */     //   311: i2l
/*     */     //   312: lcmp
/*     */     //   313: ifle -> 357
/*     */     //   316: goto -> 330
/*     */     //   319: ldc2_w -4842611840581458127
/*     */     //   322: lload #7
/*     */     //   324: <illegal opcode> w : (Ljava/io/IOException;JJ)Ljava/io/IOException;
/*     */     //   329: athrow
/*     */     //   330: aload_0
/*     */     //   331: goto -> 345
/*     */     //   334: ldc2_w -4842611840581458127
/*     */     //   337: lload #7
/*     */     //   339: <illegal opcode> w : (Ljava/io/IOException;JJ)Ljava/io/IOException;
/*     */     //   344: athrow
/*     */     //   345: lload #11
/*     */     //   347: iload_2
/*     */     //   348: lload #21
/*     */     //   350: iload #23
/*     */     //   352: i2l
/*     */     //   353: lsub
/*     */     //   354: invokespecial b : (JIJ)V
/*     */     //   357: return
/*     */     // Line number table:
/*     */     //   Java source line number -> byte code offset
/*     */     //   #75	-> 107
/*     */     //   #146	-> 166
/*     */     //   #62	-> 177
/*     */     //   #78	-> 186
/*     */     //   #42	-> 201
/*     */     //   #12	-> 204
/*     */     //   #111	-> 239
/*     */     //   #101	-> 260
/*     */     //   #139	-> 278
/*     */     //   #30	-> 307
/*     */     //   #112	-> 357
/*     */     // Exception table:
/*     */     //   from	to	target	type
/*     */     //   107	119	122	java/io/IOException
/*     */     //   113	155	155	java/io/IOException
/*     */     //   204	218	221	java/io/IOException
/*     */     //   239	316	319	java/io/IOException
/*     */     //   288	331	334	java/io/IOException
/*     */   }
/*     */   
/*     */   void a(char paramChar, int paramInt1, int paramInt2, byte paramByte, fw paramfw, short paramShort, int paramInt3) {
/*     */     // Byte code:
/*     */     //   0: iload_1
/*     */     //   1: i2l
/*     */     //   2: bipush #48
/*     */     //   4: lshl
/*     */     //   5: iload_3
/*     */     //   6: i2l
/*     */     //   7: bipush #32
/*     */     //   9: lshl
/*     */     //   10: bipush #16
/*     */     //   12: lushr
/*     */     //   13: lor
/*     */     //   14: iload #6
/*     */     //   16: i2l
/*     */     //   17: bipush #48
/*     */     //   19: lshl
/*     */     //   20: bipush #48
/*     */     //   22: lushr
/*     */     //   23: lor
/*     */     //   24: getstatic me/konsolas/aac/ja.h : J
/*     */     //   27: lxor
/*     */     //   28: lstore #8
/*     */     //   30: lload #8
/*     */     //   32: dup2
/*     */     //   33: ldc2_w 7258861769540
/*     */     //   36: lxor
/*     */     //   37: lstore #10
/*     */     //   39: dup2
/*     */     //   40: ldc2_w 16230667923145
/*     */     //   43: lxor
/*     */     //   44: dup2
/*     */     //   45: bipush #32
/*     */     //   47: lushr
/*     */     //   48: l2i
/*     */     //   49: istore #12
/*     */     //   51: dup2
/*     */     //   52: bipush #32
/*     */     //   54: lshl
/*     */     //   55: bipush #48
/*     */     //   57: lushr
/*     */     //   58: l2i
/*     */     //   59: istore #13
/*     */     //   61: dup2
/*     */     //   62: bipush #48
/*     */     //   64: lshl
/*     */     //   65: bipush #48
/*     */     //   67: lushr
/*     */     //   68: l2i
/*     */     //   69: istore #14
/*     */     //   71: pop2
/*     */     //   72: pop2
/*     */     //   73: ldc2_w -7586557553865493839
/*     */     //   76: lload #8
/*     */     //   78: <illegal opcode> w : (JJ)[Lme/konsolas/aac/aN;
/*     */     //   83: iconst_0
/*     */     //   84: istore #16
/*     */     //   86: astore #15
/*     */     //   88: aload_0
/*     */     //   89: aload #15
/*     */     //   91: ifnull -> 146
/*     */     //   94: iload_2
/*     */     //   95: iload #7
/*     */     //   97: iload #12
/*     */     //   99: iload #16
/*     */     //   101: iload #13
/*     */     //   103: i2s
/*     */     //   104: iload #4
/*     */     //   106: iload #14
/*     */     //   108: i2s
/*     */     //   109: invokevirtual a : (IIIBSBS)V
/*     */     //   112: iload #7
/*     */     //   114: ifle -> 161
/*     */     //   117: goto -> 131
/*     */     //   120: ldc2_w -7597342702916301462
/*     */     //   123: lload #8
/*     */     //   125: <illegal opcode> w : (Ljava/io/IOException;JJ)Ljava/io/IOException;
/*     */     //   130: athrow
/*     */     //   131: aload_0
/*     */     //   132: goto -> 146
/*     */     //   135: ldc2_w -7597342702916301462
/*     */     //   138: lload #8
/*     */     //   140: <illegal opcode> w : (Ljava/io/IOException;JJ)Ljava/io/IOException;
/*     */     //   145: athrow
/*     */     //   146: getfield d : Lme/konsolas/aac/gi;
/*     */     //   149: lload #10
/*     */     //   151: aload #5
/*     */     //   153: iload #7
/*     */     //   155: i2l
/*     */     //   156: invokeinterface b : (JLme/konsolas/aac/fw;J)V
/*     */     //   161: return
/*     */     // Line number table:
/*     */     //   Java source line number -> byte code offset
/*     */     //   #81	-> 83
/*     */     //   #11	-> 88
/*     */     //   #133	-> 112
/*     */     //   #121	-> 131
/*     */     //   #90	-> 161
/*     */     // Exception table:
/*     */     //   from	to	target	type
/*     */     //   88	117	120	java/io/IOException
/*     */     //   94	132	135	java/io/IOException
/*     */   }
/*     */   
/*     */   public int a() {
/*     */     return this.a;
/*     */   }
/*     */   
/*     */   public void a(int paramInt1, int paramInt2, int paramInt3, byte paramByte1, short paramShort1, byte paramByte2, short paramShort2) {
/*     */     // Byte code:
/*     */     //   0: iload_3
/*     */     //   1: i2l
/*     */     //   2: bipush #32
/*     */     //   4: lshl
/*     */     //   5: iload #5
/*     */     //   7: i2l
/*     */     //   8: bipush #48
/*     */     //   10: lshl
/*     */     //   11: bipush #32
/*     */     //   13: lushr
/*     */     //   14: lor
/*     */     //   15: iload #7
/*     */     //   17: i2l
/*     */     //   18: bipush #48
/*     */     //   20: lshl
/*     */     //   21: bipush #48
/*     */     //   23: lushr
/*     */     //   24: lor
/*     */     //   25: getstatic me/konsolas/aac/ja.h : J
/*     */     //   28: lxor
/*     */     //   29: lstore #8
/*     */     //   31: lload #8
/*     */     //   33: dup2
/*     */     //   34: ldc2_w 84756725933116
/*     */     //   37: lxor
/*     */     //   38: lstore #10
/*     */     //   40: dup2
/*     */     //   41: ldc2_w 96694126296880
/*     */     //   44: lxor
/*     */     //   45: lstore #12
/*     */     //   47: dup2
/*     */     //   48: ldc2_w 17257538952287
/*     */     //   51: lxor
/*     */     //   52: lstore #14
/*     */     //   54: dup2
/*     */     //   55: ldc2_w 138753392457424
/*     */     //   58: lxor
/*     */     //   59: dup2
/*     */     //   60: bipush #48
/*     */     //   62: lushr
/*     */     //   63: l2i
/*     */     //   64: istore #16
/*     */     //   66: dup2
/*     */     //   67: bipush #16
/*     */     //   69: lshl
/*     */     //   70: bipush #32
/*     */     //   72: lushr
/*     */     //   73: l2i
/*     */     //   74: istore #17
/*     */     //   76: dup2
/*     */     //   77: bipush #48
/*     */     //   79: lshl
/*     */     //   80: bipush #48
/*     */     //   82: lushr
/*     */     //   83: l2i
/*     */     //   84: istore #18
/*     */     //   86: pop2
/*     */     //   87: pop2
/*     */     //   88: ldc2_w 1497295970590126273
/*     */     //   91: lload #8
/*     */     //   93: <illegal opcode> w : (JJ)[Lme/konsolas/aac/aN;
/*     */     //   98: astore #19
/*     */     //   100: getstatic me/konsolas/aac/ja.f : Ljava/util/logging/Logger;
/*     */     //   103: getstatic java/util/logging/Level.FINE : Ljava/util/logging/Level;
/*     */     //   106: invokevirtual isLoggable : (Ljava/util/logging/Level;)Z
/*     */     //   109: aload #19
/*     */     //   111: ifnull -> 170
/*     */     //   114: ifeq -> 169
/*     */     //   117: goto -> 131
/*     */     //   120: ldc2_w 1504349375565598490
/*     */     //   123: lload #8
/*     */     //   125: <illegal opcode> w : (Ljava/io/IOException;JJ)Ljava/io/IOException;
/*     */     //   130: athrow
/*     */     //   131: getstatic me/konsolas/aac/ja.f : Ljava/util/logging/Logger;
/*     */     //   134: iconst_0
/*     */     //   135: iload #16
/*     */     //   137: i2c
/*     */     //   138: iload_1
/*     */     //   139: iload_2
/*     */     //   140: iload #17
/*     */     //   142: iload #18
/*     */     //   144: i2c
/*     */     //   145: iload #4
/*     */     //   147: iload #6
/*     */     //   149: invokestatic a : (ZCIIICBB)Ljava/lang/String;
/*     */     //   152: invokevirtual fine : (Ljava/lang/String;)V
/*     */     //   155: goto -> 169
/*     */     //   158: ldc2_w 1504349375565598490
/*     */     //   161: lload #8
/*     */     //   163: <illegal opcode> w : (Ljava/io/IOException;JJ)Ljava/io/IOException;
/*     */     //   168: athrow
/*     */     //   169: iload_2
/*     */     //   170: aload_0
/*     */     //   171: getfield a : I
/*     */     //   174: iload #5
/*     */     //   176: ifge -> 255
/*     */     //   179: aload #19
/*     */     //   181: ifnull -> 255
/*     */     //   184: if_icmple -> 251
/*     */     //   187: goto -> 201
/*     */     //   190: ldc2_w 1504349375565598490
/*     */     //   193: lload #8
/*     */     //   195: <illegal opcode> w : (Ljava/io/IOException;JJ)Ljava/io/IOException;
/*     */     //   200: athrow
/*     */     //   201: sipush #1551
/*     */     //   204: ldc2_w 8287857179974024659
/*     */     //   207: lload #8
/*     */     //   209: lxor
/*     */     //   210: <illegal opcode> f : (IJ)Ljava/lang/String;
/*     */     //   215: iconst_2
/*     */     //   216: anewarray java/lang/Object
/*     */     //   219: dup
/*     */     //   220: iconst_0
/*     */     //   221: aload_0
/*     */     //   222: getfield a : I
/*     */     //   225: invokestatic valueOf : (I)Ljava/lang/Integer;
/*     */     //   228: aastore
/*     */     //   229: dup
/*     */     //   230: iconst_1
/*     */     //   231: iload_2
/*     */     //   232: invokestatic valueOf : (I)Ljava/lang/Integer;
/*     */     //   235: aastore
/*     */     //   236: invokestatic a : (Ljava/lang/String;[Ljava/lang/Object;)Ljava/lang/IllegalArgumentException;
/*     */     //   239: athrow
/*     */     //   240: ldc2_w 1504349375565598490
/*     */     //   243: lload #8
/*     */     //   245: <illegal opcode> w : (Ljava/io/IOException;JJ)Ljava/io/IOException;
/*     */     //   250: athrow
/*     */     //   251: iload_1
/*     */     //   252: ldc_w -2147483648
/*     */     //   255: iand
/*     */     //   256: iload #7
/*     */     //   258: ifgt -> 267
/*     */     //   261: ifeq -> 304
/*     */     //   264: sipush #15808
/*     */     //   267: ldc2_w 4501296474281149981
/*     */     //   270: lload #8
/*     */     //   272: lxor
/*     */     //   273: <illegal opcode> f : (IJ)Ljava/lang/String;
/*     */     //   278: iconst_1
/*     */     //   279: anewarray java/lang/Object
/*     */     //   282: dup
/*     */     //   283: iconst_0
/*     */     //   284: iload_1
/*     */     //   285: invokestatic valueOf : (I)Ljava/lang/Integer;
/*     */     //   288: aastore
/*     */     //   289: invokestatic a : (Ljava/lang/String;[Ljava/lang/Object;)Ljava/lang/IllegalArgumentException;
/*     */     //   292: athrow
/*     */     //   293: ldc2_w 1504349375565598490
/*     */     //   296: lload #8
/*     */     //   298: <illegal opcode> w : (Ljava/io/IOException;JJ)Ljava/io/IOException;
/*     */     //   303: athrow
/*     */     //   304: aload_0
/*     */     //   305: getfield d : Lme/konsolas/aac/gi;
/*     */     //   308: iload_2
/*     */     //   309: lload #12
/*     */     //   311: invokestatic a : (Lme/konsolas/aac/gi;IJ)V
/*     */     //   314: aload_0
/*     */     //   315: getfield d : Lme/konsolas/aac/gi;
/*     */     //   318: iload #4
/*     */     //   320: sipush #255
/*     */     //   323: iand
/*     */     //   324: lload #14
/*     */     //   326: invokeinterface d : (IJ)Lme/konsolas/aac/gi;
/*     */     //   331: pop
/*     */     //   332: aload_0
/*     */     //   333: getfield d : Lme/konsolas/aac/gi;
/*     */     //   336: iload #6
/*     */     //   338: sipush #255
/*     */     //   341: iand
/*     */     //   342: lload #14
/*     */     //   344: invokeinterface d : (IJ)Lme/konsolas/aac/gi;
/*     */     //   349: pop
/*     */     //   350: aload_0
/*     */     //   351: getfield d : Lme/konsolas/aac/gi;
/*     */     //   354: iload_1
/*     */     //   355: ldc 2147483647
/*     */     //   357: iand
/*     */     //   358: lload #10
/*     */     //   360: dup2_x1
/*     */     //   361: pop2
/*     */     //   362: invokeinterface c : (JI)Lme/konsolas/aac/gi;
/*     */     //   367: pop
/*     */     //   368: return
/*     */     // Line number table:
/*     */     //   Java source line number -> byte code offset
/*     */     //   #87	-> 100
/*     */     //   #76	-> 169
/*     */     //   #67	-> 201
/*     */     //   #122	-> 251
/*     */     //   #66	-> 304
/*     */     //   #1	-> 314
/*     */     //   #134	-> 332
/*     */     //   #99	-> 350
/*     */     //   #31	-> 368
/*     */     // Exception table:
/*     */     //   from	to	target	type
/*     */     //   100	117	120	java/io/IOException
/*     */     //   114	155	158	java/io/IOException
/*     */     //   170	187	190	java/io/IOException
/*     */     //   184	240	240	java/io/IOException
/*     */     //   255	293	293	java/io/IOException
/*     */   }
/*     */   
/*     */   public synchronized void b(int paramInt1, byte paramByte, int paramInt2) {
/*     */     // Byte code:
/*     */     //   0: iload_1
/*     */     //   1: i2l
/*     */     //   2: bipush #32
/*     */     //   4: lshl
/*     */     //   5: iload_2
/*     */     //   6: i2l
/*     */     //   7: bipush #56
/*     */     //   9: lshl
/*     */     //   10: bipush #32
/*     */     //   12: lushr
/*     */     //   13: lor
/*     */     //   14: iload_3
/*     */     //   15: i2l
/*     */     //   16: bipush #40
/*     */     //   18: lshl
/*     */     //   19: bipush #40
/*     */     //   21: lushr
/*     */     //   22: lor
/*     */     //   23: getstatic me/konsolas/aac/ja.h : J
/*     */     //   26: lxor
/*     */     //   27: lstore #4
/*     */     //   29: ldc2_w -4821882156473231085
/*     */     //   32: lload #4
/*     */     //   34: <illegal opcode> w : (JJ)[Lme/konsolas/aac/aN;
/*     */     //   39: astore #6
/*     */     //   41: aload_0
/*     */     //   42: aload #6
/*     */     //   44: ifnull -> 101
/*     */     //   47: getfield g : Z
/*     */     //   50: ifeq -> 100
/*     */     //   53: goto -> 67
/*     */     //   56: ldc2_w -4813564393120815416
/*     */     //   59: lload #4
/*     */     //   61: <illegal opcode> w : (Ljava/io/IOException;JJ)Ljava/io/IOException;
/*     */     //   66: athrow
/*     */     //   67: new java/io/IOException
/*     */     //   70: dup
/*     */     //   71: sipush #12235
/*     */     //   74: ldc2_w 6456200826425327040
/*     */     //   77: lload #4
/*     */     //   79: lxor
/*     */     //   80: <illegal opcode> f : (IJ)Ljava/lang/String;
/*     */     //   85: invokespecial <init> : (Ljava/lang/String;)V
/*     */     //   88: athrow
/*     */     //   89: ldc2_w -4813564393120815416
/*     */     //   92: lload #4
/*     */     //   94: <illegal opcode> w : (Ljava/io/IOException;JJ)Ljava/io/IOException;
/*     */     //   99: athrow
/*     */     //   100: aload_0
/*     */     //   101: getfield d : Lme/konsolas/aac/gi;
/*     */     //   104: invokeinterface flush : ()V
/*     */     //   109: return
/*     */     // Line number table:
/*     */     //   Java source line number -> byte code offset
/*     */     //   #91	-> 41
/*     */     //   #98	-> 100
/*     */     //   #23	-> 109
/*     */     // Exception table:
/*     */     //   from	to	target	type
/*     */     //   41	53	56	java/io/IOException
/*     */     //   47	89	89	java/io/IOException
/*     */   }
/*     */   
/*     */   public synchronized void close() {
/*     */     this.g = true;
/*     */     this.d.close();
/*     */   }
/*     */   
/*     */   public synchronized void a(int paramInt, long paramLong1, long paramLong2) {
/*     */     // Byte code:
/*     */     //   0: getstatic me/konsolas/aac/ja.h : J
/*     */     //   3: lload #4
/*     */     //   5: lxor
/*     */     //   6: lstore #4
/*     */     //   8: lload #4
/*     */     //   10: dup2
/*     */     //   11: ldc2_w 58881196224971
/*     */     //   14: lxor
/*     */     //   15: lstore #6
/*     */     //   17: dup2
/*     */     //   18: ldc2_w 37947615213902
/*     */     //   21: lxor
/*     */     //   22: dup2
/*     */     //   23: bipush #32
/*     */     //   25: lushr
/*     */     //   26: l2i
/*     */     //   27: istore #8
/*     */     //   29: dup2
/*     */     //   30: bipush #32
/*     */     //   32: lshl
/*     */     //   33: bipush #48
/*     */     //   35: lushr
/*     */     //   36: l2i
/*     */     //   37: istore #9
/*     */     //   39: dup2
/*     */     //   40: bipush #48
/*     */     //   42: lshl
/*     */     //   43: bipush #48
/*     */     //   45: lushr
/*     */     //   46: l2i
/*     */     //   47: istore #10
/*     */     //   49: pop2
/*     */     //   50: pop2
/*     */     //   51: ldc2_w 4697270183489152310
/*     */     //   54: lload #4
/*     */     //   56: <illegal opcode> w : (JJ)[Lme/konsolas/aac/aN;
/*     */     //   61: astore #11
/*     */     //   63: aload_0
/*     */     //   64: getfield g : Z
/*     */     //   67: aload #11
/*     */     //   69: ifnull -> 125
/*     */     //   72: ifeq -> 122
/*     */     //   75: goto -> 89
/*     */     //   78: ldc2_w 4690496064668130029
/*     */     //   81: lload #4
/*     */     //   83: <illegal opcode> w : (Ljava/io/IOException;JJ)Ljava/io/IOException;
/*     */     //   88: athrow
/*     */     //   89: new java/io/IOException
/*     */     //   92: dup
/*     */     //   93: sipush #13637
/*     */     //   96: ldc2_w 5050808273506458473
/*     */     //   99: lload #4
/*     */     //   101: lxor
/*     */     //   102: <illegal opcode> f : (IJ)Ljava/lang/String;
/*     */     //   107: invokespecial <init> : (Ljava/lang/String;)V
/*     */     //   110: athrow
/*     */     //   111: ldc2_w 4690496064668130029
/*     */     //   114: lload #4
/*     */     //   116: <illegal opcode> w : (Ljava/io/IOException;JJ)Ljava/io/IOException;
/*     */     //   121: athrow
/*     */     //   122: lload_2
/*     */     //   123: lconst_0
/*     */     //   124: lcmp
/*     */     //   125: aload #11
/*     */     //   127: lload #4
/*     */     //   129: lconst_0
/*     */     //   130: lcmp
/*     */     //   131: ifle -> 175
/*     */     //   134: ifnull -> 173
/*     */     //   137: ifeq -> 195
/*     */     //   140: goto -> 154
/*     */     //   143: ldc2_w 4690496064668130029
/*     */     //   146: lload #4
/*     */     //   148: <illegal opcode> w : (Ljava/io/IOException;JJ)Ljava/io/IOException;
/*     */     //   153: athrow
/*     */     //   154: lload_2
/*     */     //   155: ldc2_w 2147483647
/*     */     //   158: lcmp
/*     */     //   159: goto -> 173
/*     */     //   162: ldc2_w 4690496064668130029
/*     */     //   165: lload #4
/*     */     //   167: <illegal opcode> w : (Ljava/io/IOException;JJ)Ljava/io/IOException;
/*     */     //   172: athrow
/*     */     //   173: aload #11
/*     */     //   175: ifnull -> 236
/*     */     //   178: ifle -> 235
/*     */     //   181: goto -> 195
/*     */     //   184: ldc2_w 4690496064668130029
/*     */     //   187: lload #4
/*     */     //   189: <illegal opcode> w : (Ljava/io/IOException;JJ)Ljava/io/IOException;
/*     */     //   194: athrow
/*     */     //   195: sipush #8124
/*     */     //   198: ldc2_w 7127895805138203029
/*     */     //   201: lload #4
/*     */     //   203: lxor
/*     */     //   204: <illegal opcode> f : (IJ)Ljava/lang/String;
/*     */     //   209: iconst_1
/*     */     //   210: anewarray java/lang/Object
/*     */     //   213: dup
/*     */     //   214: iconst_0
/*     */     //   215: lload_2
/*     */     //   216: invokestatic valueOf : (J)Ljava/lang/Long;
/*     */     //   219: aastore
/*     */     //   220: invokestatic a : (Ljava/lang/String;[Ljava/lang/Object;)Ljava/lang/IllegalArgumentException;
/*     */     //   223: athrow
/*     */     //   224: ldc2_w 4690496064668130029
/*     */     //   227: lload #4
/*     */     //   229: <illegal opcode> w : (Ljava/io/IOException;JJ)Ljava/io/IOException;
/*     */     //   234: athrow
/*     */     //   235: iconst_4
/*     */     //   236: istore #12
/*     */     //   238: bipush #8
/*     */     //   240: istore #13
/*     */     //   242: iconst_0
/*     */     //   243: istore #14
/*     */     //   245: aload_0
/*     */     //   246: iload_1
/*     */     //   247: iload #12
/*     */     //   249: iload #8
/*     */     //   251: iload #13
/*     */     //   253: iload #9
/*     */     //   255: i2s
/*     */     //   256: iload #14
/*     */     //   258: iload #10
/*     */     //   260: i2s
/*     */     //   261: invokevirtual a : (IIIBSBS)V
/*     */     //   264: aload_0
/*     */     //   265: getfield d : Lme/konsolas/aac/gi;
/*     */     //   268: lload_2
/*     */     //   269: l2i
/*     */     //   270: lload #6
/*     */     //   272: dup2_x1
/*     */     //   273: pop2
/*     */     //   274: invokeinterface c : (JI)Lme/konsolas/aac/gi;
/*     */     //   279: pop
/*     */     //   280: aload_0
/*     */     //   281: getfield d : Lme/konsolas/aac/gi;
/*     */     //   284: invokeinterface flush : ()V
/*     */     //   289: return
/*     */     // Line number table:
/*     */     //   Java source line number -> byte code offset
/*     */     //   #95	-> 63
/*     */     //   #43	-> 122
/*     */     //   #48	-> 195
/*     */     //   #16	-> 216
/*     */     //   #104	-> 220
/*     */     //   #84	-> 235
/*     */     //   #58	-> 238
/*     */     //   #13	-> 242
/*     */     //   #108	-> 245
/*     */     //   #86	-> 264
/*     */     //   #68	-> 280
/*     */     //   #36	-> 289
/*     */     // Exception table:
/*     */     //   from	to	target	type
/*     */     //   63	75	78	java/io/IOException
/*     */     //   72	111	111	java/io/IOException
/*     */     //   125	140	143	java/io/IOException
/*     */     //   137	159	162	java/io/IOException
/*     */     //   173	181	184	java/io/IOException
/*     */     //   178	224	224	java/io/IOException
/*     */   }
/*     */   
/*     */   static {
/*     */     long l;
/*     */     byte b1;
/*     */     for (h = nc.a(-2827487733877144154L, 5464137915106300970L, MethodHandles.lookup().lookupClass()).a(111822584494904L), k = new HashMap<>(13), l = h ^ 0x65A8C729E92L, "".toCharArray()[10] = (char)("".toCharArray()[10] ^ 0x6A2E), "".toCharArray()[0] = (char)("".toCharArray()[0] ^ 0x62CD), (new byte[8])[0] = (byte)(int)(l >>> 56L), b1 = 1; b1 < 8; ) {
/*     */       (new byte[8])[b1] = (byte)(int)(l << b1 * 8 >>> 56L);
/*     */       b1++;
/*     */     } 
/*     */     Cipher cipher;
/*     */     (cipher = Cipher.getInstance(hY$g6.H("".toCharArray(), (short)7548, (byte)4, (byte)4))).init(2, SecretKeyFactory.getInstance(hY$g6.H("".toCharArray(), (short)25218, (byte)2, (byte)5)).generateSecret(new DESKeySpec(new byte[8])), new IvParameterSpec(new byte[8]));
/*     */     String[] arrayOfString = new String[7];
/*     */     boolean bool = false;
/*     */     "????????".toCharArray()[17] = (char)("????????".toCharArray()[17] ^ 0x7C2E);
/*     */     String str;
/*     */     int i = (str = hY$g6.H("????????".toCharArray(), (short)12722, (byte)3, (byte)1)).length();
/*     */     byte b2 = 48;
/*     */     byte b = -1;
/*     */     while (true);
/*     */   }
/*     */   
/*     */   public synchronized void a(int paramInt, long paramLong, eb parameb, byte[] paramArrayOfbyte) {
/*     */     // Byte code:
/*     */     //   0: getstatic me/konsolas/aac/ja.h : J
/*     */     //   3: lload_2
/*     */     //   4: lxor
/*     */     //   5: lstore_2
/*     */     //   6: lload_2
/*     */     //   7: dup2
/*     */     //   8: ldc2_w 57473870350871
/*     */     //   11: lxor
/*     */     //   12: lstore #6
/*     */     //   14: dup2
/*     */     //   15: ldc2_w 48087244741408
/*     */     //   18: lxor
/*     */     //   19: dup2
/*     */     //   20: bipush #48
/*     */     //   22: lushr
/*     */     //   23: l2i
/*     */     //   24: istore #8
/*     */     //   26: dup2
/*     */     //   27: bipush #16
/*     */     //   29: lshl
/*     */     //   30: bipush #32
/*     */     //   32: lushr
/*     */     //   33: l2i
/*     */     //   34: istore #9
/*     */     //   36: dup2
/*     */     //   37: bipush #48
/*     */     //   39: lshl
/*     */     //   40: bipush #48
/*     */     //   42: lushr
/*     */     //   43: l2i
/*     */     //   44: istore #10
/*     */     //   46: pop2
/*     */     //   47: dup2
/*     */     //   48: ldc2_w 38807906239122
/*     */     //   51: lxor
/*     */     //   52: dup2
/*     */     //   53: bipush #32
/*     */     //   55: lushr
/*     */     //   56: l2i
/*     */     //   57: istore #11
/*     */     //   59: dup2
/*     */     //   60: bipush #32
/*     */     //   62: lshl
/*     */     //   63: bipush #48
/*     */     //   65: lushr
/*     */     //   66: l2i
/*     */     //   67: istore #12
/*     */     //   69: dup2
/*     */     //   70: bipush #48
/*     */     //   72: lshl
/*     */     //   73: bipush #48
/*     */     //   75: lushr
/*     */     //   76: l2i
/*     */     //   77: istore #13
/*     */     //   79: pop2
/*     */     //   80: pop2
/*     */     //   81: ldc2_w -365900355192545558
/*     */     //   84: lload_2
/*     */     //   85: <illegal opcode> w : (JJ)[Lme/konsolas/aac/aN;
/*     */     //   90: astore #14
/*     */     //   92: aload_0
/*     */     //   93: getfield g : Z
/*     */     //   96: aload #14
/*     */     //   98: ifnull -> 153
/*     */     //   101: ifeq -> 148
/*     */     //   104: goto -> 117
/*     */     //   107: ldc2_w -374928408829632207
/*     */     //   110: lload_2
/*     */     //   111: <illegal opcode> w : (Ljava/io/IOException;JJ)Ljava/io/IOException;
/*     */     //   116: athrow
/*     */     //   117: new java/io/IOException
/*     */     //   120: dup
/*     */     //   121: sipush #13637
/*     */     //   124: ldc2_w 5050807416470134965
/*     */     //   127: lload_2
/*     */     //   128: lxor
/*     */     //   129: <illegal opcode> f : (IJ)Ljava/lang/String;
/*     */     //   134: invokespecial <init> : (Ljava/lang/String;)V
/*     */     //   137: athrow
/*     */     //   138: ldc2_w -374928408829632207
/*     */     //   141: lload_2
/*     */     //   142: <illegal opcode> w : (Ljava/io/IOException;JJ)Ljava/io/IOException;
/*     */     //   147: athrow
/*     */     //   148: aload #4
/*     */     //   150: getfield httpCode : I
/*     */     //   153: lload_2
/*     */     //   154: lconst_0
/*     */     //   155: lcmp
/*     */     //   156: ifle -> 218
/*     */     //   159: iconst_m1
/*     */     //   160: aload #14
/*     */     //   162: ifnull -> 217
/*     */     //   165: if_icmpne -> 212
/*     */     //   168: goto -> 181
/*     */     //   171: ldc2_w -374928408829632207
/*     */     //   174: lload_2
/*     */     //   175: <illegal opcode> w : (Ljava/io/IOException;JJ)Ljava/io/IOException;
/*     */     //   180: athrow
/*     */     //   181: sipush #30372
/*     */     //   184: ldc2_w 8579621347545129815
/*     */     //   187: lload_2
/*     */     //   188: lxor
/*     */     //   189: <illegal opcode> f : (IJ)Ljava/lang/String;
/*     */     //   194: iconst_0
/*     */     //   195: anewarray java/lang/Object
/*     */     //   198: invokestatic a : (Ljava/lang/String;[Ljava/lang/Object;)Ljava/lang/IllegalArgumentException;
/*     */     //   201: athrow
/*     */     //   202: ldc2_w -374928408829632207
/*     */     //   205: lload_2
/*     */     //   206: <illegal opcode> w : (Ljava/io/IOException;JJ)Ljava/io/IOException;
/*     */     //   211: athrow
/*     */     //   212: bipush #8
/*     */     //   214: aload #5
/*     */     //   216: arraylength
/*     */     //   217: iadd
/*     */     //   218: istore #15
/*     */     //   220: bipush #7
/*     */     //   222: istore #16
/*     */     //   224: iconst_0
/*     */     //   225: istore #17
/*     */     //   227: iconst_0
/*     */     //   228: istore #18
/*     */     //   230: aload_0
/*     */     //   231: iload #18
/*     */     //   233: iload #15
/*     */     //   235: iload #11
/*     */     //   237: iload #16
/*     */     //   239: iload #12
/*     */     //   241: i2s
/*     */     //   242: iload #17
/*     */     //   244: iload #13
/*     */     //   246: i2s
/*     */     //   247: invokevirtual a : (IIIBSBS)V
/*     */     //   250: aload_0
/*     */     //   251: getfield d : Lme/konsolas/aac/gi;
/*     */     //   254: lload #6
/*     */     //   256: iload_1
/*     */     //   257: invokeinterface c : (JI)Lme/konsolas/aac/gi;
/*     */     //   262: pop
/*     */     //   263: aload_0
/*     */     //   264: getfield d : Lme/konsolas/aac/gi;
/*     */     //   267: aload #4
/*     */     //   269: getfield httpCode : I
/*     */     //   272: lload #6
/*     */     //   274: dup2_x1
/*     */     //   275: pop2
/*     */     //   276: invokeinterface c : (JI)Lme/konsolas/aac/gi;
/*     */     //   281: pop
/*     */     //   282: aload #14
/*     */     //   284: ifnull -> 348
/*     */     //   287: aload #5
/*     */     //   289: arraylength
/*     */     //   290: ifle -> 339
/*     */     //   293: goto -> 306
/*     */     //   296: ldc2_w -374928408829632207
/*     */     //   299: lload_2
/*     */     //   300: <illegal opcode> w : (Ljava/io/IOException;JJ)Ljava/io/IOException;
/*     */     //   305: athrow
/*     */     //   306: aload_0
/*     */     //   307: getfield d : Lme/konsolas/aac/gi;
/*     */     //   310: iload #8
/*     */     //   312: i2c
/*     */     //   313: iload #9
/*     */     //   315: aload #5
/*     */     //   317: iload #10
/*     */     //   319: i2c
/*     */     //   320: invokeinterface a : (CI[BC)Lme/konsolas/aac/gi;
/*     */     //   325: pop
/*     */     //   326: goto -> 339
/*     */     //   329: ldc2_w -374928408829632207
/*     */     //   332: lload_2
/*     */     //   333: <illegal opcode> w : (Ljava/io/IOException;JJ)Ljava/io/IOException;
/*     */     //   338: athrow
/*     */     //   339: aload_0
/*     */     //   340: getfield d : Lme/konsolas/aac/gi;
/*     */     //   343: invokeinterface flush : ()V
/*     */     //   348: return
/*     */     // Line number table:
/*     */     //   Java source line number -> byte code offset
/*     */     //   #135	-> 92
/*     */     //   #142	-> 148
/*     */     //   #8	-> 212
/*     */     //   #24	-> 220
/*     */     //   #29	-> 224
/*     */     //   #25	-> 227
/*     */     //   #102	-> 230
/*     */     //   #45	-> 250
/*     */     //   #41	-> 263
/*     */     //   #114	-> 282
/*     */     //   #110	-> 306
/*     */     //   #80	-> 339
/*     */     //   #127	-> 348
/*     */     // Exception table:
/*     */     //   from	to	target	type
/*     */     //   92	104	107	java/io/IOException
/*     */     //   101	138	138	java/io/IOException
/*     */     //   153	168	171	java/io/IOException
/*     */     //   165	202	202	java/io/IOException
/*     */     //   230	293	296	java/io/IOException
/*     */     //   287	326	329	java/io/IOException
/*     */   }
/*     */   
/*     */   private void b(long paramLong1, int paramInt, long paramLong2) {
/*     */     // Byte code:
/*     */     //   0: getstatic me/konsolas/aac/ja.h : J
/*     */     //   3: lload_1
/*     */     //   4: lxor
/*     */     //   5: lstore_1
/*     */     //   6: lload_1
/*     */     //   7: dup2
/*     */     //   8: ldc2_w 118363764921226
/*     */     //   11: lxor
/*     */     //   12: lstore #6
/*     */     //   14: dup2
/*     */     //   15: ldc2_w 109944132808199
/*     */     //   18: lxor
/*     */     //   19: dup2
/*     */     //   20: bipush #32
/*     */     //   22: lushr
/*     */     //   23: l2i
/*     */     //   24: istore #8
/*     */     //   26: dup2
/*     */     //   27: bipush #32
/*     */     //   29: lshl
/*     */     //   30: bipush #48
/*     */     //   32: lushr
/*     */     //   33: l2i
/*     */     //   34: istore #9
/*     */     //   36: dup2
/*     */     //   37: bipush #48
/*     */     //   39: lshl
/*     */     //   40: bipush #48
/*     */     //   42: lushr
/*     */     //   43: l2i
/*     */     //   44: istore #10
/*     */     //   46: pop2
/*     */     //   47: pop2
/*     */     //   48: ldc2_w -7603959474465574273
/*     */     //   51: lload_1
/*     */     //   52: <illegal opcode> w : (JJ)[Lme/konsolas/aac/aN;
/*     */     //   57: astore #13
/*     */     //   59: lload #4
/*     */     //   61: lconst_0
/*     */     //   62: lcmp
/*     */     //   63: ifle -> 167
/*     */     //   66: aload_0
/*     */     //   67: getfield a : I
/*     */     //   70: i2l
/*     */     //   71: lload #4
/*     */     //   73: invokestatic min : (JJ)J
/*     */     //   76: l2i
/*     */     //   77: istore #14
/*     */     //   79: lload #4
/*     */     //   81: iload #14
/*     */     //   83: i2l
/*     */     //   84: lsub
/*     */     //   85: lstore #4
/*     */     //   87: aload_0
/*     */     //   88: iload_3
/*     */     //   89: iload #14
/*     */     //   91: bipush #9
/*     */     //   93: lload #4
/*     */     //   95: lconst_0
/*     */     //   96: lcmp
/*     */     //   97: aload #13
/*     */     //   99: ifnull -> 119
/*     */     //   102: ifne -> 122
/*     */     //   105: goto -> 118
/*     */     //   108: ldc2_w -7611439419688645212
/*     */     //   111: lload_1
/*     */     //   112: <illegal opcode> w : (Ljava/io/IOException;JJ)Ljava/io/IOException;
/*     */     //   117: athrow
/*     */     //   118: iconst_4
/*     */     //   119: goto -> 123
/*     */     //   122: iconst_0
/*     */     //   123: istore #11
/*     */     //   125: istore #12
/*     */     //   127: iload #8
/*     */     //   129: iload #12
/*     */     //   131: iload #9
/*     */     //   133: i2s
/*     */     //   134: iload #11
/*     */     //   136: iload #10
/*     */     //   138: i2s
/*     */     //   139: invokevirtual a : (IIIBSBS)V
/*     */     //   142: aload_0
/*     */     //   143: getfield d : Lme/konsolas/aac/gi;
/*     */     //   146: aload_0
/*     */     //   147: getfield b : Lme/konsolas/aac/fw;
/*     */     //   150: lload #6
/*     */     //   152: dup2_x1
/*     */     //   153: pop2
/*     */     //   154: iload #14
/*     */     //   156: i2l
/*     */     //   157: invokeinterface b : (JLme/konsolas/aac/fw;J)V
/*     */     //   162: aload #13
/*     */     //   164: ifnonnull -> 59
/*     */     //   167: return
/*     */     // Line number table:
/*     */     //   Java source line number -> byte code offset
/*     */     //   #144	-> 59
/*     */     //   #113	-> 66
/*     */     //   #21	-> 79
/*     */     //   #9	-> 87
/*     */     //   #70	-> 142
/*     */     //   #61	-> 162
/*     */     //   #106	-> 167
/*     */     // Exception table:
/*     */     //   from	to	target	type
/*     */     //   87	105	108	java/io/IOException
/*     */   }
/*     */   
/*     */   private static IOException a(IOException paramIOException) {
/*     */     return paramIOException;
/*     */   }
/*     */   
/*     */   private static String a(byte[] paramArrayOfbyte) {
/*     */     byte b1 = 0;
/*     */     int i;
/*     */     char[] arrayOfChar = new char[i = paramArrayOfbyte.length];
/*     */     for (byte b2 = 0; b2 < i; b2++) {
/*     */       int j;
/*     */       if ((j = 0xFF & paramArrayOfbyte[b2]) < 192) {
/*     */         arrayOfChar[b1++] = (char)j;
/*     */       } else if (j < 224) {
/*     */         char c = (char)((char)(j & 0x1F) << 6);
/*     */         j = paramArrayOfbyte[++b2];
/*     */         c = (char)(c | (char)(j & 0x3F));
/*     */         arrayOfChar[b1++] = c;
/*     */       } else if (b2 < i - 2) {
/*     */         char c = (char)((char)(j & 0xF) << 12);
/*     */         j = paramArrayOfbyte[++b2];
/*     */         c = (char)(c | (char)(j & 0x3F) << 6);
/*     */         j = paramArrayOfbyte[++b2];
/*     */         c = (char)(c | (char)(j & 0x3F));
/*     */         arrayOfChar[b1++] = c;
/*     */       } 
/*     */     } 
/*     */     return new String(arrayOfChar, 0, b1);
/*     */   }
/*     */   
/*     */   private static String a(int paramInt, long paramLong) {
/*     */     int i = paramInt ^ (int)(paramLong & 0x7FFFL) ^ 0x2EA7;
/*     */     if (j[i] == null) {
/*     */       Object[] arrayOfObject;
/*     */       try {
/*     */         Long long_ = Long.valueOf(Thread.currentThread().getId());
/*     */         arrayOfObject = (Object[])k.get(long_);
/*     */         if (arrayOfObject == null) {
/*     */           arrayOfObject = new Object[3];
/*     */           "?".toCharArray()[2] = (char)("?".toCharArray()[2] ^ 0x6928);
/*     */           arrayOfObject[0] = Cipher.getInstance(da$gx.U("?".toCharArray(), (short)6026, false, true));
/*     */           "".toCharArray()[0] = (char)("".toCharArray()[0] ^ 0x53BF);
/*     */           arrayOfObject[1] = SecretKeyFactory.getInstance(da$gx.U("".toCharArray(), (short)11113, false, false));
/*     */           arrayOfObject[2] = new IvParameterSpec(new byte[8]);
/*     */           k.put(long_, arrayOfObject);
/*     */         } 
/*     */       } catch (Exception exception) {
/*     */         "".toCharArray()[1] = (char)("".toCharArray()[1] ^ 0x10C3);
/*     */         throw new RuntimeException(da$gx.U("".toCharArray(), (short)28622, false, true), exception);
/*     */       } 
/*     */       byte[] arrayOfByte1 = new byte[8];
/*     */       arrayOfByte1[0] = (byte)(int)(paramLong >>> 56L);
/*     */       for (byte b = 1; b < 8; b++)
/*     */         arrayOfByte1[b] = (byte)(int)(paramLong << b * 8 >>> 56L); 
/*     */       DESKeySpec dESKeySpec = new DESKeySpec(arrayOfByte1);
/*     */       SecretKey secretKey = ((SecretKeyFactory)arrayOfObject[1]).generateSecret(dESKeySpec);
/*     */       ((Cipher)arrayOfObject[0]).init(2, secretKey, (IvParameterSpec)arrayOfObject[2]);
/*     */       "".toCharArray()[9] = (char)("".toCharArray()[9] ^ 0x4C3F);
/*     */       byte[] arrayOfByte2 = i[i].getBytes(da$gx.U("".toCharArray(), (short)13237, false, false));
/*     */       j[i] = a(((Cipher)arrayOfObject[0]).doFinal(arrayOfByte2));
/*     */     } 
/*     */     return j[i];
/*     */   }
/*     */   
/*     */   private static Object a(MethodHandles.Lookup paramLookup, MutableCallSite paramMutableCallSite, String paramString, Object[] paramArrayOfObject) {
/*     */     int i = ((Integer)paramArrayOfObject[0]).intValue();
/*     */     long l = ((Long)paramArrayOfObject[1]).longValue();
/*     */     String str = a(i, l);
/*     */     MethodHandle methodHandle = MethodHandles.constant(String.class, str);
/*     */     paramMutableCallSite.setTarget(MethodHandles.dropArguments(methodHandle, 0, new Class[] { int.class, long.class }));
/*     */     return str;
/*     */   }
/*     */   
/*     */   private static CallSite a(MethodHandles.Lookup paramLookup, String paramString, MethodType paramMethodType) {
/*     */     // Byte code:
/*     */     //   0: new java/lang/invoke/MutableCallSite
/*     */     //   3: dup
/*     */     //   4: aload_2
/*     */     //   5: invokespecial <init> : (Ljava/lang/invoke/MethodType;)V
/*     */     //   8: astore_3
/*     */     //   9: aload_3
/*     */     //   10: ldc_w
/*     */     //   13: ldc_w [Ljava/lang/Object;
/*     */     //   16: aload_2
/*     */     //   17: invokevirtual parameterCount : ()I
/*     */     //   20: invokevirtual asCollector : (Ljava/lang/Class;I)Ljava/lang/invoke/MethodHandle;
/*     */     //   23: iconst_0
/*     */     //   24: iconst_3
/*     */     //   25: anewarray java/lang/Object
/*     */     //   28: dup
/*     */     //   29: iconst_0
/*     */     //   30: aload_0
/*     */     //   31: aastore
/*     */     //   32: dup
/*     */     //   33: iconst_1
/*     */     //   34: aload_3
/*     */     //   35: aastore
/*     */     //   36: dup
/*     */     //   37: iconst_2
/*     */     //   38: aload_1
/*     */     //   39: aastore
/*     */     //   40: invokestatic insertArguments : (Ljava/lang/invoke/MethodHandle;I[Ljava/lang/Object;)Ljava/lang/invoke/MethodHandle;
/*     */     //   43: aload_2
/*     */     //   44: invokestatic explicitCastArguments : (Ljava/lang/invoke/MethodHandle;Ljava/lang/invoke/MethodType;)Ljava/lang/invoke/MethodHandle;
/*     */     //   47: invokevirtual setTarget : (Ljava/lang/invoke/MethodHandle;)V
/*     */     //   50: goto -> 171
/*     */     //   53: astore #4
/*     */     //   55: new java/lang/RuntimeException
/*     */     //   58: dup
/*     */     //   59: new java/lang/StringBuilder
/*     */     //   62: dup
/*     */     //   63: invokespecial <init> : ()V
/*     */     //   66: ldc_w '?'
/*     */     //   69: invokevirtual toCharArray : ()[C
/*     */     //   72: dup
/*     */     //   73: dup
/*     */     //   74: bipush #9
/*     */     //   76: dup_x1
/*     */     //   77: caload
/*     */     //   78: sipush #19116
/*     */     //   81: ixor
/*     */     //   82: i2c
/*     */     //   83: castore
/*     */     //   84: sipush #29003
/*     */     //   87: iconst_1
/*     */     //   88: iconst_0
/*     */     //   89: invokestatic U : (Ljava/lang/Object;SZZ)Ljava/lang/String;
/*     */     //   92: invokevirtual append : (Ljava/lang/String;)Ljava/lang/StringBuilder;
/*     */     //   95: ldc_w ''
/*     */     //   98: invokevirtual toCharArray : ()[C
/*     */     //   101: dup
/*     */     //   102: dup
/*     */     //   103: iconst_2
/*     */     //   104: dup_x1
/*     */     //   105: caload
/*     */     //   106: sipush #5273
/*     */     //   109: ixor
/*     */     //   110: i2c
/*     */     //   111: castore
/*     */     //   112: sipush #13669
/*     */     //   115: iconst_1
/*     */     //   116: iconst_0
/*     */     //   117: invokestatic U : (Ljava/lang/Object;SZZ)Ljava/lang/String;
/*     */     //   120: invokevirtual append : (Ljava/lang/String;)Ljava/lang/StringBuilder;
/*     */     //   123: aload_1
/*     */     //   124: invokevirtual append : (Ljava/lang/String;)Ljava/lang/StringBuilder;
/*     */     //   127: ldc_w ''
/*     */     //   130: invokevirtual toCharArray : ()[C
/*     */     //   133: dup
/*     */     //   134: dup
/*     */     //   135: iconst_1
/*     */     //   136: dup_x1
/*     */     //   137: caload
/*     */     //   138: sipush #29783
/*     */     //   141: ixor
/*     */     //   142: i2c
/*     */     //   143: castore
/*     */     //   144: sipush #6515
/*     */     //   147: iconst_1
/*     */     //   148: iconst_0
/*     */     //   149: invokestatic U : (Ljava/lang/Object;SZZ)Ljava/lang/String;
/*     */     //   152: invokevirtual append : (Ljava/lang/String;)Ljava/lang/StringBuilder;
/*     */     //   155: aload_2
/*     */     //   156: invokevirtual toString : ()Ljava/lang/String;
/*     */     //   159: invokevirtual append : (Ljava/lang/String;)Ljava/lang/StringBuilder;
/*     */     //   162: invokevirtual toString : ()Ljava/lang/String;
/*     */     //   165: aload #4
/*     */     //   167: invokespecial <init> : (Ljava/lang/String;Ljava/lang/Throwable;)V
/*     */     //   170: athrow
/*     */     //   171: aload_3
/*     */     //   172: areturn
/*     */     // Exception table:
/*     */     //   from	to	target	type
/*     */     //   9	50	53	java/lang/Exception
/*     */   }
/*     */ }


/* Location:              C:\Users\BukkitBypass\Desktop\MatrixAC\AAC\AAC-spigot-5.2.0.jar!\me\konsolas\aac\ja.class
 * Java compiler version: 8 (52.0)
 * JD-Core Version:       1.1.3
 */