/*  1 */ package me.konsolas.aac;public final class jc extends jR { public static final mm h; public int a() { return this.a.size(); }
/*    */   
/*    */   public static final mm i; public static final mm g;
/*    */   public static final mm m;
/*    */   public static final mm d;
/*    */   private static final byte[] k;
/*    */   private static final byte[] j;
/*    */   private static final byte[] l;
/*    */   private final gZ c;
/*    */   private final mm e;
/*    */   private final mm b;
/*    */   private final List a;
/*    */   private long f;
/*    */   private static final long n;
/*    */   private static final String[] s;
/*    */   private static final String[] t;
/*    */   private static final Map u;
/*    */   
/*    */   static void a(StringBuilder paramStringBuilder, String paramString, long paramLong) {
/*    */     // Byte code:
/*    */     //   0: getstatic me/konsolas/aac/jc.n : J
/*    */     //   3: lload_2
/*    */     //   4: lxor
/*    */     //   5: lstore_2
/*    */     //   6: aload_0
/*    */     //   7: bipush #34
/*    */     //   9: invokevirtual append : (C)Ljava/lang/StringBuilder;
/*    */     //   12: pop
/*    */     //   13: ldc2_w 5761212200412794673
/*    */     //   16: lload_2
/*    */     //   17: <illegal opcode> w : (JJ)[Lme/konsolas/aac/aN;
/*    */     //   22: iconst_0
/*    */     //   23: istore #5
/*    */     //   25: aload_1
/*    */     //   26: invokevirtual length : ()I
/*    */     //   29: istore #6
/*    */     //   31: astore #4
/*    */     //   33: iload #5
/*    */     //   35: iload #6
/*    */     //   37: if_icmpge -> 288
/*    */     //   40: aload_1
/*    */     //   41: iload #5
/*    */     //   43: invokevirtual charAt : (I)C
/*    */     //   46: istore #7
/*    */     //   48: aload #4
/*    */     //   50: lload_2
/*    */     //   51: lconst_0
/*    */     //   52: lcmp
/*    */     //   53: iflt -> 61
/*    */     //   56: ifnonnull -> 301
/*    */     //   59: aload #4
/*    */     //   61: lload_2
/*    */     //   62: lconst_0
/*    */     //   63: lcmp
/*    */     //   64: iflt -> 167
/*    */     //   67: ifnonnull -> 165
/*    */     //   70: goto -> 83
/*    */     //   73: ldc2_w 5656796437601563327
/*    */     //   76: lload_2
/*    */     //   77: <illegal opcode> w : (Ljava/lang/Exception;JJ)Ljava/lang/Exception;
/*    */     //   82: athrow
/*    */     //   83: lload_2
/*    */     //   84: lconst_0
/*    */     //   85: lcmp
/*    */     //   86: iflt -> 267
/*    */     //   89: iload #7
/*    */     //   91: lookupswitch default -> 260, 10 -> 134, 13 -> 176, 34 -> 218
/*    */     //   124: ldc2_w 5656796437601563327
/*    */     //   127: lload_2
/*    */     //   128: <illegal opcode> w : (Ljava/lang/Exception;JJ)Ljava/lang/Exception;
/*    */     //   133: athrow
/*    */     //   134: aload_0
/*    */     //   135: sipush #25731
/*    */     //   138: ldc2_w 1512367732473098346
/*    */     //   141: lload_2
/*    */     //   142: lxor
/*    */     //   143: <illegal opcode> r : (IJ)Ljava/lang/String;
/*    */     //   148: invokevirtual append : (Ljava/lang/String;)Ljava/lang/StringBuilder;
/*    */     //   151: pop
/*    */     //   152: goto -> 165
/*    */     //   155: ldc2_w 5656796437601563327
/*    */     //   158: lload_2
/*    */     //   159: <illegal opcode> w : (Ljava/lang/Exception;JJ)Ljava/lang/Exception;
/*    */     //   164: athrow
/*    */     //   165: aload #4
/*    */     //   167: lload_2
/*    */     //   168: lconst_0
/*    */     //   169: lcmp
/*    */     //   170: ifle -> 285
/*    */     //   173: ifnull -> 280
/*    */     //   176: aload_0
/*    */     //   177: sipush #14003
/*    */     //   180: ldc2_w 559548753042317904
/*    */     //   183: lload_2
/*    */     //   184: lxor
/*    */     //   185: <illegal opcode> r : (IJ)Ljava/lang/String;
/*    */     //   190: invokevirtual append : (Ljava/lang/String;)Ljava/lang/StringBuilder;
/*    */     //   193: pop
/*    */     //   194: aload #4
/*    */     //   196: lload_2
/*    */     //   197: lconst_0
/*    */     //   198: lcmp
/*    */     //   199: iflt -> 285
/*    */     //   202: ifnull -> 280
/*    */     //   205: goto -> 218
/*    */     //   208: ldc2_w 5656796437601563327
/*    */     //   211: lload_2
/*    */     //   212: <illegal opcode> w : (Ljava/lang/Exception;JJ)Ljava/lang/Exception;
/*    */     //   217: athrow
/*    */     //   218: aload_0
/*    */     //   219: sipush #25592
/*    */     //   222: ldc2_w 7609269805664007954
/*    */     //   225: lload_2
/*    */     //   226: lxor
/*    */     //   227: <illegal opcode> r : (IJ)Ljava/lang/String;
/*    */     //   232: invokevirtual append : (Ljava/lang/String;)Ljava/lang/StringBuilder;
/*    */     //   235: pop
/*    */     //   236: aload #4
/*    */     //   238: lload_2
/*    */     //   239: lconst_0
/*    */     //   240: lcmp
/*    */     //   241: ifle -> 285
/*    */     //   244: ifnull -> 280
/*    */     //   247: goto -> 260
/*    */     //   250: ldc2_w 5656796437601563327
/*    */     //   253: lload_2
/*    */     //   254: <illegal opcode> w : (Ljava/lang/Exception;JJ)Ljava/lang/Exception;
/*    */     //   259: athrow
/*    */     //   260: aload_0
/*    */     //   261: iload #7
/*    */     //   263: invokevirtual append : (C)Ljava/lang/StringBuilder;
/*    */     //   266: pop
/*    */     //   267: goto -> 280
/*    */     //   270: ldc2_w 5656796437601563327
/*    */     //   273: lload_2
/*    */     //   274: <illegal opcode> w : (Ljava/lang/Exception;JJ)Ljava/lang/Exception;
/*    */     //   279: athrow
/*    */     //   280: iinc #5, 1
/*    */     //   283: aload #4
/*    */     //   285: ifnull -> 33
/*    */     //   288: aload_0
/*    */     //   289: bipush #34
/*    */     //   291: invokevirtual append : (C)Ljava/lang/StringBuilder;
/*    */     //   294: pop
/*    */     //   295: lload_2
/*    */     //   296: lconst_0
/*    */     //   297: lcmp
/*    */     //   298: ifle -> 301
/*    */     //   301: return
/*    */     // Line number table:
/*    */     //   Java source line number -> byte code offset
/*    */     //   #4	-> 6
/*    */     //   #5	-> 22
/*    */     //   #20	-> 40
/*    */     //   #41	-> 48
/*    */     //   #2	-> 134
/*    */     //   #66	-> 165
/*    */     //   #16	-> 176
/*    */     //   #44	-> 194
/*    */     //   #50	-> 218
/*    */     //   #10	-> 236
/*    */     //   #21	-> 260
/*    */     //   #78	-> 280
/*    */     //   #62	-> 288
/*    */     //   #63	-> 301
/*    */     // Exception table:
/*    */     //   from	to	target	type
/*    */     //   48	70	73	aacinternal/v
/*    */     //   59	124	124	aacinternal/v
/*    */     //   83	152	155	aacinternal/v
/*    */     //   165	205	208	aacinternal/v
/*    */     //   176	247	250	aacinternal/v
/*    */     //   218	267	270	aacinternal/v
/*    */   }
/*    */   
/*    */   public List a() {
/* 24 */     return this.a;
/*    */   }
/*    */   
/*    */   public mm a() {
/* 28 */     return this.b;
/*    */   }
/*    */   jc(gZ paramgZ, long paramLong, mm parammm, List paramList) {
/*    */     // Byte code:
/*    */     //   0: getstatic me/konsolas/aac/jc.n : J
/*    */     //   3: lload_2
/*    */     //   4: lxor
/*    */     //   5: lstore_2
/*    */     //   6: lload_2
/*    */     //   7: dup2
/*    */     //   8: ldc2_w 31855561970652
/*    */     //   11: lxor
/*    */     //   12: lstore #6
/*    */     //   14: dup2
/*    */     //   15: ldc2_w 11190735176633
/*    */     //   18: lxor
/*    */     //   19: lstore #8
/*    */     //   21: pop2
/*    */     //   22: aload_0
/*    */     //   23: invokespecial <init> : ()V
/*    */     //   26: aload_0
/*    */     //   27: ldc2_w -1
/*    */     //   30: putfield f : J
/*    */     //   33: aload_0
/*    */     //   34: aload_1
/*    */     //   35: putfield c : Lme/konsolas/aac/gZ;
/*    */     //   38: aload_0
/*    */     //   39: aload #4
/*    */     //   41: putfield e : Lme/konsolas/aac/mm;
/*    */     //   44: aload_0
/*    */     //   45: new java/lang/StringBuilder
/*    */     //   48: dup
/*    */     //   49: invokespecial <init> : ()V
/*    */     //   52: aload #4
/*    */     //   54: invokevirtual append : (Ljava/lang/Object;)Ljava/lang/StringBuilder;
/*    */     //   57: sipush #20045
/*    */     //   60: ldc2_w 4786918992190110574
/*    */     //   63: lload_2
/*    */     //   64: lxor
/*    */     //   65: <illegal opcode> r : (IJ)Ljava/lang/String;
/*    */     //   70: invokevirtual append : (Ljava/lang/String;)Ljava/lang/StringBuilder;
/*    */     //   73: aload_1
/*    */     //   74: lload #6
/*    */     //   76: invokevirtual c : (J)Ljava/lang/String;
/*    */     //   79: invokevirtual append : (Ljava/lang/String;)Ljava/lang/StringBuilder;
/*    */     //   82: invokevirtual toString : ()Ljava/lang/String;
/*    */     //   85: lload #8
/*    */     //   87: invokestatic a : (Ljava/lang/String;J)Lme/konsolas/aac/mm;
/*    */     //   90: putfield b : Lme/konsolas/aac/mm;
/*    */     //   93: aload_0
/*    */     //   94: aload #5
/*    */     //   96: invokestatic a : (Ljava/util/List;)Ljava/util/List;
/*    */     //   99: putfield a : Ljava/util/List;
/*    */     //   102: return
/*    */     // Line number table:
/*    */     //   Java source line number -> byte code offset
/*    */     //   #33	-> 22
/*    */     //   #69	-> 26
/*    */     //   #26	-> 33
/*    */     //   #55	-> 38
/*    */     //   #3	-> 44
/*    */     //   #83	-> 93
/*    */     //   #42	-> 102
/*    */   }
/*    */   
/*    */   public void a(gi paramgi, long paramLong) {
/* 35 */     long l = paramLong ^ 0x36297E6C9149L; a(paramgi, false, l);
/*    */   }
/*    */ 
/*    */ 
/*    */ 
/*    */   
/*    */   public long a(long paramLong) {
/*    */     // Byte code:
/*    */     //   0: lload_1
/*    */     //   1: dup2
/*    */     //   2: ldc2_w 97531663462654
/*    */     //   5: lxor
/*    */     //   6: lstore_3
/*    */     //   7: pop2
/*    */     //   8: ldc2_w -4793263420241756744
/*    */     //   11: lload_1
/*    */     //   12: <illegal opcode> w : (JJ)[Lme/konsolas/aac/aN;
/*    */     //   17: aload_0
/*    */     //   18: getfield f : J
/*    */     //   21: lstore #6
/*    */     //   23: astore #5
/*    */     //   25: lload #6
/*    */     //   27: aload #5
/*    */     //   29: ifnonnull -> 77
/*    */     //   32: ldc2_w -1
/*    */     //   35: lcmp
/*    */     //   36: ifeq -> 65
/*    */     //   39: goto -> 52
/*    */     //   42: ldc2_w -4897104067623239626
/*    */     //   45: lload_1
/*    */     //   46: <illegal opcode> w : (Ljava/lang/Exception;JJ)Ljava/lang/Exception;
/*    */     //   51: athrow
/*    */     //   52: lload #6
/*    */     //   54: lreturn
/*    */     //   55: ldc2_w -4897104067623239626
/*    */     //   58: lload_1
/*    */     //   59: <illegal opcode> w : (Ljava/lang/Exception;JJ)Ljava/lang/Exception;
/*    */     //   64: athrow
/*    */     //   65: aload_0
/*    */     //   66: aload_0
/*    */     //   67: aconst_null
/*    */     //   68: iconst_1
/*    */     //   69: lload_3
/*    */     //   70: invokespecial a : (Lme/konsolas/aac/gi;ZJ)J
/*    */     //   73: dup2_x1
/*    */     //   74: putfield f : J
/*    */     //   77: lreturn
/*    */     // Line number table:
/*    */     //   Java source line number -> byte code offset
/*    */     //   #39	-> 17
/*    */     //   #73	-> 25
/*    */     //   #31	-> 65
/*    */     // Exception table:
/*    */     //   from	to	target	type
/*    */     //   25	39	42	java/io/IOException
/*    */     //   32	55	55	java/io/IOException
/*    */   }
/*    */ 
/*    */ 
/*    */   
/*    */   public lP a(int paramInt) {
/* 48 */     return this.a.get(paramInt);
/*    */   }
/*    */   
/*    */   public String a(long paramLong)
/*    */   {
/* 53 */     paramLong = n ^ paramLong; long l = paramLong ^ 0x4FB0CEF89D4CL; return this.c.c(l); } public mm b() {
/* 54 */     return this.e;
/*    */   }
/*    */ 
/*    */ 
/*    */ 
/*    */ 
/*    */ 
/*    */   
/*    */   private long a(@Nullable gi paramgi, boolean paramBoolean, long paramLong) {
/*    */     // Byte code:
/*    */     //   0: getstatic me/konsolas/aac/jc.n : J
/*    */     //   3: lload_3
/*    */     //   4: lxor
/*    */     //   5: lstore_3
/*    */     //   6: lload_3
/*    */     //   7: dup2
/*    */     //   8: ldc2_w 91674956899871
/*    */     //   11: lxor
/*    */     //   12: dup2
/*    */     //   13: bipush #48
/*    */     //   15: lushr
/*    */     //   16: l2i
/*    */     //   17: istore #5
/*    */     //   19: dup2
/*    */     //   20: bipush #16
/*    */     //   22: lshl
/*    */     //   23: bipush #32
/*    */     //   25: lushr
/*    */     //   26: l2i
/*    */     //   27: istore #6
/*    */     //   29: dup2
/*    */     //   30: bipush #48
/*    */     //   32: lshl
/*    */     //   33: bipush #48
/*    */     //   35: lushr
/*    */     //   36: l2i
/*    */     //   37: istore #7
/*    */     //   39: pop2
/*    */     //   40: dup2
/*    */     //   41: ldc2_w 56056374688757
/*    */     //   44: lxor
/*    */     //   45: lstore #8
/*    */     //   47: dup2
/*    */     //   48: ldc2_w 70192057115714
/*    */     //   51: lxor
/*    */     //   52: lstore #10
/*    */     //   54: dup2
/*    */     //   55: ldc2_w 13864388450780
/*    */     //   58: lxor
/*    */     //   59: lstore #12
/*    */     //   61: dup2
/*    */     //   62: ldc2_w 74808610129420
/*    */     //   65: lxor
/*    */     //   66: dup2
/*    */     //   67: bipush #48
/*    */     //   69: lushr
/*    */     //   70: l2i
/*    */     //   71: istore #14
/*    */     //   73: dup2
/*    */     //   74: bipush #16
/*    */     //   76: lshl
/*    */     //   77: bipush #32
/*    */     //   79: lushr
/*    */     //   80: l2i
/*    */     //   81: istore #15
/*    */     //   83: dup2
/*    */     //   84: bipush #48
/*    */     //   86: lshl
/*    */     //   87: bipush #48
/*    */     //   89: lushr
/*    */     //   90: l2i
/*    */     //   91: istore #16
/*    */     //   93: pop2
/*    */     //   94: dup2
/*    */     //   95: ldc2_w 120294073151160
/*    */     //   98: lxor
/*    */     //   99: dup2
/*    */     //   100: bipush #48
/*    */     //   102: lushr
/*    */     //   103: l2i
/*    */     //   104: istore #17
/*    */     //   106: dup2
/*    */     //   107: bipush #16
/*    */     //   109: lshl
/*    */     //   110: bipush #32
/*    */     //   112: lushr
/*    */     //   113: l2i
/*    */     //   114: istore #18
/*    */     //   116: dup2
/*    */     //   117: bipush #48
/*    */     //   119: lshl
/*    */     //   120: bipush #48
/*    */     //   122: lushr
/*    */     //   123: l2i
/*    */     //   124: istore #19
/*    */     //   126: pop2
/*    */     //   127: dup2
/*    */     //   128: ldc2_w 101595405081154
/*    */     //   131: lxor
/*    */     //   132: lstore #20
/*    */     //   134: pop2
/*    */     //   135: ldc2_w 5084522932530660941
/*    */     //   138: lload_3
/*    */     //   139: <illegal opcode> w : (JJ)[Lme/konsolas/aac/aN;
/*    */     //   144: lconst_0
/*    */     //   145: lstore #23
/*    */     //   147: aconst_null
/*    */     //   148: astore #25
/*    */     //   150: astore #22
/*    */     //   152: iload_2
/*    */     //   153: ifeq -> 167
/*    */     //   156: new me/konsolas/aac/fw
/*    */     //   159: dup
/*    */     //   160: invokespecial <init> : ()V
/*    */     //   163: dup
/*    */     //   164: astore #25
/*    */     //   166: astore_1
/*    */     //   167: iconst_0
/*    */     //   168: istore #26
/*    */     //   170: aload_0
/*    */     //   171: getfield a : Ljava/util/List;
/*    */     //   174: invokeinterface size : ()I
/*    */     //   179: istore #27
/*    */     //   181: iload #26
/*    */     //   183: iload #27
/*    */     //   185: if_icmpge -> 772
/*    */     //   188: aload_0
/*    */     //   189: getfield a : Ljava/util/List;
/*    */     //   192: iload #26
/*    */     //   194: invokeinterface get : (I)Ljava/lang/Object;
/*    */     //   199: checkcast me/konsolas/aac/lP
/*    */     //   202: astore #28
/*    */     //   204: aload #28
/*    */     //   206: getfield b : Lme/konsolas/aac/J;
/*    */     //   209: astore #29
/*    */     //   211: aload #28
/*    */     //   213: getfield a : Lme/konsolas/aac/jR;
/*    */     //   216: astore #30
/*    */     //   218: aload_1
/*    */     //   219: iload #5
/*    */     //   221: i2c
/*    */     //   222: iload #6
/*    */     //   224: getstatic me/konsolas/aac/jc.l : [B
/*    */     //   227: iload #7
/*    */     //   229: i2c
/*    */     //   230: invokeinterface a : (CI[BC)Lme/konsolas/aac/gi;
/*    */     //   235: pop
/*    */     //   236: aload_1
/*    */     //   237: aload_0
/*    */     //   238: getfield c : Lme/konsolas/aac/gZ;
/*    */     //   241: lload #12
/*    */     //   243: invokeinterface a : (Lme/konsolas/aac/gZ;J)Lme/konsolas/aac/gi;
/*    */     //   248: pop
/*    */     //   249: aload_1
/*    */     //   250: iload #5
/*    */     //   252: i2c
/*    */     //   253: iload #6
/*    */     //   255: getstatic me/konsolas/aac/jc.j : [B
/*    */     //   258: iload #7
/*    */     //   260: i2c
/*    */     //   261: invokeinterface a : (CI[BC)Lme/konsolas/aac/gi;
/*    */     //   266: pop
/*    */     //   267: aload #22
/*    */     //   269: lload_3
/*    */     //   270: lconst_0
/*    */     //   271: lcmp
/*    */     //   272: ifle -> 847
/*    */     //   275: ifnonnull -> 845
/*    */     //   278: aload #29
/*    */     //   280: ifnull -> 394
/*    */     //   283: goto -> 296
/*    */     //   286: ldc2_w 5187248676988173251
/*    */     //   289: lload_3
/*    */     //   290: <illegal opcode> w : (Ljava/lang/Exception;JJ)Ljava/lang/Exception;
/*    */     //   295: athrow
/*    */     //   296: iconst_0
/*    */     //   297: istore #31
/*    */     //   299: aload #29
/*    */     //   301: invokevirtual a : ()I
/*    */     //   304: istore #32
/*    */     //   306: iload #31
/*    */     //   308: iload #32
/*    */     //   310: if_icmpge -> 394
/*    */     //   313: aload_1
/*    */     //   314: aload #29
/*    */     //   316: iload #31
/*    */     //   318: invokevirtual a : (I)Ljava/lang/String;
/*    */     //   321: lload #10
/*    */     //   323: invokeinterface a : (Ljava/lang/String;J)Lme/konsolas/aac/gi;
/*    */     //   328: iload #5
/*    */     //   330: i2c
/*    */     //   331: iload #6
/*    */     //   333: getstatic me/konsolas/aac/jc.k : [B
/*    */     //   336: iload #7
/*    */     //   338: i2c
/*    */     //   339: invokeinterface a : (CI[BC)Lme/konsolas/aac/gi;
/*    */     //   344: aload #29
/*    */     //   346: iload #31
/*    */     //   348: invokevirtual b : (I)Ljava/lang/String;
/*    */     //   351: lload #10
/*    */     //   353: invokeinterface a : (Ljava/lang/String;J)Lme/konsolas/aac/gi;
/*    */     //   358: iload #5
/*    */     //   360: i2c
/*    */     //   361: iload #6
/*    */     //   363: getstatic me/konsolas/aac/jc.j : [B
/*    */     //   366: iload #7
/*    */     //   368: i2c
/*    */     //   369: invokeinterface a : (CI[BC)Lme/konsolas/aac/gi;
/*    */     //   374: pop
/*    */     //   375: iinc #31, 1
/*    */     //   378: aload #22
/*    */     //   380: ifnonnull -> 181
/*    */     //   383: aload #22
/*    */     //   385: lload_3
/*    */     //   386: lconst_0
/*    */     //   387: lcmp
/*    */     //   388: ifle -> 269
/*    */     //   391: ifnull -> 306
/*    */     //   394: aload #30
/*    */     //   396: invokevirtual a : ()Lme/konsolas/aac/mm;
/*    */     //   399: astore #31
/*    */     //   401: lload_3
/*    */     //   402: lconst_0
/*    */     //   403: lcmp
/*    */     //   404: ifle -> 468
/*    */     //   407: aload #31
/*    */     //   409: lload_3
/*    */     //   410: lconst_0
/*    */     //   411: lcmp
/*    */     //   412: iflt -> 199
/*    */     //   415: ifnull -> 481
/*    */     //   418: aload_1
/*    */     //   419: sipush #21793
/*    */     //   422: ldc2_w 8411934899257657525
/*    */     //   425: lload_3
/*    */     //   426: lxor
/*    */     //   427: <illegal opcode> r : (IJ)Ljava/lang/String;
/*    */     //   432: lload #10
/*    */     //   434: invokeinterface a : (Ljava/lang/String;J)Lme/konsolas/aac/gi;
/*    */     //   439: aload #31
/*    */     //   441: invokevirtual toString : ()Ljava/lang/String;
/*    */     //   444: lload #10
/*    */     //   446: invokeinterface a : (Ljava/lang/String;J)Lme/konsolas/aac/gi;
/*    */     //   451: iload #5
/*    */     //   453: i2c
/*    */     //   454: iload #6
/*    */     //   456: getstatic me/konsolas/aac/jc.j : [B
/*    */     //   459: iload #7
/*    */     //   461: i2c
/*    */     //   462: invokeinterface a : (CI[BC)Lme/konsolas/aac/gi;
/*    */     //   467: pop
/*    */     //   468: goto -> 481
/*    */     //   471: ldc2_w 5187248676988173251
/*    */     //   474: lload_3
/*    */     //   475: <illegal opcode> w : (Ljava/lang/Exception;JJ)Ljava/lang/Exception;
/*    */     //   480: athrow
/*    */     //   481: aload #30
/*    */     //   483: lload #8
/*    */     //   485: invokevirtual a : (J)J
/*    */     //   488: lstore #32
/*    */     //   490: lload #32
/*    */     //   492: ldc2_w -1
/*    */     //   495: lcmp
/*    */     //   496: aload #22
/*    */     //   498: lload_3
/*    */     //   499: lconst_0
/*    */     //   500: lcmp
/*    */     //   501: iflt -> 616
/*    */     //   504: ifnonnull -> 614
/*    */     //   507: ifeq -> 600
/*    */     //   510: goto -> 523
/*    */     //   513: ldc2_w 5187248676988173251
/*    */     //   516: lload_3
/*    */     //   517: <illegal opcode> w : (Ljava/lang/Exception;JJ)Ljava/lang/Exception;
/*    */     //   522: athrow
/*    */     //   523: aload_1
/*    */     //   524: sipush #5634
/*    */     //   527: ldc2_w 3672192468811844497
/*    */     //   530: lload_3
/*    */     //   531: lxor
/*    */     //   532: <illegal opcode> r : (IJ)Ljava/lang/String;
/*    */     //   537: lload #10
/*    */     //   539: invokeinterface a : (Ljava/lang/String;J)Lme/konsolas/aac/gi;
/*    */     //   544: iload #14
/*    */     //   546: i2s
/*    */     //   547: iload #15
/*    */     //   549: lload #32
/*    */     //   551: iload #16
/*    */     //   553: i2s
/*    */     //   554: invokeinterface a : (SIJS)Lme/konsolas/aac/gi;
/*    */     //   559: iload #5
/*    */     //   561: i2c
/*    */     //   562: iload #6
/*    */     //   564: getstatic me/konsolas/aac/jc.j : [B
/*    */     //   567: iload #7
/*    */     //   569: i2c
/*    */     //   570: invokeinterface a : (CI[BC)Lme/konsolas/aac/gi;
/*    */     //   575: pop
/*    */     //   576: aload #22
/*    */     //   578: lload_3
/*    */     //   579: lconst_0
/*    */     //   580: lcmp
/*    */     //   581: iflt -> 681
/*    */     //   584: ifnull -> 661
/*    */     //   587: goto -> 600
/*    */     //   590: ldc2_w 5187248676988173251
/*    */     //   593: lload_3
/*    */     //   594: <illegal opcode> w : (Ljava/lang/Exception;JJ)Ljava/lang/Exception;
/*    */     //   599: athrow
/*    */     //   600: iload_2
/*    */     //   601: goto -> 614
/*    */     //   604: ldc2_w 5187248676988173251
/*    */     //   607: lload_3
/*    */     //   608: <illegal opcode> w : (Ljava/lang/Exception;JJ)Ljava/lang/Exception;
/*    */     //   613: athrow
/*    */     //   614: aload #22
/*    */     //   616: ifnonnull -> 704
/*    */     //   619: ifeq -> 661
/*    */     //   622: goto -> 635
/*    */     //   625: ldc2_w 5187248676988173251
/*    */     //   628: lload_3
/*    */     //   629: <illegal opcode> w : (Ljava/lang/Exception;JJ)Ljava/lang/Exception;
/*    */     //   634: athrow
/*    */     //   635: aload #25
/*    */     //   637: iload #17
/*    */     //   639: i2c
/*    */     //   640: iload #18
/*    */     //   642: iload #19
/*    */     //   644: invokevirtual a : (CII)V
/*    */     //   647: ldc2_w -1
/*    */     //   650: lreturn
/*    */     //   651: ldc2_w 5187248676988173251
/*    */     //   654: lload_3
/*    */     //   655: <illegal opcode> w : (Ljava/lang/Exception;JJ)Ljava/lang/Exception;
/*    */     //   660: athrow
/*    */     //   661: aload_1
/*    */     //   662: iload #5
/*    */     //   664: i2c
/*    */     //   665: iload #6
/*    */     //   667: getstatic me/konsolas/aac/jc.j : [B
/*    */     //   670: iload #7
/*    */     //   672: i2c
/*    */     //   673: invokeinterface a : (CI[BC)Lme/konsolas/aac/gi;
/*    */     //   678: pop
/*    */     //   679: aload #22
/*    */     //   681: lload_3
/*    */     //   682: lconst_0
/*    */     //   683: lcmp
/*    */     //   684: ifle -> 716
/*    */     //   687: ifnonnull -> 714
/*    */     //   690: iload_2
/*    */     //   691: goto -> 704
/*    */     //   694: ldc2_w 5187248676988173251
/*    */     //   697: lload_3
/*    */     //   698: <illegal opcode> w : (Ljava/lang/Exception;JJ)Ljava/lang/Exception;
/*    */     //   703: athrow
/*    */     //   704: ifeq -> 725
/*    */     //   707: lload #23
/*    */     //   709: lload #32
/*    */     //   711: ladd
/*    */     //   712: lstore #23
/*    */     //   714: aload #22
/*    */     //   716: lload_3
/*    */     //   717: lconst_0
/*    */     //   718: lcmp
/*    */     //   719: ifle -> 769
/*    */     //   722: ifnull -> 746
/*    */     //   725: aload #30
/*    */     //   727: aload_1
/*    */     //   728: lload #20
/*    */     //   730: invokevirtual a : (Lme/konsolas/aac/gi;J)V
/*    */     //   733: goto -> 746
/*    */     //   736: ldc2_w 5187248676988173251
/*    */     //   739: lload_3
/*    */     //   740: <illegal opcode> w : (Ljava/lang/Exception;JJ)Ljava/lang/Exception;
/*    */     //   745: athrow
/*    */     //   746: aload_1
/*    */     //   747: iload #5
/*    */     //   749: i2c
/*    */     //   750: iload #6
/*    */     //   752: getstatic me/konsolas/aac/jc.j : [B
/*    */     //   755: iload #7
/*    */     //   757: i2c
/*    */     //   758: invokeinterface a : (CI[BC)Lme/konsolas/aac/gi;
/*    */     //   763: pop
/*    */     //   764: iinc #26, 1
/*    */     //   767: aload #22
/*    */     //   769: ifnull -> 181
/*    */     //   772: aload_1
/*    */     //   773: iload #5
/*    */     //   775: i2c
/*    */     //   776: iload #6
/*    */     //   778: getstatic me/konsolas/aac/jc.l : [B
/*    */     //   781: iload #7
/*    */     //   783: i2c
/*    */     //   784: invokeinterface a : (CI[BC)Lme/konsolas/aac/gi;
/*    */     //   789: pop
/*    */     //   790: aload_1
/*    */     //   791: aload_0
/*    */     //   792: getfield c : Lme/konsolas/aac/gZ;
/*    */     //   795: lload #12
/*    */     //   797: invokeinterface a : (Lme/konsolas/aac/gZ;J)Lme/konsolas/aac/gi;
/*    */     //   802: pop
/*    */     //   803: aload_1
/*    */     //   804: iload #5
/*    */     //   806: i2c
/*    */     //   807: iload #6
/*    */     //   809: getstatic me/konsolas/aac/jc.l : [B
/*    */     //   812: iload #7
/*    */     //   814: i2c
/*    */     //   815: invokeinterface a : (CI[BC)Lme/konsolas/aac/gi;
/*    */     //   820: pop
/*    */     //   821: aload_1
/*    */     //   822: iload #5
/*    */     //   824: i2c
/*    */     //   825: iload #6
/*    */     //   827: getstatic me/konsolas/aac/jc.j : [B
/*    */     //   830: iload #7
/*    */     //   832: i2c
/*    */     //   833: invokeinterface a : (CI[BC)Lme/konsolas/aac/gi;
/*    */     //   838: pop
/*    */     //   839: lload_3
/*    */     //   840: lconst_0
/*    */     //   841: lcmp
/*    */     //   842: iflt -> 188
/*    */     //   845: aload #22
/*    */     //   847: ifnonnull -> 877
/*    */     //   850: iload_2
/*    */     //   851: ifeq -> 889
/*    */     //   854: goto -> 867
/*    */     //   857: ldc2_w 5187248676988173251
/*    */     //   860: lload_3
/*    */     //   861: <illegal opcode> w : (Ljava/lang/Exception;JJ)Ljava/lang/Exception;
/*    */     //   866: athrow
/*    */     //   867: lload #23
/*    */     //   869: aload #25
/*    */     //   871: invokevirtual f : ()J
/*    */     //   874: ladd
/*    */     //   875: lstore #23
/*    */     //   877: aload #25
/*    */     //   879: iload #17
/*    */     //   881: i2c
/*    */     //   882: iload #18
/*    */     //   884: iload #19
/*    */     //   886: invokevirtual a : (CII)V
/*    */     //   889: lload #23
/*    */     //   891: lreturn
/*    */     // Line number table:
/*    */     //   Java source line number -> byte code offset
/*    */     //   #65	-> 144
/*    */     //   #25	-> 147
/*    */     //   #18	-> 152
/*    */     //   #7	-> 156
/*    */     //   #72	-> 167
/*    */     //   #61	-> 188
/*    */     //   #46	-> 204
/*    */     //   #85	-> 211
/*    */     //   #81	-> 218
/*    */     //   #6	-> 236
/*    */     //   #23	-> 249
/*    */     //   #64	-> 267
/*    */     //   #82	-> 296
/*    */     //   #14	-> 313
/*    */     //   #47	-> 336
/*    */     //   #17	-> 348
/*    */     //   #37	-> 366
/*    */     //   #84	-> 375
/*    */     //   #67	-> 394
/*    */     //   #8	-> 401
/*    */     //   #27	-> 418
/*    */     //   #59	-> 441
/*    */     //   #36	-> 459
/*    */     //   #79	-> 481
/*    */     //   #58	-> 490
/*    */     //   #32	-> 523
/*    */     //   #70	-> 551
/*    */     //   #80	-> 567
/*    */     //   #76	-> 600
/*    */     //   #13	-> 635
/*    */     //   #45	-> 647
/*    */     //   #43	-> 661
/*    */     //   #15	-> 679
/*    */     //   #9	-> 707
/*    */     //   #30	-> 725
/*    */     //   #49	-> 746
/*    */     //   #22	-> 764
/*    */     //   #77	-> 772
/*    */     //   #29	-> 790
/*    */     //   #51	-> 803
/*    */     //   #38	-> 821
/*    */     //   #71	-> 845
/*    */     //   #68	-> 867
/*    */     //   #19	-> 877
/*    */     //   #75	-> 889
/*    */     // Exception table:
/*    */     //   from	to	target	type
/*    */     //   218	283	286	java/io/IOException
/*    */     //   401	468	471	java/io/IOException
/*    */     //   490	510	513	java/io/IOException
/*    */     //   507	587	590	java/io/IOException
/*    */     //   523	601	604	java/io/IOException
/*    */     //   614	622	625	java/io/IOException
/*    */     //   619	651	651	java/io/IOException
/*    */     //   661	691	694	java/io/IOException
/*    */     //   714	733	736	java/io/IOException
/*    */     //   845	854	857	java/io/IOException
/*    */   }
/*    */ 
/*    */ 
/*    */ 
/*    */ 
/*    */ 
/*    */   
/*    */   static {
/*    */     byte b1;
/*    */     long l1, l2;
/* 74 */     for (n = nc.a(3277338793310678386L, 5378889863949129414L, MethodHandles.lookup().lookupClass()).a(2293759712285L), l1 = n ^ 0x41DCDE96DC71L, l2 = l1 ^ 0x7E1FAA2BFA1CL, u = new HashMap<>(13), "䬁선ܙᴊ߫黫嫏낹ଟ尽㮡窗힦榍巺ଢ퓴䙐笚".toCharArray()[16] = (char)("䬁선ܙᴊ߫黫嫏낹ଟ尽㮡窗힦榍巺ଢ퓴䙐笚".toCharArray()[16] ^ 0x4C02), "ṇ覜鲗恐".toCharArray()[0] = (char)("ṇ覜鲗恐".toCharArray()[0] ^ 0x1CB9), (new byte[8])[0] = (byte)(int)(l1 >>> 56L), b1 = 1; b1 < 8; ) { (new byte[8])[b1] = (byte)(int)(l1 << b1 * 8 >>> 56L); b1++; }  Cipher cipher; (cipher = Cipher.getInstance(a0$cc.G("䬁선ܙᴊ߫黫嫏낹ଟ尽㮡窗힦榍巺ଢ퓴䙐笚".toCharArray(), (short)10008, false, (byte)5))).init(2, SecretKeyFactory.getInstance(a0$cc.G("ṇ覜鲗恐".toCharArray(), (short)20602, true, (byte)0)).generateSecret(new DESKeySpec(new byte[8])), new IvParameterSpec(new byte[8])); String[] arrayOfString = new String[11]; boolean bool = false; "☇󻫀⏖⨕䘅䝨໒뾚嗓ᒳ엜?ꂡ⦕⡇壙踼峏퐂밓锹ผꮒ櫊룠焦㘍劔Ꮜ䠠?ெ㞮⤢㢇炘鯧ꂑ旣Ⲝ뽩챝䗵ꋴᰖ촣攈麝嵞謁̽퍀㹷榡瑸ⱴ꼺뒚퇯勖⟉౾忴鯼늦겙ဖ椺䡜ݸ廯ፊ଩糯骴든쥯桢扚藎롦즼뼠禷媩Ｄ쟖᫲᭾႖氨匳花䀙盱鮊꘯⍇蒙媽ά聕ú⏰䯳程怚媰庳愌倫쭜筞둠넖ᦴﾉ౳ි썴迴싷蟸첞㨗髴?ⵞ鸳㏼쌁왂瘉ᅌꭖⓌ鬴滱掞ᯜ嶜奌6怷弬朰榦曭淩蘥积糙汤ሸ鶿빶㉍⊔쏺苏瞹녩鑞坺裒퉵먤聤퓐׽敇烡줇릠䲶謡뫟嵻ⵓ⩩ꍓ쫁ᆀ㱥뉪࿳㌑딣搗侄댤衔龰鷵બ⠸櫛楼፤淚꿡Т捊Ē?鏀疎뤑ነ콅?㡕傋ᰖ氵릏鄰䕪嶺⧲㿩燮ﳷ厇㗡壁틆䲏祜ド觤㸏䠒⻕꒱ᖏᒩḂ盈靥뫪芴孴Ｑƅ핐밶ꃢ裞ꇇ矄车ർᅮ坣䨑ɞ䟔竦䋭С漺晃崜믵௹佁欝떀궗筫ଚ⮅ꟼ⧒◅ᔁݽ⪱묫Ú胢ꪝ堂뙈㤶".toCharArray()[83] = (char)("☇󻫀⏖⨕䘅䝨໒뾚嗓ᒳ엜?ꂡ⦕⡇壙踼峏퐂밓锹ผꮒ櫊룠焦㘍劔Ꮜ䠠?ெ㞮⤢㢇炘鯧ꂑ旣Ⲝ뽩챝䗵ꋴᰖ촣攈麝嵞謁̽퍀㹷榡瑸ⱴ꼺뒚퇯勖⟉౾忴鯼늦겙ဖ椺䡜ݸ廯ፊ଩糯骴든쥯桢扚藎롦즼뼠禷媩Ｄ쟖᫲᭾႖氨匳花䀙盱鮊꘯⍇蒙媽ά聕ú⏰䯳程怚媰庳愌倫쭜筞둠넖ᦴﾉ౳ි썴迴싷蟸첞㨗髴?ⵞ鸳㏼쌁왂瘉ᅌꭖⓌ鬴滱掞ᯜ嶜奌6怷弬朰榦曭淩蘥积糙汤ሸ鶿빶㉍⊔쏺苏瞹녩鑞坺裒퉵먤聤퓐׽敇烡줇릠䲶謡뫟嵻ⵓ⩩ꍓ쫁ᆀ㱥뉪࿳㌑딣搗侄댤衔龰鷵બ⠸櫛楼፤淚꿡Т捊Ē?鏀疎뤑ነ콅?㡕傋ᰖ氵릏鄰䕪嶺⧲㿩燮ﳷ厇㗡壁틆䲏祜ド觤㸏䠒⻕꒱ᖏᒩḂ盈靥뫪芴孴Ｑƅ핐밶ꃢ裞ꇇ矄车ർᅮ坣䨑ɞ䟔竦䋭С漺晃崜믵௹佁欝떀궗筫ଚ⮅ꟼ⧒◅ᔁݽ⪱묫Ú胢ꪝ堂뙈㤶".toCharArray()[83] ^ 0x3E11); String str; int i = (str = a0$cc.G("☇󻫀⏖⨕䘅䝨໒뾚嗓ᒳ엜?ꂡ⦕⡇壙踼峏퐂밓锹ผꮒ櫊룠焦㘍劔Ꮜ䠠?ெ㞮⤢㢇炘鯧ꂑ旣Ⲝ뽩챝䗵ꋴᰖ촣攈麝嵞謁̽퍀㹷榡瑸ⱴ꼺뒚퇯勖⟉౾忴鯼늦겙ဖ椺䡜ݸ廯ፊ଩糯骴든쥯桢扚藎롦즼뼠禷媩Ｄ쟖᫲᭾႖氨匳花䀙盱鮊꘯⍇蒙媽ά聕ú⏰䯳程怚媰庳愌倫쭜筞둠넖ᦴﾉ౳ි썴迴싷蟸첞㨗髴?ⵞ鸳㏼쌁왂瘉ᅌꭖⓌ鬴滱掞ᯜ嶜奌6怷弬朰榦曭淩蘥积糙汤ሸ鶿빶㉍⊔쏺苏瞹녩鑞坺裒퉵먤聤퓐׽敇烡줇릠䲶謡뫟嵻ⵓ⩩ꍓ쫁ᆀ㱥뉪࿳㌑딣搗侄댤衔龰鷵બ⠸櫛楼፤淚꿡Т捊Ē?鏀疎뤑ነ콅?㡕傋ᰖ氵릏鄰䕪嶺⧲㿩燮ﳷ厇㗡壁틆䲏祜ド觤㸏䠒⻕꒱ᖏᒩḂ盈靥뫪芴孴Ｑƅ핐밶ꃢ裞ꇇ矄车ർᅮ坣䨑ɞ䟔竦䋭С漺晃崜믵௹佁欝떀궗筫ଚ⮅ꟼ⧒◅ᔁݽ⪱묫Ú胢ꪝ堂뙈㤶".toCharArray(), (short)9852, true, (byte)4)).length(); byte b2 = 16; byte b = -1;
/*    */     while (true);
/*    */   }
/*    */   
/*    */   private static Exception a(Exception paramException) {
/*    */     return paramException;
/*    */   }
/*    */   
/*    */   private static String b(byte[] paramArrayOfbyte) {
/*    */     byte b1 = 0;
/*    */     int i;
/*    */     char[] arrayOfChar = new char[i = paramArrayOfbyte.length];
/*    */     for (byte b2 = 0; b2 < i; b2++) {
/*    */       int j;
/*    */       if ((j = 0xFF & paramArrayOfbyte[b2]) < 192) {
/*    */         arrayOfChar[b1++] = (char)j;
/*    */       } else if (j < 224) {
/*    */         char c = (char)((char)(j & 0x1F) << 6);
/*    */         j = paramArrayOfbyte[++b2];
/*    */         c = (char)(c | (char)(j & 0x3F));
/*    */         arrayOfChar[b1++] = c;
/*    */       } else if (b2 < i - 2) {
/*    */         char c = (char)((char)(j & 0xF) << 12);
/*    */         j = paramArrayOfbyte[++b2];
/*    */         c = (char)(c | (char)(j & 0x3F) << 6);
/*    */         j = paramArrayOfbyte[++b2];
/*    */         c = (char)(c | (char)(j & 0x3F));
/*    */         arrayOfChar[b1++] = c;
/*    */       } 
/*    */     } 
/*    */     return new String(arrayOfChar, 0, b1);
/*    */   }
/*    */   
/*    */   private static String b(int paramInt, long paramLong) {
/*    */     int i = paramInt ^ (int)(paramLong & 0x7FFFL) ^ 0x5BFD;
/*    */     if (t[i] == null) {
/*    */       Object[] arrayOfObject;
/*    */       try {
/*    */         Long long_ = Long.valueOf(Thread.currentThread().getId());
/*    */         arrayOfObject = (Object[])u.get(long_);
/*    */         if (arrayOfObject == null) {
/*    */           arrayOfObject = new Object[3];
/*    */           "㇀꼚倖提紟䢭᤯鉻ᬠ뼁秉̲勩〲泘碰妓".toCharArray()[19] = (char)("㇀꼚倖提紟䢭᤯鉻ᬠ뼁秉̲勩〲泘碰妓".toCharArray()[19] ^ 0x1F32);
/*    */           arrayOfObject[0] = Cipher.getInstance(da$gx.U("㇀꼚倖提紟䢭᤯鉻ᬠ뼁秉̲勩〲泘碰妓".toCharArray(), (short)22146, true, false));
/*    */           "찞ⳮۑ嫼".toCharArray()[2] = (char)("찞ⳮۑ嫼".toCharArray()[2] ^ 0x5BBC);
/*    */           arrayOfObject[1] = SecretKeyFactory.getInstance(da$gx.U("찞ⳮۑ嫼".toCharArray(), (short)29202, false, true));
/*    */           arrayOfObject[2] = new IvParameterSpec(new byte[8]);
/*    */           u.put(long_, arrayOfObject);
/*    */         } 
/*    */       } catch (Exception exception) {
/*    */         "뷐쮙邛퐒뽀ᅾ朸銛檏ƻ͠뭙慄̎햛丅뀜糯".toCharArray()[8] = (char)("뷐쮙邛퐒뽀ᅾ朸銛檏ƻ͠뭙慄̎햛丅뀜糯".toCharArray()[8] ^ 0x4348);
/*    */         throw new RuntimeException(da$gx.U("뷐쮙邛퐒뽀ᅾ朸銛檏ƻ͠뭙慄̎햛丅뀜糯".toCharArray(), (short)6681, false, false), exception);
/*    */       } 
/*    */       byte[] arrayOfByte1 = new byte[8];
/*    */       arrayOfByte1[0] = (byte)(int)(paramLong >>> 56L);
/*    */       for (byte b = 1; b < 8; b++)
/*    */         arrayOfByte1[b] = (byte)(int)(paramLong << b * 8 >>> 56L); 
/*    */       DESKeySpec dESKeySpec = new DESKeySpec(arrayOfByte1);
/*    */       SecretKey secretKey = ((SecretKeyFactory)arrayOfObject[1]).generateSecret(dESKeySpec);
/*    */       ((Cipher)arrayOfObject[0]).init(2, secretKey, (IvParameterSpec)arrayOfObject[2]);
/*    */       "㉄䣮᭥鯃꺠쯽졐鱩濒㟐㢬".toCharArray()[8] = (char)("㉄䣮᭥鯃꺠쯽졐鱩濒㟐㢬".toCharArray()[8] ^ 0x2917);
/*    */       byte[] arrayOfByte2 = s[i].getBytes(da$gx.U("㉄䣮᭥鯃꺠쯽졐鱩濒㟐㢬".toCharArray(), (short)15870, true, true));
/*    */       t[i] = b(((Cipher)arrayOfObject[0]).doFinal(arrayOfByte2));
/*    */     } 
/*    */     return t[i];
/*    */   }
/*    */   
/*    */   private static Object b(MethodHandles.Lookup paramLookup, MutableCallSite paramMutableCallSite, String paramString, Object[] paramArrayOfObject) {
/*    */     int i = ((Integer)paramArrayOfObject[0]).intValue();
/*    */     long l = ((Long)paramArrayOfObject[1]).longValue();
/*    */     String str = b(i, l);
/*    */     MethodHandle methodHandle = MethodHandles.constant(String.class, str);
/*    */     paramMutableCallSite.setTarget(MethodHandles.dropArguments(methodHandle, 0, new Class[] { int.class, long.class }));
/*    */     return str;
/*    */   }
/*    */   
/*    */   private static CallSite b(MethodHandles.Lookup paramLookup, String paramString, MethodType paramMethodType) {
/*    */     // Byte code:
/*    */     //   0: new java/lang/invoke/MutableCallSite
/*    */     //   3: dup
/*    */     //   4: aload_2
/*    */     //   5: invokespecial <init> : (Ljava/lang/invoke/MethodType;)V
/*    */     //   8: astore_3
/*    */     //   9: aload_3
/*    */     //   10: ldc_w
/*    */     //   13: ldc_w [Ljava/lang/Object;
/*    */     //   16: aload_2
/*    */     //   17: invokevirtual parameterCount : ()I
/*    */     //   20: invokevirtual asCollector : (Ljava/lang/Class;I)Ljava/lang/invoke/MethodHandle;
/*    */     //   23: iconst_0
/*    */     //   24: iconst_3
/*    */     //   25: anewarray java/lang/Object
/*    */     //   28: dup
/*    */     //   29: iconst_0
/*    */     //   30: aload_0
/*    */     //   31: aastore
/*    */     //   32: dup
/*    */     //   33: iconst_1
/*    */     //   34: aload_3
/*    */     //   35: aastore
/*    */     //   36: dup
/*    */     //   37: iconst_2
/*    */     //   38: aload_1
/*    */     //   39: aastore
/*    */     //   40: invokestatic insertArguments : (Ljava/lang/invoke/MethodHandle;I[Ljava/lang/Object;)Ljava/lang/invoke/MethodHandle;
/*    */     //   43: aload_2
/*    */     //   44: invokestatic explicitCastArguments : (Ljava/lang/invoke/MethodHandle;Ljava/lang/invoke/MethodType;)Ljava/lang/invoke/MethodHandle;
/*    */     //   47: invokevirtual setTarget : (Ljava/lang/invoke/MethodHandle;)V
/*    */     //   50: goto -> 171
/*    */     //   53: astore #4
/*    */     //   55: new java/lang/RuntimeException
/*    */     //   58: dup
/*    */     //   59: new java/lang/StringBuilder
/*    */     //   62: dup
/*    */     //   63: invokespecial <init> : ()V
/*    */     //   66: ldc_w '鍧혎槫攦⎇ᒟ由ᥕᾹ?吋與䁀升ﾛ傏醨䎣'
/*    */     //   69: invokevirtual toCharArray : ()[C
/*    */     //   72: dup
/*    */     //   73: dup
/*    */     //   74: bipush #9
/*    */     //   76: dup_x1
/*    */     //   77: caload
/*    */     //   78: sipush #29441
/*    */     //   81: ixor
/*    */     //   82: i2c
/*    */     //   83: castore
/*    */     //   84: sipush #5060
/*    */     //   87: iconst_1
/*    */     //   88: iconst_2
/*    */     //   89: invokestatic H : (Ljava/lang/Object;SBB)Ljava/lang/String;
/*    */     //   92: invokevirtual append : (Ljava/lang/String;)Ljava/lang/StringBuilder;
/*    */     //   95: ldc_w '세ᬭ먀㪁'
/*    */     //   98: invokevirtual toCharArray : ()[C
/*    */     //   101: dup
/*    */     //   102: dup
/*    */     //   103: iconst_1
/*    */     //   104: dup_x1
/*    */     //   105: caload
/*    */     //   106: sipush #8281
/*    */     //   109: ixor
/*    */     //   110: i2c
/*    */     //   111: castore
/*    */     //   112: sipush #21979
/*    */     //   115: iconst_2
/*    */     //   116: iconst_5
/*    */     //   117: invokestatic H : (Ljava/lang/Object;SBB)Ljava/lang/String;
/*    */     //   120: invokevirtual append : (Ljava/lang/String;)Ljava/lang/StringBuilder;
/*    */     //   123: aload_1
/*    */     //   124: invokevirtual append : (Ljava/lang/String;)Ljava/lang/StringBuilder;
/*    */     //   127: ldc_w '䓛♶આű'
/*    */     //   130: invokevirtual toCharArray : ()[C
/*    */     //   133: dup
/*    */     //   134: dup
/*    */     //   135: iconst_0
/*    */     //   136: dup_x1
/*    */     //   137: caload
/*    */     //   138: sipush #1033
/*    */     //   141: ixor
/*    */     //   142: i2c
/*    */     //   143: castore
/*    */     //   144: sipush #10908
/*    */     //   147: iconst_2
/*    */     //   148: iconst_4
/*    */     //   149: invokestatic H : (Ljava/lang/Object;SBB)Ljava/lang/String;
/*    */     //   152: invokevirtual append : (Ljava/lang/String;)Ljava/lang/StringBuilder;
/*    */     //   155: aload_2
/*    */     //   156: invokevirtual toString : ()Ljava/lang/String;
/*    */     //   159: invokevirtual append : (Ljava/lang/String;)Ljava/lang/StringBuilder;
/*    */     //   162: invokevirtual toString : ()Ljava/lang/String;
/*    */     //   165: aload #4
/*    */     //   167: invokespecial <init> : (Ljava/lang/String;Ljava/lang/Throwable;)V
/*    */     //   170: athrow
/*    */     //   171: aload_3
/*    */     //   172: areturn
/*    */     // Exception table:
/*    */     //   from	to	target	type
/*    */     //   9	50	53	java/lang/Exception
/*    */   } }


/* Location:              C:\Users\BukkitBypass\Desktop\MatrixAC\AAC\AAC-spigot-5.2.0.jar!\me\konsolas\aac\jc.class
 * Java compiler version: 8 (52.0)
 * JD-Core Version:       1.1.3
 */