/*    */ package me.konsolas.aac;public final class jh { final l6 e; final k4 g;
/*    */   final SocketFactory b;
/*    */   
/*    */   public List a() {
/*  5 */     return this.d;
/*    */   }
/*    */   final dp h; final List j; final List d; final ProxySelector c; @Nullable
/*    */   final Proxy i; @Nullable
/*    */   final SSLSocketFactory k; @Nullable
/*    */   final HostnameVerifier a; @Nullable
/*    */   final mG f; private static final long l = nc.a(8463162497969912780L, 1273165209319918730L, MethodHandles.lookup().lookupClass()).a(216362722028198L); private static final String[] m;
/*    */   private static final String[] n;
/*    */   private static final Map o = new HashMap<>(13);
/*    */   
/*    */   public ProxySelector a() {
/* 16 */     return this.c;
/*    */   }
/* 18 */   public SocketFactory a() { return this.b; } public String toString() { // Byte code:
/*    */     //   0: getstatic me/konsolas/aac/jh.l : J
/*    */     //   3: ldc2_w 16823878505147
/*    */     //   6: lxor
/*    */     //   7: lstore_1
/*    */     //   8: ldc2_w -6615257498725604109
/*    */     //   11: lload_1
/*    */     //   12: <illegal opcode> w : (JJ)[Lme/konsolas/aac/aN;
/*    */     //   17: new java/lang/StringBuilder
/*    */     //   20: dup
/*    */     //   21: invokespecial <init> : ()V
/*    */     //   24: sipush #28033
/*    */     //   27: ldc2_w 2763632763920457699
/*    */     //   30: lload_1
/*    */     //   31: lxor
/*    */     //   32: <illegal opcode> f : (IJ)Ljava/lang/String;
/*    */     //   37: invokevirtual append : (Ljava/lang/String;)Ljava/lang/StringBuilder;
/*    */     //   40: aload_0
/*    */     //   41: getfield e : Lme/konsolas/aac/l6;
/*    */     //   44: invokevirtual d : ()Ljava/lang/String;
/*    */     //   47: invokevirtual append : (Ljava/lang/String;)Ljava/lang/StringBuilder;
/*    */     //   50: ldc 'ᡁ'
/*    */     //   52: invokevirtual toCharArray : ()[C
/*    */     //   55: dup
/*    */     //   56: dup
/*    */     //   57: iconst_0
/*    */     //   58: dup_x1
/*    */     //   59: caload
/*    */     //   60: sipush #7948
/*    */     //   63: ixor
/*    */     //   64: i2c
/*    */     //   65: castore
/*    */     //   66: sipush #15163
/*    */     //   69: iconst_0
/*    */     //   70: iconst_1
/*    */     //   71: invokestatic H : (Ljava/lang/Object;SBB)Ljava/lang/String;
/*    */     //   74: invokevirtual append : (Ljava/lang/String;)Ljava/lang/StringBuilder;
/*    */     //   77: aload_0
/*    */     //   78: getfield e : Lme/konsolas/aac/l6;
/*    */     //   81: invokevirtual c : ()I
/*    */     //   84: invokevirtual append : (I)Ljava/lang/StringBuilder;
/*    */     //   87: astore #4
/*    */     //   89: astore_3
/*    */     //   90: aload_3
/*    */     //   91: ifnonnull -> 153
/*    */     //   94: aload_0
/*    */     //   95: getfield i : Ljava/net/Proxy;
/*    */     //   98: ifnull -> 157
/*    */     //   101: goto -> 114
/*    */     //   104: ldc2_w -6506986240762183787
/*    */     //   107: lload_1
/*    */     //   108: <illegal opcode> w : (Ljava/lang/NullPointerException;JJ)Ljava/lang/NullPointerException;
/*    */     //   113: athrow
/*    */     //   114: aload #4
/*    */     //   116: sipush #30712
/*    */     //   119: ldc2_w 5536599057742628249
/*    */     //   122: lload_1
/*    */     //   123: lxor
/*    */     //   124: <illegal opcode> f : (IJ)Ljava/lang/String;
/*    */     //   129: invokevirtual append : (Ljava/lang/String;)Ljava/lang/StringBuilder;
/*    */     //   132: aload_0
/*    */     //   133: getfield i : Ljava/net/Proxy;
/*    */     //   136: invokevirtual append : (Ljava/lang/Object;)Ljava/lang/StringBuilder;
/*    */     //   139: pop
/*    */     //   140: goto -> 153
/*    */     //   143: ldc2_w -6506986240762183787
/*    */     //   146: lload_1
/*    */     //   147: <illegal opcode> w : (Ljava/lang/NullPointerException;JJ)Ljava/lang/NullPointerException;
/*    */     //   152: athrow
/*    */     //   153: aload_3
/*    */     //   154: ifnull -> 196
/*    */     //   157: aload #4
/*    */     //   159: sipush #29565
/*    */     //   162: ldc2_w 643166210410283285
/*    */     //   165: lload_1
/*    */     //   166: lxor
/*    */     //   167: <illegal opcode> f : (IJ)Ljava/lang/String;
/*    */     //   172: invokevirtual append : (Ljava/lang/String;)Ljava/lang/StringBuilder;
/*    */     //   175: aload_0
/*    */     //   176: getfield c : Ljava/net/ProxySelector;
/*    */     //   179: invokevirtual append : (Ljava/lang/Object;)Ljava/lang/StringBuilder;
/*    */     //   182: pop
/*    */     //   183: goto -> 196
/*    */     //   186: ldc2_w -6506986240762183787
/*    */     //   189: lload_1
/*    */     //   190: <illegal opcode> w : (Ljava/lang/NullPointerException;JJ)Ljava/lang/NullPointerException;
/*    */     //   195: athrow
/*    */     //   196: aload #4
/*    */     //   198: ldc 'ઋ⢱'
/*    */     //   200: invokevirtual toCharArray : ()[C
/*    */     //   203: dup
/*    */     //   204: dup
/*    */     //   205: iconst_0
/*    */     //   206: dup_x1
/*    */     //   207: caload
/*    */     //   208: sipush #25077
/*    */     //   211: ixor
/*    */     //   212: i2c
/*    */     //   213: castore
/*    */     //   214: sipush #32538
/*    */     //   217: iconst_5
/*    */     //   218: iconst_5
/*    */     //   219: invokestatic H : (Ljava/lang/Object;SBB)Ljava/lang/String;
/*    */     //   222: invokevirtual append : (Ljava/lang/String;)Ljava/lang/StringBuilder;
/*    */     //   225: pop
/*    */     //   226: aload #4
/*    */     //   228: invokevirtual toString : ()Ljava/lang/String;
/*    */     //   231: areturn
/*    */     // Line number table:
/*    */     //   Java source line number -> byte code offset
/*    */     //   #20	-> 17
/*    */     //   #35	-> 37
/*    */     //   #1	-> 44
/*    */     //   #51	-> 90
/*    */     //   #59	-> 114
/*    */     //   #27	-> 157
/*    */     //   #63	-> 196
/*    */     //   #53	-> 226
/*    */     // Exception table:
/*    */     //   from	to	target	type
/*    */     //   90	101	104	java/lang/NullPointerException
/*    */     //   94	140	143	java/lang/NullPointerException
/*    */     //   153	183	186	java/lang/NullPointerException } public boolean equals(@Nullable Object paramObject) {
/*    */     // Byte code:
/*    */     //   0: getstatic me/konsolas/aac/jh.l : J
/*    */     //   3: ldc2_w 46278186725913
/*    */     //   6: lxor
/*    */     //   7: lstore_2
/*    */     //   8: lload_2
/*    */     //   9: dup2
/*    */     //   10: ldc2_w 37701307015354
/*    */     //   13: lxor
/*    */     //   14: lstore #4
/*    */     //   16: pop2
/*    */     //   17: ldc2_w -8893546030858730415
/*    */     //   20: lload_2
/*    */     //   21: <illegal opcode> w : (JJ)[Lme/konsolas/aac/aN;
/*    */     //   26: astore #6
/*    */     //   28: aload_1
/*    */     //   29: instanceof me/konsolas/aac/jh
/*    */     //   32: aload #6
/*    */     //   34: ifnonnull -> 80
/*    */     //   37: ifeq -> 149
/*    */     //   40: goto -> 53
/*    */     //   43: ldc2_w -8858387886229168329
/*    */     //   46: lload_2
/*    */     //   47: <illegal opcode> w : (Ljava/lang/NullPointerException;JJ)Ljava/lang/NullPointerException;
/*    */     //   52: athrow
/*    */     //   53: aload_0
/*    */     //   54: getfield e : Lme/konsolas/aac/l6;
/*    */     //   57: aload_1
/*    */     //   58: checkcast me/konsolas/aac/jh
/*    */     //   61: getfield e : Lme/konsolas/aac/l6;
/*    */     //   64: invokevirtual equals : (Ljava/lang/Object;)Z
/*    */     //   67: goto -> 80
/*    */     //   70: ldc2_w -8858387886229168329
/*    */     //   73: lload_2
/*    */     //   74: <illegal opcode> w : (Ljava/lang/NullPointerException;JJ)Ljava/lang/NullPointerException;
/*    */     //   79: athrow
/*    */     //   80: aload #6
/*    */     //   82: ifnonnull -> 124
/*    */     //   85: ifeq -> 149
/*    */     //   88: goto -> 101
/*    */     //   91: ldc2_w -8858387886229168329
/*    */     //   94: lload_2
/*    */     //   95: <illegal opcode> w : (Ljava/lang/NullPointerException;JJ)Ljava/lang/NullPointerException;
/*    */     //   100: athrow
/*    */     //   101: aload_0
/*    */     //   102: lload #4
/*    */     //   104: aload_1
/*    */     //   105: checkcast me/konsolas/aac/jh
/*    */     //   108: invokevirtual a : (JLme/konsolas/aac/jh;)Z
/*    */     //   111: goto -> 124
/*    */     //   114: ldc2_w -8858387886229168329
/*    */     //   117: lload_2
/*    */     //   118: <illegal opcode> w : (Ljava/lang/NullPointerException;JJ)Ljava/lang/NullPointerException;
/*    */     //   123: athrow
/*    */     //   124: aload #6
/*    */     //   126: ifnonnull -> 146
/*    */     //   129: ifeq -> 149
/*    */     //   132: goto -> 145
/*    */     //   135: ldc2_w -8858387886229168329
/*    */     //   138: lload_2
/*    */     //   139: <illegal opcode> w : (Ljava/lang/NullPointerException;JJ)Ljava/lang/NullPointerException;
/*    */     //   144: athrow
/*    */     //   145: iconst_1
/*    */     //   146: goto -> 150
/*    */     //   149: iconst_0
/*    */     //   150: ireturn
/*    */     // Line number table:
/*    */     //   Java source line number -> byte code offset
/*    */     //   #22	-> 28
/*    */     //   #10	-> 64
/*    */     //   #39	-> 108
/*    */     //   #19	-> 150
/*    */     // Exception table:
/*    */     //   from	to	target	type
/*    */     //   28	40	43	java/lang/NullPointerException
/*    */     //   37	67	70	java/lang/NullPointerException
/*    */     //   80	88	91	java/lang/NullPointerException
/*    */     //   85	111	114	java/lang/NullPointerException
/*    */     //   124	132	135	java/lang/NullPointerException
/*    */   }
/*    */   @Nullable
/*    */   public mG a() {
/* 23 */     return this.f;
/*    */   }
/*    */ 
/*    */   
/*    */   public List b() {
/* 28 */     return this.j;
/*    */   }
/*    */ 
/*    */   
/*    */   boolean a(long paramLong, jh paramjh) {
/*    */     // Byte code:
/*    */     //   0: getstatic me/konsolas/aac/jh.l : J
/*    */     //   3: lload_1
/*    */     //   4: lxor
/*    */     //   5: lstore_1
/*    */     //   6: ldc2_w 5928884955239961221
/*    */     //   9: lload_1
/*    */     //   10: <illegal opcode> w : (JJ)[Lme/konsolas/aac/aN;
/*    */     //   15: astore #4
/*    */     //   17: aload_0
/*    */     //   18: getfield g : Lme/konsolas/aac/k4;
/*    */     //   21: aload_3
/*    */     //   22: getfield g : Lme/konsolas/aac/k4;
/*    */     //   25: invokevirtual equals : (Ljava/lang/Object;)Z
/*    */     //   28: aload #4
/*    */     //   30: ifnonnull -> 73
/*    */     //   33: ifeq -> 526
/*    */     //   36: goto -> 49
/*    */     //   39: ldc2_w 6036170761931524579
/*    */     //   42: lload_1
/*    */     //   43: <illegal opcode> w : (Ljava/lang/NullPointerException;JJ)Ljava/lang/NullPointerException;
/*    */     //   48: athrow
/*    */     //   49: aload_0
/*    */     //   50: getfield h : Lme/konsolas/aac/dp;
/*    */     //   53: aload_3
/*    */     //   54: getfield h : Lme/konsolas/aac/dp;
/*    */     //   57: invokevirtual equals : (Ljava/lang/Object;)Z
/*    */     //   60: goto -> 73
/*    */     //   63: ldc2_w 6036170761931524579
/*    */     //   66: lload_1
/*    */     //   67: <illegal opcode> w : (Ljava/lang/NullPointerException;JJ)Ljava/lang/NullPointerException;
/*    */     //   72: athrow
/*    */     //   73: aload #4
/*    */     //   75: lload_1
/*    */     //   76: lconst_0
/*    */     //   77: lcmp
/*    */     //   78: iflt -> 128
/*    */     //   81: ifnonnull -> 126
/*    */     //   84: ifeq -> 526
/*    */     //   87: goto -> 100
/*    */     //   90: ldc2_w 6036170761931524579
/*    */     //   93: lload_1
/*    */     //   94: <illegal opcode> w : (Ljava/lang/NullPointerException;JJ)Ljava/lang/NullPointerException;
/*    */     //   99: athrow
/*    */     //   100: aload_0
/*    */     //   101: getfield j : Ljava/util/List;
/*    */     //   104: aload_3
/*    */     //   105: getfield j : Ljava/util/List;
/*    */     //   108: invokeinterface equals : (Ljava/lang/Object;)Z
/*    */     //   113: goto -> 126
/*    */     //   116: ldc2_w 6036170761931524579
/*    */     //   119: lload_1
/*    */     //   120: <illegal opcode> w : (Ljava/lang/NullPointerException;JJ)Ljava/lang/NullPointerException;
/*    */     //   125: athrow
/*    */     //   126: aload #4
/*    */     //   128: lload_1
/*    */     //   129: lconst_0
/*    */     //   130: lcmp
/*    */     //   131: ifle -> 181
/*    */     //   134: ifnonnull -> 179
/*    */     //   137: ifeq -> 526
/*    */     //   140: goto -> 153
/*    */     //   143: ldc2_w 6036170761931524579
/*    */     //   146: lload_1
/*    */     //   147: <illegal opcode> w : (Ljava/lang/NullPointerException;JJ)Ljava/lang/NullPointerException;
/*    */     //   152: athrow
/*    */     //   153: aload_0
/*    */     //   154: getfield d : Ljava/util/List;
/*    */     //   157: aload_3
/*    */     //   158: getfield d : Ljava/util/List;
/*    */     //   161: invokeinterface equals : (Ljava/lang/Object;)Z
/*    */     //   166: goto -> 179
/*    */     //   169: ldc2_w 6036170761931524579
/*    */     //   172: lload_1
/*    */     //   173: <illegal opcode> w : (Ljava/lang/NullPointerException;JJ)Ljava/lang/NullPointerException;
/*    */     //   178: athrow
/*    */     //   179: aload #4
/*    */     //   181: lload_1
/*    */     //   182: lconst_0
/*    */     //   183: lcmp
/*    */     //   184: iflt -> 232
/*    */     //   187: ifnonnull -> 230
/*    */     //   190: ifeq -> 526
/*    */     //   193: goto -> 206
/*    */     //   196: ldc2_w 6036170761931524579
/*    */     //   199: lload_1
/*    */     //   200: <illegal opcode> w : (Ljava/lang/NullPointerException;JJ)Ljava/lang/NullPointerException;
/*    */     //   205: athrow
/*    */     //   206: aload_0
/*    */     //   207: getfield c : Ljava/net/ProxySelector;
/*    */     //   210: aload_3
/*    */     //   211: getfield c : Ljava/net/ProxySelector;
/*    */     //   214: invokevirtual equals : (Ljava/lang/Object;)Z
/*    */     //   217: goto -> 230
/*    */     //   220: ldc2_w 6036170761931524579
/*    */     //   223: lload_1
/*    */     //   224: <illegal opcode> w : (Ljava/lang/NullPointerException;JJ)Ljava/lang/NullPointerException;
/*    */     //   229: athrow
/*    */     //   230: aload #4
/*    */     //   232: lload_1
/*    */     //   233: lconst_0
/*    */     //   234: lcmp
/*    */     //   235: iflt -> 283
/*    */     //   238: ifnonnull -> 281
/*    */     //   241: ifeq -> 526
/*    */     //   244: goto -> 257
/*    */     //   247: ldc2_w 6036170761931524579
/*    */     //   250: lload_1
/*    */     //   251: <illegal opcode> w : (Ljava/lang/NullPointerException;JJ)Ljava/lang/NullPointerException;
/*    */     //   256: athrow
/*    */     //   257: aload_0
/*    */     //   258: getfield i : Ljava/net/Proxy;
/*    */     //   261: aload_3
/*    */     //   262: getfield i : Ljava/net/Proxy;
/*    */     //   265: invokestatic equals : (Ljava/lang/Object;Ljava/lang/Object;)Z
/*    */     //   268: goto -> 281
/*    */     //   271: ldc2_w 6036170761931524579
/*    */     //   274: lload_1
/*    */     //   275: <illegal opcode> w : (Ljava/lang/NullPointerException;JJ)Ljava/lang/NullPointerException;
/*    */     //   280: athrow
/*    */     //   281: aload #4
/*    */     //   283: lload_1
/*    */     //   284: lconst_0
/*    */     //   285: lcmp
/*    */     //   286: iflt -> 334
/*    */     //   289: ifnonnull -> 332
/*    */     //   292: ifeq -> 526
/*    */     //   295: goto -> 308
/*    */     //   298: ldc2_w 6036170761931524579
/*    */     //   301: lload_1
/*    */     //   302: <illegal opcode> w : (Ljava/lang/NullPointerException;JJ)Ljava/lang/NullPointerException;
/*    */     //   307: athrow
/*    */     //   308: aload_0
/*    */     //   309: getfield k : Ljavax/net/ssl/SSLSocketFactory;
/*    */     //   312: aload_3
/*    */     //   313: getfield k : Ljavax/net/ssl/SSLSocketFactory;
/*    */     //   316: invokestatic equals : (Ljava/lang/Object;Ljava/lang/Object;)Z
/*    */     //   319: goto -> 332
/*    */     //   322: ldc2_w 6036170761931524579
/*    */     //   325: lload_1
/*    */     //   326: <illegal opcode> w : (Ljava/lang/NullPointerException;JJ)Ljava/lang/NullPointerException;
/*    */     //   331: athrow
/*    */     //   332: aload #4
/*    */     //   334: lload_1
/*    */     //   335: lconst_0
/*    */     //   336: lcmp
/*    */     //   337: iflt -> 385
/*    */     //   340: ifnonnull -> 383
/*    */     //   343: ifeq -> 526
/*    */     //   346: goto -> 359
/*    */     //   349: ldc2_w 6036170761931524579
/*    */     //   352: lload_1
/*    */     //   353: <illegal opcode> w : (Ljava/lang/NullPointerException;JJ)Ljava/lang/NullPointerException;
/*    */     //   358: athrow
/*    */     //   359: aload_0
/*    */     //   360: getfield a : Ljavax/net/ssl/HostnameVerifier;
/*    */     //   363: aload_3
/*    */     //   364: getfield a : Ljavax/net/ssl/HostnameVerifier;
/*    */     //   367: invokestatic equals : (Ljava/lang/Object;Ljava/lang/Object;)Z
/*    */     //   370: goto -> 383
/*    */     //   373: ldc2_w 6036170761931524579
/*    */     //   376: lload_1
/*    */     //   377: <illegal opcode> w : (Ljava/lang/NullPointerException;JJ)Ljava/lang/NullPointerException;
/*    */     //   382: athrow
/*    */     //   383: aload #4
/*    */     //   385: lload_1
/*    */     //   386: lconst_0
/*    */     //   387: lcmp
/*    */     //   388: iflt -> 436
/*    */     //   391: ifnonnull -> 434
/*    */     //   394: ifeq -> 526
/*    */     //   397: goto -> 410
/*    */     //   400: ldc2_w 6036170761931524579
/*    */     //   403: lload_1
/*    */     //   404: <illegal opcode> w : (Ljava/lang/NullPointerException;JJ)Ljava/lang/NullPointerException;
/*    */     //   409: athrow
/*    */     //   410: aload_0
/*    */     //   411: getfield f : Lme/konsolas/aac/mG;
/*    */     //   414: aload_3
/*    */     //   415: getfield f : Lme/konsolas/aac/mG;
/*    */     //   418: invokestatic equals : (Ljava/lang/Object;Ljava/lang/Object;)Z
/*    */     //   421: goto -> 434
/*    */     //   424: ldc2_w 6036170761931524579
/*    */     //   427: lload_1
/*    */     //   428: <illegal opcode> w : (Ljava/lang/NullPointerException;JJ)Ljava/lang/NullPointerException;
/*    */     //   433: athrow
/*    */     //   434: aload #4
/*    */     //   436: lload_1
/*    */     //   437: lconst_0
/*    */     //   438: lcmp
/*    */     //   439: ifle -> 483
/*    */     //   442: ifnonnull -> 481
/*    */     //   445: ifeq -> 526
/*    */     //   448: goto -> 461
/*    */     //   451: ldc2_w 6036170761931524579
/*    */     //   454: lload_1
/*    */     //   455: <illegal opcode> w : (Ljava/lang/NullPointerException;JJ)Ljava/lang/NullPointerException;
/*    */     //   460: athrow
/*    */     //   461: aload_0
/*    */     //   462: invokevirtual a : ()Lme/konsolas/aac/l6;
/*    */     //   465: invokevirtual c : ()I
/*    */     //   468: goto -> 481
/*    */     //   471: ldc2_w 6036170761931524579
/*    */     //   474: lload_1
/*    */     //   475: <illegal opcode> w : (Ljava/lang/NullPointerException;JJ)Ljava/lang/NullPointerException;
/*    */     //   480: athrow
/*    */     //   481: aload #4
/*    */     //   483: ifnonnull -> 523
/*    */     //   486: aload_3
/*    */     //   487: invokevirtual a : ()Lme/konsolas/aac/l6;
/*    */     //   490: invokevirtual c : ()I
/*    */     //   493: if_icmpne -> 526
/*    */     //   496: goto -> 509
/*    */     //   499: ldc2_w 6036170761931524579
/*    */     //   502: lload_1
/*    */     //   503: <illegal opcode> w : (Ljava/lang/NullPointerException;JJ)Ljava/lang/NullPointerException;
/*    */     //   508: athrow
/*    */     //   509: iconst_1
/*    */     //   510: goto -> 523
/*    */     //   513: ldc2_w 6036170761931524579
/*    */     //   516: lload_1
/*    */     //   517: <illegal opcode> w : (Ljava/lang/NullPointerException;JJ)Ljava/lang/NullPointerException;
/*    */     //   522: athrow
/*    */     //   523: goto -> 527
/*    */     //   526: iconst_0
/*    */     //   527: ireturn
/*    */     // Line number table:
/*    */     //   Java source line number -> byte code offset
/*    */     //   #29	-> 17
/*    */     //   #4	-> 57
/*    */     //   #26	-> 108
/*    */     //   #17	-> 161
/*    */     //   #13	-> 214
/*    */     //   #34	-> 265
/*    */     //   #3	-> 316
/*    */     //   #54	-> 367
/*    */     //   #9	-> 418
/*    */     //   #11	-> 462
/*    */     //   #25	-> 527
/*    */     // Exception table:
/*    */     //   from	to	target	type
/*    */     //   17	36	39	java/lang/NullPointerException
/*    */     //   33	60	63	java/lang/NullPointerException
/*    */     //   73	87	90	java/lang/NullPointerException
/*    */     //   84	113	116	java/lang/NullPointerException
/*    */     //   126	140	143	java/lang/NullPointerException
/*    */     //   137	166	169	java/lang/NullPointerException
/*    */     //   179	193	196	java/lang/NullPointerException
/*    */     //   190	217	220	java/lang/NullPointerException
/*    */     //   230	244	247	java/lang/NullPointerException
/*    */     //   241	268	271	java/lang/NullPointerException
/*    */     //   281	295	298	java/lang/NullPointerException
/*    */     //   292	319	322	java/lang/NullPointerException
/*    */     //   332	346	349	java/lang/NullPointerException
/*    */     //   343	370	373	java/lang/NullPointerException
/*    */     //   383	397	400	java/lang/NullPointerException
/*    */     //   394	421	424	java/lang/NullPointerException
/*    */     //   434	448	451	java/lang/NullPointerException
/*    */     //   445	468	471	java/lang/NullPointerException
/*    */     //   481	496	499	java/lang/NullPointerException
/*    */     //   486	510	513	java/lang/NullPointerException
/*    */   }
/*    */   
/*    */   public l6 a() {
/* 37 */     return this.e;
/*    */   }
/*    */   
/*    */   @Nullable
/* 41 */   public Proxy a() { return this.i; } public k4 a() {
/* 42 */     return this.g;
/*    */   }
/*    */   
/*    */   @Nullable
/*    */   public SSLSocketFactory a() {
/* 47 */     return this.k;
/*    */   }
/* 49 */   public dp a() { return this.h; } @Nullable
/* 50 */   public HostnameVerifier a() { return this.a; }
/*    */    public int hashCode() {
/* 52 */     int i = 17;
/*    */ 
/*    */ 
/*    */ 
/*    */ 
/*    */ 
/*    */     
/*    */     i = 31 * i + this.e.hashCode();
/*    */ 
/*    */ 
/*    */ 
/*    */ 
/*    */ 
/*    */     
/* 66 */     i = 31 * i + this.g.hashCode(); i = 31 * i + this.h.hashCode(); i = 31 * i + this.j.hashCode(); i = 31 * i + this.d.hashCode();
/*    */     i = 31 * i + this.c.hashCode();
/* 68 */     i = 31 * i + Objects.hashCode(this.i);
/*    */     i = 31 * i + Objects.hashCode(this.k);
/*    */     i = 31 * i + Objects.hashCode(this.a);
/*    */     i = 31 * i + Objects.hashCode(this.f);
/*    */     return i;
/*    */   }
/*    */   
/*    */   public jh(String paramString, int paramInt, k4 paramk4, SocketFactory paramSocketFactory, @Nullable SSLSocketFactory paramSSLSocketFactory, @Nullable HostnameVerifier paramHostnameVerifier, @Nullable mG parammG, dp paramdp, @Nullable Proxy paramProxy, List paramList1, long paramLong, List paramList2, ProxySelector paramProxySelector) {
/*    */     // Byte code:
/*    */     //   0: getstatic me/konsolas/aac/jh.l : J
/*    */     //   3: lload #11
/*    */     //   5: lxor
/*    */     //   6: lstore #11
/*    */     //   8: lload #11
/*    */     //   10: dup2
/*    */     //   11: ldc2_w 62421262399561
/*    */     //   14: lxor
/*    */     //   15: lstore #15
/*    */     //   17: dup2
/*    */     //   18: ldc2_w 32792593632558
/*    */     //   21: lxor
/*    */     //   22: lstore #17
/*    */     //   24: dup2
/*    */     //   25: ldc2_w 35943403849617
/*    */     //   28: lxor
/*    */     //   29: lstore #19
/*    */     //   31: dup2
/*    */     //   32: ldc2_w 118643000646900
/*    */     //   35: lxor
/*    */     //   36: lstore #21
/*    */     //   38: pop2
/*    */     //   39: ldc2_w 6416410476630596041
/*    */     //   42: lload #11
/*    */     //   44: <illegal opcode> w : (JJ)[Lme/konsolas/aac/aN;
/*    */     //   49: aload_0
/*    */     //   50: invokespecial <init> : ()V
/*    */     //   53: astore #23
/*    */     //   55: aload_0
/*    */     //   56: new me/konsolas/aac/j5
/*    */     //   59: dup
/*    */     //   60: invokespecial <init> : ()V
/*    */     //   63: aload #5
/*    */     //   65: ifnull -> 96
/*    */     //   68: sipush #7442
/*    */     //   71: ldc2_w 5808392499220714059
/*    */     //   74: lload #11
/*    */     //   76: lxor
/*    */     //   77: <illegal opcode> f : (IJ)Ljava/lang/String;
/*    */     //   82: goto -> 110
/*    */     //   85: ldc2_w 6379563769970950831
/*    */     //   88: lload #11
/*    */     //   90: <illegal opcode> w : (Ljava/lang/NullPointerException;JJ)Ljava/lang/NullPointerException;
/*    */     //   95: athrow
/*    */     //   96: sipush #5441
/*    */     //   99: ldc2_w 1510880705163565596
/*    */     //   102: lload #11
/*    */     //   104: lxor
/*    */     //   105: <illegal opcode> f : (IJ)Ljava/lang/String;
/*    */     //   110: lload #15
/*    */     //   112: dup2_x1
/*    */     //   113: pop2
/*    */     //   114: invokevirtual d : (JLjava/lang/String;)Lme/konsolas/aac/j5;
/*    */     //   117: aload_1
/*    */     //   118: lload #21
/*    */     //   120: invokevirtual l : (Ljava/lang/String;J)Lme/konsolas/aac/j5;
/*    */     //   123: iload_2
/*    */     //   124: lload #17
/*    */     //   126: invokevirtual b : (IJ)Lme/konsolas/aac/j5;
/*    */     //   129: lload #19
/*    */     //   131: invokevirtual a : (J)Lme/konsolas/aac/l6;
/*    */     //   134: putfield e : Lme/konsolas/aac/l6;
/*    */     //   137: aload #23
/*    */     //   139: lload #11
/*    */     //   141: lconst_0
/*    */     //   142: lcmp
/*    */     //   143: iflt -> 207
/*    */     //   146: ifnonnull -> 205
/*    */     //   149: aload_3
/*    */     //   150: ifnonnull -> 200
/*    */     //   153: goto -> 167
/*    */     //   156: ldc2_w 6379563769970950831
/*    */     //   159: lload #11
/*    */     //   161: <illegal opcode> w : (Ljava/lang/NullPointerException;JJ)Ljava/lang/NullPointerException;
/*    */     //   166: athrow
/*    */     //   167: new java/lang/NullPointerException
/*    */     //   170: dup
/*    */     //   171: sipush #8145
/*    */     //   174: ldc2_w 5367823731956551819
/*    */     //   177: lload #11
/*    */     //   179: lxor
/*    */     //   180: <illegal opcode> f : (IJ)Ljava/lang/String;
/*    */     //   185: invokespecial <init> : (Ljava/lang/String;)V
/*    */     //   188: athrow
/*    */     //   189: ldc2_w 6379563769970950831
/*    */     //   192: lload #11
/*    */     //   194: <illegal opcode> w : (Ljava/lang/NullPointerException;JJ)Ljava/lang/NullPointerException;
/*    */     //   199: athrow
/*    */     //   200: aload_0
/*    */     //   201: aload_3
/*    */     //   202: putfield g : Lme/konsolas/aac/k4;
/*    */     //   205: aload #23
/*    */     //   207: lload #11
/*    */     //   209: lconst_0
/*    */     //   210: lcmp
/*    */     //   211: ifle -> 284
/*    */     //   214: ifnonnull -> 275
/*    */     //   217: aload #4
/*    */     //   219: ifnonnull -> 269
/*    */     //   222: goto -> 236
/*    */     //   225: ldc2_w 6379563769970950831
/*    */     //   228: lload #11
/*    */     //   230: <illegal opcode> w : (Ljava/lang/NullPointerException;JJ)Ljava/lang/NullPointerException;
/*    */     //   235: athrow
/*    */     //   236: new java/lang/NullPointerException
/*    */     //   239: dup
/*    */     //   240: sipush #24063
/*    */     //   243: ldc2_w 5504364212464407200
/*    */     //   246: lload #11
/*    */     //   248: lxor
/*    */     //   249: <illegal opcode> f : (IJ)Ljava/lang/String;
/*    */     //   254: invokespecial <init> : (Ljava/lang/String;)V
/*    */     //   257: athrow
/*    */     //   258: ldc2_w 6379563769970950831
/*    */     //   261: lload #11
/*    */     //   263: <illegal opcode> w : (Ljava/lang/NullPointerException;JJ)Ljava/lang/NullPointerException;
/*    */     //   268: athrow
/*    */     //   269: aload_0
/*    */     //   270: aload #4
/*    */     //   272: putfield b : Ljavax/net/SocketFactory;
/*    */     //   275: lload #11
/*    */     //   277: lconst_0
/*    */     //   278: lcmp
/*    */     //   279: ifle -> 345
/*    */     //   282: aload #23
/*    */     //   284: ifnonnull -> 345
/*    */     //   287: aload #8
/*    */     //   289: ifnonnull -> 339
/*    */     //   292: goto -> 306
/*    */     //   295: ldc2_w 6379563769970950831
/*    */     //   298: lload #11
/*    */     //   300: <illegal opcode> w : (Ljava/lang/NullPointerException;JJ)Ljava/lang/NullPointerException;
/*    */     //   305: athrow
/*    */     //   306: new java/lang/NullPointerException
/*    */     //   309: dup
/*    */     //   310: sipush #1101
/*    */     //   313: ldc2_w 2477008643449621265
/*    */     //   316: lload #11
/*    */     //   318: lxor
/*    */     //   319: <illegal opcode> f : (IJ)Ljava/lang/String;
/*    */     //   324: invokespecial <init> : (Ljava/lang/String;)V
/*    */     //   327: athrow
/*    */     //   328: ldc2_w 6379563769970950831
/*    */     //   331: lload #11
/*    */     //   333: <illegal opcode> w : (Ljava/lang/NullPointerException;JJ)Ljava/lang/NullPointerException;
/*    */     //   338: athrow
/*    */     //   339: aload_0
/*    */     //   340: aload #8
/*    */     //   342: putfield h : Lme/konsolas/aac/dp;
/*    */     //   345: aload #10
/*    */     //   347: lload #11
/*    */     //   349: lconst_0
/*    */     //   350: lcmp
/*    */     //   351: ifle -> 446
/*    */     //   354: aload #23
/*    */     //   356: ifnonnull -> 446
/*    */     //   359: ifnonnull -> 409
/*    */     //   362: goto -> 376
/*    */     //   365: ldc2_w 6379563769970950831
/*    */     //   368: lload #11
/*    */     //   370: <illegal opcode> w : (Ljava/lang/NullPointerException;JJ)Ljava/lang/NullPointerException;
/*    */     //   375: athrow
/*    */     //   376: new java/lang/NullPointerException
/*    */     //   379: dup
/*    */     //   380: sipush #16229
/*    */     //   383: ldc2_w 7927066854402994229
/*    */     //   386: lload #11
/*    */     //   388: lxor
/*    */     //   389: <illegal opcode> f : (IJ)Ljava/lang/String;
/*    */     //   394: invokespecial <init> : (Ljava/lang/String;)V
/*    */     //   397: athrow
/*    */     //   398: ldc2_w 6379563769970950831
/*    */     //   401: lload #11
/*    */     //   403: <illegal opcode> w : (Ljava/lang/NullPointerException;JJ)Ljava/lang/NullPointerException;
/*    */     //   408: athrow
/*    */     //   409: aload_0
/*    */     //   410: aload #10
/*    */     //   412: invokestatic a : (Ljava/util/List;)Ljava/util/List;
/*    */     //   415: putfield j : Ljava/util/List;
/*    */     //   418: aload #23
/*    */     //   420: lload #11
/*    */     //   422: lconst_0
/*    */     //   423: lcmp
/*    */     //   424: ifle -> 493
/*    */     //   427: ifnonnull -> 491
/*    */     //   430: aload #13
/*    */     //   432: goto -> 446
/*    */     //   435: ldc2_w 6379563769970950831
/*    */     //   438: lload #11
/*    */     //   440: <illegal opcode> w : (Ljava/lang/NullPointerException;JJ)Ljava/lang/NullPointerException;
/*    */     //   445: athrow
/*    */     //   446: ifnonnull -> 482
/*    */     //   449: new java/lang/NullPointerException
/*    */     //   452: dup
/*    */     //   453: sipush #19049
/*    */     //   456: ldc2_w 1271844898697692472
/*    */     //   459: lload #11
/*    */     //   461: lxor
/*    */     //   462: <illegal opcode> f : (IJ)Ljava/lang/String;
/*    */     //   467: invokespecial <init> : (Ljava/lang/String;)V
/*    */     //   470: athrow
/*    */     //   471: ldc2_w 6379563769970950831
/*    */     //   474: lload #11
/*    */     //   476: <illegal opcode> w : (Ljava/lang/NullPointerException;JJ)Ljava/lang/NullPointerException;
/*    */     //   481: athrow
/*    */     //   482: aload_0
/*    */     //   483: aload #13
/*    */     //   485: invokestatic a : (Ljava/util/List;)Ljava/util/List;
/*    */     //   488: putfield d : Ljava/util/List;
/*    */     //   491: aload #23
/*    */     //   493: ifnonnull -> 578
/*    */     //   496: aload #14
/*    */     //   498: ifnonnull -> 548
/*    */     //   501: goto -> 515
/*    */     //   504: ldc2_w 6379563769970950831
/*    */     //   507: lload #11
/*    */     //   509: <illegal opcode> w : (Ljava/lang/NullPointerException;JJ)Ljava/lang/NullPointerException;
/*    */     //   514: athrow
/*    */     //   515: new java/lang/NullPointerException
/*    */     //   518: dup
/*    */     //   519: sipush #16893
/*    */     //   522: ldc2_w 4364729747274682019
/*    */     //   525: lload #11
/*    */     //   527: lxor
/*    */     //   528: <illegal opcode> f : (IJ)Ljava/lang/String;
/*    */     //   533: invokespecial <init> : (Ljava/lang/String;)V
/*    */     //   536: athrow
/*    */     //   537: ldc2_w 6379563769970950831
/*    */     //   540: lload #11
/*    */     //   542: <illegal opcode> w : (Ljava/lang/NullPointerException;JJ)Ljava/lang/NullPointerException;
/*    */     //   547: athrow
/*    */     //   548: aload_0
/*    */     //   549: aload #14
/*    */     //   551: putfield c : Ljava/net/ProxySelector;
/*    */     //   554: aload_0
/*    */     //   555: aload #9
/*    */     //   557: putfield i : Ljava/net/Proxy;
/*    */     //   560: aload_0
/*    */     //   561: aload #5
/*    */     //   563: putfield k : Ljavax/net/ssl/SSLSocketFactory;
/*    */     //   566: aload_0
/*    */     //   567: aload #6
/*    */     //   569: putfield a : Ljavax/net/ssl/HostnameVerifier;
/*    */     //   572: aload_0
/*    */     //   573: aload #7
/*    */     //   575: putfield f : Lme/konsolas/aac/mG;
/*    */     //   578: return
/*    */     // Line number table:
/*    */     //   Java source line number -> byte code offset
/*    */     //   #70	-> 49
/*    */     //   #65	-> 55
/*    */     //   #61	-> 63
/*    */     //   #31	-> 118
/*    */     //   #40	-> 124
/*    */     //   #21	-> 129
/*    */     //   #69	-> 137
/*    */     //   #55	-> 200
/*    */     //   #62	-> 205
/*    */     //   #8	-> 269
/*    */     //   #6	-> 275
/*    */     //   #56	-> 306
/*    */     //   #64	-> 339
/*    */     //   #7	-> 345
/*    */     //   #67	-> 409
/*    */     //   #15	-> 418
/*    */     //   #33	-> 482
/*    */     //   #58	-> 491
/*    */     //   #57	-> 548
/*    */     //   #36	-> 554
/*    */     //   #43	-> 560
/*    */     //   #44	-> 566
/*    */     //   #48	-> 572
/*    */     //   #32	-> 578
/*    */     // Exception table:
/*    */     //   from	to	target	type
/*    */     //   55	85	85	java/lang/NullPointerException
/*    */     //   110	153	156	java/lang/NullPointerException
/*    */     //   149	189	189	java/lang/NullPointerException
/*    */     //   205	222	225	java/lang/NullPointerException
/*    */     //   217	258	258	java/lang/NullPointerException
/*    */     //   275	292	295	java/lang/NullPointerException
/*    */     //   287	328	328	java/lang/NullPointerException
/*    */     //   345	362	365	java/lang/NullPointerException
/*    */     //   359	398	398	java/lang/NullPointerException
/*    */     //   409	432	435	java/lang/NullPointerException
/*    */     //   446	471	471	java/lang/NullPointerException
/*    */     //   491	501	504	java/lang/NullPointerException
/*    */     //   496	537	537	java/lang/NullPointerException
/*    */   }
/*    */   
/*    */   static {
/*    */     long l = l ^ 0x61D215BE4A62L;
/*    */     "훧ﳿ腩鹥ꔹ┐ᅖ嚥쇕אּ舱婙㶂ቩ蛍䢗굵遦ᩔ".toCharArray()[10] = (char)("훧ﳿ腩鹥ꔹ┐ᅖ嚥쇕אּ舱婙㶂ቩ蛍䢗굵遦ᩔ".toCharArray()[10] ^ 0x39F3);
/*    */     "?ꬕᴳⷥ".toCharArray()[1] = (char)("?ꬕᴳⷥ".toCharArray()[1] ^ 0x75AD);
/*    */     (new byte[8])[0] = (byte)(int)(l >>> 56L);
/*    */     for (byte b1 = 1; b1 < 8; b1++)
/*    */       (new byte[8])[b1] = (byte)(int)(l << b1 * 8 >>> 56L); 
/*    */     Cipher cipher;
/*    */     (cipher = Cipher.getInstance(dP$dt.X("훧ﳿ腩鹥ꔹ┐ᅖ嚥쇕אּ舱婙㶂ቩ蛍䢗굵遦ᩔ".toCharArray(), (short)30258, true, true))).init(2, SecretKeyFactory.getInstance(dP$dt.X("?ꬕᴳⷥ".toCharArray(), (short)1984, true, true)).generateSecret(new DESKeySpec(new byte[8])), new IvParameterSpec(new byte[8]));
/*    */     String[] arrayOfString = new String[11];
/*    */     boolean bool = false;
/*    */     "ꆙ㳤鞢ꔑ鑉⽠ﯣ깱䟀뿯炬㏨詊 俈賝彂屏鈊䐙쓘桊荱ᶾﳎ䂣䤗쎔䎜࠷︀ᣕ?ꏏ곋蔿蔔髪隙䗝㴃菠ꔲѳࣈ഻ር᯹扛픾嵍ײⶫᓿ꼶欅䥗窕媇裊䠻딩挩꘡඘ꣷƁ媉뽴亘걑렭庆쐥嚔翟嚝뺔炠ﰈ喌ࢍ艸苟箪㭞뽍䛐ꜰꝬ뤇ꭶᆩ䬐汾ʼ峘뉻示鰪溜얜虼꼠腎뱵綡Ͽ⦼⯾鉌⪟ૻ衖⾡⃴ⶮ皞ύ鮮荎ﲳꠝ킡栦姃笹ỷ䑤꫎쐹偕᧖驼?퍗㖨堝ᆅ폕鳾㲰맴툺﵀촗酩鯺瀘㿗梫堆삗쫃▴਴㝀퀭獱重隝擄獅궮㨺ᐔ攅桧?蜔ፅꮆ䋊⒝虘쫗馤篥䶿靂맍﯂⁡І箿㝰녀⍝郗밢깿ꯁ鑦㑥뤞⸢ᾣᙔ㢎ꪬꕿ嘠䍧䬐ꗟᄙ毬怈㡛᮶夾㮅똣ㅫ퐉⪎鈋媭?뎨ύ?컅ᔝ?攙飛⯌傁諗๗瘉耖鱽?㽐鯥ᤍ힄둵⃡墿䨿뎩蛘崉뀌ϧ딹蔎渍䘫쉨鋤휹뒛櫜꥘ꍋꑁ┚辽쥃ၚඋ贗沷ꔦ椼볢꬐讱䆻폤纄狯贃충髒嗺".toCharArray()[19] = (char)("ꆙ㳤鞢ꔑ鑉⽠ﯣ깱䟀뿯炬㏨詊 俈賝彂屏鈊䐙쓘桊荱ᶾﳎ䂣䤗쎔䎜࠷︀ᣕ?ꏏ곋蔿蔔髪隙䗝㴃菠ꔲѳࣈ഻ር᯹扛픾嵍ײⶫᓿ꼶欅䥗窕媇裊䠻딩挩꘡඘ꣷƁ媉뽴亘걑렭庆쐥嚔翟嚝뺔炠ﰈ喌ࢍ艸苟箪㭞뽍䛐ꜰꝬ뤇ꭶᆩ䬐汾ʼ峘뉻示鰪溜얜虼꼠腎뱵綡Ͽ⦼⯾鉌⪟ૻ衖⾡⃴ⶮ皞ύ鮮荎ﲳꠝ킡栦姃笹ỷ䑤꫎쐹偕᧖驼?퍗㖨堝ᆅ폕鳾㲰맴툺﵀촗酩鯺瀘㿗梫堆삗쫃▴਴㝀퀭獱重隝擄獅궮㨺ᐔ攅桧?蜔ፅꮆ䋊⒝虘쫗馤篥䶿靂맍﯂⁡І箿㝰녀⍝郗밢깿ꯁ鑦㑥뤞⸢ᾣᙔ㢎ꪬꕿ嘠䍧䬐ꗟᄙ毬怈㡛᮶夾㮅똣ㅫ퐉⪎鈋媭?뎨ύ?컅ᔝ?攙飛⯌傁諗๗瘉耖鱽?㽐鯥ᤍ힄둵⃡墿䨿뎩蛘崉뀌ϧ딹蔎渍䘫쉨鋤휹뒛櫜꥘ꍋꑁ┚辽쥃ၚඋ贗沷ꔦ椼볢꬐讱䆻폤纄狯贃충髒嗺".toCharArray()[19] ^ 0x5F2D);
/*    */     String str;
/*    */     int i = (str = dP$dt.X("ꆙ㳤鞢ꔑ鑉⽠ﯣ깱䟀뿯炬㏨詊 俈賝彂屏鈊䐙쓘桊荱ᶾﳎ䂣䤗쎔䎜࠷︀ᣕ?ꏏ곋蔿蔔髪隙䗝㴃菠ꔲѳࣈ഻ር᯹扛픾嵍ײⶫᓿ꼶欅䥗窕媇裊䠻딩挩꘡඘ꣷƁ媉뽴亘걑렭庆쐥嚔翟嚝뺔炠ﰈ喌ࢍ艸苟箪㭞뽍䛐ꜰꝬ뤇ꭶᆩ䬐汾ʼ峘뉻示鰪溜얜虼꼠腎뱵綡Ͽ⦼⯾鉌⪟ૻ衖⾡⃴ⶮ皞ύ鮮荎ﲳꠝ킡栦姃笹ỷ䑤꫎쐹偕᧖驼?퍗㖨堝ᆅ폕鳾㲰맴툺﵀촗酩鯺瀘㿗梫堆삗쫃▴਴㝀퀭獱重隝擄獅궮㨺ᐔ攅桧?蜔ፅꮆ䋊⒝虘쫗馤篥䶿靂맍﯂⁡І箿㝰녀⍝郗밢깿ꯁ鑦㑥뤞⸢ᾣᙔ㢎ꪬꕿ嘠䍧䬐ꗟᄙ毬怈㡛᮶夾㮅똣ㅫ퐉⪎鈋媭?뎨ύ?컅ᔝ?攙飛⯌傁諗๗瘉耖鱽?㽐鯥ᤍ힄둵⃡墿䨿뎩蛘崉뀌ϧ딹蔎渍䘫쉨鋤휹뒛櫜꥘ꍋꑁ┚辽쥃ၚඋ贗沷ꔦ椼볢꬐讱䆻폤纄狯贃충髒嗺".toCharArray(), (short)6643, false, true)).length();
/*    */     byte b2 = 32;
/*    */     byte b = -1;
/*    */     while (true);
/*    */   }
/*    */   
/*    */   private static NullPointerException a(NullPointerException paramNullPointerException) {
/*    */     return paramNullPointerException;
/*    */   }
/*    */   
/*    */   private static String a(byte[] paramArrayOfbyte) {
/*    */     byte b1 = 0;
/*    */     int i;
/*    */     char[] arrayOfChar = new char[i = paramArrayOfbyte.length];
/*    */     for (byte b2 = 0; b2 < i; b2++) {
/*    */       int j;
/*    */       if ((j = 0xFF & paramArrayOfbyte[b2]) < 192) {
/*    */         arrayOfChar[b1++] = (char)j;
/*    */       } else if (j < 224) {
/*    */         char c = (char)((char)(j & 0x1F) << 6);
/*    */         j = paramArrayOfbyte[++b2];
/*    */         c = (char)(c | (char)(j & 0x3F));
/*    */         arrayOfChar[b1++] = c;
/*    */       } else if (b2 < i - 2) {
/*    */         char c = (char)((char)(j & 0xF) << 12);
/*    */         j = paramArrayOfbyte[++b2];
/*    */         c = (char)(c | (char)(j & 0x3F) << 6);
/*    */         j = paramArrayOfbyte[++b2];
/*    */         c = (char)(c | (char)(j & 0x3F));
/*    */         arrayOfChar[b1++] = c;
/*    */       } 
/*    */     } 
/*    */     return new String(arrayOfChar, 0, b1);
/*    */   }
/*    */   
/*    */   private static String a(int paramInt, long paramLong) {
/*    */     int i = paramInt ^ (int)(paramLong & 0x7FFFL) ^ 0x56B7;
/*    */     if (n[i] == null) {
/*    */       Object[] arrayOfObject;
/*    */       try {
/*    */         Long long_ = Long.valueOf(Thread.currentThread().getId());
/*    */         arrayOfObject = (Object[])o.get(long_);
/*    */         if (arrayOfObject == null) {
/*    */           arrayOfObject = new Object[3];
/*    */           "穫홌ፙ䣱뎊ٞ뾩늈揂㚾譡Ṍ呖ﵱ蓥벂濚".toCharArray()[3] = (char)("穫홌ፙ䣱뎊ٞ뾩늈揂㚾譡Ṍ呖ﵱ蓥벂濚".toCharArray()[3] ^ 0x6882);
/*    */           arrayOfObject[0] = Cipher.getInstance(fW$gy.A("穫홌ፙ䣱뎊ٞ뾩늈揂㚾譡Ṍ呖ﵱ蓥벂濚".toCharArray(), (short)25071, false, 1));
/*    */           "뱊懕₅".toCharArray()[2] = (char)("뱊懕₅".toCharArray()[2] ^ 0x38DC);
/*    */           arrayOfObject[1] = SecretKeyFactory.getInstance(fW$gy.A("뱊懕₅".toCharArray(), (short)9050, false, 5));
/*    */           arrayOfObject[2] = new IvParameterSpec(new byte[8]);
/*    */           o.put(long_, arrayOfObject);
/*    */         } 
/*    */       } catch (Exception exception) {
/*    */         "盖㝈◅ꄛ✔枡䲫㻠籪鬽済ȷ숊ⵥᶸݙ".toCharArray()[11] = (char)("盖㝈◅ꄛ✔枡䲫㻠籪鬽済ȷ숊ⵥᶸݙ".toCharArray()[11] ^ 0x66D8);
/*    */         throw new RuntimeException(fW$gy.A("盖㝈◅ꄛ✔枡䲫㻠籪鬽済ȷ숊ⵥᶸݙ".toCharArray(), (short)17064, true, 1), exception);
/*    */       } 
/*    */       byte[] arrayOfByte1 = new byte[8];
/*    */       arrayOfByte1[0] = (byte)(int)(paramLong >>> 56L);
/*    */       for (byte b = 1; b < 8; b++)
/*    */         arrayOfByte1[b] = (byte)(int)(paramLong << b * 8 >>> 56L); 
/*    */       DESKeySpec dESKeySpec = new DESKeySpec(arrayOfByte1);
/*    */       SecretKey secretKey = ((SecretKeyFactory)arrayOfObject[1]).generateSecret(dESKeySpec);
/*    */       ((Cipher)arrayOfObject[0]).init(2, secretKey, (IvParameterSpec)arrayOfObject[2]);
/*    */       "華ꛒ厵ὂ揋鏧㼙몽䨣".toCharArray()[7] = (char)("華ꛒ厵ὂ揋鏧㼙몽䨣".toCharArray()[7] ^ 0xD4F);
/*    */       byte[] arrayOfByte2 = m[i].getBytes(fW$gy.A("華ꛒ厵ὂ揋鏧㼙몽䨣".toCharArray(), (short)15918, true, 1));
/*    */       n[i] = a(((Cipher)arrayOfObject[0]).doFinal(arrayOfByte2));
/*    */     } 
/*    */     return n[i];
/*    */   }
/*    */   
/*    */   private static Object a(MethodHandles.Lookup paramLookup, MutableCallSite paramMutableCallSite, String paramString, Object[] paramArrayOfObject) {
/*    */     int i = ((Integer)paramArrayOfObject[0]).intValue();
/*    */     long l = ((Long)paramArrayOfObject[1]).longValue();
/*    */     String str = a(i, l);
/*    */     MethodHandle methodHandle = MethodHandles.constant(String.class, str);
/*    */     paramMutableCallSite.setTarget(MethodHandles.dropArguments(methodHandle, 0, new Class[] { int.class, long.class }));
/*    */     return str;
/*    */   }
/*    */   
/*    */   private static CallSite a(MethodHandles.Lookup paramLookup, String paramString, MethodType paramMethodType) {
/*    */     // Byte code:
/*    */     //   0: new java/lang/invoke/MutableCallSite
/*    */     //   3: dup
/*    */     //   4: aload_2
/*    */     //   5: invokespecial <init> : (Ljava/lang/invoke/MethodType;)V
/*    */     //   8: astore_3
/*    */     //   9: aload_3
/*    */     //   10: ldc_w
/*    */     //   13: ldc_w [Ljava/lang/Object;
/*    */     //   16: aload_2
/*    */     //   17: invokevirtual parameterCount : ()I
/*    */     //   20: invokevirtual asCollector : (Ljava/lang/Class;I)Ljava/lang/invoke/MethodHandle;
/*    */     //   23: iconst_0
/*    */     //   24: iconst_3
/*    */     //   25: anewarray java/lang/Object
/*    */     //   28: dup
/*    */     //   29: iconst_0
/*    */     //   30: aload_0
/*    */     //   31: aastore
/*    */     //   32: dup
/*    */     //   33: iconst_1
/*    */     //   34: aload_3
/*    */     //   35: aastore
/*    */     //   36: dup
/*    */     //   37: iconst_2
/*    */     //   38: aload_1
/*    */     //   39: aastore
/*    */     //   40: invokestatic insertArguments : (Ljava/lang/invoke/MethodHandle;I[Ljava/lang/Object;)Ljava/lang/invoke/MethodHandle;
/*    */     //   43: aload_2
/*    */     //   44: invokestatic explicitCastArguments : (Ljava/lang/invoke/MethodHandle;Ljava/lang/invoke/MethodType;)Ljava/lang/invoke/MethodHandle;
/*    */     //   47: invokevirtual setTarget : (Ljava/lang/invoke/MethodHandle;)V
/*    */     //   50: goto -> 171
/*    */     //   53: astore #4
/*    */     //   55: new java/lang/RuntimeException
/*    */     //   58: dup
/*    */     //   59: new java/lang/StringBuilder
/*    */     //   62: dup
/*    */     //   63: invokespecial <init> : ()V
/*    */     //   66: ldc_w '緽샢断硙貘縿美꿃跪寪⪾刞ᜢ쨊⏥棴桩Ꮚ'
/*    */     //   69: invokevirtual toCharArray : ()[C
/*    */     //   72: dup
/*    */     //   73: dup
/*    */     //   74: bipush #15
/*    */     //   76: dup_x1
/*    */     //   77: caload
/*    */     //   78: sipush #32336
/*    */     //   81: ixor
/*    */     //   82: i2c
/*    */     //   83: castore
/*    */     //   84: sipush #21104
/*    */     //   87: iconst_1
/*    */     //   88: iconst_1
/*    */     //   89: invokestatic H : (Ljava/lang/Object;SBB)Ljava/lang/String;
/*    */     //   92: invokevirtual append : (Ljava/lang/String;)Ljava/lang/StringBuilder;
/*    */     //   95: ldc_w 'ꇚ鑲?味'
/*    */     //   98: invokevirtual toCharArray : ()[C
/*    */     //   101: dup
/*    */     //   102: dup
/*    */     //   103: iconst_1
/*    */     //   104: dup_x1
/*    */     //   105: caload
/*    */     //   106: sipush #15097
/*    */     //   109: ixor
/*    */     //   110: i2c
/*    */     //   111: castore
/*    */     //   112: sipush #12522
/*    */     //   115: iconst_3
/*    */     //   116: iconst_4
/*    */     //   117: invokestatic H : (Ljava/lang/Object;SBB)Ljava/lang/String;
/*    */     //   120: invokevirtual append : (Ljava/lang/String;)Ljava/lang/StringBuilder;
/*    */     //   123: aload_1
/*    */     //   124: invokevirtual append : (Ljava/lang/String;)Ljava/lang/StringBuilder;
/*    */     //   127: ldc_w '弨ݾ伺'
/*    */     //   130: invokevirtual toCharArray : ()[C
/*    */     //   133: dup
/*    */     //   134: dup
/*    */     //   135: iconst_1
/*    */     //   136: dup_x1
/*    */     //   137: caload
/*    */     //   138: sipush #4854
/*    */     //   141: ixor
/*    */     //   142: i2c
/*    */     //   143: castore
/*    */     //   144: sipush #24875
/*    */     //   147: iconst_3
/*    */     //   148: iconst_1
/*    */     //   149: invokestatic H : (Ljava/lang/Object;SBB)Ljava/lang/String;
/*    */     //   152: invokevirtual append : (Ljava/lang/String;)Ljava/lang/StringBuilder;
/*    */     //   155: aload_2
/*    */     //   156: invokevirtual toString : ()Ljava/lang/String;
/*    */     //   159: invokevirtual append : (Ljava/lang/String;)Ljava/lang/StringBuilder;
/*    */     //   162: invokevirtual toString : ()Ljava/lang/String;
/*    */     //   165: aload #4
/*    */     //   167: invokespecial <init> : (Ljava/lang/String;Ljava/lang/Throwable;)V
/*    */     //   170: athrow
/*    */     //   171: aload_3
/*    */     //   172: areturn
/*    */     // Exception table:
/*    */     //   from	to	target	type
/*    */     //   9	50	53	java/lang/Exception
/*    */   } }


/* Location:              C:\Users\BukkitBypass\Desktop\MatrixAC\AAC\AAC-spigot-5.2.0.jar!\me\konsolas\aac\jh.class
 * Java compiler version: 8 (52.0)
 * JD-Core Version:       1.1.3
 */