/*  1 */ package me.konsolas.aac;final class jq implements hp { private final fw d; private final fw c; private final long a; static fw a(jq paramjq) { return paramjq.d; }
/*    */   
/*    */   private J g; boolean e; boolean h; static final boolean b; final cQ f; private static final long i; private static final String[] j;
/*    */   private static final String[] k;
/*    */   private static final Map l;
/*    */   
/*    */   public void close() {
/*    */     // Byte code:
/*    */     //   0: getstatic me/konsolas/aac/jq.i : J
/*    */     //   3: ldc2_w 3764746785574
/*    */     //   6: lxor
/*    */     //   7: lstore_1
/*    */     //   8: lload_1
/*    */     //   9: dup2
/*    */     //   10: ldc2_w 130136784078034
/*    */     //   13: lxor
/*    */     //   14: lstore_3
/*    */     //   15: dup2
/*    */     //   16: ldc2_w 67021711585976
/*    */     //   19: lxor
/*    */     //   20: lstore #5
/*    */     //   22: dup2
/*    */     //   23: ldc2_w 42056975637184
/*    */     //   26: lxor
/*    */     //   27: dup2
/*    */     //   28: bipush #48
/*    */     //   30: lushr
/*    */     //   31: l2i
/*    */     //   32: istore #7
/*    */     //   34: dup2
/*    */     //   35: bipush #16
/*    */     //   37: lshl
/*    */     //   38: bipush #32
/*    */     //   40: lushr
/*    */     //   41: l2i
/*    */     //   42: istore #8
/*    */     //   44: dup2
/*    */     //   45: bipush #48
/*    */     //   47: lshl
/*    */     //   48: bipush #48
/*    */     //   50: lushr
/*    */     //   51: l2i
/*    */     //   52: istore #9
/*    */     //   54: pop2
/*    */     //   55: pop2
/*    */     //   56: aload_0
/*    */     //   57: getfield f : Lme/konsolas/aac/cQ;
/*    */     //   60: dup
/*    */     //   61: astore #12
/*    */     //   63: monitorenter
/*    */     //   64: aload_0
/*    */     //   65: iconst_1
/*    */     //   66: putfield e : Z
/*    */     //   69: aload_0
/*    */     //   70: getfield c : Lme/konsolas/aac/fw;
/*    */     //   73: invokevirtual f : ()J
/*    */     //   76: lstore #10
/*    */     //   78: aload_0
/*    */     //   79: getfield c : Lme/konsolas/aac/fw;
/*    */     //   82: iload #7
/*    */     //   84: i2c
/*    */     //   85: iload #8
/*    */     //   87: iload #9
/*    */     //   89: invokevirtual a : (CII)V
/*    */     //   92: aload_0
/*    */     //   93: getfield f : Lme/konsolas/aac/cQ;
/*    */     //   96: invokevirtual notifyAll : ()V
/*    */     //   99: aload #12
/*    */     //   101: monitorexit
/*    */     //   102: goto -> 113
/*    */     //   105: astore #13
/*    */     //   107: aload #12
/*    */     //   109: monitorexit
/*    */     //   110: aload #13
/*    */     //   112: athrow
/*    */     //   113: lload #10
/*    */     //   115: lconst_0
/*    */     //   116: lcmp
/*    */     //   117: ifle -> 140
/*    */     //   120: aload_0
/*    */     //   121: lload #10
/*    */     //   123: lload_3
/*    */     //   124: invokespecial a : (JJ)V
/*    */     //   127: goto -> 140
/*    */     //   130: ldc2_w 3661976514480909708
/*    */     //   133: lload_1
/*    */     //   134: <illegal opcode> w : (Ljava/lang/Exception;JJ)Ljava/lang/Exception;
/*    */     //   139: athrow
/*    */     //   140: aload_0
/*    */     //   141: getfield f : Lme/konsolas/aac/cQ;
/*    */     //   144: lload #5
/*    */     //   146: invokevirtual c : (J)V
/*    */     //   149: return
/*    */     // Line number table:
/*    */     //   Java source line number -> byte code offset
/*    */     //   #9	-> 56
/*    */     //   #71	-> 64
/*    */     //   #56	-> 69
/*    */     //   #55	-> 78
/*    */     //   #47	-> 92
/*    */     //   #61	-> 99
/*    */     //   #66	-> 113
/*    */     //   #65	-> 120
/*    */     //   #79	-> 140
/*    */     //   #42	-> 149
/*    */     // Exception table:
/*    */     //   from	to	target	type
/*    */     //   64	102	105	finally
/*    */     //   105	110	105	finally
/*    */     //   113	127	130	java/io/IOException
/*    */   }
/*    */   
/*    */   void a(bX parambX, short paramShort, long paramLong1, long paramLong2) {
/*    */     // Byte code:
/*    */     //   0: iload_2
/*    */     //   1: i2l
/*    */     //   2: bipush #48
/*    */     //   4: lshl
/*    */     //   5: lload #5
/*    */     //   7: bipush #16
/*    */     //   9: lshl
/*    */     //   10: bipush #16
/*    */     //   12: lushr
/*    */     //   13: lor
/*    */     //   14: getstatic me/konsolas/aac/jq.i : J
/*    */     //   17: lxor
/*    */     //   18: lstore #7
/*    */     //   20: lload #7
/*    */     //   22: dup2
/*    */     //   23: ldc2_w 134539010800292
/*    */     //   26: lxor
/*    */     //   27: dup2
/*    */     //   28: bipush #16
/*    */     //   30: lushr
/*    */     //   31: lstore #9
/*    */     //   33: dup2
/*    */     //   34: bipush #48
/*    */     //   36: lshl
/*    */     //   37: bipush #48
/*    */     //   39: lushr
/*    */     //   40: l2i
/*    */     //   41: istore #11
/*    */     //   43: pop2
/*    */     //   44: dup2
/*    */     //   45: ldc2_w 77848136294702
/*    */     //   48: lxor
/*    */     //   49: lstore #12
/*    */     //   51: dup2
/*    */     //   52: ldc2_w 2806612074279
/*    */     //   55: lxor
/*    */     //   56: lstore #14
/*    */     //   58: dup2
/*    */     //   59: ldc2_w 140288745889385
/*    */     //   62: lxor
/*    */     //   63: lstore #16
/*    */     //   65: dup2
/*    */     //   66: ldc2_w 19044997729789
/*    */     //   69: lxor
/*    */     //   70: lstore #18
/*    */     //   72: dup2
/*    */     //   73: ldc2_w 90806425993525
/*    */     //   76: lxor
/*    */     //   77: dup2
/*    */     //   78: bipush #48
/*    */     //   80: lushr
/*    */     //   81: l2i
/*    */     //   82: istore #20
/*    */     //   84: dup2
/*    */     //   85: bipush #16
/*    */     //   87: lshl
/*    */     //   88: bipush #32
/*    */     //   90: lushr
/*    */     //   91: l2i
/*    */     //   92: istore #21
/*    */     //   94: dup2
/*    */     //   95: bipush #48
/*    */     //   97: lshl
/*    */     //   98: bipush #48
/*    */     //   100: lushr
/*    */     //   101: l2i
/*    */     //   102: istore #22
/*    */     //   104: pop2
/*    */     //   105: pop2
/*    */     //   106: ldc2_w 2908842342866406488
/*    */     //   109: lload #7
/*    */     //   111: <illegal opcode> w : (JJ)[Lme/konsolas/aac/aN;
/*    */     //   116: astore #23
/*    */     //   118: getstatic me/konsolas/aac/jq.b : Z
/*    */     //   121: aload #23
/*    */     //   123: ifnull -> 208
/*    */     //   126: ifne -> 205
/*    */     //   129: goto -> 143
/*    */     //   132: ldc2_w 2964636198479410809
/*    */     //   135: lload #7
/*    */     //   137: <illegal opcode> w : (Ljava/lang/Exception;JJ)Ljava/lang/Exception;
/*    */     //   142: athrow
/*    */     //   143: aload_0
/*    */     //   144: getfield f : Lme/konsolas/aac/cQ;
/*    */     //   147: invokestatic holdsLock : (Ljava/lang/Object;)Z
/*    */     //   150: aload #23
/*    */     //   152: ifnull -> 208
/*    */     //   155: goto -> 169
/*    */     //   158: ldc2_w 2964636198479410809
/*    */     //   161: lload #7
/*    */     //   163: <illegal opcode> w : (Ljava/lang/Exception;JJ)Ljava/lang/Exception;
/*    */     //   168: athrow
/*    */     //   169: ifeq -> 205
/*    */     //   172: goto -> 186
/*    */     //   175: ldc2_w 2964636198479410809
/*    */     //   178: lload #7
/*    */     //   180: <illegal opcode> w : (Ljava/lang/Exception;JJ)Ljava/lang/Exception;
/*    */     //   185: athrow
/*    */     //   186: new java/lang/AssertionError
/*    */     //   189: dup
/*    */     //   190: invokespecial <init> : ()V
/*    */     //   193: athrow
/*    */     //   194: ldc2_w 2964636198479410809
/*    */     //   197: lload #7
/*    */     //   199: <illegal opcode> w : (Ljava/lang/Exception;JJ)Ljava/lang/Exception;
/*    */     //   204: athrow
/*    */     //   205: lload_3
/*    */     //   206: lconst_0
/*    */     //   207: lcmp
/*    */     //   208: ifle -> 675
/*    */     //   211: aload_0
/*    */     //   212: getfield f : Lme/konsolas/aac/cQ;
/*    */     //   215: dup
/*    */     //   216: astore #26
/*    */     //   218: monitorenter
/*    */     //   219: aload_0
/*    */     //   220: getfield h : Z
/*    */     //   223: istore #24
/*    */     //   225: lload_3
/*    */     //   226: aload_0
/*    */     //   227: getfield c : Lme/konsolas/aac/fw;
/*    */     //   230: invokevirtual f : ()J
/*    */     //   233: ladd
/*    */     //   234: aload_0
/*    */     //   235: getfield a : J
/*    */     //   238: lcmp
/*    */     //   239: aload #23
/*    */     //   241: ifnull -> 262
/*    */     //   244: ifle -> 265
/*    */     //   247: goto -> 261
/*    */     //   250: ldc2_w 2964636198479410809
/*    */     //   253: lload #7
/*    */     //   255: <illegal opcode> w : (Ljava/lang/Exception;JJ)Ljava/lang/Exception;
/*    */     //   260: athrow
/*    */     //   261: iconst_1
/*    */     //   262: goto -> 266
/*    */     //   265: iconst_0
/*    */     //   266: istore #25
/*    */     //   268: aload #26
/*    */     //   270: monitorexit
/*    */     //   271: goto -> 282
/*    */     //   274: astore #27
/*    */     //   276: aload #26
/*    */     //   278: monitorexit
/*    */     //   279: aload #27
/*    */     //   281: athrow
/*    */     //   282: iload #25
/*    */     //   284: iload_2
/*    */     //   285: iflt -> 348
/*    */     //   288: aload #23
/*    */     //   290: ifnull -> 348
/*    */     //   293: ifeq -> 346
/*    */     //   296: goto -> 310
/*    */     //   299: ldc2_w 2964636198479410809
/*    */     //   302: lload #7
/*    */     //   304: <illegal opcode> w : (Ljava/lang/Exception;JJ)Ljava/lang/Exception;
/*    */     //   309: athrow
/*    */     //   310: aload_1
/*    */     //   311: lload_3
/*    */     //   312: lload #16
/*    */     //   314: invokeinterface a : (JJ)V
/*    */     //   319: aload_0
/*    */     //   320: getfield f : Lme/konsolas/aac/cQ;
/*    */     //   323: lload #9
/*    */     //   325: iload #11
/*    */     //   327: i2s
/*    */     //   328: getstatic me/konsolas/aac/eb.FLOW_CONTROL_ERROR : Lme/konsolas/aac/eb;
/*    */     //   331: invokevirtual b : (JSLme/konsolas/aac/eb;)V
/*    */     //   334: return
/*    */     //   335: ldc2_w 2964636198479410809
/*    */     //   338: lload #7
/*    */     //   340: <illegal opcode> w : (Ljava/lang/Exception;JJ)Ljava/lang/Exception;
/*    */     //   345: athrow
/*    */     //   346: iload #24
/*    */     //   348: ifeq -> 372
/*    */     //   351: aload_1
/*    */     //   352: lload_3
/*    */     //   353: lload #16
/*    */     //   355: invokeinterface a : (JJ)V
/*    */     //   360: return
/*    */     //   361: ldc2_w 2964636198479410809
/*    */     //   364: lload #7
/*    */     //   366: <illegal opcode> w : (Ljava/lang/Exception;JJ)Ljava/lang/Exception;
/*    */     //   371: athrow
/*    */     //   372: aload_1
/*    */     //   373: aload_0
/*    */     //   374: getfield d : Lme/konsolas/aac/fw;
/*    */     //   377: lload #12
/*    */     //   379: dup2_x1
/*    */     //   380: pop2
/*    */     //   381: lload_3
/*    */     //   382: invokeinterface a : (JLme/konsolas/aac/fw;J)J
/*    */     //   387: lstore #26
/*    */     //   389: lload #26
/*    */     //   391: iload_2
/*    */     //   392: iflt -> 446
/*    */     //   395: ldc2_w -1
/*    */     //   398: aload #23
/*    */     //   400: ifnull -> 443
/*    */     //   403: lcmp
/*    */     //   404: ifne -> 440
/*    */     //   407: goto -> 421
/*    */     //   410: ldc2_w 2964636198479410809
/*    */     //   413: lload #7
/*    */     //   415: <illegal opcode> w : (Ljava/lang/Exception;JJ)Ljava/lang/Exception;
/*    */     //   420: athrow
/*    */     //   421: new java/io/EOFException
/*    */     //   424: dup
/*    */     //   425: invokespecial <init> : ()V
/*    */     //   428: athrow
/*    */     //   429: ldc2_w 2964636198479410809
/*    */     //   432: lload #7
/*    */     //   434: <illegal opcode> w : (Ljava/lang/Exception;JJ)Ljava/lang/Exception;
/*    */     //   439: athrow
/*    */     //   440: lload_3
/*    */     //   441: lload #26
/*    */     //   443: lsub
/*    */     //   444: lstore_3
/*    */     //   445: lconst_0
/*    */     //   446: lstore #28
/*    */     //   448: aload_0
/*    */     //   449: getfield f : Lme/konsolas/aac/cQ;
/*    */     //   452: dup
/*    */     //   453: astore #30
/*    */     //   455: monitorenter
/*    */     //   456: aload_0
/*    */     //   457: getfield e : Z
/*    */     //   460: aload #23
/*    */     //   462: lload #5
/*    */     //   464: lconst_0
/*    */     //   465: lcmp
/*    */     //   466: iflt -> 532
/*    */     //   469: ifnull -> 530
/*    */     //   472: ifeq -> 507
/*    */     //   475: aload_0
/*    */     //   476: getfield d : Lme/konsolas/aac/fw;
/*    */     //   479: invokevirtual f : ()J
/*    */     //   482: lstore #28
/*    */     //   484: aload_0
/*    */     //   485: getfield d : Lme/konsolas/aac/fw;
/*    */     //   488: iload #20
/*    */     //   490: i2c
/*    */     //   491: iload #21
/*    */     //   493: iload #22
/*    */     //   495: invokevirtual a : (CII)V
/*    */     //   498: iload_2
/*    */     //   499: iflt -> 623
/*    */     //   502: aload #23
/*    */     //   504: ifnonnull -> 620
/*    */     //   507: aload_0
/*    */     //   508: getfield c : Lme/konsolas/aac/fw;
/*    */     //   511: invokevirtual f : ()J
/*    */     //   514: lconst_0
/*    */     //   515: lcmp
/*    */     //   516: goto -> 530
/*    */     //   519: ldc2_w 2964636198479410809
/*    */     //   522: lload #7
/*    */     //   524: <illegal opcode> w : (Ljava/lang/Exception;JJ)Ljava/lang/Exception;
/*    */     //   529: athrow
/*    */     //   530: aload #23
/*    */     //   532: ifnull -> 553
/*    */     //   535: ifne -> 556
/*    */     //   538: goto -> 552
/*    */     //   541: ldc2_w 2964636198479410809
/*    */     //   544: lload #7
/*    */     //   546: <illegal opcode> w : (Ljava/lang/Exception;JJ)Ljava/lang/Exception;
/*    */     //   551: athrow
/*    */     //   552: iconst_1
/*    */     //   553: goto -> 557
/*    */     //   556: iconst_0
/*    */     //   557: istore #31
/*    */     //   559: aload_0
/*    */     //   560: getfield c : Lme/konsolas/aac/fw;
/*    */     //   563: aload_0
/*    */     //   564: getfield d : Lme/konsolas/aac/fw;
/*    */     //   567: lload #18
/*    */     //   569: dup2_x1
/*    */     //   570: pop2
/*    */     //   571: invokevirtual a : (JLme/konsolas/aac/hp;)J
/*    */     //   574: pop2
/*    */     //   575: aload #23
/*    */     //   577: ifnull -> 623
/*    */     //   580: iload #31
/*    */     //   582: ifeq -> 620
/*    */     //   585: goto -> 599
/*    */     //   588: ldc2_w 2964636198479410809
/*    */     //   591: lload #7
/*    */     //   593: <illegal opcode> w : (Ljava/lang/Exception;JJ)Ljava/lang/Exception;
/*    */     //   598: athrow
/*    */     //   599: aload_0
/*    */     //   600: getfield f : Lme/konsolas/aac/cQ;
/*    */     //   603: invokevirtual notifyAll : ()V
/*    */     //   606: goto -> 620
/*    */     //   609: ldc2_w 2964636198479410809
/*    */     //   612: lload #7
/*    */     //   614: <illegal opcode> w : (Ljava/lang/Exception;JJ)Ljava/lang/Exception;
/*    */     //   619: athrow
/*    */     //   620: aload #30
/*    */     //   622: monitorexit
/*    */     //   623: goto -> 634
/*    */     //   626: astore #32
/*    */     //   628: aload #30
/*    */     //   630: monitorexit
/*    */     //   631: aload #32
/*    */     //   633: athrow
/*    */     //   634: lload #5
/*    */     //   636: lconst_0
/*    */     //   637: lcmp
/*    */     //   638: ifle -> 656
/*    */     //   641: lload #28
/*    */     //   643: lconst_0
/*    */     //   644: lcmp
/*    */     //   645: ifle -> 670
/*    */     //   648: aload_0
/*    */     //   649: lload #28
/*    */     //   651: lload #14
/*    */     //   653: invokespecial a : (JJ)V
/*    */     //   656: goto -> 670
/*    */     //   659: ldc2_w 2964636198479410809
/*    */     //   662: lload #7
/*    */     //   664: <illegal opcode> w : (Ljava/lang/Exception;JJ)Ljava/lang/Exception;
/*    */     //   669: athrow
/*    */     //   670: aload #23
/*    */     //   672: ifnonnull -> 205
/*    */     //   675: lload #5
/*    */     //   677: lconst_0
/*    */     //   678: lcmp
/*    */     //   679: ifle -> 211
/*    */     //   682: return
/*    */     // Line number table:
/*    */     //   Java source line number -> byte code offset
/*    */     //   #13	-> 118
/*    */     //   #53	-> 205
/*    */     //   #17	-> 211
/*    */     //   #26	-> 219
/*    */     //   #52	-> 225
/*    */     //   #41	-> 268
/*    */     //   #8	-> 282
/*    */     //   #81	-> 310
/*    */     //   #12	-> 319
/*    */     //   #44	-> 334
/*    */     //   #75	-> 346
/*    */     //   #48	-> 351
/*    */     //   #2	-> 360
/*    */     //   #5	-> 372
/*    */     //   #83	-> 389
/*    */     //   #19	-> 440
/*    */     //   #68	-> 445
/*    */     //   #20	-> 448
/*    */     //   #14	-> 456
/*    */     //   #51	-> 475
/*    */     //   #3	-> 484
/*    */     //   #39	-> 507
/*    */     //   #64	-> 559
/*    */     //   #28	-> 575
/*    */     //   #77	-> 599
/*    */     //   #23	-> 620
/*    */     //   #78	-> 634
/*    */     //   #69	-> 648
/*    */     //   #50	-> 670
/*    */     //   #27	-> 675
/*    */     // Exception table:
/*    */     //   from	to	target	type
/*    */     //   118	129	132	java/io/IOException
/*    */     //   126	155	158	java/io/IOException
/*    */     //   143	172	175	java/io/IOException
/*    */     //   169	194	194	java/io/IOException
/*    */     //   219	271	274	finally
/*    */     //   225	247	250	java/io/IOException
/*    */     //   274	279	274	finally
/*    */     //   282	296	299	java/io/IOException
/*    */     //   293	335	335	java/io/IOException
/*    */     //   348	361	361	java/io/IOException
/*    */     //   389	407	410	java/io/IOException
/*    */     //   403	429	429	java/io/IOException
/*    */     //   456	623	626	finally
/*    */     //   484	516	519	java/io/IOException
/*    */     //   530	538	541	java/io/IOException
/*    */     //   559	585	588	java/io/IOException
/*    */     //   580	606	609	java/io/IOException
/*    */     //   626	631	626	finally
/*    */     //   634	656	659	java/io/IOException
/*    */   }
/*    */   
/*    */   static fw b(jq paramjq) {
/* 16 */     return paramjq.c;
/*    */   }
/*    */ 
/*    */ 
/*    */ 
/*    */ 
/*    */ 
/*    */ 
/*    */ 
/*    */ 
/*    */   
/*    */   static {
/*    */     long l;
/*    */     byte b1;
/* 30 */     for (i = nc.a(-7309463733829798996L, 8084574759205939148L, MethodHandles.lookup().lookupClass()).a(31243570840351L), l = new HashMap<>(13), l = i ^ 0x59733CB17A5EL, "짃弼躔은舳畭?먹줷䪩꫾툵怛굡䘮ሞƝ运㦝".toCharArray()[15] = (char)("짃弼躔은舳畭?먹줷䪩꫾툵怛굡䘮ሞƝ运㦝".toCharArray()[15] ^ 0x7E4D), "?ས?玠".toCharArray()[0] = (char)("?ས?玠".toCharArray()[0] ^ 0x6536), (new byte[8])[0] = (byte)(int)(l >>> 56L), b1 = 1; b1 < 8; ) { (new byte[8])[b1] = (byte)(int)(l << b1 * 8 >>> 56L); b1++; }  Cipher cipher; (cipher = Cipher.getInstance(dP$dt.X("짃弼躔은舳畭?먹줷䪩꫾툵怛굡䘮ሞƝ运㦝".toCharArray(), (short)4695, true, false))).init(2, SecretKeyFactory.getInstance(dP$dt.X("?ས?玠".toCharArray(), (short)16692, true, true)).generateSecret(new DESKeySpec(new byte[8])), new IvParameterSpec(new byte[8])); String[] arrayOfString = new String[2]; boolean bool = false; "갸賐厥ᙸ૝â샰햛о봭䩩혩ඳ附䁙꘎䫡堧쾠ࠖ瓇᦯ຍ搖㯘态ፒ冸셚呕姒᠝↕ᤇ㴢〛᫭ᬣޅᙅ﵀汇詼牶滱蓅陃ᶀ⨝㓒黁몣戾笑".toCharArray()[41] = (char)("갸賐厥ᙸ૝â샰햛о봭䩩혩ඳ附䁙꘎䫡堧쾠ࠖ瓇᦯ຍ搖㯘态ፒ冸셚呕姒᠝↕ᤇ㴢〛᫭ᬣޅᙅ﵀汇詼牶滱蓅陃ᶀ⨝㓒黁몣戾笑".toCharArray()[41] ^ 0x3904); String str; int i = (str = dP$dt.X("갸賐厥ᙸ૝â샰햛о봭䩩혩ඳ附䁙꘎䫡堧쾠ࠖ瓇᦯ຍ搖㯘态ፒ冸셚呕姒᠝↕ᤇ㴢〛᫭ᬣޅᙅ﵀汇詼牶滱蓅陃ᶀ⨝㓒黁몣戾笑".toCharArray(), (short)32293, false, false)).length(); byte b2 = 32; byte b = -1; while (true); throw a(-1);
/*    */   }
/*    */   
/*    */   static J a(jq paramjq, J paramJ) {
/* 34 */     return paramjq.g = paramJ;
/*    */   }
/*    */ 
/*    */ 
/*    */ 
/*    */ 
/*    */ 
/*    */ 
/*    */ 
/*    */ 
/*    */   
/*    */   public long a(long paramLong1, fw paramfw, long paramLong2) {
/*    */     // Byte code:
/*    */     //   0: lload_1
/*    */     //   1: dup2
/*    */     //   2: ldc2_w 968090230974
/*    */     //   5: lxor
/*    */     //   6: lstore #6
/*    */     //   8: dup2
/*    */     //   9: ldc2_w 75042098462217
/*    */     //   12: lxor
/*    */     //   13: lstore #8
/*    */     //   15: dup2
/*    */     //   16: ldc2_w 71663743419272
/*    */     //   19: lxor
/*    */     //   20: lstore #10
/*    */     //   22: dup2
/*    */     //   23: ldc2_w 43480790717734
/*    */     //   26: lxor
/*    */     //   27: lstore #12
/*    */     //   29: dup2
/*    */     //   30: ldc2_w 0
/*    */     //   33: lxor
/*    */     //   34: lstore #14
/*    */     //   36: dup2
/*    */     //   37: ldc2_w 114002353787231
/*    */     //   40: lxor
/*    */     //   41: dup2
/*    */     //   42: bipush #32
/*    */     //   44: lushr
/*    */     //   45: l2i
/*    */     //   46: istore #16
/*    */     //   48: dup2
/*    */     //   49: bipush #32
/*    */     //   51: lshl
/*    */     //   52: bipush #48
/*    */     //   54: lushr
/*    */     //   55: l2i
/*    */     //   56: istore #17
/*    */     //   58: dup2
/*    */     //   59: bipush #48
/*    */     //   61: lshl
/*    */     //   62: bipush #48
/*    */     //   64: lushr
/*    */     //   65: l2i
/*    */     //   66: istore #18
/*    */     //   68: pop2
/*    */     //   69: dup2
/*    */     //   70: ldc2_w 36173488155477
/*    */     //   73: lxor
/*    */     //   74: lstore #19
/*    */     //   76: pop2
/*    */     //   77: ldc2_w -8543312552004129418
/*    */     //   80: lload_1
/*    */     //   81: <illegal opcode> w : (JJ)[Lme/konsolas/aac/aN;
/*    */     //   86: astore #21
/*    */     //   88: lload #4
/*    */     //   90: aload #21
/*    */     //   92: ifnull -> 165
/*    */     //   95: lconst_0
/*    */     //   96: lcmp
/*    */     //   97: ifge -> 162
/*    */     //   100: goto -> 113
/*    */     //   103: ldc2_w -8643878663371909289
/*    */     //   106: lload_1
/*    */     //   107: <illegal opcode> w : (Ljava/lang/Exception;JJ)Ljava/lang/Exception;
/*    */     //   112: athrow
/*    */     //   113: new java/lang/IllegalArgumentException
/*    */     //   116: dup
/*    */     //   117: new java/lang/StringBuilder
/*    */     //   120: dup
/*    */     //   121: invokespecial <init> : ()V
/*    */     //   124: sipush #27693
/*    */     //   127: ldc2_w 7109835190798003022
/*    */     //   130: lload_1
/*    */     //   131: lxor
/*    */     //   132: <illegal opcode> y : (IJ)Ljava/lang/String;
/*    */     //   137: invokevirtual append : (Ljava/lang/String;)Ljava/lang/StringBuilder;
/*    */     //   140: lload #4
/*    */     //   142: invokevirtual append : (J)Ljava/lang/StringBuilder;
/*    */     //   145: invokevirtual toString : ()Ljava/lang/String;
/*    */     //   148: invokespecial <init> : (Ljava/lang/String;)V
/*    */     //   151: athrow
/*    */     //   152: ldc2_w -8643878663371909289
/*    */     //   155: lload_1
/*    */     //   156: <illegal opcode> w : (Ljava/lang/Exception;JJ)Ljava/lang/Exception;
/*    */     //   161: athrow
/*    */     //   162: ldc2_w -1
/*    */     //   165: lstore #22
/*    */     //   167: aconst_null
/*    */     //   168: astore #24
/*    */     //   170: aload_0
/*    */     //   171: getfield f : Lme/konsolas/aac/cQ;
/*    */     //   174: dup
/*    */     //   175: astore #25
/*    */     //   177: monitorenter
/*    */     //   178: aload_0
/*    */     //   179: getfield f : Lme/konsolas/aac/cQ;
/*    */     //   182: getfield d : Lme/konsolas/aac/ld;
/*    */     //   185: lload #10
/*    */     //   187: invokevirtual b : (J)V
/*    */     //   190: aload_0
/*    */     //   191: getfield f : Lme/konsolas/aac/cQ;
/*    */     //   194: lload_1
/*    */     //   195: lconst_0
/*    */     //   196: lcmp
/*    */     //   197: iflt -> 210
/*    */     //   200: getfield k : Lme/konsolas/aac/eb;
/*    */     //   203: ifnull -> 278
/*    */     //   206: aload_0
/*    */     //   207: getfield f : Lme/konsolas/aac/cQ;
/*    */     //   210: getfield m : Ljava/io/IOException;
/*    */     //   213: aload #21
/*    */     //   215: ifnull -> 257
/*    */     //   218: ifnull -> 260
/*    */     //   221: goto -> 234
/*    */     //   224: ldc2_w -8643878663371909289
/*    */     //   227: lload_1
/*    */     //   228: <illegal opcode> w : (Ljava/lang/Exception;JJ)Ljava/lang/Exception;
/*    */     //   233: athrow
/*    */     //   234: aload_0
/*    */     //   235: getfield f : Lme/konsolas/aac/cQ;
/*    */     //   238: getfield m : Ljava/io/IOException;
/*    */     //   241: lload_1
/*    */     //   242: lconst_0
/*    */     //   243: lcmp
/*    */     //   244: ifgt -> 257
/*    */     //   247: ldc2_w -8643878663371909289
/*    */     //   250: lload_1
/*    */     //   251: <illegal opcode> w : (Ljava/lang/Exception;JJ)Ljava/lang/Exception;
/*    */     //   256: athrow
/*    */     //   257: goto -> 276
/*    */     //   260: new me/konsolas/aac/fF
/*    */     //   263: dup
/*    */     //   264: aload_0
/*    */     //   265: getfield f : Lme/konsolas/aac/cQ;
/*    */     //   268: getfield k : Lme/konsolas/aac/eb;
/*    */     //   271: lload #19
/*    */     //   273: invokespecial <init> : (Lme/konsolas/aac/eb;J)V
/*    */     //   276: astore #24
/*    */     //   278: aload_0
/*    */     //   279: getfield e : Z
/*    */     //   282: aload #21
/*    */     //   284: lload_1
/*    */     //   285: lconst_0
/*    */     //   286: lcmp
/*    */     //   287: iflt -> 357
/*    */     //   290: ifnull -> 349
/*    */     //   293: ifeq -> 340
/*    */     //   296: goto -> 309
/*    */     //   299: ldc2_w -8643878663371909289
/*    */     //   302: lload_1
/*    */     //   303: <illegal opcode> w : (Ljava/lang/Exception;JJ)Ljava/lang/Exception;
/*    */     //   308: athrow
/*    */     //   309: new java/io/IOException
/*    */     //   312: dup
/*    */     //   313: sipush #30576
/*    */     //   316: ldc2_w 6054635299931762706
/*    */     //   319: lload_1
/*    */     //   320: lxor
/*    */     //   321: <illegal opcode> y : (IJ)Ljava/lang/String;
/*    */     //   326: invokespecial <init> : (Ljava/lang/String;)V
/*    */     //   329: athrow
/*    */     //   330: ldc2_w -8643878663371909289
/*    */     //   333: lload_1
/*    */     //   334: <illegal opcode> w : (Ljava/lang/Exception;JJ)Ljava/lang/Exception;
/*    */     //   339: athrow
/*    */     //   340: aload_0
/*    */     //   341: getfield c : Lme/konsolas/aac/fw;
/*    */     //   344: invokevirtual f : ()J
/*    */     //   347: lconst_0
/*    */     //   348: lcmp
/*    */     //   349: lload_1
/*    */     //   350: lconst_0
/*    */     //   351: lcmp
/*    */     //   352: ifle -> 598
/*    */     //   355: aload #21
/*    */     //   357: ifnull -> 598
/*    */     //   360: ifle -> 563
/*    */     //   363: goto -> 376
/*    */     //   366: ldc2_w -8643878663371909289
/*    */     //   369: lload_1
/*    */     //   370: <illegal opcode> w : (Ljava/lang/Exception;JJ)Ljava/lang/Exception;
/*    */     //   375: athrow
/*    */     //   376: aload_0
/*    */     //   377: getfield c : Lme/konsolas/aac/fw;
/*    */     //   380: lload #14
/*    */     //   382: aload_3
/*    */     //   383: lload #4
/*    */     //   385: aload_0
/*    */     //   386: getfield c : Lme/konsolas/aac/fw;
/*    */     //   389: invokevirtual f : ()J
/*    */     //   392: invokestatic min : (JJ)J
/*    */     //   395: invokevirtual a : (JLme/konsolas/aac/fw;J)J
/*    */     //   398: lstore #22
/*    */     //   400: aload_0
/*    */     //   401: getfield f : Lme/konsolas/aac/cQ;
/*    */     //   404: dup
/*    */     //   405: getfield e : J
/*    */     //   408: lload #22
/*    */     //   410: ladd
/*    */     //   411: putfield e : J
/*    */     //   414: aload #21
/*    */     //   416: ifnull -> 664
/*    */     //   419: aload #24
/*    */     //   421: ifnonnull -> 646
/*    */     //   424: goto -> 437
/*    */     //   427: ldc2_w -8643878663371909289
/*    */     //   430: lload_1
/*    */     //   431: <illegal opcode> w : (Ljava/lang/Exception;JJ)Ljava/lang/Exception;
/*    */     //   436: athrow
/*    */     //   437: lload_1
/*    */     //   438: lconst_0
/*    */     //   439: lcmp
/*    */     //   440: ifle -> 664
/*    */     //   443: aload_0
/*    */     //   444: getfield f : Lme/konsolas/aac/cQ;
/*    */     //   447: aload #21
/*    */     //   449: ifnull -> 656
/*    */     //   452: goto -> 465
/*    */     //   455: ldc2_w -8643878663371909289
/*    */     //   458: lload_1
/*    */     //   459: <illegal opcode> w : (Ljava/lang/Exception;JJ)Ljava/lang/Exception;
/*    */     //   464: athrow
/*    */     //   465: getfield e : J
/*    */     //   468: aload_0
/*    */     //   469: getfield f : Lme/konsolas/aac/cQ;
/*    */     //   472: getfield b : Lme/konsolas/aac/cZ;
/*    */     //   475: getfield v : Lme/konsolas/aac/dM;
/*    */     //   478: iload #16
/*    */     //   480: iload #17
/*    */     //   482: i2c
/*    */     //   483: iload #18
/*    */     //   485: i2s
/*    */     //   486: invokevirtual a : (ICS)I
/*    */     //   489: iconst_2
/*    */     //   490: idiv
/*    */     //   491: i2l
/*    */     //   492: lcmp
/*    */     //   493: iflt -> 646
/*    */     //   496: goto -> 509
/*    */     //   499: ldc2_w -8643878663371909289
/*    */     //   502: lload_1
/*    */     //   503: <illegal opcode> w : (Ljava/lang/Exception;JJ)Ljava/lang/Exception;
/*    */     //   508: athrow
/*    */     //   509: aload_0
/*    */     //   510: getfield f : Lme/konsolas/aac/cQ;
/*    */     //   513: getfield b : Lme/konsolas/aac/cZ;
/*    */     //   516: aload_0
/*    */     //   517: getfield f : Lme/konsolas/aac/cQ;
/*    */     //   520: getfield i : I
/*    */     //   523: lload #12
/*    */     //   525: dup2_x1
/*    */     //   526: pop2
/*    */     //   527: aload_0
/*    */     //   528: getfield f : Lme/konsolas/aac/cQ;
/*    */     //   531: getfield e : J
/*    */     //   534: invokevirtual a : (JIJ)V
/*    */     //   537: aload_0
/*    */     //   538: getfield f : Lme/konsolas/aac/cQ;
/*    */     //   541: lconst_0
/*    */     //   542: putfield e : J
/*    */     //   545: aload #21
/*    */     //   547: ifnonnull -> 646
/*    */     //   550: goto -> 563
/*    */     //   553: ldc2_w -8643878663371909289
/*    */     //   556: lload_1
/*    */     //   557: <illegal opcode> w : (Ljava/lang/Exception;JJ)Ljava/lang/Exception;
/*    */     //   562: athrow
/*    */     //   563: aload_0
/*    */     //   564: aload #21
/*    */     //   566: ifnull -> 653
/*    */     //   569: goto -> 582
/*    */     //   572: ldc2_w -8643878663371909289
/*    */     //   575: lload_1
/*    */     //   576: <illegal opcode> w : (Ljava/lang/Exception;JJ)Ljava/lang/Exception;
/*    */     //   581: athrow
/*    */     //   582: getfield h : Z
/*    */     //   585: goto -> 598
/*    */     //   588: ldc2_w -8643878663371909289
/*    */     //   591: lload_1
/*    */     //   592: <illegal opcode> w : (Ljava/lang/Exception;JJ)Ljava/lang/Exception;
/*    */     //   597: athrow
/*    */     //   598: ifne -> 646
/*    */     //   601: aload #24
/*    */     //   603: ifnonnull -> 646
/*    */     //   606: goto -> 619
/*    */     //   609: ldc2_w -8643878663371909289
/*    */     //   612: lload_1
/*    */     //   613: <illegal opcode> w : (Ljava/lang/Exception;JJ)Ljava/lang/Exception;
/*    */     //   618: athrow
/*    */     //   619: aload_0
/*    */     //   620: getfield f : Lme/konsolas/aac/cQ;
/*    */     //   623: invokevirtual b : ()V
/*    */     //   626: aload_0
/*    */     //   627: getfield f : Lme/konsolas/aac/cQ;
/*    */     //   630: getfield d : Lme/konsolas/aac/ld;
/*    */     //   633: lload #6
/*    */     //   635: invokevirtual d : (J)V
/*    */     //   638: aload #25
/*    */     //   640: monitorexit
/*    */     //   641: aload #21
/*    */     //   643: ifnonnull -> 162
/*    */     //   646: lload_1
/*    */     //   647: lconst_0
/*    */     //   648: lcmp
/*    */     //   649: ifle -> 167
/*    */     //   652: aload_0
/*    */     //   653: getfield f : Lme/konsolas/aac/cQ;
/*    */     //   656: getfield d : Lme/konsolas/aac/ld;
/*    */     //   659: lload #6
/*    */     //   661: invokevirtual d : (J)V
/*    */     //   664: goto -> 684
/*    */     //   667: astore #26
/*    */     //   669: aload_0
/*    */     //   670: getfield f : Lme/konsolas/aac/cQ;
/*    */     //   673: getfield d : Lme/konsolas/aac/ld;
/*    */     //   676: lload #6
/*    */     //   678: invokevirtual d : (J)V
/*    */     //   681: aload #26
/*    */     //   683: athrow
/*    */     //   684: aload #25
/*    */     //   686: monitorexit
/*    */     //   687: goto -> 698
/*    */     //   690: astore #27
/*    */     //   692: aload #25
/*    */     //   694: monitorexit
/*    */     //   695: aload #27
/*    */     //   697: athrow
/*    */     //   698: lload #22
/*    */     //   700: aload #21
/*    */     //   702: ifnull -> 748
/*    */     //   705: ldc2_w -1
/*    */     //   708: lcmp
/*    */     //   709: ifeq -> 749
/*    */     //   712: goto -> 725
/*    */     //   715: ldc2_w -8643878663371909289
/*    */     //   718: lload_1
/*    */     //   719: <illegal opcode> w : (Ljava/lang/Exception;JJ)Ljava/lang/Exception;
/*    */     //   724: athrow
/*    */     //   725: aload_0
/*    */     //   726: lload #22
/*    */     //   728: lload #8
/*    */     //   730: invokespecial a : (JJ)V
/*    */     //   733: lload #22
/*    */     //   735: goto -> 748
/*    */     //   738: ldc2_w -8643878663371909289
/*    */     //   741: lload_1
/*    */     //   742: <illegal opcode> w : (Ljava/lang/Exception;JJ)Ljava/lang/Exception;
/*    */     //   747: athrow
/*    */     //   748: lreturn
/*    */     //   749: aload #24
/*    */     //   751: aload #21
/*    */     //   753: ifnull -> 774
/*    */     //   756: ifnull -> 775
/*    */     //   759: goto -> 772
/*    */     //   762: ldc2_w -8643878663371909289
/*    */     //   765: lload_1
/*    */     //   766: <illegal opcode> w : (Ljava/lang/Exception;JJ)Ljava/lang/Exception;
/*    */     //   771: athrow
/*    */     //   772: aload #24
/*    */     //   774: athrow
/*    */     //   775: ldc2_w -1
/*    */     //   778: lreturn
/*    */     // Line number table:
/*    */     //   Java source line number -> byte code offset
/*    */     //   #37	-> 88
/*    */     //   #38	-> 162
/*    */     //   #21	-> 167
/*    */     //   #46	-> 170
/*    */     //   #22	-> 178
/*    */     //   #11	-> 190
/*    */     //   #40	-> 206
/*    */     //   #76	-> 234
/*    */     //   #31	-> 260
/*    */     //   #60	-> 278
/*    */     //   #15	-> 309
/*    */     //   #74	-> 340
/*    */     //   #63	-> 376
/*    */     //   #80	-> 400
/*    */     //   #4	-> 414
/*    */     //   #36	-> 478
/*    */     //   #70	-> 509
/*    */     //   #18	-> 537
/*    */     //   #6	-> 563
/*    */     //   #7	-> 619
/*    */     //   #32	-> 626
/*    */     //   #72	-> 664
/*    */     //   #49	-> 667
/*    */     //   #35	-> 684
/*    */     //   #24	-> 698
/*    */     //   #25	-> 725
/*    */     //   #58	-> 733
/*    */     //   #33	-> 749
/*    */     //   #10	-> 772
/*    */     //   #62	-> 775
/*    */     // Exception table:
/*    */     //   from	to	target	type
/*    */     //   88	100	103	java/io/IOException
/*    */     //   95	152	152	java/io/IOException
/*    */     //   178	641	690	finally
/*    */     //   190	626	667	finally
/*    */     //   206	221	224	java/io/IOException
/*    */     //   218	241	247	java/io/IOException
/*    */     //   278	296	299	java/io/IOException
/*    */     //   293	330	330	java/io/IOException
/*    */     //   349	363	366	java/io/IOException
/*    */     //   400	424	427	java/io/IOException
/*    */     //   419	452	455	java/io/IOException
/*    */     //   437	496	499	java/io/IOException
/*    */     //   465	550	553	java/io/IOException
/*    */     //   509	569	572	java/io/IOException
/*    */     //   563	585	588	java/io/IOException
/*    */     //   598	606	609	java/io/IOException
/*    */     //   646	687	690	finally
/*    */     //   667	669	667	finally
/*    */     //   690	695	690	finally
/*    */     //   698	712	715	java/io/IOException
/*    */     //   705	735	738	java/io/IOException
/*    */     //   749	759	762	java/io/IOException
/*    */   }
/*    */ 
/*    */ 
/*    */ 
/*    */ 
/*    */ 
/*    */ 
/*    */ 
/*    */   
/*    */   jq(cQ paramcQ, long paramLong) {
/* 57 */     this.d = new fw();
/*    */ 
/*    */ 
/*    */ 
/*    */ 
/*    */ 
/*    */ 
/*    */ 
/*    */ 
/*    */ 
/*    */ 
/*    */ 
/*    */ 
/*    */ 
/*    */ 
/*    */     
/* 73 */     this.c = new fw();
/*    */     this.a = paramLong;
/*    */   }
/*    */   private void a(long paramLong1, long paramLong2) {
/*    */     // Byte code:
/*    */     //   0: getstatic me/konsolas/aac/jq.i : J
/*    */     //   3: lload_3
/*    */     //   4: lxor
/*    */     //   5: lstore_3
/*    */     //   6: lload_3
/*    */     //   7: dup2
/*    */     //   8: ldc2_w 133303406072902
/*    */     //   11: lxor
/*    */     //   12: lstore #5
/*    */     //   14: pop2
/*    */     //   15: ldc2_w -7616587556767567286
/*    */     //   18: lload_3
/*    */     //   19: <illegal opcode> w : (JJ)[Lme/konsolas/aac/aN;
/*    */     //   24: astore #7
/*    */     //   26: aload #7
/*    */     //   28: ifnull -> 128
/*    */     //   31: getstatic me/konsolas/aac/jq.b : Z
/*    */     //   34: ifne -> 115
/*    */     //   37: goto -> 50
/*    */     //   40: ldc2_w -7550643628281001877
/*    */     //   43: lload_3
/*    */     //   44: <illegal opcode> w : (Ljava/lang/Exception;JJ)Ljava/lang/Exception;
/*    */     //   49: athrow
/*    */     //   50: lload_3
/*    */     //   51: lconst_0
/*    */     //   52: lcmp
/*    */     //   53: ifle -> 128
/*    */     //   56: aload_0
/*    */     //   57: getfield f : Lme/konsolas/aac/cQ;
/*    */     //   60: aload #7
/*    */     //   62: ifnull -> 119
/*    */     //   65: goto -> 78
/*    */     //   68: ldc2_w -7550643628281001877
/*    */     //   71: lload_3
/*    */     //   72: <illegal opcode> w : (Ljava/lang/Exception;JJ)Ljava/lang/Exception;
/*    */     //   77: athrow
/*    */     //   78: invokestatic holdsLock : (Ljava/lang/Object;)Z
/*    */     //   81: ifeq -> 115
/*    */     //   84: goto -> 97
/*    */     //   87: ldc2_w -7550643628281001877
/*    */     //   90: lload_3
/*    */     //   91: <illegal opcode> w : (Ljava/lang/Exception;JJ)Ljava/lang/Exception;
/*    */     //   96: athrow
/*    */     //   97: new java/lang/AssertionError
/*    */     //   100: dup
/*    */     //   101: invokespecial <init> : ()V
/*    */     //   104: athrow
/*    */     //   105: ldc2_w -7550643628281001877
/*    */     //   108: lload_3
/*    */     //   109: <illegal opcode> w : (Ljava/lang/Exception;JJ)Ljava/lang/Exception;
/*    */     //   114: athrow
/*    */     //   115: aload_0
/*    */     //   116: getfield f : Lme/konsolas/aac/cQ;
/*    */     //   119: getfield b : Lme/konsolas/aac/cZ;
/*    */     //   122: lload_1
/*    */     //   123: lload #5
/*    */     //   125: invokevirtual a : (JJ)V
/*    */     //   128: return
/*    */     // Line number table:
/*    */     //   Java source line number -> byte code offset
/*    */     //   #54	-> 26
/*    */     //   #45	-> 115
/*    */     //   #29	-> 128
/*    */     // Exception table:
/*    */     //   from	to	target	type
/*    */     //   26	37	40	java/lang/IllegalArgumentException
/*    */     //   31	65	68	java/lang/IllegalArgumentException
/*    */     //   50	84	87	java/lang/IllegalArgumentException
/*    */     //   78	105	105	java/lang/IllegalArgumentException
/*    */   }
/*    */   public li a() {
/*    */     return this.f.d;
/*    */   }
/*    */   
/*    */   static J a(jq paramjq) {
/* 84 */     return paramjq.g;
/*    */   }
/*    */   
/*    */   private static Exception a(Exception paramException) {
/*    */     return paramException;
/*    */   }
/*    */   
/*    */   private static String a(byte[] paramArrayOfbyte) {
/*    */     byte b1 = 0;
/*    */     int i;
/*    */     char[] arrayOfChar = new char[i = paramArrayOfbyte.length];
/*    */     for (byte b2 = 0; b2 < i; b2++) {
/*    */       int j;
/*    */       if ((j = 0xFF & paramArrayOfbyte[b2]) < 192) {
/*    */         arrayOfChar[b1++] = (char)j;
/*    */       } else if (j < 224) {
/*    */         char c = (char)((char)(j & 0x1F) << 6);
/*    */         j = paramArrayOfbyte[++b2];
/*    */         c = (char)(c | (char)(j & 0x3F));
/*    */         arrayOfChar[b1++] = c;
/*    */       } else if (b2 < i - 2) {
/*    */         char c = (char)((char)(j & 0xF) << 12);
/*    */         j = paramArrayOfbyte[++b2];
/*    */         c = (char)(c | (char)(j & 0x3F) << 6);
/*    */         j = paramArrayOfbyte[++b2];
/*    */         c = (char)(c | (char)(j & 0x3F));
/*    */         arrayOfChar[b1++] = c;
/*    */       } 
/*    */     } 
/*    */     return new String(arrayOfChar, 0, b1);
/*    */   }
/*    */   
/*    */   private static String a(int paramInt, long paramLong) {
/*    */     int i = paramInt ^ (int)(paramLong & 0x7FFFL) ^ 0x4FAB;
/*    */     if (k[i] == null) {
/*    */       Object[] arrayOfObject;
/*    */       try {
/*    */         Long long_ = Long.valueOf(Thread.currentThread().getId());
/*    */         arrayOfObject = (Object[])l.get(long_);
/*    */         if (arrayOfObject == null) {
/*    */           arrayOfObject = new Object[3];
/*    */           "쬀⿨列꟨ꊝ㠽䅮ꏦ㠇彫᪰债ꩧᕬ䴿礙ᛁ汞슯㊒১".toCharArray()[19] = (char)("쬀⿨列꟨ꊝ㠽䅮ꏦ㠇彫᪰债ꩧᕬ䴿礙ᛁ汞슯㊒১".toCharArray()[19] ^ 0x403C);
/*    */           arrayOfObject[0] = Cipher.getInstance(fW$gy.A("쬀⿨列꟨ꊝ㠽䅮ꏦ㠇彫᪰债ꩧᕬ䴿礙ᛁ汞슯㊒১".toCharArray(), (short)4527, false, 2));
/*    */           "㺢찮凓₍".toCharArray()[0] = (char)("㺢찮凓₍".toCharArray()[0] ^ 0xE84);
/*    */           arrayOfObject[1] = SecretKeyFactory.getInstance(fW$gy.A("㺢찮凓₍".toCharArray(), (short)22816, true, 2));
/*    */           arrayOfObject[2] = new IvParameterSpec(new byte[8]);
/*    */           l.put(long_, arrayOfObject);
/*    */         } 
/*    */       } catch (Exception exception) {
/*    */         "窅붔?䬷ꉘᡍớ粂黵⬢쒢«뙩ゲ쳦봟㻿紛".toCharArray()[11] = (char)("窅붔?䬷ꉘᡍớ粂黵⬢쒢«뙩ゲ쳦봟㻿紛".toCharArray()[11] ^ 0xD79);
/*    */         throw new RuntimeException(fW$gy.A("窅붔?䬷ꉘᡍớ粂黵⬢쒢«뙩ゲ쳦봟㻿紛".toCharArray(), (short)2114, true, 1), exception);
/*    */       } 
/*    */       byte[] arrayOfByte1 = new byte[8];
/*    */       arrayOfByte1[0] = (byte)(int)(paramLong >>> 56L);
/*    */       for (byte b = 1; b < 8; b++)
/*    */         arrayOfByte1[b] = (byte)(int)(paramLong << b * 8 >>> 56L); 
/*    */       DESKeySpec dESKeySpec = new DESKeySpec(arrayOfByte1);
/*    */       SecretKey secretKey = ((SecretKeyFactory)arrayOfObject[1]).generateSecret(dESKeySpec);
/*    */       ((Cipher)arrayOfObject[0]).init(2, secretKey, (IvParameterSpec)arrayOfObject[2]);
/*    */       "雬鈘홆罛㳧戉溠怯䞆ڱ".toCharArray()[7] = (char)("雬鈘홆罛㳧戉溠怯䞆ڱ".toCharArray()[7] ^ 0x4C58);
/*    */       byte[] arrayOfByte2 = j[i].getBytes(fW$gy.A("雬鈘홆罛㳧戉溠怯䞆ڱ".toCharArray(), (short)15514, false, 2));
/*    */       k[i] = a(((Cipher)arrayOfObject[0]).doFinal(arrayOfByte2));
/*    */     } 
/*    */     return k[i];
/*    */   }
/*    */   
/*    */   private static Object a(MethodHandles.Lookup paramLookup, MutableCallSite paramMutableCallSite, String paramString, Object[] paramArrayOfObject) {
/*    */     int i = ((Integer)paramArrayOfObject[0]).intValue();
/*    */     long l = ((Long)paramArrayOfObject[1]).longValue();
/*    */     String str = a(i, l);
/*    */     MethodHandle methodHandle = MethodHandles.constant(String.class, str);
/*    */     paramMutableCallSite.setTarget(MethodHandles.dropArguments(methodHandle, 0, new Class[] { int.class, long.class }));
/*    */     return str;
/*    */   }
/*    */   
/*    */   private static CallSite a(MethodHandles.Lookup paramLookup, String paramString, MethodType paramMethodType) {
/*    */     // Byte code:
/*    */     //   0: new java/lang/invoke/MutableCallSite
/*    */     //   3: dup
/*    */     //   4: aload_2
/*    */     //   5: invokespecial <init> : (Ljava/lang/invoke/MethodType;)V
/*    */     //   8: astore_3
/*    */     //   9: aload_3
/*    */     //   10: ldc_w
/*    */     //   13: ldc_w [Ljava/lang/Object;
/*    */     //   16: aload_2
/*    */     //   17: invokevirtual parameterCount : ()I
/*    */     //   20: invokevirtual asCollector : (Ljava/lang/Class;I)Ljava/lang/invoke/MethodHandle;
/*    */     //   23: iconst_0
/*    */     //   24: iconst_3
/*    */     //   25: anewarray java/lang/Object
/*    */     //   28: dup
/*    */     //   29: iconst_0
/*    */     //   30: aload_0
/*    */     //   31: aastore
/*    */     //   32: dup
/*    */     //   33: iconst_1
/*    */     //   34: aload_3
/*    */     //   35: aastore
/*    */     //   36: dup
/*    */     //   37: iconst_2
/*    */     //   38: aload_1
/*    */     //   39: aastore
/*    */     //   40: invokestatic insertArguments : (Ljava/lang/invoke/MethodHandle;I[Ljava/lang/Object;)Ljava/lang/invoke/MethodHandle;
/*    */     //   43: aload_2
/*    */     //   44: invokestatic explicitCastArguments : (Ljava/lang/invoke/MethodHandle;Ljava/lang/invoke/MethodType;)Ljava/lang/invoke/MethodHandle;
/*    */     //   47: invokevirtual setTarget : (Ljava/lang/invoke/MethodHandle;)V
/*    */     //   50: goto -> 171
/*    */     //   53: astore #4
/*    */     //   55: new java/lang/RuntimeException
/*    */     //   58: dup
/*    */     //   59: new java/lang/StringBuilder
/*    */     //   62: dup
/*    */     //   63: invokespecial <init> : ()V
/*    */     //   66: ldc_w 'ꊶ낪쟔턋㋴蔿肋瓍䡍з盒笻ᑍ䂔֨鎵榇'
/*    */     //   69: invokevirtual toCharArray : ()[C
/*    */     //   72: dup
/*    */     //   73: dup
/*    */     //   74: bipush #11
/*    */     //   76: dup_x1
/*    */     //   77: caload
/*    */     //   78: sipush #1842
/*    */     //   81: ixor
/*    */     //   82: i2c
/*    */     //   83: castore
/*    */     //   84: sipush #9941
/*    */     //   87: iconst_0
/*    */     //   88: iconst_0
/*    */     //   89: invokestatic U : (Ljava/lang/Object;SZZ)Ljava/lang/String;
/*    */     //   92: invokevirtual append : (Ljava/lang/String;)Ljava/lang/StringBuilder;
/*    */     //   95: ldc_w '늹卆痖'
/*    */     //   98: invokevirtual toCharArray : ()[C
/*    */     //   101: dup
/*    */     //   102: dup
/*    */     //   103: iconst_0
/*    */     //   104: dup_x1
/*    */     //   105: caload
/*    */     //   106: sipush #9214
/*    */     //   109: ixor
/*    */     //   110: i2c
/*    */     //   111: castore
/*    */     //   112: sipush #16308
/*    */     //   115: iconst_1
/*    */     //   116: iconst_0
/*    */     //   117: invokestatic U : (Ljava/lang/Object;SZZ)Ljava/lang/String;
/*    */     //   120: invokevirtual append : (Ljava/lang/String;)Ljava/lang/StringBuilder;
/*    */     //   123: aload_1
/*    */     //   124: invokevirtual append : (Ljava/lang/String;)Ljava/lang/StringBuilder;
/*    */     //   127: ldc_w '㮟꾳᷈ㅨ'
/*    */     //   130: invokevirtual toCharArray : ()[C
/*    */     //   133: dup
/*    */     //   134: dup
/*    */     //   135: iconst_2
/*    */     //   136: dup_x1
/*    */     //   137: caload
/*    */     //   138: sipush #31472
/*    */     //   141: ixor
/*    */     //   142: i2c
/*    */     //   143: castore
/*    */     //   144: sipush #9396
/*    */     //   147: iconst_1
/*    */     //   148: iconst_1
/*    */     //   149: invokestatic U : (Ljava/lang/Object;SZZ)Ljava/lang/String;
/*    */     //   152: invokevirtual append : (Ljava/lang/String;)Ljava/lang/StringBuilder;
/*    */     //   155: aload_2
/*    */     //   156: invokevirtual toString : ()Ljava/lang/String;
/*    */     //   159: invokevirtual append : (Ljava/lang/String;)Ljava/lang/StringBuilder;
/*    */     //   162: invokevirtual toString : ()Ljava/lang/String;
/*    */     //   165: aload #4
/*    */     //   167: invokespecial <init> : (Ljava/lang/String;Ljava/lang/Throwable;)V
/*    */     //   170: athrow
/*    */     //   171: aload_3
/*    */     //   172: areturn
/*    */     // Exception table:
/*    */     //   from	to	target	type
/*    */     //   9	50	53	java/lang/Exception
/*    */   } }


/* Location:              C:\Users\BukkitBypass\Desktop\MatrixAC\AAC\AAC-spigot-5.2.0.jar!\me\konsolas\aac\jq.class
 * Java compiler version: 8 (52.0)
 * JD-Core Version:       1.1.3
 */