/* 1 */ package me.konsolas.aac;public interface k4 { static { long l; byte b1; for (b = nc.a(-4989704730110602852L, -7238953502162363244L, MethodHandles.lookup().lookupClass()).a(79701840866131L), e = new HashMap<>(13), l = b ^ 0x51D6630419E1L, "壬兣绐窔ﾮ즼훑쑎酒੍썉௒Ⓖ䅻䪀迠ꝯ˹உੳ".toCharArray()[14] = (char)("壬兣绐窔ﾮ즼훑쑎酒੍썉௒Ⓖ䅻䪀迠ꝯ˹உੳ".toCharArray()[14] ^ 0x1F70), "㎻柋㎆ሴ".toCharArray()[0] = (char)("㎻柋㎆ሴ".toCharArray()[0] ^ 0x48D3), (new byte[8])[0] = (byte)(int)(l >>> 56L), b1 = 1; b1 < 8; ) { (new byte[8])[b1] = (byte)(int)(l << b1 * 8 >>> 56L); b1++; }  Cipher cipher; (cipher = Cipher.getInstance(a0$cc.G("壬兣绐窔ﾮ즼훑쑎酒੍썉௒Ⓖ䅻䪀迠ꝯ˹உੳ".toCharArray(), (short)24646, false, (byte)3))).init(2, SecretKeyFactory.getInstance(a0$cc.G("㎻柋㎆ሴ".toCharArray(), (short)26174, true, (byte)3)).generateSecret(new DESKeySpec(new byte[8])), new IvParameterSpec(new byte[8])); String[] arrayOfString = new String[2]; boolean bool = false; "稄?툝⫵嗮랢⏧榗䜨⚟倝庯륦篚齄䏯껑剂뱪삌繛硣烳᢬堺湻㑡?瑙䁹Ꮦ䔶⤈ꒅ㤞ￊ낕颐簆쪿쉿壡㽫즚즂ㆡ웜ꆉꝚ퇋⋍长㩆账炽瞰ਝഄ镮Ӝ꺳铏잠贘枨팣쐜ꦃⷆ䏛郷㯲ꔘⶒ냧쎸?䳰朗䧝럟㵜㉜偽ὁ졌摔ﾓꗧ?㤒芻랄꡵쭁翇蹾狈줳ꎫᄶ龈?纖ꈆꍍ菕᭱?恟⼂".toCharArray()[86] = (char)("稄?툝⫵嗮랢⏧榗䜨⚟倝庯륦篚齄䏯껑剂뱪삌繛硣烳᢬堺湻㑡?瑙䁹Ꮦ䔶⤈ꒅ㤞ￊ낕颐簆쪿쉿壡㽫즚즂ㆡ웜ꆉꝚ퇋⋍长㩆账炽瞰ਝഄ镮Ӝ꺳铏잠贘枨팣쐜ꦃⷆ䏛郷㯲ꔘⶒ냧쎸?䳰朗䧝럟㵜㉜偽ὁ졌摔ﾓꗧ?㤒芻랄꡵쭁翇蹾狈줳ꎫᄶ龈?纖ꈆꍍ菕᭱?恟⼂".toCharArray()[86] ^ 0x70A0); String str; int i = (str = a0$cc.G("稄?툝⫵嗮랢⏧榗䜨⚟倝庯륦篚齄䏯껑剂뱪삌繛硣烳᢬堺湻㑡?瑙䁹Ꮦ䔶⤈ꒅ㤞ￊ낕颐簆쪿쉿壡㽫즚즂ㆡ웜ꆉꝚ퇋⋍长㩆账炽瞰ਝഄ镮Ӝ꺳铏잠贘枨팣쐜ꦃⷆ䏛郷㯲ꔘⶒ냧쎸?䳰朗䧝럟㵜㉜偽ὁ졌摔ﾓꗧ?㤒芻랄꡵쭁翇蹾狈줳ꎫᄶ龈?纖ꈆꍍ菕᭱?恟⼂".toCharArray(), (short)9472, false, (byte)2)).length(); byte b2 = 80; byte b = -1;
/*   */     while (true); }
/*   */ 
/*   */   
/*   */   public static final k4 a;
/*   */   public static final long b;
/*   */   public static final String[] c;
/*   */   public static final String[] d;
/*   */   public static final Map e;
/*   */   
/*   */   private static CallSite a(MethodHandles.Lookup paramLookup, String paramString, MethodType paramMethodType) {
/*   */     // Byte code:
/*   */     //   0: new java/lang/invoke/MutableCallSite
/*   */     //   3: dup
/*   */     //   4: aload_2
/*   */     //   5: invokespecial <init> : (Ljava/lang/invoke/MethodType;)V
/*   */     //   8: astore_3
/*   */     //   9: aload_3
/*   */     //   10: ldc_w
/*   */     //   13: ldc [Ljava/lang/Object;
/*   */     //   15: aload_2
/*   */     //   16: invokevirtual parameterCount : ()I
/*   */     //   19: invokevirtual asCollector : (Ljava/lang/Class;I)Ljava/lang/invoke/MethodHandle;
/*   */     //   22: iconst_0
/*   */     //   23: iconst_3
/*   */     //   24: anewarray java/lang/Object
/*   */     //   27: dup
/*   */     //   28: iconst_0
/*   */     //   29: aload_0
/*   */     //   30: aastore
/*   */     //   31: dup
/*   */     //   32: iconst_1
/*   */     //   33: aload_3
/*   */     //   34: aastore
/*   */     //   35: dup
/*   */     //   36: iconst_2
/*   */     //   37: aload_1
/*   */     //   38: aastore
/*   */     //   39: invokestatic insertArguments : (Ljava/lang/invoke/MethodHandle;I[Ljava/lang/Object;)Ljava/lang/invoke/MethodHandle;
/*   */     //   42: aload_2
/*   */     //   43: invokestatic explicitCastArguments : (Ljava/lang/invoke/MethodHandle;Ljava/lang/invoke/MethodType;)Ljava/lang/invoke/MethodHandle;
/*   */     //   46: invokevirtual setTarget : (Ljava/lang/invoke/MethodHandle;)V
/*   */     //   49: goto -> 170
/*   */     //   52: astore #4
/*   */     //   54: new java/lang/RuntimeException
/*   */     //   57: dup
/*   */     //   58: new java/lang/StringBuilder
/*   */     //   61: dup
/*   */     //   62: invokespecial <init> : ()V
/*   */     //   65: ldc_w '쨯矎횄ௗ떋㖺懣㠁榹뒴吹⏒埽匼'
/*   */     //   68: invokevirtual toCharArray : ()[C
/*   */     //   71: dup
/*   */     //   72: dup
/*   */     //   73: bipush #12
/*   */     //   75: dup_x1
/*   */     //   76: caload
/*   */     //   77: sipush #6044
/*   */     //   80: ixor
/*   */     //   81: i2c
/*   */     //   82: castore
/*   */     //   83: sipush #20459
/*   */     //   86: iconst_2
/*   */     //   87: iconst_2
/*   */     //   88: invokestatic H : (Ljava/lang/Object;SBB)Ljava/lang/String;
/*   */     //   91: invokevirtual append : (Ljava/lang/String;)Ljava/lang/StringBuilder;
/*   */     //   94: ldc_w 'ਾ홉縉礙'
/*   */     //   97: invokevirtual toCharArray : ()[C
/*   */     //   100: dup
/*   */     //   101: dup
/*   */     //   102: iconst_1
/*   */     //   103: dup_x1
/*   */     //   104: caload
/*   */     //   105: sipush #30057
/*   */     //   108: ixor
/*   */     //   109: i2c
/*   */     //   110: castore
/*   */     //   111: sipush #15633
/*   */     //   114: iconst_5
/*   */     //   115: iconst_5
/*   */     //   116: invokestatic H : (Ljava/lang/Object;SBB)Ljava/lang/String;
/*   */     //   119: invokevirtual append : (Ljava/lang/String;)Ljava/lang/StringBuilder;
/*   */     //   122: aload_1
/*   */     //   123: invokevirtual append : (Ljava/lang/String;)Ljava/lang/StringBuilder;
/*   */     //   126: ldc_w '뜒非딨午'
/*   */     //   129: invokevirtual toCharArray : ()[C
/*   */     //   132: dup
/*   */     //   133: dup
/*   */     //   134: iconst_2
/*   */     //   135: dup_x1
/*   */     //   136: caload
/*   */     //   137: sipush #13845
/*   */     //   140: ixor
/*   */     //   141: i2c
/*   */     //   142: castore
/*   */     //   143: sipush #18397
/*   */     //   146: iconst_4
/*   */     //   147: iconst_5
/*   */     //   148: invokestatic H : (Ljava/lang/Object;SBB)Ljava/lang/String;
/*   */     //   151: invokevirtual append : (Ljava/lang/String;)Ljava/lang/StringBuilder;
/*   */     //   154: aload_2
/*   */     //   155: invokevirtual toString : ()Ljava/lang/String;
/*   */     //   158: invokevirtual append : (Ljava/lang/String;)Ljava/lang/StringBuilder;
/*   */     //   161: invokevirtual toString : ()Ljava/lang/String;
/*   */     //   164: aload #4
/*   */     //   166: invokespecial <init> : (Ljava/lang/String;Ljava/lang/Throwable;)V
/*   */     //   169: athrow
/*   */     //   170: aload_3
/*   */     //   171: areturn
/*   */     // Exception table:
/*   */     //   from	to	target	type
/*   */     //   9	49	52	java/lang/Exception
/*   */   }
/*   */   
/*   */   private static Object a(MethodHandles.Lookup paramLookup, MutableCallSite paramMutableCallSite, String paramString, Object[] paramArrayOfObject) {
/*   */     int i = ((Integer)paramArrayOfObject[0]).intValue();
/*   */     long l = ((Long)paramArrayOfObject[1]).longValue();
/*   */     String str = a(i, l);
/*   */     MethodHandle methodHandle = MethodHandles.constant(String.class, str);
/*   */     paramMutableCallSite.setTarget(MethodHandles.dropArguments(methodHandle, 0, new Class[] { int.class, long.class }));
/*   */     return str;
/*   */   }
/*   */   
/*   */   private static String a(int paramInt, long paramLong) {
/*   */     int i = paramInt ^ (int)(paramLong & 0x7FFFL) ^ 0x1E18;
/*   */     if (d[i] == null) {
/*   */       Object[] arrayOfObject;
/*   */       try {
/*   */         Long long_ = Long.valueOf(Thread.currentThread().getId());
/*   */         arrayOfObject = (Object[])e.get(long_);
/*   */         if (arrayOfObject == null) {
/*   */           arrayOfObject = new Object[3];
/*   */           "宭詭䁤쨸卢ꘅ場喼⹄㬼晷㿲콴㌶ﲨ➚㚲阂Ϙ".toCharArray()[18] = (char)("宭詭䁤쨸卢ꘅ場喼⹄㬼晷㿲콴㌶ﲨ➚㚲阂Ϙ".toCharArray()[18] ^ 0x709E);
/*   */           arrayOfObject[0] = Cipher.getInstance(a0$cc.G("宭詭䁤쨸卢ꘅ場喼⹄㬼晷㿲콴㌶ﲨ➚㚲阂Ϙ".toCharArray(), (short)10771, true, (byte)4));
/*   */           "ꩪ잃ﭷ庁".toCharArray()[0] = (char)("ꩪ잃ﭷ庁".toCharArray()[0] ^ 0x7F03);
/*   */           arrayOfObject[1] = SecretKeyFactory.getInstance(a0$cc.G("ꩪ잃ﭷ庁".toCharArray(), (short)23826, true, (byte)5));
/*   */           arrayOfObject[2] = new IvParameterSpec(new byte[8]);
/*   */           e.put(long_, arrayOfObject);
/*   */         } 
/*   */       } catch (Exception exception) {
/*   */         "೧羀늟蹭㱻?駴㬳픧훓嫚鍔帣嫆綖␉".toCharArray()[14] = (char)("೧羀늟蹭㱻?駴㬳픧훓嫚鍔帣嫆綖␉".toCharArray()[14] ^ 0x6FF8);
/*   */         throw new RuntimeException(a0$cc.G("೧羀늟蹭㱻?駴㬳픧훓嫚鍔帣嫆綖␉".toCharArray(), (short)31245, true, (byte)4), exception);
/*   */       } 
/*   */       byte[] arrayOfByte1 = new byte[8];
/*   */       arrayOfByte1[0] = (byte)(int)(paramLong >>> 56L);
/*   */       for (byte b = 1; b < 8; b++)
/*   */         arrayOfByte1[b] = (byte)(int)(paramLong << b * 8 >>> 56L); 
/*   */       DESKeySpec dESKeySpec = new DESKeySpec(arrayOfByte1);
/*   */       SecretKey secretKey = ((SecretKeyFactory)arrayOfObject[1]).generateSecret(dESKeySpec);
/*   */       ((Cipher)arrayOfObject[0]).init(2, secretKey, (IvParameterSpec)arrayOfObject[2]);
/*   */       "氕벍⛅Ĭ䣱뎰綷旉䄭䐼".toCharArray()[0] = (char)("氕벍⛅Ĭ䣱뎰綷旉䄭䐼".toCharArray()[0] ^ 0x75F1);
/*   */       byte[] arrayOfByte2 = c[i].getBytes(a0$cc.G("氕벍⛅Ĭ䣱뎰綷旉䄭䐼".toCharArray(), (short)3118, false, (byte)5));
/*   */       d[i] = a(((Cipher)arrayOfObject[0]).doFinal(arrayOfByte2));
/*   */     } 
/*   */     return d[i];
/*   */   }
/*   */   
/*   */   private static String a(byte[] paramArrayOfbyte) {
/*   */     byte b1 = 0;
/*   */     int i;
/*   */     char[] arrayOfChar = new char[i = paramArrayOfbyte.length];
/*   */     for (byte b2 = 0; b2 < i; b2++) {
/*   */       int j;
/*   */       if ((j = 0xFF & paramArrayOfbyte[b2]) < 192) {
/*   */         arrayOfChar[b1++] = (char)j;
/*   */       } else if (j < 224) {
/*   */         char c = (char)((char)(j & 0x1F) << 6);
/*   */         j = paramArrayOfbyte[++b2];
/*   */         c = (char)(c | (char)(j & 0x3F));
/*   */         arrayOfChar[b1++] = c;
/*   */       } else if (b2 < i - 2) {
/*   */         char c = (char)((char)(j & 0xF) << 12);
/*   */         j = paramArrayOfbyte[++b2];
/*   */         c = (char)(c | (char)(j & 0x3F) << 6);
/*   */         j = paramArrayOfbyte[++b2];
/*   */         c = (char)(c | (char)(j & 0x3F));
/*   */         arrayOfChar[b1++] = c;
/*   */       } 
/*   */     } 
/*   */     return new String(arrayOfChar, 0, b1);
/*   */   }
/*   */   
/*   */   private static NullPointerException a(NullPointerException paramNullPointerException) {
/*   */     return paramNullPointerException;
/*   */   }
/*   */   
/*   */   List a(String paramString) throws UnknownHostException; }


/* Location:              C:\Users\BukkitBypass\Desktop\MatrixAC\AAC\AAC-spigot-5.2.0.jar!\me\konsolas\aac\k4.class
 * Java compiler version: 8 (52.0)
 * JD-Core Version:       1.1.3
 */