/*    */ package me.konsolas.aac;
/*    */ 
/*    */ import java.lang.invoke.CallSite;
/*    */ import java.lang.invoke.MethodHandle;
/*    */ import java.lang.invoke.MethodHandles;
/*    */ import java.lang.invoke.MethodType;
/*    */ import java.lang.invoke.MutableCallSite;
/*    */ import java.net.URL;
/*    */ import java.util.HashMap;
/*    */ import java.util.Map;
/*    */ import javax.annotation.Nullable;
/*    */ import javax.crypto.Cipher;
/*    */ import javax.crypto.SecretKey;
/*    */ import javax.crypto.SecretKeyFactory;
/*    */ import javax.crypto.spec.DESKeySpec;
/*    */ import javax.crypto.spec.IvParameterSpec;
/*    */ 
/*    */ 
/*    */ public class k_
/*    */ {
/*    */   @Nullable
/*    */   l6 b;
/*    */   String a;
/*    */   mr c;
/*    */   @Nullable
/*    */   jR d;
/*    */   Map e;
/*    */   private static final long f = nc.a(1387787819869698844L, 8201905544304069826L, MethodHandles.lookup().lookupClass()).a(29981643358815L);
/*    */   private static final String[] g;
/*    */   private static final String[] h;
/*    */   
/*    */   public k_ b(long paramLong, String paramString) {
/* 33 */     paramLong = f ^ paramLong; long l = paramLong ^ 0x6CEEA196B47FL; this.c.c(l, paramString); return this;
/*    */   }
/*    */   private static final Map i = new HashMap<>(13);
/*    */   public k_ a(long paramLong, String paramString) { // Byte code:
/*    */     //   0: getstatic me/konsolas/aac/k_.f : J
/*    */     //   3: lload_1
/*    */     //   4: lxor
/*    */     //   5: lstore_1
/*    */     //   6: lload_1
/*    */     //   7: dup2
/*    */     //   8: ldc2_w 38789130809616
/*    */     //   11: lxor
/*    */     //   12: lstore #4
/*    */     //   14: dup2
/*    */     //   15: ldc2_w 124545136483223
/*    */     //   18: lxor
/*    */     //   19: lstore #6
/*    */     //   21: pop2
/*    */     //   22: ldc2_w 3673510991977067064
/*    */     //   25: lload_1
/*    */     //   26: <illegal opcode> w : (JJ)[Lme/konsolas/aac/aN;
/*    */     //   31: astore #8
/*    */     //   33: aload_3
/*    */     //   34: aload #8
/*    */     //   36: ifnonnull -> 87
/*    */     //   39: ifnonnull -> 86
/*    */     //   42: goto -> 55
/*    */     //   45: ldc2_w 3723758641111712508
/*    */     //   48: lload_1
/*    */     //   49: <illegal opcode> w : (Ljava/lang/NullPointerException;JJ)Ljava/lang/NullPointerException;
/*    */     //   54: athrow
/*    */     //   55: new java/lang/NullPointerException
/*    */     //   58: dup
/*    */     //   59: sipush #30518
/*    */     //   62: ldc2_w 5717115772072197435
/*    */     //   65: lload_1
/*    */     //   66: lxor
/*    */     //   67: <illegal opcode> p : (IJ)Ljava/lang/String;
/*    */     //   72: invokespecial <init> : (Ljava/lang/String;)V
/*    */     //   75: athrow
/*    */     //   76: ldc2_w 3723758641111712508
/*    */     //   79: lload_1
/*    */     //   80: <illegal opcode> w : (Ljava/lang/NullPointerException;JJ)Ljava/lang/NullPointerException;
/*    */     //   85: athrow
/*    */     //   86: aload_3
/*    */     //   87: iconst_1
/*    */     //   88: iconst_0
/*    */     //   89: sipush #12359
/*    */     //   92: ldc2_w 4217898000967219802
/*    */     //   95: lload_1
/*    */     //   96: lxor
/*    */     //   97: <illegal opcode> p : (IJ)Ljava/lang/String;
/*    */     //   102: iconst_0
/*    */     //   103: iconst_3
/*    */     //   104: invokevirtual regionMatches : (ZILjava/lang/String;II)Z
/*    */     //   107: lload_1
/*    */     //   108: lconst_0
/*    */     //   109: lcmp
/*    */     //   110: iflt -> 232
/*    */     //   113: aload #8
/*    */     //   115: ifnonnull -> 232
/*    */     //   118: ifeq -> 180
/*    */     //   121: goto -> 134
/*    */     //   124: ldc2_w 3723758641111712508
/*    */     //   127: lload_1
/*    */     //   128: <illegal opcode> w : (Ljava/lang/NullPointerException;JJ)Ljava/lang/NullPointerException;
/*    */     //   133: athrow
/*    */     //   134: new java/lang/StringBuilder
/*    */     //   137: dup
/*    */     //   138: invokespecial <init> : ()V
/*    */     //   141: sipush #19645
/*    */     //   144: ldc2_w 1053140592756180647
/*    */     //   147: lload_1
/*    */     //   148: lxor
/*    */     //   149: <illegal opcode> p : (IJ)Ljava/lang/String;
/*    */     //   154: invokevirtual append : (Ljava/lang/String;)Ljava/lang/StringBuilder;
/*    */     //   157: aload_3
/*    */     //   158: iconst_3
/*    */     //   159: invokevirtual substring : (I)Ljava/lang/String;
/*    */     //   162: invokevirtual append : (Ljava/lang/String;)Ljava/lang/StringBuilder;
/*    */     //   165: invokevirtual toString : ()Ljava/lang/String;
/*    */     //   168: astore_3
/*    */     //   169: lload_1
/*    */     //   170: lconst_0
/*    */     //   171: lcmp
/*    */     //   172: ifle -> 180
/*    */     //   175: aload #8
/*    */     //   177: ifnull -> 283
/*    */     //   180: aload_3
/*    */     //   181: aload #8
/*    */     //   183: ifnonnull -> 282
/*    */     //   186: goto -> 199
/*    */     //   189: ldc2_w 3723758641111712508
/*    */     //   192: lload_1
/*    */     //   193: <illegal opcode> w : (Ljava/lang/NullPointerException;JJ)Ljava/lang/NullPointerException;
/*    */     //   198: athrow
/*    */     //   199: iconst_1
/*    */     //   200: iconst_0
/*    */     //   201: sipush #7209
/*    */     //   204: ldc2_w 8573149920232805941
/*    */     //   207: lload_1
/*    */     //   208: lxor
/*    */     //   209: <illegal opcode> p : (IJ)Ljava/lang/String;
/*    */     //   214: iconst_0
/*    */     //   215: iconst_4
/*    */     //   216: invokevirtual regionMatches : (ZILjava/lang/String;II)Z
/*    */     //   219: goto -> 232
/*    */     //   222: ldc2_w 3723758641111712508
/*    */     //   225: lload_1
/*    */     //   226: <illegal opcode> w : (Ljava/lang/NullPointerException;JJ)Ljava/lang/NullPointerException;
/*    */     //   231: athrow
/*    */     //   232: ifeq -> 283
/*    */     //   235: new java/lang/StringBuilder
/*    */     //   238: dup
/*    */     //   239: invokespecial <init> : ()V
/*    */     //   242: sipush #25436
/*    */     //   245: ldc2_w 320404298475792708
/*    */     //   248: lload_1
/*    */     //   249: lxor
/*    */     //   250: <illegal opcode> p : (IJ)Ljava/lang/String;
/*    */     //   255: invokevirtual append : (Ljava/lang/String;)Ljava/lang/StringBuilder;
/*    */     //   258: aload_3
/*    */     //   259: iconst_4
/*    */     //   260: invokevirtual substring : (I)Ljava/lang/String;
/*    */     //   263: invokevirtual append : (Ljava/lang/String;)Ljava/lang/StringBuilder;
/*    */     //   266: invokevirtual toString : ()Ljava/lang/String;
/*    */     //   269: goto -> 282
/*    */     //   272: ldc2_w 3723758641111712508
/*    */     //   275: lload_1
/*    */     //   276: <illegal opcode> w : (Ljava/lang/NullPointerException;JJ)Ljava/lang/NullPointerException;
/*    */     //   281: athrow
/*    */     //   282: astore_3
/*    */     //   283: aload_0
/*    */     //   284: aload_3
/*    */     //   285: lload #4
/*    */     //   287: invokestatic c : (Ljava/lang/String;J)Lme/konsolas/aac/l6;
/*    */     //   290: lload #6
/*    */     //   292: invokevirtual a : (Lme/konsolas/aac/l6;J)Lme/konsolas/aac/k_;
/*    */     //   295: areturn
/*    */     // Line number table:
/*    */     //   Java source line number -> byte code offset
/*    */     //   #9	-> 33
/*    */     //   #28	-> 86
/*    */     //   #31	-> 134
/*    */     //   #13	-> 180
/*    */     //   #15	-> 235
/*    */     //   #8	-> 283
/*    */     // Exception table:
/*    */     //   from	to	target	type
/*    */     //   33	42	45	java/lang/NullPointerException
/*    */     //   39	76	76	java/lang/NullPointerException
/*    */     //   87	121	124	java/lang/NullPointerException
/*    */     //   169	186	189	java/lang/NullPointerException
/*    */     //   180	219	222	java/lang/NullPointerException
/*    */     //   232	269	272	java/lang/NullPointerException }
/*    */   public k_ a(long paramLong, jR paramjR) { // Byte code:
/*    */     //   0: getstatic me/konsolas/aac/k_.f : J
/*    */     //   3: lload_1
/*    */     //   4: lxor
/*    */     //   5: lstore_1
/*    */     //   6: lload_1
/*    */     //   7: dup2
/*    */     //   8: ldc2_w 26431791278921
/*    */     //   11: lxor
/*    */     //   12: lstore #4
/*    */     //   14: pop2
/*    */     //   15: aload_0
/*    */     //   16: sipush #20875
/*    */     //   19: ldc2_w 5643552106134333374
/*    */     //   22: lload_1
/*    */     //   23: lxor
/*    */     //   24: <illegal opcode> p : (IJ)Ljava/lang/String;
/*    */     //   29: lload #4
/*    */     //   31: aload_3
/*    */     //   32: invokevirtual a : (Ljava/lang/String;JLme/konsolas/aac/jR;)Lme/konsolas/aac/k_;
/*    */     //   35: areturn
/*    */     // Line number table:
/*    */     //   Java source line number -> byte code offset
/*    */     //   #10	-> 15 }
/*    */   public k_(long paramLong) { // Byte code:
/*    */     //   0: getstatic me/konsolas/aac/k_.f : J
/*    */     //   3: lload_1
/*    */     //   4: lxor
/*    */     //   5: lstore_1
/*    */     //   6: aload_0
/*    */     //   7: invokespecial <init> : ()V
/*    */     //   10: aload_0
/*    */     //   11: invokestatic emptyMap : ()Ljava/util/Map;
/*    */     //   14: putfield e : Ljava/util/Map;
/*    */     //   17: aload_0
/*    */     //   18: sipush #3292
/*    */     //   21: ldc2_w 2967681716879998189
/*    */     //   24: lload_1
/*    */     //   25: lxor
/*    */     //   26: <illegal opcode> p : (IJ)Ljava/lang/String;
/*    */     //   31: putfield a : Ljava/lang/String;
/*    */     //   34: aload_0
/*    */     //   35: new me/konsolas/aac/mr
/*    */     //   38: dup
/*    */     //   39: invokespecial <init> : ()V
/*    */     //   42: putfield c : Lme/konsolas/aac/mr;
/*    */     //   45: return
/*    */     // Line number table:
/*    */     //   Java source line number -> byte code offset
/*    */     //   #11	-> 6
/*    */     //   #57	-> 10
/*    */     //   #27	-> 17
/*    */     //   #20	-> 34
/*    */     //   #56	-> 45 }
/*    */   public k_ b(long paramLong, byte paramByte) { // Byte code:
/*    */     //   0: lload_1
/*    */     //   1: bipush #8
/*    */     //   3: lshl
/*    */     //   4: iload_3
/*    */     //   5: i2l
/*    */     //   6: bipush #56
/*    */     //   8: lshl
/*    */     //   9: bipush #56
/*    */     //   11: lushr
/*    */     //   12: lor
/*    */     //   13: getstatic me/konsolas/aac/k_.f : J
/*    */     //   16: lxor
/*    */     //   17: lstore #4
/*    */     //   19: lload #4
/*    */     //   21: dup2
/*    */     //   22: ldc2_w 103756138831005
/*    */     //   25: lxor
/*    */     //   26: lstore #6
/*    */     //   28: pop2
/*    */     //   29: aload_0
/*    */     //   30: sipush #26036
/*    */     //   33: ldc2_w 4254282437195244621
/*    */     //   36: lload #4
/*    */     //   38: lxor
/*    */     //   39: <illegal opcode> p : (IJ)Ljava/lang/String;
/*    */     //   44: lload #6
/*    */     //   46: aconst_null
/*    */     //   47: invokevirtual a : (Ljava/lang/String;JLme/konsolas/aac/jR;)Lme/konsolas/aac/k_;
/*    */     //   50: areturn
/*    */     // Line number table:
/*    */     //   Java source line number -> byte code offset
/*    */     //   #12	-> 29 } public s a(long paramLong) { // Byte code:
/*    */     //   0: getstatic me/konsolas/aac/k_.f : J
/*    */     //   3: lload_1
/*    */     //   4: lxor
/*    */     //   5: lstore_1
/*    */     //   6: lload_1
/*    */     //   7: dup2
/*    */     //   8: ldc2_w 66027197814565
/*    */     //   11: lxor
/*    */     //   12: lstore_3
/*    */     //   13: pop2
/*    */     //   14: aload_0
/*    */     //   15: getfield b : Lme/konsolas/aac/l6;
/*    */     //   18: ifnonnull -> 52
/*    */     //   21: new java/lang/IllegalStateException
/*    */     //   24: dup
/*    */     //   25: sipush #30518
/*    */     //   28: ldc2_w 5717105051275076213
/*    */     //   31: lload_1
/*    */     //   32: lxor
/*    */     //   33: <illegal opcode> p : (IJ)Ljava/lang/String;
/*    */     //   38: invokespecial <init> : (Ljava/lang/String;)V
/*    */     //   41: athrow
/*    */     //   42: ldc2_w -1377247711535587918
/*    */     //   45: lload_1
/*    */     //   46: <illegal opcode> w : (Ljava/lang/NullPointerException;JJ)Ljava/lang/NullPointerException;
/*    */     //   51: athrow
/*    */     //   52: new me/konsolas/aac/s
/*    */     //   55: dup
/*    */     //   56: aload_0
/*    */     //   57: lload_3
/*    */     //   58: invokespecial <init> : (Lme/konsolas/aac/k_;J)V
/*    */     //   61: areturn
/*    */     // Line number table:
/*    */     //   Java source line number -> byte code offset
/*    */     //   #17	-> 14
/*    */     //   #40	-> 52
/*    */     // Exception table:
/*    */     //   from	to	target	type
/*    */     //   14	42	42	java/lang/NullPointerException } public k_ a(l6 paraml6, long paramLong) { // Byte code:
/*    */     //   0: getstatic me/konsolas/aac/k_.f : J
/*    */     //   3: lload_2
/*    */     //   4: lxor
/*    */     //   5: lstore_2
/*    */     //   6: ldc2_w 4255863473212636109
/*    */     //   9: lload_2
/*    */     //   10: <illegal opcode> w : (JJ)[Lme/konsolas/aac/aN;
/*    */     //   15: astore #4
/*    */     //   17: aload #4
/*    */     //   19: ifnonnull -> 75
/*    */     //   22: aload_1
/*    */     //   23: ifnonnull -> 70
/*    */     //   26: goto -> 39
/*    */     //   29: ldc2_w 4204182056603634441
/*    */     //   32: lload_2
/*    */     //   33: <illegal opcode> w : (Ljava/lang/NullPointerException;JJ)Ljava/lang/NullPointerException;
/*    */     //   38: athrow
/*    */     //   39: new java/lang/NullPointerException
/*    */     //   42: dup
/*    */     //   43: sipush #30518
/*    */     //   46: ldc2_w 5717166956839859406
/*    */     //   49: lload_2
/*    */     //   50: lxor
/*    */     //   51: <illegal opcode> p : (IJ)Ljava/lang/String;
/*    */     //   56: invokespecial <init> : (Ljava/lang/String;)V
/*    */     //   59: athrow
/*    */     //   60: ldc2_w 4204182056603634441
/*    */     //   63: lload_2
/*    */     //   64: <illegal opcode> w : (Ljava/lang/NullPointerException;JJ)Ljava/lang/NullPointerException;
/*    */     //   69: athrow
/*    */     //   70: aload_0
/*    */     //   71: aload_1
/*    */     //   72: putfield b : Lme/konsolas/aac/l6;
/*    */     //   75: aload_0
/*    */     //   76: areturn
/*    */     // Line number table:
/*    */     //   Java source line number -> byte code offset
/*    */     //   #21	-> 17
/*    */     //   #25	-> 70
/*    */     //   #35	-> 75
/*    */     // Exception table:
/*    */     //   from	to	target	type
/*    */     //   17	26	29	java/lang/NullPointerException
/*    */     //   22	60	60	java/lang/NullPointerException } public k_ b(long paramLong, jR paramjR) { // Byte code:
/*    */     //   0: getstatic me/konsolas/aac/k_.f : J
/*    */     //   3: lload_1
/*    */     //   4: lxor
/*    */     //   5: lstore_1
/*    */     //   6: lload_1
/*    */     //   7: dup2
/*    */     //   8: ldc2_w 76853365606452
/*    */     //   11: lxor
/*    */     //   12: lstore #4
/*    */     //   14: pop2
/*    */     //   15: aload_0
/*    */     //   16: sipush #14857
/*    */     //   19: ldc2_w 5641421129593335647
/*    */     //   22: lload_1
/*    */     //   23: lxor
/*    */     //   24: <illegal opcode> p : (IJ)Ljava/lang/String;
/*    */     //   29: lload #4
/*    */     //   31: aload_3
/*    */     //   32: invokevirtual a : (Ljava/lang/String;JLme/konsolas/aac/jR;)Lme/konsolas/aac/k_;
/*    */     //   35: areturn
/*    */     // Line number table:
/*    */     //   Java source line number -> byte code offset
/*    */     //   #23	-> 15 } public k_ a(long paramLong, Class paramClass, @Nullable Object paramObject) { // Byte code:
/*    */     //   0: getstatic me/konsolas/aac/k_.f : J
/*    */     //   3: lload_1
/*    */     //   4: lxor
/*    */     //   5: lstore_1
/*    */     //   6: ldc2_w -6472291757833345297
/*    */     //   9: lload_1
/*    */     //   10: <illegal opcode> w : (JJ)[Lme/konsolas/aac/aN;
/*    */     //   15: astore #5
/*    */     //   17: aload_3
/*    */     //   18: aload #5
/*    */     //   20: ifnonnull -> 72
/*    */     //   23: ifnonnull -> 70
/*    */     //   26: goto -> 39
/*    */     //   29: ldc2_w -6378696889286535637
/*    */     //   32: lload_1
/*    */     //   33: <illegal opcode> w : (Ljava/lang/NullPointerException;JJ)Ljava/lang/NullPointerException;
/*    */     //   38: athrow
/*    */     //   39: new java/lang/NullPointerException
/*    */     //   42: dup
/*    */     //   43: sipush #10048
/*    */     //   46: ldc2_w 2983284939718277528
/*    */     //   49: lload_1
/*    */     //   50: lxor
/*    */     //   51: <illegal opcode> p : (IJ)Ljava/lang/String;
/*    */     //   56: invokespecial <init> : (Ljava/lang/String;)V
/*    */     //   59: athrow
/*    */     //   60: ldc2_w -6378696889286535637
/*    */     //   63: lload_1
/*    */     //   64: <illegal opcode> w : (Ljava/lang/NullPointerException;JJ)Ljava/lang/NullPointerException;
/*    */     //   69: athrow
/*    */     //   70: aload #4
/*    */     //   72: lload_1
/*    */     //   73: lconst_0
/*    */     //   74: lcmp
/*    */     //   75: ifle -> 122
/*    */     //   78: aload #5
/*    */     //   80: ifnonnull -> 122
/*    */     //   83: ifnonnull -> 134
/*    */     //   86: goto -> 99
/*    */     //   89: ldc2_w -6378696889286535637
/*    */     //   92: lload_1
/*    */     //   93: <illegal opcode> w : (Ljava/lang/NullPointerException;JJ)Ljava/lang/NullPointerException;
/*    */     //   98: athrow
/*    */     //   99: aload_0
/*    */     //   100: getfield e : Ljava/util/Map;
/*    */     //   103: aload_3
/*    */     //   104: invokeinterface remove : (Ljava/lang/Object;)Ljava/lang/Object;
/*    */     //   109: goto -> 122
/*    */     //   112: ldc2_w -6378696889286535637
/*    */     //   115: lload_1
/*    */     //   116: <illegal opcode> w : (Ljava/lang/NullPointerException;JJ)Ljava/lang/NullPointerException;
/*    */     //   121: athrow
/*    */     //   122: pop
/*    */     //   123: lload_1
/*    */     //   124: lconst_0
/*    */     //   125: lcmp
/*    */     //   126: iflt -> 134
/*    */     //   129: aload #5
/*    */     //   131: ifnull -> 224
/*    */     //   134: aload_0
/*    */     //   135: getfield e : Ljava/util/Map;
/*    */     //   138: aload #5
/*    */     //   140: ifnonnull -> 223
/*    */     //   143: goto -> 156
/*    */     //   146: ldc2_w -6378696889286535637
/*    */     //   149: lload_1
/*    */     //   150: <illegal opcode> w : (Ljava/lang/NullPointerException;JJ)Ljava/lang/NullPointerException;
/*    */     //   155: athrow
/*    */     //   156: lload_1
/*    */     //   157: lconst_0
/*    */     //   158: lcmp
/*    */     //   159: iflt -> 211
/*    */     //   162: invokeinterface isEmpty : ()Z
/*    */     //   167: ifeq -> 207
/*    */     //   170: goto -> 183
/*    */     //   173: ldc2_w -6378696889286535637
/*    */     //   176: lload_1
/*    */     //   177: <illegal opcode> w : (Ljava/lang/NullPointerException;JJ)Ljava/lang/NullPointerException;
/*    */     //   182: athrow
/*    */     //   183: aload_0
/*    */     //   184: new java/util/LinkedHashMap
/*    */     //   187: dup
/*    */     //   188: invokespecial <init> : ()V
/*    */     //   191: putfield e : Ljava/util/Map;
/*    */     //   194: goto -> 207
/*    */     //   197: ldc2_w -6378696889286535637
/*    */     //   200: lload_1
/*    */     //   201: <illegal opcode> w : (Ljava/lang/NullPointerException;JJ)Ljava/lang/NullPointerException;
/*    */     //   206: athrow
/*    */     //   207: aload_0
/*    */     //   208: getfield e : Ljava/util/Map;
/*    */     //   211: aload_3
/*    */     //   212: aload_3
/*    */     //   213: aload #4
/*    */     //   215: invokevirtual cast : (Ljava/lang/Object;)Ljava/lang/Object;
/*    */     //   218: invokeinterface put : (Ljava/lang/Object;Ljava/lang/Object;)Ljava/lang/Object;
/*    */     //   223: pop
/*    */     //   224: aload_0
/*    */     //   225: areturn
/*    */     // Line number table:
/*    */     //   Java source line number -> byte code offset
/*    */     //   #34	-> 17
/*    */     //   #7	-> 70
/*    */     //   #6	-> 99
/*    */     //   #42	-> 134
/*    */     //   #30	-> 207
/*    */     //   #19	-> 224
/*    */     // Exception table:
/*    */     //   from	to	target	type
/*    */     //   17	26	29	java/lang/NullPointerException
/*    */     //   23	60	60	java/lang/NullPointerException
/*    */     //   72	86	89	java/lang/NullPointerException
/*    */     //   83	109	112	java/lang/NullPointerException
/*    */     //   122	143	146	java/lang/NullPointerException
/*    */     //   134	170	173	java/lang/NullPointerException
/*    */     //   156	194	197	java/lang/NullPointerException } public k_ a(b0 paramb0, long paramLong) { // Byte code:
/*    */     //   0: getstatic me/konsolas/aac/k_.f : J
/*    */     //   3: lload_2
/*    */     //   4: lxor
/*    */     //   5: lstore_2
/*    */     //   6: lload_2
/*    */     //   7: dup2
/*    */     //   8: ldc2_w 80009072978339
/*    */     //   11: lxor
/*    */     //   12: dup2
/*    */     //   13: bipush #8
/*    */     //   15: lushr
/*    */     //   16: lstore #4
/*    */     //   18: dup2
/*    */     //   19: bipush #56
/*    */     //   21: lshl
/*    */     //   22: bipush #56
/*    */     //   24: lushr
/*    */     //   25: l2i
/*    */     //   26: istore #6
/*    */     //   28: pop2
/*    */     //   29: dup2
/*    */     //   30: ldc2_w 73574562462225
/*    */     //   33: lxor
/*    */     //   34: lstore #7
/*    */     //   36: pop2
/*    */     //   37: aload_1
/*    */     //   38: invokevirtual toString : ()Ljava/lang/String;
/*    */     //   41: astore #9
/*    */     //   43: aload #9
/*    */     //   45: invokevirtual isEmpty : ()Z
/*    */     //   48: ifeq -> 81
/*    */     //   51: aload_0
/*    */     //   52: lload #7
/*    */     //   54: sipush #13542
/*    */     //   57: ldc2_w 8271595584215203493
/*    */     //   60: lload_2
/*    */     //   61: lxor
/*    */     //   62: <illegal opcode> p : (IJ)Ljava/lang/String;
/*    */     //   67: invokevirtual b : (JLjava/lang/String;)Lme/konsolas/aac/k_;
/*    */     //   70: areturn
/*    */     //   71: ldc2_w 3745936130900116141
/*    */     //   74: lload_2
/*    */     //   75: <illegal opcode> w : (Ljava/lang/NullPointerException;JJ)Ljava/lang/NullPointerException;
/*    */     //   80: athrow
/*    */     //   81: aload_0
/*    */     //   82: sipush #19592
/*    */     //   85: ldc2_w 3977358011079214805
/*    */     //   88: lload_2
/*    */     //   89: lxor
/*    */     //   90: <illegal opcode> p : (IJ)Ljava/lang/String;
/*    */     //   95: lload #4
/*    */     //   97: iload #6
/*    */     //   99: i2b
/*    */     //   100: aload #9
/*    */     //   102: invokevirtual a : (Ljava/lang/String;JBLjava/lang/String;)Lme/konsolas/aac/k_;
/*    */     //   105: areturn
/*    */     // Line number table:
/*    */     //   Java source line number -> byte code offset
/*    */     //   #38	-> 37
/*    */     //   #16	-> 43
/*    */     //   #50	-> 81
/*    */     // Exception table:
/*    */     //   from	to	target	type
/* 39 */     //   43	71	71	java/lang/NullPointerException } public k_ a(long paramLong, @Nullable Object paramObject) { paramLong = f ^ paramLong; long l = paramLong ^ 0x1F4DD2670248L; return a(l, Object.class, paramObject); }
/*    */ 
/*    */ 
/*    */ 
/*    */   
/*    */   public k_ a(long paramLong) {
/* 45 */     paramLong = f ^ paramLong; long l = paramLong ^ 0x391D36061B36L; return d(l, eO.m);
/*    */   } k_(int paramInt, char paramChar1, s params, char paramChar2) {
/*    */     // Byte code:
/*    */     //   0: iload_1
/*    */     //   1: i2l
/*    */     //   2: bipush #32
/*    */     //   4: lshl
/*    */     //   5: iload_2
/*    */     //   6: i2l
/*    */     //   7: bipush #48
/*    */     //   9: lshl
/*    */     //   10: bipush #32
/*    */     //   12: lushr
/*    */     //   13: lor
/*    */     //   14: iload #4
/*    */     //   16: i2l
/*    */     //   17: bipush #48
/*    */     //   19: lshl
/*    */     //   20: bipush #48
/*    */     //   22: lushr
/*    */     //   23: lor
/*    */     //   24: getstatic me/konsolas/aac/k_.f : J
/*    */     //   27: lxor
/*    */     //   28: lstore #5
/*    */     //   30: aload_0
/*    */     //   31: invokespecial <init> : ()V
/*    */     //   34: aload_0
/*    */     //   35: invokestatic emptyMap : ()Ljava/util/Map;
/*    */     //   38: putfield e : Ljava/util/Map;
/*    */     //   41: ldc2_w 701974250490038655
/*    */     //   44: lload #5
/*    */     //   46: <illegal opcode> w : (JJ)[Lme/konsolas/aac/aN;
/*    */     //   51: aload_0
/*    */     //   52: aload_3
/*    */     //   53: getfield g : Lme/konsolas/aac/l6;
/*    */     //   56: putfield b : Lme/konsolas/aac/l6;
/*    */     //   59: astore #7
/*    */     //   61: aload_0
/*    */     //   62: aload_3
/*    */     //   63: getfield b : Ljava/lang/String;
/*    */     //   66: putfield a : Ljava/lang/String;
/*    */     //   69: aload_0
/*    */     //   70: aload_3
/*    */     //   71: getfield a : Lme/konsolas/aac/jR;
/*    */     //   74: putfield d : Lme/konsolas/aac/jR;
/*    */     //   77: aload_0
/*    */     //   78: aload_3
/*    */     //   79: getfield e : Ljava/util/Map;
/*    */     //   82: aload #7
/*    */     //   84: ifnonnull -> 126
/*    */     //   87: invokeinterface isEmpty : ()Z
/*    */     //   92: ifeq -> 129
/*    */     //   95: goto -> 109
/*    */     //   98: ldc2_w 642455454850906555
/*    */     //   101: lload #5
/*    */     //   103: <illegal opcode> w : (Ljava/lang/NullPointerException;JJ)Ljava/lang/NullPointerException;
/*    */     //   108: athrow
/*    */     //   109: invokestatic emptyMap : ()Ljava/util/Map;
/*    */     //   112: goto -> 126
/*    */     //   115: ldc2_w 642455454850906555
/*    */     //   118: lload #5
/*    */     //   120: <illegal opcode> w : (Ljava/lang/NullPointerException;JJ)Ljava/lang/NullPointerException;
/*    */     //   125: athrow
/*    */     //   126: goto -> 140
/*    */     //   129: new java/util/LinkedHashMap
/*    */     //   132: dup
/*    */     //   133: aload_3
/*    */     //   134: getfield e : Ljava/util/Map;
/*    */     //   137: invokespecial <init> : (Ljava/util/Map;)V
/*    */     //   140: putfield e : Ljava/util/Map;
/*    */     //   143: aload_0
/*    */     //   144: aload_3
/*    */     //   145: getfield f : Lme/konsolas/aac/J;
/*    */     //   148: invokevirtual a : ()Lme/konsolas/aac/mr;
/*    */     //   151: putfield c : Lme/konsolas/aac/mr;
/*    */     //   154: return
/*    */     // Line number table:
/*    */     //   Java source line number -> byte code offset
/*    */     //   #47	-> 30
/*    */     //   #1	-> 34
/*    */     //   #43	-> 51
/*    */     //   #46	-> 61
/*    */     //   #32	-> 69
/*    */     //   #36	-> 77
/*    */     //   #55	-> 109
/*    */     //   #2	-> 129
/*    */     //   #3	-> 143
/*    */     //   #48	-> 154
/*    */     // Exception table:
/*    */     //   from	to	target	type
/*    */     //   61	95	98	java/lang/NullPointerException
/*    */     //   87	112	115	java/lang/NullPointerException
/*    */   }
/* 49 */   public k_ a(String paramString1, long paramLong, byte paramByte, String paramString2) { long l1 = (paramLong << 8L | paramByte << 56L >>> 56L) ^ f, l2 = l1 ^ 0x2FB2D58C3BA0L; this.c.b(l2, paramString1, paramString2);
/*    */     return this; } public k_ c(jR paramjR, long paramLong) {
/*    */     // Byte code:
/*    */     //   0: getstatic me/konsolas/aac/k_.f : J
/*    */     //   3: lload_2
/*    */     //   4: lxor
/*    */     //   5: lstore_2
/*    */     //   6: lload_2
/*    */     //   7: dup2
/*    */     //   8: ldc2_w 119976746124851
/*    */     //   11: lxor
/*    */     //   12: lstore #4
/*    */     //   14: pop2
/*    */     //   15: aload_0
/*    */     //   16: sipush #11972
/*    */     //   19: ldc2_w 4956978209502442890
/*    */     //   22: lload_2
/*    */     //   23: lxor
/*    */     //   24: <illegal opcode> p : (IJ)Ljava/lang/String;
/*    */     //   29: lload #4
/*    */     //   31: aload_1
/*    */     //   32: invokevirtual a : (Ljava/lang/String;JLme/konsolas/aac/jR;)Lme/konsolas/aac/k_;
/*    */     //   35: areturn
/*    */     // Line number table:
/*    */     //   Java source line number -> byte code offset
/*    */     //   #51	-> 15
/*    */   }
/* 53 */   public k_ b(String paramString1, String paramString2, long paramLong) { paramLong = f ^ paramLong; long l = paramLong ^ 0x25A39BB67640L; this.c.d(paramString1, paramString2, l);
/*    */     return this; } public k_ a(URL paramURL, long paramLong) { // Byte code:
/*    */     //   0: getstatic me/konsolas/aac/k_.f : J
/*    */     //   3: lload_2
/*    */     //   4: lxor
/*    */     //   5: lstore_2
/*    */     //   6: lload_2
/*    */     //   7: dup2
/*    */     //   8: ldc2_w 19494290127064
/*    */     //   11: lxor
/*    */     //   12: lstore #4
/*    */     //   14: dup2
/*    */     //   15: ldc2_w 74459683639903
/*    */     //   18: lxor
/*    */     //   19: lstore #6
/*    */     //   21: pop2
/*    */     //   22: aload_1
/*    */     //   23: ifnonnull -> 57
/*    */     //   26: new java/lang/NullPointerException
/*    */     //   29: dup
/*    */     //   30: sipush #8521
/*    */     //   33: ldc2_w 7777132264550867614
/*    */     //   36: lload_2
/*    */     //   37: lxor
/*    */     //   38: <illegal opcode> p : (IJ)Ljava/lang/String;
/*    */     //   43: invokespecial <init> : (Ljava/lang/String;)V
/*    */     //   46: athrow
/*    */     //   47: ldc2_w 4207840056152509236
/*    */     //   50: lload_2
/*    */     //   51: <illegal opcode> w : (Ljava/lang/NullPointerException;JJ)Ljava/lang/NullPointerException;
/*    */     //   56: athrow
/*    */     //   57: aload_0
/*    */     //   58: aload_1
/*    */     //   59: invokevirtual toString : ()Ljava/lang/String;
/*    */     //   62: lload #4
/*    */     //   64: invokestatic c : (Ljava/lang/String;J)Lme/konsolas/aac/l6;
/*    */     //   67: lload #6
/*    */     //   69: invokevirtual a : (Lme/konsolas/aac/l6;J)Lme/konsolas/aac/k_;
/*    */     //   72: areturn
/*    */     // Line number table:
/*    */     //   Java source line number -> byte code offset
/*    */     //   #54	-> 22
/*    */     //   #52	-> 57
/*    */     // Exception table:
/*    */     //   from	to	target	type
/*    */     //   22	47	47	java/lang/NullPointerException } public k_ d(long paramLong, @Nullable jR paramjR) {
/*    */     // Byte code:
/*    */     //   0: getstatic me/konsolas/aac/k_.f : J
/*    */     //   3: lload_1
/*    */     //   4: lxor
/*    */     //   5: lstore_1
/*    */     //   6: lload_1
/*    */     //   7: dup2
/*    */     //   8: ldc2_w 84462874499650
/*    */     //   11: lxor
/*    */     //   12: lstore #4
/*    */     //   14: pop2
/*    */     //   15: aload_0
/*    */     //   16: sipush #30292
/*    */     //   19: ldc2_w 3853102254470721905
/*    */     //   22: lload_1
/*    */     //   23: lxor
/*    */     //   24: <illegal opcode> p : (IJ)Ljava/lang/String;
/*    */     //   29: lload #4
/*    */     //   31: aload_3
/*    */     //   32: invokevirtual a : (Ljava/lang/String;JLme/konsolas/aac/jR;)Lme/konsolas/aac/k_;
/*    */     //   35: areturn
/*    */     // Line number table:
/*    */     //   Java source line number -> byte code offset
/*    */     //   #58	-> 15
/*    */   } public k_ c(long paramLong) {
/*    */     // Byte code:
/*    */     //   0: getstatic me/konsolas/aac/k_.f : J
/*    */     //   3: lload_1
/*    */     //   4: lxor
/*    */     //   5: lstore_1
/*    */     //   6: lload_1
/*    */     //   7: dup2
/*    */     //   8: ldc2_w 84111468326268
/*    */     //   11: lxor
/*    */     //   12: lstore_3
/*    */     //   13: pop2
/*    */     //   14: aload_0
/*    */     //   15: sipush #32662
/*    */     //   18: ldc2_w 4254168586158018451
/*    */     //   21: lload_1
/*    */     //   22: lxor
/*    */     //   23: <illegal opcode> p : (IJ)Ljava/lang/String;
/*    */     //   28: lload_3
/*    */     //   29: aconst_null
/*    */     //   30: invokevirtual a : (Ljava/lang/String;JLme/konsolas/aac/jR;)Lme/konsolas/aac/k_;
/*    */     //   33: areturn
/*    */     // Line number table:
/*    */     //   Java source line number -> byte code offset
/*    */     //   #59	-> 14
/*    */   }
/*    */   public k_ a(J paramJ) {
/* 60 */     this.c = paramJ.a();
/*    */     return this;
/*    */   }
/*    */   
/*    */   public k_ a(String paramString, long paramLong, @Nullable jR paramjR) {
/*    */     // Byte code:
/*    */     //   0: getstatic me/konsolas/aac/k_.f : J
/*    */     //   3: lload_2
/*    */     //   4: lxor
/*    */     //   5: lstore_2
/*    */     //   6: lload_2
/*    */     //   7: dup2
/*    */     //   8: ldc2_w 69759192361706
/*    */     //   11: lxor
/*    */     //   12: dup2
/*    */     //   13: bipush #48
/*    */     //   15: lushr
/*    */     //   16: l2i
/*    */     //   17: istore #5
/*    */     //   19: dup2
/*    */     //   20: bipush #16
/*    */     //   22: lshl
/*    */     //   23: bipush #32
/*    */     //   25: lushr
/*    */     //   26: l2i
/*    */     //   27: istore #6
/*    */     //   29: dup2
/*    */     //   30: bipush #48
/*    */     //   32: lshl
/*    */     //   33: bipush #48
/*    */     //   35: lushr
/*    */     //   36: l2i
/*    */     //   37: istore #7
/*    */     //   39: pop2
/*    */     //   40: dup2
/*    */     //   41: ldc2_w 21849589756201
/*    */     //   44: lxor
/*    */     //   45: lstore #8
/*    */     //   47: pop2
/*    */     //   48: ldc2_w -581019410056546515
/*    */     //   51: lload_2
/*    */     //   52: <illegal opcode> w : (JJ)[Lme/konsolas/aac/aN;
/*    */     //   57: astore #10
/*    */     //   59: aload_1
/*    */     //   60: aload #10
/*    */     //   62: ifnonnull -> 113
/*    */     //   65: ifnonnull -> 112
/*    */     //   68: goto -> 81
/*    */     //   71: ldc2_w -668694499526932503
/*    */     //   74: lload_2
/*    */     //   75: <illegal opcode> w : (Ljava/lang/NullPointerException;JJ)Ljava/lang/NullPointerException;
/*    */     //   80: athrow
/*    */     //   81: new java/lang/NullPointerException
/*    */     //   84: dup
/*    */     //   85: sipush #17895
/*    */     //   88: ldc2_w 7645511710108191462
/*    */     //   91: lload_2
/*    */     //   92: lxor
/*    */     //   93: <illegal opcode> p : (IJ)Ljava/lang/String;
/*    */     //   98: invokespecial <init> : (Ljava/lang/String;)V
/*    */     //   101: athrow
/*    */     //   102: ldc2_w -668694499526932503
/*    */     //   105: lload_2
/*    */     //   106: <illegal opcode> w : (Ljava/lang/NullPointerException;JJ)Ljava/lang/NullPointerException;
/*    */     //   111: athrow
/*    */     //   112: aload_1
/*    */     //   113: invokevirtual length : ()I
/*    */     //   116: ifne -> 150
/*    */     //   119: new java/lang/IllegalArgumentException
/*    */     //   122: dup
/*    */     //   123: sipush #23958
/*    */     //   126: ldc2_w 5485720367763395226
/*    */     //   129: lload_2
/*    */     //   130: lxor
/*    */     //   131: <illegal opcode> p : (IJ)Ljava/lang/String;
/*    */     //   136: invokespecial <init> : (Ljava/lang/String;)V
/*    */     //   139: athrow
/*    */     //   140: ldc2_w -668694499526932503
/*    */     //   143: lload_2
/*    */     //   144: <illegal opcode> w : (Ljava/lang/NullPointerException;JJ)Ljava/lang/NullPointerException;
/*    */     //   149: athrow
/*    */     //   150: aload #4
/*    */     //   152: lload_2
/*    */     //   153: lconst_0
/*    */     //   154: lcmp
/*    */     //   155: iflt -> 273
/*    */     //   158: aload #10
/*    */     //   160: ifnonnull -> 273
/*    */     //   163: ifnull -> 271
/*    */     //   166: goto -> 179
/*    */     //   169: ldc2_w -668694499526932503
/*    */     //   172: lload_2
/*    */     //   173: <illegal opcode> w : (Ljava/lang/NullPointerException;JJ)Ljava/lang/NullPointerException;
/*    */     //   178: athrow
/*    */     //   179: aload_1
/*    */     //   180: iload #5
/*    */     //   182: i2s
/*    */     //   183: iload #6
/*    */     //   185: iload #7
/*    */     //   187: i2c
/*    */     //   188: invokestatic e : (Ljava/lang/String;SIC)Z
/*    */     //   191: ifne -> 271
/*    */     //   194: goto -> 207
/*    */     //   197: ldc2_w -668694499526932503
/*    */     //   200: lload_2
/*    */     //   201: <illegal opcode> w : (Ljava/lang/NullPointerException;JJ)Ljava/lang/NullPointerException;
/*    */     //   206: athrow
/*    */     //   207: new java/lang/IllegalArgumentException
/*    */     //   210: dup
/*    */     //   211: new java/lang/StringBuilder
/*    */     //   214: dup
/*    */     //   215: invokespecial <init> : ()V
/*    */     //   218: sipush #31323
/*    */     //   221: ldc2_w 9079794654751470937
/*    */     //   224: lload_2
/*    */     //   225: lxor
/*    */     //   226: <illegal opcode> p : (IJ)Ljava/lang/String;
/*    */     //   231: invokevirtual append : (Ljava/lang/String;)Ljava/lang/StringBuilder;
/*    */     //   234: aload_1
/*    */     //   235: invokevirtual append : (Ljava/lang/String;)Ljava/lang/StringBuilder;
/*    */     //   238: sipush #3093
/*    */     //   241: ldc2_w 4471260436055933718
/*    */     //   244: lload_2
/*    */     //   245: lxor
/*    */     //   246: <illegal opcode> p : (IJ)Ljava/lang/String;
/*    */     //   251: invokevirtual append : (Ljava/lang/String;)Ljava/lang/StringBuilder;
/*    */     //   254: invokevirtual toString : ()Ljava/lang/String;
/*    */     //   257: invokespecial <init> : (Ljava/lang/String;)V
/*    */     //   260: athrow
/*    */     //   261: ldc2_w -668694499526932503
/*    */     //   264: lload_2
/*    */     //   265: <illegal opcode> w : (Ljava/lang/NullPointerException;JJ)Ljava/lang/NullPointerException;
/*    */     //   270: athrow
/*    */     //   271: aload #4
/*    */     //   273: ifnonnull -> 362
/*    */     //   276: lload #8
/*    */     //   278: aload_1
/*    */     //   279: invokestatic d : (JLjava/lang/String;)Z
/*    */     //   282: ifeq -> 362
/*    */     //   285: goto -> 298
/*    */     //   288: ldc2_w -668694499526932503
/*    */     //   291: lload_2
/*    */     //   292: <illegal opcode> w : (Ljava/lang/NullPointerException;JJ)Ljava/lang/NullPointerException;
/*    */     //   297: athrow
/*    */     //   298: new java/lang/IllegalArgumentException
/*    */     //   301: dup
/*    */     //   302: new java/lang/StringBuilder
/*    */     //   305: dup
/*    */     //   306: invokespecial <init> : ()V
/*    */     //   309: sipush #6652
/*    */     //   312: ldc2_w 8194703023564478200
/*    */     //   315: lload_2
/*    */     //   316: lxor
/*    */     //   317: <illegal opcode> p : (IJ)Ljava/lang/String;
/*    */     //   322: invokevirtual append : (Ljava/lang/String;)Ljava/lang/StringBuilder;
/*    */     //   325: aload_1
/*    */     //   326: invokevirtual append : (Ljava/lang/String;)Ljava/lang/StringBuilder;
/*    */     //   329: sipush #21809
/*    */     //   332: ldc2_w 5021143900478151226
/*    */     //   335: lload_2
/*    */     //   336: lxor
/*    */     //   337: <illegal opcode> p : (IJ)Ljava/lang/String;
/*    */     //   342: invokevirtual append : (Ljava/lang/String;)Ljava/lang/StringBuilder;
/*    */     //   345: invokevirtual toString : ()Ljava/lang/String;
/*    */     //   348: invokespecial <init> : (Ljava/lang/String;)V
/*    */     //   351: athrow
/*    */     //   352: ldc2_w -668694499526932503
/*    */     //   355: lload_2
/*    */     //   356: <illegal opcode> w : (Ljava/lang/NullPointerException;JJ)Ljava/lang/NullPointerException;
/*    */     //   361: athrow
/*    */     //   362: aload_0
/*    */     //   363: aload_1
/*    */     //   364: putfield a : Ljava/lang/String;
/*    */     //   367: aload_0
/*    */     //   368: aload #4
/*    */     //   370: putfield d : Lme/konsolas/aac/jR;
/*    */     //   373: aload_0
/*    */     //   374: areturn
/*    */     // Line number table:
/*    */     //   Java source line number -> byte code offset
/*    */     //   #61	-> 59
/*    */     //   #24	-> 112
/*    */     //   #14	-> 150
/*    */     //   #5	-> 207
/*    */     //   #26	-> 271
/*    */     //   #18	-> 298
/*    */     //   #44	-> 362
/*    */     //   #62	-> 367
/*    */     //   #29	-> 373
/*    */     // Exception table:
/*    */     //   from	to	target	type
/*    */     //   59	68	71	java/lang/NullPointerException
/*    */     //   65	102	102	java/lang/NullPointerException
/*    */     //   113	140	140	java/lang/NullPointerException
/*    */     //   150	166	169	java/lang/NullPointerException
/*    */     //   163	194	197	java/lang/NullPointerException
/*    */     //   179	261	261	java/lang/NullPointerException
/*    */     //   273	285	288	java/lang/NullPointerException
/*    */     //   276	352	352	java/lang/NullPointerException
/*    */   }
/*    */   
/*    */   static {
/*    */     long l = f ^ 0x19C578C04761L;
/*    */     "콞翅ﮰꯈ㦖＿ࠫ૑ꔦ锰๕舴貤坥采숳춣ሇ".toCharArray()[3] = (char)("콞翅ﮰꯈ㦖＿ࠫ૑ꔦ锰๕舴貤坥采숳춣ሇ".toCharArray()[3] ^ 0x732D);
/*    */     "᱕ࡋၡ焇".toCharArray()[1] = (char)("᱕ࡋၡ焇".toCharArray()[1] ^ 0x18FC);
/*    */     (new byte[8])[0] = (byte)(int)(l >>> 56L);
/*    */     for (byte b1 = 1; b1 < 8; b1++)
/*    */       (new byte[8])[b1] = (byte)(int)(l << b1 * 8 >>> 56L); 
/*    */     Cipher cipher;
/*    */     (cipher = Cipher.getInstance(a0$cc.G("콞翅ﮰꯈ㦖＿ࠫ૑ꔦ锰๕舴貤坥采숳춣ሇ".toCharArray(), (short)18080, false, (byte)0))).init(2, SecretKeyFactory.getInstance(a0$cc.G("᱕ࡋၡ焇".toCharArray(), (short)3205, false, (byte)0)).generateSecret(new DESKeySpec(new byte[8])), new IvParameterSpec(new byte[8]));
/*    */     String[] arrayOfString = new String[22];
/*    */     boolean bool = false;
/*    */     "泜湧邺䍀⦨얡귪阚⵶栁◬㱓媪᫅嚽⭶ｘ઎㛵㙲䵗?⋹嗆៪⛾Ɯլ턛웟띞㝖모ᚆ鋈朝?綗㣯블鲯畾鼺벾Ủ೛詹ꂁ?䡾ퟳ瑔ॲ䞂㏣減馈쾻鼤竴賱䭁괳⸹ꊔ⛌壵㸚沫豞匣뱬ୄឿ䢮贗ᵭꅼǺ࿳ࠂ㡏憿气㤁᱇袉䁇?䷱꿄郷ꃬ挾蜕ꊱ䏂壼痃㡆洠᳎뤛⺇붮哞賾㪎ం䭀ᷣ雭롿跱蚻왜颱ꚿ?⋧屋䑅歙蝵ᴮ雿ꆝ乼뾆줆◰╵菮靿瞡㓫銬蠂㐙ิ┤ꦩ쩡ທ顇䆷ꩩ峯쳾䂼檽膴寄쾘쫻ე웬퐬㢀ꎫl뮱?췓탠ﱺꎠ眘왁Ⓣ矴鑚弸䕱㹎릩緪㸠奸蒑㡚캠帠荮ᚢ権젼䰹꾷ﱒᱸ節?⴪缌ᆑ㯿거⤁ɻᦾÉ죢▄㥆ᴉ雿鉜읰☻ﰺॆ棬舋箍ᾈꜟ䔤简㚇ⳡ㢦燭큛雳ᆵ⻲㥏彚ꉃ譬茘ᶍ츎╗豢➉⅃臚教䘰꯮६˗璀奕뮏鐡抆⢓┝㟶ؽ圤猤ీ瀹៦ⰰꭕ萒徫㬨孞읖ꍼⱒꪘᗝ⡆踑㩥Ẳ齶畻ꃙ৹쿀ᅯ祼ﰏ㣖邅⻴먽뺐誢麒〝惲떻袊췰蠮鋿왌㚙ᅈⅎ峩걢瀞횴㼆굑퓗敻咶䥎⮌埲풅酛铯巜椲錙둾ꈉÃ耴?綕श䌅丧짟煪혷⵩়ꛘ쁱겷趥䠍햱┣挟賓贘䲤趆릫닀?躒㢏徧㳽?੩醽鬏뙬像ࠥ嗙礞濥㒭쮂訐⇂힟寁꫈绘㌖⏈ꋽ嶻⢡?떊倾갆骼ﬥ獭꣧夾㹊ዩ?ꚝ듄ﻼᘸ꾻ᵸ롮᷺뛴㡙ዃ넲ខ訥䈇庶䢩惊䚌꿹᫓Ӡ離?퐪㧛盟?ൟ婾䂻칛匧ﺛᏗ⯡六둧獠耚ཙ굋艩脨쥓䞶ᤇ䡢前囘ⶄ籦旮譫䃤殶?籡텇ꎖ㗾駿᧔պ嬢ﱊୟꦈ쾽邺瑂랮嗀敼".toCharArray()[386] = (char)("泜湧邺䍀⦨얡귪阚⵶栁◬㱓媪᫅嚽⭶ｘ઎㛵㙲䵗?⋹嗆៪⛾Ɯլ턛웟띞㝖모ᚆ鋈朝?綗㣯블鲯畾鼺벾Ủ೛詹ꂁ?䡾ퟳ瑔ॲ䞂㏣減馈쾻鼤竴賱䭁괳⸹ꊔ⛌壵㸚沫豞匣뱬ୄឿ䢮贗ᵭꅼǺ࿳ࠂ㡏憿气㤁᱇袉䁇?䷱꿄郷ꃬ挾蜕ꊱ䏂壼痃㡆洠᳎뤛⺇붮哞賾㪎ం䭀ᷣ雭롿跱蚻왜颱ꚿ?⋧屋䑅歙蝵ᴮ雿ꆝ乼뾆줆◰╵菮靿瞡㓫銬蠂㐙ิ┤ꦩ쩡ທ顇䆷ꩩ峯쳾䂼檽膴寄쾘쫻ე웬퐬㢀ꎫl뮱?췓탠ﱺꎠ眘왁Ⓣ矴鑚弸䕱㹎릩緪㸠奸蒑㡚캠帠荮ᚢ権젼䰹꾷ﱒᱸ節?⴪缌ᆑ㯿거⤁ɻᦾÉ죢▄㥆ᴉ雿鉜읰☻ﰺॆ棬舋箍ᾈꜟ䔤简㚇ⳡ㢦燭큛雳ᆵ⻲㥏彚ꉃ譬茘ᶍ츎╗豢➉⅃臚教䘰꯮६˗璀奕뮏鐡抆⢓┝㟶ؽ圤猤ీ瀹៦ⰰꭕ萒徫㬨孞읖ꍼⱒꪘᗝ⡆踑㩥Ẳ齶畻ꃙ৹쿀ᅯ祼ﰏ㣖邅⻴먽뺐誢麒〝惲떻袊췰蠮鋿왌㚙ᅈⅎ峩걢瀞횴㼆굑퓗敻咶䥎⮌埲풅酛铯巜椲錙둾ꈉÃ耴?綕श䌅丧짟煪혷⵩়ꛘ쁱겷趥䠍햱┣挟賓贘䲤趆릫닀?躒㢏徧㳽?੩醽鬏뙬像ࠥ嗙礞濥㒭쮂訐⇂힟寁꫈绘㌖⏈ꋽ嶻⢡?떊倾갆骼ﬥ獭꣧夾㹊ዩ?ꚝ듄ﻼᘸ꾻ᵸ롮᷺뛴㡙ዃ넲ខ訥䈇庶䢩惊䚌꿹᫓Ӡ離?퐪㧛盟?ൟ婾䂻칛匧ﺛᏗ⯡六둧獠耚ཙ굋艩脨쥓䞶ᤇ䡢前囘ⶄ籦旮譫䃤殶?籡텇ꎖ㗾駿᧔պ嬢ﱊୟꦈ쾽邺瑂랮嗀敼".toCharArray()[386] ^ 0x5A83);
/*    */     String str;
/*    */     int i = (str = a0$cc.G("泜湧邺䍀⦨얡귪阚⵶栁◬㱓媪᫅嚽⭶ｘ઎㛵㙲䵗?⋹嗆៪⛾Ɯլ턛웟띞㝖모ᚆ鋈朝?綗㣯블鲯畾鼺벾Ủ೛詹ꂁ?䡾ퟳ瑔ॲ䞂㏣減馈쾻鼤竴賱䭁괳⸹ꊔ⛌壵㸚沫豞匣뱬ୄឿ䢮贗ᵭꅼǺ࿳ࠂ㡏憿气㤁᱇袉䁇?䷱꿄郷ꃬ挾蜕ꊱ䏂壼痃㡆洠᳎뤛⺇붮哞賾㪎ం䭀ᷣ雭롿跱蚻왜颱ꚿ?⋧屋䑅歙蝵ᴮ雿ꆝ乼뾆줆◰╵菮靿瞡㓫銬蠂㐙ิ┤ꦩ쩡ທ顇䆷ꩩ峯쳾䂼檽膴寄쾘쫻ე웬퐬㢀ꎫl뮱?췓탠ﱺꎠ眘왁Ⓣ矴鑚弸䕱㹎릩緪㸠奸蒑㡚캠帠荮ᚢ権젼䰹꾷ﱒᱸ節?⴪缌ᆑ㯿거⤁ɻᦾÉ죢▄㥆ᴉ雿鉜읰☻ﰺॆ棬舋箍ᾈꜟ䔤简㚇ⳡ㢦燭큛雳ᆵ⻲㥏彚ꉃ譬茘ᶍ츎╗豢➉⅃臚教䘰꯮६˗璀奕뮏鐡抆⢓┝㟶ؽ圤猤ీ瀹៦ⰰꭕ萒徫㬨孞읖ꍼⱒꪘᗝ⡆踑㩥Ẳ齶畻ꃙ৹쿀ᅯ祼ﰏ㣖邅⻴먽뺐誢麒〝惲떻袊췰蠮鋿왌㚙ᅈⅎ峩걢瀞횴㼆굑퓗敻咶䥎⮌埲풅酛铯巜椲錙둾ꈉÃ耴?綕श䌅丧짟煪혷⵩়ꛘ쁱겷趥䠍햱┣挟賓贘䲤趆릫닀?躒㢏徧㳽?੩醽鬏뙬像ࠥ嗙礞濥㒭쮂訐⇂힟寁꫈绘㌖⏈ꋽ嶻⢡?떊倾갆骼ﬥ獭꣧夾㹊ዩ?ꚝ듄ﻼᘸ꾻ᵸ롮᷺뛴㡙ዃ넲ខ訥䈇庶䢩惊䚌꿹᫓Ӡ離?퐪㧛盟?ൟ婾䂻칛匧ﺛᏗ⯡六둧獠耚ཙ굋艩脨쥓䞶ᤇ䡢前囘ⶄ籦旮譫䃤殶?籡텇ꎖ㗾駿᧔պ嬢ﱊୟꦈ쾽邺瑂랮嗀敼".toCharArray(), (short)20575, true, (byte)1)).length();
/*    */     byte b2 = 32;
/*    */     byte b = -1;
/*    */     while (true);
/*    */   }
/*    */   
/*    */   private static NullPointerException a(NullPointerException paramNullPointerException) {
/*    */     return paramNullPointerException;
/*    */   }
/*    */   
/*    */   private static String a(byte[] paramArrayOfbyte) {
/*    */     byte b1 = 0;
/*    */     int i;
/*    */     char[] arrayOfChar = new char[i = paramArrayOfbyte.length];
/*    */     for (byte b2 = 0; b2 < i; b2++) {
/*    */       int j;
/*    */       if ((j = 0xFF & paramArrayOfbyte[b2]) < 192) {
/*    */         arrayOfChar[b1++] = (char)j;
/*    */       } else if (j < 224) {
/*    */         char c = (char)((char)(j & 0x1F) << 6);
/*    */         j = paramArrayOfbyte[++b2];
/*    */         c = (char)(c | (char)(j & 0x3F));
/*    */         arrayOfChar[b1++] = c;
/*    */       } else if (b2 < i - 2) {
/*    */         char c = (char)((char)(j & 0xF) << 12);
/*    */         j = paramArrayOfbyte[++b2];
/*    */         c = (char)(c | (char)(j & 0x3F) << 6);
/*    */         j = paramArrayOfbyte[++b2];
/*    */         c = (char)(c | (char)(j & 0x3F));
/*    */         arrayOfChar[b1++] = c;
/*    */       } 
/*    */     } 
/*    */     return new String(arrayOfChar, 0, b1);
/*    */   }
/*    */   
/*    */   private static String a(int paramInt, long paramLong) {
/*    */     int i = paramInt ^ (int)(paramLong & 0x7FFFL) ^ 0x3801;
/*    */     if (h[i] == null) {
/*    */       Object[] arrayOfObject;
/*    */       try {
/*    */         Long long_ = Long.valueOf(Thread.currentThread().getId());
/*    */         arrayOfObject = (Object[])i.get(long_);
/*    */         if (arrayOfObject == null) {
/*    */           arrayOfObject = new Object[3];
/*    */           "伽藮锼燜睎덤념鯫쩹⪭轝᳔炡␲兄聝彄".toCharArray()[11] = (char)("伽藮锼燜睎덤념鯫쩹⪭轝᳔炡␲兄聝彄".toCharArray()[11] ^ 0x7AE6);
/*    */           arrayOfObject[0] = Cipher.getInstance(fW$gy.A("伽藮锼燜睎덤념鯫쩹⪭轝᳔炡␲兄聝彄".toCharArray(), (short)27550, true, 3));
/*    */           "Ⅻ깸䍚".toCharArray()[1] = (char)("Ⅻ깸䍚".toCharArray()[1] ^ 0x56D0);
/*    */           arrayOfObject[1] = SecretKeyFactory.getInstance(fW$gy.A("Ⅻ깸䍚".toCharArray(), (short)16317, true, 0));
/*    */           arrayOfObject[2] = new IvParameterSpec(new byte[8]);
/*    */           i.put(long_, arrayOfObject);
/*    */         } 
/*    */       } catch (Exception exception) {
/*    */         "뫘䬆꾆냃聳匱堎洌堽歩쒈ᜫꋧ\033礸锂ᇋ˂".toCharArray()[3] = (char)("뫘䬆꾆냃聳匱堎洌堽歩쒈ᜫꋧ\033礸锂ᇋ˂".toCharArray()[3] ^ 0x3C53);
/*    */         throw new RuntimeException(fW$gy.A("뫘䬆꾆냃聳匱堎洌堽歩쒈ᜫꋧ\033礸锂ᇋ˂".toCharArray(), (short)124, true, 3), exception);
/*    */       } 
/*    */       byte[] arrayOfByte1 = new byte[8];
/*    */       arrayOfByte1[0] = (byte)(int)(paramLong >>> 56L);
/*    */       for (byte b = 1; b < 8; b++)
/*    */         arrayOfByte1[b] = (byte)(int)(paramLong << b * 8 >>> 56L); 
/*    */       DESKeySpec dESKeySpec = new DESKeySpec(arrayOfByte1);
/*    */       SecretKey secretKey = ((SecretKeyFactory)arrayOfObject[1]).generateSecret(dESKeySpec);
/*    */       ((Cipher)arrayOfObject[0]).init(2, secretKey, (IvParameterSpec)arrayOfObject[2]);
/*    */       "웶⬆쮡蔲愢㴵瑻翚ต拖".toCharArray()[1] = (char)("웶⬆쮡蔲愢㴵瑻翚ต拖".toCharArray()[1] ^ 0x6B02);
/*    */       byte[] arrayOfByte2 = g[i].getBytes(fW$gy.A("웶⬆쮡蔲愢㴵瑻翚ต拖".toCharArray(), (short)19176, false, 1));
/*    */       h[i] = a(((Cipher)arrayOfObject[0]).doFinal(arrayOfByte2));
/*    */     } 
/*    */     return h[i];
/*    */   }
/*    */   
/*    */   private static Object a(MethodHandles.Lookup paramLookup, MutableCallSite paramMutableCallSite, String paramString, Object[] paramArrayOfObject) {
/*    */     int i = ((Integer)paramArrayOfObject[0]).intValue();
/*    */     long l = ((Long)paramArrayOfObject[1]).longValue();
/*    */     String str = a(i, l);
/*    */     MethodHandle methodHandle = MethodHandles.constant(String.class, str);
/*    */     paramMutableCallSite.setTarget(MethodHandles.dropArguments(methodHandle, 0, new Class[] { int.class, long.class }));
/*    */     return str;
/*    */   }
/*    */   
/*    */   private static CallSite a(MethodHandles.Lookup paramLookup, String paramString, MethodType paramMethodType) {
/*    */     // Byte code:
/*    */     //   0: new java/lang/invoke/MutableCallSite
/*    */     //   3: dup
/*    */     //   4: aload_2
/*    */     //   5: invokespecial <init> : (Ljava/lang/invoke/MethodType;)V
/*    */     //   8: astore_3
/*    */     //   9: aload_3
/*    */     //   10: ldc_w
/*    */     //   13: ldc_w [Ljava/lang/Object;
/*    */     //   16: aload_2
/*    */     //   17: invokevirtual parameterCount : ()I
/*    */     //   20: invokevirtual asCollector : (Ljava/lang/Class;I)Ljava/lang/invoke/MethodHandle;
/*    */     //   23: iconst_0
/*    */     //   24: iconst_3
/*    */     //   25: anewarray java/lang/Object
/*    */     //   28: dup
/*    */     //   29: iconst_0
/*    */     //   30: aload_0
/*    */     //   31: aastore
/*    */     //   32: dup
/*    */     //   33: iconst_1
/*    */     //   34: aload_3
/*    */     //   35: aastore
/*    */     //   36: dup
/*    */     //   37: iconst_2
/*    */     //   38: aload_1
/*    */     //   39: aastore
/*    */     //   40: invokestatic insertArguments : (Ljava/lang/invoke/MethodHandle;I[Ljava/lang/Object;)Ljava/lang/invoke/MethodHandle;
/*    */     //   43: aload_2
/*    */     //   44: invokestatic explicitCastArguments : (Ljava/lang/invoke/MethodHandle;Ljava/lang/invoke/MethodType;)Ljava/lang/invoke/MethodHandle;
/*    */     //   47: invokevirtual setTarget : (Ljava/lang/invoke/MethodHandle;)V
/*    */     //   50: goto -> 170
/*    */     //   53: astore #4
/*    */     //   55: new java/lang/RuntimeException
/*    */     //   58: dup
/*    */     //   59: new java/lang/StringBuilder
/*    */     //   62: dup
/*    */     //   63: invokespecial <init> : ()V
/*    */     //   66: ldc_w '䇉⶚浂㱹䡟ꗉ瘈딢괋ᬼ翣먡摡᫽쮟䪤'
/*    */     //   69: invokevirtual toCharArray : ()[C
/*    */     //   72: dup
/*    */     //   73: dup
/*    */     //   74: iconst_4
/*    */     //   75: dup_x1
/*    */     //   76: caload
/*    */     //   77: sipush #11115
/*    */     //   80: ixor
/*    */     //   81: i2c
/*    */     //   82: castore
/*    */     //   83: sipush #10453
/*    */     //   86: iconst_0
/*    */     //   87: iconst_1
/*    */     //   88: invokestatic U : (Ljava/lang/Object;SZZ)Ljava/lang/String;
/*    */     //   91: invokevirtual append : (Ljava/lang/String;)Ljava/lang/StringBuilder;
/*    */     //   94: ldc_w '?庩縘琇'
/*    */     //   97: invokevirtual toCharArray : ()[C
/*    */     //   100: dup
/*    */     //   101: dup
/*    */     //   102: iconst_1
/*    */     //   103: dup_x1
/*    */     //   104: caload
/*    */     //   105: sipush #32489
/*    */     //   108: ixor
/*    */     //   109: i2c
/*    */     //   110: castore
/*    */     //   111: sipush #31277
/*    */     //   114: iconst_0
/*    */     //   115: iconst_0
/*    */     //   116: invokestatic U : (Ljava/lang/Object;SZZ)Ljava/lang/String;
/*    */     //   119: invokevirtual append : (Ljava/lang/String;)Ljava/lang/StringBuilder;
/*    */     //   122: aload_1
/*    */     //   123: invokevirtual append : (Ljava/lang/String;)Ljava/lang/StringBuilder;
/*    */     //   126: ldc_w '乕ꥫ⬔䢁'
/*    */     //   129: invokevirtual toCharArray : ()[C
/*    */     //   132: dup
/*    */     //   133: dup
/*    */     //   134: iconst_1
/*    */     //   135: dup_x1
/*    */     //   136: caload
/*    */     //   137: sipush #22348
/*    */     //   140: ixor
/*    */     //   141: i2c
/*    */     //   142: castore
/*    */     //   143: sipush #24128
/*    */     //   146: iconst_1
/*    */     //   147: iconst_0
/*    */     //   148: invokestatic U : (Ljava/lang/Object;SZZ)Ljava/lang/String;
/*    */     //   151: invokevirtual append : (Ljava/lang/String;)Ljava/lang/StringBuilder;
/*    */     //   154: aload_2
/*    */     //   155: invokevirtual toString : ()Ljava/lang/String;
/*    */     //   158: invokevirtual append : (Ljava/lang/String;)Ljava/lang/StringBuilder;
/*    */     //   161: invokevirtual toString : ()Ljava/lang/String;
/*    */     //   164: aload #4
/*    */     //   166: invokespecial <init> : (Ljava/lang/String;Ljava/lang/Throwable;)V
/*    */     //   169: athrow
/*    */     //   170: aload_3
/*    */     //   171: areturn
/*    */     // Exception table:
/*    */     //   from	to	target	type
/*    */     //   9	50	53	java/lang/Exception
/*    */   }
/*    */ }


/* Location:              C:\Users\BukkitBypass\Desktop\MatrixAC\AAC\AAC-spigot-5.2.0.jar!\me\konsolas\aac\k_.class
 * Java compiler version: 8 (52.0)
 * JD-Core Version:       1.1.3
 */