/*    */ package me.konsolas.aac;
/*    */ public final class kd { boolean a; @Nullable
/*    */   String[] b; @Nullable
/*    */   String[] c; boolean d;
/*    */   
/*  6 */   kd(boolean paramBoolean) { this.a = paramBoolean; }
/*    */   private static final long e = nc.a(2360935625387167630L, -2610098089056670968L, MethodHandles.lookup().lookupClass()).a(260793152423757L); private static final String[] f; private static final String[] g; private static final Map h = new HashMap<>(13); public kd a(fn[] paramArrayOffn, long paramLong) { // Byte code:
/*    */     //   0: getstatic me/konsolas/aac/kd.e : J
/*    */     //   3: lload_2
/*    */     //   4: lxor
/*    */     //   5: lstore_2
/*    */     //   6: lload_2
/*    */     //   7: dup2
/*    */     //   8: ldc2_w 124321869642348
/*    */     //   11: lxor
/*    */     //   12: lstore #4
/*    */     //   14: pop2
/*    */     //   15: aload_0
/*    */     //   16: getfield a : Z
/*    */     //   19: ifne -> 53
/*    */     //   22: new java/lang/IllegalStateException
/*    */     //   25: dup
/*    */     //   26: sipush #31440
/*    */     //   29: ldc2_w 1161042994069691908
/*    */     //   32: lload_2
/*    */     //   33: lxor
/*    */     //   34: <illegal opcode> t : (IJ)Ljava/lang/String;
/*    */     //   39: invokespecial <init> : (Ljava/lang/String;)V
/*    */     //   42: athrow
/*    */     //   43: ldc2_w 1951955151576485355
/*    */     //   46: lload_2
/*    */     //   47: <illegal opcode> w : (Ljava/lang/IllegalStateException;JJ)Ljava/lang/IllegalStateException;
/*    */     //   52: athrow
/*    */     //   53: aload_1
/*    */     //   54: arraylength
/*    */     //   55: anewarray java/lang/String
/*    */     //   58: astore #6
/*    */     //   60: iconst_0
/*    */     //   61: istore #7
/*    */     //   63: iload #7
/*    */     //   65: aload_1
/*    */     //   66: arraylength
/*    */     //   67: if_icmpge -> 98
/*    */     //   70: aload #6
/*    */     //   72: iload #7
/*    */     //   74: aload_1
/*    */     //   75: iload #7
/*    */     //   77: aaload
/*    */     //   78: getfield bf : Ljava/lang/String;
/*    */     //   81: aastore
/*    */     //   82: iinc #7, 1
/*    */     //   85: goto -> 63
/*    */     //   88: ldc2_w 1951955151576485355
/*    */     //   91: lload_2
/*    */     //   92: <illegal opcode> w : (Ljava/lang/IllegalStateException;JJ)Ljava/lang/IllegalStateException;
/*    */     //   97: athrow
/*    */     //   98: aload_0
/*    */     //   99: aload #6
/*    */     //   101: lload #4
/*    */     //   103: invokevirtual b : ([Ljava/lang/String;J)Lme/konsolas/aac/kd;
/*    */     //   106: areturn
/*    */     // Line number table:
/*    */     //   Java source line number -> byte code offset
/*    */     //   #3	-> 15
/*    */     //   #40	-> 53
/*    */     //   #17	-> 60
/*    */     //   #2	-> 70
/*    */     //   #34	-> 82
/*    */     //   #9	-> 98
/*    */     // Exception table:
/*    */     //   from	to	target	type
/*    */     //   15	43	43	java/lang/IllegalStateException
/*    */     //   63	88	88	java/lang/IllegalStateException } public kB a() {
/*  8 */     return new kB(this); } public kd b(String[] paramArrayOfString, long paramLong) { // Byte code:
/*    */     //   0: getstatic me/konsolas/aac/kd.e : J
/*    */     //   3: lload_2
/*    */     //   4: lxor
/*    */     //   5: lstore_2
/*    */     //   6: aload_0
/*    */     //   7: getfield a : Z
/*    */     //   10: ifne -> 44
/*    */     //   13: new java/lang/IllegalStateException
/*    */     //   16: dup
/*    */     //   17: sipush #31783
/*    */     //   20: ldc2_w 1711302625301113616
/*    */     //   23: lload_2
/*    */     //   24: lxor
/*    */     //   25: <illegal opcode> t : (IJ)Ljava/lang/String;
/*    */     //   30: invokespecial <init> : (Ljava/lang/String;)V
/*    */     //   33: athrow
/*    */     //   34: ldc2_w 7562081057022393868
/*    */     //   37: lload_2
/*    */     //   38: <illegal opcode> w : (Ljava/lang/IllegalStateException;JJ)Ljava/lang/IllegalStateException;
/*    */     //   43: athrow
/*    */     //   44: lload_2
/*    */     //   45: lconst_0
/*    */     //   46: lcmp
/*    */     //   47: ifle -> 97
/*    */     //   50: aload_1
/*    */     //   51: arraylength
/*    */     //   52: ifne -> 86
/*    */     //   55: new java/lang/IllegalArgumentException
/*    */     //   58: dup
/*    */     //   59: sipush #30802
/*    */     //   62: ldc2_w 1231228641582002023
/*    */     //   65: lload_2
/*    */     //   66: lxor
/*    */     //   67: <illegal opcode> t : (IJ)Ljava/lang/String;
/*    */     //   72: invokespecial <init> : (Ljava/lang/String;)V
/*    */     //   75: athrow
/*    */     //   76: ldc2_w 7562081057022393868
/*    */     //   79: lload_2
/*    */     //   80: <illegal opcode> w : (Ljava/lang/IllegalStateException;JJ)Ljava/lang/IllegalStateException;
/*    */     //   85: athrow
/*    */     //   86: aload_0
/*    */     //   87: aload_1
/*    */     //   88: invokevirtual clone : ()Ljava/lang/Object;
/*    */     //   91: checkcast [Ljava/lang/String;
/*    */     //   94: putfield b : [Ljava/lang/String;
/*    */     //   97: aload_0
/*    */     //   98: areturn
/*    */     // Line number table:
/*    */     //   Java source line number -> byte code offset
/*    */     //   #12	-> 6
/*    */     //   #5	-> 44
/*    */     //   #26	-> 55
/*    */     //   #24	-> 86
/*    */     //   #21	-> 97
/*    */     // Exception table:
/*    */     //   from	to	target	type
/*    */     //   6	34	34	java/lang/IllegalStateException
/*    */     //   44	76	76	java/lang/IllegalStateException }
/*    */   public kd a(long paramLong) { // Byte code:
/*    */     //   0: getstatic me/konsolas/aac/kd.e : J
/*    */     //   3: lload_1
/*    */     //   4: lxor
/*    */     //   5: lstore_1
/*    */     //   6: ldc2_w 2536053652109468659
/*    */     //   9: lload_1
/*    */     //   10: <illegal opcode> w : (JJ)[Lme/konsolas/aac/aN;
/*    */     //   15: astore_3
/*    */     //   16: aload_0
/*    */     //   17: aload_3
/*    */     //   18: ifnonnull -> 77
/*    */     //   21: getfield a : Z
/*    */     //   24: ifne -> 71
/*    */     //   27: goto -> 40
/*    */     //   30: ldc2_w 2532598982044284376
/*    */     //   33: lload_1
/*    */     //   34: <illegal opcode> w : (Ljava/lang/IllegalStateException;JJ)Ljava/lang/IllegalStateException;
/*    */     //   39: athrow
/*    */     //   40: new java/lang/IllegalStateException
/*    */     //   43: dup
/*    */     //   44: sipush #31783
/*    */     //   47: ldc2_w 1711285770729316548
/*    */     //   50: lload_1
/*    */     //   51: lxor
/*    */     //   52: <illegal opcode> t : (IJ)Ljava/lang/String;
/*    */     //   57: invokespecial <init> : (Ljava/lang/String;)V
/*    */     //   60: athrow
/*    */     //   61: ldc2_w 2532598982044284376
/*    */     //   64: lload_1
/*    */     //   65: <illegal opcode> w : (Ljava/lang/IllegalStateException;JJ)Ljava/lang/IllegalStateException;
/*    */     //   70: athrow
/*    */     //   71: aload_0
/*    */     //   72: aconst_null
/*    */     //   73: putfield b : [Ljava/lang/String;
/*    */     //   76: aload_0
/*    */     //   77: areturn
/*    */     // Line number table:
/*    */     //   Java source line number -> byte code offset
/*    */     //   #15	-> 16
/*    */     //   #33	-> 71
/*    */     //   #27	-> 76
/*    */     // Exception table:
/*    */     //   from	to	target	type
/*    */     //   16	27	30	java/lang/IllegalStateException
/*    */     //   21	61	61	java/lang/IllegalStateException }
/*    */   public kd a(long paramLong, String[] paramArrayOfString) { // Byte code:
/*    */     //   0: getstatic me/konsolas/aac/kd.e : J
/*    */     //   3: lload_1
/*    */     //   4: lxor
/*    */     //   5: lstore_1
/*    */     //   6: aload_0
/*    */     //   7: getfield a : Z
/*    */     //   10: ifne -> 44
/*    */     //   13: new java/lang/IllegalStateException
/*    */     //   16: dup
/*    */     //   17: sipush #5883
/*    */     //   20: ldc2_w 2921174916560361867
/*    */     //   23: lload_1
/*    */     //   24: lxor
/*    */     //   25: <illegal opcode> t : (IJ)Ljava/lang/String;
/*    */     //   30: invokespecial <init> : (Ljava/lang/String;)V
/*    */     //   33: athrow
/*    */     //   34: ldc2_w -5714505099803728308
/*    */     //   37: lload_1
/*    */     //   38: <illegal opcode> w : (Ljava/lang/IllegalStateException;JJ)Ljava/lang/IllegalStateException;
/*    */     //   43: athrow
/*    */     //   44: lload_1
/*    */     //   45: lconst_0
/*    */     //   46: lcmp
/*    */     //   47: iflt -> 97
/*    */     //   50: aload_3
/*    */     //   51: arraylength
/*    */     //   52: ifne -> 86
/*    */     //   55: new java/lang/IllegalArgumentException
/*    */     //   58: dup
/*    */     //   59: sipush #6547
/*    */     //   62: ldc2_w 1019467384179922657
/*    */     //   65: lload_1
/*    */     //   66: lxor
/*    */     //   67: <illegal opcode> t : (IJ)Ljava/lang/String;
/*    */     //   72: invokespecial <init> : (Ljava/lang/String;)V
/*    */     //   75: athrow
/*    */     //   76: ldc2_w -5714505099803728308
/*    */     //   79: lload_1
/*    */     //   80: <illegal opcode> w : (Ljava/lang/IllegalStateException;JJ)Ljava/lang/IllegalStateException;
/*    */     //   85: athrow
/*    */     //   86: aload_0
/*    */     //   87: aload_3
/*    */     //   88: invokevirtual clone : ()Ljava/lang/Object;
/*    */     //   91: checkcast [Ljava/lang/String;
/*    */     //   94: putfield c : [Ljava/lang/String;
/*    */     //   97: aload_0
/*    */     //   98: areturn
/*    */     // Line number table:
/*    */     //   Java source line number -> byte code offset
/*    */     //   #25	-> 6
/*    */     //   #4	-> 44
/*    */     //   #32	-> 55
/*    */     //   #20	-> 86
/*    */     //   #37	-> 97
/*    */     // Exception table:
/*    */     //   from	to	target	type
/*    */     //   6	34	34	java/lang/IllegalStateException
/*    */     //   44	76	76	java/lang/IllegalStateException }
/*    */   public kd b(long paramLong) { // Byte code:
/*    */     //   0: getstatic me/konsolas/aac/kd.e : J
/*    */     //   3: lload_1
/*    */     //   4: lxor
/*    */     //   5: lstore_1
/*    */     //   6: ldc2_w 4471740405384101580
/*    */     //   9: lload_1
/*    */     //   10: <illegal opcode> w : (JJ)[Lme/konsolas/aac/aN;
/*    */     //   15: astore_3
/*    */     //   16: aload_0
/*    */     //   17: aload_3
/*    */     //   18: ifnonnull -> 77
/*    */     //   21: getfield a : Z
/*    */     //   24: ifne -> 71
/*    */     //   27: goto -> 40
/*    */     //   30: ldc2_w 4475054329371093223
/*    */     //   33: lload_1
/*    */     //   34: <illegal opcode> w : (Ljava/lang/IllegalStateException;JJ)Ljava/lang/IllegalStateException;
/*    */     //   39: athrow
/*    */     //   40: new java/lang/IllegalStateException
/*    */     //   43: dup
/*    */     //   44: sipush #5883
/*    */     //   47: ldc2_w 2921271332394637088
/*    */     //   50: lload_1
/*    */     //   51: lxor
/*    */     //   52: <illegal opcode> t : (IJ)Ljava/lang/String;
/*    */     //   57: invokespecial <init> : (Ljava/lang/String;)V
/*    */     //   60: athrow
/*    */     //   61: ldc2_w 4475054329371093223
/*    */     //   64: lload_1
/*    */     //   65: <illegal opcode> w : (Ljava/lang/IllegalStateException;JJ)Ljava/lang/IllegalStateException;
/*    */     //   70: athrow
/*    */     //   71: aload_0
/*    */     //   72: aconst_null
/*    */     //   73: putfield c : [Ljava/lang/String;
/*    */     //   76: aload_0
/*    */     //   77: areturn
/*    */     // Line number table:
/*    */     //   Java source line number -> byte code offset
/*    */     //   #28	-> 16
/*    */     //   #16	-> 71
/*    */     //   #22	-> 76
/*    */     // Exception table:
/*    */     //   from	to	target	type
/*    */     //   16	27	30	java/lang/IllegalStateException
/*    */     //   21	61	61	java/lang/IllegalStateException }
/*    */   public kd a(iy[] paramArrayOfiy, char paramChar1, char paramChar2, int paramInt) { // Byte code:
/*    */     //   0: iload_2
/*    */     //   1: i2l
/*    */     //   2: bipush #48
/*    */     //   4: lshl
/*    */     //   5: iload_3
/*    */     //   6: i2l
/*    */     //   7: bipush #48
/*    */     //   9: lshl
/*    */     //   10: bipush #16
/*    */     //   12: lushr
/*    */     //   13: lor
/*    */     //   14: iload #4
/*    */     //   16: i2l
/*    */     //   17: bipush #32
/*    */     //   19: lshl
/*    */     //   20: bipush #32
/*    */     //   22: lushr
/*    */     //   23: lor
/*    */     //   24: getstatic me/konsolas/aac/kd.e : J
/*    */     //   27: lxor
/*    */     //   28: lstore #5
/*    */     //   30: lload #5
/*    */     //   32: dup2
/*    */     //   33: ldc2_w 89366214952704
/*    */     //   36: lxor
/*    */     //   37: lstore #7
/*    */     //   39: pop2
/*    */     //   40: aload_0
/*    */     //   41: getfield a : Z
/*    */     //   44: ifne -> 80
/*    */     //   47: new java/lang/IllegalStateException
/*    */     //   50: dup
/*    */     //   51: sipush #20657
/*    */     //   54: ldc2_w 3233753883937165644
/*    */     //   57: lload #5
/*    */     //   59: lxor
/*    */     //   60: <illegal opcode> t : (IJ)Ljava/lang/String;
/*    */     //   65: invokespecial <init> : (Ljava/lang/String;)V
/*    */     //   68: athrow
/*    */     //   69: ldc2_w 4484050088349919431
/*    */     //   72: lload #5
/*    */     //   74: <illegal opcode> w : (Ljava/lang/IllegalStateException;JJ)Ljava/lang/IllegalStateException;
/*    */     //   79: athrow
/*    */     //   80: aload_1
/*    */     //   81: arraylength
/*    */     //   82: anewarray java/lang/String
/*    */     //   85: astore #9
/*    */     //   87: iconst_0
/*    */     //   88: istore #10
/*    */     //   90: iload #10
/*    */     //   92: aload_1
/*    */     //   93: arraylength
/*    */     //   94: if_icmpge -> 126
/*    */     //   97: aload #9
/*    */     //   99: iload #10
/*    */     //   101: aload_1
/*    */     //   102: iload #10
/*    */     //   104: aaload
/*    */     //   105: getfield a : Ljava/lang/String;
/*    */     //   108: aastore
/*    */     //   109: iinc #10, 1
/*    */     //   112: goto -> 90
/*    */     //   115: ldc2_w 4484050088349919431
/*    */     //   118: lload #5
/*    */     //   120: <illegal opcode> w : (Ljava/lang/IllegalStateException;JJ)Ljava/lang/IllegalStateException;
/*    */     //   125: athrow
/*    */     //   126: aload_0
/*    */     //   127: lload #7
/*    */     //   129: aload #9
/*    */     //   131: invokevirtual a : (J[Ljava/lang/String;)Lme/konsolas/aac/kd;
/*    */     //   134: areturn
/*    */     // Line number table:
/*    */     //   Java source line number -> byte code offset
/*    */     //   #31	-> 40
/*    */     //   #10	-> 80
/*    */     //   #35	-> 87
/*    */     //   #30	-> 97
/*    */     //   #23	-> 109
/*    */     //   #13	-> 126
/*    */     // Exception table:
/*    */     //   from	to	target	type
/*    */     //   40	69	69	java/lang/IllegalStateException
/*    */     //   90	115	115	java/lang/IllegalStateException }
/*    */   public kd(kB paramkB) {
/* 14 */     this.a = paramkB.g;
/*    */ 
/*    */ 
/*    */ 
/*    */ 
/*    */ 
/*    */ 
/*    */ 
/*    */ 
/*    */ 
/*    */ 
/*    */ 
/*    */ 
/*    */ 
/*    */ 
/*    */ 
/*    */ 
/*    */ 
/*    */ 
/*    */ 
/*    */ 
/*    */     
/* 36 */     this.b = paramkB.d;
/*    */     this.c = paramkB.i;
/* 38 */     this.d = paramkB.j;
/*    */   }
/*    */   
/*    */   public kd a(long paramLong, boolean paramBoolean, short paramShort) {
/*    */     // Byte code:
/*    */     //   0: lload_1
/*    */     //   1: bipush #16
/*    */     //   3: lshl
/*    */     //   4: iload #4
/*    */     //   6: i2l
/*    */     //   7: bipush #48
/*    */     //   9: lshl
/*    */     //   10: bipush #48
/*    */     //   12: lushr
/*    */     //   13: lor
/*    */     //   14: getstatic me/konsolas/aac/kd.e : J
/*    */     //   17: lxor
/*    */     //   18: lstore #5
/*    */     //   20: aload_0
/*    */     //   21: getfield a : Z
/*    */     //   24: ifne -> 60
/*    */     //   27: new java/lang/IllegalStateException
/*    */     //   30: dup
/*    */     //   31: sipush #11970
/*    */     //   34: ldc2_w 1218337150407792233
/*    */     //   37: lload #5
/*    */     //   39: lxor
/*    */     //   40: <illegal opcode> t : (IJ)Ljava/lang/String;
/*    */     //   45: invokespecial <init> : (Ljava/lang/String;)V
/*    */     //   48: athrow
/*    */     //   49: ldc2_w 5147330190727352723
/*    */     //   52: lload #5
/*    */     //   54: <illegal opcode> w : (Ljava/lang/IllegalStateException;JJ)Ljava/lang/IllegalStateException;
/*    */     //   59: athrow
/*    */     //   60: aload_0
/*    */     //   61: iload_3
/*    */     //   62: putfield d : Z
/*    */     //   65: aload_0
/*    */     //   66: areturn
/*    */     // Line number table:
/*    */     //   Java source line number -> byte code offset
/*    */     //   #41	-> 20
/*    */     //   #19	-> 60
/*    */     //   #29	-> 65
/*    */     // Exception table:
/*    */     //   from	to	target	type
/*    */     //   20	49	49	java/lang/IllegalStateException
/*    */   }
/*    */   
/*    */   static {
/*    */     long l = e ^ 0x174A1C58E942L;
/*    */     "煦牻儤䆋⯷嫅ḧㅌ㗉껵䅏—ￖ麏㎞튱䉛ዔ語鞽⬱".toCharArray()[1] = (char)("煦牻儤䆋⯷嫅ḧㅌ㗉껵䅏—ￖ麏㎞튱䉛ዔ語鞽⬱".toCharArray()[1] ^ 0x10A3);
/*    */     "ꌶ纵綢Ԅ".toCharArray()[0] = (char)("ꌶ纵綢Ԅ".toCharArray()[0] ^ 0x270E);
/*    */     (new byte[8])[0] = (byte)(int)(l >>> 56L);
/*    */     for (byte b1 = 1; b1 < 8; b1++)
/*    */       (new byte[8])[b1] = (byte)(int)(l << b1 * 8 >>> 56L); 
/*    */     Cipher cipher;
/*    */     (cipher = Cipher.getInstance(a0$cc.G("煦牻儤䆋⯷嫅ḧㅌ㗉껵䅏—ￖ麏㎞튱䉛ዔ語鞽⬱".toCharArray(), (short)24232, false, (byte)2))).init(2, SecretKeyFactory.getInstance(a0$cc.G("ꌶ纵綢Ԅ".toCharArray(), (short)862, true, (byte)0)).generateSecret(new DESKeySpec(new byte[8])), new IvParameterSpec(new byte[8]));
/*    */     String[] arrayOfString = new String[7];
/*    */     boolean bool = false;
/*    */     "뎁僐﬐ₑ凙茙甆溊觐ꡛⲶﲚ쮉䷢酊䷸?렱甎戧櫜㷣⯎飕믘豫튈装᰷᩶뭘쟸ᒪ鳵ዊꞭ獼츃ਵ鳪䚈ຑ뢗缛끳옱팑渧≺킇੹꛱結鏟尀돶玪ሽ펩㓹搕뇉榓넌঻⸞导訄?໑꫆௿鐌㨼ꉀ꩎䣙瓇窇鄃䉬ꎪ綇?뽕뾢闊ꠇ腿䡊窓书뤤㻅䉷滪桸࢐醂헜䟚부ﻀ㶭ꖴ䷐ぶ꺗빂ᑚ덄騸倥햘鎕öю명ᕶ릵욢፫干P鉪泲㤬某稲ा箲ေ瑦䮄?⢶ﯳ锒?톼桴⢅뇅㣄惤﹞◦뇤渔ﯯ헟蕞ᐼǾ璹ㄖ⠢⃿ꜫ氋㷮횰髾㘜㧮쵸᪰莰쏠㼱䊉礞죃㽃椘ተ폡?⇡죌ꦚ栈戀䄕ᥖ퉠槪劔㺢Ϋ聙?꿬㨨䫷⌒笕⛚մᩤ᳜虒㘑碾ꄬ䕍脖驛䉽໱洁敄섒䚪넵蛵✵篵ি䮮←뾦ɕ⼴?㣄﹬迢宓䨳겧兗ꜣ婓┺巘?޼胜ೣ镬챣㹱俀쳆쿖᥹⊽閩᩶牝㺹䃬땗藺躟ꋳ䣥ꢏ᧩ꟃ⃘뮼?ꌿ雝Ꮸ쇂ꥴ䒤ᛛ↽鲦삀Ὲꞿ繐睍㢕⋬戾겦茁洳涙觼ﴈ挎璘흟?秲恹?鐝ᱻ皛⹣ళᚯ滑☐೑깩ꋽ鍮誦恶ꐻ玱ɷ奯㓼飈᠕ꈴ宮ဃ变鍹견༂紾".toCharArray()[187] = (char)("뎁僐﬐ₑ凙茙甆溊觐ꡛⲶﲚ쮉䷢酊䷸?렱甎戧櫜㷣⯎飕믘豫튈装᰷᩶뭘쟸ᒪ鳵ዊꞭ獼츃ਵ鳪䚈ຑ뢗缛끳옱팑渧≺킇੹꛱結鏟尀돶玪ሽ펩㓹搕뇉榓넌঻⸞导訄?໑꫆௿鐌㨼ꉀ꩎䣙瓇窇鄃䉬ꎪ綇?뽕뾢闊ꠇ腿䡊窓书뤤㻅䉷滪桸࢐醂헜䟚부ﻀ㶭ꖴ䷐ぶ꺗빂ᑚ덄騸倥햘鎕öю명ᕶ릵욢፫干P鉪泲㤬某稲ा箲ေ瑦䮄?⢶ﯳ锒?톼桴⢅뇅㣄惤﹞◦뇤渔ﯯ헟蕞ᐼǾ璹ㄖ⠢⃿ꜫ氋㷮횰髾㘜㧮쵸᪰莰쏠㼱䊉礞죃㽃椘ተ폡?⇡죌ꦚ栈戀䄕ᥖ퉠槪劔㺢Ϋ聙?꿬㨨䫷⌒笕⛚մᩤ᳜虒㘑碾ꄬ䕍脖驛䉽໱洁敄섒䚪넵蛵✵篵ি䮮←뾦ɕ⼴?㣄﹬迢宓䨳겧兗ꜣ婓┺巘?޼胜ೣ镬챣㹱俀쳆쿖᥹⊽閩᩶牝㺹䃬땗藺躟ꋳ䣥ꢏ᧩ꟃ⃘뮼?ꌿ雝Ꮸ쇂ꥴ䒤ᛛ↽鲦삀Ὲꞿ繐睍㢕⋬戾겦茁洳涙觼ﴈ挎璘흟?秲恹?鐝ᱻ皛⹣ళᚯ滑☐೑깩ꋽ鍮誦恶ꐻ玱ɷ奯㓼飈᠕ꈴ宮ဃ变鍹견༂紾".toCharArray()[187] ^ 0x2C42);
/*    */     String str;
/*    */     int i = (str = a0$cc.G("뎁僐﬐ₑ凙茙甆溊觐ꡛⲶﲚ쮉䷢酊䷸?렱甎戧櫜㷣⯎飕믘豫튈装᰷᩶뭘쟸ᒪ鳵ዊꞭ獼츃ਵ鳪䚈ຑ뢗缛끳옱팑渧≺킇੹꛱結鏟尀돶玪ሽ펩㓹搕뇉榓넌঻⸞导訄?໑꫆௿鐌㨼ꉀ꩎䣙瓇窇鄃䉬ꎪ綇?뽕뾢闊ꠇ腿䡊窓书뤤㻅䉷滪桸࢐醂헜䟚부ﻀ㶭ꖴ䷐ぶ꺗빂ᑚ덄騸倥햘鎕öю명ᕶ릵욢፫干P鉪泲㤬某稲ा箲ေ瑦䮄?⢶ﯳ锒?톼桴⢅뇅㣄惤﹞◦뇤渔ﯯ헟蕞ᐼǾ璹ㄖ⠢⃿ꜫ氋㷮횰髾㘜㧮쵸᪰莰쏠㼱䊉礞죃㽃椘ተ폡?⇡죌ꦚ栈戀䄕ᥖ퉠槪劔㺢Ϋ聙?꿬㨨䫷⌒笕⛚մᩤ᳜虒㘑碾ꄬ䕍脖驛䉽໱洁敄섒䚪넵蛵✵篵ি䮮←뾦ɕ⼴?㣄﹬迢宓䨳겧兗ꜣ婓┺巘?޼胜ೣ镬챣㹱俀쳆쿖᥹⊽閩᩶牝㺹䃬땗藺躟ꋳ䣥ꢏ᧩ꟃ⃘뮼?ꌿ雝Ꮸ쇂ꥴ䒤ᛛ↽鲦삀Ὲꞿ繐睍㢕⋬戾겦茁洳涙觼ﴈ挎璘흟?秲恹?鐝ᱻ皛⹣ళᚯ滑☐೑깩ꋽ鍮誦恶ꐻ玱ɷ奯㓼飈᠕ꈴ宮ဃ变鍹견༂紾".toCharArray(), (short)24478, false, (byte)2)).length();
/*    */     byte b2 = 80;
/*    */     byte b = -1;
/*    */     while (true);
/*    */   }
/*    */   
/*    */   private static IllegalStateException a(IllegalStateException paramIllegalStateException) {
/*    */     return paramIllegalStateException;
/*    */   }
/*    */   
/*    */   private static String a(byte[] paramArrayOfbyte) {
/*    */     byte b1 = 0;
/*    */     int i;
/*    */     char[] arrayOfChar = new char[i = paramArrayOfbyte.length];
/*    */     for (byte b2 = 0; b2 < i; b2++) {
/*    */       int j;
/*    */       if ((j = 0xFF & paramArrayOfbyte[b2]) < 192) {
/*    */         arrayOfChar[b1++] = (char)j;
/*    */       } else if (j < 224) {
/*    */         char c = (char)((char)(j & 0x1F) << 6);
/*    */         j = paramArrayOfbyte[++b2];
/*    */         c = (char)(c | (char)(j & 0x3F));
/*    */         arrayOfChar[b1++] = c;
/*    */       } else if (b2 < i - 2) {
/*    */         char c = (char)((char)(j & 0xF) << 12);
/*    */         j = paramArrayOfbyte[++b2];
/*    */         c = (char)(c | (char)(j & 0x3F) << 6);
/*    */         j = paramArrayOfbyte[++b2];
/*    */         c = (char)(c | (char)(j & 0x3F));
/*    */         arrayOfChar[b1++] = c;
/*    */       } 
/*    */     } 
/*    */     return new String(arrayOfChar, 0, b1);
/*    */   }
/*    */   
/*    */   private static String a(int paramInt, long paramLong) {
/*    */     int i = paramInt ^ (int)(paramLong & 0x7FFFL) ^ 0x3F37;
/*    */     if (g[i] == null) {
/*    */       Object[] arrayOfObject;
/*    */       try {
/*    */         Long long_ = Long.valueOf(Thread.currentThread().getId());
/*    */         arrayOfObject = (Object[])h.get(long_);
/*    */         if (arrayOfObject == null) {
/*    */           arrayOfObject = new Object[3];
/*    */           "堐࡙㸫ﰞ湐㗫䌖恏ꢿ憮㝂淉䮩ꗤ罶뤃ᔬ푈祐㑫".toCharArray()[19] = (char)("堐࡙㸫ﰞ湐㗫䌖恏ꢿ憮㝂淉䮩ꗤ罶뤃ᔬ푈祐㑫".toCharArray()[19] ^ 0x51F0);
/*    */           arrayOfObject[0] = Cipher.getInstance(hY$g6.H("堐࡙㸫ﰞ湐㗫䌖恏ꢿ憮㝂淉䮩ꗤ罶뤃ᔬ푈祐㑫".toCharArray(), (short)4789, (byte)0, (byte)0));
/*    */           "䵶刻ᵬᐄ".toCharArray()[2] = (char)("䵶刻ᵬᐄ".toCharArray()[2] ^ 0x3F22);
/*    */           arrayOfObject[1] = SecretKeyFactory.getInstance(hY$g6.H("䵶刻ᵬᐄ".toCharArray(), (short)14694, (byte)5, (byte)0));
/*    */           arrayOfObject[2] = new IvParameterSpec(new byte[8]);
/*    */           h.put(long_, arrayOfObject);
/*    */         } 
/*    */       } catch (Exception exception) {
/*    */         "冖俋챚媸ዩ꽹⢡⻯Ꮏ㦈ﯺ呱埐비䬌夊ٙ".toCharArray()[3] = (char)("冖俋챚媸ዩ꽹⢡⻯Ꮏ㦈ﯺ呱埐비䬌夊ٙ".toCharArray()[3] ^ 0x166B);
/*    */         throw new RuntimeException(hY$g6.H("冖俋챚媸ዩ꽹⢡⻯Ꮏ㦈ﯺ呱埐비䬌夊ٙ".toCharArray(), (short)13539, (byte)1, (byte)5), exception);
/*    */       } 
/*    */       byte[] arrayOfByte1 = new byte[8];
/*    */       arrayOfByte1[0] = (byte)(int)(paramLong >>> 56L);
/*    */       for (byte b = 1; b < 8; b++)
/*    */         arrayOfByte1[b] = (byte)(int)(paramLong << b * 8 >>> 56L); 
/*    */       DESKeySpec dESKeySpec = new DESKeySpec(arrayOfByte1);
/*    */       SecretKey secretKey = ((SecretKeyFactory)arrayOfObject[1]).generateSecret(dESKeySpec);
/*    */       ((Cipher)arrayOfObject[0]).init(2, secretKey, (IvParameterSpec)arrayOfObject[2]);
/*    */       "䌙⼸꧷ㆣ✤嗷ҽ韦㜮".toCharArray()[0] = (char)("䌙⼸꧷ㆣ✤嗷ҽ韦㜮".toCharArray()[0] ^ 0x598E);
/*    */       byte[] arrayOfByte2 = f[i].getBytes(hY$g6.H("䌙⼸꧷ㆣ✤嗷ҽ韦㜮".toCharArray(), (short)16624, (byte)0, (byte)5));
/*    */       g[i] = a(((Cipher)arrayOfObject[0]).doFinal(arrayOfByte2));
/*    */     } 
/*    */     return g[i];
/*    */   }
/*    */   
/*    */   private static Object a(MethodHandles.Lookup paramLookup, MutableCallSite paramMutableCallSite, String paramString, Object[] paramArrayOfObject) {
/*    */     int i = ((Integer)paramArrayOfObject[0]).intValue();
/*    */     long l = ((Long)paramArrayOfObject[1]).longValue();
/*    */     String str = a(i, l);
/*    */     MethodHandle methodHandle = MethodHandles.constant(String.class, str);
/*    */     paramMutableCallSite.setTarget(MethodHandles.dropArguments(methodHandle, 0, new Class[] { int.class, long.class }));
/*    */     return str;
/*    */   }
/*    */   
/*    */   private static CallSite a(MethodHandles.Lookup paramLookup, String paramString, MethodType paramMethodType) {
/*    */     // Byte code:
/*    */     //   0: new java/lang/invoke/MutableCallSite
/*    */     //   3: dup
/*    */     //   4: aload_2
/*    */     //   5: invokespecial <init> : (Ljava/lang/invoke/MethodType;)V
/*    */     //   8: astore_3
/*    */     //   9: aload_3
/*    */     //   10: ldc_w
/*    */     //   13: ldc_w [Ljava/lang/Object;
/*    */     //   16: aload_2
/*    */     //   17: invokevirtual parameterCount : ()I
/*    */     //   20: invokevirtual asCollector : (Ljava/lang/Class;I)Ljava/lang/invoke/MethodHandle;
/*    */     //   23: iconst_0
/*    */     //   24: iconst_3
/*    */     //   25: anewarray java/lang/Object
/*    */     //   28: dup
/*    */     //   29: iconst_0
/*    */     //   30: aload_0
/*    */     //   31: aastore
/*    */     //   32: dup
/*    */     //   33: iconst_1
/*    */     //   34: aload_3
/*    */     //   35: aastore
/*    */     //   36: dup
/*    */     //   37: iconst_2
/*    */     //   38: aload_1
/*    */     //   39: aastore
/*    */     //   40: invokestatic insertArguments : (Ljava/lang/invoke/MethodHandle;I[Ljava/lang/Object;)Ljava/lang/invoke/MethodHandle;
/*    */     //   43: aload_2
/*    */     //   44: invokestatic explicitCastArguments : (Ljava/lang/invoke/MethodHandle;Ljava/lang/invoke/MethodType;)Ljava/lang/invoke/MethodHandle;
/*    */     //   47: invokevirtual setTarget : (Ljava/lang/invoke/MethodHandle;)V
/*    */     //   50: goto -> 171
/*    */     //   53: astore #4
/*    */     //   55: new java/lang/RuntimeException
/*    */     //   58: dup
/*    */     //   59: new java/lang/StringBuilder
/*    */     //   62: dup
/*    */     //   63: invokespecial <init> : ()V
/*    */     //   66: ldc_w '돳瘵᪫˫ꮔ캶䲍訫鉼鹕蹫節筍湊䑹'
/*    */     //   69: invokevirtual toCharArray : ()[C
/*    */     //   72: dup
/*    */     //   73: dup
/*    */     //   74: bipush #6
/*    */     //   76: dup_x1
/*    */     //   77: caload
/*    */     //   78: sipush #3016
/*    */     //   81: ixor
/*    */     //   82: i2c
/*    */     //   83: castore
/*    */     //   84: sipush #16891
/*    */     //   87: iconst_0
/*    */     //   88: iconst_1
/*    */     //   89: invokestatic U : (Ljava/lang/Object;SZZ)Ljava/lang/String;
/*    */     //   92: invokevirtual append : (Ljava/lang/String;)Ljava/lang/StringBuilder;
/*    */     //   95: ldc_w '촕⎂헜䯪'
/*    */     //   98: invokevirtual toCharArray : ()[C
/*    */     //   101: dup
/*    */     //   102: dup
/*    */     //   103: iconst_0
/*    */     //   104: dup_x1
/*    */     //   105: caload
/*    */     //   106: sipush #29085
/*    */     //   109: ixor
/*    */     //   110: i2c
/*    */     //   111: castore
/*    */     //   112: sipush #21917
/*    */     //   115: iconst_0
/*    */     //   116: iconst_0
/*    */     //   117: invokestatic U : (Ljava/lang/Object;SZZ)Ljava/lang/String;
/*    */     //   120: invokevirtual append : (Ljava/lang/String;)Ljava/lang/StringBuilder;
/*    */     //   123: aload_1
/*    */     //   124: invokevirtual append : (Ljava/lang/String;)Ljava/lang/StringBuilder;
/*    */     //   127: ldc_w '↽썒悻ᖔ'
/*    */     //   130: invokevirtual toCharArray : ()[C
/*    */     //   133: dup
/*    */     //   134: dup
/*    */     //   135: iconst_0
/*    */     //   136: dup_x1
/*    */     //   137: caload
/*    */     //   138: sipush #21691
/*    */     //   141: ixor
/*    */     //   142: i2c
/*    */     //   143: castore
/*    */     //   144: sipush #23497
/*    */     //   147: iconst_0
/*    */     //   148: iconst_0
/*    */     //   149: invokestatic U : (Ljava/lang/Object;SZZ)Ljava/lang/String;
/*    */     //   152: invokevirtual append : (Ljava/lang/String;)Ljava/lang/StringBuilder;
/*    */     //   155: aload_2
/*    */     //   156: invokevirtual toString : ()Ljava/lang/String;
/*    */     //   159: invokevirtual append : (Ljava/lang/String;)Ljava/lang/StringBuilder;
/*    */     //   162: invokevirtual toString : ()Ljava/lang/String;
/*    */     //   165: aload #4
/*    */     //   167: invokespecial <init> : (Ljava/lang/String;Ljava/lang/Throwable;)V
/*    */     //   170: athrow
/*    */     //   171: aload_3
/*    */     //   172: areturn
/*    */     // Exception table:
/*    */     //   from	to	target	type
/*    */     //   9	50	53	java/lang/Exception
/*    */   } }


/* Location:              C:\Users\BukkitBypass\Desktop\MatrixAC\AAC\AAC-spigot-5.2.0.jar!\me\konsolas\aac\kd.class
 * Java compiler version: 8 (52.0)
 * JD-Core Version:       1.1.3
 */