/*    */ package me.konsolas.aac;
/*    */ 
/*    */ class ke {
/*    */   private final double a;
/*    */   private final double b;
/*    */   private final d7 c;
/*    */   
/*  8 */   static double b(ke paramke) { return paramke.a; }
/*    */   private static final long d = nc.a(-703054623185930586L, -838793410900742640L, MethodHandles.lookup().lookupClass()).a(139453719541991L); private boolean a(long paramLong, short paramShort, ke paramke) { // Byte code:
/*    */     //   0: lload_1
/*    */     //   1: bipush #16
/*    */     //   3: lshl
/*    */     //   4: iload_3
/*    */     //   5: i2l
/*    */     //   6: bipush #48
/*    */     //   8: lshl
/*    */     //   9: bipush #48
/*    */     //   11: lushr
/*    */     //   12: lor
/*    */     //   13: getstatic me/konsolas/aac/ke.d : J
/*    */     //   16: lxor
/*    */     //   17: lstore #5
/*    */     //   19: lload #5
/*    */     //   21: dup2
/*    */     //   22: ldc2_w 58253696086590
/*    */     //   25: lxor
/*    */     //   26: lstore #7
/*    */     //   28: pop2
/*    */     //   29: ldc2_w 760465602256336750
/*    */     //   32: lload #5
/*    */     //   34: <illegal opcode> w : (JJ)Ljava/lang/String;
/*    */     //   39: astore #9
/*    */     //   41: aload #4
/*    */     //   43: aload #9
/*    */     //   45: ifnonnull -> 79
/*    */     //   48: ifnonnull -> 78
/*    */     //   51: goto -> 65
/*    */     //   54: ldc2_w 769965925761670313
/*    */     //   57: lload #5
/*    */     //   59: <illegal opcode> w : (Laacinternal/v;JJ)Laacinternal/v;
/*    */     //   64: athrow
/*    */     //   65: iconst_1
/*    */     //   66: ireturn
/*    */     //   67: ldc2_w 769965925761670313
/*    */     //   70: lload #5
/*    */     //   72: <illegal opcode> w : (Laacinternal/v;JJ)Laacinternal/v;
/*    */     //   77: athrow
/*    */     //   78: aload_0
/*    */     //   79: getfield a : D
/*    */     //   82: ldc2_w 742875602278636913
/*    */     //   85: lload #5
/*    */     //   87: <illegal opcode> w : (DJJ)Z
/*    */     //   92: aload #9
/*    */     //   94: ifnonnull -> 193
/*    */     //   97: ifeq -> 184
/*    */     //   100: goto -> 114
/*    */     //   103: ldc2_w 769965925761670313
/*    */     //   106: lload #5
/*    */     //   108: <illegal opcode> w : (Laacinternal/v;JJ)Laacinternal/v;
/*    */     //   113: athrow
/*    */     //   114: aload #4
/*    */     //   116: getfield a : D
/*    */     //   119: ldc2_w 742875602278636913
/*    */     //   122: lload #5
/*    */     //   124: <illegal opcode> w : (DJJ)Z
/*    */     //   129: aload #9
/*    */     //   131: lload_1
/*    */     //   132: lconst_0
/*    */     //   133: lcmp
/*    */     //   134: ifle -> 195
/*    */     //   137: ifnonnull -> 193
/*    */     //   140: goto -> 154
/*    */     //   143: ldc2_w 769965925761670313
/*    */     //   146: lload #5
/*    */     //   148: <illegal opcode> w : (Laacinternal/v;JJ)Laacinternal/v;
/*    */     //   153: athrow
/*    */     //   154: ifne -> 184
/*    */     //   157: goto -> 171
/*    */     //   160: ldc2_w 769965925761670313
/*    */     //   163: lload #5
/*    */     //   165: <illegal opcode> w : (Laacinternal/v;JJ)Laacinternal/v;
/*    */     //   170: athrow
/*    */     //   171: iconst_1
/*    */     //   172: ireturn
/*    */     //   173: ldc2_w 769965925761670313
/*    */     //   176: lload #5
/*    */     //   178: <illegal opcode> w : (Laacinternal/v;JJ)Laacinternal/v;
/*    */     //   183: athrow
/*    */     //   184: aload_0
/*    */     //   185: getfield a : D
/*    */     //   188: aload_0
/*    */     //   189: getfield b : D
/*    */     //   192: dcmpg
/*    */     //   193: aload #9
/*    */     //   195: ifnonnull -> 307
/*    */     //   198: ifgt -> 279
/*    */     //   201: goto -> 215
/*    */     //   204: ldc2_w 769965925761670313
/*    */     //   207: lload #5
/*    */     //   209: <illegal opcode> w : (Laacinternal/v;JJ)Laacinternal/v;
/*    */     //   214: athrow
/*    */     //   215: aload #4
/*    */     //   217: getfield a : D
/*    */     //   220: aload #4
/*    */     //   222: getfield b : D
/*    */     //   225: dcmpl
/*    */     //   226: aload #9
/*    */     //   228: iload_3
/*    */     //   229: ifge -> 309
/*    */     //   232: ifnonnull -> 307
/*    */     //   235: goto -> 249
/*    */     //   238: ldc2_w 769965925761670313
/*    */     //   241: lload #5
/*    */     //   243: <illegal opcode> w : (Laacinternal/v;JJ)Laacinternal/v;
/*    */     //   248: athrow
/*    */     //   249: ifle -> 279
/*    */     //   252: goto -> 266
/*    */     //   255: ldc2_w 769965925761670313
/*    */     //   258: lload #5
/*    */     //   260: <illegal opcode> w : (Laacinternal/v;JJ)Laacinternal/v;
/*    */     //   265: athrow
/*    */     //   266: iconst_1
/*    */     //   267: ireturn
/*    */     //   268: ldc2_w 769965925761670313
/*    */     //   271: lload #5
/*    */     //   273: <illegal opcode> w : (Laacinternal/v;JJ)Laacinternal/v;
/*    */     //   278: athrow
/*    */     //   279: aload_0
/*    */     //   280: lload #7
/*    */     //   282: ldc2_w 745872285329594897
/*    */     //   285: lload #5
/*    */     //   287: <illegal opcode> Ö : (Lme/konsolas/aac/ke;JJJ)F
/*    */     //   292: aload #4
/*    */     //   294: lload #7
/*    */     //   296: ldc2_w 745872285329594897
/*    */     //   299: lload #5
/*    */     //   301: <illegal opcode> Ö : (Lme/konsolas/aac/ke;JJJ)F
/*    */     //   306: fcmpg
/*    */     //   307: aload #9
/*    */     //   309: ifnonnull -> 330
/*    */     //   312: ifge -> 333
/*    */     //   315: goto -> 329
/*    */     //   318: ldc2_w 769965925761670313
/*    */     //   321: lload #5
/*    */     //   323: <illegal opcode> w : (Laacinternal/v;JJ)Laacinternal/v;
/*    */     //   328: athrow
/*    */     //   329: iconst_1
/*    */     //   330: goto -> 334
/*    */     //   333: iconst_0
/*    */     //   334: ireturn
/*    */     // Line number table:
/*    */     //   Java source line number -> byte code offset
/*    */     //   #4	-> 41
/*    */     //   #2	-> 78
/*    */     //   #1	-> 184
/*    */     //   #20	-> 279
/*    */     // Exception table:
/*    */     //   from	to	target	type
/*    */     //   41	51	54	aacinternal/v
/*    */     //   48	67	67	aacinternal/v
/*    */     //   79	100	103	aacinternal/v
/*    */     //   97	140	143	aacinternal/v
/*    */     //   114	157	160	aacinternal/v
/*    */     //   154	173	173	aacinternal/v
/*    */     //   193	201	204	aacinternal/v
/*    */     //   198	235	238	aacinternal/v
/*    */     //   215	252	255	aacinternal/v
/*    */     //   249	268	268	aacinternal/v
/*    */     //   307	315	318	aacinternal/v } private float a(long paramLong) { // Byte code:
/*    */     //   0: getstatic me/konsolas/aac/ke.d : J
/*    */     //   3: lload_1
/*    */     //   4: lxor
/*    */     //   5: lstore_1
/*    */     //   6: ldc2_w 5974587517544247050
/*    */     //   9: lload_1
/*    */     //   10: <illegal opcode> w : (JJ)Ljava/lang/String;
/*    */     //   15: astore_3
/*    */     //   16: aload_0
/*    */     //   17: getfield a : D
/*    */     //   20: ldc2_w 5920951145547564309
/*    */     //   23: lload_1
/*    */     //   24: <illegal opcode> w : (DJJ)Z
/*    */     //   29: aload_3
/*    */     //   30: ifnonnull -> 87
/*    */     //   33: ifne -> 61
/*    */     //   36: goto -> 49
/*    */     //   39: ldc2_w 5965931610917078221
/*    */     //   42: lload_1
/*    */     //   43: <illegal opcode> w : (Laacinternal/v;JJ)Laacinternal/v;
/*    */     //   48: athrow
/*    */     //   49: fconst_1
/*    */     //   50: freturn
/*    */     //   51: ldc2_w 5965931610917078221
/*    */     //   54: lload_1
/*    */     //   55: <illegal opcode> w : (Laacinternal/v;JJ)Laacinternal/v;
/*    */     //   60: athrow
/*    */     //   61: aload_0
/*    */     //   62: getfield a : D
/*    */     //   65: aload_3
/*    */     //   66: ifnonnull -> 117
/*    */     //   69: aload_0
/*    */     //   70: getfield b : D
/*    */     //   73: dcmpl
/*    */     //   74: goto -> 87
/*    */     //   77: ldc2_w 5965931610917078221
/*    */     //   80: lload_1
/*    */     //   81: <illegal opcode> w : (Laacinternal/v;JJ)Laacinternal/v;
/*    */     //   86: athrow
/*    */     //   87: ifle -> 113
/*    */     //   90: aload_0
/*    */     //   91: getfield a : D
/*    */     //   94: aload_0
/*    */     //   95: getfield b : D
/*    */     //   98: dsub
/*    */     //   99: d2f
/*    */     //   100: fconst_1
/*    */     //   101: fadd
/*    */     //   102: freturn
/*    */     //   103: ldc2_w 5965931610917078221
/*    */     //   106: lload_1
/*    */     //   107: <illegal opcode> w : (Laacinternal/v;JJ)Laacinternal/v;
/*    */     //   112: athrow
/*    */     //   113: aload_0
/*    */     //   114: getfield a : D
/*    */     //   117: d2f
/*    */     //   118: ldc 3.0
/*    */     //   120: fsub
/*    */     //   121: freturn
/*    */     // Line number table:
/*    */     //   Java source line number -> byte code offset
/*    */     //   #5	-> 16
/*    */     //   #17	-> 49
/*    */     //   #6	-> 61
/*    */     //   #7	-> 90
/*    */     //   #11	-> 113
/*    */     // Exception table:
/*    */     //   from	to	target	type
/*    */     //   16	36	39	aacinternal/v
/*    */     //   33	51	51	aacinternal/v
/*    */     //   61	74	77	aacinternal/v
/*  9 */     //   87	103	103	aacinternal/v } ke(double paramDouble1, double paramDouble2, d7 paramd7, mn parammn) { this(paramDouble1, paramDouble2, paramd7); }
/*    */   
/*    */   static float a(byte paramByte, ke paramke, int paramInt1, int paramInt2) {
/*    */     // Byte code:
/*    */     //   0: iload_0
/*    */     //   1: i2l
/*    */     //   2: bipush #56
/*    */     //   4: lshl
/*    */     //   5: iload_2
/*    */     //   6: i2l
/*    */     //   7: bipush #32
/*    */     //   9: lshl
/*    */     //   10: bipush #8
/*    */     //   12: lushr
/*    */     //   13: lor
/*    */     //   14: iload_3
/*    */     //   15: i2l
/*    */     //   16: bipush #40
/*    */     //   18: lshl
/*    */     //   19: bipush #40
/*    */     //   21: lushr
/*    */     //   22: lor
/*    */     //   23: getstatic me/konsolas/aac/ke.d : J
/*    */     //   26: lxor
/*    */     //   27: lstore #4
/*    */     //   29: lload #4
/*    */     //   31: dup2
/*    */     //   32: ldc2_w 15992115810203
/*    */     //   35: lxor
/*    */     //   36: lstore #6
/*    */     //   38: pop2
/*    */     //   39: aload_1
/*    */     //   40: lload #6
/*    */     //   42: ldc2_w 8646036709158184884
/*    */     //   45: lload #4
/*    */     //   47: <illegal opcode> Ö : (Lme/konsolas/aac/ke;JJJ)F
/*    */     //   52: freturn
/*    */     // Line number table:
/*    */     //   Java source line number -> byte code offset
/*    */     //   #12	-> 39
/*    */   }
/*    */   
/*    */   private ke(double paramDouble1, double paramDouble2, d7 paramd7) { this.a = paramDouble1;
/* 16 */     this.b = paramDouble2;
/*    */     
/* 18 */     this.c = paramd7; } static d7 a(ke paramke) { return paramke.c; } static boolean a(long paramLong, ke paramke1, ke paramke2) { // Byte code:
/*    */     //   0: getstatic me/konsolas/aac/ke.d : J
/*    */     //   3: lload_0
/*    */     //   4: lxor
/*    */     //   5: lstore_0
/*    */     //   6: lload_0
/*    */     //   7: dup2
/*    */     //   8: ldc2_w 22330745053927
/*    */     //   11: lxor
/*    */     //   12: dup2
/*    */     //   13: bipush #16
/*    */     //   15: lushr
/*    */     //   16: lstore #4
/*    */     //   18: dup2
/*    */     //   19: bipush #48
/*    */     //   21: lshl
/*    */     //   22: bipush #48
/*    */     //   24: lushr
/*    */     //   25: l2i
/*    */     //   26: istore #6
/*    */     //   28: pop2
/*    */     //   29: pop2
/*    */     //   30: aload_2
/*    */     //   31: lload #4
/*    */     //   33: iload #6
/*    */     //   35: i2s
/*    */     //   36: aload_3
/*    */     //   37: ldc2_w -8971262331425190757
/*    */     //   40: lload_0
/*    */     //   41: <illegal opcode> Ö : (Lme/konsolas/aac/ke;JSLme/konsolas/aac/ke;JJ)Z
/*    */     //   46: ireturn
/*    */     // Line number table:
/*    */     //   Java source line number -> byte code offset
/*    */     //   #15	-> 30 }
/* 19 */   static double a(ke paramke) { return paramke.b; }
/*    */ 
/*    */   
/*    */   private static v a(v paramv) {
/*    */     return paramv;
/*    */   }
/*    */ }


/* Location:              C:\Users\BukkitBypass\Desktop\MatrixAC\AAC\AAC-spigot-5.2.0.jar!\me\konsolas\aac\ke.class
 * Java compiler version: 8 (52.0)
 * JD-Core Version:       1.1.3
 */