/*     */ package me.konsolas.aac;public final class kn { public static final float[][] g; public static final float[][] e; public static final m9 j; private static final int d = 7; private static final int a = 8192; private static void c(float[][] paramArrayOffloat, long paramLong1, long paramLong2) { long l;
/*   2 */     for (l = paramLong1; l < paramLong2 - 1L; ) {
/*     */ 
/*     */ 
/*     */ 
/*     */ 
/*     */ 
/*     */ 
/*     */ 
/*     */ 
/*     */ 
/*     */ 
/*     */ 
/*     */ 
/*     */ 
/*     */ 
/*     */ 
/*     */ 
/*     */ 
/*     */ 
/*     */ 
/*     */ 
/*     */ 
/*     */ 
/*     */ 
/*     */ 
/*     */ 
/*     */ 
/*     */ 
/*     */ 
/*     */ 
/*     */ 
/*     */ 
/*     */ 
/*     */ 
/*     */ 
/*     */ 
/*     */ 
/*     */ 
/*     */ 
/*     */ 
/*     */ 
/*     */ 
/*     */       
/*  45 */       long l1 = l;
/*     */       
/*  47 */       long l2 = l + 1L; while (true) { try { if (l2 < paramLong2) { if (Float.compare(k.a(paramArrayOffloat, l2), k.a(paramArrayOffloat, l1)) < 0) l1 = l2;  l2++; continue; }  } catch (IllegalArgumentException illegalArgumentException) { throw a(null); }
/*     */ 
/*     */ 
/*     */ 
/*     */ 
/*     */ 
/*     */ 
/*     */ 
/*     */ 
/*     */ 
/*     */ 
/*     */ 
/*     */ 
/*     */ 
/*     */ 
/*     */ 
/*     */ 
/*     */ 
/*     */ 
/*     */ 
/*     */ 
/*     */ 
/*     */ 
/*     */ 
/*     */ 
/*     */ 
/*     */ 
/*     */ 
/*     */ 
/*     */ 
/*     */ 
/*     */ 
/*     */ 
/*     */ 
/*     */ 
/*     */ 
/*     */ 
/*     */ 
/*     */ 
/*     */ 
/*     */ 
/*     */ 
/*     */ 
/*     */ 
/*     */ 
/*     */ 
/*     */ 
/*     */ 
/*     */ 
/*     */ 
/*     */ 
/*     */ 
/*     */ 
/*     */ 
/*     */ 
/*     */ 
/*     */ 
/*     */ 
/*     */ 
/*     */ 
/*     */ 
/*     */ 
/*     */ 
/*     */ 
/*     */ 
/*     */ 
/*     */ 
/*     */ 
/*     */ 
/*     */ 
/*     */ 
/*     */ 
/*     */ 
/*     */ 
/*     */ 
/*     */ 
/*     */ 
/*     */ 
/*     */ 
/*     */ 
/*     */ 
/*     */ 
/*     */ 
/*     */ 
/*     */ 
/*     */ 
/*     */ 
/*     */ 
/*     */ 
/*     */ 
/*     */ 
/*     */ 
/*     */ 
/*     */ 
/*     */ 
/*     */ 
/*     */ 
/*     */ 
/*     */ 
/*     */ 
/*     */ 
/*     */ 
/*     */ 
/*     */ 
/*     */ 
/*     */ 
/*     */ 
/*     */         
/*     */         break; }
/*     */ 
/*     */ 
/*     */ 
/*     */ 
/*     */ 
/*     */ 
/*     */ 
/*     */ 
/*     */ 
/*     */ 
/*     */ 
/*     */ 
/*     */ 
/*     */ 
/*     */ 
/*     */ 
/*     */ 
/*     */ 
/*     */ 
/*     */ 
/*     */ 
/*     */ 
/*     */ 
/*     */ 
/*     */ 
/*     */ 
/*     */ 
/*     */ 
/*     */ 
/*     */ 
/*     */ 
/*     */ 
/*     */ 
/*     */ 
/*     */ 
/*     */ 
/*     */ 
/*     */ 
/*     */ 
/*     */ 
/*     */ 
/*     */ 
/*     */ 
/*     */ 
/*     */ 
/*     */ 
/*     */ 
/*     */ 
/*     */ 
/*     */ 
/*     */ 
/*     */ 
/*     */ 
/*     */ 
/*     */ 
/*     */ 
/*     */ 
/*     */ 
/*     */ 
/*     */ 
/*     */ 
/*     */ 
/*     */ 
/*     */ 
/*     */ 
/*     */ 
/*     */ 
/*     */ 
/*     */ 
/*     */ 
/*     */ 
/*     */ 
/*     */ 
/*     */ 
/*     */ 
/*     */ 
/*     */ 
/*     */ 
/*     */ 
/*     */ 
/*     */ 
/*     */ 
/*     */ 
/*     */ 
/*     */ 
/*     */ 
/*     */ 
/*     */ 
/*     */ 
/*     */ 
/*     */ 
/*     */ 
/*     */ 
/*     */ 
/*     */ 
/*     */ 
/*     */ 
/*     */ 
/*     */ 
/*     */ 
/*     */ 
/*     */ 
/*     */ 
/*     */ 
/*     */ 
/*     */ 
/*     */ 
/*     */       
/* 264 */       try { if (l1 != l) k.b(paramArrayOffloat, l, l1);  } catch (IllegalArgumentException illegalArgumentException) { throw a(null); }
/*     */ 
/*     */ 
/*     */ 
/*     */ 
/*     */ 
/*     */ 
/*     */ 
/*     */ 
/*     */ 
/*     */ 
/*     */ 
/*     */ 
/*     */ 
/*     */ 
/*     */ 
/*     */ 
/*     */ 
/*     */ 
/*     */ 
/*     */ 
/*     */ 
/*     */ 
/*     */ 
/*     */ 
/*     */ 
/*     */ 
/*     */ 
/*     */ 
/*     */ 
/*     */ 
/*     */ 
/*     */ 
/*     */ 
/*     */ 
/*     */ 
/*     */ 
/*     */ 
/*     */ 
/*     */ 
/*     */ 
/*     */ 
/*     */ 
/*     */ 
/*     */ 
/*     */       
/* 310 */       l++;
/*     */     }  }
/*     */    private static final int h = 40; private static final int f = 8; private static final int i = 255; private static final int c = 4; private static final int b = 1024; @Deprecated
/*     */   public static String a(float[][] paramArrayOffloat) {
/*     */     return k.a(paramArrayOffloat);
/*     */   } public static void a(float[][] paramArrayOffloat1, float[][] paramArrayOffloat2) {
/*     */     a(paramArrayOffloat1, paramArrayOffloat2, 0L, k.a(paramArrayOffloat1));
/*     */   } @Deprecated
/*     */   public static void a(float[][] paramArrayOffloat, long paramLong) {
/*     */     paramArrayOffloat[k.b(paramLong)][k.a(paramLong)] = paramArrayOffloat[k.b(paramLong)][k.a(paramLong)] - 1.0F;
/*     */   } @Deprecated
/*     */   public static float[][] c(float[][] paramArrayOffloat, long paramLong1, long paramLong2) {
/*     */     try {
/*     */     
/*     */     } catch (IllegalArgumentException illegalArgumentException) {
/*     */       throw a(null);
/*     */     } 
/*     */     return (paramLong1 > a(paramArrayOffloat)) ? d(paramArrayOffloat, paramLong1, paramLong2) : paramArrayOffloat;
/*     */   } public static void a(float[][] paramArrayOffloat1, float[][] paramArrayOffloat2, long paramLong1, long paramLong2) {
/*     */     // Byte code:
/*     */     //   0: getstatic me/konsolas/aac/kn.k : J
/*     */     //   3: ldc2_w 6768219863403
/*     */     //   6: lxor
/*     */     //   7: lstore #6
/*     */     //   9: iconst_2
/*     */     //   10: istore #8
/*     */     //   12: aload_0
/*     */     //   13: invokestatic a : ([[F)J
/*     */     //   16: aload_1
/*     */     //   17: invokestatic a : ([[F)J
/*     */     //   20: lcmp
/*     */     //   21: ifeq -> 68
/*     */     //   24: new java/lang/IllegalArgumentException
/*     */     //   27: dup
/*     */     //   28: ldc_w '䀹띤쨷┺⧻㎫瓬⸱퉶톀砓ூ?ዱ훫瞟畒䙾'
/*     */     //   31: invokevirtual toCharArray : ()[C
/*     */     //   34: dup
/*     */     //   35: dup
/*     */     //   36: iconst_3
/*     */     //   37: dup_x1
/*     */     //   38: caload
/*     */     //   39: sipush #6092
/*     */     //   42: ixor
/*     */     //   43: i2c
/*     */     //   44: castore
/*     */     //   45: sipush #16104
/*     */     //   48: iconst_1
/*     */     //   49: iconst_0
/*     */     //   50: invokestatic X : (Ljava/lang/Object;SZZ)Ljava/lang/String;
/*     */     //   53: invokespecial <init> : (Ljava/lang/String;)V
/*     */     //   56: athrow
/*     */     //   57: ldc2_w -1102069506861159613
/*     */     //   60: lload #6
/*     */     //   62: <illegal opcode> w : (Ljava/lang/IllegalArgumentException;JJ)Ljava/lang/IllegalArgumentException;
/*     */     //   67: athrow
/*     */     //   68: bipush #7
/*     */     //   70: istore #9
/*     */     //   72: sipush #1786
/*     */     //   75: istore #10
/*     */     //   77: sipush #1786
/*     */     //   80: newarray long
/*     */     //   82: astore #11
/*     */     //   84: iconst_0
/*     */     //   85: istore #12
/*     */     //   87: sipush #1786
/*     */     //   90: newarray long
/*     */     //   92: astore #13
/*     */     //   94: iconst_0
/*     */     //   95: istore #14
/*     */     //   97: sipush #1786
/*     */     //   100: newarray int
/*     */     //   102: astore #15
/*     */     //   104: iconst_0
/*     */     //   105: istore #16
/*     */     //   107: aload #11
/*     */     //   109: iload #12
/*     */     //   111: iinc #12, 1
/*     */     //   114: lload_2
/*     */     //   115: lastore
/*     */     //   116: aload #13
/*     */     //   118: iload #14
/*     */     //   120: iinc #14, 1
/*     */     //   123: lload #4
/*     */     //   125: lload_2
/*     */     //   126: lsub
/*     */     //   127: lastore
/*     */     //   128: aload #15
/*     */     //   130: iload #16
/*     */     //   132: iinc #16, 1
/*     */     //   135: iconst_0
/*     */     //   136: iastore
/*     */     //   137: sipush #256
/*     */     //   140: newarray long
/*     */     //   142: astore #17
/*     */     //   144: sipush #256
/*     */     //   147: newarray long
/*     */     //   149: astore #18
/*     */     //   151: lload #4
/*     */     //   153: lload_2
/*     */     //   154: lsub
/*     */     //   155: invokestatic a : (J)[[B
/*     */     //   158: astore #19
/*     */     //   160: iload #12
/*     */     //   162: ifle -> 761
/*     */     //   165: aload #11
/*     */     //   167: iinc #12, -1
/*     */     //   170: iload #12
/*     */     //   172: laload
/*     */     //   173: lstore #20
/*     */     //   175: aload #13
/*     */     //   177: iinc #14, -1
/*     */     //   180: iload #14
/*     */     //   182: laload
/*     */     //   183: lstore #22
/*     */     //   185: aload #15
/*     */     //   187: iinc #16, -1
/*     */     //   190: iload #16
/*     */     //   192: iaload
/*     */     //   193: istore #24
/*     */     //   195: iload #24
/*     */     //   197: iconst_4
/*     */     //   198: irem
/*     */     //   199: ifne -> 219
/*     */     //   202: sipush #128
/*     */     //   205: goto -> 220
/*     */     //   208: ldc2_w -1102069506861159613
/*     */     //   211: lload #6
/*     */     //   213: <illegal opcode> w : (Ljava/lang/IllegalArgumentException;JJ)Ljava/lang/IllegalArgumentException;
/*     */     //   218: athrow
/*     */     //   219: iconst_0
/*     */     //   220: istore #25
/*     */     //   222: lload #22
/*     */     //   224: ldc2_w 40
/*     */     //   227: lcmp
/*     */     //   228: ifge -> 257
/*     */     //   231: aload_0
/*     */     //   232: aload_1
/*     */     //   233: lload #20
/*     */     //   235: lload #20
/*     */     //   237: lload #22
/*     */     //   239: ladd
/*     */     //   240: invokestatic b : ([[F[[FJJ)V
/*     */     //   243: goto -> 160
/*     */     //   246: ldc2_w -1102069506861159613
/*     */     //   249: lload #6
/*     */     //   251: <illegal opcode> w : (Ljava/lang/IllegalArgumentException;JJ)Ljava/lang/IllegalArgumentException;
/*     */     //   256: athrow
/*     */     //   257: iload #24
/*     */     //   259: iconst_4
/*     */     //   260: if_icmpge -> 278
/*     */     //   263: aload_0
/*     */     //   264: goto -> 279
/*     */     //   267: ldc2_w -1102069506861159613
/*     */     //   270: lload #6
/*     */     //   272: <illegal opcode> w : (Ljava/lang/IllegalArgumentException;JJ)Ljava/lang/IllegalArgumentException;
/*     */     //   277: athrow
/*     */     //   278: aload_1
/*     */     //   279: astore #26
/*     */     //   281: iconst_3
/*     */     //   282: iload #24
/*     */     //   284: iconst_4
/*     */     //   285: irem
/*     */     //   286: isub
/*     */     //   287: bipush #8
/*     */     //   289: imul
/*     */     //   290: istore #27
/*     */     //   292: lload #22
/*     */     //   294: lstore #28
/*     */     //   296: lload #28
/*     */     //   298: dup2
/*     */     //   299: lconst_1
/*     */     //   300: lsub
/*     */     //   301: lstore #28
/*     */     //   303: lconst_0
/*     */     //   304: lcmp
/*     */     //   305: ifeq -> 353
/*     */     //   308: aload #19
/*     */     //   310: lload #28
/*     */     //   312: aload #26
/*     */     //   314: lload #20
/*     */     //   316: lload #28
/*     */     //   318: ladd
/*     */     //   319: invokestatic a : ([[FJ)F
/*     */     //   322: invokestatic a : (F)I
/*     */     //   325: iload #27
/*     */     //   327: iushr
/*     */     //   328: sipush #255
/*     */     //   331: iand
/*     */     //   332: iload #25
/*     */     //   334: ixor
/*     */     //   335: i2b
/*     */     //   336: invokestatic b : ([[BJB)V
/*     */     //   339: goto -> 296
/*     */     //   342: ldc2_w -1102069506861159613
/*     */     //   345: lload #6
/*     */     //   347: <illegal opcode> w : (Ljava/lang/IllegalArgumentException;JJ)Ljava/lang/IllegalArgumentException;
/*     */     //   352: athrow
/*     */     //   353: lload #22
/*     */     //   355: lstore #28
/*     */     //   357: lload #28
/*     */     //   359: dup2
/*     */     //   360: lconst_1
/*     */     //   361: lsub
/*     */     //   362: lstore #28
/*     */     //   364: lconst_0
/*     */     //   365: lcmp
/*     */     //   366: ifeq -> 401
/*     */     //   369: aload #17
/*     */     //   371: aload #19
/*     */     //   373: lload #28
/*     */     //   375: invokestatic a : ([[BJ)B
/*     */     //   378: sipush #255
/*     */     //   381: iand
/*     */     //   382: dup2
/*     */     //   383: laload
/*     */     //   384: lconst_1
/*     */     //   385: ladd
/*     */     //   386: lastore
/*     */     //   387: goto -> 357
/*     */     //   390: ldc2_w -1102069506861159613
/*     */     //   393: lload #6
/*     */     //   395: <illegal opcode> w : (Ljava/lang/IllegalArgumentException;JJ)Ljava/lang/IllegalArgumentException;
/*     */     //   400: athrow
/*     */     //   401: iconst_m1
/*     */     //   402: istore #28
/*     */     //   404: lconst_0
/*     */     //   405: lstore #29
/*     */     //   407: iconst_0
/*     */     //   408: istore #31
/*     */     //   410: iload #31
/*     */     //   412: sipush #256
/*     */     //   415: if_icmpge -> 551
/*     */     //   418: aload #17
/*     */     //   420: iload #31
/*     */     //   422: laload
/*     */     //   423: lconst_0
/*     */     //   424: lcmp
/*     */     //   425: ifeq -> 529
/*     */     //   428: goto -> 442
/*     */     //   431: ldc2_w -1102069506861159613
/*     */     //   434: lload #6
/*     */     //   436: <illegal opcode> w : (Ljava/lang/IllegalArgumentException;JJ)Ljava/lang/IllegalArgumentException;
/*     */     //   441: athrow
/*     */     //   442: iload #31
/*     */     //   444: istore #28
/*     */     //   446: iload #24
/*     */     //   448: bipush #7
/*     */     //   450: if_icmpge -> 529
/*     */     //   453: aload #17
/*     */     //   455: iload #31
/*     */     //   457: laload
/*     */     //   458: lconst_1
/*     */     //   459: lcmp
/*     */     //   460: ifle -> 529
/*     */     //   463: goto -> 477
/*     */     //   466: ldc2_w -1102069506861159613
/*     */     //   469: lload #6
/*     */     //   471: <illegal opcode> w : (Ljava/lang/IllegalArgumentException;JJ)Ljava/lang/IllegalArgumentException;
/*     */     //   476: athrow
/*     */     //   477: aload #11
/*     */     //   479: iload #12
/*     */     //   481: iinc #12, 1
/*     */     //   484: lload #29
/*     */     //   486: lload #20
/*     */     //   488: ladd
/*     */     //   489: lastore
/*     */     //   490: aload #13
/*     */     //   492: iload #14
/*     */     //   494: iinc #14, 1
/*     */     //   497: aload #17
/*     */     //   499: iload #31
/*     */     //   501: laload
/*     */     //   502: lastore
/*     */     //   503: aload #15
/*     */     //   505: iload #16
/*     */     //   507: iinc #16, 1
/*     */     //   510: iload #24
/*     */     //   512: iconst_1
/*     */     //   513: iadd
/*     */     //   514: iastore
/*     */     //   515: goto -> 529
/*     */     //   518: ldc2_w -1102069506861159613
/*     */     //   521: lload #6
/*     */     //   523: <illegal opcode> w : (Ljava/lang/IllegalArgumentException;JJ)Ljava/lang/IllegalArgumentException;
/*     */     //   528: athrow
/*     */     //   529: aload #18
/*     */     //   531: iload #31
/*     */     //   533: lload #29
/*     */     //   535: aload #17
/*     */     //   537: iload #31
/*     */     //   539: laload
/*     */     //   540: ladd
/*     */     //   541: dup2
/*     */     //   542: lstore #29
/*     */     //   544: lastore
/*     */     //   545: iinc #31, 1
/*     */     //   548: goto -> 410
/*     */     //   551: lload #22
/*     */     //   553: aload #17
/*     */     //   555: iload #28
/*     */     //   557: laload
/*     */     //   558: lsub
/*     */     //   559: lstore #31
/*     */     //   561: aload #17
/*     */     //   563: iload #28
/*     */     //   565: lconst_0
/*     */     //   566: lastore
/*     */     //   567: iconst_m1
/*     */     //   568: istore #33
/*     */     //   570: lconst_0
/*     */     //   571: lstore #34
/*     */     //   573: lload #34
/*     */     //   575: lload #31
/*     */     //   577: lcmp
/*     */     //   578: ifge -> 758
/*     */     //   581: aload_0
/*     */     //   582: lload #34
/*     */     //   584: lload #20
/*     */     //   586: ladd
/*     */     //   587: invokestatic a : ([[FJ)F
/*     */     //   590: fstore #38
/*     */     //   592: aload_1
/*     */     //   593: lload #34
/*     */     //   595: lload #20
/*     */     //   597: ladd
/*     */     //   598: invokestatic a : ([[FJ)F
/*     */     //   601: fstore #39
/*     */     //   603: aload #19
/*     */     //   605: lload #34
/*     */     //   607: invokestatic a : ([[BJ)B
/*     */     //   610: sipush #255
/*     */     //   613: iand
/*     */     //   614: istore #33
/*     */     //   616: aload #18
/*     */     //   618: iload #33
/*     */     //   620: dup2
/*     */     //   621: laload
/*     */     //   622: lconst_1
/*     */     //   623: lsub
/*     */     //   624: dup2_x2
/*     */     //   625: lastore
/*     */     //   626: dup2
/*     */     //   627: lstore #36
/*     */     //   629: lload #34
/*     */     //   631: lcmp
/*     */     //   632: ifle -> 717
/*     */     //   635: fload #38
/*     */     //   637: fstore #40
/*     */     //   639: iload #33
/*     */     //   641: istore #41
/*     */     //   643: aload_0
/*     */     //   644: lload #36
/*     */     //   646: lload #20
/*     */     //   648: ladd
/*     */     //   649: invokestatic a : ([[FJ)F
/*     */     //   652: fstore #38
/*     */     //   654: aload_0
/*     */     //   655: lload #36
/*     */     //   657: lload #20
/*     */     //   659: ladd
/*     */     //   660: fload #40
/*     */     //   662: invokestatic a : ([[FJF)V
/*     */     //   665: fload #39
/*     */     //   667: fstore #40
/*     */     //   669: aload_1
/*     */     //   670: lload #36
/*     */     //   672: lload #20
/*     */     //   674: ladd
/*     */     //   675: invokestatic a : ([[FJ)F
/*     */     //   678: fstore #39
/*     */     //   680: aload_1
/*     */     //   681: lload #36
/*     */     //   683: lload #20
/*     */     //   685: ladd
/*     */     //   686: fload #40
/*     */     //   688: invokestatic a : ([[FJF)V
/*     */     //   691: aload #19
/*     */     //   693: lload #36
/*     */     //   695: invokestatic a : ([[BJ)B
/*     */     //   698: sipush #255
/*     */     //   701: iand
/*     */     //   702: istore #33
/*     */     //   704: aload #19
/*     */     //   706: lload #36
/*     */     //   708: iload #41
/*     */     //   710: i2b
/*     */     //   711: invokestatic b : ([[BJB)V
/*     */     //   714: goto -> 616
/*     */     //   717: aload_0
/*     */     //   718: lload #34
/*     */     //   720: lload #20
/*     */     //   722: ladd
/*     */     //   723: fload #38
/*     */     //   725: invokestatic a : ([[FJF)V
/*     */     //   728: aload_1
/*     */     //   729: lload #34
/*     */     //   731: lload #20
/*     */     //   733: ladd
/*     */     //   734: fload #39
/*     */     //   736: invokestatic a : ([[FJF)V
/*     */     //   739: lload #34
/*     */     //   741: aload #17
/*     */     //   743: iload #33
/*     */     //   745: laload
/*     */     //   746: ladd
/*     */     //   747: lstore #34
/*     */     //   749: aload #17
/*     */     //   751: iload #33
/*     */     //   753: lconst_0
/*     */     //   754: lastore
/*     */     //   755: goto -> 573
/*     */     //   758: goto -> 160
/*     */     //   761: return
/*     */     // Line number table:
/*     */     //   Java source line number -> byte code offset
/*     */     //   #41	-> 9
/*     */     //   #182	-> 12
/*     */     //   #138	-> 68
/*     */     //   #286	-> 72
/*     */     //   #240	-> 77
/*     */     //   #177	-> 84
/*     */     //   #210	-> 87
/*     */     //   #349	-> 94
/*     */     //   #230	-> 97
/*     */     //   #357	-> 104
/*     */     //   #38	-> 107
/*     */     //   #237	-> 116
/*     */     //   #195	-> 128
/*     */     //   #304	-> 137
/*     */     //   #172	-> 144
/*     */     //   #312	-> 151
/*     */     //   #232	-> 160
/*     */     //   #322	-> 165
/*     */     //   #383	-> 175
/*     */     //   #350	-> 185
/*     */     //   #171	-> 195
/*     */     //   #97	-> 222
/*     */     //   #100	-> 231
/*     */     //   #213	-> 243
/*     */     //   #203	-> 257
/*     */     //   #207	-> 281
/*     */     //   #198	-> 292
/*     */     //   #104	-> 353
/*     */     //   #222	-> 401
/*     */     //   #226	-> 404
/*     */     //   #379	-> 407
/*     */     //   #52	-> 418
/*     */     //   #120	-> 442
/*     */     //   #252	-> 446
/*     */     //   #234	-> 477
/*     */     //   #279	-> 490
/*     */     //   #103	-> 503
/*     */     //   #183	-> 529
/*     */     //   #405	-> 545
/*     */     //   #174	-> 551
/*     */     //   #87	-> 561
/*     */     //   #128	-> 567
/*     */     //   #92	-> 570
/*     */     //   #72	-> 581
/*     */     //   #415	-> 592
/*     */     //   #215	-> 603
/*     */     //   #110	-> 616
/*     */     //   #307	-> 635
/*     */     //   #170	-> 639
/*     */     //   #395	-> 643
/*     */     //   #12	-> 654
/*     */     //   #16	-> 665
/*     */     //   #8	-> 669
/*     */     //   #69	-> 680
/*     */     //   #129	-> 691
/*     */     //   #291	-> 704
/*     */     //   #315	-> 714
/*     */     //   #64	-> 717
/*     */     //   #22	-> 728
/*     */     //   #18	-> 739
/*     */     //   #168	-> 758
/*     */     //   #154	-> 761
/*     */     // Exception table:
/*     */     //   from	to	target	type
/*     */     //   12	57	57	java/lang/IllegalArgumentException
/*     */     //   195	208	208	java/lang/IllegalArgumentException
/*     */     //   222	246	246	java/lang/IllegalArgumentException
/*     */     //   257	267	267	java/lang/IllegalArgumentException
/*     */     //   303	342	342	java/lang/IllegalArgumentException
/*     */     //   364	390	390	java/lang/IllegalArgumentException
/*     */     //   410	428	431	java/lang/IllegalArgumentException
/*     */     //   446	463	466	java/lang/IllegalArgumentException
/*     */     //   453	515	518	java/lang/IllegalArgumentException
/*     */   } private static final long k = nc.a(-2014394378632959842L, -8263937628818661080L, MethodHandles.lookup().lookupClass()).a(158600997818165L); static {
/*     */     g = new float[0][];
/*     */     e = new float[0][];
/*     */     j = new dn(null);
/*     */   }
/*     */   @Deprecated
/*     */   public static float[][] b(float[][] paramArrayOffloat, long paramLong) {
/*     */     long l = a(paramArrayOffloat);
/*     */     try {
/*     */     
/*     */     } catch (IllegalArgumentException illegalArgumentException) {
/*     */       throw a(null);
/*     */     } 
/*     */     return (paramLong > l) ? b(paramArrayOffloat, paramLong, l) : paramArrayOffloat;
/*     */   }
/*     */   public static void c(float[][] paramArrayOffloat, long paramLong1, long paramLong2, il paramil) {
/*     */     ForkJoinPool forkJoinPool = a();
/*     */     
/* 348 */     try { if (paramLong2 - paramLong1 >= 8192L) { try { if (forkJoinPool.getParallelism() == 1) { b(paramArrayOffloat, paramLong1, paramLong2, paramil); return; }  } catch (IllegalArgumentException illegalArgumentException) { throw a(null); }  forkJoinPool.invoke(new iX(paramArrayOffloat, paramLong1, paramLong2, paramil)); return; }  } catch (IllegalArgumentException illegalArgumentException) { throw a(null); }  b(paramArrayOffloat, paramLong1, paramLong2, paramil);
/*     */   }
/*     */ 
/*     */   
/*     */   @Deprecated
/*     */   public static float[][] a(float[][] paramArrayOffloat, long paramLong1, long paramLong2) {
/*     */     return k.b(paramArrayOffloat, paramLong1, paramLong2);
/*     */   }
/*     */ 
/*     */   
/*     */   @Deprecated
/*     */   public static void d(float[][] paramArrayOffloat, long paramLong1, long paramLong2) {
/*     */     k.a(a(paramArrayOffloat), paramLong1, paramLong2);
/*     */   }
/*     */   
/*     */   public static long a(float[][] paramArrayOffloat, float paramFloat) {
/*     */     return a(paramArrayOffloat, 0L, k.a(paramArrayOffloat), paramFloat);
/*     */   }
/*     */   
/*     */   public static long a(float[][] paramArrayOffloat, long paramLong1, long paramLong2, float paramFloat) {
/*     */     paramLong2--;
/*     */     while (paramLong1 <= paramLong2) {
/*     */       long l = paramLong1 + paramLong2 >>> 1L;
/*     */       float f = k.a(paramArrayOffloat, l);
/*     */       if (f < paramFloat) {
/*     */         paramLong1 = l + 1L;
/*     */         continue;
/*     */       } 
/*     */       if (f > paramFloat) {
/*     */         paramLong2 = l - 1L;
/*     */         continue;
/*     */       } 
/*     */       return l;
/*     */     } 
/*     */     return -(paramLong1 + 1L);
/*     */   }
/*     */   
/*     */   @Deprecated
/*     */   public static float[][] b(float[][] paramArrayOffloat, long paramLong1, long paramLong2) {
/*     */     long l = a(paramArrayOffloat);
/*     */     try {
/*     */     
/*     */     } catch (IllegalArgumentException illegalArgumentException) {
/*     */       throw a(null);
/*     */     } 
/*     */     return (paramLong1 > l) ? c(paramArrayOffloat, Math.max(l + (l >> 1L), paramLong1), paramLong2) : paramArrayOffloat;
/*     */   }
/*     */   
/*     */   @Deprecated
/*     */   public static void a(float[] paramArrayOffloat, int paramInt, float[][] paramArrayOffloat1, long paramLong1, long paramLong2) {
/*     */     k.a(paramArrayOffloat, paramInt, paramArrayOffloat1, paramLong1, paramLong2);
/*     */   }
/*     */   
/*     */   @Deprecated
/*     */   public static void a(float[][] paramArrayOffloat, long paramLong1, long paramLong2, float paramFloat) {
/*     */     k.a(paramArrayOffloat, paramLong1, paramLong2, paramFloat);
/*     */   }
/*     */   
/*     */   public static float[][] a(long paramLong) {
/*     */     try {
/*     */       if (paramLong == 0L) {
/*     */         return g;
/*     */       }
/*     */     } catch (IllegalArgumentException illegalArgumentException) {
/*     */       throw a(null);
/*     */     } 
/*     */     k.a(paramLong);
/*     */     int i = (int)(paramLong + 134217727L >>> 27L);
/*     */     float[][] arrayOfFloat = new float[i][];
/* 417 */     int j = (int)(paramLong & 0x7FFFFFFL);
/*     */     if (j != 0) {
/*     */       byte b = 0;
/*     */       try {
/*     */         while (b < i - 1) {
/*     */           arrayOfFloat[b] = new float[134217728];
/*     */           b++;
/*     */         } 
/*     */       } catch (IllegalArgumentException illegalArgumentException) {
/*     */         throw a(null);
/*     */       } 
/*     */       arrayOfFloat[i - 1] = new float[j];
/*     */     } else {
/*     */       byte b = 0;
/*     */       try {
/*     */         while (b < i) {
/*     */           arrayOfFloat[b] = new float[134217728];
/*     */           b++;
/*     */         } 
/*     */       } catch (IllegalArgumentException illegalArgumentException) {
/*     */         throw a(null);
/*     */       } 
/*     */     } 
/*     */     return arrayOfFloat;
/*     */   }
/*     */   
/*     */   @Deprecated
/*     */   public static void b(float[][] paramArrayOffloat, long paramLong, float paramFloat) {
/*     */     paramArrayOffloat[k.b(paramLong)][k.a(paramLong)] = paramFloat;
/*     */   }
/*     */   
/*     */   @Deprecated
/*     */   public static float[][] c(float[][] paramArrayOffloat, long paramLong) {
/*     */     return c(paramArrayOffloat, paramLong, a(paramArrayOffloat));
/*     */   }
/*     */   
/*     */   public static void b(float[][] paramArrayOffloat, long paramLong1, long paramLong2, il paramil) {
/*     */     // Byte code:
/*     */     //   0: lload_3
/*     */     //   1: lload_1
/*     */     //   2: lsub
/*     */     //   3: lstore #6
/*     */     //   5: lload #6
/*     */     //   7: ldc2_w 7
/*     */     //   10: lcmp
/*     */     //   11: ifge -> 27
/*     */     //   14: aload_0
/*     */     //   15: lload_1
/*     */     //   16: lload_3
/*     */     //   17: aload #5
/*     */     //   19: invokestatic a : ([[FJJLme/konsolas/aac/il;)V
/*     */     //   22: return
/*     */     //   23: invokestatic a : (Ljava/lang/IllegalArgumentException;)Ljava/lang/IllegalArgumentException;
/*     */     //   26: athrow
/*     */     //   27: lload_1
/*     */     //   28: lload #6
/*     */     //   30: ldc2_w 2
/*     */     //   33: ldiv
/*     */     //   34: ladd
/*     */     //   35: lstore #8
/*     */     //   37: lload #6
/*     */     //   39: ldc2_w 7
/*     */     //   42: lcmp
/*     */     //   43: ifle -> 153
/*     */     //   46: lload_1
/*     */     //   47: lstore #10
/*     */     //   49: lload_3
/*     */     //   50: lconst_1
/*     */     //   51: lsub
/*     */     //   52: lstore #12
/*     */     //   54: lload #6
/*     */     //   56: ldc2_w 40
/*     */     //   59: lcmp
/*     */     //   60: ifle -> 139
/*     */     //   63: lload #6
/*     */     //   65: ldc2_w 8
/*     */     //   68: ldiv
/*     */     //   69: lstore #14
/*     */     //   71: aload_0
/*     */     //   72: lload #10
/*     */     //   74: lload #10
/*     */     //   76: lload #14
/*     */     //   78: ladd
/*     */     //   79: lload #10
/*     */     //   81: ldc2_w 2
/*     */     //   84: lload #14
/*     */     //   86: lmul
/*     */     //   87: ladd
/*     */     //   88: aload #5
/*     */     //   90: invokestatic a : ([[FJJJLme/konsolas/aac/il;)J
/*     */     //   93: lstore #10
/*     */     //   95: aload_0
/*     */     //   96: lload #8
/*     */     //   98: lload #14
/*     */     //   100: lsub
/*     */     //   101: lload #8
/*     */     //   103: lload #8
/*     */     //   105: lload #14
/*     */     //   107: ladd
/*     */     //   108: aload #5
/*     */     //   110: invokestatic a : ([[FJJJLme/konsolas/aac/il;)J
/*     */     //   113: lstore #8
/*     */     //   115: aload_0
/*     */     //   116: lload #12
/*     */     //   118: ldc2_w 2
/*     */     //   121: lload #14
/*     */     //   123: lmul
/*     */     //   124: lsub
/*     */     //   125: lload #12
/*     */     //   127: lload #14
/*     */     //   129: lsub
/*     */     //   130: lload #12
/*     */     //   132: aload #5
/*     */     //   134: invokestatic a : ([[FJJJLme/konsolas/aac/il;)J
/*     */     //   137: lstore #12
/*     */     //   139: aload_0
/*     */     //   140: lload #10
/*     */     //   142: lload #8
/*     */     //   144: lload #12
/*     */     //   146: aload #5
/*     */     //   148: invokestatic a : ([[FJJJLme/konsolas/aac/il;)J
/*     */     //   151: lstore #8
/*     */     //   153: aload_0
/*     */     //   154: lload #8
/*     */     //   156: invokestatic a : ([[FJ)F
/*     */     //   159: fstore #10
/*     */     //   161: lload_1
/*     */     //   162: lstore #11
/*     */     //   164: lload #11
/*     */     //   166: lstore #13
/*     */     //   168: lload_3
/*     */     //   169: lconst_1
/*     */     //   170: lsub
/*     */     //   171: lstore #15
/*     */     //   173: lload #15
/*     */     //   175: lstore #17
/*     */     //   177: lload #13
/*     */     //   179: lload #15
/*     */     //   181: lcmp
/*     */     //   182: ifgt -> 240
/*     */     //   185: aload #5
/*     */     //   187: aload_0
/*     */     //   188: lload #13
/*     */     //   190: invokestatic a : ([[FJ)F
/*     */     //   193: fload #10
/*     */     //   195: invokeinterface a : (FF)I
/*     */     //   200: dup
/*     */     //   201: istore #19
/*     */     //   203: ifgt -> 240
/*     */     //   206: iload #19
/*     */     //   208: ifne -> 231
/*     */     //   211: goto -> 218
/*     */     //   214: invokestatic a : (Ljava/lang/IllegalArgumentException;)Ljava/lang/IllegalArgumentException;
/*     */     //   217: athrow
/*     */     //   218: aload_0
/*     */     //   219: lload #11
/*     */     //   221: dup2
/*     */     //   222: lconst_1
/*     */     //   223: ladd
/*     */     //   224: lstore #11
/*     */     //   226: lload #13
/*     */     //   228: invokestatic b : ([[FJJ)V
/*     */     //   231: lload #13
/*     */     //   233: lconst_1
/*     */     //   234: ladd
/*     */     //   235: lstore #13
/*     */     //   237: goto -> 177
/*     */     //   240: lload #15
/*     */     //   242: lload #13
/*     */     //   244: lcmp
/*     */     //   245: iflt -> 303
/*     */     //   248: aload #5
/*     */     //   250: aload_0
/*     */     //   251: lload #15
/*     */     //   253: invokestatic a : ([[FJ)F
/*     */     //   256: fload #10
/*     */     //   258: invokeinterface a : (FF)I
/*     */     //   263: dup
/*     */     //   264: istore #19
/*     */     //   266: iflt -> 303
/*     */     //   269: iload #19
/*     */     //   271: ifne -> 294
/*     */     //   274: goto -> 281
/*     */     //   277: invokestatic a : (Ljava/lang/IllegalArgumentException;)Ljava/lang/IllegalArgumentException;
/*     */     //   280: athrow
/*     */     //   281: aload_0
/*     */     //   282: lload #15
/*     */     //   284: lload #17
/*     */     //   286: dup2
/*     */     //   287: lconst_1
/*     */     //   288: lsub
/*     */     //   289: lstore #17
/*     */     //   291: invokestatic b : ([[FJJ)V
/*     */     //   294: lload #15
/*     */     //   296: lconst_1
/*     */     //   297: lsub
/*     */     //   298: lstore #15
/*     */     //   300: goto -> 240
/*     */     //   303: lload #13
/*     */     //   305: lload #15
/*     */     //   307: lcmp
/*     */     //   308: ifle -> 318
/*     */     //   311: goto -> 339
/*     */     //   314: invokestatic a : (Ljava/lang/IllegalArgumentException;)Ljava/lang/IllegalArgumentException;
/*     */     //   317: athrow
/*     */     //   318: aload_0
/*     */     //   319: lload #13
/*     */     //   321: dup2
/*     */     //   322: lconst_1
/*     */     //   323: ladd
/*     */     //   324: lstore #13
/*     */     //   326: lload #15
/*     */     //   328: dup2
/*     */     //   329: lconst_1
/*     */     //   330: lsub
/*     */     //   331: lstore #15
/*     */     //   333: invokestatic b : ([[FJJ)V
/*     */     //   336: goto -> 177
/*     */     //   339: lload_3
/*     */     //   340: lstore #21
/*     */     //   342: lload #11
/*     */     //   344: lload_1
/*     */     //   345: lsub
/*     */     //   346: lload #13
/*     */     //   348: lload #11
/*     */     //   350: lsub
/*     */     //   351: invokestatic min : (JJ)J
/*     */     //   354: lstore #19
/*     */     //   356: aload_0
/*     */     //   357: lload_1
/*     */     //   358: lload #13
/*     */     //   360: lload #19
/*     */     //   362: lsub
/*     */     //   363: lload #19
/*     */     //   365: invokestatic b : ([[FJJJ)V
/*     */     //   368: lload #17
/*     */     //   370: lload #15
/*     */     //   372: lsub
/*     */     //   373: lload #21
/*     */     //   375: lload #17
/*     */     //   377: lsub
/*     */     //   378: lconst_1
/*     */     //   379: lsub
/*     */     //   380: invokestatic min : (JJ)J
/*     */     //   383: lstore #19
/*     */     //   385: aload_0
/*     */     //   386: lload #13
/*     */     //   388: lload #21
/*     */     //   390: lload #19
/*     */     //   392: lsub
/*     */     //   393: lload #19
/*     */     //   395: invokestatic b : ([[FJJJ)V
/*     */     //   398: lload #13
/*     */     //   400: lload #11
/*     */     //   402: lsub
/*     */     //   403: dup2
/*     */     //   404: lstore #19
/*     */     //   406: lconst_1
/*     */     //   407: lcmp
/*     */     //   408: ifle -> 429
/*     */     //   411: aload_0
/*     */     //   412: lload_1
/*     */     //   413: lload_1
/*     */     //   414: lload #19
/*     */     //   416: ladd
/*     */     //   417: aload #5
/*     */     //   419: invokestatic b : ([[FJJLme/konsolas/aac/il;)V
/*     */     //   422: goto -> 429
/*     */     //   425: invokestatic a : (Ljava/lang/IllegalArgumentException;)Ljava/lang/IllegalArgumentException;
/*     */     //   428: athrow
/*     */     //   429: lload #17
/*     */     //   431: lload #15
/*     */     //   433: lsub
/*     */     //   434: dup2
/*     */     //   435: lstore #19
/*     */     //   437: lconst_1
/*     */     //   438: lcmp
/*     */     //   439: ifle -> 462
/*     */     //   442: aload_0
/*     */     //   443: lload #21
/*     */     //   445: lload #19
/*     */     //   447: lsub
/*     */     //   448: lload #21
/*     */     //   450: aload #5
/*     */     //   452: invokestatic b : ([[FJJLme/konsolas/aac/il;)V
/*     */     //   455: goto -> 462
/*     */     //   458: invokestatic a : (Ljava/lang/IllegalArgumentException;)Ljava/lang/IllegalArgumentException;
/*     */     //   461: athrow
/*     */     //   462: return
/*     */     // Line number table:
/*     */     //   Java source line number -> byte code offset
/*     */     //   #133	-> 0
/*     */     //   #17	-> 5
/*     */     //   #325	-> 14
/*     */     //   #361	-> 22
/*     */     //   #123	-> 27
/*     */     //   #61	-> 37
/*     */     //   #75	-> 46
/*     */     //   #50	-> 49
/*     */     //   #344	-> 54
/*     */     //   #277	-> 63
/*     */     //   #39	-> 71
/*     */     //   #141	-> 95
/*     */     //   #221	-> 115
/*     */     //   #165	-> 139
/*     */     //   #418	-> 153
/*     */     //   #238	-> 161
/*     */     //   #295	-> 177
/*     */     //   #131	-> 206
/*     */     //   #389	-> 231
/*     */     //   #90	-> 240
/*     */     //   #298	-> 269
/*     */     //   #71	-> 294
/*     */     //   #137	-> 303
/*     */     //   #194	-> 318
/*     */     //   #85	-> 339
/*     */     //   #223	-> 342
/*     */     //   #391	-> 356
/*     */     //   #368	-> 368
/*     */     //   #188	-> 385
/*     */     //   #288	-> 398
/*     */     //   #369	-> 429
/*     */     //   #48	-> 462
/*     */     // Exception table:
/*     */     //   from	to	target	type
/*     */     //   5	23	23	java/lang/IllegalArgumentException
/*     */     //   203	211	214	java/lang/IllegalArgumentException
/*     */     //   266	274	277	java/lang/IllegalArgumentException
/*     */     //   303	314	314	java/lang/IllegalArgumentException
/*     */     //   406	422	425	java/lang/IllegalArgumentException
/*     */     //   437	455	458	java/lang/IllegalArgumentException
/*     */   }
/*     */   
/*     */   @Deprecated
/*     */   public static void e(float[][] paramArrayOffloat, long paramLong1, long paramLong2) {
/*     */     float f = paramArrayOffloat[k.b(paramLong1)][k.a(paramLong1)];
/*     */     paramArrayOffloat[k.b(paramLong1)][k.a(paramLong1)] = paramArrayOffloat[k.b(paramLong2)][k.a(paramLong2)];
/*     */     paramArrayOffloat[k.b(paramLong2)][k.a(paramLong2)] = f;
/*     */   }
/*     */   
/*     */   public static void a(long[][] paramArrayOflong, float[][] paramArrayOffloat1, float[][] paramArrayOffloat2, boolean paramBoolean) {
/*     */     b(paramArrayOffloat1, paramArrayOffloat2);
/*     */     a(paramArrayOflong, paramArrayOffloat1, paramArrayOffloat2, 0L, k.a(paramArrayOffloat1), paramBoolean);
/*     */   }
/*     */   
/*     */   @Deprecated
/*     */   public static void a(float[][] paramArrayOffloat, float paramFloat) {
/*     */     int i = paramArrayOffloat.length;
/*     */     try {
/*     */       for (; i-- != 0; Arrays.fill(paramArrayOffloat[i], paramFloat));
/*     */     } catch (IllegalArgumentException illegalArgumentException) {
/*     */       throw a(null);
/*     */     } 
/*     */   }
/*     */   
/*     */   public static void b(float[][] paramArrayOffloat, long paramLong1, long paramLong2) {
/*     */     ForkJoinPool forkJoinPool = a();
/*     */     try {
/*     */       if (paramLong2 - paramLong1 >= 8192L) {
/*     */         try {
/*     */           if (forkJoinPool.getParallelism() == 1) {
/*     */             g(paramArrayOffloat, paramLong1, paramLong2);
/*     */             return;
/*     */           } 
/*     */         } catch (IllegalArgumentException illegalArgumentException) {
/*     */           throw a(null);
/*     */         } 
/*     */         forkJoinPool.invoke(new lf(paramArrayOffloat, paramLong1, paramLong2));
/*     */         return;
/*     */       } 
/*     */     } catch (IllegalArgumentException illegalArgumentException) {
/*     */       throw a(null);
/*     */     } 
/*     */     g(paramArrayOffloat, paramLong1, paramLong2);
/*     */   }
/*     */   
/*     */   private static void a(float[][] paramArrayOffloat, long paramLong1, long paramLong2, il paramil) {
/*     */     for (long l = paramLong1; l < paramLong2 - 1L; l2 = l + 1L)
/*     */       long l2, l1 = l; 
/*     */   }
/*     */   
/*     */   @Deprecated
/*     */   public static long a(float[][] paramArrayOffloat) {
/*     */     int i = paramArrayOffloat.length;
/*     */     try {
/*     */     
/*     */     } catch (IllegalArgumentException illegalArgumentException) {
/*     */       throw a(null);
/*     */     } 
/*     */     return (i == 0) ? 0L : (k.a(i - 1) + (paramArrayOffloat[i - 1]).length);
/*     */   }
/*     */   
/*     */   @Deprecated
/*     */   public static void b(float[][] paramArrayOffloat1, float[][] paramArrayOffloat2) {
/*     */     // Byte code:
/*     */     //   0: getstatic me/konsolas/aac/kn.k : J
/*     */     //   3: ldc2_w 109429181780808
/*     */     //   6: lxor
/*     */     //   7: lstore_2
/*     */     //   8: aload_0
/*     */     //   9: invokestatic a : ([[F)J
/*     */     //   12: aload_1
/*     */     //   13: invokestatic a : ([[F)J
/*     */     //   16: lcmp
/*     */     //   17: ifeq -> 117
/*     */     //   20: new java/lang/IllegalArgumentException
/*     */     //   23: dup
/*     */     //   24: new java/lang/StringBuilder
/*     */     //   27: dup
/*     */     //   28: invokespecial <init> : ()V
/*     */     //   31: ldc 'ᖗﯡ嬶ᅺ塽铧긒탑?⫐犎?ܠ엄夓ｩꌔ䰛'
/*     */     //   33: invokevirtual toCharArray : ()[C
/*     */     //   36: dup
/*     */     //   37: dup
/*     */     //   38: bipush #10
/*     */     //   40: dup_x1
/*     */     //   41: caload
/*     */     //   42: sipush #23958
/*     */     //   45: ixor
/*     */     //   46: i2c
/*     */     //   47: castore
/*     */     //   48: sipush #12277
/*     */     //   51: iconst_0
/*     */     //   52: iconst_1
/*     */     //   53: invokestatic U : (Ljava/lang/Object;SZZ)Ljava/lang/String;
/*     */     //   56: invokevirtual append : (Ljava/lang/String;)Ljava/lang/StringBuilder;
/*     */     //   59: aload_0
/*     */     //   60: invokestatic a : ([[F)J
/*     */     //   63: invokevirtual append : (J)Ljava/lang/StringBuilder;
/*     */     //   66: ldc '䠧ᱳ屦ῇ'
/*     */     //   68: invokevirtual toCharArray : ()[C
/*     */     //   71: dup
/*     */     //   72: dup
/*     */     //   73: iconst_3
/*     */     //   74: dup_x1
/*     */     //   75: caload
/*     */     //   76: sipush #9845
/*     */     //   79: ixor
/*     */     //   80: i2c
/*     */     //   81: castore
/*     */     //   82: sipush #5409
/*     */     //   85: iconst_0
/*     */     //   86: iconst_1
/*     */     //   87: invokestatic U : (Ljava/lang/Object;SZZ)Ljava/lang/String;
/*     */     //   90: invokevirtual append : (Ljava/lang/String;)Ljava/lang/StringBuilder;
/*     */     //   93: aload_1
/*     */     //   94: invokestatic a : ([[F)J
/*     */     //   97: invokevirtual append : (J)Ljava/lang/StringBuilder;
/*     */     //   100: invokevirtual toString : ()Ljava/lang/String;
/*     */     //   103: invokespecial <init> : (Ljava/lang/String;)V
/*     */     //   106: athrow
/*     */     //   107: ldc2_w -2695461281219673760
/*     */     //   110: lload_2
/*     */     //   111: <illegal opcode> w : (Ljava/lang/IllegalArgumentException;JJ)Ljava/lang/IllegalArgumentException;
/*     */     //   116: athrow
/*     */     //   117: return
/*     */     // Line number table:
/*     */     //   Java source line number -> byte code offset
/*     */     //   #178	-> 8
/*     */     //   #91	-> 117
/*     */     // Exception table:
/*     */     //   from	to	target	type
/*     */     //   8	107	107	java/lang/IllegalArgumentException
/*     */   }
/*     */   
/*     */   private static final int a(float paramFloat) {
/*     */     int i = Float.floatToRawIntBits(paramFloat);
/*     */     try {
/*     */     
/*     */     } catch (IllegalArgumentException illegalArgumentException) {
/*     */       throw a(null);
/*     */     } 
/*     */     return (i >= 0) ? i : (i ^ Integer.MAX_VALUE);
/*     */   }
/*     */   
/*     */   @Deprecated
/*     */   public static void b(float[][] paramArrayOffloat, long paramLong) {
/*     */     paramArrayOffloat[k.b(paramLong)][k.a(paramLong)] = paramArrayOffloat[k.b(paramLong)][k.a(paramLong)] + 1.0F;
/*     */   }
/*     */   
/*     */   @Deprecated
/*     */   public static boolean a(float[][] paramArrayOffloat1, float[][] paramArrayOffloat2) {
/*     */     return k.a(paramArrayOffloat1, paramArrayOffloat2);
/*     */   }
/*     */   
/*     */   public static void c(float[][] paramArrayOffloat) {
/*     */     b(paramArrayOffloat, 0L, k.a(paramArrayOffloat));
/*     */   }
/*     */   
/*     */   @Deprecated
/*     */   public static void a(float[][] paramArrayOffloat, long paramLong, float paramFloat) {
/*     */     paramArrayOffloat[k.b(paramLong)][k.a(paramLong)] = paramArrayOffloat[k.b(paramLong)][k.a(paramLong)] * paramFloat;
/*     */   }
/*     */   
/*     */   @Deprecated
/*     */   public static float a(float[][] paramArrayOffloat, long paramLong) {
/*     */     return paramArrayOffloat[k.b(paramLong)][k.a(paramLong)];
/*     */   }
/*     */   
/*     */   private static long b(float[][] paramArrayOffloat, long paramLong1, long paramLong2, long paramLong3) {
/*     */     int i = Float.compare(k.a(paramArrayOffloat, paramLong1), k.a(paramArrayOffloat, paramLong2));
/*     */     int j = Float.compare(k.a(paramArrayOffloat, paramLong1), k.a(paramArrayOffloat, paramLong3));
/*     */     int k = Float.compare(k.a(paramArrayOffloat, paramLong2), k.a(paramArrayOffloat, paramLong3));
/*     */     try {
/*     */       if (i < 0) {
/*     */         try {
/*     */           try {
/*     */           
/*     */           } catch (IllegalArgumentException illegalArgumentException) {
/*     */             throw a(null);
/*     */           } 
/*     */         } catch (IllegalArgumentException illegalArgumentException) {
/*     */           throw a(null);
/*     */         } 
/*     */       } else {
/*     */         try {
/*     */           try {
/*     */           
/*     */           } catch (IllegalArgumentException illegalArgumentException) {
/*     */             throw a(null);
/*     */           } 
/*     */         } catch (IllegalArgumentException illegalArgumentException) {
/*     */           throw a(null);
/*     */         } 
/*     */       } 
/*     */     } catch (IllegalArgumentException illegalArgumentException) {
/*     */       throw a(null);
/*     */     } 
/*     */     return (k > 0) ? paramLong2 : ((j > 0) ? paramLong3 : paramLong1);
/*     */   }
/*     */   
/*     */   @Deprecated
/*     */   public static float[][] d(float[][] paramArrayOffloat, long paramLong) {
/*     */     k.a(paramLong);
/*     */     long l = a(paramArrayOffloat);
/*     */     try {
/*     */       if (paramLong >= l)
/*     */         return paramArrayOffloat; 
/*     */     } catch (IllegalArgumentException illegalArgumentException) {
/*     */       throw a(null);
/*     */     } 
/*     */     int i = (int)(paramLong + 134217727L >>> 27L);
/*     */     float[][] arrayOfFloat = Arrays.<float[]>copyOf(paramArrayOffloat, i);
/*     */     int j = (int)(paramLong & 0x7FFFFFFL);
/*     */     try {
/*     */       if (j != 0)
/*     */         arrayOfFloat[i - 1] = fI.d(arrayOfFloat[i - 1], j); 
/*     */     } catch (IllegalArgumentException illegalArgumentException) {
/*     */       throw a(null);
/*     */     } 
/*     */     return arrayOfFloat;
/*     */   }
/*     */   
/*     */   private static void a(long[][] paramArrayOflong, float[][] paramArrayOffloat1, float[][] paramArrayOffloat2, long paramLong1, long paramLong2) {
/*     */     for (long l = paramLong1; ++l < paramLong2; l1 = l, l2 = k.a(paramArrayOflong, l1 - 1L)) {
/*     */       long l1 = k.a(paramArrayOflong, l);
/*     */       continue;
/*     */     } 
/*     */   }
/*     */   
/*     */   @Deprecated
/*     */   public static float[][] a(float[] paramArrayOffloat) {
/*     */     return k.a(paramArrayOffloat);
/*     */   }
/*     */   
/*     */   @Deprecated
/*     */   public static float[][] d(float[][] paramArrayOffloat, long paramLong1, long paramLong2) {
/*     */     return k.c(paramArrayOffloat, paramLong1, paramLong2);
/*     */   }
/*     */   
/*     */   @Deprecated
/*     */   public static float[][] a(float[][] paramArrayOffloat, long paramLong) {
/*     */     return k.d(paramArrayOffloat, paramLong);
/*     */   }
/*     */   
/*     */   public static float[][] a(float[][] paramArrayOffloat, Random paramRandom) {
/*     */     return k.a(paramArrayOffloat, paramRandom);
/*     */   }
/*     */   
/*     */   private static void b(float[][] paramArrayOffloat1, float[][] paramArrayOffloat2, long paramLong1, long paramLong2) {
/*     */     // Byte code:
/*     */     //   0: lload_2
/*     */     //   1: lstore #6
/*     */     //   3: lload #6
/*     */     //   5: lload #4
/*     */     //   7: lconst_1
/*     */     //   8: lsub
/*     */     //   9: lcmp
/*     */     //   10: ifge -> 192
/*     */     //   13: lload #6
/*     */     //   15: lstore #8
/*     */     //   17: lload #6
/*     */     //   19: lconst_1
/*     */     //   20: ladd
/*     */     //   21: lstore #10
/*     */     //   23: lload #10
/*     */     //   25: lload #4
/*     */     //   27: lcmp
/*     */     //   28: ifge -> 119
/*     */     //   31: aload_0
/*     */     //   32: lload #10
/*     */     //   34: invokestatic a : ([[FJ)F
/*     */     //   37: aload_0
/*     */     //   38: lload #8
/*     */     //   40: invokestatic a : ([[FJ)F
/*     */     //   43: invokestatic compare : (FF)I
/*     */     //   46: iflt -> 106
/*     */     //   49: goto -> 56
/*     */     //   52: invokestatic a : (Ljava/lang/IllegalArgumentException;)Ljava/lang/IllegalArgumentException;
/*     */     //   55: athrow
/*     */     //   56: aload_0
/*     */     //   57: lload #10
/*     */     //   59: invokestatic a : ([[FJ)F
/*     */     //   62: aload_0
/*     */     //   63: lload #8
/*     */     //   65: invokestatic a : ([[FJ)F
/*     */     //   68: invokestatic compare : (FF)I
/*     */     //   71: ifne -> 110
/*     */     //   74: goto -> 81
/*     */     //   77: invokestatic a : (Ljava/lang/IllegalArgumentException;)Ljava/lang/IllegalArgumentException;
/*     */     //   80: athrow
/*     */     //   81: aload_1
/*     */     //   82: lload #10
/*     */     //   84: invokestatic a : ([[FJ)F
/*     */     //   87: aload_1
/*     */     //   88: lload #8
/*     */     //   90: invokestatic a : ([[FJ)F
/*     */     //   93: invokestatic compare : (FF)I
/*     */     //   96: ifge -> 110
/*     */     //   99: goto -> 106
/*     */     //   102: invokestatic a : (Ljava/lang/IllegalArgumentException;)Ljava/lang/IllegalArgumentException;
/*     */     //   105: athrow
/*     */     //   106: lload #10
/*     */     //   108: lstore #8
/*     */     //   110: lload #10
/*     */     //   112: lconst_1
/*     */     //   113: ladd
/*     */     //   114: lstore #10
/*     */     //   116: goto -> 23
/*     */     //   119: lload #8
/*     */     //   121: lload #6
/*     */     //   123: lcmp
/*     */     //   124: ifeq -> 183
/*     */     //   127: aload_0
/*     */     //   128: lload #6
/*     */     //   130: invokestatic a : ([[FJ)F
/*     */     //   133: fstore #10
/*     */     //   135: aload_0
/*     */     //   136: lload #6
/*     */     //   138: aload_0
/*     */     //   139: lload #8
/*     */     //   141: invokestatic a : ([[FJ)F
/*     */     //   144: invokestatic a : ([[FJF)V
/*     */     //   147: aload_0
/*     */     //   148: lload #8
/*     */     //   150: fload #10
/*     */     //   152: invokestatic a : ([[FJF)V
/*     */     //   155: aload_1
/*     */     //   156: lload #6
/*     */     //   158: invokestatic a : ([[FJ)F
/*     */     //   161: fstore #10
/*     */     //   163: aload_1
/*     */     //   164: lload #6
/*     */     //   166: aload_1
/*     */     //   167: lload #8
/*     */     //   169: invokestatic a : ([[FJ)F
/*     */     //   172: invokestatic a : ([[FJF)V
/*     */     //   175: aload_1
/*     */     //   176: lload #8
/*     */     //   178: fload #10
/*     */     //   180: invokestatic a : ([[FJF)V
/*     */     //   183: lload #6
/*     */     //   185: lconst_1
/*     */     //   186: ladd
/*     */     //   187: lstore #6
/*     */     //   189: goto -> 3
/*     */     //   192: return
/*     */     // Line number table:
/*     */     //   Java source line number -> byte code offset
/*     */     //   #266	-> 0
/*     */     //   #160	-> 13
/*     */     //   #236	-> 17
/*     */     //   #179	-> 31
/*     */     //   #190	-> 110
/*     */     //   #150	-> 119
/*     */     //   #326	-> 127
/*     */     //   #126	-> 135
/*     */     //   #394	-> 147
/*     */     //   #220	-> 155
/*     */     //   #32	-> 163
/*     */     //   #116	-> 175
/*     */     //   #36	-> 183
/*     */     //   #101	-> 192
/*     */     // Exception table:
/*     */     //   from	to	target	type
/*     */     //   23	49	52	java/lang/IllegalArgumentException
/*     */     //   31	74	77	java/lang/IllegalArgumentException
/*     */     //   56	99	102	java/lang/IllegalArgumentException
/*     */   }
/*     */   
/*     */   private static ForkJoinPool a() {
/*     */     ForkJoinPool forkJoinPool = ForkJoinTask.getPool();
/*     */     try {
/*     */     
/*     */     } catch (IllegalArgumentException illegalArgumentException) {
/*     */       throw a(null);
/*     */     } 
/*     */     return (forkJoinPool == null) ? ForkJoinPool.commonPool() : forkJoinPool;
/*     */   }
/*     */   
/*     */   private static long a(float[][] paramArrayOffloat, long paramLong1, long paramLong2, long paramLong3, il paramil) {
/*     */     int i = paramil.a(k.a(paramArrayOffloat, paramLong1), k.a(paramArrayOffloat, paramLong2));
/*     */     int j = paramil.a(k.a(paramArrayOffloat, paramLong1), k.a(paramArrayOffloat, paramLong3));
/*     */     int k = paramil.a(k.a(paramArrayOffloat, paramLong2), k.a(paramArrayOffloat, paramLong3));
/*     */     try {
/*     */       if (i < 0) {
/*     */         try {
/*     */           try {
/*     */           
/*     */           } catch (IllegalArgumentException illegalArgumentException) {
/*     */             throw a(null);
/*     */           } 
/*     */         } catch (IllegalArgumentException illegalArgumentException) {
/*     */           throw a(null);
/*     */         } 
/*     */       } else {
/*     */         try {
/*     */           try {
/*     */           
/*     */           } catch (IllegalArgumentException illegalArgumentException) {
/*     */             throw a(null);
/*     */           } 
/*     */         } catch (IllegalArgumentException illegalArgumentException) {
/*     */           throw a(null);
/*     */         } 
/*     */       } 
/*     */     } catch (IllegalArgumentException illegalArgumentException) {
/*     */       throw a(null);
/*     */     } 
/*     */     return (k > 0) ? paramLong2 : ((j > 0) ? paramLong3 : paramLong1);
/*     */   }
/*     */   
/*     */   public static void b(float[][] paramArrayOffloat, il paramil) {
/*     */     c(paramArrayOffloat, 0L, k.a(paramArrayOffloat), paramil);
/*     */   }
/*     */   
/*     */   public static void g(float[][] paramArrayOffloat, long paramLong1, long paramLong2) {
/*     */     // Byte code:
/*     */     //   0: lload_3
/*     */     //   1: lload_1
/*     */     //   2: lsub
/*     */     //   3: lstore #5
/*     */     //   5: lload #5
/*     */     //   7: ldc2_w 7
/*     */     //   10: lcmp
/*     */     //   11: ifge -> 25
/*     */     //   14: aload_0
/*     */     //   15: lload_1
/*     */     //   16: lload_3
/*     */     //   17: invokestatic c : ([[FJJ)V
/*     */     //   20: return
/*     */     //   21: invokestatic a : (Ljava/lang/IllegalArgumentException;)Ljava/lang/IllegalArgumentException;
/*     */     //   24: athrow
/*     */     //   25: lload_1
/*     */     //   26: lload #5
/*     */     //   28: ldc2_w 2
/*     */     //   31: ldiv
/*     */     //   32: ladd
/*     */     //   33: lstore #7
/*     */     //   35: lload #5
/*     */     //   37: ldc2_w 7
/*     */     //   40: lcmp
/*     */     //   41: ifle -> 143
/*     */     //   44: lload_1
/*     */     //   45: lstore #9
/*     */     //   47: lload_3
/*     */     //   48: lconst_1
/*     */     //   49: lsub
/*     */     //   50: lstore #11
/*     */     //   52: lload #5
/*     */     //   54: ldc2_w 40
/*     */     //   57: lcmp
/*     */     //   58: ifle -> 131
/*     */     //   61: lload #5
/*     */     //   63: ldc2_w 8
/*     */     //   66: ldiv
/*     */     //   67: lstore #13
/*     */     //   69: aload_0
/*     */     //   70: lload #9
/*     */     //   72: lload #9
/*     */     //   74: lload #13
/*     */     //   76: ladd
/*     */     //   77: lload #9
/*     */     //   79: ldc2_w 2
/*     */     //   82: lload #13
/*     */     //   84: lmul
/*     */     //   85: ladd
/*     */     //   86: invokestatic b : ([[FJJJ)J
/*     */     //   89: lstore #9
/*     */     //   91: aload_0
/*     */     //   92: lload #7
/*     */     //   94: lload #13
/*     */     //   96: lsub
/*     */     //   97: lload #7
/*     */     //   99: lload #7
/*     */     //   101: lload #13
/*     */     //   103: ladd
/*     */     //   104: invokestatic b : ([[FJJJ)J
/*     */     //   107: lstore #7
/*     */     //   109: aload_0
/*     */     //   110: lload #11
/*     */     //   112: ldc2_w 2
/*     */     //   115: lload #13
/*     */     //   117: lmul
/*     */     //   118: lsub
/*     */     //   119: lload #11
/*     */     //   121: lload #13
/*     */     //   123: lsub
/*     */     //   124: lload #11
/*     */     //   126: invokestatic b : ([[FJJJ)J
/*     */     //   129: lstore #11
/*     */     //   131: aload_0
/*     */     //   132: lload #9
/*     */     //   134: lload #7
/*     */     //   136: lload #11
/*     */     //   138: invokestatic b : ([[FJJJ)J
/*     */     //   141: lstore #7
/*     */     //   143: aload_0
/*     */     //   144: lload #7
/*     */     //   146: invokestatic a : ([[FJ)F
/*     */     //   149: fstore #9
/*     */     //   151: lload_1
/*     */     //   152: lstore #10
/*     */     //   154: lload #10
/*     */     //   156: lstore #12
/*     */     //   158: lload_3
/*     */     //   159: lconst_1
/*     */     //   160: lsub
/*     */     //   161: lstore #14
/*     */     //   163: lload #14
/*     */     //   165: lstore #16
/*     */     //   167: lload #12
/*     */     //   169: lload #14
/*     */     //   171: lcmp
/*     */     //   172: ifgt -> 226
/*     */     //   175: aload_0
/*     */     //   176: lload #12
/*     */     //   178: invokestatic a : ([[FJ)F
/*     */     //   181: fload #9
/*     */     //   183: invokestatic compare : (FF)I
/*     */     //   186: dup
/*     */     //   187: istore #18
/*     */     //   189: ifgt -> 226
/*     */     //   192: iload #18
/*     */     //   194: ifne -> 217
/*     */     //   197: goto -> 204
/*     */     //   200: invokestatic a : (Ljava/lang/IllegalArgumentException;)Ljava/lang/IllegalArgumentException;
/*     */     //   203: athrow
/*     */     //   204: aload_0
/*     */     //   205: lload #10
/*     */     //   207: dup2
/*     */     //   208: lconst_1
/*     */     //   209: ladd
/*     */     //   210: lstore #10
/*     */     //   212: lload #12
/*     */     //   214: invokestatic b : ([[FJJ)V
/*     */     //   217: lload #12
/*     */     //   219: lconst_1
/*     */     //   220: ladd
/*     */     //   221: lstore #12
/*     */     //   223: goto -> 167
/*     */     //   226: lload #14
/*     */     //   228: lload #12
/*     */     //   230: lcmp
/*     */     //   231: iflt -> 285
/*     */     //   234: aload_0
/*     */     //   235: lload #14
/*     */     //   237: invokestatic a : ([[FJ)F
/*     */     //   240: fload #9
/*     */     //   242: invokestatic compare : (FF)I
/*     */     //   245: dup
/*     */     //   246: istore #18
/*     */     //   248: iflt -> 285
/*     */     //   251: iload #18
/*     */     //   253: ifne -> 276
/*     */     //   256: goto -> 263
/*     */     //   259: invokestatic a : (Ljava/lang/IllegalArgumentException;)Ljava/lang/IllegalArgumentException;
/*     */     //   262: athrow
/*     */     //   263: aload_0
/*     */     //   264: lload #14
/*     */     //   266: lload #16
/*     */     //   268: dup2
/*     */     //   269: lconst_1
/*     */     //   270: lsub
/*     */     //   271: lstore #16
/*     */     //   273: invokestatic b : ([[FJJ)V
/*     */     //   276: lload #14
/*     */     //   278: lconst_1
/*     */     //   279: lsub
/*     */     //   280: lstore #14
/*     */     //   282: goto -> 226
/*     */     //   285: lload #12
/*     */     //   287: lload #14
/*     */     //   289: lcmp
/*     */     //   290: ifle -> 300
/*     */     //   293: goto -> 321
/*     */     //   296: invokestatic a : (Ljava/lang/IllegalArgumentException;)Ljava/lang/IllegalArgumentException;
/*     */     //   299: athrow
/*     */     //   300: aload_0
/*     */     //   301: lload #12
/*     */     //   303: dup2
/*     */     //   304: lconst_1
/*     */     //   305: ladd
/*     */     //   306: lstore #12
/*     */     //   308: lload #14
/*     */     //   310: dup2
/*     */     //   311: lconst_1
/*     */     //   312: lsub
/*     */     //   313: lstore #14
/*     */     //   315: invokestatic b : ([[FJJ)V
/*     */     //   318: goto -> 167
/*     */     //   321: lload_3
/*     */     //   322: lstore #20
/*     */     //   324: lload #10
/*     */     //   326: lload_1
/*     */     //   327: lsub
/*     */     //   328: lload #12
/*     */     //   330: lload #10
/*     */     //   332: lsub
/*     */     //   333: invokestatic min : (JJ)J
/*     */     //   336: lstore #18
/*     */     //   338: aload_0
/*     */     //   339: lload_1
/*     */     //   340: lload #12
/*     */     //   342: lload #18
/*     */     //   344: lsub
/*     */     //   345: lload #18
/*     */     //   347: invokestatic b : ([[FJJJ)V
/*     */     //   350: lload #16
/*     */     //   352: lload #14
/*     */     //   354: lsub
/*     */     //   355: lload #20
/*     */     //   357: lload #16
/*     */     //   359: lsub
/*     */     //   360: lconst_1
/*     */     //   361: lsub
/*     */     //   362: invokestatic min : (JJ)J
/*     */     //   365: lstore #18
/*     */     //   367: aload_0
/*     */     //   368: lload #12
/*     */     //   370: lload #20
/*     */     //   372: lload #18
/*     */     //   374: lsub
/*     */     //   375: lload #18
/*     */     //   377: invokestatic b : ([[FJJJ)V
/*     */     //   380: lload #12
/*     */     //   382: lload #10
/*     */     //   384: lsub
/*     */     //   385: dup2
/*     */     //   386: lstore #18
/*     */     //   388: lconst_1
/*     */     //   389: lcmp
/*     */     //   390: ifle -> 409
/*     */     //   393: aload_0
/*     */     //   394: lload_1
/*     */     //   395: lload_1
/*     */     //   396: lload #18
/*     */     //   398: ladd
/*     */     //   399: invokestatic g : ([[FJJ)V
/*     */     //   402: goto -> 409
/*     */     //   405: invokestatic a : (Ljava/lang/IllegalArgumentException;)Ljava/lang/IllegalArgumentException;
/*     */     //   408: athrow
/*     */     //   409: lload #16
/*     */     //   411: lload #14
/*     */     //   413: lsub
/*     */     //   414: dup2
/*     */     //   415: lstore #18
/*     */     //   417: lconst_1
/*     */     //   418: lcmp
/*     */     //   419: ifle -> 440
/*     */     //   422: aload_0
/*     */     //   423: lload #20
/*     */     //   425: lload #18
/*     */     //   427: lsub
/*     */     //   428: lload #20
/*     */     //   430: invokestatic g : ([[FJJ)V
/*     */     //   433: goto -> 440
/*     */     //   436: invokestatic a : (Ljava/lang/IllegalArgumentException;)Ljava/lang/IllegalArgumentException;
/*     */     //   439: athrow
/*     */     //   440: return
/*     */     // Line number table:
/*     */     //   Java source line number -> byte code offset
/*     */     //   #289	-> 0
/*     */     //   #292	-> 5
/*     */     //   #352	-> 14
/*     */     //   #211	-> 20
/*     */     //   #397	-> 25
/*     */     //   #416	-> 35
/*     */     //   #406	-> 44
/*     */     //   #378	-> 47
/*     */     //   #243	-> 52
/*     */     //   #356	-> 61
/*     */     //   #153	-> 69
/*     */     //   #19	-> 91
/*     */     //   #57	-> 109
/*     */     //   #414	-> 131
/*     */     //   #66	-> 143
/*     */     //   #1	-> 151
/*     */     //   #146	-> 167
/*     */     //   #242	-> 192
/*     */     //   #130	-> 217
/*     */     //   #28	-> 226
/*     */     //   #30	-> 251
/*     */     //   #77	-> 276
/*     */     //   #390	-> 285
/*     */     //   #106	-> 300
/*     */     //   #336	-> 321
/*     */     //   #74	-> 324
/*     */     //   #371	-> 338
/*     */     //   #318	-> 350
/*     */     //   #308	-> 367
/*     */     //   #88	-> 380
/*     */     //   #285	-> 409
/*     */     //   #398	-> 440
/*     */     // Exception table:
/*     */     //   from	to	target	type
/*     */     //   5	21	21	java/lang/IllegalArgumentException
/*     */     //   189	197	200	java/lang/IllegalArgumentException
/*     */     //   248	256	259	java/lang/IllegalArgumentException
/*     */     //   285	296	296	java/lang/IllegalArgumentException
/*     */     //   388	402	405	java/lang/IllegalArgumentException
/*     */     //   417	433	436	java/lang/IllegalArgumentException
/*     */   }
/*     */   
/*     */   @Deprecated
/*     */   public static void f(float[][] paramArrayOffloat, long paramLong1, long paramLong2) {
/*     */     k.b(a(paramArrayOffloat), paramLong1, paramLong2);
/*     */   }
/*     */   
/*     */   private static void b(float[][] paramArrayOffloat, long paramLong1, long paramLong2, long paramLong3) {
/*     */     for (byte b = 0; b < paramLong3; ) {
/*     */       k.b(paramArrayOffloat, paramLong1, paramLong2);
/*     */       b++;
/*     */       paramLong1++;
/*     */       paramLong2++;
/*     */     } 
/*     */   }
/*     */   
/*     */   public static long a(float[][] paramArrayOffloat, long paramLong1, long paramLong2, float paramFloat, il paramil) {
/*     */     paramLong2--;
/*     */     while (paramLong1 <= paramLong2) {
/*     */       long l = paramLong1 + paramLong2 >>> 1L;
/*     */       float f = k.a(paramArrayOffloat, l);
/*     */       int i = paramil.a(f, paramFloat);
/*     */       if (i < 0)
/*     */         paramLong1 = l + 1L; 
/*     */     } 
/*     */     return -(paramLong1 + 1L);
/*     */   }
/*     */   
/*     */   public static void a(float[][] paramArrayOffloat, long paramLong1, long paramLong2) {
/*     */     byte b1 = 3;
/*     */     char c = '˾';
/*     */     long[] arrayOfLong1 = new long[766];
/*     */     byte b2 = 0;
/*     */     long[] arrayOfLong2 = new long[766];
/*     */     byte b3 = 0;
/*     */     int[] arrayOfInt = new int[766];
/*     */     byte b4 = 0;
/*     */     arrayOfLong1[b2++] = paramLong1;
/*     */     arrayOfLong2[b3++] = paramLong2 - paramLong1;
/*     */     arrayOfInt[b4++] = 0;
/*     */     long[] arrayOfLong3 = new long[256];
/*     */     long[] arrayOfLong4 = new long[256];
/*     */     byte[][] arrayOfByte = fd.a(paramLong2 - paramLong1);
/*     */     while (b2 > 0) {
/*     */       long l1 = arrayOfLong1[--b2];
/*     */       long l2 = arrayOfLong2[--b3];
/*     */       int i = arrayOfInt[--b4];
/*     */     } 
/*     */   }
/*     */   
/*     */   public static float[][] a(float[][] paramArrayOffloat, long paramLong1, long paramLong2, Random paramRandom) {
/*     */     return k.a(paramArrayOffloat, paramLong1, paramLong2, paramRandom);
/*     */   }
/*     */   
/*     */   @Deprecated
/*     */   public static void a(float[][] paramArrayOffloat, long paramLong, float[] paramArrayOffloat1, int paramInt1, int paramInt2) {
/*     */     k.a(paramArrayOffloat, paramLong, paramArrayOffloat1, paramInt1, paramInt2);
/*     */   }
/*     */   
/*     */   @Deprecated
/*     */   public static float[][] a(float[][] paramArrayOffloat) {
/*     */     return k.b(paramArrayOffloat);
/*     */   }
/*     */   
/*     */   public static void a(float[][] paramArrayOffloat) {
/*     */     a(paramArrayOffloat, 0L, k.a(paramArrayOffloat));
/*     */   }
/*     */   
/*     */   public static void a(long[][] paramArrayOflong, float[][] paramArrayOffloat1, float[][] paramArrayOffloat2, long paramLong1, long paramLong2, boolean paramBoolean) {
/*     */     // Byte code:
/*     */     //   0: lload #5
/*     */     //   2: lload_3
/*     */     //   3: lsub
/*     */     //   4: ldc2_w 1024
/*     */     //   7: lcmp
/*     */     //   8: ifge -> 25
/*     */     //   11: aload_0
/*     */     //   12: aload_1
/*     */     //   13: aload_2
/*     */     //   14: lload_3
/*     */     //   15: lload #5
/*     */     //   17: invokestatic a : ([[J[[F[[FJJ)V
/*     */     //   20: return
/*     */     //   21: invokestatic a : (Ljava/lang/IllegalArgumentException;)Ljava/lang/IllegalArgumentException;
/*     */     //   24: athrow
/*     */     //   25: iconst_2
/*     */     //   26: istore #8
/*     */     //   28: bipush #7
/*     */     //   30: istore #9
/*     */     //   32: sipush #1786
/*     */     //   35: istore #10
/*     */     //   37: iconst_0
/*     */     //   38: istore #11
/*     */     //   40: sipush #1786
/*     */     //   43: newarray long
/*     */     //   45: astore #12
/*     */     //   47: sipush #1786
/*     */     //   50: newarray long
/*     */     //   52: astore #13
/*     */     //   54: sipush #1786
/*     */     //   57: newarray int
/*     */     //   59: astore #14
/*     */     //   61: aload #12
/*     */     //   63: iload #11
/*     */     //   65: lload_3
/*     */     //   66: lastore
/*     */     //   67: aload #13
/*     */     //   69: iload #11
/*     */     //   71: lload #5
/*     */     //   73: lload_3
/*     */     //   74: lsub
/*     */     //   75: lastore
/*     */     //   76: aload #14
/*     */     //   78: iload #11
/*     */     //   80: iinc #11, 1
/*     */     //   83: iconst_0
/*     */     //   84: iastore
/*     */     //   85: sipush #256
/*     */     //   88: newarray long
/*     */     //   90: astore #15
/*     */     //   92: sipush #256
/*     */     //   95: newarray long
/*     */     //   97: astore #16
/*     */     //   99: iload #7
/*     */     //   101: ifeq -> 118
/*     */     //   104: aload_0
/*     */     //   105: invokestatic a : ([[J)J
/*     */     //   108: invokestatic a : (J)[[J
/*     */     //   111: goto -> 119
/*     */     //   114: invokestatic a : (Ljava/lang/IllegalArgumentException;)Ljava/lang/IllegalArgumentException;
/*     */     //   117: athrow
/*     */     //   118: aconst_null
/*     */     //   119: astore #17
/*     */     //   121: iload #11
/*     */     //   123: ifle -> 813
/*     */     //   126: aload #12
/*     */     //   128: iinc #11, -1
/*     */     //   131: iload #11
/*     */     //   133: laload
/*     */     //   134: lstore #18
/*     */     //   136: aload #13
/*     */     //   138: iload #11
/*     */     //   140: laload
/*     */     //   141: lstore #20
/*     */     //   143: aload #14
/*     */     //   145: iload #11
/*     */     //   147: iaload
/*     */     //   148: istore #22
/*     */     //   150: iload #22
/*     */     //   152: iconst_4
/*     */     //   153: irem
/*     */     //   154: ifne -> 167
/*     */     //   157: sipush #128
/*     */     //   160: goto -> 168
/*     */     //   163: invokestatic a : (Ljava/lang/IllegalArgumentException;)Ljava/lang/IllegalArgumentException;
/*     */     //   166: athrow
/*     */     //   167: iconst_0
/*     */     //   168: istore #23
/*     */     //   170: iload #22
/*     */     //   172: iconst_4
/*     */     //   173: if_icmpge -> 184
/*     */     //   176: aload_1
/*     */     //   177: goto -> 185
/*     */     //   180: invokestatic a : (Ljava/lang/IllegalArgumentException;)Ljava/lang/IllegalArgumentException;
/*     */     //   183: athrow
/*     */     //   184: aload_2
/*     */     //   185: astore #24
/*     */     //   187: iconst_3
/*     */     //   188: iload #22
/*     */     //   190: iconst_4
/*     */     //   191: irem
/*     */     //   192: isub
/*     */     //   193: bipush #8
/*     */     //   195: imul
/*     */     //   196: istore #25
/*     */     //   198: lload #18
/*     */     //   200: lload #20
/*     */     //   202: ladd
/*     */     //   203: lstore #26
/*     */     //   205: lload #26
/*     */     //   207: dup2
/*     */     //   208: lconst_1
/*     */     //   209: lsub
/*     */     //   210: lstore #26
/*     */     //   212: lload #18
/*     */     //   214: lcmp
/*     */     //   215: ifeq -> 256
/*     */     //   218: aload #15
/*     */     //   220: aload #24
/*     */     //   222: aload_0
/*     */     //   223: lload #26
/*     */     //   225: invokestatic a : ([[JJ)J
/*     */     //   228: invokestatic a : ([[FJ)F
/*     */     //   231: invokestatic a : (F)I
/*     */     //   234: iload #25
/*     */     //   236: iushr
/*     */     //   237: sipush #255
/*     */     //   240: iand
/*     */     //   241: iload #23
/*     */     //   243: ixor
/*     */     //   244: dup2
/*     */     //   245: laload
/*     */     //   246: lconst_1
/*     */     //   247: ladd
/*     */     //   248: lastore
/*     */     //   249: goto -> 205
/*     */     //   252: invokestatic a : (Ljava/lang/IllegalArgumentException;)Ljava/lang/IllegalArgumentException;
/*     */     //   255: athrow
/*     */     //   256: iconst_m1
/*     */     //   257: istore #26
/*     */     //   259: iload #7
/*     */     //   261: ifeq -> 272
/*     */     //   264: lconst_0
/*     */     //   265: goto -> 274
/*     */     //   268: invokestatic a : (Ljava/lang/IllegalArgumentException;)Ljava/lang/IllegalArgumentException;
/*     */     //   271: athrow
/*     */     //   272: lload #18
/*     */     //   274: lstore #27
/*     */     //   276: iconst_0
/*     */     //   277: istore #29
/*     */     //   279: iload #29
/*     */     //   281: sipush #256
/*     */     //   284: if_icmpge -> 330
/*     */     //   287: aload #15
/*     */     //   289: iload #29
/*     */     //   291: laload
/*     */     //   292: lconst_0
/*     */     //   293: lcmp
/*     */     //   294: ifeq -> 308
/*     */     //   297: goto -> 304
/*     */     //   300: invokestatic a : (Ljava/lang/IllegalArgumentException;)Ljava/lang/IllegalArgumentException;
/*     */     //   303: athrow
/*     */     //   304: iload #29
/*     */     //   306: istore #26
/*     */     //   308: aload #16
/*     */     //   310: iload #29
/*     */     //   312: lload #27
/*     */     //   314: aload #15
/*     */     //   316: iload #29
/*     */     //   318: laload
/*     */     //   319: ladd
/*     */     //   320: dup2
/*     */     //   321: lstore #27
/*     */     //   323: lastore
/*     */     //   324: iinc #29, 1
/*     */     //   327: goto -> 279
/*     */     //   330: iload #7
/*     */     //   332: ifeq -> 558
/*     */     //   335: lload #18
/*     */     //   337: lload #20
/*     */     //   339: ladd
/*     */     //   340: lstore #29
/*     */     //   342: lload #29
/*     */     //   344: dup2
/*     */     //   345: lconst_1
/*     */     //   346: lsub
/*     */     //   347: lstore #29
/*     */     //   349: lload #18
/*     */     //   351: lcmp
/*     */     //   352: ifeq -> 405
/*     */     //   355: aload #17
/*     */     //   357: aload #16
/*     */     //   359: aload #24
/*     */     //   361: aload_0
/*     */     //   362: lload #29
/*     */     //   364: invokestatic a : ([[JJ)J
/*     */     //   367: invokestatic a : ([[FJ)F
/*     */     //   370: invokestatic a : (F)I
/*     */     //   373: iload #25
/*     */     //   375: iushr
/*     */     //   376: sipush #255
/*     */     //   379: iand
/*     */     //   380: iload #23
/*     */     //   382: ixor
/*     */     //   383: dup2
/*     */     //   384: laload
/*     */     //   385: lconst_1
/*     */     //   386: lsub
/*     */     //   387: dup2_x2
/*     */     //   388: lastore
/*     */     //   389: aload_0
/*     */     //   390: lload #29
/*     */     //   392: invokestatic a : ([[JJ)J
/*     */     //   395: invokestatic d : ([[JJJ)V
/*     */     //   398: goto -> 342
/*     */     //   401: invokestatic a : (Ljava/lang/IllegalArgumentException;)Ljava/lang/IllegalArgumentException;
/*     */     //   404: athrow
/*     */     //   405: aload #17
/*     */     //   407: lconst_0
/*     */     //   408: aload_0
/*     */     //   409: lload #18
/*     */     //   411: lload #20
/*     */     //   413: invokestatic a : ([[JJ[[JJJ)V
/*     */     //   416: lload #18
/*     */     //   418: lstore #27
/*     */     //   420: iconst_0
/*     */     //   421: istore #29
/*     */     //   423: iload #29
/*     */     //   425: sipush #256
/*     */     //   428: if_icmpge -> 549
/*     */     //   431: iload #22
/*     */     //   433: bipush #7
/*     */     //   435: if_icmpge -> 533
/*     */     //   438: goto -> 445
/*     */     //   441: invokestatic a : (Ljava/lang/IllegalArgumentException;)Ljava/lang/IllegalArgumentException;
/*     */     //   444: athrow
/*     */     //   445: aload #15
/*     */     //   447: iload #29
/*     */     //   449: laload
/*     */     //   450: lconst_1
/*     */     //   451: lcmp
/*     */     //   452: ifle -> 533
/*     */     //   455: goto -> 462
/*     */     //   458: invokestatic a : (Ljava/lang/IllegalArgumentException;)Ljava/lang/IllegalArgumentException;
/*     */     //   461: athrow
/*     */     //   462: aload #15
/*     */     //   464: iload #29
/*     */     //   466: laload
/*     */     //   467: ldc2_w 1024
/*     */     //   470: lcmp
/*     */     //   471: ifge -> 504
/*     */     //   474: goto -> 481
/*     */     //   477: invokestatic a : (Ljava/lang/IllegalArgumentException;)Ljava/lang/IllegalArgumentException;
/*     */     //   480: athrow
/*     */     //   481: aload_0
/*     */     //   482: aload_1
/*     */     //   483: aload_2
/*     */     //   484: lload #27
/*     */     //   486: lload #27
/*     */     //   488: aload #15
/*     */     //   490: iload #29
/*     */     //   492: laload
/*     */     //   493: ladd
/*     */     //   494: invokestatic a : ([[J[[F[[FJJ)V
/*     */     //   497: goto -> 533
/*     */     //   500: invokestatic a : (Ljava/lang/IllegalArgumentException;)Ljava/lang/IllegalArgumentException;
/*     */     //   503: athrow
/*     */     //   504: aload #12
/*     */     //   506: iload #11
/*     */     //   508: lload #27
/*     */     //   510: lastore
/*     */     //   511: aload #13
/*     */     //   513: iload #11
/*     */     //   515: aload #15
/*     */     //   517: iload #29
/*     */     //   519: laload
/*     */     //   520: lastore
/*     */     //   521: aload #14
/*     */     //   523: iload #11
/*     */     //   525: iinc #11, 1
/*     */     //   528: iload #22
/*     */     //   530: iconst_1
/*     */     //   531: iadd
/*     */     //   532: iastore
/*     */     //   533: lload #27
/*     */     //   535: aload #15
/*     */     //   537: iload #29
/*     */     //   539: laload
/*     */     //   540: ladd
/*     */     //   541: lstore #27
/*     */     //   543: iinc #29, 1
/*     */     //   546: goto -> 423
/*     */     //   549: aload #15
/*     */     //   551: lconst_0
/*     */     //   552: invokestatic fill : ([JJ)V
/*     */     //   555: goto -> 810
/*     */     //   558: lload #18
/*     */     //   560: lload #20
/*     */     //   562: ladd
/*     */     //   563: aload #15
/*     */     //   565: iload #26
/*     */     //   567: laload
/*     */     //   568: lsub
/*     */     //   569: lstore #29
/*     */     //   571: iconst_m1
/*     */     //   572: istore #31
/*     */     //   574: lload #18
/*     */     //   576: lstore #32
/*     */     //   578: lload #32
/*     */     //   580: lload #29
/*     */     //   582: lcmp
/*     */     //   583: ifgt -> 810
/*     */     //   586: aload_0
/*     */     //   587: lload #32
/*     */     //   589: invokestatic a : ([[JJ)J
/*     */     //   592: lstore #36
/*     */     //   594: aload #24
/*     */     //   596: lload #36
/*     */     //   598: invokestatic a : ([[FJ)F
/*     */     //   601: invokestatic a : (F)I
/*     */     //   604: iload #25
/*     */     //   606: iushr
/*     */     //   607: sipush #255
/*     */     //   610: iand
/*     */     //   611: iload #23
/*     */     //   613: ixor
/*     */     //   614: istore #31
/*     */     //   616: lload #32
/*     */     //   618: lload #29
/*     */     //   620: lcmp
/*     */     //   621: ifge -> 696
/*     */     //   624: aload #16
/*     */     //   626: iload #31
/*     */     //   628: dup2
/*     */     //   629: laload
/*     */     //   630: lconst_1
/*     */     //   631: lsub
/*     */     //   632: dup2_x2
/*     */     //   633: lastore
/*     */     //   634: dup2
/*     */     //   635: lstore #34
/*     */     //   637: lload #32
/*     */     //   639: lcmp
/*     */     //   640: ifle -> 688
/*     */     //   643: lload #36
/*     */     //   645: lstore #38
/*     */     //   647: aload_0
/*     */     //   648: lload #34
/*     */     //   650: invokestatic a : ([[JJ)J
/*     */     //   653: lstore #36
/*     */     //   655: aload_0
/*     */     //   656: lload #34
/*     */     //   658: lload #38
/*     */     //   660: invokestatic d : ([[JJJ)V
/*     */     //   663: aload #24
/*     */     //   665: lload #36
/*     */     //   667: invokestatic a : ([[FJ)F
/*     */     //   670: invokestatic a : (F)I
/*     */     //   673: iload #25
/*     */     //   675: iushr
/*     */     //   676: sipush #255
/*     */     //   679: iand
/*     */     //   680: iload #23
/*     */     //   682: ixor
/*     */     //   683: istore #31
/*     */     //   685: goto -> 624
/*     */     //   688: aload_0
/*     */     //   689: lload #32
/*     */     //   691: lload #36
/*     */     //   693: invokestatic d : ([[JJJ)V
/*     */     //   696: iload #22
/*     */     //   698: bipush #7
/*     */     //   700: if_icmpge -> 791
/*     */     //   703: aload #15
/*     */     //   705: iload #31
/*     */     //   707: laload
/*     */     //   708: lconst_1
/*     */     //   709: lcmp
/*     */     //   710: ifle -> 791
/*     */     //   713: goto -> 720
/*     */     //   716: invokestatic a : (Ljava/lang/IllegalArgumentException;)Ljava/lang/IllegalArgumentException;
/*     */     //   719: athrow
/*     */     //   720: aload #15
/*     */     //   722: iload #31
/*     */     //   724: laload
/*     */     //   725: ldc2_w 1024
/*     */     //   728: lcmp
/*     */     //   729: ifge -> 762
/*     */     //   732: goto -> 739
/*     */     //   735: invokestatic a : (Ljava/lang/IllegalArgumentException;)Ljava/lang/IllegalArgumentException;
/*     */     //   738: athrow
/*     */     //   739: aload_0
/*     */     //   740: aload_1
/*     */     //   741: aload_2
/*     */     //   742: lload #32
/*     */     //   744: lload #32
/*     */     //   746: aload #15
/*     */     //   748: iload #31
/*     */     //   750: laload
/*     */     //   751: ladd
/*     */     //   752: invokestatic a : ([[J[[F[[FJJ)V
/*     */     //   755: goto -> 791
/*     */     //   758: invokestatic a : (Ljava/lang/IllegalArgumentException;)Ljava/lang/IllegalArgumentException;
/*     */     //   761: athrow
/*     */     //   762: aload #12
/*     */     //   764: iload #11
/*     */     //   766: lload #32
/*     */     //   768: lastore
/*     */     //   769: aload #13
/*     */     //   771: iload #11
/*     */     //   773: aload #15
/*     */     //   775: iload #31
/*     */     //   777: laload
/*     */     //   778: lastore
/*     */     //   779: aload #14
/*     */     //   781: iload #11
/*     */     //   783: iinc #11, 1
/*     */     //   786: iload #22
/*     */     //   788: iconst_1
/*     */     //   789: iadd
/*     */     //   790: iastore
/*     */     //   791: lload #32
/*     */     //   793: aload #15
/*     */     //   795: iload #31
/*     */     //   797: laload
/*     */     //   798: ladd
/*     */     //   799: lstore #32
/*     */     //   801: aload #15
/*     */     //   803: iload #31
/*     */     //   805: lconst_0
/*     */     //   806: lastore
/*     */     //   807: goto -> 578
/*     */     //   810: goto -> 121
/*     */     //   813: return
/*     */     // Line number table:
/*     */     //   Java source line number -> byte code offset
/*     */     //   #362	-> 0
/*     */     //   #127	-> 11
/*     */     //   #95	-> 20
/*     */     //   #43	-> 25
/*     */     //   #360	-> 28
/*     */     //   #42	-> 32
/*     */     //   #186	-> 37
/*     */     //   #125	-> 40
/*     */     //   #80	-> 47
/*     */     //   #319	-> 54
/*     */     //   #302	-> 61
/*     */     //   #20	-> 67
/*     */     //   #278	-> 76
/*     */     //   #11	-> 85
/*     */     //   #115	-> 92
/*     */     //   #167	-> 99
/*     */     //   #255	-> 121
/*     */     //   #411	-> 126
/*     */     //   #275	-> 136
/*     */     //   #214	-> 143
/*     */     //   #239	-> 150
/*     */     //   #216	-> 170
/*     */     //   #305	-> 187
/*     */     //   #353	-> 198
/*     */     //   #193	-> 256
/*     */     //   #49	-> 259
/*     */     //   #409	-> 276
/*     */     //   #7	-> 287
/*     */     //   #419	-> 308
/*     */     //   #10	-> 324
/*     */     //   #199	-> 330
/*     */     //   #206	-> 335
/*     */     //   #189	-> 405
/*     */     //   #181	-> 416
/*     */     //   #15	-> 420
/*     */     //   #121	-> 431
/*     */     //   #367	-> 462
/*     */     //   #134	-> 504
/*     */     //   #23	-> 511
/*     */     //   #259	-> 521
/*     */     //   #387	-> 533
/*     */     //   #412	-> 543
/*     */     //   #335	-> 549
/*     */     //   #306	-> 558
/*     */     //   #358	-> 571
/*     */     //   #330	-> 574
/*     */     //   #385	-> 586
/*     */     //   #164	-> 594
/*     */     //   #313	-> 616
/*     */     //   #355	-> 624
/*     */     //   #282	-> 643
/*     */     //   #382	-> 647
/*     */     //   #366	-> 655
/*     */     //   #219	-> 663
/*     */     //   #76	-> 685
/*     */     //   #256	-> 688
/*     */     //   #293	-> 696
/*     */     //   #260	-> 720
/*     */     //   #287	-> 762
/*     */     //   #26	-> 769
/*     */     //   #324	-> 779
/*     */     //   #410	-> 791
/*     */     //   #392	-> 810
/*     */     //   #301	-> 813
/*     */     // Exception table:
/*     */     //   from	to	target	type
/*     */     //   0	21	21	java/lang/IllegalArgumentException
/*     */     //   99	114	114	java/lang/IllegalArgumentException
/*     */     //   150	163	163	java/lang/IllegalArgumentException
/*     */     //   170	180	180	java/lang/IllegalArgumentException
/*     */     //   212	252	252	java/lang/IllegalArgumentException
/*     */     //   259	268	268	java/lang/IllegalArgumentException
/*     */     //   279	297	300	java/lang/IllegalArgumentException
/*     */     //   349	401	401	java/lang/IllegalArgumentException
/*     */     //   423	438	441	java/lang/IllegalArgumentException
/*     */     //   431	455	458	java/lang/IllegalArgumentException
/*     */     //   445	474	477	java/lang/IllegalArgumentException
/*     */     //   462	500	500	java/lang/IllegalArgumentException
/*     */     //   696	713	716	java/lang/IllegalArgumentException
/*     */     //   703	732	735	java/lang/IllegalArgumentException
/*     */     //   720	758	758	java/lang/IllegalArgumentException
/*     */   }
/*     */   
/*     */   @Deprecated
/*     */   public static void a(float[][] paramArrayOffloat1, long paramLong1, float[][] paramArrayOffloat2, long paramLong2, long paramLong3) {
/*     */     k.a(paramArrayOffloat1, paramLong1, paramArrayOffloat2, paramLong2, paramLong3);
/*     */   }
/*     */   
/*     */   public static void a(float[][] paramArrayOffloat, il paramil) {
/*     */     b(paramArrayOffloat, 0L, k.a(paramArrayOffloat), paramil);
/*     */   }
/*     */   
/*     */   @Deprecated
/*     */   public static void c(float[][] paramArrayOffloat, long paramLong, float paramFloat) {
/*     */     paramArrayOffloat[k.b(paramLong)][k.a(paramLong)] = paramArrayOffloat[k.b(paramLong)][k.a(paramLong)] + paramFloat;
/*     */   }
/*     */   
/*     */   public static void b(float[][] paramArrayOffloat) {
/*     */     g(paramArrayOffloat, 0L, k.a(paramArrayOffloat));
/*     */   }
/*     */   
/*     */   public static long a(float[][] paramArrayOffloat, float paramFloat, il paramil) {
/*     */     return a(paramArrayOffloat, 0L, k.a(paramArrayOffloat), paramFloat, paramil);
/*     */   }
/*     */   
/*     */   private static IllegalArgumentException a(IllegalArgumentException paramIllegalArgumentException) {
/*     */     return paramIllegalArgumentException;
/*     */   } }


/* Location:              C:\Users\BukkitBypass\Desktop\MatrixAC\AAC\AAC-spigot-5.2.0.jar!\me\konsolas\aac\kn.class
 * Java compiler version: 8 (52.0)
 * JD-Core Version:       1.1.3
 */