/*     */ package me.konsolas.aac;public final class l6 { private static final char[] e; static final String a; static final String o; static final String p; static final String r; static final String u; static final String f; static final String d; static final String n; static final String q; static final String c; static final String g; final String m; private final String t; private final String i; final String k; final int s; private final List l; @Nullable
/*     */   private final List j; @Nullable
/*     */   private final String h; private final String b; private static final long v; private static final String[] w; private static final String[] x; private static final Map y;
/*     */   @Nullable
/*     */   public String c(long paramLong) {
/*     */     // Byte code:
/*     */     //   0: getstatic me/konsolas/aac/l6.v : J
/*     */     //   3: lload_1
/*     */     //   4: lxor
/*     */     //   5: lstore_1
/*     */     //   6: lload_1
/*     */     //   7: dup2
/*     */     //   8: ldc2_w 13856771525985
/*     */     //   11: lxor
/*     */     //   12: lstore_3
/*     */     //   13: pop2
/*     */     //   14: ldc2_w 8841318468755618416
/*     */     //   17: lload_1
/*     */     //   18: <illegal opcode> w : (JJ)[Lme/konsolas/aac/aN;
/*     */     //   23: astore #5
/*     */     //   25: aload_0
/*     */     //   26: getfield k : Ljava/lang/String;
/*     */     //   29: aload #5
/*     */     //   31: ifnonnull -> 78
/*     */     //   34: invokestatic a : (Ljava/lang/String;)Z
/*     */     //   37: ifeq -> 65
/*     */     //   40: goto -> 53
/*     */     //   43: ldc2_w 8835977309123049390
/*     */     //   46: lload_1
/*     */     //   47: <illegal opcode> w : (Ljava/lang/RuntimeException;JJ)Ljava/lang/RuntimeException;
/*     */     //   52: athrow
/*     */     //   53: aconst_null
/*     */     //   54: areturn
/*     */     //   55: ldc2_w 8835977309123049390
/*     */     //   58: lload_1
/*     */     //   59: <illegal opcode> w : (Ljava/lang/RuntimeException;JJ)Ljava/lang/RuntimeException;
/*     */     //   64: athrow
/*     */     //   65: invokestatic a : ()Lme/konsolas/aac/hB;
/*     */     //   68: aload_0
/*     */     //   69: getfield k : Ljava/lang/String;
/*     */     //   72: lload_3
/*     */     //   73: dup2_x1
/*     */     //   74: pop2
/*     */     //   75: invokevirtual a : (JLjava/lang/String;)Ljava/lang/String;
/*     */     //   78: areturn
/*     */     // Line number table:
/*     */     //   Java source line number -> byte code offset
/*     */     //   #8	-> 25
/*     */     //   #34	-> 65
/*     */     // Exception table:
/*     */     //   from	to	target	type
/*     */     //   25	40	43	java/lang/RuntimeException
/*     */     //   34	55	55	java/lang/RuntimeException
/*     */   }
/*     */   public j5 a(long paramLong) {
/*     */     // Byte code:
/*     */     //   0: getstatic me/konsolas/aac/l6.v : J
/*     */     //   3: lload_1
/*     */     //   4: lxor
/*     */     //   5: lstore_1
/*     */     //   6: lload_1
/*     */     //   7: dup2
/*     */     //   8: ldc2_w 45103301740185
/*     */     //   11: lxor
/*     */     //   12: dup2
/*     */     //   13: bipush #48
/*     */     //   15: lushr
/*     */     //   16: l2i
/*     */     //   17: istore_3
/*     */     //   18: dup2
/*     */     //   19: bipush #16
/*     */     //   21: lshl
/*     */     //   22: bipush #16
/*     */     //   24: lushr
/*     */     //   25: lstore #4
/*     */     //   27: pop2
/*     */     //   28: dup2
/*     */     //   29: ldc2_w 105837453552699
/*     */     //   32: lxor
/*     */     //   33: lstore #6
/*     */     //   35: dup2
/*     */     //   36: ldc2_w 53288911664914
/*     */     //   39: lxor
/*     */     //   40: dup2
/*     */     //   41: bipush #32
/*     */     //   43: lushr
/*     */     //   44: l2i
/*     */     //   45: istore #8
/*     */     //   47: dup2
/*     */     //   48: bipush #32
/*     */     //   50: lshl
/*     */     //   51: bipush #48
/*     */     //   53: lushr
/*     */     //   54: l2i
/*     */     //   55: istore #9
/*     */     //   57: dup2
/*     */     //   58: bipush #48
/*     */     //   60: lshl
/*     */     //   61: bipush #48
/*     */     //   63: lushr
/*     */     //   64: l2i
/*     */     //   65: istore #10
/*     */     //   67: pop2
/*     */     //   68: dup2
/*     */     //   69: ldc2_w 69858345734794
/*     */     //   72: lxor
/*     */     //   73: lstore #11
/*     */     //   75: dup2
/*     */     //   76: ldc2_w 64007784653383
/*     */     //   79: lxor
/*     */     //   80: lstore #13
/*     */     //   82: dup2
/*     */     //   83: ldc2_w 29050458381866
/*     */     //   86: lxor
/*     */     //   87: lstore #15
/*     */     //   89: dup2
/*     */     //   90: ldc2_w 33049742630904
/*     */     //   93: lxor
/*     */     //   94: lstore #17
/*     */     //   96: pop2
/*     */     //   97: new me/konsolas/aac/j5
/*     */     //   100: dup
/*     */     //   101: invokespecial <init> : ()V
/*     */     //   104: astore #20
/*     */     //   106: aload #20
/*     */     //   108: aload_0
/*     */     //   109: getfield m : Ljava/lang/String;
/*     */     //   112: putfield c : Ljava/lang/String;
/*     */     //   115: aload #20
/*     */     //   117: aload_0
/*     */     //   118: lload #15
/*     */     //   120: invokevirtual j : (J)Ljava/lang/String;
/*     */     //   123: putfield f : Ljava/lang/String;
/*     */     //   126: ldc2_w 5812966582503362665
/*     */     //   129: lload_1
/*     */     //   130: <illegal opcode> w : (JJ)[Lme/konsolas/aac/aN;
/*     */     //   135: aload #20
/*     */     //   137: aload_0
/*     */     //   138: lload #17
/*     */     //   140: invokevirtual b : (J)Ljava/lang/String;
/*     */     //   143: putfield a : Ljava/lang/String;
/*     */     //   146: aload #20
/*     */     //   148: aload_0
/*     */     //   149: getfield k : Ljava/lang/String;
/*     */     //   152: putfield g : Ljava/lang/String;
/*     */     //   155: astore #19
/*     */     //   157: aload #20
/*     */     //   159: aload_0
/*     */     //   160: getfield s : I
/*     */     //   163: aload #19
/*     */     //   165: ifnonnull -> 212
/*     */     //   168: aload_0
/*     */     //   169: getfield m : Ljava/lang/String;
/*     */     //   172: iload_3
/*     */     //   173: i2s
/*     */     //   174: lload #4
/*     */     //   176: invokestatic a : (Ljava/lang/String;SJ)I
/*     */     //   179: if_icmpeq -> 215
/*     */     //   182: goto -> 195
/*     */     //   185: ldc2_w 5802554482858646967
/*     */     //   188: lload_1
/*     */     //   189: <illegal opcode> w : (Ljava/lang/RuntimeException;JJ)Ljava/lang/RuntimeException;
/*     */     //   194: athrow
/*     */     //   195: aload_0
/*     */     //   196: getfield s : I
/*     */     //   199: goto -> 212
/*     */     //   202: ldc2_w 5802554482858646967
/*     */     //   205: lload_1
/*     */     //   206: <illegal opcode> w : (Ljava/lang/RuntimeException;JJ)Ljava/lang/RuntimeException;
/*     */     //   211: athrow
/*     */     //   212: goto -> 216
/*     */     //   215: iconst_m1
/*     */     //   216: putfield e : I
/*     */     //   219: aload #20
/*     */     //   221: getfield i : Ljava/util/List;
/*     */     //   224: invokeinterface clear : ()V
/*     */     //   229: aload #20
/*     */     //   231: getfield i : Ljava/util/List;
/*     */     //   234: aload_0
/*     */     //   235: lload #11
/*     */     //   237: invokevirtual a : (J)Ljava/util/List;
/*     */     //   240: invokeinterface addAll : (Ljava/util/Collection;)Z
/*     */     //   245: pop
/*     */     //   246: aload #20
/*     */     //   248: aload_0
/*     */     //   249: iload #8
/*     */     //   251: iload #9
/*     */     //   253: i2s
/*     */     //   254: iload #10
/*     */     //   256: invokevirtual i : (ISI)Ljava/lang/String;
/*     */     //   259: lload #6
/*     */     //   261: dup2_x1
/*     */     //   262: pop2
/*     */     //   263: invokevirtual c : (JLjava/lang/String;)Lme/konsolas/aac/j5;
/*     */     //   266: pop
/*     */     //   267: aload #20
/*     */     //   269: aload_0
/*     */     //   270: lload #13
/*     */     //   272: invokevirtual g : (J)Ljava/lang/String;
/*     */     //   275: putfield d : Ljava/lang/String;
/*     */     //   278: aload #20
/*     */     //   280: areturn
/*     */     // Line number table:
/*     */     //   Java source line number -> byte code offset
/*     */     //   #9	-> 97
/*     */     //   #75	-> 106
/*     */     //   #3	-> 115
/*     */     //   #189	-> 135
/*     */     //   #111	-> 146
/*     */     //   #19	-> 157
/*     */     //   #221	-> 219
/*     */     //   #97	-> 229
/*     */     //   #218	-> 246
/*     */     //   #16	-> 267
/*     */     //   #170	-> 278
/*     */     // Exception table:
/*     */     //   from	to	target	type
/*     */     //   157	182	185	java/lang/RuntimeException
/*     */     //   168	199	202	java/lang/RuntimeException
/*     */   }
/*     */   public String a(long paramLong, int paramInt1, int paramInt2) {
/*     */     // Byte code:
/*     */     //   0: lload_1
/*     */     //   1: bipush #32
/*     */     //   3: lshl
/*     */     //   4: iload #4
/*     */     //   6: i2l
/*     */     //   7: bipush #32
/*     */     //   9: lshl
/*     */     //   10: bipush #32
/*     */     //   12: lushr
/*     */     //   13: lor
/*     */     //   14: getstatic me/konsolas/aac/l6.v : J
/*     */     //   17: lxor
/*     */     //   18: lstore #5
/*     */     //   20: ldc2_w -2038766937229565066
/*     */     //   23: lload #5
/*     */     //   25: <illegal opcode> w : (JJ)[Lme/konsolas/aac/aN;
/*     */     //   30: astore #7
/*     */     //   32: aload_0
/*     */     //   33: getfield j : Ljava/util/List;
/*     */     //   36: aload #7
/*     */     //   38: ifnonnull -> 89
/*     */     //   41: ifnonnull -> 77
/*     */     //   44: goto -> 58
/*     */     //   47: ldc2_w -2046386283891560792
/*     */     //   50: lload #5
/*     */     //   52: <illegal opcode> w : (Ljava/lang/RuntimeException;JJ)Ljava/lang/RuntimeException;
/*     */     //   57: athrow
/*     */     //   58: new java/lang/IndexOutOfBoundsException
/*     */     //   61: dup
/*     */     //   62: invokespecial <init> : ()V
/*     */     //   65: athrow
/*     */     //   66: ldc2_w -2046386283891560792
/*     */     //   69: lload #5
/*     */     //   71: <illegal opcode> w : (Ljava/lang/RuntimeException;JJ)Ljava/lang/RuntimeException;
/*     */     //   76: athrow
/*     */     //   77: aload_0
/*     */     //   78: getfield j : Ljava/util/List;
/*     */     //   81: iload_3
/*     */     //   82: iconst_2
/*     */     //   83: imul
/*     */     //   84: invokeinterface get : (I)Ljava/lang/Object;
/*     */     //   89: checkcast java/lang/String
/*     */     //   92: areturn
/*     */     // Line number table:
/*     */     //   Java source line number -> byte code offset
/*     */     //   #13	-> 32
/*     */     //   #190	-> 77
/*     */     // Exception table:
/*     */     //   from	to	target	type
/*     */     //   32	44	47	java/lang/RuntimeException
/*     */     //   41	66	66	java/lang/RuntimeException
/*     */   }
/*     */   public String l(long paramLong) {
/*     */     // Byte code:
/*     */     //   0: getstatic me/konsolas/aac/l6.v : J
/*     */     //   3: lload_1
/*     */     //   4: lxor
/*     */     //   5: lstore_1
/*     */     //   6: lload_1
/*     */     //   7: dup2
/*     */     //   8: ldc2_w 121510459132923
/*     */     //   11: lxor
/*     */     //   12: lstore_3
/*     */     //   13: pop2
/*     */     //   14: aload_0
/*     */     //   15: getfield b : Ljava/lang/String;
/*     */     //   18: bipush #47
/*     */     //   20: aload_0
/*     */     //   21: getfield m : Ljava/lang/String;
/*     */     //   24: invokevirtual length : ()I
/*     */     //   27: iconst_3
/*     */     //   28: iadd
/*     */     //   29: invokevirtual indexOf : (II)I
/*     */     //   32: istore #5
/*     */     //   34: aload_0
/*     */     //   35: getfield b : Ljava/lang/String;
/*     */     //   38: lload_3
/*     */     //   39: dup2_x1
/*     */     //   40: pop2
/*     */     //   41: iload #5
/*     */     //   43: aload_0
/*     */     //   44: getfield b : Ljava/lang/String;
/*     */     //   47: invokevirtual length : ()I
/*     */     //   50: sipush #24829
/*     */     //   53: ldc2_w 2585497709575676251
/*     */     //   56: lload_1
/*     */     //   57: lxor
/*     */     //   58: <illegal opcode> y : (IJ)Ljava/lang/String;
/*     */     //   63: invokestatic a : (JLjava/lang/String;IILjava/lang/String;)I
/*     */     //   66: istore #6
/*     */     //   68: aload_0
/*     */     //   69: getfield b : Ljava/lang/String;
/*     */     //   72: iload #5
/*     */     //   74: iload #6
/*     */     //   76: invokevirtual substring : (II)Ljava/lang/String;
/*     */     //   79: areturn
/*     */     // Line number table:
/*     */     //   Java source line number -> byte code offset
/*     */     //   #15	-> 14
/*     */     //   #26	-> 34
/*     */     //   #73	-> 68
/*     */   }
/*     */   
/*     */   public String j(long paramLong) {
/*     */     // Byte code:
/*     */     //   0: getstatic me/konsolas/aac/l6.v : J
/*     */     //   3: lload_1
/*     */     //   4: lxor
/*     */     //   5: lstore_1
/*     */     //   6: lload_1
/*     */     //   7: dup2
/*     */     //   8: ldc2_w 42934908743089
/*     */     //   11: lxor
/*     */     //   12: lstore_3
/*     */     //   13: pop2
/*     */     //   14: ldc2_w 2985197020245862831
/*     */     //   17: lload_1
/*     */     //   18: <illegal opcode> w : (JJ)[Lme/konsolas/aac/aN;
/*     */     //   23: astore #5
/*     */     //   25: aload_0
/*     */     //   26: getfield t : Ljava/lang/String;
/*     */     //   29: invokevirtual isEmpty : ()Z
/*     */     //   32: aload #5
/*     */     //   34: ifnonnull -> 75
/*     */     //   37: ifeq -> 66
/*     */     //   40: goto -> 53
/*     */     //   43: ldc2_w 2972536412915147889
/*     */     //   46: lload_1
/*     */     //   47: <illegal opcode> w : (Ljava/lang/RuntimeException;JJ)Ljava/lang/RuntimeException;
/*     */     //   52: athrow
/*     */     //   53: ldc ''
/*     */     //   55: areturn
/*     */     //   56: ldc2_w 2972536412915147889
/*     */     //   59: lload_1
/*     */     //   60: <illegal opcode> w : (Ljava/lang/RuntimeException;JJ)Ljava/lang/RuntimeException;
/*     */     //   65: athrow
/*     */     //   66: aload_0
/*     */     //   67: getfield m : Ljava/lang/String;
/*     */     //   70: invokevirtual length : ()I
/*     */     //   73: iconst_3
/*     */     //   74: iadd
/*     */     //   75: istore #6
/*     */     //   77: aload_0
/*     */     //   78: getfield b : Ljava/lang/String;
/*     */     //   81: lload_3
/*     */     //   82: dup2_x1
/*     */     //   83: pop2
/*     */     //   84: iload #6
/*     */     //   86: aload_0
/*     */     //   87: getfield b : Ljava/lang/String;
/*     */     //   90: invokevirtual length : ()I
/*     */     //   93: sipush #4078
/*     */     //   96: ldc2_w 7600653171651733510
/*     */     //   99: lload_1
/*     */     //   100: lxor
/*     */     //   101: <illegal opcode> y : (IJ)Ljava/lang/String;
/*     */     //   106: invokestatic a : (JLjava/lang/String;IILjava/lang/String;)I
/*     */     //   109: istore #7
/*     */     //   111: aload_0
/*     */     //   112: getfield b : Ljava/lang/String;
/*     */     //   115: iload #6
/*     */     //   117: iload #7
/*     */     //   119: invokevirtual substring : (II)Ljava/lang/String;
/*     */     //   122: areturn
/*     */     // Line number table:
/*     */     //   Java source line number -> byte code offset
/*     */     //   #21	-> 25
/*     */     //   #230	-> 66
/*     */     //   #152	-> 77
/*     */     //   #169	-> 111
/*     */     // Exception table:
/*     */     //   from	to	target	type
/*     */     //   25	40	43	java/lang/RuntimeException
/*     */     //   37	56	56	java/lang/RuntimeException
/*     */   }
/*     */   
/*  22 */   static String a(String paramString1, String paramString2, long paramLong, boolean paramBoolean1, boolean paramBoolean2, boolean paramBoolean3, boolean paramBoolean4) { paramLong = v ^ paramLong; int i = (int)((paramLong ^ 0x584E59EA6453L) >>> 32L); long l = (paramLong ^ 0x584E59EA6453L) << 32L >>> 32L; paramLong ^ 0x584E59EA6453L;
/*     */ 
/*     */ 
/*     */ 
/*     */ 
/*     */ 
/*     */ 
/*     */ 
/*     */ 
/*     */ 
/*     */ 
/*     */ 
/*     */ 
/*     */ 
/*     */ 
/*     */ 
/*     */ 
/*     */ 
/*     */ 
/*     */ 
/*     */ 
/*     */ 
/*     */ 
/*     */ 
/*     */ 
/*     */ 
/*     */ 
/*     */ 
/*     */ 
/*     */ 
/*     */ 
/*     */ 
/*     */ 
/*     */ 
/*     */ 
/*     */ 
/*     */ 
/*     */ 
/*     */ 
/*     */ 
/*     */ 
/*     */ 
/*     */ 
/*     */ 
/*     */ 
/*     */ 
/*     */ 
/*     */ 
/*     */ 
/*     */ 
/*     */ 
/*     */ 
/*     */ 
/*     */ 
/*     */ 
/*     */ 
/*     */ 
/*     */ 
/*     */ 
/*     */ 
/*     */ 
/*     */ 
/*     */ 
/*     */ 
/*     */ 
/*     */ 
/*     */ 
/*     */ 
/*     */ 
/*     */ 
/*     */ 
/*     */ 
/*     */ 
/*     */ 
/*     */ 
/*     */ 
/*     */ 
/*     */ 
/*     */ 
/*     */ 
/*     */ 
/*     */ 
/*     */ 
/*     */ 
/*     */ 
/*     */ 
/*     */ 
/*     */ 
/*     */ 
/*     */ 
/*     */ 
/*     */ 
/*     */ 
/*     */ 
/*     */ 
/*     */ 
/*     */ 
/*     */ 
/*     */ 
/*     */ 
/*     */ 
/*     */ 
/*     */ 
/*     */ 
/*     */ 
/*     */ 
/*     */ 
/*     */ 
/*     */ 
/*     */ 
/*     */ 
/*     */     
/* 134 */     return a(i, paramString1, 0, paramString1.length(), paramString2, paramBoolean1, paramBoolean2, paramBoolean3, paramBoolean4, (Charset)null, l); }
/*     */   @Nullable public static l6 a(URL paramURL, long paramLong) { paramLong = v ^ paramLong; long l = paramLong ^ 0x36E46B1365F5L; return b(paramURL.toString(), l); }
/*     */   public URL a() { try { return new URL(this.b); } catch (MalformedURLException malformedURLException) { throw new RuntimeException(malformedURLException); }  }
/*     */   @Nullable public String i(int paramInt1, short paramShort, int paramInt2) { // Byte code:
/*     */     //   0: iload_1
/*     */     //   1: i2l
/*     */     //   2: bipush #32
/*     */     //   4: lshl
/*     */     //   5: iload_2
/*     */     //   6: i2l
/*     */     //   7: bipush #48
/*     */     //   9: lshl
/*     */     //   10: bipush #32
/*     */     //   12: lushr
/*     */     //   13: lor
/*     */     //   14: iload_3
/*     */     //   15: i2l
/*     */     //   16: bipush #48
/*     */     //   18: lshl
/*     */     //   19: bipush #48
/*     */     //   21: lushr
/*     */     //   22: lor
/*     */     //   23: getstatic me/konsolas/aac/l6.v : J
/*     */     //   26: lxor
/*     */     //   27: lstore #4
/*     */     //   29: lload #4
/*     */     //   31: dup2
/*     */     //   32: ldc2_w 60678662474509
/*     */     //   35: lxor
/*     */     //   36: lstore #6
/*     */     //   38: pop2
/*     */     //   39: ldc2_w -4587577288074608489
/*     */     //   42: lload #4
/*     */     //   44: <illegal opcode> w : (JJ)[Lme/konsolas/aac/aN;
/*     */     //   49: astore #8
/*     */     //   51: aload_0
/*     */     //   52: aload #8
/*     */     //   54: ifnonnull -> 91
/*     */     //   57: getfield j : Ljava/util/List;
/*     */     //   60: ifnonnull -> 90
/*     */     //   63: goto -> 77
/*     */     //   66: ldc2_w -4577706698980045495
/*     */     //   69: lload #4
/*     */     //   71: <illegal opcode> w : (Ljava/lang/RuntimeException;JJ)Ljava/lang/RuntimeException;
/*     */     //   76: athrow
/*     */     //   77: aconst_null
/*     */     //   78: areturn
/*     */     //   79: ldc2_w -4577706698980045495
/*     */     //   82: lload #4
/*     */     //   84: <illegal opcode> w : (Ljava/lang/RuntimeException;JJ)Ljava/lang/RuntimeException;
/*     */     //   89: athrow
/*     */     //   90: aload_0
/*     */     //   91: getfield b : Ljava/lang/String;
/*     */     //   94: bipush #63
/*     */     //   96: invokevirtual indexOf : (I)I
/*     */     //   99: iconst_1
/*     */     //   100: iadd
/*     */     //   101: istore #9
/*     */     //   103: aload_0
/*     */     //   104: getfield b : Ljava/lang/String;
/*     */     //   107: iload #9
/*     */     //   109: aload_0
/*     */     //   110: getfield b : Ljava/lang/String;
/*     */     //   113: invokevirtual length : ()I
/*     */     //   116: lload #6
/*     */     //   118: dup2_x1
/*     */     //   119: pop2
/*     */     //   120: bipush #35
/*     */     //   122: invokestatic a : (Ljava/lang/String;IJIC)I
/*     */     //   125: istore #10
/*     */     //   127: aload_0
/*     */     //   128: getfield b : Ljava/lang/String;
/*     */     //   131: iload #9
/*     */     //   133: iload #10
/*     */     //   135: invokevirtual substring : (II)Ljava/lang/String;
/*     */     //   138: areturn
/*     */     // Line number table:
/*     */     //   Java source line number -> byte code offset
/*     */     //   #27	-> 51
/*     */     //   #141	-> 90
/*     */     //   #144	-> 103
/*     */     //   #161	-> 127
/*     */     // Exception table:
/*     */     //   from	to	target	type
/*     */     //   51	63	66	java/lang/RuntimeException
/*     */     //   57	79	79	java/lang/RuntimeException }
/*     */   static void b(StringBuilder paramStringBuilder, long paramLong, List paramList) { // Byte code:
/*     */     //   0: getstatic me/konsolas/aac/l6.v : J
/*     */     //   3: lload_1
/*     */     //   4: lxor
/*     */     //   5: lstore_1
/*     */     //   6: ldc2_w 4930295356512617641
/*     */     //   9: lload_1
/*     */     //   10: <illegal opcode> w : (JJ)[Lme/konsolas/aac/aN;
/*     */     //   15: iconst_0
/*     */     //   16: istore #5
/*     */     //   18: astore #4
/*     */     //   20: aload_3
/*     */     //   21: invokeinterface size : ()I
/*     */     //   26: istore #6
/*     */     //   28: iload #5
/*     */     //   30: iload #6
/*     */     //   32: if_icmpge -> 183
/*     */     //   35: aload_3
/*     */     //   36: iload #5
/*     */     //   38: invokeinterface get : (I)Ljava/lang/Object;
/*     */     //   43: checkcast java/lang/String
/*     */     //   46: astore #7
/*     */     //   48: aload_3
/*     */     //   49: iload #5
/*     */     //   51: iconst_1
/*     */     //   52: iadd
/*     */     //   53: invokeinterface get : (I)Ljava/lang/Object;
/*     */     //   58: checkcast java/lang/String
/*     */     //   61: astore #8
/*     */     //   63: aload #4
/*     */     //   65: lload_1
/*     */     //   66: lconst_0
/*     */     //   67: lcmp
/*     */     //   68: ifle -> 121
/*     */     //   71: ifnonnull -> 119
/*     */     //   74: iload #5
/*     */     //   76: ifle -> 112
/*     */     //   79: goto -> 92
/*     */     //   82: ldc2_w 4919887101958736247
/*     */     //   85: lload_1
/*     */     //   86: <illegal opcode> w : (Ljava/lang/RuntimeException;JJ)Ljava/lang/RuntimeException;
/*     */     //   91: athrow
/*     */     //   92: aload_0
/*     */     //   93: bipush #38
/*     */     //   95: invokevirtual append : (C)Ljava/lang/StringBuilder;
/*     */     //   98: pop
/*     */     //   99: goto -> 112
/*     */     //   102: ldc2_w 4919887101958736247
/*     */     //   105: lload_1
/*     */     //   106: <illegal opcode> w : (Ljava/lang/RuntimeException;JJ)Ljava/lang/RuntimeException;
/*     */     //   111: athrow
/*     */     //   112: aload_0
/*     */     //   113: aload #7
/*     */     //   115: invokevirtual append : (Ljava/lang/String;)Ljava/lang/StringBuilder;
/*     */     //   118: pop
/*     */     //   119: aload #4
/*     */     //   121: lload_1
/*     */     //   122: lconst_0
/*     */     //   123: lcmp
/*     */     //   124: ifle -> 180
/*     */     //   127: ifnonnull -> 178
/*     */     //   130: aload #8
/*     */     //   132: ifnull -> 175
/*     */     //   135: goto -> 148
/*     */     //   138: ldc2_w 4919887101958736247
/*     */     //   141: lload_1
/*     */     //   142: <illegal opcode> w : (Ljava/lang/RuntimeException;JJ)Ljava/lang/RuntimeException;
/*     */     //   147: athrow
/*     */     //   148: aload_0
/*     */     //   149: bipush #61
/*     */     //   151: invokevirtual append : (C)Ljava/lang/StringBuilder;
/*     */     //   154: pop
/*     */     //   155: aload_0
/*     */     //   156: aload #8
/*     */     //   158: invokevirtual append : (Ljava/lang/String;)Ljava/lang/StringBuilder;
/*     */     //   161: pop
/*     */     //   162: goto -> 175
/*     */     //   165: ldc2_w 4919887101958736247
/*     */     //   168: lload_1
/*     */     //   169: <illegal opcode> w : (Ljava/lang/RuntimeException;JJ)Ljava/lang/RuntimeException;
/*     */     //   174: athrow
/*     */     //   175: iinc #5, 2
/*     */     //   178: aload #4
/*     */     //   180: ifnull -> 28
/*     */     //   183: return
/*     */     // Line number table:
/*     */     //   Java source line number -> byte code offset
/*     */     //   #30	-> 15
/*     */     //   #40	-> 35
/*     */     //   #61	-> 48
/*     */     //   #197	-> 63
/*     */     //   #74	-> 112
/*     */     //   #143	-> 119
/*     */     //   #222	-> 148
/*     */     //   #150	-> 155
/*     */     //   #202	-> 175
/*     */     //   #11	-> 183
/*     */     // Exception table:
/*     */     //   from	to	target	type
/*     */     //   63	79	82	java/lang/RuntimeException
/*     */     //   74	99	102	java/lang/RuntimeException
/*     */     //   119	135	138	java/lang/RuntimeException
/*     */     //   130	162	165	java/lang/RuntimeException }
/*     */   @Nullable public static l6 b(String paramString, long paramLong) { paramLong = v ^ paramLong; long l = paramLong ^ 0x4C3BECDE1B81L; try { return c(paramString, l); } catch (IllegalArgumentException illegalArgumentException) { return null; }  }
/*     */   public List a(String paramString, long paramLong) { // Byte code:
/*     */     //   0: getstatic me/konsolas/aac/l6.v : J
/*     */     //   3: lload_2
/*     */     //   4: lxor
/*     */     //   5: lstore_2
/*     */     //   6: ldc2_w -1772805955055196249
/*     */     //   9: lload_2
/*     */     //   10: <illegal opcode> w : (JJ)[Lme/konsolas/aac/aN;
/*     */     //   15: astore #4
/*     */     //   17: aload_0
/*     */     //   18: getfield j : Ljava/util/List;
/*     */     //   21: aload #4
/*     */     //   23: ifnonnull -> 45
/*     */     //   26: ifnonnull -> 46
/*     */     //   29: goto -> 42
/*     */     //   32: ldc2_w -1780992638866199943
/*     */     //   35: lload_2
/*     */     //   36: <illegal opcode> w : (Ljava/lang/RuntimeException;JJ)Ljava/lang/RuntimeException;
/*     */     //   41: athrow
/*     */     //   42: invokestatic emptyList : ()Ljava/util/List;
/*     */     //   45: areturn
/*     */     //   46: new java/util/ArrayList
/*     */     //   49: dup
/*     */     //   50: invokespecial <init> : ()V
/*     */     //   53: astore #5
/*     */     //   55: iconst_0
/*     */     //   56: istore #6
/*     */     //   58: aload_0
/*     */     //   59: getfield j : Ljava/util/List;
/*     */     //   62: invokeinterface size : ()I
/*     */     //   67: istore #7
/*     */     //   69: iload #6
/*     */     //   71: iload #7
/*     */     //   73: if_icmpge -> 157
/*     */     //   76: aload_1
/*     */     //   77: aload_0
/*     */     //   78: getfield j : Ljava/util/List;
/*     */     //   81: iload #6
/*     */     //   83: invokeinterface get : (I)Ljava/lang/Object;
/*     */     //   88: invokevirtual equals : (Ljava/lang/Object;)Z
/*     */     //   91: aload #4
/*     */     //   93: ifnonnull -> 148
/*     */     //   96: ifeq -> 149
/*     */     //   99: goto -> 112
/*     */     //   102: ldc2_w -1780992638866199943
/*     */     //   105: lload_2
/*     */     //   106: <illegal opcode> w : (Ljava/lang/RuntimeException;JJ)Ljava/lang/RuntimeException;
/*     */     //   111: athrow
/*     */     //   112: aload #5
/*     */     //   114: aload_0
/*     */     //   115: getfield j : Ljava/util/List;
/*     */     //   118: iload #6
/*     */     //   120: iconst_1
/*     */     //   121: iadd
/*     */     //   122: invokeinterface get : (I)Ljava/lang/Object;
/*     */     //   127: checkcast java/lang/String
/*     */     //   130: invokeinterface add : (Ljava/lang/Object;)Z
/*     */     //   135: goto -> 148
/*     */     //   138: ldc2_w -1780992638866199943
/*     */     //   141: lload_2
/*     */     //   142: <illegal opcode> w : (Ljava/lang/RuntimeException;JJ)Ljava/lang/RuntimeException;
/*     */     //   147: athrow
/*     */     //   148: pop
/*     */     //   149: iinc #6, 2
/*     */     //   152: aload #4
/*     */     //   154: ifnull -> 69
/*     */     //   157: aload #5
/*     */     //   159: lload_2
/*     */     //   160: lconst_0
/*     */     //   161: lcmp
/*     */     //   162: ifle -> 114
/*     */     //   165: invokestatic unmodifiableList : (Ljava/util/List;)Ljava/util/List;
/*     */     //   168: areturn
/*     */     // Line number table:
/*     */     //   Java source line number -> byte code offset
/*     */     //   #32	-> 17
/*     */     //   #185	-> 46
/*     */     //   #14	-> 55
/*     */     //   #175	-> 76
/*     */     //   #188	-> 112
/*     */     //   #168	-> 149
/*     */     //   #114	-> 157
/*     */     // Exception table:
/*     */     //   from	to	target	type
/*     */     //   17	29	32	java/lang/RuntimeException
/*     */     //   76	99	102	java/lang/RuntimeException
/*     */     //   96	135	138	java/lang/RuntimeException }
/*     */   @Nullable public String k(long paramLong) { // Byte code:
/*     */     //   0: getstatic me/konsolas/aac/l6.v : J
/*     */     //   3: lload_1
/*     */     //   4: lxor
/*     */     //   5: lstore_1
/*     */     //   6: lload_1
/*     */     //   7: dup2
/*     */     //   8: ldc2_w 122673310675098
/*     */     //   11: lxor
/*     */     //   12: lstore_3
/*     */     //   13: pop2
/*     */     //   14: aload_0
/*     */     //   15: getfield j : Ljava/util/List;
/*     */     //   18: ifnonnull -> 33
/*     */     //   21: aconst_null
/*     */     //   22: areturn
/*     */     //   23: ldc2_w -7840551274318258687
/*     */     //   26: lload_1
/*     */     //   27: <illegal opcode> w : (Ljava/lang/RuntimeException;JJ)Ljava/lang/RuntimeException;
/*     */     //   32: athrow
/*     */     //   33: new java/lang/StringBuilder
/*     */     //   36: dup
/*     */     //   37: invokespecial <init> : ()V
/*     */     //   40: astore #5
/*     */     //   42: aload #5
/*     */     //   44: aload_0
/*     */     //   45: getfield j : Ljava/util/List;
/*     */     //   48: lload_3
/*     */     //   49: dup2_x1
/*     */     //   50: pop2
/*     */     //   51: invokestatic b : (Ljava/lang/StringBuilder;JLjava/util/List;)V
/*     */     //   54: aload #5
/*     */     //   56: invokevirtual toString : ()Ljava/lang/String;
/*     */     //   59: areturn
/*     */     // Line number table:
/*     */     //   Java source line number -> byte code offset
/*     */     //   #35	-> 14
/*     */     //   #47	-> 33
/*     */     //   #90	-> 42
/*     */     //   #158	-> 54
/*     */     // Exception table:
/*     */     //   from	to	target	type
/*     */     //   14	23	23	java/lang/RuntimeException }
/*     */   public String toString() { return this.b; } public String f() { return this.m; } static String a(String paramString1, byte paramByte, String paramString2, boolean paramBoolean1, boolean paramBoolean2, boolean paramBoolean3, int paramInt1, boolean paramBoolean4, int paramInt2, @Nullable Charset paramCharset) { long l1 = (paramByte << 56L | paramInt1 << 32L >>> 8L | paramInt2 << 40L >>> 40L) ^ v; int i = (int)((l1 ^ 0x7F9DD32EB569L) >>> 32L); long l2 = (l1 ^ 0x7F9DD32EB569L) << 32L >>> 32L; l1 ^ 0x7F9DD32EB569L; return a(i, paramString1, 0, paramString1.length(), paramString2, paramBoolean1, paramBoolean2, paramBoolean3, paramBoolean4, paramCharset, l2); } public List a(long paramLong) { // Byte code:
/*     */     //   0: getstatic me/konsolas/aac/l6.v : J
/*     */     //   3: lload_1
/*     */     //   4: lxor
/*     */     //   5: lstore_1
/*     */     //   6: lload_1
/*     */     //   7: dup2
/*     */     //   8: ldc2_w 3223110459665
/*     */     //   11: lxor
/*     */     //   12: lstore_3
/*     */     //   13: dup2
/*     */     //   14: ldc2_w 62473408933525
/*     */     //   17: lxor
/*     */     //   18: lstore #5
/*     */     //   20: pop2
/*     */     //   21: aload_0
/*     */     //   22: getfield b : Ljava/lang/String;
/*     */     //   25: bipush #47
/*     */     //   27: aload_0
/*     */     //   28: getfield m : Ljava/lang/String;
/*     */     //   31: invokevirtual length : ()I
/*     */     //   34: iconst_3
/*     */     //   35: iadd
/*     */     //   36: invokevirtual indexOf : (II)I
/*     */     //   39: istore #8
/*     */     //   41: ldc2_w 7335705448989746447
/*     */     //   44: lload_1
/*     */     //   45: <illegal opcode> w : (JJ)[Lme/konsolas/aac/aN;
/*     */     //   50: aload_0
/*     */     //   51: getfield b : Ljava/lang/String;
/*     */     //   54: lload_3
/*     */     //   55: dup2_x1
/*     */     //   56: pop2
/*     */     //   57: iload #8
/*     */     //   59: aload_0
/*     */     //   60: getfield b : Ljava/lang/String;
/*     */     //   63: invokevirtual length : ()I
/*     */     //   66: sipush #16448
/*     */     //   69: ldc2_w 8008014106960816900
/*     */     //   72: lload_1
/*     */     //   73: lxor
/*     */     //   74: <illegal opcode> y : (IJ)Ljava/lang/String;
/*     */     //   79: invokestatic a : (JLjava/lang/String;IILjava/lang/String;)I
/*     */     //   82: istore #9
/*     */     //   84: new java/util/ArrayList
/*     */     //   87: dup
/*     */     //   88: invokespecial <init> : ()V
/*     */     //   91: astore #10
/*     */     //   93: iload #8
/*     */     //   95: istore #11
/*     */     //   97: astore #7
/*     */     //   99: iload #11
/*     */     //   101: iload #9
/*     */     //   103: if_icmpge -> 165
/*     */     //   106: iinc #11, 1
/*     */     //   109: aload_0
/*     */     //   110: getfield b : Ljava/lang/String;
/*     */     //   113: iload #11
/*     */     //   115: lload #5
/*     */     //   117: iload #9
/*     */     //   119: bipush #47
/*     */     //   121: invokestatic a : (Ljava/lang/String;IJIC)I
/*     */     //   124: istore #12
/*     */     //   126: lload_1
/*     */     //   127: lconst_0
/*     */     //   128: lcmp
/*     */     //   129: iflt -> 160
/*     */     //   132: aload #10
/*     */     //   134: aload #7
/*     */     //   136: ifnonnull -> 173
/*     */     //   139: aload_0
/*     */     //   140: getfield b : Ljava/lang/String;
/*     */     //   143: iload #11
/*     */     //   145: iload #12
/*     */     //   147: invokevirtual substring : (II)Ljava/lang/String;
/*     */     //   150: invokeinterface add : (Ljava/lang/Object;)Z
/*     */     //   155: pop
/*     */     //   156: iload #12
/*     */     //   158: istore #11
/*     */     //   160: aload #7
/*     */     //   162: ifnull -> 99
/*     */     //   165: lload_1
/*     */     //   166: lconst_0
/*     */     //   167: lcmp
/*     */     //   168: ifle -> 109
/*     */     //   171: aload #10
/*     */     //   173: areturn
/*     */     // Line number table:
/*     */     //   Java source line number -> byte code offset
/*     */     //   #57	-> 21
/*     */     //   #226	-> 50
/*     */     //   #62	-> 84
/*     */     //   #149	-> 93
/*     */     //   #33	-> 106
/*     */     //   #45	-> 109
/*     */     //   #12	-> 126
/*     */     //   #118	-> 156
/*     */     //   #66	-> 160
/*     */     //   #167	-> 165 } static boolean a(int paramInt1, short paramShort, String paramString, int paramInt2, int paramInt3, char paramChar) { // Byte code:
/*     */     //   0: iload_0
/*     */     //   1: i2l
/*     */     //   2: bipush #32
/*     */     //   4: lshl
/*     */     //   5: iload_1
/*     */     //   6: i2l
/*     */     //   7: bipush #48
/*     */     //   9: lshl
/*     */     //   10: bipush #32
/*     */     //   12: lushr
/*     */     //   13: lor
/*     */     //   14: iload #5
/*     */     //   16: i2l
/*     */     //   17: bipush #48
/*     */     //   19: lshl
/*     */     //   20: bipush #48
/*     */     //   22: lushr
/*     */     //   23: lor
/*     */     //   24: getstatic me/konsolas/aac/l6.v : J
/*     */     //   27: lxor
/*     */     //   28: lstore #6
/*     */     //   30: lload #6
/*     */     //   32: dup2
/*     */     //   33: ldc2_w 126132507961204
/*     */     //   36: lxor
/*     */     //   37: lstore #8
/*     */     //   39: pop2
/*     */     //   40: ldc2_w 7901733278724287850
/*     */     //   43: lload #6
/*     */     //   45: <illegal opcode> w : (JJ)[Lme/konsolas/aac/aN;
/*     */     //   50: astore #10
/*     */     //   52: iload_3
/*     */     //   53: iconst_2
/*     */     //   54: iadd
/*     */     //   55: iload #4
/*     */     //   57: aload #10
/*     */     //   59: ifnonnull -> 100
/*     */     //   62: if_icmpge -> 232
/*     */     //   65: goto -> 79
/*     */     //   68: ldc2_w 7891861585726660788
/*     */     //   71: lload #6
/*     */     //   73: <illegal opcode> w : (Ljava/lang/RuntimeException;JJ)Ljava/lang/RuntimeException;
/*     */     //   78: athrow
/*     */     //   79: aload_2
/*     */     //   80: iload_3
/*     */     //   81: invokevirtual charAt : (I)C
/*     */     //   84: bipush #37
/*     */     //   86: goto -> 100
/*     */     //   89: ldc2_w 7891861585726660788
/*     */     //   92: lload #6
/*     */     //   94: <illegal opcode> w : (Ljava/lang/RuntimeException;JJ)Ljava/lang/RuntimeException;
/*     */     //   99: athrow
/*     */     //   100: aload #10
/*     */     //   102: iload_0
/*     */     //   103: ifle -> 157
/*     */     //   106: ifnonnull -> 155
/*     */     //   109: if_icmpne -> 232
/*     */     //   112: goto -> 126
/*     */     //   115: ldc2_w 7891861585726660788
/*     */     //   118: lload #6
/*     */     //   120: <illegal opcode> w : (Ljava/lang/RuntimeException;JJ)Ljava/lang/RuntimeException;
/*     */     //   125: athrow
/*     */     //   126: aload_2
/*     */     //   127: iload_3
/*     */     //   128: iconst_1
/*     */     //   129: iadd
/*     */     //   130: invokevirtual charAt : (I)C
/*     */     //   133: lload #8
/*     */     //   135: dup2_x1
/*     */     //   136: pop2
/*     */     //   137: invokestatic a : (JC)I
/*     */     //   140: iconst_m1
/*     */     //   141: goto -> 155
/*     */     //   144: ldc2_w 7891861585726660788
/*     */     //   147: lload #6
/*     */     //   149: <illegal opcode> w : (Ljava/lang/RuntimeException;JJ)Ljava/lang/RuntimeException;
/*     */     //   154: athrow
/*     */     //   155: aload #10
/*     */     //   157: ifnonnull -> 225
/*     */     //   160: if_icmpeq -> 232
/*     */     //   163: goto -> 177
/*     */     //   166: ldc2_w 7891861585726660788
/*     */     //   169: lload #6
/*     */     //   171: <illegal opcode> w : (Ljava/lang/RuntimeException;JJ)Ljava/lang/RuntimeException;
/*     */     //   176: athrow
/*     */     //   177: aload_2
/*     */     //   178: iload_3
/*     */     //   179: iconst_2
/*     */     //   180: iadd
/*     */     //   181: invokevirtual charAt : (I)C
/*     */     //   184: lload #8
/*     */     //   186: dup2_x1
/*     */     //   187: pop2
/*     */     //   188: invokestatic a : (JC)I
/*     */     //   191: aload #10
/*     */     //   193: ifnonnull -> 229
/*     */     //   196: goto -> 210
/*     */     //   199: ldc2_w 7891861585726660788
/*     */     //   202: lload #6
/*     */     //   204: <illegal opcode> w : (Ljava/lang/RuntimeException;JJ)Ljava/lang/RuntimeException;
/*     */     //   209: athrow
/*     */     //   210: iconst_m1
/*     */     //   211: goto -> 225
/*     */     //   214: ldc2_w 7891861585726660788
/*     */     //   217: lload #6
/*     */     //   219: <illegal opcode> w : (Ljava/lang/RuntimeException;JJ)Ljava/lang/RuntimeException;
/*     */     //   224: athrow
/*     */     //   225: if_icmpeq -> 232
/*     */     //   228: iconst_1
/*     */     //   229: goto -> 233
/*     */     //   232: iconst_0
/*     */     //   233: ireturn
/*     */     // Line number table:
/*     */     //   Java source line number -> byte code offset
/*     */     //   #58	-> 52
/*     */     //   #108	-> 81
/*     */     //   #76	-> 130
/*     */     //   #208	-> 181
/*     */     //   #29	-> 233
/*     */     // Exception table:
/*     */     //   from	to	target	type
/*     */     //   52	65	68	java/lang/RuntimeException
/*     */     //   62	86	89	java/lang/RuntimeException
/*     */     //   100	112	115	java/lang/RuntimeException
/*     */     //   109	141	144	java/lang/RuntimeException
/*     */     //   155	163	166	java/lang/RuntimeException
/*     */     //   160	196	199	java/lang/RuntimeException
/* 142 */     //   177	211	214	java/lang/RuntimeException } public int b() { return this.l.size(); } public int hashCode() { return this.b.hashCode(); }
/*     */   static void a(long paramLong, fw paramfw, String paramString, int paramInt1, int paramInt2, byte paramByte, boolean paramBoolean) { // Byte code:
/*     */     //   0: lload_0
/*     */     //   1: bipush #8
/*     */     //   3: lshl
/*     */     //   4: iload #6
/*     */     //   6: i2l
/*     */     //   7: bipush #56
/*     */     //   9: lshl
/*     */     //   10: bipush #56
/*     */     //   12: lushr
/*     */     //   13: lor
/*     */     //   14: getstatic me/konsolas/aac/l6.v : J
/*     */     //   17: lxor
/*     */     //   18: lstore #8
/*     */     //   20: lload #8
/*     */     //   22: dup2
/*     */     //   23: ldc2_w 12453909131245
/*     */     //   26: lxor
/*     */     //   27: lstore #10
/*     */     //   29: dup2
/*     */     //   30: ldc2_w 39059123233288
/*     */     //   33: lxor
/*     */     //   34: lstore #12
/*     */     //   36: dup2
/*     */     //   37: ldc2_w 112847698085566
/*     */     //   40: lxor
/*     */     //   41: lstore #14
/*     */     //   43: pop2
/*     */     //   44: ldc2_w -1669487748559345642
/*     */     //   47: lload #8
/*     */     //   49: <illegal opcode> w : (JJ)[Lme/konsolas/aac/aN;
/*     */     //   54: iload #4
/*     */     //   56: istore #18
/*     */     //   58: astore #16
/*     */     //   60: iload #18
/*     */     //   62: iload #5
/*     */     //   64: if_icmpge -> 416
/*     */     //   67: aload_3
/*     */     //   68: iload #18
/*     */     //   70: invokevirtual codePointAt : (I)I
/*     */     //   73: istore #17
/*     */     //   75: iload #17
/*     */     //   77: bipush #37
/*     */     //   79: aload #16
/*     */     //   81: ifnonnull -> 336
/*     */     //   84: if_icmpne -> 294
/*     */     //   87: goto -> 101
/*     */     //   90: ldc2_w -1659058055641864760
/*     */     //   93: lload #8
/*     */     //   95: <illegal opcode> w : (Ljava/lang/RuntimeException;JJ)Ljava/lang/RuntimeException;
/*     */     //   100: athrow
/*     */     //   101: iload #18
/*     */     //   103: iconst_2
/*     */     //   104: iadd
/*     */     //   105: iload #5
/*     */     //   107: aload #16
/*     */     //   109: ifnonnull -> 336
/*     */     //   112: goto -> 126
/*     */     //   115: ldc2_w -1659058055641864760
/*     */     //   118: lload #8
/*     */     //   120: <illegal opcode> w : (Ljava/lang/RuntimeException;JJ)Ljava/lang/RuntimeException;
/*     */     //   125: athrow
/*     */     //   126: if_icmpge -> 294
/*     */     //   129: goto -> 143
/*     */     //   132: ldc2_w -1659058055641864760
/*     */     //   135: lload #8
/*     */     //   137: <illegal opcode> w : (Ljava/lang/RuntimeException;JJ)Ljava/lang/RuntimeException;
/*     */     //   142: athrow
/*     */     //   143: aload_3
/*     */     //   144: iload #18
/*     */     //   146: iconst_1
/*     */     //   147: iadd
/*     */     //   148: invokevirtual charAt : (I)C
/*     */     //   151: lload #12
/*     */     //   153: dup2_x1
/*     */     //   154: pop2
/*     */     //   155: invokestatic a : (JC)I
/*     */     //   158: istore #19
/*     */     //   160: aload_3
/*     */     //   161: iload #18
/*     */     //   163: iconst_2
/*     */     //   164: iadd
/*     */     //   165: invokevirtual charAt : (I)C
/*     */     //   168: lload #12
/*     */     //   170: dup2_x1
/*     */     //   171: pop2
/*     */     //   172: invokestatic a : (JC)I
/*     */     //   175: istore #20
/*     */     //   177: iload #19
/*     */     //   179: iconst_m1
/*     */     //   180: lload_0
/*     */     //   181: lconst_0
/*     */     //   182: lcmp
/*     */     //   183: iflt -> 225
/*     */     //   186: aload #16
/*     */     //   188: ifnonnull -> 225
/*     */     //   191: if_icmpeq -> 269
/*     */     //   194: goto -> 208
/*     */     //   197: ldc2_w -1659058055641864760
/*     */     //   200: lload #8
/*     */     //   202: <illegal opcode> w : (Ljava/lang/RuntimeException;JJ)Ljava/lang/RuntimeException;
/*     */     //   207: athrow
/*     */     //   208: iload #20
/*     */     //   210: iconst_m1
/*     */     //   211: goto -> 225
/*     */     //   214: ldc2_w -1659058055641864760
/*     */     //   217: lload #8
/*     */     //   219: <illegal opcode> w : (Ljava/lang/RuntimeException;JJ)Ljava/lang/RuntimeException;
/*     */     //   224: athrow
/*     */     //   225: if_icmpeq -> 269
/*     */     //   228: aload_2
/*     */     //   229: iload #19
/*     */     //   231: iconst_4
/*     */     //   232: ishl
/*     */     //   233: iload #20
/*     */     //   235: iadd
/*     */     //   236: lload #10
/*     */     //   238: invokevirtual a : (IJ)Lme/konsolas/aac/fw;
/*     */     //   241: pop
/*     */     //   242: iinc #18, 2
/*     */     //   245: aload #16
/*     */     //   247: iload #6
/*     */     //   249: ifgt -> 413
/*     */     //   252: ifnull -> 401
/*     */     //   255: goto -> 269
/*     */     //   258: ldc2_w -1659058055641864760
/*     */     //   261: lload #8
/*     */     //   263: <illegal opcode> w : (Ljava/lang/RuntimeException;JJ)Ljava/lang/RuntimeException;
/*     */     //   268: athrow
/*     */     //   269: lload_0
/*     */     //   270: lconst_0
/*     */     //   271: lcmp
/*     */     //   272: ifle -> 387
/*     */     //   275: aload #16
/*     */     //   277: ifnull -> 378
/*     */     //   280: goto -> 294
/*     */     //   283: ldc2_w -1659058055641864760
/*     */     //   286: lload #8
/*     */     //   288: <illegal opcode> w : (Ljava/lang/RuntimeException;JJ)Ljava/lang/RuntimeException;
/*     */     //   293: athrow
/*     */     //   294: iload #17
/*     */     //   296: iload #6
/*     */     //   298: ifgt -> 341
/*     */     //   301: aload #16
/*     */     //   303: ifnonnull -> 341
/*     */     //   306: goto -> 320
/*     */     //   309: ldc2_w -1659058055641864760
/*     */     //   312: lload #8
/*     */     //   314: <illegal opcode> w : (Ljava/lang/RuntimeException;JJ)Ljava/lang/RuntimeException;
/*     */     //   319: athrow
/*     */     //   320: bipush #43
/*     */     //   322: goto -> 336
/*     */     //   325: ldc2_w -1659058055641864760
/*     */     //   328: lload #8
/*     */     //   330: <illegal opcode> w : (Ljava/lang/RuntimeException;JJ)Ljava/lang/RuntimeException;
/*     */     //   335: athrow
/*     */     //   336: if_icmpne -> 378
/*     */     //   339: iload #7
/*     */     //   341: ifeq -> 378
/*     */     //   344: aload_2
/*     */     //   345: bipush #32
/*     */     //   347: lload #10
/*     */     //   349: invokevirtual a : (IJ)Lme/konsolas/aac/fw;
/*     */     //   352: pop
/*     */     //   353: aload #16
/*     */     //   355: lload_0
/*     */     //   356: lconst_0
/*     */     //   357: lcmp
/*     */     //   358: iflt -> 413
/*     */     //   361: ifnull -> 401
/*     */     //   364: goto -> 378
/*     */     //   367: ldc2_w -1659058055641864760
/*     */     //   370: lload #8
/*     */     //   372: <illegal opcode> w : (Ljava/lang/RuntimeException;JJ)Ljava/lang/RuntimeException;
/*     */     //   377: athrow
/*     */     //   378: aload_2
/*     */     //   379: lload #14
/*     */     //   381: iload #17
/*     */     //   383: invokevirtual d : (JI)Lme/konsolas/aac/fw;
/*     */     //   386: pop
/*     */     //   387: goto -> 401
/*     */     //   390: ldc2_w -1659058055641864760
/*     */     //   393: lload #8
/*     */     //   395: <illegal opcode> w : (Ljava/lang/RuntimeException;JJ)Ljava/lang/RuntimeException;
/*     */     //   400: athrow
/*     */     //   401: iload #18
/*     */     //   403: iload #17
/*     */     //   405: invokestatic charCount : (I)I
/*     */     //   408: iadd
/*     */     //   409: istore #18
/*     */     //   411: aload #16
/*     */     //   413: ifnull -> 60
/*     */     //   416: return
/*     */     // Line number table:
/*     */     //   Java source line number -> byte code offset
/*     */     //   #86	-> 54
/*     */     //   #87	-> 67
/*     */     //   #211	-> 75
/*     */     //   #199	-> 143
/*     */     //   #146	-> 160
/*     */     //   #83	-> 177
/*     */     //   #85	-> 228
/*     */     //   #138	-> 242
/*     */     //   #156	-> 245
/*     */     //   #154	-> 269
/*     */     //   #72	-> 344
/*     */     //   #204	-> 353
/*     */     //   #25	-> 378
/*     */     //   #173	-> 401
/*     */     //   #59	-> 416
/*     */     // Exception table:
/*     */     //   from	to	target	type
/*     */     //   75	87	90	java/lang/RuntimeException
/*     */     //   84	112	115	java/lang/RuntimeException
/*     */     //   101	129	132	java/lang/RuntimeException
/*     */     //   177	194	197	java/lang/RuntimeException
/*     */     //   191	211	214	java/lang/RuntimeException
/*     */     //   225	255	258	java/lang/RuntimeException
/*     */     //   228	280	283	java/lang/RuntimeException
/*     */     //   269	306	309	java/lang/RuntimeException
/*     */     //   294	322	325	java/lang/RuntimeException
/*     */     //   341	364	367	java/lang/RuntimeException
/*     */     //   344	387	390	java/lang/RuntimeException }
/*     */   @Nullable public static l6 a(long paramLong, URI paramURI) { paramLong = v ^ paramLong; long l = paramLong ^ 0x7468E92B7FEFL; return b(paramURI.toString(), l); }
/*     */   public String d() { return this.k; }
/*     */   public URI a(int paramInt, short paramShort1, short paramShort2) { // Byte code:
/*     */     //   0: iload_1
/*     */     //   1: i2l
/*     */     //   2: bipush #32
/*     */     //   4: lshl
/*     */     //   5: iload_2
/*     */     //   6: i2l
/*     */     //   7: bipush #48
/*     */     //   9: lshl
/*     */     //   10: bipush #32
/*     */     //   12: lushr
/*     */     //   13: lor
/*     */     //   14: iload_3
/*     */     //   15: i2l
/*     */     //   16: bipush #48
/*     */     //   18: lshl
/*     */     //   19: bipush #48
/*     */     //   21: lushr
/*     */     //   22: lor
/*     */     //   23: getstatic me/konsolas/aac/l6.v : J
/*     */     //   26: lxor
/*     */     //   27: lstore #4
/*     */     //   29: lload #4
/*     */     //   31: dup2
/*     */     //   32: ldc2_w 50866281039034
/*     */     //   35: lxor
/*     */     //   36: lstore #6
/*     */     //   38: dup2
/*     */     //   39: ldc2_w 47885844255213
/*     */     //   42: lxor
/*     */     //   43: lstore #8
/*     */     //   45: pop2
/*     */     //   46: aload_0
/*     */     //   47: lload #6
/*     */     //   49: invokevirtual a : (J)Lme/konsolas/aac/j5;
/*     */     //   52: lload #8
/*     */     //   54: invokevirtual a : (J)Lme/konsolas/aac/j5;
/*     */     //   57: invokevirtual toString : ()Ljava/lang/String;
/*     */     //   60: astore #10
/*     */     //   62: new java/net/URI
/*     */     //   65: dup
/*     */     //   66: aload #10
/*     */     //   68: invokespecial <init> : (Ljava/lang/String;)V
/*     */     //   71: areturn
/*     */     //   72: astore #11
/*     */     //   74: aload #10
/*     */     //   76: sipush #14803
/*     */     //   79: ldc2_w 5166233633381057709
/*     */     //   82: lload #4
/*     */     //   84: lxor
/*     */     //   85: <illegal opcode> y : (IJ)Ljava/lang/String;
/*     */     //   90: ldc ''
/*     */     //   92: invokevirtual replaceAll : (Ljava/lang/String;Ljava/lang/String;)Ljava/lang/String;
/*     */     //   95: astore #12
/*     */     //   97: aload #12
/*     */     //   99: invokestatic create : (Ljava/lang/String;)Ljava/net/URI;
/*     */     //   102: areturn
/*     */     //   103: astore #12
/*     */     //   105: new java/lang/RuntimeException
/*     */     //   108: dup
/*     */     //   109: aload #11
/*     */     //   111: invokespecial <init> : (Ljava/lang/Throwable;)V
/*     */     //   114: athrow
/*     */     // Line number table:
/*     */     //   Java source line number -> byte code offset
/*     */     //   #104	-> 46
/*     */     //   #94	-> 62
/*     */     //   #51	-> 72
/*     */     //   #63	-> 74
/*     */     //   #205	-> 97
/*     */     //   #220	-> 103
/*     */     //   #137	-> 105
/*     */     // Exception table:
/*     */     //   from	to	target	type
/*     */     //   62	71	72	java/net/URISyntaxException
/*     */     //   74	102	103	java/lang/Exception }
/*     */   static String a(int paramInt1, String paramString1, int paramInt2, int paramInt3, String paramString2, boolean paramBoolean1, boolean paramBoolean2, boolean paramBoolean3, boolean paramBoolean4, @Nullable Charset paramCharset, long paramLong) { // Byte code:
/*     */     //   0: iload_0
/*     */     //   1: i2l
/*     */     //   2: bipush #32
/*     */     //   4: lshl
/*     */     //   5: lload #10
/*     */     //   7: bipush #32
/*     */     //   9: lshl
/*     */     //   10: bipush #32
/*     */     //   12: lushr
/*     */     //   13: lor
/*     */     //   14: getstatic me/konsolas/aac/l6.v : J
/*     */     //   17: lxor
/*     */     //   18: lstore #12
/*     */     //   20: lload #12
/*     */     //   22: dup2
/*     */     //   23: ldc2_w 50399234131149
/*     */     //   26: lxor
/*     */     //   27: dup2
/*     */     //   28: bipush #32
/*     */     //   30: lushr
/*     */     //   31: l2i
/*     */     //   32: istore #14
/*     */     //   34: dup2
/*     */     //   35: bipush #32
/*     */     //   37: lshl
/*     */     //   38: bipush #48
/*     */     //   40: lushr
/*     */     //   41: l2i
/*     */     //   42: istore #15
/*     */     //   44: dup2
/*     */     //   45: bipush #48
/*     */     //   47: lshl
/*     */     //   48: bipush #48
/*     */     //   50: lushr
/*     */     //   51: l2i
/*     */     //   52: istore #16
/*     */     //   54: pop2
/*     */     //   55: dup2
/*     */     //   56: ldc2_w 40367686004691
/*     */     //   59: lxor
/*     */     //   60: lstore #17
/*     */     //   62: dup2
/*     */     //   63: ldc2_w 44771112037037
/*     */     //   66: lxor
/*     */     //   67: lstore #19
/*     */     //   69: dup2
/*     */     //   70: ldc2_w 14097633456833
/*     */     //   73: lxor
/*     */     //   74: lstore #21
/*     */     //   76: pop2
/*     */     //   77: ldc2_w 1047629667157610059
/*     */     //   80: lload #12
/*     */     //   82: <illegal opcode> w : (JJ)[Lme/konsolas/aac/aN;
/*     */     //   87: iload_2
/*     */     //   88: istore #25
/*     */     //   90: astore #23
/*     */     //   92: iload #25
/*     */     //   94: iload_3
/*     */     //   95: if_icmpge -> 628
/*     */     //   98: aload_1
/*     */     //   99: iload_0
/*     */     //   100: iflt -> 638
/*     */     //   103: iload #25
/*     */     //   105: aload #23
/*     */     //   107: ifnonnull -> 634
/*     */     //   110: invokevirtual codePointAt : (I)I
/*     */     //   113: istore #24
/*     */     //   115: iload #24
/*     */     //   117: bipush #32
/*     */     //   119: aload #23
/*     */     //   121: lload #10
/*     */     //   123: lconst_0
/*     */     //   124: lcmp
/*     */     //   125: ifle -> 168
/*     */     //   128: ifnonnull -> 166
/*     */     //   131: if_icmplt -> 561
/*     */     //   134: goto -> 148
/*     */     //   137: ldc2_w 1055235807744394133
/*     */     //   140: lload #12
/*     */     //   142: <illegal opcode> w : (Ljava/lang/RuntimeException;JJ)Ljava/lang/RuntimeException;
/*     */     //   147: athrow
/*     */     //   148: iload #24
/*     */     //   150: bipush #127
/*     */     //   152: goto -> 166
/*     */     //   155: ldc2_w 1055235807744394133
/*     */     //   158: lload #12
/*     */     //   160: <illegal opcode> w : (Ljava/lang/RuntimeException;JJ)Ljava/lang/RuntimeException;
/*     */     //   165: athrow
/*     */     //   166: aload #23
/*     */     //   168: lload #10
/*     */     //   170: lconst_0
/*     */     //   171: lcmp
/*     */     //   172: ifle -> 216
/*     */     //   175: ifnonnull -> 214
/*     */     //   178: if_icmpeq -> 561
/*     */     //   181: goto -> 195
/*     */     //   184: ldc2_w 1055235807744394133
/*     */     //   187: lload #12
/*     */     //   189: <illegal opcode> w : (Ljava/lang/RuntimeException;JJ)Ljava/lang/RuntimeException;
/*     */     //   194: athrow
/*     */     //   195: iload #24
/*     */     //   197: sipush #128
/*     */     //   200: goto -> 214
/*     */     //   203: ldc2_w 1055235807744394133
/*     */     //   206: lload #12
/*     */     //   208: <illegal opcode> w : (Ljava/lang/RuntimeException;JJ)Ljava/lang/RuntimeException;
/*     */     //   213: athrow
/*     */     //   214: aload #23
/*     */     //   216: iload_0
/*     */     //   217: ifle -> 302
/*     */     //   220: ifnonnull -> 300
/*     */     //   223: if_icmplt -> 278
/*     */     //   226: goto -> 240
/*     */     //   229: ldc2_w 1055235807744394133
/*     */     //   232: lload #12
/*     */     //   234: <illegal opcode> w : (Ljava/lang/RuntimeException;JJ)Ljava/lang/RuntimeException;
/*     */     //   239: athrow
/*     */     //   240: iload #8
/*     */     //   242: aload #23
/*     */     //   244: ifnonnull -> 299
/*     */     //   247: goto -> 261
/*     */     //   250: ldc2_w 1055235807744394133
/*     */     //   253: lload #12
/*     */     //   255: <illegal opcode> w : (Ljava/lang/RuntimeException;JJ)Ljava/lang/RuntimeException;
/*     */     //   260: athrow
/*     */     //   261: ifne -> 561
/*     */     //   264: goto -> 278
/*     */     //   267: ldc2_w 1055235807744394133
/*     */     //   270: lload #12
/*     */     //   272: <illegal opcode> w : (Ljava/lang/RuntimeException;JJ)Ljava/lang/RuntimeException;
/*     */     //   277: athrow
/*     */     //   278: aload #4
/*     */     //   280: iload #24
/*     */     //   282: invokevirtual indexOf : (I)I
/*     */     //   285: goto -> 299
/*     */     //   288: ldc2_w 1055235807744394133
/*     */     //   291: lload #12
/*     */     //   293: <illegal opcode> w : (Ljava/lang/RuntimeException;JJ)Ljava/lang/RuntimeException;
/*     */     //   298: athrow
/*     */     //   299: iconst_m1
/*     */     //   300: aload #23
/*     */     //   302: iload_0
/*     */     //   303: ifle -> 346
/*     */     //   306: ifnonnull -> 344
/*     */     //   309: if_icmpne -> 561
/*     */     //   312: goto -> 326
/*     */     //   315: ldc2_w 1055235807744394133
/*     */     //   318: lload #12
/*     */     //   320: <illegal opcode> w : (Ljava/lang/RuntimeException;JJ)Ljava/lang/RuntimeException;
/*     */     //   325: athrow
/*     */     //   326: iload #24
/*     */     //   328: bipush #37
/*     */     //   330: goto -> 344
/*     */     //   333: ldc2_w 1055235807744394133
/*     */     //   336: lload #12
/*     */     //   338: <illegal opcode> w : (Ljava/lang/RuntimeException;JJ)Ljava/lang/RuntimeException;
/*     */     //   343: athrow
/*     */     //   344: aload #23
/*     */     //   346: lload #10
/*     */     //   348: lconst_0
/*     */     //   349: lcmp
/*     */     //   350: iflt -> 496
/*     */     //   353: ifnonnull -> 494
/*     */     //   356: if_icmpne -> 490
/*     */     //   359: goto -> 373
/*     */     //   362: ldc2_w 1055235807744394133
/*     */     //   365: lload #12
/*     */     //   367: <illegal opcode> w : (Ljava/lang/RuntimeException;JJ)Ljava/lang/RuntimeException;
/*     */     //   372: athrow
/*     */     //   373: iload #5
/*     */     //   375: aload #23
/*     */     //   377: iload_0
/*     */     //   378: iflt -> 419
/*     */     //   381: ifnonnull -> 417
/*     */     //   384: goto -> 398
/*     */     //   387: ldc2_w 1055235807744394133
/*     */     //   390: lload #12
/*     */     //   392: <illegal opcode> w : (Ljava/lang/RuntimeException;JJ)Ljava/lang/RuntimeException;
/*     */     //   397: athrow
/*     */     //   398: ifeq -> 561
/*     */     //   401: goto -> 415
/*     */     //   404: ldc2_w 1055235807744394133
/*     */     //   407: lload #12
/*     */     //   409: <illegal opcode> w : (Ljava/lang/RuntimeException;JJ)Ljava/lang/RuntimeException;
/*     */     //   414: athrow
/*     */     //   415: iload #6
/*     */     //   417: aload #23
/*     */     //   419: ifnonnull -> 492
/*     */     //   422: ifeq -> 490
/*     */     //   425: goto -> 439
/*     */     //   428: ldc2_w 1055235807744394133
/*     */     //   431: lload #12
/*     */     //   433: <illegal opcode> w : (Ljava/lang/RuntimeException;JJ)Ljava/lang/RuntimeException;
/*     */     //   438: athrow
/*     */     //   439: iload #14
/*     */     //   441: iload #15
/*     */     //   443: i2s
/*     */     //   444: aload_1
/*     */     //   445: iload #25
/*     */     //   447: iload_3
/*     */     //   448: iload #16
/*     */     //   450: i2c
/*     */     //   451: invokestatic a : (ISLjava/lang/String;IIC)Z
/*     */     //   454: aload #23
/*     */     //   456: ifnonnull -> 492
/*     */     //   459: goto -> 473
/*     */     //   462: ldc2_w 1055235807744394133
/*     */     //   465: lload #12
/*     */     //   467: <illegal opcode> w : (Ljava/lang/RuntimeException;JJ)Ljava/lang/RuntimeException;
/*     */     //   472: athrow
/*     */     //   473: ifeq -> 561
/*     */     //   476: goto -> 490
/*     */     //   479: ldc2_w 1055235807744394133
/*     */     //   482: lload #12
/*     */     //   484: <illegal opcode> w : (Ljava/lang/RuntimeException;JJ)Ljava/lang/RuntimeException;
/*     */     //   489: athrow
/*     */     //   490: iload #24
/*     */     //   492: bipush #43
/*     */     //   494: aload #23
/*     */     //   496: ifnonnull -> 620
/*     */     //   499: if_icmpne -> 613
/*     */     //   502: goto -> 516
/*     */     //   505: ldc2_w 1055235807744394133
/*     */     //   508: lload #12
/*     */     //   510: <illegal opcode> w : (Ljava/lang/RuntimeException;JJ)Ljava/lang/RuntimeException;
/*     */     //   515: athrow
/*     */     //   516: lload #10
/*     */     //   518: lconst_0
/*     */     //   519: lcmp
/*     */     //   520: ifle -> 623
/*     */     //   523: iload #7
/*     */     //   525: aload #23
/*     */     //   527: ifnonnull -> 621
/*     */     //   530: goto -> 544
/*     */     //   533: ldc2_w 1055235807744394133
/*     */     //   536: lload #12
/*     */     //   538: <illegal opcode> w : (Ljava/lang/RuntimeException;JJ)Ljava/lang/RuntimeException;
/*     */     //   543: athrow
/*     */     //   544: ifeq -> 613
/*     */     //   547: goto -> 561
/*     */     //   550: ldc2_w 1055235807744394133
/*     */     //   553: lload #12
/*     */     //   555: <illegal opcode> w : (Ljava/lang/RuntimeException;JJ)Ljava/lang/RuntimeException;
/*     */     //   560: athrow
/*     */     //   561: new me/konsolas/aac/fw
/*     */     //   564: dup
/*     */     //   565: invokespecial <init> : ()V
/*     */     //   568: astore #26
/*     */     //   570: aload #26
/*     */     //   572: aload_1
/*     */     //   573: iload_2
/*     */     //   574: lload #21
/*     */     //   576: iload #25
/*     */     //   578: invokevirtual a : (Ljava/lang/String;IJI)Lme/konsolas/aac/fw;
/*     */     //   581: pop
/*     */     //   582: aload #26
/*     */     //   584: aload_1
/*     */     //   585: iload #25
/*     */     //   587: lload #17
/*     */     //   589: iload_3
/*     */     //   590: aload #4
/*     */     //   592: iload #5
/*     */     //   594: iload #6
/*     */     //   596: iload #7
/*     */     //   598: iload #8
/*     */     //   600: aload #9
/*     */     //   602: invokestatic a : (Lme/konsolas/aac/fw;Ljava/lang/String;IJILjava/lang/String;ZZZZLjava/nio/charset/Charset;)V
/*     */     //   605: aload #26
/*     */     //   607: lload #19
/*     */     //   609: invokevirtual c : (J)Ljava/lang/String;
/*     */     //   612: areturn
/*     */     //   613: iload #25
/*     */     //   615: iload #24
/*     */     //   617: invokestatic charCount : (I)I
/*     */     //   620: iadd
/*     */     //   621: istore #25
/*     */     //   623: aload #23
/*     */     //   625: ifnull -> 92
/*     */     //   628: aload_1
/*     */     //   629: iload_0
/*     */     //   630: ifle -> 99
/*     */     //   633: iload_2
/*     */     //   634: iload_3
/*     */     //   635: invokevirtual substring : (II)Ljava/lang/String;
/*     */     //   638: areturn
/*     */     // Line number table:
/*     */     //   Java source line number -> byte code offset
/*     */     //   #105	-> 87
/*     */     //   #70	-> 98
/*     */     //   #160	-> 115
/*     */     //   #6	-> 282
/*     */     //   #93	-> 448
/*     */     //   #212	-> 561
/*     */     //   #196	-> 570
/*     */     //   #88	-> 582
/*     */     //   #36	-> 605
/*     */     //   #174	-> 613
/*     */     //   #132	-> 628
/*     */     // Exception table:
/*     */     //   from	to	target	type
/*     */     //   115	134	137	java/lang/RuntimeException
/*     */     //   131	152	155	java/lang/RuntimeException
/*     */     //   166	181	184	java/lang/RuntimeException
/*     */     //   178	200	203	java/lang/RuntimeException
/*     */     //   214	226	229	java/lang/RuntimeException
/*     */     //   223	247	250	java/lang/RuntimeException
/*     */     //   240	264	267	java/lang/RuntimeException
/*     */     //   261	285	288	java/lang/RuntimeException
/*     */     //   300	312	315	java/lang/RuntimeException
/*     */     //   309	330	333	java/lang/RuntimeException
/*     */     //   344	359	362	java/lang/RuntimeException
/*     */     //   356	384	387	java/lang/RuntimeException
/*     */     //   373	401	404	java/lang/RuntimeException
/*     */     //   417	425	428	java/lang/RuntimeException
/*     */     //   422	459	462	java/lang/RuntimeException
/*     */     //   439	476	479	java/lang/RuntimeException
/*     */     //   494	502	505	java/lang/RuntimeException
/*     */     //   499	530	533	java/lang/RuntimeException
/*     */     //   516	547	550	java/lang/RuntimeException } @Nullable public String m() { return this.h; } private List a(List paramList, char paramChar, int paramInt, short paramShort, boolean paramBoolean) { // Byte code:
/*     */     //   0: iload_2
/*     */     //   1: i2l
/*     */     //   2: bipush #48
/*     */     //   4: lshl
/*     */     //   5: iload_3
/*     */     //   6: i2l
/*     */     //   7: bipush #32
/*     */     //   9: lshl
/*     */     //   10: bipush #16
/*     */     //   12: lushr
/*     */     //   13: lor
/*     */     //   14: iload #4
/*     */     //   16: i2l
/*     */     //   17: bipush #48
/*     */     //   19: lshl
/*     */     //   20: bipush #48
/*     */     //   22: lushr
/*     */     //   23: lor
/*     */     //   24: getstatic me/konsolas/aac/l6.v : J
/*     */     //   27: lxor
/*     */     //   28: lstore #6
/*     */     //   30: lload #6
/*     */     //   32: dup2
/*     */     //   33: ldc2_w 26964339568874
/*     */     //   36: lxor
/*     */     //   37: lstore #8
/*     */     //   39: pop2
/*     */     //   40: ldc2_w -3449880901912309539
/*     */     //   43: lload #6
/*     */     //   45: <illegal opcode> w : (JJ)[Lme/konsolas/aac/aN;
/*     */     //   50: aload_1
/*     */     //   51: invokeinterface size : ()I
/*     */     //   56: istore #11
/*     */     //   58: astore #10
/*     */     //   60: new java/util/ArrayList
/*     */     //   63: dup
/*     */     //   64: iload #11
/*     */     //   66: invokespecial <init> : (I)V
/*     */     //   69: astore #12
/*     */     //   71: iconst_0
/*     */     //   72: istore #13
/*     */     //   74: iload #13
/*     */     //   76: iload #11
/*     */     //   78: if_icmpge -> 180
/*     */     //   81: aload_1
/*     */     //   82: iload #13
/*     */     //   84: invokeinterface get : (I)Ljava/lang/Object;
/*     */     //   89: checkcast java/lang/String
/*     */     //   92: astore #14
/*     */     //   94: aload #12
/*     */     //   96: aload #10
/*     */     //   98: ifnonnull -> 189
/*     */     //   101: aload #14
/*     */     //   103: aload #10
/*     */     //   105: ifnonnull -> 162
/*     */     //   108: goto -> 122
/*     */     //   111: ldc2_w -3444530953783124733
/*     */     //   114: lload #6
/*     */     //   116: <illegal opcode> w : (Ljava/lang/RuntimeException;JJ)Ljava/lang/RuntimeException;
/*     */     //   121: athrow
/*     */     //   122: ifnull -> 165
/*     */     //   125: goto -> 139
/*     */     //   128: ldc2_w -3444530953783124733
/*     */     //   131: lload #6
/*     */     //   133: <illegal opcode> w : (Ljava/lang/RuntimeException;JJ)Ljava/lang/RuntimeException;
/*     */     //   138: athrow
/*     */     //   139: lload #8
/*     */     //   141: aload #14
/*     */     //   143: iload #5
/*     */     //   145: invokestatic a : (JLjava/lang/String;Z)Ljava/lang/String;
/*     */     //   148: goto -> 162
/*     */     //   151: ldc2_w -3444530953783124733
/*     */     //   154: lload #6
/*     */     //   156: <illegal opcode> w : (Ljava/lang/RuntimeException;JJ)Ljava/lang/RuntimeException;
/*     */     //   161: athrow
/*     */     //   162: goto -> 166
/*     */     //   165: aconst_null
/*     */     //   166: invokeinterface add : (Ljava/lang/Object;)Z
/*     */     //   171: pop
/*     */     //   172: iinc #13, 1
/*     */     //   175: aload #10
/*     */     //   177: ifnull -> 74
/*     */     //   180: aload #12
/*     */     //   182: iload_3
/*     */     //   183: iflt -> 89
/*     */     //   186: invokestatic unmodifiableList : (Ljava/util/List;)Ljava/util/List;
/*     */     //   189: areturn
/*     */     // Line number table:
/*     */     //   Java source line number -> byte code offset
/*     */     //   #113	-> 50
/*     */     //   #2	-> 60
/*     */     //   #182	-> 71
/*     */     //   #103	-> 81
/*     */     //   #43	-> 94
/*     */     //   #157	-> 172
/*     */     //   #195	-> 180
/*     */     // Exception table:
/*     */     //   from	to	target	type
/*     */     //   94	108	111	java/lang/RuntimeException
/*     */     //   101	125	128	java/lang/RuntimeException
/*     */     //   122	148	151	java/lang/RuntimeException } @Nullable public String a(int paramInt1, int paramInt2, short paramShort, String paramString) { // Byte code:
/*     */     //   0: iload_1
/*     */     //   1: i2l
/*     */     //   2: bipush #32
/*     */     //   4: lshl
/*     */     //   5: iload_2
/*     */     //   6: i2l
/*     */     //   7: bipush #48
/*     */     //   9: lshl
/*     */     //   10: bipush #32
/*     */     //   12: lushr
/*     */     //   13: lor
/*     */     //   14: iload_3
/*     */     //   15: i2l
/*     */     //   16: bipush #48
/*     */     //   18: lshl
/*     */     //   19: bipush #48
/*     */     //   21: lushr
/*     */     //   22: lor
/*     */     //   23: getstatic me/konsolas/aac/l6.v : J
/*     */     //   26: lxor
/*     */     //   27: lstore #5
/*     */     //   29: ldc2_w 3276623563772997050
/*     */     //   32: lload #5
/*     */     //   34: <illegal opcode> w : (JJ)[Lme/konsolas/aac/aN;
/*     */     //   39: astore #7
/*     */     //   41: aload_0
/*     */     //   42: getfield j : Ljava/util/List;
/*     */     //   45: ifnonnull -> 61
/*     */     //   48: aconst_null
/*     */     //   49: areturn
/*     */     //   50: ldc2_w 3266790903400538212
/*     */     //   53: lload #5
/*     */     //   55: <illegal opcode> w : (Ljava/lang/RuntimeException;JJ)Ljava/lang/RuntimeException;
/*     */     //   60: athrow
/*     */     //   61: iconst_0
/*     */     //   62: istore #8
/*     */     //   64: aload_0
/*     */     //   65: getfield j : Ljava/util/List;
/*     */     //   68: invokeinterface size : ()I
/*     */     //   73: istore #9
/*     */     //   75: iload #8
/*     */     //   77: iload #9
/*     */     //   79: if_icmpge -> 163
/*     */     //   82: aload #4
/*     */     //   84: aload #7
/*     */     //   86: iload_3
/*     */     //   87: ifgt -> 104
/*     */     //   90: ifnonnull -> 154
/*     */     //   93: aload_0
/*     */     //   94: getfield j : Ljava/util/List;
/*     */     //   97: iload #8
/*     */     //   99: invokeinterface get : (I)Ljava/lang/Object;
/*     */     //   104: invokevirtual equals : (Ljava/lang/Object;)Z
/*     */     //   107: ifeq -> 155
/*     */     //   110: goto -> 124
/*     */     //   113: ldc2_w 3266790903400538212
/*     */     //   116: lload #5
/*     */     //   118: <illegal opcode> w : (Ljava/lang/RuntimeException;JJ)Ljava/lang/RuntimeException;
/*     */     //   123: athrow
/*     */     //   124: aload_0
/*     */     //   125: getfield j : Ljava/util/List;
/*     */     //   128: iload #8
/*     */     //   130: iconst_1
/*     */     //   131: iadd
/*     */     //   132: invokeinterface get : (I)Ljava/lang/Object;
/*     */     //   137: checkcast java/lang/String
/*     */     //   140: goto -> 154
/*     */     //   143: ldc2_w 3266790903400538212
/*     */     //   146: lload #5
/*     */     //   148: <illegal opcode> w : (Ljava/lang/RuntimeException;JJ)Ljava/lang/RuntimeException;
/*     */     //   153: athrow
/*     */     //   154: areturn
/*     */     //   155: iinc #8, 2
/*     */     //   158: aload #7
/*     */     //   160: ifnull -> 75
/*     */     //   163: iload_1
/*     */     //   164: iflt -> 82
/*     */     //   167: aconst_null
/*     */     //   168: areturn
/*     */     // Line number table:
/*     */     //   Java source line number -> byte code offset
/*     */     //   #116	-> 41
/*     */     //   #95	-> 61
/*     */     //   #125	-> 82
/*     */     //   #84	-> 124
/*     */     //   #229	-> 155
/*     */     //   #209	-> 163
/*     */     // Exception table:
/*     */     //   from	to	target	type
/*     */     //   41	50	50	java/lang/RuntimeException
/*     */     //   82	110	113	java/lang/RuntimeException
/*     */     //   93	140	143	java/lang/RuntimeException } static String a(short paramShort, String paramString, int paramInt1, int paramInt2, long paramLong, boolean paramBoolean) { // Byte code:
/*     */     //   0: iload_0
/*     */     //   1: i2l
/*     */     //   2: bipush #48
/*     */     //   4: lshl
/*     */     //   5: lload #4
/*     */     //   7: bipush #16
/*     */     //   9: lshl
/*     */     //   10: bipush #16
/*     */     //   12: lushr
/*     */     //   13: lor
/*     */     //   14: getstatic me/konsolas/aac/l6.v : J
/*     */     //   17: lxor
/*     */     //   18: lstore #7
/*     */     //   20: lload #7
/*     */     //   22: dup2
/*     */     //   23: ldc2_w 108881630635651
/*     */     //   26: lxor
/*     */     //   27: dup2
/*     */     //   28: bipush #8
/*     */     //   30: lushr
/*     */     //   31: lstore #9
/*     */     //   33: dup2
/*     */     //   34: bipush #56
/*     */     //   36: lshl
/*     */     //   37: bipush #56
/*     */     //   39: lushr
/*     */     //   40: l2i
/*     */     //   41: istore #11
/*     */     //   43: pop2
/*     */     //   44: dup2
/*     */     //   45: ldc2_w 60856379116959
/*     */     //   48: lxor
/*     */     //   49: lstore #12
/*     */     //   51: dup2
/*     */     //   52: ldc2_w 21111652324851
/*     */     //   55: lxor
/*     */     //   56: lstore #14
/*     */     //   58: pop2
/*     */     //   59: ldc2_w -6216108501346702983
/*     */     //   62: lload #7
/*     */     //   64: <illegal opcode> w : (JJ)[Lme/konsolas/aac/aN;
/*     */     //   69: iload_2
/*     */     //   70: istore #17
/*     */     //   72: astore #16
/*     */     //   74: iload #17
/*     */     //   76: iload_3
/*     */     //   77: if_icmpge -> 221
/*     */     //   80: aload_1
/*     */     //   81: iload_0
/*     */     //   82: iflt -> 234
/*     */     //   85: iload #17
/*     */     //   87: aload #16
/*     */     //   89: ifnonnull -> 230
/*     */     //   92: invokevirtual charAt : (I)C
/*     */     //   95: istore #18
/*     */     //   97: iload #18
/*     */     //   99: bipush #37
/*     */     //   101: aload #16
/*     */     //   103: ifnonnull -> 160
/*     */     //   106: if_icmpeq -> 168
/*     */     //   109: goto -> 123
/*     */     //   112: ldc2_w -6226529393883863897
/*     */     //   115: lload #7
/*     */     //   117: <illegal opcode> w : (Ljava/lang/RuntimeException;JJ)Ljava/lang/RuntimeException;
/*     */     //   122: athrow
/*     */     //   123: iload #18
/*     */     //   125: aload #16
/*     */     //   127: ifnonnull -> 165
/*     */     //   130: goto -> 144
/*     */     //   133: ldc2_w -6226529393883863897
/*     */     //   136: lload #7
/*     */     //   138: <illegal opcode> w : (Ljava/lang/RuntimeException;JJ)Ljava/lang/RuntimeException;
/*     */     //   143: athrow
/*     */     //   144: bipush #43
/*     */     //   146: goto -> 160
/*     */     //   149: ldc2_w -6226529393883863897
/*     */     //   152: lload #7
/*     */     //   154: <illegal opcode> w : (Ljava/lang/RuntimeException;JJ)Ljava/lang/RuntimeException;
/*     */     //   159: athrow
/*     */     //   160: if_icmpne -> 213
/*     */     //   163: iload #6
/*     */     //   165: ifeq -> 213
/*     */     //   168: new me/konsolas/aac/fw
/*     */     //   171: dup
/*     */     //   172: invokespecial <init> : ()V
/*     */     //   175: astore #19
/*     */     //   177: aload #19
/*     */     //   179: aload_1
/*     */     //   180: iload_2
/*     */     //   181: lload #14
/*     */     //   183: iload #17
/*     */     //   185: invokevirtual a : (Ljava/lang/String;IJI)Lme/konsolas/aac/fw;
/*     */     //   188: pop
/*     */     //   189: lload #9
/*     */     //   191: aload #19
/*     */     //   193: aload_1
/*     */     //   194: iload #17
/*     */     //   196: iload_3
/*     */     //   197: iload #11
/*     */     //   199: i2b
/*     */     //   200: iload #6
/*     */     //   202: invokestatic a : (JLme/konsolas/aac/fw;Ljava/lang/String;IIBZ)V
/*     */     //   205: aload #19
/*     */     //   207: lload #12
/*     */     //   209: invokevirtual c : (J)Ljava/lang/String;
/*     */     //   212: areturn
/*     */     //   213: iinc #17, 1
/*     */     //   216: aload #16
/*     */     //   218: ifnull -> 74
/*     */     //   221: aload_1
/*     */     //   222: lload #4
/*     */     //   224: lconst_0
/*     */     //   225: lcmp
/*     */     //   226: ifle -> 81
/*     */     //   229: iload_2
/*     */     //   230: iload_3
/*     */     //   231: invokevirtual substring : (II)Ljava/lang/String;
/*     */     //   234: areturn
/*     */     // Line number table:
/*     */     //   Java source line number -> byte code offset
/*     */     //   #121	-> 69
/*     */     //   #155	-> 80
/*     */     //   #148	-> 97
/*     */     //   #50	-> 168
/*     */     //   #159	-> 177
/*     */     //   #128	-> 189
/*     */     //   #68	-> 205
/*     */     //   #136	-> 213
/*     */     //   #213	-> 221
/*     */     // Exception table:
/*     */     //   from	to	target	type
/*     */     //   97	109	112	java/lang/RuntimeException
/*     */     //   106	130	133	java/lang/RuntimeException
/*     */     //   123	146	149	java/lang/RuntimeException } public String b(int paramInt, long paramLong) { // Byte code:
/*     */     //   0: getstatic me/konsolas/aac/l6.v : J
/*     */     //   3: lload_2
/*     */     //   4: lxor
/*     */     //   5: lstore_2
/*     */     //   6: ldc2_w 3777651403266340014
/*     */     //   9: lload_2
/*     */     //   10: <illegal opcode> w : (JJ)[Lme/konsolas/aac/aN;
/*     */     //   15: astore #4
/*     */     //   17: aload_0
/*     */     //   18: getfield j : Ljava/util/List;
/*     */     //   21: aload #4
/*     */     //   23: ifnonnull -> 74
/*     */     //   26: ifnonnull -> 60
/*     */     //   29: goto -> 42
/*     */     //   32: ldc2_w 3765562541959657840
/*     */     //   35: lload_2
/*     */     //   36: <illegal opcode> w : (Ljava/lang/RuntimeException;JJ)Ljava/lang/RuntimeException;
/*     */     //   41: athrow
/*     */     //   42: new java/lang/IndexOutOfBoundsException
/*     */     //   45: dup
/*     */     //   46: invokespecial <init> : ()V
/*     */     //   49: athrow
/*     */     //   50: ldc2_w 3765562541959657840
/*     */     //   53: lload_2
/*     */     //   54: <illegal opcode> w : (Ljava/lang/RuntimeException;JJ)Ljava/lang/RuntimeException;
/*     */     //   59: athrow
/*     */     //   60: aload_0
/*     */     //   61: getfield j : Ljava/util/List;
/*     */     //   64: iload_1
/*     */     //   65: iconst_2
/*     */     //   66: imul
/*     */     //   67: iconst_1
/*     */     //   68: iadd
/*     */     //   69: invokeinterface get : (I)Ljava/lang/Object;
/*     */     //   74: checkcast java/lang/String
/*     */     //   77: areturn
/*     */     // Line number table:
/*     */     //   Java source line number -> byte code offset
/*     */     //   #123	-> 17
/*     */     //   #223	-> 60
/*     */     // Exception table:
/*     */     //   from	to	target	type
/*     */     //   17	29	32	java/lang/RuntimeException
/*     */     //   26	50	50	java/lang/RuntimeException } public Set a(char paramChar, int paramInt, short paramShort) { // Byte code:
/*     */     //   0: iload_1
/*     */     //   1: i2l
/*     */     //   2: bipush #48
/*     */     //   4: lshl
/*     */     //   5: iload_2
/*     */     //   6: i2l
/*     */     //   7: bipush #32
/*     */     //   9: lshl
/*     */     //   10: bipush #16
/*     */     //   12: lushr
/*     */     //   13: lor
/*     */     //   14: iload_3
/*     */     //   15: i2l
/*     */     //   16: bipush #48
/*     */     //   18: lshl
/*     */     //   19: bipush #48
/*     */     //   21: lushr
/*     */     //   22: lor
/*     */     //   23: getstatic me/konsolas/aac/l6.v : J
/*     */     //   26: lxor
/*     */     //   27: lstore #4
/*     */     //   29: ldc2_w -8499997750727636277
/*     */     //   32: lload #4
/*     */     //   34: <illegal opcode> w : (JJ)[Lme/konsolas/aac/aN;
/*     */     //   39: astore #6
/*     */     //   41: aload_0
/*     */     //   42: getfield j : Ljava/util/List;
/*     */     //   45: ifnonnull -> 63
/*     */     //   48: invokestatic emptySet : ()Ljava/util/Set;
/*     */     //   51: areturn
/*     */     //   52: ldc2_w -8492399298104457451
/*     */     //   55: lload #4
/*     */     //   57: <illegal opcode> w : (Ljava/lang/RuntimeException;JJ)Ljava/lang/RuntimeException;
/*     */     //   62: athrow
/*     */     //   63: new java/util/LinkedHashSet
/*     */     //   66: dup
/*     */     //   67: invokespecial <init> : ()V
/*     */     //   70: astore #7
/*     */     //   72: iconst_0
/*     */     //   73: istore #8
/*     */     //   75: aload_0
/*     */     //   76: getfield j : Ljava/util/List;
/*     */     //   79: invokeinterface size : ()I
/*     */     //   84: istore #9
/*     */     //   86: iload #8
/*     */     //   88: iload #9
/*     */     //   90: if_icmpge -> 150
/*     */     //   93: aload #7
/*     */     //   95: aload #6
/*     */     //   97: iload_2
/*     */     //   98: ifle -> 115
/*     */     //   101: ifnonnull -> 155
/*     */     //   104: aload_0
/*     */     //   105: getfield j : Ljava/util/List;
/*     */     //   108: iload #8
/*     */     //   110: invokeinterface get : (I)Ljava/lang/Object;
/*     */     //   115: checkcast java/lang/String
/*     */     //   118: invokeinterface add : (Ljava/lang/Object;)Z
/*     */     //   123: pop
/*     */     //   124: iinc #8, 2
/*     */     //   127: aload #6
/*     */     //   129: ifnull -> 86
/*     */     //   132: iload_3
/*     */     //   133: iflt -> 93
/*     */     //   136: goto -> 150
/*     */     //   139: ldc2_w -8492399298104457451
/*     */     //   142: lload #4
/*     */     //   144: <illegal opcode> w : (Ljava/lang/RuntimeException;JJ)Ljava/lang/RuntimeException;
/*     */     //   149: athrow
/*     */     //   150: aload #7
/*     */     //   152: invokestatic unmodifiableSet : (Ljava/util/Set;)Ljava/util/Set;
/*     */     //   155: areturn
/*     */     // Line number table:
/*     */     //   Java source line number -> byte code offset
/*     */     //   #129	-> 41
/*     */     //   #42	-> 63
/*     */     //   #162	-> 72
/*     */     //   #89	-> 93
/*     */     //   #82	-> 124
/*     */     //   #126	-> 150
/*     */     // Exception table:
/*     */     //   from	to	target	type
/*     */     //   41	52	52	java/lang/RuntimeException
/*     */     //   93	132	139	java/lang/RuntimeException } static void a(long paramLong, StringBuilder paramStringBuilder, List paramList) { // Byte code:
/*     */     //   0: getstatic me/konsolas/aac/l6.v : J
/*     */     //   3: lload_0
/*     */     //   4: lxor
/*     */     //   5: lstore_0
/*     */     //   6: iconst_0
/*     */     //   7: istore #5
/*     */     //   9: ldc2_w 352834708440876071
/*     */     //   12: lload_0
/*     */     //   13: <illegal opcode> w : (JJ)[Lme/konsolas/aac/aN;
/*     */     //   18: aload_3
/*     */     //   19: invokeinterface size : ()I
/*     */     //   24: istore #6
/*     */     //   26: astore #4
/*     */     //   28: iload #5
/*     */     //   30: iload #6
/*     */     //   32: if_icmpge -> 66
/*     */     //   35: aload_2
/*     */     //   36: bipush #47
/*     */     //   38: invokevirtual append : (C)Ljava/lang/StringBuilder;
/*     */     //   41: pop
/*     */     //   42: aload_2
/*     */     //   43: aload_3
/*     */     //   44: iload #5
/*     */     //   46: invokeinterface get : (I)Ljava/lang/Object;
/*     */     //   51: checkcast java/lang/String
/*     */     //   54: invokevirtual append : (Ljava/lang/String;)Ljava/lang/StringBuilder;
/*     */     //   57: pop
/*     */     //   58: iinc #5, 1
/*     */     //   61: aload #4
/*     */     //   63: ifnull -> 28
/*     */     //   66: lload_0
/*     */     //   67: lconst_0
/*     */     //   68: lcmp
/*     */     //   69: iflt -> 61
/*     */     //   72: return
/*     */     // Line number table:
/*     */     //   Java source line number -> byte code offset
/*     */     //   #130	-> 6
/*     */     //   #18	-> 35
/*     */     //   #37	-> 42
/*     */     //   #165	-> 58
/*     */     //   #214	-> 66 } public static l6 c(String paramString, long paramLong) { paramLong = v ^ paramLong; long l1 = paramLong ^ 0x6EC6782FF1F1L, l2 = paramLong ^ 0x1E90F936FA9CL; return (new j5()).a((l6)null, l1, paramString).a(l2); } public boolean a(long paramLong) { // Byte code:
/*     */     //   0: getstatic me/konsolas/aac/l6.v : J
/*     */     //   3: lload_1
/*     */     //   4: lxor
/*     */     //   5: lstore_1
/*     */     //   6: aload_0
/*     */     //   7: getfield m : Ljava/lang/String;
/*     */     //   10: sipush #12268
/*     */     //   13: ldc2_w 6931542890421547167
/*     */     //   16: lload_1
/*     */     //   17: lxor
/*     */     //   18: <illegal opcode> y : (IJ)Ljava/lang/String;
/*     */     //   23: invokevirtual equals : (Ljava/lang/Object;)Z
/*     */     //   26: ireturn
/*     */     // Line number table:
/*     */     //   Java source line number -> byte code offset
/* 147 */     //   #139	-> 6 } static { long l; byte b1; for (c = "", v = nc.a(-3418989362855552194L, 6687855318502646766L, MethodHandles.lookup().lookupClass()).a(120814989704381L), y = new HashMap<>(13), l = v ^ 0x7C2471CD4C29L, "?".toCharArray()[14] = (char)("?".toCharArray()[14] ^ 0x553F), "".toCharArray()[1] = (char)("".toCharArray()[1] ^ 0x1119), (new byte[8])[0] = (byte)(int)(l >>> 56L), b1 = 1; b1 < 8; ) { (new byte[8])[b1] = (byte)(int)(l << b1 * 8 >>> 56L); b1++; }  Cipher cipher; (cipher = Cipher.getInstance(fW$gy.A("?".toCharArray(), (short)30255, true, 4))).init(2, SecretKeyFactory.getInstance(fW$gy.A("".toCharArray(), (short)25300, false, 5)).generateSecret(new DESKeySpec(new byte[8])), new IvParameterSpec(new byte[8])); String[] arrayOfString = new String[18]; boolean bool = false; "?????????".toCharArray()[351] = (char)("?????????".toCharArray()[351] ^ 0x64E6); String str; int i = (str = fW$gy.A("?????????".toCharArray(), (short)16201, true, 1)).length(); byte b2 = 16; byte b = -1;
/*     */     while (true); }
/*     */ 
/*     */ 
/*     */   
/*     */   @Nullable
/*     */   public String g(long paramLong) {
/*     */     // Byte code:
/*     */     //   0: getstatic me/konsolas/aac/l6.v : J
/*     */     //   3: lload_1
/*     */     //   4: lxor
/*     */     //   5: lstore_1
/*     */     //   6: ldc2_w -3098286867015281214
/*     */     //   9: lload_1
/*     */     //   10: <illegal opcode> w : (JJ)[Lme/konsolas/aac/aN;
/*     */     //   15: astore_3
/*     */     //   16: aload_0
/*     */     //   17: getfield h : Ljava/lang/String;
/*     */     //   20: aload_3
/*     */     //   21: ifnonnull -> 56
/*     */     //   24: ifnonnull -> 52
/*     */     //   27: goto -> 40
/*     */     //   30: ldc2_w -3085614167189858276
/*     */     //   33: lload_1
/*     */     //   34: <illegal opcode> w : (Ljava/lang/RuntimeException;JJ)Ljava/lang/RuntimeException;
/*     */     //   39: athrow
/*     */     //   40: aconst_null
/*     */     //   41: areturn
/*     */     //   42: ldc2_w -3085614167189858276
/*     */     //   45: lload_1
/*     */     //   46: <illegal opcode> w : (Ljava/lang/RuntimeException;JJ)Ljava/lang/RuntimeException;
/*     */     //   51: athrow
/*     */     //   52: aload_0
/*     */     //   53: getfield b : Ljava/lang/String;
/*     */     //   56: bipush #35
/*     */     //   58: invokevirtual indexOf : (I)I
/*     */     //   61: iconst_1
/*     */     //   62: iadd
/*     */     //   63: istore #4
/*     */     //   65: aload_0
/*     */     //   66: getfield b : Ljava/lang/String;
/*     */     //   69: iload #4
/*     */     //   71: invokevirtual substring : (I)Ljava/lang/String;
/*     */     //   74: areturn
/*     */     // Line number table:
/*     */     //   Java source line number -> byte code offset
/*     */     //   #151	-> 16
/*     */     //   #64	-> 52
/*     */     //   #232	-> 65
/*     */     // Exception table:
/*     */     //   from	to	target	type
/*     */     //   16	27	30	java/lang/RuntimeException
/*     */     //   24	42	42	java/lang/RuntimeException
/*     */   }
/*     */ 
/*     */   
/*     */   @Nullable
/*     */   public l6 a(long paramLong, String paramString) {
/*     */     // Byte code:
/*     */     //   0: getstatic me/konsolas/aac/l6.v : J
/*     */     //   3: lload_1
/*     */     //   4: lxor
/*     */     //   5: lstore_1
/*     */     //   6: lload_1
/*     */     //   7: dup2
/*     */     //   8: ldc2_w 31883585827329
/*     */     //   11: lxor
/*     */     //   12: dup2
/*     */     //   13: bipush #16
/*     */     //   15: lushr
/*     */     //   16: lstore #4
/*     */     //   18: dup2
/*     */     //   19: bipush #48
/*     */     //   21: lshl
/*     */     //   22: bipush #48
/*     */     //   24: lushr
/*     */     //   25: l2i
/*     */     //   26: istore #6
/*     */     //   28: pop2
/*     */     //   29: dup2
/*     */     //   30: ldc2_w 69613722703819
/*     */     //   33: lxor
/*     */     //   34: lstore #7
/*     */     //   36: pop2
/*     */     //   37: ldc2_w 5283202530389412243
/*     */     //   40: lload_1
/*     */     //   41: <illegal opcode> w : (JJ)[Lme/konsolas/aac/aN;
/*     */     //   46: aload_0
/*     */     //   47: lload #4
/*     */     //   49: iload #6
/*     */     //   51: i2s
/*     */     //   52: aload_3
/*     */     //   53: invokevirtual a : (JSLjava/lang/String;)Lme/konsolas/aac/j5;
/*     */     //   56: astore #10
/*     */     //   58: astore #9
/*     */     //   60: aload #10
/*     */     //   62: aload #9
/*     */     //   64: ifnonnull -> 85
/*     */     //   67: ifnull -> 93
/*     */     //   70: goto -> 83
/*     */     //   73: ldc2_w 5295294678444917837
/*     */     //   76: lload_1
/*     */     //   77: <illegal opcode> w : (Ljava/lang/RuntimeException;JJ)Ljava/lang/RuntimeException;
/*     */     //   82: athrow
/*     */     //   83: aload #10
/*     */     //   85: lload #7
/*     */     //   87: invokevirtual a : (J)Lme/konsolas/aac/l6;
/*     */     //   90: goto -> 94
/*     */     //   93: aconst_null
/*     */     //   94: areturn
/*     */     // Line number table:
/*     */     //   Java source line number -> byte code offset
/*     */     //   #163	-> 46
/*     */     //   #52	-> 60
/*     */     // Exception table:
/*     */     //   from	to	target	type
/*     */     //   60	70	73	java/lang/RuntimeException
/*     */   }
/*     */   
/*     */   static String a(long paramLong, String paramString, boolean paramBoolean) {
/* 164 */     paramLong = v ^ paramLong; int i = (int)((paramLong ^ 0x655F900CC94EL) >>> 48L); long l = (paramLong ^ 0x655F900CC94EL) << 16L >>> 16L; paramLong ^ 0x655F900CC94EL; return a((short)i, paramString, 0, paramString.length(), l, paramBoolean);
/*     */   }
/*     */ 
/*     */   
/*     */   public String b(long paramLong) {
/*     */     // Byte code:
/*     */     //   0: getstatic me/konsolas/aac/l6.v : J
/*     */     //   3: lload_1
/*     */     //   4: lxor
/*     */     //   5: lstore_1
/*     */     //   6: ldc2_w -1675470201763338115
/*     */     //   9: lload_1
/*     */     //   10: <illegal opcode> w : (JJ)[Lme/konsolas/aac/aN;
/*     */     //   15: astore_3
/*     */     //   16: aload_0
/*     */     //   17: getfield i : Ljava/lang/String;
/*     */     //   20: invokevirtual isEmpty : ()Z
/*     */     //   23: aload_3
/*     */     //   24: ifnonnull -> 76
/*     */     //   27: ifeq -> 56
/*     */     //   30: goto -> 43
/*     */     //   33: ldc2_w -1688121453577017949
/*     */     //   36: lload_1
/*     */     //   37: <illegal opcode> w : (Ljava/lang/RuntimeException;JJ)Ljava/lang/RuntimeException;
/*     */     //   42: athrow
/*     */     //   43: ldc ''
/*     */     //   45: areturn
/*     */     //   46: ldc2_w -1688121453577017949
/*     */     //   49: lload_1
/*     */     //   50: <illegal opcode> w : (Ljava/lang/RuntimeException;JJ)Ljava/lang/RuntimeException;
/*     */     //   55: athrow
/*     */     //   56: aload_0
/*     */     //   57: getfield b : Ljava/lang/String;
/*     */     //   60: bipush #58
/*     */     //   62: aload_0
/*     */     //   63: getfield m : Ljava/lang/String;
/*     */     //   66: invokevirtual length : ()I
/*     */     //   69: iconst_3
/*     */     //   70: iadd
/*     */     //   71: invokevirtual indexOf : (II)I
/*     */     //   74: iconst_1
/*     */     //   75: iadd
/*     */     //   76: istore #4
/*     */     //   78: aload_0
/*     */     //   79: getfield b : Ljava/lang/String;
/*     */     //   82: bipush #64
/*     */     //   84: invokevirtual indexOf : (I)I
/*     */     //   87: istore #5
/*     */     //   89: aload_0
/*     */     //   90: getfield b : Ljava/lang/String;
/*     */     //   93: iload #4
/*     */     //   95: iload #5
/*     */     //   97: invokevirtual substring : (II)Ljava/lang/String;
/*     */     //   100: areturn
/*     */     // Line number table:
/*     */     //   Java source line number -> byte code offset
/*     */     //   #172	-> 16
/*     */     //   #207	-> 56
/*     */     //   #7	-> 78
/*     */     //   #216	-> 89
/*     */     // Exception table:
/*     */     //   from	to	target	type
/*     */     //   16	30	33	java/lang/RuntimeException
/*     */     //   27	46	46	java/lang/RuntimeException
/*     */   }
/*     */   
/*     */   static void a(fw paramfw, String paramString1, int paramInt1, long paramLong, int paramInt2, String paramString2, boolean paramBoolean1, boolean paramBoolean2, boolean paramBoolean3, boolean paramBoolean4, @Nullable Charset paramCharset) {
/*     */     // Byte code:
/*     */     //   0: getstatic me/konsolas/aac/l6.v : J
/*     */     //   3: lload_3
/*     */     //   4: lxor
/*     */     //   5: lstore_3
/*     */     //   6: lload_3
/*     */     //   7: dup2
/*     */     //   8: ldc2_w 91270828376463
/*     */     //   11: lxor
/*     */     //   12: lstore #12
/*     */     //   14: dup2
/*     */     //   15: ldc2_w 83534818004736
/*     */     //   18: lxor
/*     */     //   19: dup2
/*     */     //   20: bipush #32
/*     */     //   22: lushr
/*     */     //   23: l2i
/*     */     //   24: istore #14
/*     */     //   26: dup2
/*     */     //   27: bipush #32
/*     */     //   29: lshl
/*     */     //   30: bipush #48
/*     */     //   32: lushr
/*     */     //   33: l2i
/*     */     //   34: istore #15
/*     */     //   36: dup2
/*     */     //   37: bipush #48
/*     */     //   39: lshl
/*     */     //   40: bipush #48
/*     */     //   42: lushr
/*     */     //   43: l2i
/*     */     //   44: istore #16
/*     */     //   46: pop2
/*     */     //   47: dup2
/*     */     //   48: ldc2_w 89722516720882
/*     */     //   51: lxor
/*     */     //   52: dup2
/*     */     //   53: bipush #32
/*     */     //   55: lushr
/*     */     //   56: l2i
/*     */     //   57: istore #17
/*     */     //   59: dup2
/*     */     //   60: bipush #32
/*     */     //   62: lshl
/*     */     //   63: bipush #48
/*     */     //   65: lushr
/*     */     //   66: l2i
/*     */     //   67: istore #18
/*     */     //   69: dup2
/*     */     //   70: bipush #48
/*     */     //   72: lshl
/*     */     //   73: bipush #48
/*     */     //   75: lushr
/*     */     //   76: l2i
/*     */     //   77: istore #19
/*     */     //   79: pop2
/*     */     //   80: dup2
/*     */     //   81: ldc2_w 69215099611356
/*     */     //   84: lxor
/*     */     //   85: lstore #20
/*     */     //   87: dup2
/*     */     //   88: ldc2_w 54463548411602
/*     */     //   91: lxor
/*     */     //   92: lstore #22
/*     */     //   94: dup2
/*     */     //   95: ldc2_w 548094250663
/*     */     //   98: lxor
/*     */     //   99: dup2
/*     */     //   100: bipush #32
/*     */     //   102: lushr
/*     */     //   103: l2i
/*     */     //   104: istore #24
/*     */     //   106: dup2
/*     */     //   107: bipush #32
/*     */     //   109: lshl
/*     */     //   110: bipush #48
/*     */     //   112: lushr
/*     */     //   113: l2i
/*     */     //   114: istore #25
/*     */     //   116: dup2
/*     */     //   117: bipush #48
/*     */     //   119: lshl
/*     */     //   120: bipush #48
/*     */     //   122: lushr
/*     */     //   123: l2i
/*     */     //   124: istore #26
/*     */     //   126: pop2
/*     */     //   127: dup2
/*     */     //   128: ldc2_w 79519608304039
/*     */     //   131: lxor
/*     */     //   132: lstore #27
/*     */     //   134: pop2
/*     */     //   135: ldc2_w 5095420479500011124
/*     */     //   138: lload_3
/*     */     //   139: <illegal opcode> w : (JJ)[Lme/konsolas/aac/aN;
/*     */     //   144: aconst_null
/*     */     //   145: astore #30
/*     */     //   147: astore #29
/*     */     //   149: iload_2
/*     */     //   150: istore #32
/*     */     //   152: iload #32
/*     */     //   154: iload #5
/*     */     //   156: if_icmpge -> 1185
/*     */     //   159: aload_1
/*     */     //   160: iload #32
/*     */     //   162: invokevirtual codePointAt : (I)I
/*     */     //   165: istore #31
/*     */     //   167: iload #7
/*     */     //   169: aload #29
/*     */     //   171: ifnonnull -> 380
/*     */     //   174: ifeq -> 378
/*     */     //   177: goto -> 190
/*     */     //   180: ldc2_w 5087817623323724714
/*     */     //   183: lload_3
/*     */     //   184: <illegal opcode> w : (Ljava/lang/RuntimeException;JJ)Ljava/lang/RuntimeException;
/*     */     //   189: athrow
/*     */     //   190: iload #31
/*     */     //   192: bipush #9
/*     */     //   194: aload #29
/*     */     //   196: ifnonnull -> 1177
/*     */     //   199: goto -> 212
/*     */     //   202: ldc2_w 5087817623323724714
/*     */     //   205: lload_3
/*     */     //   206: <illegal opcode> w : (Ljava/lang/RuntimeException;JJ)Ljava/lang/RuntimeException;
/*     */     //   211: athrow
/*     */     //   212: lload_3
/*     */     //   213: lconst_0
/*     */     //   214: lcmp
/*     */     //   215: iflt -> 1174
/*     */     //   218: if_icmpeq -> 1170
/*     */     //   221: goto -> 234
/*     */     //   224: ldc2_w 5087817623323724714
/*     */     //   227: lload_3
/*     */     //   228: <illegal opcode> w : (Ljava/lang/RuntimeException;JJ)Ljava/lang/RuntimeException;
/*     */     //   233: athrow
/*     */     //   234: iload #31
/*     */     //   236: bipush #10
/*     */     //   238: aload #29
/*     */     //   240: ifnonnull -> 1177
/*     */     //   243: goto -> 256
/*     */     //   246: ldc2_w 5087817623323724714
/*     */     //   249: lload_3
/*     */     //   250: <illegal opcode> w : (Ljava/lang/RuntimeException;JJ)Ljava/lang/RuntimeException;
/*     */     //   255: athrow
/*     */     //   256: lload_3
/*     */     //   257: lconst_0
/*     */     //   258: lcmp
/*     */     //   259: ifle -> 1174
/*     */     //   262: if_icmpeq -> 1170
/*     */     //   265: goto -> 278
/*     */     //   268: ldc2_w 5087817623323724714
/*     */     //   271: lload_3
/*     */     //   272: <illegal opcode> w : (Ljava/lang/RuntimeException;JJ)Ljava/lang/RuntimeException;
/*     */     //   277: athrow
/*     */     //   278: iload #31
/*     */     //   280: lload_3
/*     */     //   281: lconst_0
/*     */     //   282: lcmp
/*     */     //   283: iflt -> 1178
/*     */     //   286: bipush #12
/*     */     //   288: aload #29
/*     */     //   290: ifnonnull -> 1177
/*     */     //   293: goto -> 306
/*     */     //   296: ldc2_w 5087817623323724714
/*     */     //   299: lload_3
/*     */     //   300: <illegal opcode> w : (Ljava/lang/RuntimeException;JJ)Ljava/lang/RuntimeException;
/*     */     //   305: athrow
/*     */     //   306: lload_3
/*     */     //   307: lconst_0
/*     */     //   308: lcmp
/*     */     //   309: iflt -> 1174
/*     */     //   312: if_icmpeq -> 1170
/*     */     //   315: goto -> 328
/*     */     //   318: ldc2_w 5087817623323724714
/*     */     //   321: lload_3
/*     */     //   322: <illegal opcode> w : (Ljava/lang/RuntimeException;JJ)Ljava/lang/RuntimeException;
/*     */     //   327: athrow
/*     */     //   328: iload #31
/*     */     //   330: bipush #13
/*     */     //   332: aload #29
/*     */     //   334: lload_3
/*     */     //   335: lconst_0
/*     */     //   336: lcmp
/*     */     //   337: ifle -> 384
/*     */     //   340: ifnonnull -> 382
/*     */     //   343: goto -> 356
/*     */     //   346: ldc2_w 5087817623323724714
/*     */     //   349: lload_3
/*     */     //   350: <illegal opcode> w : (Ljava/lang/RuntimeException;JJ)Ljava/lang/RuntimeException;
/*     */     //   355: athrow
/*     */     //   356: if_icmpne -> 378
/*     */     //   359: goto -> 372
/*     */     //   362: ldc2_w 5087817623323724714
/*     */     //   365: lload_3
/*     */     //   366: <illegal opcode> w : (Ljava/lang/RuntimeException;JJ)Ljava/lang/RuntimeException;
/*     */     //   371: athrow
/*     */     //   372: lload_3
/*     */     //   373: lconst_0
/*     */     //   374: lcmp
/*     */     //   375: ifgt -> 1170
/*     */     //   378: iload #31
/*     */     //   380: bipush #43
/*     */     //   382: aload #29
/*     */     //   384: lload_3
/*     */     //   385: lconst_0
/*     */     //   386: lcmp
/*     */     //   387: ifle -> 559
/*     */     //   390: ifnonnull -> 557
/*     */     //   393: if_icmpne -> 540
/*     */     //   396: goto -> 409
/*     */     //   399: ldc2_w 5087817623323724714
/*     */     //   402: lload_3
/*     */     //   403: <illegal opcode> w : (Ljava/lang/RuntimeException;JJ)Ljava/lang/RuntimeException;
/*     */     //   408: athrow
/*     */     //   409: iload #9
/*     */     //   411: aload #29
/*     */     //   413: ifnonnull -> 555
/*     */     //   416: goto -> 429
/*     */     //   419: ldc2_w 5087817623323724714
/*     */     //   422: lload_3
/*     */     //   423: <illegal opcode> w : (Ljava/lang/RuntimeException;JJ)Ljava/lang/RuntimeException;
/*     */     //   428: athrow
/*     */     //   429: lload_3
/*     */     //   430: lconst_0
/*     */     //   431: lcmp
/*     */     //   432: iflt -> 542
/*     */     //   435: ifeq -> 540
/*     */     //   438: goto -> 451
/*     */     //   441: ldc2_w 5087817623323724714
/*     */     //   444: lload_3
/*     */     //   445: <illegal opcode> w : (Ljava/lang/RuntimeException;JJ)Ljava/lang/RuntimeException;
/*     */     //   450: athrow
/*     */     //   451: aload_0
/*     */     //   452: iload #7
/*     */     //   454: lload_3
/*     */     //   455: lconst_0
/*     */     //   456: lcmp
/*     */     //   457: iflt -> 517
/*     */     //   460: ifeq -> 514
/*     */     //   463: goto -> 476
/*     */     //   466: ldc2_w 5087817623323724714
/*     */     //   469: lload_3
/*     */     //   470: <illegal opcode> w : (Ljava/lang/RuntimeException;JJ)Ljava/lang/RuntimeException;
/*     */     //   475: athrow
/*     */     //   476: ldc_w ''
/*     */     //   479: invokevirtual toCharArray : ()[C
/*     */     //   482: dup
/*     */     //   483: dup
/*     */     //   484: iconst_0
/*     */     //   485: dup_x1
/*     */     //   486: caload
/*     */     //   487: sipush #31300
/*     */     //   490: ixor
/*     */     //   491: i2c
/*     */     //   492: castore
/*     */     //   493: sipush #6464
/*     */     //   496: iconst_1
/*     */     //   497: iconst_5
/*     */     //   498: invokestatic A : (Ljava/lang/Object;SZI)Ljava/lang/String;
/*     */     //   501: goto -> 527
/*     */     //   504: ldc2_w 5087817623323724714
/*     */     //   507: lload_3
/*     */     //   508: <illegal opcode> w : (Ljava/lang/RuntimeException;JJ)Ljava/lang/RuntimeException;
/*     */     //   513: athrow
/*     */     //   514: sipush #25848
/*     */     //   517: ldc2_w 1666421873366330570
/*     */     //   520: lload_3
/*     */     //   521: lxor
/*     */     //   522: <illegal opcode> y : (IJ)Ljava/lang/String;
/*     */     //   527: lload #27
/*     */     //   529: dup2_x1
/*     */     //   530: pop2
/*     */     //   531: invokevirtual a : (JLjava/lang/String;)Lme/konsolas/aac/fw;
/*     */     //   534: pop
/*     */     //   535: aload #29
/*     */     //   537: ifnull -> 1170
/*     */     //   540: iload #31
/*     */     //   542: goto -> 555
/*     */     //   545: ldc2_w 5087817623323724714
/*     */     //   548: lload_3
/*     */     //   549: <illegal opcode> w : (Ljava/lang/RuntimeException;JJ)Ljava/lang/RuntimeException;
/*     */     //   554: athrow
/*     */     //   555: bipush #32
/*     */     //   557: aload #29
/*     */     //   559: lload_3
/*     */     //   560: lconst_0
/*     */     //   561: lcmp
/*     */     //   562: iflt -> 603
/*     */     //   565: ifnonnull -> 601
/*     */     //   568: if_icmplt -> 885
/*     */     //   571: goto -> 584
/*     */     //   574: ldc2_w 5087817623323724714
/*     */     //   577: lload_3
/*     */     //   578: <illegal opcode> w : (Ljava/lang/RuntimeException;JJ)Ljava/lang/RuntimeException;
/*     */     //   583: athrow
/*     */     //   584: iload #31
/*     */     //   586: bipush #127
/*     */     //   588: goto -> 601
/*     */     //   591: ldc2_w 5087817623323724714
/*     */     //   594: lload_3
/*     */     //   595: <illegal opcode> w : (Ljava/lang/RuntimeException;JJ)Ljava/lang/RuntimeException;
/*     */     //   600: athrow
/*     */     //   601: aload #29
/*     */     //   603: lload_3
/*     */     //   604: lconst_0
/*     */     //   605: lcmp
/*     */     //   606: iflt -> 648
/*     */     //   609: ifnonnull -> 646
/*     */     //   612: if_icmpeq -> 885
/*     */     //   615: goto -> 628
/*     */     //   618: ldc2_w 5087817623323724714
/*     */     //   621: lload_3
/*     */     //   622: <illegal opcode> w : (Ljava/lang/RuntimeException;JJ)Ljava/lang/RuntimeException;
/*     */     //   627: athrow
/*     */     //   628: iload #31
/*     */     //   630: sipush #128
/*     */     //   633: goto -> 646
/*     */     //   636: ldc2_w 5087817623323724714
/*     */     //   639: lload_3
/*     */     //   640: <illegal opcode> w : (Ljava/lang/RuntimeException;JJ)Ljava/lang/RuntimeException;
/*     */     //   645: athrow
/*     */     //   646: aload #29
/*     */     //   648: lload_3
/*     */     //   649: lconst_0
/*     */     //   650: lcmp
/*     */     //   651: ifle -> 732
/*     */     //   654: ifnonnull -> 730
/*     */     //   657: if_icmplt -> 709
/*     */     //   660: goto -> 673
/*     */     //   663: ldc2_w 5087817623323724714
/*     */     //   666: lload_3
/*     */     //   667: <illegal opcode> w : (Ljava/lang/RuntimeException;JJ)Ljava/lang/RuntimeException;
/*     */     //   672: athrow
/*     */     //   673: iload #10
/*     */     //   675: aload #29
/*     */     //   677: ifnonnull -> 729
/*     */     //   680: goto -> 693
/*     */     //   683: ldc2_w 5087817623323724714
/*     */     //   686: lload_3
/*     */     //   687: <illegal opcode> w : (Ljava/lang/RuntimeException;JJ)Ljava/lang/RuntimeException;
/*     */     //   692: athrow
/*     */     //   693: ifne -> 885
/*     */     //   696: goto -> 709
/*     */     //   699: ldc2_w 5087817623323724714
/*     */     //   702: lload_3
/*     */     //   703: <illegal opcode> w : (Ljava/lang/RuntimeException;JJ)Ljava/lang/RuntimeException;
/*     */     //   708: athrow
/*     */     //   709: aload #6
/*     */     //   711: iload #31
/*     */     //   713: invokevirtual indexOf : (I)I
/*     */     //   716: goto -> 729
/*     */     //   719: ldc2_w 5087817623323724714
/*     */     //   722: lload_3
/*     */     //   723: <illegal opcode> w : (Ljava/lang/RuntimeException;JJ)Ljava/lang/RuntimeException;
/*     */     //   728: athrow
/*     */     //   729: iconst_m1
/*     */     //   730: aload #29
/*     */     //   732: ifnonnull -> 792
/*     */     //   735: if_icmpne -> 885
/*     */     //   738: goto -> 751
/*     */     //   741: ldc2_w 5087817623323724714
/*     */     //   744: lload_3
/*     */     //   745: <illegal opcode> w : (Ljava/lang/RuntimeException;JJ)Ljava/lang/RuntimeException;
/*     */     //   750: athrow
/*     */     //   751: iload #31
/*     */     //   753: aload #29
/*     */     //   755: lload_3
/*     */     //   756: lconst_0
/*     */     //   757: lcmp
/*     */     //   758: ifle -> 799
/*     */     //   761: ifnonnull -> 797
/*     */     //   764: goto -> 777
/*     */     //   767: ldc2_w 5087817623323724714
/*     */     //   770: lload_3
/*     */     //   771: <illegal opcode> w : (Ljava/lang/RuntimeException;JJ)Ljava/lang/RuntimeException;
/*     */     //   776: athrow
/*     */     //   777: bipush #37
/*     */     //   779: goto -> 792
/*     */     //   782: ldc2_w 5087817623323724714
/*     */     //   785: lload_3
/*     */     //   786: <illegal opcode> w : (Ljava/lang/RuntimeException;JJ)Ljava/lang/RuntimeException;
/*     */     //   791: athrow
/*     */     //   792: if_icmpne -> 1161
/*     */     //   795: iload #7
/*     */     //   797: aload #29
/*     */     //   799: lload_3
/*     */     //   800: lconst_0
/*     */     //   801: lcmp
/*     */     //   802: iflt -> 834
/*     */     //   805: ifnonnull -> 826
/*     */     //   808: ifeq -> 885
/*     */     //   811: goto -> 824
/*     */     //   814: ldc2_w 5087817623323724714
/*     */     //   817: lload_3
/*     */     //   818: <illegal opcode> w : (Ljava/lang/RuntimeException;JJ)Ljava/lang/RuntimeException;
/*     */     //   823: athrow
/*     */     //   824: iload #8
/*     */     //   826: lload_3
/*     */     //   827: lconst_0
/*     */     //   828: lcmp
/*     */     //   829: ifle -> 882
/*     */     //   832: aload #29
/*     */     //   834: ifnonnull -> 882
/*     */     //   837: ifeq -> 1161
/*     */     //   840: goto -> 853
/*     */     //   843: ldc2_w 5087817623323724714
/*     */     //   846: lload_3
/*     */     //   847: <illegal opcode> w : (Ljava/lang/RuntimeException;JJ)Ljava/lang/RuntimeException;
/*     */     //   852: athrow
/*     */     //   853: iload #17
/*     */     //   855: iload #18
/*     */     //   857: i2s
/*     */     //   858: aload_1
/*     */     //   859: iload #32
/*     */     //   861: iload #5
/*     */     //   863: iload #19
/*     */     //   865: i2c
/*     */     //   866: invokestatic a : (ISLjava/lang/String;IIC)Z
/*     */     //   869: goto -> 882
/*     */     //   872: ldc2_w 5087817623323724714
/*     */     //   875: lload_3
/*     */     //   876: <illegal opcode> w : (Ljava/lang/RuntimeException;JJ)Ljava/lang/RuntimeException;
/*     */     //   881: athrow
/*     */     //   882: ifne -> 1161
/*     */     //   885: aload #30
/*     */     //   887: aload #29
/*     */     //   889: ifnonnull -> 941
/*     */     //   892: goto -> 905
/*     */     //   895: ldc2_w 5087817623323724714
/*     */     //   898: lload_3
/*     */     //   899: <illegal opcode> w : (Ljava/lang/RuntimeException;JJ)Ljava/lang/RuntimeException;
/*     */     //   904: athrow
/*     */     //   905: ifnonnull -> 943
/*     */     //   908: goto -> 921
/*     */     //   911: ldc2_w 5087817623323724714
/*     */     //   914: lload_3
/*     */     //   915: <illegal opcode> w : (Ljava/lang/RuntimeException;JJ)Ljava/lang/RuntimeException;
/*     */     //   920: athrow
/*     */     //   921: new me/konsolas/aac/fw
/*     */     //   924: dup
/*     */     //   925: invokespecial <init> : ()V
/*     */     //   928: goto -> 941
/*     */     //   931: ldc2_w 5087817623323724714
/*     */     //   934: lload_3
/*     */     //   935: <illegal opcode> w : (Ljava/lang/RuntimeException;JJ)Ljava/lang/RuntimeException;
/*     */     //   940: athrow
/*     */     //   941: astore #30
/*     */     //   943: aload #11
/*     */     //   945: lload_3
/*     */     //   946: lconst_0
/*     */     //   947: lcmp
/*     */     //   948: iflt -> 974
/*     */     //   951: aload #29
/*     */     //   953: ifnonnull -> 974
/*     */     //   956: ifnull -> 983
/*     */     //   959: goto -> 972
/*     */     //   962: ldc2_w 5087817623323724714
/*     */     //   965: lload_3
/*     */     //   966: <illegal opcode> w : (Ljava/lang/RuntimeException;JJ)Ljava/lang/RuntimeException;
/*     */     //   971: athrow
/*     */     //   972: aload #11
/*     */     //   974: getstatic java/nio/charset/StandardCharsets.UTF_8 : Ljava/nio/charset/Charset;
/*     */     //   977: invokevirtual equals : (Ljava/lang/Object;)Z
/*     */     //   980: ifeq -> 1017
/*     */     //   983: aload #30
/*     */     //   985: lload #20
/*     */     //   987: iload #31
/*     */     //   989: invokevirtual d : (JI)Lme/konsolas/aac/fw;
/*     */     //   992: lload_3
/*     */     //   993: lconst_0
/*     */     //   994: lcmp
/*     */     //   995: ifle -> 1057
/*     */     //   998: pop
/*     */     //   999: aload #29
/*     */     //   1001: ifnull -> 1055
/*     */     //   1004: goto -> 1017
/*     */     //   1007: ldc2_w 5087817623323724714
/*     */     //   1010: lload_3
/*     */     //   1011: <illegal opcode> w : (Ljava/lang/RuntimeException;JJ)Ljava/lang/RuntimeException;
/*     */     //   1016: athrow
/*     */     //   1017: aload #30
/*     */     //   1019: iload #24
/*     */     //   1021: iload #25
/*     */     //   1023: iload #26
/*     */     //   1025: aload_1
/*     */     //   1026: iload #32
/*     */     //   1028: iload #32
/*     */     //   1030: iload #31
/*     */     //   1032: invokestatic charCount : (I)I
/*     */     //   1035: iadd
/*     */     //   1036: aload #11
/*     */     //   1038: invokevirtual a : (IIILjava/lang/String;IILjava/nio/charset/Charset;)Lme/konsolas/aac/fw;
/*     */     //   1041: pop
/*     */     //   1042: goto -> 1055
/*     */     //   1045: ldc2_w 5087817623323724714
/*     */     //   1048: lload_3
/*     */     //   1049: <illegal opcode> w : (Ljava/lang/RuntimeException;JJ)Ljava/lang/RuntimeException;
/*     */     //   1054: athrow
/*     */     //   1055: aload #30
/*     */     //   1057: iload #14
/*     */     //   1059: iload #15
/*     */     //   1061: i2c
/*     */     //   1062: iload #16
/*     */     //   1064: invokevirtual a : (ICI)Z
/*     */     //   1067: ifne -> 1170
/*     */     //   1070: aload #30
/*     */     //   1072: lload #22
/*     */     //   1074: invokevirtual a : (J)B
/*     */     //   1077: sipush #255
/*     */     //   1080: iand
/*     */     //   1081: istore #33
/*     */     //   1083: aload_0
/*     */     //   1084: bipush #37
/*     */     //   1086: lload #12
/*     */     //   1088: invokevirtual a : (IJ)Lme/konsolas/aac/fw;
/*     */     //   1091: pop
/*     */     //   1092: aload_0
/*     */     //   1093: getstatic me/konsolas/aac/l6.e : [C
/*     */     //   1096: iload #33
/*     */     //   1098: iconst_4
/*     */     //   1099: ishr
/*     */     //   1100: bipush #15
/*     */     //   1102: iand
/*     */     //   1103: caload
/*     */     //   1104: lload #12
/*     */     //   1106: invokevirtual a : (IJ)Lme/konsolas/aac/fw;
/*     */     //   1109: pop
/*     */     //   1110: aload_0
/*     */     //   1111: getstatic me/konsolas/aac/l6.e : [C
/*     */     //   1114: iload #33
/*     */     //   1116: bipush #15
/*     */     //   1118: iand
/*     */     //   1119: caload
/*     */     //   1120: lload #12
/*     */     //   1122: invokevirtual a : (IJ)Lme/konsolas/aac/fw;
/*     */     //   1125: pop
/*     */     //   1126: aload #29
/*     */     //   1128: lload_3
/*     */     //   1129: lconst_0
/*     */     //   1130: lcmp
/*     */     //   1131: ifle -> 1182
/*     */     //   1134: ifnonnull -> 1180
/*     */     //   1137: aload #29
/*     */     //   1139: ifnull -> 1055
/*     */     //   1142: lload_3
/*     */     //   1143: lconst_0
/*     */     //   1144: lcmp
/*     */     //   1145: ifle -> 1126
/*     */     //   1148: goto -> 1161
/*     */     //   1151: ldc2_w 5087817623323724714
/*     */     //   1154: lload_3
/*     */     //   1155: <illegal opcode> w : (Ljava/lang/RuntimeException;JJ)Ljava/lang/RuntimeException;
/*     */     //   1160: athrow
/*     */     //   1161: aload_0
/*     */     //   1162: lload #20
/*     */     //   1164: iload #31
/*     */     //   1166: invokevirtual d : (JI)Lme/konsolas/aac/fw;
/*     */     //   1169: pop
/*     */     //   1170: iload #32
/*     */     //   1172: iload #31
/*     */     //   1174: invokestatic charCount : (I)I
/*     */     //   1177: iadd
/*     */     //   1178: istore #32
/*     */     //   1180: aload #29
/*     */     //   1182: ifnull -> 152
/*     */     //   1185: return
/*     */     // Line number table:
/*     */     //   Java source line number -> byte code offset
/*     */     //   #178	-> 144
/*     */     //   #96	-> 149
/*     */     //   #48	-> 159
/*     */     //   #166	-> 167
/*     */     //   #112	-> 378
/*     */     //   #122	-> 451
/*     */     //   #115	-> 540
/*     */     //   #192	-> 713
/*     */     //   #117	-> 863
/*     */     //   #1	-> 885
/*     */     //   #228	-> 921
/*     */     //   #5	-> 943
/*     */     //   #200	-> 983
/*     */     //   #77	-> 1017
/*     */     //   #210	-> 1055
/*     */     //   #171	-> 1070
/*     */     //   #69	-> 1083
/*     */     //   #39	-> 1092
/*     */     //   #177	-> 1110
/*     */     //   #56	-> 1126
/*     */     //   #98	-> 1161
/*     */     //   #194	-> 1170
/*     */     //   #10	-> 1185
/*     */     // Exception table:
/*     */     //   from	to	target	type
/*     */     //   167	177	180	java/lang/RuntimeException
/*     */     //   174	199	202	java/lang/RuntimeException
/*     */     //   190	221	224	java/lang/RuntimeException
/*     */     //   212	243	246	java/lang/RuntimeException
/*     */     //   234	265	268	java/lang/RuntimeException
/*     */     //   256	293	296	java/lang/RuntimeException
/*     */     //   278	315	318	java/lang/RuntimeException
/*     */     //   306	343	346	java/lang/RuntimeException
/*     */     //   328	359	362	java/lang/RuntimeException
/*     */     //   382	396	399	java/lang/RuntimeException
/*     */     //   393	416	419	java/lang/RuntimeException
/*     */     //   409	438	441	java/lang/RuntimeException
/*     */     //   429	463	466	java/lang/RuntimeException
/*     */     //   451	504	504	java/lang/RuntimeException
/*     */     //   527	542	545	java/lang/RuntimeException
/*     */     //   557	571	574	java/lang/RuntimeException
/*     */     //   568	588	591	java/lang/RuntimeException
/*     */     //   601	615	618	java/lang/RuntimeException
/*     */     //   612	633	636	java/lang/RuntimeException
/*     */     //   646	660	663	java/lang/RuntimeException
/*     */     //   657	680	683	java/lang/RuntimeException
/*     */     //   673	696	699	java/lang/RuntimeException
/*     */     //   693	716	719	java/lang/RuntimeException
/*     */     //   730	738	741	java/lang/RuntimeException
/*     */     //   735	764	767	java/lang/RuntimeException
/*     */     //   751	779	782	java/lang/RuntimeException
/*     */     //   797	811	814	java/lang/RuntimeException
/*     */     //   826	840	843	java/lang/RuntimeException
/*     */     //   837	869	872	java/lang/RuntimeException
/*     */     //   882	892	895	java/lang/RuntimeException
/*     */     //   885	908	911	java/lang/RuntimeException
/*     */     //   905	928	931	java/lang/RuntimeException
/*     */     //   943	959	962	java/lang/RuntimeException
/*     */     //   974	1004	1007	java/lang/RuntimeException
/*     */     //   983	1042	1045	java/lang/RuntimeException
/*     */     //   1083	1142	1151	java/lang/RuntimeException
/*     */   }
/*     */   
/*     */   public int a(long paramLong) {
/*     */     // Byte code:
/*     */     //   0: getstatic me/konsolas/aac/l6.v : J
/*     */     //   3: lload_1
/*     */     //   4: lxor
/*     */     //   5: lstore_1
/*     */     //   6: ldc2_w 6920038618815357130
/*     */     //   9: lload_1
/*     */     //   10: <illegal opcode> w : (JJ)[Lme/konsolas/aac/aN;
/*     */     //   15: astore_3
/*     */     //   16: aload_0
/*     */     //   17: getfield j : Ljava/util/List;
/*     */     //   20: aload_3
/*     */     //   21: ifnonnull -> 57
/*     */     //   24: ifnull -> 67
/*     */     //   27: goto -> 40
/*     */     //   30: ldc2_w 6928212657313869076
/*     */     //   33: lload_1
/*     */     //   34: <illegal opcode> w : (Ljava/lang/RuntimeException;JJ)Ljava/lang/RuntimeException;
/*     */     //   39: athrow
/*     */     //   40: aload_0
/*     */     //   41: getfield j : Ljava/util/List;
/*     */     //   44: goto -> 57
/*     */     //   47: ldc2_w 6928212657313869076
/*     */     //   50: lload_1
/*     */     //   51: <illegal opcode> w : (Ljava/lang/RuntimeException;JJ)Ljava/lang/RuntimeException;
/*     */     //   56: athrow
/*     */     //   57: invokeinterface size : ()I
/*     */     //   62: iconst_2
/*     */     //   63: idiv
/*     */     //   64: goto -> 68
/*     */     //   67: iconst_0
/*     */     //   68: ireturn
/*     */     // Line number table:
/*     */     //   Java source line number -> byte code offset
/*     */     //   #180	-> 16
/*     */     // Exception table:
/*     */     //   from	to	target	type
/*     */     //   16	27	30	java/lang/RuntimeException
/*     */     //   24	44	47	java/lang/RuntimeException
/*     */   }
/*     */   
/*     */   public String e() {
/* 181 */     return this.t;
/*     */   }
/*     */ 
/*     */   
/*     */   l6(long paramLong, j5 paramj5) {
/*     */     // Byte code:
/*     */     //   0: getstatic me/konsolas/aac/l6.v : J
/*     */     //   3: lload_1
/*     */     //   4: lxor
/*     */     //   5: lstore_1
/*     */     //   6: lload_1
/*     */     //   7: dup2
/*     */     //   8: ldc2_w 116337133246791
/*     */     //   11: lxor
/*     */     //   12: dup2
/*     */     //   13: bipush #48
/*     */     //   15: lushr
/*     */     //   16: l2i
/*     */     //   17: istore #4
/*     */     //   19: dup2
/*     */     //   20: bipush #16
/*     */     //   22: lshl
/*     */     //   23: bipush #32
/*     */     //   25: lushr
/*     */     //   26: l2i
/*     */     //   27: istore #5
/*     */     //   29: dup2
/*     */     //   30: bipush #48
/*     */     //   32: lshl
/*     */     //   33: bipush #48
/*     */     //   35: lushr
/*     */     //   36: l2i
/*     */     //   37: istore #6
/*     */     //   39: pop2
/*     */     //   40: dup2
/*     */     //   41: ldc2_w 45845709459009
/*     */     //   44: lxor
/*     */     //   45: lstore #7
/*     */     //   47: dup2
/*     */     //   48: ldc2_w 18941427310370
/*     */     //   51: lxor
/*     */     //   52: lstore #9
/*     */     //   54: pop2
/*     */     //   55: aload_0
/*     */     //   56: invokespecial <init> : ()V
/*     */     //   59: ldc2_w 7977210491338976886
/*     */     //   62: lload_1
/*     */     //   63: <illegal opcode> w : (JJ)[Lme/konsolas/aac/aN;
/*     */     //   68: aload_0
/*     */     //   69: aload_3
/*     */     //   70: getfield c : Ljava/lang/String;
/*     */     //   73: putfield m : Ljava/lang/String;
/*     */     //   76: astore #11
/*     */     //   78: aload_0
/*     */     //   79: aload_3
/*     */     //   80: getfield f : Ljava/lang/String;
/*     */     //   83: lload #7
/*     */     //   85: dup2_x1
/*     */     //   86: pop2
/*     */     //   87: iconst_0
/*     */     //   88: invokestatic a : (JLjava/lang/String;Z)Ljava/lang/String;
/*     */     //   91: putfield t : Ljava/lang/String;
/*     */     //   94: aload_0
/*     */     //   95: aload_3
/*     */     //   96: getfield a : Ljava/lang/String;
/*     */     //   99: lload #7
/*     */     //   101: dup2_x1
/*     */     //   102: pop2
/*     */     //   103: iconst_0
/*     */     //   104: invokestatic a : (JLjava/lang/String;Z)Ljava/lang/String;
/*     */     //   107: putfield i : Ljava/lang/String;
/*     */     //   110: aload_0
/*     */     //   111: aload_3
/*     */     //   112: getfield g : Ljava/lang/String;
/*     */     //   115: putfield k : Ljava/lang/String;
/*     */     //   118: aload_0
/*     */     //   119: aload_3
/*     */     //   120: lload #9
/*     */     //   122: invokevirtual a : (J)I
/*     */     //   125: putfield s : I
/*     */     //   128: aload_0
/*     */     //   129: aload_0
/*     */     //   130: aload_3
/*     */     //   131: getfield i : Ljava/util/List;
/*     */     //   134: iload #4
/*     */     //   136: i2c
/*     */     //   137: iload #5
/*     */     //   139: iload #6
/*     */     //   141: i2s
/*     */     //   142: iconst_0
/*     */     //   143: invokespecial a : (Ljava/util/List;CISZ)Ljava/util/List;
/*     */     //   146: putfield l : Ljava/util/List;
/*     */     //   149: aload_0
/*     */     //   150: aload_3
/*     */     //   151: getfield h : Ljava/util/List;
/*     */     //   154: aload #11
/*     */     //   156: ifnonnull -> 205
/*     */     //   159: ifnull -> 208
/*     */     //   162: goto -> 175
/*     */     //   165: ldc2_w 7969577404130714536
/*     */     //   168: lload_1
/*     */     //   169: <illegal opcode> w : (Ljava/lang/RuntimeException;JJ)Ljava/lang/RuntimeException;
/*     */     //   174: athrow
/*     */     //   175: aload_0
/*     */     //   176: aload_3
/*     */     //   177: getfield h : Ljava/util/List;
/*     */     //   180: iload #4
/*     */     //   182: i2c
/*     */     //   183: iload #5
/*     */     //   185: iload #6
/*     */     //   187: i2s
/*     */     //   188: iconst_1
/*     */     //   189: invokespecial a : (Ljava/util/List;CISZ)Ljava/util/List;
/*     */     //   192: goto -> 205
/*     */     //   195: ldc2_w 7969577404130714536
/*     */     //   198: lload_1
/*     */     //   199: <illegal opcode> w : (Ljava/lang/RuntimeException;JJ)Ljava/lang/RuntimeException;
/*     */     //   204: athrow
/*     */     //   205: goto -> 209
/*     */     //   208: aconst_null
/*     */     //   209: putfield j : Ljava/util/List;
/*     */     //   212: aload_0
/*     */     //   213: aload_3
/*     */     //   214: getfield d : Ljava/lang/String;
/*     */     //   217: aload #11
/*     */     //   219: ifnonnull -> 263
/*     */     //   222: ifnull -> 266
/*     */     //   225: goto -> 238
/*     */     //   228: ldc2_w 7969577404130714536
/*     */     //   231: lload_1
/*     */     //   232: <illegal opcode> w : (Ljava/lang/RuntimeException;JJ)Ljava/lang/RuntimeException;
/*     */     //   237: athrow
/*     */     //   238: aload_3
/*     */     //   239: getfield d : Ljava/lang/String;
/*     */     //   242: lload #7
/*     */     //   244: dup2_x1
/*     */     //   245: pop2
/*     */     //   246: iconst_0
/*     */     //   247: invokestatic a : (JLjava/lang/String;Z)Ljava/lang/String;
/*     */     //   250: goto -> 263
/*     */     //   253: ldc2_w 7969577404130714536
/*     */     //   256: lload_1
/*     */     //   257: <illegal opcode> w : (Ljava/lang/RuntimeException;JJ)Ljava/lang/RuntimeException;
/*     */     //   262: athrow
/*     */     //   263: goto -> 267
/*     */     //   266: aconst_null
/*     */     //   267: putfield h : Ljava/lang/String;
/*     */     //   270: aload_0
/*     */     //   271: aload_3
/*     */     //   272: invokevirtual toString : ()Ljava/lang/String;
/*     */     //   275: putfield b : Ljava/lang/String;
/*     */     //   278: return
/*     */     // Line number table:
/*     */     //   Java source line number -> byte code offset
/*     */     //   #183	-> 55
/*     */     //   #186	-> 68
/*     */     //   #198	-> 78
/*     */     //   #135	-> 94
/*     */     //   #231	-> 110
/*     */     //   #49	-> 118
/*     */     //   #184	-> 128
/*     */     //   #176	-> 149
/*     */     //   #179	-> 175
/*     */     //   #20	-> 208
/*     */     //   #99	-> 212
/*     */     //   #187	-> 238
/*     */     //   #124	-> 266
/*     */     //   #4	-> 270
/*     */     //   #119	-> 278
/*     */     // Exception table:
/*     */     //   from	to	target	type
/*     */     //   78	162	165	java/lang/RuntimeException
/*     */     //   159	192	195	java/lang/RuntimeException
/*     */     //   209	225	228	java/lang/RuntimeException
/*     */     //   222	250	253	java/lang/RuntimeException
/*     */   }
/*     */   
/*     */   public List b()
/*     */   {
/* 191 */     return this.l; } @Nullable
/*     */   public j5 a(long paramLong, short paramShort, String paramString) {
/* 193 */     long l1 = (paramLong << 16L | paramShort << 48L >>> 48L) ^ v, l2 = l1 ^ 0xB0342BAC94BL; try { return (new j5()).a(this, l2, paramString); }
/*     */     catch (IllegalArgumentException illegalArgumentException)
/*     */     { return null; }
/*     */   
/*     */   }
/*     */ 
/*     */   
/*     */   public int c() {
/* 201 */     return this.s;
/*     */   }
/*     */ 
/*     */ 
/*     */ 
/*     */ 
/*     */   
/*     */   static List b(int paramInt1, String paramString, int paramInt2) {
/*     */     // Byte code:
/*     */     //   0: iload_0
/*     */     //   1: i2l
/*     */     //   2: bipush #32
/*     */     //   4: lshl
/*     */     //   5: iload_2
/*     */     //   6: i2l
/*     */     //   7: bipush #32
/*     */     //   9: lshl
/*     */     //   10: bipush #32
/*     */     //   12: lushr
/*     */     //   13: lor
/*     */     //   14: getstatic me/konsolas/aac/l6.v : J
/*     */     //   17: lxor
/*     */     //   18: lstore_3
/*     */     //   19: ldc2_w -3756358568672376036
/*     */     //   22: lload_3
/*     */     //   23: <illegal opcode> w : (JJ)[Lme/konsolas/aac/aN;
/*     */     //   28: new java/util/ArrayList
/*     */     //   31: dup
/*     */     //   32: invokespecial <init> : ()V
/*     */     //   35: astore #6
/*     */     //   37: iconst_0
/*     */     //   38: istore #7
/*     */     //   40: astore #5
/*     */     //   42: iload #7
/*     */     //   44: aload_1
/*     */     //   45: invokevirtual length : ()I
/*     */     //   48: if_icmpgt -> 276
/*     */     //   51: aload_1
/*     */     //   52: bipush #38
/*     */     //   54: iload #7
/*     */     //   56: invokevirtual indexOf : (II)I
/*     */     //   59: istore #8
/*     */     //   61: iload #8
/*     */     //   63: aload #5
/*     */     //   65: ifnonnull -> 99
/*     */     //   68: iconst_m1
/*     */     //   69: if_icmpne -> 91
/*     */     //   72: goto -> 85
/*     */     //   75: ldc2_w -3750472605308664126
/*     */     //   78: lload_3
/*     */     //   79: <illegal opcode> w : (Ljava/lang/RuntimeException;JJ)Ljava/lang/RuntimeException;
/*     */     //   84: athrow
/*     */     //   85: aload_1
/*     */     //   86: invokevirtual length : ()I
/*     */     //   89: istore #8
/*     */     //   91: aload_1
/*     */     //   92: bipush #61
/*     */     //   94: iload #7
/*     */     //   96: invokevirtual indexOf : (II)I
/*     */     //   99: istore #9
/*     */     //   101: iload #9
/*     */     //   103: iload_0
/*     */     //   104: iflt -> 208
/*     */     //   107: aload #5
/*     */     //   109: ifnonnull -> 208
/*     */     //   112: iconst_m1
/*     */     //   113: if_icmpeq -> 171
/*     */     //   116: goto -> 129
/*     */     //   119: ldc2_w -3750472605308664126
/*     */     //   122: lload_3
/*     */     //   123: <illegal opcode> w : (Ljava/lang/RuntimeException;JJ)Ljava/lang/RuntimeException;
/*     */     //   128: athrow
/*     */     //   129: iload #9
/*     */     //   131: aload #5
/*     */     //   133: ifnonnull -> 264
/*     */     //   136: goto -> 149
/*     */     //   139: ldc2_w -3750472605308664126
/*     */     //   142: lload_3
/*     */     //   143: <illegal opcode> w : (Ljava/lang/RuntimeException;JJ)Ljava/lang/RuntimeException;
/*     */     //   148: athrow
/*     */     //   149: iload_0
/*     */     //   150: ifle -> 251
/*     */     //   153: iload #8
/*     */     //   155: if_icmple -> 218
/*     */     //   158: goto -> 171
/*     */     //   161: ldc2_w -3750472605308664126
/*     */     //   164: lload_3
/*     */     //   165: <illegal opcode> w : (Ljava/lang/RuntimeException;JJ)Ljava/lang/RuntimeException;
/*     */     //   170: athrow
/*     */     //   171: aload #6
/*     */     //   173: aload_1
/*     */     //   174: iload #7
/*     */     //   176: iload #8
/*     */     //   178: invokevirtual substring : (II)Ljava/lang/String;
/*     */     //   181: invokeinterface add : (Ljava/lang/Object;)Z
/*     */     //   186: pop
/*     */     //   187: aload #6
/*     */     //   189: aconst_null
/*     */     //   190: invokeinterface add : (Ljava/lang/Object;)Z
/*     */     //   195: goto -> 208
/*     */     //   198: ldc2_w -3750472605308664126
/*     */     //   201: lload_3
/*     */     //   202: <illegal opcode> w : (Ljava/lang/RuntimeException;JJ)Ljava/lang/RuntimeException;
/*     */     //   207: athrow
/*     */     //   208: pop
/*     */     //   209: aload #5
/*     */     //   211: iload_0
/*     */     //   212: ifle -> 273
/*     */     //   215: ifnull -> 265
/*     */     //   218: aload #6
/*     */     //   220: aload_1
/*     */     //   221: iload #7
/*     */     //   223: iload #9
/*     */     //   225: invokevirtual substring : (II)Ljava/lang/String;
/*     */     //   228: invokeinterface add : (Ljava/lang/Object;)Z
/*     */     //   233: pop
/*     */     //   234: aload #6
/*     */     //   236: aload_1
/*     */     //   237: iload #9
/*     */     //   239: iconst_1
/*     */     //   240: iadd
/*     */     //   241: iload #8
/*     */     //   243: invokevirtual substring : (II)Ljava/lang/String;
/*     */     //   246: invokeinterface add : (Ljava/lang/Object;)Z
/*     */     //   251: goto -> 264
/*     */     //   254: ldc2_w -3750472605308664126
/*     */     //   257: lload_3
/*     */     //   258: <illegal opcode> w : (Ljava/lang/RuntimeException;JJ)Ljava/lang/RuntimeException;
/*     */     //   263: athrow
/*     */     //   264: pop
/*     */     //   265: iload #8
/*     */     //   267: iconst_1
/*     */     //   268: iadd
/*     */     //   269: istore #7
/*     */     //   271: aload #5
/*     */     //   273: ifnull -> 42
/*     */     //   276: aload #6
/*     */     //   278: areturn
/*     */     // Line number table:
/*     */     //   Java source line number -> byte code offset
/*     */     //   #203	-> 28
/*     */     //   #80	-> 37
/*     */     //   #127	-> 51
/*     */     //   #140	-> 61
/*     */     //   #38	-> 91
/*     */     //   #219	-> 101
/*     */     //   #44	-> 171
/*     */     //   #120	-> 187
/*     */     //   #71	-> 218
/*     */     //   #91	-> 234
/*     */     //   #153	-> 265
/*     */     //   #215	-> 271
/*     */     //   #17	-> 276
/*     */     // Exception table:
/*     */     //   from	to	target	type
/*     */     //   61	72	75	java/lang/RuntimeException
/*     */     //   101	116	119	java/lang/RuntimeException
/*     */     //   112	136	139	java/lang/RuntimeException
/*     */     //   129	158	161	java/lang/RuntimeException
/*     */     //   149	195	198	java/lang/RuntimeException
/*     */     //   208	251	254	java/lang/RuntimeException
/*     */   }
/*     */ 
/*     */ 
/*     */ 
/*     */ 
/*     */   
/*     */   public String a() {
/* 217 */     return this.i;
/*     */   }
/*     */   
/*     */   public static int a(String paramString, short paramShort, long paramLong) {
/*     */     // Byte code:
/*     */     //   0: iload_1
/*     */     //   1: i2l
/*     */     //   2: bipush #48
/*     */     //   4: lshl
/*     */     //   5: lload_2
/*     */     //   6: bipush #16
/*     */     //   8: lshl
/*     */     //   9: bipush #16
/*     */     //   11: lushr
/*     */     //   12: lor
/*     */     //   13: getstatic me/konsolas/aac/l6.v : J
/*     */     //   16: lxor
/*     */     //   17: lstore #4
/*     */     //   19: ldc2_w -1018165698535821028
/*     */     //   22: lload #4
/*     */     //   24: <illegal opcode> w : (JJ)[Lme/konsolas/aac/aN;
/*     */     //   29: astore #6
/*     */     //   31: aload_0
/*     */     //   32: sipush #17541
/*     */     //   35: ldc2_w 7512955169464548305
/*     */     //   38: lload #4
/*     */     //   40: lxor
/*     */     //   41: <illegal opcode> y : (IJ)Ljava/lang/String;
/*     */     //   46: invokevirtual equals : (Ljava/lang/Object;)Z
/*     */     //   49: aload #6
/*     */     //   51: ifnonnull -> 103
/*     */     //   54: ifeq -> 85
/*     */     //   57: goto -> 71
/*     */     //   60: ldc2_w -1012287984696853310
/*     */     //   63: lload #4
/*     */     //   65: <illegal opcode> w : (Ljava/lang/RuntimeException;JJ)Ljava/lang/RuntimeException;
/*     */     //   70: athrow
/*     */     //   71: bipush #80
/*     */     //   73: ireturn
/*     */     //   74: ldc2_w -1012287984696853310
/*     */     //   77: lload #4
/*     */     //   79: <illegal opcode> w : (Ljava/lang/RuntimeException;JJ)Ljava/lang/RuntimeException;
/*     */     //   84: athrow
/*     */     //   85: aload_0
/*     */     //   86: sipush #13164
/*     */     //   89: ldc2_w 831267835906526256
/*     */     //   92: lload #4
/*     */     //   94: lxor
/*     */     //   95: <illegal opcode> y : (IJ)Ljava/lang/String;
/*     */     //   100: invokevirtual equals : (Ljava/lang/Object;)Z
/*     */     //   103: aload #6
/*     */     //   105: ifnonnull -> 141
/*     */     //   108: ifeq -> 140
/*     */     //   111: goto -> 125
/*     */     //   114: ldc2_w -1012287984696853310
/*     */     //   117: lload #4
/*     */     //   119: <illegal opcode> w : (Ljava/lang/RuntimeException;JJ)Ljava/lang/RuntimeException;
/*     */     //   124: athrow
/*     */     //   125: sipush #443
/*     */     //   128: ireturn
/*     */     //   129: ldc2_w -1012287984696853310
/*     */     //   132: lload #4
/*     */     //   134: <illegal opcode> w : (Ljava/lang/RuntimeException;JJ)Ljava/lang/RuntimeException;
/*     */     //   139: athrow
/*     */     //   140: iconst_m1
/*     */     //   141: ireturn
/*     */     // Line number table:
/*     */     //   Java source line number -> byte code offset
/*     */     //   #224	-> 31
/*     */     //   #101	-> 71
/*     */     //   #107	-> 85
/*     */     //   #145	-> 125
/*     */     //   #79	-> 140
/*     */     // Exception table:
/*     */     //   from	to	target	type
/*     */     //   31	57	60	java/lang/RuntimeException
/*     */     //   54	74	74	java/lang/RuntimeException
/*     */     //   103	111	114	java/lang/RuntimeException
/*     */     //   108	129	129	java/lang/RuntimeException
/*     */   }
/*     */   
/*     */   public boolean equals(@Nullable Object paramObject) {
/*     */     // Byte code:
/*     */     //   0: getstatic me/konsolas/aac/l6.v : J
/*     */     //   3: ldc2_w 45412319353732
/*     */     //   6: lxor
/*     */     //   7: lstore_2
/*     */     //   8: ldc2_w 4363100317880695886
/*     */     //   11: lload_2
/*     */     //   12: <illegal opcode> w : (JJ)[Lme/konsolas/aac/aN;
/*     */     //   17: astore #4
/*     */     //   19: aload_1
/*     */     //   20: instanceof me/konsolas/aac/l6
/*     */     //   23: aload #4
/*     */     //   25: ifnonnull -> 71
/*     */     //   28: ifeq -> 96
/*     */     //   31: goto -> 44
/*     */     //   34: ldc2_w 4368991223564448144
/*     */     //   37: lload_2
/*     */     //   38: <illegal opcode> w : (Ljava/lang/RuntimeException;JJ)Ljava/lang/RuntimeException;
/*     */     //   43: athrow
/*     */     //   44: aload_1
/*     */     //   45: checkcast me/konsolas/aac/l6
/*     */     //   48: getfield b : Ljava/lang/String;
/*     */     //   51: aload_0
/*     */     //   52: getfield b : Ljava/lang/String;
/*     */     //   55: invokevirtual equals : (Ljava/lang/Object;)Z
/*     */     //   58: goto -> 71
/*     */     //   61: ldc2_w 4368991223564448144
/*     */     //   64: lload_2
/*     */     //   65: <illegal opcode> w : (Ljava/lang/RuntimeException;JJ)Ljava/lang/RuntimeException;
/*     */     //   70: athrow
/*     */     //   71: aload #4
/*     */     //   73: ifnonnull -> 93
/*     */     //   76: ifeq -> 96
/*     */     //   79: goto -> 92
/*     */     //   82: ldc2_w 4368991223564448144
/*     */     //   85: lload_2
/*     */     //   86: <illegal opcode> w : (Ljava/lang/RuntimeException;JJ)Ljava/lang/RuntimeException;
/*     */     //   91: athrow
/*     */     //   92: iconst_1
/*     */     //   93: goto -> 97
/*     */     //   96: iconst_0
/*     */     //   97: ireturn
/*     */     // Line number table:
/*     */     //   Java source line number -> byte code offset
/*     */     //   #225	-> 19
/*     */     // Exception table:
/*     */     //   from	to	target	type
/*     */     //   19	31	34	java/lang/RuntimeException
/*     */     //   28	58	61	java/lang/RuntimeException
/*     */     //   71	79	82	java/lang/RuntimeException
/*     */   }
/*     */   
/*     */   public String h(long paramLong) {
/*     */     // Byte code:
/*     */     //   0: getstatic me/konsolas/aac/l6.v : J
/*     */     //   3: lload_1
/*     */     //   4: lxor
/*     */     //   5: lstore_1
/*     */     //   6: lload_1
/*     */     //   7: dup2
/*     */     //   8: ldc2_w 89239885128327
/*     */     //   11: lxor
/*     */     //   12: lstore_3
/*     */     //   13: dup2
/*     */     //   14: ldc2_w 89170581200143
/*     */     //   17: lxor
/*     */     //   18: dup2
/*     */     //   19: bipush #16
/*     */     //   21: lushr
/*     */     //   22: lstore #5
/*     */     //   24: dup2
/*     */     //   25: bipush #48
/*     */     //   27: lshl
/*     */     //   28: bipush #48
/*     */     //   30: lushr
/*     */     //   31: l2i
/*     */     //   32: istore #7
/*     */     //   34: pop2
/*     */     //   35: dup2
/*     */     //   36: ldc2_w 126129904629957
/*     */     //   39: lxor
/*     */     //   40: lstore #8
/*     */     //   42: dup2
/*     */     //   43: ldc2_w 7161557724060
/*     */     //   46: lxor
/*     */     //   47: dup2
/*     */     //   48: bipush #32
/*     */     //   50: lushr
/*     */     //   51: l2i
/*     */     //   52: istore #10
/*     */     //   54: dup2
/*     */     //   55: bipush #32
/*     */     //   57: lshl
/*     */     //   58: bipush #32
/*     */     //   60: lushr
/*     */     //   61: l2i
/*     */     //   62: istore #11
/*     */     //   64: pop2
/*     */     //   65: pop2
/*     */     //   66: aload_0
/*     */     //   67: lload #5
/*     */     //   69: iload #7
/*     */     //   71: i2s
/*     */     //   72: sipush #25475
/*     */     //   75: ldc2_w 5657394931653233473
/*     */     //   78: lload_1
/*     */     //   79: lxor
/*     */     //   80: <illegal opcode> y : (IJ)Ljava/lang/String;
/*     */     //   85: invokevirtual a : (JSLjava/lang/String;)Lme/konsolas/aac/j5;
/*     */     //   88: ldc ''
/*     */     //   90: iload #10
/*     */     //   92: iload #11
/*     */     //   94: invokevirtual p : (Ljava/lang/String;II)Lme/konsolas/aac/j5;
/*     */     //   97: ldc ''
/*     */     //   99: lload_3
/*     */     //   100: invokevirtual b : (Ljava/lang/String;J)Lme/konsolas/aac/j5;
/*     */     //   103: lload #8
/*     */     //   105: invokevirtual a : (J)Lme/konsolas/aac/l6;
/*     */     //   108: invokevirtual toString : ()Ljava/lang/String;
/*     */     //   111: areturn
/*     */     // Line number table:
/*     */     //   Java source line number -> byte code offset
/*     */     //   #227	-> 66
/*     */     //   #78	-> 90
/*     */     //   #28	-> 99
/*     */     //   #54	-> 103
/*     */     //   #92	-> 108
/*     */     //   #206	-> 111
/*     */   }
/*     */   
/*     */   private static RuntimeException a(RuntimeException paramRuntimeException) {
/*     */     return paramRuntimeException;
/*     */   }
/*     */   
/*     */   private static String a(byte[] paramArrayOfbyte) {
/*     */     byte b1 = 0;
/*     */     int i;
/*     */     char[] arrayOfChar = new char[i = paramArrayOfbyte.length];
/*     */     for (byte b2 = 0; b2 < i; b2++) {
/*     */       int j;
/*     */       if ((j = 0xFF & paramArrayOfbyte[b2]) < 192) {
/*     */         arrayOfChar[b1++] = (char)j;
/*     */       } else if (j < 224) {
/*     */         char c = (char)((char)(j & 0x1F) << 6);
/*     */         j = paramArrayOfbyte[++b2];
/*     */         c = (char)(c | (char)(j & 0x3F));
/*     */         arrayOfChar[b1++] = c;
/*     */       } else if (b2 < i - 2) {
/*     */         char c = (char)((char)(j & 0xF) << 12);
/*     */         j = paramArrayOfbyte[++b2];
/*     */         c = (char)(c | (char)(j & 0x3F) << 6);
/*     */         j = paramArrayOfbyte[++b2];
/*     */         c = (char)(c | (char)(j & 0x3F));
/*     */         arrayOfChar[b1++] = c;
/*     */       } 
/*     */     } 
/*     */     return new String(arrayOfChar, 0, b1);
/*     */   }
/*     */   
/*     */   private static String a(int paramInt, long paramLong) {
/*     */     int i = paramInt ^ (int)(paramLong & 0x7FFFL) ^ 0x4E69;
/*     */     if (x[i] == null) {
/*     */       Object[] arrayOfObject;
/*     */       try {
/*     */         Long long_ = Long.valueOf(Thread.currentThread().getId());
/*     */         arrayOfObject = (Object[])y.get(long_);
/*     */         if (arrayOfObject == null) {
/*     */           arrayOfObject = new Object[3];
/*     */           "".toCharArray()[18] = (char)("".toCharArray()[18] ^ 0x6887);
/*     */           arrayOfObject[0] = Cipher.getInstance(hY$g6.H("".toCharArray(), (short)5784, (byte)1, (byte)3));
/*     */           "".toCharArray()[0] = (char)("".toCharArray()[0] ^ 0x46B6);
/*     */           arrayOfObject[1] = SecretKeyFactory.getInstance(hY$g6.H("".toCharArray(), (short)3379, (byte)2, (byte)4));
/*     */           arrayOfObject[2] = new IvParameterSpec(new byte[8]);
/*     */           y.put(long_, arrayOfObject);
/*     */         } 
/*     */       } catch (Exception exception) {
/*     */         "".toCharArray()[17] = (char)("".toCharArray()[17] ^ 0x56F7);
/*     */         throw new RuntimeException(hY$g6.H("".toCharArray(), (short)12346, (byte)5, (byte)5), exception);
/*     */       } 
/*     */       byte[] arrayOfByte1 = new byte[8];
/*     */       arrayOfByte1[0] = (byte)(int)(paramLong >>> 56L);
/*     */       for (byte b = 1; b < 8; b++)
/*     */         arrayOfByte1[b] = (byte)(int)(paramLong << b * 8 >>> 56L); 
/*     */       DESKeySpec dESKeySpec = new DESKeySpec(arrayOfByte1);
/*     */       SecretKey secretKey = ((SecretKeyFactory)arrayOfObject[1]).generateSecret(dESKeySpec);
/*     */       ((Cipher)arrayOfObject[0]).init(2, secretKey, (IvParameterSpec)arrayOfObject[2]);
/*     */       "".toCharArray()[8] = (char)("".toCharArray()[8] ^ 0x79F4);
/*     */       byte[] arrayOfByte2 = w[i].getBytes(hY$g6.H("".toCharArray(), (short)5595, (byte)1, (byte)5));
/*     */       x[i] = a(((Cipher)arrayOfObject[0]).doFinal(arrayOfByte2));
/*     */     } 
/*     */     return x[i];
/*     */   }
/*     */   
/*     */   private static Object a(MethodHandles.Lookup paramLookup, MutableCallSite paramMutableCallSite, String paramString, Object[] paramArrayOfObject) {
/*     */     int i = ((Integer)paramArrayOfObject[0]).intValue();
/*     */     long l = ((Long)paramArrayOfObject[1]).longValue();
/*     */     String str = a(i, l);
/*     */     MethodHandle methodHandle = MethodHandles.constant(String.class, str);
/*     */     paramMutableCallSite.setTarget(MethodHandles.dropArguments(methodHandle, 0, new Class[] { int.class, long.class }));
/*     */     return str;
/*     */   }
/*     */   
/*     */   private static CallSite a(MethodHandles.Lookup paramLookup, String paramString, MethodType paramMethodType) {
/*     */     // Byte code:
/*     */     //   0: new java/lang/invoke/MutableCallSite
/*     */     //   3: dup
/*     */     //   4: aload_2
/*     */     //   5: invokespecial <init> : (Ljava/lang/invoke/MethodType;)V
/*     */     //   8: astore_3
/*     */     //   9: aload_3
/*     */     //   10: ldc_w
/*     */     //   13: ldc_w [Ljava/lang/Object;
/*     */     //   16: aload_2
/*     */     //   17: invokevirtual parameterCount : ()I
/*     */     //   20: invokevirtual asCollector : (Ljava/lang/Class;I)Ljava/lang/invoke/MethodHandle;
/*     */     //   23: iconst_0
/*     */     //   24: iconst_3
/*     */     //   25: anewarray java/lang/Object
/*     */     //   28: dup
/*     */     //   29: iconst_0
/*     */     //   30: aload_0
/*     */     //   31: aastore
/*     */     //   32: dup
/*     */     //   33: iconst_1
/*     */     //   34: aload_3
/*     */     //   35: aastore
/*     */     //   36: dup
/*     */     //   37: iconst_2
/*     */     //   38: aload_1
/*     */     //   39: aastore
/*     */     //   40: invokestatic insertArguments : (Ljava/lang/invoke/MethodHandle;I[Ljava/lang/Object;)Ljava/lang/invoke/MethodHandle;
/*     */     //   43: aload_2
/*     */     //   44: invokestatic explicitCastArguments : (Ljava/lang/invoke/MethodHandle;Ljava/lang/invoke/MethodType;)Ljava/lang/invoke/MethodHandle;
/*     */     //   47: invokevirtual setTarget : (Ljava/lang/invoke/MethodHandle;)V
/*     */     //   50: goto -> 171
/*     */     //   53: astore #4
/*     */     //   55: new java/lang/RuntimeException
/*     */     //   58: dup
/*     */     //   59: new java/lang/StringBuilder
/*     */     //   62: dup
/*     */     //   63: invokespecial <init> : ()V
/*     */     //   66: ldc_w ''
/*     */     //   69: invokevirtual toCharArray : ()[C
/*     */     //   72: dup
/*     */     //   73: dup
/*     */     //   74: bipush #13
/*     */     //   76: dup_x1
/*     */     //   77: caload
/*     */     //   78: sipush #14776
/*     */     //   81: ixor
/*     */     //   82: i2c
/*     */     //   83: castore
/*     */     //   84: sipush #139
/*     */     //   87: iconst_0
/*     */     //   88: iconst_3
/*     */     //   89: invokestatic H : (Ljava/lang/Object;SBB)Ljava/lang/String;
/*     */     //   92: invokevirtual append : (Ljava/lang/String;)Ljava/lang/StringBuilder;
/*     */     //   95: ldc_w ''
/*     */     //   98: invokevirtual toCharArray : ()[C
/*     */     //   101: dup
/*     */     //   102: dup
/*     */     //   103: iconst_2
/*     */     //   104: dup_x1
/*     */     //   105: caload
/*     */     //   106: sipush #3975
/*     */     //   109: ixor
/*     */     //   110: i2c
/*     */     //   111: castore
/*     */     //   112: sipush #16584
/*     */     //   115: iconst_2
/*     */     //   116: iconst_4
/*     */     //   117: invokestatic H : (Ljava/lang/Object;SBB)Ljava/lang/String;
/*     */     //   120: invokevirtual append : (Ljava/lang/String;)Ljava/lang/StringBuilder;
/*     */     //   123: aload_1
/*     */     //   124: invokevirtual append : (Ljava/lang/String;)Ljava/lang/StringBuilder;
/*     */     //   127: ldc_w ''
/*     */     //   130: invokevirtual toCharArray : ()[C
/*     */     //   133: dup
/*     */     //   134: dup
/*     */     //   135: iconst_0
/*     */     //   136: dup_x1
/*     */     //   137: caload
/*     */     //   138: sipush #8519
/*     */     //   141: ixor
/*     */     //   142: i2c
/*     */     //   143: castore
/*     */     //   144: sipush #15781
/*     */     //   147: iconst_4
/*     */     //   148: iconst_4
/*     */     //   149: invokestatic H : (Ljava/lang/Object;SBB)Ljava/lang/String;
/*     */     //   152: invokevirtual append : (Ljava/lang/String;)Ljava/lang/StringBuilder;
/*     */     //   155: aload_2
/*     */     //   156: invokevirtual toString : ()Ljava/lang/String;
/*     */     //   159: invokevirtual append : (Ljava/lang/String;)Ljava/lang/StringBuilder;
/*     */     //   162: invokevirtual toString : ()Ljava/lang/String;
/*     */     //   165: aload #4
/*     */     //   167: invokespecial <init> : (Ljava/lang/String;Ljava/lang/Throwable;)V
/*     */     //   170: athrow
/*     */     //   171: aload_3
/*     */     //   172: areturn
/*     */     // Exception table:
/*     */     //   from	to	target	type
/*     */     //   9	50	53	java/lang/Exception
/*     */   } }


/* Location:              C:\Users\BukkitBypass\Desktop\MatrixAC\AAC\AAC-spigot-5.2.0.jar!\me\konsolas\aac\l6.class
 * Java compiler version: 8 (52.0)
 * JD-Core Version:       1.1.3
 */