/* 1 */ package me.konsolas.aac;class la implements InvocationHandler { la(List paramList) { this.a = paramList; }
/*   */ 
/*   */   
/*   */   private final List a;
/*   */   
/*   */   boolean c;
/*   */   String b;
/*   */   private static final long d = nc.a(5828835010808667662L, 6924027221959499408L, MethodHandles.lookup().lookupClass()).a(40657577805123L);
/*   */   private static final String[] e;
/*   */   private static final String[] f;
/*   */   private static final Map g = new HashMap<>(13);
/*   */   
/*   */   private static CallSite a(MethodHandles.Lookup paramLookup, String paramString, MethodType paramMethodType) {
/*   */     // Byte code:
/*   */     //   0: new java/lang/invoke/MutableCallSite
/*   */     //   3: dup
/*   */     //   4: aload_2
/*   */     //   5: invokespecial <init> : (Ljava/lang/invoke/MethodType;)V
/*   */     //   8: astore_3
/*   */     //   9: aload_3
/*   */     //   10: ldc_w
/*   */     //   13: ldc [Ljava/lang/Object;
/*   */     //   15: aload_2
/*   */     //   16: invokevirtual parameterCount : ()I
/*   */     //   19: invokevirtual asCollector : (Ljava/lang/Class;I)Ljava/lang/invoke/MethodHandle;
/*   */     //   22: iconst_0
/*   */     //   23: iconst_3
/*   */     //   24: anewarray java/lang/Object
/*   */     //   27: dup
/*   */     //   28: iconst_0
/*   */     //   29: aload_0
/*   */     //   30: aastore
/*   */     //   31: dup
/*   */     //   32: iconst_1
/*   */     //   33: aload_3
/*   */     //   34: aastore
/*   */     //   35: dup
/*   */     //   36: iconst_2
/*   */     //   37: aload_1
/*   */     //   38: aastore
/*   */     //   39: invokestatic insertArguments : (Ljava/lang/invoke/MethodHandle;I[Ljava/lang/Object;)Ljava/lang/invoke/MethodHandle;
/*   */     //   42: aload_2
/*   */     //   43: invokestatic explicitCastArguments : (Ljava/lang/invoke/MethodHandle;Ljava/lang/invoke/MethodType;)Ljava/lang/invoke/MethodHandle;
/*   */     //   46: invokevirtual setTarget : (Ljava/lang/invoke/MethodHandle;)V
/*   */     //   49: goto -> 170
/*   */     //   52: astore #4
/*   */     //   54: new java/lang/RuntimeException
/*   */     //   57: dup
/*   */     //   58: new java/lang/StringBuilder
/*   */     //   61: dup
/*   */     //   62: invokespecial <init> : ()V
/*   */     //   65: ldc_w 'ь볨鑄驱蕚뇭砂噆羄툔퉾見␲噟㌗凖汩ⷔ'
/*   */     //   68: invokevirtual toCharArray : ()[C
/*   */     //   71: dup
/*   */     //   72: dup
/*   */     //   73: bipush #8
/*   */     //   75: dup_x1
/*   */     //   76: caload
/*   */     //   77: sipush #10221
/*   */     //   80: ixor
/*   */     //   81: i2c
/*   */     //   82: castore
/*   */     //   83: sipush #24744
/*   */     //   86: iconst_3
/*   */     //   87: iconst_4
/*   */     //   88: invokestatic H : (Ljava/lang/Object;SBB)Ljava/lang/String;
/*   */     //   91: invokevirtual append : (Ljava/lang/String;)Ljava/lang/StringBuilder;
/*   */     //   94: ldc_w '힫⣆뾮娴'
/*   */     //   97: invokevirtual toCharArray : ()[C
/*   */     //   100: dup
/*   */     //   101: dup
/*   */     //   102: iconst_2
/*   */     //   103: dup_x1
/*   */     //   104: caload
/*   */     //   105: sipush #27423
/*   */     //   108: ixor
/*   */     //   109: i2c
/*   */     //   110: castore
/*   */     //   111: sipush #12424
/*   */     //   114: iconst_0
/*   */     //   115: iconst_5
/*   */     //   116: invokestatic H : (Ljava/lang/Object;SBB)Ljava/lang/String;
/*   */     //   119: invokevirtual append : (Ljava/lang/String;)Ljava/lang/StringBuilder;
/*   */     //   122: aload_1
/*   */     //   123: invokevirtual append : (Ljava/lang/String;)Ljava/lang/StringBuilder;
/*   */     //   126: ldc_w '㾳抪鏕䱓'
/*   */     //   129: invokevirtual toCharArray : ()[C
/*   */     //   132: dup
/*   */     //   133: dup
/*   */     //   134: iconst_0
/*   */     //   135: dup_x1
/*   */     //   136: caload
/*   */     //   137: sipush #516
/*   */     //   140: ixor
/*   */     //   141: i2c
/*   */     //   142: castore
/*   */     //   143: sipush #19005
/*   */     //   146: iconst_3
/*   */     //   147: iconst_2
/*   */     //   148: invokestatic H : (Ljava/lang/Object;SBB)Ljava/lang/String;
/*   */     //   151: invokevirtual append : (Ljava/lang/String;)Ljava/lang/StringBuilder;
/*   */     //   154: aload_2
/*   */     //   155: invokevirtual toString : ()Ljava/lang/String;
/*   */     //   158: invokevirtual append : (Ljava/lang/String;)Ljava/lang/StringBuilder;
/*   */     //   161: invokevirtual toString : ()Ljava/lang/String;
/*   */     //   164: aload #4
/*   */     //   166: invokespecial <init> : (Ljava/lang/String;Ljava/lang/Throwable;)V
/*   */     //   169: athrow
/*   */     //   170: aload_3
/*   */     //   171: areturn
/*   */     // Exception table:
/*   */     //   from	to	target	type
/*   */     //   9	49	52	java/lang/Exception
/*   */   }
/*   */   
/*   */   private static Object a(MethodHandles.Lookup paramLookup, MutableCallSite paramMutableCallSite, String paramString, Object[] paramArrayOfObject) {
/*   */     int i = ((Integer)paramArrayOfObject[0]).intValue();
/*   */     long l = ((Long)paramArrayOfObject[1]).longValue();
/*   */     String str = a(i, l);
/*   */     MethodHandle methodHandle = MethodHandles.constant(String.class, str);
/*   */     paramMutableCallSite.setTarget(MethodHandles.dropArguments(methodHandle, 0, new Class[] { int.class, long.class }));
/*   */     return str;
/*   */   }
/*   */   
/*   */   private static String a(int paramInt, long paramLong) {
/*   */     int i = paramInt ^ (int)(paramLong & 0x7FFFL) ^ 0x197C;
/*   */     if (f[i] == null) {
/*   */       Object[] arrayOfObject;
/*   */       try {
/*   */         Long long_ = Long.valueOf(Thread.currentThread().getId());
/*   */         arrayOfObject = (Object[])g.get(long_);
/*   */         if (arrayOfObject == null) {
/*   */           arrayOfObject = new Object[3];
/*   */           "몺뀎㡂闹槧竘薵뱔芉ඊ斅ꭋ몟㫵Ṳ洂Ê껎禛".toCharArray()[5] = (char)("몺뀎㡂闹槧竘薵뱔芉ඊ斅ꭋ몟㫵Ṳ洂Ê껎禛".toCharArray()[5] ^ 0x4588);
/*   */           arrayOfObject[0] = Cipher.getInstance(dP$dt.X("몺뀎㡂闹槧竘薵뱔芉ඊ斅ꭋ몟㫵Ṳ洂Ê껎禛".toCharArray(), (short)18892, false, false));
/*   */           "?﮵䤩ℷ".toCharArray()[0] = (char)("?﮵䤩ℷ".toCharArray()[0] ^ 0x16C5);
/*   */           arrayOfObject[1] = SecretKeyFactory.getInstance(dP$dt.X("?﮵䤩ℷ".toCharArray(), (short)2780, false, true));
/*   */           arrayOfObject[2] = new IvParameterSpec(new byte[8]);
/*   */           g.put(long_, arrayOfObject);
/*   */         } 
/*   */       } catch (Exception exception) {
/*   */         "蒓鸸騸༁ⷙ钟髄슰唚旵뎆쿠鵽逸ᢆ".toCharArray()[11] = (char)("蒓鸸騸༁ⷙ钟髄슰唚旵뎆쿠鵽逸ᢆ".toCharArray()[11] ^ 0x18F0);
/*   */         throw new RuntimeException(dP$dt.X("蒓鸸騸༁ⷙ钟髄슰唚旵뎆쿠鵽逸ᢆ".toCharArray(), (short)23623, false, true), exception);
/*   */       } 
/*   */       byte[] arrayOfByte1 = new byte[8];
/*   */       arrayOfByte1[0] = (byte)(int)(paramLong >>> 56L);
/*   */       for (byte b = 1; b < 8; b++)
/*   */         arrayOfByte1[b] = (byte)(int)(paramLong << b * 8 >>> 56L); 
/*   */       DESKeySpec dESKeySpec = new DESKeySpec(arrayOfByte1);
/*   */       SecretKey secretKey = ((SecretKeyFactory)arrayOfObject[1]).generateSecret(dESKeySpec);
/*   */       ((Cipher)arrayOfObject[0]).init(2, secretKey, (IvParameterSpec)arrayOfObject[2]);
/*   */       "इꖰ躌匚攣䧂켆꘧啦".toCharArray()[1] = (char)("इꖰ躌匚攣䧂켆꘧啦".toCharArray()[1] ^ 0x7DB9);
/*   */       byte[] arrayOfByte2 = e[i].getBytes(dP$dt.X("इꖰ躌匚攣䧂켆꘧啦".toCharArray(), (short)6686, true, true));
/*   */       f[i] = a(((Cipher)arrayOfObject[0]).doFinal(arrayOfByte2));
/*   */     } 
/*   */     return f[i];
/*   */   }
/*   */   
/*   */   private static String a(byte[] paramArrayOfbyte) {
/*   */     byte b1 = 0;
/*   */     int i;
/*   */     char[] arrayOfChar = new char[i = paramArrayOfbyte.length];
/*   */     for (byte b2 = 0; b2 < i; b2++) {
/*   */       int j;
/*   */       if ((j = 0xFF & paramArrayOfbyte[b2]) < 192) {
/*   */         arrayOfChar[b1++] = (char)j;
/*   */       } else if (j < 224) {
/*   */         char c = (char)((char)(j & 0x1F) << 6);
/*   */         j = paramArrayOfbyte[++b2];
/*   */         c = (char)(c | (char)(j & 0x3F));
/*   */         arrayOfChar[b1++] = c;
/*   */       } else if (b2 < i - 2) {
/*   */         char c = (char)((char)(j & 0xF) << 12);
/*   */         j = paramArrayOfbyte[++b2];
/*   */         c = (char)(c | (char)(j & 0x3F) << 6);
/*   */         j = paramArrayOfbyte[++b2];
/*   */         c = (char)(c | (char)(j & 0x3F));
/*   */         arrayOfChar[b1++] = c;
/*   */       } 
/*   */     } 
/*   */     return new String(arrayOfChar, 0, b1);
/*   */   }
/*   */   
/*   */   private static Throwable a(Throwable paramThrowable) {
/*   */     return paramThrowable;
/*   */   }
/*   */   
/*   */   static {
/*   */     long l = d ^ 0x7ADC61CE3C35L;
/*   */     "점仯?䕃㞆⻐剿愨⮊驸웈腢繺炖貘⍵䄎".toCharArray()[3] = (char)("점仯?䕃㞆⻐剿愨⮊驸웈腢繺炖貘⍵䄎".toCharArray()[3] ^ 0x69AF);
/*   */     "ꦓ궁鷦圅".toCharArray()[1] = (char)("ꦓ궁鷦圅".toCharArray()[1] ^ 0x40BF);
/*   */     (new byte[8])[0] = (byte)(int)(l >>> 56L);
/*   */     for (byte b1 = 1; b1 < 8; b1++)
/*   */       (new byte[8])[b1] = (byte)(int)(l << b1 * 8 >>> 56L); 
/*   */     Cipher cipher;
/*   */     (cipher = Cipher.getInstance(fW$gy.A("점仯?䕃㞆⻐剿愨⮊驸웈腢繺炖貘⍵䄎".toCharArray(), (short)8902, true, 5))).init(2, SecretKeyFactory.getInstance(fW$gy.A("ꦓ궁鷦圅".toCharArray(), (short)29884, false, 1)).generateSecret(new DESKeySpec(new byte[8])), new IvParameterSpec(new byte[8]));
/*   */     String[] arrayOfString = new String[7];
/*   */     boolean bool = false;
/*   */     "瓖鉘?㐝鐐?ꭜ⬞鑉厛➺懷䬼嬅ᾡ䨅蠄̢ꃬ㷩퍑ཻ‭ȝ諨ꡲ࠼㖃姘櫗唈椕υ匪疘ꖲ繳㶋롂࠘中緝ᴩ魽栶줾後喕ꀼ첛΁돣ࡤ݆峀隱涧餌숸?ῐ⍬唒཯疐ᮒ鸞ﰾᶹㅎὤ홴ვ껰뀸솑坚뿜銝腂ﶚ藠ꣾྺ澊霐ٚ㄰䳴﵍ꙩ鹠꜏া侽?︔⭳னᙍꜝ告ꠏ묓㰄࿄뙑艹촰ꥫ藕ផ鳻藭靧﹐ቷ롳אַ厠?⁙튯큡㉫峞緡딡ꡌ㍘".toCharArray()[18] = (char)("瓖鉘?㐝鐐?ꭜ⬞鑉厛➺懷䬼嬅ᾡ䨅蠄̢ꃬ㷩퍑ཻ‭ȝ諨ꡲ࠼㖃姘櫗唈椕υ匪疘ꖲ繳㶋롂࠘中緝ᴩ魽栶줾後喕ꀼ첛΁돣ࡤ݆峀隱涧餌숸?ῐ⍬唒཯疐ᮒ鸞ﰾᶹㅎὤ홴ვ껰뀸솑坚뿜銝腂ﶚ藠ꣾྺ澊霐ٚ㄰䳴﵍ꙩ鹠꜏া侽?︔⭳னᙍꜝ告ꠏ묓㰄࿄뙑艹촰ꥫ藕ផ鳻藭靧﹐ቷ롳אַ厠?⁙튯큡㉫峞緡딡ꡌ㍘".toCharArray()[18] ^ 0x277D);
/*   */     String str;
/*   */     int i = (str = fW$gy.A("瓖鉘?㐝鐐?ꭜ⬞鑉厛➺懷䬼嬅ᾡ䨅蠄̢ꃬ㷩퍑ཻ‭ȝ諨ꡲ࠼㖃姘櫗唈椕υ匪疘ꖲ繳㶋롂࠘中緝ᴩ魽栶줾後喕ꀼ첛΁돣ࡤ݆峀隱涧餌숸?ῐ⍬唒཯疐ᮒ鸞ﰾᶹㅎὤ홴ვ껰뀸솑坚뿜銝腂ﶚ藠ꣾྺ澊霐ٚ㄰䳴﵍ꙩ鹠꜏া侽?︔⭳னᙍꜝ告ꠏ묓㰄࿄뙑艹촰ꥫ藕ផ鳻藭靧﹐ቷ롳אַ厠?⁙튯큡㉫峞緡딡ꡌ㍘".toCharArray(), (short)21745, false, 0)).length();
/*   */     byte b2 = 24;
/*   */     byte b = -1;
/*   */     while (true);
/*   */   }
/*   */   
/*   */   public Object invoke(Object paramObject, Method paramMethod, Object[] paramArrayOfObject) {
/*   */     // Byte code:
/*   */     //   0: getstatic me/konsolas/aac/la.d : J
/*   */     //   3: ldc2_w 28853763264345
/*   */     //   6: lxor
/*   */     //   7: lstore #4
/*   */     //   9: aload_2
/*   */     //   10: invokevirtual getName : ()Ljava/lang/String;
/*   */     //   13: astore #7
/*   */     //   15: ldc2_w -392085917242102620
/*   */     //   18: lload #4
/*   */     //   20: <illegal opcode> w : (JJ)I
/*   */     //   25: aload_2
/*   */     //   26: invokevirtual getReturnType : ()Ljava/lang/Class;
/*   */     //   29: astore #8
/*   */     //   31: istore #6
/*   */     //   33: aload_3
/*   */     //   34: ifnonnull -> 41
/*   */     //   37: getstatic me/konsolas/aac/eO.g : [Ljava/lang/String;
/*   */     //   40: astore_3
/*   */     //   41: aload #7
/*   */     //   43: sipush #5852
/*   */     //   46: ldc2_w 5405990797795259895
/*   */     //   49: lload #4
/*   */     //   51: lxor
/*   */     //   52: <illegal opcode> s : (IJ)Ljava/lang/String;
/*   */     //   57: invokevirtual equals : (Ljava/lang/Object;)Z
/*   */     //   60: iload #6
/*   */     //   62: ifeq -> 139
/*   */     //   65: ifeq -> 120
/*   */     //   68: goto -> 82
/*   */     //   71: ldc2_w -328145205934294547
/*   */     //   74: lload #4
/*   */     //   76: <illegal opcode> w : (Ljava/lang/Throwable;JJ)Ljava/lang/Throwable;
/*   */     //   81: athrow
/*   */     //   82: getstatic java/lang/Boolean.TYPE : Ljava/lang/Class;
/*   */     //   85: aload #8
/*   */     //   87: if_acmpne -> 120
/*   */     //   90: goto -> 104
/*   */     //   93: ldc2_w -328145205934294547
/*   */     //   96: lload #4
/*   */     //   98: <illegal opcode> w : (Ljava/lang/Throwable;JJ)Ljava/lang/Throwable;
/*   */     //   103: athrow
/*   */     //   104: iconst_1
/*   */     //   105: invokestatic valueOf : (Z)Ljava/lang/Boolean;
/*   */     //   108: areturn
/*   */     //   109: ldc2_w -328145205934294547
/*   */     //   112: lload #4
/*   */     //   114: <illegal opcode> w : (Ljava/lang/Throwable;JJ)Ljava/lang/Throwable;
/*   */     //   119: athrow
/*   */     //   120: aload #7
/*   */     //   122: sipush #17686
/*   */     //   125: ldc2_w 6580315293287851578
/*   */     //   128: lload #4
/*   */     //   130: lxor
/*   */     //   131: <illegal opcode> s : (IJ)Ljava/lang/String;
/*   */     //   136: invokevirtual equals : (Ljava/lang/Object;)Z
/*   */     //   139: iload #6
/*   */     //   141: ifeq -> 220
/*   */     //   144: ifeq -> 201
/*   */     //   147: goto -> 161
/*   */     //   150: ldc2_w -328145205934294547
/*   */     //   153: lload #4
/*   */     //   155: <illegal opcode> w : (Ljava/lang/Throwable;JJ)Ljava/lang/Throwable;
/*   */     //   160: athrow
/*   */     //   161: getstatic java/lang/Void.TYPE : Ljava/lang/Class;
/*   */     //   164: aload #8
/*   */     //   166: if_acmpne -> 201
/*   */     //   169: goto -> 183
/*   */     //   172: ldc2_w -328145205934294547
/*   */     //   175: lload #4
/*   */     //   177: <illegal opcode> w : (Ljava/lang/Throwable;JJ)Ljava/lang/Throwable;
/*   */     //   182: athrow
/*   */     //   183: aload_0
/*   */     //   184: iconst_1
/*   */     //   185: putfield c : Z
/*   */     //   188: aconst_null
/*   */     //   189: areturn
/*   */     //   190: ldc2_w -328145205934294547
/*   */     //   193: lload #4
/*   */     //   195: <illegal opcode> w : (Ljava/lang/Throwable;JJ)Ljava/lang/Throwable;
/*   */     //   200: athrow
/*   */     //   201: aload #7
/*   */     //   203: sipush #22497
/*   */     //   206: ldc2_w 2209155672485606604
/*   */     //   209: lload #4
/*   */     //   211: lxor
/*   */     //   212: <illegal opcode> s : (IJ)Ljava/lang/String;
/*   */     //   217: invokevirtual equals : (Ljava/lang/Object;)Z
/*   */     //   220: iload #6
/*   */     //   222: ifeq -> 315
/*   */     //   225: ifeq -> 296
/*   */     //   228: goto -> 242
/*   */     //   231: ldc2_w -328145205934294547
/*   */     //   234: lload #4
/*   */     //   236: <illegal opcode> w : (Ljava/lang/Throwable;JJ)Ljava/lang/Throwable;
/*   */     //   241: athrow
/*   */     //   242: aload_3
/*   */     //   243: arraylength
/*   */     //   244: iload #6
/*   */     //   246: ifeq -> 315
/*   */     //   249: goto -> 263
/*   */     //   252: ldc2_w -328145205934294547
/*   */     //   255: lload #4
/*   */     //   257: <illegal opcode> w : (Ljava/lang/Throwable;JJ)Ljava/lang/Throwable;
/*   */     //   262: athrow
/*   */     //   263: ifne -> 296
/*   */     //   266: goto -> 280
/*   */     //   269: ldc2_w -328145205934294547
/*   */     //   272: lload #4
/*   */     //   274: <illegal opcode> w : (Ljava/lang/Throwable;JJ)Ljava/lang/Throwable;
/*   */     //   279: athrow
/*   */     //   280: aload_0
/*   */     //   281: getfield a : Ljava/util/List;
/*   */     //   284: areturn
/*   */     //   285: ldc2_w -328145205934294547
/*   */     //   288: lload #4
/*   */     //   290: <illegal opcode> w : (Ljava/lang/Throwable;JJ)Ljava/lang/Throwable;
/*   */     //   295: athrow
/*   */     //   296: aload #7
/*   */     //   298: sipush #24336
/*   */     //   301: ldc2_w 2488999982884961343
/*   */     //   304: lload #4
/*   */     //   306: lxor
/*   */     //   307: <illegal opcode> s : (IJ)Ljava/lang/String;
/*   */     //   312: invokevirtual equals : (Ljava/lang/Object;)Z
/*   */     //   315: iload #6
/*   */     //   317: ifeq -> 370
/*   */     //   320: ifne -> 392
/*   */     //   323: goto -> 337
/*   */     //   326: ldc2_w -328145205934294547
/*   */     //   329: lload #4
/*   */     //   331: <illegal opcode> w : (Ljava/lang/Throwable;JJ)Ljava/lang/Throwable;
/*   */     //   336: athrow
/*   */     //   337: aload #7
/*   */     //   339: sipush #16079
/*   */     //   342: ldc2_w 1259095710899920359
/*   */     //   345: lload #4
/*   */     //   347: lxor
/*   */     //   348: <illegal opcode> s : (IJ)Ljava/lang/String;
/*   */     //   353: invokevirtual equals : (Ljava/lang/Object;)Z
/*   */     //   356: goto -> 370
/*   */     //   359: ldc2_w -328145205934294547
/*   */     //   362: lload #4
/*   */     //   364: <illegal opcode> w : (Ljava/lang/Throwable;JJ)Ljava/lang/Throwable;
/*   */     //   369: athrow
/*   */     //   370: iload #6
/*   */     //   372: ifeq -> 652
/*   */     //   375: ifeq -> 633
/*   */     //   378: goto -> 392
/*   */     //   381: ldc2_w -328145205934294547
/*   */     //   384: lload #4
/*   */     //   386: <illegal opcode> w : (Ljava/lang/Throwable;JJ)Ljava/lang/Throwable;
/*   */     //   391: athrow
/*   */     //   392: ldc java/lang/String
/*   */     //   394: aload #8
/*   */     //   396: if_acmpne -> 633
/*   */     //   399: goto -> 413
/*   */     //   402: ldc2_w -328145205934294547
/*   */     //   405: lload #4
/*   */     //   407: <illegal opcode> w : (Ljava/lang/Throwable;JJ)Ljava/lang/Throwable;
/*   */     //   412: athrow
/*   */     //   413: aload_3
/*   */     //   414: arraylength
/*   */     //   415: iload #6
/*   */     //   417: ifeq -> 652
/*   */     //   420: goto -> 434
/*   */     //   423: ldc2_w -328145205934294547
/*   */     //   426: lload #4
/*   */     //   428: <illegal opcode> w : (Ljava/lang/Throwable;JJ)Ljava/lang/Throwable;
/*   */     //   433: athrow
/*   */     //   434: iconst_1
/*   */     //   435: if_icmpne -> 633
/*   */     //   438: goto -> 452
/*   */     //   441: ldc2_w -328145205934294547
/*   */     //   444: lload #4
/*   */     //   446: <illegal opcode> w : (Ljava/lang/Throwable;JJ)Ljava/lang/Throwable;
/*   */     //   451: athrow
/*   */     //   452: aload_3
/*   */     //   453: iconst_0
/*   */     //   454: aaload
/*   */     //   455: instanceof java/util/List
/*   */     //   458: iload #6
/*   */     //   460: ifeq -> 652
/*   */     //   463: goto -> 477
/*   */     //   466: ldc2_w -328145205934294547
/*   */     //   469: lload #4
/*   */     //   471: <illegal opcode> w : (Ljava/lang/Throwable;JJ)Ljava/lang/Throwable;
/*   */     //   476: athrow
/*   */     //   477: ifeq -> 633
/*   */     //   480: goto -> 494
/*   */     //   483: ldc2_w -328145205934294547
/*   */     //   486: lload #4
/*   */     //   488: <illegal opcode> w : (Ljava/lang/Throwable;JJ)Ljava/lang/Throwable;
/*   */     //   493: athrow
/*   */     //   494: aload_3
/*   */     //   495: iconst_0
/*   */     //   496: aaload
/*   */     //   497: checkcast java/util/List
/*   */     //   500: astore #9
/*   */     //   502: iconst_0
/*   */     //   503: istore #10
/*   */     //   505: aload #9
/*   */     //   507: invokeinterface size : ()I
/*   */     //   512: istore #11
/*   */     //   514: iload #10
/*   */     //   516: iload #11
/*   */     //   518: if_icmpge -> 614
/*   */     //   521: aload #9
/*   */     //   523: iload #10
/*   */     //   525: invokeinterface get : (I)Ljava/lang/Object;
/*   */     //   530: checkcast java/lang/String
/*   */     //   533: astore #12
/*   */     //   535: iload #6
/*   */     //   537: ifeq -> 609
/*   */     //   540: aload_0
/*   */     //   541: iload #6
/*   */     //   543: ifeq -> 615
/*   */     //   546: goto -> 560
/*   */     //   549: ldc2_w -328145205934294547
/*   */     //   552: lload #4
/*   */     //   554: <illegal opcode> w : (Ljava/lang/Throwable;JJ)Ljava/lang/Throwable;
/*   */     //   559: athrow
/*   */     //   560: getfield a : Ljava/util/List;
/*   */     //   563: aload #12
/*   */     //   565: invokeinterface contains : (Ljava/lang/Object;)Z
/*   */     //   570: ifeq -> 606
/*   */     //   573: goto -> 587
/*   */     //   576: ldc2_w -328145205934294547
/*   */     //   579: lload #4
/*   */     //   581: <illegal opcode> w : (Ljava/lang/Throwable;JJ)Ljava/lang/Throwable;
/*   */     //   586: athrow
/*   */     //   587: aload_0
/*   */     //   588: aload #12
/*   */     //   590: dup_x1
/*   */     //   591: putfield b : Ljava/lang/String;
/*   */     //   594: areturn
/*   */     //   595: ldc2_w -328145205934294547
/*   */     //   598: lload #4
/*   */     //   600: <illegal opcode> w : (Ljava/lang/Throwable;JJ)Ljava/lang/Throwable;
/*   */     //   605: athrow
/*   */     //   606: iinc #10, 1
/*   */     //   609: iload #6
/*   */     //   611: ifne -> 514
/*   */     //   614: aload_0
/*   */     //   615: aload_0
/*   */     //   616: getfield a : Ljava/util/List;
/*   */     //   619: iconst_0
/*   */     //   620: invokeinterface get : (I)Ljava/lang/Object;
/*   */     //   625: checkcast java/lang/String
/*   */     //   628: dup_x1
/*   */     //   629: putfield b : Ljava/lang/String;
/*   */     //   632: areturn
/*   */     //   633: aload #7
/*   */     //   635: sipush #12972
/*   */     //   638: ldc2_w 5721187230188425606
/*   */     //   641: lload #4
/*   */     //   643: lxor
/*   */     //   644: <illegal opcode> s : (IJ)Ljava/lang/String;
/*   */     //   649: invokevirtual equals : (Ljava/lang/Object;)Z
/*   */     //   652: iload #6
/*   */     //   654: ifeq -> 764
/*   */     //   657: ifne -> 729
/*   */     //   660: goto -> 674
/*   */     //   663: ldc2_w -328145205934294547
/*   */     //   666: lload #4
/*   */     //   668: <illegal opcode> w : (Ljava/lang/Throwable;JJ)Ljava/lang/Throwable;
/*   */     //   673: athrow
/*   */     //   674: aload #7
/*   */     //   676: iload #6
/*   */     //   678: ifeq -> 797
/*   */     //   681: goto -> 695
/*   */     //   684: ldc2_w -328145205934294547
/*   */     //   687: lload #4
/*   */     //   689: <illegal opcode> w : (Ljava/lang/Throwable;JJ)Ljava/lang/Throwable;
/*   */     //   694: athrow
/*   */     //   695: sipush #30675
/*   */     //   698: ldc2_w 6389597836084024570
/*   */     //   701: lload #4
/*   */     //   703: lxor
/*   */     //   704: <illegal opcode> s : (IJ)Ljava/lang/String;
/*   */     //   709: invokevirtual equals : (Ljava/lang/Object;)Z
/*   */     //   712: ifeq -> 791
/*   */     //   715: goto -> 729
/*   */     //   718: ldc2_w -328145205934294547
/*   */     //   721: lload #4
/*   */     //   723: <illegal opcode> w : (Ljava/lang/Throwable;JJ)Ljava/lang/Throwable;
/*   */     //   728: athrow
/*   */     //   729: aload_3
/*   */     //   730: iload #6
/*   */     //   732: ifeq -> 797
/*   */     //   735: goto -> 749
/*   */     //   738: ldc2_w -328145205934294547
/*   */     //   741: lload #4
/*   */     //   743: <illegal opcode> w : (Ljava/lang/Throwable;JJ)Ljava/lang/Throwable;
/*   */     //   748: athrow
/*   */     //   749: arraylength
/*   */     //   750: goto -> 764
/*   */     //   753: ldc2_w -328145205934294547
/*   */     //   756: lload #4
/*   */     //   758: <illegal opcode> w : (Ljava/lang/Throwable;JJ)Ljava/lang/Throwable;
/*   */     //   763: athrow
/*   */     //   764: iconst_1
/*   */     //   765: if_icmpne -> 791
/*   */     //   768: aload_0
/*   */     //   769: aload_3
/*   */     //   770: iconst_0
/*   */     //   771: aaload
/*   */     //   772: checkcast java/lang/String
/*   */     //   775: putfield b : Ljava/lang/String;
/*   */     //   778: aconst_null
/*   */     //   779: areturn
/*   */     //   780: ldc2_w -328145205934294547
/*   */     //   783: lload #4
/*   */     //   785: <illegal opcode> w : (Ljava/lang/Throwable;JJ)Ljava/lang/Throwable;
/*   */     //   790: athrow
/*   */     //   791: aload_2
/*   */     //   792: aload_0
/*   */     //   793: aload_3
/*   */     //   794: invokevirtual invoke : (Ljava/lang/Object;[Ljava/lang/Object;)Ljava/lang/Object;
/*   */     //   797: areturn
/*   */     // Line number table:
/*   */     //   Java source line number -> byte code offset
/*   */     //   #15	-> 9
/*   */     //   #10	-> 25
/*   */     //   #8	-> 33
/*   */     //   #22	-> 37
/*   */     //   #4	-> 41
/*   */     //   #9	-> 104
/*   */     //   #24	-> 120
/*   */     //   #17	-> 183
/*   */     //   #5	-> 188
/*   */     //   #14	-> 201
/*   */     //   #11	-> 280
/*   */     //   #2	-> 296
/*   */     //   #20	-> 494
/*   */     //   #19	-> 502
/*   */     //   #21	-> 521
/*   */     //   #13	-> 535
/*   */     //   #16	-> 587
/*   */     //   #18	-> 606
/*   */     //   #25	-> 614
/*   */     //   #26	-> 633
/*   */     //   #12	-> 768
/*   */     //   #7	-> 778
/*   */     //   #3	-> 791
/*   */     // Exception table:
/*   */     //   from	to	target	type
/*   */     //   41	68	71	java/lang/Throwable
/*   */     //   65	90	93	java/lang/Throwable
/*   */     //   82	109	109	java/lang/Throwable
/*   */     //   139	147	150	java/lang/Throwable
/*   */     //   144	169	172	java/lang/Throwable
/*   */     //   161	190	190	java/lang/Throwable
/*   */     //   220	228	231	java/lang/Throwable
/*   */     //   225	249	252	java/lang/Throwable
/*   */     //   242	266	269	java/lang/Throwable
/*   */     //   263	285	285	java/lang/Throwable
/*   */     //   315	323	326	java/lang/Throwable
/*   */     //   320	356	359	java/lang/Throwable
/*   */     //   370	378	381	java/lang/Throwable
/*   */     //   375	399	402	java/lang/Throwable
/*   */     //   392	420	423	java/lang/Throwable
/*   */     //   413	438	441	java/lang/Throwable
/*   */     //   434	463	466	java/lang/Throwable
/*   */     //   452	480	483	java/lang/Throwable
/*   */     //   535	546	549	java/lang/Throwable
/*   */     //   540	573	576	java/lang/Throwable
/*   */     //   560	595	595	java/lang/Throwable
/*   */     //   652	660	663	java/lang/Throwable
/*   */     //   657	681	684	java/lang/Throwable
/*   */     //   674	715	718	java/lang/Throwable
/*   */     //   695	735	738	java/lang/Throwable
/*   */     //   729	750	753	java/lang/Throwable
/*   */     //   764	780	780	java/lang/Throwable
/*   */   } }


/* Location:              C:\Users\BukkitBypass\Desktop\MatrixAC\AAC\AAC-spigot-5.2.0.jar!\me\konsolas\aac\la.class
 * Java compiler version: 8 (52.0)
 * JD-Core Version:       1.1.3
 */