/*     */ package me.konsolas.aac;
/*     */ 
/*     */ import java.io.IOException;
/*     */ import java.lang.invoke.CallSite;
/*     */ import java.lang.invoke.MethodHandle;
/*     */ import java.lang.invoke.MethodHandles;
/*     */ import java.lang.invoke.MethodType;
/*     */ import java.lang.invoke.MutableCallSite;
/*     */ import java.util.HashMap;
/*     */ import java.util.Map;
/*     */ import javax.annotation.Nullable;
/*     */ import javax.crypto.Cipher;
/*     */ import javax.crypto.SecretKey;
/*     */ import javax.crypto.SecretKeyFactory;
/*     */ import javax.crypto.spec.DESKeySpec;
/*     */ import javax.crypto.spec.IvParameterSpec;
/*     */ 
/*     */ 
/*     */ 
/*     */ 
/*     */ 
/*     */ 
/*     */ 
/*     */ 
/*     */ 
/*     */ 
/*     */ 
/*     */ 
/*     */ 
/*     */ 
/*     */ 
/*     */ 
/*     */ 
/*     */ 
/*     */ 
/*     */ 
/*     */ 
/*     */ 
/*     */ 
/*     */ 
/*     */ 
/*     */ 
/*     */ 
/*     */ 
/*     */ 
/*     */ 
/*     */ 
/*     */ 
/*     */ 
/*     */ 
/*     */ 
/*     */ 
/*     */ 
/*     */ 
/*     */ 
/*     */ 
/*     */ 
/*     */ 
/*     */ 
/*     */ 
/*     */ 
/*     */ 
/*     */ 
/*     */ 
/*     */ 
/*     */ 
/*     */ 
/*     */ 
/*     */ 
/*     */ 
/*     */ 
/*     */ 
/*     */ 
/*     */ 
/*     */ 
/*     */ 
/*     */ 
/*     */ 
/*     */ 
/*     */ 
/*     */ 
/*     */ 
/*     */ 
/*     */ 
/*     */ 
/*     */ 
/*     */ 
/*     */ 
/*     */ 
/*     */ 
/*     */ 
/*     */ 
/*     */ 
/*     */ 
/*     */ 
/*     */ 
/*     */ 
/*     */ 
/*     */ 
/*     */ 
/*     */ 
/*     */ 
/*     */ public final class lc
/*     */   implements ki
/*     */ {
/*     */   private static final int b = 20;
/*     */   private final gf a;
/*     */   private static final long c = nc.a(8782134566734053016L, -6643570628037959824L, MethodHandles.lookup().lookupClass()).a(121943099659839L);
/*     */   private static final String[] d;
/*     */   private static final String[] e;
/*     */   private static final Map f = new HashMap<>(13);
/*     */   
/*     */   private boolean a(IOException paramIOException, long paramLong, s params) {
/*     */     // Byte code:
/*     */     //   0: getstatic me/konsolas/aac/lc.c : J
/*     */     //   3: lload_2
/*     */     //   4: lxor
/*     */     //   5: lstore_2
/*     */     //   6: ldc2_w -5351716960756118495
/*     */     //   9: lload_2
/*     */     //   10: <illegal opcode> w : (JJ)Z
/*     */     //   15: aload #4
/*     */     //   17: invokevirtual a : ()Lme/konsolas/aac/jR;
/*     */     //   20: astore #6
/*     */     //   22: istore #5
/*     */     //   24: aload #6
/*     */     //   26: iload #5
/*     */     //   28: ifeq -> 49
/*     */     //   31: ifnull -> 73
/*     */     //   34: goto -> 47
/*     */     //   37: ldc2_w -5389172223918292211
/*     */     //   40: lload_2
/*     */     //   41: <illegal opcode> w : (Ljava/lang/Exception;JJ)Ljava/lang/Exception;
/*     */     //   46: athrow
/*     */     //   47: aload #6
/*     */     //   49: invokevirtual a : ()Z
/*     */     //   52: iload #5
/*     */     //   54: ifeq -> 112
/*     */     //   57: ifne -> 111
/*     */     //   60: goto -> 73
/*     */     //   63: ldc2_w -5389172223918292211
/*     */     //   66: lload_2
/*     */     //   67: <illegal opcode> w : (Ljava/lang/Exception;JJ)Ljava/lang/Exception;
/*     */     //   72: athrow
/*     */     //   73: aload_1
/*     */     //   74: instanceof java/io/FileNotFoundException
/*     */     //   77: iload #5
/*     */     //   79: ifeq -> 112
/*     */     //   82: goto -> 95
/*     */     //   85: ldc2_w -5389172223918292211
/*     */     //   88: lload_2
/*     */     //   89: <illegal opcode> w : (Ljava/lang/Exception;JJ)Ljava/lang/Exception;
/*     */     //   94: athrow
/*     */     //   95: ifeq -> 115
/*     */     //   98: goto -> 111
/*     */     //   101: ldc2_w -5389172223918292211
/*     */     //   104: lload_2
/*     */     //   105: <illegal opcode> w : (Ljava/lang/Exception;JJ)Ljava/lang/Exception;
/*     */     //   110: athrow
/*     */     //   111: iconst_1
/*     */     //   112: goto -> 116
/*     */     //   115: iconst_0
/*     */     //   116: ireturn
/*     */     // Line number table:
/*     */     //   Java source line number -> byte code offset
/*     */     //   #2	-> 15
/*     */     //   #31	-> 24
/*     */     // Exception table:
/*     */     //   from	to	target	type
/*     */     //   24	34	37	me/konsolas/aac/jj
/*     */     //   49	60	63	me/konsolas/aac/jj
/*     */     //   57	82	85	me/konsolas/aac/jj
/*     */     //   73	98	101	me/konsolas/aac/jj
/*     */   }
/*     */   
/*     */   public lc(gf paramgf) {
/* 118 */     this.a = paramgf;
/*     */   }
/*     */   
/*     */   private s a(int paramInt1, H paramH, @Nullable hQ paramhQ, int paramInt2, int paramInt3) {
/*     */     // Byte code:
/*     */     //   0: iload_1
/*     */     //   1: i2l
/*     */     //   2: bipush #32
/*     */     //   4: lshl
/*     */     //   5: iload #4
/*     */     //   7: i2l
/*     */     //   8: bipush #48
/*     */     //   10: lshl
/*     */     //   11: bipush #32
/*     */     //   13: lushr
/*     */     //   14: lor
/*     */     //   15: iload #5
/*     */     //   17: i2l
/*     */     //   18: bipush #48
/*     */     //   20: lshl
/*     */     //   21: bipush #48
/*     */     //   23: lushr
/*     */     //   24: lor
/*     */     //   25: getstatic me/konsolas/aac/lc.c : J
/*     */     //   28: lxor
/*     */     //   29: lstore #6
/*     */     //   31: lload #6
/*     */     //   33: dup2
/*     */     //   34: ldc2_w 26152700155815
/*     */     //   37: lxor
/*     */     //   38: lstore #8
/*     */     //   40: dup2
/*     */     //   41: ldc2_w 50327729997516
/*     */     //   44: lxor
/*     */     //   45: lstore #10
/*     */     //   47: dup2
/*     */     //   48: ldc2_w 21566055442884
/*     */     //   51: lxor
/*     */     //   52: dup2
/*     */     //   53: bipush #48
/*     */     //   55: lushr
/*     */     //   56: l2i
/*     */     //   57: istore #12
/*     */     //   59: dup2
/*     */     //   60: bipush #16
/*     */     //   62: lshl
/*     */     //   63: bipush #16
/*     */     //   65: lushr
/*     */     //   66: lstore #13
/*     */     //   68: pop2
/*     */     //   69: dup2
/*     */     //   70: ldc2_w 131864308675576
/*     */     //   73: lxor
/*     */     //   74: dup2
/*     */     //   75: bipush #32
/*     */     //   77: lushr
/*     */     //   78: l2i
/*     */     //   79: istore #15
/*     */     //   81: dup2
/*     */     //   82: bipush #32
/*     */     //   84: lshl
/*     */     //   85: bipush #48
/*     */     //   87: lushr
/*     */     //   88: l2i
/*     */     //   89: istore #16
/*     */     //   91: dup2
/*     */     //   92: bipush #48
/*     */     //   94: lshl
/*     */     //   95: bipush #48
/*     */     //   97: lushr
/*     */     //   98: l2i
/*     */     //   99: istore #17
/*     */     //   101: pop2
/*     */     //   102: dup2
/*     */     //   103: ldc2_w 26893051523488
/*     */     //   106: lxor
/*     */     //   107: lstore #18
/*     */     //   109: dup2
/*     */     //   110: ldc2_w 116748503149166
/*     */     //   113: lxor
/*     */     //   114: lstore #20
/*     */     //   116: dup2
/*     */     //   117: ldc2_w 127391067233668
/*     */     //   120: lxor
/*     */     //   121: dup2
/*     */     //   122: bipush #48
/*     */     //   124: lushr
/*     */     //   125: l2i
/*     */     //   126: istore #22
/*     */     //   128: dup2
/*     */     //   129: bipush #16
/*     */     //   131: lshl
/*     */     //   132: bipush #48
/*     */     //   134: lushr
/*     */     //   135: l2i
/*     */     //   136: istore #23
/*     */     //   138: dup2
/*     */     //   139: bipush #32
/*     */     //   141: lshl
/*     */     //   142: bipush #32
/*     */     //   144: lushr
/*     */     //   145: l2i
/*     */     //   146: istore #24
/*     */     //   148: pop2
/*     */     //   149: dup2
/*     */     //   150: ldc2_w 50398574217778
/*     */     //   153: lxor
/*     */     //   154: lstore #25
/*     */     //   156: dup2
/*     */     //   157: ldc2_w 10002063107103
/*     */     //   160: lxor
/*     */     //   161: dup2
/*     */     //   162: bipush #48
/*     */     //   164: lushr
/*     */     //   165: l2i
/*     */     //   166: istore #27
/*     */     //   168: dup2
/*     */     //   169: bipush #16
/*     */     //   171: lshl
/*     */     //   172: bipush #32
/*     */     //   174: lushr
/*     */     //   175: l2i
/*     */     //   176: istore #28
/*     */     //   178: dup2
/*     */     //   179: bipush #48
/*     */     //   181: lshl
/*     */     //   182: bipush #48
/*     */     //   184: lushr
/*     */     //   185: l2i
/*     */     //   186: istore #29
/*     */     //   188: pop2
/*     */     //   189: dup2
/*     */     //   190: ldc2_w 27276909771274
/*     */     //   193: lxor
/*     */     //   194: lstore #30
/*     */     //   196: dup2
/*     */     //   197: ldc2_w 128231755422871
/*     */     //   200: lxor
/*     */     //   201: lstore #32
/*     */     //   203: dup2
/*     */     //   204: ldc2_w 109999659798647
/*     */     //   207: lxor
/*     */     //   208: lstore #34
/*     */     //   210: pop2
/*     */     //   211: ldc2_w -5130445916091203241
/*     */     //   214: lload #6
/*     */     //   216: <illegal opcode> w : (JJ)Z
/*     */     //   221: istore #36
/*     */     //   223: aload_2
/*     */     //   224: iload #36
/*     */     //   226: ifeq -> 266
/*     */     //   229: ifnonnull -> 265
/*     */     //   232: goto -> 246
/*     */     //   235: ldc2_w -5169060132960088453
/*     */     //   238: lload #6
/*     */     //   240: <illegal opcode> w : (Ljava/lang/Exception;JJ)Ljava/lang/Exception;
/*     */     //   245: athrow
/*     */     //   246: new java/lang/IllegalStateException
/*     */     //   249: dup
/*     */     //   250: invokespecial <init> : ()V
/*     */     //   253: athrow
/*     */     //   254: ldc2_w -5169060132960088453
/*     */     //   257: lload #6
/*     */     //   259: <illegal opcode> w : (Ljava/lang/Exception;JJ)Ljava/lang/Exception;
/*     */     //   264: athrow
/*     */     //   265: aload_2
/*     */     //   266: invokevirtual a : ()I
/*     */     //   269: istore #37
/*     */     //   271: aload_2
/*     */     //   272: invokevirtual a : ()Lme/konsolas/aac/s;
/*     */     //   275: invokevirtual a : ()Ljava/lang/String;
/*     */     //   278: astore #38
/*     */     //   280: iload #5
/*     */     //   282: iflt -> 376
/*     */     //   285: iload #37
/*     */     //   287: lookupswitch default -> 1550, 300 -> 617, 301 -> 617, 302 -> 617, 303 -> 617, 307 -> 503, 308 -> 503, 401 -> 488, 407 -> 376, 408 -> 1221, 503 -> 1426
/*     */     //   376: aload_3
/*     */     //   377: iload #36
/*     */     //   379: ifeq -> 414
/*     */     //   382: goto -> 396
/*     */     //   385: ldc2_w -5169060132960088453
/*     */     //   388: lload #6
/*     */     //   390: <illegal opcode> w : (Ljava/lang/Exception;JJ)Ljava/lang/Exception;
/*     */     //   395: athrow
/*     */     //   396: ifnull -> 420
/*     */     //   399: goto -> 413
/*     */     //   402: ldc2_w -5169060132960088453
/*     */     //   405: lload #6
/*     */     //   407: <illegal opcode> w : (Ljava/lang/Exception;JJ)Ljava/lang/Exception;
/*     */     //   412: athrow
/*     */     //   413: aload_3
/*     */     //   414: invokevirtual a : ()Ljava/net/Proxy;
/*     */     //   417: goto -> 427
/*     */     //   420: aload_0
/*     */     //   421: getfield a : Lme/konsolas/aac/gf;
/*     */     //   424: invokevirtual a : ()Ljava/net/Proxy;
/*     */     //   427: astore #39
/*     */     //   429: aload #39
/*     */     //   431: invokevirtual type : ()Ljava/net/Proxy$Type;
/*     */     //   434: getstatic java/net/Proxy$Type.HTTP : Ljava/net/Proxy$Type;
/*     */     //   437: if_acmpeq -> 473
/*     */     //   440: new java/net/ProtocolException
/*     */     //   443: dup
/*     */     //   444: sipush #21082
/*     */     //   447: ldc2_w 2484187277598374783
/*     */     //   450: lload #6
/*     */     //   452: lxor
/*     */     //   453: <illegal opcode> l : (IJ)Ljava/lang/String;
/*     */     //   458: invokespecial <init> : (Ljava/lang/String;)V
/*     */     //   461: athrow
/*     */     //   462: ldc2_w -5169060132960088453
/*     */     //   465: lload #6
/*     */     //   467: <illegal opcode> w : (Ljava/lang/Exception;JJ)Ljava/lang/Exception;
/*     */     //   472: athrow
/*     */     //   473: aload_0
/*     */     //   474: getfield a : Lme/konsolas/aac/gf;
/*     */     //   477: invokevirtual b : ()Lme/konsolas/aac/dp;
/*     */     //   480: aload_3
/*     */     //   481: aload_2
/*     */     //   482: invokeinterface a : (Lme/konsolas/aac/hQ;Lme/konsolas/aac/H;)Lme/konsolas/aac/s;
/*     */     //   487: areturn
/*     */     //   488: aload_0
/*     */     //   489: getfield a : Lme/konsolas/aac/gf;
/*     */     //   492: invokevirtual a : ()Lme/konsolas/aac/dp;
/*     */     //   495: aload_3
/*     */     //   496: aload_2
/*     */     //   497: invokeinterface a : (Lme/konsolas/aac/hQ;Lme/konsolas/aac/H;)Lme/konsolas/aac/s;
/*     */     //   502: areturn
/*     */     //   503: aload #38
/*     */     //   505: sipush #16438
/*     */     //   508: ldc2_w 1013694204247484703
/*     */     //   511: lload #6
/*     */     //   513: lxor
/*     */     //   514: <illegal opcode> l : (IJ)Ljava/lang/String;
/*     */     //   519: invokevirtual equals : (Ljava/lang/Object;)Z
/*     */     //   522: iload #36
/*     */     //   524: ifeq -> 624
/*     */     //   527: ifne -> 617
/*     */     //   530: goto -> 544
/*     */     //   533: ldc2_w -5169060132960088453
/*     */     //   536: lload #6
/*     */     //   538: <illegal opcode> w : (Ljava/lang/Exception;JJ)Ljava/lang/Exception;
/*     */     //   543: athrow
/*     */     //   544: aload #38
/*     */     //   546: sipush #20801
/*     */     //   549: ldc2_w 5222025252274387046
/*     */     //   552: lload #6
/*     */     //   554: lxor
/*     */     //   555: <illegal opcode> l : (IJ)Ljava/lang/String;
/*     */     //   560: invokevirtual equals : (Ljava/lang/Object;)Z
/*     */     //   563: iload #4
/*     */     //   565: ifle -> 624
/*     */     //   568: iload #36
/*     */     //   570: ifeq -> 624
/*     */     //   573: goto -> 587
/*     */     //   576: ldc2_w -5169060132960088453
/*     */     //   579: lload #6
/*     */     //   581: <illegal opcode> w : (Ljava/lang/Exception;JJ)Ljava/lang/Exception;
/*     */     //   586: athrow
/*     */     //   587: ifne -> 617
/*     */     //   590: goto -> 604
/*     */     //   593: ldc2_w -5169060132960088453
/*     */     //   596: lload #6
/*     */     //   598: <illegal opcode> w : (Ljava/lang/Exception;JJ)Ljava/lang/Exception;
/*     */     //   603: athrow
/*     */     //   604: aconst_null
/*     */     //   605: areturn
/*     */     //   606: ldc2_w -5169060132960088453
/*     */     //   609: lload #6
/*     */     //   611: <illegal opcode> w : (Ljava/lang/Exception;JJ)Ljava/lang/Exception;
/*     */     //   616: athrow
/*     */     //   617: aload_0
/*     */     //   618: getfield a : Lme/konsolas/aac/gf;
/*     */     //   621: invokevirtual b : ()Z
/*     */     //   624: ifne -> 640
/*     */     //   627: aconst_null
/*     */     //   628: areturn
/*     */     //   629: ldc2_w -5169060132960088453
/*     */     //   632: lload #6
/*     */     //   634: <illegal opcode> w : (Ljava/lang/Exception;JJ)Ljava/lang/Exception;
/*     */     //   639: athrow
/*     */     //   640: aload_2
/*     */     //   641: lload #30
/*     */     //   643: sipush #21414
/*     */     //   646: ldc2_w 7099690717008575114
/*     */     //   649: lload #6
/*     */     //   651: lxor
/*     */     //   652: <illegal opcode> l : (IJ)Ljava/lang/String;
/*     */     //   657: invokevirtual a : (JLjava/lang/String;)Ljava/lang/String;
/*     */     //   660: astore #40
/*     */     //   662: aload #40
/*     */     //   664: ifnonnull -> 680
/*     */     //   667: aconst_null
/*     */     //   668: areturn
/*     */     //   669: ldc2_w -5169060132960088453
/*     */     //   672: lload #6
/*     */     //   674: <illegal opcode> w : (Ljava/lang/Exception;JJ)Ljava/lang/Exception;
/*     */     //   679: athrow
/*     */     //   680: aload_2
/*     */     //   681: invokevirtual a : ()Lme/konsolas/aac/s;
/*     */     //   684: invokevirtual a : ()Lme/konsolas/aac/l6;
/*     */     //   687: lload #8
/*     */     //   689: aload #40
/*     */     //   691: invokevirtual a : (JLjava/lang/String;)Lme/konsolas/aac/l6;
/*     */     //   694: astore #41
/*     */     //   696: aload #41
/*     */     //   698: iload #36
/*     */     //   700: ifeq -> 735
/*     */     //   703: ifnonnull -> 733
/*     */     //   706: goto -> 720
/*     */     //   709: ldc2_w -5169060132960088453
/*     */     //   712: lload #6
/*     */     //   714: <illegal opcode> w : (Ljava/lang/Exception;JJ)Ljava/lang/Exception;
/*     */     //   719: athrow
/*     */     //   720: aconst_null
/*     */     //   721: areturn
/*     */     //   722: ldc2_w -5169060132960088453
/*     */     //   725: lload #6
/*     */     //   727: <illegal opcode> w : (Ljava/lang/Exception;JJ)Ljava/lang/Exception;
/*     */     //   732: athrow
/*     */     //   733: aload #41
/*     */     //   735: invokevirtual f : ()Ljava/lang/String;
/*     */     //   738: aload_2
/*     */     //   739: invokevirtual a : ()Lme/konsolas/aac/s;
/*     */     //   742: invokevirtual a : ()Lme/konsolas/aac/l6;
/*     */     //   745: invokevirtual f : ()Ljava/lang/String;
/*     */     //   748: invokevirtual equals : (Ljava/lang/Object;)Z
/*     */     //   751: istore #42
/*     */     //   753: iload #42
/*     */     //   755: iload #4
/*     */     //   757: ifle -> 803
/*     */     //   760: iload #36
/*     */     //   762: ifeq -> 803
/*     */     //   765: ifne -> 819
/*     */     //   768: goto -> 782
/*     */     //   771: ldc2_w -5169060132960088453
/*     */     //   774: lload #6
/*     */     //   776: <illegal opcode> w : (Ljava/lang/Exception;JJ)Ljava/lang/Exception;
/*     */     //   781: athrow
/*     */     //   782: aload_0
/*     */     //   783: getfield a : Lme/konsolas/aac/gf;
/*     */     //   786: invokevirtual a : ()Z
/*     */     //   789: goto -> 803
/*     */     //   792: ldc2_w -5169060132960088453
/*     */     //   795: lload #6
/*     */     //   797: <illegal opcode> w : (Ljava/lang/Exception;JJ)Ljava/lang/Exception;
/*     */     //   802: athrow
/*     */     //   803: ifne -> 819
/*     */     //   806: aconst_null
/*     */     //   807: areturn
/*     */     //   808: ldc2_w -5169060132960088453
/*     */     //   811: lload #6
/*     */     //   813: <illegal opcode> w : (Ljava/lang/Exception;JJ)Ljava/lang/Exception;
/*     */     //   818: athrow
/*     */     //   819: aload_2
/*     */     //   820: invokevirtual a : ()Lme/konsolas/aac/s;
/*     */     //   823: lload #25
/*     */     //   825: invokevirtual a : (J)Lme/konsolas/aac/k_;
/*     */     //   828: astore #43
/*     */     //   830: aload #38
/*     */     //   832: iload #27
/*     */     //   834: i2s
/*     */     //   835: iload #28
/*     */     //   837: iload #29
/*     */     //   839: i2c
/*     */     //   840: invokestatic e : (Ljava/lang/String;SIC)Z
/*     */     //   843: iload #36
/*     */     //   845: ifeq -> 1167
/*     */     //   848: ifeq -> 1128
/*     */     //   851: goto -> 865
/*     */     //   854: ldc2_w -5169060132960088453
/*     */     //   857: lload #6
/*     */     //   859: <illegal opcode> w : (Ljava/lang/Exception;JJ)Ljava/lang/Exception;
/*     */     //   864: athrow
/*     */     //   865: iload #12
/*     */     //   867: i2s
/*     */     //   868: lload #13
/*     */     //   870: aload #38
/*     */     //   872: invokestatic a : (SJLjava/lang/String;)Z
/*     */     //   875: istore #44
/*     */     //   877: iload #22
/*     */     //   879: i2s
/*     */     //   880: iload #23
/*     */     //   882: i2s
/*     */     //   883: iload #24
/*     */     //   885: aload #38
/*     */     //   887: invokestatic b : (SSILjava/lang/String;)Z
/*     */     //   890: iload #5
/*     */     //   892: iflt -> 980
/*     */     //   895: iload #36
/*     */     //   897: ifeq -> 980
/*     */     //   900: ifeq -> 964
/*     */     //   903: goto -> 917
/*     */     //   906: ldc2_w -5169060132960088453
/*     */     //   909: lload #6
/*     */     //   911: <illegal opcode> w : (Ljava/lang/Exception;JJ)Ljava/lang/Exception;
/*     */     //   916: athrow
/*     */     //   917: aload #43
/*     */     //   919: sipush #31459
/*     */     //   922: ldc2_w 5794081614231213003
/*     */     //   925: lload #6
/*     */     //   927: lxor
/*     */     //   928: <illegal opcode> l : (IJ)Ljava/lang/String;
/*     */     //   933: lload #32
/*     */     //   935: aconst_null
/*     */     //   936: invokevirtual a : (Ljava/lang/String;JLme/konsolas/aac/jR;)Lme/konsolas/aac/k_;
/*     */     //   939: pop
/*     */     //   940: iload #36
/*     */     //   942: iload #5
/*     */     //   944: ifle -> 1021
/*     */     //   947: ifne -> 1019
/*     */     //   950: goto -> 964
/*     */     //   953: ldc2_w -5169060132960088453
/*     */     //   956: lload #6
/*     */     //   958: <illegal opcode> w : (Ljava/lang/Exception;JJ)Ljava/lang/Exception;
/*     */     //   963: athrow
/*     */     //   964: iload #44
/*     */     //   966: goto -> 980
/*     */     //   969: ldc2_w -5169060132960088453
/*     */     //   972: lload #6
/*     */     //   974: <illegal opcode> w : (Ljava/lang/Exception;JJ)Ljava/lang/Exception;
/*     */     //   979: athrow
/*     */     //   980: ifeq -> 1004
/*     */     //   983: aload_2
/*     */     //   984: invokevirtual a : ()Lme/konsolas/aac/s;
/*     */     //   987: invokevirtual a : ()Lme/konsolas/aac/jR;
/*     */     //   990: goto -> 1005
/*     */     //   993: ldc2_w -5169060132960088453
/*     */     //   996: lload #6
/*     */     //   998: <illegal opcode> w : (Ljava/lang/Exception;JJ)Ljava/lang/Exception;
/*     */     //   1003: athrow
/*     */     //   1004: aconst_null
/*     */     //   1005: astore #45
/*     */     //   1007: aload #43
/*     */     //   1009: aload #38
/*     */     //   1011: lload #32
/*     */     //   1013: aload #45
/*     */     //   1015: invokevirtual a : (Ljava/lang/String;JLme/konsolas/aac/jR;)Lme/konsolas/aac/k_;
/*     */     //   1018: pop
/*     */     //   1019: iload #44
/*     */     //   1021: iload #4
/*     */     //   1023: ifle -> 1167
/*     */     //   1026: iload #36
/*     */     //   1028: ifeq -> 1167
/*     */     //   1031: ifne -> 1128
/*     */     //   1034: goto -> 1048
/*     */     //   1037: ldc2_w -5169060132960088453
/*     */     //   1040: lload #6
/*     */     //   1042: <illegal opcode> w : (Ljava/lang/Exception;JJ)Ljava/lang/Exception;
/*     */     //   1047: athrow
/*     */     //   1048: aload #43
/*     */     //   1050: lload #18
/*     */     //   1052: sipush #18411
/*     */     //   1055: ldc2_w 474646739346763457
/*     */     //   1058: lload #6
/*     */     //   1060: lxor
/*     */     //   1061: <illegal opcode> l : (IJ)Ljava/lang/String;
/*     */     //   1066: invokevirtual b : (JLjava/lang/String;)Lme/konsolas/aac/k_;
/*     */     //   1069: pop
/*     */     //   1070: aload #43
/*     */     //   1072: lload #18
/*     */     //   1074: sipush #32403
/*     */     //   1077: ldc2_w 7580745588465113016
/*     */     //   1080: lload #6
/*     */     //   1082: lxor
/*     */     //   1083: <illegal opcode> l : (IJ)Ljava/lang/String;
/*     */     //   1088: invokevirtual b : (JLjava/lang/String;)Lme/konsolas/aac/k_;
/*     */     //   1091: pop
/*     */     //   1092: aload #43
/*     */     //   1094: lload #18
/*     */     //   1096: sipush #22007
/*     */     //   1099: ldc2_w 6686483900686318803
/*     */     //   1102: lload #6
/*     */     //   1104: lxor
/*     */     //   1105: <illegal opcode> l : (IJ)Ljava/lang/String;
/*     */     //   1110: invokevirtual b : (JLjava/lang/String;)Lme/konsolas/aac/k_;
/*     */     //   1113: pop
/*     */     //   1114: goto -> 1128
/*     */     //   1117: ldc2_w -5169060132960088453
/*     */     //   1120: lload #6
/*     */     //   1122: <illegal opcode> w : (Ljava/lang/Exception;JJ)Ljava/lang/Exception;
/*     */     //   1127: athrow
/*     */     //   1128: aload_2
/*     */     //   1129: invokevirtual a : ()Lme/konsolas/aac/s;
/*     */     //   1132: iload #36
/*     */     //   1134: ifeq -> 1220
/*     */     //   1137: invokevirtual a : ()Lme/konsolas/aac/l6;
/*     */     //   1140: aload #41
/*     */     //   1142: iload #15
/*     */     //   1144: iload #16
/*     */     //   1146: i2s
/*     */     //   1147: iload #17
/*     */     //   1149: i2s
/*     */     //   1150: invokestatic a : (Lme/konsolas/aac/l6;Lme/konsolas/aac/l6;ISS)Z
/*     */     //   1153: goto -> 1167
/*     */     //   1156: ldc2_w -5169060132960088453
/*     */     //   1159: lload #6
/*     */     //   1161: <illegal opcode> w : (Ljava/lang/Exception;JJ)Ljava/lang/Exception;
/*     */     //   1166: athrow
/*     */     //   1167: ifne -> 1206
/*     */     //   1170: aload #43
/*     */     //   1172: lload #18
/*     */     //   1174: sipush #6038
/*     */     //   1177: ldc2_w 1835513046745087664
/*     */     //   1180: lload #6
/*     */     //   1182: lxor
/*     */     //   1183: <illegal opcode> l : (IJ)Ljava/lang/String;
/*     */     //   1188: invokevirtual b : (JLjava/lang/String;)Lme/konsolas/aac/k_;
/*     */     //   1191: pop
/*     */     //   1192: goto -> 1206
/*     */     //   1195: ldc2_w -5169060132960088453
/*     */     //   1198: lload #6
/*     */     //   1200: <illegal opcode> w : (Ljava/lang/Exception;JJ)Ljava/lang/Exception;
/*     */     //   1205: athrow
/*     */     //   1206: aload #43
/*     */     //   1208: aload #41
/*     */     //   1210: lload #34
/*     */     //   1212: invokevirtual a : (Lme/konsolas/aac/l6;J)Lme/konsolas/aac/k_;
/*     */     //   1215: lload #10
/*     */     //   1217: invokevirtual a : (J)Lme/konsolas/aac/s;
/*     */     //   1220: areturn
/*     */     //   1221: aload_0
/*     */     //   1222: getfield a : Lme/konsolas/aac/gf;
/*     */     //   1225: invokevirtual c : ()Z
/*     */     //   1228: ifne -> 1244
/*     */     //   1231: aconst_null
/*     */     //   1232: areturn
/*     */     //   1233: ldc2_w -5169060132960088453
/*     */     //   1236: lload #6
/*     */     //   1238: <illegal opcode> w : (Ljava/lang/Exception;JJ)Ljava/lang/Exception;
/*     */     //   1243: athrow
/*     */     //   1244: aload_2
/*     */     //   1245: invokevirtual a : ()Lme/konsolas/aac/s;
/*     */     //   1248: invokevirtual a : ()Lme/konsolas/aac/jR;
/*     */     //   1251: astore #44
/*     */     //   1253: aload #44
/*     */     //   1255: iload #5
/*     */     //   1257: iflt -> 1284
/*     */     //   1260: iload #36
/*     */     //   1262: ifeq -> 1284
/*     */     //   1265: ifnull -> 1303
/*     */     //   1268: goto -> 1282
/*     */     //   1271: ldc2_w -5169060132960088453
/*     */     //   1274: lload #6
/*     */     //   1276: <illegal opcode> w : (Ljava/lang/Exception;JJ)Ljava/lang/Exception;
/*     */     //   1281: athrow
/*     */     //   1282: aload #44
/*     */     //   1284: invokevirtual a : ()Z
/*     */     //   1287: ifeq -> 1303
/*     */     //   1290: aconst_null
/*     */     //   1291: areturn
/*     */     //   1292: ldc2_w -5169060132960088453
/*     */     //   1295: lload #6
/*     */     //   1297: <illegal opcode> w : (Ljava/lang/Exception;JJ)Ljava/lang/Exception;
/*     */     //   1302: athrow
/*     */     //   1303: aload_2
/*     */     //   1304: invokevirtual a : ()Lme/konsolas/aac/H;
/*     */     //   1307: iload #4
/*     */     //   1309: iflt -> 1352
/*     */     //   1312: iload #36
/*     */     //   1314: ifeq -> 1352
/*     */     //   1317: ifnull -> 1397
/*     */     //   1320: goto -> 1334
/*     */     //   1323: ldc2_w -5169060132960088453
/*     */     //   1326: lload #6
/*     */     //   1328: <illegal opcode> w : (Ljava/lang/Exception;JJ)Ljava/lang/Exception;
/*     */     //   1333: athrow
/*     */     //   1334: aload_2
/*     */     //   1335: invokevirtual a : ()Lme/konsolas/aac/H;
/*     */     //   1338: goto -> 1352
/*     */     //   1341: ldc2_w -5169060132960088453
/*     */     //   1344: lload #6
/*     */     //   1346: <illegal opcode> w : (Ljava/lang/Exception;JJ)Ljava/lang/Exception;
/*     */     //   1351: athrow
/*     */     //   1352: invokevirtual a : ()I
/*     */     //   1355: iload_1
/*     */     //   1356: iflt -> 1405
/*     */     //   1359: iload #36
/*     */     //   1361: ifeq -> 1405
/*     */     //   1364: sipush #408
/*     */     //   1367: if_icmpne -> 1397
/*     */     //   1370: goto -> 1384
/*     */     //   1373: ldc2_w -5169060132960088453
/*     */     //   1376: lload #6
/*     */     //   1378: <illegal opcode> w : (Ljava/lang/Exception;JJ)Ljava/lang/Exception;
/*     */     //   1383: athrow
/*     */     //   1384: aconst_null
/*     */     //   1385: areturn
/*     */     //   1386: ldc2_w -5169060132960088453
/*     */     //   1389: lload #6
/*     */     //   1391: <illegal opcode> w : (Ljava/lang/Exception;JJ)Ljava/lang/Exception;
/*     */     //   1396: athrow
/*     */     //   1397: aload_0
/*     */     //   1398: aload_2
/*     */     //   1399: lload #20
/*     */     //   1401: iconst_0
/*     */     //   1402: invokespecial a : (Lme/konsolas/aac/H;JI)I
/*     */     //   1405: ifle -> 1421
/*     */     //   1408: aconst_null
/*     */     //   1409: areturn
/*     */     //   1410: ldc2_w -5169060132960088453
/*     */     //   1413: lload #6
/*     */     //   1415: <illegal opcode> w : (Ljava/lang/Exception;JJ)Ljava/lang/Exception;
/*     */     //   1420: athrow
/*     */     //   1421: aload_2
/*     */     //   1422: invokevirtual a : ()Lme/konsolas/aac/s;
/*     */     //   1425: areturn
/*     */     //   1426: aload_2
/*     */     //   1427: invokevirtual a : ()Lme/konsolas/aac/H;
/*     */     //   1430: iload_1
/*     */     //   1431: iflt -> 1474
/*     */     //   1434: iload #36
/*     */     //   1436: ifeq -> 1474
/*     */     //   1439: ifnull -> 1519
/*     */     //   1442: goto -> 1456
/*     */     //   1445: ldc2_w -5169060132960088453
/*     */     //   1448: lload #6
/*     */     //   1450: <illegal opcode> w : (Ljava/lang/Exception;JJ)Ljava/lang/Exception;
/*     */     //   1455: athrow
/*     */     //   1456: aload_2
/*     */     //   1457: invokevirtual a : ()Lme/konsolas/aac/H;
/*     */     //   1460: goto -> 1474
/*     */     //   1463: ldc2_w -5169060132960088453
/*     */     //   1466: lload #6
/*     */     //   1468: <illegal opcode> w : (Ljava/lang/Exception;JJ)Ljava/lang/Exception;
/*     */     //   1473: athrow
/*     */     //   1474: invokevirtual a : ()I
/*     */     //   1477: iload_1
/*     */     //   1478: iflt -> 1529
/*     */     //   1481: iload #36
/*     */     //   1483: ifeq -> 1529
/*     */     //   1486: sipush #503
/*     */     //   1489: if_icmpne -> 1519
/*     */     //   1492: goto -> 1506
/*     */     //   1495: ldc2_w -5169060132960088453
/*     */     //   1498: lload #6
/*     */     //   1500: <illegal opcode> w : (Ljava/lang/Exception;JJ)Ljava/lang/Exception;
/*     */     //   1505: athrow
/*     */     //   1506: aconst_null
/*     */     //   1507: areturn
/*     */     //   1508: ldc2_w -5169060132960088453
/*     */     //   1511: lload #6
/*     */     //   1513: <illegal opcode> w : (Ljava/lang/Exception;JJ)Ljava/lang/Exception;
/*     */     //   1518: athrow
/*     */     //   1519: aload_0
/*     */     //   1520: aload_2
/*     */     //   1521: lload #20
/*     */     //   1523: ldc_w 2147483647
/*     */     //   1526: invokespecial a : (Lme/konsolas/aac/H;JI)I
/*     */     //   1529: ifne -> 1548
/*     */     //   1532: aload_2
/*     */     //   1533: invokevirtual a : ()Lme/konsolas/aac/s;
/*     */     //   1536: areturn
/*     */     //   1537: ldc2_w -5169060132960088453
/*     */     //   1540: lload #6
/*     */     //   1542: <illegal opcode> w : (Ljava/lang/Exception;JJ)Ljava/lang/Exception;
/*     */     //   1547: athrow
/*     */     //   1548: aconst_null
/*     */     //   1549: areturn
/*     */     //   1550: aconst_null
/*     */     //   1551: areturn
/*     */     // Line number table:
/*     */     //   Java source line number -> byte code offset
/*     */     //   #38	-> 223
/*     */     //   #75	-> 265
/*     */     //   #128	-> 271
/*     */     //   #112	-> 280
/*     */     //   #15	-> 376
/*     */     //   #10	-> 413
/*     */     //   #34	-> 420
/*     */     //   #109	-> 429
/*     */     //   #108	-> 440
/*     */     //   #65	-> 473
/*     */     //   #7	-> 488
/*     */     //   #11	-> 503
/*     */     //   #16	-> 604
/*     */     //   #84	-> 617
/*     */     //   #35	-> 640
/*     */     //   #103	-> 662
/*     */     //   #101	-> 680
/*     */     //   #20	-> 696
/*     */     //   #102	-> 733
/*     */     //   #56	-> 753
/*     */     //   #88	-> 819
/*     */     //   #8	-> 830
/*     */     //   #80	-> 865
/*     */     //   #50	-> 877
/*     */     //   #17	-> 917
/*     */     //   #23	-> 964
/*     */     //   #93	-> 1007
/*     */     //   #13	-> 1019
/*     */     //   #44	-> 1048
/*     */     //   #41	-> 1070
/*     */     //   #68	-> 1092
/*     */     //   #48	-> 1128
/*     */     //   #106	-> 1170
/*     */     //   #46	-> 1206
/*     */     //   #104	-> 1221
/*     */     //   #40	-> 1231
/*     */     //   #115	-> 1244
/*     */     //   #74	-> 1253
/*     */     //   #119	-> 1290
/*     */     //   #76	-> 1303
/*     */     //   #36	-> 1335
/*     */     //   #62	-> 1384
/*     */     //   #96	-> 1397
/*     */     //   #45	-> 1408
/*     */     //   #52	-> 1421
/*     */     //   #6	-> 1426
/*     */     //   #98	-> 1457
/*     */     //   #81	-> 1506
/*     */     //   #114	-> 1519
/*     */     //   #71	-> 1532
/*     */     //   #28	-> 1548
/*     */     //   #33	-> 1550
/*     */     // Exception table:
/*     */     //   from	to	target	type
/*     */     //   223	232	235	java/io/IOException
/*     */     //   229	254	254	java/io/IOException
/*     */     //   280	382	385	java/io/IOException
/*     */     //   376	399	402	java/io/IOException
/*     */     //   429	462	462	java/io/IOException
/*     */     //   503	530	533	java/io/IOException
/*     */     //   527	573	576	java/io/IOException
/*     */     //   544	590	593	java/io/IOException
/*     */     //   587	606	606	java/io/IOException
/*     */     //   624	629	629	java/io/IOException
/*     */     //   662	669	669	java/io/IOException
/*     */     //   696	706	709	java/io/IOException
/*     */     //   703	722	722	java/io/IOException
/*     */     //   753	768	771	java/io/IOException
/*     */     //   765	789	792	java/io/IOException
/*     */     //   803	808	808	java/io/IOException
/*     */     //   830	851	854	java/io/IOException
/*     */     //   877	903	906	java/io/IOException
/*     */     //   900	950	953	java/io/IOException
/*     */     //   917	966	969	java/io/IOException
/*     */     //   980	993	993	java/io/IOException
/*     */     //   1019	1034	1037	java/io/IOException
/*     */     //   1031	1114	1117	java/io/IOException
/*     */     //   1128	1153	1156	java/io/IOException
/*     */     //   1167	1192	1195	java/io/IOException
/*     */     //   1221	1233	1233	java/io/IOException
/*     */     //   1253	1268	1271	java/io/IOException
/*     */     //   1284	1292	1292	java/io/IOException
/*     */     //   1303	1320	1323	java/io/IOException
/*     */     //   1317	1338	1341	java/io/IOException
/*     */     //   1352	1370	1373	java/io/IOException
/*     */     //   1364	1386	1386	java/io/IOException
/*     */     //   1405	1410	1410	java/io/IOException
/*     */     //   1426	1442	1445	java/io/IOException
/*     */     //   1439	1460	1463	java/io/IOException
/*     */     //   1474	1492	1495	java/io/IOException
/*     */     //   1486	1508	1508	java/io/IOException
/*     */     //   1529	1537	1537	java/io/IOException
/*     */   }
/*     */   
/*     */   private boolean a(IOException paramIOException, short paramShort1, boolean paramBoolean, short paramShort2, int paramInt) {
/*     */     // Byte code:
/*     */     //   0: iload_2
/*     */     //   1: i2l
/*     */     //   2: bipush #48
/*     */     //   4: lshl
/*     */     //   5: iload #4
/*     */     //   7: i2l
/*     */     //   8: bipush #48
/*     */     //   10: lshl
/*     */     //   11: bipush #16
/*     */     //   13: lushr
/*     */     //   14: lor
/*     */     //   15: iload #5
/*     */     //   17: i2l
/*     */     //   18: bipush #32
/*     */     //   20: lshl
/*     */     //   21: bipush #32
/*     */     //   23: lushr
/*     */     //   24: lor
/*     */     //   25: getstatic me/konsolas/aac/lc.c : J
/*     */     //   28: lxor
/*     */     //   29: lstore #6
/*     */     //   31: ldc2_w -3542723714380574214
/*     */     //   34: lload #6
/*     */     //   36: <illegal opcode> w : (JJ)Z
/*     */     //   41: istore #8
/*     */     //   43: aload_1
/*     */     //   44: instanceof java/net/ProtocolException
/*     */     //   47: iload #8
/*     */     //   49: ifne -> 86
/*     */     //   52: ifeq -> 82
/*     */     //   55: goto -> 69
/*     */     //   58: ldc2_w -3594511002951108571
/*     */     //   61: lload #6
/*     */     //   63: <illegal opcode> w : (Ljava/lang/Exception;JJ)Ljava/lang/Exception;
/*     */     //   68: athrow
/*     */     //   69: iconst_0
/*     */     //   70: ireturn
/*     */     //   71: ldc2_w -3594511002951108571
/*     */     //   74: lload #6
/*     */     //   76: <illegal opcode> w : (Ljava/lang/Exception;JJ)Ljava/lang/Exception;
/*     */     //   81: athrow
/*     */     //   82: aload_1
/*     */     //   83: instanceof java/io/InterruptedIOException
/*     */     //   86: iload #8
/*     */     //   88: iload #5
/*     */     //   90: ifgt -> 193
/*     */     //   93: ifne -> 191
/*     */     //   96: ifeq -> 187
/*     */     //   99: goto -> 113
/*     */     //   102: ldc2_w -3594511002951108571
/*     */     //   105: lload #6
/*     */     //   107: <illegal opcode> w : (Ljava/lang/Exception;JJ)Ljava/lang/Exception;
/*     */     //   112: athrow
/*     */     //   113: aload_1
/*     */     //   114: instanceof java/net/SocketTimeoutException
/*     */     //   117: iload #8
/*     */     //   119: iload #4
/*     */     //   121: iflt -> 161
/*     */     //   124: ifne -> 159
/*     */     //   127: goto -> 141
/*     */     //   130: ldc2_w -3594511002951108571
/*     */     //   133: lload #6
/*     */     //   135: <illegal opcode> w : (Ljava/lang/Exception;JJ)Ljava/lang/Exception;
/*     */     //   140: athrow
/*     */     //   141: ifeq -> 185
/*     */     //   144: goto -> 158
/*     */     //   147: ldc2_w -3594511002951108571
/*     */     //   150: lload #6
/*     */     //   152: <illegal opcode> w : (Ljava/lang/Exception;JJ)Ljava/lang/Exception;
/*     */     //   157: athrow
/*     */     //   158: iload_3
/*     */     //   159: iload #8
/*     */     //   161: ifne -> 182
/*     */     //   164: ifne -> 185
/*     */     //   167: goto -> 181
/*     */     //   170: ldc2_w -3594511002951108571
/*     */     //   173: lload #6
/*     */     //   175: <illegal opcode> w : (Ljava/lang/Exception;JJ)Ljava/lang/Exception;
/*     */     //   180: athrow
/*     */     //   181: iconst_1
/*     */     //   182: goto -> 186
/*     */     //   185: iconst_0
/*     */     //   186: ireturn
/*     */     //   187: aload_1
/*     */     //   188: instanceof javax/net/ssl/SSLHandshakeException
/*     */     //   191: iload #8
/*     */     //   193: ifne -> 278
/*     */     //   196: ifeq -> 274
/*     */     //   199: goto -> 213
/*     */     //   202: ldc2_w -3594511002951108571
/*     */     //   205: lload #6
/*     */     //   207: <illegal opcode> w : (Ljava/lang/Exception;JJ)Ljava/lang/Exception;
/*     */     //   212: athrow
/*     */     //   213: aload_1
/*     */     //   214: invokevirtual getCause : ()Ljava/lang/Throwable;
/*     */     //   217: instanceof java/security/cert/CertificateException
/*     */     //   220: iload #8
/*     */     //   222: iload #4
/*     */     //   224: iflt -> 280
/*     */     //   227: ifne -> 278
/*     */     //   230: goto -> 244
/*     */     //   233: ldc2_w -3594511002951108571
/*     */     //   236: lload #6
/*     */     //   238: <illegal opcode> w : (Ljava/lang/Exception;JJ)Ljava/lang/Exception;
/*     */     //   243: athrow
/*     */     //   244: ifeq -> 274
/*     */     //   247: goto -> 261
/*     */     //   250: ldc2_w -3594511002951108571
/*     */     //   253: lload #6
/*     */     //   255: <illegal opcode> w : (Ljava/lang/Exception;JJ)Ljava/lang/Exception;
/*     */     //   260: athrow
/*     */     //   261: iconst_0
/*     */     //   262: ireturn
/*     */     //   263: ldc2_w -3594511002951108571
/*     */     //   266: lload #6
/*     */     //   268: <illegal opcode> w : (Ljava/lang/Exception;JJ)Ljava/lang/Exception;
/*     */     //   273: athrow
/*     */     //   274: aload_1
/*     */     //   275: instanceof javax/net/ssl/SSLPeerUnverifiedException
/*     */     //   278: iload #8
/*     */     //   280: ifne -> 314
/*     */     //   283: ifeq -> 313
/*     */     //   286: goto -> 300
/*     */     //   289: ldc2_w -3594511002951108571
/*     */     //   292: lload #6
/*     */     //   294: <illegal opcode> w : (Ljava/lang/Exception;JJ)Ljava/lang/Exception;
/*     */     //   299: athrow
/*     */     //   300: iconst_0
/*     */     //   301: ireturn
/*     */     //   302: ldc2_w -3594511002951108571
/*     */     //   305: lload #6
/*     */     //   307: <illegal opcode> w : (Ljava/lang/Exception;JJ)Ljava/lang/Exception;
/*     */     //   312: athrow
/*     */     //   313: iconst_1
/*     */     //   314: ireturn
/*     */     // Line number table:
/*     */     //   Java source line number -> byte code offset
/*     */     //   #63	-> 43
/*     */     //   #58	-> 69
/*     */     //   #43	-> 82
/*     */     //   #42	-> 113
/*     */     //   #99	-> 187
/*     */     //   #94	-> 213
/*     */     //   #110	-> 261
/*     */     //   #21	-> 274
/*     */     //   #89	-> 300
/*     */     //   #70	-> 313
/*     */     // Exception table:
/*     */     //   from	to	target	type
/*     */     //   43	55	58	me/konsolas/aac/jj
/*     */     //   52	71	71	me/konsolas/aac/jj
/*     */     //   86	99	102	me/konsolas/aac/jj
/*     */     //   96	127	130	me/konsolas/aac/jj
/*     */     //   113	144	147	me/konsolas/aac/jj
/*     */     //   159	167	170	me/konsolas/aac/jj
/*     */     //   191	199	202	me/konsolas/aac/jj
/*     */     //   196	230	233	me/konsolas/aac/jj
/*     */     //   213	247	250	me/konsolas/aac/jj
/*     */     //   244	263	263	me/konsolas/aac/jj
/*     */     //   278	286	289	me/konsolas/aac/jj
/*     */     //   283	302	302	me/konsolas/aac/jj
/*     */   }
/*     */   
/*     */   private int a(H paramH, long paramLong, int paramInt) {
/*     */     // Byte code:
/*     */     //   0: getstatic me/konsolas/aac/lc.c : J
/*     */     //   3: lload_2
/*     */     //   4: lxor
/*     */     //   5: lstore_2
/*     */     //   6: lload_2
/*     */     //   7: dup2
/*     */     //   8: ldc2_w 100613812882308
/*     */     //   11: lxor
/*     */     //   12: lstore #5
/*     */     //   14: pop2
/*     */     //   15: ldc2_w 5278990415290183897
/*     */     //   18: lload_2
/*     */     //   19: <illegal opcode> w : (JJ)Z
/*     */     //   24: aload_1
/*     */     //   25: lload #5
/*     */     //   27: sipush #24500
/*     */     //   30: ldc2_w 8261739323275790100
/*     */     //   33: lload_2
/*     */     //   34: lxor
/*     */     //   35: <illegal opcode> l : (IJ)Ljava/lang/String;
/*     */     //   40: invokevirtual a : (JLjava/lang/String;)Ljava/lang/String;
/*     */     //   43: astore #8
/*     */     //   45: istore #7
/*     */     //   47: aload #8
/*     */     //   49: iload #7
/*     */     //   51: ifeq -> 85
/*     */     //   54: ifnonnull -> 83
/*     */     //   57: goto -> 70
/*     */     //   60: ldc2_w 5318061204370898933
/*     */     //   63: lload_2
/*     */     //   64: <illegal opcode> w : (Ljava/lang/Exception;JJ)Ljava/lang/Exception;
/*     */     //   69: athrow
/*     */     //   70: iload #4
/*     */     //   72: ireturn
/*     */     //   73: ldc2_w 5318061204370898933
/*     */     //   76: lload_2
/*     */     //   77: <illegal opcode> w : (Ljava/lang/Exception;JJ)Ljava/lang/Exception;
/*     */     //   82: athrow
/*     */     //   83: aload #8
/*     */     //   85: sipush #19153
/*     */     //   88: ldc2_w 4612852561267380848
/*     */     //   91: lload_2
/*     */     //   92: lxor
/*     */     //   93: <illegal opcode> l : (IJ)Ljava/lang/String;
/*     */     //   98: invokevirtual matches : (Ljava/lang/String;)Z
/*     */     //   101: iload #7
/*     */     //   103: ifeq -> 144
/*     */     //   106: ifeq -> 141
/*     */     //   109: goto -> 122
/*     */     //   112: ldc2_w 5318061204370898933
/*     */     //   115: lload_2
/*     */     //   116: <illegal opcode> w : (Ljava/lang/Exception;JJ)Ljava/lang/Exception;
/*     */     //   121: athrow
/*     */     //   122: aload #8
/*     */     //   124: invokestatic valueOf : (Ljava/lang/String;)Ljava/lang/Integer;
/*     */     //   127: invokevirtual intValue : ()I
/*     */     //   130: ireturn
/*     */     //   131: ldc2_w 5318061204370898933
/*     */     //   134: lload_2
/*     */     //   135: <illegal opcode> w : (Ljava/lang/Exception;JJ)Ljava/lang/Exception;
/*     */     //   140: athrow
/*     */     //   141: ldc_w 2147483647
/*     */     //   144: ireturn
/*     */     // Line number table:
/*     */     //   Java source line number -> byte code offset
/*     */     //   #97	-> 24
/*     */     //   #19	-> 47
/*     */     //   #49	-> 70
/*     */     //   #37	-> 83
/*     */     //   #1	-> 122
/*     */     //   #26	-> 141
/*     */     // Exception table:
/*     */     //   from	to	target	type
/*     */     //   47	57	60	me/konsolas/aac/jj
/*     */     //   54	73	73	me/konsolas/aac/jj
/*     */     //   85	109	112	me/konsolas/aac/jj
/*     */     //   106	131	131	me/konsolas/aac/jj
/*     */   }
/*     */   
/*     */   public H a(long paramLong, ko paramko) {
/*     */     // Byte code:
/*     */     //   0: lload_1
/*     */     //   1: dup2
/*     */     //   2: ldc2_w 108770219837298
/*     */     //   5: lxor
/*     */     //   6: lstore #4
/*     */     //   8: dup2
/*     */     //   9: ldc2_w 30721071364235
/*     */     //   12: lxor
/*     */     //   13: dup2
/*     */     //   14: bipush #48
/*     */     //   16: lushr
/*     */     //   17: l2i
/*     */     //   18: istore #6
/*     */     //   20: dup2
/*     */     //   21: bipush #16
/*     */     //   23: lshl
/*     */     //   24: bipush #32
/*     */     //   26: lushr
/*     */     //   27: l2i
/*     */     //   28: istore #7
/*     */     //   30: dup2
/*     */     //   31: bipush #48
/*     */     //   33: lshl
/*     */     //   34: bipush #48
/*     */     //   36: lushr
/*     */     //   37: l2i
/*     */     //   38: istore #8
/*     */     //   40: pop2
/*     */     //   41: dup2
/*     */     //   42: ldc2_w 24523815385115
/*     */     //   45: lxor
/*     */     //   46: dup2
/*     */     //   47: bipush #32
/*     */     //   49: lushr
/*     */     //   50: l2i
/*     */     //   51: istore #9
/*     */     //   53: dup2
/*     */     //   54: bipush #32
/*     */     //   56: lshl
/*     */     //   57: bipush #48
/*     */     //   59: lushr
/*     */     //   60: l2i
/*     */     //   61: istore #10
/*     */     //   63: dup2
/*     */     //   64: bipush #48
/*     */     //   66: lshl
/*     */     //   67: bipush #48
/*     */     //   69: lushr
/*     */     //   70: l2i
/*     */     //   71: istore #11
/*     */     //   73: pop2
/*     */     //   74: dup2
/*     */     //   75: ldc2_w 22678922942745
/*     */     //   78: lxor
/*     */     //   79: dup2
/*     */     //   80: bipush #32
/*     */     //   82: lushr
/*     */     //   83: l2i
/*     */     //   84: istore #12
/*     */     //   86: dup2
/*     */     //   87: bipush #32
/*     */     //   89: lshl
/*     */     //   90: bipush #32
/*     */     //   92: lushr
/*     */     //   93: l2i
/*     */     //   94: istore #13
/*     */     //   96: pop2
/*     */     //   97: dup2
/*     */     //   98: ldc2_w 47362620127718
/*     */     //   101: lxor
/*     */     //   102: lstore #14
/*     */     //   104: dup2
/*     */     //   105: ldc2_w 110128304985271
/*     */     //   108: lxor
/*     */     //   109: lstore #16
/*     */     //   111: dup2
/*     */     //   112: ldc2_w 123956286709911
/*     */     //   115: lxor
/*     */     //   116: lstore #18
/*     */     //   118: dup2
/*     */     //   119: ldc2_w 70861095970165
/*     */     //   122: lxor
/*     */     //   123: lstore #20
/*     */     //   125: dup2
/*     */     //   126: ldc2_w 1250055110467
/*     */     //   129: lxor
/*     */     //   130: lstore #22
/*     */     //   132: dup2
/*     */     //   133: ldc2_w 34653664372396
/*     */     //   136: lxor
/*     */     //   137: lstore #24
/*     */     //   139: dup2
/*     */     //   140: ldc2_w 34245277093652
/*     */     //   143: lxor
/*     */     //   144: lstore #26
/*     */     //   146: pop2
/*     */     //   147: ldc2_w 6589044271115977823
/*     */     //   150: lload_1
/*     */     //   151: <illegal opcode> w : (JJ)Z
/*     */     //   156: aload_3
/*     */     //   157: invokeinterface a : ()Lme/konsolas/aac/s;
/*     */     //   162: astore #29
/*     */     //   164: aload_3
/*     */     //   165: checkcast me/konsolas/aac/jL
/*     */     //   168: astore #30
/*     */     //   170: istore #28
/*     */     //   172: aload #30
/*     */     //   174: invokevirtual a : ()Lme/konsolas/aac/fO;
/*     */     //   177: astore #31
/*     */     //   179: iconst_0
/*     */     //   180: istore #32
/*     */     //   182: aconst_null
/*     */     //   183: astore #33
/*     */     //   185: aload #31
/*     */     //   187: lload #26
/*     */     //   189: aload #29
/*     */     //   191: invokevirtual a : (JLme/konsolas/aac/s;)V
/*     */     //   194: aload #31
/*     */     //   196: invokevirtual c : ()Z
/*     */     //   199: lload_1
/*     */     //   200: lconst_0
/*     */     //   201: lcmp
/*     */     //   202: ifle -> 240
/*     */     //   205: ifeq -> 239
/*     */     //   208: new java/io/IOException
/*     */     //   211: dup
/*     */     //   212: sipush #270
/*     */     //   215: ldc2_w 7018635606689778645
/*     */     //   218: lload_1
/*     */     //   219: lxor
/*     */     //   220: <illegal opcode> l : (IJ)Ljava/lang/String;
/*     */     //   225: invokespecial <init> : (Ljava/lang/String;)V
/*     */     //   228: athrow
/*     */     //   229: ldc2_w 6609296466686193024
/*     */     //   232: lload_1
/*     */     //   233: <illegal opcode> w : (Ljava/lang/Exception;JJ)Ljava/lang/Exception;
/*     */     //   238: athrow
/*     */     //   239: iconst_0
/*     */     //   240: istore #35
/*     */     //   242: aload #30
/*     */     //   244: aload #29
/*     */     //   246: lload #20
/*     */     //   248: aload #31
/*     */     //   250: aconst_null
/*     */     //   251: invokevirtual a : (Lme/konsolas/aac/s;JLme/konsolas/aac/fO;Lme/konsolas/aac/ec;)Lme/konsolas/aac/H;
/*     */     //   254: astore #34
/*     */     //   256: iconst_1
/*     */     //   257: istore #35
/*     */     //   259: iload #28
/*     */     //   261: lload_1
/*     */     //   262: lconst_0
/*     */     //   263: lcmp
/*     */     //   264: ifle -> 272
/*     */     //   267: ifne -> 314
/*     */     //   270: iload #35
/*     */     //   272: ifne -> 563
/*     */     //   275: goto -> 288
/*     */     //   278: ldc2_w 6609296466686193024
/*     */     //   281: lload_1
/*     */     //   282: <illegal opcode> w : (Ljava/lang/Exception;JJ)Ljava/lang/Exception;
/*     */     //   287: athrow
/*     */     //   288: aload #31
/*     */     //   290: iload #6
/*     */     //   292: i2s
/*     */     //   293: iload #7
/*     */     //   295: iload #8
/*     */     //   297: i2c
/*     */     //   298: invokevirtual d : (SIC)V
/*     */     //   301: goto -> 314
/*     */     //   304: ldc2_w 6609296466686193024
/*     */     //   307: lload_1
/*     */     //   308: <illegal opcode> w : (Ljava/lang/Exception;JJ)Ljava/lang/Exception;
/*     */     //   313: athrow
/*     */     //   314: goto -> 563
/*     */     //   317: astore #36
/*     */     //   319: aload_0
/*     */     //   320: aload #36
/*     */     //   322: invokevirtual a : ()Ljava/io/IOException;
/*     */     //   325: lload #14
/*     */     //   327: dup2_x1
/*     */     //   328: pop2
/*     */     //   329: aload #31
/*     */     //   331: iconst_0
/*     */     //   332: aload #29
/*     */     //   334: invokespecial a : (JLjava/io/IOException;Lme/konsolas/aac/fO;ZLme/konsolas/aac/s;)Z
/*     */     //   337: iload #28
/*     */     //   339: lload_1
/*     */     //   340: lconst_0
/*     */     //   341: lcmp
/*     */     //   342: ifle -> 384
/*     */     //   345: ifne -> 382
/*     */     //   348: ifne -> 380
/*     */     //   351: goto -> 364
/*     */     //   354: ldc2_w 6609296466686193024
/*     */     //   357: lload_1
/*     */     //   358: <illegal opcode> w : (Ljava/lang/Exception;JJ)Ljava/lang/Exception;
/*     */     //   363: athrow
/*     */     //   364: aload #36
/*     */     //   366: invokevirtual b : ()Ljava/io/IOException;
/*     */     //   369: athrow
/*     */     //   370: ldc2_w 6609296466686193024
/*     */     //   373: lload_1
/*     */     //   374: <illegal opcode> w : (Ljava/lang/Exception;JJ)Ljava/lang/Exception;
/*     */     //   379: athrow
/*     */     //   380: iload #35
/*     */     //   382: iload #28
/*     */     //   384: ifne -> 199
/*     */     //   387: ifne -> 185
/*     */     //   390: aload #31
/*     */     //   392: iload #6
/*     */     //   394: i2s
/*     */     //   395: iload #7
/*     */     //   397: iload #8
/*     */     //   399: i2c
/*     */     //   400: invokevirtual d : (SIC)V
/*     */     //   403: goto -> 185
/*     */     //   406: astore #36
/*     */     //   408: aload #36
/*     */     //   410: instanceof me/konsolas/aac/R
/*     */     //   413: iload #28
/*     */     //   415: ifne -> 435
/*     */     //   418: ifne -> 438
/*     */     //   421: goto -> 434
/*     */     //   424: ldc2_w 6609296466686193024
/*     */     //   427: lload_1
/*     */     //   428: <illegal opcode> w : (Ljava/lang/Exception;JJ)Ljava/lang/Exception;
/*     */     //   433: athrow
/*     */     //   434: iconst_1
/*     */     //   435: goto -> 439
/*     */     //   438: iconst_0
/*     */     //   439: istore #37
/*     */     //   441: aload_0
/*     */     //   442: lload #14
/*     */     //   444: aload #36
/*     */     //   446: aload #31
/*     */     //   448: iload #37
/*     */     //   450: aload #29
/*     */     //   452: invokespecial a : (JLjava/io/IOException;Lme/konsolas/aac/fO;ZLme/konsolas/aac/s;)Z
/*     */     //   455: iload #28
/*     */     //   457: lload_1
/*     */     //   458: lconst_0
/*     */     //   459: lcmp
/*     */     //   460: ifle -> 499
/*     */     //   463: ifne -> 497
/*     */     //   466: ifne -> 495
/*     */     //   469: goto -> 482
/*     */     //   472: ldc2_w 6609296466686193024
/*     */     //   475: lload_1
/*     */     //   476: <illegal opcode> w : (Ljava/lang/Exception;JJ)Ljava/lang/Exception;
/*     */     //   481: athrow
/*     */     //   482: aload #36
/*     */     //   484: athrow
/*     */     //   485: ldc2_w 6609296466686193024
/*     */     //   488: lload_1
/*     */     //   489: <illegal opcode> w : (Ljava/lang/Exception;JJ)Ljava/lang/Exception;
/*     */     //   494: athrow
/*     */     //   495: iload #35
/*     */     //   497: iload #28
/*     */     //   499: ifne -> 199
/*     */     //   502: ifne -> 185
/*     */     //   505: aload #31
/*     */     //   507: iload #6
/*     */     //   509: i2s
/*     */     //   510: iload #7
/*     */     //   512: iload #8
/*     */     //   514: i2c
/*     */     //   515: invokevirtual d : (SIC)V
/*     */     //   518: goto -> 185
/*     */     //   521: astore #38
/*     */     //   523: lload_1
/*     */     //   524: lconst_0
/*     */     //   525: lcmp
/*     */     //   526: iflt -> 547
/*     */     //   529: iload #35
/*     */     //   531: ifne -> 560
/*     */     //   534: aload #31
/*     */     //   536: iload #6
/*     */     //   538: i2s
/*     */     //   539: iload #7
/*     */     //   541: iload #8
/*     */     //   543: i2c
/*     */     //   544: invokevirtual d : (SIC)V
/*     */     //   547: goto -> 560
/*     */     //   550: ldc2_w 6609296466686193024
/*     */     //   553: lload_1
/*     */     //   554: <illegal opcode> w : (Ljava/lang/Exception;JJ)Ljava/lang/Exception;
/*     */     //   559: athrow
/*     */     //   560: aload #38
/*     */     //   562: athrow
/*     */     //   563: aload #33
/*     */     //   565: iload #28
/*     */     //   567: ifne -> 630
/*     */     //   570: ifnull -> 632
/*     */     //   573: goto -> 586
/*     */     //   576: ldc2_w 6609296466686193024
/*     */     //   579: lload_1
/*     */     //   580: <illegal opcode> w : (Ljava/lang/Exception;JJ)Ljava/lang/Exception;
/*     */     //   585: athrow
/*     */     //   586: aload #34
/*     */     //   588: invokevirtual a : ()Lme/konsolas/aac/T;
/*     */     //   591: aload #33
/*     */     //   593: invokevirtual a : ()Lme/konsolas/aac/T;
/*     */     //   596: aconst_null
/*     */     //   597: invokevirtual a : (Lme/konsolas/aac/d2;)Lme/konsolas/aac/T;
/*     */     //   600: lload #18
/*     */     //   602: invokevirtual a : (J)Lme/konsolas/aac/H;
/*     */     //   605: lload #4
/*     */     //   607: dup2_x1
/*     */     //   608: pop2
/*     */     //   609: invokevirtual c : (JLme/konsolas/aac/H;)Lme/konsolas/aac/T;
/*     */     //   612: lload #18
/*     */     //   614: invokevirtual a : (J)Lme/konsolas/aac/H;
/*     */     //   617: goto -> 630
/*     */     //   620: ldc2_w 6609296466686193024
/*     */     //   623: lload_1
/*     */     //   624: <illegal opcode> w : (Ljava/lang/Exception;JJ)Ljava/lang/Exception;
/*     */     //   629: athrow
/*     */     //   630: astore #34
/*     */     //   632: getstatic me/konsolas/aac/dJ.a : Lme/konsolas/aac/dJ;
/*     */     //   635: aload #34
/*     */     //   637: invokevirtual a : (Lme/konsolas/aac/H;)Lme/konsolas/aac/ec;
/*     */     //   640: astore #36
/*     */     //   642: aload #36
/*     */     //   644: iload #28
/*     */     //   646: ifne -> 667
/*     */     //   649: ifnull -> 676
/*     */     //   652: goto -> 665
/*     */     //   655: ldc2_w 6609296466686193024
/*     */     //   658: lload_1
/*     */     //   659: <illegal opcode> w : (Ljava/lang/Exception;JJ)Ljava/lang/Exception;
/*     */     //   664: athrow
/*     */     //   665: aload #36
/*     */     //   667: invokevirtual a : ()Lme/konsolas/aac/el;
/*     */     //   670: invokevirtual a : ()Lme/konsolas/aac/hQ;
/*     */     //   673: goto -> 677
/*     */     //   676: aconst_null
/*     */     //   677: astore #37
/*     */     //   679: aload_0
/*     */     //   680: iload #9
/*     */     //   682: aload #34
/*     */     //   684: aload #37
/*     */     //   686: iload #10
/*     */     //   688: iload #11
/*     */     //   690: invokespecial a : (ILme/konsolas/aac/H;Lme/konsolas/aac/hQ;II)Lme/konsolas/aac/s;
/*     */     //   693: astore #38
/*     */     //   695: aload #38
/*     */     //   697: iload #28
/*     */     //   699: ifne -> 795
/*     */     //   702: ifnonnull -> 793
/*     */     //   705: goto -> 718
/*     */     //   708: ldc2_w 6609296466686193024
/*     */     //   711: lload_1
/*     */     //   712: <illegal opcode> w : (Ljava/lang/Exception;JJ)Ljava/lang/Exception;
/*     */     //   717: athrow
/*     */     //   718: aload #36
/*     */     //   720: lload_1
/*     */     //   721: lconst_0
/*     */     //   722: lcmp
/*     */     //   723: ifle -> 762
/*     */     //   726: iload #28
/*     */     //   728: ifne -> 762
/*     */     //   731: goto -> 744
/*     */     //   734: ldc2_w 6609296466686193024
/*     */     //   737: lload_1
/*     */     //   738: <illegal opcode> w : (Ljava/lang/Exception;JJ)Ljava/lang/Exception;
/*     */     //   743: athrow
/*     */     //   744: ifnull -> 790
/*     */     //   747: goto -> 760
/*     */     //   750: ldc2_w 6609296466686193024
/*     */     //   753: lload_1
/*     */     //   754: <illegal opcode> w : (Ljava/lang/Exception;JJ)Ljava/lang/Exception;
/*     */     //   759: athrow
/*     */     //   760: aload #36
/*     */     //   762: invokevirtual a : ()Z
/*     */     //   765: ifeq -> 790
/*     */     //   768: aload #31
/*     */     //   770: iload #12
/*     */     //   772: iload #13
/*     */     //   774: invokevirtual c : (II)V
/*     */     //   777: goto -> 790
/*     */     //   780: ldc2_w 6609296466686193024
/*     */     //   783: lload_1
/*     */     //   784: <illegal opcode> w : (Ljava/lang/Exception;JJ)Ljava/lang/Exception;
/*     */     //   789: athrow
/*     */     //   790: aload #34
/*     */     //   792: areturn
/*     */     //   793: aload #38
/*     */     //   795: invokevirtual a : ()Lme/konsolas/aac/jR;
/*     */     //   798: astore #39
/*     */     //   800: iload #28
/*     */     //   802: ifne -> 893
/*     */     //   805: aload #39
/*     */     //   807: ifnull -> 881
/*     */     //   810: goto -> 823
/*     */     //   813: ldc2_w 6609296466686193024
/*     */     //   816: lload_1
/*     */     //   817: <illegal opcode> w : (Ljava/lang/Exception;JJ)Ljava/lang/Exception;
/*     */     //   822: athrow
/*     */     //   823: aload #39
/*     */     //   825: invokevirtual a : ()Z
/*     */     //   828: iload #28
/*     */     //   830: lload_1
/*     */     //   831: lconst_0
/*     */     //   832: lcmp
/*     */     //   833: ifle -> 902
/*     */     //   836: ifne -> 900
/*     */     //   839: goto -> 852
/*     */     //   842: ldc2_w 6609296466686193024
/*     */     //   845: lload_1
/*     */     //   846: <illegal opcode> w : (Ljava/lang/Exception;JJ)Ljava/lang/Exception;
/*     */     //   851: athrow
/*     */     //   852: ifeq -> 881
/*     */     //   855: goto -> 868
/*     */     //   858: ldc2_w 6609296466686193024
/*     */     //   861: lload_1
/*     */     //   862: <illegal opcode> w : (Ljava/lang/Exception;JJ)Ljava/lang/Exception;
/*     */     //   867: athrow
/*     */     //   868: aload #34
/*     */     //   870: areturn
/*     */     //   871: ldc2_w 6609296466686193024
/*     */     //   874: lload_1
/*     */     //   875: <illegal opcode> w : (Ljava/lang/Exception;JJ)Ljava/lang/Exception;
/*     */     //   880: athrow
/*     */     //   881: aload #34
/*     */     //   883: invokevirtual a : ()Lme/konsolas/aac/d2;
/*     */     //   886: lload #22
/*     */     //   888: dup2_x1
/*     */     //   889: pop2
/*     */     //   890: invokestatic a : (JLjava/io/Closeable;)V
/*     */     //   893: aload #31
/*     */     //   895: lload #16
/*     */     //   897: invokevirtual b : (J)Z
/*     */     //   900: iload #28
/*     */     //   902: lload_1
/*     */     //   903: lconst_0
/*     */     //   904: lcmp
/*     */     //   905: ifle -> 978
/*     */     //   908: ifne -> 976
/*     */     //   911: ifeq -> 947
/*     */     //   914: goto -> 927
/*     */     //   917: ldc2_w 6609296466686193024
/*     */     //   920: lload_1
/*     */     //   921: <illegal opcode> w : (Ljava/lang/Exception;JJ)Ljava/lang/Exception;
/*     */     //   926: athrow
/*     */     //   927: aload #36
/*     */     //   929: lload #24
/*     */     //   931: invokevirtual a : (J)V
/*     */     //   934: goto -> 947
/*     */     //   937: ldc2_w 6609296466686193024
/*     */     //   940: lload_1
/*     */     //   941: <illegal opcode> w : (Ljava/lang/Exception;JJ)Ljava/lang/Exception;
/*     */     //   946: athrow
/*     */     //   947: iinc #32, 1
/*     */     //   950: iload #28
/*     */     //   952: lload_1
/*     */     //   953: lconst_0
/*     */     //   954: lcmp
/*     */     //   955: ifle -> 963
/*     */     //   958: ifne -> 1038
/*     */     //   961: iload #32
/*     */     //   963: goto -> 976
/*     */     //   966: ldc2_w 6609296466686193024
/*     */     //   969: lload_1
/*     */     //   970: <illegal opcode> w : (Ljava/lang/Exception;JJ)Ljava/lang/Exception;
/*     */     //   975: athrow
/*     */     //   976: bipush #20
/*     */     //   978: if_icmple -> 1030
/*     */     //   981: new java/net/ProtocolException
/*     */     //   984: dup
/*     */     //   985: new java/lang/StringBuilder
/*     */     //   988: dup
/*     */     //   989: invokespecial <init> : ()V
/*     */     //   992: sipush #20807
/*     */     //   995: ldc2_w 4645915337131088785
/*     */     //   998: lload_1
/*     */     //   999: lxor
/*     */     //   1000: <illegal opcode> l : (IJ)Ljava/lang/String;
/*     */     //   1005: invokevirtual append : (Ljava/lang/String;)Ljava/lang/StringBuilder;
/*     */     //   1008: iload #32
/*     */     //   1010: invokevirtual append : (I)Ljava/lang/StringBuilder;
/*     */     //   1013: invokevirtual toString : ()Ljava/lang/String;
/*     */     //   1016: invokespecial <init> : (Ljava/lang/String;)V
/*     */     //   1019: athrow
/*     */     //   1020: ldc2_w 6609296466686193024
/*     */     //   1023: lload_1
/*     */     //   1024: <illegal opcode> w : (Ljava/lang/Exception;JJ)Ljava/lang/Exception;
/*     */     //   1029: athrow
/*     */     //   1030: aload #38
/*     */     //   1032: astore #29
/*     */     //   1034: aload #34
/*     */     //   1036: astore #33
/*     */     //   1038: goto -> 185
/*     */     // Line number table:
/*     */     //   Java source line number -> byte code offset
/*     */     //   #122	-> 156
/*     */     //   #60	-> 164
/*     */     //   #83	-> 172
/*     */     //   #47	-> 179
/*     */     //   #125	-> 182
/*     */     //   #57	-> 185
/*     */     //   #120	-> 194
/*     */     //   #39	-> 208
/*     */     //   #27	-> 239
/*     */     //   #73	-> 242
/*     */     //   #59	-> 256
/*     */     //   #55	-> 259
/*     */     //   #123	-> 288
/*     */     //   #66	-> 317
/*     */     //   #9	-> 319
/*     */     //   #78	-> 364
/*     */     //   #77	-> 380
/*     */     //   #90	-> 390
/*     */     //   #85	-> 406
/*     */     //   #51	-> 408
/*     */     //   #121	-> 441
/*     */     //   #87	-> 495
/*     */     //   #64	-> 505
/*     */     //   #105	-> 521
/*     */     //   #92	-> 534
/*     */     //   #86	-> 563
/*     */     //   #111	-> 586
/*     */     //   #100	-> 593
/*     */     //   #61	-> 597
/*     */     //   #95	-> 600
/*     */     //   #24	-> 609
/*     */     //   #53	-> 612
/*     */     //   #69	-> 632
/*     */     //   #127	-> 642
/*     */     //   #32	-> 679
/*     */     //   #124	-> 695
/*     */     //   #30	-> 718
/*     */     //   #117	-> 768
/*     */     //   #18	-> 790
/*     */     //   #67	-> 793
/*     */     //   #5	-> 800
/*     */     //   #91	-> 868
/*     */     //   #113	-> 881
/*     */     //   #25	-> 893
/*     */     //   #12	-> 927
/*     */     //   #79	-> 947
/*     */     //   #82	-> 981
/*     */     //   #72	-> 1030
/*     */     //   #54	-> 1034
/*     */     //   #14	-> 1038
/*     */     // Exception table:
/*     */     //   from	to	target	type
/*     */     //   199	229	229	me/konsolas/aac/jj
/*     */     //   242	259	317	me/konsolas/aac/jj
/*     */     //   242	259	406	java/io/IOException
/*     */     //   242	259	521	finally
/*     */     //   259	275	278	me/konsolas/aac/jj
/*     */     //   270	301	304	me/konsolas/aac/jj
/*     */     //   317	380	521	finally
/*     */     //   319	351	354	me/konsolas/aac/jj
/*     */     //   348	370	370	me/konsolas/aac/jj
/*     */     //   406	495	521	finally
/*     */     //   408	421	424	me/konsolas/aac/jj
/*     */     //   441	469	472	me/konsolas/aac/jj
/*     */     //   466	485	485	me/konsolas/aac/jj
/*     */     //   521	523	521	finally
/*     */     //   523	547	550	me/konsolas/aac/jj
/*     */     //   563	573	576	me/konsolas/aac/jj
/*     */     //   570	617	620	me/konsolas/aac/jj
/*     */     //   642	652	655	me/konsolas/aac/jj
/*     */     //   695	705	708	me/konsolas/aac/jj
/*     */     //   702	731	734	me/konsolas/aac/jj
/*     */     //   718	747	750	me/konsolas/aac/jj
/*     */     //   762	777	780	me/konsolas/aac/jj
/*     */     //   800	810	813	me/konsolas/aac/jj
/*     */     //   805	839	842	me/konsolas/aac/jj
/*     */     //   823	855	858	me/konsolas/aac/jj
/*     */     //   852	871	871	me/konsolas/aac/jj
/*     */     //   900	914	917	me/konsolas/aac/jj
/*     */     //   911	934	937	me/konsolas/aac/jj
/*     */     //   947	963	966	me/konsolas/aac/jj
/*     */     //   976	1020	1020	me/konsolas/aac/jj
/*     */   }
/*     */   
/*     */   private boolean a(long paramLong, IOException paramIOException, fO paramfO, boolean paramBoolean, s params) {
/*     */     // Byte code:
/*     */     //   0: getstatic me/konsolas/aac/lc.c : J
/*     */     //   3: lload_1
/*     */     //   4: lxor
/*     */     //   5: lstore_1
/*     */     //   6: lload_1
/*     */     //   7: dup2
/*     */     //   8: ldc2_w 128657611700988
/*     */     //   11: lxor
/*     */     //   12: lstore #7
/*     */     //   14: dup2
/*     */     //   15: ldc2_w 12538616223595
/*     */     //   18: lxor
/*     */     //   19: lstore #9
/*     */     //   21: dup2
/*     */     //   22: ldc2_w 105847454395459
/*     */     //   25: lxor
/*     */     //   26: dup2
/*     */     //   27: bipush #48
/*     */     //   29: lushr
/*     */     //   30: l2i
/*     */     //   31: istore #11
/*     */     //   33: dup2
/*     */     //   34: bipush #16
/*     */     //   36: lshl
/*     */     //   37: bipush #48
/*     */     //   39: lushr
/*     */     //   40: l2i
/*     */     //   41: istore #12
/*     */     //   43: dup2
/*     */     //   44: bipush #32
/*     */     //   46: lshl
/*     */     //   47: bipush #32
/*     */     //   49: lushr
/*     */     //   50: l2i
/*     */     //   51: istore #13
/*     */     //   53: pop2
/*     */     //   54: pop2
/*     */     //   55: ldc2_w -5082595130053220775
/*     */     //   58: lload_1
/*     */     //   59: <illegal opcode> w : (JJ)Z
/*     */     //   64: istore #14
/*     */     //   66: aload_0
/*     */     //   67: getfield a : Lme/konsolas/aac/gf;
/*     */     //   70: invokevirtual c : ()Z
/*     */     //   73: iload #14
/*     */     //   75: ifne -> 108
/*     */     //   78: ifne -> 106
/*     */     //   81: goto -> 94
/*     */     //   84: ldc2_w -5062342382407659642
/*     */     //   87: lload_1
/*     */     //   88: <illegal opcode> w : (Ljava/lang/Exception;JJ)Ljava/lang/Exception;
/*     */     //   93: athrow
/*     */     //   94: iconst_0
/*     */     //   95: ireturn
/*     */     //   96: ldc2_w -5062342382407659642
/*     */     //   99: lload_1
/*     */     //   100: <illegal opcode> w : (Ljava/lang/Exception;JJ)Ljava/lang/Exception;
/*     */     //   105: athrow
/*     */     //   106: iload #5
/*     */     //   108: iload #14
/*     */     //   110: ifne -> 205
/*     */     //   113: ifeq -> 190
/*     */     //   116: goto -> 129
/*     */     //   119: ldc2_w -5062342382407659642
/*     */     //   122: lload_1
/*     */     //   123: <illegal opcode> w : (Ljava/lang/Exception;JJ)Ljava/lang/Exception;
/*     */     //   128: athrow
/*     */     //   129: aload_0
/*     */     //   130: aload_3
/*     */     //   131: lload #9
/*     */     //   133: aload #6
/*     */     //   135: invokespecial a : (Ljava/io/IOException;JLme/konsolas/aac/s;)Z
/*     */     //   138: iload #14
/*     */     //   140: lload_1
/*     */     //   141: lconst_0
/*     */     //   142: lcmp
/*     */     //   143: ifle -> 207
/*     */     //   146: ifne -> 205
/*     */     //   149: goto -> 162
/*     */     //   152: ldc2_w -5062342382407659642
/*     */     //   155: lload_1
/*     */     //   156: <illegal opcode> w : (Ljava/lang/Exception;JJ)Ljava/lang/Exception;
/*     */     //   161: athrow
/*     */     //   162: ifeq -> 190
/*     */     //   165: goto -> 178
/*     */     //   168: ldc2_w -5062342382407659642
/*     */     //   171: lload_1
/*     */     //   172: <illegal opcode> w : (Ljava/lang/Exception;JJ)Ljava/lang/Exception;
/*     */     //   177: athrow
/*     */     //   178: iconst_0
/*     */     //   179: ireturn
/*     */     //   180: ldc2_w -5062342382407659642
/*     */     //   183: lload_1
/*     */     //   184: <illegal opcode> w : (Ljava/lang/Exception;JJ)Ljava/lang/Exception;
/*     */     //   189: athrow
/*     */     //   190: aload_0
/*     */     //   191: aload_3
/*     */     //   192: iload #11
/*     */     //   194: i2s
/*     */     //   195: iload #5
/*     */     //   197: iload #12
/*     */     //   199: i2s
/*     */     //   200: iload #13
/*     */     //   202: invokespecial a : (Ljava/io/IOException;SZSI)Z
/*     */     //   205: iload #14
/*     */     //   207: lload_1
/*     */     //   208: lconst_0
/*     */     //   209: lcmp
/*     */     //   210: iflt -> 253
/*     */     //   213: ifne -> 251
/*     */     //   216: ifne -> 244
/*     */     //   219: goto -> 232
/*     */     //   222: ldc2_w -5062342382407659642
/*     */     //   225: lload_1
/*     */     //   226: <illegal opcode> w : (Ljava/lang/Exception;JJ)Ljava/lang/Exception;
/*     */     //   231: athrow
/*     */     //   232: iconst_0
/*     */     //   233: ireturn
/*     */     //   234: ldc2_w -5062342382407659642
/*     */     //   237: lload_1
/*     */     //   238: <illegal opcode> w : (Ljava/lang/Exception;JJ)Ljava/lang/Exception;
/*     */     //   243: athrow
/*     */     //   244: aload #4
/*     */     //   246: lload #7
/*     */     //   248: invokevirtual a : (J)Z
/*     */     //   251: iload #14
/*     */     //   253: ifne -> 285
/*     */     //   256: ifne -> 284
/*     */     //   259: goto -> 272
/*     */     //   262: ldc2_w -5062342382407659642
/*     */     //   265: lload_1
/*     */     //   266: <illegal opcode> w : (Ljava/lang/Exception;JJ)Ljava/lang/Exception;
/*     */     //   271: athrow
/*     */     //   272: iconst_0
/*     */     //   273: ireturn
/*     */     //   274: ldc2_w -5062342382407659642
/*     */     //   277: lload_1
/*     */     //   278: <illegal opcode> w : (Ljava/lang/Exception;JJ)Ljava/lang/Exception;
/*     */     //   283: athrow
/*     */     //   284: iconst_1
/*     */     //   285: ireturn
/*     */     // Line number table:
/*     */     //   Java source line number -> byte code offset
/*     */     //   #126	-> 66
/*     */     //   #107	-> 106
/*     */     //   #3	-> 190
/*     */     //   #116	-> 244
/*     */     //   #22	-> 284
/*     */     // Exception table:
/*     */     //   from	to	target	type
/*     */     //   66	81	84	me/konsolas/aac/jj
/*     */     //   78	96	96	me/konsolas/aac/jj
/*     */     //   108	116	119	me/konsolas/aac/jj
/*     */     //   113	149	152	me/konsolas/aac/jj
/*     */     //   129	165	168	me/konsolas/aac/jj
/*     */     //   162	180	180	me/konsolas/aac/jj
/*     */     //   205	219	222	me/konsolas/aac/jj
/*     */     //   216	234	234	me/konsolas/aac/jj
/*     */     //   251	259	262	me/konsolas/aac/jj
/*     */     //   256	274	274	me/konsolas/aac/jj
/*     */   }
/*     */   
/*     */   static {
/*     */     long l = c ^ 0x46C1032A272FL;
/*     */     "?".toCharArray()[14] = (char)("?".toCharArray()[14] ^ 0xF02);
/*     */     "".toCharArray()[0] = (char)("".toCharArray()[0] ^ 0x7786);
/*     */     (new byte[8])[0] = (byte)(int)(l >>> 56L);
/*     */     for (byte b1 = 1; b1 < 8; b1++)
/*     */       (new byte[8])[b1] = (byte)(int)(l << b1 * 8 >>> 56L); 
/*     */     Cipher cipher;
/*     */     (cipher = Cipher.getInstance(fW$gy.A("?".toCharArray(), (short)739, false, 1))).init(2, SecretKeyFactory.getInstance(fW$gy.A("".toCharArray(), (short)31453, false, 3)).generateSecret(new DESKeySpec(new byte[8])), new IvParameterSpec(new byte[8]));
/*     */     String[] arrayOfString = new String[13];
/*     */     boolean bool = false;
/*     */     "??????????Er??".toCharArray()[124] = (char)("??????????Er??".toCharArray()[124] ^ 0x765);
/*     */     String str;
/*     */     int i = (str = fW$gy.A("??????????Er??".toCharArray(), (short)8746, false, 4)).length();
/*     */     byte b2 = 24;
/*     */     byte b = -1;
/*     */     while (true);
/*     */   }
/*     */   
/*     */   private static Exception a(Exception paramException) {
/*     */     return paramException;
/*     */   }
/*     */   
/*     */   private static String a(byte[] paramArrayOfbyte) {
/*     */     byte b1 = 0;
/*     */     int i;
/*     */     char[] arrayOfChar = new char[i = paramArrayOfbyte.length];
/*     */     for (byte b2 = 0; b2 < i; b2++) {
/*     */       int j;
/*     */       if ((j = 0xFF & paramArrayOfbyte[b2]) < 192) {
/*     */         arrayOfChar[b1++] = (char)j;
/*     */       } else if (j < 224) {
/*     */         char c = (char)((char)(j & 0x1F) << 6);
/*     */         j = paramArrayOfbyte[++b2];
/*     */         c = (char)(c | (char)(j & 0x3F));
/*     */         arrayOfChar[b1++] = c;
/*     */       } else if (b2 < i - 2) {
/*     */         char c = (char)((char)(j & 0xF) << 12);
/*     */         j = paramArrayOfbyte[++b2];
/*     */         c = (char)(c | (char)(j & 0x3F) << 6);
/*     */         j = paramArrayOfbyte[++b2];
/*     */         c = (char)(c | (char)(j & 0x3F));
/*     */         arrayOfChar[b1++] = c;
/*     */       } 
/*     */     } 
/*     */     return new String(arrayOfChar, 0, b1);
/*     */   }
/*     */   
/*     */   private static String a(int paramInt, long paramLong) {
/*     */     int i = paramInt ^ (int)(paramLong & 0x7FFFL) ^ 0x50D2;
/*     */     if (e[i] == null) {
/*     */       Object[] arrayOfObject;
/*     */       try {
/*     */         Long long_ = Long.valueOf(Thread.currentThread().getId());
/*     */         arrayOfObject = (Object[])f.get(long_);
/*     */         if (arrayOfObject == null) {
/*     */           arrayOfObject = new Object[3];
/*     */           "".toCharArray()[4] = (char)("".toCharArray()[4] ^ 0x675E);
/*     */           arrayOfObject[0] = Cipher.getInstance(fW$gy.A("".toCharArray(), (short)10402, true, 1));
/*     */           "".toCharArray()[0] = (char)("".toCharArray()[0] ^ 0x2203);
/*     */           arrayOfObject[1] = SecretKeyFactory.getInstance(fW$gy.A("".toCharArray(), (short)8613, false, 4));
/*     */           arrayOfObject[2] = new IvParameterSpec(new byte[8]);
/*     */           f.put(long_, arrayOfObject);
/*     */         } 
/*     */       } catch (Exception exception) {
/*     */         "?".toCharArray()[11] = (char)("?".toCharArray()[11] ^ 0x6066);
/*     */         throw new RuntimeException(fW$gy.A("?".toCharArray(), (short)21398, false, 5), exception);
/*     */       } 
/*     */       byte[] arrayOfByte1 = new byte[8];
/*     */       arrayOfByte1[0] = (byte)(int)(paramLong >>> 56L);
/*     */       for (byte b = 1; b < 8; b++)
/*     */         arrayOfByte1[b] = (byte)(int)(paramLong << b * 8 >>> 56L); 
/*     */       DESKeySpec dESKeySpec = new DESKeySpec(arrayOfByte1);
/*     */       SecretKey secretKey = ((SecretKeyFactory)arrayOfObject[1]).generateSecret(dESKeySpec);
/*     */       ((Cipher)arrayOfObject[0]).init(2, secretKey, (IvParameterSpec)arrayOfObject[2]);
/*     */       "".toCharArray()[1] = (char)("".toCharArray()[1] ^ 0xBDA);
/*     */       byte[] arrayOfByte2 = d[i].getBytes(fW$gy.A("".toCharArray(), (short)4441, false, 5));
/*     */       e[i] = a(((Cipher)arrayOfObject[0]).doFinal(arrayOfByte2));
/*     */     } 
/*     */     return e[i];
/*     */   }
/*     */   
/*     */   private static Object a(MethodHandles.Lookup paramLookup, MutableCallSite paramMutableCallSite, String paramString, Object[] paramArrayOfObject) {
/*     */     int i = ((Integer)paramArrayOfObject[0]).intValue();
/*     */     long l = ((Long)paramArrayOfObject[1]).longValue();
/*     */     String str = a(i, l);
/*     */     MethodHandle methodHandle = MethodHandles.constant(String.class, str);
/*     */     paramMutableCallSite.setTarget(MethodHandles.dropArguments(methodHandle, 0, new Class[] { int.class, long.class }));
/*     */     return str;
/*     */   }
/*     */   
/*     */   private static CallSite a(MethodHandles.Lookup paramLookup, String paramString, MethodType paramMethodType) {
/*     */     // Byte code:
/*     */     //   0: new java/lang/invoke/MutableCallSite
/*     */     //   3: dup
/*     */     //   4: aload_2
/*     */     //   5: invokespecial <init> : (Ljava/lang/invoke/MethodType;)V
/*     */     //   8: astore_3
/*     */     //   9: aload_3
/*     */     //   10: ldc_w
/*     */     //   13: ldc_w [Ljava/lang/Object;
/*     */     //   16: aload_2
/*     */     //   17: invokevirtual parameterCount : ()I
/*     */     //   20: invokevirtual asCollector : (Ljava/lang/Class;I)Ljava/lang/invoke/MethodHandle;
/*     */     //   23: iconst_0
/*     */     //   24: iconst_3
/*     */     //   25: anewarray java/lang/Object
/*     */     //   28: dup
/*     */     //   29: iconst_0
/*     */     //   30: aload_0
/*     */     //   31: aastore
/*     */     //   32: dup
/*     */     //   33: iconst_1
/*     */     //   34: aload_3
/*     */     //   35: aastore
/*     */     //   36: dup
/*     */     //   37: iconst_2
/*     */     //   38: aload_1
/*     */     //   39: aastore
/*     */     //   40: invokestatic insertArguments : (Ljava/lang/invoke/MethodHandle;I[Ljava/lang/Object;)Ljava/lang/invoke/MethodHandle;
/*     */     //   43: aload_2
/*     */     //   44: invokestatic explicitCastArguments : (Ljava/lang/invoke/MethodHandle;Ljava/lang/invoke/MethodType;)Ljava/lang/invoke/MethodHandle;
/*     */     //   47: invokevirtual setTarget : (Ljava/lang/invoke/MethodHandle;)V
/*     */     //   50: goto -> 170
/*     */     //   53: astore #4
/*     */     //   55: new java/lang/RuntimeException
/*     */     //   58: dup
/*     */     //   59: new java/lang/StringBuilder
/*     */     //   62: dup
/*     */     //   63: invokespecial <init> : ()V
/*     */     //   66: ldc_w '??'
/*     */     //   69: invokevirtual toCharArray : ()[C
/*     */     //   72: dup
/*     */     //   73: dup
/*     */     //   74: iconst_3
/*     */     //   75: dup_x1
/*     */     //   76: caload
/*     */     //   77: sipush #28809
/*     */     //   80: ixor
/*     */     //   81: i2c
/*     */     //   82: castore
/*     */     //   83: sipush #25904
/*     */     //   86: iconst_1
/*     */     //   87: iconst_2
/*     */     //   88: invokestatic G : (Ljava/lang/Object;SZB)Ljava/lang/String;
/*     */     //   91: invokevirtual append : (Ljava/lang/String;)Ljava/lang/StringBuilder;
/*     */     //   94: ldc_w ''
/*     */     //   97: invokevirtual toCharArray : ()[C
/*     */     //   100: dup
/*     */     //   101: dup
/*     */     //   102: iconst_1
/*     */     //   103: dup_x1
/*     */     //   104: caload
/*     */     //   105: sipush #28439
/*     */     //   108: ixor
/*     */     //   109: i2c
/*     */     //   110: castore
/*     */     //   111: sipush #11557
/*     */     //   114: iconst_1
/*     */     //   115: iconst_4
/*     */     //   116: invokestatic G : (Ljava/lang/Object;SZB)Ljava/lang/String;
/*     */     //   119: invokevirtual append : (Ljava/lang/String;)Ljava/lang/StringBuilder;
/*     */     //   122: aload_1
/*     */     //   123: invokevirtual append : (Ljava/lang/String;)Ljava/lang/StringBuilder;
/*     */     //   126: ldc_w ''
/*     */     //   129: invokevirtual toCharArray : ()[C
/*     */     //   132: dup
/*     */     //   133: dup
/*     */     //   134: iconst_0
/*     */     //   135: dup_x1
/*     */     //   136: caload
/*     */     //   137: sipush #22788
/*     */     //   140: ixor
/*     */     //   141: i2c
/*     */     //   142: castore
/*     */     //   143: sipush #16804
/*     */     //   146: iconst_0
/*     */     //   147: iconst_4
/*     */     //   148: invokestatic G : (Ljava/lang/Object;SZB)Ljava/lang/String;
/*     */     //   151: invokevirtual append : (Ljava/lang/String;)Ljava/lang/StringBuilder;
/*     */     //   154: aload_2
/*     */     //   155: invokevirtual toString : ()Ljava/lang/String;
/*     */     //   158: invokevirtual append : (Ljava/lang/String;)Ljava/lang/StringBuilder;
/*     */     //   161: invokevirtual toString : ()Ljava/lang/String;
/*     */     //   164: aload #4
/*     */     //   166: invokespecial <init> : (Ljava/lang/String;Ljava/lang/Throwable;)V
/*     */     //   169: athrow
/*     */     //   170: aload_3
/*     */     //   171: areturn
/*     */     // Exception table:
/*     */     //   from	to	target	type
/*     */     //   9	50	53	java/lang/Exception
/*     */   }
/*     */ }


/* Location:              C:\Users\BukkitBypass\Desktop\MatrixAC\AAC\AAC-spigot-5.2.0.jar!\me\konsolas\aac\lc.class
 * Java compiler version: 8 (52.0)
 * JD-Core Version:       1.1.3
 */