/*    */ package me.konsolas.aac;
/*    */ 
/*    */ import java.io.IOException;
/*    */ import java.lang.invoke.CallSite;
/*    */ import java.lang.invoke.MethodHandle;
/*    */ import java.lang.invoke.MethodHandles;
/*    */ import java.lang.invoke.MethodType;
/*    */ import java.lang.invoke.MutableCallSite;
/*    */ import java.util.HashMap;
/*    */ import java.util.Map;
/*    */ import javax.crypto.Cipher;
/*    */ import javax.crypto.SecretKey;
/*    */ import javax.crypto.SecretKeyFactory;
/*    */ import javax.crypto.spec.DESKeySpec;
/*    */ import javax.crypto.spec.IvParameterSpec;
/*    */ 
/*    */ public enum le
/*    */ {
/*    */   le(String paramString1) {
/* 20 */     this.b = paramString1;
/*    */   }
/*    */   
/*    */   public static final le HTTP_1_0;
/*    */   
/*    */   public static final le HTTP_1_1;
/*    */   public static final le SPDY_3;
/*    */   public static final le HTTP_2;
/*    */   public static final le H2_PRIOR_KNOWLEDGE;
/*    */   public static final le QUIC;
/*    */   private final String b;
/*    */   private static final long c;
/*    */   private static final String[] d;
/*    */   private static final String[] e;
/*    */   private static final Map f;
/*    */   
/*    */   public static le a(String paramString, long paramLong) {
/*    */     // Byte code:
/*    */     //   0: getstatic me/konsolas/aac/le.c : J
/*    */     //   3: lload_1
/*    */     //   4: lxor
/*    */     //   5: lstore_1
/*    */     //   6: ldc2_w 3166028822952553261
/*    */     //   9: lload_1
/*    */     //   10: <illegal opcode> w : (JJ)[Lme/konsolas/aac/aN;
/*    */     //   15: astore_3
/*    */     //   16: aload_0
/*    */     //   17: getstatic me/konsolas/aac/le.HTTP_1_0 : Lme/konsolas/aac/le;
/*    */     //   20: getfield b : Ljava/lang/String;
/*    */     //   23: invokevirtual equals : (Ljava/lang/Object;)Z
/*    */     //   26: aload_3
/*    */     //   27: ifnonnull -> 70
/*    */     //   30: ifeq -> 60
/*    */     //   33: goto -> 46
/*    */     //   36: ldc2_w 3027243802091397223
/*    */     //   39: lload_1
/*    */     //   40: <illegal opcode> w : (Ljava/io/IOException;JJ)Ljava/io/IOException;
/*    */     //   45: athrow
/*    */     //   46: getstatic me/konsolas/aac/le.HTTP_1_0 : Lme/konsolas/aac/le;
/*    */     //   49: areturn
/*    */     //   50: ldc2_w 3027243802091397223
/*    */     //   53: lload_1
/*    */     //   54: <illegal opcode> w : (Ljava/io/IOException;JJ)Ljava/io/IOException;
/*    */     //   59: athrow
/*    */     //   60: aload_0
/*    */     //   61: getstatic me/konsolas/aac/le.HTTP_1_1 : Lme/konsolas/aac/le;
/*    */     //   64: getfield b : Ljava/lang/String;
/*    */     //   67: invokevirtual equals : (Ljava/lang/Object;)Z
/*    */     //   70: aload_3
/*    */     //   71: lload_1
/*    */     //   72: lconst_0
/*    */     //   73: lcmp
/*    */     //   74: iflt -> 121
/*    */     //   77: ifnonnull -> 120
/*    */     //   80: ifeq -> 110
/*    */     //   83: goto -> 96
/*    */     //   86: ldc2_w 3027243802091397223
/*    */     //   89: lload_1
/*    */     //   90: <illegal opcode> w : (Ljava/io/IOException;JJ)Ljava/io/IOException;
/*    */     //   95: athrow
/*    */     //   96: getstatic me/konsolas/aac/le.HTTP_1_1 : Lme/konsolas/aac/le;
/*    */     //   99: areturn
/*    */     //   100: ldc2_w 3027243802091397223
/*    */     //   103: lload_1
/*    */     //   104: <illegal opcode> w : (Ljava/io/IOException;JJ)Ljava/io/IOException;
/*    */     //   109: athrow
/*    */     //   110: aload_0
/*    */     //   111: getstatic me/konsolas/aac/le.H2_PRIOR_KNOWLEDGE : Lme/konsolas/aac/le;
/*    */     //   114: getfield b : Ljava/lang/String;
/*    */     //   117: invokevirtual equals : (Ljava/lang/Object;)Z
/*    */     //   120: aload_3
/*    */     //   121: lload_1
/*    */     //   122: lconst_0
/*    */     //   123: lcmp
/*    */     //   124: ifle -> 171
/*    */     //   127: ifnonnull -> 170
/*    */     //   130: ifeq -> 160
/*    */     //   133: goto -> 146
/*    */     //   136: ldc2_w 3027243802091397223
/*    */     //   139: lload_1
/*    */     //   140: <illegal opcode> w : (Ljava/io/IOException;JJ)Ljava/io/IOException;
/*    */     //   145: athrow
/*    */     //   146: getstatic me/konsolas/aac/le.H2_PRIOR_KNOWLEDGE : Lme/konsolas/aac/le;
/*    */     //   149: areturn
/*    */     //   150: ldc2_w 3027243802091397223
/*    */     //   153: lload_1
/*    */     //   154: <illegal opcode> w : (Ljava/io/IOException;JJ)Ljava/io/IOException;
/*    */     //   159: athrow
/*    */     //   160: aload_0
/*    */     //   161: getstatic me/konsolas/aac/le.HTTP_2 : Lme/konsolas/aac/le;
/*    */     //   164: getfield b : Ljava/lang/String;
/*    */     //   167: invokevirtual equals : (Ljava/lang/Object;)Z
/*    */     //   170: aload_3
/*    */     //   171: lload_1
/*    */     //   172: lconst_0
/*    */     //   173: lcmp
/*    */     //   174: iflt -> 227
/*    */     //   177: ifnonnull -> 220
/*    */     //   180: ifeq -> 210
/*    */     //   183: goto -> 196
/*    */     //   186: ldc2_w 3027243802091397223
/*    */     //   189: lload_1
/*    */     //   190: <illegal opcode> w : (Ljava/io/IOException;JJ)Ljava/io/IOException;
/*    */     //   195: athrow
/*    */     //   196: getstatic me/konsolas/aac/le.HTTP_2 : Lme/konsolas/aac/le;
/*    */     //   199: areturn
/*    */     //   200: ldc2_w 3027243802091397223
/*    */     //   203: lload_1
/*    */     //   204: <illegal opcode> w : (Ljava/io/IOException;JJ)Ljava/io/IOException;
/*    */     //   209: athrow
/*    */     //   210: aload_0
/*    */     //   211: getstatic me/konsolas/aac/le.SPDY_3 : Lme/konsolas/aac/le;
/*    */     //   214: getfield b : Ljava/lang/String;
/*    */     //   217: invokevirtual equals : (Ljava/lang/Object;)Z
/*    */     //   220: lload_1
/*    */     //   221: lconst_0
/*    */     //   222: lcmp
/*    */     //   223: iflt -> 270
/*    */     //   226: aload_3
/*    */     //   227: ifnonnull -> 270
/*    */     //   230: ifeq -> 260
/*    */     //   233: goto -> 246
/*    */     //   236: ldc2_w 3027243802091397223
/*    */     //   239: lload_1
/*    */     //   240: <illegal opcode> w : (Ljava/io/IOException;JJ)Ljava/io/IOException;
/*    */     //   245: athrow
/*    */     //   246: getstatic me/konsolas/aac/le.SPDY_3 : Lme/konsolas/aac/le;
/*    */     //   249: areturn
/*    */     //   250: ldc2_w 3027243802091397223
/*    */     //   253: lload_1
/*    */     //   254: <illegal opcode> w : (Ljava/io/IOException;JJ)Ljava/io/IOException;
/*    */     //   259: athrow
/*    */     //   260: aload_0
/*    */     //   261: getstatic me/konsolas/aac/le.QUIC : Lme/konsolas/aac/le;
/*    */     //   264: getfield b : Ljava/lang/String;
/*    */     //   267: invokevirtual equals : (Ljava/lang/Object;)Z
/*    */     //   270: ifeq -> 287
/*    */     //   273: getstatic me/konsolas/aac/le.QUIC : Lme/konsolas/aac/le;
/*    */     //   276: areturn
/*    */     //   277: ldc2_w 3027243802091397223
/*    */     //   280: lload_1
/*    */     //   281: <illegal opcode> w : (Ljava/io/IOException;JJ)Ljava/io/IOException;
/*    */     //   286: athrow
/*    */     //   287: new java/io/IOException
/*    */     //   290: dup
/*    */     //   291: new java/lang/StringBuilder
/*    */     //   294: dup
/*    */     //   295: invokespecial <init> : ()V
/*    */     //   298: sipush #6071
/*    */     //   301: ldc2_w 7455543391068907236
/*    */     //   304: lload_1
/*    */     //   305: lxor
/*    */     //   306: <illegal opcode> d : (IJ)Ljava/lang/String;
/*    */     //   311: invokevirtual append : (Ljava/lang/String;)Ljava/lang/StringBuilder;
/*    */     //   314: aload_0
/*    */     //   315: invokevirtual append : (Ljava/lang/String;)Ljava/lang/StringBuilder;
/*    */     //   318: invokevirtual toString : ()Ljava/lang/String;
/*    */     //   321: invokespecial <init> : (Ljava/lang/String;)V
/*    */     //   324: athrow
/*    */     // Line number table:
/*    */     //   Java source line number -> byte code offset
/*    */     //   #7	-> 16
/*    */     //   #14	-> 60
/*    */     //   #5	-> 110
/*    */     //   #1	-> 160
/*    */     //   #9	-> 210
/*    */     //   #4	-> 260
/*    */     //   #2	-> 287
/*    */     // Exception table:
/*    */     //   from	to	target	type
/*    */     //   16	33	36	java/io/IOException
/*    */     //   30	50	50	java/io/IOException
/*    */     //   70	83	86	java/io/IOException
/*    */     //   80	100	100	java/io/IOException
/*    */     //   120	133	136	java/io/IOException
/*    */     //   130	150	150	java/io/IOException
/*    */     //   170	183	186	java/io/IOException
/*    */     //   180	200	200	java/io/IOException
/*    */     //   220	233	236	java/io/IOException
/*    */     //   230	250	250	java/io/IOException
/*    */     //   270	277	277	java/io/IOException
/*    */   }
/*    */   
/*    */   public String toString() {
/*    */     return this.b;
/*    */   }
/*    */   
/*    */   static {
/*    */     byte b1;
/*    */     long l;
/*    */     for (c = nc.a(8673732875177000854L, 3891778958779475870L, MethodHandles.lookup().lookupClass()).a(107060791529791L), l = c ^ 0x614F399DAAC2L, f = new HashMap<>(13), "厇๚氀鯺ॄϻ鱼买詘ⅇࣼĤ暡뛼멛尖∻㪩⥛".toCharArray()[7] = (char)("厇๚氀鯺ॄϻ鱼买詘ⅇࣼĤ暡뛼멛尖∻㪩⥛".toCharArray()[7] ^ 0x4E17), "ν䅍၁Ẳ".toCharArray()[1] = (char)("ν䅍၁Ẳ".toCharArray()[1] ^ 0x128), (new byte[8])[0] = (byte)(int)(l >>> 56L), b1 = 1; b1 < 8; ) {
/*    */       (new byte[8])[b1] = (byte)(int)(l << b1 * 8 >>> 56L);
/*    */       b1++;
/*    */     } 
/*    */     Cipher cipher;
/*    */     (cipher = Cipher.getInstance(hY$g6.H("厇๚氀鯺ॄϻ鱼买詘ⅇࣼĤ暡뛼멛尖∻㪩⥛".toCharArray(), (short)16119, (byte)4, (byte)1))).init(2, SecretKeyFactory.getInstance(hY$g6.H("ν䅍၁Ẳ".toCharArray(), (short)31868, (byte)2, (byte)4)).generateSecret(new DESKeySpec(new byte[8])), new IvParameterSpec(new byte[8]));
/*    */     String[] arrayOfString = new String[13];
/*    */     boolean bool = false;
/*    */     "괹癉圐섁ᚒỖ⻸䞞팢꺍醽ᨬ慚烎⩒޿䙕煔ռ쮻嵾卣᫻䱄絿ꓭ団蠀ଡ଼㫲帽庝컮퇅褋憰龌뻄홨꛰뭷⑝厛⏩䜉噵䴻?歧?腰좖醧ﮣ媾旯﷤ﻸ㡙ￗ묈脻Ⓖᢸ竊톊᩷⸏㩨娐쓈ฒ閎耬熪饹㴪≊滵ᆉ᧥㲛贵썫ꇙ걻輞嚟㾺銖땮䩜끧ᢃ塚成ꑟ륚Ⲋ溩좰磘爝皵욤菶鴷䄬?퐄갈쿮㘤惕箌?ￋ骠䲇忪筙玌擢圎軱驑⽇⧼谲閽㆕ᔙ짡ଙꆄᮤ灎탪⍎ᑑ೴ꩉ딭霧减ㆰ৻꫸굱䈐ﱬ䰝爛⼁釳鎋拸寍쇣擵?⟭妌呵∻ꮺꡅ戏咢≯ቒ씥榷蒃秈酔ឱꜗ鮬갠嵳ⵤ熩팔?肒᯼⤢巙꼳ᰒ䣹뜬将ଔ풥砮䌷騒ό蹙붶饳ዚ䰣먡㪉ß쿸⁠뚍䄖㓸簐腕冇ᜆ恖䝾랄?蚻怜橚蜬䓤誵ᰪ䟰푝栻㮎꣹蔴绶售আᇭ癹쩹擼䃔澾᠛礍䗲摍⤜䪒ᚸጞ뀘済൴ൔ歟૏娗쳖儈愁藪솻螿쟂⮝尃틯㭆䝑￲墆촡ꁥⰠ炏䁵楚㹗艙ሱ".toCharArray()[213] = (char)("괹癉圐섁ᚒỖ⻸䞞팢꺍醽ᨬ慚烎⩒޿䙕煔ռ쮻嵾卣᫻䱄絿ꓭ団蠀ଡ଼㫲帽庝컮퇅褋憰龌뻄홨꛰뭷⑝厛⏩䜉噵䴻?歧?腰좖醧ﮣ媾旯﷤ﻸ㡙ￗ묈脻Ⓖᢸ竊톊᩷⸏㩨娐쓈ฒ閎耬熪饹㴪≊滵ᆉ᧥㲛贵썫ꇙ걻輞嚟㾺銖땮䩜끧ᢃ塚成ꑟ륚Ⲋ溩좰磘爝皵욤菶鴷䄬?퐄갈쿮㘤惕箌?ￋ骠䲇忪筙玌擢圎軱驑⽇⧼谲閽㆕ᔙ짡ଙꆄᮤ灎탪⍎ᑑ೴ꩉ딭霧减ㆰ৻꫸굱䈐ﱬ䰝爛⼁釳鎋拸寍쇣擵?⟭妌呵∻ꮺꡅ戏咢≯ቒ씥榷蒃秈酔ឱꜗ鮬갠嵳ⵤ熩팔?肒᯼⤢巙꼳ᰒ䣹뜬将ଔ풥砮䌷騒ό蹙붶饳ዚ䰣먡㪉ß쿸⁠뚍䄖㓸簐腕冇ᜆ恖䝾랄?蚻怜橚蜬䓤誵ᰪ䟰푝栻㮎꣹蔴绶售আᇭ癹쩹擼䃔澾᠛礍䗲摍⤜䪒ᚸጞ뀘済൴ൔ歟૏娗쳖儈愁藪솻螿쟂⮝尃틯㭆䝑￲墆촡ꁥⰠ炏䁵楚㹗艙ሱ".toCharArray()[213] ^ 0x1781);
/*    */     String str;
/*    */     int i = (str = hY$g6.H("괹癉圐섁ᚒỖ⻸䞞팢꺍醽ᨬ慚烎⩒޿䙕煔ռ쮻嵾卣᫻䱄絿ꓭ団蠀ଡ଼㫲帽庝컮퇅褋憰龌뻄홨꛰뭷⑝厛⏩䜉噵䴻?歧?腰좖醧ﮣ媾旯﷤ﻸ㡙ￗ묈脻Ⓖᢸ竊톊᩷⸏㩨娐쓈ฒ閎耬熪饹㴪≊滵ᆉ᧥㲛贵썫ꇙ걻輞嚟㾺銖땮䩜끧ᢃ塚成ꑟ륚Ⲋ溩좰磘爝皵욤菶鴷䄬?퐄갈쿮㘤惕箌?ￋ骠䲇忪筙玌擢圎軱驑⽇⧼谲閽㆕ᔙ짡ଙꆄᮤ灎탪⍎ᑑ೴ꩉ딭霧减ㆰ৻꫸굱䈐ﱬ䰝爛⼁釳鎋拸寍쇣擵?⟭妌呵∻ꮺꡅ戏咢≯ቒ씥榷蒃秈酔ឱꜗ鮬갠嵳ⵤ熩팔?肒᯼⤢巙꼳ᰒ䣹뜬将ଔ풥砮䌷騒ό蹙붶饳ዚ䰣먡㪉ß쿸⁠뚍䄖㓸簐腕冇ᜆ恖䝾랄?蚻怜橚蜬䓤誵ᰪ䟰푝栻㮎꣹蔴绶售আᇭ癹쩹擼䃔澾᠛礍䗲摍⤜䪒ᚸጞ뀘済൴ൔ歟૏娗쳖儈愁藪솻螿쟂⮝尃틯㭆䝑￲墆촡ꁥⰠ炏䁵楚㹗艙ሱ".toCharArray(), (short)8882, (byte)3, (byte)2)).length();
/*    */     byte b2 = 24;
/*    */     byte b = -1;
/*    */     while (true);
/*    */   }
/*    */   
/*    */   private static IOException a(IOException paramIOException) {
/*    */     return paramIOException;
/*    */   }
/*    */   
/*    */   private static String a(byte[] paramArrayOfbyte) {
/*    */     byte b1 = 0;
/*    */     int i;
/*    */     char[] arrayOfChar = new char[i = paramArrayOfbyte.length];
/*    */     for (byte b2 = 0; b2 < i; b2++) {
/*    */       int j;
/*    */       if ((j = 0xFF & paramArrayOfbyte[b2]) < 192) {
/*    */         arrayOfChar[b1++] = (char)j;
/*    */       } else if (j < 224) {
/*    */         char c = (char)((char)(j & 0x1F) << 6);
/*    */         j = paramArrayOfbyte[++b2];
/*    */         c = (char)(c | (char)(j & 0x3F));
/*    */         arrayOfChar[b1++] = c;
/*    */       } else if (b2 < i - 2) {
/*    */         char c = (char)((char)(j & 0xF) << 12);
/*    */         j = paramArrayOfbyte[++b2];
/*    */         c = (char)(c | (char)(j & 0x3F) << 6);
/*    */         j = paramArrayOfbyte[++b2];
/*    */         c = (char)(c | (char)(j & 0x3F));
/*    */         arrayOfChar[b1++] = c;
/*    */       } 
/*    */     } 
/*    */     return new String(arrayOfChar, 0, b1);
/*    */   }
/*    */   
/*    */   private static String a(int paramInt, long paramLong) {
/*    */     int i = paramInt ^ (int)(paramLong & 0x7FFFL) ^ 0x5A50;
/*    */     if (e[i] == null) {
/*    */       Object[] arrayOfObject;
/*    */       try {
/*    */         Long long_ = Long.valueOf(Thread.currentThread().getId());
/*    */         arrayOfObject = (Object[])f.get(long_);
/*    */         if (arrayOfObject == null) {
/*    */           arrayOfObject = new Object[3];
/*    */           "?䊙肨쏹䘍敃ʀꝏ沄ᖒꍘᏇ땇ꆨ⢟祣㕫繛".toCharArray()[14] = (char)("?䊙肨쏹䘍敃ʀꝏ沄ᖒꍘᏇ땇ꆨ⢟祣㕫繛".toCharArray()[14] ^ 0x670C);
/*    */           arrayOfObject[0] = Cipher.getInstance(fW$gy.A("?䊙肨쏹䘍敃ʀꝏ沄ᖒꍘᏇ땇ꆨ⢟祣㕫繛".toCharArray(), (short)4711, true, 0));
/*    */           "䏭ค⁰၈".toCharArray()[0] = (char)("䏭ค⁰၈".toCharArray()[0] ^ 0x176A);
/*    */           arrayOfObject[1] = SecretKeyFactory.getInstance(fW$gy.A("䏭ค⁰၈".toCharArray(), (short)32557, false, 3));
/*    */           arrayOfObject[2] = new IvParameterSpec(new byte[8]);
/*    */           f.put(long_, arrayOfObject);
/*    */         } 
/*    */       } catch (Exception exception) {
/*    */         "꺀皴乬ⵜ嵯免㥷K推曇勭䏧묈岐➜俦ࣞ".toCharArray()[5] = (char)("꺀皴乬ⵜ嵯免㥷K推曇勭䏧묈岐➜俦ࣞ".toCharArray()[5] ^ 0x34A5);
/*    */         throw new RuntimeException(fW$gy.A("꺀皴乬ⵜ嵯免㥷K推曇勭䏧묈岐➜俦ࣞ".toCharArray(), (short)22500, true, 5), exception);
/*    */       } 
/*    */       byte[] arrayOfByte1 = new byte[8];
/*    */       arrayOfByte1[0] = (byte)(int)(paramLong >>> 56L);
/*    */       for (byte b = 1; b < 8; b++)
/*    */         arrayOfByte1[b] = (byte)(int)(paramLong << b * 8 >>> 56L); 
/*    */       DESKeySpec dESKeySpec = new DESKeySpec(arrayOfByte1);
/*    */       SecretKey secretKey = ((SecretKeyFactory)arrayOfObject[1]).generateSecret(dESKeySpec);
/*    */       ((Cipher)arrayOfObject[0]).init(2, secretKey, (IvParameterSpec)arrayOfObject[2]);
/*    */       "ᰯ꣨盠饎磌⳧͋ቱ‶?紃".toCharArray()[5] = (char)("ᰯ꣨盠饎磌⳧͋ቱ‶?紃".toCharArray()[5] ^ 0x76D7);
/*    */       byte[] arrayOfByte2 = d[i].getBytes(fW$gy.A("ᰯ꣨盠饎磌⳧͋ቱ‶?紃".toCharArray(), (short)8178, true, 5));
/*    */       e[i] = a(((Cipher)arrayOfObject[0]).doFinal(arrayOfByte2));
/*    */     } 
/*    */     return e[i];
/*    */   }
/*    */   
/*    */   private static Object a(MethodHandles.Lookup paramLookup, MutableCallSite paramMutableCallSite, String paramString, Object[] paramArrayOfObject) {
/*    */     int i = ((Integer)paramArrayOfObject[0]).intValue();
/*    */     long l = ((Long)paramArrayOfObject[1]).longValue();
/*    */     String str = a(i, l);
/*    */     MethodHandle methodHandle = MethodHandles.constant(String.class, str);
/*    */     paramMutableCallSite.setTarget(MethodHandles.dropArguments(methodHandle, 0, new Class[] { int.class, long.class }));
/*    */     return str;
/*    */   }
/*    */   
/*    */   private static CallSite a(MethodHandles.Lookup paramLookup, String paramString, MethodType paramMethodType) {
/*    */     // Byte code:
/*    */     //   0: new java/lang/invoke/MutableCallSite
/*    */     //   3: dup
/*    */     //   4: aload_2
/*    */     //   5: invokespecial <init> : (Ljava/lang/invoke/MethodType;)V
/*    */     //   8: astore_3
/*    */     //   9: aload_3
/*    */     //   10: ldc_w
/*    */     //   13: ldc_w [Ljava/lang/Object;
/*    */     //   16: aload_2
/*    */     //   17: invokevirtual parameterCount : ()I
/*    */     //   20: invokevirtual asCollector : (Ljava/lang/Class;I)Ljava/lang/invoke/MethodHandle;
/*    */     //   23: iconst_0
/*    */     //   24: iconst_3
/*    */     //   25: anewarray java/lang/Object
/*    */     //   28: dup
/*    */     //   29: iconst_0
/*    */     //   30: aload_0
/*    */     //   31: aastore
/*    */     //   32: dup
/*    */     //   33: iconst_1
/*    */     //   34: aload_3
/*    */     //   35: aastore
/*    */     //   36: dup
/*    */     //   37: iconst_2
/*    */     //   38: aload_1
/*    */     //   39: aastore
/*    */     //   40: invokestatic insertArguments : (Ljava/lang/invoke/MethodHandle;I[Ljava/lang/Object;)Ljava/lang/invoke/MethodHandle;
/*    */     //   43: aload_2
/*    */     //   44: invokestatic explicitCastArguments : (Ljava/lang/invoke/MethodHandle;Ljava/lang/invoke/MethodType;)Ljava/lang/invoke/MethodHandle;
/*    */     //   47: invokevirtual setTarget : (Ljava/lang/invoke/MethodHandle;)V
/*    */     //   50: goto -> 171
/*    */     //   53: astore #4
/*    */     //   55: new java/lang/RuntimeException
/*    */     //   58: dup
/*    */     //   59: new java/lang/StringBuilder
/*    */     //   62: dup
/*    */     //   63: invokespecial <init> : ()V
/*    */     //   66: ldc_w '죺秝ꂧ⩤瑛뤏웈뢈笋論꿱᪂?ȷ뙸㒗㮒'
/*    */     //   69: invokevirtual toCharArray : ()[C
/*    */     //   72: dup
/*    */     //   73: dup
/*    */     //   74: bipush #17
/*    */     //   76: dup_x1
/*    */     //   77: caload
/*    */     //   78: sipush #30425
/*    */     //   81: ixor
/*    */     //   82: i2c
/*    */     //   83: castore
/*    */     //   84: sipush #2527
/*    */     //   87: iconst_0
/*    */     //   88: iconst_1
/*    */     //   89: invokestatic G : (Ljava/lang/Object;SZB)Ljava/lang/String;
/*    */     //   92: invokevirtual append : (Ljava/lang/String;)Ljava/lang/StringBuilder;
/*    */     //   95: ldc_w '犼ف宣'
/*    */     //   98: invokevirtual toCharArray : ()[C
/*    */     //   101: dup
/*    */     //   102: dup
/*    */     //   103: iconst_2
/*    */     //   104: dup_x1
/*    */     //   105: caload
/*    */     //   106: sipush #28938
/*    */     //   109: ixor
/*    */     //   110: i2c
/*    */     //   111: castore
/*    */     //   112: sipush #12263
/*    */     //   115: iconst_1
/*    */     //   116: iconst_3
/*    */     //   117: invokestatic G : (Ljava/lang/Object;SZB)Ljava/lang/String;
/*    */     //   120: invokevirtual append : (Ljava/lang/String;)Ljava/lang/StringBuilder;
/*    */     //   123: aload_1
/*    */     //   124: invokevirtual append : (Ljava/lang/String;)Ljava/lang/StringBuilder;
/*    */     //   127: ldc_w '?Ჰ滮潑'
/*    */     //   130: invokevirtual toCharArray : ()[C
/*    */     //   133: dup
/*    */     //   134: dup
/*    */     //   135: iconst_2
/*    */     //   136: dup_x1
/*    */     //   137: caload
/*    */     //   138: sipush #4689
/*    */     //   141: ixor
/*    */     //   142: i2c
/*    */     //   143: castore
/*    */     //   144: sipush #32050
/*    */     //   147: iconst_1
/*    */     //   148: iconst_3
/*    */     //   149: invokestatic G : (Ljava/lang/Object;SZB)Ljava/lang/String;
/*    */     //   152: invokevirtual append : (Ljava/lang/String;)Ljava/lang/StringBuilder;
/*    */     //   155: aload_2
/*    */     //   156: invokevirtual toString : ()Ljava/lang/String;
/*    */     //   159: invokevirtual append : (Ljava/lang/String;)Ljava/lang/StringBuilder;
/*    */     //   162: invokevirtual toString : ()Ljava/lang/String;
/*    */     //   165: aload #4
/*    */     //   167: invokespecial <init> : (Ljava/lang/String;Ljava/lang/Throwable;)V
/*    */     //   170: athrow
/*    */     //   171: aload_3
/*    */     //   172: areturn
/*    */     // Exception table:
/*    */     //   from	to	target	type
/*    */     //   9	50	53	java/lang/Exception
/*    */   }
/*    */ }


/* Location:              C:\Users\BukkitBypass\Desktop\MatrixAC\AAC\AAC-spigot-5.2.0.jar!\me\konsolas\aac\le.class
 * Java compiler version: 8 (52.0)
 * JD-Core Version:       1.1.3
 */