/*     */ package me.konsolas.aac;public class lq { private final double c; private final double a; private final double d; private final double f; private final double b; private final double e; private static int[] g; private static final long h; private static final String[] i; private static final String[] j; private static final Map k; public boolean a(long paramLong, Vector paramVector1, Vector paramVector2) { // Byte code:
/*     */     //   0: getstatic me/konsolas/aac/lq.h : J
/*     */     //   3: lload_1
/*     */     //   4: lxor
/*     */     //   5: lstore_1
/*     */     //   6: ldc2_w -3794196301357580040
/*     */     //   9: lload_1
/*     */     //   10: <illegal opcode> w : (JJ)[I
/*     */     //   15: aload_0
/*     */     //   16: aload_3
/*     */     //   17: aload #4
/*     */     //   19: invokespecial a : (Lorg/bukkit/util/Vector;Lorg/bukkit/util/Vector;)[D
/*     */     //   22: astore #6
/*     */     //   24: astore #5
/*     */     //   26: aload #6
/*     */     //   28: iconst_0
/*     */     //   29: daload
/*     */     //   30: aload #6
/*     */     //   32: iconst_1
/*     */     //   33: daload
/*     */     //   34: invokestatic max : (DD)D
/*     */     //   37: aload #6
/*     */     //   39: iconst_2
/*     */     //   40: daload
/*     */     //   41: aload #6
/*     */     //   43: iconst_3
/*     */     //   44: daload
/*     */     //   45: invokestatic max : (DD)D
/*     */     //   48: invokestatic min : (DD)D
/*     */     //   51: aload #6
/*     */     //   53: iconst_4
/*     */     //   54: daload
/*     */     //   55: aload #6
/*     */     //   57: iconst_5
/*     */     //   58: daload
/*     */     //   59: invokestatic max : (DD)D
/*     */     //   62: invokestatic min : (DD)D
/*     */     //   65: dconst_0
/*     */     //   66: dcmpl
/*     */     //   67: aload #5
/*     */     //   69: ifnull -> 180
/*     */     //   72: iflt -> 205
/*     */     //   75: goto -> 88
/*     */     //   78: ldc2_w -3784316269368627802
/*     */     //   81: lload_1
/*     */     //   82: <illegal opcode> w : (Laacinternal/v;JJ)Laacinternal/v;
/*     */     //   87: athrow
/*     */     //   88: aload #6
/*     */     //   90: iconst_0
/*     */     //   91: daload
/*     */     //   92: aload #6
/*     */     //   94: iconst_1
/*     */     //   95: daload
/*     */     //   96: invokestatic min : (DD)D
/*     */     //   99: aload #6
/*     */     //   101: iconst_2
/*     */     //   102: daload
/*     */     //   103: aload #6
/*     */     //   105: iconst_3
/*     */     //   106: daload
/*     */     //   107: invokestatic min : (DD)D
/*     */     //   110: invokestatic max : (DD)D
/*     */     //   113: aload #6
/*     */     //   115: iconst_4
/*     */     //   116: daload
/*     */     //   117: aload #6
/*     */     //   119: iconst_5
/*     */     //   120: daload
/*     */     //   121: invokestatic min : (DD)D
/*     */     //   124: invokestatic max : (DD)D
/*     */     //   127: aload #6
/*     */     //   129: iconst_0
/*     */     //   130: daload
/*     */     //   131: aload #6
/*     */     //   133: iconst_1
/*     */     //   134: daload
/*     */     //   135: invokestatic max : (DD)D
/*     */     //   138: aload #6
/*     */     //   140: iconst_2
/*     */     //   141: daload
/*     */     //   142: aload #6
/*     */     //   144: iconst_3
/*     */     //   145: daload
/*     */     //   146: invokestatic max : (DD)D
/*     */     //   149: invokestatic min : (DD)D
/*     */     //   152: aload #6
/*     */     //   154: iconst_4
/*     */     //   155: daload
/*     */     //   156: aload #6
/*     */     //   158: iconst_5
/*     */     //   159: daload
/*     */     //   160: invokestatic max : (DD)D
/*     */     //   163: invokestatic min : (DD)D
/*     */     //   166: dcmpg
/*     */     //   167: goto -> 180
/*     */     //   170: ldc2_w -3784316269368627802
/*     */     //   173: lload_1
/*     */     //   174: <illegal opcode> w : (Laacinternal/v;JJ)Laacinternal/v;
/*     */     //   179: athrow
/*     */     //   180: aload #5
/*     */     //   182: ifnull -> 202
/*     */     //   185: ifgt -> 205
/*     */     //   188: goto -> 201
/*     */     //   191: ldc2_w -3784316269368627802
/*     */     //   194: lload_1
/*     */     //   195: <illegal opcode> w : (Laacinternal/v;JJ)Laacinternal/v;
/*     */     //   200: athrow
/*     */     //   201: iconst_1
/*     */     //   202: goto -> 206
/*     */     //   205: iconst_0
/*     */     //   206: ireturn
/*     */     // Line number table:
/*     */     //   Java source line number -> byte code offset
/*     */     //   #1	-> 15
/*     */     //   #119	-> 26
/*     */     //   #171	-> 96
/*     */     //   #71	-> 135
/*     */     //   #88	-> 206
/*     */     // Exception table:
/*     */     //   from	to	target	type
/*     */     //   26	75	78	aacinternal/v
/*     */     //   72	167	170	aacinternal/v
/*     */     //   180	188	191	aacinternal/v }
/*   2 */   public lq a() { return new lq(
/*     */ 
/*     */ 
/*     */ 
/*     */ 
/*     */ 
/*     */ 
/*     */ 
/*     */ 
/*     */ 
/*     */ 
/*     */ 
/*     */ 
/*     */ 
/*     */ 
/*     */ 
/*     */ 
/*     */ 
/*     */ 
/*     */ 
/*     */ 
/*     */ 
/*     */ 
/*     */ 
/*     */ 
/*     */ 
/*     */ 
/*     */ 
/*     */ 
/*     */ 
/*     */ 
/*     */ 
/*     */ 
/*     */ 
/*     */ 
/*     */ 
/*     */ 
/*     */ 
/*     */ 
/*     */ 
/*     */ 
/*     */ 
/*     */ 
/*     */ 
/*     */ 
/*     */ 
/*     */ 
/*     */ 
/*     */ 
/*     */ 
/*     */ 
/*     */ 
/*     */ 
/*     */ 
/*     */ 
/*     */ 
/*     */ 
/*     */ 
/*     */ 
/*     */ 
/*     */         
/*  63 */         NumberConversions.floor(this.c), 
/*     */ 
/*     */ 
/*     */ 
/*     */ 
/*     */ 
/*     */ 
/*     */ 
/*     */ 
/*     */ 
/*     */ 
/*     */ 
/*     */ 
/*     */ 
/*     */ 
/*     */ 
/*     */ 
/*     */ 
/*     */ 
/*     */ 
/*     */ 
/*     */ 
/*     */ 
/*     */ 
/*     */ 
/*     */ 
/*     */ 
/*     */ 
/*     */ 
/*     */ 
/*     */ 
/*     */ 
/*     */ 
/*     */ 
/*     */ 
/*     */ 
/*     */ 
/*     */ 
/*     */ 
/*     */ 
/*     */ 
/*     */ 
/*     */ 
/*     */ 
/*     */ 
/*     */ 
/*     */ 
/*     */ 
/*     */ 
/*     */ 
/*     */ 
/*     */ 
/*     */ 
/*     */ 
/*     */ 
/*     */ 
/*     */ 
/*     */ 
/*     */ 
/*     */ 
/*     */ 
/*     */ 
/*     */ 
/*     */ 
/*     */ 
/*     */ 
/*     */ 
/*     */ 
/*     */ 
/*     */ 
/*     */ 
/*     */ 
/*     */ 
/*     */ 
/*     */ 
/*     */ 
/*     */ 
/*     */ 
/*     */ 
/*     */ 
/*     */ 
/*     */ 
/*     */ 
/*     */ 
/*     */ 
/*     */ 
/*     */         
/* 150 */         NumberConversions.floor(this.a), 
/*     */ 
/*     */ 
/*     */ 
/*     */ 
/*     */ 
/*     */ 
/*     */ 
/*     */ 
/*     */ 
/*     */ 
/*     */ 
/*     */ 
/*     */ 
/*     */ 
/*     */ 
/*     */ 
/*     */ 
/*     */ 
/*     */ 
/*     */ 
/*     */ 
/*     */ 
/*     */ 
/*     */ 
/*     */ 
/*     */ 
/*     */ 
/*     */ 
/*     */ 
/*     */ 
/*     */ 
/*     */ 
/*     */ 
/*     */ 
/*     */ 
/*     */ 
/*     */ 
/*     */ 
/*     */ 
/*     */ 
/*     */ 
/*     */ 
/*     */ 
/*     */         
/* 195 */         NumberConversions.floor(this.d), 
/*     */ 
/*     */ 
/*     */ 
/*     */ 
/*     */ 
/*     */         
/* 202 */         NumberConversions.ceil(this.f), NumberConversions.ceil(this.b), NumberConversions.ceil(this.e)); } public double e() { return this.a; } public lq b(double paramDouble) { return new lq(this.c, paramDouble, this.d, this.f, this.b, this.e); } public lq b(double paramDouble1, double paramDouble2, double paramDouble3, long paramLong) { // Byte code:
/*     */     //   0: getstatic me/konsolas/aac/lq.h : J
/*     */     //   3: lload #7
/*     */     //   5: lxor
/*     */     //   6: lstore #7
/*     */     //   8: ldc2_w -8922357661550948467
/*     */     //   11: lload #7
/*     */     //   13: <illegal opcode> w : (JJ)[I
/*     */     //   18: astore #9
/*     */     //   20: new me/konsolas/aac/lq
/*     */     //   23: dup
/*     */     //   24: aload_0
/*     */     //   25: getfield c : D
/*     */     //   28: dload_1
/*     */     //   29: dconst_0
/*     */     //   30: dcmpg
/*     */     //   31: ifge -> 49
/*     */     //   34: dload_1
/*     */     //   35: goto -> 50
/*     */     //   38: ldc2_w -8931117392450067757
/*     */     //   41: lload #7
/*     */     //   43: <illegal opcode> w : (Laacinternal/v;JJ)Laacinternal/v;
/*     */     //   48: athrow
/*     */     //   49: dconst_0
/*     */     //   50: dadd
/*     */     //   51: aload_0
/*     */     //   52: getfield a : D
/*     */     //   55: dload_3
/*     */     //   56: dconst_0
/*     */     //   57: dcmpg
/*     */     //   58: ifge -> 65
/*     */     //   61: dload_3
/*     */     //   62: goto -> 66
/*     */     //   65: dconst_0
/*     */     //   66: dadd
/*     */     //   67: aload_0
/*     */     //   68: getfield d : D
/*     */     //   71: dload #5
/*     */     //   73: dconst_0
/*     */     //   74: dcmpg
/*     */     //   75: ifge -> 83
/*     */     //   78: dload #5
/*     */     //   80: goto -> 84
/*     */     //   83: dconst_0
/*     */     //   84: dadd
/*     */     //   85: aload_0
/*     */     //   86: getfield f : D
/*     */     //   89: dload_1
/*     */     //   90: dconst_0
/*     */     //   91: dcmpl
/*     */     //   92: ifle -> 99
/*     */     //   95: dload_1
/*     */     //   96: goto -> 100
/*     */     //   99: dconst_0
/*     */     //   100: dadd
/*     */     //   101: aload_0
/*     */     //   102: getfield b : D
/*     */     //   105: dload_3
/*     */     //   106: dconst_0
/*     */     //   107: dcmpl
/*     */     //   108: ifle -> 115
/*     */     //   111: dload_3
/*     */     //   112: goto -> 116
/*     */     //   115: dconst_0
/*     */     //   116: dadd
/*     */     //   117: aload_0
/*     */     //   118: getfield e : D
/*     */     //   121: dload #5
/*     */     //   123: dconst_0
/*     */     //   124: dcmpl
/*     */     //   125: ifle -> 133
/*     */     //   128: dload #5
/*     */     //   130: goto -> 134
/*     */     //   133: dconst_0
/*     */     //   134: dadd
/*     */     //   135: invokespecial <init> : (DDDDDD)V
/*     */     //   138: ldc2_w -8925289770066067328
/*     */     //   141: lload #7
/*     */     //   143: <illegal opcode> w : (JJ)[Lme/konsolas/aac/aN;
/*     */     //   148: ifnull -> 164
/*     */     //   151: iconst_3
/*     */     //   152: newarray int
/*     */     //   154: ldc2_w -8934004195099420890
/*     */     //   157: lload #7
/*     */     //   159: <illegal opcode> w : ([IJJ)V
/*     */     //   164: areturn
/*     */     // Line number table:
/*     */     //   Java source line number -> byte code offset
/*     */     //   #16	-> 20
/*     */     //   #131	-> 28
/*     */     //   #140	-> 55
/*     */     //   #66	-> 71
/*     */     //   #170	-> 89
/*     */     //   #89	-> 105
/*     */     //   #17	-> 121
/*     */     //   #185	-> 138
/*     */     // Exception table:
/*     */     //   from	to	target	type
/*     */     //   20	38	38	aacinternal/v } public double c() { return this.c; } public double a(long paramLong, lq paramlq, double paramDouble) { // Byte code:
/*     */     //   0: getstatic me/konsolas/aac/lq.h : J
/*     */     //   3: lload_1
/*     */     //   4: lxor
/*     */     //   5: lstore_1
/*     */     //   6: ldc2_w -8747938927892411079
/*     */     //   9: lload_1
/*     */     //   10: <illegal opcode> w : (JJ)[I
/*     */     //   15: astore #6
/*     */     //   17: aload_3
/*     */     //   18: getfield f : D
/*     */     //   21: aload #6
/*     */     //   23: ifnull -> 455
/*     */     //   26: aload_0
/*     */     //   27: getfield c : D
/*     */     //   30: dcmpl
/*     */     //   31: ifle -> 453
/*     */     //   34: goto -> 47
/*     */     //   37: ldc2_w -8738613771475394457
/*     */     //   40: lload_1
/*     */     //   41: <illegal opcode> w : (Laacinternal/v;JJ)Laacinternal/v;
/*     */     //   46: athrow
/*     */     //   47: aload_3
/*     */     //   48: getfield c : D
/*     */     //   51: aload #6
/*     */     //   53: ifnull -> 455
/*     */     //   56: goto -> 69
/*     */     //   59: ldc2_w -8738613771475394457
/*     */     //   62: lload_1
/*     */     //   63: <illegal opcode> w : (Laacinternal/v;JJ)Laacinternal/v;
/*     */     //   68: athrow
/*     */     //   69: aload_0
/*     */     //   70: getfield f : D
/*     */     //   73: dcmpg
/*     */     //   74: ifge -> 453
/*     */     //   77: goto -> 90
/*     */     //   80: ldc2_w -8738613771475394457
/*     */     //   83: lload_1
/*     */     //   84: <illegal opcode> w : (Laacinternal/v;JJ)Laacinternal/v;
/*     */     //   89: athrow
/*     */     //   90: aload_3
/*     */     //   91: getfield b : D
/*     */     //   94: aload #6
/*     */     //   96: ifnull -> 455
/*     */     //   99: goto -> 112
/*     */     //   102: ldc2_w -8738613771475394457
/*     */     //   105: lload_1
/*     */     //   106: <illegal opcode> w : (Laacinternal/v;JJ)Laacinternal/v;
/*     */     //   111: athrow
/*     */     //   112: aload_0
/*     */     //   113: getfield a : D
/*     */     //   116: dcmpl
/*     */     //   117: ifle -> 453
/*     */     //   120: goto -> 133
/*     */     //   123: ldc2_w -8738613771475394457
/*     */     //   126: lload_1
/*     */     //   127: <illegal opcode> w : (Laacinternal/v;JJ)Laacinternal/v;
/*     */     //   132: athrow
/*     */     //   133: aload_3
/*     */     //   134: getfield a : D
/*     */     //   137: aload #6
/*     */     //   139: ifnull -> 455
/*     */     //   142: goto -> 155
/*     */     //   145: ldc2_w -8738613771475394457
/*     */     //   148: lload_1
/*     */     //   149: <illegal opcode> w : (Laacinternal/v;JJ)Laacinternal/v;
/*     */     //   154: athrow
/*     */     //   155: aload_0
/*     */     //   156: getfield b : D
/*     */     //   159: dcmpg
/*     */     //   160: ifge -> 453
/*     */     //   163: goto -> 176
/*     */     //   166: ldc2_w -8738613771475394457
/*     */     //   169: lload_1
/*     */     //   170: <illegal opcode> w : (Laacinternal/v;JJ)Laacinternal/v;
/*     */     //   175: athrow
/*     */     //   176: dload #4
/*     */     //   178: dconst_0
/*     */     //   179: dcmpl
/*     */     //   180: aload #6
/*     */     //   182: ifnull -> 363
/*     */     //   185: goto -> 198
/*     */     //   188: ldc2_w -8738613771475394457
/*     */     //   191: lload_1
/*     */     //   192: <illegal opcode> w : (Laacinternal/v;JJ)Laacinternal/v;
/*     */     //   197: athrow
/*     */     //   198: ifle -> 328
/*     */     //   201: goto -> 214
/*     */     //   204: ldc2_w -8738613771475394457
/*     */     //   207: lload_1
/*     */     //   208: <illegal opcode> w : (Laacinternal/v;JJ)Laacinternal/v;
/*     */     //   213: athrow
/*     */     //   214: aload_3
/*     */     //   215: getfield e : D
/*     */     //   218: aload_0
/*     */     //   219: getfield d : D
/*     */     //   222: dcmpg
/*     */     //   223: lload_1
/*     */     //   224: lconst_0
/*     */     //   225: lcmp
/*     */     //   226: iflt -> 363
/*     */     //   229: aload #6
/*     */     //   231: ifnull -> 363
/*     */     //   234: goto -> 247
/*     */     //   237: ldc2_w -8738613771475394457
/*     */     //   240: lload_1
/*     */     //   241: <illegal opcode> w : (Laacinternal/v;JJ)Laacinternal/v;
/*     */     //   246: athrow
/*     */     //   247: ifgt -> 328
/*     */     //   250: goto -> 263
/*     */     //   253: ldc2_w -8738613771475394457
/*     */     //   256: lload_1
/*     */     //   257: <illegal opcode> w : (Laacinternal/v;JJ)Laacinternal/v;
/*     */     //   262: athrow
/*     */     //   263: aload_0
/*     */     //   264: getfield d : D
/*     */     //   267: aload_3
/*     */     //   268: getfield e : D
/*     */     //   271: dsub
/*     */     //   272: dstore #7
/*     */     //   274: dload #7
/*     */     //   276: aload #6
/*     */     //   278: ifnull -> 315
/*     */     //   281: dload #4
/*     */     //   283: dcmpg
/*     */     //   284: ifge -> 317
/*     */     //   287: goto -> 300
/*     */     //   290: ldc2_w -8738613771475394457
/*     */     //   293: lload_1
/*     */     //   294: <illegal opcode> w : (Laacinternal/v;JJ)Laacinternal/v;
/*     */     //   299: athrow
/*     */     //   300: dload #7
/*     */     //   302: goto -> 315
/*     */     //   305: ldc2_w -8738613771475394457
/*     */     //   308: lload_1
/*     */     //   309: <illegal opcode> w : (Laacinternal/v;JJ)Laacinternal/v;
/*     */     //   314: athrow
/*     */     //   315: dstore #4
/*     */     //   317: lload_1
/*     */     //   318: lconst_0
/*     */     //   319: lcmp
/*     */     //   320: iflt -> 328
/*     */     //   323: aload #6
/*     */     //   325: ifnonnull -> 450
/*     */     //   328: dload #4
/*     */     //   330: aload #6
/*     */     //   332: ifnull -> 452
/*     */     //   335: goto -> 348
/*     */     //   338: ldc2_w -8738613771475394457
/*     */     //   341: lload_1
/*     */     //   342: <illegal opcode> w : (Laacinternal/v;JJ)Laacinternal/v;
/*     */     //   347: athrow
/*     */     //   348: dconst_0
/*     */     //   349: dcmpg
/*     */     //   350: goto -> 363
/*     */     //   353: ldc2_w -8738613771475394457
/*     */     //   356: lload_1
/*     */     //   357: <illegal opcode> w : (Laacinternal/v;JJ)Laacinternal/v;
/*     */     //   362: athrow
/*     */     //   363: ifge -> 450
/*     */     //   366: aload_3
/*     */     //   367: getfield d : D
/*     */     //   370: aload #6
/*     */     //   372: ifnull -> 452
/*     */     //   375: goto -> 388
/*     */     //   378: ldc2_w -8738613771475394457
/*     */     //   381: lload_1
/*     */     //   382: <illegal opcode> w : (Laacinternal/v;JJ)Laacinternal/v;
/*     */     //   387: athrow
/*     */     //   388: aload_0
/*     */     //   389: getfield e : D
/*     */     //   392: dcmpl
/*     */     //   393: iflt -> 450
/*     */     //   396: goto -> 409
/*     */     //   399: ldc2_w -8738613771475394457
/*     */     //   402: lload_1
/*     */     //   403: <illegal opcode> w : (Laacinternal/v;JJ)Laacinternal/v;
/*     */     //   408: athrow
/*     */     //   409: aload_0
/*     */     //   410: getfield e : D
/*     */     //   413: aload_3
/*     */     //   414: getfield d : D
/*     */     //   417: dsub
/*     */     //   418: dstore #7
/*     */     //   420: dload #7
/*     */     //   422: aload #6
/*     */     //   424: ifnull -> 452
/*     */     //   427: dload #4
/*     */     //   429: dcmpl
/*     */     //   430: ifle -> 450
/*     */     //   433: goto -> 446
/*     */     //   436: ldc2_w -8738613771475394457
/*     */     //   439: lload_1
/*     */     //   440: <illegal opcode> w : (Laacinternal/v;JJ)Laacinternal/v;
/*     */     //   445: athrow
/*     */     //   446: dload #7
/*     */     //   448: dstore #4
/*     */     //   450: dload #4
/*     */     //   452: dreturn
/*     */     //   453: dload #4
/*     */     //   455: dreturn
/*     */     // Line number table:
/*     */     //   Java source line number -> byte code offset
/*     */     //   #19	-> 17
/*     */     //   #5	-> 176
/*     */     //   #26	-> 263
/*     */     //   #132	-> 274
/*     */     //   #100	-> 317
/*     */     //   #197	-> 409
/*     */     //   #75	-> 420
/*     */     //   #139	-> 446
/*     */     //   #122	-> 450
/*     */     //   #193	-> 453
/*     */     // Exception table:
/*     */     //   from	to	target	type
/*     */     //   17	34	37	aacinternal/v
/*     */     //   26	56	59	aacinternal/v
/*     */     //   47	77	80	aacinternal/v
/*     */     //   69	99	102	aacinternal/v
/*     */     //   90	120	123	aacinternal/v
/*     */     //   112	142	145	aacinternal/v
/*     */     //   133	163	166	aacinternal/v
/*     */     //   155	185	188	aacinternal/v
/*     */     //   176	201	204	aacinternal/v
/*     */     //   198	234	237	aacinternal/v
/*     */     //   214	250	253	aacinternal/v
/*     */     //   274	287	290	aacinternal/v
/*     */     //   281	302	305	aacinternal/v
/*     */     //   317	335	338	aacinternal/v
/*     */     //   328	350	353	aacinternal/v
/*     */     //   363	375	378	aacinternal/v
/*     */     //   366	396	399	aacinternal/v
/*     */     //   420	433	436	aacinternal/v } public double a() { return this.b; } public double d() { return this.d; } public lq a(double paramDouble) { return new lq(this.c, this.a, this.d, this.f, paramDouble, this.e); } public lq(Vector paramVector, double paramDouble1, double paramDouble2) { double d = paramDouble1 / 2.0D; this.c = paramVector.getX() - d; this.a = paramVector.getY(); this.d = paramVector.getZ() - d; this.f = paramVector.getX() + d; this.b = paramVector.getY() + paramDouble2; this.e = paramVector.getZ() + d; } public lq c(double paramDouble) { return new lq(this.c, this.a, this.d, this.f, this.b, paramDouble); } public lq f(double paramDouble) { return new lq(this.c, this.a, paramDouble, this.f, this.b, this.e); } public boolean equals(Object paramObject) { // Byte code:
/*     */     //   0: getstatic me/konsolas/aac/lq.h : J
/*     */     //   3: ldc2_w 132272042382846
/*     */     //   6: lxor
/*     */     //   7: lstore_2
/*     */     //   8: ldc2_w 6392992114551395096
/*     */     //   11: lload_2
/*     */     //   12: <illegal opcode> w : (JJ)[I
/*     */     //   17: astore #4
/*     */     //   19: aload_0
/*     */     //   20: aload #4
/*     */     //   22: ifnull -> 55
/*     */     //   25: aload_1
/*     */     //   26: if_acmpne -> 54
/*     */     //   29: goto -> 42
/*     */     //   32: ldc2_w 6384800812660670022
/*     */     //   35: lload_2
/*     */     //   36: <illegal opcode> w : (Laacinternal/v;JJ)Laacinternal/v;
/*     */     //   41: athrow
/*     */     //   42: iconst_1
/*     */     //   43: ireturn
/*     */     //   44: ldc2_w 6384800812660670022
/*     */     //   47: lload_2
/*     */     //   48: <illegal opcode> w : (Laacinternal/v;JJ)Laacinternal/v;
/*     */     //   53: athrow
/*     */     //   54: aload_1
/*     */     //   55: ifnull -> 100
/*     */     //   58: aload_0
/*     */     //   59: invokevirtual getClass : ()Ljava/lang/Class;
/*     */     //   62: aload #4
/*     */     //   64: ifnull -> 113
/*     */     //   67: goto -> 80
/*     */     //   70: ldc2_w 6384800812660670022
/*     */     //   73: lload_2
/*     */     //   74: <illegal opcode> w : (Laacinternal/v;JJ)Laacinternal/v;
/*     */     //   79: athrow
/*     */     //   80: aload_1
/*     */     //   81: invokevirtual getClass : ()Ljava/lang/Class;
/*     */     //   84: if_acmpeq -> 112
/*     */     //   87: goto -> 100
/*     */     //   90: ldc2_w 6384800812660670022
/*     */     //   93: lload_2
/*     */     //   94: <illegal opcode> w : (Laacinternal/v;JJ)Laacinternal/v;
/*     */     //   99: athrow
/*     */     //   100: iconst_0
/*     */     //   101: ireturn
/*     */     //   102: ldc2_w 6384800812660670022
/*     */     //   105: lload_2
/*     */     //   106: <illegal opcode> w : (Laacinternal/v;JJ)Laacinternal/v;
/*     */     //   111: athrow
/*     */     //   112: aload_1
/*     */     //   113: checkcast me/konsolas/aac/lq
/*     */     //   116: astore #5
/*     */     //   118: aload #5
/*     */     //   120: getfield c : D
/*     */     //   123: aload_0
/*     */     //   124: getfield c : D
/*     */     //   127: invokestatic compare : (DD)I
/*     */     //   130: aload #4
/*     */     //   132: ifnull -> 176
/*     */     //   135: ifne -> 385
/*     */     //   138: goto -> 151
/*     */     //   141: ldc2_w 6384800812660670022
/*     */     //   144: lload_2
/*     */     //   145: <illegal opcode> w : (Laacinternal/v;JJ)Laacinternal/v;
/*     */     //   150: athrow
/*     */     //   151: aload #5
/*     */     //   153: getfield a : D
/*     */     //   156: aload_0
/*     */     //   157: getfield a : D
/*     */     //   160: invokestatic compare : (DD)I
/*     */     //   163: goto -> 176
/*     */     //   166: ldc2_w 6384800812660670022
/*     */     //   169: lload_2
/*     */     //   170: <illegal opcode> w : (Laacinternal/v;JJ)Laacinternal/v;
/*     */     //   175: athrow
/*     */     //   176: aload #4
/*     */     //   178: ifnull -> 222
/*     */     //   181: ifne -> 385
/*     */     //   184: goto -> 197
/*     */     //   187: ldc2_w 6384800812660670022
/*     */     //   190: lload_2
/*     */     //   191: <illegal opcode> w : (Laacinternal/v;JJ)Laacinternal/v;
/*     */     //   196: athrow
/*     */     //   197: aload #5
/*     */     //   199: getfield d : D
/*     */     //   202: aload_0
/*     */     //   203: getfield d : D
/*     */     //   206: invokestatic compare : (DD)I
/*     */     //   209: goto -> 222
/*     */     //   212: ldc2_w 6384800812660670022
/*     */     //   215: lload_2
/*     */     //   216: <illegal opcode> w : (Laacinternal/v;JJ)Laacinternal/v;
/*     */     //   221: athrow
/*     */     //   222: aload #4
/*     */     //   224: ifnull -> 268
/*     */     //   227: ifne -> 385
/*     */     //   230: goto -> 243
/*     */     //   233: ldc2_w 6384800812660670022
/*     */     //   236: lload_2
/*     */     //   237: <illegal opcode> w : (Laacinternal/v;JJ)Laacinternal/v;
/*     */     //   242: athrow
/*     */     //   243: aload #5
/*     */     //   245: getfield f : D
/*     */     //   248: aload_0
/*     */     //   249: getfield f : D
/*     */     //   252: invokestatic compare : (DD)I
/*     */     //   255: goto -> 268
/*     */     //   258: ldc2_w 6384800812660670022
/*     */     //   261: lload_2
/*     */     //   262: <illegal opcode> w : (Laacinternal/v;JJ)Laacinternal/v;
/*     */     //   267: athrow
/*     */     //   268: aload #4
/*     */     //   270: ifnull -> 314
/*     */     //   273: ifne -> 385
/*     */     //   276: goto -> 289
/*     */     //   279: ldc2_w 6384800812660670022
/*     */     //   282: lload_2
/*     */     //   283: <illegal opcode> w : (Laacinternal/v;JJ)Laacinternal/v;
/*     */     //   288: athrow
/*     */     //   289: aload #5
/*     */     //   291: getfield b : D
/*     */     //   294: aload_0
/*     */     //   295: getfield b : D
/*     */     //   298: invokestatic compare : (DD)I
/*     */     //   301: goto -> 314
/*     */     //   304: ldc2_w 6384800812660670022
/*     */     //   307: lload_2
/*     */     //   308: <illegal opcode> w : (Laacinternal/v;JJ)Laacinternal/v;
/*     */     //   313: athrow
/*     */     //   314: aload #4
/*     */     //   316: ifnull -> 360
/*     */     //   319: ifne -> 385
/*     */     //   322: goto -> 335
/*     */     //   325: ldc2_w 6384800812660670022
/*     */     //   328: lload_2
/*     */     //   329: <illegal opcode> w : (Laacinternal/v;JJ)Laacinternal/v;
/*     */     //   334: athrow
/*     */     //   335: aload #5
/*     */     //   337: getfield e : D
/*     */     //   340: aload_0
/*     */     //   341: getfield e : D
/*     */     //   344: invokestatic compare : (DD)I
/*     */     //   347: goto -> 360
/*     */     //   350: ldc2_w 6384800812660670022
/*     */     //   353: lload_2
/*     */     //   354: <illegal opcode> w : (Laacinternal/v;JJ)Laacinternal/v;
/*     */     //   359: athrow
/*     */     //   360: aload #4
/*     */     //   362: ifnull -> 382
/*     */     //   365: ifne -> 385
/*     */     //   368: goto -> 381
/*     */     //   371: ldc2_w 6384800812660670022
/*     */     //   374: lload_2
/*     */     //   375: <illegal opcode> w : (Laacinternal/v;JJ)Laacinternal/v;
/*     */     //   380: athrow
/*     */     //   381: iconst_1
/*     */     //   382: goto -> 386
/*     */     //   385: iconst_0
/*     */     //   386: ireturn
/*     */     // Line number table:
/*     */     //   Java source line number -> byte code offset
/*     */     //   #39	-> 19
/*     */     //   #58	-> 54
/*     */     //   #182	-> 112
/*     */     //   #123	-> 118
/*     */     //   #87	-> 160
/*     */     //   #47	-> 206
/*     */     //   #104	-> 252
/*     */     //   #162	-> 298
/*     */     //   #84	-> 344
/*     */     //   #200	-> 386
/*     */     // Exception table:
/*     */     //   from	to	target	type
/*     */     //   19	29	32	aacinternal/v
/*     */     //   25	44	44	aacinternal/v
/*     */     //   55	67	70	aacinternal/v
/*     */     //   58	87	90	aacinternal/v
/*     */     //   80	102	102	aacinternal/v
/*     */     //   118	138	141	aacinternal/v
/*     */     //   135	163	166	aacinternal/v
/*     */     //   176	184	187	aacinternal/v
/*     */     //   181	209	212	aacinternal/v
/*     */     //   222	230	233	aacinternal/v
/*     */     //   227	255	258	aacinternal/v
/*     */     //   268	276	279	aacinternal/v
/*     */     //   273	301	304	aacinternal/v
/*     */     //   314	322	325	aacinternal/v
/*     */     //   319	347	350	aacinternal/v
/*     */     //   360	368	371	aacinternal/v } public lq c(Vector paramVector) { return a(paramVector.getX(), paramVector.getY(), paramVector.getZ()); } public static lq a(int paramInt1, int paramInt2, int paramInt3) { int i = paramInt1 << 4; int j = paramInt2 << 4; int k = paramInt3 << 4; return new lq(i, j, k, (i + 16), (j + 16), (k + 16)); } public lq a(double paramDouble1, double paramDouble2, double paramDouble3) { return new lq(this.c + paramDouble1, this.a + paramDouble2, this.d + paramDouble3, this.f + paramDouble1, this.b + paramDouble2, this.e + paramDouble3); } public String toString() { // Byte code:
/*     */     //   0: getstatic me/konsolas/aac/lq.h : J
/*     */     //   3: ldc2_w 91770331428960
/*     */     //   6: lxor
/*     */     //   7: lstore_1
/*     */     //   8: new java/lang/StringBuilder
/*     */     //   11: dup
/*     */     //   12: invokespecial <init> : ()V
/*     */     //   15: sipush #15337
/*     */     //   18: ldc2_w 4150228338353803829
/*     */     //   21: lload_1
/*     */     //   22: lxor
/*     */     //   23: <illegal opcode> z : (IJ)Ljava/lang/String;
/*     */     //   28: invokevirtual append : (Ljava/lang/String;)Ljava/lang/StringBuilder;
/*     */     //   31: aload_0
/*     */     //   32: getfield c : D
/*     */     //   35: invokevirtual append : (D)Ljava/lang/StringBuilder;
/*     */     //   38: sipush #20679
/*     */     //   41: ldc2_w 7493935069418780956
/*     */     //   44: lload_1
/*     */     //   45: lxor
/*     */     //   46: <illegal opcode> z : (IJ)Ljava/lang/String;
/*     */     //   51: invokevirtual append : (Ljava/lang/String;)Ljava/lang/StringBuilder;
/*     */     //   54: aload_0
/*     */     //   55: getfield a : D
/*     */     //   58: invokevirtual append : (D)Ljava/lang/StringBuilder;
/*     */     //   61: sipush #30657
/*     */     //   64: ldc2_w 29991930782342687
/*     */     //   67: lload_1
/*     */     //   68: lxor
/*     */     //   69: <illegal opcode> z : (IJ)Ljava/lang/String;
/*     */     //   74: invokevirtual append : (Ljava/lang/String;)Ljava/lang/StringBuilder;
/*     */     //   77: aload_0
/*     */     //   78: getfield d : D
/*     */     //   81: invokevirtual append : (D)Ljava/lang/StringBuilder;
/*     */     //   84: sipush #4150
/*     */     //   87: ldc2_w 105828046373370347
/*     */     //   90: lload_1
/*     */     //   91: lxor
/*     */     //   92: <illegal opcode> z : (IJ)Ljava/lang/String;
/*     */     //   97: invokevirtual append : (Ljava/lang/String;)Ljava/lang/StringBuilder;
/*     */     //   100: aload_0
/*     */     //   101: getfield f : D
/*     */     //   104: invokevirtual append : (D)Ljava/lang/StringBuilder;
/*     */     //   107: bipush #29
/*     */     //   109: ldc2_w 460887397143030215
/*     */     //   112: lload_1
/*     */     //   113: lxor
/*     */     //   114: <illegal opcode> z : (IJ)Ljava/lang/String;
/*     */     //   119: invokevirtual append : (Ljava/lang/String;)Ljava/lang/StringBuilder;
/*     */     //   122: aload_0
/*     */     //   123: getfield b : D
/*     */     //   126: invokevirtual append : (D)Ljava/lang/StringBuilder;
/*     */     //   129: sipush #2082
/*     */     //   132: ldc2_w 1128688641213637117
/*     */     //   135: lload_1
/*     */     //   136: lxor
/*     */     //   137: <illegal opcode> z : (IJ)Ljava/lang/String;
/*     */     //   142: invokevirtual append : (Ljava/lang/String;)Ljava/lang/StringBuilder;
/*     */     //   145: aload_0
/*     */     //   146: getfield e : D
/*     */     //   149: invokevirtual append : (D)Ljava/lang/StringBuilder;
/*     */     //   152: bipush #125
/*     */     //   154: invokevirtual append : (C)Ljava/lang/StringBuilder;
/*     */     //   157: invokevirtual toString : ()Ljava/lang/String;
/*     */     //   160: areturn
/*     */     // Line number table:
/*     */     //   Java source line number -> byte code offset
/*     */     //   #74	-> 8 }
/*     */   public boolean b(long paramLong, byte paramByte, lq paramlq) { // Byte code:
/*     */     //   0: lload_1
/*     */     //   1: bipush #8
/*     */     //   3: lshl
/*     */     //   4: iload_3
/*     */     //   5: i2l
/*     */     //   6: bipush #56
/*     */     //   8: lshl
/*     */     //   9: bipush #56
/*     */     //   11: lushr
/*     */     //   12: lor
/*     */     //   13: getstatic me/konsolas/aac/lq.h : J
/*     */     //   16: lxor
/*     */     //   17: lstore #5
/*     */     //   19: ldc2_w -1223172904272386906
/*     */     //   22: lload #5
/*     */     //   24: <illegal opcode> w : (JJ)[I
/*     */     //   29: astore #7
/*     */     //   31: aload_0
/*     */     //   32: getfield c : D
/*     */     //   35: aload #4
/*     */     //   37: getfield f : D
/*     */     //   40: dcmpg
/*     */     //   41: aload #7
/*     */     //   43: ifnull -> 87
/*     */     //   46: ifge -> 317
/*     */     //   49: goto -> 63
/*     */     //   52: ldc2_w -1214480620944619016
/*     */     //   55: lload #5
/*     */     //   57: <illegal opcode> w : (Laacinternal/v;JJ)Laacinternal/v;
/*     */     //   62: athrow
/*     */     //   63: aload_0
/*     */     //   64: getfield f : D
/*     */     //   67: aload #4
/*     */     //   69: getfield c : D
/*     */     //   72: dcmpl
/*     */     //   73: goto -> 87
/*     */     //   76: ldc2_w -1214480620944619016
/*     */     //   79: lload #5
/*     */     //   81: <illegal opcode> w : (Laacinternal/v;JJ)Laacinternal/v;
/*     */     //   86: athrow
/*     */     //   87: aload #7
/*     */     //   89: iload_3
/*     */     //   90: iflt -> 139
/*     */     //   93: ifnull -> 137
/*     */     //   96: ifle -> 317
/*     */     //   99: goto -> 113
/*     */     //   102: ldc2_w -1214480620944619016
/*     */     //   105: lload #5
/*     */     //   107: <illegal opcode> w : (Laacinternal/v;JJ)Laacinternal/v;
/*     */     //   112: athrow
/*     */     //   113: aload_0
/*     */     //   114: getfield a : D
/*     */     //   117: aload #4
/*     */     //   119: getfield b : D
/*     */     //   122: dcmpg
/*     */     //   123: goto -> 137
/*     */     //   126: ldc2_w -1214480620944619016
/*     */     //   129: lload #5
/*     */     //   131: <illegal opcode> w : (Laacinternal/v;JJ)Laacinternal/v;
/*     */     //   136: athrow
/*     */     //   137: aload #7
/*     */     //   139: lload_1
/*     */     //   140: lconst_0
/*     */     //   141: lcmp
/*     */     //   142: iflt -> 191
/*     */     //   145: ifnull -> 189
/*     */     //   148: ifge -> 317
/*     */     //   151: goto -> 165
/*     */     //   154: ldc2_w -1214480620944619016
/*     */     //   157: lload #5
/*     */     //   159: <illegal opcode> w : (Laacinternal/v;JJ)Laacinternal/v;
/*     */     //   164: athrow
/*     */     //   165: aload_0
/*     */     //   166: getfield b : D
/*     */     //   169: aload #4
/*     */     //   171: getfield a : D
/*     */     //   174: dcmpl
/*     */     //   175: goto -> 189
/*     */     //   178: ldc2_w -1214480620944619016
/*     */     //   181: lload #5
/*     */     //   183: <illegal opcode> w : (Laacinternal/v;JJ)Laacinternal/v;
/*     */     //   188: athrow
/*     */     //   189: aload #7
/*     */     //   191: iload_3
/*     */     //   192: ifle -> 241
/*     */     //   195: ifnull -> 239
/*     */     //   198: ifle -> 317
/*     */     //   201: goto -> 215
/*     */     //   204: ldc2_w -1214480620944619016
/*     */     //   207: lload #5
/*     */     //   209: <illegal opcode> w : (Laacinternal/v;JJ)Laacinternal/v;
/*     */     //   214: athrow
/*     */     //   215: aload_0
/*     */     //   216: getfield d : D
/*     */     //   219: aload #4
/*     */     //   221: getfield e : D
/*     */     //   224: dcmpg
/*     */     //   225: goto -> 239
/*     */     //   228: ldc2_w -1214480620944619016
/*     */     //   231: lload #5
/*     */     //   233: <illegal opcode> w : (Laacinternal/v;JJ)Laacinternal/v;
/*     */     //   238: athrow
/*     */     //   239: aload #7
/*     */     //   241: lload_1
/*     */     //   242: lconst_0
/*     */     //   243: lcmp
/*     */     //   244: iflt -> 293
/*     */     //   247: ifnull -> 291
/*     */     //   250: ifge -> 317
/*     */     //   253: goto -> 267
/*     */     //   256: ldc2_w -1214480620944619016
/*     */     //   259: lload #5
/*     */     //   261: <illegal opcode> w : (Laacinternal/v;JJ)Laacinternal/v;
/*     */     //   266: athrow
/*     */     //   267: aload_0
/*     */     //   268: getfield e : D
/*     */     //   271: aload #4
/*     */     //   273: getfield d : D
/*     */     //   276: dcmpl
/*     */     //   277: goto -> 291
/*     */     //   280: ldc2_w -1214480620944619016
/*     */     //   283: lload #5
/*     */     //   285: <illegal opcode> w : (Laacinternal/v;JJ)Laacinternal/v;
/*     */     //   290: athrow
/*     */     //   291: aload #7
/*     */     //   293: ifnull -> 314
/*     */     //   296: ifle -> 317
/*     */     //   299: goto -> 313
/*     */     //   302: ldc2_w -1214480620944619016
/*     */     //   305: lload #5
/*     */     //   307: <illegal opcode> w : (Laacinternal/v;JJ)Laacinternal/v;
/*     */     //   312: athrow
/*     */     //   313: iconst_1
/*     */     //   314: goto -> 318
/*     */     //   317: iconst_0
/*     */     //   318: ireturn
/*     */     // Line number table:
/*     */     //   Java source line number -> byte code offset
/*     */     //   #77	-> 31
/*     */     // Exception table:
/*     */     //   from	to	target	type
/*     */     //   31	49	52	aacinternal/v
/*     */     //   46	73	76	aacinternal/v
/*     */     //   87	99	102	aacinternal/v
/*     */     //   96	123	126	aacinternal/v
/*     */     //   137	151	154	aacinternal/v
/*     */     //   148	175	178	aacinternal/v
/*     */     //   189	201	204	aacinternal/v
/*     */     //   198	225	228	aacinternal/v
/*     */     //   239	253	256	aacinternal/v
/*     */     //   250	277	280	aacinternal/v
/*     */     //   291	299	302	aacinternal/v }
/* 204 */   private double[] a(Vector paramVector1, Vector paramVector2) { Vector vector = new Vector(1.0D / paramVector2.getX(), 1.0D / paramVector2.getY(), 1.0D / paramVector2.getZ()); double[] arrayOfDouble = new double[6]; arrayOfDouble[0] = (this.c - paramVector1.getX()) * vector.getX(); arrayOfDouble[1] = (this.f - paramVector1.getX()) * vector.getX(); arrayOfDouble[2] = (this.a - paramVector1.getY()) * vector.getY(); arrayOfDouble[3] = (this.b - paramVector1.getY()) * vector.getY(); arrayOfDouble[4] = (this.d - paramVector1.getZ()) * vector.getZ(); arrayOfDouble[5] = (this.e - paramVector1.getZ()) * vector.getZ(); return arrayOfDouble; }
/*     */   public boolean a(char paramChar, int paramInt1, Collection paramCollection, int paramInt2) { // Byte code:
/*     */     //   0: iload_1
/*     */     //   1: i2l
/*     */     //   2: bipush #48
/*     */     //   4: lshl
/*     */     //   5: iload_2
/*     */     //   6: i2l
/*     */     //   7: bipush #32
/*     */     //   9: lshl
/*     */     //   10: bipush #16
/*     */     //   12: lushr
/*     */     //   13: lor
/*     */     //   14: iload #4
/*     */     //   16: i2l
/*     */     //   17: bipush #48
/*     */     //   19: lshl
/*     */     //   20: bipush #48
/*     */     //   22: lushr
/*     */     //   23: lor
/*     */     //   24: getstatic me/konsolas/aac/lq.h : J
/*     */     //   27: lxor
/*     */     //   28: lstore #5
/*     */     //   30: lload #5
/*     */     //   32: dup2
/*     */     //   33: ldc2_w 118360146197714
/*     */     //   36: lxor
/*     */     //   37: dup2
/*     */     //   38: bipush #8
/*     */     //   40: lushr
/*     */     //   41: lstore #7
/*     */     //   43: dup2
/*     */     //   44: bipush #56
/*     */     //   46: lshl
/*     */     //   47: bipush #56
/*     */     //   49: lushr
/*     */     //   50: l2i
/*     */     //   51: istore #9
/*     */     //   53: pop2
/*     */     //   54: pop2
/*     */     //   55: ldc2_w 2303377310279062615
/*     */     //   58: lload #5
/*     */     //   60: <illegal opcode> w : (JJ)[I
/*     */     //   65: aload_3
/*     */     //   66: invokeinterface iterator : ()Ljava/util/Iterator;
/*     */     //   71: astore #11
/*     */     //   73: astore #10
/*     */     //   75: aload #11
/*     */     //   77: invokeinterface hasNext : ()Z
/*     */     //   82: ifeq -> 160
/*     */     //   85: aload #11
/*     */     //   87: invokeinterface next : ()Ljava/lang/Object;
/*     */     //   92: checkcast me/konsolas/aac/lq
/*     */     //   95: astore #12
/*     */     //   97: aload_0
/*     */     //   98: lload #7
/*     */     //   100: iload #9
/*     */     //   102: i2b
/*     */     //   103: aload #12
/*     */     //   105: invokevirtual b : (JBLme/konsolas/aac/lq;)Z
/*     */     //   108: aload #10
/*     */     //   110: iload_2
/*     */     //   111: ifle -> 119
/*     */     //   114: ifnull -> 161
/*     */     //   117: aload #10
/*     */     //   119: ifnull -> 154
/*     */     //   122: goto -> 136
/*     */     //   125: ldc2_w 2293488362060183817
/*     */     //   128: lload #5
/*     */     //   130: <illegal opcode> w : (Laacinternal/v;JJ)Laacinternal/v;
/*     */     //   135: athrow
/*     */     //   136: ifeq -> 155
/*     */     //   139: goto -> 153
/*     */     //   142: ldc2_w 2293488362060183817
/*     */     //   145: lload #5
/*     */     //   147: <illegal opcode> w : (Laacinternal/v;JJ)Laacinternal/v;
/*     */     //   152: athrow
/*     */     //   153: iconst_0
/*     */     //   154: ireturn
/*     */     //   155: aload #10
/*     */     //   157: ifnonnull -> 75
/*     */     //   160: iconst_1
/*     */     //   161: ireturn
/*     */     // Line number table:
/*     */     //   Java source line number -> byte code offset
/*     */     //   #93	-> 65
/*     */     //   #190	-> 97
/*     */     //   #91	-> 155
/*     */     //   #41	-> 160
/*     */     // Exception table:
/*     */     //   from	to	target	type
/*     */     //   97	122	125	aacinternal/v
/*     */     //   117	139	142	aacinternal/v } public boolean a(byte paramByte, int paramInt1, int paramInt2, Vector paramVector) { // Byte code:
/*     */     //   0: iload_1
/*     */     //   1: i2l
/*     */     //   2: bipush #56
/*     */     //   4: lshl
/*     */     //   5: iload_2
/*     */     //   6: i2l
/*     */     //   7: bipush #32
/*     */     //   9: lshl
/*     */     //   10: bipush #8
/*     */     //   12: lushr
/*     */     //   13: lor
/*     */     //   14: iload_3
/*     */     //   15: i2l
/*     */     //   16: bipush #40
/*     */     //   18: lshl
/*     */     //   19: bipush #40
/*     */     //   21: lushr
/*     */     //   22: lor
/*     */     //   23: getstatic me/konsolas/aac/lq.h : J
/*     */     //   26: lxor
/*     */     //   27: lstore #5
/*     */     //   29: ldc2_w -1654190797951982933
/*     */     //   32: lload #5
/*     */     //   34: <illegal opcode> w : (JJ)[I
/*     */     //   39: astore #7
/*     */     //   41: aload_0
/*     */     //   42: getfield c : D
/*     */     //   45: aload #4
/*     */     //   47: invokevirtual getX : ()D
/*     */     //   50: dcmpg
/*     */     //   51: aload #7
/*     */     //   53: ifnull -> 97
/*     */     //   56: ifge -> 323
/*     */     //   59: goto -> 73
/*     */     //   62: ldc2_w -1646060381016420363
/*     */     //   65: lload #5
/*     */     //   67: <illegal opcode> w : (Laacinternal/v;JJ)Laacinternal/v;
/*     */     //   72: athrow
/*     */     //   73: aload_0
/*     */     //   74: getfield f : D
/*     */     //   77: aload #4
/*     */     //   79: invokevirtual getX : ()D
/*     */     //   82: dcmpl
/*     */     //   83: goto -> 97
/*     */     //   86: ldc2_w -1646060381016420363
/*     */     //   89: lload #5
/*     */     //   91: <illegal opcode> w : (Laacinternal/v;JJ)Laacinternal/v;
/*     */     //   96: athrow
/*     */     //   97: aload #7
/*     */     //   99: iload_3
/*     */     //   100: iflt -> 149
/*     */     //   103: ifnull -> 147
/*     */     //   106: ifle -> 323
/*     */     //   109: goto -> 123
/*     */     //   112: ldc2_w -1646060381016420363
/*     */     //   115: lload #5
/*     */     //   117: <illegal opcode> w : (Laacinternal/v;JJ)Laacinternal/v;
/*     */     //   122: athrow
/*     */     //   123: aload_0
/*     */     //   124: getfield a : D
/*     */     //   127: aload #4
/*     */     //   129: invokevirtual getY : ()D
/*     */     //   132: dcmpg
/*     */     //   133: goto -> 147
/*     */     //   136: ldc2_w -1646060381016420363
/*     */     //   139: lload #5
/*     */     //   141: <illegal opcode> w : (Laacinternal/v;JJ)Laacinternal/v;
/*     */     //   146: athrow
/*     */     //   147: aload #7
/*     */     //   149: iload_3
/*     */     //   150: iflt -> 199
/*     */     //   153: ifnull -> 197
/*     */     //   156: ifge -> 323
/*     */     //   159: goto -> 173
/*     */     //   162: ldc2_w -1646060381016420363
/*     */     //   165: lload #5
/*     */     //   167: <illegal opcode> w : (Laacinternal/v;JJ)Laacinternal/v;
/*     */     //   172: athrow
/*     */     //   173: aload_0
/*     */     //   174: getfield b : D
/*     */     //   177: aload #4
/*     */     //   179: invokevirtual getY : ()D
/*     */     //   182: dcmpl
/*     */     //   183: goto -> 197
/*     */     //   186: ldc2_w -1646060381016420363
/*     */     //   189: lload #5
/*     */     //   191: <illegal opcode> w : (Laacinternal/v;JJ)Laacinternal/v;
/*     */     //   196: athrow
/*     */     //   197: aload #7
/*     */     //   199: iload_2
/*     */     //   200: iflt -> 249
/*     */     //   203: ifnull -> 247
/*     */     //   206: ifle -> 323
/*     */     //   209: goto -> 223
/*     */     //   212: ldc2_w -1646060381016420363
/*     */     //   215: lload #5
/*     */     //   217: <illegal opcode> w : (Laacinternal/v;JJ)Laacinternal/v;
/*     */     //   222: athrow
/*     */     //   223: aload_0
/*     */     //   224: getfield d : D
/*     */     //   227: aload #4
/*     */     //   229: invokevirtual getZ : ()D
/*     */     //   232: dcmpg
/*     */     //   233: goto -> 247
/*     */     //   236: ldc2_w -1646060381016420363
/*     */     //   239: lload #5
/*     */     //   241: <illegal opcode> w : (Laacinternal/v;JJ)Laacinternal/v;
/*     */     //   246: athrow
/*     */     //   247: aload #7
/*     */     //   249: iload_2
/*     */     //   250: ifle -> 299
/*     */     //   253: ifnull -> 297
/*     */     //   256: ifge -> 323
/*     */     //   259: goto -> 273
/*     */     //   262: ldc2_w -1646060381016420363
/*     */     //   265: lload #5
/*     */     //   267: <illegal opcode> w : (Laacinternal/v;JJ)Laacinternal/v;
/*     */     //   272: athrow
/*     */     //   273: aload_0
/*     */     //   274: getfield e : D
/*     */     //   277: aload #4
/*     */     //   279: invokevirtual getZ : ()D
/*     */     //   282: dcmpl
/*     */     //   283: goto -> 297
/*     */     //   286: ldc2_w -1646060381016420363
/*     */     //   289: lload #5
/*     */     //   291: <illegal opcode> w : (Laacinternal/v;JJ)Laacinternal/v;
/*     */     //   296: athrow
/*     */     //   297: aload #7
/*     */     //   299: ifnull -> 320
/*     */     //   302: ifle -> 323
/*     */     //   305: goto -> 319
/*     */     //   308: ldc2_w -1646060381016420363
/*     */     //   311: lload #5
/*     */     //   313: <illegal opcode> w : (Laacinternal/v;JJ)Laacinternal/v;
/*     */     //   318: athrow
/*     */     //   319: iconst_1
/*     */     //   320: goto -> 324
/*     */     //   323: iconst_0
/*     */     //   324: ireturn
/*     */     // Line number table:
/*     */     //   Java source line number -> byte code offset
/*     */     //   #96	-> 41
/*     */     //   #199	-> 129
/*     */     //   #99	-> 229
/*     */     //   #159	-> 324
/*     */     // Exception table:
/*     */     //   from	to	target	type
/*     */     //   41	59	62	aacinternal/v
/*     */     //   56	83	86	aacinternal/v
/*     */     //   97	109	112	aacinternal/v
/*     */     //   106	133	136	aacinternal/v
/*     */     //   147	159	162	aacinternal/v
/*     */     //   156	183	186	aacinternal/v
/*     */     //   197	209	212	aacinternal/v
/*     */     //   206	233	236	aacinternal/v
/*     */     //   247	259	262	aacinternal/v
/*     */     //   256	283	286	aacinternal/v
/*     */     //   297	305	308	aacinternal/v } public double c(long paramLong, lq paramlq, double paramDouble) { // Byte code:
/*     */     //   0: getstatic me/konsolas/aac/lq.h : J
/*     */     //   3: lload_1
/*     */     //   4: lxor
/*     */     //   5: lstore_1
/*     */     //   6: ldc2_w -3118908505542549737
/*     */     //   9: lload_1
/*     */     //   10: <illegal opcode> w : (JJ)[I
/*     */     //   15: astore #6
/*     */     //   17: aload_3
/*     */     //   18: getfield b : D
/*     */     //   21: aload #6
/*     */     //   23: ifnull -> 455
/*     */     //   26: aload_0
/*     */     //   27: getfield a : D
/*     */     //   30: dcmpl
/*     */     //   31: ifle -> 453
/*     */     //   34: goto -> 47
/*     */     //   37: ldc2_w -3128788107285548471
/*     */     //   40: lload_1
/*     */     //   41: <illegal opcode> w : (Laacinternal/v;JJ)Laacinternal/v;
/*     */     //   46: athrow
/*     */     //   47: aload_3
/*     */     //   48: getfield a : D
/*     */     //   51: aload #6
/*     */     //   53: ifnull -> 455
/*     */     //   56: goto -> 69
/*     */     //   59: ldc2_w -3128788107285548471
/*     */     //   62: lload_1
/*     */     //   63: <illegal opcode> w : (Laacinternal/v;JJ)Laacinternal/v;
/*     */     //   68: athrow
/*     */     //   69: aload_0
/*     */     //   70: getfield b : D
/*     */     //   73: dcmpg
/*     */     //   74: ifge -> 453
/*     */     //   77: goto -> 90
/*     */     //   80: ldc2_w -3128788107285548471
/*     */     //   83: lload_1
/*     */     //   84: <illegal opcode> w : (Laacinternal/v;JJ)Laacinternal/v;
/*     */     //   89: athrow
/*     */     //   90: aload_3
/*     */     //   91: getfield e : D
/*     */     //   94: aload #6
/*     */     //   96: ifnull -> 455
/*     */     //   99: goto -> 112
/*     */     //   102: ldc2_w -3128788107285548471
/*     */     //   105: lload_1
/*     */     //   106: <illegal opcode> w : (Laacinternal/v;JJ)Laacinternal/v;
/*     */     //   111: athrow
/*     */     //   112: aload_0
/*     */     //   113: getfield d : D
/*     */     //   116: dcmpl
/*     */     //   117: ifle -> 453
/*     */     //   120: goto -> 133
/*     */     //   123: ldc2_w -3128788107285548471
/*     */     //   126: lload_1
/*     */     //   127: <illegal opcode> w : (Laacinternal/v;JJ)Laacinternal/v;
/*     */     //   132: athrow
/*     */     //   133: aload_3
/*     */     //   134: getfield d : D
/*     */     //   137: aload #6
/*     */     //   139: ifnull -> 455
/*     */     //   142: goto -> 155
/*     */     //   145: ldc2_w -3128788107285548471
/*     */     //   148: lload_1
/*     */     //   149: <illegal opcode> w : (Laacinternal/v;JJ)Laacinternal/v;
/*     */     //   154: athrow
/*     */     //   155: aload_0
/*     */     //   156: getfield e : D
/*     */     //   159: dcmpg
/*     */     //   160: ifge -> 453
/*     */     //   163: goto -> 176
/*     */     //   166: ldc2_w -3128788107285548471
/*     */     //   169: lload_1
/*     */     //   170: <illegal opcode> w : (Laacinternal/v;JJ)Laacinternal/v;
/*     */     //   175: athrow
/*     */     //   176: dload #4
/*     */     //   178: dconst_0
/*     */     //   179: dcmpl
/*     */     //   180: aload #6
/*     */     //   182: ifnull -> 363
/*     */     //   185: goto -> 198
/*     */     //   188: ldc2_w -3128788107285548471
/*     */     //   191: lload_1
/*     */     //   192: <illegal opcode> w : (Laacinternal/v;JJ)Laacinternal/v;
/*     */     //   197: athrow
/*     */     //   198: ifle -> 328
/*     */     //   201: goto -> 214
/*     */     //   204: ldc2_w -3128788107285548471
/*     */     //   207: lload_1
/*     */     //   208: <illegal opcode> w : (Laacinternal/v;JJ)Laacinternal/v;
/*     */     //   213: athrow
/*     */     //   214: aload_3
/*     */     //   215: getfield f : D
/*     */     //   218: aload_0
/*     */     //   219: getfield c : D
/*     */     //   222: dcmpg
/*     */     //   223: lload_1
/*     */     //   224: lconst_0
/*     */     //   225: lcmp
/*     */     //   226: ifle -> 363
/*     */     //   229: aload #6
/*     */     //   231: ifnull -> 363
/*     */     //   234: goto -> 247
/*     */     //   237: ldc2_w -3128788107285548471
/*     */     //   240: lload_1
/*     */     //   241: <illegal opcode> w : (Laacinternal/v;JJ)Laacinternal/v;
/*     */     //   246: athrow
/*     */     //   247: ifgt -> 328
/*     */     //   250: goto -> 263
/*     */     //   253: ldc2_w -3128788107285548471
/*     */     //   256: lload_1
/*     */     //   257: <illegal opcode> w : (Laacinternal/v;JJ)Laacinternal/v;
/*     */     //   262: athrow
/*     */     //   263: aload_0
/*     */     //   264: getfield c : D
/*     */     //   267: aload_3
/*     */     //   268: getfield f : D
/*     */     //   271: dsub
/*     */     //   272: dstore #7
/*     */     //   274: dload #7
/*     */     //   276: aload #6
/*     */     //   278: ifnull -> 315
/*     */     //   281: dload #4
/*     */     //   283: dcmpg
/*     */     //   284: ifge -> 317
/*     */     //   287: goto -> 300
/*     */     //   290: ldc2_w -3128788107285548471
/*     */     //   293: lload_1
/*     */     //   294: <illegal opcode> w : (Laacinternal/v;JJ)Laacinternal/v;
/*     */     //   299: athrow
/*     */     //   300: dload #7
/*     */     //   302: goto -> 315
/*     */     //   305: ldc2_w -3128788107285548471
/*     */     //   308: lload_1
/*     */     //   309: <illegal opcode> w : (Laacinternal/v;JJ)Laacinternal/v;
/*     */     //   314: athrow
/*     */     //   315: dstore #4
/*     */     //   317: lload_1
/*     */     //   318: lconst_0
/*     */     //   319: lcmp
/*     */     //   320: ifle -> 328
/*     */     //   323: aload #6
/*     */     //   325: ifnonnull -> 450
/*     */     //   328: dload #4
/*     */     //   330: aload #6
/*     */     //   332: ifnull -> 452
/*     */     //   335: goto -> 348
/*     */     //   338: ldc2_w -3128788107285548471
/*     */     //   341: lload_1
/*     */     //   342: <illegal opcode> w : (Laacinternal/v;JJ)Laacinternal/v;
/*     */     //   347: athrow
/*     */     //   348: dconst_0
/*     */     //   349: dcmpg
/*     */     //   350: goto -> 363
/*     */     //   353: ldc2_w -3128788107285548471
/*     */     //   356: lload_1
/*     */     //   357: <illegal opcode> w : (Laacinternal/v;JJ)Laacinternal/v;
/*     */     //   362: athrow
/*     */     //   363: ifge -> 450
/*     */     //   366: aload_3
/*     */     //   367: getfield c : D
/*     */     //   370: aload #6
/*     */     //   372: ifnull -> 452
/*     */     //   375: goto -> 388
/*     */     //   378: ldc2_w -3128788107285548471
/*     */     //   381: lload_1
/*     */     //   382: <illegal opcode> w : (Laacinternal/v;JJ)Laacinternal/v;
/*     */     //   387: athrow
/*     */     //   388: aload_0
/*     */     //   389: getfield f : D
/*     */     //   392: dcmpl
/*     */     //   393: iflt -> 450
/*     */     //   396: goto -> 409
/*     */     //   399: ldc2_w -3128788107285548471
/*     */     //   402: lload_1
/*     */     //   403: <illegal opcode> w : (Laacinternal/v;JJ)Laacinternal/v;
/*     */     //   408: athrow
/*     */     //   409: aload_0
/*     */     //   410: getfield f : D
/*     */     //   413: aload_3
/*     */     //   414: getfield c : D
/*     */     //   417: dsub
/*     */     //   418: dstore #7
/*     */     //   420: dload #7
/*     */     //   422: aload #6
/*     */     //   424: ifnull -> 452
/*     */     //   427: dload #4
/*     */     //   429: dcmpl
/*     */     //   430: ifle -> 450
/*     */     //   433: goto -> 446
/*     */     //   436: ldc2_w -3128788107285548471
/*     */     //   439: lload_1
/*     */     //   440: <illegal opcode> w : (Laacinternal/v;JJ)Laacinternal/v;
/*     */     //   445: athrow
/*     */     //   446: dload #7
/*     */     //   448: dstore #4
/*     */     //   450: dload #4
/*     */     //   452: dreturn
/*     */     //   453: dload #4
/*     */     //   455: dreturn
/*     */     // Line number table:
/*     */     //   Java source line number -> byte code offset
/*     */     //   #107	-> 17
/*     */     //   #120	-> 176
/*     */     //   #109	-> 263
/*     */     //   #15	-> 274
/*     */     //   #86	-> 317
/*     */     //   #68	-> 409
/*     */     //   #24	-> 420
/*     */     //   #70	-> 446
/*     */     //   #7	-> 450
/*     */     //   #79	-> 453
/*     */     // Exception table:
/*     */     //   from	to	target	type
/*     */     //   17	34	37	aacinternal/v
/*     */     //   26	56	59	aacinternal/v
/*     */     //   47	77	80	aacinternal/v
/*     */     //   69	99	102	aacinternal/v
/*     */     //   90	120	123	aacinternal/v
/*     */     //   112	142	145	aacinternal/v
/*     */     //   133	163	166	aacinternal/v
/*     */     //   155	185	188	aacinternal/v
/*     */     //   176	201	204	aacinternal/v
/*     */     //   198	234	237	aacinternal/v
/*     */     //   214	250	253	aacinternal/v
/*     */     //   274	287	290	aacinternal/v
/*     */     //   281	302	305	aacinternal/v
/*     */     //   317	335	338	aacinternal/v
/*     */     //   328	350	353	aacinternal/v
/*     */     //   363	375	378	aacinternal/v
/*     */     //   366	396	399	aacinternal/v
/*     */     //   420	433	436	aacinternal/v } public boolean a(long paramLong) { // Byte code:
/*     */     //   0: getstatic me/konsolas/aac/lq.h : J
/*     */     //   3: lload_1
/*     */     //   4: lxor
/*     */     //   5: lstore_1
/*     */     //   6: ldc2_w 4200460875052610027
/*     */     //   9: lload_1
/*     */     //   10: <illegal opcode> w : (JJ)[I
/*     */     //   15: astore_3
/*     */     //   16: aload_0
/*     */     //   17: getfield c : D
/*     */     //   20: aload_0
/*     */     //   21: getfield f : D
/*     */     //   24: dcmpl
/*     */     //   25: aload_3
/*     */     //   26: ifnull -> 130
/*     */     //   29: ifeq -> 129
/*     */     //   32: goto -> 45
/*     */     //   35: ldc2_w 4208664562886106293
/*     */     //   38: lload_1
/*     */     //   39: <illegal opcode> w : (Laacinternal/v;JJ)Laacinternal/v;
/*     */     //   44: athrow
/*     */     //   45: aload_0
/*     */     //   46: getfield a : D
/*     */     //   49: aload_0
/*     */     //   50: getfield b : D
/*     */     //   53: dcmpl
/*     */     //   54: aload_3
/*     */     //   55: ifnull -> 130
/*     */     //   58: goto -> 71
/*     */     //   61: ldc2_w 4208664562886106293
/*     */     //   64: lload_1
/*     */     //   65: <illegal opcode> w : (Laacinternal/v;JJ)Laacinternal/v;
/*     */     //   70: athrow
/*     */     //   71: ifeq -> 129
/*     */     //   74: goto -> 87
/*     */     //   77: ldc2_w 4208664562886106293
/*     */     //   80: lload_1
/*     */     //   81: <illegal opcode> w : (Laacinternal/v;JJ)Laacinternal/v;
/*     */     //   86: athrow
/*     */     //   87: aload_0
/*     */     //   88: getfield d : D
/*     */     //   91: aload_0
/*     */     //   92: getfield e : D
/*     */     //   95: dcmpl
/*     */     //   96: aload_3
/*     */     //   97: ifnull -> 130
/*     */     //   100: goto -> 113
/*     */     //   103: ldc2_w 4208664562886106293
/*     */     //   106: lload_1
/*     */     //   107: <illegal opcode> w : (Laacinternal/v;JJ)Laacinternal/v;
/*     */     //   112: athrow
/*     */     //   113: ifne -> 133
/*     */     //   116: goto -> 129
/*     */     //   119: ldc2_w 4208664562886106293
/*     */     //   122: lload_1
/*     */     //   123: <illegal opcode> w : (Laacinternal/v;JJ)Laacinternal/v;
/*     */     //   128: athrow
/*     */     //   129: iconst_1
/*     */     //   130: goto -> 134
/*     */     //   133: iconst_0
/*     */     //   134: ireturn
/*     */     // Line number table:
/*     */     //   Java source line number -> byte code offset
/*     */     //   #114	-> 16
/*     */     // Exception table:
/*     */     //   from	to	target	type
/*     */     //   16	32	35	aacinternal/v
/*     */     //   29	58	61	aacinternal/v
/*     */     //   45	74	77	aacinternal/v
/*     */     //   71	100	103	aacinternal/v
/*     */     //   87	116	119	aacinternal/v } public double a(Vector paramVector) { Vector vector = new Vector(a(paramVector.getX(), this.c, this.f), a(paramVector.getY(), this.a, this.b), a(paramVector.getZ(), this.d, this.e)); return vector.distance(paramVector); } public double a(Vector paramVector1, long paramLong, Vector paramVector2) { // Byte code:
/*     */     //   0: getstatic me/konsolas/aac/lq.h : J
/*     */     //   3: lload_2
/*     */     //   4: lxor
/*     */     //   5: lstore_2
/*     */     //   6: aload_0
/*     */     //   7: aload_1
/*     */     //   8: aload #4
/*     */     //   10: invokespecial a : (Lorg/bukkit/util/Vector;Lorg/bukkit/util/Vector;)[D
/*     */     //   13: astore #6
/*     */     //   15: ldc2_w 6602919446580137986
/*     */     //   18: lload_2
/*     */     //   19: <illegal opcode> w : (JJ)[I
/*     */     //   24: aload #6
/*     */     //   26: iconst_0
/*     */     //   27: daload
/*     */     //   28: aload #6
/*     */     //   30: iconst_1
/*     */     //   31: daload
/*     */     //   32: invokestatic min : (DD)D
/*     */     //   35: aload #6
/*     */     //   37: iconst_2
/*     */     //   38: daload
/*     */     //   39: aload #6
/*     */     //   41: iconst_3
/*     */     //   42: daload
/*     */     //   43: invokestatic min : (DD)D
/*     */     //   46: invokestatic max : (DD)D
/*     */     //   49: aload #6
/*     */     //   51: iconst_4
/*     */     //   52: daload
/*     */     //   53: aload #6
/*     */     //   55: iconst_5
/*     */     //   56: daload
/*     */     //   57: invokestatic min : (DD)D
/*     */     //   60: invokestatic max : (DD)D
/*     */     //   63: dstore #7
/*     */     //   65: astore #5
/*     */     //   67: aload #6
/*     */     //   69: iconst_0
/*     */     //   70: daload
/*     */     //   71: aload #6
/*     */     //   73: iconst_1
/*     */     //   74: daload
/*     */     //   75: invokestatic max : (DD)D
/*     */     //   78: aload #6
/*     */     //   80: iconst_2
/*     */     //   81: daload
/*     */     //   82: aload #6
/*     */     //   84: iconst_3
/*     */     //   85: daload
/*     */     //   86: invokestatic max : (DD)D
/*     */     //   89: invokestatic min : (DD)D
/*     */     //   92: aload #6
/*     */     //   94: iconst_4
/*     */     //   95: daload
/*     */     //   96: aload #6
/*     */     //   98: iconst_5
/*     */     //   99: daload
/*     */     //   100: invokestatic max : (DD)D
/*     */     //   103: invokestatic min : (DD)D
/*     */     //   106: dstore #9
/*     */     //   108: dload #9
/*     */     //   110: aload #5
/*     */     //   112: ifnull -> 188
/*     */     //   115: dconst_0
/*     */     //   116: dcmpg
/*     */     //   117: iflt -> 172
/*     */     //   120: goto -> 133
/*     */     //   123: ldc2_w 6593673059727293788
/*     */     //   126: lload_2
/*     */     //   127: <illegal opcode> w : (Laacinternal/v;JJ)Laacinternal/v;
/*     */     //   132: athrow
/*     */     //   133: dload #7
/*     */     //   135: aload #5
/*     */     //   137: ifnull -> 191
/*     */     //   140: goto -> 153
/*     */     //   143: ldc2_w 6593673059727293788
/*     */     //   146: lload_2
/*     */     //   147: <illegal opcode> w : (Laacinternal/v;JJ)Laacinternal/v;
/*     */     //   152: athrow
/*     */     //   153: dload #9
/*     */     //   155: dcmpl
/*     */     //   156: ifle -> 189
/*     */     //   159: goto -> 172
/*     */     //   162: ldc2_w 6593673059727293788
/*     */     //   165: lload_2
/*     */     //   166: <illegal opcode> w : (Laacinternal/v;JJ)Laacinternal/v;
/*     */     //   171: athrow
/*     */     //   172: ldc2_w Infinity
/*     */     //   175: goto -> 188
/*     */     //   178: ldc2_w 6593673059727293788
/*     */     //   181: lload_2
/*     */     //   182: <illegal opcode> w : (Laacinternal/v;JJ)Laacinternal/v;
/*     */     //   187: athrow
/*     */     //   188: dreturn
/*     */     //   189: dload #7
/*     */     //   191: dreturn
/*     */     // Line number table:
/*     */     //   Java source line number -> byte code offset
/*     */     //   #118	-> 6
/*     */     //   #188	-> 24
/*     */     //   #130	-> 67
/*     */     //   #201	-> 108
/*     */     //   #8	-> 189
/*     */     // Exception table:
/*     */     //   from	to	target	type
/*     */     //   108	120	123	aacinternal/v
/*     */     //   115	140	143	aacinternal/v
/*     */     //   133	159	162	aacinternal/v
/*     */     //   153	175	178	aacinternal/v } public lq d(double paramDouble) { return new lq(this.c, this.a, this.d, paramDouble, this.b, this.e); } public lq a(lq paramlq, long paramLong) { // Byte code:
/*     */     //   0: getstatic me/konsolas/aac/lq.h : J
/*     */     //   3: lload_2
/*     */     //   4: lxor
/*     */     //   5: lstore_2
/*     */     //   6: lload_2
/*     */     //   7: dup2
/*     */     //   8: ldc2_w 26572843005729
/*     */     //   11: lxor
/*     */     //   12: dup2
/*     */     //   13: bipush #8
/*     */     //   15: lushr
/*     */     //   16: lstore #4
/*     */     //   18: dup2
/*     */     //   19: bipush #56
/*     */     //   21: lshl
/*     */     //   22: bipush #56
/*     */     //   24: lushr
/*     */     //   25: l2i
/*     */     //   26: istore #6
/*     */     //   28: pop2
/*     */     //   29: pop2
/*     */     //   30: ldc2_w 1442364618936082340
/*     */     //   33: lload_2
/*     */     //   34: <illegal opcode> w : (JJ)[I
/*     */     //   39: astore #7
/*     */     //   41: aload_1
/*     */     //   42: aload #7
/*     */     //   44: ifnull -> 64
/*     */     //   47: ifnull -> 94
/*     */     //   50: goto -> 63
/*     */     //   53: ldc2_w 1452243808479671034
/*     */     //   56: lload_2
/*     */     //   57: <illegal opcode> w : (Laacinternal/v;JJ)Laacinternal/v;
/*     */     //   62: athrow
/*     */     //   63: aload_0
/*     */     //   64: aload #7
/*     */     //   66: ifnull -> 179
/*     */     //   69: lload #4
/*     */     //   71: iload #6
/*     */     //   73: i2b
/*     */     //   74: aload_1
/*     */     //   75: invokevirtual b : (JBLme/konsolas/aac/lq;)Z
/*     */     //   78: ifne -> 106
/*     */     //   81: goto -> 94
/*     */     //   84: ldc2_w 1452243808479671034
/*     */     //   87: lload_2
/*     */     //   88: <illegal opcode> w : (Laacinternal/v;JJ)Laacinternal/v;
/*     */     //   93: athrow
/*     */     //   94: aconst_null
/*     */     //   95: areturn
/*     */     //   96: ldc2_w 1452243808479671034
/*     */     //   99: lload_2
/*     */     //   100: <illegal opcode> w : (Laacinternal/v;JJ)Laacinternal/v;
/*     */     //   105: athrow
/*     */     //   106: new me/konsolas/aac/lq
/*     */     //   109: dup
/*     */     //   110: aload_0
/*     */     //   111: getfield c : D
/*     */     //   114: aload_1
/*     */     //   115: getfield c : D
/*     */     //   118: invokestatic max : (DD)D
/*     */     //   121: aload_0
/*     */     //   122: getfield a : D
/*     */     //   125: aload_1
/*     */     //   126: getfield a : D
/*     */     //   129: invokestatic max : (DD)D
/*     */     //   132: aload_0
/*     */     //   133: getfield d : D
/*     */     //   136: aload_1
/*     */     //   137: getfield d : D
/*     */     //   140: invokestatic max : (DD)D
/*     */     //   143: aload_0
/*     */     //   144: getfield f : D
/*     */     //   147: aload_1
/*     */     //   148: getfield f : D
/*     */     //   151: invokestatic min : (DD)D
/*     */     //   154: aload_0
/*     */     //   155: getfield b : D
/*     */     //   158: aload_1
/*     */     //   159: getfield b : D
/*     */     //   162: invokestatic min : (DD)D
/*     */     //   165: aload_0
/*     */     //   166: getfield e : D
/*     */     //   169: aload_1
/*     */     //   170: getfield e : D
/*     */     //   173: invokestatic min : (DD)D
/*     */     //   176: invokespecial <init> : (DDDDDD)V
/*     */     //   179: areturn
/*     */     // Line number table:
/*     */     //   Java source line number -> byte code offset
/*     */     //   #126	-> 41
/*     */     //   #44	-> 106
/*     */     //   #60	-> 118
/*     */     //   #110	-> 129
/*     */     //   #30	-> 140
/*     */     //   #48	-> 151
/*     */     //   #61	-> 162
/*     */     //   #65	-> 173
/*     */     //   #37	-> 179
/*     */     // Exception table:
/*     */     //   from	to	target	type
/*     */     //   41	50	53	aacinternal/v
/*     */     //   64	81	84	aacinternal/v
/*     */     //   69	96	96	aacinternal/v } public lq b(char paramChar1, lq paramlq, char paramChar2, int paramInt) { // Byte code:
/*     */     //   0: iload_1
/*     */     //   1: i2l
/*     */     //   2: bipush #48
/*     */     //   4: lshl
/*     */     //   5: iload_3
/*     */     //   6: i2l
/*     */     //   7: bipush #48
/*     */     //   9: lshl
/*     */     //   10: bipush #16
/*     */     //   12: lushr
/*     */     //   13: lor
/*     */     //   14: iload #4
/*     */     //   16: i2l
/*     */     //   17: bipush #32
/*     */     //   19: lshl
/*     */     //   20: bipush #32
/*     */     //   22: lushr
/*     */     //   23: lor
/*     */     //   24: getstatic me/konsolas/aac/lq.h : J
/*     */     //   27: lxor
/*     */     //   28: lstore #5
/*     */     //   30: ldc2_w 5533814587378861932
/*     */     //   33: lload #5
/*     */     //   35: <illegal opcode> w : (JJ)[I
/*     */     //   40: astore #7
/*     */     //   42: aload_2
/*     */     //   43: aload #7
/*     */     //   45: ifnull -> 151
/*     */     //   48: ifnonnull -> 78
/*     */     //   51: goto -> 65
/*     */     //   54: ldc2_w 5543695820209105458
/*     */     //   57: lload #5
/*     */     //   59: <illegal opcode> w : (Laacinternal/v;JJ)Laacinternal/v;
/*     */     //   64: athrow
/*     */     //   65: aload_0
/*     */     //   66: areturn
/*     */     //   67: ldc2_w 5543695820209105458
/*     */     //   70: lload #5
/*     */     //   72: <illegal opcode> w : (Laacinternal/v;JJ)Laacinternal/v;
/*     */     //   77: athrow
/*     */     //   78: new me/konsolas/aac/lq
/*     */     //   81: dup
/*     */     //   82: aload_0
/*     */     //   83: getfield c : D
/*     */     //   86: aload_2
/*     */     //   87: getfield c : D
/*     */     //   90: invokestatic min : (DD)D
/*     */     //   93: aload_0
/*     */     //   94: getfield a : D
/*     */     //   97: aload_2
/*     */     //   98: getfield a : D
/*     */     //   101: invokestatic min : (DD)D
/*     */     //   104: aload_0
/*     */     //   105: getfield d : D
/*     */     //   108: aload_2
/*     */     //   109: getfield d : D
/*     */     //   112: invokestatic min : (DD)D
/*     */     //   115: aload_0
/*     */     //   116: getfield f : D
/*     */     //   119: aload_2
/*     */     //   120: getfield f : D
/*     */     //   123: invokestatic max : (DD)D
/*     */     //   126: aload_0
/*     */     //   127: getfield b : D
/*     */     //   130: aload_2
/*     */     //   131: getfield b : D
/*     */     //   134: invokestatic max : (DD)D
/*     */     //   137: aload_0
/*     */     //   138: getfield e : D
/*     */     //   141: aload_2
/*     */     //   142: getfield e : D
/*     */     //   145: invokestatic max : (DD)D
/*     */     //   148: invokespecial <init> : (DDDDDD)V
/*     */     //   151: areturn
/*     */     // Line number table:
/*     */     //   Java source line number -> byte code offset
/*     */     //   #128	-> 42
/*     */     //   #13	-> 78
/*     */     //   #72	-> 90
/*     */     //   #94	-> 101
/*     */     //   #102	-> 112
/*     */     //   #192	-> 123
/*     */     //   #64	-> 134
/*     */     //   #142	-> 145
/*     */     //   #112	-> 151
/*     */     // Exception table:
/*     */     //   from	to	target	type
/*     */     //   42	51	54	aacinternal/v
/*     */     //   48	67	67	aacinternal/v } public lq e(double paramDouble) { return new lq(paramDouble, this.a, this.d, this.f, this.b, this.e); } public Vector a() { return new Vector((this.c + this.f) / 2.0D, this.a, (this.d + this.e) / 2.0D); } public double b() { return this.f; } public lq a(Collection paramCollection, long paramLong) { // Byte code:
/*     */     //   0: getstatic me/konsolas/aac/lq.h : J
/*     */     //   3: lload_2
/*     */     //   4: lxor
/*     */     //   5: lstore_2
/*     */     //   6: lload_2
/*     */     //   7: dup2
/*     */     //   8: ldc2_w 74978555375707
/*     */     //   11: lxor
/*     */     //   12: dup2
/*     */     //   13: bipush #8
/*     */     //   15: lushr
/*     */     //   16: lstore #4
/*     */     //   18: dup2
/*     */     //   19: bipush #56
/*     */     //   21: lshl
/*     */     //   22: bipush #56
/*     */     //   24: lushr
/*     */     //   25: l2i
/*     */     //   26: istore #6
/*     */     //   28: pop2
/*     */     //   29: pop2
/*     */     //   30: ldc2_w -7818791144775460642
/*     */     //   33: lload_2
/*     */     //   34: <illegal opcode> w : (JJ)[I
/*     */     //   39: aload_0
/*     */     //   40: astore #8
/*     */     //   42: aload_1
/*     */     //   43: invokeinterface iterator : ()Ljava/util/Iterator;
/*     */     //   48: astore #9
/*     */     //   50: astore #7
/*     */     //   52: aload #9
/*     */     //   54: invokeinterface hasNext : ()Z
/*     */     //   59: ifeq -> 697
/*     */     //   62: aload #9
/*     */     //   64: invokeinterface next : ()Ljava/lang/Object;
/*     */     //   69: checkcast me/konsolas/aac/lq
/*     */     //   72: astore #10
/*     */     //   74: aload #10
/*     */     //   76: aload #7
/*     */     //   78: lload_2
/*     */     //   79: lconst_0
/*     */     //   80: lcmp
/*     */     //   81: ifle -> 89
/*     */     //   84: ifnull -> 699
/*     */     //   87: aload #7
/*     */     //   89: ifnull -> 146
/*     */     //   92: goto -> 105
/*     */     //   95: ldc2_w -7828043303420004992
/*     */     //   98: lload_2
/*     */     //   99: <illegal opcode> w : (Laacinternal/v;JJ)Laacinternal/v;
/*     */     //   104: athrow
/*     */     //   105: lload #4
/*     */     //   107: iload #6
/*     */     //   109: i2b
/*     */     //   110: aload #8
/*     */     //   112: invokevirtual b : (JBLme/konsolas/aac/lq;)Z
/*     */     //   115: ifeq -> 692
/*     */     //   118: goto -> 131
/*     */     //   121: ldc2_w -7828043303420004992
/*     */     //   124: lload_2
/*     */     //   125: <illegal opcode> w : (Laacinternal/v;JJ)Laacinternal/v;
/*     */     //   130: athrow
/*     */     //   131: aload #10
/*     */     //   133: goto -> 146
/*     */     //   136: ldc2_w -7828043303420004992
/*     */     //   139: lload_2
/*     */     //   140: <illegal opcode> w : (Laacinternal/v;JJ)Laacinternal/v;
/*     */     //   145: athrow
/*     */     //   146: getfield c : D
/*     */     //   149: aload #8
/*     */     //   151: getfield f : D
/*     */     //   154: dsub
/*     */     //   155: dstore #13
/*     */     //   157: aload #10
/*     */     //   159: getfield f : D
/*     */     //   162: aload #8
/*     */     //   164: getfield c : D
/*     */     //   167: dsub
/*     */     //   168: dstore #15
/*     */     //   170: dload #13
/*     */     //   172: invokestatic abs : (D)D
/*     */     //   175: aload #7
/*     */     //   177: ifnull -> 232
/*     */     //   180: dload #15
/*     */     //   182: invokestatic abs : (D)D
/*     */     //   185: dcmpl
/*     */     //   186: ifle -> 217
/*     */     //   189: goto -> 202
/*     */     //   192: ldc2_w -7828043303420004992
/*     */     //   195: lload_2
/*     */     //   196: <illegal opcode> w : (Laacinternal/v;JJ)Laacinternal/v;
/*     */     //   201: athrow
/*     */     //   202: dload #15
/*     */     //   204: dstore #11
/*     */     //   206: lload_2
/*     */     //   207: lconst_0
/*     */     //   208: lcmp
/*     */     //   209: ifle -> 247
/*     */     //   212: aload #7
/*     */     //   214: ifnonnull -> 234
/*     */     //   217: dload #13
/*     */     //   219: goto -> 232
/*     */     //   222: ldc2_w -7828043303420004992
/*     */     //   225: lload_2
/*     */     //   226: <illegal opcode> w : (Laacinternal/v;JJ)Laacinternal/v;
/*     */     //   231: athrow
/*     */     //   232: dstore #11
/*     */     //   234: aload #10
/*     */     //   236: getfield a : D
/*     */     //   239: aload #8
/*     */     //   241: getfield b : D
/*     */     //   244: dsub
/*     */     //   245: dstore #15
/*     */     //   247: aload #10
/*     */     //   249: getfield b : D
/*     */     //   252: aload #8
/*     */     //   254: getfield a : D
/*     */     //   257: dsub
/*     */     //   258: dstore #17
/*     */     //   260: dload #15
/*     */     //   262: invokestatic abs : (D)D
/*     */     //   265: aload #7
/*     */     //   267: ifnull -> 322
/*     */     //   270: dload #17
/*     */     //   272: invokestatic abs : (D)D
/*     */     //   275: dcmpl
/*     */     //   276: ifle -> 307
/*     */     //   279: goto -> 292
/*     */     //   282: ldc2_w -7828043303420004992
/*     */     //   285: lload_2
/*     */     //   286: <illegal opcode> w : (Laacinternal/v;JJ)Laacinternal/v;
/*     */     //   291: athrow
/*     */     //   292: dload #17
/*     */     //   294: dstore #13
/*     */     //   296: lload_2
/*     */     //   297: lconst_0
/*     */     //   298: lcmp
/*     */     //   299: iflt -> 337
/*     */     //   302: aload #7
/*     */     //   304: ifnonnull -> 324
/*     */     //   307: dload #15
/*     */     //   309: goto -> 322
/*     */     //   312: ldc2_w -7828043303420004992
/*     */     //   315: lload_2
/*     */     //   316: <illegal opcode> w : (Laacinternal/v;JJ)Laacinternal/v;
/*     */     //   321: athrow
/*     */     //   322: dstore #13
/*     */     //   324: aload #10
/*     */     //   326: getfield d : D
/*     */     //   329: aload #8
/*     */     //   331: getfield e : D
/*     */     //   334: dsub
/*     */     //   335: dstore #17
/*     */     //   337: aload #10
/*     */     //   339: getfield e : D
/*     */     //   342: aload #8
/*     */     //   344: getfield d : D
/*     */     //   347: dsub
/*     */     //   348: dstore #19
/*     */     //   350: dload #17
/*     */     //   352: invokestatic abs : (D)D
/*     */     //   355: aload #7
/*     */     //   357: ifnull -> 412
/*     */     //   360: dload #19
/*     */     //   362: invokestatic abs : (D)D
/*     */     //   365: dcmpl
/*     */     //   366: ifle -> 397
/*     */     //   369: goto -> 382
/*     */     //   372: ldc2_w -7828043303420004992
/*     */     //   375: lload_2
/*     */     //   376: <illegal opcode> w : (Laacinternal/v;JJ)Laacinternal/v;
/*     */     //   381: athrow
/*     */     //   382: dload #19
/*     */     //   384: dstore #15
/*     */     //   386: lload_2
/*     */     //   387: lconst_0
/*     */     //   388: lcmp
/*     */     //   389: ifle -> 414
/*     */     //   392: aload #7
/*     */     //   394: ifnonnull -> 414
/*     */     //   397: dload #17
/*     */     //   399: goto -> 412
/*     */     //   402: ldc2_w -7828043303420004992
/*     */     //   405: lload_2
/*     */     //   406: <illegal opcode> w : (Laacinternal/v;JJ)Laacinternal/v;
/*     */     //   411: athrow
/*     */     //   412: dstore #15
/*     */     //   414: dload #13
/*     */     //   416: invokestatic abs : (D)D
/*     */     //   419: dload #15
/*     */     //   421: invokestatic abs : (D)D
/*     */     //   424: dcmpg
/*     */     //   425: aload #7
/*     */     //   427: ifnull -> 447
/*     */     //   430: ifge -> 450
/*     */     //   433: goto -> 446
/*     */     //   436: ldc2_w -7828043303420004992
/*     */     //   439: lload_2
/*     */     //   440: <illegal opcode> w : (Laacinternal/v;JJ)Laacinternal/v;
/*     */     //   445: athrow
/*     */     //   446: iconst_1
/*     */     //   447: goto -> 451
/*     */     //   450: iconst_0
/*     */     //   451: istore #17
/*     */     //   453: dload #11
/*     */     //   455: invokestatic abs : (D)D
/*     */     //   458: dload #15
/*     */     //   460: invokestatic abs : (D)D
/*     */     //   463: dcmpg
/*     */     //   464: aload #7
/*     */     //   466: ifnull -> 486
/*     */     //   469: ifge -> 489
/*     */     //   472: goto -> 485
/*     */     //   475: ldc2_w -7828043303420004992
/*     */     //   478: lload_2
/*     */     //   479: <illegal opcode> w : (Laacinternal/v;JJ)Laacinternal/v;
/*     */     //   484: athrow
/*     */     //   485: iconst_1
/*     */     //   486: goto -> 490
/*     */     //   489: iconst_0
/*     */     //   490: istore #18
/*     */     //   492: dload #11
/*     */     //   494: invokestatic abs : (D)D
/*     */     //   497: dload #13
/*     */     //   499: invokestatic abs : (D)D
/*     */     //   502: dcmpg
/*     */     //   503: aload #7
/*     */     //   505: ifnull -> 525
/*     */     //   508: ifge -> 528
/*     */     //   511: goto -> 524
/*     */     //   514: ldc2_w -7828043303420004992
/*     */     //   517: lload_2
/*     */     //   518: <illegal opcode> w : (Laacinternal/v;JJ)Laacinternal/v;
/*     */     //   523: athrow
/*     */     //   524: iconst_1
/*     */     //   525: goto -> 529
/*     */     //   528: iconst_0
/*     */     //   529: istore #19
/*     */     //   531: iload #19
/*     */     //   533: aload #7
/*     */     //   535: ifnull -> 633
/*     */     //   538: ifeq -> 618
/*     */     //   541: goto -> 554
/*     */     //   544: ldc2_w -7828043303420004992
/*     */     //   547: lload_2
/*     */     //   548: <illegal opcode> w : (Laacinternal/v;JJ)Laacinternal/v;
/*     */     //   553: athrow
/*     */     //   554: iload #18
/*     */     //   556: aload #7
/*     */     //   558: lload_2
/*     */     //   559: lconst_0
/*     */     //   560: lcmp
/*     */     //   561: ifle -> 635
/*     */     //   564: ifnull -> 633
/*     */     //   567: goto -> 580
/*     */     //   570: ldc2_w -7828043303420004992
/*     */     //   573: lload_2
/*     */     //   574: <illegal opcode> w : (Laacinternal/v;JJ)Laacinternal/v;
/*     */     //   579: athrow
/*     */     //   580: ifeq -> 618
/*     */     //   583: goto -> 596
/*     */     //   586: ldc2_w -7828043303420004992
/*     */     //   589: lload_2
/*     */     //   590: <illegal opcode> w : (Laacinternal/v;JJ)Laacinternal/v;
/*     */     //   595: athrow
/*     */     //   596: aload #8
/*     */     //   598: dload #11
/*     */     //   600: dconst_0
/*     */     //   601: dconst_0
/*     */     //   602: invokevirtual a : (DDD)Lme/konsolas/aac/lq;
/*     */     //   605: astore #8
/*     */     //   607: aload #7
/*     */     //   609: lload_2
/*     */     //   610: lconst_0
/*     */     //   611: lcmp
/*     */     //   612: ifle -> 694
/*     */     //   615: ifnonnull -> 692
/*     */     //   618: iload #19
/*     */     //   620: goto -> 633
/*     */     //   623: ldc2_w -7828043303420004992
/*     */     //   626: lload_2
/*     */     //   627: <illegal opcode> w : (Laacinternal/v;JJ)Laacinternal/v;
/*     */     //   632: athrow
/*     */     //   633: aload #7
/*     */     //   635: ifnull -> 656
/*     */     //   638: ifne -> 681
/*     */     //   641: goto -> 654
/*     */     //   644: ldc2_w -7828043303420004992
/*     */     //   647: lload_2
/*     */     //   648: <illegal opcode> w : (Laacinternal/v;JJ)Laacinternal/v;
/*     */     //   653: athrow
/*     */     //   654: iload #17
/*     */     //   656: ifeq -> 681
/*     */     //   659: aload #8
/*     */     //   661: dconst_0
/*     */     //   662: dload #13
/*     */     //   664: dconst_0
/*     */     //   665: invokevirtual a : (DDD)Lme/konsolas/aac/lq;
/*     */     //   668: astore #8
/*     */     //   670: aload #7
/*     */     //   672: lload_2
/*     */     //   673: lconst_0
/*     */     //   674: lcmp
/*     */     //   675: iflt -> 694
/*     */     //   678: ifnonnull -> 692
/*     */     //   681: aload #8
/*     */     //   683: dconst_0
/*     */     //   684: dconst_0
/*     */     //   685: dload #15
/*     */     //   687: invokevirtual a : (DDD)Lme/konsolas/aac/lq;
/*     */     //   690: astore #8
/*     */     //   692: aload #7
/*     */     //   694: ifnonnull -> 52
/*     */     //   697: aload #8
/*     */     //   699: areturn
/*     */     // Line number table:
/*     */     //   Java source line number -> byte code offset
/*     */     //   #138	-> 39
/*     */     //   #36	-> 42
/*     */     //   #174	-> 74
/*     */     //   #29	-> 131
/*     */     //   #80	-> 157
/*     */     //   #46	-> 170
/*     */     //   #45	-> 202
/*     */     //   #176	-> 217
/*     */     //   #82	-> 234
/*     */     //   #56	-> 247
/*     */     //   #178	-> 260
/*     */     //   #43	-> 292
/*     */     //   #184	-> 307
/*     */     //   #198	-> 324
/*     */     //   #57	-> 337
/*     */     //   #183	-> 350
/*     */     //   #203	-> 382
/*     */     //   #158	-> 397
/*     */     //   #106	-> 414
/*     */     //   #177	-> 453
/*     */     //   #189	-> 492
/*     */     //   #90	-> 531
/*     */     //   #53	-> 596
/*     */     //   #34	-> 618
/*     */     //   #173	-> 659
/*     */     //   #76	-> 681
/*     */     //   #166	-> 692
/*     */     //   #147	-> 697
/*     */     // Exception table:
/*     */     //   from	to	target	type
/*     */     //   74	92	95	aacinternal/v
/*     */     //   87	118	121	aacinternal/v
/*     */     //   105	133	136	aacinternal/v
/*     */     //   170	189	192	aacinternal/v
/*     */     //   206	219	222	aacinternal/v
/*     */     //   260	279	282	aacinternal/v
/*     */     //   296	309	312	aacinternal/v
/*     */     //   350	369	372	aacinternal/v
/*     */     //   386	399	402	aacinternal/v
/*     */     //   414	433	436	aacinternal/v
/*     */     //   453	472	475	aacinternal/v
/*     */     //   492	511	514	aacinternal/v
/*     */     //   531	541	544	aacinternal/v
/*     */     //   538	567	570	aacinternal/v
/*     */     //   554	583	586	aacinternal/v
/*     */     //   607	620	623	aacinternal/v
/* 205 */     //   633	641	644	aacinternal/v } public lq b(Vector paramVector) { return c(paramVector.getX(), paramVector.getY(), paramVector.getZ()); } public static lq a(BoundingBox paramBoundingBox) { return new lq(paramBoundingBox.getMinX(), paramBoundingBox.getMinY(), paramBoundingBox.getMinZ(), paramBoundingBox.getMaxX(), paramBoundingBox.getMaxY(), paramBoundingBox.getMaxZ()); }
/*     */   public static lq a(int paramInt1, int paramInt2) { int i = paramInt1 << 4; int j = paramInt2 << 4; return new lq(i, 0.0D, j, (i + 16), 256.0D, (j + 16)); } public lq(double paramDouble1, double paramDouble2, double paramDouble3, double paramDouble4, double paramDouble5, double paramDouble6) { this.c = paramDouble1; this.a = paramDouble2; this.d = paramDouble3; this.f = paramDouble4; this.b = paramDouble5; this.e = paramDouble6; } public static lq b(int paramInt1, int paramInt2, int paramInt3) { return new lq(paramInt1, paramInt2, paramInt3, (paramInt1 + 1), (paramInt2 + 1), (paramInt3 + 1)); } public lq a(double paramDouble1, double paramDouble2) { return new lq(this.c, Math.max(paramDouble1, this.a), this.d, this.f, Math.min(paramDouble2, this.b), this.e); } public double b(long paramLong, lq paramlq, double paramDouble) { // Byte code:
/*     */     //   0: getstatic me/konsolas/aac/lq.h : J
/*     */     //   3: lload_1
/*     */     //   4: lxor
/*     */     //   5: lstore_1
/*     */     //   6: ldc2_w 4056366395044131819
/*     */     //   9: lload_1
/*     */     //   10: <illegal opcode> w : (JJ)[I
/*     */     //   15: astore #6
/*     */     //   17: aload_3
/*     */     //   18: getfield f : D
/*     */     //   21: aload #6
/*     */     //   23: ifnull -> 455
/*     */     //   26: aload_0
/*     */     //   27: getfield c : D
/*     */     //   30: dcmpl
/*     */     //   31: ifle -> 453
/*     */     //   34: goto -> 47
/*     */     //   37: ldc2_w 4064566045574815413
/*     */     //   40: lload_1
/*     */     //   41: <illegal opcode> w : (Laacinternal/v;JJ)Laacinternal/v;
/*     */     //   46: athrow
/*     */     //   47: aload_3
/*     */     //   48: getfield c : D
/*     */     //   51: aload #6
/*     */     //   53: ifnull -> 455
/*     */     //   56: goto -> 69
/*     */     //   59: ldc2_w 4064566045574815413
/*     */     //   62: lload_1
/*     */     //   63: <illegal opcode> w : (Laacinternal/v;JJ)Laacinternal/v;
/*     */     //   68: athrow
/*     */     //   69: aload_0
/*     */     //   70: getfield f : D
/*     */     //   73: dcmpg
/*     */     //   74: ifge -> 453
/*     */     //   77: goto -> 90
/*     */     //   80: ldc2_w 4064566045574815413
/*     */     //   83: lload_1
/*     */     //   84: <illegal opcode> w : (Laacinternal/v;JJ)Laacinternal/v;
/*     */     //   89: athrow
/*     */     //   90: aload_3
/*     */     //   91: getfield e : D
/*     */     //   94: aload #6
/*     */     //   96: ifnull -> 455
/*     */     //   99: goto -> 112
/*     */     //   102: ldc2_w 4064566045574815413
/*     */     //   105: lload_1
/*     */     //   106: <illegal opcode> w : (Laacinternal/v;JJ)Laacinternal/v;
/*     */     //   111: athrow
/*     */     //   112: aload_0
/*     */     //   113: getfield d : D
/*     */     //   116: dcmpl
/*     */     //   117: ifle -> 453
/*     */     //   120: goto -> 133
/*     */     //   123: ldc2_w 4064566045574815413
/*     */     //   126: lload_1
/*     */     //   127: <illegal opcode> w : (Laacinternal/v;JJ)Laacinternal/v;
/*     */     //   132: athrow
/*     */     //   133: aload_3
/*     */     //   134: getfield d : D
/*     */     //   137: aload #6
/*     */     //   139: ifnull -> 455
/*     */     //   142: goto -> 155
/*     */     //   145: ldc2_w 4064566045574815413
/*     */     //   148: lload_1
/*     */     //   149: <illegal opcode> w : (Laacinternal/v;JJ)Laacinternal/v;
/*     */     //   154: athrow
/*     */     //   155: aload_0
/*     */     //   156: getfield e : D
/*     */     //   159: dcmpg
/*     */     //   160: ifge -> 453
/*     */     //   163: goto -> 176
/*     */     //   166: ldc2_w 4064566045574815413
/*     */     //   169: lload_1
/*     */     //   170: <illegal opcode> w : (Laacinternal/v;JJ)Laacinternal/v;
/*     */     //   175: athrow
/*     */     //   176: dload #4
/*     */     //   178: dconst_0
/*     */     //   179: dcmpl
/*     */     //   180: aload #6
/*     */     //   182: ifnull -> 363
/*     */     //   185: goto -> 198
/*     */     //   188: ldc2_w 4064566045574815413
/*     */     //   191: lload_1
/*     */     //   192: <illegal opcode> w : (Laacinternal/v;JJ)Laacinternal/v;
/*     */     //   197: athrow
/*     */     //   198: ifle -> 328
/*     */     //   201: goto -> 214
/*     */     //   204: ldc2_w 4064566045574815413
/*     */     //   207: lload_1
/*     */     //   208: <illegal opcode> w : (Laacinternal/v;JJ)Laacinternal/v;
/*     */     //   213: athrow
/*     */     //   214: aload_3
/*     */     //   215: getfield b : D
/*     */     //   218: aload_0
/*     */     //   219: getfield a : D
/*     */     //   222: dcmpg
/*     */     //   223: lload_1
/*     */     //   224: lconst_0
/*     */     //   225: lcmp
/*     */     //   226: iflt -> 363
/*     */     //   229: aload #6
/*     */     //   231: ifnull -> 363
/*     */     //   234: goto -> 247
/*     */     //   237: ldc2_w 4064566045574815413
/*     */     //   240: lload_1
/*     */     //   241: <illegal opcode> w : (Laacinternal/v;JJ)Laacinternal/v;
/*     */     //   246: athrow
/*     */     //   247: ifgt -> 328
/*     */     //   250: goto -> 263
/*     */     //   253: ldc2_w 4064566045574815413
/*     */     //   256: lload_1
/*     */     //   257: <illegal opcode> w : (Laacinternal/v;JJ)Laacinternal/v;
/*     */     //   262: athrow
/*     */     //   263: aload_0
/*     */     //   264: getfield a : D
/*     */     //   267: aload_3
/*     */     //   268: getfield b : D
/*     */     //   271: dsub
/*     */     //   272: dstore #7
/*     */     //   274: dload #7
/*     */     //   276: aload #6
/*     */     //   278: ifnull -> 315
/*     */     //   281: dload #4
/*     */     //   283: dcmpg
/*     */     //   284: ifge -> 317
/*     */     //   287: goto -> 300
/*     */     //   290: ldc2_w 4064566045574815413
/*     */     //   293: lload_1
/*     */     //   294: <illegal opcode> w : (Laacinternal/v;JJ)Laacinternal/v;
/*     */     //   299: athrow
/*     */     //   300: dload #7
/*     */     //   302: goto -> 315
/*     */     //   305: ldc2_w 4064566045574815413
/*     */     //   308: lload_1
/*     */     //   309: <illegal opcode> w : (Laacinternal/v;JJ)Laacinternal/v;
/*     */     //   314: athrow
/*     */     //   315: dstore #4
/*     */     //   317: lload_1
/*     */     //   318: lconst_0
/*     */     //   319: lcmp
/*     */     //   320: ifle -> 328
/*     */     //   323: aload #6
/*     */     //   325: ifnonnull -> 450
/*     */     //   328: dload #4
/*     */     //   330: aload #6
/*     */     //   332: ifnull -> 452
/*     */     //   335: goto -> 348
/*     */     //   338: ldc2_w 4064566045574815413
/*     */     //   341: lload_1
/*     */     //   342: <illegal opcode> w : (Laacinternal/v;JJ)Laacinternal/v;
/*     */     //   347: athrow
/*     */     //   348: dconst_0
/*     */     //   349: dcmpg
/*     */     //   350: goto -> 363
/*     */     //   353: ldc2_w 4064566045574815413
/*     */     //   356: lload_1
/*     */     //   357: <illegal opcode> w : (Laacinternal/v;JJ)Laacinternal/v;
/*     */     //   362: athrow
/*     */     //   363: ifge -> 450
/*     */     //   366: aload_3
/*     */     //   367: getfield a : D
/*     */     //   370: aload #6
/*     */     //   372: ifnull -> 452
/*     */     //   375: goto -> 388
/*     */     //   378: ldc2_w 4064566045574815413
/*     */     //   381: lload_1
/*     */     //   382: <illegal opcode> w : (Laacinternal/v;JJ)Laacinternal/v;
/*     */     //   387: athrow
/*     */     //   388: aload_0
/*     */     //   389: getfield b : D
/*     */     //   392: dcmpl
/*     */     //   393: iflt -> 450
/*     */     //   396: goto -> 409
/*     */     //   399: ldc2_w 4064566045574815413
/*     */     //   402: lload_1
/*     */     //   403: <illegal opcode> w : (Laacinternal/v;JJ)Laacinternal/v;
/*     */     //   408: athrow
/*     */     //   409: aload_0
/*     */     //   410: getfield b : D
/*     */     //   413: aload_3
/*     */     //   414: getfield a : D
/*     */     //   417: dsub
/*     */     //   418: dstore #7
/*     */     //   420: dload #7
/*     */     //   422: aload #6
/*     */     //   424: ifnull -> 452
/*     */     //   427: dload #4
/*     */     //   429: dcmpl
/*     */     //   430: ifle -> 450
/*     */     //   433: goto -> 446
/*     */     //   436: ldc2_w 4064566045574815413
/*     */     //   439: lload_1
/*     */     //   440: <illegal opcode> w : (Laacinternal/v;JJ)Laacinternal/v;
/*     */     //   445: athrow
/*     */     //   446: dload #7
/*     */     //   448: dstore #4
/*     */     //   450: dload #4
/*     */     //   452: dreturn
/*     */     //   453: dload #4
/*     */     //   455: dreturn
/*     */     // Line number table:
/*     */     //   Java source line number -> byte code offset
/*     */     //   #156	-> 17
/*     */     //   #27	-> 176
/*     */     //   #129	-> 263
/*     */     //   #101	-> 274
/*     */     //   #134	-> 317
/*     */     //   #40	-> 409
/*     */     //   #165	-> 420
/*     */     //   #148	-> 446
/*     */     //   #9	-> 450
/*     */     //   #187	-> 453
/*     */     // Exception table:
/*     */     //   from	to	target	type
/*     */     //   17	34	37	aacinternal/v
/*     */     //   26	56	59	aacinternal/v
/*     */     //   47	77	80	aacinternal/v
/*     */     //   69	99	102	aacinternal/v
/*     */     //   90	120	123	aacinternal/v
/*     */     //   112	142	145	aacinternal/v
/*     */     //   133	163	166	aacinternal/v
/*     */     //   155	185	188	aacinternal/v
/*     */     //   176	201	204	aacinternal/v
/*     */     //   198	234	237	aacinternal/v
/*     */     //   214	250	253	aacinternal/v
/*     */     //   274	287	290	aacinternal/v
/*     */     //   281	302	305	aacinternal/v
/*     */     //   317	335	338	aacinternal/v
/*     */     //   328	350	353	aacinternal/v
/*     */     //   363	375	378	aacinternal/v
/*     */     //   366	396	399	aacinternal/v
/*     */     //   420	433	436	aacinternal/v } public int hashCode() { return Objects.hash(new Object[] { Double.valueOf(this.c), Double.valueOf(this.a), Double.valueOf(this.d), Double.valueOf(this.f), Double.valueOf(this.b), Double.valueOf(this.e) }); } public boolean a(lq paramlq, double paramDouble1, double paramDouble2, double paramDouble3, long paramLong) { // Byte code:
/*     */     //   0: getstatic me/konsolas/aac/lq.h : J
/*     */     //   3: lload #8
/*     */     //   5: lxor
/*     */     //   6: lstore #8
/*     */     //   8: ldc2_w -1367903870839413084
/*     */     //   11: lload #8
/*     */     //   13: <illegal opcode> w : (JJ)[I
/*     */     //   18: astore #10
/*     */     //   20: aload_0
/*     */     //   21: getfield c : D
/*     */     //   24: aload_1
/*     */     //   25: getfield f : D
/*     */     //   28: dload_2
/*     */     //   29: dadd
/*     */     //   30: dcmpg
/*     */     //   31: aload #10
/*     */     //   33: ifnull -> 78
/*     */     //   36: ifge -> 324
/*     */     //   39: goto -> 53
/*     */     //   42: ldc2_w -1358085583376086022
/*     */     //   45: lload #8
/*     */     //   47: <illegal opcode> w : (Laacinternal/v;JJ)Laacinternal/v;
/*     */     //   52: athrow
/*     */     //   53: aload_0
/*     */     //   54: getfield f : D
/*     */     //   57: aload_1
/*     */     //   58: getfield c : D
/*     */     //   61: dload_2
/*     */     //   62: dadd
/*     */     //   63: dcmpl
/*     */     //   64: goto -> 78
/*     */     //   67: ldc2_w -1358085583376086022
/*     */     //   70: lload #8
/*     */     //   72: <illegal opcode> w : (Laacinternal/v;JJ)Laacinternal/v;
/*     */     //   77: athrow
/*     */     //   78: aload #10
/*     */     //   80: lload #8
/*     */     //   82: lconst_0
/*     */     //   83: lcmp
/*     */     //   84: ifle -> 135
/*     */     //   87: ifnull -> 133
/*     */     //   90: ifle -> 324
/*     */     //   93: goto -> 107
/*     */     //   96: ldc2_w -1358085583376086022
/*     */     //   99: lload #8
/*     */     //   101: <illegal opcode> w : (Laacinternal/v;JJ)Laacinternal/v;
/*     */     //   106: athrow
/*     */     //   107: aload_0
/*     */     //   108: getfield a : D
/*     */     //   111: aload_1
/*     */     //   112: getfield b : D
/*     */     //   115: dload #4
/*     */     //   117: dadd
/*     */     //   118: dcmpg
/*     */     //   119: goto -> 133
/*     */     //   122: ldc2_w -1358085583376086022
/*     */     //   125: lload #8
/*     */     //   127: <illegal opcode> w : (Laacinternal/v;JJ)Laacinternal/v;
/*     */     //   132: athrow
/*     */     //   133: aload #10
/*     */     //   135: lload #8
/*     */     //   137: lconst_0
/*     */     //   138: lcmp
/*     */     //   139: iflt -> 190
/*     */     //   142: ifnull -> 188
/*     */     //   145: ifge -> 324
/*     */     //   148: goto -> 162
/*     */     //   151: ldc2_w -1358085583376086022
/*     */     //   154: lload #8
/*     */     //   156: <illegal opcode> w : (Laacinternal/v;JJ)Laacinternal/v;
/*     */     //   161: athrow
/*     */     //   162: aload_0
/*     */     //   163: getfield b : D
/*     */     //   166: aload_1
/*     */     //   167: getfield a : D
/*     */     //   170: dload #4
/*     */     //   172: dadd
/*     */     //   173: dcmpl
/*     */     //   174: goto -> 188
/*     */     //   177: ldc2_w -1358085583376086022
/*     */     //   180: lload #8
/*     */     //   182: <illegal opcode> w : (Laacinternal/v;JJ)Laacinternal/v;
/*     */     //   187: athrow
/*     */     //   188: aload #10
/*     */     //   190: lload #8
/*     */     //   192: lconst_0
/*     */     //   193: lcmp
/*     */     //   194: iflt -> 245
/*     */     //   197: ifnull -> 243
/*     */     //   200: ifle -> 324
/*     */     //   203: goto -> 217
/*     */     //   206: ldc2_w -1358085583376086022
/*     */     //   209: lload #8
/*     */     //   211: <illegal opcode> w : (Laacinternal/v;JJ)Laacinternal/v;
/*     */     //   216: athrow
/*     */     //   217: aload_0
/*     */     //   218: getfield d : D
/*     */     //   221: aload_1
/*     */     //   222: getfield e : D
/*     */     //   225: dload #6
/*     */     //   227: dadd
/*     */     //   228: dcmpg
/*     */     //   229: goto -> 243
/*     */     //   232: ldc2_w -1358085583376086022
/*     */     //   235: lload #8
/*     */     //   237: <illegal opcode> w : (Laacinternal/v;JJ)Laacinternal/v;
/*     */     //   242: athrow
/*     */     //   243: aload #10
/*     */     //   245: lload #8
/*     */     //   247: lconst_0
/*     */     //   248: lcmp
/*     */     //   249: iflt -> 300
/*     */     //   252: ifnull -> 298
/*     */     //   255: ifge -> 324
/*     */     //   258: goto -> 272
/*     */     //   261: ldc2_w -1358085583376086022
/*     */     //   264: lload #8
/*     */     //   266: <illegal opcode> w : (Laacinternal/v;JJ)Laacinternal/v;
/*     */     //   271: athrow
/*     */     //   272: aload_0
/*     */     //   273: getfield e : D
/*     */     //   276: aload_1
/*     */     //   277: getfield d : D
/*     */     //   280: dload #6
/*     */     //   282: dadd
/*     */     //   283: dcmpl
/*     */     //   284: goto -> 298
/*     */     //   287: ldc2_w -1358085583376086022
/*     */     //   290: lload #8
/*     */     //   292: <illegal opcode> w : (Laacinternal/v;JJ)Laacinternal/v;
/*     */     //   297: athrow
/*     */     //   298: aload #10
/*     */     //   300: ifnull -> 321
/*     */     //   303: ifle -> 324
/*     */     //   306: goto -> 320
/*     */     //   309: ldc2_w -1358085583376086022
/*     */     //   312: lload #8
/*     */     //   314: <illegal opcode> w : (Laacinternal/v;JJ)Laacinternal/v;
/*     */     //   319: athrow
/*     */     //   320: iconst_1
/*     */     //   321: goto -> 325
/*     */     //   324: iconst_0
/*     */     //   325: ireturn
/*     */     // Line number table:
/*     */     //   Java source line number -> byte code offset
/*     */     //   #161	-> 20
/*     */     // Exception table:
/*     */     //   from	to	target	type
/*     */     //   20	39	42	aacinternal/v
/*     */     //   36	64	67	aacinternal/v
/*     */     //   78	93	96	aacinternal/v
/*     */     //   90	119	122	aacinternal/v
/*     */     //   133	148	151	aacinternal/v
/*     */     //   145	174	177	aacinternal/v
/*     */     //   188	203	206	aacinternal/v
/*     */     //   200	229	232	aacinternal/v
/*     */     //   243	258	261	aacinternal/v
/*     */     //   255	284	287	aacinternal/v
/*     */     //   298	306	309	aacinternal/v } public lq a(char paramChar, long paramLong, Vector paramVector) { long l1 = (paramChar << 48L | paramLong << 16L >>> 16L) ^ h, l2 = l1 ^ 0x388A5DD762A2L; return b(paramVector.getX(), paramVector.getY(), paramVector.getZ(), l2); } public lq(Vector paramVector, eo parameo) { this(paramVector, parameo.b(), parameo.a()); } public boolean b(long paramLong, Vector paramVector) { // Byte code:
/*     */     //   0: getstatic me/konsolas/aac/lq.h : J
/*     */     //   3: lload_1
/*     */     //   4: lxor
/*     */     //   5: lstore_1
/*     */     //   6: ldc2_w 4073794445102084905
/*     */     //   9: lload_1
/*     */     //   10: <illegal opcode> w : (JJ)[I
/*     */     //   15: astore #4
/*     */     //   17: aload_0
/*     */     //   18: getfield c : D
/*     */     //   21: aload_3
/*     */     //   22: invokevirtual getX : ()D
/*     */     //   25: dcmpg
/*     */     //   26: aload #4
/*     */     //   28: ifnull -> 69
/*     */     //   31: ifgt -> 290
/*     */     //   34: goto -> 47
/*     */     //   37: ldc2_w 4083111750381264503
/*     */     //   40: lload_1
/*     */     //   41: <illegal opcode> w : (Laacinternal/v;JJ)Laacinternal/v;
/*     */     //   46: athrow
/*     */     //   47: aload_0
/*     */     //   48: getfield f : D
/*     */     //   51: aload_3
/*     */     //   52: invokevirtual getX : ()D
/*     */     //   55: dcmpl
/*     */     //   56: goto -> 69
/*     */     //   59: ldc2_w 4083111750381264503
/*     */     //   62: lload_1
/*     */     //   63: <illegal opcode> w : (Laacinternal/v;JJ)Laacinternal/v;
/*     */     //   68: athrow
/*     */     //   69: aload #4
/*     */     //   71: lload_1
/*     */     //   72: lconst_0
/*     */     //   73: lcmp
/*     */     //   74: ifle -> 120
/*     */     //   77: ifnull -> 118
/*     */     //   80: iflt -> 290
/*     */     //   83: goto -> 96
/*     */     //   86: ldc2_w 4083111750381264503
/*     */     //   89: lload_1
/*     */     //   90: <illegal opcode> w : (Laacinternal/v;JJ)Laacinternal/v;
/*     */     //   95: athrow
/*     */     //   96: aload_0
/*     */     //   97: getfield a : D
/*     */     //   100: aload_3
/*     */     //   101: invokevirtual getY : ()D
/*     */     //   104: dcmpg
/*     */     //   105: goto -> 118
/*     */     //   108: ldc2_w 4083111750381264503
/*     */     //   111: lload_1
/*     */     //   112: <illegal opcode> w : (Laacinternal/v;JJ)Laacinternal/v;
/*     */     //   117: athrow
/*     */     //   118: aload #4
/*     */     //   120: lload_1
/*     */     //   121: lconst_0
/*     */     //   122: lcmp
/*     */     //   123: iflt -> 169
/*     */     //   126: ifnull -> 167
/*     */     //   129: ifgt -> 290
/*     */     //   132: goto -> 145
/*     */     //   135: ldc2_w 4083111750381264503
/*     */     //   138: lload_1
/*     */     //   139: <illegal opcode> w : (Laacinternal/v;JJ)Laacinternal/v;
/*     */     //   144: athrow
/*     */     //   145: aload_0
/*     */     //   146: getfield b : D
/*     */     //   149: aload_3
/*     */     //   150: invokevirtual getY : ()D
/*     */     //   153: dcmpl
/*     */     //   154: goto -> 167
/*     */     //   157: ldc2_w 4083111750381264503
/*     */     //   160: lload_1
/*     */     //   161: <illegal opcode> w : (Laacinternal/v;JJ)Laacinternal/v;
/*     */     //   166: athrow
/*     */     //   167: aload #4
/*     */     //   169: lload_1
/*     */     //   170: lconst_0
/*     */     //   171: lcmp
/*     */     //   172: iflt -> 218
/*     */     //   175: ifnull -> 216
/*     */     //   178: iflt -> 290
/*     */     //   181: goto -> 194
/*     */     //   184: ldc2_w 4083111750381264503
/*     */     //   187: lload_1
/*     */     //   188: <illegal opcode> w : (Laacinternal/v;JJ)Laacinternal/v;
/*     */     //   193: athrow
/*     */     //   194: aload_0
/*     */     //   195: getfield d : D
/*     */     //   198: aload_3
/*     */     //   199: invokevirtual getZ : ()D
/*     */     //   202: dcmpg
/*     */     //   203: goto -> 216
/*     */     //   206: ldc2_w 4083111750381264503
/*     */     //   209: lload_1
/*     */     //   210: <illegal opcode> w : (Laacinternal/v;JJ)Laacinternal/v;
/*     */     //   215: athrow
/*     */     //   216: aload #4
/*     */     //   218: lload_1
/*     */     //   219: lconst_0
/*     */     //   220: lcmp
/*     */     //   221: iflt -> 267
/*     */     //   224: ifnull -> 265
/*     */     //   227: ifgt -> 290
/*     */     //   230: goto -> 243
/*     */     //   233: ldc2_w 4083111750381264503
/*     */     //   236: lload_1
/*     */     //   237: <illegal opcode> w : (Laacinternal/v;JJ)Laacinternal/v;
/*     */     //   242: athrow
/*     */     //   243: aload_0
/*     */     //   244: getfield e : D
/*     */     //   247: aload_3
/*     */     //   248: invokevirtual getZ : ()D
/*     */     //   251: dcmpl
/*     */     //   252: goto -> 265
/*     */     //   255: ldc2_w 4083111750381264503
/*     */     //   258: lload_1
/*     */     //   259: <illegal opcode> w : (Laacinternal/v;JJ)Laacinternal/v;
/*     */     //   264: athrow
/*     */     //   265: aload #4
/*     */     //   267: ifnull -> 287
/*     */     //   270: iflt -> 290
/*     */     //   273: goto -> 286
/*     */     //   276: ldc2_w 4083111750381264503
/*     */     //   279: lload_1
/*     */     //   280: <illegal opcode> w : (Laacinternal/v;JJ)Laacinternal/v;
/*     */     //   285: athrow
/*     */     //   286: iconst_1
/*     */     //   287: goto -> 291
/*     */     //   290: iconst_0
/*     */     //   291: ireturn
/*     */     // Line number table:
/*     */     //   Java source line number -> byte code offset
/*     */     //   #168	-> 17
/*     */     //   #98	-> 101
/*     */     //   #55	-> 199
/*     */     //   #108	-> 291
/*     */     // Exception table:
/*     */     //   from	to	target	type
/*     */     //   17	34	37	aacinternal/v
/*     */     //   31	56	59	aacinternal/v
/*     */     //   69	83	86	aacinternal/v
/*     */     //   80	105	108	aacinternal/v
/*     */     //   118	132	135	aacinternal/v
/*     */     //   129	154	157	aacinternal/v
/*     */     //   167	181	184	aacinternal/v
/*     */     //   178	203	206	aacinternal/v
/*     */     //   216	230	233	aacinternal/v
/*     */     //   227	252	255	aacinternal/v
/*     */     //   265	273	276	aacinternal/v } public double f() { return this.e; } private static double a(double paramDouble1, double paramDouble2, double paramDouble3) { return Math.min(Math.max(paramDouble1, paramDouble2), paramDouble3); } public lq c(double paramDouble1, double paramDouble2, double paramDouble3) { return new lq(this.c - paramDouble1, this.a - paramDouble2, this.d - paramDouble3, this.f + paramDouble1, this.b + paramDouble2, this.e + paramDouble3); } public boolean a(lq paramlq, long paramLong) { // Byte code:
/*     */     //   0: getstatic me/konsolas/aac/lq.h : J
/*     */     //   3: lload_2
/*     */     //   4: lxor
/*     */     //   5: lstore_2
/*     */     //   6: ldc2_w -5047323503641857452
/*     */     //   9: lload_2
/*     */     //   10: <illegal opcode> w : (JJ)[I
/*     */     //   15: astore #4
/*     */     //   17: aload_0
/*     */     //   18: getfield c : D
/*     */     //   21: aload_1
/*     */     //   22: getfield c : D
/*     */     //   25: dcmpg
/*     */     //   26: aload #4
/*     */     //   28: ifnull -> 69
/*     */     //   31: ifgt -> 290
/*     */     //   34: goto -> 47
/*     */     //   37: ldc2_w -5055456651515764982
/*     */     //   40: lload_2
/*     */     //   41: <illegal opcode> w : (Laacinternal/v;JJ)Laacinternal/v;
/*     */     //   46: athrow
/*     */     //   47: aload_0
/*     */     //   48: getfield f : D
/*     */     //   51: aload_1
/*     */     //   52: getfield f : D
/*     */     //   55: dcmpl
/*     */     //   56: goto -> 69
/*     */     //   59: ldc2_w -5055456651515764982
/*     */     //   62: lload_2
/*     */     //   63: <illegal opcode> w : (Laacinternal/v;JJ)Laacinternal/v;
/*     */     //   68: athrow
/*     */     //   69: aload #4
/*     */     //   71: lload_2
/*     */     //   72: lconst_0
/*     */     //   73: lcmp
/*     */     //   74: iflt -> 120
/*     */     //   77: ifnull -> 118
/*     */     //   80: iflt -> 290
/*     */     //   83: goto -> 96
/*     */     //   86: ldc2_w -5055456651515764982
/*     */     //   89: lload_2
/*     */     //   90: <illegal opcode> w : (Laacinternal/v;JJ)Laacinternal/v;
/*     */     //   95: athrow
/*     */     //   96: aload_0
/*     */     //   97: getfield a : D
/*     */     //   100: aload_1
/*     */     //   101: getfield a : D
/*     */     //   104: dcmpg
/*     */     //   105: goto -> 118
/*     */     //   108: ldc2_w -5055456651515764982
/*     */     //   111: lload_2
/*     */     //   112: <illegal opcode> w : (Laacinternal/v;JJ)Laacinternal/v;
/*     */     //   117: athrow
/*     */     //   118: aload #4
/*     */     //   120: lload_2
/*     */     //   121: lconst_0
/*     */     //   122: lcmp
/*     */     //   123: iflt -> 169
/*     */     //   126: ifnull -> 167
/*     */     //   129: ifgt -> 290
/*     */     //   132: goto -> 145
/*     */     //   135: ldc2_w -5055456651515764982
/*     */     //   138: lload_2
/*     */     //   139: <illegal opcode> w : (Laacinternal/v;JJ)Laacinternal/v;
/*     */     //   144: athrow
/*     */     //   145: aload_0
/*     */     //   146: getfield b : D
/*     */     //   149: aload_1
/*     */     //   150: getfield b : D
/*     */     //   153: dcmpl
/*     */     //   154: goto -> 167
/*     */     //   157: ldc2_w -5055456651515764982
/*     */     //   160: lload_2
/*     */     //   161: <illegal opcode> w : (Laacinternal/v;JJ)Laacinternal/v;
/*     */     //   166: athrow
/*     */     //   167: aload #4
/*     */     //   169: lload_2
/*     */     //   170: lconst_0
/*     */     //   171: lcmp
/*     */     //   172: ifle -> 218
/*     */     //   175: ifnull -> 216
/*     */     //   178: iflt -> 290
/*     */     //   181: goto -> 194
/*     */     //   184: ldc2_w -5055456651515764982
/*     */     //   187: lload_2
/*     */     //   188: <illegal opcode> w : (Laacinternal/v;JJ)Laacinternal/v;
/*     */     //   193: athrow
/*     */     //   194: aload_0
/*     */     //   195: getfield d : D
/*     */     //   198: aload_1
/*     */     //   199: getfield d : D
/*     */     //   202: dcmpg
/*     */     //   203: goto -> 216
/*     */     //   206: ldc2_w -5055456651515764982
/*     */     //   209: lload_2
/*     */     //   210: <illegal opcode> w : (Laacinternal/v;JJ)Laacinternal/v;
/*     */     //   215: athrow
/*     */     //   216: aload #4
/*     */     //   218: lload_2
/*     */     //   219: lconst_0
/*     */     //   220: lcmp
/*     */     //   221: iflt -> 267
/*     */     //   224: ifnull -> 265
/*     */     //   227: ifgt -> 290
/*     */     //   230: goto -> 243
/*     */     //   233: ldc2_w -5055456651515764982
/*     */     //   236: lload_2
/*     */     //   237: <illegal opcode> w : (Laacinternal/v;JJ)Laacinternal/v;
/*     */     //   242: athrow
/*     */     //   243: aload_0
/*     */     //   244: getfield e : D
/*     */     //   247: aload_1
/*     */     //   248: getfield e : D
/*     */     //   251: dcmpl
/*     */     //   252: goto -> 265
/*     */     //   255: ldc2_w -5055456651515764982
/*     */     //   258: lload_2
/*     */     //   259: <illegal opcode> w : (Laacinternal/v;JJ)Laacinternal/v;
/*     */     //   264: athrow
/*     */     //   265: aload #4
/*     */     //   267: ifnull -> 287
/*     */     //   270: iflt -> 290
/*     */     //   273: goto -> 286
/*     */     //   276: ldc2_w -5055456651515764982
/*     */     //   279: lload_2
/*     */     //   280: <illegal opcode> w : (Laacinternal/v;JJ)Laacinternal/v;
/*     */     //   285: athrow
/*     */     //   286: iconst_1
/*     */     //   287: goto -> 291
/*     */     //   290: iconst_0
/*     */     //   291: ireturn
/*     */     // Line number table:
/*     */     //   Java source line number -> byte code offset
/*     */     //   #196	-> 17
/*     */     // Exception table:
/*     */     //   from	to	target	type
/*     */     //   17	34	37	aacinternal/v
/*     */     //   31	56	59	aacinternal/v
/*     */     //   69	83	86	aacinternal/v
/*     */     //   80	105	108	aacinternal/v
/*     */     //   118	132	135	aacinternal/v
/*     */     //   129	154	157	aacinternal/v
/*     */     //   167	181	184	aacinternal/v
/*     */     //   178	203	206	aacinternal/v
/*     */     //   216	230	233	aacinternal/v
/*     */     //   227	252	255	aacinternal/v
/* 206 */     //   265	273	276	aacinternal/v } public static lq a(Vector paramVector1, Vector paramVector2) { return new lq(Math.min(paramVector1.getX(), paramVector2.getX()), Math.min(paramVector1.getY(), paramVector2.getY()), Math.min(paramVector1.getZ(), paramVector2.getZ()), Math.max(paramVector1.getX(), paramVector2.getX()), Math.max(paramVector1.getY(), paramVector2.getY()), Math.max(paramVector1.getZ(), paramVector2.getZ())); }
/*     */ 
/*     */   
/*     */   public static void b(int[] paramArrayOfint) {
/*     */     g = paramArrayOfint;
/*     */   }
/*     */   
/*     */   public static int[] b() {
/*     */     return g;
/*     */   }
/*     */   
/*     */   static {
/*     */     // Byte code:
/*     */     //   0: ldc2_w 8648979105896787736
/*     */     //   3: ldc2_w 563195716245639930
/*     */     //   6: invokestatic lookup : ()Ljava/lang/invoke/MethodHandles$Lookup;
/*     */     //   9: invokevirtual lookupClass : ()Ljava/lang/Class;
/*     */     //   12: invokestatic a : (JJLjava/lang/Object;)Lme/konsolas/aac/na;
/*     */     //   15: ldc2_w 229705025260843
/*     */     //   18: invokeinterface a : (J)J
/*     */     //   23: putstatic me/konsolas/aac/lq.h : J
/*     */     //   26: getstatic me/konsolas/aac/lq.h : J
/*     */     //   29: ldc2_w 52485422390398
/*     */     //   32: lxor
/*     */     //   33: lstore #9
/*     */     //   35: iconst_4
/*     */     //   36: newarray int
/*     */     //   38: new java/util/HashMap
/*     */     //   41: dup
/*     */     //   42: bipush #13
/*     */     //   44: invokespecial <init> : (I)V
/*     */     //   47: putstatic me/konsolas/aac/lq.k : Ljava/util/Map;
/*     */     //   50: ldc2_w -3381833909143371213
/*     */     //   53: lload #9
/*     */     //   55: <illegal opcode> w : ([IJJ)V
/*     */     //   60: ldc_w ''
/*     */     //   63: invokevirtual toCharArray : ()[C
/*     */     //   66: dup
/*     */     //   67: dup
/*     */     //   68: iconst_5
/*     */     //   69: dup_x1
/*     */     //   70: caload
/*     */     //   71: sipush #31872
/*     */     //   74: ixor
/*     */     //   75: i2c
/*     */     //   76: castore
/*     */     //   77: sipush #12152
/*     */     //   80: iconst_1
/*     */     //   81: iconst_1
/*     */     //   82: invokestatic U : (Ljava/lang/Object;SZZ)Ljava/lang/String;
/*     */     //   85: invokestatic getInstance : (Ljava/lang/String;)Ljavax/crypto/Cipher;
/*     */     //   88: dup
/*     */     //   89: astore_0
/*     */     //   90: iconst_2
/*     */     //   91: ldc_w ''
/*     */     //   94: invokevirtual toCharArray : ()[C
/*     */     //   97: dup
/*     */     //   98: dup
/*     */     //   99: iconst_0
/*     */     //   100: dup_x1
/*     */     //   101: caload
/*     */     //   102: sipush #7662
/*     */     //   105: ixor
/*     */     //   106: i2c
/*     */     //   107: castore
/*     */     //   108: sipush #7532
/*     */     //   111: iconst_1
/*     */     //   112: iconst_1
/*     */     //   113: invokestatic U : (Ljava/lang/Object;SZZ)Ljava/lang/String;
/*     */     //   116: invokestatic getInstance : (Ljava/lang/String;)Ljavax/crypto/SecretKeyFactory;
/*     */     //   119: bipush #8
/*     */     //   121: newarray byte
/*     */     //   123: dup
/*     */     //   124: iconst_0
/*     */     //   125: lload #9
/*     */     //   127: bipush #56
/*     */     //   129: lushr
/*     */     //   130: l2i
/*     */     //   131: i2b
/*     */     //   132: bastore
/*     */     //   133: iconst_1
/*     */     //   134: istore_1
/*     */     //   135: iload_1
/*     */     //   136: bipush #8
/*     */     //   138: if_icmpge -> 162
/*     */     //   141: dup
/*     */     //   142: iload_1
/*     */     //   143: lload #9
/*     */     //   145: iload_1
/*     */     //   146: bipush #8
/*     */     //   148: imul
/*     */     //   149: lshl
/*     */     //   150: bipush #56
/*     */     //   152: lushr
/*     */     //   153: l2i
/*     */     //   154: i2b
/*     */     //   155: bastore
/*     */     //   156: iinc #1, 1
/*     */     //   159: goto -> 135
/*     */     //   162: new javax/crypto/spec/DESKeySpec
/*     */     //   165: dup_x1
/*     */     //   166: swap
/*     */     //   167: invokespecial <init> : ([B)V
/*     */     //   170: invokevirtual generateSecret : (Ljava/security/spec/KeySpec;)Ljavax/crypto/SecretKey;
/*     */     //   173: new javax/crypto/spec/IvParameterSpec
/*     */     //   176: dup
/*     */     //   177: bipush #8
/*     */     //   179: newarray byte
/*     */     //   181: invokespecial <init> : ([B)V
/*     */     //   184: invokevirtual init : (ILjava/security/Key;Ljava/security/spec/AlgorithmParameterSpec;)V
/*     */     //   187: bipush #6
/*     */     //   189: anewarray java/lang/String
/*     */     //   192: astore #7
/*     */     //   194: iconst_0
/*     */     //   195: istore #5
/*     */     //   197: ldc_w '0?'
/*     */     //   200: invokevirtual toCharArray : ()[C
/*     */     //   203: dup
/*     */     //   204: dup
/*     */     //   205: bipush #23
/*     */     //   207: dup_x1
/*     */     //   208: caload
/*     */     //   209: sipush #28670
/*     */     //   212: ixor
/*     */     //   213: i2c
/*     */     //   214: castore
/*     */     //   215: sipush #16480
/*     */     //   218: iconst_1
/*     */     //   219: iconst_0
/*     */     //   220: invokestatic U : (Ljava/lang/Object;SZZ)Ljava/lang/String;
/*     */     //   223: dup
/*     */     //   224: astore #4
/*     */     //   226: invokevirtual length : ()I
/*     */     //   229: istore #6
/*     */     //   231: bipush #16
/*     */     //   233: istore_3
/*     */     //   234: iconst_m1
/*     */     //   235: istore_2
/*     */     //   236: iinc #2, 1
/*     */     //   239: aload #4
/*     */     //   241: iload_2
/*     */     //   242: dup
/*     */     //   243: iload_3
/*     */     //   244: iadd
/*     */     //   245: invokevirtual substring : (II)Ljava/lang/String;
/*     */     //   248: iconst_m1
/*     */     //   249: goto -> 383
/*     */     //   252: aload #7
/*     */     //   254: swap
/*     */     //   255: iload #5
/*     */     //   257: iinc #5, 1
/*     */     //   260: swap
/*     */     //   261: aastore
/*     */     //   262: iload_2
/*     */     //   263: iload_3
/*     */     //   264: iadd
/*     */     //   265: dup
/*     */     //   266: istore_2
/*     */     //   267: iload #6
/*     */     //   269: if_icmpge -> 282
/*     */     //   272: aload #4
/*     */     //   274: iload_2
/*     */     //   275: invokevirtual charAt : (I)C
/*     */     //   278: istore_3
/*     */     //   279: goto -> 236
/*     */     //   282: ldc_w '?'
/*     */     //   285: invokevirtual toCharArray : ()[C
/*     */     //   288: dup
/*     */     //   289: dup
/*     */     //   290: bipush #10
/*     */     //   292: dup_x1
/*     */     //   293: caload
/*     */     //   294: sipush #4922
/*     */     //   297: ixor
/*     */     //   298: i2c
/*     */     //   299: castore
/*     */     //   300: sipush #5323
/*     */     //   303: iconst_0
/*     */     //   304: iconst_1
/*     */     //   305: invokestatic U : (Ljava/lang/Object;SZZ)Ljava/lang/String;
/*     */     //   308: dup
/*     */     //   309: astore #4
/*     */     //   311: invokevirtual length : ()I
/*     */     //   314: istore #6
/*     */     //   316: bipush #16
/*     */     //   318: istore_3
/*     */     //   319: iconst_m1
/*     */     //   320: istore_2
/*     */     //   321: iinc #2, 1
/*     */     //   324: aload #4
/*     */     //   326: iload_2
/*     */     //   327: dup
/*     */     //   328: iload_3
/*     */     //   329: iadd
/*     */     //   330: invokevirtual substring : (II)Ljava/lang/String;
/*     */     //   333: iconst_0
/*     */     //   334: goto -> 383
/*     */     //   337: aload #7
/*     */     //   339: swap
/*     */     //   340: iload #5
/*     */     //   342: iinc #5, 1
/*     */     //   345: swap
/*     */     //   346: aastore
/*     */     //   347: iload_2
/*     */     //   348: iload_3
/*     */     //   349: iadd
/*     */     //   350: dup
/*     */     //   351: istore_2
/*     */     //   352: iload #6
/*     */     //   354: if_icmpge -> 367
/*     */     //   357: aload #4
/*     */     //   359: iload_2
/*     */     //   360: invokevirtual charAt : (I)C
/*     */     //   363: istore_3
/*     */     //   364: goto -> 321
/*     */     //   367: aload #7
/*     */     //   369: putstatic me/konsolas/aac/lq.i : [Ljava/lang/String;
/*     */     //   372: bipush #6
/*     */     //   374: anewarray java/lang/String
/*     */     //   377: putstatic me/konsolas/aac/lq.j : [Ljava/lang/String;
/*     */     //   380: goto -> 448
/*     */     //   383: swap
/*     */     //   384: ldc_w ''
/*     */     //   387: invokevirtual toCharArray : ()[C
/*     */     //   390: dup
/*     */     //   391: dup
/*     */     //   392: bipush #6
/*     */     //   394: dup_x1
/*     */     //   395: caload
/*     */     //   396: sipush #13239
/*     */     //   399: ixor
/*     */     //   400: i2c
/*     */     //   401: castore
/*     */     //   402: sipush #3776
/*     */     //   405: iconst_0
/*     */     //   406: iconst_1
/*     */     //   407: invokestatic U : (Ljava/lang/Object;SZZ)Ljava/lang/String;
/*     */     //   410: invokevirtual getBytes : (Ljava/lang/String;)[B
/*     */     //   413: aload_0
/*     */     //   414: swap
/*     */     //   415: invokevirtual doFinal : ([B)[B
/*     */     //   418: astore #8
/*     */     //   420: aload #8
/*     */     //   422: invokestatic a : ([B)Ljava/lang/String;
/*     */     //   425: invokevirtual intern : ()Ljava/lang/String;
/*     */     //   428: swap
/*     */     //   429: tableswitch default -> 252, 0 -> 337
/*     */     //   448: return
/*     */   }
/*     */   
/*     */   private static v a(v paramv) {
/*     */     return paramv;
/*     */   }
/*     */   
/*     */   private static String a(byte[] paramArrayOfbyte) {
/*     */     byte b1 = 0;
/*     */     int i;
/*     */     char[] arrayOfChar = new char[i = paramArrayOfbyte.length];
/*     */     for (byte b2 = 0; b2 < i; b2++) {
/*     */       int j;
/*     */       if ((j = 0xFF & paramArrayOfbyte[b2]) < 192) {
/*     */         arrayOfChar[b1++] = (char)j;
/*     */       } else if (j < 224) {
/*     */         char c = (char)((char)(j & 0x1F) << 6);
/*     */         j = paramArrayOfbyte[++b2];
/*     */         c = (char)(c | (char)(j & 0x3F));
/*     */         arrayOfChar[b1++] = c;
/*     */       } else if (b2 < i - 2) {
/*     */         char c = (char)((char)(j & 0xF) << 12);
/*     */         j = paramArrayOfbyte[++b2];
/*     */         c = (char)(c | (char)(j & 0x3F) << 6);
/*     */         j = paramArrayOfbyte[++b2];
/*     */         c = (char)(c | (char)(j & 0x3F));
/*     */         arrayOfChar[b1++] = c;
/*     */       } 
/*     */     } 
/*     */     return new String(arrayOfChar, 0, b1);
/*     */   }
/*     */   
/*     */   private static String a(int paramInt, long paramLong) {
/*     */     int i = paramInt ^ (int)(paramLong & 0x7FFFL) ^ 0x1D9D;
/*     */     if (j[i] == null) {
/*     */       Object[] arrayOfObject;
/*     */       try {
/*     */         Long long_ = Long.valueOf(Thread.currentThread().getId());
/*     */         arrayOfObject = (Object[])k.get(long_);
/*     */         if (arrayOfObject == null) {
/*     */           arrayOfObject = new Object[3];
/*     */           "?".toCharArray()[7] = (char)("?".toCharArray()[7] ^ 0x717D);
/*     */           arrayOfObject[0] = Cipher.getInstance(a0$cc.G("?".toCharArray(), (short)1660, true, (byte)2));
/*     */           "".toCharArray()[2] = (char)("".toCharArray()[2] ^ 0x66);
/*     */           arrayOfObject[1] = SecretKeyFactory.getInstance(a0$cc.G("".toCharArray(), (short)21991, true, (byte)2));
/*     */           arrayOfObject[2] = new IvParameterSpec(new byte[8]);
/*     */           k.put(long_, arrayOfObject);
/*     */         } 
/*     */       } catch (Exception exception) {
/*     */         "".toCharArray()[9] = (char)("".toCharArray()[9] ^ 0x3B71);
/*     */         throw new RuntimeException(a0$cc.G("".toCharArray(), (short)24357, false, (byte)4), exception);
/*     */       } 
/*     */       byte[] arrayOfByte1 = new byte[8];
/*     */       arrayOfByte1[0] = (byte)(int)(paramLong >>> 56L);
/*     */       for (byte b = 1; b < 8; b++)
/*     */         arrayOfByte1[b] = (byte)(int)(paramLong << b * 8 >>> 56L); 
/*     */       DESKeySpec dESKeySpec = new DESKeySpec(arrayOfByte1);
/*     */       SecretKey secretKey = ((SecretKeyFactory)arrayOfObject[1]).generateSecret(dESKeySpec);
/*     */       ((Cipher)arrayOfObject[0]).init(2, secretKey, (IvParameterSpec)arrayOfObject[2]);
/*     */       "".toCharArray()[6] = (char)("".toCharArray()[6] ^ 0x6453);
/*     */       byte[] arrayOfByte2 = i[i].getBytes(a0$cc.G("".toCharArray(), (short)5187, false, (byte)2));
/*     */       j[i] = a(((Cipher)arrayOfObject[0]).doFinal(arrayOfByte2));
/*     */     } 
/*     */     return j[i];
/*     */   }
/*     */   
/*     */   private static Object a(MethodHandles.Lookup paramLookup, MutableCallSite paramMutableCallSite, String paramString, Object[] paramArrayOfObject) {
/*     */     int i = ((Integer)paramArrayOfObject[0]).intValue();
/*     */     long l = ((Long)paramArrayOfObject[1]).longValue();
/*     */     String str = a(i, l);
/*     */     MethodHandle methodHandle = MethodHandles.constant(String.class, str);
/*     */     paramMutableCallSite.setTarget(MethodHandles.dropArguments(methodHandle, 0, new Class[] { int.class, long.class }));
/*     */     return str;
/*     */   }
/*     */   
/*     */   private static CallSite a(MethodHandles.Lookup paramLookup, String paramString, MethodType paramMethodType) {
/*     */     // Byte code:
/*     */     //   0: new java/lang/invoke/MutableCallSite
/*     */     //   3: dup
/*     */     //   4: aload_2
/*     */     //   5: invokespecial <init> : (Ljava/lang/invoke/MethodType;)V
/*     */     //   8: astore_3
/*     */     //   9: aload_3
/*     */     //   10: ldc_w
/*     */     //   13: ldc_w [Ljava/lang/Object;
/*     */     //   16: aload_2
/*     */     //   17: invokevirtual parameterCount : ()I
/*     */     //   20: invokevirtual asCollector : (Ljava/lang/Class;I)Ljava/lang/invoke/MethodHandle;
/*     */     //   23: iconst_0
/*     */     //   24: iconst_3
/*     */     //   25: anewarray java/lang/Object
/*     */     //   28: dup
/*     */     //   29: iconst_0
/*     */     //   30: aload_0
/*     */     //   31: aastore
/*     */     //   32: dup
/*     */     //   33: iconst_1
/*     */     //   34: aload_3
/*     */     //   35: aastore
/*     */     //   36: dup
/*     */     //   37: iconst_2
/*     */     //   38: aload_1
/*     */     //   39: aastore
/*     */     //   40: invokestatic insertArguments : (Ljava/lang/invoke/MethodHandle;I[Ljava/lang/Object;)Ljava/lang/invoke/MethodHandle;
/*     */     //   43: aload_2
/*     */     //   44: invokestatic explicitCastArguments : (Ljava/lang/invoke/MethodHandle;Ljava/lang/invoke/MethodType;)Ljava/lang/invoke/MethodHandle;
/*     */     //   47: invokevirtual setTarget : (Ljava/lang/invoke/MethodHandle;)V
/*     */     //   50: goto -> 171
/*     */     //   53: astore #4
/*     */     //   55: new java/lang/RuntimeException
/*     */     //   58: dup
/*     */     //   59: new java/lang/StringBuilder
/*     */     //   62: dup
/*     */     //   63: invokespecial <init> : ()V
/*     */     //   66: ldc_w ''
/*     */     //   69: invokevirtual toCharArray : ()[C
/*     */     //   72: dup
/*     */     //   73: dup
/*     */     //   74: bipush #11
/*     */     //   76: dup_x1
/*     */     //   77: caload
/*     */     //   78: sipush #22779
/*     */     //   81: ixor
/*     */     //   82: i2c
/*     */     //   83: castore
/*     */     //   84: sipush #17987
/*     */     //   87: iconst_1
/*     */     //   88: iconst_1
/*     */     //   89: invokestatic X : (Ljava/lang/Object;SZZ)Ljava/lang/String;
/*     */     //   92: invokevirtual append : (Ljava/lang/String;)Ljava/lang/StringBuilder;
/*     */     //   95: ldc_w ''
/*     */     //   98: invokevirtual toCharArray : ()[C
/*     */     //   101: dup
/*     */     //   102: dup
/*     */     //   103: iconst_0
/*     */     //   104: dup_x1
/*     */     //   105: caload
/*     */     //   106: sipush #30260
/*     */     //   109: ixor
/*     */     //   110: i2c
/*     */     //   111: castore
/*     */     //   112: sipush #29170
/*     */     //   115: iconst_0
/*     */     //   116: iconst_0
/*     */     //   117: invokestatic X : (Ljava/lang/Object;SZZ)Ljava/lang/String;
/*     */     //   120: invokevirtual append : (Ljava/lang/String;)Ljava/lang/StringBuilder;
/*     */     //   123: aload_1
/*     */     //   124: invokevirtual append : (Ljava/lang/String;)Ljava/lang/StringBuilder;
/*     */     //   127: ldc_w ''
/*     */     //   130: invokevirtual toCharArray : ()[C
/*     */     //   133: dup
/*     */     //   134: dup
/*     */     //   135: iconst_0
/*     */     //   136: dup_x1
/*     */     //   137: caload
/*     */     //   138: sipush #10830
/*     */     //   141: ixor
/*     */     //   142: i2c
/*     */     //   143: castore
/*     */     //   144: sipush #25688
/*     */     //   147: iconst_0
/*     */     //   148: iconst_1
/*     */     //   149: invokestatic X : (Ljava/lang/Object;SZZ)Ljava/lang/String;
/*     */     //   152: invokevirtual append : (Ljava/lang/String;)Ljava/lang/StringBuilder;
/*     */     //   155: aload_2
/*     */     //   156: invokevirtual toString : ()Ljava/lang/String;
/*     */     //   159: invokevirtual append : (Ljava/lang/String;)Ljava/lang/StringBuilder;
/*     */     //   162: invokevirtual toString : ()Ljava/lang/String;
/*     */     //   165: aload #4
/*     */     //   167: invokespecial <init> : (Ljava/lang/String;Ljava/lang/Throwable;)V
/*     */     //   170: athrow
/*     */     //   171: aload_3
/*     */     //   172: areturn
/*     */     // Exception table:
/*     */     //   from	to	target	type
/*     */     //   9	50	53	java/lang/Exception
/*     */   } }


/* Location:              C:\Users\BukkitBypass\Desktop\MatrixAC\AAC\AAC-spigot-5.2.0.jar!\me\konsolas\aac\lq.class
 * Java compiler version: 8 (52.0)
 * JD-Core Version:       1.1.3
 */