/*     */ package me.konsolas.aac;
/*     */ import java.io.Closeable;
/*     */ import java.io.File;
/*     */ import java.io.Flushable;
/*     */ import java.lang.invoke.CallSite;
/*     */ import java.lang.invoke.MethodHandle;
/*     */ import java.lang.invoke.MethodHandles;
/*     */ import java.lang.invoke.MethodType;
/*     */ import java.lang.invoke.MutableCallSite;
/*     */ import java.util.Iterator;
/*     */ import java.util.LinkedHashMap;
/*     */ import java.util.Map;
/*     */ import java.util.concurrent.Executor;
/*     */ import java.util.regex.Pattern;
/*     */ import javax.annotation.Nullable;
/*     */ import javax.crypto.Cipher;
/*     */ import javax.crypto.SecretKey;
/*     */ import javax.crypto.SecretKeyFactory;
/*     */ import javax.crypto.spec.DESKeySpec;
/*     */ import javax.crypto.spec.IvParameterSpec;
/*     */ 
/*     */ public final class m5 implements Closeable, Flushable {
/*     */   static final String n;
/*     */   static final String F;
/*     */   static final String j;
/*     */   static final String o;
/*     */   static final String a;
/*     */   static final long b = -1L;
/*     */   static final Pattern t;
/*     */   private static final String c;
/*     */   private static final String g;
/*     */   private static final String y;
/*     */   private static final String v;
/*     */   final j9 h;
/*     */   final File E;
/*     */   private final File A;
/*     */   private final File m;
/*     */   private final File q;
/*     */   private final int C;
/*     */   private long w;
/*     */   final int r;
/*     */   
/*     */   public synchronized long b() {
/*  44 */     return this.w;
/*     */   }
/*     */ 
/*     */ 
/*     */   
/*     */   private long G;
/*     */ 
/*     */   
/*     */   gi D;
/*     */ 
/*     */   
/*     */   final LinkedHashMap f;
/*     */ 
/*     */   
/*     */   int k;
/*     */   
/*     */   boolean d;
/*     */   
/*     */   boolean e;
/*     */   
/*     */   boolean z;
/*     */   
/*     */   boolean x;
/*     */   
/*     */   boolean i;
/*     */   
/*     */   private long s;
/*     */   
/*     */   private final Executor u;
/*     */ 
/*     */   
/*     */   public synchronized long a(long paramLong) {
/*  76 */     paramLong = H ^ paramLong; long l = paramLong ^ 0x6CD285730FF7L; b(l);
/*     */ 
/*     */ 
/*     */ 
/*     */ 
/*     */ 
/*     */ 
/*     */ 
/*     */ 
/*     */ 
/*     */ 
/*     */ 
/*     */ 
/*     */ 
/*     */ 
/*     */ 
/*     */ 
/*     */ 
/*     */ 
/*     */ 
/*     */ 
/*     */ 
/*     */ 
/*     */ 
/*     */ 
/*     */ 
/*     */ 
/*     */ 
/*     */ 
/*     */ 
/*     */ 
/*     */ 
/*     */ 
/*     */ 
/*     */ 
/*     */ 
/*     */ 
/*     */ 
/*     */ 
/*     */ 
/*     */ 
/*     */ 
/*     */ 
/*     */ 
/*     */ 
/*     */ 
/*     */ 
/*     */ 
/*     */ 
/*     */ 
/*     */ 
/*     */ 
/*     */ 
/*     */ 
/*     */ 
/*     */ 
/*     */ 
/*     */ 
/*     */ 
/*     */ 
/*     */ 
/*     */ 
/*     */ 
/*     */ 
/*     */ 
/*     */ 
/*     */ 
/*     */ 
/*     */ 
/*     */ 
/*     */ 
/*     */ 
/*     */ 
/*     */     
/* 150 */     return this.G;
/*     */   }
/*     */ 
/*     */ 
/*     */ 
/*     */   
/*     */   private final Runnable l;
/*     */ 
/*     */ 
/*     */   
/*     */   private static String[] B;
/*     */ 
/*     */ 
/*     */   
/*     */   private static final long H;
/*     */ 
/*     */ 
/*     */   
/*     */   private static final String[] I;
/*     */ 
/*     */ 
/*     */   
/*     */   private static final String[] J;
/*     */ 
/*     */ 
/*     */   
/*     */   private static final Map K;
/*     */ 
/*     */ 
/*     */ 
/*     */   
/*     */   boolean a(bT parambT, long paramLong) {
/*     */     // Byte code:
/*     */     //   0: getstatic me/konsolas/aac/m5.H : J
/*     */     //   3: lload_2
/*     */     //   4: lxor
/*     */     //   5: lstore_2
/*     */     //   6: lload_2
/*     */     //   7: dup2
/*     */     //   8: ldc2_w 46822255389444
/*     */     //   11: lxor
/*     */     //   12: lstore #4
/*     */     //   14: dup2
/*     */     //   15: ldc2_w 54940416775855
/*     */     //   18: lxor
/*     */     //   19: lstore #6
/*     */     //   21: dup2
/*     */     //   22: ldc2_w 134124701538129
/*     */     //   25: lxor
/*     */     //   26: lstore #8
/*     */     //   28: dup2
/*     */     //   29: ldc2_w 30226487623693
/*     */     //   32: lxor
/*     */     //   33: lstore #10
/*     */     //   35: dup2
/*     */     //   36: ldc2_w 96465017575138
/*     */     //   39: lxor
/*     */     //   40: lstore #12
/*     */     //   42: pop2
/*     */     //   43: ldc2_w -2040871850142380854
/*     */     //   46: lload_2
/*     */     //   47: <illegal opcode> w : (JJ)[Ljava/lang/String;
/*     */     //   52: astore #14
/*     */     //   54: aload_1
/*     */     //   55: getfield f : Lme/konsolas/aac/dO;
/*     */     //   58: aload #14
/*     */     //   60: ifnonnull -> 96
/*     */     //   63: ifnull -> 101
/*     */     //   66: goto -> 79
/*     */     //   69: ldc2_w -2051950480130609969
/*     */     //   72: lload_2
/*     */     //   73: <illegal opcode> w : (Ljava/lang/Throwable;JJ)Ljava/lang/Throwable;
/*     */     //   78: athrow
/*     */     //   79: aload_1
/*     */     //   80: getfield f : Lme/konsolas/aac/dO;
/*     */     //   83: goto -> 96
/*     */     //   86: ldc2_w -2051950480130609969
/*     */     //   89: lload_2
/*     */     //   90: <illegal opcode> w : (Ljava/lang/Throwable;JJ)Ljava/lang/Throwable;
/*     */     //   95: athrow
/*     */     //   96: lload #6
/*     */     //   98: invokevirtual a : (J)V
/*     */     //   101: iconst_0
/*     */     //   102: istore #15
/*     */     //   104: iload #15
/*     */     //   106: aload_0
/*     */     //   107: getfield r : I
/*     */     //   110: if_icmpge -> 195
/*     */     //   113: aload_0
/*     */     //   114: getfield h : Lme/konsolas/aac/j9;
/*     */     //   117: aload_1
/*     */     //   118: getfield b : [Ljava/io/File;
/*     */     //   121: iload #15
/*     */     //   123: aaload
/*     */     //   124: lload #12
/*     */     //   126: dup2_x1
/*     */     //   127: pop2
/*     */     //   128: invokeinterface b : (JLjava/io/File;)V
/*     */     //   133: aload_0
/*     */     //   134: dup
/*     */     //   135: getfield G : J
/*     */     //   138: aload_1
/*     */     //   139: getfield e : [J
/*     */     //   142: iload #15
/*     */     //   144: laload
/*     */     //   145: lsub
/*     */     //   146: putfield G : J
/*     */     //   149: aload_1
/*     */     //   150: getfield e : [J
/*     */     //   153: iload #15
/*     */     //   155: lconst_0
/*     */     //   156: lastore
/*     */     //   157: iinc #15, 1
/*     */     //   160: lload_2
/*     */     //   161: lconst_0
/*     */     //   162: lcmp
/*     */     //   163: iflt -> 271
/*     */     //   166: aload #14
/*     */     //   168: ifnonnull -> 271
/*     */     //   171: aload #14
/*     */     //   173: ifnull -> 104
/*     */     //   176: lload_2
/*     */     //   177: lconst_0
/*     */     //   178: lcmp
/*     */     //   179: ifle -> 160
/*     */     //   182: goto -> 195
/*     */     //   185: ldc2_w -2051950480130609969
/*     */     //   188: lload_2
/*     */     //   189: <illegal opcode> w : (Ljava/lang/Throwable;JJ)Ljava/lang/Throwable;
/*     */     //   194: athrow
/*     */     //   195: aload_0
/*     */     //   196: dup
/*     */     //   197: getfield k : I
/*     */     //   200: iconst_1
/*     */     //   201: iadd
/*     */     //   202: putfield k : I
/*     */     //   205: aload_0
/*     */     //   206: getfield D : Lme/konsolas/aac/gi;
/*     */     //   209: sipush #30054
/*     */     //   212: ldc2_w 3861823713467303317
/*     */     //   215: lload_2
/*     */     //   216: lxor
/*     */     //   217: <illegal opcode> z : (IJ)Ljava/lang/String;
/*     */     //   222: lload #10
/*     */     //   224: invokeinterface a : (Ljava/lang/String;J)Lme/konsolas/aac/gi;
/*     */     //   229: bipush #32
/*     */     //   231: lload #4
/*     */     //   233: invokeinterface d : (IJ)Lme/konsolas/aac/gi;
/*     */     //   238: aload_1
/*     */     //   239: getfield g : Ljava/lang/String;
/*     */     //   242: lload #10
/*     */     //   244: invokeinterface a : (Ljava/lang/String;J)Lme/konsolas/aac/gi;
/*     */     //   249: bipush #10
/*     */     //   251: lload #4
/*     */     //   253: invokeinterface d : (IJ)Lme/konsolas/aac/gi;
/*     */     //   258: pop
/*     */     //   259: aload_0
/*     */     //   260: getfield f : Ljava/util/LinkedHashMap;
/*     */     //   263: aload_1
/*     */     //   264: getfield g : Ljava/lang/String;
/*     */     //   267: invokevirtual remove : (Ljava/lang/Object;)Ljava/lang/Object;
/*     */     //   270: pop
/*     */     //   271: aload_0
/*     */     //   272: lload #8
/*     */     //   274: invokevirtual b : (J)Z
/*     */     //   277: aload #14
/*     */     //   279: ifnonnull -> 325
/*     */     //   282: ifeq -> 324
/*     */     //   285: goto -> 298
/*     */     //   288: ldc2_w -2051950480130609969
/*     */     //   291: lload_2
/*     */     //   292: <illegal opcode> w : (Ljava/lang/Throwable;JJ)Ljava/lang/Throwable;
/*     */     //   297: athrow
/*     */     //   298: aload_0
/*     */     //   299: getfield u : Ljava/util/concurrent/Executor;
/*     */     //   302: aload_0
/*     */     //   303: getfield l : Ljava/lang/Runnable;
/*     */     //   306: invokeinterface execute : (Ljava/lang/Runnable;)V
/*     */     //   311: goto -> 324
/*     */     //   314: ldc2_w -2051950480130609969
/*     */     //   317: lload_2
/*     */     //   318: <illegal opcode> w : (Ljava/lang/Throwable;JJ)Ljava/lang/Throwable;
/*     */     //   323: athrow
/*     */     //   324: iconst_1
/*     */     //   325: ireturn
/*     */     // Line number table:
/*     */     //   Java source line number -> byte code offset
/*     */     //   #8	-> 54
/*     */     //   #69	-> 79
/*     */     //   #12	-> 101
/*     */     //   #285	-> 113
/*     */     //   #290	-> 133
/*     */     //   #184	-> 149
/*     */     //   #110	-> 157
/*     */     //   #219	-> 195
/*     */     //   #86	-> 205
/*     */     //   #21	-> 259
/*     */     //   #159	-> 271
/*     */     //   #213	-> 298
/*     */     //   #52	-> 324
/*     */     // Exception table:
/*     */     //   from	to	target	type
/*     */     //   54	66	69	java/io/IOException
/*     */     //   63	83	86	java/io/IOException
/*     */     //   113	176	185	java/io/IOException
/*     */     //   271	285	288	java/io/IOException
/*     */     //   282	311	314	java/io/IOException
/*     */   }
/*     */ 
/*     */ 
/*     */   
/*     */   public synchronized boolean a(String paramString, long paramLong) {
/*     */     // Byte code:
/*     */     //   0: getstatic me/konsolas/aac/m5.H : J
/*     */     //   3: lload_2
/*     */     //   4: lxor
/*     */     //   5: lstore_2
/*     */     //   6: lload_2
/*     */     //   7: dup2
/*     */     //   8: ldc2_w 79329047958817
/*     */     //   11: lxor
/*     */     //   12: lstore #4
/*     */     //   14: dup2
/*     */     //   15: ldc2_w 85524266115451
/*     */     //   18: lxor
/*     */     //   19: lstore #6
/*     */     //   21: dup2
/*     */     //   22: ldc2_w 64843889679970
/*     */     //   25: lxor
/*     */     //   26: dup2
/*     */     //   27: bipush #48
/*     */     //   29: lushr
/*     */     //   30: l2i
/*     */     //   31: istore #8
/*     */     //   33: dup2
/*     */     //   34: bipush #16
/*     */     //   36: lshl
/*     */     //   37: bipush #16
/*     */     //   39: lushr
/*     */     //   40: lstore #9
/*     */     //   42: pop2
/*     */     //   43: dup2
/*     */     //   44: ldc2_w 404288646152
/*     */     //   47: lxor
/*     */     //   48: lstore #11
/*     */     //   50: pop2
/*     */     //   51: ldc2_w 5970970789733072314
/*     */     //   54: lload_2
/*     */     //   55: <illegal opcode> w : (JJ)[Ljava/lang/String;
/*     */     //   60: aload_0
/*     */     //   61: lload #11
/*     */     //   63: invokevirtual b : (J)V
/*     */     //   66: astore #13
/*     */     //   68: aload_0
/*     */     //   69: iload #8
/*     */     //   71: i2c
/*     */     //   72: lload #9
/*     */     //   74: invokespecial c : (CJ)V
/*     */     //   77: aload_0
/*     */     //   78: aload_1
/*     */     //   79: lload #4
/*     */     //   81: invokespecial b : (Ljava/lang/String;J)V
/*     */     //   84: aload_0
/*     */     //   85: getfield f : Ljava/util/LinkedHashMap;
/*     */     //   88: aload_1
/*     */     //   89: invokevirtual get : (Ljava/lang/Object;)Ljava/lang/Object;
/*     */     //   92: checkcast me/konsolas/aac/bT
/*     */     //   95: astore #14
/*     */     //   97: aload #14
/*     */     //   99: ifnonnull -> 114
/*     */     //   102: iconst_0
/*     */     //   103: ireturn
/*     */     //   104: ldc2_w 5978100216655633855
/*     */     //   107: lload_2
/*     */     //   108: <illegal opcode> w : (Ljava/lang/Throwable;JJ)Ljava/lang/Throwable;
/*     */     //   113: athrow
/*     */     //   114: aload_0
/*     */     //   115: aload #14
/*     */     //   117: lload #6
/*     */     //   119: invokevirtual a : (Lme/konsolas/aac/bT;J)Z
/*     */     //   122: istore #15
/*     */     //   124: iload #15
/*     */     //   126: aload #13
/*     */     //   128: ifnonnull -> 210
/*     */     //   131: ifeq -> 208
/*     */     //   134: goto -> 147
/*     */     //   137: ldc2_w 5978100216655633855
/*     */     //   140: lload_2
/*     */     //   141: <illegal opcode> w : (Ljava/lang/Throwable;JJ)Ljava/lang/Throwable;
/*     */     //   146: athrow
/*     */     //   147: aload_0
/*     */     //   148: getfield G : J
/*     */     //   151: aload_0
/*     */     //   152: getfield w : J
/*     */     //   155: lcmp
/*     */     //   156: aload #13
/*     */     //   158: ifnonnull -> 210
/*     */     //   161: goto -> 174
/*     */     //   164: ldc2_w 5978100216655633855
/*     */     //   167: lload_2
/*     */     //   168: <illegal opcode> w : (Ljava/lang/Throwable;JJ)Ljava/lang/Throwable;
/*     */     //   173: athrow
/*     */     //   174: ifgt -> 208
/*     */     //   177: goto -> 190
/*     */     //   180: ldc2_w 5978100216655633855
/*     */     //   183: lload_2
/*     */     //   184: <illegal opcode> w : (Ljava/lang/Throwable;JJ)Ljava/lang/Throwable;
/*     */     //   189: athrow
/*     */     //   190: aload_0
/*     */     //   191: iconst_0
/*     */     //   192: putfield x : Z
/*     */     //   195: goto -> 208
/*     */     //   198: ldc2_w 5978100216655633855
/*     */     //   201: lload_2
/*     */     //   202: <illegal opcode> w : (Ljava/lang/Throwable;JJ)Ljava/lang/Throwable;
/*     */     //   207: athrow
/*     */     //   208: iload #15
/*     */     //   210: ireturn
/*     */     // Line number table:
/*     */     //   Java source line number -> byte code offset
/*     */     //   #16	-> 60
/*     */     //   #115	-> 68
/*     */     //   #163	-> 77
/*     */     //   #7	-> 84
/*     */     //   #283	-> 97
/*     */     //   #120	-> 114
/*     */     //   #171	-> 124
/*     */     //   #267	-> 208
/*     */     // Exception table:
/*     */     //   from	to	target	type
/*     */     //   97	104	104	java/io/IOException
/*     */     //   124	134	137	java/io/IOException
/*     */     //   131	161	164	java/io/IOException
/*     */     //   147	177	180	java/io/IOException
/*     */     //   174	195	198	java/io/IOException
/*     */   }
/*     */ 
/*     */ 
/*     */   
/*     */   public static m5 a(short paramShort1, j9 paramj9, File paramFile, int paramInt1, int paramInt2, int paramInt3, short paramShort2, long paramLong) {
/*     */     // Byte code:
/*     */     //   0: iload_0
/*     */     //   1: i2l
/*     */     //   2: bipush #48
/*     */     //   4: lshl
/*     */     //   5: iload #5
/*     */     //   7: i2l
/*     */     //   8: bipush #32
/*     */     //   10: lshl
/*     */     //   11: bipush #16
/*     */     //   13: lushr
/*     */     //   14: lor
/*     */     //   15: iload #6
/*     */     //   17: i2l
/*     */     //   18: bipush #48
/*     */     //   20: lshl
/*     */     //   21: bipush #48
/*     */     //   23: lushr
/*     */     //   24: lor
/*     */     //   25: getstatic me/konsolas/aac/m5.H : J
/*     */     //   28: lxor
/*     */     //   29: lstore #9
/*     */     //   31: lload #9
/*     */     //   33: dup2
/*     */     //   34: ldc2_w 89197639180074
/*     */     //   37: lxor
/*     */     //   38: dup2
/*     */     //   39: bipush #48
/*     */     //   41: lushr
/*     */     //   42: l2i
/*     */     //   43: istore #11
/*     */     //   45: dup2
/*     */     //   46: bipush #16
/*     */     //   48: lshl
/*     */     //   49: bipush #32
/*     */     //   51: lushr
/*     */     //   52: l2i
/*     */     //   53: istore #12
/*     */     //   55: dup2
/*     */     //   56: bipush #48
/*     */     //   58: lshl
/*     */     //   59: bipush #48
/*     */     //   61: lushr
/*     */     //   62: l2i
/*     */     //   63: istore #13
/*     */     //   65: pop2
/*     */     //   66: pop2
/*     */     //   67: ldc2_w -1928630051974854053
/*     */     //   70: lload #9
/*     */     //   72: <illegal opcode> w : (JJ)[Ljava/lang/String;
/*     */     //   77: astore #14
/*     */     //   79: lload #7
/*     */     //   81: lconst_0
/*     */     //   82: lcmp
/*     */     //   83: aload #14
/*     */     //   85: ifnonnull -> 140
/*     */     //   88: ifgt -> 138
/*     */     //   91: goto -> 105
/*     */     //   94: ldc2_w -1938943560383370658
/*     */     //   97: lload #9
/*     */     //   99: <illegal opcode> w : (Ljava/lang/Throwable;JJ)Ljava/lang/Throwable;
/*     */     //   104: athrow
/*     */     //   105: new java/lang/IllegalArgumentException
/*     */     //   108: dup
/*     */     //   109: sipush #23245
/*     */     //   112: ldc2_w 6698736908383464585
/*     */     //   115: lload #9
/*     */     //   117: lxor
/*     */     //   118: <illegal opcode> z : (IJ)Ljava/lang/String;
/*     */     //   123: invokespecial <init> : (Ljava/lang/String;)V
/*     */     //   126: athrow
/*     */     //   127: ldc2_w -1938943560383370658
/*     */     //   130: lload #9
/*     */     //   132: <illegal opcode> w : (Ljava/lang/Throwable;JJ)Ljava/lang/Throwable;
/*     */     //   137: athrow
/*     */     //   138: iload #4
/*     */     //   140: ifgt -> 176
/*     */     //   143: new java/lang/IllegalArgumentException
/*     */     //   146: dup
/*     */     //   147: sipush #6623
/*     */     //   150: ldc2_w 6034265732250202020
/*     */     //   153: lload #9
/*     */     //   155: lxor
/*     */     //   156: <illegal opcode> z : (IJ)Ljava/lang/String;
/*     */     //   161: invokespecial <init> : (Ljava/lang/String;)V
/*     */     //   164: athrow
/*     */     //   165: ldc2_w -1938943560383370658
/*     */     //   168: lload #9
/*     */     //   170: <illegal opcode> w : (Ljava/lang/Throwable;JJ)Ljava/lang/Throwable;
/*     */     //   175: athrow
/*     */     //   176: new java/util/concurrent/ThreadPoolExecutor
/*     */     //   179: dup
/*     */     //   180: iconst_0
/*     */     //   181: iconst_1
/*     */     //   182: ldc2_w 60
/*     */     //   185: getstatic java/util/concurrent/TimeUnit.SECONDS : Ljava/util/concurrent/TimeUnit;
/*     */     //   188: new java/util/concurrent/LinkedBlockingQueue
/*     */     //   191: dup
/*     */     //   192: invokespecial <init> : ()V
/*     */     //   195: sipush #13631
/*     */     //   198: ldc2_w 2825915452937552724
/*     */     //   201: lload #9
/*     */     //   203: lxor
/*     */     //   204: <illegal opcode> z : (IJ)Ljava/lang/String;
/*     */     //   209: iconst_1
/*     */     //   210: invokestatic a : (Ljava/lang/String;Z)Ljava/util/concurrent/ThreadFactory;
/*     */     //   213: invokespecial <init> : (IIJLjava/util/concurrent/TimeUnit;Ljava/util/concurrent/BlockingQueue;Ljava/util/concurrent/ThreadFactory;)V
/*     */     //   216: astore #15
/*     */     //   218: new me/konsolas/aac/m5
/*     */     //   221: dup
/*     */     //   222: aload_1
/*     */     //   223: iload #11
/*     */     //   225: i2s
/*     */     //   226: aload_2
/*     */     //   227: iload_3
/*     */     //   228: iload #4
/*     */     //   230: iload #12
/*     */     //   232: iload #13
/*     */     //   234: lload #7
/*     */     //   236: aload #15
/*     */     //   238: invokespecial <init> : (Lme/konsolas/aac/j9;SLjava/io/File;IIIIJLjava/util/concurrent/Executor;)V
/*     */     //   241: areturn
/*     */     // Line number table:
/*     */     //   Java source line number -> byte code offset
/*     */     //   #35	-> 79
/*     */     //   #27	-> 105
/*     */     //   #247	-> 138
/*     */     //   #128	-> 143
/*     */     //   #87	-> 176
/*     */     //   #174	-> 210
/*     */     //   #73	-> 218
/*     */     // Exception table:
/*     */     //   from	to	target	type
/*     */     //   79	91	94	java/lang/IllegalArgumentException
/*     */     //   88	127	127	java/lang/IllegalArgumentException
/*     */     //   140	165	165	java/lang/IllegalArgumentException
/*     */   }
/*     */ 
/*     */ 
/*     */   
/*     */   public void g(long paramLong) {
/*     */     paramLong = H ^ paramLong;
/*     */     long l = paramLong ^ 0x1BCC4EBFF213L;
/*     */     close();
/* 203 */     this.h.a(l, this.E);
/*     */   } public synchronized void e(long paramLong) {
/*     */     // Byte code:
/*     */     //   0: getstatic me/konsolas/aac/m5.H : J
/*     */     //   3: lload_1
/*     */     //   4: lxor
/*     */     //   5: lstore_1
/*     */     //   6: lload_1
/*     */     //   7: dup2
/*     */     //   8: ldc2_w 51212443862993
/*     */     //   11: lxor
/*     */     //   12: lstore_3
/*     */     //   13: dup2
/*     */     //   14: ldc2_w 108874627353250
/*     */     //   17: lxor
/*     */     //   18: lstore #5
/*     */     //   20: pop2
/*     */     //   21: aload_0
/*     */     //   22: lload #5
/*     */     //   24: invokevirtual b : (J)V
/*     */     //   27: aload_0
/*     */     //   28: getfield f : Ljava/util/LinkedHashMap;
/*     */     //   31: invokevirtual values : ()Ljava/util/Collection;
/*     */     //   34: aload_0
/*     */     //   35: getfield f : Ljava/util/LinkedHashMap;
/*     */     //   38: invokevirtual size : ()I
/*     */     //   41: anewarray me/konsolas/aac/bT
/*     */     //   44: invokeinterface toArray : ([Ljava/lang/Object;)[Ljava/lang/Object;
/*     */     //   49: checkcast [Lme/konsolas/aac/bT;
/*     */     //   52: astore #8
/*     */     //   54: aload #8
/*     */     //   56: arraylength
/*     */     //   57: istore #9
/*     */     //   59: ldc2_w 8392252397027842832
/*     */     //   62: lload_1
/*     */     //   63: <illegal opcode> w : (JJ)[Ljava/lang/String;
/*     */     //   68: iconst_0
/*     */     //   69: istore #10
/*     */     //   71: astore #7
/*     */     //   73: iload #10
/*     */     //   75: iload #9
/*     */     //   77: if_icmpge -> 133
/*     */     //   80: aload #8
/*     */     //   82: iload #10
/*     */     //   84: aaload
/*     */     //   85: astore #11
/*     */     //   87: aload_0
/*     */     //   88: aload #11
/*     */     //   90: lload_3
/*     */     //   91: invokevirtual a : (Lme/konsolas/aac/bT;J)Z
/*     */     //   94: pop
/*     */     //   95: iinc #10, 1
/*     */     //   98: aload #7
/*     */     //   100: lload_1
/*     */     //   101: lconst_0
/*     */     //   102: lcmp
/*     */     //   103: iflt -> 111
/*     */     //   106: ifnonnull -> 138
/*     */     //   109: aload #7
/*     */     //   111: ifnull -> 73
/*     */     //   114: lload_1
/*     */     //   115: lconst_0
/*     */     //   116: lcmp
/*     */     //   117: iflt -> 98
/*     */     //   120: goto -> 133
/*     */     //   123: ldc2_w 8384604241107876629
/*     */     //   126: lload_1
/*     */     //   127: <illegal opcode> w : (Ljava/lang/Throwable;JJ)Ljava/lang/Throwable;
/*     */     //   132: athrow
/*     */     //   133: aload_0
/*     */     //   134: iconst_0
/*     */     //   135: putfield x : Z
/*     */     //   138: return
/*     */     // Line number table:
/*     */     //   Java source line number -> byte code offset
/*     */     //   #49	-> 21
/*     */     //   #57	-> 27
/*     */     //   #29	-> 87
/*     */     //   #250	-> 95
/*     */     //   #98	-> 133
/*     */     //   #288	-> 138
/*     */     // Exception table:
/*     */     //   from	to	target	type
/*     */     //   87	114	123	java/io/IOException
/*     */   } private synchronized void c(char paramChar, long paramLong) {
/*     */     // Byte code:
/*     */     //   0: iload_1
/*     */     //   1: i2l
/*     */     //   2: bipush #48
/*     */     //   4: lshl
/*     */     //   5: lload_2
/*     */     //   6: bipush #16
/*     */     //   8: lshl
/*     */     //   9: bipush #16
/*     */     //   11: lushr
/*     */     //   12: lor
/*     */     //   13: getstatic me/konsolas/aac/m5.H : J
/*     */     //   16: lxor
/*     */     //   17: lstore #4
/*     */     //   19: aload_0
/*     */     //   20: invokevirtual a : ()Z
/*     */     //   23: ifeq -> 59
/*     */     //   26: new java/lang/IllegalStateException
/*     */     //   29: dup
/*     */     //   30: sipush #3005
/*     */     //   33: ldc2_w 2667514286607205491
/*     */     //   36: lload #4
/*     */     //   38: lxor
/*     */     //   39: <illegal opcode> z : (IJ)Ljava/lang/String;
/*     */     //   44: invokespecial <init> : (Ljava/lang/String;)V
/*     */     //   47: athrow
/*     */     //   48: ldc2_w 2062497832926811094
/*     */     //   51: lload #4
/*     */     //   53: <illegal opcode> w : (Ljava/lang/Throwable;JJ)Ljava/lang/Throwable;
/*     */     //   58: athrow
/*     */     //   59: return
/*     */     // Line number table:
/*     */     //   Java source line number -> byte code offset
/*     */     //   #51	-> 19
/*     */     //   #11	-> 26
/*     */     //   #289	-> 59
/*     */     // Exception table:
/*     */     //   from	to	target	type
/*     */     //   19	48	48	java/lang/IllegalArgumentException
/*     */   } public synchronized void flush() {
/*     */     // Byte code:
/*     */     //   0: getstatic me/konsolas/aac/m5.H : J
/*     */     //   3: ldc2_w 12621481122757
/*     */     //   6: lxor
/*     */     //   7: lstore_1
/*     */     //   8: lload_1
/*     */     //   9: dup2
/*     */     //   10: ldc2_w 121011870734914
/*     */     //   13: lxor
/*     */     //   14: lstore_3
/*     */     //   15: dup2
/*     */     //   16: ldc2_w 47705992988408
/*     */     //   19: lxor
/*     */     //   20: dup2
/*     */     //   21: bipush #48
/*     */     //   23: lushr
/*     */     //   24: l2i
/*     */     //   25: istore #5
/*     */     //   27: dup2
/*     */     //   28: bipush #16
/*     */     //   30: lshl
/*     */     //   31: bipush #16
/*     */     //   33: lushr
/*     */     //   34: lstore #6
/*     */     //   36: pop2
/*     */     //   37: pop2
/*     */     //   38: ldc2_w -3871063958252985056
/*     */     //   41: lload_1
/*     */     //   42: <illegal opcode> w : (JJ)[Ljava/lang/String;
/*     */     //   47: astore #8
/*     */     //   49: aload_0
/*     */     //   50: aload #8
/*     */     //   52: ifnonnull -> 100
/*     */     //   55: getfield e : Z
/*     */     //   58: ifne -> 85
/*     */     //   61: goto -> 74
/*     */     //   64: ldc2_w -3860592155534342875
/*     */     //   67: lload_1
/*     */     //   68: <illegal opcode> w : (Ljava/lang/Throwable;JJ)Ljava/lang/Throwable;
/*     */     //   73: athrow
/*     */     //   74: return
/*     */     //   75: ldc2_w -3860592155534342875
/*     */     //   78: lload_1
/*     */     //   79: <illegal opcode> w : (Ljava/lang/Throwable;JJ)Ljava/lang/Throwable;
/*     */     //   84: athrow
/*     */     //   85: aload_0
/*     */     //   86: iload #5
/*     */     //   88: i2c
/*     */     //   89: lload #6
/*     */     //   91: invokespecial c : (CJ)V
/*     */     //   94: aload_0
/*     */     //   95: lload_3
/*     */     //   96: invokevirtual a : (J)V
/*     */     //   99: aload_0
/*     */     //   100: getfield D : Lme/konsolas/aac/gi;
/*     */     //   103: invokeinterface flush : ()V
/*     */     //   108: return
/*     */     // Line number table:
/*     */     //   Java source line number -> byte code offset
/*     */     //   #75	-> 49
/*     */     //   #172	-> 85
/*     */     //   #137	-> 94
/*     */     //   #79	-> 99
/*     */     //   #50	-> 108
/*     */     // Exception table:
/*     */     //   from	to	target	type
/*     */     //   49	61	64	java/io/IOException
/*     */     //   55	75	75	java/io/IOException
/*     */   } public File a() {
/*     */     return this.E;
/*     */   } void a(long paramLong) {
/*     */     // Byte code:
/*     */     //   0: getstatic me/konsolas/aac/m5.H : J
/*     */     //   3: lload_1
/*     */     //   4: lxor
/*     */     //   5: lstore_1
/*     */     //   6: lload_1
/*     */     //   7: dup2
/*     */     //   8: ldc2_w 4416169685928
/*     */     //   11: lxor
/*     */     //   12: lstore_3
/*     */     //   13: pop2
/*     */     //   14: ldc2_w -9219308788849561751
/*     */     //   17: lload_1
/*     */     //   18: <illegal opcode> w : (JJ)[Ljava/lang/String;
/*     */     //   23: astore #5
/*     */     //   25: aload_0
/*     */     //   26: getfield G : J
/*     */     //   29: aload_0
/*     */     //   30: getfield w : J
/*     */     //   33: lcmp
/*     */     //   34: ifle -> 102
/*     */     //   37: aload_0
/*     */     //   38: getfield f : Ljava/util/LinkedHashMap;
/*     */     //   41: invokevirtual values : ()Ljava/util/Collection;
/*     */     //   44: invokeinterface iterator : ()Ljava/util/Iterator;
/*     */     //   49: invokeinterface next : ()Ljava/lang/Object;
/*     */     //   54: checkcast me/konsolas/aac/bT
/*     */     //   57: astore #6
/*     */     //   59: aload_0
/*     */     //   60: aload #6
/*     */     //   62: lload_3
/*     */     //   63: invokevirtual a : (Lme/konsolas/aac/bT;J)Z
/*     */     //   66: pop
/*     */     //   67: aload #5
/*     */     //   69: lload_1
/*     */     //   70: lconst_0
/*     */     //   71: lcmp
/*     */     //   72: ifle -> 80
/*     */     //   75: ifnonnull -> 107
/*     */     //   78: aload #5
/*     */     //   80: ifnull -> 25
/*     */     //   83: lload_1
/*     */     //   84: lconst_0
/*     */     //   85: lcmp
/*     */     //   86: iflt -> 67
/*     */     //   89: goto -> 102
/*     */     //   92: ldc2_w -9212900606630949012
/*     */     //   95: lload_1
/*     */     //   96: <illegal opcode> w : (Ljava/lang/Throwable;JJ)Ljava/lang/Throwable;
/*     */     //   101: athrow
/*     */     //   102: aload_0
/*     */     //   103: iconst_0
/*     */     //   104: putfield x : Z
/*     */     //   107: return
/*     */     // Line number table:
/*     */     //   Java source line number -> byte code offset
/*     */     //   #101	-> 25
/*     */     //   #140	-> 37
/*     */     //   #274	-> 59
/*     */     //   #272	-> 67
/*     */     //   #276	-> 102
/*     */     //   #280	-> 107
/*     */     // Exception table:
/*     */     //   from	to	target	type
/*     */     //   59	83	92	java/io/IOException
/*     */   } public synchronized boolean a() {
/*     */     return this.z;
/*     */   } public synchronized void a(long paramLong, int paramInt1, short paramShort, int paramInt2) {
/*     */     // Byte code:
/*     */     //   0: iload_3
/*     */     //   1: i2l
/*     */     //   2: bipush #32
/*     */     //   4: lshl
/*     */     //   5: iload #4
/*     */     //   7: i2l
/*     */     //   8: bipush #48
/*     */     //   10: lshl
/*     */     //   11: bipush #32
/*     */     //   13: lushr
/*     */     //   14: lor
/*     */     //   15: iload #5
/*     */     //   17: i2l
/*     */     //   18: bipush #48
/*     */     //   20: lshl
/*     */     //   21: bipush #48
/*     */     //   23: lushr
/*     */     //   24: lor
/*     */     //   25: getstatic me/konsolas/aac/m5.H : J
/*     */     //   28: lxor
/*     */     //   29: lstore #6
/*     */     //   31: ldc2_w -4297526314739143877
/*     */     //   34: lload #6
/*     */     //   36: <illegal opcode> w : (JJ)[Ljava/lang/String;
/*     */     //   41: aload_0
/*     */     //   42: lload_1
/*     */     //   43: putfield w : J
/*     */     //   46: astore #8
/*     */     //   48: aload_0
/*     */     //   49: aload #8
/*     */     //   51: ifnonnull -> 89
/*     */     //   54: getfield e : Z
/*     */     //   57: ifeq -> 101
/*     */     //   60: goto -> 74
/*     */     //   63: ldc2_w -4289886850218177730
/*     */     //   66: lload #6
/*     */     //   68: <illegal opcode> w : (Ljava/lang/Throwable;JJ)Ljava/lang/Throwable;
/*     */     //   73: athrow
/*     */     //   74: aload_0
/*     */     //   75: goto -> 89
/*     */     //   78: ldc2_w -4289886850218177730
/*     */     //   81: lload #6
/*     */     //   83: <illegal opcode> w : (Ljava/lang/Throwable;JJ)Ljava/lang/Throwable;
/*     */     //   88: athrow
/*     */     //   89: getfield u : Ljava/util/concurrent/Executor;
/*     */     //   92: aload_0
/*     */     //   93: getfield l : Ljava/lang/Runnable;
/*     */     //   96: invokeinterface execute : (Ljava/lang/Runnable;)V
/*     */     //   101: return
/*     */     // Line number table:
/*     */     //   Java source line number -> byte code offset
/*     */     //   #113	-> 41
/*     */     //   #204	-> 48
/*     */     //   #279	-> 74
/*     */     //   #264	-> 101
/*     */     // Exception table:
/*     */     //   from	to	target	type
/*     */     //   48	60	63	java/lang/IllegalArgumentException
/*     */     //   54	75	78	java/lang/IllegalArgumentException
/*     */   } m5(j9 paramj9, short paramShort, File paramFile, int paramInt1, int paramInt2, int paramInt3, int paramInt4, long paramLong, Executor paramExecutor) {
/*     */     // Byte code:
/*     */     //   0: iload_2
/*     */     //   1: i2l
/*     */     //   2: bipush #48
/*     */     //   4: lshl
/*     */     //   5: iload #6
/*     */     //   7: i2l
/*     */     //   8: bipush #32
/*     */     //   10: lshl
/*     */     //   11: bipush #16
/*     */     //   13: lushr
/*     */     //   14: lor
/*     */     //   15: iload #7
/*     */     //   17: i2l
/*     */     //   18: bipush #48
/*     */     //   20: lshl
/*     */     //   21: bipush #48
/*     */     //   23: lushr
/*     */     //   24: lor
/*     */     //   25: getstatic me/konsolas/aac/m5.H : J
/*     */     //   28: lxor
/*     */     //   29: lstore #11
/*     */     //   31: ldc2_w 3034659141920654714
/*     */     //   34: lload #11
/*     */     //   36: <illegal opcode> w : (JJ)[Ljava/lang/String;
/*     */     //   41: aload_0
/*     */     //   42: invokespecial <init> : ()V
/*     */     //   45: aload_0
/*     */     //   46: lconst_0
/*     */     //   47: putfield G : J
/*     */     //   50: astore #13
/*     */     //   52: aload_0
/*     */     //   53: new java/util/LinkedHashMap
/*     */     //   56: dup
/*     */     //   57: iconst_0
/*     */     //   58: ldc 0.75
/*     */     //   60: iconst_1
/*     */     //   61: invokespecial <init> : (IFZ)V
/*     */     //   64: putfield f : Ljava/util/LinkedHashMap;
/*     */     //   67: aload_0
/*     */     //   68: lconst_0
/*     */     //   69: putfield s : J
/*     */     //   72: aload_0
/*     */     //   73: new me/konsolas/aac/mS
/*     */     //   76: dup
/*     */     //   77: aload_0
/*     */     //   78: invokespecial <init> : (Lme/konsolas/aac/m5;)V
/*     */     //   81: putfield l : Ljava/lang/Runnable;
/*     */     //   84: aload_0
/*     */     //   85: aload_1
/*     */     //   86: putfield h : Lme/konsolas/aac/j9;
/*     */     //   89: aload_0
/*     */     //   90: aload_3
/*     */     //   91: putfield E : Ljava/io/File;
/*     */     //   94: aload_0
/*     */     //   95: iload #4
/*     */     //   97: putfield C : I
/*     */     //   100: aload_0
/*     */     //   101: new java/io/File
/*     */     //   104: dup
/*     */     //   105: aload_3
/*     */     //   106: sipush #31166
/*     */     //   109: ldc2_w 6278352646349930729
/*     */     //   112: lload #11
/*     */     //   114: lxor
/*     */     //   115: <illegal opcode> z : (IJ)Ljava/lang/String;
/*     */     //   120: invokespecial <init> : (Ljava/io/File;Ljava/lang/String;)V
/*     */     //   123: putfield A : Ljava/io/File;
/*     */     //   126: aload_0
/*     */     //   127: new java/io/File
/*     */     //   130: dup
/*     */     //   131: aload_3
/*     */     //   132: sipush #1225
/*     */     //   135: ldc2_w 6051267142301793684
/*     */     //   138: lload #11
/*     */     //   140: lxor
/*     */     //   141: <illegal opcode> z : (IJ)Ljava/lang/String;
/*     */     //   146: invokespecial <init> : (Ljava/io/File;Ljava/lang/String;)V
/*     */     //   149: putfield m : Ljava/io/File;
/*     */     //   152: aload_0
/*     */     //   153: new java/io/File
/*     */     //   156: dup
/*     */     //   157: aload_3
/*     */     //   158: sipush #1433
/*     */     //   161: ldc2_w 8816635117215202498
/*     */     //   164: lload #11
/*     */     //   166: lxor
/*     */     //   167: <illegal opcode> z : (IJ)Ljava/lang/String;
/*     */     //   172: invokespecial <init> : (Ljava/io/File;Ljava/lang/String;)V
/*     */     //   175: putfield q : Ljava/io/File;
/*     */     //   178: aload_0
/*     */     //   179: iload #5
/*     */     //   181: putfield r : I
/*     */     //   184: aload_0
/*     */     //   185: lload #8
/*     */     //   187: putfield w : J
/*     */     //   190: aload_0
/*     */     //   191: aload #10
/*     */     //   193: putfield u : Ljava/util/concurrent/Executor;
/*     */     //   196: ldc2_w 3098223698123320924
/*     */     //   199: lload #11
/*     */     //   201: <illegal opcode> w : (JJ)[Lme/konsolas/aac/aN;
/*     */     //   206: ifnull -> 237
/*     */     //   209: iconst_5
/*     */     //   210: anewarray java/lang/String
/*     */     //   213: ldc2_w 3080395107310442705
/*     */     //   216: lload #11
/*     */     //   218: <illegal opcode> w : ([Ljava/lang/String;JJ)V
/*     */     //   223: goto -> 237
/*     */     //   226: ldc2_w 3041647581775439231
/*     */     //   229: lload #11
/*     */     //   231: <illegal opcode> w : (Ljava/lang/Throwable;JJ)Ljava/lang/Throwable;
/*     */     //   236: athrow
/*     */     //   237: return
/*     */     // Line number table:
/*     */     //   Java source line number -> byte code offset
/*     */     //   #116	-> 41
/*     */     //   #144	-> 45
/*     */     //   #154	-> 52
/*     */     //   #14	-> 67
/*     */     //   #31	-> 72
/*     */     //   #58	-> 84
/*     */     //   #292	-> 89
/*     */     //   #43	-> 94
/*     */     //   #146	-> 100
/*     */     //   #17	-> 126
/*     */     //   #37	-> 152
/*     */     //   #190	-> 178
/*     */     //   #109	-> 184
/*     */     //   #83	-> 190
/*     */     //   #275	-> 196
/*     */     // Exception table:
/*     */     //   from	to	target	type
/*     */     //   52	223	226	java/lang/IllegalArgumentException
/*     */   }
/*     */   private void f(long paramLong) {
/*     */     // Byte code:
/*     */     //   0: getstatic me/konsolas/aac/m5.H : J
/*     */     //   3: lload_1
/*     */     //   4: lxor
/*     */     //   5: lstore_1
/*     */     //   6: lload_1
/*     */     //   7: dup2
/*     */     //   8: ldc2_w 110218345002126
/*     */     //   11: lxor
/*     */     //   12: lstore_3
/*     */     //   13: dup2
/*     */     //   14: ldc2_w 124015853313946
/*     */     //   17: lxor
/*     */     //   18: dup2
/*     */     //   19: bipush #32
/*     */     //   21: lushr
/*     */     //   22: l2i
/*     */     //   23: istore #5
/*     */     //   25: dup2
/*     */     //   26: bipush #32
/*     */     //   28: lshl
/*     */     //   29: bipush #48
/*     */     //   31: lushr
/*     */     //   32: l2i
/*     */     //   33: istore #6
/*     */     //   35: dup2
/*     */     //   36: bipush #48
/*     */     //   38: lshl
/*     */     //   39: bipush #48
/*     */     //   41: lushr
/*     */     //   42: l2i
/*     */     //   43: istore #7
/*     */     //   45: pop2
/*     */     //   46: dup2
/*     */     //   47: ldc2_w 73311459028545
/*     */     //   50: lxor
/*     */     //   51: lstore #8
/*     */     //   53: dup2
/*     */     //   54: ldc2_w 101897187541885
/*     */     //   57: lxor
/*     */     //   58: dup2
/*     */     //   59: bipush #48
/*     */     //   61: lushr
/*     */     //   62: l2i
/*     */     //   63: istore #10
/*     */     //   65: dup2
/*     */     //   66: bipush #16
/*     */     //   68: lshl
/*     */     //   69: bipush #48
/*     */     //   71: lushr
/*     */     //   72: l2i
/*     */     //   73: istore #11
/*     */     //   75: dup2
/*     */     //   76: bipush #32
/*     */     //   78: lshl
/*     */     //   79: bipush #32
/*     */     //   81: lushr
/*     */     //   82: l2i
/*     */     //   83: istore #12
/*     */     //   85: pop2
/*     */     //   86: dup2
/*     */     //   87: ldc2_w 36916724994659
/*     */     //   90: lxor
/*     */     //   91: dup2
/*     */     //   92: bipush #32
/*     */     //   94: lushr
/*     */     //   95: l2i
/*     */     //   96: istore #13
/*     */     //   98: dup2
/*     */     //   99: bipush #32
/*     */     //   101: lshl
/*     */     //   102: bipush #32
/*     */     //   104: lushr
/*     */     //   105: lstore #14
/*     */     //   107: pop2
/*     */     //   108: dup2
/*     */     //   109: ldc2_w 46199384285882
/*     */     //   112: lxor
/*     */     //   113: lstore #16
/*     */     //   115: dup2
/*     */     //   116: ldc2_w 136967079598704
/*     */     //   119: lxor
/*     */     //   120: dup2
/*     */     //   121: bipush #48
/*     */     //   123: lushr
/*     */     //   124: l2i
/*     */     //   125: istore #18
/*     */     //   127: dup2
/*     */     //   128: bipush #16
/*     */     //   130: lshl
/*     */     //   131: bipush #48
/*     */     //   133: lushr
/*     */     //   134: l2i
/*     */     //   135: istore #19
/*     */     //   137: dup2
/*     */     //   138: bipush #32
/*     */     //   140: lshl
/*     */     //   141: bipush #32
/*     */     //   143: lushr
/*     */     //   144: l2i
/*     */     //   145: istore #20
/*     */     //   147: pop2
/*     */     //   148: dup2
/*     */     //   149: ldc2_w 46968225206901
/*     */     //   152: lxor
/*     */     //   153: lstore #21
/*     */     //   155: pop2
/*     */     //   156: ldc2_w 1675630448476796966
/*     */     //   159: lload_1
/*     */     //   160: <illegal opcode> w : (JJ)[Ljava/lang/String;
/*     */     //   165: aload_0
/*     */     //   166: getfield h : Lme/konsolas/aac/j9;
/*     */     //   169: aload_0
/*     */     //   170: getfield A : Ljava/io/File;
/*     */     //   173: iload #13
/*     */     //   175: lload #14
/*     */     //   177: invokeinterface a : (Ljava/io/File;IJ)Lme/konsolas/aac/hp;
/*     */     //   182: iload #18
/*     */     //   184: i2s
/*     */     //   185: swap
/*     */     //   186: iload #19
/*     */     //   188: i2c
/*     */     //   189: iload #20
/*     */     //   191: invokestatic a : (SLme/konsolas/aac/hp;CI)Lme/konsolas/aac/bX;
/*     */     //   194: astore #24
/*     */     //   196: astore #23
/*     */     //   198: aconst_null
/*     */     //   199: astore #25
/*     */     //   201: aload #24
/*     */     //   203: iload #10
/*     */     //   205: i2s
/*     */     //   206: iload #11
/*     */     //   208: i2s
/*     */     //   209: iload #12
/*     */     //   211: invokeinterface b : (SSI)Ljava/lang/String;
/*     */     //   216: astore #26
/*     */     //   218: aload #24
/*     */     //   220: iload #10
/*     */     //   222: i2s
/*     */     //   223: iload #11
/*     */     //   225: i2s
/*     */     //   226: iload #12
/*     */     //   228: invokeinterface b : (SSI)Ljava/lang/String;
/*     */     //   233: astore #27
/*     */     //   235: aload #24
/*     */     //   237: iload #10
/*     */     //   239: i2s
/*     */     //   240: iload #11
/*     */     //   242: i2s
/*     */     //   243: iload #12
/*     */     //   245: invokeinterface b : (SSI)Ljava/lang/String;
/*     */     //   250: astore #28
/*     */     //   252: aload #24
/*     */     //   254: iload #10
/*     */     //   256: i2s
/*     */     //   257: iload #11
/*     */     //   259: i2s
/*     */     //   260: iload #12
/*     */     //   262: invokeinterface b : (SSI)Ljava/lang/String;
/*     */     //   267: astore #29
/*     */     //   269: aload #24
/*     */     //   271: iload #10
/*     */     //   273: i2s
/*     */     //   274: iload #11
/*     */     //   276: i2s
/*     */     //   277: iload #12
/*     */     //   279: invokeinterface b : (SSI)Ljava/lang/String;
/*     */     //   284: astore #30
/*     */     //   286: sipush #12133
/*     */     //   289: ldc2_w 6723539018579094367
/*     */     //   292: lload_1
/*     */     //   293: lxor
/*     */     //   294: <illegal opcode> z : (IJ)Ljava/lang/String;
/*     */     //   299: aload #26
/*     */     //   301: invokevirtual equals : (Ljava/lang/Object;)Z
/*     */     //   304: aload #23
/*     */     //   306: ifnonnull -> 371
/*     */     //   309: ifeq -> 544
/*     */     //   312: goto -> 325
/*     */     //   315: ldc2_w 1687254703697401891
/*     */     //   318: lload_1
/*     */     //   319: <illegal opcode> w : (Ljava/lang/Throwable;JJ)Ljava/lang/Throwable;
/*     */     //   324: athrow
/*     */     //   325: ldc_w 'ႏ剪'
/*     */     //   328: invokevirtual toCharArray : ()[C
/*     */     //   331: dup
/*     */     //   332: dup
/*     */     //   333: iconst_0
/*     */     //   334: dup_x1
/*     */     //   335: caload
/*     */     //   336: sipush #24421
/*     */     //   339: ixor
/*     */     //   340: i2c
/*     */     //   341: castore
/*     */     //   342: sipush #2267
/*     */     //   345: iconst_1
/*     */     //   346: iconst_4
/*     */     //   347: invokestatic A : (Ljava/lang/Object;SZI)Ljava/lang/String;
/*     */     //   350: invokevirtual intern : ()Ljava/lang/String;
/*     */     //   353: aload #27
/*     */     //   355: invokevirtual equals : (Ljava/lang/Object;)Z
/*     */     //   358: goto -> 371
/*     */     //   361: ldc2_w 1687254703697401891
/*     */     //   364: lload_1
/*     */     //   365: <illegal opcode> w : (Ljava/lang/Throwable;JJ)Ljava/lang/Throwable;
/*     */     //   370: athrow
/*     */     //   371: aload #23
/*     */     //   373: lload_1
/*     */     //   374: lconst_0
/*     */     //   375: lcmp
/*     */     //   376: iflt -> 425
/*     */     //   379: ifnonnull -> 423
/*     */     //   382: ifeq -> 544
/*     */     //   385: goto -> 398
/*     */     //   388: ldc2_w 1687254703697401891
/*     */     //   391: lload_1
/*     */     //   392: <illegal opcode> w : (Ljava/lang/Throwable;JJ)Ljava/lang/Throwable;
/*     */     //   397: athrow
/*     */     //   398: aload_0
/*     */     //   399: getfield C : I
/*     */     //   402: invokestatic toString : (I)Ljava/lang/String;
/*     */     //   405: aload #28
/*     */     //   407: invokevirtual equals : (Ljava/lang/Object;)Z
/*     */     //   410: goto -> 423
/*     */     //   413: ldc2_w 1687254703697401891
/*     */     //   416: lload_1
/*     */     //   417: <illegal opcode> w : (Ljava/lang/Throwable;JJ)Ljava/lang/Throwable;
/*     */     //   422: athrow
/*     */     //   423: aload #23
/*     */     //   425: lload_1
/*     */     //   426: lconst_0
/*     */     //   427: lcmp
/*     */     //   428: ifle -> 477
/*     */     //   431: ifnonnull -> 475
/*     */     //   434: ifeq -> 544
/*     */     //   437: goto -> 450
/*     */     //   440: ldc2_w 1687254703697401891
/*     */     //   443: lload_1
/*     */     //   444: <illegal opcode> w : (Ljava/lang/Throwable;JJ)Ljava/lang/Throwable;
/*     */     //   449: athrow
/*     */     //   450: aload_0
/*     */     //   451: getfield r : I
/*     */     //   454: invokestatic toString : (I)Ljava/lang/String;
/*     */     //   457: aload #29
/*     */     //   459: invokevirtual equals : (Ljava/lang/Object;)Z
/*     */     //   462: goto -> 475
/*     */     //   465: ldc2_w 1687254703697401891
/*     */     //   468: lload_1
/*     */     //   469: <illegal opcode> w : (Ljava/lang/Throwable;JJ)Ljava/lang/Throwable;
/*     */     //   474: athrow
/*     */     //   475: aload #23
/*     */     //   477: lload_1
/*     */     //   478: lconst_0
/*     */     //   479: lcmp
/*     */     //   480: iflt -> 525
/*     */     //   483: ifnonnull -> 523
/*     */     //   486: ifeq -> 544
/*     */     //   489: goto -> 502
/*     */     //   492: ldc2_w 1687254703697401891
/*     */     //   495: lload_1
/*     */     //   496: <illegal opcode> w : (Ljava/lang/Throwable;JJ)Ljava/lang/Throwable;
/*     */     //   501: athrow
/*     */     //   502: ldc_w ''
/*     */     //   505: aload #30
/*     */     //   507: invokevirtual equals : (Ljava/lang/Object;)Z
/*     */     //   510: goto -> 523
/*     */     //   513: ldc2_w 1687254703697401891
/*     */     //   516: lload_1
/*     */     //   517: <illegal opcode> w : (Ljava/lang/Throwable;JJ)Ljava/lang/Throwable;
/*     */     //   522: athrow
/*     */     //   523: aload #23
/*     */     //   525: ifnonnull -> 685
/*     */     //   528: ifne -> 684
/*     */     //   531: goto -> 544
/*     */     //   534: ldc2_w 1687254703697401891
/*     */     //   537: lload_1
/*     */     //   538: <illegal opcode> w : (Ljava/lang/Throwable;JJ)Ljava/lang/Throwable;
/*     */     //   543: athrow
/*     */     //   544: new java/io/IOException
/*     */     //   547: dup
/*     */     //   548: new java/lang/StringBuilder
/*     */     //   551: dup
/*     */     //   552: invokespecial <init> : ()V
/*     */     //   555: sipush #19841
/*     */     //   558: ldc2_w 6896137854897932697
/*     */     //   561: lload_1
/*     */     //   562: lxor
/*     */     //   563: <illegal opcode> z : (IJ)Ljava/lang/String;
/*     */     //   568: invokevirtual append : (Ljava/lang/String;)Ljava/lang/StringBuilder;
/*     */     //   571: aload #26
/*     */     //   573: invokevirtual append : (Ljava/lang/String;)Ljava/lang/StringBuilder;
/*     */     //   576: sipush #1181
/*     */     //   579: ldc2_w 3856635107391963288
/*     */     //   582: lload_1
/*     */     //   583: lxor
/*     */     //   584: <illegal opcode> z : (IJ)Ljava/lang/String;
/*     */     //   589: invokevirtual append : (Ljava/lang/String;)Ljava/lang/StringBuilder;
/*     */     //   592: aload #27
/*     */     //   594: invokevirtual append : (Ljava/lang/String;)Ljava/lang/StringBuilder;
/*     */     //   597: sipush #27074
/*     */     //   600: ldc2_w 5562136501870357977
/*     */     //   603: lload_1
/*     */     //   604: lxor
/*     */     //   605: <illegal opcode> z : (IJ)Ljava/lang/String;
/*     */     //   610: invokevirtual append : (Ljava/lang/String;)Ljava/lang/StringBuilder;
/*     */     //   613: aload #29
/*     */     //   615: invokevirtual append : (Ljava/lang/String;)Ljava/lang/StringBuilder;
/*     */     //   618: sipush #27074
/*     */     //   621: ldc2_w 5562136501870357977
/*     */     //   624: lload_1
/*     */     //   625: lxor
/*     */     //   626: <illegal opcode> z : (IJ)Ljava/lang/String;
/*     */     //   631: invokevirtual append : (Ljava/lang/String;)Ljava/lang/StringBuilder;
/*     */     //   634: aload #30
/*     */     //   636: invokevirtual append : (Ljava/lang/String;)Ljava/lang/StringBuilder;
/*     */     //   639: ldc_w '䀟ୢ'
/*     */     //   642: invokevirtual toCharArray : ()[C
/*     */     //   645: dup
/*     */     //   646: dup
/*     */     //   647: iconst_0
/*     */     //   648: dup_x1
/*     */     //   649: caload
/*     */     //   650: sipush #13340
/*     */     //   653: ixor
/*     */     //   654: i2c
/*     */     //   655: castore
/*     */     //   656: sipush #19458
/*     */     //   659: iconst_1
/*     */     //   660: iconst_2
/*     */     //   661: invokestatic A : (Ljava/lang/Object;SZI)Ljava/lang/String;
/*     */     //   664: invokevirtual append : (Ljava/lang/String;)Ljava/lang/StringBuilder;
/*     */     //   667: invokevirtual toString : ()Ljava/lang/String;
/*     */     //   670: invokespecial <init> : (Ljava/lang/String;)V
/*     */     //   673: athrow
/*     */     //   674: ldc2_w 1687254703697401891
/*     */     //   677: lload_1
/*     */     //   678: <illegal opcode> w : (Ljava/lang/Throwable;JJ)Ljava/lang/Throwable;
/*     */     //   683: athrow
/*     */     //   684: iconst_0
/*     */     //   685: istore #31
/*     */     //   687: aload_0
/*     */     //   688: aload #24
/*     */     //   690: iload #10
/*     */     //   692: i2s
/*     */     //   693: iload #11
/*     */     //   695: i2s
/*     */     //   696: iload #12
/*     */     //   698: invokeinterface b : (SSI)Ljava/lang/String;
/*     */     //   703: lload_3
/*     */     //   704: invokespecial a : (Ljava/lang/String;J)V
/*     */     //   707: iinc #31, 1
/*     */     //   710: goto -> 687
/*     */     //   713: astore #32
/*     */     //   715: goto -> 718
/*     */     //   718: lload_1
/*     */     //   719: lconst_0
/*     */     //   720: lcmp
/*     */     //   721: ifle -> 743
/*     */     //   724: aload_0
/*     */     //   725: aload #23
/*     */     //   727: ifnonnull -> 817
/*     */     //   730: iload #31
/*     */     //   732: aload_0
/*     */     //   733: getfield f : Ljava/util/LinkedHashMap;
/*     */     //   736: invokevirtual size : ()I
/*     */     //   739: isub
/*     */     //   740: putfield k : I
/*     */     //   743: aload #24
/*     */     //   745: iload #5
/*     */     //   747: iload #6
/*     */     //   749: i2c
/*     */     //   750: iload #7
/*     */     //   752: invokeinterface a : (ICI)Z
/*     */     //   757: ifne -> 803
/*     */     //   760: goto -> 773
/*     */     //   763: ldc2_w 1687254703697401891
/*     */     //   766: lload_1
/*     */     //   767: <illegal opcode> w : (Ljava/lang/Throwable;JJ)Ljava/lang/Throwable;
/*     */     //   772: athrow
/*     */     //   773: aload_0
/*     */     //   774: lload #16
/*     */     //   776: invokevirtual h : (J)V
/*     */     //   779: lload_1
/*     */     //   780: lconst_0
/*     */     //   781: lcmp
/*     */     //   782: ifle -> 826
/*     */     //   785: aload #23
/*     */     //   787: ifnull -> 826
/*     */     //   790: goto -> 803
/*     */     //   793: ldc2_w 1687254703697401891
/*     */     //   796: lload_1
/*     */     //   797: <illegal opcode> w : (Ljava/lang/Throwable;JJ)Ljava/lang/Throwable;
/*     */     //   802: athrow
/*     */     //   803: aload_0
/*     */     //   804: goto -> 817
/*     */     //   807: ldc2_w 1687254703697401891
/*     */     //   810: lload_1
/*     */     //   811: <illegal opcode> w : (Ljava/lang/Throwable;JJ)Ljava/lang/Throwable;
/*     */     //   816: athrow
/*     */     //   817: aload_0
/*     */     //   818: lload #21
/*     */     //   820: invokespecial a : (J)Lme/konsolas/aac/gi;
/*     */     //   823: putfield D : Lme/konsolas/aac/gi;
/*     */     //   826: lload_1
/*     */     //   827: lconst_0
/*     */     //   828: lcmp
/*     */     //   829: ifle -> 846
/*     */     //   832: aload #24
/*     */     //   834: ifnull -> 906
/*     */     //   837: lload #8
/*     */     //   839: aload #25
/*     */     //   841: aload #24
/*     */     //   843: invokestatic a : (JLjava/lang/Throwable;Ljava/lang/AutoCloseable;)V
/*     */     //   846: goto -> 906
/*     */     //   849: ldc2_w 1687254703697401891
/*     */     //   852: lload_1
/*     */     //   853: <illegal opcode> w : (Ljava/lang/Throwable;JJ)Ljava/lang/Throwable;
/*     */     //   858: athrow
/*     */     //   859: astore #26
/*     */     //   861: aload #26
/*     */     //   863: astore #25
/*     */     //   865: aload #26
/*     */     //   867: athrow
/*     */     //   868: astore #33
/*     */     //   870: lload_1
/*     */     //   871: lconst_0
/*     */     //   872: lcmp
/*     */     //   873: ifle -> 890
/*     */     //   876: aload #24
/*     */     //   878: ifnull -> 903
/*     */     //   881: lload #8
/*     */     //   883: aload #25
/*     */     //   885: aload #24
/*     */     //   887: invokestatic a : (JLjava/lang/Throwable;Ljava/lang/AutoCloseable;)V
/*     */     //   890: goto -> 903
/*     */     //   893: ldc2_w 1687254703697401891
/*     */     //   896: lload_1
/*     */     //   897: <illegal opcode> w : (Ljava/lang/Throwable;JJ)Ljava/lang/Throwable;
/*     */     //   902: athrow
/*     */     //   903: aload #33
/*     */     //   905: athrow
/*     */     //   906: return
/*     */     // Line number table:
/*     */     //   Java source line number -> byte code offset
/*     */     //   #125	-> 165
/*     */     //   #239	-> 201
/*     */     //   #40	-> 218
/*     */     //   #96	-> 235
/*     */     //   #169	-> 252
/*     */     //   #15	-> 269
/*     */     //   #207	-> 286
/*     */     //   #165	-> 355
/*     */     //   #2	-> 402
/*     */     //   #254	-> 454
/*     */     //   #293	-> 507
/*     */     //   #294	-> 544
/*     */     //   #246	-> 684
/*     */     //   #119	-> 687
/*     */     //   #123	-> 707
/*     */     //   #195	-> 710
/*     */     //   #142	-> 713
/*     */     //   #153	-> 715
/*     */     //   #248	-> 718
/*     */     //   #173	-> 743
/*     */     //   #95	-> 773
/*     */     //   #157	-> 803
/*     */     //   #19	-> 826
/*     */     //   #216	-> 859
/*     */     //   #74	-> 868
/*     */     //   #82	-> 906
/*     */     // Exception table:
/*     */     //   from	to	target	type
/*     */     //   201	826	859	java/lang/Throwable
/*     */     //   201	826	868	finally
/*     */     //   286	312	315	java/io/EOFException
/*     */     //   309	358	361	java/io/EOFException
/*     */     //   371	385	388	java/io/EOFException
/*     */     //   382	410	413	java/io/EOFException
/*     */     //   423	437	440	java/io/EOFException
/*     */     //   434	462	465	java/io/EOFException
/*     */     //   475	489	492	java/io/EOFException
/*     */     //   486	510	513	java/io/EOFException
/*     */     //   523	531	534	java/io/EOFException
/*     */     //   528	674	674	java/io/EOFException
/*     */     //   687	710	713	java/io/EOFException
/*     */     //   718	760	763	java/io/EOFException
/*     */     //   730	790	793	java/io/EOFException
/*     */     //   773	804	807	java/io/EOFException
/*     */     //   826	849	849	java/io/EOFException
/*     */     //   859	870	868	finally
/*     */     //   870	890	893	java/io/EOFException
/*     */   }
/*     */   public synchronized Iterator a(long paramLong) {
/*     */     paramLong = H ^ paramLong;
/*     */     long l = paramLong ^ 0x6AA711E0796EL;
/*     */     b(l);
/* 228 */     return new jU(this);
/*     */   }
/*     */   private void b(String paramString, long paramLong) {
/*     */     // Byte code:
/*     */     //   0: getstatic me/konsolas/aac/m5.H : J
/*     */     //   3: lload_2
/*     */     //   4: lxor
/*     */     //   5: lstore_2
/*     */     //   6: getstatic me/konsolas/aac/m5.t : Ljava/util/regex/Pattern;
/*     */     //   9: aload_1
/*     */     //   10: invokevirtual matcher : (Ljava/lang/CharSequence;)Ljava/util/regex/Matcher;
/*     */     //   13: astore #4
/*     */     //   15: aload #4
/*     */     //   17: invokevirtual matches : ()Z
/*     */     //   20: ifne -> 99
/*     */     //   23: new java/lang/IllegalArgumentException
/*     */     //   26: dup
/*     */     //   27: new java/lang/StringBuilder
/*     */     //   30: dup
/*     */     //   31: invokespecial <init> : ()V
/*     */     //   34: sipush #2077
/*     */     //   37: ldc2_w 1611312616479083689
/*     */     //   40: lload_2
/*     */     //   41: lxor
/*     */     //   42: <illegal opcode> z : (IJ)Ljava/lang/String;
/*     */     //   47: invokevirtual append : (Ljava/lang/String;)Ljava/lang/StringBuilder;
/*     */     //   50: aload_1
/*     */     //   51: invokevirtual append : (Ljava/lang/String;)Ljava/lang/StringBuilder;
/*     */     //   54: ldc_w '杜歇'
/*     */     //   57: invokevirtual toCharArray : ()[C
/*     */     //   60: dup
/*     */     //   61: dup
/*     */     //   62: iconst_0
/*     */     //   63: dup_x1
/*     */     //   64: caload
/*     */     //   65: sipush #22809
/*     */     //   68: ixor
/*     */     //   69: i2c
/*     */     //   70: castore
/*     */     //   71: sipush #28393
/*     */     //   74: iconst_0
/*     */     //   75: iconst_0
/*     */     //   76: invokestatic U : (Ljava/lang/Object;SZZ)Ljava/lang/String;
/*     */     //   79: invokevirtual append : (Ljava/lang/String;)Ljava/lang/StringBuilder;
/*     */     //   82: invokevirtual toString : ()Ljava/lang/String;
/*     */     //   85: invokespecial <init> : (Ljava/lang/String;)V
/*     */     //   88: athrow
/*     */     //   89: ldc2_w -2892432435131819883
/*     */     //   92: lload_2
/*     */     //   93: <illegal opcode> w : (Ljava/lang/Throwable;JJ)Ljava/lang/Throwable;
/*     */     //   98: athrow
/*     */     //   99: return
/*     */     // Line number table:
/*     */     //   Java source line number -> byte code offset
/*     */     //   #152	-> 6
/*     */     //   #59	-> 15
/*     */     //   #91	-> 23
/*     */     //   #196	-> 99
/*     */     // Exception table:
/*     */     //   from	to	target	type
/*     */     //   15	89	89	java/lang/IllegalArgumentException
/*     */   }
/*     */   public synchronized void b(long paramLong) {
/*     */     // Byte code:
/*     */     //   0: getstatic me/konsolas/aac/m5.H : J
/*     */     //   3: lload_1
/*     */     //   4: lxor
/*     */     //   5: lstore_1
/*     */     //   6: lload_1
/*     */     //   7: dup2
/*     */     //   8: ldc2_w 51753541659028
/*     */     //   11: lxor
/*     */     //   12: lstore_3
/*     */     //   13: dup2
/*     */     //   14: ldc2_w 10460316345826
/*     */     //   17: lxor
/*     */     //   18: dup2
/*     */     //   19: bipush #32
/*     */     //   21: lushr
/*     */     //   22: l2i
/*     */     //   23: istore #5
/*     */     //   25: dup2
/*     */     //   26: bipush #32
/*     */     //   28: lshl
/*     */     //   29: bipush #48
/*     */     //   31: lushr
/*     */     //   32: l2i
/*     */     //   33: istore #6
/*     */     //   35: dup2
/*     */     //   36: bipush #48
/*     */     //   38: lshl
/*     */     //   39: bipush #48
/*     */     //   41: lushr
/*     */     //   42: l2i
/*     */     //   43: istore #7
/*     */     //   45: pop2
/*     */     //   46: dup2
/*     */     //   47: ldc2_w 106298552304028
/*     */     //   50: lxor
/*     */     //   51: lstore #8
/*     */     //   53: dup2
/*     */     //   54: ldc2_w 28770004130705
/*     */     //   57: lxor
/*     */     //   58: lstore #10
/*     */     //   60: dup2
/*     */     //   61: ldc2_w 56403515022117
/*     */     //   64: lxor
/*     */     //   65: lstore #12
/*     */     //   67: dup2
/*     */     //   68: ldc2_w 20388530392848
/*     */     //   71: lxor
/*     */     //   72: lstore #14
/*     */     //   74: dup2
/*     */     //   75: ldc2_w 64469769652213
/*     */     //   78: lxor
/*     */     //   79: lstore #16
/*     */     //   81: pop2
/*     */     //   82: ldc2_w -5846217351723220551
/*     */     //   85: lload_1
/*     */     //   86: <illegal opcode> w : (JJ)[Ljava/lang/String;
/*     */     //   91: astore #18
/*     */     //   93: getstatic me/konsolas/aac/m5.p : Z
/*     */     //   96: aload #18
/*     */     //   98: ifnonnull -> 183
/*     */     //   101: ifne -> 179
/*     */     //   104: goto -> 117
/*     */     //   107: ldc2_w -5839677235654286916
/*     */     //   110: lload_1
/*     */     //   111: <illegal opcode> w : (Ljava/lang/Throwable;JJ)Ljava/lang/Throwable;
/*     */     //   116: athrow
/*     */     //   117: aload_0
/*     */     //   118: invokestatic holdsLock : (Ljava/lang/Object;)Z
/*     */     //   121: aload #18
/*     */     //   123: lload_1
/*     */     //   124: lconst_0
/*     */     //   125: lcmp
/*     */     //   126: ifle -> 185
/*     */     //   129: ifnonnull -> 183
/*     */     //   132: goto -> 145
/*     */     //   135: ldc2_w -5839677235654286916
/*     */     //   138: lload_1
/*     */     //   139: <illegal opcode> w : (Ljava/lang/Throwable;JJ)Ljava/lang/Throwable;
/*     */     //   144: athrow
/*     */     //   145: ifne -> 179
/*     */     //   148: goto -> 161
/*     */     //   151: ldc2_w -5839677235654286916
/*     */     //   154: lload_1
/*     */     //   155: <illegal opcode> w : (Ljava/lang/Throwable;JJ)Ljava/lang/Throwable;
/*     */     //   160: athrow
/*     */     //   161: new java/lang/AssertionError
/*     */     //   164: dup
/*     */     //   165: invokespecial <init> : ()V
/*     */     //   168: athrow
/*     */     //   169: ldc2_w -5839677235654286916
/*     */     //   172: lload_1
/*     */     //   173: <illegal opcode> w : (Ljava/lang/Throwable;JJ)Ljava/lang/Throwable;
/*     */     //   178: athrow
/*     */     //   179: aload_0
/*     */     //   180: getfield e : Z
/*     */     //   183: aload #18
/*     */     //   185: lload_1
/*     */     //   186: lconst_0
/*     */     //   187: lcmp
/*     */     //   188: iflt -> 232
/*     */     //   191: ifnonnull -> 224
/*     */     //   194: ifeq -> 211
/*     */     //   197: goto -> 210
/*     */     //   200: ldc2_w -5839677235654286916
/*     */     //   203: lload_1
/*     */     //   204: <illegal opcode> w : (Ljava/lang/Throwable;JJ)Ljava/lang/Throwable;
/*     */     //   209: athrow
/*     */     //   210: return
/*     */     //   211: aload_0
/*     */     //   212: getfield h : Lme/konsolas/aac/j9;
/*     */     //   215: aload_0
/*     */     //   216: getfield q : Ljava/io/File;
/*     */     //   219: invokeinterface a : (Ljava/io/File;)Z
/*     */     //   224: lload_1
/*     */     //   225: lconst_0
/*     */     //   226: lcmp
/*     */     //   227: iflt -> 416
/*     */     //   230: aload #18
/*     */     //   232: ifnonnull -> 416
/*     */     //   235: ifeq -> 379
/*     */     //   238: goto -> 251
/*     */     //   241: ldc2_w -5839677235654286916
/*     */     //   244: lload_1
/*     */     //   245: <illegal opcode> w : (Ljava/lang/Throwable;JJ)Ljava/lang/Throwable;
/*     */     //   250: athrow
/*     */     //   251: aload_0
/*     */     //   252: getfield h : Lme/konsolas/aac/j9;
/*     */     //   255: aload_0
/*     */     //   256: getfield A : Ljava/io/File;
/*     */     //   259: aload #18
/*     */     //   261: ifnonnull -> 366
/*     */     //   264: goto -> 277
/*     */     //   267: ldc2_w -5839677235654286916
/*     */     //   270: lload_1
/*     */     //   271: <illegal opcode> w : (Ljava/lang/Throwable;JJ)Ljava/lang/Throwable;
/*     */     //   276: athrow
/*     */     //   277: lload_1
/*     */     //   278: lconst_0
/*     */     //   279: lcmp
/*     */     //   280: ifle -> 353
/*     */     //   283: invokeinterface a : (Ljava/io/File;)Z
/*     */     //   288: ifeq -> 345
/*     */     //   291: goto -> 304
/*     */     //   294: ldc2_w -5839677235654286916
/*     */     //   297: lload_1
/*     */     //   298: <illegal opcode> w : (Ljava/lang/Throwable;JJ)Ljava/lang/Throwable;
/*     */     //   303: athrow
/*     */     //   304: aload_0
/*     */     //   305: getfield h : Lme/konsolas/aac/j9;
/*     */     //   308: aload_0
/*     */     //   309: getfield q : Ljava/io/File;
/*     */     //   312: lload #10
/*     */     //   314: dup2_x1
/*     */     //   315: pop2
/*     */     //   316: invokeinterface b : (JLjava/io/File;)V
/*     */     //   321: lload_1
/*     */     //   322: lconst_0
/*     */     //   323: lcmp
/*     */     //   324: ifle -> 379
/*     */     //   327: aload #18
/*     */     //   329: ifnull -> 379
/*     */     //   332: goto -> 345
/*     */     //   335: ldc2_w -5839677235654286916
/*     */     //   338: lload_1
/*     */     //   339: <illegal opcode> w : (Ljava/lang/Throwable;JJ)Ljava/lang/Throwable;
/*     */     //   344: athrow
/*     */     //   345: aload_0
/*     */     //   346: getfield h : Lme/konsolas/aac/j9;
/*     */     //   349: aload_0
/*     */     //   350: getfield q : Ljava/io/File;
/*     */     //   353: goto -> 366
/*     */     //   356: ldc2_w -5839677235654286916
/*     */     //   359: lload_1
/*     */     //   360: <illegal opcode> w : (Ljava/lang/Throwable;JJ)Ljava/lang/Throwable;
/*     */     //   365: athrow
/*     */     //   366: aload_0
/*     */     //   367: getfield A : Ljava/io/File;
/*     */     //   370: lload #14
/*     */     //   372: dup2_x1
/*     */     //   373: pop2
/*     */     //   374: invokeinterface a : (Ljava/io/File;JLjava/io/File;)V
/*     */     //   379: lload_1
/*     */     //   380: lconst_0
/*     */     //   381: lcmp
/*     */     //   382: ifle -> 575
/*     */     //   385: aload_0
/*     */     //   386: aload #18
/*     */     //   388: ifnonnull -> 571
/*     */     //   391: getfield h : Lme/konsolas/aac/j9;
/*     */     //   394: aload_0
/*     */     //   395: getfield A : Ljava/io/File;
/*     */     //   398: invokeinterface a : (Ljava/io/File;)Z
/*     */     //   403: goto -> 416
/*     */     //   406: ldc2_w -5839677235654286916
/*     */     //   409: lload_1
/*     */     //   410: <illegal opcode> w : (Ljava/lang/Throwable;JJ)Ljava/lang/Throwable;
/*     */     //   415: athrow
/*     */     //   416: ifeq -> 564
/*     */     //   419: aload_0
/*     */     //   420: lload_3
/*     */     //   421: invokespecial f : (J)V
/*     */     //   424: aload_0
/*     */     //   425: lload #16
/*     */     //   427: invokespecial d : (J)V
/*     */     //   430: aload_0
/*     */     //   431: iconst_1
/*     */     //   432: putfield e : Z
/*     */     //   435: return
/*     */     //   436: ldc2_w -5839677235654286916
/*     */     //   439: lload_1
/*     */     //   440: <illegal opcode> w : (Ljava/lang/Throwable;JJ)Ljava/lang/Throwable;
/*     */     //   445: athrow
/*     */     //   446: astore #19
/*     */     //   448: invokestatic c : ()Lme/konsolas/aac/io;
/*     */     //   451: iconst_5
/*     */     //   452: new java/lang/StringBuilder
/*     */     //   455: dup
/*     */     //   456: invokespecial <init> : ()V
/*     */     //   459: sipush #30043
/*     */     //   462: ldc2_w 2044101069546342603
/*     */     //   465: lload_1
/*     */     //   466: lxor
/*     */     //   467: <illegal opcode> z : (IJ)Ljava/lang/String;
/*     */     //   472: invokevirtual append : (Ljava/lang/String;)Ljava/lang/StringBuilder;
/*     */     //   475: aload_0
/*     */     //   476: getfield E : Ljava/io/File;
/*     */     //   479: invokevirtual append : (Ljava/lang/Object;)Ljava/lang/StringBuilder;
/*     */     //   482: sipush #13263
/*     */     //   485: ldc2_w 8104450370012450396
/*     */     //   488: lload_1
/*     */     //   489: lxor
/*     */     //   490: <illegal opcode> z : (IJ)Ljava/lang/String;
/*     */     //   495: invokevirtual append : (Ljava/lang/String;)Ljava/lang/StringBuilder;
/*     */     //   498: aload #19
/*     */     //   500: invokevirtual getMessage : ()Ljava/lang/String;
/*     */     //   503: invokevirtual append : (Ljava/lang/String;)Ljava/lang/StringBuilder;
/*     */     //   506: sipush #20350
/*     */     //   509: ldc2_w 415733563059794665
/*     */     //   512: lload_1
/*     */     //   513: lxor
/*     */     //   514: <illegal opcode> z : (IJ)Ljava/lang/String;
/*     */     //   519: invokevirtual append : (Ljava/lang/String;)Ljava/lang/StringBuilder;
/*     */     //   522: invokevirtual toString : ()Ljava/lang/String;
/*     */     //   525: iload #5
/*     */     //   527: swap
/*     */     //   528: iload #6
/*     */     //   530: i2c
/*     */     //   531: swap
/*     */     //   532: iload #7
/*     */     //   534: i2s
/*     */     //   535: aload #19
/*     */     //   537: invokevirtual a : (IICLjava/lang/String;SLjava/lang/Throwable;)V
/*     */     //   540: aload_0
/*     */     //   541: lload #8
/*     */     //   543: invokevirtual g : (J)V
/*     */     //   546: aload_0
/*     */     //   547: iconst_0
/*     */     //   548: putfield z : Z
/*     */     //   551: goto -> 564
/*     */     //   554: astore #20
/*     */     //   556: aload_0
/*     */     //   557: iconst_0
/*     */     //   558: putfield z : Z
/*     */     //   561: aload #20
/*     */     //   563: athrow
/*     */     //   564: aload_0
/*     */     //   565: lload #12
/*     */     //   567: invokevirtual h : (J)V
/*     */     //   570: aload_0
/*     */     //   571: iconst_1
/*     */     //   572: putfield e : Z
/*     */     //   575: return
/*     */     // Line number table:
/*     */     //   Java source line number -> byte code offset
/*     */     //   #162	-> 93
/*     */     //   #4	-> 179
/*     */     //   #185	-> 210
/*     */     //   #30	-> 211
/*     */     //   #20	-> 251
/*     */     //   #34	-> 304
/*     */     //   #36	-> 345
/*     */     //   #243	-> 379
/*     */     //   #244	-> 419
/*     */     //   #9	-> 424
/*     */     //   #198	-> 430
/*     */     //   #231	-> 435
/*     */     //   #129	-> 446
/*     */     //   #38	-> 448
/*     */     //   #136	-> 500
/*     */     //   #208	-> 537
/*     */     //   #28	-> 540
/*     */     //   #273	-> 546
/*     */     //   #164	-> 551
/*     */     //   #47	-> 554
/*     */     //   #65	-> 564
/*     */     //   #194	-> 570
/*     */     //   #230	-> 575
/*     */     // Exception table:
/*     */     //   from	to	target	type
/*     */     //   93	104	107	java/io/IOException
/*     */     //   101	132	135	java/io/IOException
/*     */     //   117	148	151	java/io/IOException
/*     */     //   145	169	169	java/io/IOException
/*     */     //   183	197	200	java/io/IOException
/*     */     //   224	238	241	java/io/IOException
/*     */     //   235	264	267	java/io/IOException
/*     */     //   251	291	294	java/io/IOException
/*     */     //   277	332	335	java/io/IOException
/*     */     //   304	353	356	java/io/IOException
/*     */     //   379	403	406	java/io/IOException
/*     */     //   416	436	436	java/lang/IllegalArgumentException
/*     */     //   419	435	446	java/io/IOException
/*     */     //   540	546	554	finally
/*     */   }
/*     */   synchronized void h(long paramLong) {
/*     */     // Byte code:
/*     */     //   0: getstatic me/konsolas/aac/m5.H : J
/*     */     //   3: lload_1
/*     */     //   4: lxor
/*     */     //   5: lstore_1
/*     */     //   6: lload_1
/*     */     //   7: dup2
/*     */     //   8: ldc2_w 81503727546233
/*     */     //   11: lxor
/*     */     //   12: lstore_3
/*     */     //   13: dup2
/*     */     //   14: ldc2_w 13963946016190
/*     */     //   17: lxor
/*     */     //   18: lstore #5
/*     */     //   20: dup2
/*     */     //   21: ldc2_w 104387560365296
/*     */     //   24: lxor
/*     */     //   25: lstore #7
/*     */     //   27: dup2
/*     */     //   28: ldc2_w 107847761915225
/*     */     //   31: lxor
/*     */     //   32: lstore #9
/*     */     //   34: dup2
/*     */     //   35: ldc2_w 92351517247056
/*     */     //   38: lxor
/*     */     //   39: lstore #11
/*     */     //   41: dup2
/*     */     //   42: ldc2_w 16127843290085
/*     */     //   45: lxor
/*     */     //   46: dup2
/*     */     //   47: bipush #48
/*     */     //   49: lushr
/*     */     //   50: l2i
/*     */     //   51: istore #13
/*     */     //   53: dup2
/*     */     //   54: bipush #16
/*     */     //   56: lshl
/*     */     //   57: bipush #48
/*     */     //   59: lushr
/*     */     //   60: l2i
/*     */     //   61: istore #14
/*     */     //   63: dup2
/*     */     //   64: bipush #32
/*     */     //   66: lshl
/*     */     //   67: bipush #32
/*     */     //   69: lushr
/*     */     //   70: l2i
/*     */     //   71: istore #15
/*     */     //   73: pop2
/*     */     //   74: dup2
/*     */     //   75: ldc2_w 34359326576831
/*     */     //   78: lxor
/*     */     //   79: lstore #16
/*     */     //   81: dup2
/*     */     //   82: ldc2_w 44122792666142
/*     */     //   85: lxor
/*     */     //   86: dup2
/*     */     //   87: bipush #48
/*     */     //   89: lushr
/*     */     //   90: l2i
/*     */     //   91: istore #18
/*     */     //   93: dup2
/*     */     //   94: bipush #16
/*     */     //   96: lshl
/*     */     //   97: bipush #32
/*     */     //   99: lushr
/*     */     //   100: l2i
/*     */     //   101: istore #19
/*     */     //   103: dup2
/*     */     //   104: bipush #48
/*     */     //   106: lshl
/*     */     //   107: bipush #48
/*     */     //   109: lushr
/*     */     //   110: l2i
/*     */     //   111: istore #20
/*     */     //   113: pop2
/*     */     //   114: dup2
/*     */     //   115: ldc2_w 25969478353982
/*     */     //   118: lxor
/*     */     //   119: lstore #21
/*     */     //   121: dup2
/*     */     //   122: ldc2_w 60379127111876
/*     */     //   125: lxor
/*     */     //   126: lstore #23
/*     */     //   128: pop2
/*     */     //   129: ldc2_w 7345394487327509143
/*     */     //   132: lload_1
/*     */     //   133: <illegal opcode> w : (JJ)[Ljava/lang/String;
/*     */     //   138: astore #25
/*     */     //   140: aload_0
/*     */     //   141: getfield D : Lme/konsolas/aac/gi;
/*     */     //   144: aload #25
/*     */     //   146: ifnonnull -> 208
/*     */     //   149: ifnull -> 187
/*     */     //   152: goto -> 165
/*     */     //   155: ldc2_w 7339540741966850706
/*     */     //   158: lload_1
/*     */     //   159: <illegal opcode> w : (Ljava/lang/Throwable;JJ)Ljava/lang/Throwable;
/*     */     //   164: athrow
/*     */     //   165: aload_0
/*     */     //   166: getfield D : Lme/konsolas/aac/gi;
/*     */     //   169: invokeinterface close : ()V
/*     */     //   174: goto -> 187
/*     */     //   177: ldc2_w 7339540741966850706
/*     */     //   180: lload_1
/*     */     //   181: <illegal opcode> w : (Ljava/lang/Throwable;JJ)Ljava/lang/Throwable;
/*     */     //   186: athrow
/*     */     //   187: aload_0
/*     */     //   188: getfield h : Lme/konsolas/aac/j9;
/*     */     //   191: aload_0
/*     */     //   192: getfield m : Ljava/io/File;
/*     */     //   195: lload_3
/*     */     //   196: dup2_x1
/*     */     //   197: pop2
/*     */     //   198: invokeinterface a : (JLjava/io/File;)Lme/konsolas/aac/gp;
/*     */     //   203: lload #5
/*     */     //   205: invokestatic a : (Lme/konsolas/aac/gp;J)Lme/konsolas/aac/gi;
/*     */     //   208: astore #26
/*     */     //   210: aconst_null
/*     */     //   211: astore #27
/*     */     //   213: aload #26
/*     */     //   215: sipush #21332
/*     */     //   218: ldc2_w 4141487338594575871
/*     */     //   221: lload_1
/*     */     //   222: lxor
/*     */     //   223: <illegal opcode> z : (IJ)Ljava/lang/String;
/*     */     //   228: lload #11
/*     */     //   230: invokeinterface a : (Ljava/lang/String;J)Lme/konsolas/aac/gi;
/*     */     //   235: bipush #10
/*     */     //   237: lload #9
/*     */     //   239: invokeinterface d : (IJ)Lme/konsolas/aac/gi;
/*     */     //   244: pop
/*     */     //   245: aload #26
/*     */     //   247: ldc_w '菚棧'
/*     */     //   250: invokevirtual toCharArray : ()[C
/*     */     //   253: dup
/*     */     //   254: dup
/*     */     //   255: iconst_0
/*     */     //   256: dup_x1
/*     */     //   257: caload
/*     */     //   258: sipush #21232
/*     */     //   261: ixor
/*     */     //   262: i2c
/*     */     //   263: castore
/*     */     //   264: sipush #14995
/*     */     //   267: iconst_0
/*     */     //   268: iconst_2
/*     */     //   269: invokestatic G : (Ljava/lang/Object;SZB)Ljava/lang/String;
/*     */     //   272: invokevirtual intern : ()Ljava/lang/String;
/*     */     //   275: lload #11
/*     */     //   277: invokeinterface a : (Ljava/lang/String;J)Lme/konsolas/aac/gi;
/*     */     //   282: bipush #10
/*     */     //   284: lload #9
/*     */     //   286: invokeinterface d : (IJ)Lme/konsolas/aac/gi;
/*     */     //   291: pop
/*     */     //   292: aload #26
/*     */     //   294: aload_0
/*     */     //   295: getfield C : I
/*     */     //   298: i2l
/*     */     //   299: iload #18
/*     */     //   301: i2s
/*     */     //   302: dup_x2
/*     */     //   303: pop
/*     */     //   304: iload #19
/*     */     //   306: dup_x2
/*     */     //   307: pop
/*     */     //   308: iload #20
/*     */     //   310: i2s
/*     */     //   311: invokeinterface a : (SIJS)Lme/konsolas/aac/gi;
/*     */     //   316: bipush #10
/*     */     //   318: lload #9
/*     */     //   320: invokeinterface d : (IJ)Lme/konsolas/aac/gi;
/*     */     //   325: pop
/*     */     //   326: aload #26
/*     */     //   328: aload_0
/*     */     //   329: getfield r : I
/*     */     //   332: i2l
/*     */     //   333: iload #18
/*     */     //   335: i2s
/*     */     //   336: dup_x2
/*     */     //   337: pop
/*     */     //   338: iload #19
/*     */     //   340: dup_x2
/*     */     //   341: pop
/*     */     //   342: iload #20
/*     */     //   344: i2s
/*     */     //   345: invokeinterface a : (SIJS)Lme/konsolas/aac/gi;
/*     */     //   350: bipush #10
/*     */     //   352: lload #9
/*     */     //   354: invokeinterface d : (IJ)Lme/konsolas/aac/gi;
/*     */     //   359: pop
/*     */     //   360: aload #26
/*     */     //   362: bipush #10
/*     */     //   364: lload #9
/*     */     //   366: invokeinterface d : (IJ)Lme/konsolas/aac/gi;
/*     */     //   371: pop
/*     */     //   372: aload_0
/*     */     //   373: getfield f : Ljava/util/LinkedHashMap;
/*     */     //   376: invokevirtual values : ()Ljava/util/Collection;
/*     */     //   379: invokeinterface iterator : ()Ljava/util/Iterator;
/*     */     //   384: astore #28
/*     */     //   386: aload #28
/*     */     //   388: invokeinterface hasNext : ()Z
/*     */     //   393: ifeq -> 646
/*     */     //   396: aload #28
/*     */     //   398: invokeinterface next : ()Ljava/lang/Object;
/*     */     //   403: checkcast me/konsolas/aac/bT
/*     */     //   406: astore #29
/*     */     //   408: lload_1
/*     */     //   409: lconst_0
/*     */     //   410: lcmp
/*     */     //   411: ifle -> 732
/*     */     //   414: aload #25
/*     */     //   416: ifnonnull -> 732
/*     */     //   419: aload #29
/*     */     //   421: aload #25
/*     */     //   423: ifnonnull -> 616
/*     */     //   426: goto -> 439
/*     */     //   429: ldc2_w 7339540741966850706
/*     */     //   432: lload_1
/*     */     //   433: <illegal opcode> w : (Ljava/lang/Throwable;JJ)Ljava/lang/Throwable;
/*     */     //   438: athrow
/*     */     //   439: getfield f : Lme/konsolas/aac/dO;
/*     */     //   442: ifnull -> 567
/*     */     //   445: goto -> 458
/*     */     //   448: ldc2_w 7339540741966850706
/*     */     //   451: lload_1
/*     */     //   452: <illegal opcode> w : (Ljava/lang/Throwable;JJ)Ljava/lang/Throwable;
/*     */     //   457: athrow
/*     */     //   458: aload #26
/*     */     //   460: sipush #2578
/*     */     //   463: ldc2_w 9175845896006073524
/*     */     //   466: lload_1
/*     */     //   467: lxor
/*     */     //   468: <illegal opcode> z : (IJ)Ljava/lang/String;
/*     */     //   473: lload #11
/*     */     //   475: invokeinterface a : (Ljava/lang/String;J)Lme/konsolas/aac/gi;
/*     */     //   480: bipush #32
/*     */     //   482: lload #9
/*     */     //   484: invokeinterface d : (IJ)Lme/konsolas/aac/gi;
/*     */     //   489: pop
/*     */     //   490: aload #26
/*     */     //   492: aload #29
/*     */     //   494: getfield g : Ljava/lang/String;
/*     */     //   497: lload #11
/*     */     //   499: invokeinterface a : (Ljava/lang/String;J)Lme/konsolas/aac/gi;
/*     */     //   504: pop
/*     */     //   505: aload #26
/*     */     //   507: bipush #10
/*     */     //   509: lload #9
/*     */     //   511: invokeinterface d : (IJ)Lme/konsolas/aac/gi;
/*     */     //   516: pop
/*     */     //   517: aload #25
/*     */     //   519: lload_1
/*     */     //   520: lconst_0
/*     */     //   521: lcmp
/*     */     //   522: iflt -> 643
/*     */     //   525: ifnull -> 641
/*     */     //   528: goto -> 541
/*     */     //   531: ldc2_w 7339540741966850706
/*     */     //   534: lload_1
/*     */     //   535: <illegal opcode> w : (Ljava/lang/Throwable;JJ)Ljava/lang/Throwable;
/*     */     //   540: athrow
/*     */     //   541: iconst_5
/*     */     //   542: anewarray me/konsolas/aac/aN
/*     */     //   545: ldc2_w 7291218663725186298
/*     */     //   548: lload_1
/*     */     //   549: <illegal opcode> w : ([Lme/konsolas/aac/aN;JJ)V
/*     */     //   554: goto -> 567
/*     */     //   557: ldc2_w 7339540741966850706
/*     */     //   560: lload_1
/*     */     //   561: <illegal opcode> w : (Ljava/lang/Throwable;JJ)Ljava/lang/Throwable;
/*     */     //   566: athrow
/*     */     //   567: aload #26
/*     */     //   569: sipush #18933
/*     */     //   572: ldc2_w 84305563008778074
/*     */     //   575: lload_1
/*     */     //   576: lxor
/*     */     //   577: <illegal opcode> z : (IJ)Ljava/lang/String;
/*     */     //   582: lload #11
/*     */     //   584: invokeinterface a : (Ljava/lang/String;J)Lme/konsolas/aac/gi;
/*     */     //   589: bipush #32
/*     */     //   591: lload #9
/*     */     //   593: invokeinterface d : (IJ)Lme/konsolas/aac/gi;
/*     */     //   598: pop
/*     */     //   599: aload #26
/*     */     //   601: aload #29
/*     */     //   603: getfield g : Ljava/lang/String;
/*     */     //   606: lload #11
/*     */     //   608: invokeinterface a : (Ljava/lang/String;J)Lme/konsolas/aac/gi;
/*     */     //   613: pop
/*     */     //   614: aload #29
/*     */     //   616: aload #26
/*     */     //   618: iload #13
/*     */     //   620: i2c
/*     */     //   621: iload #14
/*     */     //   623: i2s
/*     */     //   624: iload #15
/*     */     //   626: invokevirtual a : (Lme/konsolas/aac/gi;CSI)V
/*     */     //   629: aload #26
/*     */     //   631: bipush #10
/*     */     //   633: lload #9
/*     */     //   635: invokeinterface d : (IJ)Lme/konsolas/aac/gi;
/*     */     //   640: pop
/*     */     //   641: aload #25
/*     */     //   643: ifnull -> 386
/*     */     //   646: lload_1
/*     */     //   647: lconst_0
/*     */     //   648: lcmp
/*     */     //   649: iflt -> 672
/*     */     //   652: aload #26
/*     */     //   654: lload_1
/*     */     //   655: lconst_0
/*     */     //   656: lcmp
/*     */     //   657: ifle -> 403
/*     */     //   660: ifnull -> 732
/*     */     //   663: lload #7
/*     */     //   665: aload #27
/*     */     //   667: aload #26
/*     */     //   669: invokestatic a : (JLjava/lang/Throwable;Ljava/lang/AutoCloseable;)V
/*     */     //   672: goto -> 732
/*     */     //   675: ldc2_w 7339540741966850706
/*     */     //   678: lload_1
/*     */     //   679: <illegal opcode> w : (Ljava/lang/Throwable;JJ)Ljava/lang/Throwable;
/*     */     //   684: athrow
/*     */     //   685: astore #28
/*     */     //   687: aload #28
/*     */     //   689: astore #27
/*     */     //   691: aload #28
/*     */     //   693: athrow
/*     */     //   694: astore #30
/*     */     //   696: lload_1
/*     */     //   697: lconst_0
/*     */     //   698: lcmp
/*     */     //   699: ifle -> 716
/*     */     //   702: aload #26
/*     */     //   704: ifnull -> 729
/*     */     //   707: lload #7
/*     */     //   709: aload #27
/*     */     //   711: aload #26
/*     */     //   713: invokestatic a : (JLjava/lang/Throwable;Ljava/lang/AutoCloseable;)V
/*     */     //   716: goto -> 729
/*     */     //   719: ldc2_w 7339540741966850706
/*     */     //   722: lload_1
/*     */     //   723: <illegal opcode> w : (Ljava/lang/Throwable;JJ)Ljava/lang/Throwable;
/*     */     //   728: athrow
/*     */     //   729: aload #30
/*     */     //   731: athrow
/*     */     //   732: aload_0
/*     */     //   733: lload_1
/*     */     //   734: lconst_0
/*     */     //   735: lcmp
/*     */     //   736: iflt -> 860
/*     */     //   739: getfield h : Lme/konsolas/aac/j9;
/*     */     //   742: aload_0
/*     */     //   743: getfield A : Ljava/io/File;
/*     */     //   746: aload #25
/*     */     //   748: ifnonnull -> 835
/*     */     //   751: invokeinterface a : (Ljava/io/File;)Z
/*     */     //   756: ifeq -> 806
/*     */     //   759: goto -> 772
/*     */     //   762: ldc2_w 7339540741966850706
/*     */     //   765: lload_1
/*     */     //   766: <illegal opcode> w : (Ljava/lang/Throwable;JJ)Ljava/lang/Throwable;
/*     */     //   771: athrow
/*     */     //   772: aload_0
/*     */     //   773: getfield h : Lme/konsolas/aac/j9;
/*     */     //   776: aload_0
/*     */     //   777: getfield A : Ljava/io/File;
/*     */     //   780: aload_0
/*     */     //   781: getfield q : Ljava/io/File;
/*     */     //   784: lload #21
/*     */     //   786: dup2_x1
/*     */     //   787: pop2
/*     */     //   788: invokeinterface a : (Ljava/io/File;JLjava/io/File;)V
/*     */     //   793: goto -> 806
/*     */     //   796: ldc2_w 7339540741966850706
/*     */     //   799: lload_1
/*     */     //   800: <illegal opcode> w : (Ljava/lang/Throwable;JJ)Ljava/lang/Throwable;
/*     */     //   805: athrow
/*     */     //   806: aload_0
/*     */     //   807: getfield h : Lme/konsolas/aac/j9;
/*     */     //   810: aload_0
/*     */     //   811: getfield m : Ljava/io/File;
/*     */     //   814: aload_0
/*     */     //   815: getfield A : Ljava/io/File;
/*     */     //   818: lload #21
/*     */     //   820: dup2_x1
/*     */     //   821: pop2
/*     */     //   822: invokeinterface a : (Ljava/io/File;JLjava/io/File;)V
/*     */     //   827: aload_0
/*     */     //   828: getfield h : Lme/konsolas/aac/j9;
/*     */     //   831: aload_0
/*     */     //   832: getfield q : Ljava/io/File;
/*     */     //   835: lload #16
/*     */     //   837: dup2_x1
/*     */     //   838: pop2
/*     */     //   839: invokeinterface b : (JLjava/io/File;)V
/*     */     //   844: aload_0
/*     */     //   845: aload_0
/*     */     //   846: lload #23
/*     */     //   848: invokespecial a : (J)Lme/konsolas/aac/gi;
/*     */     //   851: putfield D : Lme/konsolas/aac/gi;
/*     */     //   854: aload_0
/*     */     //   855: iconst_0
/*     */     //   856: putfield d : Z
/*     */     //   859: aload_0
/*     */     //   860: iconst_0
/*     */     //   861: putfield i : Z
/*     */     //   864: return
/*     */     // Line number table:
/*     */     //   Java source line number -> byte code offset
/*     */     //   #166	-> 140
/*     */     //   #5	-> 165
/*     */     //   #282	-> 187
/*     */     //   #281	-> 213
/*     */     //   #178	-> 245
/*     */     //   #242	-> 292
/*     */     //   #177	-> 326
/*     */     //   #10	-> 360
/*     */     //   #269	-> 372
/*     */     //   #78	-> 408
/*     */     //   #151	-> 458
/*     */     //   #92	-> 490
/*     */     //   #233	-> 505
/*     */     //   #227	-> 567
/*     */     //   #60	-> 599
/*     */     //   #114	-> 614
/*     */     //   #71	-> 629
/*     */     //   #268	-> 641
/*     */     //   #63	-> 646
/*     */     //   #161	-> 685
/*     */     //   #175	-> 694
/*     */     //   #186	-> 732
/*     */     //   #191	-> 772
/*     */     //   #241	-> 806
/*     */     //   #41	-> 827
/*     */     //   #111	-> 844
/*     */     //   #102	-> 854
/*     */     //   #222	-> 859
/*     */     //   #141	-> 864
/*     */     // Exception table:
/*     */     //   from	to	target	type
/*     */     //   140	152	155	java/lang/Throwable
/*     */     //   149	174	177	java/lang/Throwable
/*     */     //   213	646	685	java/lang/Throwable
/*     */     //   213	646	694	finally
/*     */     //   408	426	429	java/lang/Throwable
/*     */     //   419	445	448	java/lang/Throwable
/*     */     //   439	528	531	java/lang/Throwable
/*     */     //   458	554	557	java/lang/Throwable
/*     */     //   646	675	675	java/lang/Throwable
/*     */     //   685	696	694	finally
/*     */     //   696	716	719	java/lang/Throwable
/*     */     //   732	759	762	java/lang/Throwable
/*     */     //   751	793	796	java/lang/Throwable
/*     */   }
/*     */   synchronized void a(dO paramdO, long paramLong, boolean paramBoolean) {
/*     */     // Byte code:
/*     */     //   0: getstatic me/konsolas/aac/m5.H : J
/*     */     //   3: lload_2
/*     */     //   4: lxor
/*     */     //   5: lstore_2
/*     */     //   6: lload_2
/*     */     //   7: dup2
/*     */     //   8: ldc2_w 42104148757257
/*     */     //   11: lxor
/*     */     //   12: dup2
/*     */     //   13: bipush #48
/*     */     //   15: lushr
/*     */     //   16: l2i
/*     */     //   17: istore #5
/*     */     //   19: dup2
/*     */     //   20: bipush #16
/*     */     //   22: lshl
/*     */     //   23: bipush #48
/*     */     //   25: lushr
/*     */     //   26: l2i
/*     */     //   27: istore #6
/*     */     //   29: dup2
/*     */     //   30: bipush #32
/*     */     //   32: lshl
/*     */     //   33: bipush #32
/*     */     //   35: lushr
/*     */     //   36: l2i
/*     */     //   37: istore #7
/*     */     //   39: pop2
/*     */     //   40: dup2
/*     */     //   41: ldc2_w 98552616921761
/*     */     //   44: lxor
/*     */     //   45: lstore #8
/*     */     //   47: dup2
/*     */     //   48: ldc2_w 11870776825588
/*     */     //   51: lxor
/*     */     //   52: lstore #10
/*     */     //   54: dup2
/*     */     //   55: ldc2_w 114667327422888
/*     */     //   58: lxor
/*     */     //   59: lstore #12
/*     */     //   61: dup2
/*     */     //   62: ldc2_w 58408810974237
/*     */     //   65: lxor
/*     */     //   66: dup2
/*     */     //   67: bipush #48
/*     */     //   69: lushr
/*     */     //   70: l2i
/*     */     //   71: istore #14
/*     */     //   73: dup2
/*     */     //   74: bipush #16
/*     */     //   76: lshl
/*     */     //   77: bipush #48
/*     */     //   79: lushr
/*     */     //   80: l2i
/*     */     //   81: istore #15
/*     */     //   83: dup2
/*     */     //   84: bipush #32
/*     */     //   86: lshl
/*     */     //   87: bipush #32
/*     */     //   89: lushr
/*     */     //   90: l2i
/*     */     //   91: istore #16
/*     */     //   93: pop2
/*     */     //   94: dup2
/*     */     //   95: ldc2_w 40182460208967
/*     */     //   98: lxor
/*     */     //   99: lstore #17
/*     */     //   101: dup2
/*     */     //   102: ldc2_w 48559700870086
/*     */     //   105: lxor
/*     */     //   106: lstore #19
/*     */     //   108: pop2
/*     */     //   109: ldc2_w -6771110456347849361
/*     */     //   112: lload_2
/*     */     //   113: <illegal opcode> w : (JJ)[Ljava/lang/String;
/*     */     //   118: aload_1
/*     */     //   119: getfield c : Lme/konsolas/aac/bT;
/*     */     //   122: astore #22
/*     */     //   124: astore #21
/*     */     //   126: aload #22
/*     */     //   128: getfield f : Lme/konsolas/aac/dO;
/*     */     //   131: aload_1
/*     */     //   132: if_acmpeq -> 153
/*     */     //   135: new java/lang/IllegalStateException
/*     */     //   138: dup
/*     */     //   139: invokespecial <init> : ()V
/*     */     //   142: athrow
/*     */     //   143: ldc2_w -6763435912182354582
/*     */     //   146: lload_2
/*     */     //   147: <illegal opcode> w : (Ljava/lang/Throwable;JJ)Ljava/lang/Throwable;
/*     */     //   152: athrow
/*     */     //   153: iload #4
/*     */     //   155: aload #21
/*     */     //   157: ifnonnull -> 392
/*     */     //   160: ifeq -> 391
/*     */     //   163: goto -> 176
/*     */     //   166: ldc2_w -6763435912182354582
/*     */     //   169: lload_2
/*     */     //   170: <illegal opcode> w : (Ljava/lang/Throwable;JJ)Ljava/lang/Throwable;
/*     */     //   175: athrow
/*     */     //   176: aload #22
/*     */     //   178: getfield d : Z
/*     */     //   181: aload #21
/*     */     //   183: ifnonnull -> 392
/*     */     //   186: goto -> 199
/*     */     //   189: ldc2_w -6763435912182354582
/*     */     //   192: lload_2
/*     */     //   193: <illegal opcode> w : (Ljava/lang/Throwable;JJ)Ljava/lang/Throwable;
/*     */     //   198: athrow
/*     */     //   199: ifne -> 391
/*     */     //   202: goto -> 215
/*     */     //   205: ldc2_w -6763435912182354582
/*     */     //   208: lload_2
/*     */     //   209: <illegal opcode> w : (Ljava/lang/Throwable;JJ)Ljava/lang/Throwable;
/*     */     //   214: athrow
/*     */     //   215: iconst_0
/*     */     //   216: istore #23
/*     */     //   218: iload #23
/*     */     //   220: aload_0
/*     */     //   221: getfield r : I
/*     */     //   224: if_icmpge -> 391
/*     */     //   227: aload_1
/*     */     //   228: getfield b : [Z
/*     */     //   231: iload #23
/*     */     //   233: baload
/*     */     //   234: aload #21
/*     */     //   236: lload_2
/*     */     //   237: lconst_0
/*     */     //   238: lcmp
/*     */     //   239: ifle -> 247
/*     */     //   242: ifnonnull -> 392
/*     */     //   245: aload #21
/*     */     //   247: ifnonnull -> 357
/*     */     //   250: goto -> 263
/*     */     //   253: ldc2_w -6763435912182354582
/*     */     //   256: lload_2
/*     */     //   257: <illegal opcode> w : (Ljava/lang/Throwable;JJ)Ljava/lang/Throwable;
/*     */     //   262: athrow
/*     */     //   263: ifne -> 340
/*     */     //   266: goto -> 279
/*     */     //   269: ldc2_w -6763435912182354582
/*     */     //   272: lload_2
/*     */     //   273: <illegal opcode> w : (Ljava/lang/Throwable;JJ)Ljava/lang/Throwable;
/*     */     //   278: athrow
/*     */     //   279: aload_1
/*     */     //   280: iload #5
/*     */     //   282: i2c
/*     */     //   283: iload #6
/*     */     //   285: i2c
/*     */     //   286: iload #7
/*     */     //   288: invokevirtual d : (CCI)V
/*     */     //   291: new java/lang/IllegalStateException
/*     */     //   294: dup
/*     */     //   295: new java/lang/StringBuilder
/*     */     //   298: dup
/*     */     //   299: invokespecial <init> : ()V
/*     */     //   302: sipush #18465
/*     */     //   305: ldc2_w 7664135291141257574
/*     */     //   308: lload_2
/*     */     //   309: lxor
/*     */     //   310: <illegal opcode> z : (IJ)Ljava/lang/String;
/*     */     //   315: invokevirtual append : (Ljava/lang/String;)Ljava/lang/StringBuilder;
/*     */     //   318: iload #23
/*     */     //   320: invokevirtual append : (I)Ljava/lang/StringBuilder;
/*     */     //   323: invokevirtual toString : ()Ljava/lang/String;
/*     */     //   326: invokespecial <init> : (Ljava/lang/String;)V
/*     */     //   329: athrow
/*     */     //   330: ldc2_w -6763435912182354582
/*     */     //   333: lload_2
/*     */     //   334: <illegal opcode> w : (Ljava/lang/Throwable;JJ)Ljava/lang/Throwable;
/*     */     //   339: athrow
/*     */     //   340: aload_0
/*     */     //   341: getfield h : Lme/konsolas/aac/j9;
/*     */     //   344: aload #22
/*     */     //   346: getfield h : [Ljava/io/File;
/*     */     //   349: iload #23
/*     */     //   351: aaload
/*     */     //   352: invokeinterface a : (Ljava/io/File;)Z
/*     */     //   357: ifne -> 383
/*     */     //   360: aload_1
/*     */     //   361: iload #5
/*     */     //   363: i2c
/*     */     //   364: iload #6
/*     */     //   366: i2c
/*     */     //   367: iload #7
/*     */     //   369: invokevirtual d : (CCI)V
/*     */     //   372: return
/*     */     //   373: ldc2_w -6763435912182354582
/*     */     //   376: lload_2
/*     */     //   377: <illegal opcode> w : (Ljava/lang/Throwable;JJ)Ljava/lang/Throwable;
/*     */     //   382: athrow
/*     */     //   383: iinc #23, 1
/*     */     //   386: aload #21
/*     */     //   388: ifnull -> 218
/*     */     //   391: iconst_0
/*     */     //   392: istore #23
/*     */     //   394: iload #23
/*     */     //   396: aload_0
/*     */     //   397: getfield r : I
/*     */     //   400: if_icmpge -> 604
/*     */     //   403: aload #22
/*     */     //   405: getfield h : [Ljava/io/File;
/*     */     //   408: iload #23
/*     */     //   410: aaload
/*     */     //   411: astore #24
/*     */     //   413: iload #4
/*     */     //   415: lload_2
/*     */     //   416: lconst_0
/*     */     //   417: lcmp
/*     */     //   418: iflt -> 658
/*     */     //   421: aload #21
/*     */     //   423: ifnonnull -> 658
/*     */     //   426: aload #21
/*     */     //   428: ifnonnull -> 484
/*     */     //   431: goto -> 444
/*     */     //   434: ldc2_w -6763435912182354582
/*     */     //   437: lload_2
/*     */     //   438: <illegal opcode> w : (Ljava/lang/Throwable;JJ)Ljava/lang/Throwable;
/*     */     //   443: athrow
/*     */     //   444: ifeq -> 570
/*     */     //   447: goto -> 460
/*     */     //   450: ldc2_w -6763435912182354582
/*     */     //   453: lload_2
/*     */     //   454: <illegal opcode> w : (Ljava/lang/Throwable;JJ)Ljava/lang/Throwable;
/*     */     //   459: athrow
/*     */     //   460: aload_0
/*     */     //   461: getfield h : Lme/konsolas/aac/j9;
/*     */     //   464: aload #24
/*     */     //   466: invokeinterface a : (Ljava/io/File;)Z
/*     */     //   471: goto -> 484
/*     */     //   474: ldc2_w -6763435912182354582
/*     */     //   477: lload_2
/*     */     //   478: <illegal opcode> w : (Ljava/lang/Throwable;JJ)Ljava/lang/Throwable;
/*     */     //   483: athrow
/*     */     //   484: ifeq -> 596
/*     */     //   487: aload #22
/*     */     //   489: getfield b : [Ljava/io/File;
/*     */     //   492: iload #23
/*     */     //   494: aaload
/*     */     //   495: astore #25
/*     */     //   497: aload_0
/*     */     //   498: getfield h : Lme/konsolas/aac/j9;
/*     */     //   501: aload #24
/*     */     //   503: lload #19
/*     */     //   505: aload #25
/*     */     //   507: invokeinterface a : (Ljava/io/File;JLjava/io/File;)V
/*     */     //   512: aload #22
/*     */     //   514: getfield e : [J
/*     */     //   517: iload #23
/*     */     //   519: laload
/*     */     //   520: lstore #26
/*     */     //   522: aload_0
/*     */     //   523: getfield h : Lme/konsolas/aac/j9;
/*     */     //   526: aload #25
/*     */     //   528: invokeinterface a : (Ljava/io/File;)J
/*     */     //   533: lstore #28
/*     */     //   535: aload #22
/*     */     //   537: getfield e : [J
/*     */     //   540: iload #23
/*     */     //   542: lload #28
/*     */     //   544: lastore
/*     */     //   545: aload_0
/*     */     //   546: aload_0
/*     */     //   547: getfield G : J
/*     */     //   550: lload #26
/*     */     //   552: lsub
/*     */     //   553: lload #28
/*     */     //   555: ladd
/*     */     //   556: putfield G : J
/*     */     //   559: aload #21
/*     */     //   561: lload_2
/*     */     //   562: lconst_0
/*     */     //   563: lcmp
/*     */     //   564: iflt -> 601
/*     */     //   567: ifnull -> 596
/*     */     //   570: aload_0
/*     */     //   571: getfield h : Lme/konsolas/aac/j9;
/*     */     //   574: lload #17
/*     */     //   576: aload #24
/*     */     //   578: invokeinterface b : (JLjava/io/File;)V
/*     */     //   583: goto -> 596
/*     */     //   586: ldc2_w -6763435912182354582
/*     */     //   589: lload_2
/*     */     //   590: <illegal opcode> w : (Ljava/lang/Throwable;JJ)Ljava/lang/Throwable;
/*     */     //   595: athrow
/*     */     //   596: iinc #23, 1
/*     */     //   599: aload #21
/*     */     //   601: ifnull -> 394
/*     */     //   604: aload_0
/*     */     //   605: dup
/*     */     //   606: getfield k : I
/*     */     //   609: iconst_1
/*     */     //   610: iadd
/*     */     //   611: putfield k : I
/*     */     //   614: aload #22
/*     */     //   616: aconst_null
/*     */     //   617: putfield f : Lme/konsolas/aac/dO;
/*     */     //   620: lload_2
/*     */     //   621: lconst_0
/*     */     //   622: lcmp
/*     */     //   623: ifle -> 914
/*     */     //   626: aload #22
/*     */     //   628: lload_2
/*     */     //   629: lconst_0
/*     */     //   630: lcmp
/*     */     //   631: iflt -> 405
/*     */     //   634: aload #21
/*     */     //   636: ifnonnull -> 862
/*     */     //   639: getfield d : Z
/*     */     //   642: iload #4
/*     */     //   644: ior
/*     */     //   645: goto -> 658
/*     */     //   648: ldc2_w -6763435912182354582
/*     */     //   651: lload_2
/*     */     //   652: <illegal opcode> w : (Ljava/lang/Throwable;JJ)Ljava/lang/Throwable;
/*     */     //   657: athrow
/*     */     //   658: lload_2
/*     */     //   659: lconst_0
/*     */     //   660: lcmp
/*     */     //   661: ifle -> 757
/*     */     //   664: ifeq -> 837
/*     */     //   667: aload #22
/*     */     //   669: iconst_1
/*     */     //   670: putfield d : Z
/*     */     //   673: aload_0
/*     */     //   674: getfield D : Lme/konsolas/aac/gi;
/*     */     //   677: sipush #1508
/*     */     //   680: ldc2_w 4363237425969411236
/*     */     //   683: lload_2
/*     */     //   684: lxor
/*     */     //   685: <illegal opcode> z : (IJ)Ljava/lang/String;
/*     */     //   690: lload #12
/*     */     //   692: invokeinterface a : (Ljava/lang/String;J)Lme/konsolas/aac/gi;
/*     */     //   697: bipush #32
/*     */     //   699: lload #8
/*     */     //   701: invokeinterface d : (IJ)Lme/konsolas/aac/gi;
/*     */     //   706: pop
/*     */     //   707: aload_0
/*     */     //   708: getfield D : Lme/konsolas/aac/gi;
/*     */     //   711: aload #22
/*     */     //   713: getfield g : Ljava/lang/String;
/*     */     //   716: lload #12
/*     */     //   718: invokeinterface a : (Ljava/lang/String;J)Lme/konsolas/aac/gi;
/*     */     //   723: pop
/*     */     //   724: aload #22
/*     */     //   726: aload_0
/*     */     //   727: getfield D : Lme/konsolas/aac/gi;
/*     */     //   730: iload #14
/*     */     //   732: i2c
/*     */     //   733: iload #15
/*     */     //   735: i2s
/*     */     //   736: iload #16
/*     */     //   738: invokevirtual a : (Lme/konsolas/aac/gi;CSI)V
/*     */     //   741: aload_0
/*     */     //   742: getfield D : Lme/konsolas/aac/gi;
/*     */     //   745: bipush #10
/*     */     //   747: lload #8
/*     */     //   749: invokeinterface d : (IJ)Lme/konsolas/aac/gi;
/*     */     //   754: pop
/*     */     //   755: iload #4
/*     */     //   757: lload_2
/*     */     //   758: lconst_0
/*     */     //   759: lcmp
/*     */     //   760: ifle -> 964
/*     */     //   763: aload #21
/*     */     //   765: ifnonnull -> 964
/*     */     //   768: goto -> 781
/*     */     //   771: ldc2_w -6763435912182354582
/*     */     //   774: lload_2
/*     */     //   775: <illegal opcode> w : (Ljava/lang/Throwable;JJ)Ljava/lang/Throwable;
/*     */     //   780: athrow
/*     */     //   781: ifeq -> 928
/*     */     //   784: goto -> 797
/*     */     //   787: ldc2_w -6763435912182354582
/*     */     //   790: lload_2
/*     */     //   791: <illegal opcode> w : (Ljava/lang/Throwable;JJ)Ljava/lang/Throwable;
/*     */     //   796: athrow
/*     */     //   797: aload #22
/*     */     //   799: aload_0
/*     */     //   800: dup
/*     */     //   801: getfield s : J
/*     */     //   804: dup2_x1
/*     */     //   805: lconst_1
/*     */     //   806: ladd
/*     */     //   807: putfield s : J
/*     */     //   810: putfield c : J
/*     */     //   813: lload_2
/*     */     //   814: lconst_0
/*     */     //   815: lcmp
/*     */     //   816: ifle -> 937
/*     */     //   819: aload #21
/*     */     //   821: ifnull -> 928
/*     */     //   824: goto -> 837
/*     */     //   827: ldc2_w -6763435912182354582
/*     */     //   830: lload_2
/*     */     //   831: <illegal opcode> w : (Ljava/lang/Throwable;JJ)Ljava/lang/Throwable;
/*     */     //   836: athrow
/*     */     //   837: aload_0
/*     */     //   838: getfield f : Ljava/util/LinkedHashMap;
/*     */     //   841: aload #22
/*     */     //   843: getfield g : Ljava/lang/String;
/*     */     //   846: invokevirtual remove : (Ljava/lang/Object;)Ljava/lang/Object;
/*     */     //   849: goto -> 862
/*     */     //   852: ldc2_w -6763435912182354582
/*     */     //   855: lload_2
/*     */     //   856: <illegal opcode> w : (Ljava/lang/Throwable;JJ)Ljava/lang/Throwable;
/*     */     //   861: athrow
/*     */     //   862: pop
/*     */     //   863: aload_0
/*     */     //   864: getfield D : Lme/konsolas/aac/gi;
/*     */     //   867: sipush #1046
/*     */     //   870: ldc2_w 2781977398185014610
/*     */     //   873: lload_2
/*     */     //   874: lxor
/*     */     //   875: <illegal opcode> z : (IJ)Ljava/lang/String;
/*     */     //   880: lload #12
/*     */     //   882: invokeinterface a : (Ljava/lang/String;J)Lme/konsolas/aac/gi;
/*     */     //   887: bipush #32
/*     */     //   889: lload #8
/*     */     //   891: invokeinterface d : (IJ)Lme/konsolas/aac/gi;
/*     */     //   896: pop
/*     */     //   897: aload_0
/*     */     //   898: getfield D : Lme/konsolas/aac/gi;
/*     */     //   901: aload #22
/*     */     //   903: getfield g : Ljava/lang/String;
/*     */     //   906: lload #12
/*     */     //   908: invokeinterface a : (Ljava/lang/String;J)Lme/konsolas/aac/gi;
/*     */     //   913: pop
/*     */     //   914: aload_0
/*     */     //   915: getfield D : Lme/konsolas/aac/gi;
/*     */     //   918: bipush #10
/*     */     //   920: lload #8
/*     */     //   922: invokeinterface d : (IJ)Lme/konsolas/aac/gi;
/*     */     //   927: pop
/*     */     //   928: aload_0
/*     */     //   929: getfield D : Lme/konsolas/aac/gi;
/*     */     //   932: invokeinterface flush : ()V
/*     */     //   937: aload_0
/*     */     //   938: aload #21
/*     */     //   940: ifnonnull -> 1021
/*     */     //   943: getfield G : J
/*     */     //   946: aload_0
/*     */     //   947: getfield w : J
/*     */     //   950: lcmp
/*     */     //   951: goto -> 964
/*     */     //   954: ldc2_w -6763435912182354582
/*     */     //   957: lload_2
/*     */     //   958: <illegal opcode> w : (Ljava/lang/Throwable;JJ)Ljava/lang/Throwable;
/*     */     //   963: athrow
/*     */     //   964: ifgt -> 1007
/*     */     //   967: aload_0
/*     */     //   968: aload #21
/*     */     //   970: ifnonnull -> 1021
/*     */     //   973: goto -> 986
/*     */     //   976: ldc2_w -6763435912182354582
/*     */     //   979: lload_2
/*     */     //   980: <illegal opcode> w : (Ljava/lang/Throwable;JJ)Ljava/lang/Throwable;
/*     */     //   985: athrow
/*     */     //   986: lload #10
/*     */     //   988: invokevirtual b : (J)Z
/*     */     //   991: ifeq -> 1033
/*     */     //   994: goto -> 1007
/*     */     //   997: ldc2_w -6763435912182354582
/*     */     //   1000: lload_2
/*     */     //   1001: <illegal opcode> w : (Ljava/lang/Throwable;JJ)Ljava/lang/Throwable;
/*     */     //   1006: athrow
/*     */     //   1007: aload_0
/*     */     //   1008: goto -> 1021
/*     */     //   1011: ldc2_w -6763435912182354582
/*     */     //   1014: lload_2
/*     */     //   1015: <illegal opcode> w : (Ljava/lang/Throwable;JJ)Ljava/lang/Throwable;
/*     */     //   1020: athrow
/*     */     //   1021: getfield u : Ljava/util/concurrent/Executor;
/*     */     //   1024: aload_0
/*     */     //   1025: getfield l : Ljava/lang/Runnable;
/*     */     //   1028: invokeinterface execute : (Ljava/lang/Runnable;)V
/*     */     //   1033: return
/*     */     // Line number table:
/*     */     //   Java source line number -> byte code offset
/*     */     //   #183	-> 118
/*     */     //   #271	-> 126
/*     */     //   #55	-> 135
/*     */     //   #192	-> 153
/*     */     //   #199	-> 215
/*     */     //   #103	-> 227
/*     */     //   #253	-> 279
/*     */     //   #259	-> 291
/*     */     //   #296	-> 340
/*     */     //   #93	-> 360
/*     */     //   #235	-> 372
/*     */     //   #53	-> 383
/*     */     //   #88	-> 391
/*     */     //   #39	-> 403
/*     */     //   #134	-> 413
/*     */     //   #139	-> 460
/*     */     //   #262	-> 487
/*     */     //   #189	-> 497
/*     */     //   #240	-> 512
/*     */     //   #26	-> 522
/*     */     //   #6	-> 535
/*     */     //   #148	-> 545
/*     */     //   #182	-> 559
/*     */     //   #197	-> 570
/*     */     //   #258	-> 596
/*     */     //   #255	-> 604
/*     */     //   #155	-> 614
/*     */     //   #131	-> 620
/*     */     //   #220	-> 667
/*     */     //   #61	-> 673
/*     */     //   #206	-> 707
/*     */     //   #160	-> 724
/*     */     //   #72	-> 741
/*     */     //   #226	-> 755
/*     */     //   #287	-> 797
/*     */     //   #232	-> 837
/*     */     //   #234	-> 863
/*     */     //   #260	-> 897
/*     */     //   #64	-> 914
/*     */     //   #200	-> 928
/*     */     //   #245	-> 937
/*     */     //   #127	-> 1007
/*     */     //   #215	-> 1033
/*     */     // Exception table:
/*     */     //   from	to	target	type
/*     */     //   126	143	143	java/io/IOException
/*     */     //   153	163	166	java/io/IOException
/*     */     //   160	186	189	java/io/IOException
/*     */     //   176	202	205	java/io/IOException
/*     */     //   227	250	253	java/io/IOException
/*     */     //   245	266	269	java/io/IOException
/*     */     //   263	330	330	java/io/IOException
/*     */     //   357	373	373	java/io/IOException
/*     */     //   413	431	434	java/io/IOException
/*     */     //   426	447	450	java/io/IOException
/*     */     //   444	471	474	java/io/IOException
/*     */     //   535	583	586	java/io/IOException
/*     */     //   604	645	648	java/io/IOException
/*     */     //   658	768	771	java/io/IOException
/*     */     //   667	784	787	java/io/IOException
/*     */     //   781	824	827	java/io/IOException
/*     */     //   797	849	852	java/io/IOException
/*     */     //   928	951	954	java/io/IOException
/*     */     //   964	973	976	java/io/IOException
/*     */     //   967	994	997	java/io/IOException
/*     */     //   986	1008	1011	java/io/IOException
/*     */   }
/*     */   boolean b(long paramLong) {
/*     */     // Byte code:
/*     */     //   0: getstatic me/konsolas/aac/m5.H : J
/*     */     //   3: lload_1
/*     */     //   4: lxor
/*     */     //   5: lstore_1
/*     */     //   6: ldc2_w -1948068003804001392
/*     */     //   9: lload_1
/*     */     //   10: <illegal opcode> w : (JJ)[Ljava/lang/String;
/*     */     //   15: sipush #2000
/*     */     //   18: istore #4
/*     */     //   20: astore_3
/*     */     //   21: aload_0
/*     */     //   22: getfield k : I
/*     */     //   25: sipush #2000
/*     */     //   28: aload_3
/*     */     //   29: ifnonnull -> 89
/*     */     //   32: if_icmplt -> 96
/*     */     //   35: goto -> 48
/*     */     //   38: ldc2_w -1955602042449728619
/*     */     //   41: lload_1
/*     */     //   42: <illegal opcode> w : (Ljava/lang/Throwable;JJ)Ljava/lang/Throwable;
/*     */     //   47: athrow
/*     */     //   48: aload_0
/*     */     //   49: getfield k : I
/*     */     //   52: aload_3
/*     */     //   53: ifnonnull -> 93
/*     */     //   56: goto -> 69
/*     */     //   59: ldc2_w -1955602042449728619
/*     */     //   62: lload_1
/*     */     //   63: <illegal opcode> w : (Ljava/lang/Throwable;JJ)Ljava/lang/Throwable;
/*     */     //   68: athrow
/*     */     //   69: aload_0
/*     */     //   70: getfield f : Ljava/util/LinkedHashMap;
/*     */     //   73: invokevirtual size : ()I
/*     */     //   76: goto -> 89
/*     */     //   79: ldc2_w -1955602042449728619
/*     */     //   82: lload_1
/*     */     //   83: <illegal opcode> w : (Ljava/lang/Throwable;JJ)Ljava/lang/Throwable;
/*     */     //   88: athrow
/*     */     //   89: if_icmplt -> 96
/*     */     //   92: iconst_1
/*     */     //   93: goto -> 97
/*     */     //   96: iconst_0
/*     */     //   97: ireturn
/*     */     // Line number table:
/*     */     //   Java source line number -> byte code offset
/*     */     //   #221	-> 15
/*     */     //   #66	-> 21
/*     */     //   #18	-> 73
/*     */     //   #167	-> 97
/*     */     // Exception table:
/*     */     //   from	to	target	type
/*     */     //   21	35	38	java/lang/IllegalArgumentException
/*     */     //   32	56	59	java/lang/IllegalArgumentException
/*     */     //   48	76	79	java/lang/IllegalArgumentException
/*     */   }
/*     */   private void d(long paramLong) {
/*     */     // Byte code:
/*     */     //   0: getstatic me/konsolas/aac/m5.H : J
/*     */     //   3: lload_1
/*     */     //   4: lxor
/*     */     //   5: lstore_1
/*     */     //   6: lload_1
/*     */     //   7: dup2
/*     */     //   8: ldc2_w 25087335369839
/*     */     //   11: lxor
/*     */     //   12: lstore_3
/*     */     //   13: pop2
/*     */     //   14: aload_0
/*     */     //   15: getfield h : Lme/konsolas/aac/j9;
/*     */     //   18: aload_0
/*     */     //   19: getfield m : Ljava/io/File;
/*     */     //   22: lload_3
/*     */     //   23: dup2_x1
/*     */     //   24: pop2
/*     */     //   25: invokeinterface b : (JLjava/io/File;)V
/*     */     //   30: ldc2_w 8728007622743479879
/*     */     //   33: lload_1
/*     */     //   34: <illegal opcode> w : (JJ)[Ljava/lang/String;
/*     */     //   39: aload_0
/*     */     //   40: getfield f : Ljava/util/LinkedHashMap;
/*     */     //   43: invokevirtual values : ()Ljava/util/Collection;
/*     */     //   46: invokeinterface iterator : ()Ljava/util/Iterator;
/*     */     //   51: astore #6
/*     */     //   53: astore #5
/*     */     //   55: aload #6
/*     */     //   57: invokeinterface hasNext : ()Z
/*     */     //   62: ifeq -> 302
/*     */     //   65: aload #6
/*     */     //   67: invokeinterface next : ()Ljava/lang/Object;
/*     */     //   72: checkcast me/konsolas/aac/bT
/*     */     //   75: astore #7
/*     */     //   77: lload_1
/*     */     //   78: lconst_0
/*     */     //   79: lcmp
/*     */     //   80: ifle -> 200
/*     */     //   83: aload #7
/*     */     //   85: aload #5
/*     */     //   87: ifnonnull -> 196
/*     */     //   90: getfield f : Lme/konsolas/aac/dO;
/*     */     //   93: ifnonnull -> 181
/*     */     //   96: goto -> 109
/*     */     //   99: ldc2_w 8722136047295854146
/*     */     //   102: lload_1
/*     */     //   103: <illegal opcode> w : (Ljava/lang/Throwable;JJ)Ljava/lang/Throwable;
/*     */     //   108: athrow
/*     */     //   109: iconst_0
/*     */     //   110: istore #8
/*     */     //   112: iload #8
/*     */     //   114: aload_0
/*     */     //   115: getfield r : I
/*     */     //   118: if_icmpge -> 176
/*     */     //   121: aload_0
/*     */     //   122: dup
/*     */     //   123: getfield G : J
/*     */     //   126: aload #7
/*     */     //   128: getfield e : [J
/*     */     //   131: iload #8
/*     */     //   133: laload
/*     */     //   134: ladd
/*     */     //   135: putfield G : J
/*     */     //   138: iinc #8, 1
/*     */     //   141: aload #5
/*     */     //   143: lload_1
/*     */     //   144: lconst_0
/*     */     //   145: lcmp
/*     */     //   146: iflt -> 154
/*     */     //   149: ifnonnull -> 297
/*     */     //   152: aload #5
/*     */     //   154: ifnull -> 112
/*     */     //   157: lload_1
/*     */     //   158: lconst_0
/*     */     //   159: lcmp
/*     */     //   160: iflt -> 141
/*     */     //   163: goto -> 176
/*     */     //   166: ldc2_w 8722136047295854146
/*     */     //   169: lload_1
/*     */     //   170: <illegal opcode> w : (Ljava/lang/Throwable;JJ)Ljava/lang/Throwable;
/*     */     //   175: athrow
/*     */     //   176: aload #5
/*     */     //   178: ifnull -> 297
/*     */     //   181: aload #7
/*     */     //   183: goto -> 196
/*     */     //   186: ldc2_w 8722136047295854146
/*     */     //   189: lload_1
/*     */     //   190: <illegal opcode> w : (Ljava/lang/Throwable;JJ)Ljava/lang/Throwable;
/*     */     //   195: athrow
/*     */     //   196: aconst_null
/*     */     //   197: putfield f : Lme/konsolas/aac/dO;
/*     */     //   200: iconst_0
/*     */     //   201: istore #8
/*     */     //   203: iload #8
/*     */     //   205: aload_0
/*     */     //   206: getfield r : I
/*     */     //   209: if_icmpge -> 290
/*     */     //   212: aload_0
/*     */     //   213: getfield h : Lme/konsolas/aac/j9;
/*     */     //   216: aload #7
/*     */     //   218: getfield b : [Ljava/io/File;
/*     */     //   221: iload #8
/*     */     //   223: aaload
/*     */     //   224: lload_3
/*     */     //   225: dup2_x1
/*     */     //   226: pop2
/*     */     //   227: invokeinterface b : (JLjava/io/File;)V
/*     */     //   232: aload_0
/*     */     //   233: getfield h : Lme/konsolas/aac/j9;
/*     */     //   236: aload #7
/*     */     //   238: getfield h : [Ljava/io/File;
/*     */     //   241: iload #8
/*     */     //   243: aaload
/*     */     //   244: lload_3
/*     */     //   245: dup2_x1
/*     */     //   246: pop2
/*     */     //   247: invokeinterface b : (JLjava/io/File;)V
/*     */     //   252: iinc #8, 1
/*     */     //   255: aload #5
/*     */     //   257: lload_1
/*     */     //   258: lconst_0
/*     */     //   259: lcmp
/*     */     //   260: ifle -> 299
/*     */     //   263: ifnonnull -> 297
/*     */     //   266: aload #5
/*     */     //   268: ifnull -> 203
/*     */     //   271: lload_1
/*     */     //   272: lconst_0
/*     */     //   273: lcmp
/*     */     //   274: ifle -> 255
/*     */     //   277: goto -> 290
/*     */     //   280: ldc2_w 8722136047295854146
/*     */     //   283: lload_1
/*     */     //   284: <illegal opcode> w : (Ljava/lang/Throwable;JJ)Ljava/lang/Throwable;
/*     */     //   289: athrow
/*     */     //   290: aload #6
/*     */     //   292: invokeinterface remove : ()V
/*     */     //   297: aload #5
/*     */     //   299: ifnull -> 55
/*     */     //   302: return
/*     */     // Line number table:
/*     */     //   Java source line number -> byte code offset
/*     */     //   #237	-> 14
/*     */     //   #295	-> 39
/*     */     //   #212	-> 65
/*     */     //   #106	-> 77
/*     */     //   #135	-> 109
/*     */     //   #23	-> 121
/*     */     //   #188	-> 138
/*     */     //   #217	-> 181
/*     */     //   #202	-> 200
/*     */     //   #68	-> 212
/*     */     //   #112	-> 232
/*     */     //   #205	-> 252
/*     */     //   #265	-> 290
/*     */     //   #122	-> 297
/*     */     //   #121	-> 302
/*     */     // Exception table:
/*     */     //   from	to	target	type
/*     */     //   77	96	99	java/io/IOException
/*     */     //   121	157	166	java/io/IOException
/*     */     //   176	183	186	java/io/IOException
/*     */     //   212	271	280	java/io/IOException
/*     */   }
/*     */   
/*     */   public synchronized void close() {
/*     */     // Byte code:
/*     */     //   0: getstatic me/konsolas/aac/m5.H : J
/*     */     //   3: ldc2_w 7808588113993
/*     */     //   6: lxor
/*     */     //   7: lstore_1
/*     */     //   8: lload_1
/*     */     //   9: dup2
/*     */     //   10: ldc2_w 108233098881486
/*     */     //   13: lxor
/*     */     //   14: lstore_3
/*     */     //   15: dup2
/*     */     //   16: ldc2_w 56175351238858
/*     */     //   19: lxor
/*     */     //   20: dup2
/*     */     //   21: bipush #48
/*     */     //   23: lushr
/*     */     //   24: l2i
/*     */     //   25: istore #5
/*     */     //   27: dup2
/*     */     //   28: bipush #16
/*     */     //   30: lshl
/*     */     //   31: bipush #48
/*     */     //   33: lushr
/*     */     //   34: l2i
/*     */     //   35: istore #6
/*     */     //   37: dup2
/*     */     //   38: bipush #32
/*     */     //   40: lshl
/*     */     //   41: bipush #32
/*     */     //   43: lushr
/*     */     //   44: l2i
/*     */     //   45: istore #7
/*     */     //   47: pop2
/*     */     //   48: pop2
/*     */     //   49: ldc2_w 4164487934503524012
/*     */     //   52: lload_1
/*     */     //   53: <illegal opcode> w : (JJ)[Ljava/lang/String;
/*     */     //   58: astore #8
/*     */     //   60: aload_0
/*     */     //   61: aload #8
/*     */     //   63: ifnonnull -> 137
/*     */     //   66: getfield e : Z
/*     */     //   69: ifeq -> 123
/*     */     //   72: goto -> 85
/*     */     //   75: ldc2_w 4170447068161095337
/*     */     //   78: lload_1
/*     */     //   79: <illegal opcode> w : (Ljava/lang/Throwable;JJ)Ljava/lang/Throwable;
/*     */     //   84: athrow
/*     */     //   85: aload_0
/*     */     //   86: aload #8
/*     */     //   88: ifnonnull -> 143
/*     */     //   91: goto -> 104
/*     */     //   94: ldc2_w 4170447068161095337
/*     */     //   97: lload_1
/*     */     //   98: <illegal opcode> w : (Ljava/lang/Throwable;JJ)Ljava/lang/Throwable;
/*     */     //   103: athrow
/*     */     //   104: getfield z : Z
/*     */     //   107: ifeq -> 142
/*     */     //   110: goto -> 123
/*     */     //   113: ldc2_w 4170447068161095337
/*     */     //   116: lload_1
/*     */     //   117: <illegal opcode> w : (Ljava/lang/Throwable;JJ)Ljava/lang/Throwable;
/*     */     //   122: athrow
/*     */     //   123: aload_0
/*     */     //   124: goto -> 137
/*     */     //   127: ldc2_w 4170447068161095337
/*     */     //   130: lload_1
/*     */     //   131: <illegal opcode> w : (Ljava/lang/Throwable;JJ)Ljava/lang/Throwable;
/*     */     //   136: athrow
/*     */     //   137: iconst_1
/*     */     //   138: putfield z : Z
/*     */     //   141: return
/*     */     //   142: aload_0
/*     */     //   143: getfield f : Ljava/util/LinkedHashMap;
/*     */     //   146: invokevirtual values : ()Ljava/util/Collection;
/*     */     //   149: aload_0
/*     */     //   150: getfield f : Ljava/util/LinkedHashMap;
/*     */     //   153: invokevirtual size : ()I
/*     */     //   156: anewarray me/konsolas/aac/bT
/*     */     //   159: invokeinterface toArray : ([Ljava/lang/Object;)[Ljava/lang/Object;
/*     */     //   164: checkcast [Lme/konsolas/aac/bT;
/*     */     //   167: astore #9
/*     */     //   169: aload #9
/*     */     //   171: arraylength
/*     */     //   172: istore #10
/*     */     //   174: iconst_0
/*     */     //   175: istore #11
/*     */     //   177: iload #11
/*     */     //   179: iload #10
/*     */     //   181: if_icmpge -> 272
/*     */     //   184: aload #9
/*     */     //   186: iload #11
/*     */     //   188: aaload
/*     */     //   189: astore #12
/*     */     //   191: aload #8
/*     */     //   193: ifnonnull -> 296
/*     */     //   196: aload #8
/*     */     //   198: ifnonnull -> 267
/*     */     //   201: goto -> 214
/*     */     //   204: ldc2_w 4170447068161095337
/*     */     //   207: lload_1
/*     */     //   208: <illegal opcode> w : (Ljava/lang/Throwable;JJ)Ljava/lang/Throwable;
/*     */     //   213: athrow
/*     */     //   214: aload #12
/*     */     //   216: getfield f : Lme/konsolas/aac/dO;
/*     */     //   219: ifnull -> 264
/*     */     //   222: goto -> 235
/*     */     //   225: ldc2_w 4170447068161095337
/*     */     //   228: lload_1
/*     */     //   229: <illegal opcode> w : (Ljava/lang/Throwable;JJ)Ljava/lang/Throwable;
/*     */     //   234: athrow
/*     */     //   235: aload #12
/*     */     //   237: getfield f : Lme/konsolas/aac/dO;
/*     */     //   240: iload #5
/*     */     //   242: i2c
/*     */     //   243: iload #6
/*     */     //   245: i2c
/*     */     //   246: iload #7
/*     */     //   248: invokevirtual d : (CCI)V
/*     */     //   251: goto -> 264
/*     */     //   254: ldc2_w 4170447068161095337
/*     */     //   257: lload_1
/*     */     //   258: <illegal opcode> w : (Ljava/lang/Throwable;JJ)Ljava/lang/Throwable;
/*     */     //   263: athrow
/*     */     //   264: iinc #11, 1
/*     */     //   267: aload #8
/*     */     //   269: ifnull -> 177
/*     */     //   272: aload_0
/*     */     //   273: lload_3
/*     */     //   274: invokevirtual a : (J)V
/*     */     //   277: aload_0
/*     */     //   278: getfield D : Lme/konsolas/aac/gi;
/*     */     //   281: invokeinterface close : ()V
/*     */     //   286: aload_0
/*     */     //   287: aconst_null
/*     */     //   288: putfield D : Lme/konsolas/aac/gi;
/*     */     //   291: aload_0
/*     */     //   292: iconst_1
/*     */     //   293: putfield z : Z
/*     */     //   296: return
/*     */     // Line number table:
/*     */     //   Java source line number -> byte code offset
/*     */     //   #238	-> 60
/*     */     //   #67	-> 123
/*     */     //   #42	-> 141
/*     */     //   #117	-> 142
/*     */     //   #261	-> 191
/*     */     //   #236	-> 235
/*     */     //   #252	-> 264
/*     */     //   #124	-> 272
/*     */     //   #147	-> 277
/*     */     //   #270	-> 286
/*     */     //   #168	-> 291
/*     */     //   #107	-> 296
/*     */     // Exception table:
/*     */     //   from	to	target	type
/*     */     //   60	72	75	java/io/IOException
/*     */     //   66	91	94	java/io/IOException
/*     */     //   85	110	113	java/io/IOException
/*     */     //   104	124	127	java/io/IOException
/*     */     //   191	201	204	java/io/IOException
/*     */     //   196	222	225	java/io/IOException
/*     */     //   214	251	254	java/io/IOException
/*     */   }
/*     */   
/*     */   synchronized dO a(String paramString, long paramLong1, long paramLong2) {
/*     */     // Byte code:
/*     */     //   0: getstatic me/konsolas/aac/m5.H : J
/*     */     //   3: lload #4
/*     */     //   5: lxor
/*     */     //   6: lstore #4
/*     */     //   8: lload #4
/*     */     //   10: dup2
/*     */     //   11: ldc2_w 101598606766235
/*     */     //   14: lxor
/*     */     //   15: lstore #6
/*     */     //   17: dup2
/*     */     //   18: ldc2_w 51371473009624
/*     */     //   21: lxor
/*     */     //   22: dup2
/*     */     //   23: bipush #48
/*     */     //   25: lushr
/*     */     //   26: l2i
/*     */     //   27: istore #8
/*     */     //   29: dup2
/*     */     //   30: bipush #16
/*     */     //   32: lshl
/*     */     //   33: bipush #16
/*     */     //   35: lushr
/*     */     //   36: lstore #9
/*     */     //   38: pop2
/*     */     //   39: dup2
/*     */     //   40: ldc2_w 76164448927694
/*     */     //   43: lxor
/*     */     //   44: lstore #11
/*     */     //   46: dup2
/*     */     //   47: ldc2_w 66847523782092
/*     */     //   50: lxor
/*     */     //   51: lstore #13
/*     */     //   53: dup2
/*     */     //   54: ldc2_w 22124955683250
/*     */     //   57: lxor
/*     */     //   58: lstore #15
/*     */     //   60: dup2
/*     */     //   61: ldc2_w 128288156849351
/*     */     //   64: lxor
/*     */     //   65: lstore #17
/*     */     //   67: dup2
/*     */     //   68: ldc2_w 132795818932535
/*     */     //   71: lxor
/*     */     //   72: lstore #19
/*     */     //   74: pop2
/*     */     //   75: ldc2_w -5231157409524672512
/*     */     //   78: lload #4
/*     */     //   80: <illegal opcode> w : (JJ)[Ljava/lang/String;
/*     */     //   85: aload_0
/*     */     //   86: lload #15
/*     */     //   88: invokevirtual b : (J)V
/*     */     //   91: astore #21
/*     */     //   93: aload_0
/*     */     //   94: iload #8
/*     */     //   96: i2c
/*     */     //   97: lload #9
/*     */     //   99: invokespecial c : (CJ)V
/*     */     //   102: aload_0
/*     */     //   103: aload_1
/*     */     //   104: lload #6
/*     */     //   106: invokespecial b : (Ljava/lang/String;J)V
/*     */     //   109: aload_0
/*     */     //   110: getfield f : Ljava/util/LinkedHashMap;
/*     */     //   113: aload_1
/*     */     //   114: invokevirtual get : (Ljava/lang/Object;)Ljava/lang/Object;
/*     */     //   117: checkcast me/konsolas/aac/bT
/*     */     //   120: astore #22
/*     */     //   122: lload_2
/*     */     //   123: ldc2_w -1
/*     */     //   126: lcmp
/*     */     //   127: ifeq -> 224
/*     */     //   130: aload #22
/*     */     //   132: aload #21
/*     */     //   134: lload #4
/*     */     //   136: lconst_0
/*     */     //   137: lcmp
/*     */     //   138: ifle -> 179
/*     */     //   141: ifnonnull -> 177
/*     */     //   144: goto -> 158
/*     */     //   147: ldc2_w -5238691078767036411
/*     */     //   150: lload #4
/*     */     //   152: <illegal opcode> w : (Ljava/lang/Throwable;JJ)Ljava/lang/Throwable;
/*     */     //   157: athrow
/*     */     //   158: ifnull -> 211
/*     */     //   161: goto -> 175
/*     */     //   164: ldc2_w -5238691078767036411
/*     */     //   167: lload #4
/*     */     //   169: <illegal opcode> w : (Ljava/lang/Throwable;JJ)Ljava/lang/Throwable;
/*     */     //   174: athrow
/*     */     //   175: aload #22
/*     */     //   177: aload #21
/*     */     //   179: lload #4
/*     */     //   181: lconst_0
/*     */     //   182: lcmp
/*     */     //   183: ifle -> 235
/*     */     //   186: ifnonnull -> 226
/*     */     //   189: getfield c : J
/*     */     //   192: lload_2
/*     */     //   193: lcmp
/*     */     //   194: ifeq -> 224
/*     */     //   197: goto -> 211
/*     */     //   200: ldc2_w -5238691078767036411
/*     */     //   203: lload #4
/*     */     //   205: <illegal opcode> w : (Ljava/lang/Throwable;JJ)Ljava/lang/Throwable;
/*     */     //   210: athrow
/*     */     //   211: aconst_null
/*     */     //   212: areturn
/*     */     //   213: ldc2_w -5238691078767036411
/*     */     //   216: lload #4
/*     */     //   218: <illegal opcode> w : (Ljava/lang/Throwable;JJ)Ljava/lang/Throwable;
/*     */     //   223: athrow
/*     */     //   224: aload #22
/*     */     //   226: lload #4
/*     */     //   228: lconst_0
/*     */     //   229: lcmp
/*     */     //   230: ifle -> 257
/*     */     //   233: aload #21
/*     */     //   235: ifnonnull -> 257
/*     */     //   238: ifnull -> 276
/*     */     //   241: goto -> 255
/*     */     //   244: ldc2_w -5238691078767036411
/*     */     //   247: lload #4
/*     */     //   249: <illegal opcode> w : (Ljava/lang/Throwable;JJ)Ljava/lang/Throwable;
/*     */     //   254: athrow
/*     */     //   255: aload #22
/*     */     //   257: getfield f : Lme/konsolas/aac/dO;
/*     */     //   260: ifnull -> 276
/*     */     //   263: aconst_null
/*     */     //   264: areturn
/*     */     //   265: ldc2_w -5238691078767036411
/*     */     //   268: lload #4
/*     */     //   270: <illegal opcode> w : (Ljava/lang/Throwable;JJ)Ljava/lang/Throwable;
/*     */     //   275: athrow
/*     */     //   276: lload #4
/*     */     //   278: lconst_0
/*     */     //   279: lcmp
/*     */     //   280: iflt -> 369
/*     */     //   283: aload_0
/*     */     //   284: aload #21
/*     */     //   286: ifnonnull -> 357
/*     */     //   289: getfield x : Z
/*     */     //   292: ifne -> 356
/*     */     //   295: goto -> 309
/*     */     //   298: ldc2_w -5238691078767036411
/*     */     //   301: lload #4
/*     */     //   303: <illegal opcode> w : (Ljava/lang/Throwable;JJ)Ljava/lang/Throwable;
/*     */     //   308: athrow
/*     */     //   309: aload_0
/*     */     //   310: getfield i : Z
/*     */     //   313: lload #4
/*     */     //   315: lconst_0
/*     */     //   316: lcmp
/*     */     //   317: ifle -> 436
/*     */     //   320: aload #21
/*     */     //   322: ifnonnull -> 436
/*     */     //   325: goto -> 339
/*     */     //   328: ldc2_w -5238691078767036411
/*     */     //   331: lload #4
/*     */     //   333: <illegal opcode> w : (Ljava/lang/Throwable;JJ)Ljava/lang/Throwable;
/*     */     //   338: athrow
/*     */     //   339: ifeq -> 371
/*     */     //   342: goto -> 356
/*     */     //   345: ldc2_w -5238691078767036411
/*     */     //   348: lload #4
/*     */     //   350: <illegal opcode> w : (Ljava/lang/Throwable;JJ)Ljava/lang/Throwable;
/*     */     //   355: athrow
/*     */     //   356: aload_0
/*     */     //   357: getfield u : Ljava/util/concurrent/Executor;
/*     */     //   360: aload_0
/*     */     //   361: getfield l : Ljava/lang/Runnable;
/*     */     //   364: invokeinterface execute : (Ljava/lang/Runnable;)V
/*     */     //   369: aconst_null
/*     */     //   370: areturn
/*     */     //   371: aload_0
/*     */     //   372: getfield D : Lme/konsolas/aac/gi;
/*     */     //   375: sipush #22219
/*     */     //   378: ldc2_w 3692240966896808685
/*     */     //   381: lload #4
/*     */     //   383: lxor
/*     */     //   384: <illegal opcode> z : (IJ)Ljava/lang/String;
/*     */     //   389: lload #17
/*     */     //   391: invokeinterface a : (Ljava/lang/String;J)Lme/konsolas/aac/gi;
/*     */     //   396: bipush #32
/*     */     //   398: lload #11
/*     */     //   400: invokeinterface d : (IJ)Lme/konsolas/aac/gi;
/*     */     //   405: aload_1
/*     */     //   406: lload #17
/*     */     //   408: invokeinterface a : (Ljava/lang/String;J)Lme/konsolas/aac/gi;
/*     */     //   413: bipush #10
/*     */     //   415: lload #11
/*     */     //   417: invokeinterface d : (IJ)Lme/konsolas/aac/gi;
/*     */     //   422: pop
/*     */     //   423: aload_0
/*     */     //   424: getfield D : Lme/konsolas/aac/gi;
/*     */     //   427: invokeinterface flush : ()V
/*     */     //   432: aload_0
/*     */     //   433: getfield d : Z
/*     */     //   436: ifeq -> 452
/*     */     //   439: aconst_null
/*     */     //   440: areturn
/*     */     //   441: ldc2_w -5238691078767036411
/*     */     //   444: lload #4
/*     */     //   446: <illegal opcode> w : (Ljava/lang/Throwable;JJ)Ljava/lang/Throwable;
/*     */     //   451: athrow
/*     */     //   452: aload #22
/*     */     //   454: aload #21
/*     */     //   456: ifnonnull -> 499
/*     */     //   459: ifnonnull -> 500
/*     */     //   462: goto -> 476
/*     */     //   465: ldc2_w -5238691078767036411
/*     */     //   468: lload #4
/*     */     //   470: <illegal opcode> w : (Ljava/lang/Throwable;JJ)Ljava/lang/Throwable;
/*     */     //   475: athrow
/*     */     //   476: new me/konsolas/aac/bT
/*     */     //   479: dup
/*     */     //   480: aload_0
/*     */     //   481: aload_1
/*     */     //   482: lload #13
/*     */     //   484: invokespecial <init> : (Lme/konsolas/aac/m5;Ljava/lang/String;J)V
/*     */     //   487: astore #22
/*     */     //   489: aload_0
/*     */     //   490: getfield f : Ljava/util/LinkedHashMap;
/*     */     //   493: aload_1
/*     */     //   494: aload #22
/*     */     //   496: invokevirtual put : (Ljava/lang/Object;Ljava/lang/Object;)Ljava/lang/Object;
/*     */     //   499: pop
/*     */     //   500: new me/konsolas/aac/dO
/*     */     //   503: dup
/*     */     //   504: aload_0
/*     */     //   505: aload #22
/*     */     //   507: lload #19
/*     */     //   509: invokespecial <init> : (Lme/konsolas/aac/m5;Lme/konsolas/aac/bT;J)V
/*     */     //   512: astore #23
/*     */     //   514: aload #22
/*     */     //   516: aload #23
/*     */     //   518: putfield f : Lme/konsolas/aac/dO;
/*     */     //   521: aload #23
/*     */     //   523: areturn
/*     */     // Line number table:
/*     */     //   Java source line number -> byte code offset
/*     */     //   #249	-> 85
/*     */     //   #210	-> 93
/*     */     //   #225	-> 102
/*     */     //   #132	-> 109
/*     */     //   #56	-> 122
/*     */     //   #156	-> 211
/*     */     //   #133	-> 224
/*     */     //   #22	-> 263
/*     */     //   #97	-> 276
/*     */     //   #209	-> 356
/*     */     //   #180	-> 369
/*     */     //   #62	-> 371
/*     */     //   #13	-> 423
/*     */     //   #181	-> 432
/*     */     //   #223	-> 439
/*     */     //   #187	-> 452
/*     */     //   #286	-> 476
/*     */     //   #118	-> 489
/*     */     //   #25	-> 500
/*     */     //   #218	-> 514
/*     */     //   #33	-> 521
/*     */     // Exception table:
/*     */     //   from	to	target	type
/*     */     //   122	144	147	java/io/IOException
/*     */     //   130	161	164	java/io/IOException
/*     */     //   177	197	200	java/io/IOException
/*     */     //   189	213	213	java/io/IOException
/*     */     //   226	241	244	java/io/IOException
/*     */     //   257	265	265	java/io/IOException
/*     */     //   276	295	298	java/io/IOException
/*     */     //   289	325	328	java/io/IOException
/*     */     //   309	342	345	java/io/IOException
/*     */     //   436	441	441	java/io/IOException
/*     */     //   452	462	465	java/io/IOException
/*     */   }
/*     */   
/*     */   private void a(String paramString, long paramLong) {
/*     */     // Byte code:
/*     */     //   0: getstatic me/konsolas/aac/m5.H : J
/*     */     //   3: lload_2
/*     */     //   4: lxor
/*     */     //   5: lstore_2
/*     */     //   6: lload_2
/*     */     //   7: dup2
/*     */     //   8: ldc2_w 94169760790895
/*     */     //   11: lxor
/*     */     //   12: lstore #4
/*     */     //   14: dup2
/*     */     //   15: ldc2_w 126609347155624
/*     */     //   18: lxor
/*     */     //   19: lstore #6
/*     */     //   21: dup2
/*     */     //   22: ldc2_w 19444698332564
/*     */     //   25: lxor
/*     */     //   26: lstore #8
/*     */     //   28: pop2
/*     */     //   29: ldc2_w -881479137893917533
/*     */     //   32: lload_2
/*     */     //   33: <illegal opcode> w : (JJ)[Ljava/lang/String;
/*     */     //   38: aload_1
/*     */     //   39: bipush #32
/*     */     //   41: invokevirtual indexOf : (I)I
/*     */     //   44: istore #11
/*     */     //   46: astore #10
/*     */     //   48: iload #11
/*     */     //   50: iconst_m1
/*     */     //   51: aload #10
/*     */     //   53: ifnonnull -> 123
/*     */     //   56: if_icmpne -> 120
/*     */     //   59: goto -> 72
/*     */     //   62: ldc2_w -869468156305965914
/*     */     //   65: lload_2
/*     */     //   66: <illegal opcode> w : (Ljava/lang/Throwable;JJ)Ljava/lang/Throwable;
/*     */     //   71: athrow
/*     */     //   72: new java/io/IOException
/*     */     //   75: dup
/*     */     //   76: new java/lang/StringBuilder
/*     */     //   79: dup
/*     */     //   80: invokespecial <init> : ()V
/*     */     //   83: sipush #14451
/*     */     //   86: ldc2_w 6065226681670195429
/*     */     //   89: lload_2
/*     */     //   90: lxor
/*     */     //   91: <illegal opcode> z : (IJ)Ljava/lang/String;
/*     */     //   96: invokevirtual append : (Ljava/lang/String;)Ljava/lang/StringBuilder;
/*     */     //   99: aload_1
/*     */     //   100: invokevirtual append : (Ljava/lang/String;)Ljava/lang/StringBuilder;
/*     */     //   103: invokevirtual toString : ()Ljava/lang/String;
/*     */     //   106: invokespecial <init> : (Ljava/lang/String;)V
/*     */     //   109: athrow
/*     */     //   110: ldc2_w -869468156305965914
/*     */     //   113: lload_2
/*     */     //   114: <illegal opcode> w : (Ljava/lang/Throwable;JJ)Ljava/lang/Throwable;
/*     */     //   119: athrow
/*     */     //   120: iload #11
/*     */     //   122: iconst_1
/*     */     //   123: iadd
/*     */     //   124: istore #12
/*     */     //   126: aload_1
/*     */     //   127: bipush #32
/*     */     //   129: iload #12
/*     */     //   131: invokevirtual indexOf : (II)I
/*     */     //   134: istore #13
/*     */     //   136: iload #13
/*     */     //   138: iconst_m1
/*     */     //   139: if_icmpne -> 267
/*     */     //   142: aload_1
/*     */     //   143: iload #12
/*     */     //   145: invokevirtual substring : (I)Ljava/lang/String;
/*     */     //   148: astore #14
/*     */     //   150: iload #11
/*     */     //   152: lload_2
/*     */     //   153: lconst_0
/*     */     //   154: lcmp
/*     */     //   155: ifle -> 243
/*     */     //   158: aload #10
/*     */     //   160: ifnonnull -> 243
/*     */     //   163: sipush #1046
/*     */     //   166: ldc2_w 2782068136774853790
/*     */     //   169: lload_2
/*     */     //   170: lxor
/*     */     //   171: <illegal opcode> z : (IJ)Ljava/lang/String;
/*     */     //   176: invokevirtual length : ()I
/*     */     //   179: if_icmpne -> 277
/*     */     //   182: goto -> 195
/*     */     //   185: ldc2_w -869468156305965914
/*     */     //   188: lload_2
/*     */     //   189: <illegal opcode> w : (Ljava/lang/Throwable;JJ)Ljava/lang/Throwable;
/*     */     //   194: athrow
/*     */     //   195: aload_1
/*     */     //   196: aload #10
/*     */     //   198: ifnonnull -> 286
/*     */     //   201: goto -> 214
/*     */     //   204: ldc2_w -869468156305965914
/*     */     //   207: lload_2
/*     */     //   208: <illegal opcode> w : (Ljava/lang/Throwable;JJ)Ljava/lang/Throwable;
/*     */     //   213: athrow
/*     */     //   214: sipush #1046
/*     */     //   217: ldc2_w 2782068136774853790
/*     */     //   220: lload_2
/*     */     //   221: lxor
/*     */     //   222: <illegal opcode> z : (IJ)Ljava/lang/String;
/*     */     //   227: invokevirtual startsWith : (Ljava/lang/String;)Z
/*     */     //   230: goto -> 243
/*     */     //   233: ldc2_w -869468156305965914
/*     */     //   236: lload_2
/*     */     //   237: <illegal opcode> w : (Ljava/lang/Throwable;JJ)Ljava/lang/Throwable;
/*     */     //   242: athrow
/*     */     //   243: ifeq -> 277
/*     */     //   246: aload_0
/*     */     //   247: getfield f : Ljava/util/LinkedHashMap;
/*     */     //   250: aload #14
/*     */     //   252: invokevirtual remove : (Ljava/lang/Object;)Ljava/lang/Object;
/*     */     //   255: pop
/*     */     //   256: return
/*     */     //   257: ldc2_w -869468156305965914
/*     */     //   260: lload_2
/*     */     //   261: <illegal opcode> w : (Ljava/lang/Throwable;JJ)Ljava/lang/Throwable;
/*     */     //   266: athrow
/*     */     //   267: aload_1
/*     */     //   268: iload #12
/*     */     //   270: iload #13
/*     */     //   272: invokevirtual substring : (II)Ljava/lang/String;
/*     */     //   275: astore #14
/*     */     //   277: aload_0
/*     */     //   278: getfield f : Ljava/util/LinkedHashMap;
/*     */     //   281: aload #14
/*     */     //   283: invokevirtual get : (Ljava/lang/Object;)Ljava/lang/Object;
/*     */     //   286: checkcast me/konsolas/aac/bT
/*     */     //   289: astore #15
/*     */     //   291: aload #15
/*     */     //   293: aload #10
/*     */     //   295: ifnonnull -> 339
/*     */     //   298: ifnonnull -> 340
/*     */     //   301: goto -> 314
/*     */     //   304: ldc2_w -869468156305965914
/*     */     //   307: lload_2
/*     */     //   308: <illegal opcode> w : (Ljava/lang/Throwable;JJ)Ljava/lang/Throwable;
/*     */     //   313: athrow
/*     */     //   314: new me/konsolas/aac/bT
/*     */     //   317: dup
/*     */     //   318: aload_0
/*     */     //   319: aload #14
/*     */     //   321: lload #4
/*     */     //   323: invokespecial <init> : (Lme/konsolas/aac/m5;Ljava/lang/String;J)V
/*     */     //   326: astore #15
/*     */     //   328: aload_0
/*     */     //   329: getfield f : Ljava/util/LinkedHashMap;
/*     */     //   332: aload #14
/*     */     //   334: aload #15
/*     */     //   336: invokevirtual put : (Ljava/lang/Object;Ljava/lang/Object;)Ljava/lang/Object;
/*     */     //   339: pop
/*     */     //   340: iload #13
/*     */     //   342: iconst_m1
/*     */     //   343: aload #10
/*     */     //   345: ifnonnull -> 553
/*     */     //   348: if_icmpeq -> 537
/*     */     //   351: goto -> 364
/*     */     //   354: ldc2_w -869468156305965914
/*     */     //   357: lload_2
/*     */     //   358: <illegal opcode> w : (Ljava/lang/Throwable;JJ)Ljava/lang/Throwable;
/*     */     //   363: athrow
/*     */     //   364: iload #11
/*     */     //   366: sipush #1508
/*     */     //   369: ldc2_w 4363179745589257576
/*     */     //   372: lload_2
/*     */     //   373: lxor
/*     */     //   374: <illegal opcode> z : (IJ)Ljava/lang/String;
/*     */     //   379: invokevirtual length : ()I
/*     */     //   382: aload #10
/*     */     //   384: lload_2
/*     */     //   385: lconst_0
/*     */     //   386: lcmp
/*     */     //   387: iflt -> 555
/*     */     //   390: ifnonnull -> 553
/*     */     //   393: goto -> 406
/*     */     //   396: ldc2_w -869468156305965914
/*     */     //   399: lload_2
/*     */     //   400: <illegal opcode> w : (Ljava/lang/Throwable;JJ)Ljava/lang/Throwable;
/*     */     //   405: athrow
/*     */     //   406: if_icmpne -> 537
/*     */     //   409: goto -> 422
/*     */     //   412: ldc2_w -869468156305965914
/*     */     //   415: lload_2
/*     */     //   416: <illegal opcode> w : (Ljava/lang/Throwable;JJ)Ljava/lang/Throwable;
/*     */     //   421: athrow
/*     */     //   422: aload_1
/*     */     //   423: sipush #1508
/*     */     //   426: ldc2_w 4363179745589257576
/*     */     //   429: lload_2
/*     */     //   430: lxor
/*     */     //   431: <illegal opcode> z : (IJ)Ljava/lang/String;
/*     */     //   436: invokevirtual startsWith : (Ljava/lang/String;)Z
/*     */     //   439: aload #10
/*     */     //   441: ifnonnull -> 552
/*     */     //   444: goto -> 457
/*     */     //   447: ldc2_w -869468156305965914
/*     */     //   450: lload_2
/*     */     //   451: <illegal opcode> w : (Ljava/lang/Throwable;JJ)Ljava/lang/Throwable;
/*     */     //   456: athrow
/*     */     //   457: ifeq -> 537
/*     */     //   460: goto -> 473
/*     */     //   463: ldc2_w -869468156305965914
/*     */     //   466: lload_2
/*     */     //   467: <illegal opcode> w : (Ljava/lang/Throwable;JJ)Ljava/lang/Throwable;
/*     */     //   472: athrow
/*     */     //   473: aload_1
/*     */     //   474: iload #13
/*     */     //   476: iconst_1
/*     */     //   477: iadd
/*     */     //   478: invokevirtual substring : (I)Ljava/lang/String;
/*     */     //   481: ldc_w '굸㡡'
/*     */     //   484: invokevirtual toCharArray : ()[C
/*     */     //   487: dup
/*     */     //   488: dup
/*     */     //   489: iconst_0
/*     */     //   490: dup_x1
/*     */     //   491: caload
/*     */     //   492: sipush #8094
/*     */     //   495: ixor
/*     */     //   496: i2c
/*     */     //   497: castore
/*     */     //   498: sipush #8567
/*     */     //   501: iconst_0
/*     */     //   502: iconst_0
/*     */     //   503: invokestatic U : (Ljava/lang/Object;SZZ)Ljava/lang/String;
/*     */     //   506: invokevirtual split : (Ljava/lang/String;)[Ljava/lang/String;
/*     */     //   509: astore #16
/*     */     //   511: aload #15
/*     */     //   513: iconst_1
/*     */     //   514: putfield d : Z
/*     */     //   517: aload #15
/*     */     //   519: aconst_null
/*     */     //   520: putfield f : Lme/konsolas/aac/dO;
/*     */     //   523: aload #15
/*     */     //   525: aload #16
/*     */     //   527: lload #6
/*     */     //   529: invokevirtual a : ([Ljava/lang/String;J)V
/*     */     //   532: aload #10
/*     */     //   534: ifnull -> 893
/*     */     //   537: iload #13
/*     */     //   539: goto -> 552
/*     */     //   542: ldc2_w -869468156305965914
/*     */     //   545: lload_2
/*     */     //   546: <illegal opcode> w : (Ljava/lang/Throwable;JJ)Ljava/lang/Throwable;
/*     */     //   551: athrow
/*     */     //   552: iconst_m1
/*     */     //   553: aload #10
/*     */     //   555: ifnonnull -> 740
/*     */     //   558: if_icmpne -> 724
/*     */     //   561: goto -> 574
/*     */     //   564: ldc2_w -869468156305965914
/*     */     //   567: lload_2
/*     */     //   568: <illegal opcode> w : (Ljava/lang/Throwable;JJ)Ljava/lang/Throwable;
/*     */     //   573: athrow
/*     */     //   574: iload #11
/*     */     //   576: sipush #22219
/*     */     //   579: ldc2_w 3692125898477942350
/*     */     //   582: lload_2
/*     */     //   583: lxor
/*     */     //   584: <illegal opcode> z : (IJ)Ljava/lang/String;
/*     */     //   589: invokevirtual length : ()I
/*     */     //   592: aload #10
/*     */     //   594: lload_2
/*     */     //   595: lconst_0
/*     */     //   596: lcmp
/*     */     //   597: iflt -> 748
/*     */     //   600: ifnonnull -> 740
/*     */     //   603: goto -> 616
/*     */     //   606: ldc2_w -869468156305965914
/*     */     //   609: lload_2
/*     */     //   610: <illegal opcode> w : (Ljava/lang/Throwable;JJ)Ljava/lang/Throwable;
/*     */     //   615: athrow
/*     */     //   616: if_icmpne -> 724
/*     */     //   619: goto -> 632
/*     */     //   622: ldc2_w -869468156305965914
/*     */     //   625: lload_2
/*     */     //   626: <illegal opcode> w : (Ljava/lang/Throwable;JJ)Ljava/lang/Throwable;
/*     */     //   631: athrow
/*     */     //   632: aload_1
/*     */     //   633: sipush #22219
/*     */     //   636: ldc2_w 3692125898477942350
/*     */     //   639: lload_2
/*     */     //   640: lxor
/*     */     //   641: <illegal opcode> z : (IJ)Ljava/lang/String;
/*     */     //   646: invokevirtual startsWith : (Ljava/lang/String;)Z
/*     */     //   649: aload #10
/*     */     //   651: ifnonnull -> 739
/*     */     //   654: goto -> 667
/*     */     //   657: ldc2_w -869468156305965914
/*     */     //   660: lload_2
/*     */     //   661: <illegal opcode> w : (Ljava/lang/Throwable;JJ)Ljava/lang/Throwable;
/*     */     //   666: athrow
/*     */     //   667: lload_2
/*     */     //   668: lconst_0
/*     */     //   669: lcmp
/*     */     //   670: iflt -> 726
/*     */     //   673: ifeq -> 724
/*     */     //   676: goto -> 689
/*     */     //   679: ldc2_w -869468156305965914
/*     */     //   682: lload_2
/*     */     //   683: <illegal opcode> w : (Ljava/lang/Throwable;JJ)Ljava/lang/Throwable;
/*     */     //   688: athrow
/*     */     //   689: aload #15
/*     */     //   691: new me/konsolas/aac/dO
/*     */     //   694: dup
/*     */     //   695: aload_0
/*     */     //   696: aload #15
/*     */     //   698: lload #8
/*     */     //   700: invokespecial <init> : (Lme/konsolas/aac/m5;Lme/konsolas/aac/bT;J)V
/*     */     //   703: putfield f : Lme/konsolas/aac/dO;
/*     */     //   706: aload #10
/*     */     //   708: ifnull -> 893
/*     */     //   711: goto -> 724
/*     */     //   714: ldc2_w -869468156305965914
/*     */     //   717: lload_2
/*     */     //   718: <illegal opcode> w : (Ljava/lang/Throwable;JJ)Ljava/lang/Throwable;
/*     */     //   723: athrow
/*     */     //   724: iload #13
/*     */     //   726: goto -> 739
/*     */     //   729: ldc2_w -869468156305965914
/*     */     //   732: lload_2
/*     */     //   733: <illegal opcode> w : (Ljava/lang/Throwable;JJ)Ljava/lang/Throwable;
/*     */     //   738: athrow
/*     */     //   739: iconst_m1
/*     */     //   740: lload_2
/*     */     //   741: lconst_0
/*     */     //   742: lcmp
/*     */     //   743: iflt -> 816
/*     */     //   746: aload #10
/*     */     //   748: ifnonnull -> 816
/*     */     //   751: if_icmpne -> 855
/*     */     //   754: goto -> 767
/*     */     //   757: ldc2_w -869468156305965914
/*     */     //   760: lload_2
/*     */     //   761: <illegal opcode> w : (Ljava/lang/Throwable;JJ)Ljava/lang/Throwable;
/*     */     //   766: athrow
/*     */     //   767: iload #11
/*     */     //   769: aload #10
/*     */     //   771: ifnonnull -> 849
/*     */     //   774: goto -> 787
/*     */     //   777: ldc2_w -869468156305965914
/*     */     //   780: lload_2
/*     */     //   781: <illegal opcode> w : (Ljava/lang/Throwable;JJ)Ljava/lang/Throwable;
/*     */     //   786: athrow
/*     */     //   787: sipush #2873
/*     */     //   790: ldc2_w 3155483927149636484
/*     */     //   793: lload_2
/*     */     //   794: lxor
/*     */     //   795: <illegal opcode> z : (IJ)Ljava/lang/String;
/*     */     //   800: invokevirtual length : ()I
/*     */     //   803: goto -> 816
/*     */     //   806: ldc2_w -869468156305965914
/*     */     //   809: lload_2
/*     */     //   810: <illegal opcode> w : (Ljava/lang/Throwable;JJ)Ljava/lang/Throwable;
/*     */     //   815: athrow
/*     */     //   816: if_icmpne -> 855
/*     */     //   819: aload_1
/*     */     //   820: sipush #2873
/*     */     //   823: ldc2_w 3155483927149636484
/*     */     //   826: lload_2
/*     */     //   827: lxor
/*     */     //   828: <illegal opcode> z : (IJ)Ljava/lang/String;
/*     */     //   833: invokevirtual startsWith : (Ljava/lang/String;)Z
/*     */     //   836: goto -> 849
/*     */     //   839: ldc2_w -869468156305965914
/*     */     //   842: lload_2
/*     */     //   843: <illegal opcode> w : (Ljava/lang/Throwable;JJ)Ljava/lang/Throwable;
/*     */     //   848: athrow
/*     */     //   849: ifeq -> 855
/*     */     //   852: goto -> 893
/*     */     //   855: new java/io/IOException
/*     */     //   858: dup
/*     */     //   859: new java/lang/StringBuilder
/*     */     //   862: dup
/*     */     //   863: invokespecial <init> : ()V
/*     */     //   866: sipush #29874
/*     */     //   869: ldc2_w 4563860134983537716
/*     */     //   872: lload_2
/*     */     //   873: lxor
/*     */     //   874: <illegal opcode> z : (IJ)Ljava/lang/String;
/*     */     //   879: invokevirtual append : (Ljava/lang/String;)Ljava/lang/StringBuilder;
/*     */     //   882: aload_1
/*     */     //   883: invokevirtual append : (Ljava/lang/String;)Ljava/lang/StringBuilder;
/*     */     //   886: invokevirtual toString : ()Ljava/lang/String;
/*     */     //   889: invokespecial <init> : (Ljava/lang/String;)V
/*     */     //   892: athrow
/*     */     //   893: return
/*     */     // Line number table:
/*     */     //   Java source line number -> byte code offset
/*     */     //   #257	-> 38
/*     */     //   #277	-> 48
/*     */     //   #48	-> 72
/*     */     //   #130	-> 120
/*     */     //   #251	-> 126
/*     */     //   #54	-> 136
/*     */     //   #214	-> 142
/*     */     //   #84	-> 150
/*     */     //   #256	-> 246
/*     */     //   #138	-> 256
/*     */     //   #108	-> 267
/*     */     //   #99	-> 277
/*     */     //   #1	-> 291
/*     */     //   #24	-> 314
/*     */     //   #104	-> 328
/*     */     //   #229	-> 340
/*     */     //   #278	-> 473
/*     */     //   #45	-> 511
/*     */     //   #90	-> 517
/*     */     //   #193	-> 523
/*     */     //   #284	-> 532
/*     */     //   #145	-> 689
/*     */     //   #298	-> 724
/*     */     //   #80	-> 855
/*     */     //   #89	-> 893
/*     */     // Exception table:
/*     */     //   from	to	target	type
/*     */     //   48	59	62	java/io/IOException
/*     */     //   56	110	110	java/io/IOException
/*     */     //   150	182	185	java/io/IOException
/*     */     //   163	201	204	java/io/IOException
/*     */     //   195	230	233	java/io/IOException
/*     */     //   243	257	257	java/io/IOException
/*     */     //   291	301	304	java/io/IOException
/*     */     //   340	351	354	java/io/IOException
/*     */     //   348	393	396	java/io/IOException
/*     */     //   364	409	412	java/io/IOException
/*     */     //   406	444	447	java/io/IOException
/*     */     //   422	460	463	java/io/IOException
/*     */     //   511	539	542	java/io/IOException
/*     */     //   553	561	564	java/io/IOException
/*     */     //   558	603	606	java/io/IOException
/*     */     //   574	619	622	java/io/IOException
/*     */     //   616	654	657	java/io/IOException
/*     */     //   632	676	679	java/io/IOException
/*     */     //   667	711	714	java/io/IOException
/*     */     //   689	726	729	java/io/IOException
/*     */     //   740	754	757	java/io/IOException
/*     */     //   751	774	777	java/io/IOException
/*     */     //   767	803	806	java/io/IOException
/*     */     //   816	836	839	java/io/IOException
/*     */   }
/*     */   
/*     */   public synchronized kW a(String paramString, long paramLong) {
/*     */     // Byte code:
/*     */     //   0: getstatic me/konsolas/aac/m5.H : J
/*     */     //   3: lload_2
/*     */     //   4: lxor
/*     */     //   5: lstore_2
/*     */     //   6: lload_2
/*     */     //   7: dup2
/*     */     //   8: ldc2_w 113472006341766
/*     */     //   11: lxor
/*     */     //   12: lstore #4
/*     */     //   14: dup2
/*     */     //   15: ldc2_w 20989130660520
/*     */     //   18: lxor
/*     */     //   19: lstore #6
/*     */     //   21: dup2
/*     */     //   22: ldc2_w 24104901709765
/*     */     //   25: lxor
/*     */     //   26: dup2
/*     */     //   27: bipush #48
/*     */     //   29: lushr
/*     */     //   30: l2i
/*     */     //   31: istore #8
/*     */     //   33: dup2
/*     */     //   34: bipush #16
/*     */     //   36: lshl
/*     */     //   37: bipush #16
/*     */     //   39: lushr
/*     */     //   40: lstore #9
/*     */     //   42: pop2
/*     */     //   43: dup2
/*     */     //   44: ldc2_w 138615448456147
/*     */     //   47: lxor
/*     */     //   48: lstore #11
/*     */     //   50: dup2
/*     */     //   51: ldc2_w 52002799435183
/*     */     //   54: lxor
/*     */     //   55: lstore #13
/*     */     //   57: dup2
/*     */     //   58: ldc2_w 49993893705606
/*     */     //   61: lxor
/*     */     //   62: lstore #15
/*     */     //   64: dup2
/*     */     //   65: ldc2_w 87934832763098
/*     */     //   68: lxor
/*     */     //   69: lstore #17
/*     */     //   71: pop2
/*     */     //   72: ldc2_w 4862209029035650077
/*     */     //   75: lload_2
/*     */     //   76: <illegal opcode> w : (JJ)[Ljava/lang/String;
/*     */     //   81: aload_0
/*     */     //   82: lload #13
/*     */     //   84: invokevirtual b : (J)V
/*     */     //   87: astore #19
/*     */     //   89: aload_0
/*     */     //   90: iload #8
/*     */     //   92: i2c
/*     */     //   93: lload #9
/*     */     //   95: invokespecial c : (CJ)V
/*     */     //   98: aload_0
/*     */     //   99: aload_1
/*     */     //   100: lload #4
/*     */     //   102: invokespecial b : (Ljava/lang/String;J)V
/*     */     //   105: aload_0
/*     */     //   106: getfield f : Ljava/util/LinkedHashMap;
/*     */     //   109: aload_1
/*     */     //   110: invokevirtual get : (Ljava/lang/Object;)Ljava/lang/Object;
/*     */     //   113: checkcast me/konsolas/aac/bT
/*     */     //   116: astore #20
/*     */     //   118: aload #20
/*     */     //   120: aload #19
/*     */     //   122: ifnonnull -> 143
/*     */     //   125: ifnull -> 167
/*     */     //   128: goto -> 141
/*     */     //   131: ldc2_w 4850752199160613912
/*     */     //   134: lload_2
/*     */     //   135: <illegal opcode> w : (Ljava/lang/Throwable;JJ)Ljava/lang/Throwable;
/*     */     //   140: athrow
/*     */     //   141: aload #20
/*     */     //   143: aload #19
/*     */     //   145: ifnonnull -> 181
/*     */     //   148: getfield d : Z
/*     */     //   151: ifne -> 179
/*     */     //   154: goto -> 167
/*     */     //   157: ldc2_w 4850752199160613912
/*     */     //   160: lload_2
/*     */     //   161: <illegal opcode> w : (Ljava/lang/Throwable;JJ)Ljava/lang/Throwable;
/*     */     //   166: athrow
/*     */     //   167: aconst_null
/*     */     //   168: areturn
/*     */     //   169: ldc2_w 4850752199160613912
/*     */     //   172: lload_2
/*     */     //   173: <illegal opcode> w : (Ljava/lang/Throwable;JJ)Ljava/lang/Throwable;
/*     */     //   178: athrow
/*     */     //   179: aload #20
/*     */     //   181: lload #6
/*     */     //   183: invokevirtual a : (J)Lme/konsolas/aac/kW;
/*     */     //   186: astore #21
/*     */     //   188: lload_2
/*     */     //   189: lconst_0
/*     */     //   190: lcmp
/*     */     //   191: iflt -> 290
/*     */     //   194: aload #19
/*     */     //   196: ifnonnull -> 290
/*     */     //   199: aload #21
/*     */     //   201: ifnonnull -> 229
/*     */     //   204: goto -> 217
/*     */     //   207: ldc2_w 4850752199160613912
/*     */     //   210: lload_2
/*     */     //   211: <illegal opcode> w : (Ljava/lang/Throwable;JJ)Ljava/lang/Throwable;
/*     */     //   216: athrow
/*     */     //   217: aconst_null
/*     */     //   218: areturn
/*     */     //   219: ldc2_w 4850752199160613912
/*     */     //   222: lload_2
/*     */     //   223: <illegal opcode> w : (Ljava/lang/Throwable;JJ)Ljava/lang/Throwable;
/*     */     //   228: athrow
/*     */     //   229: aload_0
/*     */     //   230: dup
/*     */     //   231: getfield k : I
/*     */     //   234: iconst_1
/*     */     //   235: iadd
/*     */     //   236: putfield k : I
/*     */     //   239: aload_0
/*     */     //   240: getfield D : Lme/konsolas/aac/gi;
/*     */     //   243: sipush #19698
/*     */     //   246: ldc2_w 6852891096710028509
/*     */     //   249: lload_2
/*     */     //   250: lxor
/*     */     //   251: <illegal opcode> z : (IJ)Ljava/lang/String;
/*     */     //   256: lload #17
/*     */     //   258: invokeinterface a : (Ljava/lang/String;J)Lme/konsolas/aac/gi;
/*     */     //   263: bipush #32
/*     */     //   265: lload #11
/*     */     //   267: invokeinterface d : (IJ)Lme/konsolas/aac/gi;
/*     */     //   272: aload_1
/*     */     //   273: lload #17
/*     */     //   275: invokeinterface a : (Ljava/lang/String;J)Lme/konsolas/aac/gi;
/*     */     //   280: bipush #10
/*     */     //   282: lload #11
/*     */     //   284: invokeinterface d : (IJ)Lme/konsolas/aac/gi;
/*     */     //   289: pop
/*     */     //   290: aload_0
/*     */     //   291: aload #19
/*     */     //   293: ifnonnull -> 331
/*     */     //   296: lload #15
/*     */     //   298: invokevirtual b : (J)Z
/*     */     //   301: ifeq -> 343
/*     */     //   304: goto -> 317
/*     */     //   307: ldc2_w 4850752199160613912
/*     */     //   310: lload_2
/*     */     //   311: <illegal opcode> w : (Ljava/lang/Throwable;JJ)Ljava/lang/Throwable;
/*     */     //   316: athrow
/*     */     //   317: aload_0
/*     */     //   318: goto -> 331
/*     */     //   321: ldc2_w 4850752199160613912
/*     */     //   324: lload_2
/*     */     //   325: <illegal opcode> w : (Ljava/lang/Throwable;JJ)Ljava/lang/Throwable;
/*     */     //   330: athrow
/*     */     //   331: getfield u : Ljava/util/concurrent/Executor;
/*     */     //   334: aload_0
/*     */     //   335: getfield l : Ljava/lang/Runnable;
/*     */     //   338: invokeinterface execute : (Ljava/lang/Runnable;)V
/*     */     //   343: aload #21
/*     */     //   345: areturn
/*     */     // Line number table:
/*     */     //   Java source line number -> byte code offset
/*     */     //   #263	-> 81
/*     */     //   #224	-> 89
/*     */     //   #32	-> 98
/*     */     //   #143	-> 105
/*     */     //   #100	-> 118
/*     */     //   #201	-> 179
/*     */     //   #211	-> 188
/*     */     //   #291	-> 229
/*     */     //   #176	-> 239
/*     */     //   #158	-> 290
/*     */     //   #94	-> 317
/*     */     //   #170	-> 343
/*     */     // Exception table:
/*     */     //   from	to	target	type
/*     */     //   118	128	131	java/io/IOException
/*     */     //   143	154	157	java/io/IOException
/*     */     //   148	169	169	java/io/IOException
/*     */     //   188	204	207	java/io/IOException
/*     */     //   199	219	219	java/io/IOException
/*     */     //   290	304	307	java/io/IOException
/*     */     //   296	318	321	java/io/IOException
/*     */   }
/*     */   
/*     */   private gi a(long paramLong) {
/* 266 */     paramLong = H ^ paramLong; long l1 = paramLong ^ 0x7AA8B415DCC2L, l2 = paramLong ^ 0xC0039880D71L, l3 = paramLong ^ 0x16DC404AE924L; gp gp = this.h.b(l3, this.A);
/*     */     l4 l4 = new l4(this, l1, gp);
/*     */     return ds.a(l4, l2);
/*     */   }
/*     */ 
/*     */ 
/*     */ 
/*     */ 
/*     */ 
/*     */ 
/*     */ 
/*     */ 
/*     */ 
/*     */ 
/*     */ 
/*     */ 
/*     */ 
/*     */ 
/*     */ 
/*     */ 
/*     */ 
/*     */ 
/*     */ 
/*     */ 
/*     */ 
/*     */ 
/*     */ 
/*     */ 
/*     */   
/*     */   @Nullable
/*     */   public dO a(long paramLong, String paramString) {
/* 297 */     paramLong = H ^ paramLong; long l = paramLong ^ 0x275BF3378731L; return a(paramString, -1L, l);
/*     */   }
/*     */   
/*     */   static {
/*     */     // Byte code:
/*     */     //   0: ldc_w '睜璦'
/*     */     //   3: invokevirtual toCharArray : ()[C
/*     */     //   6: dup
/*     */     //   7: dup
/*     */     //   8: iconst_0
/*     */     //   9: dup_x1
/*     */     //   10: caload
/*     */     //   11: sipush #13437
/*     */     //   14: ixor
/*     */     //   15: i2c
/*     */     //   16: castore
/*     */     //   17: sipush #22984
/*     */     //   20: iconst_0
/*     */     //   21: iconst_4
/*     */     //   22: invokestatic G : (Ljava/lang/Object;SZB)Ljava/lang/String;
/*     */     //   25: invokevirtual intern : ()Ljava/lang/String;
/*     */     //   28: putstatic me/konsolas/aac/m5.a : Ljava/lang/String;
/*     */     //   31: ldc2_w -5230646787658133404
/*     */     //   34: ldc2_w 4837546147333391634
/*     */     //   37: invokestatic lookup : ()Ljava/lang/invoke/MethodHandles$Lookup;
/*     */     //   40: invokevirtual lookupClass : ()Ljava/lang/Class;
/*     */     //   43: invokestatic a : (JJLjava/lang/Object;)Lme/konsolas/aac/na;
/*     */     //   46: ldc2_w 248993394101856
/*     */     //   49: invokeinterface a : (J)J
/*     */     //   54: putstatic me/konsolas/aac/m5.H : J
/*     */     //   57: getstatic me/konsolas/aac/m5.H : J
/*     */     //   60: ldc2_w 124655432493633
/*     */     //   63: lxor
/*     */     //   64: lstore #9
/*     */     //   66: aconst_null
/*     */     //   67: new java/util/HashMap
/*     */     //   70: dup
/*     */     //   71: bipush #13
/*     */     //   73: invokespecial <init> : (I)V
/*     */     //   76: putstatic me/konsolas/aac/m5.K : Ljava/util/Map;
/*     */     //   79: ldc2_w 4278921697784301839
/*     */     //   82: lload #9
/*     */     //   84: <illegal opcode> w : ([Ljava/lang/String;JJ)V
/*     */     //   89: ldc_w '䝡ɗ⩝쏋戥澕F᫦欤ꅲ诌誩鶛⭖㴬ྔ쏟稏ⓢ'
/*     */     //   92: invokevirtual toCharArray : ()[C
/*     */     //   95: dup
/*     */     //   96: dup
/*     */     //   97: bipush #6
/*     */     //   99: dup_x1
/*     */     //   100: caload
/*     */     //   101: sipush #28418
/*     */     //   104: ixor
/*     */     //   105: i2c
/*     */     //   106: castore
/*     */     //   107: sipush #27463
/*     */     //   110: iconst_0
/*     */     //   111: iconst_1
/*     */     //   112: invokestatic G : (Ljava/lang/Object;SZB)Ljava/lang/String;
/*     */     //   115: invokestatic getInstance : (Ljava/lang/String;)Ljavax/crypto/Cipher;
/*     */     //   118: dup
/*     */     //   119: astore_0
/*     */     //   120: iconst_2
/*     */     //   121: ldc_w '骜꤁꒡㭢'
/*     */     //   124: invokevirtual toCharArray : ()[C
/*     */     //   127: dup
/*     */     //   128: dup
/*     */     //   129: iconst_0
/*     */     //   130: dup_x1
/*     */     //   131: caload
/*     */     //   132: sipush #24816
/*     */     //   135: ixor
/*     */     //   136: i2c
/*     */     //   137: castore
/*     */     //   138: sipush #18390
/*     */     //   141: iconst_0
/*     */     //   142: iconst_4
/*     */     //   143: invokestatic G : (Ljava/lang/Object;SZB)Ljava/lang/String;
/*     */     //   146: invokestatic getInstance : (Ljava/lang/String;)Ljavax/crypto/SecretKeyFactory;
/*     */     //   149: bipush #8
/*     */     //   151: newarray byte
/*     */     //   153: dup
/*     */     //   154: iconst_0
/*     */     //   155: lload #9
/*     */     //   157: bipush #56
/*     */     //   159: lushr
/*     */     //   160: l2i
/*     */     //   161: i2b
/*     */     //   162: bastore
/*     */     //   163: iconst_1
/*     */     //   164: istore_1
/*     */     //   165: iload_1
/*     */     //   166: bipush #8
/*     */     //   168: if_icmpge -> 192
/*     */     //   171: dup
/*     */     //   172: iload_1
/*     */     //   173: lload #9
/*     */     //   175: iload_1
/*     */     //   176: bipush #8
/*     */     //   178: imul
/*     */     //   179: lshl
/*     */     //   180: bipush #56
/*     */     //   182: lushr
/*     */     //   183: l2i
/*     */     //   184: i2b
/*     */     //   185: bastore
/*     */     //   186: iinc #1, 1
/*     */     //   189: goto -> 165
/*     */     //   192: new javax/crypto/spec/DESKeySpec
/*     */     //   195: dup_x1
/*     */     //   196: swap
/*     */     //   197: invokespecial <init> : ([B)V
/*     */     //   200: invokevirtual generateSecret : (Ljava/security/spec/KeySpec;)Ljavax/crypto/SecretKey;
/*     */     //   203: new javax/crypto/spec/IvParameterSpec
/*     */     //   206: dup
/*     */     //   207: bipush #8
/*     */     //   209: newarray byte
/*     */     //   211: invokespecial <init> : ([B)V
/*     */     //   214: invokevirtual init : (ILjava/security/Key;Ljava/security/spec/AlgorithmParameterSpec;)V
/*     */     //   217: bipush #36
/*     */     //   219: anewarray java/lang/String
/*     */     //   222: astore #7
/*     */     //   224: iconst_0
/*     */     //   225: istore #5
/*     */     //   227: ldc_w '﫿뽒綯緌瘏䶼萭䍏଻쨐灧탇䜈㈓宜镫쥩嗩뿶⵽ⲩ䧪꒾ᬋ喳骽昽沝ꆂ綔㱙栛峃䓡좶϶뉣⻲꿒嚈봘▄䋩ｱ⯩ໂ?钲礿᫙䔊䑧㗗?歝ﯦᙺ瀞轣̬ꧢ옩?⧕잌췕⯇쭰憩⟌㜏␠㪗铑銎㕉㿡๻ϕ嬥谧卮ꑝ跻帶ᔃ腇엱㛺℈詃솳㢣昏嶯嶋ድ岺ẫᢁ?贻ἰ툴覉쎆蹉᪭쎕版쬠複괠晴ㅞᇲ짂⡺ି磊둏ⅷ㝉꽢堕ᬫЇ?中佭⎭瀺ᦤ燇ꝙ犏뒌᳾癚ၑ鏴흩走쨧ꔴ袘ⰲ爧쐍㫜䶗穀᜾寰ण䏄㧖켢鏰⇿騮㯥䄜ᜡ?ﭷꄥ來袞ট릳?ҽ䦎縑퉽ߚ灎?뉘惂㔍씎⛼ᗵㆸ䥢墠袑鏙整ᥱ蒅뿼༣ὂೌ?㍳祟ઘ萣⌂뫭颴骄夒⯣?ⓕ┋엃ø좗ᆉը龭ᛸୠ왼蔚㎚Ḕ曶᫱㼂삳櫋궓︬坷?ⓔ逅襥孳赽?伹鷄각奘ﹷࢧﺸኍ஁?뎾篁饋瓮ӵ䆣림沑䶴ꧫ鶤䄒贯폩쐷뽶앪৽䢴ᢓশ뤒뾸楙킣Ꮲ⩥វ띅잂畔驐ῆ碾䦼핿ﹰ㽸჉࿚脎蕅柪﫵芢뗏厷䩠솜잰?屛쐲ᡅ⚾淙뿾쏄塆ࠔ爛㮍䓦ᶷ᛺㝶꨹畁矐兔붗䖵䐹悀肝⩍⍗湗봑鑃⸁뢦療攁䯠숮몤ϳ荜鉙䜤䨳ť슨⌋듀牂懣㐔䧄杛㦠ް핽䙐럀탂龍ݴ鳩筮岝꠬줙戣䝯ڠᖸ髳아ᤃ↦᾿뮧偽⡙这帜閉兪⸘읹䜊㞵䶍誒뷚꽝䯩쨤☚됱饵鄈핶バ走뽝˺䱪뽢ᠪ躌ὤઅ㋐驝츤릁?뚏?嫱峮譔?㄃᠅꠼䕦潶䳪㵆故銗Ꮻ臼遹䵳໲璔鹐ϱ釡艞?볼嶟㣄⏌汊冟캝念஺檠䇊㈿鷍펾烳嘱믥騼ﬤ?횥㽸㥧钵鄑㸘㿯ߞ㷶ᓍ髆?╏ϛ袍鵼⛂ሣ㩟ᾸⳠꩨ읾䴱肄휣았㑬ॳ⽇䤚혗䕒끭⬱崢随炄椙歷鐍䍁ᓺ࢜쏨噏ﾷ?꿬鰧鋛㭿寷?⯲芺ᛊ☑폅ퟅᔕ␳⺍ōᎀᙲ焫된寚섐䣚䩂킜듹쩹ꗲⰎ坷뭛틅藡렎⌗璻媆쟗齿鄆Ꚗ탛誽⻲☡鬸맀ᥰ䈒畬服槒ﰻꫤ깜綁徥⍮丟ﾵꌜ滖჏ᵥ⛐ݘ값䖜䒪愵ֻ⧀⩭毭ౝ᧔恭ۧỜ뷛侃Ⴌ䒎鱛ꪌ銼걹য⢎좻⦦ཉ宭ꙶꆌ㓇胨嚀鶸芽멭伭⅏ᖽ㡴㵣냥拨騅??怖猻埅晘ꆋ⬀老⾽샅❷닫룶譩ᰢ쒕눚웵娜篲ﶾ᫃蠩）颪㺳捂㹭뵓疰ᙩᭃ刧웱옹ᗖ绷駿ᩮ抅抁戯쎚⍙Ḯ踧蓋է壘ஞএ홃悧ｔ鴂䙐⇬瑀덆჋膲愧﨔༘⯭儻ᷞ⋿룻띚㚭媥뤮⒖쉾늍脞ᙼ➇圲됡ぃ祁銀漡᜞噠⎘痯믔趣휇薕Ấ梽⿪妭࿙蛼ḳ娒빖溟놯嬵枷汮䧪㙼堉쒍䨵嗻ⴄ皪귴䶾Ự鄨뿼沥꛳᳨谌צ齕秽둤奯믜农䠻汁㇝烄˹櫁퓹㸁ʧ诼ఱ瑹➶顥⇡ᦷ᳒吚Ⓟ擣鷬⤁⏲꫓獀?䌦﵋预ౡ叶ᰆ硳腅㭓ꦓ춋ഭ캊秼ǐ椟䔂芛台㻰哄砗伋썪哻ヨ䍇ﻩ⃉聊⬄韝숝ꬬᣕҷ滎銧팚ズ뚋ㅰᳱ댷鐶讎헤⻦苰躵㐓ɿ䇟覱⛍弓섯䀁䏥诣诮錄덜훧㲼?ҷꌿ斌쇾㔘本⚜Ⳋ霰墬䥃᪘嗼掲ɷ䮜沤쯟⸀ᠡ昍?䡒幼枠㜈૝냁⛊櫒렟ގ쥗俼‷ᵯᶂ⬻흺區ፁﳟ盾긲哈玳뢘䭜ᰃ敟께㎺쁣迡ﳀ绪ಫ苊꽢䂝뒢驗犰ꤗ겾ᆎ籖౼榚턎緧䨶륐ﭰꅆ铿窂塞葱▾ₜ뮚煸㕞䟣隱헨㕣틑氢ㆂŚ䤩ꈱ䏽ﯡ縅讝⹖襽쭛ὲ㿘尬묂矿䏕堒碆퐡⅀ᱟ'
/*     */     //   230: invokevirtual toCharArray : ()[C
/*     */     //   233: dup
/*     */     //   234: dup
/*     */     //   235: sipush #715
/*     */     //   238: dup_x1
/*     */     //   239: caload
/*     */     //   240: sipush #6919
/*     */     //   243: ixor
/*     */     //   244: i2c
/*     */     //   245: castore
/*     */     //   246: sipush #23295
/*     */     //   249: iconst_1
/*     */     //   250: iconst_4
/*     */     //   251: invokestatic G : (Ljava/lang/Object;SZB)Ljava/lang/String;
/*     */     //   254: dup
/*     */     //   255: astore #4
/*     */     //   257: invokevirtual length : ()I
/*     */     //   260: istore #6
/*     */     //   262: bipush #16
/*     */     //   264: istore_3
/*     */     //   265: iconst_m1
/*     */     //   266: istore_2
/*     */     //   267: iinc #2, 1
/*     */     //   270: aload #4
/*     */     //   272: iload_2
/*     */     //   273: dup
/*     */     //   274: iload_3
/*     */     //   275: iadd
/*     */     //   276: invokevirtual substring : (II)Ljava/lang/String;
/*     */     //   279: iconst_m1
/*     */     //   280: goto -> 550
/*     */     //   283: aload #7
/*     */     //   285: swap
/*     */     //   286: iload #5
/*     */     //   288: iinc #5, 1
/*     */     //   291: swap
/*     */     //   292: aastore
/*     */     //   293: iload_2
/*     */     //   294: iload_3
/*     */     //   295: iadd
/*     */     //   296: dup
/*     */     //   297: istore_2
/*     */     //   298: iload #6
/*     */     //   300: if_icmpge -> 313
/*     */     //   303: aload #4
/*     */     //   305: iload_2
/*     */     //   306: invokevirtual charAt : (I)C
/*     */     //   309: istore_3
/*     */     //   310: goto -> 267
/*     */     //   313: ldc_w '⦅꫇揻縖䟯騇⟉镲䀊놬佛媥㷨ᝤ몜옏맚喹逼ࠒ᜿焐理੘突첖븛ী䌉摧ð뀖ഥꆭિ䛳'
/*     */     //   316: invokevirtual toCharArray : ()[C
/*     */     //   319: dup
/*     */     //   320: dup
/*     */     //   321: bipush #27
/*     */     //   323: dup_x1
/*     */     //   324: caload
/*     */     //   325: sipush #23757
/*     */     //   328: ixor
/*     */     //   329: i2c
/*     */     //   330: castore
/*     */     //   331: sipush #20422
/*     */     //   334: iconst_1
/*     */     //   335: iconst_5
/*     */     //   336: invokestatic G : (Ljava/lang/Object;SZB)Ljava/lang/String;
/*     */     //   339: dup
/*     */     //   340: astore #4
/*     */     //   342: invokevirtual length : ()I
/*     */     //   345: istore #6
/*     */     //   347: bipush #24
/*     */     //   349: istore_3
/*     */     //   350: iconst_m1
/*     */     //   351: istore_2
/*     */     //   352: iinc #2, 1
/*     */     //   355: aload #4
/*     */     //   357: iload_2
/*     */     //   358: dup
/*     */     //   359: iload_3
/*     */     //   360: iadd
/*     */     //   361: invokevirtual substring : (II)Ljava/lang/String;
/*     */     //   364: iconst_0
/*     */     //   365: goto -> 550
/*     */     //   368: aload #7
/*     */     //   370: swap
/*     */     //   371: iload #5
/*     */     //   373: iinc #5, 1
/*     */     //   376: swap
/*     */     //   377: aastore
/*     */     //   378: iload_2
/*     */     //   379: iload_3
/*     */     //   380: iadd
/*     */     //   381: dup
/*     */     //   382: istore_2
/*     */     //   383: iload #6
/*     */     //   385: if_icmpge -> 398
/*     */     //   388: aload #4
/*     */     //   390: iload_2
/*     */     //   391: invokevirtual charAt : (I)C
/*     */     //   394: istore_3
/*     */     //   395: goto -> 352
/*     */     //   398: aload #7
/*     */     //   400: putstatic me/konsolas/aac/m5.I : [Ljava/lang/String;
/*     */     //   403: bipush #36
/*     */     //   405: anewarray java/lang/String
/*     */     //   408: putstatic me/konsolas/aac/m5.J : [Ljava/lang/String;
/*     */     //   411: sipush #25463
/*     */     //   414: ldc2_w 8895096773285563377
/*     */     //   417: lload #9
/*     */     //   419: lxor
/*     */     //   420: <illegal opcode> z : (IJ)Ljava/lang/String;
/*     */     //   425: putstatic me/konsolas/aac/m5.c : Ljava/lang/String;
/*     */     //   428: sipush #28154
/*     */     //   431: ldc2_w 1090976020270335341
/*     */     //   434: lload #9
/*     */     //   436: lxor
/*     */     //   437: <illegal opcode> z : (IJ)Ljava/lang/String;
/*     */     //   442: putstatic me/konsolas/aac/m5.y : Ljava/lang/String;
/*     */     //   445: sipush #5235
/*     */     //   448: ldc2_w 4231031212188908781
/*     */     //   451: lload #9
/*     */     //   453: lxor
/*     */     //   454: <illegal opcode> z : (IJ)Ljava/lang/String;
/*     */     //   459: putstatic me/konsolas/aac/m5.n : Ljava/lang/String;
/*     */     //   462: sipush #14610
/*     */     //   465: ldc2_w 2832444278236778889
/*     */     //   468: lload #9
/*     */     //   470: lxor
/*     */     //   471: <illegal opcode> z : (IJ)Ljava/lang/String;
/*     */     //   476: putstatic me/konsolas/aac/m5.j : Ljava/lang/String;
/*     */     //   479: sipush #16344
/*     */     //   482: ldc2_w 4374509698932250443
/*     */     //   485: lload #9
/*     */     //   487: lxor
/*     */     //   488: <illegal opcode> z : (IJ)Ljava/lang/String;
/*     */     //   493: putstatic me/konsolas/aac/m5.g : Ljava/lang/String;
/*     */     //   496: sipush #29468
/*     */     //   499: ldc2_w 7784449634413337486
/*     */     //   502: lload #9
/*     */     //   504: lxor
/*     */     //   505: <illegal opcode> z : (IJ)Ljava/lang/String;
/*     */     //   510: putstatic me/konsolas/aac/m5.F : Ljava/lang/String;
/*     */     //   513: sipush #18994
/*     */     //   516: ldc2_w 389906327194297005
/*     */     //   519: lload #9
/*     */     //   521: lxor
/*     */     //   522: <illegal opcode> z : (IJ)Ljava/lang/String;
/*     */     //   527: putstatic me/konsolas/aac/m5.v : Ljava/lang/String;
/*     */     //   530: sipush #1053
/*     */     //   533: ldc2_w 6289455404293827733
/*     */     //   536: lload #9
/*     */     //   538: lxor
/*     */     //   539: <illegal opcode> z : (IJ)Ljava/lang/String;
/*     */     //   544: putstatic me/konsolas/aac/m5.o : Ljava/lang/String;
/*     */     //   547: goto -> 612
/*     */     //   550: swap
/*     */     //   551: ldc_w '횮冞䳟ὓ蠒᭄訮沎஺'
/*     */     //   554: invokevirtual toCharArray : ()[C
/*     */     //   557: dup
/*     */     //   558: dup
/*     */     //   559: iconst_4
/*     */     //   560: dup_x1
/*     */     //   561: caload
/*     */     //   562: sipush #1175
/*     */     //   565: ixor
/*     */     //   566: i2c
/*     */     //   567: castore
/*     */     //   568: sipush #20970
/*     */     //   571: iconst_1
/*     */     //   572: iconst_2
/*     */     //   573: invokestatic G : (Ljava/lang/Object;SZB)Ljava/lang/String;
/*     */     //   576: invokevirtual getBytes : (Ljava/lang/String;)[B
/*     */     //   579: aload_0
/*     */     //   580: swap
/*     */     //   581: invokevirtual doFinal : ([B)[B
/*     */     //   584: astore #8
/*     */     //   586: aload #8
/*     */     //   588: invokestatic a : ([B)Ljava/lang/String;
/*     */     //   591: invokevirtual intern : ()Ljava/lang/String;
/*     */     //   594: swap
/*     */     //   595: tableswitch default -> 283, 0 -> 368
/*     */     //   612: ldc me/konsolas/aac/m5
/*     */     //   614: invokevirtual desiredAssertionStatus : ()Z
/*     */     //   617: ifne -> 635
/*     */     //   620: iconst_1
/*     */     //   621: goto -> 636
/*     */     //   624: ldc2_w 4316719788066124961
/*     */     //   627: lload #9
/*     */     //   629: <illegal opcode> w : (Ljava/lang/Throwable;JJ)Ljava/lang/Throwable;
/*     */     //   634: athrow
/*     */     //   635: iconst_0
/*     */     //   636: putstatic me/konsolas/aac/m5.p : Z
/*     */     //   639: sipush #24826
/*     */     //   642: ldc2_w 8690264200395311210
/*     */     //   645: lload #9
/*     */     //   647: lxor
/*     */     //   648: <illegal opcode> z : (IJ)Ljava/lang/String;
/*     */     //   653: invokestatic compile : (Ljava/lang/String;)Ljava/util/regex/Pattern;
/*     */     //   656: putstatic me/konsolas/aac/m5.t : Ljava/util/regex/Pattern;
/*     */     //   659: return
/*     */     // Line number table:
/*     */     //   Java source line number -> byte code offset
/*     */     //   #85	-> 612
/*     */     //   #3	-> 648
/*     */     // Exception table:
/*     */     //   from	to	target	type
/*     */     //   612	624	624	java/lang/IllegalArgumentException
/*     */   }
/*     */   
/*     */   public static void b(String[] paramArrayOfString) {
/*     */     B = paramArrayOfString;
/*     */   }
/*     */   
/*     */   public static String[] b() {
/*     */     return B;
/*     */   }
/*     */   
/*     */   private static Throwable a(Throwable paramThrowable) {
/*     */     return paramThrowable;
/*     */   }
/*     */   
/*     */   private static String a(byte[] paramArrayOfbyte) {
/*     */     byte b1 = 0;
/*     */     int i;
/*     */     char[] arrayOfChar = new char[i = paramArrayOfbyte.length];
/*     */     for (byte b2 = 0; b2 < i; b2++) {
/*     */       int j;
/*     */       if ((j = 0xFF & paramArrayOfbyte[b2]) < 192) {
/*     */         arrayOfChar[b1++] = (char)j;
/*     */       } else if (j < 224) {
/*     */         char c = (char)((char)(j & 0x1F) << 6);
/*     */         j = paramArrayOfbyte[++b2];
/*     */         c = (char)(c | (char)(j & 0x3F));
/*     */         arrayOfChar[b1++] = c;
/*     */       } else if (b2 < i - 2) {
/*     */         char c = (char)((char)(j & 0xF) << 12);
/*     */         j = paramArrayOfbyte[++b2];
/*     */         c = (char)(c | (char)(j & 0x3F) << 6);
/*     */         j = paramArrayOfbyte[++b2];
/*     */         c = (char)(c | (char)(j & 0x3F));
/*     */         arrayOfChar[b1++] = c;
/*     */       } 
/*     */     } 
/*     */     return new String(arrayOfChar, 0, b1);
/*     */   }
/*     */   
/*     */   private static String a(int paramInt, long paramLong) {
/*     */     int i = paramInt ^ (int)(paramLong & 0x7FFFL) ^ 0x12D3;
/*     */     if (J[i] == null) {
/*     */       Object[] arrayOfObject;
/*     */       try {
/*     */         Long long_ = Long.valueOf(Thread.currentThread().getId());
/*     */         arrayOfObject = (Object[])K.get(long_);
/*     */         if (arrayOfObject == null) {
/*     */           arrayOfObject = new Object[3];
/*     */           "⤗?桒ι㩏튛쵸詧ລ馻㞑묊讫鲉콄漡".toCharArray()[3] = (char)("⤗?桒ι㩏튛쵸詧ລ馻㞑묊讫鲉콄漡".toCharArray()[3] ^ 0x3A06);
/*     */           arrayOfObject[0] = Cipher.getInstance(fW$gy.A("⤗?桒ι㩏튛쵸詧ລ馻㞑묊讫鲉콄漡".toCharArray(), (short)26327, false, 5));
/*     */           "歼ᶱሱၸ".toCharArray()[2] = (char)("歼ᶱሱၸ".toCharArray()[2] ^ 0x7D34);
/*     */           arrayOfObject[1] = SecretKeyFactory.getInstance(fW$gy.A("歼ᶱሱၸ".toCharArray(), (short)3022, true, 1));
/*     */           arrayOfObject[2] = new IvParameterSpec(new byte[8]);
/*     */           K.put(long_, arrayOfObject);
/*     */         } 
/*     */       } catch (Exception exception) {
/*     */         "⑽辏蛰স⌬ﰝ☌毰辯疵ꝶ蔗㩎?ḁ㕕".toCharArray()[0] = (char)("⑽辏蛰স⌬ﰝ☌毰辯疵ꝶ蔗㩎?ḁ㕕".toCharArray()[0] ^ 0x3616);
/*     */         throw new RuntimeException(fW$gy.A("⑽辏蛰স⌬ﰝ☌毰辯疵ꝶ蔗㩎?ḁ㕕".toCharArray(), (short)4214, false, 1), exception);
/*     */       } 
/*     */       byte[] arrayOfByte1 = new byte[8];
/*     */       arrayOfByte1[0] = (byte)(int)(paramLong >>> 56L);
/*     */       for (byte b = 1; b < 8; b++)
/*     */         arrayOfByte1[b] = (byte)(int)(paramLong << b * 8 >>> 56L); 
/*     */       DESKeySpec dESKeySpec = new DESKeySpec(arrayOfByte1);
/*     */       SecretKey secretKey = ((SecretKeyFactory)arrayOfObject[1]).generateSecret(dESKeySpec);
/*     */       ((Cipher)arrayOfObject[0]).init(2, secretKey, (IvParameterSpec)arrayOfObject[2]);
/*     */       "⮉鈁ｳ젘᜼笟础히愸㻓Ⅴ".toCharArray()[7] = (char)("⮉鈁ｳ젘᜼笟础히愸㻓Ⅴ".toCharArray()[7] ^ 0x3CC1);
/*     */       byte[] arrayOfByte2 = I[i].getBytes(fW$gy.A("⮉鈁ｳ젘᜼笟础히愸㻓Ⅴ".toCharArray(), (short)17643, false, 5));
/*     */       J[i] = a(((Cipher)arrayOfObject[0]).doFinal(arrayOfByte2));
/*     */     } 
/*     */     return J[i];
/*     */   }
/*     */   
/*     */   private static Object a(MethodHandles.Lookup paramLookup, MutableCallSite paramMutableCallSite, String paramString, Object[] paramArrayOfObject) {
/*     */     int i = ((Integer)paramArrayOfObject[0]).intValue();
/*     */     long l = ((Long)paramArrayOfObject[1]).longValue();
/*     */     String str = a(i, l);
/*     */     MethodHandle methodHandle = MethodHandles.constant(String.class, str);
/*     */     paramMutableCallSite.setTarget(MethodHandles.dropArguments(methodHandle, 0, new Class[] { int.class, long.class }));
/*     */     return str;
/*     */   }
/*     */   
/*     */   private static CallSite a(MethodHandles.Lookup paramLookup, String paramString, MethodType paramMethodType) {
/*     */     // Byte code:
/*     */     //   0: new java/lang/invoke/MutableCallSite
/*     */     //   3: dup
/*     */     //   4: aload_2
/*     */     //   5: invokespecial <init> : (Ljava/lang/invoke/MethodType;)V
/*     */     //   8: astore_3
/*     */     //   9: aload_3
/*     */     //   10: ldc_w
/*     */     //   13: ldc_w [Ljava/lang/Object;
/*     */     //   16: aload_2
/*     */     //   17: invokevirtual parameterCount : ()I
/*     */     //   20: invokevirtual asCollector : (Ljava/lang/Class;I)Ljava/lang/invoke/MethodHandle;
/*     */     //   23: iconst_0
/*     */     //   24: iconst_3
/*     */     //   25: anewarray java/lang/Object
/*     */     //   28: dup
/*     */     //   29: iconst_0
/*     */     //   30: aload_0
/*     */     //   31: aastore
/*     */     //   32: dup
/*     */     //   33: iconst_1
/*     */     //   34: aload_3
/*     */     //   35: aastore
/*     */     //   36: dup
/*     */     //   37: iconst_2
/*     */     //   38: aload_1
/*     */     //   39: aastore
/*     */     //   40: invokestatic insertArguments : (Ljava/lang/invoke/MethodHandle;I[Ljava/lang/Object;)Ljava/lang/invoke/MethodHandle;
/*     */     //   43: aload_2
/*     */     //   44: invokestatic explicitCastArguments : (Ljava/lang/invoke/MethodHandle;Ljava/lang/invoke/MethodType;)Ljava/lang/invoke/MethodHandle;
/*     */     //   47: invokevirtual setTarget : (Ljava/lang/invoke/MethodHandle;)V
/*     */     //   50: goto -> 170
/*     */     //   53: astore #4
/*     */     //   55: new java/lang/RuntimeException
/*     */     //   58: dup
/*     */     //   59: new java/lang/StringBuilder
/*     */     //   62: dup
/*     */     //   63: invokespecial <init> : ()V
/*     */     //   66: ldc_w '懥㮈ᢏ诂끼㎒Ａ荢녢Ᏸ禪冊섮☡᛾ਵ'
/*     */     //   69: invokevirtual toCharArray : ()[C
/*     */     //   72: dup
/*     */     //   73: dup
/*     */     //   74: iconst_4
/*     */     //   75: dup_x1
/*     */     //   76: caload
/*     */     //   77: sipush #28667
/*     */     //   80: ixor
/*     */     //   81: i2c
/*     */     //   82: castore
/*     */     //   83: sipush #25985
/*     */     //   86: iconst_0
/*     */     //   87: iconst_4
/*     */     //   88: invokestatic G : (Ljava/lang/Object;SZB)Ljava/lang/String;
/*     */     //   91: invokevirtual append : (Ljava/lang/String;)Ljava/lang/StringBuilder;
/*     */     //   94: ldc_w '鞉澶㲊㘆'
/*     */     //   97: invokevirtual toCharArray : ()[C
/*     */     //   100: dup
/*     */     //   101: dup
/*     */     //   102: iconst_0
/*     */     //   103: dup_x1
/*     */     //   104: caload
/*     */     //   105: sipush #6585
/*     */     //   108: ixor
/*     */     //   109: i2c
/*     */     //   110: castore
/*     */     //   111: sipush #15240
/*     */     //   114: iconst_1
/*     */     //   115: iconst_5
/*     */     //   116: invokestatic G : (Ljava/lang/Object;SZB)Ljava/lang/String;
/*     */     //   119: invokevirtual append : (Ljava/lang/String;)Ljava/lang/StringBuilder;
/*     */     //   122: aload_1
/*     */     //   123: invokevirtual append : (Ljava/lang/String;)Ljava/lang/StringBuilder;
/*     */     //   126: ldc_w 'Ꞝ셼?⎐'
/*     */     //   129: invokevirtual toCharArray : ()[C
/*     */     //   132: dup
/*     */     //   133: dup
/*     */     //   134: iconst_0
/*     */     //   135: dup_x1
/*     */     //   136: caload
/*     */     //   137: sipush #22963
/*     */     //   140: ixor
/*     */     //   141: i2c
/*     */     //   142: castore
/*     */     //   143: sipush #18748
/*     */     //   146: iconst_0
/*     */     //   147: iconst_2
/*     */     //   148: invokestatic G : (Ljava/lang/Object;SZB)Ljava/lang/String;
/*     */     //   151: invokevirtual append : (Ljava/lang/String;)Ljava/lang/StringBuilder;
/*     */     //   154: aload_2
/*     */     //   155: invokevirtual toString : ()Ljava/lang/String;
/*     */     //   158: invokevirtual append : (Ljava/lang/String;)Ljava/lang/StringBuilder;
/*     */     //   161: invokevirtual toString : ()Ljava/lang/String;
/*     */     //   164: aload #4
/*     */     //   166: invokespecial <init> : (Ljava/lang/String;Ljava/lang/Throwable;)V
/*     */     //   169: athrow
/*     */     //   170: aload_3
/*     */     //   171: areturn
/*     */     // Exception table:
/*     */     //   from	to	target	type
/*     */     //   9	50	53	java/lang/Exception
/*     */   }
/*     */ }


/* Location:              C:\Users\BukkitBypass\Desktop\MatrixAC\AAC\AAC-spigot-5.2.0.jar!\me\konsolas\aac\m5.class
 * Java compiler version: 8 (52.0)
 * JD-Core Version:       1.1.3
 */