/*     */ package me.konsolas.aac;
/*     */ 
/*     */ import java.io.File;
/*     */ import java.lang.invoke.CallSite;
/*     */ import java.lang.invoke.MethodHandle;
/*     */ import java.lang.invoke.MethodHandles;
/*     */ import java.lang.invoke.MethodType;
/*     */ import java.lang.invoke.MutableCallSite;
/*     */ import java.util.HashMap;
/*     */ import java.util.List;
/*     */ import java.util.Map;
/*     */ import java.util.concurrent.CompletionStage;
/*     */ import javax.crypto.Cipher;
/*     */ import javax.crypto.SecretKey;
/*     */ import javax.crypto.SecretKeyFactory;
/*     */ import javax.crypto.spec.DESKeySpec;
/*     */ import javax.crypto.spec.IvParameterSpec;
/*     */ import net.md_5.bungee.api.ChatColor;
/*     */ import net.md_5.bungee.api.chat.BaseComponent;
/*     */ import org.bukkit.OfflinePlayer;
/*     */ import org.bukkit.command.Command;
/*     */ import org.bukkit.command.CommandSender;
/*     */ import org.bukkit.command.TabExecutor;
/*     */ import org.bukkit.entity.Player;
/*     */ 
/*     */ 
/*     */ 
/*     */ 
/*     */ 
/*     */ 
/*     */ 
/*     */ 
/*     */ 
/*     */ 
/*     */ 
/*     */ 
/*     */ 
/*     */ 
/*     */ 
/*     */ 
/*     */ 
/*     */ 
/*     */ 
/*     */ 
/*     */ 
/*     */ 
/*     */ 
/*     */ 
/*     */ 
/*     */ 
/*     */ 
/*     */ 
/*     */ 
/*     */ 
/*     */ 
/*     */ 
/*     */ 
/*     */ 
/*     */ 
/*     */ 
/*     */ 
/*     */ 
/*     */ 
/*     */ 
/*     */ 
/*     */ 
/*     */ 
/*     */ 
/*     */ 
/*     */ 
/*     */ 
/*     */ 
/*     */ 
/*     */ 
/*     */ 
/*     */ 
/*     */ 
/*     */ 
/*     */ 
/*     */ 
/*     */ 
/*     */ 
/*     */ 
/*     */ 
/*     */ 
/*     */ 
/*     */ 
/*     */ 
/*     */ 
/*     */ 
/*     */ 
/*     */ public class mi
/*     */   implements TabExecutor
/*     */ {
/*     */   private final AAC b;
/*     */   private final ChatColor c;
/*     */   private final Map d;
/*     */   private final Map e;
/*     */   private static final List f;
/*     */   private static final List a;
/*     */   private static final long g;
/*     */   private static final String[] h;
/*     */   private static final String[] i;
/*     */   private static final Map j;
/*     */   
/*     */   private BaseComponent a(OfflinePlayer paramOfflinePlayer, long paramLong) {
/*     */     // Byte code:
/*     */     //   0: getstatic me/konsolas/aac/mi.g : J
/*     */     //   3: lload_2
/*     */     //   4: lxor
/*     */     //   5: lstore_2
/*     */     //   6: lload_2
/*     */     //   7: dup2
/*     */     //   8: ldc2_w 106036338715808
/*     */     //   11: lxor
/*     */     //   12: lstore #4
/*     */     //   14: dup2
/*     */     //   15: ldc2_w 19677097666906
/*     */     //   18: lxor
/*     */     //   19: dup2
/*     */     //   20: bipush #48
/*     */     //   22: lushr
/*     */     //   23: l2i
/*     */     //   24: istore #6
/*     */     //   26: dup2
/*     */     //   27: bipush #16
/*     */     //   29: lshl
/*     */     //   30: bipush #16
/*     */     //   32: lushr
/*     */     //   33: lstore #7
/*     */     //   35: pop2
/*     */     //   36: pop2
/*     */     //   37: new net/md_5/bungee/api/chat/TextComponent
/*     */     //   40: dup
/*     */     //   41: aload_1
/*     */     //   42: invokeinterface getName : ()Ljava/lang/String;
/*     */     //   47: invokespecial <init> : (Ljava/lang/String;)V
/*     */     //   50: astore #10
/*     */     //   52: aload #10
/*     */     //   54: new net/md_5/bungee/api/chat/ClickEvent
/*     */     //   57: dup
/*     */     //   58: getstatic net/md_5/bungee/api/chat/ClickEvent$Action.RUN_COMMAND : Lnet/md_5/bungee/api/chat/ClickEvent$Action;
/*     */     //   61: new java/lang/StringBuilder
/*     */     //   64: dup
/*     */     //   65: invokespecial <init> : ()V
/*     */     //   68: sipush #10865
/*     */     //   71: ldc2_w 7477933852009911970
/*     */     //   74: lload_2
/*     */     //   75: lxor
/*     */     //   76: <illegal opcode> e : (IJ)Ljava/lang/String;
/*     */     //   81: invokevirtual append : (Ljava/lang/String;)Ljava/lang/StringBuilder;
/*     */     //   84: aload_1
/*     */     //   85: invokeinterface getName : ()Ljava/lang/String;
/*     */     //   90: invokevirtual append : (Ljava/lang/String;)Ljava/lang/StringBuilder;
/*     */     //   93: invokevirtual toString : ()Ljava/lang/String;
/*     */     //   96: invokespecial <init> : (Lnet/md_5/bungee/api/chat/ClickEvent$Action;Ljava/lang/String;)V
/*     */     //   99: invokevirtual setClickEvent : (Lnet/md_5/bungee/api/chat/ClickEvent;)V
/*     */     //   102: aload #10
/*     */     //   104: new net/md_5/bungee/api/chat/HoverEvent
/*     */     //   107: dup
/*     */     //   108: getstatic net/md_5/bungee/api/chat/HoverEvent$Action.SHOW_TEXT : Lnet/md_5/bungee/api/chat/HoverEvent$Action;
/*     */     //   111: iconst_1
/*     */     //   112: anewarray net/md_5/bungee/api/chat/BaseComponent
/*     */     //   115: dup
/*     */     //   116: iconst_0
/*     */     //   117: new net/md_5/bungee/api/chat/TextComponent
/*     */     //   120: dup
/*     */     //   121: new java/lang/StringBuilder
/*     */     //   124: dup
/*     */     //   125: invokespecial <init> : ()V
/*     */     //   128: sipush #7659
/*     */     //   131: ldc2_w 8248441216273670634
/*     */     //   134: lload_2
/*     */     //   135: lxor
/*     */     //   136: <illegal opcode> e : (IJ)Ljava/lang/String;
/*     */     //   141: invokevirtual append : (Ljava/lang/String;)Ljava/lang/StringBuilder;
/*     */     //   144: aload_1
/*     */     //   145: invokeinterface getName : ()Ljava/lang/String;
/*     */     //   150: invokevirtual append : (Ljava/lang/String;)Ljava/lang/StringBuilder;
/*     */     //   153: invokevirtual toString : ()Ljava/lang/String;
/*     */     //   156: invokespecial <init> : (Ljava/lang/String;)V
/*     */     //   159: aastore
/*     */     //   160: invokespecial <init> : (Lnet/md_5/bungee/api/chat/HoverEvent$Action;[Lnet/md_5/bungee/api/chat/BaseComponent;)V
/*     */     //   163: invokevirtual setHoverEvent : (Lnet/md_5/bungee/api/chat/HoverEvent;)V
/*     */     //   166: ldc2_w 1775877453673962281
/*     */     //   169: lload_2
/*     */     //   170: <illegal opcode> w : (JJ)I
/*     */     //   175: aload #10
/*     */     //   177: iconst_0
/*     */     //   178: invokestatic valueOf : (Z)Ljava/lang/Boolean;
/*     */     //   181: invokevirtual setBold : (Ljava/lang/Boolean;)V
/*     */     //   184: aload_0
/*     */     //   185: getfield b : Lme/konsolas/aac/AAC;
/*     */     //   188: invokevirtual a : ()Lme/konsolas/aac/fv;
/*     */     //   191: aload_1
/*     */     //   192: iload #6
/*     */     //   194: i2s
/*     */     //   195: lload #7
/*     */     //   197: invokevirtual a : (Lorg/bukkit/OfflinePlayer;SJ)Lme/konsolas/aac/jX;
/*     */     //   200: astore #11
/*     */     //   202: istore #9
/*     */     //   204: aload #11
/*     */     //   206: iload #9
/*     */     //   208: ifne -> 229
/*     */     //   211: ifnull -> 250
/*     */     //   214: goto -> 227
/*     */     //   217: ldc2_w 1867248320640169026
/*     */     //   220: lload_2
/*     */     //   221: <illegal opcode> w : (Ljava/lang/Throwable;JJ)Ljava/lang/Throwable;
/*     */     //   226: athrow
/*     */     //   227: aload #11
/*     */     //   229: invokevirtual a : ()Lme/konsolas/aac/e6;
/*     */     //   232: aload #10
/*     */     //   234: lload #4
/*     */     //   236: invokevirtual a : (Lnet/md_5/bungee/api/chat/BaseComponent;J)V
/*     */     //   239: iload #9
/*     */     //   241: lload_2
/*     */     //   242: lconst_0
/*     */     //   243: lcmp
/*     */     //   244: iflt -> 279
/*     */     //   247: ifeq -> 273
/*     */     //   250: getstatic me/konsolas/aac/e6.NEUTRAL : Lme/konsolas/aac/e6;
/*     */     //   253: aload #10
/*     */     //   255: lload #4
/*     */     //   257: invokevirtual a : (Lnet/md_5/bungee/api/chat/BaseComponent;J)V
/*     */     //   260: goto -> 273
/*     */     //   263: ldc2_w 1867248320640169026
/*     */     //   266: lload_2
/*     */     //   267: <illegal opcode> w : (Ljava/lang/Throwable;JJ)Ljava/lang/Throwable;
/*     */     //   272: athrow
/*     */     //   273: aload_1
/*     */     //   274: invokeinterface isOnline : ()Z
/*     */     //   279: lload_2
/*     */     //   280: lconst_0
/*     */     //   281: lcmp
/*     */     //   282: ifle -> 338
/*     */     //   285: iload #9
/*     */     //   287: ifne -> 338
/*     */     //   290: ifeq -> 341
/*     */     //   293: goto -> 306
/*     */     //   296: ldc2_w 1867248320640169026
/*     */     //   299: lload_2
/*     */     //   300: <illegal opcode> w : (Ljava/lang/Throwable;JJ)Ljava/lang/Throwable;
/*     */     //   305: athrow
/*     */     //   306: aload_0
/*     */     //   307: getfield b : Lme/konsolas/aac/AAC;
/*     */     //   310: invokevirtual a : ()Lme/konsolas/aac/iS;
/*     */     //   313: aload_1
/*     */     //   314: checkcast org/bukkit/entity/Player
/*     */     //   317: invokevirtual a : (Lorg/bukkit/entity/Player;)Ljava/util/Set;
/*     */     //   320: invokeinterface isEmpty : ()Z
/*     */     //   325: goto -> 338
/*     */     //   328: ldc2_w 1867248320640169026
/*     */     //   331: lload_2
/*     */     //   332: <illegal opcode> w : (Ljava/lang/Throwable;JJ)Ljava/lang/Throwable;
/*     */     //   337: athrow
/*     */     //   338: ifne -> 364
/*     */     //   341: getstatic me/konsolas/aac/e6.IGNORED : Lme/konsolas/aac/e6;
/*     */     //   344: aload #10
/*     */     //   346: lload #4
/*     */     //   348: invokevirtual a : (Lnet/md_5/bungee/api/chat/BaseComponent;J)V
/*     */     //   351: goto -> 364
/*     */     //   354: ldc2_w 1867248320640169026
/*     */     //   357: lload_2
/*     */     //   358: <illegal opcode> w : (Ljava/lang/Throwable;JJ)Ljava/lang/Throwable;
/*     */     //   363: athrow
/*     */     //   364: aload #10
/*     */     //   366: areturn
/*     */     // Line number table:
/*     */     //   Java source line number -> byte code offset
/*     */     //   #102	-> 37
/*     */     //   #279	-> 52
/*     */     //   #22	-> 102
/*     */     //   #389	-> 145
/*     */     //   #237	-> 163
/*     */     //   #10	-> 175
/*     */     //   #160	-> 184
/*     */     //   #364	-> 204
/*     */     //   #400	-> 250
/*     */     //   #385	-> 273
/*     */     //   #274	-> 341
/*     */     //   #18	-> 364
/*     */     // Exception table:
/*     */     //   from	to	target	type
/*     */     //   204	214	217	aacinternal/v
/*     */     //   229	260	263	aacinternal/v
/*     */     //   273	293	296	aacinternal/v
/*     */     //   290	325	328	aacinternal/v
/*     */     //   338	351	354	aacinternal/v
/*     */   }
/*     */   
/*     */   static {
/*     */     byte b1;
/*     */     long l;
/* 113 */     for (g = nc.a(5138411658580872107L, 5894296842442415536L, MethodHandles.lookup().lookupClass()).a(280319632844864L), l = g ^ 0x64D7648239CAL, j = new HashMap<>(13), "梙쇴듈ꛩᨁ쏖鯣⺓䂭鯟㈶곮푉훈ᔙ藇갷挄麑掰".toCharArray()[13] = (char)("梙쇴듈ꛩᨁ쏖鯣⺓䂭鯟㈶곮푉훈ᔙ藇갷挄麑掰".toCharArray()[13] ^ 0x70E5), "녇궎羏㸿".toCharArray()[1] = (char)("녇궎羏㸿".toCharArray()[1] ^ 0x468D), (new byte[8])[0] = (byte)(int)(l >>> 56L), b1 = 1; b1 < 8; ) { (new byte[8])[b1] = (byte)(int)(l << b1 * 8 >>> 56L); b1++; }  Cipher cipher; (cipher = Cipher.getInstance(dP$dt.X("梙쇴듈ꛩᨁ쏖鯣⺓䂭鯟㈶곮푉훈ᔙ藇갷挄麑掰".toCharArray(), (short)11255, false, false))).init(2, SecretKeyFactory.getInstance(dP$dt.X("녇궎羏㸿".toCharArray(), (short)976, false, true)).generateSecret(new DESKeySpec(new byte[8])), new IvParameterSpec(new byte[8])); String[] arrayOfString = new String[152]; boolean bool = false; "渧ﾣ䧈⪆顛Ⳣ撑姨﷧ꝟ碏Ѵ騏嫓㬱$큯ￇ䟘굦㘗ؚĚ됃祗蟃ဆ㯛僜騧镸䛆쟪뺘隟齳⽳䆾劭惱⚳鉛풁멌꜅ダ듺禎㙯洼鈁ꚵ剛蟶㏜汹慵徠襑ࡠ䛦?手酼⻢磎ᤏ鬰ྟ햧圡㻡⟤㬥貜묐㦮˾뫉᯲斔醸禕︉饋婡ᕁ藣␡讈篂僌¼対먶㉺?⦎鷢ᮬ䐚녿ꮕ滁瓐Ư䷽ෲ꟭咎ꢹﾇ뤫㐦䠖퍵씖꼶鶏懺耵ꪤ䛌鸚䤃唽０쿏✮蛟릜ỻ엁悵晃Óれ磑濊☘ﴘ款듳촘弿摠䋦聑倌鉶˝잚ฮ眞抢絢?ݤ騄ኮ춷艛瞛厬ݛ䁯鈘偑㪇㼛̱㬰骆铘쮿䟩ꀂ躐认ﰛ㘥欘濾쇷碇퇏ᰅ꼎郧丯?导㹍齅ᯭ劽콌鸞ມ렢拼ᐯ閶僈ℍ췾읲턤᲋ꂗ팢犭ᕨ㈄箈潐⹙럋縻풑뤀揹紾磦䨉ꗤ↸ꂵ캅있誶?㍚⽍㿱킛ꔅ꺮쨺썰﷓游䃶䑢뷯寔㔐꿧᷇扑ꁁ?ᅯ椝쨚䅁龋ᄁ⣄ꬬ㸃乽뎮ኟ趞즆栧曛匞ᣠⱘ漒瀖?旡ﲋཫ怫啔璗ൿॸ岲੍勦졸⿚โ곤٩?ꝩ籇⼐銤軒贳궉銺㉜꿄㐿壿ウﲞ뭄촓冝۝ٸ䶍ᆧ?褒㛋㋊垒噘壘쥸?잌柑䷏✘鲻犝訠뿢㘴㲭▱⧰烈ꄙᄢ?痒莑ﲒ쐃됕릶崙롅孫ӋⓅ숮㱽邹兾䙺義쿷魠問雡ꯡ㫊缌멘媚냇׌ϯ홲쳼?尒?㣿⪚䮬ᗝ馶碵⻃蔱㸖䟽诜漟善逈엾ᢃﯽཌ䳁運䶈䍳䴘㷉뉓篴??⎨果놫﫪⇆ⶖ愖윙?巔젍臗䬗꾗꽞䠩혠烴瓝﹄䉤혞ᾊ聄噔?簸䯹풠撖䚿ྏ駎媟줪沇ី梤폀灷篮Ꙓั悽偶镚輿βₖ䂫㛒튋哋戈䤘躟萄ꅲ⺴㣡ි⡹艝긺ཊ溳餾罄?ᨽꗊ☎㴄版丳⥀晎ꎖᇔﰧ卝執憹멡굍话◊礹࿼\n?埛㺳ꐎ錑أ桺෸ꠕโ㴗슜Ά菲ꋴ䋵騑렔⨯季崓㬃ﴚ縗㐳ࠣ鰨딐샾ﯤ識⢿伳퇗滣ￜ鷲닕㯜䰌?凊鋕翭鯗鞍ઈ缙ୃ迭씎鯀䇌끍뎂ப쨯砐醨ᇚퟬ㺈卆⯭㰗䞂嘴厓⻉뫨᫚뱀တ☼䤝擂?냱焢鿀ꀆ糵宻䈯?켐욚⹫꧿ɾ䖳䈞䎲䐕渱ۇ꒛芳軫?抺晇⳶飳鑵싉Ę쁆㬇剆撕ꃊ禵ᅴ亭➨㮛䜄Ὀ鰏᲏껆艹㨵⥏ँ띋ὁ㏙ᳵ⠷ﻤ쒿?왕歬᝱䨚ؑ䑽믁즴㢳뢽﹐┏謄뢱㕬⟡ꃰ竿摎ੌ殖麿ᖢ묳䠨夥㉢崇栓讎♶놆硲踽볭䳆葷ꩍ㸾቗瘿궎鱱ꓘ俱湈⭝涛辏釂领䒊㤓딟⒗캩鈞得狴렏唿௩쇕亶儰煈䡠튈篿ⲥ婠㍺貏榀傕濎谦ꅪ뜢馎觺߾픻綱⌋咑ᓉ㾦瀩뢆琣Ὕഏ쫰쪎儢顒䀞纁࢘啹繥㕽䞟잖ዶᵠ丒麥脩䢊೨䐡庁丏䳢왊㰽ᬥ蝆艁?ཌྷ뱚﹉쫾捊⎩湩玙⇂㩜⇉憲Ꞥ窋勧壶䝽㵉?䲯ﳅ剮踮㔱擵ﶄ呿窔錳꓅১袠秧驀嗥ʧ깶禴ﾀ殣쿿?侥➅ᇈḸ?ﱡ쵟ꋰ䓪덽쬦嚧撺엃⽒鎃Ởᕩ칫蘨㿪剰娾璹卙쯈䈁酏蝎斦则ᚌ輾旀짃껾⹂뱫枰됓⃸?᐀挊ꬒྐྵὠ죭減翿휨堰㘂腻盌ࢱ奬ꛆꁞ늬ꁴ⋏όᅃ衏砼癜鴏脹콶뾡萟ⅺ?沮䌖扞囸手ǆᰎꈡ呌趆귄?Ⅼ⡻혓杴꒾翦ꮘꕊ俴凕蓀롑鄣렔瀣礧䶥฿辭ᴽ协㍗➹稁ꇄ掸떾ঙ⑹咬皑綸뉏楰፞뺲봵⾾≡䃈즬嬿?力ᤆ䯉ዘ藷豜Ꟑꗆ떰?砓뤥씶⪤鼈潸쎚꘼翅訿ឰ௕鑣ꢬྀ餖໇殺?蹢⯍ꘃ凰鯴䝰嬔蒺胮瓟ފ麥⢌Ჯ璈篭橎䬗꽐퇅鐫碃ɗ籐嵛惪卤졅⻤颇﹫蕅ᕴᲘ詧鲪必ⶢ??囗䘮剝ꩴ蠚ඝ切（棈㭕靓愠ฒ锉̻庩?ܱ୛麲痛ꈼ挢㆏䘆ꅊ◈⽖졩艩딀๨ህ?꣓듴﷼䇙论ɪ츃䫚㜲섓땁먄㞘ㆺ岨꾉闹㗬ힼ雓엍༂醡댳鞹地⬳ﷷ듢?䵶䘼顨ﱗ偐罦౓ꭦ৘ꜣܹ䭭㵷礿潪⾄ᶫ岆ᨵ旔绱湆?苁࡛큀뺊촋᭻ꐫ눋邢茲吠苎⾆淏⧁餻˅餰獆౰蜞儧잛릚ቋ둷瑌鲶嵵쨀˧鼻텗Ⓩ晲乆⠯菆縙쨰⁰稍㼳ጳ?䉲?ऑʩ䷙鎭騬寱뀹裧෯쥄庉鼅ﮦꞽ岋술箓多垩켼殀㝊᥉䛏鹹驾Ṱ濅睯犿哷﬉戟꣋?裏娯ꈍ븂텤膵楲䯝偷仪誹㼰ａྚ麟㗎쓛?擄幙ꈴ≉ﺯ卵눲ꛝ鑜䫰珴넗놪맇槠䠪瓃ꂣᶿ媹꣏许௽䭋鬖繀릫芕ꁬ백초焝ꪧ⩠⤃䭗뢧埫킀Ꮦ쌱쓺鶈娗㢑쏌Ṹ䧿?睟賹࡮脾굃ტ꾙ゾ㉫鯄琲ᲂ᯼?誌ᖠ蔍㸇촌偊栕㑴縮芹ɤ䧷軈ק퍞ὓ兔浗쥂蟦㉁䏆嚮?麨￰䀏麹ѡ뮢⮰⢪ᖗ꾾㕗ㄮאָ㚠⧝䈵滸鲣ꛩ⒦焻ጀ桼斬䅫蝽經㇟䃃狈ⶺ걅⏪?혆력䜞✗䞴㩭췧庄䟊浱巽?뱳䖤컱斋?䌺鮿텶ᙦ鉪?ꢈ?훪蹖뀚懊宻鄐࿺䤫韈뼞岂㹝鑴篡謌Ⅼ䳁˒딱✭鉺徏슩昁ᠸ쯳ࠓ缽ೆ열蹮蓍閕匛葂馴퀙运聴㙋Ⱐ直숅㚯탣칽鋣Ⴠ씉⣂￉?卓賅暌›㾡⟱﹵豘䱬ꑣὋ뉽노?墏兩븜ꈑ?㭪烮뇆ᨰ넗높鎀ϫ⽀Ⲏ浰౬ɠ촌樱ꂄ䫞欦햦౓龋⺎儶볥稤뮺㌸荕⸧耱些儋실姨혇ﻻﾳ㏋䈅꓇夈틝槃絖걦㻇당攰?蜞თ鲰䶢ꈖ鸉묧웥㨶柳側ᄇ븄뎵♿飭ࢿ䉞껅ㆳ鹐ឲ巕䷂췘㬩俖圇ⶶ?Ҽ걷㶯罀⠾쮇憡澓㿊輏坑真촢㤥䡚쾅編徘쀲悃䵮롻凌剶꫺⨨郝メ랸䬞⵼ಽ莑穡朔輁艭Ձ㿈탇纍넽锋᮲ᕫ고ᯠ猅ࢁ묝᡹ῲ릕秙뇠?焘䪈᝔胺礒䂜柇ᴌ堂儤뮀镉⭨戯컙ᴆ⨖├菍㜱ꩃۓ쬂⤫㽃퐍ꑈᄐᯥ뒏뙩⬞ሰ佭칣띹巗핂?㷥䌘쏶倱恾䯕庞死䬛蠐?홹ᚆ튜࢖荁䂪죋ꉃᰅ䏂㟝荵᎐ሴ䫼섿䉽?ꇔ⭄슸姦枈첱ఇ淛쐧ᐹ蛮㥚㇊?虗퓛莋ꍝ尭緞껃奨䍴힄뙬၊䲆紬敏씀䴇倖ꡈ蚉␡ꓟ瓏讧䔧塞奍槬楂禪侅榜呯辍?ᝤ飸㋍꧳?踩?爊㱒ꂹ쵬㕈袓嫜㏙厜羾十῱毓蔿쎭⒞䛂⭵酌ꘇ?頰礄处?瑠鬅?卽▿龻ข㸢衡阡쇌듂诣퍉ŜṔᐩ?깐ꓸ䅟凥栥쒽胔ミ丸⁧껀죀镀柶附ꇏ?举躄璘ꓚ뻼ﻖ핺圿涠?嵨韜䚡᨟領〓楀虊ퟍ⥫?藗ꜞ躈폜櫜죕瑦咪ﲤ᪎佦鐅?줓䐪鸥狙졥퀕坝И幱滿撋驅깛쿇㴬ꌂ㔶瀯᯸偝읏ⱒ띏⻁瞨䫠깔黩鏲鯙ႊ릀씔㒅䦕្陙폯军撝䑆嫰䣛堣ॄ舝欿덉棦ۖ惬튣載궕ꤖ鬫䨷竊䮚ￕ錼ⱓ瑩譍?䢩殤ᣍ萀䲋랜뺰㊷䍋☉ƛ壔䌆폶㸲㿧꫹狵ᡤ뷃衹겇ᮛᶻધ俽숔?秮纡焢垄衻ꏍ哿诎위ေꊩƤ뇳ࡲᤈ熢譇햀⹆맾넋枤읧Ꝟ踺ৎ帠׆ꯃ똴࣓䇴聓罅噏咩輲⁍᠕?怩߸䔅䌅榰??⯶紐並㳸撵홵釠ೢ吜㰉䍑쟺흼햞븿礕욓狷⤦볿̽罙뿿⴪ₓㄳ㪛窆꾬満뚳ৡ럼ᆈ黠ꯚ斳㶁ﵪ玸邿墠菨嫮⊏芲糯떈碃ࡋ梈읪錭葉휘䘡棪乱剪哯裄賔᫴靁㽓ᓖꗰ⃃蔞甈癈誠䞙力ԉ۩⚅䵋\024錁琤훏ྚ祐팎ല됫㺭䞌⠴ꭖ⏈▇⣮ꝅ僬ꎵ⽻ᤧ賏骙㊭㉟鴋ꡏဧ碘键齱慡㄃솕쫹巺庳墺楧᧞ࡤ?歁쾺䬒艶՛㠛?⅊?ꟙ?뤒颼㭅﹗᧩琸❸〘⯛็꿍달⋾勎᏿馵뵆ݯ躭몠澘쾚塐계뮼ﶾᛊ컂黇첃Ⳟ肿燺❔᷼鋽靡Ӈ킩ᕉ狷薔洔Ṹ鮤?鯭䲝ܫꇮꀎ龜諧௃冻﮺댔溲뗄શᄤ᪛몎ഀㄥ쳅묽뵅獺ꨠ垽Ն↬높?澥衙㒨幍밦쨛鸇⪲鉣㲃檠曥抮❛䁅褁尋삗﬒ᄤ雰ᔷ쥕柫稁噷킌潵뱫붞淆഼ꈣងꜜ왦蟧↞㝚?욵⺎㉈ს㹣㞁ﲡꋓ죎䇶업꬀膞卷틏ᝓ푋馠ᚸ⁭꠫뽩ﭶ悪낗䌭ࣾ䡃혶頱ﰠﻈ섵ᔐ抎㬊듵ᓹ澇⯞辘児쨭泎秒豁ǀ鿂ﭺ寧Ὰ袯暩옓䓊蓻ૐｭ崥덑ퟛﻁ롮至ⅆ㺜ཬퟰ흠ㅏ埫㳾䛩鈡䖜탚ꉵ铳?븊ﰛ眑⾓踣뢮鉣䁀ླྀ阯?巩늖ꅓ轅㝀타㣑Ό㾐焔Ṯ濿㟮ꠘힸ瘶馅贇◔ꦅ쭾㛺ሃ俒괡뜫젮悆䪷毝ꟑ娻䝪퍳Ɓ᠍麈ě㗈纚亀諍흪叓磑ꗊ傤禣ۨճ폂䴐砨䐏̉싶螆㑎⠇燣ぐ簰?ꌂ㨅錙↎忩㒞쒹⑟荪捶孜임盷媈㏐ꋹ䱠놯ｩ迆엑≋뽹?歆⺲쯾懠㙼濍莵柷䎫⃻篨癫৔뗯佾࣫箧敝熼䏴猢剜母겑꿹瑕↪맥Ϝ诉ꞹ溟ঃ聾ᢒ牫檦쭚꫆稱樷嗀ឡ罚踟챻䰹廉ꈐౢ䷺奸䮡蜏젴펨퀢쵠燆殽ꘃ㠡⊅䄣蒂▿ᣥ儆ꛎዠ䟁ꜞ୎㳠帥ବ녑ẖ瀢퍰⨹莪懃?꾨ᖲ쵑꫁ᎁ᭪렜ꓝ눘鱈҅䡐?鿎컳Რ餅㠐ቡ崓\006쬳渓ዽ褺㗗筵ퟧ尒룶뢧靼덏㇁癪여豗ᥩ⢛䊥䰂ｦ㹡䨱㚕⌣颳᝜॔࣬艸铏ꁝ짌횵ꑻ떉靡颅眆䕨픪훋锅䰵쏸គ싦焖蔡䕑顐笪퉐竚ᥘ즓ꊓ?旰威쌑㦻⺶개犥略놿䳹讋쳸㐞ꍥ㡬坑掫穟?ᙲꍒ诲⟒⯯ﲂꪕ䌨萶ᒢ頨띍ꖍꪜԮ鍦㖗Ď廷絆뺼衽躇秿䰜鳰訚䦝ʙ픵祍햮꾍䥩ꨫ齁࿝闠奣쇑ૈ笶븁뛭⧀ᷔ漗픑웝샑㾜⹤熧䚤雛庑⸢蘰曘艟벒ც惃栱ꅂ친폃祃⹾ࣥ뜃䪻矌嚄䨊䒠홄म捀錞䦚摂ቩᶳ꾈ޓ䁪䔹斔䢦獉뷐ญ⦬䕞ꜰ?ᱩ鲟ᴷ朊싙喭⑓珫Ꮝ宂窼ⷙᖕ海ꙛꚑ唭篧㿢킟狊嬢ጬ䆓誸묟?밃ݥ蒧㟭ᜩ菭먄麉蝹嫄쌉ࡣ좃袚賮万斺फ䈨⤙〄邼궈鈑쿛뀿⏪ꇝ풧榝ᚆ࢘齲啠ꫀ᳣瞃펍⃗첨ꩲ袩ᔈ⸱?쑧捙悭웟秏ꍗ㭤쁬穗ڂ䓨ԓ녓㑙䎴⡬픨뇔ꆎ鍒攧쩢Ⴛ㯯麉㣀ퟀꯥ劐癔?瘋ﳞꎎ콡笐公㒺Ꟗ噄桑秿ℿ뚒﶑達㕷?뢘빟হ纻읮ꖭ៤螜릴?㳉쀗ᓱ귓벑潎ﱱ✓蛒欧䬌⥝禄ꘑϟ揹⹋쮰쩘ᙕ㔧ᄾʕ꛼ﮌ嚝犡ɸ奔웶큪멸ᶓᨉ団㳈덏菈똨챐娤ꊟ⥁ן䡤双✓譆䭲㴃僂缙璇䙽㲯횫㝱ᩮ兿᭽໌잯₞鱞冘퀮䋞?預兴뤗摄左騉韡碲࠘움敘킊ř퍔븮尝䃣⿃砉霑손膙맺뺩ꝅ俖퐙㰴ꦝ⺿ດ靧螉ɜ潘驾츞?滲਋¶뚳ࣱ숔㖽ࠄ㘬?탺쯗䅳뵉ﰺ?蔎⏴챢嗁㯾暴妄ꁼ烩ؤꏬ녷냕勒㖽ꁱ鴯錭㞫㸗ꕤ費䬅謧컐뺤駖?酾﬑ݨꇠ瘄?쯙㋭긌﵏鼰Ꞌ籪Ɍ䑲餈㍩ᱣ★⑼녓꯶鱴븘괔?⩘襄塻ꮇቸ㴮軨धꦒ狚彘氲ꓠ涜ᤅ礴긛ᜍ饉燀﹢魛圙雬׊뒰苃ə폅톟몎댱襝伈⪞뀭㹓૚戋쳣䕞䭷?堋ﮧ䅜炤㳩蕎ꇭශ넖묆䨟囑聿坑逦ꌞᭌ就넀ꡯ裺ᜯ擌迵깰Ⴎ蘭즞迂Æᰘ첶ㆎ藽ر竎羗㉰⩹?홄謅ㅧ觵詘Ꭲ⚠౾榪봴傍鮴ቸ腴冺晳Ҧ澸奀숾ꒃ햿㪠⨱苚킩ળ슁⊒뛵쉑他螒쫓㋱瘂冩볦祿٧㭫쌝⣚毨ꪂ죌覢鰵䈪䋬㆏꥚帟⽖穘퐰㯗ꑖ吩촟ଔﷸͻ孳ꬕ哛骱ꅹ灌灠栧ቹ潋뚒痰輮觢ጫ廖蔤抽ぅ쩪͈⸌瞓㪗臾榾﶐뻮球䳭膜걆쩀䗕⿘氨桾ോ뎒썖鄥傶Ô搧漴略⦆擭㡹刣揼䩐災믙??妦졡?䣄ྼﻹἛꯥ?쪬ꔡ㞧✚伋❠视ﹾ焉㖔댽埴웭ꦤ計䔺ؘ駥呵遥?ㄟ媷퀴싥틗쪢瘔쪰╈ǽ஛核䐄⎦䎞럮揪伳⮁縺乩瑱鳅쒘琘ᔇ쎪묎놗ࠚ䀚ꟈ栟䈘儮ᢓｅ券힐캷迚濍⎋幘괩ꋨ㿣䑖ཨ픇㽤Ⓞ⽇袄뿳?ꯐ㑤⑍崧侔蜥ꬃଽ홧✡Ḡ綾蔠ᑨ鱗ɔ縷嬇챮贈ᳮ퓣砫皽精捖ई驀'ﱋ꺘괽ʟ謔꯽袦퓷떙?怋ᩈ뺅顐㉂軼삵ྲྀ⑳汍萊㽀ෙ?믟噚ꂶࡌ翯ᄨ놾䀬ᥴ樳쒼ᇏ﨧娋z䵺荃렕엚ԇꗍ桇⚜ꪦ糱匽簘搬뀀뻍鬡椕㘉誀捞挾刭ⳁ֯ࡄ좀壧曽뎰⍜耧䦅怌ϲ쩶䩢䳹壒؊퐐?膝૎陘됰㈣ᰚ嘯棛底鑕焄苔䶗䑰뙇¾轾⃫ꯄ炱ꔁ檜汹?瞇唿┋삊添∆僴顮﫯懒鸺理┽썗侰캷뼷꧜⼁蓪䚧䉊眡铟−ﲊ㜒ㄑ鰦醪᪋傽䘍㲈刲鯴副⛾隣땳䂉឴弳ᲐἻ斟붏剪蜛ڂ혓䕴櫝䘷虺㧐蚹蚠蠮怉䎤잦㑫煛ၸ헌愁㬤禼뤼쵾䥿୕ﶌ㎵쉷쁸奖莛᳕쀠ﯧ뺭࢛뇢찵쌛暃꣆ё舡鞺觳赣셑휧靰꼔螳㤸꧙\020瘥ﳭ⫥ᕏ啥͵槀砰㐼ヰꄟ즶繒籐鏾㫰횺⺈渥꺰☄똡Ŗ挆쉏秔례ダ水콟袧☕㊊콋뵚飃莐㪖╱ᒜ㒽⦯ဗ⥵삩ꪄሩ⡰驃媪ᜢ⼵ҩ浙ꚡ?㥮툩ゴ᳁છ衠阬趉Ղ䠎嘳䘔樍͊ᴚ칿ᝢ恠競猔韫꺋얒羆楡淋謘᫣絑된䤷亹쿯饦裴캊霤ᒈ级쒓败麳俌遼數Έ蟓푀昳涢딏馻䗙뉉钞ษ쾢⭀톸ﻯᤳ륭＇⏝뚲㐛笫笠枲麱਷㪙ᐓⰼ촫ꖀℨ笆⽡滵䫂伹祎㎳ਸ㏫숋삄啉碊伊儝䰦ᾬ㥳䆏ﾍ尢逯舲끅暒瞮☼盛咶ᛁߓᶮᏵ⛲꣮㿙榧磖摭ﭔ铏壤慶੽熶짖ﭽ麭裸힁篬僂傾乧顱勮⮳秀?ｌ퀃熡膱မ䴿隑ꆏ擌녏ᶛꭚ燾삑Ĳ辩㐷⎣ᭊ몎ṝ謟츷ⷽ秨ꩧ띫퓭椇꿧孫갰뗢ᄨ끃慽㓠䑌䑣矖뷈셗풂ꉧὑ폤킡䮦䈒阋㤮㲇憡삕ㄝ괺㢼Ꮊ콳锑큎邿왌滑됷ꃆ鸐?衉壡濉뱿樜멵藎蓑ｵ㵁䘛뀄响珍駒卼孡뤀⅏ꣳ郏㽣㗦苼㋢ﱦ竄䗕鬆رﳙⅲﴓ虼ᐙ쏿嵙凴ﯩህ뙿瀕輦崟ᘤԙ瘍?㊹ㅿ戰鋱❕钑❣欳촮뚽硐搏ࣱʋ⃉틬揺銺ⵄ睋餡䭲됝﫺觢쏫踫틘씶틉䟗䝁ᝍ雌癁䤒ⴆ祔?燂슿៕緺绌樦ᡂᘽ댪榮ↂ䤩﫱ⴈ䚙굂雙夠ﶻ㞜?馞䄅ﾬ羰驾䀑懱ꝙ⹑ꃕ㫴ﱦ佐넯㜃⡏❩Э뗣믲䅞揭淬헊ꓕ썸魅蓗젏旈ꦒ譴冖诵㸫뉠鴄즀쓶艦ꑧ긽쉓蕋쮛珰탶ꨯṘ乳貅༓Ṡ鳏ᕄꢏආἙ튘ᚴ砑駱ဓ薮?៑準ั皹發恝ቈ暆馜㄀쫰陋ꆐ勇ډ贋눍枂룹决㒼餬悚ꆻ츘ᬞꝞซ燯㛿⊑挴ેꟋ棪쯎盫㱵ꂺｻ攇毪?储쁤船馏뿤硬ᗯ➱?槤㬠ꌍⱕ駫誟᭽涐ᢹ䡙ณ램⬤ҺꑙẸ震蚒쎛Ⅻ薌⠳璍赟厞앓ਁ쏗㔘₢ᐣ灗蚊ｷ仒楠ꇘ幄읖뻭㭮㙭씔?㳍蔲?킏镈壵⳧巠䱝⌋◚躽葝穇蒇鶓롘ل맩菀ꠗ૔玃盢⒜ڔﲴ﷠?驂?ꕖ뼴ᅅ⎗㵸?珧黡狾漤糌ἕ拉꒪幄媒䗮ఱุ糡棞丗撰葮뎹᜹凤噽㡶?皻쒰ﯬ㨲쒂胺䝚鮭彖ꖼ㎭肥ᯎ۩ⷵӥ?䋙㯪僦雊싟퐝俟淂唷暯䢃贖벤䎤䔂ﳐ餍握䗺䋎Ⰽ뺪凴䐊難갍ﷰ筄蛟閿ボ襱シᅷፌ끷䗾ꩊඍ䥔슏ẇ檻滘䃈ꕏ믲携㥜摃䳖睁툨駦調?鵡?蓓뚻踚䱽걽﹵塤ﰁꠝꈂ欫梑ﯡ앗ᶅ붎ﻟ⡭ᒓᒶ୛⠦⭚쀭觧뾥촋㺧ﲧ볡兿ᮓ庰ົ듸溍拠剠ꭏଃ翲劤鴧ᣦ毤ꇱ싽₯砈⒘칣팫쀞잌暢?⥛ᑱꜨ奘얏뒪쟉膄땙䓖ɳᰬዺ㓆ҍ㢴쏇?㌌膊ᄧ퉜蒠ᠩ鸦蒖ꀅ롡ﻇ뮚芆?髦ﮫ욤弗ㇱᓰ鰥㜢‟ꀋﻀ狼ꤣ얦ᇻ돀钪琷좚귈Կ왆盷龸ꣃꒈﳟⳂ朣뤱ꔇ孠驢検ᨁ轔닾♨㼺捅ࣄ惚䝥牿⾀떃읈츾?럦ꮅ艻ﲵ脁⡝⻓옹㘷驫ﾍ셺ஶ䅡잀䣋魉랺꼬둜ꛈ땴낪겿虰㙊۝꘾공퀀ⳗ䄕㏥惾蒾䞱䩖㚠᠉䋮댅ޣ爰㗔ॅ䫿ⲯᦨ磠禆翤䪦ஒ챀⨸댹牟핈䞳埣꣯䤵﷓曵?崬緘에廒ℇ䃱誷䠒岜霨彜⃧놘ฌ?몼ൕ互韆覞甘?쁇ꙥ㮻⣮쯾戽꫏碌溰℉｟뎎୸ȴ釒윢갻戏逾敗餴׶Ⱒ箓힨㈽࿡竰୑橿耡鏎ﺂ樬呯买壂થ෰뼠䞆쮨껂㲼㌭徕行쨿⃑휩၅⋶睯ᷱ鏜ȯ䧒죬㠚켟Ὢী賈썒鍾ȉﳞ?쉉ࢹ틱錽羽ᖣ햦罁ৢ쐼攭辫絜Ⰲ袈뚙ᓝ錒㪒ক蕩絧눜摖ᜟꦲ簦轒ᡧ?琋ᗠ⽡蛝橛㜼鐘ꭍ圗觅郚釃읓?ᜨ歷ᤘ䔠ᇞ톦袋罵㛀ힽ㌛궚도㊼⽛蠿蒵瞟ޢ估ᨥᣤ星鿝വ㰮ꂥ鐓鏉⩋ꆡﴽ䬼ﻡ潹␄⪳ಭ糑苞?傻䓝넩镂畨뇐㬰褚褞쥁㩍艱䙥篊䋃೴悈橴冩륯꓈穫鵟冮匿騞淃莁㺂㐏듣푹떅冣៑௝⸋竹푟ဓ貕ꁞ喌ꎏἷ贓읩Ӓ፷ྦ㦤ᳰ겊摏呩桽楪䧨몐瀋뽓쨔⽘쨒窓拦筹ﵚ，滚칌缬徊?範礝霥ꅨቤ㮽碧朶稟腁䂞⟚웼愈꺀ᄑ쒖瑸篫쬀衛둞홨ꮓ웈ཬꄂ鰾蜠䑁傸욲⼒擬爼❅뛆奅웺珩褀꡿璮桵摎鋟쩉빌龽諞㬯쒐绎࿑෢喩咒䌠〮?垰੷㝟죥꽐刄谼꘩ᷕꗪᾥ纸日﷈推㱹ꜛ瀀柑粶Ⴌ⿥却鍐⽁ᖍ♱與ꁪ鶘䊙볨骃兵ධ蟯椪썫翩ܿ⣾쫑溞佴埘縥룙㚊锷뀣襥꼻?뭨㼌渻ꨴϑၯe廚Ἂ꨺?쑪ﺠ揋雨宔鮞琉压䱐拮띁螦Ⅴ桅簪ᕈ턵㬩떻硔အ㉯⿚퐿쭒累폆뽘枒숔㚙ꖰ䢜Њቔ걦౼㑓々⒰掓㴓禅囗㚂⸂း蒇͓爏懲Ꮪ㗽皕摿겧栝ㅖ掄㜭馻옚ᄘ䒈埖쐣㣇뇢븋䭒ਹ웜ଃꄱ㑐넡ᷕそ턬昄㰠ϯ볁‟뭴怩뤕㏨嚔爷鶇ꖋ?૶豪貆隬榥ꏲ扶쵄?墩Ꚅ攏?蕜縌അ缞뫩꠯⭻歙ﳘ⹀讫춑ƾ牲㙦沁⃯?壡㹖ﮕꁝ堗澩悯箶☯ᙹ㦻礨顼⡗緐嵲䛣襻迌魄艏哿ﹻ嶶켻憤䁁陋ᆰ叉꤇谸㏂减怦䧤㬾ẑ릿ⳇ暕핕钜ꌰᛕ镑瘠﫹踃̳晸ⰷ霒燙せ䋎❩輙殒ↅꎄ梲盹䜬Ů踌ꣁ뾴뎸欢뇅尅餲酈딍ॾই쑷줿⺀㞎饃짣库枯덽ꐋㆀ芐ᵔ턈䭼⯙蟷춬䘯熾䉺ꩫ㢧ꨜ铿覨ꚦ䀋砵␸㲢ܾ桳켈鱪➭䡒솛쓵ܼ㰻᎝䥮Ⰽ酉?紽ꑧꊈ뚹猒䄯큧⿥?腡홼讞痦쪑殳ꕩ゙慵拻鴸晜熻쿭別❜Ⳅ灗獖슎䛈㺘篏쬛쀰툱ᲃ䌙吟㝮䑅䢌\f讁艟籨랤쑨萌쫳ខ蜶⢅潩䃖澰⡢❗렕?곂笂잗㮎袔៮फ़栶휎㷜㑬蘃䀦䛦៮ˍ疑쎇鸑迹晦뗏꿡셦⠕੍ĺ晘朎ﬢ᳞崦䁵౎聣鿼ᴢ᫻Ṉ䟤伵竛澷顎쬢涊硘丗緲鶋Ȅꊈ阌Єꠧ燇평䳇ￊ绀O議㯣ꀴᩢ얿㐐䗐썀ꌰ층솲袨쐟㎦묇ꈅຉ豚튾火鏚颟郦殂넾ꜬӐ풷๳飡䵅红옭呴ϻ辩셹?ǚ򉩽ꯉۓ勛㜛櫹糯?ﳔ彳獆䦴⾔㐦鴥蔏ⲉ壂魕ﱙ搛橄怱֥㽿꼑癭ᇾ斫蟭᪝◘잜?葁밠앳Ȇ㵃䗿䚗煅ਉ竽扄Ϫ薺嚦䖋ꃦ?䷦ۃࡷˢ㥙숗業걜⇻Ụ饚亟芢蔕쉐玷ꋕ၅?ᇏ쏱딍枰㿳쥰钵棫뙲๶ᮬ6슨茁ᓼ倫滢毥髫罧쒯毤為祄뱮↚裕帒䰣鷌磌針㊪꘢䪃鼁䛂갶녟姹닺ᄃ➥휩❢홡ꍽ첦⚍䃦耎縈⸃໯⼃꘠볎싎ꦷ샡郘綩亿믊牿ꆯⶔ剒Ⱌȶ纍ೇ蟋⏓ក窹眻赇㋔醁뷩瞫ꃈۜ全ゟ厌Ο◇ဳ䧸猠څ絛貀畻亇ꃓ銘ꖗ゚秩⧮녖鐪㔹ý炇뻁寧䲚ﵹ᪐仂讋꘸?䰵㇭ଭ歱䭸㯚캉䵲芅ᅆ ㏸塪ꭆᰟ筑쯮玷䯅੧?ᩤ⺸鯝੨䓁췘鬤㾀䅠⢷챽禈蜂ꑴ䖙ݴ㵲⧡⡢텔쫅襎攻ᕌ?␸媰⢔뽐莮ꮝ|훹侍礪黍촒뱩㦘旰斂︐ኯៜ좛埝ೈẇ㥠ￒ魯㾽㯳?௪駰᜔濥໘⤢蘄受⒋垎ᦰ⮲蔕꾳꽜톭῏◧먖퀠猥Ỡ䅳켉甝?脹诼澪힡䈳ỗ๪䵎鉏箮㧇뻿몸ﲥ嵯ǔ瑩ូ甚猺ꏃ⫚䫞쎪掼赲幌﫝뽗鯟撌୐짖ᩑ錡૾祰ꞡ뿸嘕?⧹㨔ꈎꝺ鳘ｵ졘쉨㽀鄵པ蘃詷忚欑﵃莃冉⚙዆艭禘䁴龡詺省墚ﳕ췑䟙슴盫⾯ꕅ疏蹏ⶋ햝傦㤘愤镁諻훥퇶箓灵쩪ꐠⰏꐛ靇᪆ᤸ䯭儌洍ꔺ亐종㠕૨ᛰ뵦ꌫ嘄텪鳈犊㢥傞렪都笸龇ﱎꒁ༘Ⳗ沭ꟊ俫惵췝ᱢɭ㔡獀⊴뀨糛틩?䔝Ꚑ㌈㾖鳆殍齪࿨ὒ闪烎ⱐⷉꮠ◣∹ℼ왥螚ዳ趶ꦚ涅뗢ᰈ넇橘㇮﹩洝Ⱡ⼳湭㚿ᓏ⸥똸锟㜉︮텁壄聛?㭆둏㓰瑠衋烳᠗ઐ确롇팞ꊈ麕?⧠堇핢㩴괂᫓ㅑꞛᖀ੤⁏걎⬁惨殊ຑ豵鬒䵰쑈黗ꅳ뉇ᮃ韮΄ಓ㔵篁葧瓸樧퀠⾮䩣ꛘ赯只쟥ꚳ툆⽻ⴘ飇ᔻ㔄퓟빘ċ酺圼컅盫欘ᩅ赆妀∠テ眢?톈쩤깽鰶툧Ṏ䩗쫫埾쒑꽔乣惊暩爵㴈캎?ᤷ潘켐歴⸣쵇∤⾸ꥊ셏쓄伽͛㣒﬌㐢ꌉ㑰꓆㿢삊탹莫낮毂ㄪ棾薍鰡荷λᎤ墋峞젅졈᳕ͅ銬ഋ޻둕愛㢍䧍膻鵎砍卶绋賢ਸ਼Ც⸍밊݂熧蜂첫観᭛랇缎?릿ڴ㍷햠቟塳췆悚㏸儜ꥋ¥ꈔꤘ☆毁?彺뇲룏鉶焚ꛬ籅앞娞萲칄臨ᑻ끱顴ߙﵕ䯰␹擥꿅퍟誺ꊛ褡腙㛴⧲툲緧⛓幻ꂟг갃꘡윃낄䯵嵞㩻ൃꓮ⁍痁㿱୸ྎ밁꿩랕戆ﰦ룼犐賈滑שּׂ鳝Ⴢභ데堌婆ᎎ롟癇㤂?샇፩㐬䲥㴺᧚㮀﫭⋈ﰮ页?撠韉倉뭰譾‏隵༔䡗쟒夿┎媂ꄊ⯙毀㩠儉狑ₖ뭦濑劅댈蝮☆䅲뎜偭䤫燊䓥麟肊༇鐸嵴掛ⅳ䨮⫔琢ᴷᓤ忴ಧ㉮朶죠튰弚芔단┬䒖ⱔ㹜籐䃘맪浡鎢睊筫헐ﺽഏ闔㵞佞鵢✃紾쉎荲疊홀뎌㥘窌澧鹖郍뽸ōࢁ粄榒৶䐮刚旀삏풠뵉≰綟窾땞?伧獵듴捗發匜ྃ䠱誡ケ랶坷濬娕ꋽƚ됂騎⸝ླ勴쥉錼곣鋜㌠深鶌瞎⦣윾⴮송짴䒖妩".toCharArray()[2959] = (char)("渧ﾣ䧈⪆顛Ⳣ撑姨﷧ꝟ碏Ѵ騏嫓㬱$큯ￇ䟘굦㘗ؚĚ됃祗蟃ဆ㯛僜騧镸䛆쟪뺘隟齳⽳䆾劭惱⚳鉛풁멌꜅ダ듺禎㙯洼鈁ꚵ剛蟶㏜汹慵徠襑ࡠ䛦?手酼⻢磎ᤏ鬰ྟ햧圡㻡⟤㬥貜묐㦮˾뫉᯲斔醸禕︉饋婡ᕁ藣␡讈篂僌¼対먶㉺?⦎鷢ᮬ䐚녿ꮕ滁瓐Ư䷽ෲ꟭咎ꢹﾇ뤫㐦䠖퍵씖꼶鶏懺耵ꪤ䛌鸚䤃唽０쿏✮蛟릜ỻ엁悵晃Óれ磑濊☘ﴘ款듳촘弿摠䋦聑倌鉶˝잚ฮ眞抢絢?ݤ騄ኮ춷艛瞛厬ݛ䁯鈘偑㪇㼛̱㬰骆铘쮿䟩ꀂ躐认ﰛ㘥欘濾쇷碇퇏ᰅ꼎郧丯?导㹍齅ᯭ劽콌鸞ມ렢拼ᐯ閶僈ℍ췾읲턤᲋ꂗ팢犭ᕨ㈄箈潐⹙럋縻풑뤀揹紾磦䨉ꗤ↸ꂵ캅있誶?㍚⽍㿱킛ꔅ꺮쨺썰﷓游䃶䑢뷯寔㔐꿧᷇扑ꁁ?ᅯ椝쨚䅁龋ᄁ⣄ꬬ㸃乽뎮ኟ趞즆栧曛匞ᣠⱘ漒瀖?旡ﲋཫ怫啔璗ൿॸ岲੍勦졸⿚โ곤٩?ꝩ籇⼐銤軒贳궉銺㉜꿄㐿壿ウﲞ뭄촓冝۝ٸ䶍ᆧ?褒㛋㋊垒噘壘쥸?잌柑䷏✘鲻犝訠뿢㘴㲭▱⧰烈ꄙᄢ?痒莑ﲒ쐃됕릶崙롅孫ӋⓅ숮㱽邹兾䙺義쿷魠問雡ꯡ㫊缌멘媚냇׌ϯ홲쳼?尒?㣿⪚䮬ᗝ馶碵⻃蔱㸖䟽诜漟善逈엾ᢃﯽཌ䳁運䶈䍳䴘㷉뉓篴??⎨果놫﫪⇆ⶖ愖윙?巔젍臗䬗꾗꽞䠩혠烴瓝﹄䉤혞ᾊ聄噔?簸䯹풠撖䚿ྏ駎媟줪沇ី梤폀灷篮Ꙓั悽偶镚輿βₖ䂫㛒튋哋戈䤘躟萄ꅲ⺴㣡ි⡹艝긺ཊ溳餾罄?ᨽꗊ☎㴄版丳⥀晎ꎖᇔﰧ卝執憹멡굍话◊礹࿼\n?埛㺳ꐎ錑أ桺෸ꠕโ㴗슜Ά菲ꋴ䋵騑렔⨯季崓㬃ﴚ縗㐳ࠣ鰨딐샾ﯤ識⢿伳퇗滣ￜ鷲닕㯜䰌?凊鋕翭鯗鞍ઈ缙ୃ迭씎鯀䇌끍뎂ப쨯砐醨ᇚퟬ㺈卆⯭㰗䞂嘴厓⻉뫨᫚뱀တ☼䤝擂?냱焢鿀ꀆ糵宻䈯?켐욚⹫꧿ɾ䖳䈞䎲䐕渱ۇ꒛芳軫?抺晇⳶飳鑵싉Ę쁆㬇剆撕ꃊ禵ᅴ亭➨㮛䜄Ὀ鰏᲏껆艹㨵⥏ँ띋ὁ㏙ᳵ⠷ﻤ쒿?왕歬᝱䨚ؑ䑽믁즴㢳뢽﹐┏謄뢱㕬⟡ꃰ竿摎ੌ殖麿ᖢ묳䠨夥㉢崇栓讎♶놆硲踽볭䳆葷ꩍ㸾቗瘿궎鱱ꓘ俱湈⭝涛辏釂领䒊㤓딟⒗캩鈞得狴렏唿௩쇕亶儰煈䡠튈篿ⲥ婠㍺貏榀傕濎谦ꅪ뜢馎觺߾픻綱⌋咑ᓉ㾦瀩뢆琣Ὕഏ쫰쪎儢顒䀞纁࢘啹繥㕽䞟잖ዶᵠ丒麥脩䢊೨䐡庁丏䳢왊㰽ᬥ蝆艁?ཌྷ뱚﹉쫾捊⎩湩玙⇂㩜⇉憲Ꞥ窋勧壶䝽㵉?䲯ﳅ剮踮㔱擵ﶄ呿窔錳꓅১袠秧驀嗥ʧ깶禴ﾀ殣쿿?侥➅ᇈḸ?ﱡ쵟ꋰ䓪덽쬦嚧撺엃⽒鎃Ởᕩ칫蘨㿪剰娾璹卙쯈䈁酏蝎斦则ᚌ輾旀짃껾⹂뱫枰됓⃸?᐀挊ꬒྐྵὠ죭減翿휨堰㘂腻盌ࢱ奬ꛆꁞ늬ꁴ⋏όᅃ衏砼癜鴏脹콶뾡萟ⅺ?沮䌖扞囸手ǆᰎꈡ呌趆귄?Ⅼ⡻혓杴꒾翦ꮘꕊ俴凕蓀롑鄣렔瀣礧䶥฿辭ᴽ协㍗➹稁ꇄ掸떾ঙ⑹咬皑綸뉏楰፞뺲봵⾾≡䃈즬嬿?力ᤆ䯉ዘ藷豜Ꟑꗆ떰?砓뤥씶⪤鼈潸쎚꘼翅訿ឰ௕鑣ꢬྀ餖໇殺?蹢⯍ꘃ凰鯴䝰嬔蒺胮瓟ފ麥⢌Ჯ璈篭橎䬗꽐퇅鐫碃ɗ籐嵛惪卤졅⻤颇﹫蕅ᕴᲘ詧鲪必ⶢ??囗䘮剝ꩴ蠚ඝ切（棈㭕靓愠ฒ锉̻庩?ܱ୛麲痛ꈼ挢㆏䘆ꅊ◈⽖졩艩딀๨ህ?꣓듴﷼䇙论ɪ츃䫚㜲섓땁먄㞘ㆺ岨꾉闹㗬ힼ雓엍༂醡댳鞹地⬳ﷷ듢?䵶䘼顨ﱗ偐罦౓ꭦ৘ꜣܹ䭭㵷礿潪⾄ᶫ岆ᨵ旔绱湆?苁࡛큀뺊촋᭻ꐫ눋邢茲吠苎⾆淏⧁餻˅餰獆౰蜞儧잛릚ቋ둷瑌鲶嵵쨀˧鼻텗Ⓩ晲乆⠯菆縙쨰⁰稍㼳ጳ?䉲?ऑʩ䷙鎭騬寱뀹裧෯쥄庉鼅ﮦꞽ岋술箓多垩켼殀㝊᥉䛏鹹驾Ṱ濅睯犿哷﬉戟꣋?裏娯ꈍ븂텤膵楲䯝偷仪誹㼰ａྚ麟㗎쓛?擄幙ꈴ≉ﺯ卵눲ꛝ鑜䫰珴넗놪맇槠䠪瓃ꂣᶿ媹꣏许௽䭋鬖繀릫芕ꁬ백초焝ꪧ⩠⤃䭗뢧埫킀Ꮦ쌱쓺鶈娗㢑쏌Ṹ䧿?睟賹࡮脾굃ტ꾙ゾ㉫鯄琲ᲂ᯼?誌ᖠ蔍㸇촌偊栕㑴縮芹ɤ䧷軈ק퍞ὓ兔浗쥂蟦㉁䏆嚮?麨￰䀏麹ѡ뮢⮰⢪ᖗ꾾㕗ㄮאָ㚠⧝䈵滸鲣ꛩ⒦焻ጀ桼斬䅫蝽經㇟䃃狈ⶺ걅⏪?혆력䜞✗䞴㩭췧庄䟊浱巽?뱳䖤컱斋?䌺鮿텶ᙦ鉪?ꢈ?훪蹖뀚懊宻鄐࿺䤫韈뼞岂㹝鑴篡謌Ⅼ䳁˒딱✭鉺徏슩昁ᠸ쯳ࠓ缽ೆ열蹮蓍閕匛葂馴퀙运聴㙋Ⱐ直숅㚯탣칽鋣Ⴠ씉⣂￉?卓賅暌›㾡⟱﹵豘䱬ꑣὋ뉽노?墏兩븜ꈑ?㭪烮뇆ᨰ넗높鎀ϫ⽀Ⲏ浰౬ɠ촌樱ꂄ䫞欦햦౓龋⺎儶볥稤뮺㌸荕⸧耱些儋실姨혇ﻻﾳ㏋䈅꓇夈틝槃絖걦㻇당攰?蜞თ鲰䶢ꈖ鸉묧웥㨶柳側ᄇ븄뎵♿飭ࢿ䉞껅ㆳ鹐ឲ巕䷂췘㬩俖圇ⶶ?Ҽ걷㶯罀⠾쮇憡澓㿊輏坑真촢㤥䡚쾅編徘쀲悃䵮롻凌剶꫺⨨郝メ랸䬞⵼ಽ莑穡朔輁艭Ձ㿈탇纍넽锋᮲ᕫ고ᯠ猅ࢁ묝᡹ῲ릕秙뇠?焘䪈᝔胺礒䂜柇ᴌ堂儤뮀镉⭨戯컙ᴆ⨖├菍㜱ꩃۓ쬂⤫㽃퐍ꑈᄐᯥ뒏뙩⬞ሰ佭칣띹巗핂?㷥䌘쏶倱恾䯕庞死䬛蠐?홹ᚆ튜࢖荁䂪죋ꉃᰅ䏂㟝荵᎐ሴ䫼섿䉽?ꇔ⭄슸姦枈첱ఇ淛쐧ᐹ蛮㥚㇊?虗퓛莋ꍝ尭緞껃奨䍴힄뙬၊䲆紬敏씀䴇倖ꡈ蚉␡ꓟ瓏讧䔧塞奍槬楂禪侅榜呯辍?ᝤ飸㋍꧳?踩?爊㱒ꂹ쵬㕈袓嫜㏙厜羾十῱毓蔿쎭⒞䛂⭵酌ꘇ?頰礄处?瑠鬅?卽▿龻ข㸢衡阡쇌듂诣퍉ŜṔᐩ?깐ꓸ䅟凥栥쒽胔ミ丸⁧껀죀镀柶附ꇏ?举躄璘ꓚ뻼ﻖ핺圿涠?嵨韜䚡᨟領〓楀虊ퟍ⥫?藗ꜞ躈폜櫜죕瑦咪ﲤ᪎佦鐅?줓䐪鸥狙졥퀕坝И幱滿撋驅깛쿇㴬ꌂ㔶瀯᯸偝읏ⱒ띏⻁瞨䫠깔黩鏲鯙ႊ릀씔㒅䦕្陙폯军撝䑆嫰䣛堣ॄ舝欿덉棦ۖ惬튣載궕ꤖ鬫䨷竊䮚ￕ錼ⱓ瑩譍?䢩殤ᣍ萀䲋랜뺰㊷䍋☉ƛ壔䌆폶㸲㿧꫹狵ᡤ뷃衹겇ᮛᶻધ俽숔?秮纡焢垄衻ꏍ哿诎위ေꊩƤ뇳ࡲᤈ熢譇햀⹆맾넋枤읧Ꝟ踺ৎ帠׆ꯃ똴࣓䇴聓罅噏咩輲⁍᠕?怩߸䔅䌅榰??⯶紐並㳸撵홵釠ೢ吜㰉䍑쟺흼햞븿礕욓狷⤦볿̽罙뿿⴪ₓㄳ㪛窆꾬満뚳ৡ럼ᆈ黠ꯚ斳㶁ﵪ玸邿墠菨嫮⊏芲糯떈碃ࡋ梈읪錭葉휘䘡棪乱剪哯裄賔᫴靁㽓ᓖꗰ⃃蔞甈癈誠䞙力ԉ۩⚅䵋\024錁琤훏ྚ祐팎ല됫㺭䞌⠴ꭖ⏈▇⣮ꝅ僬ꎵ⽻ᤧ賏骙㊭㉟鴋ꡏဧ碘键齱慡㄃솕쫹巺庳墺楧᧞ࡤ?歁쾺䬒艶՛㠛?⅊?ꟙ?뤒颼㭅﹗᧩琸❸〘⯛็꿍달⋾勎᏿馵뵆ݯ躭몠澘쾚塐계뮼ﶾᛊ컂黇첃Ⳟ肿燺❔᷼鋽靡Ӈ킩ᕉ狷薔洔Ṹ鮤?鯭䲝ܫꇮꀎ龜諧௃冻﮺댔溲뗄શᄤ᪛몎ഀㄥ쳅묽뵅獺ꨠ垽Ն↬높?澥衙㒨幍밦쨛鸇⪲鉣㲃檠曥抮❛䁅褁尋삗﬒ᄤ雰ᔷ쥕柫稁噷킌潵뱫붞淆഼ꈣងꜜ왦蟧↞㝚?욵⺎㉈ს㹣㞁ﲡꋓ죎䇶업꬀膞卷틏ᝓ푋馠ᚸ⁭꠫뽩ﭶ悪낗䌭ࣾ䡃혶頱ﰠﻈ섵ᔐ抎㬊듵ᓹ澇⯞辘児쨭泎秒豁ǀ鿂ﭺ寧Ὰ袯暩옓䓊蓻ૐｭ崥덑ퟛﻁ롮至ⅆ㺜ཬퟰ흠ㅏ埫㳾䛩鈡䖜탚ꉵ铳?븊ﰛ眑⾓踣뢮鉣䁀ླྀ阯?巩늖ꅓ轅㝀타㣑Ό㾐焔Ṯ濿㟮ꠘힸ瘶馅贇◔ꦅ쭾㛺ሃ俒괡뜫젮悆䪷毝ꟑ娻䝪퍳Ɓ᠍麈ě㗈纚亀諍흪叓磑ꗊ傤禣ۨճ폂䴐砨䐏̉싶螆㑎⠇燣ぐ簰?ꌂ㨅錙↎忩㒞쒹⑟荪捶孜임盷媈㏐ꋹ䱠놯ｩ迆엑≋뽹?歆⺲쯾懠㙼濍莵柷䎫⃻篨癫৔뗯佾࣫箧敝熼䏴猢剜母겑꿹瑕↪맥Ϝ诉ꞹ溟ঃ聾ᢒ牫檦쭚꫆稱樷嗀ឡ罚踟챻䰹廉ꈐౢ䷺奸䮡蜏젴펨퀢쵠燆殽ꘃ㠡⊅䄣蒂▿ᣥ儆ꛎዠ䟁ꜞ୎㳠帥ବ녑ẖ瀢퍰⨹莪懃?꾨ᖲ쵑꫁ᎁ᭪렜ꓝ눘鱈҅䡐?鿎컳Რ餅㠐ቡ崓\006쬳渓ዽ褺㗗筵ퟧ尒룶뢧靼덏㇁癪여豗ᥩ⢛䊥䰂ｦ㹡䨱㚕⌣颳᝜॔࣬艸铏ꁝ짌횵ꑻ떉靡颅眆䕨픪훋锅䰵쏸គ싦焖蔡䕑顐笪퉐竚ᥘ즓ꊓ?旰威쌑㦻⺶개犥略놿䳹讋쳸㐞ꍥ㡬坑掫穟?ᙲꍒ诲⟒⯯ﲂꪕ䌨萶ᒢ頨띍ꖍꪜԮ鍦㖗Ď廷絆뺼衽躇秿䰜鳰訚䦝ʙ픵祍햮꾍䥩ꨫ齁࿝闠奣쇑ૈ笶븁뛭⧀ᷔ漗픑웝샑㾜⹤熧䚤雛庑⸢蘰曘艟벒ც惃栱ꅂ친폃祃⹾ࣥ뜃䪻矌嚄䨊䒠홄म捀錞䦚摂ቩᶳ꾈ޓ䁪䔹斔䢦獉뷐ญ⦬䕞ꜰ?ᱩ鲟ᴷ朊싙喭⑓珫Ꮝ宂窼ⷙᖕ海ꙛꚑ唭篧㿢킟狊嬢ጬ䆓誸묟?밃ݥ蒧㟭ᜩ菭먄麉蝹嫄쌉ࡣ좃袚賮万斺फ䈨⤙〄邼궈鈑쿛뀿⏪ꇝ풧榝ᚆ࢘齲啠ꫀ᳣瞃펍⃗첨ꩲ袩ᔈ⸱?쑧捙悭웟秏ꍗ㭤쁬穗ڂ䓨ԓ녓㑙䎴⡬픨뇔ꆎ鍒攧쩢Ⴛ㯯麉㣀ퟀꯥ劐癔?瘋ﳞꎎ콡笐公㒺Ꟗ噄桑秿ℿ뚒﶑達㕷?뢘빟হ纻읮ꖭ៤螜릴?㳉쀗ᓱ귓벑潎ﱱ✓蛒欧䬌⥝禄ꘑϟ揹⹋쮰쩘ᙕ㔧ᄾʕ꛼ﮌ嚝犡ɸ奔웶큪멸ᶓᨉ団㳈덏菈똨챐娤ꊟ⥁ן䡤双✓譆䭲㴃僂缙璇䙽㲯횫㝱ᩮ兿᭽໌잯₞鱞冘퀮䋞?預兴뤗摄左騉韡碲࠘움敘킊ř퍔븮尝䃣⿃砉霑손膙맺뺩ꝅ俖퐙㰴ꦝ⺿ດ靧螉ɜ潘驾츞?滲਋¶뚳ࣱ숔㖽ࠄ㘬?탺쯗䅳뵉ﰺ?蔎⏴챢嗁㯾暴妄ꁼ烩ؤꏬ녷냕勒㖽ꁱ鴯錭㞫㸗ꕤ費䬅謧컐뺤駖?酾﬑ݨꇠ瘄?쯙㋭긌﵏鼰Ꞌ籪Ɍ䑲餈㍩ᱣ★⑼녓꯶鱴븘괔?⩘襄塻ꮇቸ㴮軨धꦒ狚彘氲ꓠ涜ᤅ礴긛ᜍ饉燀﹢魛圙雬׊뒰苃ə폅톟몎댱襝伈⪞뀭㹓૚戋쳣䕞䭷?堋ﮧ䅜炤㳩蕎ꇭශ넖묆䨟囑聿坑逦ꌞᭌ就넀ꡯ裺ᜯ擌迵깰Ⴎ蘭즞迂Æᰘ첶ㆎ藽ر竎羗㉰⩹?홄謅ㅧ觵詘Ꭲ⚠౾榪봴傍鮴ቸ腴冺晳Ҧ澸奀숾ꒃ햿㪠⨱苚킩ળ슁⊒뛵쉑他螒쫓㋱瘂冩볦祿٧㭫쌝⣚毨ꪂ죌覢鰵䈪䋬㆏꥚帟⽖穘퐰㯗ꑖ吩촟ଔﷸͻ孳ꬕ哛骱ꅹ灌灠栧ቹ潋뚒痰輮觢ጫ廖蔤抽ぅ쩪͈⸌瞓㪗臾榾﶐뻮球䳭膜걆쩀䗕⿘氨桾ോ뎒썖鄥傶Ô搧漴略⦆擭㡹刣揼䩐災믙??妦졡?䣄ྼﻹἛꯥ?쪬ꔡ㞧✚伋❠视ﹾ焉㖔댽埴웭ꦤ計䔺ؘ駥呵遥?ㄟ媷퀴싥틗쪢瘔쪰╈ǽ஛核䐄⎦䎞럮揪伳⮁縺乩瑱鳅쒘琘ᔇ쎪묎놗ࠚ䀚ꟈ栟䈘儮ᢓｅ券힐캷迚濍⎋幘괩ꋨ㿣䑖ཨ픇㽤Ⓞ⽇袄뿳?ꯐ㑤⑍崧侔蜥ꬃଽ홧✡Ḡ綾蔠ᑨ鱗ɔ縷嬇챮贈ᳮ퓣砫皽精捖ई驀'ﱋ꺘괽ʟ謔꯽袦퓷떙?怋ᩈ뺅顐㉂軼삵ྲྀ⑳汍萊㽀ෙ?믟噚ꂶࡌ翯ᄨ놾䀬ᥴ樳쒼ᇏ﨧娋z䵺荃렕엚ԇꗍ桇⚜ꪦ糱匽簘搬뀀뻍鬡椕㘉誀捞挾刭ⳁ֯ࡄ좀壧曽뎰⍜耧䦅怌ϲ쩶䩢䳹壒؊퐐?膝૎陘됰㈣ᰚ嘯棛底鑕焄苔䶗䑰뙇¾轾⃫ꯄ炱ꔁ檜汹?瞇唿┋삊添∆僴顮﫯懒鸺理┽썗侰캷뼷꧜⼁蓪䚧䉊眡铟−ﲊ㜒ㄑ鰦醪᪋傽䘍㲈刲鯴副⛾隣땳䂉឴弳ᲐἻ斟붏剪蜛ڂ혓䕴櫝䘷虺㧐蚹蚠蠮怉䎤잦㑫煛ၸ헌愁㬤禼뤼쵾䥿୕ﶌ㎵쉷쁸奖莛᳕쀠ﯧ뺭࢛뇢찵쌛暃꣆ё舡鞺觳赣셑휧靰꼔螳㤸꧙\020瘥ﳭ⫥ᕏ啥͵槀砰㐼ヰꄟ즶繒籐鏾㫰횺⺈渥꺰☄똡Ŗ挆쉏秔례ダ水콟袧☕㊊콋뵚飃莐㪖╱ᒜ㒽⦯ဗ⥵삩ꪄሩ⡰驃媪ᜢ⼵ҩ浙ꚡ?㥮툩ゴ᳁છ衠阬趉Ղ䠎嘳䘔樍͊ᴚ칿ᝢ恠競猔韫꺋얒羆楡淋謘᫣絑된䤷亹쿯饦裴캊霤ᒈ级쒓败麳俌遼數Έ蟓푀昳涢딏馻䗙뉉钞ษ쾢⭀톸ﻯᤳ륭＇⏝뚲㐛笫笠枲麱਷㪙ᐓⰼ촫ꖀℨ笆⽡滵䫂伹祎㎳ਸ㏫숋삄啉碊伊儝䰦ᾬ㥳䆏ﾍ尢逯舲끅暒瞮☼盛咶ᛁߓᶮᏵ⛲꣮㿙榧磖摭ﭔ铏壤慶੽熶짖ﭽ麭裸힁篬僂傾乧顱勮⮳秀?ｌ퀃熡膱မ䴿隑ꆏ擌녏ᶛꭚ燾삑Ĳ辩㐷⎣ᭊ몎ṝ謟츷ⷽ秨ꩧ띫퓭椇꿧孫갰뗢ᄨ끃慽㓠䑌䑣矖뷈셗풂ꉧὑ폤킡䮦䈒阋㤮㲇憡삕ㄝ괺㢼Ꮊ콳锑큎邿왌滑됷ꃆ鸐?衉壡濉뱿樜멵藎蓑ｵ㵁䘛뀄响珍駒卼孡뤀⅏ꣳ郏㽣㗦苼㋢ﱦ竄䗕鬆رﳙⅲﴓ虼ᐙ쏿嵙凴ﯩህ뙿瀕輦崟ᘤԙ瘍?㊹ㅿ戰鋱❕钑❣欳촮뚽硐搏ࣱʋ⃉틬揺銺ⵄ睋餡䭲됝﫺觢쏫踫틘씶틉䟗䝁ᝍ雌癁䤒ⴆ祔?燂슿៕緺绌樦ᡂᘽ댪榮ↂ䤩﫱ⴈ䚙굂雙夠ﶻ㞜?馞䄅ﾬ羰驾䀑懱ꝙ⹑ꃕ㫴ﱦ佐넯㜃⡏❩Э뗣믲䅞揭淬헊ꓕ썸魅蓗젏旈ꦒ譴冖诵㸫뉠鴄즀쓶艦ꑧ긽쉓蕋쮛珰탶ꨯṘ乳貅༓Ṡ鳏ᕄꢏආἙ튘ᚴ砑駱ဓ薮?៑準ั皹發恝ቈ暆馜㄀쫰陋ꆐ勇ډ贋눍枂룹决㒼餬悚ꆻ츘ᬞꝞซ燯㛿⊑挴ેꟋ棪쯎盫㱵ꂺｻ攇毪?储쁤船馏뿤硬ᗯ➱?槤㬠ꌍⱕ駫誟᭽涐ᢹ䡙ณ램⬤ҺꑙẸ震蚒쎛Ⅻ薌⠳璍赟厞앓ਁ쏗㔘₢ᐣ灗蚊ｷ仒楠ꇘ幄읖뻭㭮㙭씔?㳍蔲?킏镈壵⳧巠䱝⌋◚躽葝穇蒇鶓롘ل맩菀ꠗ૔玃盢⒜ڔﲴ﷠?驂?ꕖ뼴ᅅ⎗㵸?珧黡狾漤糌ἕ拉꒪幄媒䗮ఱุ糡棞丗撰葮뎹᜹凤噽㡶?皻쒰ﯬ㨲쒂胺䝚鮭彖ꖼ㎭肥ᯎ۩ⷵӥ?䋙㯪僦雊싟퐝俟淂唷暯䢃贖벤䎤䔂ﳐ餍握䗺䋎Ⰽ뺪凴䐊難갍ﷰ筄蛟閿ボ襱シᅷፌ끷䗾ꩊඍ䥔슏ẇ檻滘䃈ꕏ믲携㥜摃䳖睁툨駦調?鵡?蓓뚻踚䱽걽﹵塤ﰁꠝꈂ欫梑ﯡ앗ᶅ붎ﻟ⡭ᒓᒶ୛⠦⭚쀭觧뾥촋㺧ﲧ볡兿ᮓ庰ົ듸溍拠剠ꭏଃ翲劤鴧ᣦ毤ꇱ싽₯砈⒘칣팫쀞잌暢?⥛ᑱꜨ奘얏뒪쟉膄땙䓖ɳᰬዺ㓆ҍ㢴쏇?㌌膊ᄧ퉜蒠ᠩ鸦蒖ꀅ롡ﻇ뮚芆?髦ﮫ욤弗ㇱᓰ鰥㜢‟ꀋﻀ狼ꤣ얦ᇻ돀钪琷좚귈Կ왆盷龸ꣃꒈﳟⳂ朣뤱ꔇ孠驢検ᨁ轔닾♨㼺捅ࣄ惚䝥牿⾀떃읈츾?럦ꮅ艻ﲵ脁⡝⻓옹㘷驫ﾍ셺ஶ䅡잀䣋魉랺꼬둜ꛈ땴낪겿虰㙊۝꘾공퀀ⳗ䄕㏥惾蒾䞱䩖㚠᠉䋮댅ޣ爰㗔ॅ䫿ⲯᦨ磠禆翤䪦ஒ챀⨸댹牟핈䞳埣꣯䤵﷓曵?崬緘에廒ℇ䃱誷䠒岜霨彜⃧놘ฌ?몼ൕ互韆覞甘?쁇ꙥ㮻⣮쯾戽꫏碌溰℉｟뎎୸ȴ釒윢갻戏逾敗餴׶Ⱒ箓힨㈽࿡竰୑橿耡鏎ﺂ樬呯买壂થ෰뼠䞆쮨껂㲼㌭徕行쨿⃑휩၅⋶睯ᷱ鏜ȯ䧒죬㠚켟Ὢী賈썒鍾ȉﳞ?쉉ࢹ틱錽羽ᖣ햦罁ৢ쐼攭辫絜Ⰲ袈뚙ᓝ錒㪒ক蕩絧눜摖ᜟꦲ簦轒ᡧ?琋ᗠ⽡蛝橛㜼鐘ꭍ圗觅郚釃읓?ᜨ歷ᤘ䔠ᇞ톦袋罵㛀ힽ㌛궚도㊼⽛蠿蒵瞟ޢ估ᨥᣤ星鿝വ㰮ꂥ鐓鏉⩋ꆡﴽ䬼ﻡ潹␄⪳ಭ糑苞?傻䓝넩镂畨뇐㬰褚褞쥁㩍艱䙥篊䋃೴悈橴冩륯꓈穫鵟冮匿騞淃莁㺂㐏듣푹떅冣៑௝⸋竹푟ဓ貕ꁞ喌ꎏἷ贓읩Ӓ፷ྦ㦤ᳰ겊摏呩桽楪䧨몐瀋뽓쨔⽘쨒窓拦筹ﵚ，滚칌缬徊?範礝霥ꅨቤ㮽碧朶稟腁䂞⟚웼愈꺀ᄑ쒖瑸篫쬀衛둞홨ꮓ웈ཬꄂ鰾蜠䑁傸욲⼒擬爼❅뛆奅웺珩褀꡿璮桵摎鋟쩉빌龽諞㬯쒐绎࿑෢喩咒䌠〮?垰੷㝟죥꽐刄谼꘩ᷕꗪᾥ纸日﷈推㱹ꜛ瀀柑粶Ⴌ⿥却鍐⽁ᖍ♱與ꁪ鶘䊙볨骃兵ධ蟯椪썫翩ܿ⣾쫑溞佴埘縥룙㚊锷뀣襥꼻?뭨㼌渻ꨴϑၯe廚Ἂ꨺?쑪ﺠ揋雨宔鮞琉压䱐拮띁螦Ⅴ桅簪ᕈ턵㬩떻硔အ㉯⿚퐿쭒累폆뽘枒숔㚙ꖰ䢜Њቔ걦౼㑓々⒰掓㴓禅囗㚂⸂း蒇͓爏懲Ꮪ㗽皕摿겧栝ㅖ掄㜭馻옚ᄘ䒈埖쐣㣇뇢븋䭒ਹ웜ଃꄱ㑐넡ᷕそ턬昄㰠ϯ볁‟뭴怩뤕㏨嚔爷鶇ꖋ?૶豪貆隬榥ꏲ扶쵄?墩Ꚅ攏?蕜縌അ缞뫩꠯⭻歙ﳘ⹀讫춑ƾ牲㙦沁⃯?壡㹖ﮕꁝ堗澩悯箶☯ᙹ㦻礨顼⡗緐嵲䛣襻迌魄艏哿ﹻ嶶켻憤䁁陋ᆰ叉꤇谸㏂减怦䧤㬾ẑ릿ⳇ暕핕钜ꌰᛕ镑瘠﫹踃̳晸ⰷ霒燙せ䋎❩輙殒ↅꎄ梲盹䜬Ů踌ꣁ뾴뎸欢뇅尅餲酈딍ॾই쑷줿⺀㞎饃짣库枯덽ꐋㆀ芐ᵔ턈䭼⯙蟷춬䘯熾䉺ꩫ㢧ꨜ铿覨ꚦ䀋砵␸㲢ܾ桳켈鱪➭䡒솛쓵ܼ㰻᎝䥮Ⰽ酉?紽ꑧꊈ뚹猒䄯큧⿥?腡홼讞痦쪑殳ꕩ゙慵拻鴸晜熻쿭別❜Ⳅ灗獖슎䛈㺘篏쬛쀰툱ᲃ䌙吟㝮䑅䢌\f讁艟籨랤쑨萌쫳ខ蜶⢅潩䃖澰⡢❗렕?곂笂잗㮎袔៮फ़栶휎㷜㑬蘃䀦䛦៮ˍ疑쎇鸑迹晦뗏꿡셦⠕੍ĺ晘朎ﬢ᳞崦䁵౎聣鿼ᴢ᫻Ṉ䟤伵竛澷顎쬢涊硘丗緲鶋Ȅꊈ阌Єꠧ燇평䳇ￊ绀O議㯣ꀴᩢ얿㐐䗐썀ꌰ층솲袨쐟㎦묇ꈅຉ豚튾火鏚颟郦殂넾ꜬӐ풷๳飡䵅红옭呴ϻ辩셹?ǚ򉩽ꯉۓ勛㜛櫹糯?ﳔ彳獆䦴⾔㐦鴥蔏ⲉ壂魕ﱙ搛橄怱֥㽿꼑癭ᇾ斫蟭᪝◘잜?葁밠앳Ȇ㵃䗿䚗煅ਉ竽扄Ϫ薺嚦䖋ꃦ?䷦ۃࡷˢ㥙숗業걜⇻Ụ饚亟芢蔕쉐玷ꋕ၅?ᇏ쏱딍枰㿳쥰钵棫뙲๶ᮬ6슨茁ᓼ倫滢毥髫罧쒯毤為祄뱮↚裕帒䰣鷌磌針㊪꘢䪃鼁䛂갶녟姹닺ᄃ➥휩❢홡ꍽ첦⚍䃦耎縈⸃໯⼃꘠볎싎ꦷ샡郘綩亿믊牿ꆯⶔ剒Ⱌȶ纍ೇ蟋⏓ក窹眻赇㋔醁뷩瞫ꃈۜ全ゟ厌Ο◇ဳ䧸猠څ絛貀畻亇ꃓ銘ꖗ゚秩⧮녖鐪㔹ý炇뻁寧䲚ﵹ᪐仂讋꘸?䰵㇭ଭ歱䭸㯚캉䵲芅ᅆ ㏸塪ꭆᰟ筑쯮玷䯅੧?ᩤ⺸鯝੨䓁췘鬤㾀䅠⢷챽禈蜂ꑴ䖙ݴ㵲⧡⡢텔쫅襎攻ᕌ?␸媰⢔뽐莮ꮝ|훹侍礪黍촒뱩㦘旰斂︐ኯៜ좛埝ೈẇ㥠ￒ魯㾽㯳?௪駰᜔濥໘⤢蘄受⒋垎ᦰ⮲蔕꾳꽜톭῏◧먖퀠猥Ỡ䅳켉甝?脹诼澪힡䈳ỗ๪䵎鉏箮㧇뻿몸ﲥ嵯ǔ瑩ូ甚猺ꏃ⫚䫞쎪掼赲幌﫝뽗鯟撌୐짖ᩑ錡૾祰ꞡ뿸嘕?⧹㨔ꈎꝺ鳘ｵ졘쉨㽀鄵པ蘃詷忚欑﵃莃冉⚙዆艭禘䁴龡詺省墚ﳕ췑䟙슴盫⾯ꕅ疏蹏ⶋ햝傦㤘愤镁諻훥퇶箓灵쩪ꐠⰏꐛ靇᪆ᤸ䯭儌洍ꔺ亐종㠕૨ᛰ뵦ꌫ嘄텪鳈犊㢥傞렪都笸龇ﱎꒁ༘Ⳗ沭ꟊ俫惵췝ᱢɭ㔡獀⊴뀨糛틩?䔝Ꚑ㌈㾖鳆殍齪࿨ὒ闪烎ⱐⷉꮠ◣∹ℼ왥螚ዳ趶ꦚ涅뗢ᰈ넇橘㇮﹩洝Ⱡ⼳湭㚿ᓏ⸥똸锟㜉︮텁壄聛?㭆둏㓰瑠衋烳᠗ઐ确롇팞ꊈ麕?⧠堇핢㩴괂᫓ㅑꞛᖀ੤⁏걎⬁惨殊ຑ豵鬒䵰쑈黗ꅳ뉇ᮃ韮΄ಓ㔵篁葧瓸樧퀠⾮䩣ꛘ赯只쟥ꚳ툆⽻ⴘ飇ᔻ㔄퓟빘ċ酺圼컅盫欘ᩅ赆妀∠テ眢?톈쩤깽鰶툧Ṏ䩗쫫埾쒑꽔乣惊暩爵㴈캎?ᤷ潘켐歴⸣쵇∤⾸ꥊ셏쓄伽͛㣒﬌㐢ꌉ㑰꓆㿢삊탹莫낮毂ㄪ棾薍鰡荷λᎤ墋峞젅졈᳕ͅ銬ഋ޻둕愛㢍䧍膻鵎砍卶绋賢ਸ਼Ც⸍밊݂熧蜂첫観᭛랇缎?릿ڴ㍷햠቟塳췆悚㏸儜ꥋ¥ꈔꤘ☆毁?彺뇲룏鉶焚ꛬ籅앞娞萲칄臨ᑻ끱顴ߙﵕ䯰␹擥꿅퍟誺ꊛ褡腙㛴⧲툲緧⛓幻ꂟг갃꘡윃낄䯵嵞㩻ൃꓮ⁍痁㿱୸ྎ밁꿩랕戆ﰦ룼犐賈滑שּׂ鳝Ⴢභ데堌婆ᎎ롟癇㤂?샇፩㐬䲥㴺᧚㮀﫭⋈ﰮ页?撠韉倉뭰譾‏隵༔䡗쟒夿┎媂ꄊ⯙毀㩠儉狑ₖ뭦濑劅댈蝮☆䅲뎜偭䤫燊䓥麟肊༇鐸嵴掛ⅳ䨮⫔琢ᴷᓤ忴ಧ㉮朶죠튰弚芔단┬䒖ⱔ㹜籐䃘맪浡鎢睊筫헐ﺽഏ闔㵞佞鵢✃紾쉎荲疊홀뎌㥘窌澧鹖郍뽸ōࢁ粄榒৶䐮刚旀삏풠뵉≰綟窾땞?伧獵듴捗發匜ྃ䠱誡ケ랶坷濬娕ꋽƚ됂騎⸝ླ勴쥉錼곣鋜㌠深鶌瞎⦣윾⴮송짴䒖妩".toCharArray()[2959] ^ 0xA8A); String str; int i = (str = dP$dt.X("渧ﾣ䧈⪆顛Ⳣ撑姨﷧ꝟ碏Ѵ騏嫓㬱$큯ￇ䟘굦㘗ؚĚ됃祗蟃ဆ㯛僜騧镸䛆쟪뺘隟齳⽳䆾劭惱⚳鉛풁멌꜅ダ듺禎㙯洼鈁ꚵ剛蟶㏜汹慵徠襑ࡠ䛦?手酼⻢磎ᤏ鬰ྟ햧圡㻡⟤㬥貜묐㦮˾뫉᯲斔醸禕︉饋婡ᕁ藣␡讈篂僌¼対먶㉺?⦎鷢ᮬ䐚녿ꮕ滁瓐Ư䷽ෲ꟭咎ꢹﾇ뤫㐦䠖퍵씖꼶鶏懺耵ꪤ䛌鸚䤃唽０쿏✮蛟릜ỻ엁悵晃Óれ磑濊☘ﴘ款듳촘弿摠䋦聑倌鉶˝잚ฮ眞抢絢?ݤ騄ኮ춷艛瞛厬ݛ䁯鈘偑㪇㼛̱㬰骆铘쮿䟩ꀂ躐认ﰛ㘥欘濾쇷碇퇏ᰅ꼎郧丯?导㹍齅ᯭ劽콌鸞ມ렢拼ᐯ閶僈ℍ췾읲턤᲋ꂗ팢犭ᕨ㈄箈潐⹙럋縻풑뤀揹紾磦䨉ꗤ↸ꂵ캅있誶?㍚⽍㿱킛ꔅ꺮쨺썰﷓游䃶䑢뷯寔㔐꿧᷇扑ꁁ?ᅯ椝쨚䅁龋ᄁ⣄ꬬ㸃乽뎮ኟ趞즆栧曛匞ᣠⱘ漒瀖?旡ﲋཫ怫啔璗ൿॸ岲੍勦졸⿚โ곤٩?ꝩ籇⼐銤軒贳궉銺㉜꿄㐿壿ウﲞ뭄촓冝۝ٸ䶍ᆧ?褒㛋㋊垒噘壘쥸?잌柑䷏✘鲻犝訠뿢㘴㲭▱⧰烈ꄙᄢ?痒莑ﲒ쐃됕릶崙롅孫ӋⓅ숮㱽邹兾䙺義쿷魠問雡ꯡ㫊缌멘媚냇׌ϯ홲쳼?尒?㣿⪚䮬ᗝ馶碵⻃蔱㸖䟽诜漟善逈엾ᢃﯽཌ䳁運䶈䍳䴘㷉뉓篴??⎨果놫﫪⇆ⶖ愖윙?巔젍臗䬗꾗꽞䠩혠烴瓝﹄䉤혞ᾊ聄噔?簸䯹풠撖䚿ྏ駎媟줪沇ី梤폀灷篮Ꙓั悽偶镚輿βₖ䂫㛒튋哋戈䤘躟萄ꅲ⺴㣡ි⡹艝긺ཊ溳餾罄?ᨽꗊ☎㴄版丳⥀晎ꎖᇔﰧ卝執憹멡굍话◊礹࿼\n?埛㺳ꐎ錑أ桺෸ꠕโ㴗슜Ά菲ꋴ䋵騑렔⨯季崓㬃ﴚ縗㐳ࠣ鰨딐샾ﯤ識⢿伳퇗滣ￜ鷲닕㯜䰌?凊鋕翭鯗鞍ઈ缙ୃ迭씎鯀䇌끍뎂ப쨯砐醨ᇚퟬ㺈卆⯭㰗䞂嘴厓⻉뫨᫚뱀တ☼䤝擂?냱焢鿀ꀆ糵宻䈯?켐욚⹫꧿ɾ䖳䈞䎲䐕渱ۇ꒛芳軫?抺晇⳶飳鑵싉Ę쁆㬇剆撕ꃊ禵ᅴ亭➨㮛䜄Ὀ鰏᲏껆艹㨵⥏ँ띋ὁ㏙ᳵ⠷ﻤ쒿?왕歬᝱䨚ؑ䑽믁즴㢳뢽﹐┏謄뢱㕬⟡ꃰ竿摎ੌ殖麿ᖢ묳䠨夥㉢崇栓讎♶놆硲踽볭䳆葷ꩍ㸾቗瘿궎鱱ꓘ俱湈⭝涛辏釂领䒊㤓딟⒗캩鈞得狴렏唿௩쇕亶儰煈䡠튈篿ⲥ婠㍺貏榀傕濎谦ꅪ뜢馎觺߾픻綱⌋咑ᓉ㾦瀩뢆琣Ὕഏ쫰쪎儢顒䀞纁࢘啹繥㕽䞟잖ዶᵠ丒麥脩䢊೨䐡庁丏䳢왊㰽ᬥ蝆艁?ཌྷ뱚﹉쫾捊⎩湩玙⇂㩜⇉憲Ꞥ窋勧壶䝽㵉?䲯ﳅ剮踮㔱擵ﶄ呿窔錳꓅১袠秧驀嗥ʧ깶禴ﾀ殣쿿?侥➅ᇈḸ?ﱡ쵟ꋰ䓪덽쬦嚧撺엃⽒鎃Ởᕩ칫蘨㿪剰娾璹卙쯈䈁酏蝎斦则ᚌ輾旀짃껾⹂뱫枰됓⃸?᐀挊ꬒྐྵὠ죭減翿휨堰㘂腻盌ࢱ奬ꛆꁞ늬ꁴ⋏όᅃ衏砼癜鴏脹콶뾡萟ⅺ?沮䌖扞囸手ǆᰎꈡ呌趆귄?Ⅼ⡻혓杴꒾翦ꮘꕊ俴凕蓀롑鄣렔瀣礧䶥฿辭ᴽ协㍗➹稁ꇄ掸떾ঙ⑹咬皑綸뉏楰፞뺲봵⾾≡䃈즬嬿?力ᤆ䯉ዘ藷豜Ꟑꗆ떰?砓뤥씶⪤鼈潸쎚꘼翅訿ឰ௕鑣ꢬྀ餖໇殺?蹢⯍ꘃ凰鯴䝰嬔蒺胮瓟ފ麥⢌Ჯ璈篭橎䬗꽐퇅鐫碃ɗ籐嵛惪卤졅⻤颇﹫蕅ᕴᲘ詧鲪必ⶢ??囗䘮剝ꩴ蠚ඝ切（棈㭕靓愠ฒ锉̻庩?ܱ୛麲痛ꈼ挢㆏䘆ꅊ◈⽖졩艩딀๨ህ?꣓듴﷼䇙论ɪ츃䫚㜲섓땁먄㞘ㆺ岨꾉闹㗬ힼ雓엍༂醡댳鞹地⬳ﷷ듢?䵶䘼顨ﱗ偐罦౓ꭦ৘ꜣܹ䭭㵷礿潪⾄ᶫ岆ᨵ旔绱湆?苁࡛큀뺊촋᭻ꐫ눋邢茲吠苎⾆淏⧁餻˅餰獆౰蜞儧잛릚ቋ둷瑌鲶嵵쨀˧鼻텗Ⓩ晲乆⠯菆縙쨰⁰稍㼳ጳ?䉲?ऑʩ䷙鎭騬寱뀹裧෯쥄庉鼅ﮦꞽ岋술箓多垩켼殀㝊᥉䛏鹹驾Ṱ濅睯犿哷﬉戟꣋?裏娯ꈍ븂텤膵楲䯝偷仪誹㼰ａྚ麟㗎쓛?擄幙ꈴ≉ﺯ卵눲ꛝ鑜䫰珴넗놪맇槠䠪瓃ꂣᶿ媹꣏许௽䭋鬖繀릫芕ꁬ백초焝ꪧ⩠⤃䭗뢧埫킀Ꮦ쌱쓺鶈娗㢑쏌Ṹ䧿?睟賹࡮脾굃ტ꾙ゾ㉫鯄琲ᲂ᯼?誌ᖠ蔍㸇촌偊栕㑴縮芹ɤ䧷軈ק퍞ὓ兔浗쥂蟦㉁䏆嚮?麨￰䀏麹ѡ뮢⮰⢪ᖗ꾾㕗ㄮאָ㚠⧝䈵滸鲣ꛩ⒦焻ጀ桼斬䅫蝽經㇟䃃狈ⶺ걅⏪?혆력䜞✗䞴㩭췧庄䟊浱巽?뱳䖤컱斋?䌺鮿텶ᙦ鉪?ꢈ?훪蹖뀚懊宻鄐࿺䤫韈뼞岂㹝鑴篡謌Ⅼ䳁˒딱✭鉺徏슩昁ᠸ쯳ࠓ缽ೆ열蹮蓍閕匛葂馴퀙运聴㙋Ⱐ直숅㚯탣칽鋣Ⴠ씉⣂￉?卓賅暌›㾡⟱﹵豘䱬ꑣὋ뉽노?墏兩븜ꈑ?㭪烮뇆ᨰ넗높鎀ϫ⽀Ⲏ浰౬ɠ촌樱ꂄ䫞欦햦౓龋⺎儶볥稤뮺㌸荕⸧耱些儋실姨혇ﻻﾳ㏋䈅꓇夈틝槃絖걦㻇당攰?蜞თ鲰䶢ꈖ鸉묧웥㨶柳側ᄇ븄뎵♿飭ࢿ䉞껅ㆳ鹐ឲ巕䷂췘㬩俖圇ⶶ?Ҽ걷㶯罀⠾쮇憡澓㿊輏坑真촢㤥䡚쾅編徘쀲悃䵮롻凌剶꫺⨨郝メ랸䬞⵼ಽ莑穡朔輁艭Ձ㿈탇纍넽锋᮲ᕫ고ᯠ猅ࢁ묝᡹ῲ릕秙뇠?焘䪈᝔胺礒䂜柇ᴌ堂儤뮀镉⭨戯컙ᴆ⨖├菍㜱ꩃۓ쬂⤫㽃퐍ꑈᄐᯥ뒏뙩⬞ሰ佭칣띹巗핂?㷥䌘쏶倱恾䯕庞死䬛蠐?홹ᚆ튜࢖荁䂪죋ꉃᰅ䏂㟝荵᎐ሴ䫼섿䉽?ꇔ⭄슸姦枈첱ఇ淛쐧ᐹ蛮㥚㇊?虗퓛莋ꍝ尭緞껃奨䍴힄뙬၊䲆紬敏씀䴇倖ꡈ蚉␡ꓟ瓏讧䔧塞奍槬楂禪侅榜呯辍?ᝤ飸㋍꧳?踩?爊㱒ꂹ쵬㕈袓嫜㏙厜羾十῱毓蔿쎭⒞䛂⭵酌ꘇ?頰礄处?瑠鬅?卽▿龻ข㸢衡阡쇌듂诣퍉ŜṔᐩ?깐ꓸ䅟凥栥쒽胔ミ丸⁧껀죀镀柶附ꇏ?举躄璘ꓚ뻼ﻖ핺圿涠?嵨韜䚡᨟領〓楀虊ퟍ⥫?藗ꜞ躈폜櫜죕瑦咪ﲤ᪎佦鐅?줓䐪鸥狙졥퀕坝И幱滿撋驅깛쿇㴬ꌂ㔶瀯᯸偝읏ⱒ띏⻁瞨䫠깔黩鏲鯙ႊ릀씔㒅䦕្陙폯军撝䑆嫰䣛堣ॄ舝欿덉棦ۖ惬튣載궕ꤖ鬫䨷竊䮚ￕ錼ⱓ瑩譍?䢩殤ᣍ萀䲋랜뺰㊷䍋☉ƛ壔䌆폶㸲㿧꫹狵ᡤ뷃衹겇ᮛᶻધ俽숔?秮纡焢垄衻ꏍ哿诎위ေꊩƤ뇳ࡲᤈ熢譇햀⹆맾넋枤읧Ꝟ踺ৎ帠׆ꯃ똴࣓䇴聓罅噏咩輲⁍᠕?怩߸䔅䌅榰??⯶紐並㳸撵홵釠ೢ吜㰉䍑쟺흼햞븿礕욓狷⤦볿̽罙뿿⴪ₓㄳ㪛窆꾬満뚳ৡ럼ᆈ黠ꯚ斳㶁ﵪ玸邿墠菨嫮⊏芲糯떈碃ࡋ梈읪錭葉휘䘡棪乱剪哯裄賔᫴靁㽓ᓖꗰ⃃蔞甈癈誠䞙力ԉ۩⚅䵋\024錁琤훏ྚ祐팎ല됫㺭䞌⠴ꭖ⏈▇⣮ꝅ僬ꎵ⽻ᤧ賏骙㊭㉟鴋ꡏဧ碘键齱慡㄃솕쫹巺庳墺楧᧞ࡤ?歁쾺䬒艶՛㠛?⅊?ꟙ?뤒颼㭅﹗᧩琸❸〘⯛็꿍달⋾勎᏿馵뵆ݯ躭몠澘쾚塐계뮼ﶾᛊ컂黇첃Ⳟ肿燺❔᷼鋽靡Ӈ킩ᕉ狷薔洔Ṹ鮤?鯭䲝ܫꇮꀎ龜諧௃冻﮺댔溲뗄શᄤ᪛몎ഀㄥ쳅묽뵅獺ꨠ垽Ն↬높?澥衙㒨幍밦쨛鸇⪲鉣㲃檠曥抮❛䁅褁尋삗﬒ᄤ雰ᔷ쥕柫稁噷킌潵뱫붞淆഼ꈣងꜜ왦蟧↞㝚?욵⺎㉈ს㹣㞁ﲡꋓ죎䇶업꬀膞卷틏ᝓ푋馠ᚸ⁭꠫뽩ﭶ悪낗䌭ࣾ䡃혶頱ﰠﻈ섵ᔐ抎㬊듵ᓹ澇⯞辘児쨭泎秒豁ǀ鿂ﭺ寧Ὰ袯暩옓䓊蓻ૐｭ崥덑ퟛﻁ롮至ⅆ㺜ཬퟰ흠ㅏ埫㳾䛩鈡䖜탚ꉵ铳?븊ﰛ眑⾓踣뢮鉣䁀ླྀ阯?巩늖ꅓ轅㝀타㣑Ό㾐焔Ṯ濿㟮ꠘힸ瘶馅贇◔ꦅ쭾㛺ሃ俒괡뜫젮悆䪷毝ꟑ娻䝪퍳Ɓ᠍麈ě㗈纚亀諍흪叓磑ꗊ傤禣ۨճ폂䴐砨䐏̉싶螆㑎⠇燣ぐ簰?ꌂ㨅錙↎忩㒞쒹⑟荪捶孜임盷媈㏐ꋹ䱠놯ｩ迆엑≋뽹?歆⺲쯾懠㙼濍莵柷䎫⃻篨癫৔뗯佾࣫箧敝熼䏴猢剜母겑꿹瑕↪맥Ϝ诉ꞹ溟ঃ聾ᢒ牫檦쭚꫆稱樷嗀ឡ罚踟챻䰹廉ꈐౢ䷺奸䮡蜏젴펨퀢쵠燆殽ꘃ㠡⊅䄣蒂▿ᣥ儆ꛎዠ䟁ꜞ୎㳠帥ବ녑ẖ瀢퍰⨹莪懃?꾨ᖲ쵑꫁ᎁ᭪렜ꓝ눘鱈҅䡐?鿎컳Რ餅㠐ቡ崓\006쬳渓ዽ褺㗗筵ퟧ尒룶뢧靼덏㇁癪여豗ᥩ⢛䊥䰂ｦ㹡䨱㚕⌣颳᝜॔࣬艸铏ꁝ짌횵ꑻ떉靡颅眆䕨픪훋锅䰵쏸គ싦焖蔡䕑顐笪퉐竚ᥘ즓ꊓ?旰威쌑㦻⺶개犥略놿䳹讋쳸㐞ꍥ㡬坑掫穟?ᙲꍒ诲⟒⯯ﲂꪕ䌨萶ᒢ頨띍ꖍꪜԮ鍦㖗Ď廷絆뺼衽躇秿䰜鳰訚䦝ʙ픵祍햮꾍䥩ꨫ齁࿝闠奣쇑ૈ笶븁뛭⧀ᷔ漗픑웝샑㾜⹤熧䚤雛庑⸢蘰曘艟벒ც惃栱ꅂ친폃祃⹾ࣥ뜃䪻矌嚄䨊䒠홄म捀錞䦚摂ቩᶳ꾈ޓ䁪䔹斔䢦獉뷐ญ⦬䕞ꜰ?ᱩ鲟ᴷ朊싙喭⑓珫Ꮝ宂窼ⷙᖕ海ꙛꚑ唭篧㿢킟狊嬢ጬ䆓誸묟?밃ݥ蒧㟭ᜩ菭먄麉蝹嫄쌉ࡣ좃袚賮万斺फ䈨⤙〄邼궈鈑쿛뀿⏪ꇝ풧榝ᚆ࢘齲啠ꫀ᳣瞃펍⃗첨ꩲ袩ᔈ⸱?쑧捙悭웟秏ꍗ㭤쁬穗ڂ䓨ԓ녓㑙䎴⡬픨뇔ꆎ鍒攧쩢Ⴛ㯯麉㣀ퟀꯥ劐癔?瘋ﳞꎎ콡笐公㒺Ꟗ噄桑秿ℿ뚒﶑達㕷?뢘빟হ纻읮ꖭ៤螜릴?㳉쀗ᓱ귓벑潎ﱱ✓蛒欧䬌⥝禄ꘑϟ揹⹋쮰쩘ᙕ㔧ᄾʕ꛼ﮌ嚝犡ɸ奔웶큪멸ᶓᨉ団㳈덏菈똨챐娤ꊟ⥁ן䡤双✓譆䭲㴃僂缙璇䙽㲯횫㝱ᩮ兿᭽໌잯₞鱞冘퀮䋞?預兴뤗摄左騉韡碲࠘움敘킊ř퍔븮尝䃣⿃砉霑손膙맺뺩ꝅ俖퐙㰴ꦝ⺿ດ靧螉ɜ潘驾츞?滲਋¶뚳ࣱ숔㖽ࠄ㘬?탺쯗䅳뵉ﰺ?蔎⏴챢嗁㯾暴妄ꁼ烩ؤꏬ녷냕勒㖽ꁱ鴯錭㞫㸗ꕤ費䬅謧컐뺤駖?酾﬑ݨꇠ瘄?쯙㋭긌﵏鼰Ꞌ籪Ɍ䑲餈㍩ᱣ★⑼녓꯶鱴븘괔?⩘襄塻ꮇቸ㴮軨धꦒ狚彘氲ꓠ涜ᤅ礴긛ᜍ饉燀﹢魛圙雬׊뒰苃ə폅톟몎댱襝伈⪞뀭㹓૚戋쳣䕞䭷?堋ﮧ䅜炤㳩蕎ꇭශ넖묆䨟囑聿坑逦ꌞᭌ就넀ꡯ裺ᜯ擌迵깰Ⴎ蘭즞迂Æᰘ첶ㆎ藽ر竎羗㉰⩹?홄謅ㅧ觵詘Ꭲ⚠౾榪봴傍鮴ቸ腴冺晳Ҧ澸奀숾ꒃ햿㪠⨱苚킩ળ슁⊒뛵쉑他螒쫓㋱瘂冩볦祿٧㭫쌝⣚毨ꪂ죌覢鰵䈪䋬㆏꥚帟⽖穘퐰㯗ꑖ吩촟ଔﷸͻ孳ꬕ哛骱ꅹ灌灠栧ቹ潋뚒痰輮觢ጫ廖蔤抽ぅ쩪͈⸌瞓㪗臾榾﶐뻮球䳭膜걆쩀䗕⿘氨桾ോ뎒썖鄥傶Ô搧漴略⦆擭㡹刣揼䩐災믙??妦졡?䣄ྼﻹἛꯥ?쪬ꔡ㞧✚伋❠视ﹾ焉㖔댽埴웭ꦤ計䔺ؘ駥呵遥?ㄟ媷퀴싥틗쪢瘔쪰╈ǽ஛核䐄⎦䎞럮揪伳⮁縺乩瑱鳅쒘琘ᔇ쎪묎놗ࠚ䀚ꟈ栟䈘儮ᢓｅ券힐캷迚濍⎋幘괩ꋨ㿣䑖ཨ픇㽤Ⓞ⽇袄뿳?ꯐ㑤⑍崧侔蜥ꬃଽ홧✡Ḡ綾蔠ᑨ鱗ɔ縷嬇챮贈ᳮ퓣砫皽精捖ई驀'ﱋ꺘괽ʟ謔꯽袦퓷떙?怋ᩈ뺅顐㉂軼삵ྲྀ⑳汍萊㽀ෙ?믟噚ꂶࡌ翯ᄨ놾䀬ᥴ樳쒼ᇏ﨧娋z䵺荃렕엚ԇꗍ桇⚜ꪦ糱匽簘搬뀀뻍鬡椕㘉誀捞挾刭ⳁ֯ࡄ좀壧曽뎰⍜耧䦅怌ϲ쩶䩢䳹壒؊퐐?膝૎陘됰㈣ᰚ嘯棛底鑕焄苔䶗䑰뙇¾轾⃫ꯄ炱ꔁ檜汹?瞇唿┋삊添∆僴顮﫯懒鸺理┽썗侰캷뼷꧜⼁蓪䚧䉊眡铟−ﲊ㜒ㄑ鰦醪᪋傽䘍㲈刲鯴副⛾隣땳䂉឴弳ᲐἻ斟붏剪蜛ڂ혓䕴櫝䘷虺㧐蚹蚠蠮怉䎤잦㑫煛ၸ헌愁㬤禼뤼쵾䥿୕ﶌ㎵쉷쁸奖莛᳕쀠ﯧ뺭࢛뇢찵쌛暃꣆ё舡鞺觳赣셑휧靰꼔螳㤸꧙\020瘥ﳭ⫥ᕏ啥͵槀砰㐼ヰꄟ즶繒籐鏾㫰횺⺈渥꺰☄똡Ŗ挆쉏秔례ダ水콟袧☕㊊콋뵚飃莐㪖╱ᒜ㒽⦯ဗ⥵삩ꪄሩ⡰驃媪ᜢ⼵ҩ浙ꚡ?㥮툩ゴ᳁છ衠阬趉Ղ䠎嘳䘔樍͊ᴚ칿ᝢ恠競猔韫꺋얒羆楡淋謘᫣絑된䤷亹쿯饦裴캊霤ᒈ级쒓败麳俌遼數Έ蟓푀昳涢딏馻䗙뉉钞ษ쾢⭀톸ﻯᤳ륭＇⏝뚲㐛笫笠枲麱਷㪙ᐓⰼ촫ꖀℨ笆⽡滵䫂伹祎㎳ਸ㏫숋삄啉碊伊儝䰦ᾬ㥳䆏ﾍ尢逯舲끅暒瞮☼盛咶ᛁߓᶮᏵ⛲꣮㿙榧磖摭ﭔ铏壤慶੽熶짖ﭽ麭裸힁篬僂傾乧顱勮⮳秀?ｌ퀃熡膱မ䴿隑ꆏ擌녏ᶛꭚ燾삑Ĳ辩㐷⎣ᭊ몎ṝ謟츷ⷽ秨ꩧ띫퓭椇꿧孫갰뗢ᄨ끃慽㓠䑌䑣矖뷈셗풂ꉧὑ폤킡䮦䈒阋㤮㲇憡삕ㄝ괺㢼Ꮊ콳锑큎邿왌滑됷ꃆ鸐?衉壡濉뱿樜멵藎蓑ｵ㵁䘛뀄响珍駒卼孡뤀⅏ꣳ郏㽣㗦苼㋢ﱦ竄䗕鬆رﳙⅲﴓ虼ᐙ쏿嵙凴ﯩህ뙿瀕輦崟ᘤԙ瘍?㊹ㅿ戰鋱❕钑❣欳촮뚽硐搏ࣱʋ⃉틬揺銺ⵄ睋餡䭲됝﫺觢쏫踫틘씶틉䟗䝁ᝍ雌癁䤒ⴆ祔?燂슿៕緺绌樦ᡂᘽ댪榮ↂ䤩﫱ⴈ䚙굂雙夠ﶻ㞜?馞䄅ﾬ羰驾䀑懱ꝙ⹑ꃕ㫴ﱦ佐넯㜃⡏❩Э뗣믲䅞揭淬헊ꓕ썸魅蓗젏旈ꦒ譴冖诵㸫뉠鴄즀쓶艦ꑧ긽쉓蕋쮛珰탶ꨯṘ乳貅༓Ṡ鳏ᕄꢏආἙ튘ᚴ砑駱ဓ薮?៑準ั皹發恝ቈ暆馜㄀쫰陋ꆐ勇ډ贋눍枂룹决㒼餬悚ꆻ츘ᬞꝞซ燯㛿⊑挴ેꟋ棪쯎盫㱵ꂺｻ攇毪?储쁤船馏뿤硬ᗯ➱?槤㬠ꌍⱕ駫誟᭽涐ᢹ䡙ณ램⬤ҺꑙẸ震蚒쎛Ⅻ薌⠳璍赟厞앓ਁ쏗㔘₢ᐣ灗蚊ｷ仒楠ꇘ幄읖뻭㭮㙭씔?㳍蔲?킏镈壵⳧巠䱝⌋◚躽葝穇蒇鶓롘ل맩菀ꠗ૔玃盢⒜ڔﲴ﷠?驂?ꕖ뼴ᅅ⎗㵸?珧黡狾漤糌ἕ拉꒪幄媒䗮ఱุ糡棞丗撰葮뎹᜹凤噽㡶?皻쒰ﯬ㨲쒂胺䝚鮭彖ꖼ㎭肥ᯎ۩ⷵӥ?䋙㯪僦雊싟퐝俟淂唷暯䢃贖벤䎤䔂ﳐ餍握䗺䋎Ⰽ뺪凴䐊難갍ﷰ筄蛟閿ボ襱シᅷፌ끷䗾ꩊඍ䥔슏ẇ檻滘䃈ꕏ믲携㥜摃䳖睁툨駦調?鵡?蓓뚻踚䱽걽﹵塤ﰁꠝꈂ欫梑ﯡ앗ᶅ붎ﻟ⡭ᒓᒶ୛⠦⭚쀭觧뾥촋㺧ﲧ볡兿ᮓ庰ົ듸溍拠剠ꭏଃ翲劤鴧ᣦ毤ꇱ싽₯砈⒘칣팫쀞잌暢?⥛ᑱꜨ奘얏뒪쟉膄땙䓖ɳᰬዺ㓆ҍ㢴쏇?㌌膊ᄧ퉜蒠ᠩ鸦蒖ꀅ롡ﻇ뮚芆?髦ﮫ욤弗ㇱᓰ鰥㜢‟ꀋﻀ狼ꤣ얦ᇻ돀钪琷좚귈Կ왆盷龸ꣃꒈﳟⳂ朣뤱ꔇ孠驢検ᨁ轔닾♨㼺捅ࣄ惚䝥牿⾀떃읈츾?럦ꮅ艻ﲵ脁⡝⻓옹㘷驫ﾍ셺ஶ䅡잀䣋魉랺꼬둜ꛈ땴낪겿虰㙊۝꘾공퀀ⳗ䄕㏥惾蒾䞱䩖㚠᠉䋮댅ޣ爰㗔ॅ䫿ⲯᦨ磠禆翤䪦ஒ챀⨸댹牟핈䞳埣꣯䤵﷓曵?崬緘에廒ℇ䃱誷䠒岜霨彜⃧놘ฌ?몼ൕ互韆覞甘?쁇ꙥ㮻⣮쯾戽꫏碌溰℉｟뎎୸ȴ釒윢갻戏逾敗餴׶Ⱒ箓힨㈽࿡竰୑橿耡鏎ﺂ樬呯买壂થ෰뼠䞆쮨껂㲼㌭徕行쨿⃑휩၅⋶睯ᷱ鏜ȯ䧒죬㠚켟Ὢী賈썒鍾ȉﳞ?쉉ࢹ틱錽羽ᖣ햦罁ৢ쐼攭辫絜Ⰲ袈뚙ᓝ錒㪒ক蕩絧눜摖ᜟꦲ簦轒ᡧ?琋ᗠ⽡蛝橛㜼鐘ꭍ圗觅郚釃읓?ᜨ歷ᤘ䔠ᇞ톦袋罵㛀ힽ㌛궚도㊼⽛蠿蒵瞟ޢ估ᨥᣤ星鿝വ㰮ꂥ鐓鏉⩋ꆡﴽ䬼ﻡ潹␄⪳ಭ糑苞?傻䓝넩镂畨뇐㬰褚褞쥁㩍艱䙥篊䋃೴悈橴冩륯꓈穫鵟冮匿騞淃莁㺂㐏듣푹떅冣៑௝⸋竹푟ဓ貕ꁞ喌ꎏἷ贓읩Ӓ፷ྦ㦤ᳰ겊摏呩桽楪䧨몐瀋뽓쨔⽘쨒窓拦筹ﵚ，滚칌缬徊?範礝霥ꅨቤ㮽碧朶稟腁䂞⟚웼愈꺀ᄑ쒖瑸篫쬀衛둞홨ꮓ웈ཬꄂ鰾蜠䑁傸욲⼒擬爼❅뛆奅웺珩褀꡿璮桵摎鋟쩉빌龽諞㬯쒐绎࿑෢喩咒䌠〮?垰੷㝟죥꽐刄谼꘩ᷕꗪᾥ纸日﷈推㱹ꜛ瀀柑粶Ⴌ⿥却鍐⽁ᖍ♱與ꁪ鶘䊙볨骃兵ධ蟯椪썫翩ܿ⣾쫑溞佴埘縥룙㚊锷뀣襥꼻?뭨㼌渻ꨴϑၯe廚Ἂ꨺?쑪ﺠ揋雨宔鮞琉压䱐拮띁螦Ⅴ桅簪ᕈ턵㬩떻硔အ㉯⿚퐿쭒累폆뽘枒숔㚙ꖰ䢜Њቔ걦౼㑓々⒰掓㴓禅囗㚂⸂း蒇͓爏懲Ꮪ㗽皕摿겧栝ㅖ掄㜭馻옚ᄘ䒈埖쐣㣇뇢븋䭒ਹ웜ଃꄱ㑐넡ᷕそ턬昄㰠ϯ볁‟뭴怩뤕㏨嚔爷鶇ꖋ?૶豪貆隬榥ꏲ扶쵄?墩Ꚅ攏?蕜縌അ缞뫩꠯⭻歙ﳘ⹀讫춑ƾ牲㙦沁⃯?壡㹖ﮕꁝ堗澩悯箶☯ᙹ㦻礨顼⡗緐嵲䛣襻迌魄艏哿ﹻ嶶켻憤䁁陋ᆰ叉꤇谸㏂减怦䧤㬾ẑ릿ⳇ暕핕钜ꌰᛕ镑瘠﫹踃̳晸ⰷ霒燙せ䋎❩輙殒ↅꎄ梲盹䜬Ů踌ꣁ뾴뎸欢뇅尅餲酈딍ॾই쑷줿⺀㞎饃짣库枯덽ꐋㆀ芐ᵔ턈䭼⯙蟷춬䘯熾䉺ꩫ㢧ꨜ铿覨ꚦ䀋砵␸㲢ܾ桳켈鱪➭䡒솛쓵ܼ㰻᎝䥮Ⰽ酉?紽ꑧꊈ뚹猒䄯큧⿥?腡홼讞痦쪑殳ꕩ゙慵拻鴸晜熻쿭別❜Ⳅ灗獖슎䛈㺘篏쬛쀰툱ᲃ䌙吟㝮䑅䢌\f讁艟籨랤쑨萌쫳ខ蜶⢅潩䃖澰⡢❗렕?곂笂잗㮎袔៮फ़栶휎㷜㑬蘃䀦䛦៮ˍ疑쎇鸑迹晦뗏꿡셦⠕੍ĺ晘朎ﬢ᳞崦䁵౎聣鿼ᴢ᫻Ṉ䟤伵竛澷顎쬢涊硘丗緲鶋Ȅꊈ阌Єꠧ燇평䳇ￊ绀O議㯣ꀴᩢ얿㐐䗐썀ꌰ층솲袨쐟㎦묇ꈅຉ豚튾火鏚颟郦殂넾ꜬӐ풷๳飡䵅红옭呴ϻ辩셹?ǚ򉩽ꯉۓ勛㜛櫹糯?ﳔ彳獆䦴⾔㐦鴥蔏ⲉ壂魕ﱙ搛橄怱֥㽿꼑癭ᇾ斫蟭᪝◘잜?葁밠앳Ȇ㵃䗿䚗煅ਉ竽扄Ϫ薺嚦䖋ꃦ?䷦ۃࡷˢ㥙숗業걜⇻Ụ饚亟芢蔕쉐玷ꋕ၅?ᇏ쏱딍枰㿳쥰钵棫뙲๶ᮬ6슨茁ᓼ倫滢毥髫罧쒯毤為祄뱮↚裕帒䰣鷌磌針㊪꘢䪃鼁䛂갶녟姹닺ᄃ➥휩❢홡ꍽ첦⚍䃦耎縈⸃໯⼃꘠볎싎ꦷ샡郘綩亿믊牿ꆯⶔ剒Ⱌȶ纍ೇ蟋⏓ក窹眻赇㋔醁뷩瞫ꃈۜ全ゟ厌Ο◇ဳ䧸猠څ絛貀畻亇ꃓ銘ꖗ゚秩⧮녖鐪㔹ý炇뻁寧䲚ﵹ᪐仂讋꘸?䰵㇭ଭ歱䭸㯚캉䵲芅ᅆ ㏸塪ꭆᰟ筑쯮玷䯅੧?ᩤ⺸鯝੨䓁췘鬤㾀䅠⢷챽禈蜂ꑴ䖙ݴ㵲⧡⡢텔쫅襎攻ᕌ?␸媰⢔뽐莮ꮝ|훹侍礪黍촒뱩㦘旰斂︐ኯៜ좛埝ೈẇ㥠ￒ魯㾽㯳?௪駰᜔濥໘⤢蘄受⒋垎ᦰ⮲蔕꾳꽜톭῏◧먖퀠猥Ỡ䅳켉甝?脹诼澪힡䈳ỗ๪䵎鉏箮㧇뻿몸ﲥ嵯ǔ瑩ូ甚猺ꏃ⫚䫞쎪掼赲幌﫝뽗鯟撌୐짖ᩑ錡૾祰ꞡ뿸嘕?⧹㨔ꈎꝺ鳘ｵ졘쉨㽀鄵པ蘃詷忚欑﵃莃冉⚙዆艭禘䁴龡詺省墚ﳕ췑䟙슴盫⾯ꕅ疏蹏ⶋ햝傦㤘愤镁諻훥퇶箓灵쩪ꐠⰏꐛ靇᪆ᤸ䯭儌洍ꔺ亐종㠕૨ᛰ뵦ꌫ嘄텪鳈犊㢥傞렪都笸龇ﱎꒁ༘Ⳗ沭ꟊ俫惵췝ᱢɭ㔡獀⊴뀨糛틩?䔝Ꚑ㌈㾖鳆殍齪࿨ὒ闪烎ⱐⷉꮠ◣∹ℼ왥螚ዳ趶ꦚ涅뗢ᰈ넇橘㇮﹩洝Ⱡ⼳湭㚿ᓏ⸥똸锟㜉︮텁壄聛?㭆둏㓰瑠衋烳᠗ઐ确롇팞ꊈ麕?⧠堇핢㩴괂᫓ㅑꞛᖀ੤⁏걎⬁惨殊ຑ豵鬒䵰쑈黗ꅳ뉇ᮃ韮΄ಓ㔵篁葧瓸樧퀠⾮䩣ꛘ赯只쟥ꚳ툆⽻ⴘ飇ᔻ㔄퓟빘ċ酺圼컅盫欘ᩅ赆妀∠テ眢?톈쩤깽鰶툧Ṏ䩗쫫埾쒑꽔乣惊暩爵㴈캎?ᤷ潘켐歴⸣쵇∤⾸ꥊ셏쓄伽͛㣒﬌㐢ꌉ㑰꓆㿢삊탹莫낮毂ㄪ棾薍鰡荷λᎤ墋峞젅졈᳕ͅ銬ഋ޻둕愛㢍䧍膻鵎砍卶绋賢ਸ਼Ც⸍밊݂熧蜂첫観᭛랇缎?릿ڴ㍷햠቟塳췆悚㏸儜ꥋ¥ꈔꤘ☆毁?彺뇲룏鉶焚ꛬ籅앞娞萲칄臨ᑻ끱顴ߙﵕ䯰␹擥꿅퍟誺ꊛ褡腙㛴⧲툲緧⛓幻ꂟг갃꘡윃낄䯵嵞㩻ൃꓮ⁍痁㿱୸ྎ밁꿩랕戆ﰦ룼犐賈滑שּׂ鳝Ⴢභ데堌婆ᎎ롟癇㤂?샇፩㐬䲥㴺᧚㮀﫭⋈ﰮ页?撠韉倉뭰譾‏隵༔䡗쟒夿┎媂ꄊ⯙毀㩠儉狑ₖ뭦濑劅댈蝮☆䅲뎜偭䤫燊䓥麟肊༇鐸嵴掛ⅳ䨮⫔琢ᴷᓤ忴ಧ㉮朶죠튰弚芔단┬䒖ⱔ㹜籐䃘맪浡鎢睊筫헐ﺽഏ闔㵞佞鵢✃紾쉎荲疊홀뎌㥘窌澧鹖郍뽸ōࢁ粄榒৶䐮刚旀삏풠뵉≰綟窾땞?伧獵듴捗發匜ྃ䠱誡ケ랶坷濬娕ꋽƚ됂騎⸝ླ勴쥉錼곣鋜㌠深鶌瞎⦣윾⴮송짴䒖妩".toCharArray(), (short)6193, false, true)).length(); byte b2 = 16; byte b = -1;
/*     */     while (true);
/*     */   }
/*     */   
/*     */   private BaseComponent a(Player paramPlayer, long paramLong, CommandSender paramCommandSender) {
/*     */     // Byte code:
/*     */     //   0: getstatic me/konsolas/aac/mi.g : J
/*     */     //   3: lload_2
/*     */     //   4: lxor
/*     */     //   5: lstore_2
/*     */     //   6: ldc2_w -6710508296409374381
/*     */     //   9: lload_2
/*     */     //   10: <illegal opcode> w : (JJ)I
/*     */     //   15: new net/md_5/bungee/api/chat/TextComponent
/*     */     //   18: dup
/*     */     //   19: sipush #4248
/*     */     //   22: ldc2_w 2314028955245237960
/*     */     //   25: lload_2
/*     */     //   26: lxor
/*     */     //   27: <illegal opcode> e : (IJ)Ljava/lang/String;
/*     */     //   32: invokespecial <init> : (Ljava/lang/String;)V
/*     */     //   35: astore #6
/*     */     //   37: aload #6
/*     */     //   39: new net/md_5/bungee/api/chat/ClickEvent
/*     */     //   42: dup
/*     */     //   43: getstatic net/md_5/bungee/api/chat/ClickEvent$Action.RUN_COMMAND : Lnet/md_5/bungee/api/chat/ClickEvent$Action;
/*     */     //   46: new java/lang/StringBuilder
/*     */     //   49: dup
/*     */     //   50: invokespecial <init> : ()V
/*     */     //   53: sipush #3115
/*     */     //   56: ldc2_w 7829041500088617546
/*     */     //   59: lload_2
/*     */     //   60: lxor
/*     */     //   61: <illegal opcode> e : (IJ)Ljava/lang/String;
/*     */     //   66: invokevirtual append : (Ljava/lang/String;)Ljava/lang/StringBuilder;
/*     */     //   69: aload_1
/*     */     //   70: invokeinterface getName : ()Ljava/lang/String;
/*     */     //   75: invokevirtual append : (Ljava/lang/String;)Ljava/lang/StringBuilder;
/*     */     //   78: invokevirtual toString : ()Ljava/lang/String;
/*     */     //   81: invokespecial <init> : (Lnet/md_5/bungee/api/chat/ClickEvent$Action;Ljava/lang/String;)V
/*     */     //   84: invokevirtual setClickEvent : (Lnet/md_5/bungee/api/chat/ClickEvent;)V
/*     */     //   87: istore #5
/*     */     //   89: aload #6
/*     */     //   91: iload #5
/*     */     //   93: ifne -> 217
/*     */     //   96: new net/md_5/bungee/api/chat/HoverEvent
/*     */     //   99: dup
/*     */     //   100: getstatic net/md_5/bungee/api/chat/HoverEvent$Action.SHOW_TEXT : Lnet/md_5/bungee/api/chat/HoverEvent$Action;
/*     */     //   103: iconst_1
/*     */     //   104: anewarray net/md_5/bungee/api/chat/BaseComponent
/*     */     //   107: dup
/*     */     //   108: iconst_0
/*     */     //   109: new net/md_5/bungee/api/chat/TextComponent
/*     */     //   112: dup
/*     */     //   113: new java/lang/StringBuilder
/*     */     //   116: dup
/*     */     //   117: invokespecial <init> : ()V
/*     */     //   120: sipush #7553
/*     */     //   123: ldc2_w 2872776340177542126
/*     */     //   126: lload_2
/*     */     //   127: lxor
/*     */     //   128: <illegal opcode> e : (IJ)Ljava/lang/String;
/*     */     //   133: invokevirtual append : (Ljava/lang/String;)Ljava/lang/StringBuilder;
/*     */     //   136: aload_1
/*     */     //   137: invokeinterface getName : ()Ljava/lang/String;
/*     */     //   142: invokevirtual append : (Ljava/lang/String;)Ljava/lang/StringBuilder;
/*     */     //   145: invokevirtual toString : ()Ljava/lang/String;
/*     */     //   148: invokespecial <init> : (Ljava/lang/String;)V
/*     */     //   151: aastore
/*     */     //   152: invokespecial <init> : (Lnet/md_5/bungee/api/chat/HoverEvent$Action;[Lnet/md_5/bungee/api/chat/BaseComponent;)V
/*     */     //   155: invokevirtual setHoverEvent : (Lnet/md_5/bungee/api/chat/HoverEvent;)V
/*     */     //   158: aload #4
/*     */     //   160: instanceof org/bukkit/entity/Player
/*     */     //   163: ifeq -> 202
/*     */     //   166: goto -> 179
/*     */     //   169: ldc2_w -6659804512081277384
/*     */     //   172: lload_2
/*     */     //   173: <illegal opcode> w : (Ljava/lang/Throwable;JJ)Ljava/lang/Throwable;
/*     */     //   178: athrow
/*     */     //   179: aload #4
/*     */     //   181: sipush #13029
/*     */     //   184: ldc2_w 2909808913168889057
/*     */     //   187: lload_2
/*     */     //   188: lxor
/*     */     //   189: <illegal opcode> e : (IJ)Ljava/lang/String;
/*     */     //   194: invokeinterface hasPermission : (Ljava/lang/String;)Z
/*     */     //   199: ifne -> 224
/*     */     //   202: aload #6
/*     */     //   204: goto -> 217
/*     */     //   207: ldc2_w -6659804512081277384
/*     */     //   210: lload_2
/*     */     //   211: <illegal opcode> w : (Ljava/lang/Throwable;JJ)Ljava/lang/Throwable;
/*     */     //   216: athrow
/*     */     //   217: iconst_1
/*     */     //   218: invokestatic valueOf : (Z)Ljava/lang/Boolean;
/*     */     //   221: invokevirtual setStrikethrough : (Ljava/lang/Boolean;)V
/*     */     //   224: aload #6
/*     */     //   226: areturn
/*     */     // Line number table:
/*     */     //   Java source line number -> byte code offset
/*     */     //   #233	-> 15
/*     */     //   #317	-> 37
/*     */     //   #76	-> 89
/*     */     //   #316	-> 158
/*     */     //   #33	-> 202
/*     */     //   #323	-> 224
/*     */     // Exception table:
/*     */     //   from	to	target	type
/*     */     //   89	166	169	aacinternal/v
/*     */     //   179	204	207	aacinternal/v
/*     */   }
/*     */   
/*     */   private BaseComponent a(long paramLong) {
/*     */     // Byte code:
/*     */     //   0: getstatic me/konsolas/aac/mi.g : J
/*     */     //   3: lload_1
/*     */     //   4: lxor
/*     */     //   5: lstore_1
/*     */     //   6: new net/md_5/bungee/api/chat/TextComponent
/*     */     //   9: dup
/*     */     //   10: ldc_w '熝䐩'
/*     */     //   13: invokevirtual toCharArray : ()[C
/*     */     //   16: dup
/*     */     //   17: dup
/*     */     //   18: iconst_0
/*     */     //   19: dup_x1
/*     */     //   20: caload
/*     */     //   21: sipush #18083
/*     */     //   24: ixor
/*     */     //   25: i2c
/*     */     //   26: castore
/*     */     //   27: sipush #22638
/*     */     //   30: iconst_0
/*     */     //   31: iconst_1
/*     */     //   32: invokestatic G : (Ljava/lang/Object;SZB)Ljava/lang/String;
/*     */     //   35: invokespecial <init> : (Ljava/lang/String;)V
/*     */     //   38: astore_3
/*     */     //   39: new net/md_5/bungee/api/chat/TextComponent
/*     */     //   42: dup
/*     */     //   43: sipush #23164
/*     */     //   46: ldc2_w 1203071932631075689
/*     */     //   49: lload_1
/*     */     //   50: lxor
/*     */     //   51: <illegal opcode> e : (IJ)Ljava/lang/String;
/*     */     //   56: invokespecial <init> : (Ljava/lang/String;)V
/*     */     //   59: astore #4
/*     */     //   61: aload #4
/*     */     //   63: aload_0
/*     */     //   64: getfield c : Lnet/md_5/bungee/api/ChatColor;
/*     */     //   67: invokevirtual setColor : (Lnet/md_5/bungee/api/ChatColor;)V
/*     */     //   70: aload #4
/*     */     //   72: iconst_1
/*     */     //   73: invokestatic valueOf : (Z)Ljava/lang/Boolean;
/*     */     //   76: invokevirtual setBold : (Ljava/lang/Boolean;)V
/*     */     //   79: aload_3
/*     */     //   80: aload #4
/*     */     //   82: invokevirtual addExtra : (Lnet/md_5/bungee/api/chat/BaseComponent;)V
/*     */     //   85: aload_3
/*     */     //   86: areturn
/*     */     // Line number table:
/*     */     //   Java source line number -> byte code offset
/*     */     //   #291	-> 6
/*     */     //   #1	-> 39
/*     */     //   #89	-> 61
/*     */     //   #256	-> 70
/*     */     //   #67	-> 79
/*     */     //   #40	-> 85
/*     */   }
/*     */   
/*     */   public List onTabComplete(CommandSender paramCommandSender, Command paramCommand, String paramString, String[] paramArrayOfString) {
/*     */     // Byte code:
/*     */     //   0: getstatic me/konsolas/aac/mi.g : J
/*     */     //   3: ldc2_w 30709001012896
/*     */     //   6: lxor
/*     */     //   7: lstore #5
/*     */     //   9: ldc2_w 729980837565860269
/*     */     //   12: lload #5
/*     */     //   14: <illegal opcode> w : (JJ)I
/*     */     //   19: new java/util/ArrayList
/*     */     //   22: dup
/*     */     //   23: invokespecial <init> : ()V
/*     */     //   26: astore #8
/*     */     //   28: istore #7
/*     */     //   30: aload #4
/*     */     //   32: arraylength
/*     */     //   33: iload #7
/*     */     //   35: ifne -> 73
/*     */     //   38: ifne -> 70
/*     */     //   41: goto -> 55
/*     */     //   44: ldc2_w 823467012530087622
/*     */     //   47: lload #5
/*     */     //   49: <illegal opcode> w : (Ljava/lang/Throwable;JJ)Ljava/lang/Throwable;
/*     */     //   54: athrow
/*     */     //   55: getstatic me/konsolas/aac/mi.f : Ljava/util/List;
/*     */     //   58: areturn
/*     */     //   59: ldc2_w 823467012530087622
/*     */     //   62: lload #5
/*     */     //   64: <illegal opcode> w : (Ljava/lang/Throwable;JJ)Ljava/lang/Throwable;
/*     */     //   69: athrow
/*     */     //   70: aload #4
/*     */     //   72: arraylength
/*     */     //   73: iload #7
/*     */     //   75: ifne -> 163
/*     */     //   78: iconst_1
/*     */     //   79: if_icmpne -> 123
/*     */     //   82: goto -> 96
/*     */     //   85: ldc2_w 823467012530087622
/*     */     //   88: lload #5
/*     */     //   90: <illegal opcode> w : (Ljava/lang/Throwable;JJ)Ljava/lang/Throwable;
/*     */     //   95: athrow
/*     */     //   96: aload #4
/*     */     //   98: iconst_0
/*     */     //   99: aaload
/*     */     //   100: getstatic me/konsolas/aac/mi.f : Ljava/util/List;
/*     */     //   103: aload #8
/*     */     //   105: invokestatic copyPartialMatches : (Ljava/lang/String;Ljava/lang/Iterable;Ljava/util/Collection;)Ljava/util/Collection;
/*     */     //   108: pop
/*     */     //   109: aload #8
/*     */     //   111: areturn
/*     */     //   112: ldc2_w 823467012530087622
/*     */     //   115: lload #5
/*     */     //   117: <illegal opcode> w : (Ljava/lang/Throwable;JJ)Ljava/lang/Throwable;
/*     */     //   122: athrow
/*     */     //   123: sipush #18592
/*     */     //   126: ldc2_w 8715912285223953964
/*     */     //   129: lload #5
/*     */     //   131: lxor
/*     */     //   132: <illegal opcode> e : (IJ)Ljava/lang/String;
/*     */     //   137: iload #7
/*     */     //   139: ifne -> 184
/*     */     //   142: aload #4
/*     */     //   144: iconst_0
/*     */     //   145: aaload
/*     */     //   146: invokevirtual equals : (Ljava/lang/Object;)Z
/*     */     //   149: goto -> 163
/*     */     //   152: ldc2_w 823467012530087622
/*     */     //   155: lload #5
/*     */     //   157: <illegal opcode> w : (Ljava/lang/Throwable;JJ)Ljava/lang/Throwable;
/*     */     //   162: athrow
/*     */     //   163: ifeq -> 196
/*     */     //   166: aload #4
/*     */     //   168: iconst_0
/*     */     //   169: aaload
/*     */     //   170: goto -> 184
/*     */     //   173: ldc2_w 823467012530087622
/*     */     //   176: lload #5
/*     */     //   178: <illegal opcode> w : (Ljava/lang/Throwable;JJ)Ljava/lang/Throwable;
/*     */     //   183: athrow
/*     */     //   184: getstatic me/konsolas/aac/mi.a : Ljava/util/List;
/*     */     //   187: aload #8
/*     */     //   189: invokestatic copyPartialMatches : (Ljava/lang/String;Ljava/lang/Iterable;Ljava/util/Collection;)Ljava/util/Collection;
/*     */     //   192: pop
/*     */     //   193: aload #8
/*     */     //   195: areturn
/*     */     //   196: aconst_null
/*     */     //   197: areturn
/*     */     // Line number table:
/*     */     //   Java source line number -> byte code offset
/*     */     //   #334	-> 19
/*     */     //   #234	-> 30
/*     */     //   #93	-> 55
/*     */     //   #284	-> 70
/*     */     //   #322	-> 96
/*     */     //   #103	-> 109
/*     */     //   #98	-> 123
/*     */     //   #161	-> 166
/*     */     //   #402	-> 193
/*     */     //   #209	-> 196
/*     */     // Exception table:
/*     */     //   from	to	target	type
/*     */     //   30	41	44	aacinternal/v
/*     */     //   38	59	59	aacinternal/v
/*     */     //   73	82	85	aacinternal/v
/*     */     //   78	112	112	aacinternal/v
/*     */     //   123	149	152	aacinternal/v
/*     */     //   163	170	173	aacinternal/v
/*     */   }
/*     */   
/*     */   public mi(long paramLong, AAC paramAAC) {
/*     */     // Byte code:
/*     */     //   0: getstatic me/konsolas/aac/mi.g : J
/*     */     //   3: lload_1
/*     */     //   4: lxor
/*     */     //   5: lstore_1
/*     */     //   6: aload_0
/*     */     //   7: invokespecial <init> : ()V
/*     */     //   10: ldc2_w -476527557087753834
/*     */     //   13: lload_1
/*     */     //   14: <illegal opcode> w : (JJ)I
/*     */     //   19: aload_0
/*     */     //   20: new java/util/WeakHashMap
/*     */     //   23: dup
/*     */     //   24: invokespecial <init> : ()V
/*     */     //   27: putfield d : Ljava/util/Map;
/*     */     //   30: aload_0
/*     */     //   31: new java/util/WeakHashMap
/*     */     //   34: dup
/*     */     //   35: invokespecial <init> : ()V
/*     */     //   38: putfield e : Ljava/util/Map;
/*     */     //   41: istore #4
/*     */     //   43: aload_0
/*     */     //   44: aload_3
/*     */     //   45: putfield b : Lme/konsolas/aac/AAC;
/*     */     //   48: aload_3
/*     */     //   49: invokevirtual getConfig : ()Lorg/bukkit/configuration/file/FileConfiguration;
/*     */     //   52: sipush #30755
/*     */     //   55: ldc2_w 6320700095448868172
/*     */     //   58: lload_1
/*     */     //   59: lxor
/*     */     //   60: <illegal opcode> e : (IJ)Ljava/lang/String;
/*     */     //   65: invokevirtual getString : (Ljava/lang/String;)Ljava/lang/String;
/*     */     //   68: astore #5
/*     */     //   70: iload #4
/*     */     //   72: ifeq -> 247
/*     */     //   75: aload #5
/*     */     //   77: ifnull -> 173
/*     */     //   80: goto -> 93
/*     */     //   83: ldc2_w -529839903583283954
/*     */     //   86: lload_1
/*     */     //   87: <illegal opcode> w : (Ljava/lang/Throwable;JJ)Ljava/lang/Throwable;
/*     */     //   92: athrow
/*     */     //   93: aload #5
/*     */     //   95: invokevirtual length : ()I
/*     */     //   98: lload_1
/*     */     //   99: lconst_0
/*     */     //   100: lcmp
/*     */     //   101: ifle -> 170
/*     */     //   104: iload #4
/*     */     //   106: ifeq -> 170
/*     */     //   109: goto -> 122
/*     */     //   112: ldc2_w -529839903583283954
/*     */     //   115: lload_1
/*     */     //   116: <illegal opcode> w : (Ljava/lang/Throwable;JJ)Ljava/lang/Throwable;
/*     */     //   121: athrow
/*     */     //   122: iconst_1
/*     */     //   123: if_icmpne -> 173
/*     */     //   126: goto -> 139
/*     */     //   129: ldc2_w -529839903583283954
/*     */     //   132: lload_1
/*     */     //   133: <illegal opcode> w : (Ljava/lang/Throwable;JJ)Ljava/lang/Throwable;
/*     */     //   138: athrow
/*     */     //   139: sipush #16945
/*     */     //   142: ldc2_w 3112705174794559313
/*     */     //   145: lload_1
/*     */     //   146: lxor
/*     */     //   147: <illegal opcode> e : (IJ)Ljava/lang/String;
/*     */     //   152: aload #5
/*     */     //   154: invokevirtual contains : (Ljava/lang/CharSequence;)Z
/*     */     //   157: goto -> 170
/*     */     //   160: ldc2_w -529839903583283954
/*     */     //   163: lload_1
/*     */     //   164: <illegal opcode> w : (Ljava/lang/Throwable;JJ)Ljava/lang/Throwable;
/*     */     //   169: athrow
/*     */     //   170: ifne -> 284
/*     */     //   173: aload_3
/*     */     //   174: invokevirtual getLogger : ()Ljava/util/logging/Logger;
/*     */     //   177: new java/lang/StringBuilder
/*     */     //   180: dup
/*     */     //   181: invokespecial <init> : ()V
/*     */     //   184: sipush #16294
/*     */     //   187: ldc2_w 7181062078946124512
/*     */     //   190: lload_1
/*     */     //   191: lxor
/*     */     //   192: <illegal opcode> e : (IJ)Ljava/lang/String;
/*     */     //   197: invokevirtual append : (Ljava/lang/String;)Ljava/lang/StringBuilder;
/*     */     //   200: aload #5
/*     */     //   202: invokevirtual append : (Ljava/lang/String;)Ljava/lang/StringBuilder;
/*     */     //   205: sipush #3818
/*     */     //   208: ldc2_w 4588005965182636928
/*     */     //   211: lload_1
/*     */     //   212: lxor
/*     */     //   213: <illegal opcode> e : (IJ)Ljava/lang/String;
/*     */     //   218: invokevirtual append : (Ljava/lang/String;)Ljava/lang/StringBuilder;
/*     */     //   221: invokevirtual toString : ()Ljava/lang/String;
/*     */     //   224: invokevirtual warning : (Ljava/lang/String;)V
/*     */     //   227: aload_0
/*     */     //   228: getstatic net/md_5/bungee/api/ChatColor.GREEN : Lnet/md_5/bungee/api/ChatColor;
/*     */     //   231: putfield c : Lnet/md_5/bungee/api/ChatColor;
/*     */     //   234: goto -> 247
/*     */     //   237: ldc2_w -529839903583283954
/*     */     //   240: lload_1
/*     */     //   241: <illegal opcode> w : (Ljava/lang/Throwable;JJ)Ljava/lang/Throwable;
/*     */     //   246: athrow
/*     */     //   247: iload #4
/*     */     //   249: lload_1
/*     */     //   250: lconst_0
/*     */     //   251: lcmp
/*     */     //   252: iflt -> 259
/*     */     //   255: ifne -> 297
/*     */     //   258: iconst_3
/*     */     //   259: anewarray me/konsolas/aac/aN
/*     */     //   262: ldc2_w -494623854450695945
/*     */     //   265: lload_1
/*     */     //   266: <illegal opcode> w : ([Lme/konsolas/aac/aN;JJ)V
/*     */     //   271: goto -> 284
/*     */     //   274: ldc2_w -529839903583283954
/*     */     //   277: lload_1
/*     */     //   278: <illegal opcode> w : (Ljava/lang/Throwable;JJ)Ljava/lang/Throwable;
/*     */     //   283: athrow
/*     */     //   284: aload_0
/*     */     //   285: aload #5
/*     */     //   287: iconst_0
/*     */     //   288: invokevirtual charAt : (I)C
/*     */     //   291: invokestatic getByChar : (C)Lnet/md_5/bungee/api/ChatColor;
/*     */     //   294: putfield c : Lnet/md_5/bungee/api/ChatColor;
/*     */     //   297: return
/*     */     // Line number table:
/*     */     //   Java source line number -> byte code offset
/*     */     //   #335	-> 6
/*     */     //   #186	-> 19
/*     */     //   #430	-> 30
/*     */     //   #393	-> 43
/*     */     //   #271	-> 48
/*     */     //   #201	-> 70
/*     */     //   #287	-> 173
/*     */     //   #238	-> 227
/*     */     //   #254	-> 284
/*     */     //   #440	-> 297
/*     */     // Exception table:
/*     */     //   from	to	target	type
/*     */     //   70	80	83	aacinternal/v
/*     */     //   75	109	112	aacinternal/v
/*     */     //   93	126	129	aacinternal/v
/*     */     //   122	157	160	aacinternal/v
/*     */     //   170	234	237	aacinternal/v
/*     */     //   247	271	274	aacinternal/v
/*     */   }
/*     */   
/*     */   public boolean onCommand(CommandSender paramCommandSender, Command paramCommand, String paramString, String[] paramArrayOfString) {
/*     */     // Byte code:
/*     */     //   0: getstatic me/konsolas/aac/mi.g : J
/*     */     //   3: ldc2_w 99847929810425
/*     */     //   6: lxor
/*     */     //   7: lstore #5
/*     */     //   9: lload #5
/*     */     //   11: dup2
/*     */     //   12: ldc2_w 72969149394929
/*     */     //   15: lxor
/*     */     //   16: lstore #7
/*     */     //   18: dup2
/*     */     //   19: ldc2_w 26195167512123
/*     */     //   22: lxor
/*     */     //   23: lstore #9
/*     */     //   25: dup2
/*     */     //   26: ldc2_w 14413798341163
/*     */     //   29: lxor
/*     */     //   30: lstore #11
/*     */     //   32: dup2
/*     */     //   33: ldc2_w 122957182636103
/*     */     //   36: lxor
/*     */     //   37: lstore #13
/*     */     //   39: dup2
/*     */     //   40: ldc2_w 129406757845273
/*     */     //   43: lxor
/*     */     //   44: lstore #15
/*     */     //   46: dup2
/*     */     //   47: ldc2_w 24541111332999
/*     */     //   50: lxor
/*     */     //   51: dup2
/*     */     //   52: bipush #48
/*     */     //   54: lushr
/*     */     //   55: l2i
/*     */     //   56: istore #17
/*     */     //   58: dup2
/*     */     //   59: bipush #16
/*     */     //   61: lshl
/*     */     //   62: bipush #16
/*     */     //   64: lushr
/*     */     //   65: lstore #18
/*     */     //   67: pop2
/*     */     //   68: dup2
/*     */     //   69: ldc2_w 110221166956948
/*     */     //   72: lxor
/*     */     //   73: lstore #20
/*     */     //   75: dup2
/*     */     //   76: ldc2_w 12081936553153
/*     */     //   79: lxor
/*     */     //   80: lstore #22
/*     */     //   82: dup2
/*     */     //   83: ldc2_w 95778321803133
/*     */     //   86: lxor
/*     */     //   87: lstore #24
/*     */     //   89: dup2
/*     */     //   90: ldc2_w 76391225674291
/*     */     //   93: lxor
/*     */     //   94: lstore #26
/*     */     //   96: dup2
/*     */     //   97: ldc2_w 59013268100592
/*     */     //   100: lxor
/*     */     //   101: lstore #28
/*     */     //   103: dup2
/*     */     //   104: ldc2_w 30566392792202
/*     */     //   107: lxor
/*     */     //   108: dup2
/*     */     //   109: bipush #32
/*     */     //   111: lushr
/*     */     //   112: l2i
/*     */     //   113: istore #30
/*     */     //   115: dup2
/*     */     //   116: bipush #32
/*     */     //   118: lshl
/*     */     //   119: bipush #48
/*     */     //   121: lushr
/*     */     //   122: l2i
/*     */     //   123: istore #31
/*     */     //   125: dup2
/*     */     //   126: bipush #48
/*     */     //   128: lshl
/*     */     //   129: bipush #48
/*     */     //   131: lushr
/*     */     //   132: l2i
/*     */     //   133: istore #32
/*     */     //   135: pop2
/*     */     //   136: dup2
/*     */     //   137: ldc2_w 105749341597916
/*     */     //   140: lxor
/*     */     //   141: dup2
/*     */     //   142: bipush #48
/*     */     //   144: lushr
/*     */     //   145: l2i
/*     */     //   146: istore #33
/*     */     //   148: dup2
/*     */     //   149: bipush #16
/*     */     //   151: lshl
/*     */     //   152: bipush #48
/*     */     //   154: lushr
/*     */     //   155: l2i
/*     */     //   156: istore #34
/*     */     //   158: dup2
/*     */     //   159: bipush #32
/*     */     //   161: lshl
/*     */     //   162: bipush #32
/*     */     //   164: lushr
/*     */     //   165: l2i
/*     */     //   166: istore #35
/*     */     //   168: pop2
/*     */     //   169: dup2
/*     */     //   170: ldc2_w 9345363432334
/*     */     //   173: lxor
/*     */     //   174: lstore #36
/*     */     //   176: pop2
/*     */     //   177: ldc2_w -9083089622758657785
/*     */     //   180: lload #5
/*     */     //   182: <illegal opcode> w : (JJ)I
/*     */     //   187: istore #38
/*     */     //   189: aload #4
/*     */     //   191: iload #38
/*     */     //   193: ifeq -> 353
/*     */     //   196: arraylength
/*     */     //   197: ifne -> 351
/*     */     //   200: goto -> 214
/*     */     //   203: ldc2_w -9208511308924703329
/*     */     //   206: lload #5
/*     */     //   208: <illegal opcode> w : (Ljava/lang/Throwable;JJ)Ljava/lang/Throwable;
/*     */     //   213: athrow
/*     */     //   214: aload_0
/*     */     //   215: lload #15
/*     */     //   217: invokespecial a : (J)Lnet/md_5/bungee/api/chat/BaseComponent;
/*     */     //   220: astore #39
/*     */     //   222: aload #39
/*     */     //   224: new java/lang/StringBuilder
/*     */     //   227: dup
/*     */     //   228: invokespecial <init> : ()V
/*     */     //   231: sipush #9478
/*     */     //   234: ldc2_w 3588809474605662347
/*     */     //   237: lload #5
/*     */     //   239: lxor
/*     */     //   240: <illegal opcode> e : (IJ)Ljava/lang/String;
/*     */     //   245: invokevirtual append : (Ljava/lang/String;)Ljava/lang/StringBuilder;
/*     */     //   248: ldc me/konsolas/aac/AAC
/*     */     //   250: invokevirtual getPackage : ()Ljava/lang/Package;
/*     */     //   253: invokevirtual getImplementationVersion : ()Ljava/lang/String;
/*     */     //   256: invokevirtual append : (Ljava/lang/String;)Ljava/lang/StringBuilder;
/*     */     //   259: sipush #22444
/*     */     //   262: ldc2_w 4687361367878939166
/*     */     //   265: lload #5
/*     */     //   267: lxor
/*     */     //   268: <illegal opcode> e : (IJ)Ljava/lang/String;
/*     */     //   273: invokevirtual append : (Ljava/lang/String;)Ljava/lang/StringBuilder;
/*     */     //   276: invokevirtual toString : ()Ljava/lang/String;
/*     */     //   279: invokevirtual addExtra : (Ljava/lang/String;)V
/*     */     //   282: new net/md_5/bungee/api/chat/TextComponent
/*     */     //   285: dup
/*     */     //   286: sipush #32457
/*     */     //   289: ldc2_w 2981245189735750445
/*     */     //   292: lload #5
/*     */     //   294: lxor
/*     */     //   295: <illegal opcode> e : (IJ)Ljava/lang/String;
/*     */     //   300: invokespecial <init> : (Ljava/lang/String;)V
/*     */     //   303: astore #40
/*     */     //   305: aload #40
/*     */     //   307: new net/md_5/bungee/api/chat/ClickEvent
/*     */     //   310: dup
/*     */     //   311: getstatic net/md_5/bungee/api/chat/ClickEvent$Action.OPEN_URL : Lnet/md_5/bungee/api/chat/ClickEvent$Action;
/*     */     //   314: sipush #2584
/*     */     //   317: ldc2_w 3766906236547264494
/*     */     //   320: lload #5
/*     */     //   322: lxor
/*     */     //   323: <illegal opcode> e : (IJ)Ljava/lang/String;
/*     */     //   328: invokespecial <init> : (Lnet/md_5/bungee/api/chat/ClickEvent$Action;Ljava/lang/String;)V
/*     */     //   331: invokevirtual setClickEvent : (Lnet/md_5/bungee/api/chat/ClickEvent;)V
/*     */     //   334: aload #39
/*     */     //   336: aload #40
/*     */     //   338: invokevirtual addExtra : (Lnet/md_5/bungee/api/chat/BaseComponent;)V
/*     */     //   341: aload_1
/*     */     //   342: aload #39
/*     */     //   344: lload #7
/*     */     //   346: invokestatic a : (Lorg/bukkit/command/CommandSender;Lnet/md_5/bungee/api/chat/BaseComponent;J)V
/*     */     //   349: iconst_0
/*     */     //   350: ireturn
/*     */     //   351: aload #4
/*     */     //   353: iconst_0
/*     */     //   354: aaload
/*     */     //   355: invokevirtual toLowerCase : ()Ljava/lang/String;
/*     */     //   358: astore #39
/*     */     //   360: iconst_m1
/*     */     //   361: istore #40
/*     */     //   363: aload #39
/*     */     //   365: invokevirtual hashCode : ()I
/*     */     //   368: iload #38
/*     */     //   370: ifeq -> 1250
/*     */     //   373: lookupswitch default -> 1248, -2132551719 -> 680, -1415077225 -> 997, -1289483297 -> 617, -934641255 -> 1125, -892481550 -> 554, -838846263 -> 1189, 3198785 -> 491, 3536827 -> 743, 3541613 -> 806, 94627080 -> 933, 95458899 -> 1061, 108404047 -> 869
/*     */     //   480: ldc2_w -9208511308924703329
/*     */     //   483: lload #5
/*     */     //   485: <illegal opcode> w : (Ljava/lang/Throwable;JJ)Ljava/lang/Throwable;
/*     */     //   490: athrow
/*     */     //   491: aload #39
/*     */     //   493: sipush #27806
/*     */     //   496: ldc2_w 2818543576389552536
/*     */     //   499: lload #5
/*     */     //   501: lxor
/*     */     //   502: <illegal opcode> e : (IJ)Ljava/lang/String;
/*     */     //   507: invokevirtual equals : (Ljava/lang/Object;)Z
/*     */     //   510: iload #38
/*     */     //   512: ifeq -> 1250
/*     */     //   515: goto -> 529
/*     */     //   518: ldc2_w -9208511308924703329
/*     */     //   521: lload #5
/*     */     //   523: <illegal opcode> w : (Ljava/lang/Throwable;JJ)Ljava/lang/Throwable;
/*     */     //   528: athrow
/*     */     //   529: ifeq -> 1248
/*     */     //   532: goto -> 546
/*     */     //   535: ldc2_w -9208511308924703329
/*     */     //   538: lload #5
/*     */     //   540: <illegal opcode> w : (Ljava/lang/Throwable;JJ)Ljava/lang/Throwable;
/*     */     //   545: athrow
/*     */     //   546: iconst_0
/*     */     //   547: istore #40
/*     */     //   549: iload #38
/*     */     //   551: ifne -> 1248
/*     */     //   554: aload #39
/*     */     //   556: sipush #12309
/*     */     //   559: ldc2_w 1071922466306643224
/*     */     //   562: lload #5
/*     */     //   564: lxor
/*     */     //   565: <illegal opcode> e : (IJ)Ljava/lang/String;
/*     */     //   570: invokevirtual equals : (Ljava/lang/Object;)Z
/*     */     //   573: iload #38
/*     */     //   575: ifeq -> 1250
/*     */     //   578: goto -> 592
/*     */     //   581: ldc2_w -9208511308924703329
/*     */     //   584: lload #5
/*     */     //   586: <illegal opcode> w : (Ljava/lang/Throwable;JJ)Ljava/lang/Throwable;
/*     */     //   591: athrow
/*     */     //   592: ifeq -> 1248
/*     */     //   595: goto -> 609
/*     */     //   598: ldc2_w -9208511308924703329
/*     */     //   601: lload #5
/*     */     //   603: <illegal opcode> w : (Ljava/lang/Throwable;JJ)Ljava/lang/Throwable;
/*     */     //   608: athrow
/*     */     //   609: iconst_1
/*     */     //   610: istore #40
/*     */     //   612: iload #38
/*     */     //   614: ifne -> 1248
/*     */     //   617: aload #39
/*     */     //   619: sipush #24931
/*     */     //   622: ldc2_w 3956973198967178401
/*     */     //   625: lload #5
/*     */     //   627: lxor
/*     */     //   628: <illegal opcode> e : (IJ)Ljava/lang/String;
/*     */     //   633: invokevirtual equals : (Ljava/lang/Object;)Z
/*     */     //   636: iload #38
/*     */     //   638: ifeq -> 1250
/*     */     //   641: goto -> 655
/*     */     //   644: ldc2_w -9208511308924703329
/*     */     //   647: lload #5
/*     */     //   649: <illegal opcode> w : (Ljava/lang/Throwable;JJ)Ljava/lang/Throwable;
/*     */     //   654: athrow
/*     */     //   655: ifeq -> 1248
/*     */     //   658: goto -> 672
/*     */     //   661: ldc2_w -9208511308924703329
/*     */     //   664: lload #5
/*     */     //   666: <illegal opcode> w : (Ljava/lang/Throwable;JJ)Ljava/lang/Throwable;
/*     */     //   671: athrow
/*     */     //   672: iconst_2
/*     */     //   673: istore #40
/*     */     //   675: iload #38
/*     */     //   677: ifne -> 1248
/*     */     //   680: aload #39
/*     */     //   682: sipush #22877
/*     */     //   685: ldc2_w 545546758295993419
/*     */     //   688: lload #5
/*     */     //   690: lxor
/*     */     //   691: <illegal opcode> e : (IJ)Ljava/lang/String;
/*     */     //   696: invokevirtual equals : (Ljava/lang/Object;)Z
/*     */     //   699: iload #38
/*     */     //   701: ifeq -> 1250
/*     */     //   704: goto -> 718
/*     */     //   707: ldc2_w -9208511308924703329
/*     */     //   710: lload #5
/*     */     //   712: <illegal opcode> w : (Ljava/lang/Throwable;JJ)Ljava/lang/Throwable;
/*     */     //   717: athrow
/*     */     //   718: ifeq -> 1248
/*     */     //   721: goto -> 735
/*     */     //   724: ldc2_w -9208511308924703329
/*     */     //   727: lload #5
/*     */     //   729: <illegal opcode> w : (Ljava/lang/Throwable;JJ)Ljava/lang/Throwable;
/*     */     //   734: athrow
/*     */     //   735: iconst_3
/*     */     //   736: istore #40
/*     */     //   738: iload #38
/*     */     //   740: ifne -> 1248
/*     */     //   743: aload #39
/*     */     //   745: sipush #32196
/*     */     //   748: ldc2_w 2694151251214145537
/*     */     //   751: lload #5
/*     */     //   753: lxor
/*     */     //   754: <illegal opcode> e : (IJ)Ljava/lang/String;
/*     */     //   759: invokevirtual equals : (Ljava/lang/Object;)Z
/*     */     //   762: iload #38
/*     */     //   764: ifeq -> 1250
/*     */     //   767: goto -> 781
/*     */     //   770: ldc2_w -9208511308924703329
/*     */     //   773: lload #5
/*     */     //   775: <illegal opcode> w : (Ljava/lang/Throwable;JJ)Ljava/lang/Throwable;
/*     */     //   780: athrow
/*     */     //   781: ifeq -> 1248
/*     */     //   784: goto -> 798
/*     */     //   787: ldc2_w -9208511308924703329
/*     */     //   790: lload #5
/*     */     //   792: <illegal opcode> w : (Ljava/lang/Throwable;JJ)Ljava/lang/Throwable;
/*     */     //   797: athrow
/*     */     //   798: iconst_4
/*     */     //   799: istore #40
/*     */     //   801: iload #38
/*     */     //   803: ifne -> 1248
/*     */     //   806: aload #39
/*     */     //   808: sipush #4262
/*     */     //   811: ldc2_w 3361025104706041196
/*     */     //   814: lload #5
/*     */     //   816: lxor
/*     */     //   817: <illegal opcode> e : (IJ)Ljava/lang/String;
/*     */     //   822: invokevirtual equals : (Ljava/lang/Object;)Z
/*     */     //   825: iload #38
/*     */     //   827: ifeq -> 1250
/*     */     //   830: goto -> 844
/*     */     //   833: ldc2_w -9208511308924703329
/*     */     //   836: lload #5
/*     */     //   838: <illegal opcode> w : (Ljava/lang/Throwable;JJ)Ljava/lang/Throwable;
/*     */     //   843: athrow
/*     */     //   844: ifeq -> 1248
/*     */     //   847: goto -> 861
/*     */     //   850: ldc2_w -9208511308924703329
/*     */     //   853: lload #5
/*     */     //   855: <illegal opcode> w : (Ljava/lang/Throwable;JJ)Ljava/lang/Throwable;
/*     */     //   860: athrow
/*     */     //   861: iconst_5
/*     */     //   862: istore #40
/*     */     //   864: iload #38
/*     */     //   866: ifne -> 1248
/*     */     //   869: aload #39
/*     */     //   871: sipush #11885
/*     */     //   874: ldc2_w 272023691868818373
/*     */     //   877: lload #5
/*     */     //   879: lxor
/*     */     //   880: <illegal opcode> e : (IJ)Ljava/lang/String;
/*     */     //   885: invokevirtual equals : (Ljava/lang/Object;)Z
/*     */     //   888: iload #38
/*     */     //   890: ifeq -> 1250
/*     */     //   893: goto -> 907
/*     */     //   896: ldc2_w -9208511308924703329
/*     */     //   899: lload #5
/*     */     //   901: <illegal opcode> w : (Ljava/lang/Throwable;JJ)Ljava/lang/Throwable;
/*     */     //   906: athrow
/*     */     //   907: ifeq -> 1248
/*     */     //   910: goto -> 924
/*     */     //   913: ldc2_w -9208511308924703329
/*     */     //   916: lload #5
/*     */     //   918: <illegal opcode> w : (Ljava/lang/Throwable;JJ)Ljava/lang/Throwable;
/*     */     //   923: athrow
/*     */     //   924: bipush #6
/*     */     //   926: istore #40
/*     */     //   928: iload #38
/*     */     //   930: ifne -> 1248
/*     */     //   933: aload #39
/*     */     //   935: sipush #25236
/*     */     //   938: ldc2_w 191420908673828664
/*     */     //   941: lload #5
/*     */     //   943: lxor
/*     */     //   944: <illegal opcode> e : (IJ)Ljava/lang/String;
/*     */     //   949: invokevirtual equals : (Ljava/lang/Object;)Z
/*     */     //   952: iload #38
/*     */     //   954: ifeq -> 1250
/*     */     //   957: goto -> 971
/*     */     //   960: ldc2_w -9208511308924703329
/*     */     //   963: lload #5
/*     */     //   965: <illegal opcode> w : (Ljava/lang/Throwable;JJ)Ljava/lang/Throwable;
/*     */     //   970: athrow
/*     */     //   971: ifeq -> 1248
/*     */     //   974: goto -> 988
/*     */     //   977: ldc2_w -9208511308924703329
/*     */     //   980: lload #5
/*     */     //   982: <illegal opcode> w : (Ljava/lang/Throwable;JJ)Ljava/lang/Throwable;
/*     */     //   987: athrow
/*     */     //   988: bipush #7
/*     */     //   990: istore #40
/*     */     //   992: iload #38
/*     */     //   994: ifne -> 1248
/*     */     //   997: aload #39
/*     */     //   999: sipush #30588
/*     */     //   1002: ldc2_w 5699440052053316241
/*     */     //   1005: lload #5
/*     */     //   1007: lxor
/*     */     //   1008: <illegal opcode> e : (IJ)Ljava/lang/String;
/*     */     //   1013: invokevirtual equals : (Ljava/lang/Object;)Z
/*     */     //   1016: iload #38
/*     */     //   1018: ifeq -> 1250
/*     */     //   1021: goto -> 1035
/*     */     //   1024: ldc2_w -9208511308924703329
/*     */     //   1027: lload #5
/*     */     //   1029: <illegal opcode> w : (Ljava/lang/Throwable;JJ)Ljava/lang/Throwable;
/*     */     //   1034: athrow
/*     */     //   1035: ifeq -> 1248
/*     */     //   1038: goto -> 1052
/*     */     //   1041: ldc2_w -9208511308924703329
/*     */     //   1044: lload #5
/*     */     //   1046: <illegal opcode> w : (Ljava/lang/Throwable;JJ)Ljava/lang/Throwable;
/*     */     //   1051: athrow
/*     */     //   1052: bipush #8
/*     */     //   1054: istore #40
/*     */     //   1056: iload #38
/*     */     //   1058: ifne -> 1248
/*     */     //   1061: aload #39
/*     */     //   1063: sipush #3347
/*     */     //   1066: ldc2_w 7858541470260947188
/*     */     //   1069: lload #5
/*     */     //   1071: lxor
/*     */     //   1072: <illegal opcode> e : (IJ)Ljava/lang/String;
/*     */     //   1077: invokevirtual equals : (Ljava/lang/Object;)Z
/*     */     //   1080: iload #38
/*     */     //   1082: ifeq -> 1250
/*     */     //   1085: goto -> 1099
/*     */     //   1088: ldc2_w -9208511308924703329
/*     */     //   1091: lload #5
/*     */     //   1093: <illegal opcode> w : (Ljava/lang/Throwable;JJ)Ljava/lang/Throwable;
/*     */     //   1098: athrow
/*     */     //   1099: ifeq -> 1248
/*     */     //   1102: goto -> 1116
/*     */     //   1105: ldc2_w -9208511308924703329
/*     */     //   1108: lload #5
/*     */     //   1110: <illegal opcode> w : (Ljava/lang/Throwable;JJ)Ljava/lang/Throwable;
/*     */     //   1115: athrow
/*     */     //   1116: bipush #9
/*     */     //   1118: istore #40
/*     */     //   1120: iload #38
/*     */     //   1122: ifne -> 1248
/*     */     //   1125: aload #39
/*     */     //   1127: sipush #19599
/*     */     //   1130: ldc2_w 3723268986304211224
/*     */     //   1133: lload #5
/*     */     //   1135: lxor
/*     */     //   1136: <illegal opcode> e : (IJ)Ljava/lang/String;
/*     */     //   1141: invokevirtual equals : (Ljava/lang/Object;)Z
/*     */     //   1144: iload #38
/*     */     //   1146: ifeq -> 1250
/*     */     //   1149: goto -> 1163
/*     */     //   1152: ldc2_w -9208511308924703329
/*     */     //   1155: lload #5
/*     */     //   1157: <illegal opcode> w : (Ljava/lang/Throwable;JJ)Ljava/lang/Throwable;
/*     */     //   1162: athrow
/*     */     //   1163: ifeq -> 1248
/*     */     //   1166: goto -> 1180
/*     */     //   1169: ldc2_w -9208511308924703329
/*     */     //   1172: lload #5
/*     */     //   1174: <illegal opcode> w : (Ljava/lang/Throwable;JJ)Ljava/lang/Throwable;
/*     */     //   1179: athrow
/*     */     //   1180: bipush #10
/*     */     //   1182: istore #40
/*     */     //   1184: iload #38
/*     */     //   1186: ifne -> 1248
/*     */     //   1189: aload #39
/*     */     //   1191: sipush #24262
/*     */     //   1194: ldc2_w 9164202387532364643
/*     */     //   1197: lload #5
/*     */     //   1199: lxor
/*     */     //   1200: <illegal opcode> e : (IJ)Ljava/lang/String;
/*     */     //   1205: invokevirtual equals : (Ljava/lang/Object;)Z
/*     */     //   1208: iload #38
/*     */     //   1210: ifeq -> 1250
/*     */     //   1213: goto -> 1227
/*     */     //   1216: ldc2_w -9208511308924703329
/*     */     //   1219: lload #5
/*     */     //   1221: <illegal opcode> w : (Ljava/lang/Throwable;JJ)Ljava/lang/Throwable;
/*     */     //   1226: athrow
/*     */     //   1227: ifeq -> 1248
/*     */     //   1230: goto -> 1244
/*     */     //   1233: ldc2_w -9208511308924703329
/*     */     //   1236: lload #5
/*     */     //   1238: <illegal opcode> w : (Ljava/lang/Throwable;JJ)Ljava/lang/Throwable;
/*     */     //   1243: athrow
/*     */     //   1244: bipush #11
/*     */     //   1246: istore #40
/*     */     //   1248: iload #40
/*     */     //   1250: iload #38
/*     */     //   1252: ifeq -> 6454
/*     */     //   1255: tableswitch default -> 6453, 0 -> 1327, 1 -> 2261, 2 -> 2696, 3 -> 3079, 4 -> 3079, 5 -> 3841, 6 -> 4333, 7 -> 4545, 8 -> 4744, 9 -> 5481, 10 -> 6101, 11 -> 6296
/*     */     //   1316: ldc2_w -9208511308924703329
/*     */     //   1319: lload #5
/*     */     //   1321: <illegal opcode> w : (Ljava/lang/Throwable;JJ)Ljava/lang/Throwable;
/*     */     //   1326: athrow
/*     */     //   1327: aload_1
/*     */     //   1328: sipush #10888
/*     */     //   1331: ldc2_w 1191835255911534338
/*     */     //   1334: lload #5
/*     */     //   1336: lxor
/*     */     //   1337: <illegal opcode> e : (IJ)Ljava/lang/String;
/*     */     //   1342: invokeinterface hasPermission : (Ljava/lang/String;)Z
/*     */     //   1347: iload #38
/*     */     //   1349: ifeq -> 1473
/*     */     //   1352: goto -> 1366
/*     */     //   1355: ldc2_w -9208511308924703329
/*     */     //   1358: lload #5
/*     */     //   1360: <illegal opcode> w : (Ljava/lang/Throwable;JJ)Ljava/lang/Throwable;
/*     */     //   1365: athrow
/*     */     //   1366: ifeq -> 1453
/*     */     //   1369: goto -> 1383
/*     */     //   1372: ldc2_w -9208511308924703329
/*     */     //   1375: lload #5
/*     */     //   1377: <illegal opcode> w : (Ljava/lang/Throwable;JJ)Ljava/lang/Throwable;
/*     */     //   1382: athrow
/*     */     //   1383: aload_0
/*     */     //   1384: lload #15
/*     */     //   1386: invokespecial a : (J)Lnet/md_5/bungee/api/chat/BaseComponent;
/*     */     //   1389: astore #41
/*     */     //   1391: aload #41
/*     */     //   1393: sipush #4600
/*     */     //   1396: ldc2_w 8270066427161900072
/*     */     //   1399: lload #5
/*     */     //   1401: lxor
/*     */     //   1402: <illegal opcode> e : (IJ)Ljava/lang/String;
/*     */     //   1407: invokevirtual addExtra : (Ljava/lang/String;)V
/*     */     //   1410: aload_1
/*     */     //   1411: aload #41
/*     */     //   1413: lload #7
/*     */     //   1415: invokestatic a : (Lorg/bukkit/command/CommandSender;Lnet/md_5/bungee/api/chat/BaseComponent;J)V
/*     */     //   1418: aload_0
/*     */     //   1419: lload #15
/*     */     //   1421: invokespecial a : (J)Lnet/md_5/bungee/api/chat/BaseComponent;
/*     */     //   1424: astore #42
/*     */     //   1426: aload #42
/*     */     //   1428: sipush #11896
/*     */     //   1431: ldc2_w 1766047525062396777
/*     */     //   1434: lload #5
/*     */     //   1436: lxor
/*     */     //   1437: <illegal opcode> e : (IJ)Ljava/lang/String;
/*     */     //   1442: invokevirtual addExtra : (Ljava/lang/String;)V
/*     */     //   1445: aload_1
/*     */     //   1446: aload #42
/*     */     //   1448: lload #7
/*     */     //   1450: invokestatic a : (Lorg/bukkit/command/CommandSender;Lnet/md_5/bungee/api/chat/BaseComponent;J)V
/*     */     //   1453: aload_1
/*     */     //   1454: sipush #15222
/*     */     //   1457: ldc2_w 8941707196650806984
/*     */     //   1460: lload #5
/*     */     //   1462: lxor
/*     */     //   1463: <illegal opcode> e : (IJ)Ljava/lang/String;
/*     */     //   1468: invokeinterface hasPermission : (Ljava/lang/String;)Z
/*     */     //   1473: iload #38
/*     */     //   1475: ifeq -> 1550
/*     */     //   1478: ifeq -> 1530
/*     */     //   1481: goto -> 1495
/*     */     //   1484: ldc2_w -9208511308924703329
/*     */     //   1487: lload #5
/*     */     //   1489: <illegal opcode> w : (Ljava/lang/Throwable;JJ)Ljava/lang/Throwable;
/*     */     //   1494: athrow
/*     */     //   1495: aload_0
/*     */     //   1496: lload #15
/*     */     //   1498: invokespecial a : (J)Lnet/md_5/bungee/api/chat/BaseComponent;
/*     */     //   1501: astore #41
/*     */     //   1503: aload #41
/*     */     //   1505: sipush #21935
/*     */     //   1508: ldc2_w 4217492889571209337
/*     */     //   1511: lload #5
/*     */     //   1513: lxor
/*     */     //   1514: <illegal opcode> e : (IJ)Ljava/lang/String;
/*     */     //   1519: invokevirtual addExtra : (Ljava/lang/String;)V
/*     */     //   1522: aload_1
/*     */     //   1523: aload #41
/*     */     //   1525: lload #7
/*     */     //   1527: invokestatic a : (Lorg/bukkit/command/CommandSender;Lnet/md_5/bungee/api/chat/BaseComponent;J)V
/*     */     //   1530: aload_1
/*     */     //   1531: sipush #1517
/*     */     //   1534: ldc2_w 1255729896049270836
/*     */     //   1537: lload #5
/*     */     //   1539: lxor
/*     */     //   1540: <illegal opcode> e : (IJ)Ljava/lang/String;
/*     */     //   1545: invokeinterface hasPermission : (Ljava/lang/String;)Z
/*     */     //   1550: iload #38
/*     */     //   1552: ifeq -> 1662
/*     */     //   1555: ifeq -> 1642
/*     */     //   1558: goto -> 1572
/*     */     //   1561: ldc2_w -9208511308924703329
/*     */     //   1564: lload #5
/*     */     //   1566: <illegal opcode> w : (Ljava/lang/Throwable;JJ)Ljava/lang/Throwable;
/*     */     //   1571: athrow
/*     */     //   1572: aload_0
/*     */     //   1573: lload #15
/*     */     //   1575: invokespecial a : (J)Lnet/md_5/bungee/api/chat/BaseComponent;
/*     */     //   1578: astore #41
/*     */     //   1580: aload #41
/*     */     //   1582: sipush #3261
/*     */     //   1585: ldc2_w 1097746141876349289
/*     */     //   1588: lload #5
/*     */     //   1590: lxor
/*     */     //   1591: <illegal opcode> e : (IJ)Ljava/lang/String;
/*     */     //   1596: invokevirtual addExtra : (Ljava/lang/String;)V
/*     */     //   1599: aload_1
/*     */     //   1600: aload #41
/*     */     //   1602: lload #7
/*     */     //   1604: invokestatic a : (Lorg/bukkit/command/CommandSender;Lnet/md_5/bungee/api/chat/BaseComponent;J)V
/*     */     //   1607: aload_0
/*     */     //   1608: lload #15
/*     */     //   1610: invokespecial a : (J)Lnet/md_5/bungee/api/chat/BaseComponent;
/*     */     //   1613: astore #42
/*     */     //   1615: aload #42
/*     */     //   1617: sipush #1041
/*     */     //   1620: ldc2_w 3592391067722015166
/*     */     //   1623: lload #5
/*     */     //   1625: lxor
/*     */     //   1626: <illegal opcode> e : (IJ)Ljava/lang/String;
/*     */     //   1631: invokevirtual addExtra : (Ljava/lang/String;)V
/*     */     //   1634: aload_1
/*     */     //   1635: aload #42
/*     */     //   1637: lload #7
/*     */     //   1639: invokestatic a : (Lorg/bukkit/command/CommandSender;Lnet/md_5/bungee/api/chat/BaseComponent;J)V
/*     */     //   1642: aload_1
/*     */     //   1643: sipush #26385
/*     */     //   1646: ldc2_w 653494656713622032
/*     */     //   1649: lload #5
/*     */     //   1651: lxor
/*     */     //   1652: <illegal opcode> e : (IJ)Ljava/lang/String;
/*     */     //   1657: invokeinterface hasPermission : (Ljava/lang/String;)Z
/*     */     //   1662: iload #38
/*     */     //   1664: ifeq -> 1739
/*     */     //   1667: ifeq -> 1719
/*     */     //   1670: goto -> 1684
/*     */     //   1673: ldc2_w -9208511308924703329
/*     */     //   1676: lload #5
/*     */     //   1678: <illegal opcode> w : (Ljava/lang/Throwable;JJ)Ljava/lang/Throwable;
/*     */     //   1683: athrow
/*     */     //   1684: aload_0
/*     */     //   1685: lload #15
/*     */     //   1687: invokespecial a : (J)Lnet/md_5/bungee/api/chat/BaseComponent;
/*     */     //   1690: astore #41
/*     */     //   1692: aload #41
/*     */     //   1694: sipush #24329
/*     */     //   1697: ldc2_w 6080424614615431844
/*     */     //   1700: lload #5
/*     */     //   1702: lxor
/*     */     //   1703: <illegal opcode> e : (IJ)Ljava/lang/String;
/*     */     //   1708: invokevirtual addExtra : (Ljava/lang/String;)V
/*     */     //   1711: aload_1
/*     */     //   1712: aload #41
/*     */     //   1714: lload #7
/*     */     //   1716: invokestatic a : (Lorg/bukkit/command/CommandSender;Lnet/md_5/bungee/api/chat/BaseComponent;J)V
/*     */     //   1719: aload_1
/*     */     //   1720: sipush #13458
/*     */     //   1723: ldc2_w 4051711572724535585
/*     */     //   1726: lload #5
/*     */     //   1728: lxor
/*     */     //   1729: <illegal opcode> e : (IJ)Ljava/lang/String;
/*     */     //   1734: invokeinterface hasPermission : (Ljava/lang/String;)Z
/*     */     //   1739: iload #38
/*     */     //   1741: ifeq -> 1816
/*     */     //   1744: ifeq -> 1796
/*     */     //   1747: goto -> 1761
/*     */     //   1750: ldc2_w -9208511308924703329
/*     */     //   1753: lload #5
/*     */     //   1755: <illegal opcode> w : (Ljava/lang/Throwable;JJ)Ljava/lang/Throwable;
/*     */     //   1760: athrow
/*     */     //   1761: aload_0
/*     */     //   1762: lload #15
/*     */     //   1764: invokespecial a : (J)Lnet/md_5/bungee/api/chat/BaseComponent;
/*     */     //   1767: astore #41
/*     */     //   1769: aload #41
/*     */     //   1771: sipush #13837
/*     */     //   1774: ldc2_w 5575146980462318345
/*     */     //   1777: lload #5
/*     */     //   1779: lxor
/*     */     //   1780: <illegal opcode> e : (IJ)Ljava/lang/String;
/*     */     //   1785: invokevirtual addExtra : (Ljava/lang/String;)V
/*     */     //   1788: aload_1
/*     */     //   1789: aload #41
/*     */     //   1791: lload #7
/*     */     //   1793: invokestatic a : (Lorg/bukkit/command/CommandSender;Lnet/md_5/bungee/api/chat/BaseComponent;J)V
/*     */     //   1796: aload_1
/*     */     //   1797: sipush #10044
/*     */     //   1800: ldc2_w 7302392847869362751
/*     */     //   1803: lload #5
/*     */     //   1805: lxor
/*     */     //   1806: <illegal opcode> e : (IJ)Ljava/lang/String;
/*     */     //   1811: invokeinterface hasPermission : (Ljava/lang/String;)Z
/*     */     //   1816: iload #38
/*     */     //   1818: ifeq -> 1893
/*     */     //   1821: ifeq -> 1873
/*     */     //   1824: goto -> 1838
/*     */     //   1827: ldc2_w -9208511308924703329
/*     */     //   1830: lload #5
/*     */     //   1832: <illegal opcode> w : (Ljava/lang/Throwable;JJ)Ljava/lang/Throwable;
/*     */     //   1837: athrow
/*     */     //   1838: aload_0
/*     */     //   1839: lload #15
/*     */     //   1841: invokespecial a : (J)Lnet/md_5/bungee/api/chat/BaseComponent;
/*     */     //   1844: astore #41
/*     */     //   1846: aload #41
/*     */     //   1848: sipush #14928
/*     */     //   1851: ldc2_w 8387648433394016090
/*     */     //   1854: lload #5
/*     */     //   1856: lxor
/*     */     //   1857: <illegal opcode> e : (IJ)Ljava/lang/String;
/*     */     //   1862: invokevirtual addExtra : (Ljava/lang/String;)V
/*     */     //   1865: aload_1
/*     */     //   1866: aload #41
/*     */     //   1868: lload #7
/*     */     //   1870: invokestatic a : (Lorg/bukkit/command/CommandSender;Lnet/md_5/bungee/api/chat/BaseComponent;J)V
/*     */     //   1873: aload_1
/*     */     //   1874: sipush #5430
/*     */     //   1877: ldc2_w 2474439204920848634
/*     */     //   1880: lload #5
/*     */     //   1882: lxor
/*     */     //   1883: <illegal opcode> e : (IJ)Ljava/lang/String;
/*     */     //   1888: invokeinterface hasPermission : (Ljava/lang/String;)Z
/*     */     //   1893: iload #38
/*     */     //   1895: ifeq -> 2005
/*     */     //   1898: ifeq -> 1985
/*     */     //   1901: goto -> 1915
/*     */     //   1904: ldc2_w -9208511308924703329
/*     */     //   1907: lload #5
/*     */     //   1909: <illegal opcode> w : (Ljava/lang/Throwable;JJ)Ljava/lang/Throwable;
/*     */     //   1914: athrow
/*     */     //   1915: aload_0
/*     */     //   1916: lload #15
/*     */     //   1918: invokespecial a : (J)Lnet/md_5/bungee/api/chat/BaseComponent;
/*     */     //   1921: astore #41
/*     */     //   1923: aload #41
/*     */     //   1925: sipush #22579
/*     */     //   1928: ldc2_w 705864858870824368
/*     */     //   1931: lload #5
/*     */     //   1933: lxor
/*     */     //   1934: <illegal opcode> e : (IJ)Ljava/lang/String;
/*     */     //   1939: invokevirtual addExtra : (Ljava/lang/String;)V
/*     */     //   1942: aload_1
/*     */     //   1943: aload #41
/*     */     //   1945: lload #7
/*     */     //   1947: invokestatic a : (Lorg/bukkit/command/CommandSender;Lnet/md_5/bungee/api/chat/BaseComponent;J)V
/*     */     //   1950: aload_0
/*     */     //   1951: lload #15
/*     */     //   1953: invokespecial a : (J)Lnet/md_5/bungee/api/chat/BaseComponent;
/*     */     //   1956: astore #42
/*     */     //   1958: aload #42
/*     */     //   1960: sipush #15936
/*     */     //   1963: ldc2_w 473195198887287730
/*     */     //   1966: lload #5
/*     */     //   1968: lxor
/*     */     //   1969: <illegal opcode> e : (IJ)Ljava/lang/String;
/*     */     //   1974: invokevirtual addExtra : (Ljava/lang/String;)V
/*     */     //   1977: aload_1
/*     */     //   1978: aload #42
/*     */     //   1980: lload #7
/*     */     //   1982: invokestatic a : (Lorg/bukkit/command/CommandSender;Lnet/md_5/bungee/api/chat/BaseComponent;J)V
/*     */     //   1985: aload_1
/*     */     //   1986: sipush #25633
/*     */     //   1989: ldc2_w 4501323445564735995
/*     */     //   1992: lload #5
/*     */     //   1994: lxor
/*     */     //   1995: <illegal opcode> e : (IJ)Ljava/lang/String;
/*     */     //   2000: invokeinterface hasPermission : (Ljava/lang/String;)Z
/*     */     //   2005: iload #38
/*     */     //   2007: ifeq -> 2082
/*     */     //   2010: ifeq -> 2062
/*     */     //   2013: goto -> 2027
/*     */     //   2016: ldc2_w -9208511308924703329
/*     */     //   2019: lload #5
/*     */     //   2021: <illegal opcode> w : (Ljava/lang/Throwable;JJ)Ljava/lang/Throwable;
/*     */     //   2026: athrow
/*     */     //   2027: aload_0
/*     */     //   2028: lload #15
/*     */     //   2030: invokespecial a : (J)Lnet/md_5/bungee/api/chat/BaseComponent;
/*     */     //   2033: astore #41
/*     */     //   2035: aload #41
/*     */     //   2037: sipush #13829
/*     */     //   2040: ldc2_w 4563169790407398323
/*     */     //   2043: lload #5
/*     */     //   2045: lxor
/*     */     //   2046: <illegal opcode> e : (IJ)Ljava/lang/String;
/*     */     //   2051: invokevirtual addExtra : (Ljava/lang/String;)V
/*     */     //   2054: aload_1
/*     */     //   2055: aload #41
/*     */     //   2057: lload #7
/*     */     //   2059: invokestatic a : (Lorg/bukkit/command/CommandSender;Lnet/md_5/bungee/api/chat/BaseComponent;J)V
/*     */     //   2062: aload_1
/*     */     //   2063: sipush #17860
/*     */     //   2066: ldc2_w 5992320450826248318
/*     */     //   2069: lload #5
/*     */     //   2071: lxor
/*     */     //   2072: <illegal opcode> e : (IJ)Ljava/lang/String;
/*     */     //   2077: invokeinterface hasPermission : (Ljava/lang/String;)Z
/*     */     //   2082: ifeq -> 2120
/*     */     //   2085: aload_0
/*     */     //   2086: lload #15
/*     */     //   2088: invokespecial a : (J)Lnet/md_5/bungee/api/chat/BaseComponent;
/*     */     //   2091: astore #41
/*     */     //   2093: aload #41
/*     */     //   2095: sipush #142
/*     */     //   2098: ldc2_w 3342237268770219373
/*     */     //   2101: lload #5
/*     */     //   2103: lxor
/*     */     //   2104: <illegal opcode> e : (IJ)Ljava/lang/String;
/*     */     //   2109: invokevirtual addExtra : (Ljava/lang/String;)V
/*     */     //   2112: aload_1
/*     */     //   2113: aload #41
/*     */     //   2115: lload #7
/*     */     //   2117: invokestatic a : (Lorg/bukkit/command/CommandSender;Lnet/md_5/bungee/api/chat/BaseComponent;J)V
/*     */     //   2120: aload_0
/*     */     //   2121: getfield b : Lme/konsolas/aac/AAC;
/*     */     //   2124: invokevirtual a : ()Lme/konsolas/aac/kk;
/*     */     //   2127: invokevirtual b : ()Ljava/lang/String;
/*     */     //   2130: ifnull -> 2259
/*     */     //   2133: aload_1
/*     */     //   2134: sipush #7682
/*     */     //   2137: ldc2_w 4248209336332155802
/*     */     //   2140: lload #5
/*     */     //   2142: lxor
/*     */     //   2143: <illegal opcode> e : (IJ)Ljava/lang/String;
/*     */     //   2148: invokeinterface hasPermission : (Ljava/lang/String;)Z
/*     */     //   2153: iload #38
/*     */     //   2155: ifeq -> 2260
/*     */     //   2158: goto -> 2172
/*     */     //   2161: ldc2_w -9208511308924703329
/*     */     //   2164: lload #5
/*     */     //   2166: <illegal opcode> w : (Ljava/lang/Throwable;JJ)Ljava/lang/Throwable;
/*     */     //   2171: athrow
/*     */     //   2172: ifeq -> 2259
/*     */     //   2175: goto -> 2189
/*     */     //   2178: ldc2_w -9208511308924703329
/*     */     //   2181: lload #5
/*     */     //   2183: <illegal opcode> w : (Ljava/lang/Throwable;JJ)Ljava/lang/Throwable;
/*     */     //   2188: athrow
/*     */     //   2189: aload_0
/*     */     //   2190: lload #15
/*     */     //   2192: invokespecial a : (J)Lnet/md_5/bungee/api/chat/BaseComponent;
/*     */     //   2195: astore #41
/*     */     //   2197: aload #41
/*     */     //   2199: sipush #11079
/*     */     //   2202: ldc2_w 2730366344063897301
/*     */     //   2205: lload #5
/*     */     //   2207: lxor
/*     */     //   2208: <illegal opcode> e : (IJ)Ljava/lang/String;
/*     */     //   2213: invokevirtual addExtra : (Ljava/lang/String;)V
/*     */     //   2216: aload_1
/*     */     //   2217: aload #41
/*     */     //   2219: lload #7
/*     */     //   2221: invokestatic a : (Lorg/bukkit/command/CommandSender;Lnet/md_5/bungee/api/chat/BaseComponent;J)V
/*     */     //   2224: aload_0
/*     */     //   2225: lload #15
/*     */     //   2227: invokespecial a : (J)Lnet/md_5/bungee/api/chat/BaseComponent;
/*     */     //   2230: astore #42
/*     */     //   2232: aload #42
/*     */     //   2234: sipush #30486
/*     */     //   2237: ldc2_w 3362926852122088125
/*     */     //   2240: lload #5
/*     */     //   2242: lxor
/*     */     //   2243: <illegal opcode> e : (IJ)Ljava/lang/String;
/*     */     //   2248: invokevirtual addExtra : (Ljava/lang/String;)V
/*     */     //   2251: aload_1
/*     */     //   2252: aload #42
/*     */     //   2254: lload #7
/*     */     //   2256: invokestatic a : (Lorg/bukkit/command/CommandSender;Lnet/md_5/bungee/api/chat/BaseComponent;J)V
/*     */     //   2259: iconst_1
/*     */     //   2260: ireturn
/*     */     //   2261: aload_1
/*     */     //   2262: sipush #10804
/*     */     //   2265: ldc2_w 7604876589522112413
/*     */     //   2268: lload #5
/*     */     //   2270: lxor
/*     */     //   2271: <illegal opcode> e : (IJ)Ljava/lang/String;
/*     */     //   2276: invokeinterface hasPermission : (Ljava/lang/String;)Z
/*     */     //   2281: iload #38
/*     */     //   2283: ifeq -> 2339
/*     */     //   2286: ifne -> 2336
/*     */     //   2289: goto -> 2303
/*     */     //   2292: ldc2_w -9208511308924703329
/*     */     //   2295: lload #5
/*     */     //   2297: <illegal opcode> w : (Ljava/lang/Throwable;JJ)Ljava/lang/Throwable;
/*     */     //   2302: athrow
/*     */     //   2303: aload_1
/*     */     //   2304: sipush #4831
/*     */     //   2307: ldc2_w 4370035476188559124
/*     */     //   2310: lload #5
/*     */     //   2312: lxor
/*     */     //   2313: <illegal opcode> e : (IJ)Ljava/lang/String;
/*     */     //   2318: invokeinterface sendMessage : (Ljava/lang/String;)V
/*     */     //   2323: iconst_0
/*     */     //   2324: ireturn
/*     */     //   2325: ldc2_w -9208511308924703329
/*     */     //   2328: lload #5
/*     */     //   2330: <illegal opcode> w : (Ljava/lang/Throwable;JJ)Ljava/lang/Throwable;
/*     */     //   2335: athrow
/*     */     //   2336: aload #4
/*     */     //   2338: arraylength
/*     */     //   2339: iload #38
/*     */     //   2341: ifeq -> 2377
/*     */     //   2344: iconst_1
/*     */     //   2345: if_icmple -> 2547
/*     */     //   2348: goto -> 2362
/*     */     //   2351: ldc2_w -9208511308924703329
/*     */     //   2354: lload #5
/*     */     //   2356: <illegal opcode> w : (Ljava/lang/Throwable;JJ)Ljava/lang/Throwable;
/*     */     //   2361: athrow
/*     */     //   2362: iconst_1
/*     */     //   2363: goto -> 2377
/*     */     //   2366: ldc2_w -9208511308924703329
/*     */     //   2369: lload #5
/*     */     //   2371: <illegal opcode> w : (Ljava/lang/Throwable;JJ)Ljava/lang/Throwable;
/*     */     //   2376: athrow
/*     */     //   2377: istore #41
/*     */     //   2379: iload #41
/*     */     //   2381: aload #4
/*     */     //   2383: arraylength
/*     */     //   2384: if_icmpge -> 2542
/*     */     //   2387: aload_0
/*     */     //   2388: getfield b : Lme/konsolas/aac/AAC;
/*     */     //   2391: invokevirtual getServer : ()Lorg/bukkit/Server;
/*     */     //   2394: aload #4
/*     */     //   2396: iload #41
/*     */     //   2398: aaload
/*     */     //   2399: invokeinterface getOfflinePlayer : (Ljava/lang/String;)Lorg/bukkit/OfflinePlayer;
/*     */     //   2404: astore #42
/*     */     //   2406: iload #38
/*     */     //   2408: ifeq -> 2694
/*     */     //   2411: aload_0
/*     */     //   2412: getfield b : Lme/konsolas/aac/AAC;
/*     */     //   2415: invokevirtual a : ()Lme/konsolas/aac/fv;
/*     */     //   2418: aload #42
/*     */     //   2420: iload #17
/*     */     //   2422: i2s
/*     */     //   2423: lload #18
/*     */     //   2425: invokevirtual a : (Lorg/bukkit/OfflinePlayer;SJ)Lme/konsolas/aac/jX;
/*     */     //   2428: iload #38
/*     */     //   2430: ifeq -> 2514
/*     */     //   2433: goto -> 2447
/*     */     //   2436: ldc2_w -9208511308924703329
/*     */     //   2439: lload #5
/*     */     //   2441: <illegal opcode> w : (Ljava/lang/Throwable;JJ)Ljava/lang/Throwable;
/*     */     //   2446: athrow
/*     */     //   2447: ifnonnull -> 2483
/*     */     //   2450: goto -> 2464
/*     */     //   2453: ldc2_w -9208511308924703329
/*     */     //   2456: lload #5
/*     */     //   2458: <illegal opcode> w : (Ljava/lang/Throwable;JJ)Ljava/lang/Throwable;
/*     */     //   2463: athrow
/*     */     //   2464: aload_0
/*     */     //   2465: getfield b : Lme/konsolas/aac/AAC;
/*     */     //   2468: invokevirtual a : ()Lme/konsolas/aac/fv;
/*     */     //   2471: aload #42
/*     */     //   2473: invokevirtual a : (Lorg/bukkit/OfflinePlayer;)Ljava/util/concurrent/CompletableFuture;
/*     */     //   2476: astore #43
/*     */     //   2478: iload #38
/*     */     //   2480: ifne -> 2519
/*     */     //   2483: aload_0
/*     */     //   2484: getfield b : Lme/konsolas/aac/AAC;
/*     */     //   2487: invokevirtual a : ()Lme/konsolas/aac/fv;
/*     */     //   2490: aload #42
/*     */     //   2492: iload #17
/*     */     //   2494: i2s
/*     */     //   2495: lload #18
/*     */     //   2497: invokevirtual a : (Lorg/bukkit/OfflinePlayer;SJ)Lme/konsolas/aac/jX;
/*     */     //   2500: goto -> 2514
/*     */     //   2503: ldc2_w -9208511308924703329
/*     */     //   2506: lload #5
/*     */     //   2508: <illegal opcode> w : (Ljava/lang/Throwable;JJ)Ljava/lang/Throwable;
/*     */     //   2513: athrow
/*     */     //   2514: invokestatic completedFuture : (Ljava/lang/Object;)Ljava/util/concurrent/CompletableFuture;
/*     */     //   2517: astore #43
/*     */     //   2519: aload #43
/*     */     //   2521: aload_0
/*     */     //   2522: aload_1
/*     */     //   2523: aload #42
/*     */     //   2525: <illegal opcode> accept : (Lme/konsolas/aac/mi;Lorg/bukkit/command/CommandSender;Lorg/bukkit/OfflinePlayer;)Ljava/util/function/BiConsumer;
/*     */     //   2530: invokevirtual whenComplete : (Ljava/util/function/BiConsumer;)Ljava/util/concurrent/CompletableFuture;
/*     */     //   2533: pop
/*     */     //   2534: iinc #41, 1
/*     */     //   2537: iload #38
/*     */     //   2539: ifne -> 2379
/*     */     //   2542: iload #38
/*     */     //   2544: ifne -> 2694
/*     */     //   2547: aload_0
/*     */     //   2548: lload #15
/*     */     //   2550: invokespecial a : (J)Lnet/md_5/bungee/api/chat/BaseComponent;
/*     */     //   2553: astore #41
/*     */     //   2555: new java/util/ArrayList
/*     */     //   2558: dup
/*     */     //   2559: invokestatic getOnlinePlayers : ()Ljava/util/Collection;
/*     */     //   2562: invokespecial <init> : (Ljava/util/Collection;)V
/*     */     //   2565: astore #42
/*     */     //   2567: aload #42
/*     */     //   2569: aload_0
/*     */     //   2570: <illegal opcode> applyAsDouble : (Lme/konsolas/aac/mi;)Ljava/util/function/ToDoubleFunction;
/*     */     //   2575: invokestatic comparingDouble : (Ljava/util/function/ToDoubleFunction;)Ljava/util/Comparator;
/*     */     //   2578: invokeinterface reversed : ()Ljava/util/Comparator;
/*     */     //   2583: invokeinterface sort : (Ljava/util/Comparator;)V
/*     */     //   2588: aload #42
/*     */     //   2590: invokeinterface iterator : ()Ljava/util/Iterator;
/*     */     //   2595: astore #43
/*     */     //   2597: aload #43
/*     */     //   2599: invokeinterface hasNext : ()Z
/*     */     //   2604: ifeq -> 2686
/*     */     //   2607: aload #43
/*     */     //   2609: invokeinterface next : ()Ljava/lang/Object;
/*     */     //   2614: checkcast org/bukkit/entity/Player
/*     */     //   2617: astore #44
/*     */     //   2619: aload #41
/*     */     //   2621: aload_0
/*     */     //   2622: aload #44
/*     */     //   2624: lload #22
/*     */     //   2626: invokespecial a : (Lorg/bukkit/OfflinePlayer;J)Lnet/md_5/bungee/api/chat/BaseComponent;
/*     */     //   2629: invokevirtual addExtra : (Lnet/md_5/bungee/api/chat/BaseComponent;)V
/*     */     //   2632: aload #41
/*     */     //   2634: ldc_w '漯⟌'
/*     */     //   2637: invokevirtual toCharArray : ()[C
/*     */     //   2640: dup
/*     */     //   2641: dup
/*     */     //   2642: iconst_0
/*     */     //   2643: dup_x1
/*     */     //   2644: caload
/*     */     //   2645: sipush #32291
/*     */     //   2648: ixor
/*     */     //   2649: i2c
/*     */     //   2650: castore
/*     */     //   2651: sipush #8394
/*     */     //   2654: iconst_0
/*     */     //   2655: iconst_0
/*     */     //   2656: invokestatic G : (Ljava/lang/Object;SZB)Ljava/lang/String;
/*     */     //   2659: invokevirtual addExtra : (Ljava/lang/String;)V
/*     */     //   2662: iload #38
/*     */     //   2664: ifeq -> 2694
/*     */     //   2667: iload #38
/*     */     //   2669: ifne -> 2597
/*     */     //   2672: goto -> 2686
/*     */     //   2675: ldc2_w -9208511308924703329
/*     */     //   2678: lload #5
/*     */     //   2680: <illegal opcode> w : (Ljava/lang/Throwable;JJ)Ljava/lang/Throwable;
/*     */     //   2685: athrow
/*     */     //   2686: aload_1
/*     */     //   2687: aload #41
/*     */     //   2689: lload #7
/*     */     //   2691: invokestatic a : (Lorg/bukkit/command/CommandSender;Lnet/md_5/bungee/api/chat/BaseComponent;J)V
/*     */     //   2694: iconst_1
/*     */     //   2695: ireturn
/*     */     //   2696: aload_1
/*     */     //   2697: sipush #15193
/*     */     //   2700: ldc2_w 2857540778365640422
/*     */     //   2703: lload #5
/*     */     //   2705: lxor
/*     */     //   2706: <illegal opcode> e : (IJ)Ljava/lang/String;
/*     */     //   2711: invokeinterface hasPermission : (Ljava/lang/String;)Z
/*     */     //   2716: iload #38
/*     */     //   2718: ifeq -> 2774
/*     */     //   2721: ifne -> 2771
/*     */     //   2724: goto -> 2738
/*     */     //   2727: ldc2_w -9208511308924703329
/*     */     //   2730: lload #5
/*     */     //   2732: <illegal opcode> w : (Ljava/lang/Throwable;JJ)Ljava/lang/Throwable;
/*     */     //   2737: athrow
/*     */     //   2738: aload_1
/*     */     //   2739: sipush #14591
/*     */     //   2742: ldc2_w 4749963927379893536
/*     */     //   2745: lload #5
/*     */     //   2747: lxor
/*     */     //   2748: <illegal opcode> e : (IJ)Ljava/lang/String;
/*     */     //   2753: invokeinterface sendMessage : (Ljava/lang/String;)V
/*     */     //   2758: iconst_0
/*     */     //   2759: ireturn
/*     */     //   2760: ldc2_w -9208511308924703329
/*     */     //   2763: lload #5
/*     */     //   2765: <illegal opcode> w : (Ljava/lang/Throwable;JJ)Ljava/lang/Throwable;
/*     */     //   2770: athrow
/*     */     //   2771: aload #4
/*     */     //   2773: arraylength
/*     */     //   2774: iload #38
/*     */     //   2776: ifeq -> 2831
/*     */     //   2779: iconst_1
/*     */     //   2780: if_icmpgt -> 2830
/*     */     //   2783: goto -> 2797
/*     */     //   2786: ldc2_w -9208511308924703329
/*     */     //   2789: lload #5
/*     */     //   2791: <illegal opcode> w : (Ljava/lang/Throwable;JJ)Ljava/lang/Throwable;
/*     */     //   2796: athrow
/*     */     //   2797: aload_1
/*     */     //   2798: sipush #25944
/*     */     //   2801: ldc2_w 2283710962862161994
/*     */     //   2804: lload #5
/*     */     //   2806: lxor
/*     */     //   2807: <illegal opcode> e : (IJ)Ljava/lang/String;
/*     */     //   2812: invokeinterface sendMessage : (Ljava/lang/String;)V
/*     */     //   2817: iconst_0
/*     */     //   2818: ireturn
/*     */     //   2819: ldc2_w -9208511308924703329
/*     */     //   2822: lload #5
/*     */     //   2824: <illegal opcode> w : (Ljava/lang/Throwable;JJ)Ljava/lang/Throwable;
/*     */     //   2829: athrow
/*     */     //   2830: iconst_1
/*     */     //   2831: istore #41
/*     */     //   2833: iload #41
/*     */     //   2835: aload #4
/*     */     //   2837: arraylength
/*     */     //   2838: if_icmpge -> 3077
/*     */     //   2841: aload_0
/*     */     //   2842: getfield b : Lme/konsolas/aac/AAC;
/*     */     //   2845: invokevirtual getServer : ()Lorg/bukkit/Server;
/*     */     //   2848: aload #4
/*     */     //   2850: iload #41
/*     */     //   2852: aaload
/*     */     //   2853: invokeinterface getPlayer : (Ljava/lang/String;)Lorg/bukkit/entity/Player;
/*     */     //   2858: astore #42
/*     */     //   2860: aload #42
/*     */     //   2862: iload #38
/*     */     //   2864: ifeq -> 2885
/*     */     //   2867: ifnonnull -> 2930
/*     */     //   2870: goto -> 2884
/*     */     //   2873: ldc2_w -9208511308924703329
/*     */     //   2876: lload #5
/*     */     //   2878: <illegal opcode> w : (Ljava/lang/Throwable;JJ)Ljava/lang/Throwable;
/*     */     //   2883: athrow
/*     */     //   2884: aload_1
/*     */     //   2885: new java/lang/StringBuilder
/*     */     //   2888: dup
/*     */     //   2889: invokespecial <init> : ()V
/*     */     //   2892: sipush #28771
/*     */     //   2895: ldc2_w 4979785374413559250
/*     */     //   2898: lload #5
/*     */     //   2900: lxor
/*     */     //   2901: <illegal opcode> e : (IJ)Ljava/lang/String;
/*     */     //   2906: invokevirtual append : (Ljava/lang/String;)Ljava/lang/StringBuilder;
/*     */     //   2909: aload #4
/*     */     //   2911: iload #41
/*     */     //   2913: aaload
/*     */     //   2914: invokevirtual append : (Ljava/lang/String;)Ljava/lang/StringBuilder;
/*     */     //   2917: invokevirtual toString : ()Ljava/lang/String;
/*     */     //   2920: invokeinterface sendMessage : (Ljava/lang/String;)V
/*     */     //   2925: iload #38
/*     */     //   2927: ifne -> 3069
/*     */     //   2930: aload_0
/*     */     //   2931: lload #15
/*     */     //   2933: invokespecial a : (J)Lnet/md_5/bungee/api/chat/BaseComponent;
/*     */     //   2936: astore #43
/*     */     //   2938: iload #38
/*     */     //   2940: ifeq -> 3010
/*     */     //   2943: aload_0
/*     */     //   2944: getfield b : Lme/konsolas/aac/AAC;
/*     */     //   2947: aload #42
/*     */     //   2949: iload #30
/*     */     //   2951: iload #31
/*     */     //   2953: i2s
/*     */     //   2954: iload #32
/*     */     //   2956: i2s
/*     */     //   2957: invokevirtual a : (Lorg/bukkit/entity/Player;ISS)Z
/*     */     //   2960: ifeq -> 3015
/*     */     //   2963: goto -> 2977
/*     */     //   2966: ldc2_w -9208511308924703329
/*     */     //   2969: lload #5
/*     */     //   2971: <illegal opcode> w : (Ljava/lang/Throwable;JJ)Ljava/lang/Throwable;
/*     */     //   2976: athrow
/*     */     //   2977: aload #43
/*     */     //   2979: sipush #20214
/*     */     //   2982: ldc2_w 5085200430200531726
/*     */     //   2985: lload #5
/*     */     //   2987: lxor
/*     */     //   2988: <illegal opcode> e : (IJ)Ljava/lang/String;
/*     */     //   2993: invokevirtual addExtra : (Ljava/lang/String;)V
/*     */     //   2996: goto -> 3010
/*     */     //   2999: ldc2_w -9208511308924703329
/*     */     //   3002: lload #5
/*     */     //   3004: <illegal opcode> w : (Ljava/lang/Throwable;JJ)Ljava/lang/Throwable;
/*     */     //   3009: athrow
/*     */     //   3010: iload #38
/*     */     //   3012: ifne -> 3048
/*     */     //   3015: aload #43
/*     */     //   3017: sipush #20178
/*     */     //   3020: ldc2_w 7715863965630901019
/*     */     //   3023: lload #5
/*     */     //   3025: lxor
/*     */     //   3026: <illegal opcode> e : (IJ)Ljava/lang/String;
/*     */     //   3031: invokevirtual addExtra : (Ljava/lang/String;)V
/*     */     //   3034: goto -> 3048
/*     */     //   3037: ldc2_w -9208511308924703329
/*     */     //   3040: lload #5
/*     */     //   3042: <illegal opcode> w : (Ljava/lang/Throwable;JJ)Ljava/lang/Throwable;
/*     */     //   3047: athrow
/*     */     //   3048: aload #43
/*     */     //   3050: aload_0
/*     */     //   3051: aload #42
/*     */     //   3053: lload #22
/*     */     //   3055: invokespecial a : (Lorg/bukkit/OfflinePlayer;J)Lnet/md_5/bungee/api/chat/BaseComponent;
/*     */     //   3058: invokevirtual addExtra : (Lnet/md_5/bungee/api/chat/BaseComponent;)V
/*     */     //   3061: aload_1
/*     */     //   3062: aload #43
/*     */     //   3064: lload #7
/*     */     //   3066: invokestatic a : (Lorg/bukkit/command/CommandSender;Lnet/md_5/bungee/api/chat/BaseComponent;J)V
/*     */     //   3069: iinc #41, 1
/*     */     //   3072: iload #38
/*     */     //   3074: ifne -> 2833
/*     */     //   3077: iconst_1
/*     */     //   3078: ireturn
/*     */     //   3079: aload_1
/*     */     //   3080: sipush #1517
/*     */     //   3083: ldc2_w 1255729896049270836
/*     */     //   3086: lload #5
/*     */     //   3088: lxor
/*     */     //   3089: <illegal opcode> e : (IJ)Ljava/lang/String;
/*     */     //   3094: invokeinterface hasPermission : (Ljava/lang/String;)Z
/*     */     //   3099: iload #38
/*     */     //   3101: ifeq -> 3158
/*     */     //   3104: ifne -> 3154
/*     */     //   3107: goto -> 3121
/*     */     //   3110: ldc2_w -9208511308924703329
/*     */     //   3113: lload #5
/*     */     //   3115: <illegal opcode> w : (Ljava/lang/Throwable;JJ)Ljava/lang/Throwable;
/*     */     //   3120: athrow
/*     */     //   3121: aload_1
/*     */     //   3122: sipush #29147
/*     */     //   3125: ldc2_w 4149633546518664263
/*     */     //   3128: lload #5
/*     */     //   3130: lxor
/*     */     //   3131: <illegal opcode> e : (IJ)Ljava/lang/String;
/*     */     //   3136: invokeinterface sendMessage : (Ljava/lang/String;)V
/*     */     //   3141: iconst_0
/*     */     //   3142: ireturn
/*     */     //   3143: ldc2_w -9208511308924703329
/*     */     //   3146: lload #5
/*     */     //   3148: <illegal opcode> w : (Ljava/lang/Throwable;JJ)Ljava/lang/Throwable;
/*     */     //   3153: athrow
/*     */     //   3154: aload_1
/*     */     //   3155: instanceof org/bukkit/entity/Player
/*     */     //   3158: iload #38
/*     */     //   3160: ifeq -> 3216
/*     */     //   3163: ifne -> 3213
/*     */     //   3166: goto -> 3180
/*     */     //   3169: ldc2_w -9208511308924703329
/*     */     //   3172: lload #5
/*     */     //   3174: <illegal opcode> w : (Ljava/lang/Throwable;JJ)Ljava/lang/Throwable;
/*     */     //   3179: athrow
/*     */     //   3180: aload_1
/*     */     //   3181: sipush #26993
/*     */     //   3184: ldc2_w 4973918951716818108
/*     */     //   3187: lload #5
/*     */     //   3189: lxor
/*     */     //   3190: <illegal opcode> e : (IJ)Ljava/lang/String;
/*     */     //   3195: invokeinterface sendMessage : (Ljava/lang/String;)V
/*     */     //   3200: iconst_0
/*     */     //   3201: ireturn
/*     */     //   3202: ldc2_w -9208511308924703329
/*     */     //   3205: lload #5
/*     */     //   3207: <illegal opcode> w : (Ljava/lang/Throwable;JJ)Ljava/lang/Throwable;
/*     */     //   3212: athrow
/*     */     //   3213: aload #4
/*     */     //   3215: arraylength
/*     */     //   3216: iload #38
/*     */     //   3218: ifeq -> 3274
/*     */     //   3221: iconst_2
/*     */     //   3222: if_icmple -> 3275
/*     */     //   3225: goto -> 3239
/*     */     //   3228: ldc2_w -9208511308924703329
/*     */     //   3231: lload #5
/*     */     //   3233: <illegal opcode> w : (Ljava/lang/Throwable;JJ)Ljava/lang/Throwable;
/*     */     //   3238: athrow
/*     */     //   3239: aload_1
/*     */     //   3240: sipush #4596
/*     */     //   3243: ldc2_w 7547366343639069718
/*     */     //   3246: lload #5
/*     */     //   3248: lxor
/*     */     //   3249: <illegal opcode> e : (IJ)Ljava/lang/String;
/*     */     //   3254: invokeinterface sendMessage : (Ljava/lang/String;)V
/*     */     //   3259: iconst_0
/*     */     //   3260: goto -> 3274
/*     */     //   3263: ldc2_w -9208511308924703329
/*     */     //   3266: lload #5
/*     */     //   3268: <illegal opcode> w : (Ljava/lang/Throwable;JJ)Ljava/lang/Throwable;
/*     */     //   3273: athrow
/*     */     //   3274: ireturn
/*     */     //   3275: aload_1
/*     */     //   3276: checkcast org/bukkit/entity/Player
/*     */     //   3279: astore #41
/*     */     //   3281: aload #4
/*     */     //   3283: iload #38
/*     */     //   3285: ifeq -> 3622
/*     */     //   3288: arraylength
/*     */     //   3289: iconst_2
/*     */     //   3290: if_icmplt -> 3611
/*     */     //   3293: goto -> 3307
/*     */     //   3296: ldc2_w -9208511308924703329
/*     */     //   3299: lload #5
/*     */     //   3301: <illegal opcode> w : (Ljava/lang/Throwable;JJ)Ljava/lang/Throwable;
/*     */     //   3306: athrow
/*     */     //   3307: aload_0
/*     */     //   3308: getfield b : Lme/konsolas/aac/AAC;
/*     */     //   3311: invokevirtual getServer : ()Lorg/bukkit/Server;
/*     */     //   3314: aload #4
/*     */     //   3316: iconst_1
/*     */     //   3317: aaload
/*     */     //   3318: invokeinterface getPlayer : (Ljava/lang/String;)Lorg/bukkit/entity/Player;
/*     */     //   3323: astore #42
/*     */     //   3325: aload #42
/*     */     //   3327: iload #38
/*     */     //   3329: ifeq -> 3350
/*     */     //   3332: ifnonnull -> 3391
/*     */     //   3335: goto -> 3349
/*     */     //   3338: ldc2_w -9208511308924703329
/*     */     //   3341: lload #5
/*     */     //   3343: <illegal opcode> w : (Ljava/lang/Throwable;JJ)Ljava/lang/Throwable;
/*     */     //   3348: athrow
/*     */     //   3349: aload_1
/*     */     //   3350: new java/lang/StringBuilder
/*     */     //   3353: dup
/*     */     //   3354: invokespecial <init> : ()V
/*     */     //   3357: sipush #10354
/*     */     //   3360: ldc2_w 6441628477318450633
/*     */     //   3363: lload #5
/*     */     //   3365: lxor
/*     */     //   3366: <illegal opcode> e : (IJ)Ljava/lang/String;
/*     */     //   3371: invokevirtual append : (Ljava/lang/String;)Ljava/lang/StringBuilder;
/*     */     //   3374: aload #4
/*     */     //   3376: iconst_1
/*     */     //   3377: aaload
/*     */     //   3378: invokevirtual append : (Ljava/lang/String;)Ljava/lang/StringBuilder;
/*     */     //   3381: invokevirtual toString : ()Ljava/lang/String;
/*     */     //   3384: invokeinterface sendMessage : (Ljava/lang/String;)V
/*     */     //   3389: iconst_0
/*     */     //   3390: ireturn
/*     */     //   3391: aload_0
/*     */     //   3392: getfield b : Lme/konsolas/aac/AAC;
/*     */     //   3395: invokevirtual getConfig : ()Lorg/bukkit/configuration/file/FileConfiguration;
/*     */     //   3398: sipush #10697
/*     */     //   3401: ldc2_w 7071246571814046744
/*     */     //   3404: lload #5
/*     */     //   3406: lxor
/*     */     //   3407: <illegal opcode> e : (IJ)Ljava/lang/String;
/*     */     //   3412: invokevirtual getStringList : (Ljava/lang/String;)Ljava/util/List;
/*     */     //   3415: invokeinterface iterator : ()Ljava/util/Iterator;
/*     */     //   3420: astore #43
/*     */     //   3422: aload #43
/*     */     //   3424: invokeinterface hasNext : ()Z
/*     */     //   3429: ifeq -> 3497
/*     */     //   3432: aload #43
/*     */     //   3434: invokeinterface next : ()Ljava/lang/Object;
/*     */     //   3439: checkcast java/lang/String
/*     */     //   3442: astore #44
/*     */     //   3444: aload_0
/*     */     //   3445: getfield b : Lme/konsolas/aac/AAC;
/*     */     //   3448: invokevirtual getServer : ()Lorg/bukkit/Server;
/*     */     //   3451: invokestatic getConsoleSender : ()Lorg/bukkit/command/ConsoleCommandSender;
/*     */     //   3454: aload_0
/*     */     //   3455: getfield b : Lme/konsolas/aac/AAC;
/*     */     //   3458: aload #41
/*     */     //   3460: aload #44
/*     */     //   3462: lload #9
/*     */     //   3464: invokevirtual a : (Lorg/bukkit/entity/Player;Ljava/lang/String;J)Ljava/lang/String;
/*     */     //   3467: invokeinterface dispatchCommand : (Lorg/bukkit/command/CommandSender;Ljava/lang/String;)Z
/*     */     //   3472: pop
/*     */     //   3473: iload #38
/*     */     //   3475: ifeq -> 3529
/*     */     //   3478: iload #38
/*     */     //   3480: ifne -> 3422
/*     */     //   3483: goto -> 3497
/*     */     //   3486: ldc2_w -9208511308924703329
/*     */     //   3489: lload #5
/*     */     //   3491: <illegal opcode> w : (Ljava/lang/Throwable;JJ)Ljava/lang/Throwable;
/*     */     //   3496: athrow
/*     */     //   3497: aload_0
/*     */     //   3498: getfield e : Ljava/util/Map;
/*     */     //   3501: aload #41
/*     */     //   3503: aload #41
/*     */     //   3505: invokeinterface getLocation : ()Lorg/bukkit/Location;
/*     */     //   3510: invokeinterface putIfAbsent : (Ljava/lang/Object;Ljava/lang/Object;)Ljava/lang/Object;
/*     */     //   3515: pop
/*     */     //   3516: aload #41
/*     */     //   3518: aload #42
/*     */     //   3520: getstatic org/bukkit/event/player/PlayerTeleportEvent$TeleportCause.COMMAND : Lorg/bukkit/event/player/PlayerTeleportEvent$TeleportCause;
/*     */     //   3523: invokeinterface teleport : (Lorg/bukkit/entity/Entity;Lorg/bukkit/event/player/PlayerTeleportEvent$TeleportCause;)Z
/*     */     //   3528: pop
/*     */     //   3529: aload_0
/*     */     //   3530: lload #15
/*     */     //   3532: invokespecial a : (J)Lnet/md_5/bungee/api/chat/BaseComponent;
/*     */     //   3535: astore #43
/*     */     //   3537: aload #43
/*     */     //   3539: sipush #4574
/*     */     //   3542: ldc2_w 5952838999699584219
/*     */     //   3545: lload #5
/*     */     //   3547: lxor
/*     */     //   3548: <illegal opcode> e : (IJ)Ljava/lang/String;
/*     */     //   3553: invokevirtual addExtra : (Ljava/lang/String;)V
/*     */     //   3556: aload #43
/*     */     //   3558: aload_0
/*     */     //   3559: aload #42
/*     */     //   3561: lload #22
/*     */     //   3563: invokespecial a : (Lorg/bukkit/OfflinePlayer;J)Lnet/md_5/bungee/api/chat/BaseComponent;
/*     */     //   3566: invokevirtual addExtra : (Lnet/md_5/bungee/api/chat/BaseComponent;)V
/*     */     //   3569: aload #43
/*     */     //   3571: sipush #22444
/*     */     //   3574: ldc2_w 4687361367878939166
/*     */     //   3577: lload #5
/*     */     //   3579: lxor
/*     */     //   3580: <illegal opcode> e : (IJ)Ljava/lang/String;
/*     */     //   3585: invokevirtual addExtra : (Ljava/lang/String;)V
/*     */     //   3588: aload #43
/*     */     //   3590: aload_0
/*     */     //   3591: aload #41
/*     */     //   3593: lload #36
/*     */     //   3595: invokespecial a : (Lorg/bukkit/command/CommandSender;J)Lnet/md_5/bungee/api/chat/BaseComponent;
/*     */     //   3598: invokevirtual addExtra : (Lnet/md_5/bungee/api/chat/BaseComponent;)V
/*     */     //   3601: aload_1
/*     */     //   3602: aload #43
/*     */     //   3604: lload #7
/*     */     //   3606: invokestatic a : (Lorg/bukkit/command/CommandSender;Lnet/md_5/bungee/api/chat/BaseComponent;J)V
/*     */     //   3609: iconst_1
/*     */     //   3610: ireturn
/*     */     //   3611: aload_0
/*     */     //   3612: getfield e : Ljava/util/Map;
/*     */     //   3615: aload #41
/*     */     //   3617: invokeinterface get : (Ljava/lang/Object;)Ljava/lang/Object;
/*     */     //   3622: checkcast org/bukkit/Location
/*     */     //   3625: astore #42
/*     */     //   3627: iload #38
/*     */     //   3629: ifeq -> 3839
/*     */     //   3632: aload #42
/*     */     //   3634: ifnull -> 3819
/*     */     //   3637: goto -> 3651
/*     */     //   3640: ldc2_w -9208511308924703329
/*     */     //   3643: lload #5
/*     */     //   3645: <illegal opcode> w : (Ljava/lang/Throwable;JJ)Ljava/lang/Throwable;
/*     */     //   3650: athrow
/*     */     //   3651: aload_0
/*     */     //   3652: getfield b : Lme/konsolas/aac/AAC;
/*     */     //   3655: invokevirtual getConfig : ()Lorg/bukkit/configuration/file/FileConfiguration;
/*     */     //   3658: sipush #16339
/*     */     //   3661: ldc2_w 5314290533670181466
/*     */     //   3664: lload #5
/*     */     //   3666: lxor
/*     */     //   3667: <illegal opcode> e : (IJ)Ljava/lang/String;
/*     */     //   3672: invokevirtual getStringList : (Ljava/lang/String;)Ljava/util/List;
/*     */     //   3675: invokeinterface iterator : ()Ljava/util/Iterator;
/*     */     //   3680: astore #43
/*     */     //   3682: aload #43
/*     */     //   3684: invokeinterface hasNext : ()Z
/*     */     //   3689: ifeq -> 3757
/*     */     //   3692: aload #43
/*     */     //   3694: invokeinterface next : ()Ljava/lang/Object;
/*     */     //   3699: checkcast java/lang/String
/*     */     //   3702: astore #44
/*     */     //   3704: aload_0
/*     */     //   3705: getfield b : Lme/konsolas/aac/AAC;
/*     */     //   3708: invokevirtual getServer : ()Lorg/bukkit/Server;
/*     */     //   3711: invokestatic getConsoleSender : ()Lorg/bukkit/command/ConsoleCommandSender;
/*     */     //   3714: aload_0
/*     */     //   3715: getfield b : Lme/konsolas/aac/AAC;
/*     */     //   3718: aload #41
/*     */     //   3720: aload #44
/*     */     //   3722: lload #9
/*     */     //   3724: invokevirtual a : (Lorg/bukkit/entity/Player;Ljava/lang/String;J)Ljava/lang/String;
/*     */     //   3727: invokeinterface dispatchCommand : (Lorg/bukkit/command/CommandSender;Ljava/lang/String;)Z
/*     */     //   3732: pop
/*     */     //   3733: iload #38
/*     */     //   3735: ifeq -> 3782
/*     */     //   3738: iload #38
/*     */     //   3740: ifne -> 3682
/*     */     //   3743: goto -> 3757
/*     */     //   3746: ldc2_w -9208511308924703329
/*     */     //   3749: lload #5
/*     */     //   3751: <illegal opcode> w : (Ljava/lang/Throwable;JJ)Ljava/lang/Throwable;
/*     */     //   3756: athrow
/*     */     //   3757: aload #41
/*     */     //   3759: aload #42
/*     */     //   3761: getstatic org/bukkit/event/player/PlayerTeleportEvent$TeleportCause.COMMAND : Lorg/bukkit/event/player/PlayerTeleportEvent$TeleportCause;
/*     */     //   3764: invokeinterface teleport : (Lorg/bukkit/Location;Lorg/bukkit/event/player/PlayerTeleportEvent$TeleportCause;)Z
/*     */     //   3769: pop
/*     */     //   3770: aload_0
/*     */     //   3771: getfield e : Ljava/util/Map;
/*     */     //   3774: aload #41
/*     */     //   3776: invokeinterface remove : (Ljava/lang/Object;)Ljava/lang/Object;
/*     */     //   3781: pop
/*     */     //   3782: aload_0
/*     */     //   3783: lload #15
/*     */     //   3785: invokespecial a : (J)Lnet/md_5/bungee/api/chat/BaseComponent;
/*     */     //   3788: astore #43
/*     */     //   3790: aload #43
/*     */     //   3792: sipush #26312
/*     */     //   3795: ldc2_w 8937623045539660632
/*     */     //   3798: lload #5
/*     */     //   3800: lxor
/*     */     //   3801: <illegal opcode> e : (IJ)Ljava/lang/String;
/*     */     //   3806: invokevirtual addExtra : (Ljava/lang/String;)V
/*     */     //   3809: aload_1
/*     */     //   3810: aload #43
/*     */     //   3812: lload #7
/*     */     //   3814: invokestatic a : (Lorg/bukkit/command/CommandSender;Lnet/md_5/bungee/api/chat/BaseComponent;J)V
/*     */     //   3817: iconst_1
/*     */     //   3818: ireturn
/*     */     //   3819: aload_1
/*     */     //   3820: sipush #4979
/*     */     //   3823: ldc2_w 3871689570242950835
/*     */     //   3826: lload #5
/*     */     //   3828: lxor
/*     */     //   3829: <illegal opcode> e : (IJ)Ljava/lang/String;
/*     */     //   3834: invokeinterface sendMessage : (Ljava/lang/String;)V
/*     */     //   3839: iconst_0
/*     */     //   3840: ireturn
/*     */     //   3841: aload_1
/*     */     //   3842: sipush #1512
/*     */     //   3845: ldc2_w 3851131044165902435
/*     */     //   3848: lload #5
/*     */     //   3850: lxor
/*     */     //   3851: <illegal opcode> e : (IJ)Ljava/lang/String;
/*     */     //   3856: invokeinterface hasPermission : (Ljava/lang/String;)Z
/*     */     //   3861: iload #38
/*     */     //   3863: ifeq -> 3919
/*     */     //   3866: ifne -> 3916
/*     */     //   3869: goto -> 3883
/*     */     //   3872: ldc2_w -9208511308924703329
/*     */     //   3875: lload #5
/*     */     //   3877: <illegal opcode> w : (Ljava/lang/Throwable;JJ)Ljava/lang/Throwable;
/*     */     //   3882: athrow
/*     */     //   3883: aload_1
/*     */     //   3884: sipush #18314
/*     */     //   3887: ldc2_w 5995601771857715818
/*     */     //   3890: lload #5
/*     */     //   3892: lxor
/*     */     //   3893: <illegal opcode> e : (IJ)Ljava/lang/String;
/*     */     //   3898: invokeinterface sendMessage : (Ljava/lang/String;)V
/*     */     //   3903: iconst_0
/*     */     //   3904: ireturn
/*     */     //   3905: ldc2_w -9208511308924703329
/*     */     //   3908: lload #5
/*     */     //   3910: <illegal opcode> w : (Ljava/lang/Throwable;JJ)Ljava/lang/Throwable;
/*     */     //   3915: athrow
/*     */     //   3916: aload #4
/*     */     //   3918: arraylength
/*     */     //   3919: iconst_1
/*     */     //   3920: iload #38
/*     */     //   3922: ifeq -> 3998
/*     */     //   3925: if_icmpgt -> 3975
/*     */     //   3928: goto -> 3942
/*     */     //   3931: ldc2_w -9208511308924703329
/*     */     //   3934: lload #5
/*     */     //   3936: <illegal opcode> w : (Ljava/lang/Throwable;JJ)Ljava/lang/Throwable;
/*     */     //   3941: athrow
/*     */     //   3942: aload_1
/*     */     //   3943: sipush #31500
/*     */     //   3946: ldc2_w 5494635104212786830
/*     */     //   3949: lload #5
/*     */     //   3951: lxor
/*     */     //   3952: <illegal opcode> e : (IJ)Ljava/lang/String;
/*     */     //   3957: invokeinterface sendMessage : (Ljava/lang/String;)V
/*     */     //   3962: iconst_0
/*     */     //   3963: ireturn
/*     */     //   3964: ldc2_w -9208511308924703329
/*     */     //   3967: lload #5
/*     */     //   3969: <illegal opcode> w : (Ljava/lang/Throwable;JJ)Ljava/lang/Throwable;
/*     */     //   3974: athrow
/*     */     //   3975: aload #4
/*     */     //   3977: arraylength
/*     */     //   3978: iload #38
/*     */     //   3980: ifeq -> 4036
/*     */     //   3983: iconst_2
/*     */     //   3984: goto -> 3998
/*     */     //   3987: ldc2_w -9208511308924703329
/*     */     //   3990: lload #5
/*     */     //   3992: <illegal opcode> w : (Ljava/lang/Throwable;JJ)Ljava/lang/Throwable;
/*     */     //   3997: athrow
/*     */     //   3998: if_icmpgt -> 4037
/*     */     //   4001: aload_1
/*     */     //   4002: sipush #14245
/*     */     //   4005: ldc2_w 4554601258171454038
/*     */     //   4008: lload #5
/*     */     //   4010: lxor
/*     */     //   4011: <illegal opcode> e : (IJ)Ljava/lang/String;
/*     */     //   4016: invokeinterface sendMessage : (Ljava/lang/String;)V
/*     */     //   4021: iconst_0
/*     */     //   4022: goto -> 4036
/*     */     //   4025: ldc2_w -9208511308924703329
/*     */     //   4028: lload #5
/*     */     //   4030: <illegal opcode> w : (Ljava/lang/Throwable;JJ)Ljava/lang/Throwable;
/*     */     //   4035: athrow
/*     */     //   4036: ireturn
/*     */     //   4037: aload_0
/*     */     //   4038: getfield b : Lme/konsolas/aac/AAC;
/*     */     //   4041: invokevirtual getServer : ()Lorg/bukkit/Server;
/*     */     //   4044: aload #4
/*     */     //   4046: iconst_1
/*     */     //   4047: aaload
/*     */     //   4048: invokeinterface getPlayer : (Ljava/lang/String;)Lorg/bukkit/entity/Player;
/*     */     //   4053: astore #41
/*     */     //   4055: aload #41
/*     */     //   4057: iload #38
/*     */     //   4059: ifeq -> 4178
/*     */     //   4062: ifnonnull -> 4132
/*     */     //   4065: goto -> 4079
/*     */     //   4068: ldc2_w -9208511308924703329
/*     */     //   4071: lload #5
/*     */     //   4073: <illegal opcode> w : (Ljava/lang/Throwable;JJ)Ljava/lang/Throwable;
/*     */     //   4078: athrow
/*     */     //   4079: aload_1
/*     */     //   4080: new java/lang/StringBuilder
/*     */     //   4083: dup
/*     */     //   4084: invokespecial <init> : ()V
/*     */     //   4087: sipush #27846
/*     */     //   4090: ldc2_w 6049853676073683235
/*     */     //   4093: lload #5
/*     */     //   4095: lxor
/*     */     //   4096: <illegal opcode> e : (IJ)Ljava/lang/String;
/*     */     //   4101: invokevirtual append : (Ljava/lang/String;)Ljava/lang/StringBuilder;
/*     */     //   4104: aload #4
/*     */     //   4106: iconst_1
/*     */     //   4107: aaload
/*     */     //   4108: invokevirtual append : (Ljava/lang/String;)Ljava/lang/StringBuilder;
/*     */     //   4111: invokevirtual toString : ()Ljava/lang/String;
/*     */     //   4114: invokeinterface sendMessage : (Ljava/lang/String;)V
/*     */     //   4119: iconst_0
/*     */     //   4120: ireturn
/*     */     //   4121: ldc2_w -9208511308924703329
/*     */     //   4124: lload #5
/*     */     //   4126: <illegal opcode> w : (Ljava/lang/Throwable;JJ)Ljava/lang/Throwable;
/*     */     //   4131: athrow
/*     */     //   4132: aload #4
/*     */     //   4134: invokestatic stream : ([Ljava/lang/Object;)Ljava/util/stream/Stream;
/*     */     //   4137: ldc2_w 2
/*     */     //   4140: invokeinterface skip : (J)Ljava/util/stream/Stream;
/*     */     //   4145: ldc_w '䪲'
/*     */     //   4148: invokevirtual toCharArray : ()[C
/*     */     //   4151: dup
/*     */     //   4152: dup
/*     */     //   4153: iconst_0
/*     */     //   4154: dup_x1
/*     */     //   4155: caload
/*     */     //   4156: sipush #27824
/*     */     //   4159: ixor
/*     */     //   4160: i2c
/*     */     //   4161: castore
/*     */     //   4162: sipush #20861
/*     */     //   4165: iconst_0
/*     */     //   4166: iconst_5
/*     */     //   4167: invokestatic G : (Ljava/lang/Object;SZB)Ljava/lang/String;
/*     */     //   4170: invokestatic joining : (Ljava/lang/CharSequence;)Ljava/util/stream/Collector;
/*     */     //   4173: invokeinterface collect : (Ljava/util/stream/Collector;)Ljava/lang/Object;
/*     */     //   4178: checkcast java/lang/String
/*     */     //   4181: astore #42
/*     */     //   4183: aload_0
/*     */     //   4184: lload #15
/*     */     //   4186: invokespecial a : (J)Lnet/md_5/bungee/api/chat/BaseComponent;
/*     */     //   4189: astore #43
/*     */     //   4191: aload #43
/*     */     //   4193: new java/lang/StringBuilder
/*     */     //   4196: dup
/*     */     //   4197: invokespecial <init> : ()V
/*     */     //   4200: ldc_w 'スお'
/*     */     //   4203: invokevirtual toCharArray : ()[C
/*     */     //   4206: dup
/*     */     //   4207: dup
/*     */     //   4208: iconst_0
/*     */     //   4209: dup_x1
/*     */     //   4210: caload
/*     */     //   4211: sipush #5877
/*     */     //   4214: ixor
/*     */     //   4215: i2c
/*     */     //   4216: castore
/*     */     //   4217: sipush #28135
/*     */     //   4220: iconst_0
/*     */     //   4221: iconst_2
/*     */     //   4222: invokestatic G : (Ljava/lang/Object;SZB)Ljava/lang/String;
/*     */     //   4225: invokevirtual append : (Ljava/lang/String;)Ljava/lang/StringBuilder;
/*     */     //   4228: aload #42
/*     */     //   4230: invokevirtual append : (Ljava/lang/String;)Ljava/lang/StringBuilder;
/*     */     //   4233: invokevirtual toString : ()Ljava/lang/String;
/*     */     //   4236: invokevirtual addExtra : (Ljava/lang/String;)V
/*     */     //   4239: aload #41
/*     */     //   4241: aload #43
/*     */     //   4243: lload #7
/*     */     //   4245: invokestatic a : (Lorg/bukkit/command/CommandSender;Lnet/md_5/bungee/api/chat/BaseComponent;J)V
/*     */     //   4248: aload_0
/*     */     //   4249: lload #15
/*     */     //   4251: invokespecial a : (J)Lnet/md_5/bungee/api/chat/BaseComponent;
/*     */     //   4254: astore #44
/*     */     //   4256: aload #44
/*     */     //   4258: aload_0
/*     */     //   4259: aload #41
/*     */     //   4261: lload #22
/*     */     //   4263: invokespecial a : (Lorg/bukkit/OfflinePlayer;J)Lnet/md_5/bungee/api/chat/BaseComponent;
/*     */     //   4266: invokevirtual addExtra : (Lnet/md_5/bungee/api/chat/BaseComponent;)V
/*     */     //   4269: aload #44
/*     */     //   4271: new java/lang/StringBuilder
/*     */     //   4274: dup
/*     */     //   4275: invokespecial <init> : ()V
/*     */     //   4278: sipush #8881
/*     */     //   4281: ldc2_w 1846749774328940342
/*     */     //   4284: lload #5
/*     */     //   4286: lxor
/*     */     //   4287: <illegal opcode> e : (IJ)Ljava/lang/String;
/*     */     //   4292: invokevirtual append : (Ljava/lang/String;)Ljava/lang/StringBuilder;
/*     */     //   4295: aload #42
/*     */     //   4297: invokevirtual append : (Ljava/lang/String;)Ljava/lang/StringBuilder;
/*     */     //   4300: invokevirtual toString : ()Ljava/lang/String;
/*     */     //   4303: invokevirtual addExtra : (Ljava/lang/String;)V
/*     */     //   4306: aload_1
/*     */     //   4307: aload #44
/*     */     //   4309: lload #7
/*     */     //   4311: invokestatic a : (Lorg/bukkit/command/CommandSender;Lnet/md_5/bungee/api/chat/BaseComponent;J)V
/*     */     //   4314: aload_0
/*     */     //   4315: getfield b : Lme/konsolas/aac/AAC;
/*     */     //   4318: invokevirtual getServer : ()Lorg/bukkit/Server;
/*     */     //   4321: aload #41
/*     */     //   4323: aload #42
/*     */     //   4325: invokeinterface dispatchCommand : (Lorg/bukkit/command/CommandSender;Ljava/lang/String;)Z
/*     */     //   4330: pop
/*     */     //   4331: iconst_1
/*     */     //   4332: ireturn
/*     */     //   4333: aload_1
/*     */     //   4334: sipush #1225
/*     */     //   4337: ldc2_w 4657586277872066899
/*     */     //   4340: lload #5
/*     */     //   4342: lxor
/*     */     //   4343: <illegal opcode> e : (IJ)Ljava/lang/String;
/*     */     //   4348: invokeinterface hasPermission : (Ljava/lang/String;)Z
/*     */     //   4353: iload #38
/*     */     //   4355: ifeq -> 4411
/*     */     //   4358: ifne -> 4408
/*     */     //   4361: goto -> 4375
/*     */     //   4364: ldc2_w -9208511308924703329
/*     */     //   4367: lload #5
/*     */     //   4369: <illegal opcode> w : (Ljava/lang/Throwable;JJ)Ljava/lang/Throwable;
/*     */     //   4374: athrow
/*     */     //   4375: aload_1
/*     */     //   4376: sipush #31885
/*     */     //   4379: ldc2_w 1274703716766947637
/*     */     //   4382: lload #5
/*     */     //   4384: lxor
/*     */     //   4385: <illegal opcode> e : (IJ)Ljava/lang/String;
/*     */     //   4390: invokeinterface sendMessage : (Ljava/lang/String;)V
/*     */     //   4395: iconst_0
/*     */     //   4396: ireturn
/*     */     //   4397: ldc2_w -9208511308924703329
/*     */     //   4400: lload #5
/*     */     //   4402: <illegal opcode> w : (Ljava/lang/Throwable;JJ)Ljava/lang/Throwable;
/*     */     //   4407: athrow
/*     */     //   4408: aload #4
/*     */     //   4410: arraylength
/*     */     //   4411: iload #38
/*     */     //   4413: ifeq -> 4468
/*     */     //   4416: iconst_1
/*     */     //   4417: if_icmpgt -> 4467
/*     */     //   4420: goto -> 4434
/*     */     //   4423: ldc2_w -9208511308924703329
/*     */     //   4426: lload #5
/*     */     //   4428: <illegal opcode> w : (Ljava/lang/Throwable;JJ)Ljava/lang/Throwable;
/*     */     //   4433: athrow
/*     */     //   4434: aload_1
/*     */     //   4435: sipush #16779
/*     */     //   4438: ldc2_w 1529615189750228037
/*     */     //   4441: lload #5
/*     */     //   4443: lxor
/*     */     //   4444: <illegal opcode> e : (IJ)Ljava/lang/String;
/*     */     //   4449: invokeinterface sendMessage : (Ljava/lang/String;)V
/*     */     //   4454: iconst_0
/*     */     //   4455: ireturn
/*     */     //   4456: ldc2_w -9208511308924703329
/*     */     //   4459: lload #5
/*     */     //   4461: <illegal opcode> w : (Ljava/lang/Throwable;JJ)Ljava/lang/Throwable;
/*     */     //   4466: athrow
/*     */     //   4467: iconst_1
/*     */     //   4468: istore #41
/*     */     //   4470: iload #41
/*     */     //   4472: aload #4
/*     */     //   4474: arraylength
/*     */     //   4475: if_icmpge -> 4543
/*     */     //   4478: aload_0
/*     */     //   4479: getfield b : Lme/konsolas/aac/AAC;
/*     */     //   4482: invokevirtual getServer : ()Lorg/bukkit/Server;
/*     */     //   4485: aload #4
/*     */     //   4487: iload #41
/*     */     //   4489: aaload
/*     */     //   4490: invokeinterface getOfflinePlayer : (Ljava/lang/String;)Lorg/bukkit/OfflinePlayer;
/*     */     //   4495: astore #42
/*     */     //   4497: aload_0
/*     */     //   4498: getfield b : Lme/konsolas/aac/AAC;
/*     */     //   4501: invokevirtual a : ()Lme/konsolas/aac/jI;
/*     */     //   4504: aload #42
/*     */     //   4506: lload #20
/*     */     //   4508: invokevirtual a : (Lorg/bukkit/OfflinePlayer;J)Ljava/util/concurrent/CompletableFuture;
/*     */     //   4511: aload_0
/*     */     //   4512: aload #42
/*     */     //   4514: <illegal opcode> apply : (Lme/konsolas/aac/mi;Lorg/bukkit/OfflinePlayer;)Ljava/util/function/Function;
/*     */     //   4519: invokevirtual thenCompose : (Ljava/util/function/Function;)Ljava/util/concurrent/CompletableFuture;
/*     */     //   4522: aload_0
/*     */     //   4523: aload #42
/*     */     //   4525: aload_1
/*     */     //   4526: <illegal opcode> accept : (Lme/konsolas/aac/mi;Lorg/bukkit/OfflinePlayer;Lorg/bukkit/command/CommandSender;)Ljava/util/function/BiConsumer;
/*     */     //   4531: invokevirtual whenComplete : (Ljava/util/function/BiConsumer;)Ljava/util/concurrent/CompletableFuture;
/*     */     //   4534: pop
/*     */     //   4535: iinc #41, 1
/*     */     //   4538: iload #38
/*     */     //   4540: ifne -> 4470
/*     */     //   4543: iconst_1
/*     */     //   4544: ireturn
/*     */     //   4545: aload_1
/*     */     //   4546: sipush #29567
/*     */     //   4549: ldc2_w 288873360360445643
/*     */     //   4552: lload #5
/*     */     //   4554: lxor
/*     */     //   4555: <illegal opcode> e : (IJ)Ljava/lang/String;
/*     */     //   4560: invokeinterface hasPermission : (Ljava/lang/String;)Z
/*     */     //   4565: iload #38
/*     */     //   4567: ifeq -> 4623
/*     */     //   4570: ifne -> 4620
/*     */     //   4573: goto -> 4587
/*     */     //   4576: ldc2_w -9208511308924703329
/*     */     //   4579: lload #5
/*     */     //   4581: <illegal opcode> w : (Ljava/lang/Throwable;JJ)Ljava/lang/Throwable;
/*     */     //   4586: athrow
/*     */     //   4587: aload_1
/*     */     //   4588: sipush #3114
/*     */     //   4591: ldc2_w 4126160228912490963
/*     */     //   4594: lload #5
/*     */     //   4596: lxor
/*     */     //   4597: <illegal opcode> e : (IJ)Ljava/lang/String;
/*     */     //   4602: invokeinterface sendMessage : (Ljava/lang/String;)V
/*     */     //   4607: iconst_0
/*     */     //   4608: ireturn
/*     */     //   4609: ldc2_w -9208511308924703329
/*     */     //   4612: lload #5
/*     */     //   4614: <illegal opcode> w : (Ljava/lang/Throwable;JJ)Ljava/lang/Throwable;
/*     */     //   4619: athrow
/*     */     //   4620: aload #4
/*     */     //   4622: arraylength
/*     */     //   4623: iload #38
/*     */     //   4625: ifeq -> 4680
/*     */     //   4628: iconst_1
/*     */     //   4629: if_icmpgt -> 4679
/*     */     //   4632: goto -> 4646
/*     */     //   4635: ldc2_w -9208511308924703329
/*     */     //   4638: lload #5
/*     */     //   4640: <illegal opcode> w : (Ljava/lang/Throwable;JJ)Ljava/lang/Throwable;
/*     */     //   4645: athrow
/*     */     //   4646: aload_1
/*     */     //   4647: sipush #30505
/*     */     //   4650: ldc2_w 426563527868617453
/*     */     //   4653: lload #5
/*     */     //   4655: lxor
/*     */     //   4656: <illegal opcode> e : (IJ)Ljava/lang/String;
/*     */     //   4661: invokeinterface sendMessage : (Ljava/lang/String;)V
/*     */     //   4666: iconst_0
/*     */     //   4667: ireturn
/*     */     //   4668: ldc2_w -9208511308924703329
/*     */     //   4671: lload #5
/*     */     //   4673: <illegal opcode> w : (Ljava/lang/Throwable;JJ)Ljava/lang/Throwable;
/*     */     //   4678: athrow
/*     */     //   4679: iconst_1
/*     */     //   4680: istore #41
/*     */     //   4682: iload #41
/*     */     //   4684: aload #4
/*     */     //   4686: arraylength
/*     */     //   4687: if_icmpge -> 4742
/*     */     //   4690: aload_0
/*     */     //   4691: getfield b : Lme/konsolas/aac/AAC;
/*     */     //   4694: invokevirtual getServer : ()Lorg/bukkit/Server;
/*     */     //   4697: aload #4
/*     */     //   4699: iload #41
/*     */     //   4701: aaload
/*     */     //   4702: invokeinterface getOfflinePlayer : (Ljava/lang/String;)Lorg/bukkit/OfflinePlayer;
/*     */     //   4707: astore #42
/*     */     //   4709: aload_0
/*     */     //   4710: getfield b : Lme/konsolas/aac/AAC;
/*     */     //   4713: invokevirtual a : ()Lme/konsolas/aac/fv;
/*     */     //   4716: aload #42
/*     */     //   4718: invokevirtual a : (Lorg/bukkit/OfflinePlayer;)Ljava/util/concurrent/CompletableFuture;
/*     */     //   4721: aload_0
/*     */     //   4722: aload #42
/*     */     //   4724: aload_1
/*     */     //   4725: <illegal opcode> accept : (Lme/konsolas/aac/mi;Lorg/bukkit/OfflinePlayer;Lorg/bukkit/command/CommandSender;)Ljava/util/function/BiConsumer;
/*     */     //   4730: invokevirtual whenComplete : (Ljava/util/function/BiConsumer;)Ljava/util/concurrent/CompletableFuture;
/*     */     //   4733: pop
/*     */     //   4734: iinc #41, 1
/*     */     //   4737: iload #38
/*     */     //   4739: ifne -> 4682
/*     */     //   4742: iconst_1
/*     */     //   4743: ireturn
/*     */     //   4744: aload_1
/*     */     //   4745: sipush #20319
/*     */     //   4748: ldc2_w 8480782514831108740
/*     */     //   4751: lload #5
/*     */     //   4753: lxor
/*     */     //   4754: <illegal opcode> e : (IJ)Ljava/lang/String;
/*     */     //   4759: invokeinterface hasPermission : (Ljava/lang/String;)Z
/*     */     //   4764: iload #38
/*     */     //   4766: ifeq -> 4822
/*     */     //   4769: ifne -> 4819
/*     */     //   4772: goto -> 4786
/*     */     //   4775: ldc2_w -9208511308924703329
/*     */     //   4778: lload #5
/*     */     //   4780: <illegal opcode> w : (Ljava/lang/Throwable;JJ)Ljava/lang/Throwable;
/*     */     //   4785: athrow
/*     */     //   4786: aload_1
/*     */     //   4787: sipush #29182
/*     */     //   4790: ldc2_w 1803184648450020597
/*     */     //   4793: lload #5
/*     */     //   4795: lxor
/*     */     //   4796: <illegal opcode> e : (IJ)Ljava/lang/String;
/*     */     //   4801: invokeinterface sendMessage : (Ljava/lang/String;)V
/*     */     //   4806: iconst_0
/*     */     //   4807: ireturn
/*     */     //   4808: ldc2_w -9208511308924703329
/*     */     //   4811: lload #5
/*     */     //   4813: <illegal opcode> w : (Ljava/lang/Throwable;JJ)Ljava/lang/Throwable;
/*     */     //   4818: athrow
/*     */     //   4819: aload #4
/*     */     //   4821: arraylength
/*     */     //   4822: iconst_2
/*     */     //   4823: iload #38
/*     */     //   4825: ifeq -> 4901
/*     */     //   4828: if_icmple -> 4878
/*     */     //   4831: goto -> 4845
/*     */     //   4834: ldc2_w -9208511308924703329
/*     */     //   4837: lload #5
/*     */     //   4839: <illegal opcode> w : (Ljava/lang/Throwable;JJ)Ljava/lang/Throwable;
/*     */     //   4844: athrow
/*     */     //   4845: aload_1
/*     */     //   4846: sipush #18020
/*     */     //   4849: ldc2_w 1847278057655542636
/*     */     //   4852: lload #5
/*     */     //   4854: lxor
/*     */     //   4855: <illegal opcode> e : (IJ)Ljava/lang/String;
/*     */     //   4860: invokeinterface sendMessage : (Ljava/lang/String;)V
/*     */     //   4865: iconst_0
/*     */     //   4866: ireturn
/*     */     //   4867: ldc2_w -9208511308924703329
/*     */     //   4870: lload #5
/*     */     //   4872: <illegal opcode> w : (Ljava/lang/Throwable;JJ)Ljava/lang/Throwable;
/*     */     //   4877: athrow
/*     */     //   4878: aload #4
/*     */     //   4880: iload #38
/*     */     //   4882: ifeq -> 4989
/*     */     //   4885: arraylength
/*     */     //   4886: iconst_1
/*     */     //   4887: goto -> 4901
/*     */     //   4890: ldc2_w -9208511308924703329
/*     */     //   4893: lload #5
/*     */     //   4895: <illegal opcode> w : (Ljava/lang/Throwable;JJ)Ljava/lang/Throwable;
/*     */     //   4900: athrow
/*     */     //   4901: if_icmpne -> 4973
/*     */     //   4904: aload_0
/*     */     //   4905: lload #15
/*     */     //   4907: invokespecial a : (J)Lnet/md_5/bungee/api/chat/BaseComponent;
/*     */     //   4910: astore #41
/*     */     //   4912: aload #41
/*     */     //   4914: new java/lang/StringBuilder
/*     */     //   4917: dup
/*     */     //   4918: invokespecial <init> : ()V
/*     */     //   4921: sipush #30414
/*     */     //   4924: ldc2_w 1544216678108271443
/*     */     //   4927: lload #5
/*     */     //   4929: lxor
/*     */     //   4930: <illegal opcode> e : (IJ)Ljava/lang/String;
/*     */     //   4935: invokevirtual append : (Ljava/lang/String;)Ljava/lang/StringBuilder;
/*     */     //   4938: aload_0
/*     */     //   4939: getfield d : Ljava/util/Map;
/*     */     //   4942: aload_1
/*     */     //   4943: getstatic me/konsolas/aac/dh.NORMAL : Lme/konsolas/aac/dh;
/*     */     //   4946: invokeinterface getOrDefault : (Ljava/lang/Object;Ljava/lang/Object;)Ljava/lang/Object;
/*     */     //   4951: invokevirtual append : (Ljava/lang/Object;)Ljava/lang/StringBuilder;
/*     */     //   4954: invokevirtual toString : ()Ljava/lang/String;
/*     */     //   4957: invokevirtual addExtra : (Ljava/lang/String;)V
/*     */     //   4960: aload_1
/*     */     //   4961: aload #41
/*     */     //   4963: lload #7
/*     */     //   4965: invokestatic a : (Lorg/bukkit/command/CommandSender;Lnet/md_5/bungee/api/chat/BaseComponent;J)V
/*     */     //   4968: iload #38
/*     */     //   4970: ifne -> 5479
/*     */     //   4973: aload #4
/*     */     //   4975: goto -> 4989
/*     */     //   4978: ldc2_w -9208511308924703329
/*     */     //   4981: lload #5
/*     */     //   4983: <illegal opcode> w : (Ljava/lang/Throwable;JJ)Ljava/lang/Throwable;
/*     */     //   4988: athrow
/*     */     //   4989: iconst_1
/*     */     //   4990: aaload
/*     */     //   4991: invokevirtual toLowerCase : ()Ljava/lang/String;
/*     */     //   4994: astore #41
/*     */     //   4996: iconst_m1
/*     */     //   4997: istore #42
/*     */     //   4999: aload #41
/*     */     //   5001: invokevirtual hashCode : ()I
/*     */     //   5004: iload #38
/*     */     //   5006: ifeq -> 5241
/*     */     //   5009: lookupswitch default -> 5239, -1039745817 -> 5118, 109935 -> 5055, 1083684798 -> 5181
/*     */     //   5044: ldc2_w -9208511308924703329
/*     */     //   5047: lload #5
/*     */     //   5049: <illegal opcode> w : (Ljava/lang/Throwable;JJ)Ljava/lang/Throwable;
/*     */     //   5054: athrow
/*     */     //   5055: aload #41
/*     */     //   5057: sipush #23043
/*     */     //   5060: ldc2_w 6998910782481317788
/*     */     //   5063: lload #5
/*     */     //   5065: lxor
/*     */     //   5066: <illegal opcode> e : (IJ)Ljava/lang/String;
/*     */     //   5071: invokevirtual equals : (Ljava/lang/Object;)Z
/*     */     //   5074: iload #38
/*     */     //   5076: ifeq -> 5241
/*     */     //   5079: goto -> 5093
/*     */     //   5082: ldc2_w -9208511308924703329
/*     */     //   5085: lload #5
/*     */     //   5087: <illegal opcode> w : (Ljava/lang/Throwable;JJ)Ljava/lang/Throwable;
/*     */     //   5092: athrow
/*     */     //   5093: ifeq -> 5239
/*     */     //   5096: goto -> 5110
/*     */     //   5099: ldc2_w -9208511308924703329
/*     */     //   5102: lload #5
/*     */     //   5104: <illegal opcode> w : (Ljava/lang/Throwable;JJ)Ljava/lang/Throwable;
/*     */     //   5109: athrow
/*     */     //   5110: iconst_0
/*     */     //   5111: istore #42
/*     */     //   5113: iload #38
/*     */     //   5115: ifne -> 5239
/*     */     //   5118: aload #41
/*     */     //   5120: sipush #23114
/*     */     //   5123: ldc2_w 5764668051118505865
/*     */     //   5126: lload #5
/*     */     //   5128: lxor
/*     */     //   5129: <illegal opcode> e : (IJ)Ljava/lang/String;
/*     */     //   5134: invokevirtual equals : (Ljava/lang/Object;)Z
/*     */     //   5137: iload #38
/*     */     //   5139: ifeq -> 5241
/*     */     //   5142: goto -> 5156
/*     */     //   5145: ldc2_w -9208511308924703329
/*     */     //   5148: lload #5
/*     */     //   5150: <illegal opcode> w : (Ljava/lang/Throwable;JJ)Ljava/lang/Throwable;
/*     */     //   5155: athrow
/*     */     //   5156: ifeq -> 5239
/*     */     //   5159: goto -> 5173
/*     */     //   5162: ldc2_w -9208511308924703329
/*     */     //   5165: lload #5
/*     */     //   5167: <illegal opcode> w : (Ljava/lang/Throwable;JJ)Ljava/lang/Throwable;
/*     */     //   5172: athrow
/*     */     //   5173: iconst_1
/*     */     //   5174: istore #42
/*     */     //   5176: iload #38
/*     */     //   5178: ifne -> 5239
/*     */     //   5181: aload #41
/*     */     //   5183: sipush #32239
/*     */     //   5186: ldc2_w 160456738130401379
/*     */     //   5189: lload #5
/*     */     //   5191: lxor
/*     */     //   5192: <illegal opcode> e : (IJ)Ljava/lang/String;
/*     */     //   5197: invokevirtual equals : (Ljava/lang/Object;)Z
/*     */     //   5200: iload #38
/*     */     //   5202: ifeq -> 5241
/*     */     //   5205: goto -> 5219
/*     */     //   5208: ldc2_w -9208511308924703329
/*     */     //   5211: lload #5
/*     */     //   5213: <illegal opcode> w : (Ljava/lang/Throwable;JJ)Ljava/lang/Throwable;
/*     */     //   5218: athrow
/*     */     //   5219: ifeq -> 5239
/*     */     //   5222: goto -> 5236
/*     */     //   5225: ldc2_w -9208511308924703329
/*     */     //   5228: lload #5
/*     */     //   5230: <illegal opcode> w : (Ljava/lang/Throwable;JJ)Ljava/lang/Throwable;
/*     */     //   5235: athrow
/*     */     //   5236: iconst_2
/*     */     //   5237: istore #42
/*     */     //   5239: iload #42
/*     */     //   5241: iload #38
/*     */     //   5243: ifeq -> 5414
/*     */     //   5246: tableswitch default -> 5379, 0 -> 5283, 1 -> 5316, 2 -> 5346
/*     */     //   5272: ldc2_w -9208511308924703329
/*     */     //   5275: lload #5
/*     */     //   5277: <illegal opcode> w : (Ljava/lang/Throwable;JJ)Ljava/lang/Throwable;
/*     */     //   5282: athrow
/*     */     //   5283: aload_0
/*     */     //   5284: getfield d : Ljava/util/Map;
/*     */     //   5287: aload_1
/*     */     //   5288: getstatic me/konsolas/aac/dh.OFF : Lme/konsolas/aac/dh;
/*     */     //   5291: invokeinterface put : (Ljava/lang/Object;Ljava/lang/Object;)Ljava/lang/Object;
/*     */     //   5296: pop
/*     */     //   5297: iload #38
/*     */     //   5299: ifne -> 5415
/*     */     //   5302: goto -> 5316
/*     */     //   5305: ldc2_w -9208511308924703329
/*     */     //   5308: lload #5
/*     */     //   5310: <illegal opcode> w : (Ljava/lang/Throwable;JJ)Ljava/lang/Throwable;
/*     */     //   5315: athrow
/*     */     //   5316: aload_0
/*     */     //   5317: getfield d : Ljava/util/Map;
/*     */     //   5320: aload_1
/*     */     //   5321: invokeinterface remove : (Ljava/lang/Object;)Ljava/lang/Object;
/*     */     //   5326: pop
/*     */     //   5327: iload #38
/*     */     //   5329: ifne -> 5415
/*     */     //   5332: goto -> 5346
/*     */     //   5335: ldc2_w -9208511308924703329
/*     */     //   5338: lload #5
/*     */     //   5340: <illegal opcode> w : (Ljava/lang/Throwable;JJ)Ljava/lang/Throwable;
/*     */     //   5345: athrow
/*     */     //   5346: aload_0
/*     */     //   5347: getfield d : Ljava/util/Map;
/*     */     //   5350: aload_1
/*     */     //   5351: getstatic me/konsolas/aac/dh.REDUCED : Lme/konsolas/aac/dh;
/*     */     //   5354: invokeinterface put : (Ljava/lang/Object;Ljava/lang/Object;)Ljava/lang/Object;
/*     */     //   5359: pop
/*     */     //   5360: iload #38
/*     */     //   5362: ifne -> 5415
/*     */     //   5365: goto -> 5379
/*     */     //   5368: ldc2_w -9208511308924703329
/*     */     //   5371: lload #5
/*     */     //   5373: <illegal opcode> w : (Ljava/lang/Throwable;JJ)Ljava/lang/Throwable;
/*     */     //   5378: athrow
/*     */     //   5379: aload_1
/*     */     //   5380: sipush #12502
/*     */     //   5383: ldc2_w 616788292832220441
/*     */     //   5386: lload #5
/*     */     //   5388: lxor
/*     */     //   5389: <illegal opcode> e : (IJ)Ljava/lang/String;
/*     */     //   5394: invokeinterface sendMessage : (Ljava/lang/String;)V
/*     */     //   5399: iconst_0
/*     */     //   5400: goto -> 5414
/*     */     //   5403: ldc2_w -9208511308924703329
/*     */     //   5406: lload #5
/*     */     //   5408: <illegal opcode> w : (Ljava/lang/Throwable;JJ)Ljava/lang/Throwable;
/*     */     //   5413: athrow
/*     */     //   5414: ireturn
/*     */     //   5415: aload_0
/*     */     //   5416: lload #15
/*     */     //   5418: invokespecial a : (J)Lnet/md_5/bungee/api/chat/BaseComponent;
/*     */     //   5421: astore #41
/*     */     //   5423: aload #41
/*     */     //   5425: new java/lang/StringBuilder
/*     */     //   5428: dup
/*     */     //   5429: invokespecial <init> : ()V
/*     */     //   5432: sipush #26200
/*     */     //   5435: ldc2_w 3406695601134404447
/*     */     //   5438: lload #5
/*     */     //   5440: lxor
/*     */     //   5441: <illegal opcode> e : (IJ)Ljava/lang/String;
/*     */     //   5446: invokevirtual append : (Ljava/lang/String;)Ljava/lang/StringBuilder;
/*     */     //   5449: aload_0
/*     */     //   5450: getfield d : Ljava/util/Map;
/*     */     //   5453: aload_1
/*     */     //   5454: getstatic me/konsolas/aac/dh.NORMAL : Lme/konsolas/aac/dh;
/*     */     //   5457: invokeinterface getOrDefault : (Ljava/lang/Object;Ljava/lang/Object;)Ljava/lang/Object;
/*     */     //   5462: invokevirtual append : (Ljava/lang/Object;)Ljava/lang/StringBuilder;
/*     */     //   5465: invokevirtual toString : ()Ljava/lang/String;
/*     */     //   5468: invokevirtual addExtra : (Ljava/lang/String;)V
/*     */     //   5471: aload_1
/*     */     //   5472: aload #41
/*     */     //   5474: lload #7
/*     */     //   5476: invokestatic a : (Lorg/bukkit/command/CommandSender;Lnet/md_5/bungee/api/chat/BaseComponent;J)V
/*     */     //   5479: iconst_1
/*     */     //   5480: ireturn
/*     */     //   5481: aload_1
/*     */     //   5482: sipush #4766
/*     */     //   5485: ldc2_w 4526855441745311558
/*     */     //   5488: lload #5
/*     */     //   5490: lxor
/*     */     //   5491: <illegal opcode> e : (IJ)Ljava/lang/String;
/*     */     //   5496: invokeinterface hasPermission : (Ljava/lang/String;)Z
/*     */     //   5501: iload #38
/*     */     //   5503: ifeq -> 5559
/*     */     //   5506: ifne -> 5556
/*     */     //   5509: goto -> 5523
/*     */     //   5512: ldc2_w -9208511308924703329
/*     */     //   5515: lload #5
/*     */     //   5517: <illegal opcode> w : (Ljava/lang/Throwable;JJ)Ljava/lang/Throwable;
/*     */     //   5522: athrow
/*     */     //   5523: aload_1
/*     */     //   5524: sipush #9644
/*     */     //   5527: ldc2_w 5385610960059449451
/*     */     //   5530: lload #5
/*     */     //   5532: lxor
/*     */     //   5533: <illegal opcode> e : (IJ)Ljava/lang/String;
/*     */     //   5538: invokeinterface sendMessage : (Ljava/lang/String;)V
/*     */     //   5543: iconst_0
/*     */     //   5544: ireturn
/*     */     //   5545: ldc2_w -9208511308924703329
/*     */     //   5548: lload #5
/*     */     //   5550: <illegal opcode> w : (Ljava/lang/Throwable;JJ)Ljava/lang/Throwable;
/*     */     //   5555: athrow
/*     */     //   5556: aload #4
/*     */     //   5558: arraylength
/*     */     //   5559: iload #38
/*     */     //   5561: ifeq -> 5629
/*     */     //   5564: iconst_1
/*     */     //   5565: if_icmpne -> 5614
/*     */     //   5568: goto -> 5582
/*     */     //   5571: ldc2_w -9208511308924703329
/*     */     //   5574: lload #5
/*     */     //   5576: <illegal opcode> w : (Ljava/lang/Throwable;JJ)Ljava/lang/Throwable;
/*     */     //   5581: athrow
/*     */     //   5582: aload_0
/*     */     //   5583: getfield b : Lme/konsolas/aac/AAC;
/*     */     //   5586: invokevirtual a : ()Lme/konsolas/aac/w;
/*     */     //   5589: aload_1
/*     */     //   5590: lload #26
/*     */     //   5592: invokevirtual a : (Lorg/bukkit/command/CommandSender;J)V
/*     */     //   5595: iload #38
/*     */     //   5597: ifne -> 5706
/*     */     //   5600: goto -> 5614
/*     */     //   5603: ldc2_w -9208511308924703329
/*     */     //   5606: lload #5
/*     */     //   5608: <illegal opcode> w : (Ljava/lang/Throwable;JJ)Ljava/lang/Throwable;
/*     */     //   5613: athrow
/*     */     //   5614: iconst_1
/*     */     //   5615: goto -> 5629
/*     */     //   5618: ldc2_w -9208511308924703329
/*     */     //   5621: lload #5
/*     */     //   5623: <illegal opcode> w : (Ljava/lang/Throwable;JJ)Ljava/lang/Throwable;
/*     */     //   5628: athrow
/*     */     //   5629: istore #41
/*     */     //   5631: iload #41
/*     */     //   5633: aload #4
/*     */     //   5635: arraylength
/*     */     //   5636: if_icmpge -> 5706
/*     */     //   5639: aload_0
/*     */     //   5640: getfield b : Lme/konsolas/aac/AAC;
/*     */     //   5643: invokevirtual getServer : ()Lorg/bukkit/Server;
/*     */     //   5646: aload #4
/*     */     //   5648: iload #41
/*     */     //   5650: aaload
/*     */     //   5651: invokeinterface getOfflinePlayer : (Ljava/lang/String;)Lorg/bukkit/OfflinePlayer;
/*     */     //   5656: astore #42
/*     */     //   5658: aload_0
/*     */     //   5659: iload #38
/*     */     //   5661: ifeq -> 5707
/*     */     //   5664: getfield b : Lme/konsolas/aac/AAC;
/*     */     //   5667: invokevirtual a : ()Lme/konsolas/aac/w;
/*     */     //   5670: iload #33
/*     */     //   5672: i2s
/*     */     //   5673: iload #34
/*     */     //   5675: i2s
/*     */     //   5676: iload #35
/*     */     //   5678: aload_1
/*     */     //   5679: aload #42
/*     */     //   5681: invokevirtual a : (SSILorg/bukkit/command/CommandSender;Lorg/bukkit/OfflinePlayer;)V
/*     */     //   5684: iinc #41, 1
/*     */     //   5687: iload #38
/*     */     //   5689: ifne -> 5631
/*     */     //   5692: goto -> 5706
/*     */     //   5695: ldc2_w -9208511308924703329
/*     */     //   5698: lload #5
/*     */     //   5700: <illegal opcode> w : (Ljava/lang/Throwable;JJ)Ljava/lang/Throwable;
/*     */     //   5705: athrow
/*     */     //   5706: aload_0
/*     */     //   5707: lload #15
/*     */     //   5709: invokespecial a : (J)Lnet/md_5/bungee/api/chat/BaseComponent;
/*     */     //   5712: astore #41
/*     */     //   5714: aload #41
/*     */     //   5716: sipush #27056
/*     */     //   5719: ldc2_w 556019463146802222
/*     */     //   5722: lload #5
/*     */     //   5724: lxor
/*     */     //   5725: <illegal opcode> e : (IJ)Ljava/lang/String;
/*     */     //   5730: invokevirtual addExtra : (Ljava/lang/String;)V
/*     */     //   5733: aload_0
/*     */     //   5734: getfield b : Lme/konsolas/aac/AAC;
/*     */     //   5737: invokevirtual a : ()Lme/konsolas/aac/w;
/*     */     //   5740: aload_1
/*     */     //   5741: lload #28
/*     */     //   5743: invokevirtual a : (Lorg/bukkit/command/CommandSender;J)Z
/*     */     //   5746: iload #38
/*     */     //   5748: ifeq -> 5892
/*     */     //   5751: ifeq -> 5841
/*     */     //   5754: goto -> 5768
/*     */     //   5757: ldc2_w -9208511308924703329
/*     */     //   5760: lload #5
/*     */     //   5762: <illegal opcode> w : (Ljava/lang/Throwable;JJ)Ljava/lang/Throwable;
/*     */     //   5767: athrow
/*     */     //   5768: aload #41
/*     */     //   5770: ldc_w '邹㿎'
/*     */     //   5773: invokevirtual toCharArray : ()[C
/*     */     //   5776: dup
/*     */     //   5777: dup
/*     */     //   5778: iconst_0
/*     */     //   5779: dup_x1
/*     */     //   5780: caload
/*     */     //   5781: sipush #29659
/*     */     //   5784: ixor
/*     */     //   5785: i2c
/*     */     //   5786: castore
/*     */     //   5787: sipush #1883
/*     */     //   5790: iconst_0
/*     */     //   5791: iconst_4
/*     */     //   5792: invokestatic G : (Ljava/lang/Object;SZB)Ljava/lang/String;
/*     */     //   5795: invokevirtual addExtra : (Ljava/lang/String;)V
/*     */     //   5798: new net/md_5/bungee/api/chat/TextComponent
/*     */     //   5801: dup
/*     */     //   5802: sipush #16107
/*     */     //   5805: ldc2_w 8714501750374226921
/*     */     //   5808: lload #5
/*     */     //   5810: lxor
/*     */     //   5811: <illegal opcode> e : (IJ)Ljava/lang/String;
/*     */     //   5816: invokespecial <init> : (Ljava/lang/String;)V
/*     */     //   5819: astore #42
/*     */     //   5821: aload #42
/*     */     //   5823: getstatic net/md_5/bungee/api/ChatColor.GRAY : Lnet/md_5/bungee/api/ChatColor;
/*     */     //   5826: invokevirtual setColor : (Lnet/md_5/bungee/api/ChatColor;)V
/*     */     //   5829: aload #41
/*     */     //   5831: aload #42
/*     */     //   5833: invokevirtual addExtra : (Lnet/md_5/bungee/api/chat/BaseComponent;)V
/*     */     //   5836: iload #38
/*     */     //   5838: ifne -> 6091
/*     */     //   5841: aload_0
/*     */     //   5842: getfield b : Lme/konsolas/aac/AAC;
/*     */     //   5845: invokevirtual a : ()Lme/konsolas/aac/w;
/*     */     //   5848: aload_1
/*     */     //   5849: lload #24
/*     */     //   5851: invokevirtual a : (Lorg/bukkit/command/CommandSender;J)Ljava/util/Set;
/*     */     //   5854: iload #38
/*     */     //   5856: ifeq -> 5922
/*     */     //   5859: goto -> 5873
/*     */     //   5862: ldc2_w -9208511308924703329
/*     */     //   5865: lload #5
/*     */     //   5867: <illegal opcode> w : (Ljava/lang/Throwable;JJ)Ljava/lang/Throwable;
/*     */     //   5872: athrow
/*     */     //   5873: invokeinterface isEmpty : ()Z
/*     */     //   5878: goto -> 5892
/*     */     //   5881: ldc2_w -9208511308924703329
/*     */     //   5884: lload #5
/*     */     //   5886: <illegal opcode> w : (Ljava/lang/Throwable;JJ)Ljava/lang/Throwable;
/*     */     //   5891: athrow
/*     */     //   5892: ifne -> 6023
/*     */     //   5895: aload_0
/*     */     //   5896: getfield b : Lme/konsolas/aac/AAC;
/*     */     //   5899: invokevirtual a : ()Lme/konsolas/aac/w;
/*     */     //   5902: aload_1
/*     */     //   5903: lload #24
/*     */     //   5905: invokevirtual a : (Lorg/bukkit/command/CommandSender;J)Ljava/util/Set;
/*     */     //   5908: goto -> 5922
/*     */     //   5911: ldc2_w -9208511308924703329
/*     */     //   5914: lload #5
/*     */     //   5916: <illegal opcode> w : (Ljava/lang/Throwable;JJ)Ljava/lang/Throwable;
/*     */     //   5921: athrow
/*     */     //   5922: invokeinterface iterator : ()Ljava/util/Iterator;
/*     */     //   5927: astore #42
/*     */     //   5929: aload #42
/*     */     //   5931: invokeinterface hasNext : ()Z
/*     */     //   5936: ifeq -> 6018
/*     */     //   5939: aload #42
/*     */     //   5941: invokeinterface next : ()Ljava/lang/Object;
/*     */     //   5946: checkcast org/bukkit/OfflinePlayer
/*     */     //   5949: astore #43
/*     */     //   5951: aload #41
/*     */     //   5953: ldc_w '该ィ'
/*     */     //   5956: invokevirtual toCharArray : ()[C
/*     */     //   5959: dup
/*     */     //   5960: dup
/*     */     //   5961: iconst_0
/*     */     //   5962: dup_x1
/*     */     //   5963: caload
/*     */     //   5964: sipush #13607
/*     */     //   5967: ixor
/*     */     //   5968: i2c
/*     */     //   5969: castore
/*     */     //   5970: sipush #16130
/*     */     //   5973: iconst_1
/*     */     //   5974: iconst_1
/*     */     //   5975: invokestatic G : (Ljava/lang/Object;SZB)Ljava/lang/String;
/*     */     //   5978: invokevirtual addExtra : (Ljava/lang/String;)V
/*     */     //   5981: aload #41
/*     */     //   5983: aload_0
/*     */     //   5984: aload #43
/*     */     //   5986: lload #22
/*     */     //   5988: invokespecial a : (Lorg/bukkit/OfflinePlayer;J)Lnet/md_5/bungee/api/chat/BaseComponent;
/*     */     //   5991: invokevirtual addExtra : (Lnet/md_5/bungee/api/chat/BaseComponent;)V
/*     */     //   5994: iload #38
/*     */     //   5996: ifeq -> 6099
/*     */     //   5999: iload #38
/*     */     //   6001: ifne -> 5929
/*     */     //   6004: goto -> 6018
/*     */     //   6007: ldc2_w -9208511308924703329
/*     */     //   6010: lload #5
/*     */     //   6012: <illegal opcode> w : (Ljava/lang/Throwable;JJ)Ljava/lang/Throwable;
/*     */     //   6017: athrow
/*     */     //   6018: iload #38
/*     */     //   6020: ifne -> 6091
/*     */     //   6023: aload #41
/*     */     //   6025: ldc_w '⇿ㆹ'
/*     */     //   6028: invokevirtual toCharArray : ()[C
/*     */     //   6031: dup
/*     */     //   6032: dup
/*     */     //   6033: iconst_0
/*     */     //   6034: dup_x1
/*     */     //   6035: caload
/*     */     //   6036: sipush #29541
/*     */     //   6039: ixor
/*     */     //   6040: i2c
/*     */     //   6041: castore
/*     */     //   6042: sipush #28643
/*     */     //   6045: iconst_0
/*     */     //   6046: iconst_4
/*     */     //   6047: invokestatic G : (Ljava/lang/Object;SZB)Ljava/lang/String;
/*     */     //   6050: invokevirtual addExtra : (Ljava/lang/String;)V
/*     */     //   6053: new net/md_5/bungee/api/chat/TextComponent
/*     */     //   6056: dup
/*     */     //   6057: sipush #29206
/*     */     //   6060: ldc2_w 1710551842269042614
/*     */     //   6063: lload #5
/*     */     //   6065: lxor
/*     */     //   6066: <illegal opcode> e : (IJ)Ljava/lang/String;
/*     */     //   6071: invokespecial <init> : (Ljava/lang/String;)V
/*     */     //   6074: astore #42
/*     */     //   6076: aload #42
/*     */     //   6078: getstatic net/md_5/bungee/api/ChatColor.GRAY : Lnet/md_5/bungee/api/ChatColor;
/*     */     //   6081: invokevirtual setColor : (Lnet/md_5/bungee/api/ChatColor;)V
/*     */     //   6084: aload #41
/*     */     //   6086: aload #42
/*     */     //   6088: invokevirtual addExtra : (Lnet/md_5/bungee/api/chat/BaseComponent;)V
/*     */     //   6091: aload_1
/*     */     //   6092: aload #41
/*     */     //   6094: lload #7
/*     */     //   6096: invokestatic a : (Lorg/bukkit/command/CommandSender;Lnet/md_5/bungee/api/chat/BaseComponent;J)V
/*     */     //   6099: iconst_1
/*     */     //   6100: ireturn
/*     */     //   6101: aload_1
/*     */     //   6102: sipush #28684
/*     */     //   6105: ldc2_w 7064702084625208803
/*     */     //   6108: lload #5
/*     */     //   6110: lxor
/*     */     //   6111: <illegal opcode> e : (IJ)Ljava/lang/String;
/*     */     //   6116: invokeinterface hasPermission : (Ljava/lang/String;)Z
/*     */     //   6121: iload #38
/*     */     //   6123: ifeq -> 6178
/*     */     //   6126: ifne -> 6179
/*     */     //   6129: goto -> 6143
/*     */     //   6132: ldc2_w -9208511308924703329
/*     */     //   6135: lload #5
/*     */     //   6137: <illegal opcode> w : (Ljava/lang/Throwable;JJ)Ljava/lang/Throwable;
/*     */     //   6142: athrow
/*     */     //   6143: aload_1
/*     */     //   6144: sipush #4152
/*     */     //   6147: ldc2_w 4783326324328854840
/*     */     //   6150: lload #5
/*     */     //   6152: lxor
/*     */     //   6153: <illegal opcode> e : (IJ)Ljava/lang/String;
/*     */     //   6158: invokeinterface sendMessage : (Ljava/lang/String;)V
/*     */     //   6163: iconst_0
/*     */     //   6164: goto -> 6178
/*     */     //   6167: ldc2_w -9208511308924703329
/*     */     //   6170: lload #5
/*     */     //   6172: <illegal opcode> w : (Ljava/lang/Throwable;JJ)Ljava/lang/Throwable;
/*     */     //   6177: athrow
/*     */     //   6178: ireturn
/*     */     //   6179: aload_0
/*     */     //   6180: getfield b : Lme/konsolas/aac/AAC;
/*     */     //   6183: invokevirtual getLogger : ()Ljava/util/logging/Logger;
/*     */     //   6186: new java/lang/StringBuilder
/*     */     //   6189: dup
/*     */     //   6190: invokespecial <init> : ()V
/*     */     //   6193: sipush #21422
/*     */     //   6196: ldc2_w 6218944952862717449
/*     */     //   6199: lload #5
/*     */     //   6201: lxor
/*     */     //   6202: <illegal opcode> e : (IJ)Ljava/lang/String;
/*     */     //   6207: invokevirtual append : (Ljava/lang/String;)Ljava/lang/StringBuilder;
/*     */     //   6210: aload_1
/*     */     //   6211: invokeinterface getName : ()Ljava/lang/String;
/*     */     //   6216: invokevirtual append : (Ljava/lang/String;)Ljava/lang/StringBuilder;
/*     */     //   6219: invokevirtual toString : ()Ljava/lang/String;
/*     */     //   6222: invokevirtual info : (Ljava/lang/String;)V
/*     */     //   6225: invokestatic getServer : ()Lorg/bukkit/Server;
/*     */     //   6228: invokeinterface getPluginManager : ()Lorg/bukkit/plugin/PluginManager;
/*     */     //   6233: aload_0
/*     */     //   6234: getfield b : Lme/konsolas/aac/AAC;
/*     */     //   6237: invokeinterface disablePlugin : (Lorg/bukkit/plugin/Plugin;)V
/*     */     //   6242: invokestatic getServer : ()Lorg/bukkit/Server;
/*     */     //   6245: invokeinterface getPluginManager : ()Lorg/bukkit/plugin/PluginManager;
/*     */     //   6250: aload_0
/*     */     //   6251: getfield b : Lme/konsolas/aac/AAC;
/*     */     //   6254: invokeinterface enablePlugin : (Lorg/bukkit/plugin/Plugin;)V
/*     */     //   6259: aload_0
/*     */     //   6260: lload #15
/*     */     //   6262: invokespecial a : (J)Lnet/md_5/bungee/api/chat/BaseComponent;
/*     */     //   6265: astore #41
/*     */     //   6267: aload #41
/*     */     //   6269: sipush #7070
/*     */     //   6272: ldc2_w 7366399594315939440
/*     */     //   6275: lload #5
/*     */     //   6277: lxor
/*     */     //   6278: <illegal opcode> e : (IJ)Ljava/lang/String;
/*     */     //   6283: invokevirtual addExtra : (Ljava/lang/String;)V
/*     */     //   6286: aload_1
/*     */     //   6287: aload #41
/*     */     //   6289: lload #7
/*     */     //   6291: invokestatic a : (Lorg/bukkit/command/CommandSender;Lnet/md_5/bungee/api/chat/BaseComponent;J)V
/*     */     //   6294: iconst_1
/*     */     //   6295: ireturn
/*     */     //   6296: aload_0
/*     */     //   6297: getfield b : Lme/konsolas/aac/AAC;
/*     */     //   6300: invokevirtual a : ()Lme/konsolas/aac/kk;
/*     */     //   6303: invokevirtual b : ()Ljava/lang/String;
/*     */     //   6306: ifnonnull -> 6322
/*     */     //   6309: iconst_0
/*     */     //   6310: ireturn
/*     */     //   6311: ldc2_w -9208511308924703329
/*     */     //   6314: lload #5
/*     */     //   6316: <illegal opcode> w : (Ljava/lang/Throwable;JJ)Ljava/lang/Throwable;
/*     */     //   6321: athrow
/*     */     //   6322: aload_1
/*     */     //   6323: sipush #15695
/*     */     //   6326: ldc2_w 1049483762496985336
/*     */     //   6329: lload #5
/*     */     //   6331: lxor
/*     */     //   6332: <illegal opcode> e : (IJ)Ljava/lang/String;
/*     */     //   6337: invokeinterface hasPermission : (Ljava/lang/String;)Z
/*     */     //   6342: iload #38
/*     */     //   6344: ifeq -> 6399
/*     */     //   6347: ifne -> 6400
/*     */     //   6350: goto -> 6364
/*     */     //   6353: ldc2_w -9208511308924703329
/*     */     //   6356: lload #5
/*     */     //   6358: <illegal opcode> w : (Ljava/lang/Throwable;JJ)Ljava/lang/Throwable;
/*     */     //   6363: athrow
/*     */     //   6364: aload_1
/*     */     //   6365: sipush #22811
/*     */     //   6368: ldc2_w 8731541950526241933
/*     */     //   6371: lload #5
/*     */     //   6373: lxor
/*     */     //   6374: <illegal opcode> e : (IJ)Ljava/lang/String;
/*     */     //   6379: invokeinterface sendMessage : (Ljava/lang/String;)V
/*     */     //   6384: iconst_0
/*     */     //   6385: goto -> 6399
/*     */     //   6388: ldc2_w -9208511308924703329
/*     */     //   6391: lload #5
/*     */     //   6393: <illegal opcode> w : (Ljava/lang/Throwable;JJ)Ljava/lang/Throwable;
/*     */     //   6398: athrow
/*     */     //   6399: ireturn
/*     */     //   6400: new me/konsolas/aac/gI
/*     */     //   6403: dup
/*     */     //   6404: lload #13
/*     */     //   6406: invokespecial <init> : (J)V
/*     */     //   6409: getstatic java/net/Proxy.NO_PROXY : Ljava/net/Proxy;
/*     */     //   6412: invokevirtual a : (Ljava/net/Proxy;)Lme/konsolas/aac/gI;
/*     */     //   6415: lload #11
/*     */     //   6417: invokevirtual a : (J)Lme/konsolas/aac/gf;
/*     */     //   6420: astore #41
/*     */     //   6422: invokestatic getServer : ()Lorg/bukkit/Server;
/*     */     //   6425: invokeinterface getScheduler : ()Lorg/bukkit/scheduler/BukkitScheduler;
/*     */     //   6430: aload_0
/*     */     //   6431: getfield b : Lme/konsolas/aac/AAC;
/*     */     //   6434: aload_0
/*     */     //   6435: aload #4
/*     */     //   6437: aload #41
/*     */     //   6439: aload_1
/*     */     //   6440: <illegal opcode> run : (Lme/konsolas/aac/mi;[Ljava/lang/String;Lme/konsolas/aac/gf;Lorg/bukkit/command/CommandSender;)Ljava/lang/Runnable;
/*     */     //   6445: invokeinterface runTaskAsynchronously : (Lorg/bukkit/plugin/Plugin;Ljava/lang/Runnable;)Lorg/bukkit/scheduler/BukkitTask;
/*     */     //   6450: pop
/*     */     //   6451: iconst_1
/*     */     //   6452: ireturn
/*     */     //   6453: iconst_0
/*     */     //   6454: ireturn
/*     */     // Line number table:
/*     */     //   Java source line number -> byte code offset
/*     */     //   #412	-> 189
/*     */     //   #63	-> 214
/*     */     //   #194	-> 222
/*     */     //   #5	-> 282
/*     */     //   #168	-> 305
/*     */     //   #225	-> 334
/*     */     //   #366	-> 341
/*     */     //   #190	-> 349
/*     */     //   #248	-> 351
/*     */     //   #258	-> 1327
/*     */     //   #304	-> 1383
/*     */     //   #172	-> 1391
/*     */     //   #101	-> 1410
/*     */     //   #331	-> 1418
/*     */     //   #130	-> 1426
/*     */     //   #300	-> 1445
/*     */     //   #413	-> 1453
/*     */     //   #450	-> 1495
/*     */     //   #427	-> 1503
/*     */     //   #315	-> 1522
/*     */     //   #11	-> 1530
/*     */     //   #47	-> 1572
/*     */     //   #253	-> 1580
/*     */     //   #179	-> 1599
/*     */     //   #117	-> 1607
/*     */     //   #133	-> 1615
/*     */     //   #58	-> 1634
/*     */     //   #52	-> 1642
/*     */     //   #138	-> 1684
/*     */     //   #109	-> 1692
/*     */     //   #204	-> 1711
/*     */     //   #312	-> 1719
/*     */     //   #351	-> 1761
/*     */     //   #302	-> 1769
/*     */     //   #280	-> 1788
/*     */     //   #221	-> 1796
/*     */     //   #173	-> 1838
/*     */     //   #391	-> 1846
/*     */     //   #13	-> 1865
/*     */     //   #111	-> 1873
/*     */     //   #267	-> 1915
/*     */     //   #313	-> 1923
/*     */     //   #24	-> 1942
/*     */     //   #211	-> 1950
/*     */     //   #149	-> 1958
/*     */     //   #352	-> 1977
/*     */     //   #136	-> 1985
/*     */     //   #45	-> 2027
/*     */     //   #437	-> 2035
/*     */     //   #365	-> 2054
/*     */     //   #185	-> 2062
/*     */     //   #114	-> 2085
/*     */     //   #34	-> 2093
/*     */     //   #242	-> 2112
/*     */     //   #444	-> 2120
/*     */     //   #378	-> 2189
/*     */     //   #320	-> 2197
/*     */     //   #8	-> 2216
/*     */     //   #38	-> 2224
/*     */     //   #319	-> 2232
/*     */     //   #166	-> 2251
/*     */     //   #408	-> 2259
/*     */     //   #249	-> 2261
/*     */     //   #454	-> 2303
/*     */     //   #188	-> 2323
/*     */     //   #373	-> 2336
/*     */     //   #342	-> 2362
/*     */     //   #50	-> 2387
/*     */     //   #245	-> 2406
/*     */     //   #268	-> 2464
/*     */     //   #332	-> 2483
/*     */     //   #30	-> 2519
/*     */     //   #84	-> 2534
/*     */     //   #420	-> 2547
/*     */     //   #132	-> 2555
/*     */     //   #348	-> 2567
/*     */     //   #3	-> 2578
/*     */     //   #176	-> 2583
/*     */     //   #163	-> 2588
/*     */     //   #337	-> 2619
/*     */     //   #277	-> 2632
/*     */     //   #44	-> 2662
/*     */     //   #456	-> 2686
/*     */     //   #212	-> 2694
/*     */     //   #458	-> 2696
/*     */     //   #363	-> 2738
/*     */     //   #405	-> 2758
/*     */     //   #65	-> 2771
/*     */     //   #29	-> 2797
/*     */     //   #236	-> 2817
/*     */     //   #278	-> 2830
/*     */     //   #286	-> 2841
/*     */     //   #100	-> 2860
/*     */     //   #2	-> 2884
/*     */     //   #251	-> 2930
/*     */     //   #241	-> 2938
/*     */     //   #115	-> 2977
/*     */     //   #264	-> 3015
/*     */     //   #118	-> 3048
/*     */     //   #192	-> 3061
/*     */     //   #380	-> 3069
/*     */     //   #438	-> 3077
/*     */     //   #218	-> 3079
/*     */     //   #51	-> 3121
/*     */     //   #441	-> 3141
/*     */     //   #404	-> 3154
/*     */     //   #306	-> 3180
/*     */     //   #193	-> 3200
/*     */     //   #213	-> 3213
/*     */     //   #74	-> 3239
/*     */     //   #107	-> 3259
/*     */     //   #46	-> 3275
/*     */     //   #358	-> 3281
/*     */     //   #78	-> 3307
/*     */     //   #345	-> 3325
/*     */     //   #23	-> 3349
/*     */     //   #31	-> 3389
/*     */     //   #141	-> 3391
/*     */     //   #77	-> 3444
/*     */     //   #417	-> 3473
/*     */     //   #57	-> 3497
/*     */     //   #424	-> 3516
/*     */     //   #86	-> 3529
/*     */     //   #257	-> 3537
/*     */     //   #230	-> 3556
/*     */     //   #203	-> 3569
/*     */     //   #455	-> 3588
/*     */     //   #360	-> 3601
/*     */     //   #390	-> 3609
/*     */     //   #359	-> 3611
/*     */     //   #289	-> 3627
/*     */     //   #250	-> 3651
/*     */     //   #37	-> 3704
/*     */     //   #426	-> 3733
/*     */     //   #353	-> 3757
/*     */     //   #61	-> 3770
/*     */     //   #324	-> 3782
/*     */     //   #452	-> 3790
/*     */     //   #81	-> 3809
/*     */     //   #70	-> 3817
/*     */     //   #64	-> 3819
/*     */     //   #428	-> 3839
/*     */     //   #180	-> 3841
/*     */     //   #433	-> 3883
/*     */     //   #425	-> 3903
/*     */     //   #156	-> 3916
/*     */     //   #407	-> 3942
/*     */     //   #314	-> 3962
/*     */     //   #88	-> 3975
/*     */     //   #235	-> 4001
/*     */     //   #95	-> 4021
/*     */     //   #261	-> 4037
/*     */     //   #12	-> 4055
/*     */     //   #228	-> 4079
/*     */     //   #386	-> 4119
/*     */     //   #273	-> 4132
/*     */     //   #144	-> 4183
/*     */     //   #283	-> 4191
/*     */     //   #35	-> 4239
/*     */     //   #85	-> 4248
/*     */     //   #224	-> 4256
/*     */     //   #375	-> 4269
/*     */     //   #207	-> 4306
/*     */     //   #72	-> 4314
/*     */     //   #240	-> 4331
/*     */     //   #338	-> 4333
/*     */     //   #252	-> 4375
/*     */     //   #383	-> 4395
/*     */     //   #189	-> 4408
/*     */     //   #419	-> 4434
/*     */     //   #94	-> 4454
/*     */     //   #326	-> 4467
/*     */     //   #270	-> 4478
/*     */     //   #62	-> 4497
/*     */     //   #21	-> 4519
/*     */     //   #174	-> 4531
/*     */     //   #374	-> 4535
/*     */     //   #394	-> 4543
/*     */     //   #339	-> 4545
/*     */     //   #208	-> 4587
/*     */     //   #198	-> 4607
/*     */     //   #303	-> 4620
/*     */     //   #59	-> 4646
/*     */     //   #449	-> 4666
/*     */     //   #125	-> 4679
/*     */     //   #247	-> 4690
/*     */     //   #66	-> 4709
/*     */     //   #196	-> 4734
/*     */     //   #328	-> 4742
/*     */     //   #432	-> 4744
/*     */     //   #53	-> 4786
/*     */     //   #36	-> 4806
/*     */     //   #325	-> 4819
/*     */     //   #60	-> 4845
/*     */     //   #92	-> 4865
/*     */     //   #4	-> 4878
/*     */     //   #396	-> 4904
/*     */     //   #32	-> 4912
/*     */     //   #157	-> 4960
/*     */     //   #169	-> 4968
/*     */     //   #263	-> 4973
/*     */     //   #367	-> 5283
/*     */     //   #290	-> 5297
/*     */     //   #368	-> 5316
/*     */     //   #214	-> 5327
/*     */     //   #231	-> 5346
/*     */     //   #460	-> 5360
/*     */     //   #178	-> 5379
/*     */     //   #321	-> 5399
/*     */     //   #434	-> 5415
/*     */     //   #177	-> 5423
/*     */     //   #297	-> 5471
/*     */     //   #226	-> 5479
/*     */     //   #281	-> 5481
/*     */     //   #150	-> 5523
/*     */     //   #54	-> 5543
/*     */     //   #416	-> 5556
/*     */     //   #123	-> 5582
/*     */     //   #116	-> 5614
/*     */     //   #25	-> 5639
/*     */     //   #153	-> 5658
/*     */     //   #371	-> 5684
/*     */     //   #431	-> 5706
/*     */     //   #165	-> 5714
/*     */     //   #26	-> 5733
/*     */     //   #220	-> 5768
/*     */     //   #459	-> 5798
/*     */     //   #272	-> 5821
/*     */     //   #202	-> 5829
/*     */     //   #446	-> 5836
/*     */     //   #135	-> 5895
/*     */     //   #119	-> 5951
/*     */     //   #453	-> 5981
/*     */     //   #384	-> 5994
/*     */     //   #87	-> 6023
/*     */     //   #91	-> 6053
/*     */     //   #222	-> 6076
/*     */     //   #243	-> 6084
/*     */     //   #48	-> 6091
/*     */     //   #296	-> 6099
/*     */     //   #442	-> 6101
/*     */     //   #216	-> 6143
/*     */     //   #49	-> 6163
/*     */     //   #28	-> 6179
/*     */     //   #143	-> 6225
/*     */     //   #239	-> 6242
/*     */     //   #106	-> 6259
/*     */     //   #362	-> 6267
/*     */     //   #112	-> 6286
/*     */     //   #443	-> 6294
/*     */     //   #232	-> 6296
/*     */     //   #310	-> 6309
/*     */     //   #340	-> 6322
/*     */     //   #421	-> 6364
/*     */     //   #39	-> 6384
/*     */     //   #376	-> 6400
/*     */     //   #104	-> 6412
/*     */     //   #423	-> 6415
/*     */     //   #96	-> 6422
/*     */     //   #191	-> 6451
/*     */     //   #139	-> 6453
/*     */     // Exception table:
/*     */     //   from	to	target	type
/*     */     //   189	200	203	aacinternal/v
/*     */     //   363	480	480	aacinternal/v
/*     */     //   373	515	518	aacinternal/v
/*     */     //   491	532	535	aacinternal/v
/*     */     //   549	578	581	aacinternal/v
/*     */     //   554	595	598	aacinternal/v
/*     */     //   612	641	644	aacinternal/v
/*     */     //   617	658	661	aacinternal/v
/*     */     //   675	704	707	aacinternal/v
/*     */     //   680	721	724	aacinternal/v
/*     */     //   738	767	770	aacinternal/v
/*     */     //   743	784	787	aacinternal/v
/*     */     //   801	830	833	aacinternal/v
/*     */     //   806	847	850	aacinternal/v
/*     */     //   864	893	896	aacinternal/v
/*     */     //   869	910	913	aacinternal/v
/*     */     //   928	957	960	aacinternal/v
/*     */     //   933	974	977	aacinternal/v
/*     */     //   992	1021	1024	aacinternal/v
/*     */     //   997	1038	1041	aacinternal/v
/*     */     //   1056	1085	1088	aacinternal/v
/*     */     //   1061	1102	1105	aacinternal/v
/*     */     //   1120	1149	1152	aacinternal/v
/*     */     //   1125	1166	1169	aacinternal/v
/*     */     //   1184	1213	1216	aacinternal/v
/*     */     //   1189	1230	1233	aacinternal/v
/*     */     //   1250	1316	1316	aacinternal/v
/*     */     //   1255	1352	1355	aacinternal/v
/*     */     //   1327	1369	1372	aacinternal/v
/*     */     //   1473	1481	1484	aacinternal/v
/*     */     //   1550	1558	1561	aacinternal/v
/*     */     //   1662	1670	1673	aacinternal/v
/*     */     //   1739	1747	1750	aacinternal/v
/*     */     //   1816	1824	1827	aacinternal/v
/*     */     //   1893	1901	1904	aacinternal/v
/*     */     //   2005	2013	2016	aacinternal/v
/*     */     //   2120	2158	2161	aacinternal/v
/*     */     //   2133	2175	2178	aacinternal/v
/*     */     //   2261	2289	2292	aacinternal/v
/*     */     //   2286	2325	2325	aacinternal/v
/*     */     //   2339	2348	2351	aacinternal/v
/*     */     //   2344	2363	2366	aacinternal/v
/*     */     //   2406	2433	2436	aacinternal/v
/*     */     //   2411	2450	2453	aacinternal/v
/*     */     //   2478	2500	2503	aacinternal/v
/*     */     //   2619	2672	2675	aacinternal/v
/*     */     //   2696	2724	2727	aacinternal/v
/*     */     //   2721	2760	2760	aacinternal/v
/*     */     //   2774	2783	2786	aacinternal/v
/*     */     //   2779	2819	2819	aacinternal/v
/*     */     //   2860	2870	2873	aacinternal/v
/*     */     //   2938	2963	2966	aacinternal/v
/*     */     //   2943	2996	2999	aacinternal/v
/*     */     //   3010	3034	3037	aacinternal/v
/*     */     //   3079	3107	3110	aacinternal/v
/*     */     //   3104	3143	3143	aacinternal/v
/*     */     //   3158	3166	3169	aacinternal/v
/*     */     //   3163	3202	3202	aacinternal/v
/*     */     //   3216	3225	3228	aacinternal/v
/*     */     //   3221	3260	3263	aacinternal/v
/*     */     //   3281	3293	3296	aacinternal/v
/*     */     //   3325	3335	3338	aacinternal/v
/*     */     //   3444	3483	3486	aacinternal/v
/*     */     //   3627	3637	3640	aacinternal/v
/*     */     //   3704	3743	3746	aacinternal/v
/*     */     //   3841	3869	3872	aacinternal/v
/*     */     //   3866	3905	3905	aacinternal/v
/*     */     //   3919	3928	3931	aacinternal/v
/*     */     //   3925	3964	3964	aacinternal/v
/*     */     //   3975	3984	3987	aacinternal/v
/*     */     //   3998	4022	4025	aacinternal/v
/*     */     //   4055	4065	4068	aacinternal/v
/*     */     //   4062	4121	4121	aacinternal/v
/*     */     //   4333	4361	4364	aacinternal/v
/*     */     //   4358	4397	4397	aacinternal/v
/*     */     //   4411	4420	4423	aacinternal/v
/*     */     //   4416	4456	4456	aacinternal/v
/*     */     //   4545	4573	4576	aacinternal/v
/*     */     //   4570	4609	4609	aacinternal/v
/*     */     //   4623	4632	4635	aacinternal/v
/*     */     //   4628	4668	4668	aacinternal/v
/*     */     //   4744	4772	4775	aacinternal/v
/*     */     //   4769	4808	4808	aacinternal/v
/*     */     //   4822	4831	4834	aacinternal/v
/*     */     //   4828	4867	4867	aacinternal/v
/*     */     //   4878	4887	4890	aacinternal/v
/*     */     //   4912	4975	4978	aacinternal/v
/*     */     //   4999	5044	5044	aacinternal/v
/*     */     //   5009	5079	5082	aacinternal/v
/*     */     //   5055	5096	5099	aacinternal/v
/*     */     //   5113	5142	5145	aacinternal/v
/*     */     //   5118	5159	5162	aacinternal/v
/*     */     //   5176	5205	5208	aacinternal/v
/*     */     //   5181	5222	5225	aacinternal/v
/*     */     //   5241	5272	5272	aacinternal/v
/*     */     //   5246	5302	5305	aacinternal/v
/*     */     //   5283	5332	5335	aacinternal/v
/*     */     //   5316	5365	5368	aacinternal/v
/*     */     //   5346	5400	5403	aacinternal/v
/*     */     //   5481	5509	5512	aacinternal/v
/*     */     //   5506	5545	5545	aacinternal/v
/*     */     //   5559	5568	5571	aacinternal/v
/*     */     //   5564	5600	5603	aacinternal/v
/*     */     //   5582	5615	5618	aacinternal/v
/*     */     //   5658	5692	5695	aacinternal/v
/*     */     //   5714	5754	5757	aacinternal/v
/*     */     //   5821	5859	5862	aacinternal/v
/*     */     //   5841	5878	5881	aacinternal/v
/*     */     //   5892	5908	5911	aacinternal/v
/*     */     //   5951	6004	6007	aacinternal/v
/*     */     //   6101	6129	6132	aacinternal/v
/*     */     //   6126	6164	6167	aacinternal/v
/*     */     //   6296	6311	6311	aacinternal/v
/*     */     //   6322	6350	6353	aacinternal/v
/*     */     //   6347	6385	6388	aacinternal/v
/*     */   }
/*     */   
/*     */   private BaseComponent a(CommandSender paramCommandSender, long paramLong) {
/*     */     // Byte code:
/*     */     //   0: getstatic me/konsolas/aac/mi.g : J
/*     */     //   3: lload_2
/*     */     //   4: lxor
/*     */     //   5: lstore_2
/*     */     //   6: ldc2_w 2260920445956353941
/*     */     //   9: lload_2
/*     */     //   10: <illegal opcode> w : (JJ)I
/*     */     //   15: new net/md_5/bungee/api/chat/TextComponent
/*     */     //   18: dup
/*     */     //   19: sipush #22751
/*     */     //   22: ldc2_w 1875076980312515418
/*     */     //   25: lload_2
/*     */     //   26: lxor
/*     */     //   27: <illegal opcode> e : (IJ)Ljava/lang/String;
/*     */     //   32: invokespecial <init> : (Ljava/lang/String;)V
/*     */     //   35: astore #5
/*     */     //   37: istore #4
/*     */     //   39: aload #5
/*     */     //   41: new net/md_5/bungee/api/chat/ClickEvent
/*     */     //   44: dup
/*     */     //   45: getstatic net/md_5/bungee/api/chat/ClickEvent$Action.RUN_COMMAND : Lnet/md_5/bungee/api/chat/ClickEvent$Action;
/*     */     //   48: sipush #11721
/*     */     //   51: ldc2_w 851693422341936875
/*     */     //   54: lload_2
/*     */     //   55: lxor
/*     */     //   56: <illegal opcode> e : (IJ)Ljava/lang/String;
/*     */     //   61: invokespecial <init> : (Lnet/md_5/bungee/api/chat/ClickEvent$Action;Ljava/lang/String;)V
/*     */     //   64: invokevirtual setClickEvent : (Lnet/md_5/bungee/api/chat/ClickEvent;)V
/*     */     //   67: aload #5
/*     */     //   69: iload #4
/*     */     //   71: ifeq -> 171
/*     */     //   74: new net/md_5/bungee/api/chat/HoverEvent
/*     */     //   77: dup
/*     */     //   78: getstatic net/md_5/bungee/api/chat/HoverEvent$Action.SHOW_TEXT : Lnet/md_5/bungee/api/chat/HoverEvent$Action;
/*     */     //   81: iconst_1
/*     */     //   82: anewarray net/md_5/bungee/api/chat/BaseComponent
/*     */     //   85: dup
/*     */     //   86: iconst_0
/*     */     //   87: new net/md_5/bungee/api/chat/TextComponent
/*     */     //   90: dup
/*     */     //   91: sipush #24392
/*     */     //   94: ldc2_w 3902871758836409398
/*     */     //   97: lload_2
/*     */     //   98: lxor
/*     */     //   99: <illegal opcode> e : (IJ)Ljava/lang/String;
/*     */     //   104: invokespecial <init> : (Ljava/lang/String;)V
/*     */     //   107: aastore
/*     */     //   108: invokespecial <init> : (Lnet/md_5/bungee/api/chat/HoverEvent$Action;[Lnet/md_5/bungee/api/chat/BaseComponent;)V
/*     */     //   111: invokevirtual setHoverEvent : (Lnet/md_5/bungee/api/chat/HoverEvent;)V
/*     */     //   114: aload_1
/*     */     //   115: instanceof org/bukkit/entity/Player
/*     */     //   118: ifeq -> 156
/*     */     //   121: goto -> 134
/*     */     //   124: ldc2_w 2208680226243457805
/*     */     //   127: lload_2
/*     */     //   128: <illegal opcode> w : (Ljava/lang/Throwable;JJ)Ljava/lang/Throwable;
/*     */     //   133: athrow
/*     */     //   134: aload_1
/*     */     //   135: sipush #1517
/*     */     //   138: ldc2_w 1255724302478704294
/*     */     //   141: lload_2
/*     */     //   142: lxor
/*     */     //   143: <illegal opcode> e : (IJ)Ljava/lang/String;
/*     */     //   148: invokeinterface hasPermission : (Ljava/lang/String;)Z
/*     */     //   153: ifne -> 178
/*     */     //   156: aload #5
/*     */     //   158: goto -> 171
/*     */     //   161: ldc2_w 2208680226243457805
/*     */     //   164: lload_2
/*     */     //   165: <illegal opcode> w : (Ljava/lang/Throwable;JJ)Ljava/lang/Throwable;
/*     */     //   170: athrow
/*     */     //   171: iconst_1
/*     */     //   172: invokestatic valueOf : (Z)Ljava/lang/Boolean;
/*     */     //   175: invokevirtual setStrikethrough : (Ljava/lang/Boolean;)V
/*     */     //   178: aload #5
/*     */     //   180: areturn
/*     */     // Line number table:
/*     */     //   Java source line number -> byte code offset
/*     */     //   #414	-> 15
/*     */     //   #275	-> 39
/*     */     //   #184	-> 67
/*     */     //   #83	-> 114
/*     */     //   #223	-> 156
/*     */     //   #379	-> 178
/*     */     // Exception table:
/*     */     //   from	to	target	type
/*     */     //   39	121	124	aacinternal/v
/*     */     //   134	158	161	aacinternal/v
/*     */   }
/*     */   
/*     */   private void a(CommandSender paramCommandSender, OfflinePlayer paramOfflinePlayer, byte paramByte, long paramLong) {
/*     */     // Byte code:
/*     */     //   0: iload_3
/*     */     //   1: i2l
/*     */     //   2: bipush #56
/*     */     //   4: lshl
/*     */     //   5: lload #4
/*     */     //   7: bipush #8
/*     */     //   9: lshl
/*     */     //   10: bipush #8
/*     */     //   12: lushr
/*     */     //   13: lor
/*     */     //   14: getstatic me/konsolas/aac/mi.g : J
/*     */     //   17: lxor
/*     */     //   18: lstore #6
/*     */     //   20: lload #6
/*     */     //   22: dup2
/*     */     //   23: ldc2_w 121756441567792
/*     */     //   26: lxor
/*     */     //   27: lstore #8
/*     */     //   29: dup2
/*     */     //   30: ldc2_w 129176814789498
/*     */     //   33: lxor
/*     */     //   34: lstore #10
/*     */     //   36: dup2
/*     */     //   37: ldc2_w 98200377455832
/*     */     //   40: lxor
/*     */     //   41: lstore #12
/*     */     //   43: dup2
/*     */     //   44: ldc2_w 41905438136576
/*     */     //   47: lxor
/*     */     //   48: lstore #14
/*     */     //   50: pop2
/*     */     //   51: aload_0
/*     */     //   52: lload #12
/*     */     //   54: invokespecial a : (J)Lnet/md_5/bungee/api/chat/BaseComponent;
/*     */     //   57: astore #17
/*     */     //   59: ldc2_w -3694917106882097355
/*     */     //   62: lload #6
/*     */     //   64: <illegal opcode> w : (JJ)I
/*     */     //   69: aload #17
/*     */     //   71: aload_0
/*     */     //   72: aload_2
/*     */     //   73: lload #14
/*     */     //   75: invokespecial a : (Lorg/bukkit/OfflinePlayer;J)Lnet/md_5/bungee/api/chat/BaseComponent;
/*     */     //   78: invokevirtual addExtra : (Lnet/md_5/bungee/api/chat/BaseComponent;)V
/*     */     //   81: istore #16
/*     */     //   83: iload #16
/*     */     //   85: ifne -> 168
/*     */     //   88: aload_2
/*     */     //   89: invokeinterface isOnline : ()Z
/*     */     //   94: ifeq -> 160
/*     */     //   97: goto -> 111
/*     */     //   100: ldc2_w -3605721797516304290
/*     */     //   103: lload #6
/*     */     //   105: <illegal opcode> w : (Ljava/lang/Throwable;JJ)Ljava/lang/Throwable;
/*     */     //   110: athrow
/*     */     //   111: aload #17
/*     */     //   113: sipush #16333
/*     */     //   116: ldc2_w 718546356909610890
/*     */     //   119: lload #6
/*     */     //   121: lxor
/*     */     //   122: <illegal opcode> e : (IJ)Ljava/lang/String;
/*     */     //   127: invokevirtual addExtra : (Ljava/lang/String;)V
/*     */     //   130: aload #17
/*     */     //   132: aload_0
/*     */     //   133: aload_2
/*     */     //   134: checkcast org/bukkit/entity/Player
/*     */     //   137: lload #10
/*     */     //   139: aload_1
/*     */     //   140: invokespecial a : (Lorg/bukkit/entity/Player;JLorg/bukkit/command/CommandSender;)Lnet/md_5/bungee/api/chat/BaseComponent;
/*     */     //   143: invokevirtual addExtra : (Lnet/md_5/bungee/api/chat/BaseComponent;)V
/*     */     //   146: goto -> 160
/*     */     //   149: ldc2_w -3605721797516304290
/*     */     //   152: lload #6
/*     */     //   154: <illegal opcode> w : (Ljava/lang/Throwable;JJ)Ljava/lang/Throwable;
/*     */     //   159: athrow
/*     */     //   160: aload_1
/*     */     //   161: aload #17
/*     */     //   163: lload #8
/*     */     //   165: invokestatic a : (Lorg/bukkit/command/CommandSender;Lnet/md_5/bungee/api/chat/BaseComponent;J)V
/*     */     //   168: return
/*     */     // Line number table:
/*     */     //   Java source line number -> byte code offset
/*     */     //   #422	-> 51
/*     */     //   #126	-> 69
/*     */     //   #205	-> 83
/*     */     //   #294	-> 111
/*     */     //   #129	-> 130
/*     */     //   #105	-> 160
/*     */     //   #16	-> 168
/*     */     // Exception table:
/*     */     //   from	to	target	type
/*     */     //   83	97	100	aacinternal/v
/*     */     //   88	146	149	aacinternal/v
/*     */   }
/*     */   
/*     */   public void a(long paramLong, OfflinePlayer paramOfflinePlayer) {
/*     */     // Byte code:
/*     */     //   0: getstatic me/konsolas/aac/mi.g : J
/*     */     //   3: lload_1
/*     */     //   4: lxor
/*     */     //   5: lstore_1
/*     */     //   6: lload_1
/*     */     //   7: dup2
/*     */     //   8: ldc2_w 16807502623093
/*     */     //   11: lxor
/*     */     //   12: dup2
/*     */     //   13: bipush #56
/*     */     //   15: lushr
/*     */     //   16: l2i
/*     */     //   17: istore #4
/*     */     //   19: dup2
/*     */     //   20: bipush #8
/*     */     //   22: lshl
/*     */     //   23: bipush #8
/*     */     //   25: lushr
/*     */     //   26: lstore #5
/*     */     //   28: pop2
/*     */     //   29: dup2
/*     */     //   30: ldc2_w 62332819636527
/*     */     //   33: lxor
/*     */     //   34: dup2
/*     */     //   35: bipush #48
/*     */     //   37: lushr
/*     */     //   38: l2i
/*     */     //   39: istore #7
/*     */     //   41: dup2
/*     */     //   42: bipush #16
/*     */     //   44: lshl
/*     */     //   45: bipush #16
/*     */     //   47: lushr
/*     */     //   48: lstore #8
/*     */     //   50: pop2
/*     */     //   51: dup2
/*     */     //   52: ldc2_w 88587592292831
/*     */     //   55: lxor
/*     */     //   56: lstore #10
/*     */     //   58: pop2
/*     */     //   59: ldc2_w 3517318417233523548
/*     */     //   62: lload_1
/*     */     //   63: <illegal opcode> w : (JJ)I
/*     */     //   68: aload_0
/*     */     //   69: getfield b : Lme/konsolas/aac/AAC;
/*     */     //   72: invokevirtual a : ()Lme/konsolas/aac/fv;
/*     */     //   75: aload_3
/*     */     //   76: iload #7
/*     */     //   78: i2s
/*     */     //   79: lload #8
/*     */     //   81: invokevirtual a : (Lorg/bukkit/OfflinePlayer;SJ)Lme/konsolas/aac/jX;
/*     */     //   84: invokevirtual a : ()Lme/konsolas/aac/e6;
/*     */     //   87: astore #13
/*     */     //   89: istore #12
/*     */     //   91: invokestatic getOnlinePlayers : ()Ljava/util/Collection;
/*     */     //   94: invokeinterface iterator : ()Ljava/util/Iterator;
/*     */     //   99: astore #14
/*     */     //   101: aload #14
/*     */     //   103: invokeinterface hasNext : ()Z
/*     */     //   108: ifeq -> 269
/*     */     //   111: aload #14
/*     */     //   113: invokeinterface next : ()Ljava/lang/Object;
/*     */     //   118: checkcast org/bukkit/entity/Player
/*     */     //   121: astore #15
/*     */     //   123: aload #15
/*     */     //   125: sipush #14999
/*     */     //   128: ldc2_w 2076602921366908590
/*     */     //   131: lload_1
/*     */     //   132: lxor
/*     */     //   133: <illegal opcode> e : (IJ)Ljava/lang/String;
/*     */     //   138: invokeinterface hasPermission : (Ljava/lang/String;)Z
/*     */     //   143: iload #12
/*     */     //   145: lload_1
/*     */     //   146: lconst_0
/*     */     //   147: lcmp
/*     */     //   148: ifle -> 298
/*     */     //   151: ifne -> 296
/*     */     //   154: iload #12
/*     */     //   156: ifne -> 249
/*     */     //   159: goto -> 172
/*     */     //   162: ldc2_w 3574984137490799671
/*     */     //   165: lload_1
/*     */     //   166: <illegal opcode> w : (Ljava/lang/Throwable;JJ)Ljava/lang/Throwable;
/*     */     //   171: athrow
/*     */     //   172: lload_1
/*     */     //   173: lconst_0
/*     */     //   174: lcmp
/*     */     //   175: ifle -> 266
/*     */     //   178: ifeq -> 264
/*     */     //   181: goto -> 194
/*     */     //   184: ldc2_w 3574984137490799671
/*     */     //   187: lload_1
/*     */     //   188: <illegal opcode> w : (Ljava/lang/Throwable;JJ)Ljava/lang/Throwable;
/*     */     //   193: athrow
/*     */     //   194: aload_0
/*     */     //   195: iload #12
/*     */     //   197: ifne -> 253
/*     */     //   200: goto -> 213
/*     */     //   203: ldc2_w 3574984137490799671
/*     */     //   206: lload_1
/*     */     //   207: <illegal opcode> w : (Ljava/lang/Throwable;JJ)Ljava/lang/Throwable;
/*     */     //   212: athrow
/*     */     //   213: getfield d : Ljava/util/Map;
/*     */     //   216: aload #15
/*     */     //   218: getstatic me/konsolas/aac/dh.NORMAL : Lme/konsolas/aac/dh;
/*     */     //   221: invokeinterface getOrDefault : (Ljava/lang/Object;Ljava/lang/Object;)Ljava/lang/Object;
/*     */     //   226: checkcast me/konsolas/aac/dh
/*     */     //   229: lload #10
/*     */     //   231: aload #13
/*     */     //   233: invokevirtual a : (JLme/konsolas/aac/e6;)Z
/*     */     //   236: goto -> 249
/*     */     //   239: ldc2_w 3574984137490799671
/*     */     //   242: lload_1
/*     */     //   243: <illegal opcode> w : (Ljava/lang/Throwable;JJ)Ljava/lang/Throwable;
/*     */     //   248: athrow
/*     */     //   249: ifeq -> 264
/*     */     //   252: aload_0
/*     */     //   253: aload #15
/*     */     //   255: aload_3
/*     */     //   256: iload #4
/*     */     //   258: i2b
/*     */     //   259: lload #5
/*     */     //   261: invokespecial a : (Lorg/bukkit/command/CommandSender;Lorg/bukkit/OfflinePlayer;BJ)V
/*     */     //   264: iload #12
/*     */     //   266: ifeq -> 101
/*     */     //   269: invokestatic getConsoleSender : ()Lorg/bukkit/command/ConsoleCommandSender;
/*     */     //   272: lload_1
/*     */     //   273: lconst_0
/*     */     //   274: lcmp
/*     */     //   275: iflt -> 118
/*     */     //   278: sipush #20319
/*     */     //   281: ldc2_w 8480810410351631148
/*     */     //   284: lload_1
/*     */     //   285: lxor
/*     */     //   286: <illegal opcode> e : (IJ)Ljava/lang/String;
/*     */     //   291: invokeinterface hasPermission : (Ljava/lang/String;)Z
/*     */     //   296: iload #12
/*     */     //   298: ifne -> 373
/*     */     //   301: ifeq -> 389
/*     */     //   304: goto -> 317
/*     */     //   307: ldc2_w 3574984137490799671
/*     */     //   310: lload_1
/*     */     //   311: <illegal opcode> w : (Ljava/lang/Throwable;JJ)Ljava/lang/Throwable;
/*     */     //   316: athrow
/*     */     //   317: aload_0
/*     */     //   318: iload #12
/*     */     //   320: ifne -> 377
/*     */     //   323: goto -> 336
/*     */     //   326: ldc2_w 3574984137490799671
/*     */     //   329: lload_1
/*     */     //   330: <illegal opcode> w : (Ljava/lang/Throwable;JJ)Ljava/lang/Throwable;
/*     */     //   335: athrow
/*     */     //   336: getfield d : Ljava/util/Map;
/*     */     //   339: invokestatic getConsoleSender : ()Lorg/bukkit/command/ConsoleCommandSender;
/*     */     //   342: getstatic me/konsolas/aac/dh.NORMAL : Lme/konsolas/aac/dh;
/*     */     //   345: invokeinterface getOrDefault : (Ljava/lang/Object;Ljava/lang/Object;)Ljava/lang/Object;
/*     */     //   350: checkcast me/konsolas/aac/dh
/*     */     //   353: lload #10
/*     */     //   355: aload #13
/*     */     //   357: invokevirtual a : (JLme/konsolas/aac/e6;)Z
/*     */     //   360: goto -> 373
/*     */     //   363: ldc2_w 3574984137490799671
/*     */     //   366: lload_1
/*     */     //   367: <illegal opcode> w : (Ljava/lang/Throwable;JJ)Ljava/lang/Throwable;
/*     */     //   372: athrow
/*     */     //   373: ifeq -> 389
/*     */     //   376: aload_0
/*     */     //   377: invokestatic getConsoleSender : ()Lorg/bukkit/command/ConsoleCommandSender;
/*     */     //   380: aload_3
/*     */     //   381: iload #4
/*     */     //   383: i2b
/*     */     //   384: lload #5
/*     */     //   386: invokespecial a : (Lorg/bukkit/command/CommandSender;Lorg/bukkit/OfflinePlayer;BJ)V
/*     */     //   389: lload_1
/*     */     //   390: lconst_0
/*     */     //   391: lcmp
/*     */     //   392: iflt -> 421
/*     */     //   395: ldc2_w 3469513283178689669
/*     */     //   398: lload_1
/*     */     //   399: <illegal opcode> w : (JJ)[Lme/konsolas/aac/aN;
/*     */     //   404: ifnull -> 434
/*     */     //   407: iinc #12, 1
/*     */     //   410: iload #12
/*     */     //   412: ldc2_w 3579137994941304151
/*     */     //   415: lload_1
/*     */     //   416: <illegal opcode> w : (IJJ)V
/*     */     //   421: goto -> 434
/*     */     //   424: ldc2_w 3574984137490799671
/*     */     //   427: lload_1
/*     */     //   428: <illegal opcode> w : (Ljava/lang/Throwable;JJ)Ljava/lang/Throwable;
/*     */     //   433: athrow
/*     */     //   434: return
/*     */     // Line number table:
/*     */     //   Java source line number -> byte code offset
/*     */     //   #457	-> 68
/*     */     //   #128	-> 91
/*     */     //   #461	-> 123
/*     */     //   #377	-> 221
/*     */     //   #462	-> 252
/*     */     //   #142	-> 264
/*     */     //   #229	-> 269
/*     */     //   #285	-> 339
/*     */     //   #14	-> 376
/*     */     //   #159	-> 389
/*     */     // Exception table:
/*     */     //   from	to	target	type
/*     */     //   123	159	162	aacinternal/v
/*     */     //   154	181	184	aacinternal/v
/*     */     //   172	200	203	aacinternal/v
/*     */     //   194	236	239	aacinternal/v
/*     */     //   296	304	307	aacinternal/v
/*     */     //   301	323	326	aacinternal/v
/*     */     //   317	360	363	aacinternal/v
/*     */     //   389	421	424	aacinternal/v
/*     */   }
/*     */   
/*     */   private static Throwable a(Throwable paramThrowable) {
/*     */     return paramThrowable;
/*     */   }
/*     */   
/*     */   private static String a(byte[] paramArrayOfbyte) {
/*     */     byte b1 = 0;
/*     */     int i;
/*     */     char[] arrayOfChar = new char[i = paramArrayOfbyte.length];
/*     */     for (byte b2 = 0; b2 < i; b2++) {
/*     */       int j;
/*     */       if ((j = 0xFF & paramArrayOfbyte[b2]) < 192) {
/*     */         arrayOfChar[b1++] = (char)j;
/*     */       } else if (j < 224) {
/*     */         char c = (char)((char)(j & 0x1F) << 6);
/*     */         j = paramArrayOfbyte[++b2];
/*     */         c = (char)(c | (char)(j & 0x3F));
/*     */         arrayOfChar[b1++] = c;
/*     */       } else if (b2 < i - 2) {
/*     */         char c = (char)((char)(j & 0xF) << 12);
/*     */         j = paramArrayOfbyte[++b2];
/*     */         c = (char)(c | (char)(j & 0x3F) << 6);
/*     */         j = paramArrayOfbyte[++b2];
/*     */         c = (char)(c | (char)(j & 0x3F));
/*     */         arrayOfChar[b1++] = c;
/*     */       } 
/*     */     } 
/*     */     return new String(arrayOfChar, 0, b1);
/*     */   }
/*     */   
/*     */   private static String a(int paramInt, long paramLong) {
/*     */     int i = paramInt ^ (int)(paramLong & 0x7FFFL) ^ 0x6561;
/*     */     if (i[i] == null) {
/*     */       Object[] arrayOfObject;
/*     */       try {
/*     */         Long long_ = Long.valueOf(Thread.currentThread().getId());
/*     */         arrayOfObject = (Object[])j.get(long_);
/*     */         if (arrayOfObject == null) {
/*     */           arrayOfObject = new Object[3];
/*     */           "彨⫭蘛䥚㵘ዲ눓甗봐嘋筯쑫塚ꮰⓦ⁉낛ϋ흆奊盉".toCharArray()[18] = (char)("彨⫭蘛䥚㵘ዲ눓甗봐嘋筯쑫塚ꮰⓦ⁉낛ϋ흆奊盉".toCharArray()[18] ^ 0x7EA3);
/*     */           arrayOfObject[0] = Cipher.getInstance(fW$gy.A("彨⫭蘛䥚㵘ዲ눓甗봐嘋筯쑫塚ꮰⓦ⁉낛ϋ흆奊盉".toCharArray(), (short)18775, true, 4));
/*     */           "줌鄁슆瀳".toCharArray()[2] = (char)("줌鄁슆瀳".toCharArray()[2] ^ 0x75E5);
/*     */           arrayOfObject[1] = SecretKeyFactory.getInstance(fW$gy.A("줌鄁슆瀳".toCharArray(), (short)14185, true, 2));
/*     */           arrayOfObject[2] = new IvParameterSpec(new byte[8]);
/*     */           j.put(long_, arrayOfObject);
/*     */         } 
/*     */       } catch (Exception exception) {
/*     */         "啔ౝ間럤ⳁ躴ᥦ㝶?듋ꩾ??菱浶扜珱ᨱ".toCharArray()[10] = (char)("啔ౝ間럤ⳁ躴ᥦ㝶?듋ꩾ??菱浶扜珱ᨱ".toCharArray()[10] ^ 0x2380);
/*     */         throw new RuntimeException(fW$gy.A("啔ౝ間럤ⳁ躴ᥦ㝶?듋ꩾ??菱浶扜珱ᨱ".toCharArray(), (short)273, true, 2), exception);
/*     */       } 
/*     */       byte[] arrayOfByte1 = new byte[8];
/*     */       arrayOfByte1[0] = (byte)(int)(paramLong >>> 56L);
/*     */       for (byte b = 1; b < 8; b++)
/*     */         arrayOfByte1[b] = (byte)(int)(paramLong << b * 8 >>> 56L); 
/*     */       DESKeySpec dESKeySpec = new DESKeySpec(arrayOfByte1);
/*     */       SecretKey secretKey = ((SecretKeyFactory)arrayOfObject[1]).generateSecret(dESKeySpec);
/*     */       ((Cipher)arrayOfObject[0]).init(2, secretKey, (IvParameterSpec)arrayOfObject[2]);
/*     */       "靮堟펏柔툼윣ꛅ랯㼷".toCharArray()[1] = (char)("靮堟펏柔툼윣ꛅ랯㼷".toCharArray()[1] ^ 0x5865);
/*     */       byte[] arrayOfByte2 = h[i].getBytes(fW$gy.A("靮堟펏柔툼윣ꛅ랯㼷".toCharArray(), (short)17676, true, 4));
/*     */       i[i] = a(((Cipher)arrayOfObject[0]).doFinal(arrayOfByte2));
/*     */     } 
/*     */     return i[i];
/*     */   }
/*     */   
/*     */   private static Object a(MethodHandles.Lookup paramLookup, MutableCallSite paramMutableCallSite, String paramString, Object[] paramArrayOfObject) {
/*     */     int i = ((Integer)paramArrayOfObject[0]).intValue();
/*     */     long l = ((Long)paramArrayOfObject[1]).longValue();
/*     */     String str = a(i, l);
/*     */     MethodHandle methodHandle = MethodHandles.constant(String.class, str);
/*     */     paramMutableCallSite.setTarget(MethodHandles.dropArguments(methodHandle, 0, new Class[] { int.class, long.class }));
/*     */     return str;
/*     */   }
/*     */   
/*     */   private static CallSite a(MethodHandles.Lookup paramLookup, String paramString, MethodType paramMethodType) {
/*     */     // Byte code:
/*     */     //   0: new java/lang/invoke/MutableCallSite
/*     */     //   3: dup
/*     */     //   4: aload_2
/*     */     //   5: invokespecial <init> : (Ljava/lang/invoke/MethodType;)V
/*     */     //   8: astore_3
/*     */     //   9: aload_3
/*     */     //   10: ldc_w
/*     */     //   13: ldc_w [Ljava/lang/Object;
/*     */     //   16: aload_2
/*     */     //   17: invokevirtual parameterCount : ()I
/*     */     //   20: invokevirtual asCollector : (Ljava/lang/Class;I)Ljava/lang/invoke/MethodHandle;
/*     */     //   23: iconst_0
/*     */     //   24: iconst_3
/*     */     //   25: anewarray java/lang/Object
/*     */     //   28: dup
/*     */     //   29: iconst_0
/*     */     //   30: aload_0
/*     */     //   31: aastore
/*     */     //   32: dup
/*     */     //   33: iconst_1
/*     */     //   34: aload_3
/*     */     //   35: aastore
/*     */     //   36: dup
/*     */     //   37: iconst_2
/*     */     //   38: aload_1
/*     */     //   39: aastore
/*     */     //   40: invokestatic insertArguments : (Ljava/lang/invoke/MethodHandle;I[Ljava/lang/Object;)Ljava/lang/invoke/MethodHandle;
/*     */     //   43: aload_2
/*     */     //   44: invokestatic explicitCastArguments : (Ljava/lang/invoke/MethodHandle;Ljava/lang/invoke/MethodType;)Ljava/lang/invoke/MethodHandle;
/*     */     //   47: invokevirtual setTarget : (Ljava/lang/invoke/MethodHandle;)V
/*     */     //   50: goto -> 170
/*     */     //   53: astore #4
/*     */     //   55: new java/lang/RuntimeException
/*     */     //   58: dup
/*     */     //   59: new java/lang/StringBuilder
/*     */     //   62: dup
/*     */     //   63: invokespecial <init> : ()V
/*     */     //   66: ldc_w '㚈劤ቋ鄩Ĩᠯ뼔រ렓䯐駏磣饰ꊲ᤮ȗㄡ䝭琖'
/*     */     //   69: invokevirtual toCharArray : ()[C
/*     */     //   72: dup
/*     */     //   73: dup
/*     */     //   74: iconst_1
/*     */     //   75: dup_x1
/*     */     //   76: caload
/*     */     //   77: sipush #14180
/*     */     //   80: ixor
/*     */     //   81: i2c
/*     */     //   82: castore
/*     */     //   83: sipush #15772
/*     */     //   86: iconst_0
/*     */     //   87: iconst_2
/*     */     //   88: invokestatic G : (Ljava/lang/Object;SZB)Ljava/lang/String;
/*     */     //   91: invokevirtual append : (Ljava/lang/String;)Ljava/lang/StringBuilder;
/*     */     //   94: ldc_w '肢䵌ᶤಐ'
/*     */     //   97: invokevirtual toCharArray : ()[C
/*     */     //   100: dup
/*     */     //   101: dup
/*     */     //   102: iconst_0
/*     */     //   103: dup_x1
/*     */     //   104: caload
/*     */     //   105: sipush #32110
/*     */     //   108: ixor
/*     */     //   109: i2c
/*     */     //   110: castore
/*     */     //   111: sipush #15187
/*     */     //   114: iconst_1
/*     */     //   115: iconst_3
/*     */     //   116: invokestatic G : (Ljava/lang/Object;SZB)Ljava/lang/String;
/*     */     //   119: invokevirtual append : (Ljava/lang/String;)Ljava/lang/StringBuilder;
/*     */     //   122: aload_1
/*     */     //   123: invokevirtual append : (Ljava/lang/String;)Ljava/lang/StringBuilder;
/*     */     //   126: ldc_w '볝练彂絇'
/*     */     //   129: invokevirtual toCharArray : ()[C
/*     */     //   132: dup
/*     */     //   133: dup
/*     */     //   134: iconst_0
/*     */     //   135: dup_x1
/*     */     //   136: caload
/*     */     //   137: sipush #7185
/*     */     //   140: ixor
/*     */     //   141: i2c
/*     */     //   142: castore
/*     */     //   143: sipush #14604
/*     */     //   146: iconst_1
/*     */     //   147: iconst_3
/*     */     //   148: invokestatic G : (Ljava/lang/Object;SZB)Ljava/lang/String;
/*     */     //   151: invokevirtual append : (Ljava/lang/String;)Ljava/lang/StringBuilder;
/*     */     //   154: aload_2
/*     */     //   155: invokevirtual toString : ()Ljava/lang/String;
/*     */     //   158: invokevirtual append : (Ljava/lang/String;)Ljava/lang/StringBuilder;
/*     */     //   161: invokevirtual toString : ()Ljava/lang/String;
/*     */     //   164: aload #4
/*     */     //   166: invokespecial <init> : (Ljava/lang/String;Ljava/lang/Throwable;)V
/*     */     //   169: athrow
/*     */     //   170: aload_3
/*     */     //   171: areturn
/*     */     // Exception table:
/*     */     //   from	to	target	type
/*     */     //   9	50	53	java/lang/Exception
/*     */   }
/*     */ }


/* Location:              C:\Users\BukkitBypass\Desktop\MatrixAC\AAC\AAC-spigot-5.2.0.jar!\me\konsolas\aac\mi.class
 * Java compiler version: 8 (52.0)
 * JD-Core Version:       1.1.3
 */