/*    */ package me.konsolas.aac;public final class mm {
/*    */   private static final String c;
/*    */   private static final String f;
/*    */   private static final Pattern g;
/*    */   private static final Pattern h;
/*    */   private final String a;
/*    */   private final String e;
/*    */   
/*    */   public int hashCode() {
/* 10 */     return this.a.hashCode();
/*    */   } private final String d; @Nullable
/*    */   private final String b; private static final long i; private static final String[] j; private static final String[] k; private static final Map l;
/*    */   static {
/*    */     byte b1;
/*    */     long l;
/* 16 */     for (i = nc.a(-4536126962291020294L, 2151474614890568174L, MethodHandles.lookup().lookupClass()).a(167759192445670L), l = i ^ 0x5A9B72970691L, l = new HashMap<>(13), "켫ꃸ㸼싶ﱞ㥍䓛㕔蠊᠈駶┻?ꖿ㉯윝俪桽벴戹".toCharArray()[18] = (char)("켫ꃸ㸼싶ﱞ㥍䓛㕔蠊᠈駶┻?ꖿ㉯윝俪桽벴戹".toCharArray()[18] ^ 0x6B5F), "隧὿ﵳ峏".toCharArray()[2] = (char)("隧὿ﵳ峏".toCharArray()[2] ^ 0x4A9E), (new byte[8])[0] = (byte)(int)(l >>> 56L), b1 = 1; b1 < 8; ) { (new byte[8])[b1] = (byte)(int)(l << b1 * 8 >>> 56L); b1++; }  Cipher cipher; (cipher = Cipher.getInstance(dP$dt.X("켫ꃸ㸼싶ﱞ㥍䓛㕔蠊᠈駶┻?ꖿ㉯윝俪桽벴戹".toCharArray(), (short)15442, true, true))).init(2, SecretKeyFactory.getInstance(dP$dt.X("隧὿ﵳ峏".toCharArray(), (short)24451, false, true)).generateSecret(new DESKeySpec(new byte[8])), new IvParameterSpec(new byte[8])); String[] arrayOfString = new String[11]; boolean bool = false; "拠햾논க⳹詼꘺㒝널ꓕ饤뵯檲率⯗䊠ᢱᢑ炅鬝찾?ኛ猋㍇?횔跊熥剑紉鐋㤨✙漖௜礩㺌驚㝀䈮諔穫杖쟢ꄷ屮렚ᕨ뎭㯸뷪䗳䱯뼭쾫䉷蛫՞ᤖ螦뷢儖揠䧌藚鈏濃调掿ꓰ얡ꑌ愂哲᤻僴曘ﾩﴵ魴麡᤯茚銇ᕉ徣쇪?ꬮ즾㤕Ӭ旕⒱뇪䔙?ꖳ㬅?⍓鿠뒢뛌ᠩᑗ禃䲶뙑옛껚閴놚⮧剆郪쎜曊ꅛ⩥譒⸙鷴擑禜翨?ベ?늇툛艍鬙罩뽒睇贳啉兰愻쬐ףּ᥻噯輷⽍▄龏墖뫖냚죓驖隳콩༵ᦶ㺮㠣钹㸧ᶬꠐ貼㝫誨鎋뷢続༕ꆗ䛪滠ᣴ㊯䄗螛骓Ջ伸Ḳ㟿낛끲젘┟ᰊ㍄ꎪᒷ勩ᅞ淬嘂귫배봵⟂澴紌ඪ畞㩩焮虥睟鑺ᵊ妒殿蝵좟े⢑곍犄䆃Ѳ開쒞汀⩜嬃꯷쑲삇買︙কϨ턑̘㺜잰禉洴ﳅ㺟횬Ỽ嚮ந䗞䗉랏䁑㊜⶚႖砮벽䘺䈻揓⥏曃㉺᲏◵潳ѬᏫ呚틁췓핺函籌仂õ咑椁⍬⺐⋞걊ꃊ탅跱㋦❚ᏽ붿ꘒ觻蔋欺嶐耂䤃ᇰ?䰐났㾫쀵ℋ喞䅓蠆䔨搖﮳̇慺袇檇粙㷥ﾌꦅ⍱ⲛ౑ֈೀ达讀棳裐퓞䯾툣施謕渟慝뾽㡶◎斟敬禪퀆ຟӶꍶ羪躼?담蘎੨郲ͽ윥⡑誵ᣫࢼ斓瀽ύ⺛렂眷裸ュ䎸ఞ嬸偦⒜䪫饔▎ߒퟤ䎼සє잯셠抌⯎홣ꀝ斶坰଱䤮츙ꃙ㯂䴎镍꣥ﰿ뗈륝佟䥓ᘐ뙋؟贅좒녥陎?谹ꈆ⎳㜱?룪贐뇚Ƕ绢₡샷主牅뜐ྫᴈ觬聥輸媧쏵ꈍ룥僲굏冼慄鯌⵾ﲠ㽺猏穽發늄ꟷ?貒≋ヮ謾ퟃ⫋?搪邹邜?䀠갭蜳桵㠊㮁쮪皍픜⟸".toCharArray()[284] = (char)("拠햾논க⳹詼꘺㒝널ꓕ饤뵯檲率⯗䊠ᢱᢑ炅鬝찾?ኛ猋㍇?횔跊熥剑紉鐋㤨✙漖௜礩㺌驚㝀䈮諔穫杖쟢ꄷ屮렚ᕨ뎭㯸뷪䗳䱯뼭쾫䉷蛫՞ᤖ螦뷢儖揠䧌藚鈏濃调掿ꓰ얡ꑌ愂哲᤻僴曘ﾩﴵ魴麡᤯茚銇ᕉ徣쇪?ꬮ즾㤕Ӭ旕⒱뇪䔙?ꖳ㬅?⍓鿠뒢뛌ᠩᑗ禃䲶뙑옛껚閴놚⮧剆郪쎜曊ꅛ⩥譒⸙鷴擑禜翨?ベ?늇툛艍鬙罩뽒睇贳啉兰愻쬐ףּ᥻噯輷⽍▄龏墖뫖냚죓驖隳콩༵ᦶ㺮㠣钹㸧ᶬꠐ貼㝫誨鎋뷢続༕ꆗ䛪滠ᣴ㊯䄗螛骓Ջ伸Ḳ㟿낛끲젘┟ᰊ㍄ꎪᒷ勩ᅞ淬嘂귫배봵⟂澴紌ඪ畞㩩焮虥睟鑺ᵊ妒殿蝵좟े⢑곍犄䆃Ѳ開쒞汀⩜嬃꯷쑲삇買︙কϨ턑̘㺜잰禉洴ﳅ㺟횬Ỽ嚮ந䗞䗉랏䁑㊜⶚႖砮벽䘺䈻揓⥏曃㉺᲏◵潳ѬᏫ呚틁췓핺函籌仂õ咑椁⍬⺐⋞걊ꃊ탅跱㋦❚ᏽ붿ꘒ觻蔋欺嶐耂䤃ᇰ?䰐났㾫쀵ℋ喞䅓蠆䔨搖﮳̇慺袇檇粙㷥ﾌꦅ⍱ⲛ౑ֈೀ达讀棳裐퓞䯾툣施謕渟慝뾽㡶◎斟敬禪퀆ຟӶꍶ羪躼?담蘎੨郲ͽ윥⡑誵ᣫࢼ斓瀽ύ⺛렂眷裸ュ䎸ఞ嬸偦⒜䪫饔▎ߒퟤ䎼සє잯셠抌⯎홣ꀝ斶坰଱䤮츙ꃙ㯂䴎镍꣥ﰿ뗈륝佟䥓ᘐ뙋؟贅좒녥陎?谹ꈆ⎳㜱?룪贐뇚Ƕ绢₡샷主牅뜐ྫᴈ觬聥輸媧쏵ꈍ룥僲굏冼慄鯌⵾ﲠ㽺猏穽發늄ꟷ?貒≋ヮ謾ퟃ⫋?搪邹邜?䀠갭蜳桵㠊㮁쮪皍픜⟸".toCharArray()[284] ^ 0x24E0); String str; int i = (str = dP$dt.X("拠햾논க⳹詼꘺㒝널ꓕ饤뵯檲率⯗䊠ᢱᢑ炅鬝찾?ኛ猋㍇?횔跊熥剑紉鐋㤨✙漖௜礩㺌驚㝀䈮諔穫杖쟢ꄷ屮렚ᕨ뎭㯸뷪䗳䱯뼭쾫䉷蛫՞ᤖ螦뷢儖揠䧌藚鈏濃调掿ꓰ얡ꑌ愂哲᤻僴曘ﾩﴵ魴麡᤯茚銇ᕉ徣쇪?ꬮ즾㤕Ӭ旕⒱뇪䔙?ꖳ㬅?⍓鿠뒢뛌ᠩᑗ禃䲶뙑옛껚閴놚⮧剆郪쎜曊ꅛ⩥譒⸙鷴擑禜翨?ベ?늇툛艍鬙罩뽒睇贳啉兰愻쬐ףּ᥻噯輷⽍▄龏墖뫖냚죓驖隳콩༵ᦶ㺮㠣钹㸧ᶬꠐ貼㝫誨鎋뷢続༕ꆗ䛪滠ᣴ㊯䄗螛骓Ջ伸Ḳ㟿낛끲젘┟ᰊ㍄ꎪᒷ勩ᅞ淬嘂귫배봵⟂澴紌ඪ畞㩩焮虥睟鑺ᵊ妒殿蝵좟े⢑곍犄䆃Ѳ開쒞汀⩜嬃꯷쑲삇買︙কϨ턑̘㺜잰禉洴ﳅ㺟횬Ỽ嚮ந䗞䗉랏䁑㊜⶚႖砮벽䘺䈻揓⥏曃㉺᲏◵潳ѬᏫ呚틁췓핺函籌仂õ咑椁⍬⺐⋞걊ꃊ탅跱㋦❚ᏽ붿ꘒ觻蔋欺嶐耂䤃ᇰ?䰐났㾫쀵ℋ喞䅓蠆䔨搖﮳̇慺袇檇粙㷥ﾌꦅ⍱ⲛ౑ֈೀ达讀棳裐퓞䯾툣施謕渟慝뾽㡶◎斟敬禪퀆ຟӶꍶ羪躼?담蘎੨郲ͽ윥⡑誵ᣫࢼ斓瀽ύ⺛렂眷裸ュ䎸ఞ嬸偦⒜䪫饔▎ߒퟤ䎼සє잯셠抌⯎홣ꀝ斶坰଱䤮츙ꃙ㯂䴎镍꣥ﰿ뗈륝佟䥓ᘐ뙋؟贅좒녥陎?谹ꈆ⎳㜱?룪贐뇚Ƕ绢₡샷主牅뜐ྫᴈ觬聥輸媧쏵ꈍ룥僲굏冼慄鯌⵾ﲠ㽺猏穽發늄ꟷ?貒≋ヮ謾ퟃ⫋?搪邹邜?䀠갭蜳桵㠊㮁쮪皍픜⟸".toCharArray(), (short)31184, false, true)).length(); byte b2 = 104; byte b = -1;
/*    */     while (true);
/*    */   } public boolean equals(@Nullable Object paramObject) { // Byte code:
/*    */     //   0: getstatic me/konsolas/aac/mm.i : J
/*    */     //   3: ldc2_w 109104017871037
/*    */     //   6: lxor
/*    */     //   7: lstore_2
/*    */     //   8: ldc2_w -4930132827889288362
/*    */     //   11: lload_2
/*    */     //   12: <illegal opcode> w : (JJ)[Lme/konsolas/aac/aN;
/*    */     //   17: astore #4
/*    */     //   19: aload_1
/*    */     //   20: instanceof me/konsolas/aac/mm
/*    */     //   23: aload #4
/*    */     //   25: ifnonnull -> 71
/*    */     //   28: ifeq -> 96
/*    */     //   31: goto -> 44
/*    */     //   34: ldc2_w -4915122157798760161
/*    */     //   37: lload_2
/*    */     //   38: <illegal opcode> w : (Ljava/lang/IllegalArgumentException;JJ)Ljava/lang/IllegalArgumentException;
/*    */     //   43: athrow
/*    */     //   44: aload_1
/*    */     //   45: checkcast me/konsolas/aac/mm
/*    */     //   48: getfield a : Ljava/lang/String;
/*    */     //   51: aload_0
/*    */     //   52: getfield a : Ljava/lang/String;
/*    */     //   55: invokevirtual equals : (Ljava/lang/Object;)Z
/*    */     //   58: goto -> 71
/*    */     //   61: ldc2_w -4915122157798760161
/*    */     //   64: lload_2
/*    */     //   65: <illegal opcode> w : (Ljava/lang/IllegalArgumentException;JJ)Ljava/lang/IllegalArgumentException;
/*    */     //   70: athrow
/*    */     //   71: aload #4
/*    */     //   73: ifnonnull -> 93
/*    */     //   76: ifeq -> 96
/*    */     //   79: goto -> 92
/*    */     //   82: ldc2_w -4915122157798760161
/*    */     //   85: lload_2
/*    */     //   86: <illegal opcode> w : (Ljava/lang/IllegalArgumentException;JJ)Ljava/lang/IllegalArgumentException;
/*    */     //   91: athrow
/*    */     //   92: iconst_1
/*    */     //   93: goto -> 97
/*    */     //   96: iconst_0
/*    */     //   97: ireturn
/*    */     // Line number table:
/*    */     //   Java source line number -> byte code offset
/*    */     //   #17	-> 19
/*    */     // Exception table:
/*    */     //   from	to	target	type
/*    */     //   19	31	34	java/lang/IllegalArgumentException
/*    */     //   28	58	61	java/lang/IllegalArgumentException
/*    */     //   71	79	82	java/lang/IllegalArgumentException }
/*    */   private mm(String paramString1, String paramString2, String paramString3, @Nullable String paramString4) { this.a = paramString1;
/* 20 */     this.e = paramString2;
/*    */ 
/*    */ 
/*    */ 
/*    */ 
/*    */ 
/*    */ 
/*    */ 
/*    */ 
/*    */ 
/*    */     
/* 31 */     this.d = paramString3;
/*    */     this.b = paramString4; } public String toString() { return this.a; } public String a() {
/*    */     return this.d;
/*    */   }
/*    */   public static mm a(String paramString, long paramLong) {
/*    */     // Byte code:
/*    */     //   0: getstatic me/konsolas/aac/mm.i : J
/*    */     //   3: lload_1
/*    */     //   4: lxor
/*    */     //   5: lstore_1
/*    */     //   6: getstatic me/konsolas/aac/mm.g : Ljava/util/regex/Pattern;
/*    */     //   9: aload_0
/*    */     //   10: invokevirtual matcher : (Ljava/lang/CharSequence;)Ljava/util/regex/Matcher;
/*    */     //   13: astore_3
/*    */     //   14: aload_3
/*    */     //   15: invokevirtual lookingAt : ()Z
/*    */     //   18: ifne -> 74
/*    */     //   21: new java/lang/IllegalArgumentException
/*    */     //   24: dup
/*    */     //   25: new java/lang/StringBuilder
/*    */     //   28: dup
/*    */     //   29: invokespecial <init> : ()V
/*    */     //   32: sipush #18684
/*    */     //   35: ldc2_w 6262970250253665067
/*    */     //   38: lload_1
/*    */     //   39: lxor
/*    */     //   40: <illegal opcode> k : (IJ)Ljava/lang/String;
/*    */     //   45: invokevirtual append : (Ljava/lang/String;)Ljava/lang/StringBuilder;
/*    */     //   48: aload_0
/*    */     //   49: invokevirtual append : (Ljava/lang/String;)Ljava/lang/StringBuilder;
/*    */     //   52: bipush #34
/*    */     //   54: invokevirtual append : (C)Ljava/lang/StringBuilder;
/*    */     //   57: invokevirtual toString : ()Ljava/lang/String;
/*    */     //   60: invokespecial <init> : (Ljava/lang/String;)V
/*    */     //   63: athrow
/*    */     //   64: ldc2_w 5049323283316219076
/*    */     //   67: lload_1
/*    */     //   68: <illegal opcode> w : (Ljava/lang/IllegalArgumentException;JJ)Ljava/lang/IllegalArgumentException;
/*    */     //   73: athrow
/*    */     //   74: aload_3
/*    */     //   75: iconst_1
/*    */     //   76: invokevirtual group : (I)Ljava/lang/String;
/*    */     //   79: getstatic java/util/Locale.US : Ljava/util/Locale;
/*    */     //   82: invokevirtual toLowerCase : (Ljava/util/Locale;)Ljava/lang/String;
/*    */     //   85: astore #4
/*    */     //   87: aload_3
/*    */     //   88: iconst_2
/*    */     //   89: invokevirtual group : (I)Ljava/lang/String;
/*    */     //   92: getstatic java/util/Locale.US : Ljava/util/Locale;
/*    */     //   95: invokevirtual toLowerCase : (Ljava/util/Locale;)Ljava/lang/String;
/*    */     //   98: astore #5
/*    */     //   100: aconst_null
/*    */     //   101: astore #6
/*    */     //   103: getstatic me/konsolas/aac/mm.h : Ljava/util/regex/Pattern;
/*    */     //   106: aload_0
/*    */     //   107: invokevirtual matcher : (Ljava/lang/CharSequence;)Ljava/util/regex/Matcher;
/*    */     //   110: astore #7
/*    */     //   112: aload_3
/*    */     //   113: invokevirtual end : ()I
/*    */     //   116: istore #8
/*    */     //   118: iload #8
/*    */     //   120: aload_0
/*    */     //   121: invokevirtual length : ()I
/*    */     //   124: if_icmpge -> 642
/*    */     //   127: aload #7
/*    */     //   129: iload #8
/*    */     //   131: aload_0
/*    */     //   132: invokevirtual length : ()I
/*    */     //   135: invokevirtual region : (II)Ljava/util/regex/Matcher;
/*    */     //   138: pop
/*    */     //   139: aload #7
/*    */     //   141: lload_1
/*    */     //   142: lconst_0
/*    */     //   143: lcmp
/*    */     //   144: iflt -> 246
/*    */     //   147: invokevirtual lookingAt : ()Z
/*    */     //   150: ifne -> 244
/*    */     //   153: goto -> 166
/*    */     //   156: ldc2_w 5049323283316219076
/*    */     //   159: lload_1
/*    */     //   160: <illegal opcode> w : (Ljava/lang/IllegalArgumentException;JJ)Ljava/lang/IllegalArgumentException;
/*    */     //   165: athrow
/*    */     //   166: new java/lang/IllegalArgumentException
/*    */     //   169: dup
/*    */     //   170: new java/lang/StringBuilder
/*    */     //   173: dup
/*    */     //   174: invokespecial <init> : ()V
/*    */     //   177: sipush #23375
/*    */     //   180: ldc2_w 4405820617861075092
/*    */     //   183: lload_1
/*    */     //   184: lxor
/*    */     //   185: <illegal opcode> k : (IJ)Ljava/lang/String;
/*    */     //   190: invokevirtual append : (Ljava/lang/String;)Ljava/lang/StringBuilder;
/*    */     //   193: aload_0
/*    */     //   194: iload #8
/*    */     //   196: invokevirtual substring : (I)Ljava/lang/String;
/*    */     //   199: invokevirtual append : (Ljava/lang/String;)Ljava/lang/StringBuilder;
/*    */     //   202: sipush #3677
/*    */     //   205: ldc2_w 3200986194299110791
/*    */     //   208: lload_1
/*    */     //   209: lxor
/*    */     //   210: <illegal opcode> k : (IJ)Ljava/lang/String;
/*    */     //   215: invokevirtual append : (Ljava/lang/String;)Ljava/lang/StringBuilder;
/*    */     //   218: aload_0
/*    */     //   219: invokevirtual append : (Ljava/lang/String;)Ljava/lang/StringBuilder;
/*    */     //   222: bipush #34
/*    */     //   224: invokevirtual append : (C)Ljava/lang/StringBuilder;
/*    */     //   227: invokevirtual toString : ()Ljava/lang/String;
/*    */     //   230: invokespecial <init> : (Ljava/lang/String;)V
/*    */     //   233: athrow
/*    */     //   234: ldc2_w 5049323283316219076
/*    */     //   237: lload_1
/*    */     //   238: <illegal opcode> w : (Ljava/lang/IllegalArgumentException;JJ)Ljava/lang/IllegalArgumentException;
/*    */     //   243: athrow
/*    */     //   244: aload #7
/*    */     //   246: iconst_1
/*    */     //   247: invokevirtual group : (I)Ljava/lang/String;
/*    */     //   250: astore #9
/*    */     //   252: lload_1
/*    */     //   253: lconst_0
/*    */     //   254: lcmp
/*    */     //   255: iflt -> 636
/*    */     //   258: aload #9
/*    */     //   260: ifnull -> 629
/*    */     //   263: aload #9
/*    */     //   265: lload_1
/*    */     //   266: lconst_0
/*    */     //   267: lcmp
/*    */     //   268: ifle -> 322
/*    */     //   271: sipush #11117
/*    */     //   274: ldc2_w 4395745038123196594
/*    */     //   277: lload_1
/*    */     //   278: lxor
/*    */     //   279: <illegal opcode> k : (IJ)Ljava/lang/String;
/*    */     //   284: invokevirtual equalsIgnoreCase : (Ljava/lang/String;)Z
/*    */     //   287: ifne -> 316
/*    */     //   290: goto -> 303
/*    */     //   293: ldc2_w 5049323283316219076
/*    */     //   296: lload_1
/*    */     //   297: <illegal opcode> w : (Ljava/lang/IllegalArgumentException;JJ)Ljava/lang/IllegalArgumentException;
/*    */     //   302: athrow
/*    */     //   303: goto -> 629
/*    */     //   306: ldc2_w 5049323283316219076
/*    */     //   309: lload_1
/*    */     //   310: <illegal opcode> w : (Ljava/lang/IllegalArgumentException;JJ)Ljava/lang/IllegalArgumentException;
/*    */     //   315: athrow
/*    */     //   316: aload #7
/*    */     //   318: iconst_2
/*    */     //   319: invokevirtual group : (I)Ljava/lang/String;
/*    */     //   322: astore #11
/*    */     //   324: aload #11
/*    */     //   326: lload_1
/*    */     //   327: lconst_0
/*    */     //   328: lcmp
/*    */     //   329: ifle -> 488
/*    */     //   332: ifnull -> 482
/*    */     //   335: aload #11
/*    */     //   337: ldc '꩖ᗮ'
/*    */     //   339: invokevirtual toCharArray : ()[C
/*    */     //   342: dup
/*    */     //   343: dup
/*    */     //   344: iconst_0
/*    */     //   345: dup_x1
/*    */     //   346: caload
/*    */     //   347: sipush #29643
/*    */     //   350: ixor
/*    */     //   351: i2c
/*    */     //   352: castore
/*    */     //   353: bipush #100
/*    */     //   355: iconst_1
/*    */     //   356: iconst_2
/*    */     //   357: invokestatic A : (Ljava/lang/Object;SZI)Ljava/lang/String;
/*    */     //   360: invokevirtual startsWith : (Ljava/lang/String;)Z
/*    */     //   363: ifeq -> 472
/*    */     //   366: goto -> 379
/*    */     //   369: ldc2_w 5049323283316219076
/*    */     //   372: lload_1
/*    */     //   373: <illegal opcode> w : (Ljava/lang/IllegalArgumentException;JJ)Ljava/lang/IllegalArgumentException;
/*    */     //   378: athrow
/*    */     //   379: aload #11
/*    */     //   381: ldc '⣗'
/*    */     //   383: invokevirtual toCharArray : ()[C
/*    */     //   386: dup
/*    */     //   387: dup
/*    */     //   388: iconst_0
/*    */     //   389: dup_x1
/*    */     //   390: caload
/*    */     //   391: sipush #19873
/*    */     //   394: ixor
/*    */     //   395: i2c
/*    */     //   396: castore
/*    */     //   397: sipush #28377
/*    */     //   400: iconst_0
/*    */     //   401: iconst_1
/*    */     //   402: invokestatic A : (Ljava/lang/Object;SZI)Ljava/lang/String;
/*    */     //   405: invokevirtual endsWith : (Ljava/lang/String;)Z
/*    */     //   408: ifeq -> 472
/*    */     //   411: goto -> 424
/*    */     //   414: ldc2_w 5049323283316219076
/*    */     //   417: lload_1
/*    */     //   418: <illegal opcode> w : (Ljava/lang/IllegalArgumentException;JJ)Ljava/lang/IllegalArgumentException;
/*    */     //   423: athrow
/*    */     //   424: aload #11
/*    */     //   426: invokevirtual length : ()I
/*    */     //   429: iconst_2
/*    */     //   430: if_icmple -> 472
/*    */     //   433: goto -> 446
/*    */     //   436: ldc2_w 5049323283316219076
/*    */     //   439: lload_1
/*    */     //   440: <illegal opcode> w : (Ljava/lang/IllegalArgumentException;JJ)Ljava/lang/IllegalArgumentException;
/*    */     //   445: athrow
/*    */     //   446: aload #11
/*    */     //   448: iconst_1
/*    */     //   449: aload #11
/*    */     //   451: invokevirtual length : ()I
/*    */     //   454: iconst_1
/*    */     //   455: isub
/*    */     //   456: invokevirtual substring : (II)Ljava/lang/String;
/*    */     //   459: goto -> 474
/*    */     //   462: ldc2_w 5049323283316219076
/*    */     //   465: lload_1
/*    */     //   466: <illegal opcode> w : (Ljava/lang/IllegalArgumentException;JJ)Ljava/lang/IllegalArgumentException;
/*    */     //   471: athrow
/*    */     //   472: aload #11
/*    */     //   474: astore #10
/*    */     //   476: lload_1
/*    */     //   477: lconst_0
/*    */     //   478: lcmp
/*    */     //   479: ifge -> 490
/*    */     //   482: aload #7
/*    */     //   484: iconst_3
/*    */     //   485: invokevirtual group : (I)Ljava/lang/String;
/*    */     //   488: astore #10
/*    */     //   490: aload #6
/*    */     //   492: lload_1
/*    */     //   493: lconst_0
/*    */     //   494: lcmp
/*    */     //   495: iflt -> 627
/*    */     //   498: ifnull -> 625
/*    */     //   501: aload #10
/*    */     //   503: lload_1
/*    */     //   504: lconst_0
/*    */     //   505: lcmp
/*    */     //   506: ifle -> 627
/*    */     //   509: aload #6
/*    */     //   511: invokevirtual equalsIgnoreCase : (Ljava/lang/String;)Z
/*    */     //   514: ifne -> 625
/*    */     //   517: goto -> 530
/*    */     //   520: ldc2_w 5049323283316219076
/*    */     //   523: lload_1
/*    */     //   524: <illegal opcode> w : (Ljava/lang/IllegalArgumentException;JJ)Ljava/lang/IllegalArgumentException;
/*    */     //   529: athrow
/*    */     //   530: new java/lang/IllegalArgumentException
/*    */     //   533: dup
/*    */     //   534: new java/lang/StringBuilder
/*    */     //   537: dup
/*    */     //   538: invokespecial <init> : ()V
/*    */     //   541: sipush #5305
/*    */     //   544: ldc2_w 3345233207058325345
/*    */     //   547: lload_1
/*    */     //   548: lxor
/*    */     //   549: <illegal opcode> k : (IJ)Ljava/lang/String;
/*    */     //   554: invokevirtual append : (Ljava/lang/String;)Ljava/lang/StringBuilder;
/*    */     //   557: aload #6
/*    */     //   559: invokevirtual append : (Ljava/lang/String;)Ljava/lang/StringBuilder;
/*    */     //   562: sipush #17787
/*    */     //   565: ldc2_w 6716859280286944935
/*    */     //   568: lload_1
/*    */     //   569: lxor
/*    */     //   570: <illegal opcode> k : (IJ)Ljava/lang/String;
/*    */     //   575: invokevirtual append : (Ljava/lang/String;)Ljava/lang/StringBuilder;
/*    */     //   578: aload #10
/*    */     //   580: invokevirtual append : (Ljava/lang/String;)Ljava/lang/StringBuilder;
/*    */     //   583: sipush #29993
/*    */     //   586: ldc2_w 2806421021658529524
/*    */     //   589: lload_1
/*    */     //   590: lxor
/*    */     //   591: <illegal opcode> k : (IJ)Ljava/lang/String;
/*    */     //   596: invokevirtual append : (Ljava/lang/String;)Ljava/lang/StringBuilder;
/*    */     //   599: aload_0
/*    */     //   600: invokevirtual append : (Ljava/lang/String;)Ljava/lang/StringBuilder;
/*    */     //   603: bipush #34
/*    */     //   605: invokevirtual append : (C)Ljava/lang/StringBuilder;
/*    */     //   608: invokevirtual toString : ()Ljava/lang/String;
/*    */     //   611: invokespecial <init> : (Ljava/lang/String;)V
/*    */     //   614: athrow
/*    */     //   615: ldc2_w 5049323283316219076
/*    */     //   618: lload_1
/*    */     //   619: <illegal opcode> w : (Ljava/lang/IllegalArgumentException;JJ)Ljava/lang/IllegalArgumentException;
/*    */     //   624: athrow
/*    */     //   625: aload #10
/*    */     //   627: astore #6
/*    */     //   629: aload #7
/*    */     //   631: invokevirtual end : ()I
/*    */     //   634: istore #8
/*    */     //   636: lload_1
/*    */     //   637: lconst_0
/*    */     //   638: lcmp
/*    */     //   639: ifge -> 118
/*    */     //   642: new me/konsolas/aac/mm
/*    */     //   645: dup
/*    */     //   646: aload_0
/*    */     //   647: aload #4
/*    */     //   649: aload #5
/*    */     //   651: aload #6
/*    */     //   653: invokespecial <init> : (Ljava/lang/String;Ljava/lang/String;Ljava/lang/String;Ljava/lang/String;)V
/*    */     //   656: areturn
/*    */     // Line number table:
/*    */     //   Java source line number -> byte code offset
/*    */     //   #32	-> 6
/*    */     //   #36	-> 14
/*    */     //   #9	-> 21
/*    */     //   #26	-> 74
/*    */     //   #33	-> 87
/*    */     //   #15	-> 100
/*    */     //   #22	-> 103
/*    */     //   #11	-> 112
/*    */     //   #12	-> 127
/*    */     //   #13	-> 139
/*    */     //   #43	-> 166
/*    */     //   #34	-> 196
/*    */     //   #14	-> 244
/*    */     //   #41	-> 252
/*    */     //   #37	-> 316
/*    */     //   #1	-> 324
/*    */     //   #8	-> 335
/*    */     //   #38	-> 446
/*    */     //   #7	-> 472
/*    */     //   #42	-> 482
/*    */     //   #5	-> 490
/*    */     //   #24	-> 530
/*    */     //   #25	-> 625
/*    */     //   #29	-> 629
/*    */     //   #6	-> 642
/*    */     // Exception table:
/*    */     //   from	to	target	type
/*    */     //   14	64	64	java/lang/IllegalArgumentException
/*    */     //   118	153	156	java/lang/IllegalArgumentException
/*    */     //   127	234	234	java/lang/IllegalArgumentException
/*    */     //   252	290	293	java/lang/IllegalArgumentException
/*    */     //   263	306	306	java/lang/IllegalArgumentException
/*    */     //   324	366	369	java/lang/IllegalArgumentException
/*    */     //   335	411	414	java/lang/IllegalArgumentException
/*    */     //   379	433	436	java/lang/IllegalArgumentException
/*    */     //   424	462	462	java/lang/IllegalArgumentException
/*    */     //   490	517	520	java/lang/IllegalArgumentException
/*    */     //   501	615	615	java/lang/IllegalArgumentException
/*    */   }
/*    */   @Nullable
/* 39 */   public Charset a(long paramLong) { paramLong = i ^ paramLong; long l = paramLong ^ 0x52E6D6DBFB4AL; return a((Charset)null, l); } public String b() {
/* 40 */     return this.e;
/*    */   }
/*    */   @Nullable
/*    */   public static mm b(String paramString, long paramLong) {
/* 44 */     paramLong = i ^ paramLong; long l = paramLong ^ 0x2341D81FA0AAL; try { return a(paramString, l); }
/*    */     catch (IllegalArgumentException illegalArgumentException)
/*    */     { return null; }
/*    */   
/*    */   }
/*    */   
/*    */   @Nullable
/*    */   public Charset a(@Nullable Charset paramCharset, long paramLong) {
/*    */     // Byte code:
/*    */     //   0: getstatic me/konsolas/aac/mm.i : J
/*    */     //   3: lload_2
/*    */     //   4: lxor
/*    */     //   5: lstore_2
/*    */     //   6: ldc2_w -5141815363892561818
/*    */     //   9: lload_2
/*    */     //   10: <illegal opcode> w : (JJ)[Lme/konsolas/aac/aN;
/*    */     //   15: astore #4
/*    */     //   17: aload_0
/*    */     //   18: getfield b : Ljava/lang/String;
/*    */     //   21: aload #4
/*    */     //   23: ifnonnull -> 59
/*    */     //   26: ifnull -> 65
/*    */     //   29: goto -> 42
/*    */     //   32: ldc2_w -5117841748963106257
/*    */     //   35: lload_2
/*    */     //   36: <illegal opcode> w : (Ljava/lang/IllegalArgumentException;JJ)Ljava/lang/IllegalArgumentException;
/*    */     //   41: athrow
/*    */     //   42: aload_0
/*    */     //   43: getfield b : Ljava/lang/String;
/*    */     //   46: goto -> 59
/*    */     //   49: ldc2_w -5117841748963106257
/*    */     //   52: lload_2
/*    */     //   53: <illegal opcode> w : (Ljava/lang/IllegalArgumentException;JJ)Ljava/lang/IllegalArgumentException;
/*    */     //   58: athrow
/*    */     //   59: invokestatic forName : (Ljava/lang/String;)Ljava/nio/charset/Charset;
/*    */     //   62: goto -> 66
/*    */     //   65: aload_1
/*    */     //   66: areturn
/*    */     //   67: astore #5
/*    */     //   69: aload_1
/*    */     //   70: areturn
/*    */     // Line number table:
/*    */     //   Java source line number -> byte code offset
/*    */     //   #45	-> 17
/*    */     //   #30	-> 67
/*    */     //   #21	-> 69
/*    */     // Exception table:
/*    */     //   from	to	target	type
/*    */     //   17	29	32	java/lang/IllegalArgumentException
/*    */     //   17	66	67	java/lang/IllegalArgumentException
/*    */     //   26	46	49	java/lang/IllegalArgumentException
/*    */   }
/*    */   
/*    */   private static IllegalArgumentException a(IllegalArgumentException paramIllegalArgumentException) {
/*    */     return paramIllegalArgumentException;
/*    */   }
/*    */   
/*    */   private static String a(byte[] paramArrayOfbyte) {
/*    */     byte b1 = 0;
/*    */     int i;
/*    */     char[] arrayOfChar = new char[i = paramArrayOfbyte.length];
/*    */     for (byte b2 = 0; b2 < i; b2++) {
/*    */       int j;
/*    */       if ((j = 0xFF & paramArrayOfbyte[b2]) < 192) {
/*    */         arrayOfChar[b1++] = (char)j;
/*    */       } else if (j < 224) {
/*    */         char c = (char)((char)(j & 0x1F) << 6);
/*    */         j = paramArrayOfbyte[++b2];
/*    */         c = (char)(c | (char)(j & 0x3F));
/*    */         arrayOfChar[b1++] = c;
/*    */       } else if (b2 < i - 2) {
/*    */         char c = (char)((char)(j & 0xF) << 12);
/*    */         j = paramArrayOfbyte[++b2];
/*    */         c = (char)(c | (char)(j & 0x3F) << 6);
/*    */         j = paramArrayOfbyte[++b2];
/*    */         c = (char)(c | (char)(j & 0x3F));
/*    */         arrayOfChar[b1++] = c;
/*    */       } 
/*    */     } 
/*    */     return new String(arrayOfChar, 0, b1);
/*    */   }
/*    */   
/*    */   private static String a(int paramInt, long paramLong) {
/*    */     int i = paramInt ^ (int)(paramLong & 0x7FFFL) ^ 0xD75;
/*    */     if (k[i] == null) {
/*    */       Object[] arrayOfObject;
/*    */       try {
/*    */         Long long_ = Long.valueOf(Thread.currentThread().getId());
/*    */         arrayOfObject = (Object[])l.get(long_);
/*    */         if (arrayOfObject == null) {
/*    */           arrayOfObject = new Object[3];
/*    */           "謧㡫䈎ሓ໳궗᭨㼨羏ጰ죿≛楿旼爦횛褴☆䣾".toCharArray()[5] = (char)("謧㡫䈎ሓ໳궗᭨㼨羏ጰ죿≛楿旼爦횛褴☆䣾".toCharArray()[5] ^ 0x4B05);
/*    */           arrayOfObject[0] = Cipher.getInstance(fW$gy.A("謧㡫䈎ሓ໳궗᭨㼨羏ጰ죿≛楿旼爦횛褴☆䣾".toCharArray(), (short)26907, false, 1));
/*    */           "飦庺᫞".toCharArray()[1] = (char)("飦庺᫞".toCharArray()[1] ^ 0xE40);
/*    */           arrayOfObject[1] = SecretKeyFactory.getInstance(fW$gy.A("飦庺᫞".toCharArray(), (short)23862, false, 3));
/*    */           arrayOfObject[2] = new IvParameterSpec(new byte[8]);
/*    */           l.put(long_, arrayOfObject);
/*    */         } 
/*    */       } catch (Exception exception) {
/*    */         "镆㨅怀퍚픬䕼끯袤ぁ꾆슐ᙂ鱂ݏ猵惴꬜犓".toCharArray()[3] = (char)("镆㨅怀퍚픬䕼끯袤ぁ꾆슐ᙂ鱂ݏ猵惴꬜犓".toCharArray()[3] ^ 0x38BF);
/*    */         throw new RuntimeException(fW$gy.A("镆㨅怀퍚픬䕼끯袤ぁ꾆슐ᙂ鱂ݏ猵惴꬜犓".toCharArray(), (short)21208, false, 5), exception);
/*    */       } 
/*    */       byte[] arrayOfByte1 = new byte[8];
/*    */       arrayOfByte1[0] = (byte)(int)(paramLong >>> 56L);
/*    */       for (byte b = 1; b < 8; b++)
/*    */         arrayOfByte1[b] = (byte)(int)(paramLong << b * 8 >>> 56L); 
/*    */       DESKeySpec dESKeySpec = new DESKeySpec(arrayOfByte1);
/*    */       SecretKey secretKey = ((SecretKeyFactory)arrayOfObject[1]).generateSecret(dESKeySpec);
/*    */       ((Cipher)arrayOfObject[0]).init(2, secretKey, (IvParameterSpec)arrayOfObject[2]);
/*    */       "蚓्䢲镛깾㜛䧩찥ഊ胣ⱆ".toCharArray()[4] = (char)("蚓्䢲镛깾㜛䧩찥ഊ胣ⱆ".toCharArray()[4] ^ 0x2CA7);
/*    */       byte[] arrayOfByte2 = j[i].getBytes(fW$gy.A("蚓्䢲镛깾㜛䧩찥ഊ胣ⱆ".toCharArray(), (short)11238, true, 3));
/*    */       k[i] = a(((Cipher)arrayOfObject[0]).doFinal(arrayOfByte2));
/*    */     } 
/*    */     return k[i];
/*    */   }
/*    */   
/*    */   private static Object a(MethodHandles.Lookup paramLookup, MutableCallSite paramMutableCallSite, String paramString, Object[] paramArrayOfObject) {
/*    */     int i = ((Integer)paramArrayOfObject[0]).intValue();
/*    */     long l = ((Long)paramArrayOfObject[1]).longValue();
/*    */     String str = a(i, l);
/*    */     MethodHandle methodHandle = MethodHandles.constant(String.class, str);
/*    */     paramMutableCallSite.setTarget(MethodHandles.dropArguments(methodHandle, 0, new Class[] { int.class, long.class }));
/*    */     return str;
/*    */   }
/*    */   
/*    */   private static CallSite a(MethodHandles.Lookup paramLookup, String paramString, MethodType paramMethodType) {
/*    */     // Byte code:
/*    */     //   0: new java/lang/invoke/MutableCallSite
/*    */     //   3: dup
/*    */     //   4: aload_2
/*    */     //   5: invokespecial <init> : (Ljava/lang/invoke/MethodType;)V
/*    */     //   8: astore_3
/*    */     //   9: aload_3
/*    */     //   10: ldc_w
/*    */     //   13: ldc_w [Ljava/lang/Object;
/*    */     //   16: aload_2
/*    */     //   17: invokevirtual parameterCount : ()I
/*    */     //   20: invokevirtual asCollector : (Ljava/lang/Class;I)Ljava/lang/invoke/MethodHandle;
/*    */     //   23: iconst_0
/*    */     //   24: iconst_3
/*    */     //   25: anewarray java/lang/Object
/*    */     //   28: dup
/*    */     //   29: iconst_0
/*    */     //   30: aload_0
/*    */     //   31: aastore
/*    */     //   32: dup
/*    */     //   33: iconst_1
/*    */     //   34: aload_3
/*    */     //   35: aastore
/*    */     //   36: dup
/*    */     //   37: iconst_2
/*    */     //   38: aload_1
/*    */     //   39: aastore
/*    */     //   40: invokestatic insertArguments : (Ljava/lang/invoke/MethodHandle;I[Ljava/lang/Object;)Ljava/lang/invoke/MethodHandle;
/*    */     //   43: aload_2
/*    */     //   44: invokestatic explicitCastArguments : (Ljava/lang/invoke/MethodHandle;Ljava/lang/invoke/MethodType;)Ljava/lang/invoke/MethodHandle;
/*    */     //   47: invokevirtual setTarget : (Ljava/lang/invoke/MethodHandle;)V
/*    */     //   50: goto -> 170
/*    */     //   53: astore #4
/*    */     //   55: new java/lang/RuntimeException
/*    */     //   58: dup
/*    */     //   59: new java/lang/StringBuilder
/*    */     //   62: dup
/*    */     //   63: invokespecial <init> : ()V
/*    */     //   66: ldc_w 'ɬ암笨귫澖截芿䛹苨瘮쑂֔⾶἞鳟華沲'
/*    */     //   69: invokevirtual toCharArray : ()[C
/*    */     //   72: dup
/*    */     //   73: dup
/*    */     //   74: iconst_1
/*    */     //   75: dup_x1
/*    */     //   76: caload
/*    */     //   77: sipush #10869
/*    */     //   80: ixor
/*    */     //   81: i2c
/*    */     //   82: castore
/*    */     //   83: sipush #28605
/*    */     //   86: iconst_0
/*    */     //   87: iconst_0
/*    */     //   88: invokestatic X : (Ljava/lang/Object;SZZ)Ljava/lang/String;
/*    */     //   91: invokevirtual append : (Ljava/lang/String;)Ljava/lang/StringBuilder;
/*    */     //   94: ldc_w 'Ȧ커㇫痶'
/*    */     //   97: invokevirtual toCharArray : ()[C
/*    */     //   100: dup
/*    */     //   101: dup
/*    */     //   102: iconst_0
/*    */     //   103: dup_x1
/*    */     //   104: caload
/*    */     //   105: sipush #18251
/*    */     //   108: ixor
/*    */     //   109: i2c
/*    */     //   110: castore
/*    */     //   111: sipush #20273
/*    */     //   114: iconst_1
/*    */     //   115: iconst_1
/*    */     //   116: invokestatic X : (Ljava/lang/Object;SZZ)Ljava/lang/String;
/*    */     //   119: invokevirtual append : (Ljava/lang/String;)Ljava/lang/StringBuilder;
/*    */     //   122: aload_1
/*    */     //   123: invokevirtual append : (Ljava/lang/String;)Ljava/lang/StringBuilder;
/*    */     //   126: ldc_w '垯磥↢'
/*    */     //   129: invokevirtual toCharArray : ()[C
/*    */     //   132: dup
/*    */     //   133: dup
/*    */     //   134: iconst_1
/*    */     //   135: dup_x1
/*    */     //   136: caload
/*    */     //   137: sipush #30770
/*    */     //   140: ixor
/*    */     //   141: i2c
/*    */     //   142: castore
/*    */     //   143: sipush #27487
/*    */     //   146: iconst_1
/*    */     //   147: iconst_0
/*    */     //   148: invokestatic X : (Ljava/lang/Object;SZZ)Ljava/lang/String;
/*    */     //   151: invokevirtual append : (Ljava/lang/String;)Ljava/lang/StringBuilder;
/*    */     //   154: aload_2
/*    */     //   155: invokevirtual toString : ()Ljava/lang/String;
/*    */     //   158: invokevirtual append : (Ljava/lang/String;)Ljava/lang/StringBuilder;
/*    */     //   161: invokevirtual toString : ()Ljava/lang/String;
/*    */     //   164: aload #4
/*    */     //   166: invokespecial <init> : (Ljava/lang/String;Ljava/lang/Throwable;)V
/*    */     //   169: athrow
/*    */     //   170: aload_3
/*    */     //   171: areturn
/*    */     // Exception table:
/*    */     //   from	to	target	type
/*    */     //   9	50	53	java/lang/Exception
/*    */   }
/*    */ }


/* Location:              C:\Users\BukkitBypass\Desktop\MatrixAC\AAC\AAC-spigot-5.2.0.jar!\me\konsolas\aac\mm.class
 * Java compiler version: 8 (52.0)
 * JD-Core Version:       1.1.3
 */