/*    */ package me.konsolas.aac;
/*    */ import aacinternal.v;
/*    */ import java.lang.invoke.MethodHandles;
/*    */ import java.lang.invoke.MutableCallSite;
/*    */ import java.util.function.DoubleUnaryOperator;
/*    */ import javax.crypto.Cipher;
/*    */ import javax.crypto.SecretKeyFactory;
/*    */ import javax.crypto.spec.DESKeySpec;
/*    */ import javax.crypto.spec.IvParameterSpec;
/*    */ 
/*    */ public class mq extends m8 {
/*    */   public mq(String paramString, eA parameA1, eA parameA2, DoubleUnaryOperator paramDoubleUnaryOperator) {
/* 13 */     super(paramString);
/* 14 */     this.d = parameA1;
/*    */     this.e = parameA2;
/*    */     this.f = paramDoubleUnaryOperator;
/*    */   }
/*    */   
/*    */   private final eA d;
/*    */   private final eA e;
/*    */   private final DoubleUnaryOperator f;
/*    */   private static final String[] g;
/*    */   private static final String[] h;
/*    */   private static final Map i = new HashMap<>(13);
/*    */   
/*    */   private static CallSite a(MethodHandles.Lookup paramLookup, String paramString, MethodType paramMethodType) {
/*    */     // Byte code:
/*    */     //   0: new java/lang/invoke/MutableCallSite
/*    */     //   3: dup
/*    */     //   4: aload_2
/*    */     //   5: invokespecial <init> : (Ljava/lang/invoke/MethodType;)V
/*    */     //   8: astore_3
/*    */     //   9: aload_3
/*    */     //   10: ldc_w
/*    */     //   13: ldc_w [Ljava/lang/Object;
/*    */     //   16: aload_2
/*    */     //   17: invokevirtual parameterCount : ()I
/*    */     //   20: invokevirtual asCollector : (Ljava/lang/Class;I)Ljava/lang/invoke/MethodHandle;
/*    */     //   23: iconst_0
/*    */     //   24: iconst_3
/*    */     //   25: anewarray java/lang/Object
/*    */     //   28: dup
/*    */     //   29: iconst_0
/*    */     //   30: aload_0
/*    */     //   31: aastore
/*    */     //   32: dup
/*    */     //   33: iconst_1
/*    */     //   34: aload_3
/*    */     //   35: aastore
/*    */     //   36: dup
/*    */     //   37: iconst_2
/*    */     //   38: aload_1
/*    */     //   39: aastore
/*    */     //   40: invokestatic insertArguments : (Ljava/lang/invoke/MethodHandle;I[Ljava/lang/Object;)Ljava/lang/invoke/MethodHandle;
/*    */     //   43: aload_2
/*    */     //   44: invokestatic explicitCastArguments : (Ljava/lang/invoke/MethodHandle;Ljava/lang/invoke/MethodType;)Ljava/lang/invoke/MethodHandle;
/*    */     //   47: invokevirtual setTarget : (Ljava/lang/invoke/MethodHandle;)V
/*    */     //   50: goto -> 170
/*    */     //   53: astore #4
/*    */     //   55: new java/lang/RuntimeException
/*    */     //   58: dup
/*    */     //   59: new java/lang/StringBuilder
/*    */     //   62: dup
/*    */     //   63: invokespecial <init> : ()V
/*    */     //   66: ldc_w '㨭뷝堸팛嗱⛀⊵莼襯葿俟秈䨭鄚之癕歰衁ᩪ'
/*    */     //   69: invokevirtual toCharArray : ()[C
/*    */     //   72: dup
/*    */     //   73: dup
/*    */     //   74: iconst_3
/*    */     //   75: dup_x1
/*    */     //   76: caload
/*    */     //   77: sipush #7372
/*    */     //   80: ixor
/*    */     //   81: i2c
/*    */     //   82: castore
/*    */     //   83: sipush #15059
/*    */     //   86: iconst_0
/*    */     //   87: iconst_1
/*    */     //   88: invokestatic U : (Ljava/lang/Object;SZZ)Ljava/lang/String;
/*    */     //   91: invokevirtual append : (Ljava/lang/String;)Ljava/lang/StringBuilder;
/*    */     //   94: ldc_w '쐬彙?஧'
/*    */     //   97: invokevirtual toCharArray : ()[C
/*    */     //   100: dup
/*    */     //   101: dup
/*    */     //   102: iconst_0
/*    */     //   103: dup_x1
/*    */     //   104: caload
/*    */     //   105: sipush #23685
/*    */     //   108: ixor
/*    */     //   109: i2c
/*    */     //   110: castore
/*    */     //   111: sipush #21784
/*    */     //   114: iconst_0
/*    */     //   115: iconst_0
/*    */     //   116: invokestatic U : (Ljava/lang/Object;SZZ)Ljava/lang/String;
/*    */     //   119: invokevirtual append : (Ljava/lang/String;)Ljava/lang/StringBuilder;
/*    */     //   122: aload_1
/*    */     //   123: invokevirtual append : (Ljava/lang/String;)Ljava/lang/StringBuilder;
/*    */     //   126: ldc_w 'ꫭ徝壒'
/*    */     //   129: invokevirtual toCharArray : ()[C
/*    */     //   132: dup
/*    */     //   133: dup
/*    */     //   134: iconst_1
/*    */     //   135: dup_x1
/*    */     //   136: caload
/*    */     //   137: sipush #5301
/*    */     //   140: ixor
/*    */     //   141: i2c
/*    */     //   142: castore
/*    */     //   143: sipush #18088
/*    */     //   146: iconst_1
/*    */     //   147: iconst_0
/*    */     //   148: invokestatic U : (Ljava/lang/Object;SZZ)Ljava/lang/String;
/*    */     //   151: invokevirtual append : (Ljava/lang/String;)Ljava/lang/StringBuilder;
/*    */     //   154: aload_2
/*    */     //   155: invokevirtual toString : ()Ljava/lang/String;
/*    */     //   158: invokevirtual append : (Ljava/lang/String;)Ljava/lang/StringBuilder;
/*    */     //   161: invokevirtual toString : ()Ljava/lang/String;
/*    */     //   164: aload #4
/*    */     //   166: invokespecial <init> : (Ljava/lang/String;Ljava/lang/Throwable;)V
/*    */     //   169: athrow
/*    */     //   170: aload_3
/*    */     //   171: areturn
/*    */     // Exception table:
/*    */     //   from	to	target	type
/*    */     //   9	50	53	java/lang/Exception
/*    */   }
/*    */   
/*    */   private static Object a(MethodHandles.Lookup paramLookup, MutableCallSite paramMutableCallSite, String paramString, Object[] paramArrayOfObject) {
/*    */     int i = ((Integer)paramArrayOfObject[0]).intValue();
/*    */     long l = ((Long)paramArrayOfObject[1]).longValue();
/*    */     String str = a(i, l);
/*    */     MethodHandle methodHandle = MethodHandles.constant(String.class, str);
/*    */     paramMutableCallSite.setTarget(MethodHandles.dropArguments(methodHandle, 0, new Class[] { int.class, long.class }));
/*    */     return str;
/*    */   }
/*    */   
/*    */   private static String a(int paramInt, long paramLong) {
/*    */     int i = paramInt ^ (int)(paramLong & 0x7FFFL) ^ 0x6D4F;
/*    */     if (h[i] == null) {
/*    */       Object[] arrayOfObject;
/*    */       try {
/*    */         Long long_ = Long.valueOf(Thread.currentThread().getId());
/*    */         arrayOfObject = (Object[])i.get(long_);
/*    */         if (arrayOfObject == null) {
/*    */           arrayOfObject = new Object[3];
/*    */           "ﴹṯ뽌롻塬氌ሀ矅縳ỿ뽇닲ﳩ㳗쮷ꭘꟴ藸팭Ⱑ".toCharArray()[0] = (char)("ﴹṯ뽌롻塬氌ሀ矅縳ỿ뽇닲ﳩ㳗쮷ꭘꟴ藸팭Ⱑ".toCharArray()[0] ^ 0x7D2A);
/*    */           arrayOfObject[0] = Cipher.getInstance(da$gx.U("ﴹṯ뽌롻塬氌ሀ矅縳ỿ뽇닲ﳩ㳗쮷ꭘꟴ藸팭Ⱑ".toCharArray(), (short)24561, true, false));
/*    */           "Ԁᩒ患剤".toCharArray()[2] = (char)("Ԁᩒ患剤".toCharArray()[2] ^ 0x1783);
/*    */           arrayOfObject[1] = SecretKeyFactory.getInstance(da$gx.U("Ԁᩒ患剤".toCharArray(), (short)11037, false, false));
/*    */           arrayOfObject[2] = new IvParameterSpec(new byte[8]);
/*    */           i.put(long_, arrayOfObject);
/*    */         } 
/*    */       } catch (Exception exception) {
/*    */         "ꔸ鋆㈿?ﰋ㫥彂鍴鵶龜瞭썒艴詿ꆐ魻䱙즠ݪ".toCharArray()[0] = (char)("ꔸ鋆㈿?ﰋ㫥彂鍴鵶龜瞭썒艴詿ꆐ魻䱙즠ݪ".toCharArray()[0] ^ 0x7DAD);
/*    */         throw new RuntimeException(da$gx.U("ꔸ鋆㈿?ﰋ㫥彂鍴鵶龜瞭썒艴詿ꆐ魻䱙즠ݪ".toCharArray(), (short)20692, false, false), exception);
/*    */       } 
/*    */       byte[] arrayOfByte1 = new byte[8];
/*    */       arrayOfByte1[0] = (byte)(int)(paramLong >>> 56L);
/*    */       for (byte b = 1; b < 8; b++)
/*    */         arrayOfByte1[b] = (byte)(int)(paramLong << b * 8 >>> 56L); 
/*    */       DESKeySpec dESKeySpec = new DESKeySpec(arrayOfByte1);
/*    */       SecretKey secretKey = ((SecretKeyFactory)arrayOfObject[1]).generateSecret(dESKeySpec);
/*    */       ((Cipher)arrayOfObject[0]).init(2, secretKey, (IvParameterSpec)arrayOfObject[2]);
/*    */       "؁䳔ꃩ澺띑⽸묈သ?猋".toCharArray()[0] = (char)("؁䳔ꃩ澺띑⽸묈သ?猋".toCharArray()[0] ^ 0x4D13);
/*    */       byte[] arrayOfByte2 = g[i].getBytes(da$gx.U("؁䳔ꃩ澺띑⽸묈သ?猋".toCharArray(), (short)21430, false, false));
/*    */       h[i] = a(((Cipher)arrayOfObject[0]).doFinal(arrayOfByte2));
/*    */     } 
/*    */     return h[i];
/*    */   }
/*    */   
/*    */   private static String a(byte[] paramArrayOfbyte) {
/*    */     byte b1 = 0;
/*    */     int i;
/*    */     char[] arrayOfChar = new char[i = paramArrayOfbyte.length];
/*    */     for (byte b2 = 0; b2 < i; b2++) {
/*    */       int j;
/*    */       if ((j = 0xFF & paramArrayOfbyte[b2]) < 192) {
/*    */         arrayOfChar[b1++] = (char)j;
/*    */       } else if (j < 224) {
/*    */         char c = (char)((char)(j & 0x1F) << 6);
/*    */         j = paramArrayOfbyte[++b2];
/*    */         c = (char)(c | (char)(j & 0x3F));
/*    */         arrayOfChar[b1++] = c;
/*    */       } else if (b2 < i - 2) {
/*    */         char c = (char)((char)(j & 0xF) << 12);
/*    */         j = paramArrayOfbyte[++b2];
/*    */         c = (char)(c | (char)(j & 0x3F) << 6);
/*    */         j = paramArrayOfbyte[++b2];
/*    */         c = (char)(c | (char)(j & 0x3F));
/*    */         arrayOfChar[b1++] = c;
/*    */       } 
/*    */     } 
/*    */     return new String(arrayOfChar, 0, b1);
/*    */   }
/*    */   
/*    */   private static v a(v paramv) {
/*    */     return paramv;
/*    */   }
/*    */   
/*    */   static {
/*    */     long l = nc.a(8415794004729627693L, 366039618632536296L, MethodHandles.lookup().lookupClass()).a(19298491161887L) ^ 0xDF7BEB02453L;
/*    */     "Ꮮ諵艡貖琰Н礇먪픙⣟枎ទΈ㔶ᯛ?弧坰氕".toCharArray()[15] = (char)("Ꮮ諵艡貖琰Н礇먪픙⣟枎ទΈ㔶ᯛ?弧坰氕".toCharArray()[15] ^ 0x4F50);
/*    */     "䙷㿍㛆᷀".toCharArray()[0] = (char)("䙷㿍㛆᷀".toCharArray()[0] ^ 0x5397);
/*    */     (new byte[8])[0] = (byte)(int)(l >>> 56L);
/*    */     for (byte b1 = 1; b1 < 8; b1++)
/*    */       (new byte[8])[b1] = (byte)(int)(l << b1 * 8 >>> 56L); 
/*    */     Cipher cipher;
/*    */     (cipher = Cipher.getInstance(hY$g6.H("Ꮮ諵艡貖琰Н礇먪픙⣟枎ទΈ㔶ᯛ?弧坰氕".toCharArray(), (short)8691, (byte)5, (byte)2))).init(2, SecretKeyFactory.getInstance(hY$g6.H("䙷㿍㛆᷀".toCharArray(), (short)78, (byte)1, (byte)2)).generateSecret(new DESKeySpec(new byte[8])), new IvParameterSpec(new byte[8]));
/*    */     String[] arrayOfString = new String[7];
/*    */     boolean bool = false;
/*    */     "潣ꑸ꾖采쫒ꇏᆿἲ零鈱롾ꎡᑯ䆍ু䡁곔䌾匛ះⴈի헼팩厔혴?향‐卤㆒踊퐚ჄƊ竑铷길㰖㨙챣㑾훃෋ⷠ˽崀届긔﫚木躋贿삫䕈뷅陻쨳垢ዑԻ偕㉿は軜疮ἣ䰡¢⽘巛氳殜ￂ㧨".toCharArray()[26] = (char)("潣ꑸ꾖采쫒ꇏᆿἲ零鈱롾ꎡᑯ䆍ু䡁곔䌾匛ះⴈի헼팩厔혴?향‐卤㆒踊퐚ჄƊ竑铷길㰖㨙챣㑾훃෋ⷠ˽崀届긔﫚木躋贿삫䕈뷅陻쨳垢ዑԻ偕㉿は軜疮ἣ䰡¢⽘巛氳殜ￂ㧨".toCharArray()[26] ^ 0x2B97);
/*    */     String str;
/*    */     int i = (str = hY$g6.H("潣ꑸ꾖采쫒ꇏᆿἲ零鈱롾ꎡᑯ䆍ু䡁곔䌾匛ះⴈի헼팩厔혴?향‐卤㆒踊퐚ჄƊ竑铷길㰖㨙챣㑾훃෋ⷠ˽崀届긔﫚木躋贿삫䕈뷅陻쨳垢ዑԻ偕㉿は軜疮ἣ䰡¢⽘巛氳殜ￂ㧨".toCharArray(), (short)30053, (byte)1, (byte)2)).length();
/*    */     byte b2 = 16;
/*    */     byte b = -1;
/*    */     while (true);
/*    */   }
/*    */   
/*    */   public Optional a(long paramLong, List paramList, lY paramlY, ef paramef, String paramString) {
/*    */     // Byte code:
/*    */     //   0: lload_1
/*    */     //   1: dup2
/*    */     //   2: ldc2_w 39108417017163
/*    */     //   5: lxor
/*    */     //   6: lstore #7
/*    */     //   8: dup2
/*    */     //   9: ldc2_w 22549939773176
/*    */     //   12: lxor
/*    */     //   13: lstore #9
/*    */     //   15: dup2
/*    */     //   16: ldc2_w 70787500493984
/*    */     //   19: lxor
/*    */     //   20: lstore #11
/*    */     //   22: pop2
/*    */     //   23: new java/util/LinkedHashMap
/*    */     //   26: dup
/*    */     //   27: invokespecial <init> : ()V
/*    */     //   30: astore #14
/*    */     //   32: aload #4
/*    */     //   34: aload_0
/*    */     //   35: getfield e : Lme/konsolas/aac/eA;
/*    */     //   38: lload #9
/*    */     //   40: dup2_x1
/*    */     //   41: pop2
/*    */     //   42: ldc2_w 340256454903324286
/*    */     //   45: lload_1
/*    */     //   46: <illegal opcode> b : (Lme/konsolas/aac/lY;JLme/konsolas/aac/eA;JJ)D
/*    */     //   51: dstore #15
/*    */     //   53: aload #4
/*    */     //   55: aload_0
/*    */     //   56: getfield d : Lme/konsolas/aac/eA;
/*    */     //   59: lload #11
/*    */     //   61: ldc2_w 344463551402315107
/*    */     //   64: lload_1
/*    */     //   65: <illegal opcode> b : (Lme/konsolas/aac/lY;Lme/konsolas/aac/eA;JJJ)I
/*    */     //   70: istore #17
/*    */     //   72: iload #17
/*    */     //   74: i2d
/*    */     //   75: dload #15
/*    */     //   77: ldc2_w 0.5
/*    */     //   80: ldc2_w 414425595800444748
/*    */     //   83: lload_1
/*    */     //   84: <illegal opcode> w : (DDJJ)D
/*    */     //   89: ddiv
/*    */     //   90: dstore #18
/*    */     //   92: aload_0
/*    */     //   93: getfield f : Ljava/util/function/DoubleUnaryOperator;
/*    */     //   96: dload #18
/*    */     //   98: ldc2_w 393918399441373073
/*    */     //   101: lload_1
/*    */     //   102: <illegal opcode> b : (Ljava/util/function/DoubleUnaryOperator;DJJ)D
/*    */     //   107: ldc2_w 1000.0
/*    */     //   110: ldc2_w 423779890258894990
/*    */     //   113: lload_1
/*    */     //   114: <illegal opcode> w : (DDJJ)D
/*    */     //   119: dstore #20
/*    */     //   121: aload #14
/*    */     //   123: sipush #11336
/*    */     //   126: ldc2_w 8954652579283518842
/*    */     //   129: lload_1
/*    */     //   130: lxor
/*    */     //   131: <illegal opcode> z : (IJ)Ljava/lang/String;
/*    */     //   136: aload_0
/*    */     //   137: ldc2_w 328938820908178744
/*    */     //   140: lload_1
/*    */     //   141: <illegal opcode> b : (Lme/konsolas/aac/m8;JJ)Ljava/lang/String;
/*    */     //   146: invokeinterface put : (Ljava/lang/Object;Ljava/lang/Object;)Ljava/lang/Object;
/*    */     //   151: pop
/*    */     //   152: aload #14
/*    */     //   154: sipush #3952
/*    */     //   157: ldc2_w 5002039731729884739
/*    */     //   160: lload_1
/*    */     //   161: lxor
/*    */     //   162: <illegal opcode> z : (IJ)Ljava/lang/String;
/*    */     //   167: getstatic java/util/Locale.UK : Ljava/util/Locale;
/*    */     //   170: sipush #6577
/*    */     //   173: ldc2_w 1071199110306295941
/*    */     //   176: lload_1
/*    */     //   177: lxor
/*    */     //   178: <illegal opcode> z : (IJ)Ljava/lang/String;
/*    */     //   183: iconst_1
/*    */     //   184: anewarray java/lang/Object
/*    */     //   187: dup
/*    */     //   188: iconst_0
/*    */     //   189: dload #20
/*    */     //   191: ldc2_w 340189576066490091
/*    */     //   194: lload_1
/*    */     //   195: <illegal opcode> w : (DJJ)Ljava/lang/Double;
/*    */     //   200: aastore
/*    */     //   201: ldc2_w 394174069856740136
/*    */     //   204: lload_1
/*    */     //   205: <illegal opcode> w : (Ljava/util/Locale;Ljava/lang/String;[Ljava/lang/Object;JJ)Ljava/lang/String;
/*    */     //   210: invokeinterface put : (Ljava/lang/Object;Ljava/lang/Object;)Ljava/lang/Object;
/*    */     //   215: pop
/*    */     //   216: aload #14
/*    */     //   218: sipush #25417
/*    */     //   221: ldc2_w 8705023548840315513
/*    */     //   224: lload_1
/*    */     //   225: lxor
/*    */     //   226: <illegal opcode> z : (IJ)Ljava/lang/String;
/*    */     //   231: iload #17
/*    */     //   233: ldc2_w 365847678624198656
/*    */     //   236: lload_1
/*    */     //   237: <illegal opcode> w : (IJJ)Ljava/lang/String;
/*    */     //   242: invokeinterface put : (Ljava/lang/Object;Ljava/lang/Object;)Ljava/lang/Object;
/*    */     //   247: pop
/*    */     //   248: ldc2_w 341268060744998595
/*    */     //   251: lload_1
/*    */     //   252: <illegal opcode> w : (JJ)Z
/*    */     //   257: aload #14
/*    */     //   259: sipush #26576
/*    */     //   262: ldc2_w 2727093957324869350
/*    */     //   265: lload_1
/*    */     //   266: lxor
/*    */     //   267: <illegal opcode> z : (IJ)Ljava/lang/String;
/*    */     //   272: getstatic java/util/Locale.UK : Ljava/util/Locale;
/*    */     //   275: sipush #31295
/*    */     //   278: ldc2_w 969078295610168074
/*    */     //   281: lload_1
/*    */     //   282: lxor
/*    */     //   283: <illegal opcode> z : (IJ)Ljava/lang/String;
/*    */     //   288: iconst_1
/*    */     //   289: anewarray java/lang/Object
/*    */     //   292: dup
/*    */     //   293: iconst_0
/*    */     //   294: dload #15
/*    */     //   296: ldc2_w 340189576066490091
/*    */     //   299: lload_1
/*    */     //   300: <illegal opcode> w : (DJJ)Ljava/lang/Double;
/*    */     //   305: aastore
/*    */     //   306: ldc2_w 394174069856740136
/*    */     //   309: lload_1
/*    */     //   310: <illegal opcode> w : (Ljava/util/Locale;Ljava/lang/String;[Ljava/lang/Object;JJ)Ljava/lang/String;
/*    */     //   315: invokeinterface put : (Ljava/lang/Object;Ljava/lang/Object;)Ljava/lang/Object;
/*    */     //   320: pop
/*    */     //   321: istore #13
/*    */     //   323: aload #14
/*    */     //   325: sipush #5986
/*    */     //   328: ldc2_w 8455007006781668949
/*    */     //   331: lload_1
/*    */     //   332: lxor
/*    */     //   333: <illegal opcode> z : (IJ)Ljava/lang/String;
/*    */     //   338: getstatic java/util/Locale.UK : Ljava/util/Locale;
/*    */     //   341: sipush #31295
/*    */     //   344: ldc2_w 969078295610168074
/*    */     //   347: lload_1
/*    */     //   348: lxor
/*    */     //   349: <illegal opcode> z : (IJ)Ljava/lang/String;
/*    */     //   354: iconst_1
/*    */     //   355: anewarray java/lang/Object
/*    */     //   358: dup
/*    */     //   359: iconst_0
/*    */     //   360: dload #18
/*    */     //   362: ldc2_w 340189576066490091
/*    */     //   365: lload_1
/*    */     //   366: <illegal opcode> w : (DJJ)Ljava/lang/Double;
/*    */     //   371: aastore
/*    */     //   372: ldc2_w 394174069856740136
/*    */     //   375: lload_1
/*    */     //   376: <illegal opcode> w : (Ljava/util/Locale;Ljava/lang/String;[Ljava/lang/Object;JJ)Ljava/lang/String;
/*    */     //   381: invokeinterface put : (Ljava/lang/Object;Ljava/lang/Object;)Ljava/lang/Object;
/*    */     //   386: pop
/*    */     //   387: aload #6
/*    */     //   389: aload #14
/*    */     //   391: dload #20
/*    */     //   393: lload #7
/*    */     //   395: ldc2_w 339672891414467735
/*    */     //   398: lload_1
/*    */     //   399: <illegal opcode> w : (Ljava/lang/String;Ljava/util/Map;DJJJ)Lme/konsolas/aac/ah;
/*    */     //   404: ldc2_w 369840208558991866
/*    */     //   407: lload_1
/*    */     //   408: <illegal opcode> w : (Ljava/lang/Object;JJ)Ljava/util/Optional;
/*    */     //   413: ldc2_w 365494589972169137
/*    */     //   416: lload_1
/*    */     //   417: <illegal opcode> w : (JJ)[Lme/konsolas/aac/aN;
/*    */     //   422: ifnull -> 467
/*    */     //   425: iload #13
/*    */     //   427: ifeq -> 457
/*    */     //   430: goto -> 443
/*    */     //   433: ldc2_w 361076641208461382
/*    */     //   436: lload_1
/*    */     //   437: <illegal opcode> w : (Laacinternal/v;JJ)Laacinternal/v;
/*    */     //   442: athrow
/*    */     //   443: iconst_0
/*    */     //   444: goto -> 458
/*    */     //   447: ldc2_w 361076641208461382
/*    */     //   450: lload_1
/*    */     //   451: <illegal opcode> w : (Laacinternal/v;JJ)Laacinternal/v;
/*    */     //   456: athrow
/*    */     //   457: iconst_1
/*    */     //   458: ldc2_w 327207914562575601
/*    */     //   461: lload_1
/*    */     //   462: <illegal opcode> w : (ZJJ)V
/*    */     //   467: areturn
/*    */     // Line number table:
/*    */     //   Java source line number -> byte code offset
/*    */     //   #7	-> 23
/*    */     //   #11	-> 32
/*    */     //   #10	-> 53
/*    */     //   #2	-> 72
/*    */     //   #1	-> 92
/*    */     //   #3	-> 121
/*    */     //   #12	-> 152
/*    */     //   #16	-> 216
/*    */     //   #4	-> 257
/*    */     //   #6	-> 323
/*    */     //   #9	-> 387
/*    */     // Exception table:
/*    */     //   from	to	target	type
/*    */     //   323	430	433	aacinternal/v
/*    */     //   425	447	447	aacinternal/v
/*    */   }
/*    */ }


/* Location:              C:\Users\BukkitBypass\Desktop\MatrixAC\AAC\AAC-spigot-5.2.0.jar!\me\konsolas\aac\mq.class
 * Java compiler version: 8 (52.0)
 * JD-Core Version:       1.1.3
 */