/*    */ package me.konsolas.aac;public class mt {
/*    */   private static final Set h;
/*    */   private final Material e;
/*    */   
/*    */   public k5 a() {
/*  6 */     return this.b;
/*    */   }
/*    */   private final float c; private final k5 b; private final int g; private final BlockFace d; private final boolean f;
/*    */   private final hO a;
/*    */   private static final long i;
/*    */   
/*    */   public float a() {
/* 13 */     return this.c;
/*    */   }
/*    */ 
/*    */ 
/*    */ 
/*    */ 
/*    */ 
/*    */ 
/*    */ 
/*    */   
/*    */   public Material a() {
/* 24 */     return this.e;
/*    */   }
/*    */ 
/*    */ 
/*    */ 
/*    */ 
/*    */ 
/*    */ 
/*    */ 
/*    */ 
/*    */ 
/*    */ 
/*    */ 
/*    */ 
/*    */ 
/*    */ 
/*    */ 
/*    */ 
/*    */ 
/*    */ 
/*    */ 
/*    */ 
/*    */ 
/*    */ 
/*    */ 
/*    */ 
/*    */ 
/*    */ 
/*    */ 
/*    */ 
/*    */ 
/*    */ 
/*    */ 
/*    */ 
/*    */ 
/*    */ 
/*    */ 
/*    */   
/*    */   mt(Material paramMaterial, float paramFloat, k5 paramk5, int paramInt, BlockFace paramBlockFace, boolean paramBoolean) {
/* 63 */     this.e = paramMaterial;
/*    */     this.c = paramFloat;
/*    */     this.b = paramk5;
/*    */     this.g = paramInt;
/*    */     this.d = paramBlockFace;
/*    */     this.f = paramBoolean;
/*    */     this.a = ha.a();
/*    */   }
/*    */   
/*    */   public BlockFace a() {
/*    */     return this.d;
/*    */   }
/*    */   
/*    */   public boolean a() {
/*    */     return this.f;
/*    */   }
/*    */   
/*    */   public int a() {
/*    */     return this.g;
/*    */   }
/*    */   
/*    */   static {
/*    */     byte b1;
/*    */     long l;
/*    */     for (i = nc.a(-5423025879206409870L, -1479040908352649110L, MethodHandles.lookup().lookupClass()).a(190826758713772L), l = i ^ 0xA215672245EL, "Όꎂ絊轁撷퀗莟爥纼ኖ僼뺋㛭㸛蓸暺?觭撆ᑽ".toCharArray()[8] = (char)("Όꎂ絊轁撷퀗莟爥纼ኖ僼뺋㛭㸛蓸暺?觭撆ᑽ".toCharArray()[8] ^ 0x8BF), "也籆䅴᭪".toCharArray()[1] = (char)("也籆䅴᭪".toCharArray()[1] ^ 0x899), (new byte[8])[0] = (byte)(int)(l >>> 56L), b1 = 1; b1 < 8; ) {
/*    */       (new byte[8])[b1] = (byte)(int)(l << b1 * 8 >>> 56L);
/*    */       b1++;
/*    */     } 
/*    */     Cipher cipher;
/*    */     (cipher = Cipher.getInstance(fW$gy.A("Όꎂ絊轁撷퀗莟爥纼ኖ僼뺋㛭㸛蓸暺?觭撆ᑽ".toCharArray(), (short)980, true, 1))).init(2, SecretKeyFactory.getInstance(fW$gy.A("也籆䅴᭪".toCharArray(), (short)15069, true, 4)).generateSecret(new DESKeySpec(new byte[8])), new IvParameterSpec(new byte[8]));
/*    */     String[] arrayOfString = new String[9];
/*    */     boolean bool = false;
/*    */     "띰봤뷶巜Ⓘﻐ쾣髅⾂ᨁⰈ取೫賅ￗ㨚졕ㆆ✆ꂃ䤶ﬁ㋋蚐ꆹ외飙诫롸笢䳂ꍍ妝滊묲뭗璭௰䷕滬ၼ掯쥤至⿽ጽ鋅賻坂ꜭꔋ낿뼌滬㴪⳺쑇₨㏾냰㜞ꁓᑲ蝫偺臘掸궈鸶郂钢꽭ᠳ鱍㋿欺羚粽╱ꮊ⟊旘꨷鳤嗾暀➗춶ꞝᇑ⠱넗퍔讷쯺舴戲輺뒼⽦Ꭸ⫍坲綷".toCharArray()[108] = (char)("띰봤뷶巜Ⓘﻐ쾣髅⾂ᨁⰈ取೫賅ￗ㨚졕ㆆ✆ꂃ䤶ﬁ㋋蚐ꆹ외飙诫롸笢䳂ꍍ妝滊묲뭗璭௰䷕滬ၼ掯쥤至⿽ጽ鋅賻坂ꜭꔋ낿뼌滬㴪⳺쑇₨㏾냰㜞ꁓᑲ蝫偺臘掸궈鸶郂钢꽭ᠳ鱍㋿欺羚粽╱ꮊ⟊旘꨷鳤嗾暀➗춶ꞝᇑ⠱넗퍔讷쯺舴戲輺뒼⽦Ꭸ⫍坲綷".toCharArray()[108] ^ 0x35C);
/*    */     String str;
/*    */     int i = (str = fW$gy.A("띰봤뷶巜Ⓘﻐ쾣髅⾂ᨁⰈ取೫賅ￗ㨚졕ㆆ✆ꂃ䤶ﬁ㋋蚐ꆹ외飙诫롸笢䳂ꍍ妝滊묲뭗璭௰䷕滬ၼ掯쥤至⿽ጽ鋅賻坂ꜭꔋ낿뼌滬㴪⳺쑇₨㏾냰㜞ꁓᑲ蝫偺臘掸궈鸶郂钢꽭ᠳ鱍㋿欺羚粽╱ꮊ⟊旘꨷鳤嗾暀➗춶ꞝᇑ⠱넗퍔讷쯺舴戲輺뒼⽦Ꭸ⫍坲綷".toCharArray(), (short)14154, false, 0)).length();
/*    */     byte b3 = 16;
/*    */     byte b2 = -1;
/*    */     while (true);
/*    */     byte b4 = -1;
/*    */     continue;
/*    */   }
/*    */   
/*    */   public hO a() {
/*    */     return this.a;
/*    */   }
/*    */   
/*    */   mt(Player paramPlayer, short paramShort, int paramInt, char paramChar, Block paramBlock, kP paramkP) {
/*    */     // Byte code:
/*    */     //   0: iload_2
/*    */     //   1: i2l
/*    */     //   2: bipush #48
/*    */     //   4: lshl
/*    */     //   5: iload_3
/*    */     //   6: i2l
/*    */     //   7: bipush #32
/*    */     //   9: lshl
/*    */     //   10: bipush #16
/*    */     //   12: lushr
/*    */     //   13: lor
/*    */     //   14: iload #4
/*    */     //   16: i2l
/*    */     //   17: bipush #48
/*    */     //   19: lshl
/*    */     //   20: bipush #48
/*    */     //   22: lushr
/*    */     //   23: lor
/*    */     //   24: getstatic me/konsolas/aac/mt.i : J
/*    */     //   27: lxor
/*    */     //   28: lstore #7
/*    */     //   30: lload #7
/*    */     //   32: dup2
/*    */     //   33: ldc2_w 104797221769194
/*    */     //   36: lxor
/*    */     //   37: lstore #9
/*    */     //   39: dup2
/*    */     //   40: ldc2_w 62902299142890
/*    */     //   43: lxor
/*    */     //   44: lstore #11
/*    */     //   46: dup2
/*    */     //   47: ldc2_w 75609705964458
/*    */     //   50: lxor
/*    */     //   51: lstore #13
/*    */     //   53: pop2
/*    */     //   54: ldc2_w -5983756625555188859
/*    */     //   57: lload #7
/*    */     //   59: <illegal opcode> w : (JJ)Ljava/lang/String;
/*    */     //   64: aload_0
/*    */     //   65: invokespecial <init> : ()V
/*    */     //   68: aload_0
/*    */     //   69: aload #5
/*    */     //   71: invokeinterface getType : ()Lorg/bukkit/Material;
/*    */     //   76: putfield e : Lorg/bukkit/Material;
/*    */     //   79: astore #15
/*    */     //   81: aload_0
/*    */     //   82: invokestatic a : ()Lme/konsolas/aac/mJ;
/*    */     //   85: lload #9
/*    */     //   87: aload #5
/*    */     //   89: invokeinterface a : (JLorg/bukkit/block/Block;)F
/*    */     //   94: putfield c : F
/*    */     //   97: invokestatic a : ()Lme/konsolas/aac/kP;
/*    */     //   100: lload #11
/*    */     //   102: getstatic me/konsolas/aac/kP.V1_13 : Lme/konsolas/aac/kP;
/*    */     //   105: invokevirtual a : (JLme/konsolas/aac/kP;)Z
/*    */     //   108: aload #15
/*    */     //   110: ifnull -> 605
/*    */     //   113: ifeq -> 584
/*    */     //   116: goto -> 130
/*    */     //   119: ldc2_w -5990527199959302541
/*    */     //   122: lload #7
/*    */     //   124: <illegal opcode> w : (Ljava/lang/IllegalArgumentException;JJ)Ljava/lang/IllegalArgumentException;
/*    */     //   129: athrow
/*    */     //   130: aload #6
/*    */     //   132: lload #11
/*    */     //   134: getstatic me/konsolas/aac/kP.V1_13 : Lme/konsolas/aac/kP;
/*    */     //   137: invokevirtual a : (JLme/konsolas/aac/kP;)Z
/*    */     //   140: aload #15
/*    */     //   142: ifnull -> 393
/*    */     //   145: goto -> 159
/*    */     //   148: ldc2_w -5990527199959302541
/*    */     //   151: lload #7
/*    */     //   153: <illegal opcode> w : (Ljava/lang/IllegalArgumentException;JJ)Ljava/lang/IllegalArgumentException;
/*    */     //   158: athrow
/*    */     //   159: iload_3
/*    */     //   160: iflt -> 379
/*    */     //   163: ifeq -> 372
/*    */     //   166: goto -> 180
/*    */     //   169: ldc2_w -5990527199959302541
/*    */     //   172: lload #7
/*    */     //   174: <illegal opcode> w : (Ljava/lang/IllegalArgumentException;JJ)Ljava/lang/IllegalArgumentException;
/*    */     //   179: athrow
/*    */     //   180: getstatic me/konsolas/aac/mt.h : Ljava/util/Set;
/*    */     //   183: aload_0
/*    */     //   184: invokevirtual a : ()Lorg/bukkit/Material;
/*    */     //   187: invokeinterface contains : (Ljava/lang/Object;)Z
/*    */     //   192: aload #15
/*    */     //   194: iload_3
/*    */     //   195: iflt -> 258
/*    */     //   198: ifnull -> 256
/*    */     //   201: goto -> 215
/*    */     //   204: ldc2_w -5990527199959302541
/*    */     //   207: lload #7
/*    */     //   209: <illegal opcode> w : (Ljava/lang/IllegalArgumentException;JJ)Ljava/lang/IllegalArgumentException;
/*    */     //   214: athrow
/*    */     //   215: ifne -> 337
/*    */     //   218: goto -> 232
/*    */     //   221: ldc2_w -5990527199959302541
/*    */     //   224: lload #7
/*    */     //   226: <illegal opcode> w : (Ljava/lang/IllegalArgumentException;JJ)Ljava/lang/IllegalArgumentException;
/*    */     //   231: athrow
/*    */     //   232: aload #5
/*    */     //   234: invokeinterface getBlockData : ()Lorg/bukkit/block/data/BlockData;
/*    */     //   239: instanceof org/bukkit/block/data/Waterlogged
/*    */     //   242: goto -> 256
/*    */     //   245: ldc2_w -5990527199959302541
/*    */     //   248: lload #7
/*    */     //   250: <illegal opcode> w : (Ljava/lang/IllegalArgumentException;JJ)Ljava/lang/IllegalArgumentException;
/*    */     //   255: athrow
/*    */     //   256: aload #15
/*    */     //   258: ifnull -> 393
/*    */     //   261: ifeq -> 372
/*    */     //   264: goto -> 278
/*    */     //   267: ldc2_w -5990527199959302541
/*    */     //   270: lload #7
/*    */     //   272: <illegal opcode> w : (Ljava/lang/IllegalArgumentException;JJ)Ljava/lang/IllegalArgumentException;
/*    */     //   277: athrow
/*    */     //   278: aload #5
/*    */     //   280: invokeinterface getBlockData : ()Lorg/bukkit/block/data/BlockData;
/*    */     //   285: checkcast org/bukkit/block/data/Waterlogged
/*    */     //   288: invokeinterface isWaterlogged : ()Z
/*    */     //   293: aload #15
/*    */     //   295: iload_2
/*    */     //   296: iflt -> 399
/*    */     //   299: ifnull -> 393
/*    */     //   302: goto -> 316
/*    */     //   305: ldc2_w -5990527199959302541
/*    */     //   308: lload #7
/*    */     //   310: <illegal opcode> w : (Ljava/lang/IllegalArgumentException;JJ)Ljava/lang/IllegalArgumentException;
/*    */     //   315: athrow
/*    */     //   316: iload_3
/*    */     //   317: iflt -> 379
/*    */     //   320: ifeq -> 372
/*    */     //   323: goto -> 337
/*    */     //   326: ldc2_w -5990527199959302541
/*    */     //   329: lload #7
/*    */     //   331: <illegal opcode> w : (Ljava/lang/IllegalArgumentException;JJ)Ljava/lang/IllegalArgumentException;
/*    */     //   336: athrow
/*    */     //   337: aload_0
/*    */     //   338: getstatic me/konsolas/aac/k5.WATER : Lme/konsolas/aac/k5;
/*    */     //   341: putfield b : Lme/konsolas/aac/k5;
/*    */     //   344: aload_0
/*    */     //   345: iconst_0
/*    */     //   346: putfield g : I
/*    */     //   349: iload_3
/*    */     //   350: ifle -> 706
/*    */     //   353: aload #15
/*    */     //   355: ifnonnull -> 706
/*    */     //   358: goto -> 372
/*    */     //   361: ldc2_w -5990527199959302541
/*    */     //   364: lload #7
/*    */     //   366: <illegal opcode> w : (Ljava/lang/IllegalArgumentException;JJ)Ljava/lang/IllegalArgumentException;
/*    */     //   371: athrow
/*    */     //   372: aload #5
/*    */     //   374: invokeinterface isLiquid : ()Z
/*    */     //   379: goto -> 393
/*    */     //   382: ldc2_w -5990527199959302541
/*    */     //   385: lload #7
/*    */     //   387: <illegal opcode> w : (Ljava/lang/IllegalArgumentException;JJ)Ljava/lang/IllegalArgumentException;
/*    */     //   392: athrow
/*    */     //   393: iload_2
/*    */     //   394: iflt -> 462
/*    */     //   397: aload #15
/*    */     //   399: ifnull -> 462
/*    */     //   402: ifeq -> 551
/*    */     //   405: goto -> 419
/*    */     //   408: ldc2_w -5990527199959302541
/*    */     //   411: lload #7
/*    */     //   413: <illegal opcode> w : (Ljava/lang/IllegalArgumentException;JJ)Ljava/lang/IllegalArgumentException;
/*    */     //   418: athrow
/*    */     //   419: aload #5
/*    */     //   421: invokeinterface getBlockData : ()Lorg/bukkit/block/data/BlockData;
/*    */     //   426: aload #15
/*    */     //   428: ifnull -> 486
/*    */     //   431: goto -> 445
/*    */     //   434: ldc2_w -5990527199959302541
/*    */     //   437: lload #7
/*    */     //   439: <illegal opcode> w : (Ljava/lang/IllegalArgumentException;JJ)Ljava/lang/IllegalArgumentException;
/*    */     //   444: athrow
/*    */     //   445: instanceof org/bukkit/block/data/Levelled
/*    */     //   448: goto -> 462
/*    */     //   451: ldc2_w -5990527199959302541
/*    */     //   454: lload #7
/*    */     //   456: <illegal opcode> w : (Ljava/lang/IllegalArgumentException;JJ)Ljava/lang/IllegalArgumentException;
/*    */     //   461: athrow
/*    */     //   462: ifeq -> 551
/*    */     //   465: aload #5
/*    */     //   467: invokeinterface getBlockData : ()Lorg/bukkit/block/data/BlockData;
/*    */     //   472: goto -> 486
/*    */     //   475: ldc2_w -5990527199959302541
/*    */     //   478: lload #7
/*    */     //   480: <illegal opcode> w : (Ljava/lang/IllegalArgumentException;JJ)Ljava/lang/IllegalArgumentException;
/*    */     //   485: athrow
/*    */     //   486: checkcast org/bukkit/block/data/Levelled
/*    */     //   489: astore #16
/*    */     //   491: aload_0
/*    */     //   492: getstatic me/konsolas/aac/ei.LAVA : Ljava/util/Set;
/*    */     //   495: aload_0
/*    */     //   496: invokevirtual a : ()Lorg/bukkit/Material;
/*    */     //   499: invokeinterface contains : (Ljava/lang/Object;)Z
/*    */     //   504: ifeq -> 524
/*    */     //   507: getstatic me/konsolas/aac/k5.LAVA : Lme/konsolas/aac/k5;
/*    */     //   510: goto -> 527
/*    */     //   513: ldc2_w -5990527199959302541
/*    */     //   516: lload #7
/*    */     //   518: <illegal opcode> w : (Ljava/lang/IllegalArgumentException;JJ)Ljava/lang/IllegalArgumentException;
/*    */     //   523: athrow
/*    */     //   524: getstatic me/konsolas/aac/k5.WATER : Lme/konsolas/aac/k5;
/*    */     //   527: putfield b : Lme/konsolas/aac/k5;
/*    */     //   530: aload_0
/*    */     //   531: aload #16
/*    */     //   533: invokeinterface getLevel : ()I
/*    */     //   538: putfield g : I
/*    */     //   541: iload #4
/*    */     //   543: ifle -> 706
/*    */     //   546: aload #15
/*    */     //   548: ifnonnull -> 706
/*    */     //   551: aload_0
/*    */     //   552: aconst_null
/*    */     //   553: putfield b : Lme/konsolas/aac/k5;
/*    */     //   556: aload_0
/*    */     //   557: iconst_m1
/*    */     //   558: putfield g : I
/*    */     //   561: iload_2
/*    */     //   562: iflt -> 706
/*    */     //   565: aload #15
/*    */     //   567: ifnonnull -> 706
/*    */     //   570: goto -> 584
/*    */     //   573: ldc2_w -5990527199959302541
/*    */     //   576: lload #7
/*    */     //   578: <illegal opcode> w : (Ljava/lang/IllegalArgumentException;JJ)Ljava/lang/IllegalArgumentException;
/*    */     //   583: athrow
/*    */     //   584: aload #5
/*    */     //   586: invokeinterface isLiquid : ()Z
/*    */     //   591: goto -> 605
/*    */     //   594: ldc2_w -5990527199959302541
/*    */     //   597: lload #7
/*    */     //   599: <illegal opcode> w : (Ljava/lang/IllegalArgumentException;JJ)Ljava/lang/IllegalArgumentException;
/*    */     //   604: athrow
/*    */     //   605: ifeq -> 682
/*    */     //   608: aload_0
/*    */     //   609: getstatic me/konsolas/aac/ei.LAVA : Ljava/util/Set;
/*    */     //   612: aload_0
/*    */     //   613: invokevirtual a : ()Lorg/bukkit/Material;
/*    */     //   616: invokeinterface contains : (Ljava/lang/Object;)Z
/*    */     //   621: ifeq -> 655
/*    */     //   624: goto -> 638
/*    */     //   627: ldc2_w -5990527199959302541
/*    */     //   630: lload #7
/*    */     //   632: <illegal opcode> w : (Ljava/lang/IllegalArgumentException;JJ)Ljava/lang/IllegalArgumentException;
/*    */     //   637: athrow
/*    */     //   638: getstatic me/konsolas/aac/k5.LAVA : Lme/konsolas/aac/k5;
/*    */     //   641: goto -> 658
/*    */     //   644: ldc2_w -5990527199959302541
/*    */     //   647: lload #7
/*    */     //   649: <illegal opcode> w : (Ljava/lang/IllegalArgumentException;JJ)Ljava/lang/IllegalArgumentException;
/*    */     //   654: athrow
/*    */     //   655: getstatic me/konsolas/aac/k5.WATER : Lme/konsolas/aac/k5;
/*    */     //   658: putfield b : Lme/konsolas/aac/k5;
/*    */     //   661: aload_0
/*    */     //   662: aload #5
/*    */     //   664: invokeinterface getData : ()B
/*    */     //   669: putfield g : I
/*    */     //   672: iload #4
/*    */     //   674: iflt -> 706
/*    */     //   677: aload #15
/*    */     //   679: ifnonnull -> 706
/*    */     //   682: aload_0
/*    */     //   683: aconst_null
/*    */     //   684: putfield b : Lme/konsolas/aac/k5;
/*    */     //   687: aload_0
/*    */     //   688: iconst_m1
/*    */     //   689: putfield g : I
/*    */     //   692: goto -> 706
/*    */     //   695: ldc2_w -5990527199959302541
/*    */     //   698: lload #7
/*    */     //   700: <illegal opcode> w : (Ljava/lang/IllegalArgumentException;JJ)Ljava/lang/IllegalArgumentException;
/*    */     //   705: athrow
/*    */     //   706: getstatic me/konsolas/aac/ei.TRAPDOORS : Ljava/util/Set;
/*    */     //   709: aload_0
/*    */     //   710: invokevirtual a : ()Lorg/bukkit/Material;
/*    */     //   713: invokeinterface contains : (Ljava/lang/Object;)Z
/*    */     //   718: aload #15
/*    */     //   720: ifnull -> 765
/*    */     //   723: ifeq -> 858
/*    */     //   726: goto -> 740
/*    */     //   729: ldc2_w -5990527199959302541
/*    */     //   732: lload #7
/*    */     //   734: <illegal opcode> w : (Ljava/lang/IllegalArgumentException;JJ)Ljava/lang/IllegalArgumentException;
/*    */     //   739: athrow
/*    */     //   740: invokestatic a : ()Lme/konsolas/aac/kP;
/*    */     //   743: lload #11
/*    */     //   745: getstatic me/konsolas/aac/kP.V1_13 : Lme/konsolas/aac/kP;
/*    */     //   748: invokevirtual a : (JLme/konsolas/aac/kP;)Z
/*    */     //   751: goto -> 765
/*    */     //   754: ldc2_w -5990527199959302541
/*    */     //   757: lload #7
/*    */     //   759: <illegal opcode> w : (Ljava/lang/IllegalArgumentException;JJ)Ljava/lang/IllegalArgumentException;
/*    */     //   764: athrow
/*    */     //   765: ifeq -> 811
/*    */     //   768: aload #5
/*    */     //   770: invokeinterface getBlockData : ()Lorg/bukkit/block/data/BlockData;
/*    */     //   775: checkcast org/bukkit/block/data/type/TrapDoor
/*    */     //   778: astore #16
/*    */     //   780: aload_0
/*    */     //   781: aload #16
/*    */     //   783: invokeinterface getFacing : ()Lorg/bukkit/block/BlockFace;
/*    */     //   788: putfield d : Lorg/bukkit/block/BlockFace;
/*    */     //   791: aload_0
/*    */     //   792: aload #16
/*    */     //   794: invokeinterface isOpen : ()Z
/*    */     //   799: putfield f : Z
/*    */     //   802: iload_2
/*    */     //   803: iflt -> 1050
/*    */     //   806: aload #15
/*    */     //   808: ifnonnull -> 1032
/*    */     //   811: new org/bukkit/material/TrapDoor
/*    */     //   814: dup
/*    */     //   815: aload_0
/*    */     //   816: invokevirtual a : ()Lorg/bukkit/Material;
/*    */     //   819: aload #5
/*    */     //   821: invokeinterface getData : ()B
/*    */     //   826: invokespecial <init> : (Lorg/bukkit/Material;B)V
/*    */     //   829: astore #16
/*    */     //   831: aload_0
/*    */     //   832: aload #16
/*    */     //   834: invokevirtual getFacing : ()Lorg/bukkit/block/BlockFace;
/*    */     //   837: putfield d : Lorg/bukkit/block/BlockFace;
/*    */     //   840: aload_0
/*    */     //   841: aload #16
/*    */     //   843: invokevirtual isOpen : ()Z
/*    */     //   846: putfield f : Z
/*    */     //   849: iload_3
/*    */     //   850: ifle -> 1050
/*    */     //   853: aload #15
/*    */     //   855: ifnonnull -> 1032
/*    */     //   858: aload_0
/*    */     //   859: aload #15
/*    */     //   861: ifnull -> 1028
/*    */     //   864: goto -> 878
/*    */     //   867: ldc2_w -5990527199959302541
/*    */     //   870: lload #7
/*    */     //   872: <illegal opcode> w : (Ljava/lang/IllegalArgumentException;JJ)Ljava/lang/IllegalArgumentException;
/*    */     //   877: athrow
/*    */     //   878: iload_3
/*    */     //   879: iflt -> 1014
/*    */     //   882: invokevirtual a : ()Lorg/bukkit/Material;
/*    */     //   885: getstatic org/bukkit/Material.LADDER : Lorg/bukkit/Material;
/*    */     //   888: if_acmpne -> 1008
/*    */     //   891: goto -> 905
/*    */     //   894: ldc2_w -5990527199959302541
/*    */     //   897: lload #7
/*    */     //   899: <illegal opcode> w : (Ljava/lang/IllegalArgumentException;JJ)Ljava/lang/IllegalArgumentException;
/*    */     //   904: athrow
/*    */     //   905: invokestatic a : ()Lme/konsolas/aac/kP;
/*    */     //   908: lload #11
/*    */     //   910: getstatic me/konsolas/aac/kP.V1_13 : Lme/konsolas/aac/kP;
/*    */     //   913: invokevirtual a : (JLme/konsolas/aac/kP;)Z
/*    */     //   916: ifeq -> 965
/*    */     //   919: goto -> 933
/*    */     //   922: ldc2_w -5990527199959302541
/*    */     //   925: lload #7
/*    */     //   927: <illegal opcode> w : (Ljava/lang/IllegalArgumentException;JJ)Ljava/lang/IllegalArgumentException;
/*    */     //   932: athrow
/*    */     //   933: aload #5
/*    */     //   935: invokeinterface getBlockData : ()Lorg/bukkit/block/data/BlockData;
/*    */     //   940: checkcast org/bukkit/block/data/type/Ladder
/*    */     //   943: astore #16
/*    */     //   945: aload_0
/*    */     //   946: aload #16
/*    */     //   948: invokeinterface getFacing : ()Lorg/bukkit/block/BlockFace;
/*    */     //   953: putfield d : Lorg/bukkit/block/BlockFace;
/*    */     //   956: aload #15
/*    */     //   958: iload_2
/*    */     //   959: iflt -> 1005
/*    */     //   962: ifnonnull -> 994
/*    */     //   965: new org/bukkit/material/Ladder
/*    */     //   968: dup
/*    */     //   969: aload_0
/*    */     //   970: invokevirtual a : ()Lorg/bukkit/Material;
/*    */     //   973: aload #5
/*    */     //   975: invokeinterface getData : ()B
/*    */     //   980: invokespecial <init> : (Lorg/bukkit/Material;B)V
/*    */     //   983: astore #16
/*    */     //   985: aload_0
/*    */     //   986: aload #16
/*    */     //   988: invokevirtual getFacing : ()Lorg/bukkit/block/BlockFace;
/*    */     //   991: putfield d : Lorg/bukkit/block/BlockFace;
/*    */     //   994: aload_0
/*    */     //   995: iconst_0
/*    */     //   996: putfield f : Z
/*    */     //   999: iload_3
/*    */     //   1000: iflt -> 1050
/*    */     //   1003: aload #15
/*    */     //   1005: ifnonnull -> 1032
/*    */     //   1008: aload_0
/*    */     //   1009: aconst_null
/*    */     //   1010: putfield d : Lorg/bukkit/block/BlockFace;
/*    */     //   1013: aload_0
/*    */     //   1014: goto -> 1028
/*    */     //   1017: ldc2_w -5990527199959302541
/*    */     //   1020: lload #7
/*    */     //   1022: <illegal opcode> w : (Ljava/lang/IllegalArgumentException;JJ)Ljava/lang/IllegalArgumentException;
/*    */     //   1027: athrow
/*    */     //   1028: iconst_0
/*    */     //   1029: putfield f : Z
/*    */     //   1032: aload_0
/*    */     //   1033: aload_1
/*    */     //   1034: aload #5
/*    */     //   1036: aload_0
/*    */     //   1037: invokevirtual a : ()Lorg/bukkit/Material;
/*    */     //   1040: aload #6
/*    */     //   1042: lload #13
/*    */     //   1044: invokestatic a : (Lorg/bukkit/entity/Entity;Lorg/bukkit/block/Block;Lorg/bukkit/Material;Lme/konsolas/aac/kP;J)Lme/konsolas/aac/hO;
/*    */     //   1047: putfield a : Lme/konsolas/aac/hO;
/*    */     //   1050: return
/*    */     // Line number table:
/*    */     //   Java source line number -> byte code offset
/*    */     //   #61	-> 64
/*    */     //   #39	-> 68
/*    */     //   #19	-> 81
/*    */     //   #8	-> 97
/*    */     //   #43	-> 130
/*    */     //   #62	-> 234
/*    */     //   #14	-> 337
/*    */     //   #3	-> 344
/*    */     //   #7	-> 372
/*    */     //   #46	-> 465
/*    */     //   #26	-> 491
/*    */     //   #36	-> 530
/*    */     //   #33	-> 541
/*    */     //   #30	-> 551
/*    */     //   #54	-> 556
/*    */     //   #18	-> 584
/*    */     //   #1	-> 608
/*    */     //   #38	-> 661
/*    */     //   #32	-> 682
/*    */     //   #4	-> 687
/*    */     //   #2	-> 706
/*    */     //   #25	-> 740
/*    */     //   #65	-> 768
/*    */     //   #9	-> 780
/*    */     //   #40	-> 791
/*    */     //   #45	-> 802
/*    */     //   #48	-> 811
/*    */     //   #47	-> 831
/*    */     //   #5	-> 840
/*    */     //   #23	-> 849
/*    */     //   #57	-> 858
/*    */     //   #58	-> 905
/*    */     //   #16	-> 933
/*    */     //   #28	-> 945
/*    */     //   #15	-> 956
/*    */     //   #31	-> 965
/*    */     //   #20	-> 985
/*    */     //   #12	-> 994
/*    */     //   #21	-> 1008
/*    */     //   #10	-> 1013
/*    */     //   #60	-> 1032
/*    */     //   #64	-> 1050
/*    */     // Exception table:
/*    */     //   from	to	target	type
/*    */     //   81	116	119	java/lang/IllegalArgumentException
/*    */     //   113	145	148	java/lang/IllegalArgumentException
/*    */     //   130	166	169	java/lang/IllegalArgumentException
/*    */     //   159	201	204	java/lang/IllegalArgumentException
/*    */     //   180	218	221	java/lang/IllegalArgumentException
/*    */     //   215	242	245	java/lang/IllegalArgumentException
/*    */     //   256	264	267	java/lang/IllegalArgumentException
/*    */     //   261	302	305	java/lang/IllegalArgumentException
/*    */     //   278	323	326	java/lang/IllegalArgumentException
/*    */     //   316	358	361	java/lang/IllegalArgumentException
/*    */     //   337	379	382	java/lang/IllegalArgumentException
/*    */     //   393	405	408	java/lang/IllegalArgumentException
/*    */     //   402	431	434	java/lang/IllegalArgumentException
/*    */     //   419	448	451	java/lang/IllegalArgumentException
/*    */     //   462	472	475	java/lang/IllegalArgumentException
/*    */     //   491	513	513	java/lang/IllegalArgumentException
/*    */     //   527	570	573	java/lang/IllegalArgumentException
/*    */     //   551	591	594	java/lang/IllegalArgumentException
/*    */     //   605	624	627	java/lang/IllegalArgumentException
/*    */     //   608	644	644	java/lang/IllegalArgumentException
/*    */     //   658	692	695	java/lang/IllegalArgumentException
/*    */     //   706	726	729	java/lang/IllegalArgumentException
/*    */     //   723	751	754	java/lang/IllegalArgumentException
/*    */     //   831	864	867	java/lang/IllegalArgumentException
/*    */     //   858	891	894	java/lang/IllegalArgumentException
/*    */     //   878	919	922	java/lang/IllegalArgumentException
/*    */     //   994	1014	1017	java/lang/IllegalArgumentException
/*    */   }
/*    */   
/*    */   private static IllegalArgumentException a(IllegalArgumentException paramIllegalArgumentException) {
/*    */     return paramIllegalArgumentException;
/*    */   }
/*    */   
/*    */   private static String a(byte[] paramArrayOfbyte) {
/*    */     byte b1 = 0;
/*    */     int i;
/*    */     char[] arrayOfChar = new char[i = paramArrayOfbyte.length];
/*    */     for (byte b2 = 0; b2 < i; b2++) {
/*    */       int j;
/*    */       if ((j = 0xFF & paramArrayOfbyte[b2]) < 192) {
/*    */         arrayOfChar[b1++] = (char)j;
/*    */       } else if (j < 224) {
/*    */         char c = (char)((char)(j & 0x1F) << 6);
/*    */         j = paramArrayOfbyte[++b2];
/*    */         c = (char)(c | (char)(j & 0x3F));
/*    */         arrayOfChar[b1++] = c;
/*    */       } else if (b2 < i - 2) {
/*    */         char c = (char)((char)(j & 0xF) << 12);
/*    */         j = paramArrayOfbyte[++b2];
/*    */         c = (char)(c | (char)(j & 0x3F) << 6);
/*    */         j = paramArrayOfbyte[++b2];
/*    */         c = (char)(c | (char)(j & 0x3F));
/*    */         arrayOfChar[b1++] = c;
/*    */       } 
/*    */     } 
/*    */     return new String(arrayOfChar, 0, b1);
/*    */   }
/*    */ }


/* Location:              C:\Users\BukkitBypass\Desktop\MatrixAC\AAC\AAC-spigot-5.2.0.jar!\me\konsolas\aac\mt.class
 * Java compiler version: 8 (52.0)
 * JD-Core Version:       1.1.3
 */