/*  1 */ package me.konsolas.aac;public final class s { final l6 g; final String b; final J f; @Nullable final jR a; final Map e; public List a(String paramString, long paramLong) { paramLong = h ^ paramLong; long l = paramLong ^ 0xDBDC6141345L; return this.f.a(paramString, l); } @Nullable
/*  2 */   private volatile b0 c; private static aN[] d; private static final long h; private static final String[] i; private static final String[] j; private static final Map k; public String a() { return this.b; }
/*  3 */   public l6 a() { return this.g; }
/*    */   @Nullable
/*  5 */   public jR a() { return this.a; } public b0 a(int paramInt1, char paramChar, int paramInt2) { // Byte code:
/*    */     //   0: iload_1
/*    */     //   1: i2l
/*    */     //   2: bipush #32
/*    */     //   4: lshl
/*    */     //   5: iload_2
/*    */     //   6: i2l
/*    */     //   7: bipush #48
/*    */     //   9: lshl
/*    */     //   10: bipush #32
/*    */     //   12: lushr
/*    */     //   13: lor
/*    */     //   14: iload_3
/*    */     //   15: i2l
/*    */     //   16: bipush #48
/*    */     //   18: lshl
/*    */     //   19: bipush #48
/*    */     //   21: lushr
/*    */     //   22: lor
/*    */     //   23: getstatic me/konsolas/aac/s.h : J
/*    */     //   26: lxor
/*    */     //   27: lstore #4
/*    */     //   29: lload #4
/*    */     //   31: dup2
/*    */     //   32: ldc2_w 3936600205512
/*    */     //   35: lxor
/*    */     //   36: lstore #6
/*    */     //   38: pop2
/*    */     //   39: ldc2_w 1854330547717282169
/*    */     //   42: lload #4
/*    */     //   44: <illegal opcode> w : (JJ)[Lme/konsolas/aac/aN;
/*    */     //   49: aload_0
/*    */     //   50: getfield c : Lme/konsolas/aac/b0;
/*    */     //   53: astore #9
/*    */     //   55: astore #8
/*    */     //   57: aload #9
/*    */     //   59: aload #8
/*    */     //   61: ifnonnull -> 83
/*    */     //   64: ifnull -> 86
/*    */     //   67: goto -> 81
/*    */     //   70: ldc2_w 1851137816680942798
/*    */     //   73: lload #4
/*    */     //   75: <illegal opcode> w : (Laacinternal/v;JJ)Laacinternal/v;
/*    */     //   80: athrow
/*    */     //   81: aload #9
/*    */     //   83: goto -> 100
/*    */     //   86: aload_0
/*    */     //   87: aload_0
/*    */     //   88: getfield f : Lme/konsolas/aac/J;
/*    */     //   91: lload #6
/*    */     //   93: invokestatic a : (Lme/konsolas/aac/J;J)Lme/konsolas/aac/b0;
/*    */     //   96: dup_x1
/*    */     //   97: putfield c : Lme/konsolas/aac/b0;
/*    */     //   100: areturn
/*    */     // Line number table:
/*    */     //   Java source line number -> byte code offset
/*    */     //   #8	-> 49
/*    */     //   #14	-> 57
/*    */     // Exception table:
/*    */     //   from	to	target	type
/*    */     //   57	67	70	aacinternal/v }
/*  6 */   s(k_ paramk_, long paramLong) { this.g = paramk_.b;
/*    */ 
/*    */ 
/*    */ 
/*    */ 
/*    */ 
/*    */     
/*    */     this.b = paramk_.a;
/*    */ 
/*    */ 
/*    */ 
/*    */ 
/*    */     
/* 19 */     this.f = paramk_.c.a();
/*    */     this.a = paramk_.d;
/*    */     this.e = eO.a(l, paramk_.e); }
/*    */ 
/*    */   
/*    */   @Nullable
/*    */   public Object a() {
/*    */     return a(Object.class);
/*    */   }
/*    */   
/*    */   @Nullable
/*    */   public Object a(Class paramClass) {
/*    */     return paramClass.cast(this.e.get(paramClass));
/*    */   }
/*    */   
/*    */   public J a() {
/*    */     return this.f;
/*    */   }
/*    */   
/*    */   public k_ a(long paramLong) {
/*    */     paramLong = h ^ paramLong;
/*    */     int i = (int)((paramLong ^ 0x2703FCE7AA65L) >>> 32L), j = (int)((paramLong ^ 0x2703FCE7AA65L) << 32L >>> 48L), k = (int)((paramLong ^ 0x2703FCE7AA65L) << 48L >>> 48L);
/*    */     paramLong ^ 0x2703FCE7AA65L;
/*    */     return new k_(i, (char)j, this, (char)k);
/*    */   }
/*    */   
/*    */   @Nullable
/*    */   public String a(long paramLong, String paramString) {
/*    */     paramLong = h ^ paramLong;
/*    */     int i = (int)((paramLong ^ 0xF52C1F4FE08L) >>> 32L), j = (int)((paramLong ^ 0xF52C1F4FE08L) << 32L >>> 48L), k = (int)((paramLong ^ 0xF52C1F4FE08L) << 48L >>> 48L);
/*    */     paramLong ^ 0xF52C1F4FE08L;
/*    */     return this.f.a(i, (char)j, (char)k, paramString);
/*    */   }
/*    */   
/*    */   public boolean a(char paramChar, long paramLong) {
/*    */     long l1 = (paramChar << 48L | paramLong << 16L >>> 16L) ^ h, l2 = l1 ^ 0x5E243D5423B2L;
/*    */     return this.g.a(l2);
/*    */   }
/*    */   
/*    */   public String toString() {
/*    */     // Byte code:
/*    */     //   0: getstatic me/konsolas/aac/s.h : J
/*    */     //   3: ldc2_w 5146071786531
/*    */     //   6: lxor
/*    */     //   7: lstore_1
/*    */     //   8: new java/lang/StringBuilder
/*    */     //   11: dup
/*    */     //   12: invokespecial <init> : ()V
/*    */     //   15: sipush #11298
/*    */     //   18: ldc2_w 991677781743655780
/*    */     //   21: lload_1
/*    */     //   22: lxor
/*    */     //   23: <illegal opcode> p : (IJ)Ljava/lang/String;
/*    */     //   28: invokevirtual append : (Ljava/lang/String;)Ljava/lang/StringBuilder;
/*    */     //   31: aload_0
/*    */     //   32: getfield b : Ljava/lang/String;
/*    */     //   35: invokevirtual append : (Ljava/lang/String;)Ljava/lang/StringBuilder;
/*    */     //   38: sipush #26268
/*    */     //   41: ldc2_w 5931611180013261273
/*    */     //   44: lload_1
/*    */     //   45: lxor
/*    */     //   46: <illegal opcode> p : (IJ)Ljava/lang/String;
/*    */     //   51: invokevirtual append : (Ljava/lang/String;)Ljava/lang/StringBuilder;
/*    */     //   54: aload_0
/*    */     //   55: getfield g : Lme/konsolas/aac/l6;
/*    */     //   58: invokevirtual append : (Ljava/lang/Object;)Ljava/lang/StringBuilder;
/*    */     //   61: sipush #13634
/*    */     //   64: ldc2_w 4452583815454245381
/*    */     //   67: lload_1
/*    */     //   68: lxor
/*    */     //   69: <illegal opcode> p : (IJ)Ljava/lang/String;
/*    */     //   74: invokevirtual append : (Ljava/lang/String;)Ljava/lang/StringBuilder;
/*    */     //   77: aload_0
/*    */     //   78: getfield e : Ljava/util/Map;
/*    */     //   81: invokevirtual append : (Ljava/lang/Object;)Ljava/lang/StringBuilder;
/*    */     //   84: bipush #125
/*    */     //   86: invokevirtual append : (C)Ljava/lang/StringBuilder;
/*    */     //   89: invokevirtual toString : ()Ljava/lang/String;
/*    */     //   92: areturn
/*    */     // Line number table:
/*    */     //   Java source line number -> byte code offset
/*    */     //   #20	-> 8
/*    */   }
/*    */   
/*    */   public static void b(aN[] paramArrayOfaN) {
/*    */     d = paramArrayOfaN;
/*    */   }
/*    */   
/*    */   public static aN[] b() {
/*    */     return d;
/*    */   }
/*    */   
/*    */   static {
/*    */     // Byte code:
/*    */     //   0: ldc2_w 7153620150017496118
/*    */     //   3: ldc2_w -5780354475652844138
/*    */     //   6: invokestatic lookup : ()Ljava/lang/invoke/MethodHandles$Lookup;
/*    */     //   9: invokevirtual lookupClass : ()Ljava/lang/Class;
/*    */     //   12: invokestatic a : (JJLjava/lang/Object;)Lme/konsolas/aac/na;
/*    */     //   15: ldc2_w 19907421373288
/*    */     //   18: invokeinterface a : (J)J
/*    */     //   23: putstatic me/konsolas/aac/s.h : J
/*    */     //   26: getstatic me/konsolas/aac/s.h : J
/*    */     //   29: ldc2_w 118631505301326
/*    */     //   32: lxor
/*    */     //   33: lstore #9
/*    */     //   35: aconst_null
/*    */     //   36: new java/util/HashMap
/*    */     //   39: dup
/*    */     //   40: bipush #13
/*    */     //   42: invokespecial <init> : (I)V
/*    */     //   45: putstatic me/konsolas/aac/s.k : Ljava/util/Map;
/*    */     //   48: ldc2_w -3685429330021091555
/*    */     //   51: lload #9
/*    */     //   53: <illegal opcode> w : ([Lme/konsolas/aac/aN;JJ)V
/*    */     //   58: ldc '᫱蛬習姍锰砫ᬉᾑ陹঵썕遼螴ဗ웿殲䈨'
/*    */     //   60: invokevirtual toCharArray : ()[C
/*    */     //   63: dup
/*    */     //   64: dup
/*    */     //   65: bipush #6
/*    */     //   67: dup_x1
/*    */     //   68: caload
/*    */     //   69: sipush #20591
/*    */     //   72: ixor
/*    */     //   73: i2c
/*    */     //   74: castore
/*    */     //   75: sipush #18281
/*    */     //   78: iconst_1
/*    */     //   79: iconst_1
/*    */     //   80: invokestatic U : (Ljava/lang/Object;SZZ)Ljava/lang/String;
/*    */     //   83: invokestatic getInstance : (Ljava/lang/String;)Ljavax/crypto/Cipher;
/*    */     //   86: dup
/*    */     //   87: astore_0
/*    */     //   88: iconst_2
/*    */     //   89: ldc 'ࡡ喘䒧'
/*    */     //   91: invokevirtual toCharArray : ()[C
/*    */     //   94: dup
/*    */     //   95: dup
/*    */     //   96: iconst_2
/*    */     //   97: dup_x1
/*    */     //   98: caload
/*    */     //   99: sipush #6782
/*    */     //   102: ixor
/*    */     //   103: i2c
/*    */     //   104: castore
/*    */     //   105: sipush #30459
/*    */     //   108: iconst_1
/*    */     //   109: iconst_0
/*    */     //   110: invokestatic U : (Ljava/lang/Object;SZZ)Ljava/lang/String;
/*    */     //   113: invokestatic getInstance : (Ljava/lang/String;)Ljavax/crypto/SecretKeyFactory;
/*    */     //   116: bipush #8
/*    */     //   118: newarray byte
/*    */     //   120: dup
/*    */     //   121: iconst_0
/*    */     //   122: lload #9
/*    */     //   124: bipush #56
/*    */     //   126: lushr
/*    */     //   127: l2i
/*    */     //   128: i2b
/*    */     //   129: bastore
/*    */     //   130: iconst_1
/*    */     //   131: istore_1
/*    */     //   132: iload_1
/*    */     //   133: bipush #8
/*    */     //   135: if_icmpge -> 159
/*    */     //   138: dup
/*    */     //   139: iload_1
/*    */     //   140: lload #9
/*    */     //   142: iload_1
/*    */     //   143: bipush #8
/*    */     //   145: imul
/*    */     //   146: lshl
/*    */     //   147: bipush #56
/*    */     //   149: lushr
/*    */     //   150: l2i
/*    */     //   151: i2b
/*    */     //   152: bastore
/*    */     //   153: iinc #1, 1
/*    */     //   156: goto -> 132
/*    */     //   159: new javax/crypto/spec/DESKeySpec
/*    */     //   162: dup_x1
/*    */     //   163: swap
/*    */     //   164: invokespecial <init> : ([B)V
/*    */     //   167: invokevirtual generateSecret : (Ljava/security/spec/KeySpec;)Ljavax/crypto/SecretKey;
/*    */     //   170: new javax/crypto/spec/IvParameterSpec
/*    */     //   173: dup
/*    */     //   174: bipush #8
/*    */     //   176: newarray byte
/*    */     //   178: invokespecial <init> : ([B)V
/*    */     //   181: invokevirtual init : (ILjava/security/Key;Ljava/security/spec/AlgorithmParameterSpec;)V
/*    */     //   184: iconst_3
/*    */     //   185: anewarray java/lang/String
/*    */     //   188: astore #7
/*    */     //   190: iconst_0
/*    */     //   191: istore #5
/*    */     //   193: ldc_w '쬲⚓ᰏ曨䱥㋑䥒⢶㿝쓺䦀᫷ۓ雋릝ゟ㛁뀹萦ᩇ铜ꐢ㄄Ʝ䅱㓰묤⏋댵㶔롲➦禽᧘ᩧ氜寧ﯕ檾元腌я醬噬❜蛐鶑ꥃ쁖⇾꥿殾ઇ䀽¹䤏ﲂৼ?ペ漁'
/*    */     //   196: invokevirtual toCharArray : ()[C
/*    */     //   199: dup
/*    */     //   200: dup
/*    */     //   201: bipush #63
/*    */     //   203: dup_x1
/*    */     //   204: caload
/*    */     //   205: sipush #27357
/*    */     //   208: ixor
/*    */     //   209: i2c
/*    */     //   210: castore
/*    */     //   211: sipush #4693
/*    */     //   214: iconst_1
/*    */     //   215: iconst_0
/*    */     //   216: invokestatic U : (Ljava/lang/Object;SZZ)Ljava/lang/String;
/*    */     //   219: dup
/*    */     //   220: astore #4
/*    */     //   222: invokevirtual length : ()I
/*    */     //   225: istore #6
/*    */     //   227: bipush #16
/*    */     //   229: istore_3
/*    */     //   230: iconst_m1
/*    */     //   231: istore_2
/*    */     //   232: iinc #2, 1
/*    */     //   235: aload #4
/*    */     //   237: iload_2
/*    */     //   238: dup
/*    */     //   239: iload_3
/*    */     //   240: iadd
/*    */     //   241: invokevirtual substring : (II)Ljava/lang/String;
/*    */     //   244: iconst_m1
/*    */     //   245: goto -> 293
/*    */     //   248: aload #7
/*    */     //   250: swap
/*    */     //   251: iload #5
/*    */     //   253: iinc #5, 1
/*    */     //   256: swap
/*    */     //   257: aastore
/*    */     //   258: iload_2
/*    */     //   259: iload_3
/*    */     //   260: iadd
/*    */     //   261: dup
/*    */     //   262: istore_2
/*    */     //   263: iload #6
/*    */     //   265: if_icmpge -> 278
/*    */     //   268: aload #4
/*    */     //   270: iload_2
/*    */     //   271: invokevirtual charAt : (I)C
/*    */     //   274: istore_3
/*    */     //   275: goto -> 232
/*    */     //   278: aload #7
/*    */     //   280: putstatic me/konsolas/aac/s.i : [Ljava/lang/String;
/*    */     //   283: iconst_3
/*    */     //   284: anewarray java/lang/String
/*    */     //   287: putstatic me/konsolas/aac/s.j : [Ljava/lang/String;
/*    */     //   290: goto -> 342
/*    */     //   293: swap
/*    */     //   294: ldc_w '稞쬁⬳粓?ⷮ챗ᡜ௑'
/*    */     //   297: invokevirtual toCharArray : ()[C
/*    */     //   300: dup
/*    */     //   301: dup
/*    */     //   302: iconst_5
/*    */     //   303: dup_x1
/*    */     //   304: caload
/*    */     //   305: sipush #24282
/*    */     //   308: ixor
/*    */     //   309: i2c
/*    */     //   310: castore
/*    */     //   311: sipush #19082
/*    */     //   314: iconst_0
/*    */     //   315: iconst_0
/*    */     //   316: invokestatic U : (Ljava/lang/Object;SZZ)Ljava/lang/String;
/*    */     //   319: invokevirtual getBytes : (Ljava/lang/String;)[B
/*    */     //   322: aload_0
/*    */     //   323: swap
/*    */     //   324: invokevirtual doFinal : ([B)[B
/*    */     //   327: astore #8
/*    */     //   329: aload #8
/*    */     //   331: invokestatic a : ([B)Ljava/lang/String;
/*    */     //   334: invokevirtual intern : ()Ljava/lang/String;
/*    */     //   337: swap
/*    */     //   338: pop
/*    */     //   339: goto -> 248
/*    */     //   342: return
/*    */   }
/*    */   
/*    */   private static v a(v paramv) {
/*    */     return paramv;
/*    */   }
/*    */   
/*    */   private static String a(byte[] paramArrayOfbyte) {
/*    */     byte b1 = 0;
/*    */     int i;
/*    */     char[] arrayOfChar = new char[i = paramArrayOfbyte.length];
/*    */     for (byte b2 = 0; b2 < i; b2++) {
/*    */       int j;
/*    */       if ((j = 0xFF & paramArrayOfbyte[b2]) < 192) {
/*    */         arrayOfChar[b1++] = (char)j;
/*    */       } else if (j < 224) {
/*    */         char c = (char)((char)(j & 0x1F) << 6);
/*    */         j = paramArrayOfbyte[++b2];
/*    */         c = (char)(c | (char)(j & 0x3F));
/*    */         arrayOfChar[b1++] = c;
/*    */       } else if (b2 < i - 2) {
/*    */         char c = (char)((char)(j & 0xF) << 12);
/*    */         j = paramArrayOfbyte[++b2];
/*    */         c = (char)(c | (char)(j & 0x3F) << 6);
/*    */         j = paramArrayOfbyte[++b2];
/*    */         c = (char)(c | (char)(j & 0x3F));
/*    */         arrayOfChar[b1++] = c;
/*    */       } 
/*    */     } 
/*    */     return new String(arrayOfChar, 0, b1);
/*    */   }
/*    */   
/*    */   private static String a(int paramInt, long paramLong) {
/*    */     int i = paramInt ^ (int)(paramLong & 0x7FFFL) ^ 0x51F6;
/*    */     if (j[i] == null) {
/*    */       Object[] arrayOfObject;
/*    */       try {
/*    */         Long long_ = Long.valueOf(Thread.currentThread().getId());
/*    */         arrayOfObject = (Object[])k.get(long_);
/*    */         if (arrayOfObject == null) {
/*    */           arrayOfObject = new Object[3];
/*    */           "䳚蛋ࡊ晖쬡쎀獑䐆⚃︌ݫ綍暳룽䯡㣅쨚暷".toCharArray()[11] = (char)("䳚蛋ࡊ晖쬡쎀獑䐆⚃︌ݫ綍暳룽䯡㣅쨚暷".toCharArray()[11] ^ 0x5E70);
/*    */           arrayOfObject[0] = Cipher.getInstance(da$gx.U("䳚蛋ࡊ晖쬡쎀獑䐆⚃︌ݫ綍暳룽䯡㣅쨚暷".toCharArray(), (short)17379, false, false));
/*    */           "䈬琲Ἄ㮥".toCharArray()[2] = (char)("䈬琲Ἄ㮥".toCharArray()[2] ^ 0x2882);
/*    */           arrayOfObject[1] = SecretKeyFactory.getInstance(da$gx.U("䈬琲Ἄ㮥".toCharArray(), (short)1580, true, true));
/*    */           arrayOfObject[2] = new IvParameterSpec(new byte[8]);
/*    */           k.put(long_, arrayOfObject);
/*    */         } 
/*    */       } catch (Exception exception) {
/*    */         "㬽↛뱖?좎ឌ❻릭뽏놣⨦ꥬﲬ挰쿷랔炛".toCharArray()[0] = (char)("㬽↛뱖?좎ឌ❻릭뽏놣⨦ꥬﲬ挰쿷랔炛".toCharArray()[0] ^ 0x1A93);
/*    */         throw new RuntimeException(da$gx.U("㬽↛뱖?좎ឌ❻릭뽏놣⨦ꥬﲬ挰쿷랔炛".toCharArray(), (short)22798, false, true), exception);
/*    */       } 
/*    */       byte[] arrayOfByte1 = new byte[8];
/*    */       arrayOfByte1[0] = (byte)(int)(paramLong >>> 56L);
/*    */       for (byte b = 1; b < 8; b++)
/*    */         arrayOfByte1[b] = (byte)(int)(paramLong << b * 8 >>> 56L); 
/*    */       DESKeySpec dESKeySpec = new DESKeySpec(arrayOfByte1);
/*    */       SecretKey secretKey = ((SecretKeyFactory)arrayOfObject[1]).generateSecret(dESKeySpec);
/*    */       ((Cipher)arrayOfObject[0]).init(2, secretKey, (IvParameterSpec)arrayOfObject[2]);
/*    */       "閒䄎⛅젤﫷立皍".toCharArray()[2] = (char)("閒䄎⛅젤﫷立皍".toCharArray()[2] ^ 0x1049);
/*    */       byte[] arrayOfByte2 = i[i].getBytes(da$gx.U("閒䄎⛅젤﫷立皍".toCharArray(), (short)14991, true, true));
/*    */       j[i] = a(((Cipher)arrayOfObject[0]).doFinal(arrayOfByte2));
/*    */     } 
/*    */     return j[i];
/*    */   }
/*    */   
/*    */   private static Object a(MethodHandles.Lookup paramLookup, MutableCallSite paramMutableCallSite, String paramString, Object[] paramArrayOfObject) {
/*    */     int i = ((Integer)paramArrayOfObject[0]).intValue();
/*    */     long l = ((Long)paramArrayOfObject[1]).longValue();
/*    */     String str = a(i, l);
/*    */     MethodHandle methodHandle = MethodHandles.constant(String.class, str);
/*    */     paramMutableCallSite.setTarget(MethodHandles.dropArguments(methodHandle, 0, new Class[] { int.class, long.class }));
/*    */     return str;
/*    */   }
/*    */   
/*    */   private static CallSite a(MethodHandles.Lookup paramLookup, String paramString, MethodType paramMethodType) {
/*    */     // Byte code:
/*    */     //   0: new java/lang/invoke/MutableCallSite
/*    */     //   3: dup
/*    */     //   4: aload_2
/*    */     //   5: invokespecial <init> : (Ljava/lang/invoke/MethodType;)V
/*    */     //   8: astore_3
/*    */     //   9: aload_3
/*    */     //   10: ldc_w
/*    */     //   13: ldc_w [Ljava/lang/Object;
/*    */     //   16: aload_2
/*    */     //   17: invokevirtual parameterCount : ()I
/*    */     //   20: invokevirtual asCollector : (Ljava/lang/Class;I)Ljava/lang/invoke/MethodHandle;
/*    */     //   23: iconst_0
/*    */     //   24: iconst_3
/*    */     //   25: anewarray java/lang/Object
/*    */     //   28: dup
/*    */     //   29: iconst_0
/*    */     //   30: aload_0
/*    */     //   31: aastore
/*    */     //   32: dup
/*    */     //   33: iconst_1
/*    */     //   34: aload_3
/*    */     //   35: aastore
/*    */     //   36: dup
/*    */     //   37: iconst_2
/*    */     //   38: aload_1
/*    */     //   39: aastore
/*    */     //   40: invokestatic insertArguments : (Ljava/lang/invoke/MethodHandle;I[Ljava/lang/Object;)Ljava/lang/invoke/MethodHandle;
/*    */     //   43: aload_2
/*    */     //   44: invokestatic explicitCastArguments : (Ljava/lang/invoke/MethodHandle;Ljava/lang/invoke/MethodType;)Ljava/lang/invoke/MethodHandle;
/*    */     //   47: invokevirtual setTarget : (Ljava/lang/invoke/MethodHandle;)V
/*    */     //   50: goto -> 170
/*    */     //   53: astore #4
/*    */     //   55: new java/lang/RuntimeException
/*    */     //   58: dup
/*    */     //   59: new java/lang/StringBuilder
/*    */     //   62: dup
/*    */     //   63: invokespecial <init> : ()V
/*    */     //   66: ldc_w '☈㨘㿤錠?䪅속홢帧ᱤ篳ဠꑹ퉻䧤'
/*    */     //   69: invokevirtual toCharArray : ()[C
/*    */     //   72: dup
/*    */     //   73: dup
/*    */     //   74: iconst_0
/*    */     //   75: dup_x1
/*    */     //   76: caload
/*    */     //   77: sipush #10687
/*    */     //   80: ixor
/*    */     //   81: i2c
/*    */     //   82: castore
/*    */     //   83: sipush #20704
/*    */     //   86: iconst_1
/*    */     //   87: iconst_0
/*    */     //   88: invokestatic X : (Ljava/lang/Object;SZZ)Ljava/lang/String;
/*    */     //   91: invokevirtual append : (Ljava/lang/String;)Ljava/lang/StringBuilder;
/*    */     //   94: ldc_w '獄೺?㞑'
/*    */     //   97: invokevirtual toCharArray : ()[C
/*    */     //   100: dup
/*    */     //   101: dup
/*    */     //   102: iconst_2
/*    */     //   103: dup_x1
/*    */     //   104: caload
/*    */     //   105: sipush #21010
/*    */     //   108: ixor
/*    */     //   109: i2c
/*    */     //   110: castore
/*    */     //   111: sipush #14430
/*    */     //   114: iconst_0
/*    */     //   115: iconst_1
/*    */     //   116: invokestatic X : (Ljava/lang/Object;SZZ)Ljava/lang/String;
/*    */     //   119: invokevirtual append : (Ljava/lang/String;)Ljava/lang/StringBuilder;
/*    */     //   122: aload_1
/*    */     //   123: invokevirtual append : (Ljava/lang/String;)Ljava/lang/StringBuilder;
/*    */     //   126: ldc_w 'ꑈ䣹ॱ偧'
/*    */     //   129: invokevirtual toCharArray : ()[C
/*    */     //   132: dup
/*    */     //   133: dup
/*    */     //   134: iconst_0
/*    */     //   135: dup_x1
/*    */     //   136: caload
/*    */     //   137: sipush #6475
/*    */     //   140: ixor
/*    */     //   141: i2c
/*    */     //   142: castore
/*    */     //   143: sipush #2780
/*    */     //   146: iconst_0
/*    */     //   147: iconst_1
/*    */     //   148: invokestatic X : (Ljava/lang/Object;SZZ)Ljava/lang/String;
/*    */     //   151: invokevirtual append : (Ljava/lang/String;)Ljava/lang/StringBuilder;
/*    */     //   154: aload_2
/*    */     //   155: invokevirtual toString : ()Ljava/lang/String;
/*    */     //   158: invokevirtual append : (Ljava/lang/String;)Ljava/lang/StringBuilder;
/*    */     //   161: invokevirtual toString : ()Ljava/lang/String;
/*    */     //   164: aload #4
/*    */     //   166: invokespecial <init> : (Ljava/lang/String;Ljava/lang/Throwable;)V
/*    */     //   169: athrow
/*    */     //   170: aload_3
/*    */     //   171: areturn
/*    */     // Exception table:
/*    */     //   from	to	target	type
/*    */     //   9	50	53	java/lang/Exception
/*    */   } }


/* Location:              C:\Users\BukkitBypass\Desktop\MatrixAC\AAC\AAC-spigot-5.2.0.jar!\me\konsolas\aac\s.class
 * Java compiler version: 8 (52.0)
 * JD-Core Version:       1.1.3
 */