/*    */ package me.konsolas.aac;
/*    */ 
/*    */ import aacinternal.v;
/*    */ import org.bukkit.command.CommandSender;
/*    */ import org.bukkit.entity.Player;
/*    */ 
/*    */ public class w {
/*    */   private final AAC b;
/*    */   private final Executor a;
/*    */   private final Map c;
/*    */   private CommandSender d;
/*    */   
/* 13 */   public void a(Player paramPlayer, String paramString, Object[] paramArrayOfObject) { a(paramPlayer, String.format(Locale.UK, paramString, paramArrayOfObject)); }
/*    */   private static int[] e;
/*    */   private static final long f;
/*    */   public boolean a(CommandSender paramCommandSender, long paramLong) { // Byte code:
/*    */     //   0: getstatic me/konsolas/aac/w.f : J
/*    */     //   3: lload_2
/*    */     //   4: lxor
/*    */     //   5: lstore_2
/*    */     //   6: aload_1
/*    */     //   7: aload_0
/*    */     //   8: getfield d : Lorg/bukkit/command/CommandSender;
/*    */     //   11: if_acmpne -> 28
/*    */     //   14: iconst_1
/*    */     //   15: goto -> 29
/*    */     //   18: ldc2_w -7499180958583844203
/*    */     //   21: lload_2
/*    */     //   22: <illegal opcode> w : (Laacinternal/v;JJ)Laacinternal/v;
/*    */     //   27: athrow
/*    */     //   28: iconst_0
/*    */     //   29: ireturn
/*    */     // Line number table:
/*    */     //   Java source line number -> byte code offset
/*    */     //   #2	-> 6
/*    */     // Exception table:
/*    */     //   from	to	target	type
/*    */     //   6	18	18	aacinternal/v } private void a(Player paramPlayer, long paramLong1, String paramString, long paramLong2) { // Byte code:
/*    */     //   0: getstatic me/konsolas/aac/w.f : J
/*    */     //   3: lload_2
/*    */     //   4: lxor
/*    */     //   5: lstore_2
/*    */     //   6: ldc2_w -3404280527062442138
/*    */     //   9: lload_2
/*    */     //   10: <illegal opcode> w : (JJ)[I
/*    */     //   15: aload_0
/*    */     //   16: getfield c : Ljava/util/Map;
/*    */     //   19: aload_1
/*    */     //   20: invokeinterface getUniqueId : ()Ljava/util/UUID;
/*    */     //   25: invokeinterface get : (Ljava/lang/Object;)Ljava/lang/Object;
/*    */     //   30: checkcast java/util/Set
/*    */     //   33: astore #8
/*    */     //   35: astore #7
/*    */     //   37: aload_0
/*    */     //   38: getfield d : Lorg/bukkit/command/CommandSender;
/*    */     //   41: ifnull -> 125
/*    */     //   44: aload #8
/*    */     //   46: aload #7
/*    */     //   48: ifnonnull -> 115
/*    */     //   51: goto -> 64
/*    */     //   54: ldc2_w -3357494743805799393
/*    */     //   57: lload_2
/*    */     //   58: <illegal opcode> w : (Laacinternal/v;JJ)Laacinternal/v;
/*    */     //   63: athrow
/*    */     //   64: ifnonnull -> 100
/*    */     //   67: goto -> 80
/*    */     //   70: ldc2_w -3357494743805799393
/*    */     //   73: lload_2
/*    */     //   74: <illegal opcode> w : (Laacinternal/v;JJ)Laacinternal/v;
/*    */     //   79: athrow
/*    */     //   80: aload_0
/*    */     //   81: getfield d : Lorg/bukkit/command/CommandSender;
/*    */     //   84: invokestatic singleton : (Ljava/lang/Object;)Ljava/util/Set;
/*    */     //   87: astore #8
/*    */     //   89: lload_2
/*    */     //   90: lconst_0
/*    */     //   91: lcmp
/*    */     //   92: ifle -> 125
/*    */     //   95: aload #7
/*    */     //   97: ifnull -> 125
/*    */     //   100: aload #8
/*    */     //   102: goto -> 115
/*    */     //   105: ldc2_w -3357494743805799393
/*    */     //   108: lload_2
/*    */     //   109: <illegal opcode> w : (Laacinternal/v;JJ)Laacinternal/v;
/*    */     //   114: athrow
/*    */     //   115: aload_0
/*    */     //   116: getfield d : Lorg/bukkit/command/CommandSender;
/*    */     //   119: invokeinterface add : (Ljava/lang/Object;)Z
/*    */     //   124: pop
/*    */     //   125: aload #8
/*    */     //   127: ifnonnull -> 141
/*    */     //   130: return
/*    */     //   131: ldc2_w -3357494743805799393
/*    */     //   134: lload_2
/*    */     //   135: <illegal opcode> w : (Laacinternal/v;JJ)Laacinternal/v;
/*    */     //   140: athrow
/*    */     //   141: lload #5
/*    */     //   143: invokestatic toString : (J)Ljava/lang/String;
/*    */     //   146: astore #9
/*    */     //   148: new java/lang/StringBuilder
/*    */     //   151: dup
/*    */     //   152: invokespecial <init> : ()V
/*    */     //   155: ldc ''
/*    */     //   157: invokevirtual append : (Ljava/lang/String;)Ljava/lang/StringBuilder;
/*    */     //   160: getstatic org/bukkit/ChatColor.DARK_GRAY : Lorg/bukkit/ChatColor;
/*    */     //   163: invokevirtual append : (Ljava/lang/Object;)Ljava/lang/StringBuilder;
/*    */     //   166: aload #9
/*    */     //   168: aload #9
/*    */     //   170: invokevirtual length : ()I
/*    */     //   173: iconst_4
/*    */     //   174: isub
/*    */     //   175: invokevirtual substring : (I)Ljava/lang/String;
/*    */     //   178: invokevirtual append : (Ljava/lang/String;)Ljava/lang/StringBuilder;
/*    */     //   181: ldc '韦叢'
/*    */     //   183: invokevirtual toCharArray : ()[C
/*    */     //   186: dup
/*    */     //   187: dup
/*    */     //   188: iconst_0
/*    */     //   189: dup_x1
/*    */     //   190: caload
/*    */     //   191: sipush #11220
/*    */     //   194: ixor
/*    */     //   195: i2c
/*    */     //   196: castore
/*    */     //   197: sipush #937
/*    */     //   200: iconst_0
/*    */     //   201: iconst_1
/*    */     //   202: invokestatic U : (Ljava/lang/Object;SZZ)Ljava/lang/String;
/*    */     //   205: invokevirtual append : (Ljava/lang/String;)Ljava/lang/StringBuilder;
/*    */     //   208: getstatic org/bukkit/ChatColor.DARK_GREEN : Lorg/bukkit/ChatColor;
/*    */     //   211: invokevirtual append : (Ljava/lang/Object;)Ljava/lang/StringBuilder;
/*    */     //   214: aload_1
/*    */     //   215: invokeinterface getName : ()Ljava/lang/String;
/*    */     //   220: invokevirtual append : (Ljava/lang/String;)Ljava/lang/StringBuilder;
/*    */     //   223: ldc '䆬岁'
/*    */     //   225: invokevirtual toCharArray : ()[C
/*    */     //   228: dup
/*    */     //   229: dup
/*    */     //   230: iconst_0
/*    */     //   231: dup_x1
/*    */     //   232: caload
/*    */     //   233: sipush #14429
/*    */     //   236: ixor
/*    */     //   237: i2c
/*    */     //   238: castore
/*    */     //   239: sipush #25597
/*    */     //   242: iconst_0
/*    */     //   243: iconst_0
/*    */     //   244: invokestatic U : (Ljava/lang/Object;SZZ)Ljava/lang/String;
/*    */     //   247: invokevirtual append : (Ljava/lang/String;)Ljava/lang/StringBuilder;
/*    */     //   250: getstatic org/bukkit/ChatColor.GRAY : Lorg/bukkit/ChatColor;
/*    */     //   253: invokevirtual append : (Ljava/lang/Object;)Ljava/lang/StringBuilder;
/*    */     //   256: aload #4
/*    */     //   258: invokevirtual append : (Ljava/lang/String;)Ljava/lang/StringBuilder;
/*    */     //   261: invokevirtual toString : ()Ljava/lang/String;
/*    */     //   264: astore #4
/*    */     //   266: aload #8
/*    */     //   268: invokeinterface iterator : ()Ljava/util/Iterator;
/*    */     //   273: astore #10
/*    */     //   275: aload #10
/*    */     //   277: invokeinterface hasNext : ()Z
/*    */     //   282: ifeq -> 311
/*    */     //   285: aload #10
/*    */     //   287: invokeinterface next : ()Ljava/lang/Object;
/*    */     //   292: checkcast org/bukkit/command/CommandSender
/*    */     //   295: astore #11
/*    */     //   297: aload #11
/*    */     //   299: aload #4
/*    */     //   301: invokeinterface sendMessage : (Ljava/lang/String;)V
/*    */     //   306: aload #7
/*    */     //   308: ifnull -> 275
/*    */     //   311: return
/*    */     // Line number table:
/*    */     //   Java source line number -> byte code offset
/*    */     //   #6	-> 15
/*    */     //   #43	-> 37
/*    */     //   #32	-> 44
/*    */     //   #42	-> 100
/*    */     //   #27	-> 125
/*    */     //   #24	-> 141
/*    */     //   #20	-> 148
/*    */     //   #3	-> 215
/*    */     //   #29	-> 266
/*    */     //   #9	-> 297
/*    */     //   #11	-> 306
/*    */     //   #40	-> 311
/*    */     // Exception table:
/*    */     //   from	to	target	type
/*    */     //   37	51	54	aacinternal/v
/*    */     //   44	67	70	aacinternal/v
/*    */     //   89	102	105	aacinternal/v
/*    */     //   125	131	131	aacinternal/v } public w(byte paramByte, int paramInt1, int paramInt2, AAC paramAAC) { // Byte code:
/*    */     //   0: iload_1
/*    */     //   1: i2l
/*    */     //   2: bipush #56
/*    */     //   4: lshl
/*    */     //   5: iload_2
/*    */     //   6: i2l
/*    */     //   7: bipush #32
/*    */     //   9: lshl
/*    */     //   10: bipush #8
/*    */     //   12: lushr
/*    */     //   13: lor
/*    */     //   14: iload_3
/*    */     //   15: i2l
/*    */     //   16: bipush #40
/*    */     //   18: lshl
/*    */     //   19: bipush #40
/*    */     //   21: lushr
/*    */     //   22: lor
/*    */     //   23: getstatic me/konsolas/aac/w.f : J
/*    */     //   26: lxor
/*    */     //   27: lstore #5
/*    */     //   29: ldc2_w -5464059732588512372
/*    */     //   32: lload #5
/*    */     //   34: <illegal opcode> w : (JJ)[I
/*    */     //   39: aload_0
/*    */     //   40: invokespecial <init> : ()V
/*    */     //   43: aload_0
/*    */     //   44: invokestatic newSingleThreadExecutor : ()Ljava/util/concurrent/ExecutorService;
/*    */     //   47: putfield a : Ljava/util/concurrent/Executor;
/*    */     //   50: astore #7
/*    */     //   52: aload_0
/*    */     //   53: new java/util/concurrent/ConcurrentHashMap
/*    */     //   56: dup
/*    */     //   57: invokespecial <init> : ()V
/*    */     //   60: putfield c : Ljava/util/Map;
/*    */     //   63: aload_0
/*    */     //   64: aconst_null
/*    */     //   65: putfield d : Lorg/bukkit/command/CommandSender;
/*    */     //   68: aload_0
/*    */     //   69: aload #4
/*    */     //   71: putfield b : Lme/konsolas/aac/AAC;
/*    */     //   74: aload #7
/*    */     //   76: ifnull -> 107
/*    */     //   79: iconst_4
/*    */     //   80: anewarray me/konsolas/aac/aN
/*    */     //   83: ldc2_w -5349715236274476012
/*    */     //   86: lload #5
/*    */     //   88: <illegal opcode> w : ([Lme/konsolas/aac/aN;JJ)V
/*    */     //   93: goto -> 107
/*    */     //   96: ldc2_w -5364462069656276747
/*    */     //   99: lload #5
/*    */     //   101: <illegal opcode> w : (Laacinternal/v;JJ)Laacinternal/v;
/*    */     //   106: athrow
/*    */     //   107: return
/*    */     // Line number table:
/*    */     //   Java source line number -> byte code offset
/*    */     //   #7	-> 39
/*    */     //   #19	-> 43
/*    */     //   #23	-> 52
/*    */     //   #22	-> 63
/*    */     //   #33	-> 68
/*    */     //   #17	-> 74
/*    */     // Exception table:
/*    */     //   from	to	target	type
/*    */     //   52	93	96	aacinternal/v } public void a(short paramShort1, short paramShort2, int paramInt, CommandSender paramCommandSender, OfflinePlayer paramOfflinePlayer) { // Byte code:
/*    */     //   0: iload_1
/*    */     //   1: i2l
/*    */     //   2: bipush #48
/*    */     //   4: lshl
/*    */     //   5: iload_2
/*    */     //   6: i2l
/*    */     //   7: bipush #48
/*    */     //   9: lshl
/*    */     //   10: bipush #16
/*    */     //   12: lushr
/*    */     //   13: lor
/*    */     //   14: iload_3
/*    */     //   15: i2l
/*    */     //   16: bipush #32
/*    */     //   18: lshl
/*    */     //   19: bipush #32
/*    */     //   21: lushr
/*    */     //   22: lor
/*    */     //   23: getstatic me/konsolas/aac/w.f : J
/*    */     //   26: lxor
/*    */     //   27: lstore #6
/*    */     //   29: ldc2_w -5519298150018138944
/*    */     //   32: lload #6
/*    */     //   34: <illegal opcode> w : (JJ)[I
/*    */     //   39: aload_0
/*    */     //   40: getfield c : Ljava/util/Map;
/*    */     //   43: aload #5
/*    */     //   45: invokeinterface getUniqueId : ()Ljava/util/UUID;
/*    */     //   50: <illegal opcode> apply : ()Ljava/util/function/Function;
/*    */     //   55: invokeinterface computeIfAbsent : (Ljava/lang/Object;Ljava/util/function/Function;)Ljava/lang/Object;
/*    */     //   60: checkcast java/util/Set
/*    */     //   63: astore #9
/*    */     //   65: astore #8
/*    */     //   67: aload #9
/*    */     //   69: aload #4
/*    */     //   71: invokeinterface remove : (Ljava/lang/Object;)Z
/*    */     //   76: aload #8
/*    */     //   78: ifnonnull -> 208
/*    */     //   81: ifeq -> 185
/*    */     //   84: goto -> 98
/*    */     //   87: ldc2_w -5565926702859831367
/*    */     //   90: lload #6
/*    */     //   92: <illegal opcode> w : (Laacinternal/v;JJ)Laacinternal/v;
/*    */     //   97: athrow
/*    */     //   98: aload #9
/*    */     //   100: iload_3
/*    */     //   101: ifgt -> 175
/*    */     //   104: aload #8
/*    */     //   106: ifnonnull -> 175
/*    */     //   109: goto -> 123
/*    */     //   112: ldc2_w -5565926702859831367
/*    */     //   115: lload #6
/*    */     //   117: <illegal opcode> w : (Laacinternal/v;JJ)Laacinternal/v;
/*    */     //   122: athrow
/*    */     //   123: invokeinterface isEmpty : ()Z
/*    */     //   128: ifeq -> 209
/*    */     //   131: goto -> 145
/*    */     //   134: ldc2_w -5565926702859831367
/*    */     //   137: lload #6
/*    */     //   139: <illegal opcode> w : (Laacinternal/v;JJ)Laacinternal/v;
/*    */     //   144: athrow
/*    */     //   145: aload_0
/*    */     //   146: getfield c : Ljava/util/Map;
/*    */     //   149: aload #5
/*    */     //   151: invokeinterface getUniqueId : ()Ljava/util/UUID;
/*    */     //   156: invokeinterface remove : (Ljava/lang/Object;)Ljava/lang/Object;
/*    */     //   161: goto -> 175
/*    */     //   164: ldc2_w -5565926702859831367
/*    */     //   167: lload #6
/*    */     //   169: <illegal opcode> w : (Laacinternal/v;JJ)Laacinternal/v;
/*    */     //   174: athrow
/*    */     //   175: pop
/*    */     //   176: iload_1
/*    */     //   177: iflt -> 209
/*    */     //   180: aload #8
/*    */     //   182: ifnull -> 209
/*    */     //   185: aload #9
/*    */     //   187: aload #4
/*    */     //   189: invokeinterface add : (Ljava/lang/Object;)Z
/*    */     //   194: goto -> 208
/*    */     //   197: ldc2_w -5565926702859831367
/*    */     //   200: lload #6
/*    */     //   202: <illegal opcode> w : (Laacinternal/v;JJ)Laacinternal/v;
/*    */     //   207: athrow
/*    */     //   208: pop
/*    */     //   209: iload_3
/*    */     //   210: ifge -> 239
/*    */     //   213: ldc2_w -5570835250697865709
/*    */     //   216: lload #6
/*    */     //   218: <illegal opcode> w : (JJ)[Lme/konsolas/aac/aN;
/*    */     //   223: ifnull -> 253
/*    */     //   226: iconst_3
/*    */     //   227: newarray int
/*    */     //   229: ldc2_w -5545402681181497171
/*    */     //   232: lload #6
/*    */     //   234: <illegal opcode> w : ([IJJ)V
/*    */     //   239: goto -> 253
/*    */     //   242: ldc2_w -5565926702859831367
/*    */     //   245: lload #6
/*    */     //   247: <illegal opcode> w : (Laacinternal/v;JJ)Laacinternal/v;
/*    */     //   252: athrow
/*    */     //   253: return
/*    */     // Line number table:
/*    */     //   Java source line number -> byte code offset
/*    */     //   #15	-> 39
/*    */     //   #34	-> 67
/*    */     //   #41	-> 98
/*    */     //   #5	-> 185
/*    */     //   #14	-> 209
/*    */     // Exception table:
/*    */     //   from	to	target	type
/*    */     //   67	84	87	aacinternal/v
/*    */     //   81	109	112	aacinternal/v
/*    */     //   98	131	134	aacinternal/v
/*    */     //   123	161	164	aacinternal/v
/*    */     //   175	194	197	aacinternal/v
/* 16 */     //   209	239	242	aacinternal/v } public void a(Player paramPlayer, String paramString) { long l = System.currentTimeMillis();
/*    */     this.a.execute(() -> {
/*    */           long l1 = f ^ 0x275FFFC41897L;
/*    */           long l2 = l1 ^ 0x8664D7DC8EAL;
/*    */           a(paramPlayer, l2, paramString, paramLong);
/*    */         }); }
/*    */ 
/*    */   
/*    */   public Set a(CommandSender paramCommandSender, long paramLong) {
/*    */     // Byte code:
/*    */     //   0: getstatic me/konsolas/aac/w.f : J
/*    */     //   3: lload_2
/*    */     //   4: lxor
/*    */     //   5: lstore_2
/*    */     //   6: ldc2_w 7261690060173175649
/*    */     //   9: lload_2
/*    */     //   10: <illegal opcode> w : (JJ)[I
/*    */     //   15: new java/util/HashSet
/*    */     //   18: dup
/*    */     //   19: invokespecial <init> : ()V
/*    */     //   22: astore #5
/*    */     //   24: astore #4
/*    */     //   26: aload_0
/*    */     //   27: getfield c : Ljava/util/Map;
/*    */     //   30: invokeinterface entrySet : ()Ljava/util/Set;
/*    */     //   35: invokeinterface iterator : ()Ljava/util/Iterator;
/*    */     //   40: astore #6
/*    */     //   42: aload #6
/*    */     //   44: invokeinterface hasNext : ()Z
/*    */     //   49: ifeq -> 140
/*    */     //   52: aload #6
/*    */     //   54: invokeinterface next : ()Ljava/lang/Object;
/*    */     //   59: checkcast java/util/Map$Entry
/*    */     //   62: astore #7
/*    */     //   64: aload #7
/*    */     //   66: invokeinterface getValue : ()Ljava/lang/Object;
/*    */     //   71: checkcast java/util/Set
/*    */     //   74: aload_1
/*    */     //   75: invokeinterface contains : (Ljava/lang/Object;)Z
/*    */     //   80: aload #4
/*    */     //   82: ifnonnull -> 134
/*    */     //   85: ifeq -> 135
/*    */     //   88: goto -> 101
/*    */     //   91: ldc2_w 7305098177798234136
/*    */     //   94: lload_2
/*    */     //   95: <illegal opcode> w : (Laacinternal/v;JJ)Laacinternal/v;
/*    */     //   100: athrow
/*    */     //   101: aload #5
/*    */     //   103: aload #7
/*    */     //   105: invokeinterface getKey : ()Ljava/lang/Object;
/*    */     //   110: checkcast java/util/UUID
/*    */     //   113: invokestatic getOfflinePlayer : (Ljava/util/UUID;)Lorg/bukkit/OfflinePlayer;
/*    */     //   116: invokeinterface add : (Ljava/lang/Object;)Z
/*    */     //   121: goto -> 134
/*    */     //   124: ldc2_w 7305098177798234136
/*    */     //   127: lload_2
/*    */     //   128: <illegal opcode> w : (Laacinternal/v;JJ)Laacinternal/v;
/*    */     //   133: athrow
/*    */     //   134: pop
/*    */     //   135: aload #4
/*    */     //   137: ifnull -> 42
/*    */     //   140: aload #5
/*    */     //   142: lload_2
/*    */     //   143: lconst_0
/*    */     //   144: lcmp
/*    */     //   145: iflt -> 59
/*    */     //   148: areturn
/*    */     // Line number table:
/*    */     //   Java source line number -> byte code offset
/*    */     //   #18	-> 15
/*    */     //   #36	-> 26
/*    */     //   #21	-> 64
/*    */     //   #25	-> 101
/*    */     //   #4	-> 135
/*    */     //   #28	-> 140
/*    */     // Exception table:
/*    */     //   from	to	target	type
/*    */     //   64	88	91	aacinternal/v
/*    */     //   85	121	124	aacinternal/v
/*    */   }
/*    */   
/*    */   public boolean a(long paramLong, Player paramPlayer) {
/*    */     // Byte code:
/*    */     //   0: getstatic me/konsolas/aac/w.f : J
/*    */     //   3: lload_1
/*    */     //   4: lxor
/*    */     //   5: lstore_1
/*    */     //   6: ldc2_w -2773957693878905305
/*    */     //   9: lload_1
/*    */     //   10: <illegal opcode> w : (JJ)[I
/*    */     //   15: astore #4
/*    */     //   17: aload_0
/*    */     //   18: getfield d : Lorg/bukkit/command/CommandSender;
/*    */     //   21: aload #4
/*    */     //   23: ifnonnull -> 69
/*    */     //   26: ifnull -> 54
/*    */     //   29: goto -> 42
/*    */     //   32: ldc2_w -2871409144739537570
/*    */     //   35: lload_1
/*    */     //   36: <illegal opcode> w : (Laacinternal/v;JJ)Laacinternal/v;
/*    */     //   41: athrow
/*    */     //   42: iconst_1
/*    */     //   43: ireturn
/*    */     //   44: ldc2_w -2871409144739537570
/*    */     //   47: lload_1
/*    */     //   48: <illegal opcode> w : (Laacinternal/v;JJ)Laacinternal/v;
/*    */     //   53: athrow
/*    */     //   54: aload_0
/*    */     //   55: getfield c : Ljava/util/Map;
/*    */     //   58: aload_3
/*    */     //   59: invokeinterface getUniqueId : ()Ljava/util/UUID;
/*    */     //   64: invokeinterface get : (Ljava/lang/Object;)Ljava/lang/Object;
/*    */     //   69: checkcast java/util/Set
/*    */     //   72: astore #5
/*    */     //   74: aload #5
/*    */     //   76: lload_1
/*    */     //   77: lconst_0
/*    */     //   78: lcmp
/*    */     //   79: ifle -> 105
/*    */     //   82: aload #4
/*    */     //   84: ifnonnull -> 105
/*    */     //   87: ifnull -> 135
/*    */     //   90: goto -> 103
/*    */     //   93: ldc2_w -2871409144739537570
/*    */     //   96: lload_1
/*    */     //   97: <illegal opcode> w : (Laacinternal/v;JJ)Laacinternal/v;
/*    */     //   102: athrow
/*    */     //   103: aload #5
/*    */     //   105: invokeinterface isEmpty : ()Z
/*    */     //   110: aload #4
/*    */     //   112: ifnonnull -> 132
/*    */     //   115: ifne -> 135
/*    */     //   118: goto -> 131
/*    */     //   121: ldc2_w -2871409144739537570
/*    */     //   124: lload_1
/*    */     //   125: <illegal opcode> w : (Laacinternal/v;JJ)Laacinternal/v;
/*    */     //   130: athrow
/*    */     //   131: iconst_1
/*    */     //   132: goto -> 136
/*    */     //   135: iconst_0
/*    */     //   136: ireturn
/*    */     // Line number table:
/*    */     //   Java source line number -> byte code offset
/*    */     //   #31	-> 17
/*    */     //   #37	-> 54
/*    */     //   #10	-> 74
/*    */     // Exception table:
/*    */     //   from	to	target	type
/*    */     //   17	29	32	aacinternal/v
/*    */     //   26	44	44	aacinternal/v
/*    */     //   74	90	93	aacinternal/v
/*    */     //   105	118	121	aacinternal/v
/*    */   }
/*    */   
/*    */   public void a(CommandSender paramCommandSender, long paramLong) {
/*    */     // Byte code:
/*    */     //   0: getstatic me/konsolas/aac/w.f : J
/*    */     //   3: lload_2
/*    */     //   4: lxor
/*    */     //   5: lstore_2
/*    */     //   6: ldc2_w -8536389730007480785
/*    */     //   9: lload_2
/*    */     //   10: <illegal opcode> w : (JJ)[I
/*    */     //   15: astore #4
/*    */     //   17: aload_0
/*    */     //   18: aload #4
/*    */     //   20: ifnonnull -> 80
/*    */     //   23: getfield d : Lorg/bukkit/command/CommandSender;
/*    */     //   26: aload_1
/*    */     //   27: if_acmpne -> 66
/*    */     //   30: goto -> 43
/*    */     //   33: ldc2_w -8633683675847619242
/*    */     //   36: lload_2
/*    */     //   37: <illegal opcode> w : (Laacinternal/v;JJ)Laacinternal/v;
/*    */     //   42: athrow
/*    */     //   43: aload_0
/*    */     //   44: aconst_null
/*    */     //   45: putfield d : Lorg/bukkit/command/CommandSender;
/*    */     //   48: aload #4
/*    */     //   50: ifnull -> 84
/*    */     //   53: goto -> 66
/*    */     //   56: ldc2_w -8633683675847619242
/*    */     //   59: lload_2
/*    */     //   60: <illegal opcode> w : (Laacinternal/v;JJ)Laacinternal/v;
/*    */     //   65: athrow
/*    */     //   66: aload_0
/*    */     //   67: goto -> 80
/*    */     //   70: ldc2_w -8633683675847619242
/*    */     //   73: lload_2
/*    */     //   74: <illegal opcode> w : (Laacinternal/v;JJ)Laacinternal/v;
/*    */     //   79: athrow
/*    */     //   80: aload_1
/*    */     //   81: putfield d : Lorg/bukkit/command/CommandSender;
/*    */     //   84: return
/*    */     // Line number table:
/*    */     //   Java source line number -> byte code offset
/*    */     //   #35	-> 17
/*    */     //   #26	-> 66
/*    */     //   #38	-> 84
/*    */     // Exception table:
/*    */     //   from	to	target	type
/*    */     //   17	30	33	aacinternal/v
/*    */     //   23	53	56	aacinternal/v
/*    */     //   43	67	70	aacinternal/v
/*    */   }
/*    */   
/*    */   public static void b(int[] paramArrayOfint) {
/*    */     e = paramArrayOfint;
/*    */   }
/*    */   
/*    */   public static int[] b() {
/*    */     return e;
/*    */   }
/*    */   
/*    */   static {
/*    */     // Byte code:
/*    */     //   0: ldc2_w -3923773960556463962
/*    */     //   3: ldc2_w -8496802486737253968
/*    */     //   6: invokestatic lookup : ()Ljava/lang/invoke/MethodHandles$Lookup;
/*    */     //   9: invokevirtual lookupClass : ()Ljava/lang/Class;
/*    */     //   12: invokestatic a : (JJLjava/lang/Object;)Lme/konsolas/aac/na;
/*    */     //   15: ldc2_w 266738057853882
/*    */     //   18: invokeinterface a : (J)J
/*    */     //   23: putstatic me/konsolas/aac/w.f : J
/*    */     //   26: getstatic me/konsolas/aac/w.f : J
/*    */     //   29: ldc2_w 72043291685755
/*    */     //   32: lxor
/*    */     //   33: lstore_0
/*    */     //   34: ldc2_w -1142236736857505918
/*    */     //   37: lload_0
/*    */     //   38: <illegal opcode> w : (JJ)[I
/*    */     //   43: ifnull -> 58
/*    */     //   46: iconst_2
/*    */     //   47: newarray int
/*    */     //   49: ldc2_w -1132457900876506129
/*    */     //   52: lload_0
/*    */     //   53: <illegal opcode> w : ([IJJ)V
/*    */     //   58: return
/*    */   }
/*    */   
/*    */   private static v a(v paramv) {
/*    */     return paramv;
/*    */   }
/*    */ }


/* Location:              C:\Users\BukkitBypass\Desktop\MatrixAC\AAC\AAC-spigot-5.2.0.jar!\me\konsolas\aac\w.class
 * Java compiler version: 8 (52.0)
 * JD-Core Version:       1.1.3
 */