/*   1 */ package aacinternal;public class am implements aI, DoubleConsumer, Serializable { protected static final int l = -1; private static final long serialVersionUID = 20160411L; private static final aa e; private final aa m; public double a(long paramLong, aa paramaa) { paramLong = o ^ paramLong; long l = paramLong ^ 0x452B334BEF9CL; return this.d.a(paramaa, l); }
/*     */   
/*     */   private final aa g; private final aa c; private final aa b; private final aa n; private final aa f; private final aa a; private final aa k; private final aa j; private final aD h; private int i;
/*     */   private final B d;
/*     */   private static final long o;
/*     */   private static final String[] q;
/*     */   private static final String[] r;
/*     */   private static final Map s;
/*     */   
/*     */   public void a() {
/*  11 */     this.d.c();
/*     */   }
/*  13 */   public double e(long paramLong) { long l = paramLong ^ 0x14418937D397L; return a(l, this.c); } public double d(int paramInt, short paramShort1, short paramShort2) {
/*  14 */     long l1 = paramInt << 32L | paramShort1 << 48L >>> 32L | paramShort2 << 48L >>> 48L, l2 = l1 ^ 0x3CDABF9295D2L; return a(l2, this.m);
/*     */   }
/*     */   
/*     */   public am(double[] paramArrayOfdouble, long paramLong)
/*     */   {
/*  19 */     this(-1, l, true, paramArrayOfdouble); } static { long l; byte b1;
/*  20 */     for (o = nc.a(-781059564131683048L, 975178762975444420L, MethodHandles.lookup().lookupClass()).a(194643520568605L), s = new HashMap<>(13), l = o ^ 0x39C56AB351E9L, "ࡒ龌爀?䴵椱勼ⵌ樋覾㝏馛귿鮞븪曫ߋ".toCharArray()[10] = (char)("ࡒ龌爀?䴵椱勼ⵌ樋覾㝏馛귿鮞븪曫ߋ".toCharArray()[10] ^ 0x5E19), "靦棇⸕禸".toCharArray()[1] = (char)("靦棇⸕禸".toCharArray()[1] ^ 0x7EED), (new byte[8])[0] = (byte)(int)(l >>> 56L), b1 = 1; b1 < 8; ) { (new byte[8])[b1] = (byte)(int)(l << b1 * 8 >>> 56L); b1++; }  Cipher cipher; (cipher = Cipher.getInstance(aB$aG.q("ࡒ龌爀?䴵椱勼ⵌ樋覾㝏馛귿鮞븪曫ߋ".toCharArray(), (short)6115, (byte)5, (byte)3))).init(2, SecretKeyFactory.getInstance(aB$aG.q("靦棇⸕禸".toCharArray(), (short)3458, (byte)5, (byte)3)).generateSecret(new DESKeySpec(new byte[8])), new IvParameterSpec(new byte[8])); String[] arrayOfString = new String[10]; boolean bool = false; "⏆⑭곌䇚速ꊍⷱ?籠ㅫ떠㝤雽싿蘞뼽ޫ笊볶畟ﵫҌ妉垖蟐И箒勒⦓짩梊畊챌┨皗㇖杪覴ﮩ喱燖㺄⃼㉇滁퍲⨳ផ㏿ᴮ㧁鲏੒್ᑐ坿쉝短黦꣏﨨犫?衢㛹䭔⮩㦔뵢㶛닻鿹ౝ㹴‣踮ᓃ㰪义ɻ没ᒳ률ԣ㓤ᒲ킰?捓ུᇺ뵂溆ﺾ텆ꇽ㈚췥ย䭲臆슽釤ا㷔㏙꿮룙ᥱ띀䙊ꇊ䂞㯡똒嫊盉ꍰ⮒溫ꡌᆽ末彡ᢻ؋股暰깽㹓맜晩幧뀪븑礄㘉聺䄬炉䨝碾㟖工箥蒠䬻껊缞臏㺸䴫?Մ辞ⶽ⌨?雈ퟧ㱋ࣃ䆰ꪅ냆ᔒ綨붎覗轢묆놬⬈隑끤즜㭨뱰Ⓦ箦欵映ꅘ䒲ᎍⓑ?챁䈾뽖ዂẂဎ뉶灢⊒뫶⵳竦贉㱘ॐ锛ᖽ⃌ꚋᄰ閊샘﮽뺭＞㱆薼櫏".toCharArray()[220] = (char)("⏆⑭곌䇚速ꊍⷱ?籠ㅫ떠㝤雽싿蘞뼽ޫ笊볶畟ﵫҌ妉垖蟐И箒勒⦓짩梊畊챌┨皗㇖杪覴ﮩ喱燖㺄⃼㉇滁퍲⨳ផ㏿ᴮ㧁鲏੒್ᑐ坿쉝短黦꣏﨨犫?衢㛹䭔⮩㦔뵢㶛닻鿹ౝ㹴‣踮ᓃ㰪义ɻ没ᒳ률ԣ㓤ᒲ킰?捓ུᇺ뵂溆ﺾ텆ꇽ㈚췥ย䭲臆슽釤ا㷔㏙꿮룙ᥱ띀䙊ꇊ䂞㯡똒嫊盉ꍰ⮒溫ꡌᆽ末彡ᢻ؋股暰깽㹓맜晩幧뀪븑礄㘉聺䄬炉䨝碾㟖工箥蒠䬻껊缞臏㺸䴫?Մ辞ⶽ⌨?雈ퟧ㱋ࣃ䆰ꪅ냆ᔒ綨붎覗轢묆놬⬈隑끤즜㭨뱰Ⓦ箦欵映ꅘ䒲ᎍⓑ?챁䈾뽖ዂẂဎ뉶灢⊒뫶⵳竦贉㱘ॐ锛ᖽ⃌ꚋᄰ閊샘﮽뺭＞㱆薼櫏".toCharArray()[220] ^ 0x1A67); String str; int i = (str = aB$aG.q("⏆⑭곌䇚速ꊍⷱ?籠ㅫ떠㝤雽싿蘞뼽ޫ笊볶畟ﵫҌ妉垖蟐И箒勒⦓짩梊畊챌┨皗㇖杪覴ﮩ喱燖㺄⃼㉇滁퍲⨳ផ㏿ᴮ㧁鲏੒್ᑐ坿쉝短黦꣏﨨犫?衢㛹䭔⮩㦔뵢㶛닻鿹ౝ㹴‣踮ᓃ㰪义ɻ没ᒳ률ԣ㓤ᒲ킰?捓ུᇺ뵂溆ﺾ텆ꇽ㈚췥ย䭲臆슽釤ا㷔㏙꿮룙ᥱ띀䙊ꇊ䂞㯡똒嫊盉ꍰ⮒溫ꡌᆽ末彡ᢻ؋股暰깽㹓맜晩幧뀪븑礄㘉聺䄬炉䨝碾㟖工箥蒠䬻껊缞臏㺸䴫?Մ辞ⶽ⌨?雈ퟧ㱋ࣃ䆰ꪅ냆ᔒ綨붎覗轢묆놬⬈隑끤즜㭨뱰Ⓦ箦欵映ꅘ䒲ᎍⓑ?챁䈾뽖ዂẂဎ뉶灢⊒뫶⵳竦贉㱘ॐ锛ᖽ⃌ꚋᄰ閊샘﮽뺭＞㱆薼櫏".toCharArray(), (short)10066, (byte)4, (byte)5)).length(); byte b2 = 16; byte b = -1;
/*     */     while (true); }
/*     */ 
/*     */   
/*     */   public double[] a() {
/*  25 */     double[] arrayOfDouble = b();
/*     */ 
/*     */ 
/*     */ 
/*     */ 
/*     */     
/*     */     Arrays.sort(arrayOfDouble);
/*     */ 
/*     */ 
/*     */ 
/*     */     
/*  36 */     return arrayOfDouble;
/*     */   } public am a(int paramInt, char paramChar1, char paramChar2) { long l1 = (paramInt << 32L | paramChar1 << 48L >>> 32L | paramChar2 << 48L >>> 48L) ^ o, l2 = l1 ^ 0x1DC0E1687248L; return new am(l2, this); } public am(int paramInt, long paramLong) { this(paramInt, l, false, null); } public void a(double paramDouble, long paramLong) { // Byte code:
/*     */     //   0: getstatic aacinternal/am.o : J
/*     */     //   3: lload_3
/*     */     //   4: lxor
/*     */     //   5: lstore_3
/*     */     //   6: lload_3
/*     */     //   7: dup2
/*     */     //   8: ldc2_w 118691029669982
/*     */     //   11: lxor
/*     */     //   12: dup2
/*     */     //   13: bipush #48
/*     */     //   15: lushr
/*     */     //   16: l2i
/*     */     //   17: istore #5
/*     */     //   19: dup2
/*     */     //   20: bipush #16
/*     */     //   22: lshl
/*     */     //   23: bipush #48
/*     */     //   25: lushr
/*     */     //   26: l2i
/*     */     //   27: istore #6
/*     */     //   29: dup2
/*     */     //   30: bipush #32
/*     */     //   32: lshl
/*     */     //   33: bipush #32
/*     */     //   35: lushr
/*     */     //   36: l2i
/*     */     //   37: istore #7
/*     */     //   39: pop2
/*     */     //   40: dup2
/*     */     //   41: ldc2_w 105382137352666
/*     */     //   44: lxor
/*     */     //   45: dup2
/*     */     //   46: bipush #48
/*     */     //   48: lushr
/*     */     //   49: l2i
/*     */     //   50: istore #8
/*     */     //   52: dup2
/*     */     //   53: bipush #16
/*     */     //   55: lshl
/*     */     //   56: bipush #16
/*     */     //   58: lushr
/*     */     //   59: lstore #9
/*     */     //   61: pop2
/*     */     //   62: pop2
/*     */     //   63: ldc2_w -4707587790868644333
/*     */     //   66: lload_3
/*     */     //   67: <illegal opcode> w : (JJ)[Lme/konsolas/aac/aN;
/*     */     //   72: astore #11
/*     */     //   74: aload_0
/*     */     //   75: aload #11
/*     */     //   77: ifnull -> 267
/*     */     //   80: getfield i : I
/*     */     //   83: iconst_m1
/*     */     //   84: if_icmpeq -> 253
/*     */     //   87: goto -> 100
/*     */     //   90: ldc2_w -4715780538061299363
/*     */     //   93: lload_3
/*     */     //   94: <illegal opcode> w : (Laacinternal/v;JJ)Laacinternal/v;
/*     */     //   99: athrow
/*     */     //   100: aload_0
/*     */     //   101: invokevirtual a : ()J
/*     */     //   104: aload_0
/*     */     //   105: getfield i : I
/*     */     //   108: i2l
/*     */     //   109: lcmp
/*     */     //   110: aload #11
/*     */     //   112: ifnull -> 226
/*     */     //   115: goto -> 128
/*     */     //   118: ldc2_w -4715780538061299363
/*     */     //   121: lload_3
/*     */     //   122: <illegal opcode> w : (Laacinternal/v;JJ)Laacinternal/v;
/*     */     //   127: athrow
/*     */     //   128: ifne -> 179
/*     */     //   131: goto -> 144
/*     */     //   134: ldc2_w -4715780538061299363
/*     */     //   137: lload_3
/*     */     //   138: <illegal opcode> w : (Laacinternal/v;JJ)Laacinternal/v;
/*     */     //   143: athrow
/*     */     //   144: aload_0
/*     */     //   145: getfield d : Laacinternal/B;
/*     */     //   148: iload #5
/*     */     //   150: i2c
/*     */     //   151: iload #6
/*     */     //   153: i2s
/*     */     //   154: dload_1
/*     */     //   155: iload #7
/*     */     //   157: invokevirtual a : (CSDI)D
/*     */     //   160: pop2
/*     */     //   161: aload #11
/*     */     //   163: ifnonnull -> 279
/*     */     //   166: goto -> 179
/*     */     //   169: ldc2_w -4715780538061299363
/*     */     //   172: lload_3
/*     */     //   173: <illegal opcode> w : (Laacinternal/v;JJ)Laacinternal/v;
/*     */     //   178: athrow
/*     */     //   179: aload_0
/*     */     //   180: lload_3
/*     */     //   181: lconst_0
/*     */     //   182: lcmp
/*     */     //   183: ifle -> 230
/*     */     //   186: aload #11
/*     */     //   188: ifnull -> 230
/*     */     //   191: goto -> 204
/*     */     //   194: ldc2_w -4715780538061299363
/*     */     //   197: lload_3
/*     */     //   198: <illegal opcode> w : (Laacinternal/v;JJ)Laacinternal/v;
/*     */     //   203: athrow
/*     */     //   204: invokevirtual a : ()J
/*     */     //   207: aload_0
/*     */     //   208: getfield i : I
/*     */     //   211: i2l
/*     */     //   212: lcmp
/*     */     //   213: goto -> 226
/*     */     //   216: ldc2_w -4715780538061299363
/*     */     //   219: lload_3
/*     */     //   220: <illegal opcode> w : (Laacinternal/v;JJ)Laacinternal/v;
/*     */     //   225: athrow
/*     */     //   226: ifge -> 279
/*     */     //   229: aload_0
/*     */     //   230: lload_3
/*     */     //   231: lconst_0
/*     */     //   232: lcmp
/*     */     //   233: ifle -> 254
/*     */     //   236: getfield d : Laacinternal/B;
/*     */     //   239: dload_1
/*     */     //   240: iload #8
/*     */     //   242: i2c
/*     */     //   243: lload #9
/*     */     //   245: invokevirtual a : (DCJ)V
/*     */     //   248: aload #11
/*     */     //   250: ifnonnull -> 279
/*     */     //   253: aload_0
/*     */     //   254: goto -> 267
/*     */     //   257: ldc2_w -4715780538061299363
/*     */     //   260: lload_3
/*     */     //   261: <illegal opcode> w : (Laacinternal/v;JJ)Laacinternal/v;
/*     */     //   266: athrow
/*     */     //   267: getfield d : Laacinternal/B;
/*     */     //   270: dload_1
/*     */     //   271: iload #8
/*     */     //   273: i2c
/*     */     //   274: lload #9
/*     */     //   276: invokevirtual a : (DCJ)V
/*     */     //   279: return
/*     */     // Line number table:
/*     */     //   Java source line number -> byte code offset
/*     */     //   #35	-> 74
/*     */     //   #16	-> 100
/*     */     //   #82	-> 144
/*     */     //   #31	-> 179
/*     */     //   #72	-> 229
/*     */     //   #52	-> 253
/*     */     //   #56	-> 279
/*     */     // Exception table:
/*     */     //   from	to	target	type
/*     */     //   74	87	90	aacinternal/v
/*     */     //   80	115	118	aacinternal/v
/*     */     //   100	131	134	aacinternal/v
/*     */     //   128	166	169	aacinternal/v
/*     */     //   144	191	194	aacinternal/v
/*     */     //   179	213	216	aacinternal/v
/*     */     //   230	254	257	aacinternal/v } protected am(long paramLong, am paramam) { // Byte code:
/*     */     //   0: getstatic aacinternal/am.o : J
/*     */     //   3: lload_1
/*     */     //   4: lxor
/*     */     //   5: lstore_1
/*     */     //   6: lload_1
/*     */     //   7: dup2
/*     */     //   8: ldc2_w 83770715067450
/*     */     //   11: lxor
/*     */     //   12: lstore #4
/*     */     //   14: dup2
/*     */     //   15: ldc2_w 101127970328345
/*     */     //   18: lxor
/*     */     //   19: lstore #6
/*     */     //   21: dup2
/*     */     //   22: ldc2_w 56581462343043
/*     */     //   25: lxor
/*     */     //   26: lstore #8
/*     */     //   28: dup2
/*     */     //   29: ldc2_w 109696022512285
/*     */     //   32: lxor
/*     */     //   33: lstore #10
/*     */     //   35: pop2
/*     */     //   36: aload_0
/*     */     //   37: invokespecial <init> : ()V
/*     */     //   40: ldc2_w 5717689609267384289
/*     */     //   43: lload_1
/*     */     //   44: <illegal opcode> w : (JJ)[Lme/konsolas/aac/aN;
/*     */     //   49: lload #4
/*     */     //   51: aload_3
/*     */     //   52: invokestatic a : (JLjava/lang/Object;)V
/*     */     //   55: aload_0
/*     */     //   56: aload_3
/*     */     //   57: getfield i : I
/*     */     //   60: putfield i : I
/*     */     //   63: aload_0
/*     */     //   64: aload_3
/*     */     //   65: getfield d : Laacinternal/B;
/*     */     //   68: lload #6
/*     */     //   70: invokevirtual a : (J)Laacinternal/B;
/*     */     //   73: putfield d : Laacinternal/B;
/*     */     //   76: astore #12
/*     */     //   78: aload_0
/*     */     //   79: aload_3
/*     */     //   80: getfield m : Laacinternal/aa;
/*     */     //   83: lload #8
/*     */     //   85: invokeinterface a : (J)Laacinternal/aa;
/*     */     //   90: putfield m : Laacinternal/aa;
/*     */     //   93: aload_0
/*     */     //   94: aload_3
/*     */     //   95: getfield g : Laacinternal/aa;
/*     */     //   98: lload #8
/*     */     //   100: invokeinterface a : (J)Laacinternal/aa;
/*     */     //   105: putfield g : Laacinternal/aa;
/*     */     //   108: aload_0
/*     */     //   109: aload_3
/*     */     //   110: getfield n : Laacinternal/aa;
/*     */     //   113: lload #8
/*     */     //   115: invokeinterface a : (J)Laacinternal/aa;
/*     */     //   120: putfield n : Laacinternal/aa;
/*     */     //   123: aload_0
/*     */     //   124: aload_3
/*     */     //   125: getfield c : Laacinternal/aa;
/*     */     //   128: lload #8
/*     */     //   130: invokeinterface a : (J)Laacinternal/aa;
/*     */     //   135: putfield c : Laacinternal/aa;
/*     */     //   138: aload_0
/*     */     //   139: aload_3
/*     */     //   140: getfield b : Laacinternal/aa;
/*     */     //   143: lload #8
/*     */     //   145: invokeinterface a : (J)Laacinternal/aa;
/*     */     //   150: putfield b : Laacinternal/aa;
/*     */     //   153: aload_0
/*     */     //   154: aload_3
/*     */     //   155: getfield f : Laacinternal/aa;
/*     */     //   158: lload #8
/*     */     //   160: invokeinterface a : (J)Laacinternal/aa;
/*     */     //   165: putfield f : Laacinternal/aa;
/*     */     //   168: aload_0
/*     */     //   169: aload_3
/*     */     //   170: getfield a : Laacinternal/aa;
/*     */     //   173: lload #8
/*     */     //   175: invokeinterface a : (J)Laacinternal/aa;
/*     */     //   180: putfield a : Laacinternal/aa;
/*     */     //   183: aload_0
/*     */     //   184: aload_3
/*     */     //   185: getfield k : Laacinternal/aa;
/*     */     //   188: lload #8
/*     */     //   190: invokeinterface a : (J)Laacinternal/aa;
/*     */     //   195: putfield k : Laacinternal/aa;
/*     */     //   198: aload_0
/*     */     //   199: aload_3
/*     */     //   200: getfield j : Laacinternal/aa;
/*     */     //   203: lload #8
/*     */     //   205: invokeinterface a : (J)Laacinternal/aa;
/*     */     //   210: putfield j : Laacinternal/aa;
/*     */     //   213: aload_0
/*     */     //   214: aload_3
/*     */     //   215: getfield h : Laacinternal/aD;
/*     */     //   218: lload #10
/*     */     //   220: invokevirtual a : (J)Laacinternal/aD;
/*     */     //   223: putfield h : Laacinternal/aD;
/*     */     //   226: ldc2_w 5719059924837600253
/*     */     //   229: lload_1
/*     */     //   230: <illegal opcode> w : (JJ)[Lme/konsolas/aac/aN;
/*     */     //   235: ifnull -> 264
/*     */     //   238: iconst_1
/*     */     //   239: anewarray me/konsolas/aac/aN
/*     */     //   242: ldc2_w 5681094457946862968
/*     */     //   245: lload_1
/*     */     //   246: <illegal opcode> w : ([Lme/konsolas/aac/aN;JJ)V
/*     */     //   251: goto -> 264
/*     */     //   254: ldc2_w 5727513482156970159
/*     */     //   257: lload_1
/*     */     //   258: <illegal opcode> w : (Laacinternal/v;JJ)Laacinternal/v;
/*     */     //   263: athrow
/*     */     //   264: return
/*     */     // Line number table:
/*     */     //   Java source line number -> byte code offset
/*     */     //   #37	-> 36
/*     */     //   #74	-> 49
/*     */     //   #23	-> 55
/*     */     //   #75	-> 63
/*     */     //   #24	-> 78
/*     */     //   #101	-> 93
/*     */     //   #86	-> 108
/*     */     //   #102	-> 123
/*     */     //   #32	-> 138
/*     */     //   #7	-> 153
/*     */     //   #77	-> 168
/*     */     //   #91	-> 183
/*     */     //   #98	-> 198
/*     */     //   #60	-> 213
/*     */     //   #67	-> 226
/*     */     // Exception table:
/*     */     //   from	to	target	type
/*     */     //   78	251	254	aacinternal/v }
/*  38 */   public double i(long paramLong) { paramLong = o ^ paramLong; long l = paramLong ^ 0x71376AE1A412L; return a(l, this.a); }
/*  39 */   public double a(long paramLong) { long l = paramLong ^ 0x11D8C5C882E7L; return a(l, this.g); } public String toString() {
/*     */     // Byte code:
/*     */     //   0: getstatic aacinternal/am.o : J
/*     */     //   3: ldc2_w 99772393521561
/*     */     //   6: lxor
/*     */     //   7: lstore_1
/*     */     //   8: lload_1
/*     */     //   9: dup2
/*     */     //   10: ldc2_w 112139229259002
/*     */     //   13: lxor
/*     */     //   14: lstore_3
/*     */     //   15: dup2
/*     */     //   16: ldc2_w 130184857662657
/*     */     //   19: lxor
/*     */     //   20: lstore #5
/*     */     //   22: dup2
/*     */     //   23: ldc2_w 130313430404346
/*     */     //   26: lxor
/*     */     //   27: lstore #7
/*     */     //   29: dup2
/*     */     //   30: ldc2_w 121509421932032
/*     */     //   33: lxor
/*     */     //   34: lstore #9
/*     */     //   36: dup2
/*     */     //   37: ldc2_w 1429883739798
/*     */     //   40: lxor
/*     */     //   41: lstore #11
/*     */     //   43: dup2
/*     */     //   44: ldc2_w 72196399580727
/*     */     //   47: lxor
/*     */     //   48: dup2
/*     */     //   49: bipush #48
/*     */     //   51: lushr
/*     */     //   52: l2i
/*     */     //   53: istore #13
/*     */     //   55: dup2
/*     */     //   56: bipush #16
/*     */     //   58: lshl
/*     */     //   59: bipush #32
/*     */     //   61: lushr
/*     */     //   62: l2i
/*     */     //   63: istore #14
/*     */     //   65: dup2
/*     */     //   66: bipush #48
/*     */     //   68: lshl
/*     */     //   69: bipush #48
/*     */     //   71: lushr
/*     */     //   72: l2i
/*     */     //   73: istore #15
/*     */     //   75: pop2
/*     */     //   76: dup2
/*     */     //   77: ldc2_w 80260200068047
/*     */     //   80: lxor
/*     */     //   81: dup2
/*     */     //   82: bipush #32
/*     */     //   84: lushr
/*     */     //   85: l2i
/*     */     //   86: istore #16
/*     */     //   88: dup2
/*     */     //   89: bipush #32
/*     */     //   91: lshl
/*     */     //   92: bipush #48
/*     */     //   94: lushr
/*     */     //   95: l2i
/*     */     //   96: istore #17
/*     */     //   98: dup2
/*     */     //   99: bipush #48
/*     */     //   101: lshl
/*     */     //   102: bipush #48
/*     */     //   104: lushr
/*     */     //   105: l2i
/*     */     //   106: istore #18
/*     */     //   108: pop2
/*     */     //   109: pop2
/*     */     //   110: new java/lang/StringBuilder
/*     */     //   113: dup
/*     */     //   114: bipush #100
/*     */     //   116: invokespecial <init> : (I)V
/*     */     //   119: astore #19
/*     */     //   121: ldc_w '᳀亟'
/*     */     //   124: invokevirtual toCharArray : ()[C
/*     */     //   127: dup
/*     */     //   128: dup
/*     */     //   129: iconst_0
/*     */     //   130: dup_x1
/*     */     //   131: caload
/*     */     //   132: sipush #29079
/*     */     //   135: ixor
/*     */     //   136: i2c
/*     */     //   137: castore
/*     */     //   138: sipush #16907
/*     */     //   141: iconst_0
/*     */     //   142: iconst_1
/*     */     //   143: invokestatic L : (Ljava/lang/Object;SBZ)Ljava/lang/String;
/*     */     //   146: astore #20
/*     */     //   148: aload #19
/*     */     //   150: sipush #28213
/*     */     //   153: ldc2_w 6920514081268497853
/*     */     //   156: lload_1
/*     */     //   157: lxor
/*     */     //   158: <illegal opcode> j : (IJ)Ljava/lang/String;
/*     */     //   163: invokevirtual append : (Ljava/lang/String;)Ljava/lang/StringBuilder;
/*     */     //   166: ldc_w '终搉'
/*     */     //   169: invokevirtual toCharArray : ()[C
/*     */     //   172: dup
/*     */     //   173: dup
/*     */     //   174: iconst_0
/*     */     //   175: dup_x1
/*     */     //   176: caload
/*     */     //   177: sipush #6957
/*     */     //   180: ixor
/*     */     //   181: i2c
/*     */     //   182: castore
/*     */     //   183: sipush #8484
/*     */     //   186: iconst_4
/*     */     //   187: iconst_0
/*     */     //   188: invokestatic L : (Ljava/lang/Object;SBZ)Ljava/lang/String;
/*     */     //   191: invokevirtual append : (Ljava/lang/String;)Ljava/lang/StringBuilder;
/*     */     //   194: sipush #25619
/*     */     //   197: ldc2_w 136443641639630745
/*     */     //   200: lload_1
/*     */     //   201: lxor
/*     */     //   202: <illegal opcode> j : (IJ)Ljava/lang/String;
/*     */     //   207: invokevirtual append : (Ljava/lang/String;)Ljava/lang/StringBuilder;
/*     */     //   210: aload_0
/*     */     //   211: invokevirtual a : ()J
/*     */     //   214: invokevirtual append : (J)Ljava/lang/StringBuilder;
/*     */     //   217: ldc_w '٫怼'
/*     */     //   220: invokevirtual toCharArray : ()[C
/*     */     //   223: dup
/*     */     //   224: dup
/*     */     //   225: iconst_0
/*     */     //   226: dup_x1
/*     */     //   227: caload
/*     */     //   228: sipush #29480
/*     */     //   231: ixor
/*     */     //   232: i2c
/*     */     //   233: castore
/*     */     //   234: sipush #4127
/*     */     //   237: iconst_3
/*     */     //   238: iconst_0
/*     */     //   239: invokestatic L : (Ljava/lang/Object;SBZ)Ljava/lang/String;
/*     */     //   242: invokevirtual append : (Ljava/lang/String;)Ljava/lang/StringBuilder;
/*     */     //   245: sipush #32165
/*     */     //   248: ldc2_w 3784880882125729313
/*     */     //   251: lload_1
/*     */     //   252: lxor
/*     */     //   253: <illegal opcode> j : (IJ)Ljava/lang/String;
/*     */     //   258: invokevirtual append : (Ljava/lang/String;)Ljava/lang/StringBuilder;
/*     */     //   261: aload_0
/*     */     //   262: lload_3
/*     */     //   263: invokevirtual a : (J)D
/*     */     //   266: invokevirtual append : (D)Ljava/lang/StringBuilder;
/*     */     //   269: ldc_w '읈疃'
/*     */     //   272: invokevirtual toCharArray : ()[C
/*     */     //   275: dup
/*     */     //   276: dup
/*     */     //   277: iconst_0
/*     */     //   278: dup_x1
/*     */     //   279: caload
/*     */     //   280: sipush #17791
/*     */     //   283: ixor
/*     */     //   284: i2c
/*     */     //   285: castore
/*     */     //   286: sipush #31271
/*     */     //   289: iconst_3
/*     */     //   290: iconst_1
/*     */     //   291: invokestatic L : (Ljava/lang/Object;SBZ)Ljava/lang/String;
/*     */     //   294: invokevirtual append : (Ljava/lang/String;)Ljava/lang/StringBuilder;
/*     */     //   297: sipush #13011
/*     */     //   300: ldc2_w 1666934173071810910
/*     */     //   303: lload_1
/*     */     //   304: lxor
/*     */     //   305: <illegal opcode> j : (IJ)Ljava/lang/String;
/*     */     //   310: invokevirtual append : (Ljava/lang/String;)Ljava/lang/StringBuilder;
/*     */     //   313: aload_0
/*     */     //   314: iload #16
/*     */     //   316: iload #17
/*     */     //   318: i2s
/*     */     //   319: iload #18
/*     */     //   321: i2s
/*     */     //   322: invokevirtual d : (ISS)D
/*     */     //   325: invokevirtual append : (D)Ljava/lang/StringBuilder;
/*     */     //   328: ldc_w 'ᴜ媧'
/*     */     //   331: invokevirtual toCharArray : ()[C
/*     */     //   334: dup
/*     */     //   335: dup
/*     */     //   336: iconst_0
/*     */     //   337: dup_x1
/*     */     //   338: caload
/*     */     //   339: sipush #29154
/*     */     //   342: ixor
/*     */     //   343: i2c
/*     */     //   344: castore
/*     */     //   345: sipush #20714
/*     */     //   348: iconst_5
/*     */     //   349: iconst_1
/*     */     //   350: invokestatic L : (Ljava/lang/Object;SBZ)Ljava/lang/String;
/*     */     //   353: invokevirtual append : (Ljava/lang/String;)Ljava/lang/StringBuilder;
/*     */     //   356: sipush #9285
/*     */     //   359: ldc2_w 6951601935710140362
/*     */     //   362: lload_1
/*     */     //   363: lxor
/*     */     //   364: <illegal opcode> j : (IJ)Ljava/lang/String;
/*     */     //   369: invokevirtual append : (Ljava/lang/String;)Ljava/lang/StringBuilder;
/*     */     //   372: aload_0
/*     */     //   373: lload #5
/*     */     //   375: invokevirtual b : (J)D
/*     */     //   378: invokevirtual append : (D)Ljava/lang/StringBuilder;
/*     */     //   381: ldc_w 'ꦸܾ'
/*     */     //   384: invokevirtual toCharArray : ()[C
/*     */     //   387: dup
/*     */     //   388: dup
/*     */     //   389: iconst_0
/*     */     //   390: dup_x1
/*     */     //   391: caload
/*     */     //   392: sipush #25657
/*     */     //   395: ixor
/*     */     //   396: i2c
/*     */     //   397: castore
/*     */     //   398: sipush #19478
/*     */     //   401: iconst_5
/*     */     //   402: iconst_1
/*     */     //   403: invokestatic L : (Ljava/lang/Object;SBZ)Ljava/lang/String;
/*     */     //   406: invokevirtual append : (Ljava/lang/String;)Ljava/lang/StringBuilder;
/*     */     //   409: sipush #12212
/*     */     //   412: ldc2_w 2046611955508624433
/*     */     //   415: lload_1
/*     */     //   416: lxor
/*     */     //   417: <illegal opcode> j : (IJ)Ljava/lang/String;
/*     */     //   422: invokevirtual append : (Ljava/lang/String;)Ljava/lang/StringBuilder;
/*     */     //   425: aload_0
/*     */     //   426: lload #7
/*     */     //   428: invokevirtual c : (J)D
/*     */     //   431: invokevirtual append : (D)Ljava/lang/StringBuilder;
/*     */     //   434: ldc_w '绣⇶'
/*     */     //   437: invokevirtual toCharArray : ()[C
/*     */     //   440: dup
/*     */     //   441: dup
/*     */     //   442: iconst_0
/*     */     //   443: dup_x1
/*     */     //   444: caload
/*     */     //   445: sipush #2606
/*     */     //   448: ixor
/*     */     //   449: i2c
/*     */     //   450: castore
/*     */     //   451: sipush #5556
/*     */     //   454: iconst_1
/*     */     //   455: iconst_1
/*     */     //   456: invokestatic L : (Ljava/lang/Object;SBZ)Ljava/lang/String;
/*     */     //   459: invokevirtual append : (Ljava/lang/String;)Ljava/lang/StringBuilder;
/*     */     //   462: pop
/*     */     //   463: aload #19
/*     */     //   465: sipush #21316
/*     */     //   468: ldc2_w 718254579039125711
/*     */     //   471: lload_1
/*     */     //   472: lxor
/*     */     //   473: <illegal opcode> j : (IJ)Ljava/lang/String;
/*     */     //   478: invokevirtual append : (Ljava/lang/String;)Ljava/lang/StringBuilder;
/*     */     //   481: aload_0
/*     */     //   482: ldc2_w 50.0
/*     */     //   485: lload #11
/*     */     //   487: invokevirtual b : (DJ)D
/*     */     //   490: invokevirtual append : (D)Ljava/lang/StringBuilder;
/*     */     //   493: ldc_w '蚼ⷑ'
/*     */     //   496: invokevirtual toCharArray : ()[C
/*     */     //   499: dup
/*     */     //   500: dup
/*     */     //   501: iconst_0
/*     */     //   502: dup_x1
/*     */     //   503: caload
/*     */     //   504: sipush #295
/*     */     //   507: ixor
/*     */     //   508: i2c
/*     */     //   509: castore
/*     */     //   510: sipush #7975
/*     */     //   513: iconst_5
/*     */     //   514: iconst_0
/*     */     //   515: invokestatic L : (Ljava/lang/Object;SBZ)Ljava/lang/String;
/*     */     //   518: invokevirtual append : (Ljava/lang/String;)Ljava/lang/StringBuilder;
/*     */     //   521: pop
/*     */     //   522: goto -> 574
/*     */     //   525: astore #21
/*     */     //   527: aload #19
/*     */     //   529: sipush #31802
/*     */     //   532: ldc2_w 326318386658668468
/*     */     //   535: lload_1
/*     */     //   536: lxor
/*     */     //   537: <illegal opcode> j : (IJ)Ljava/lang/String;
/*     */     //   542: invokevirtual append : (Ljava/lang/String;)Ljava/lang/StringBuilder;
/*     */     //   545: ldc_w '큖㬝'
/*     */     //   548: invokevirtual toCharArray : ()[C
/*     */     //   551: dup
/*     */     //   552: dup
/*     */     //   553: iconst_0
/*     */     //   554: dup_x1
/*     */     //   555: caload
/*     */     //   556: sipush #18734
/*     */     //   559: ixor
/*     */     //   560: i2c
/*     */     //   561: castore
/*     */     //   562: sipush #18579
/*     */     //   565: iconst_0
/*     */     //   566: iconst_0
/*     */     //   567: invokestatic L : (Ljava/lang/Object;SBZ)Ljava/lang/String;
/*     */     //   570: invokevirtual append : (Ljava/lang/String;)Ljava/lang/StringBuilder;
/*     */     //   573: pop
/*     */     //   574: aload #19
/*     */     //   576: sipush #14278
/*     */     //   579: ldc2_w 4655184563291956298
/*     */     //   582: lload_1
/*     */     //   583: lxor
/*     */     //   584: <illegal opcode> j : (IJ)Ljava/lang/String;
/*     */     //   589: invokevirtual append : (Ljava/lang/String;)Ljava/lang/StringBuilder;
/*     */     //   592: aload_0
/*     */     //   593: lload #9
/*     */     //   595: invokevirtual g : (J)D
/*     */     //   598: invokevirtual append : (D)Ljava/lang/StringBuilder;
/*     */     //   601: ldc_w 'ﳙᄳ'
/*     */     //   604: invokevirtual toCharArray : ()[C
/*     */     //   607: dup
/*     */     //   608: dup
/*     */     //   609: iconst_0
/*     */     //   610: dup_x1
/*     */     //   611: caload
/*     */     //   612: sipush #13548
/*     */     //   615: ixor
/*     */     //   616: i2c
/*     */     //   617: castore
/*     */     //   618: sipush #31464
/*     */     //   621: iconst_0
/*     */     //   622: iconst_0
/*     */     //   623: invokestatic L : (Ljava/lang/Object;SBZ)Ljava/lang/String;
/*     */     //   626: invokevirtual append : (Ljava/lang/String;)Ljava/lang/StringBuilder;
/*     */     //   629: sipush #17197
/*     */     //   632: ldc2_w 3893438116474278052
/*     */     //   635: lload_1
/*     */     //   636: lxor
/*     */     //   637: <illegal opcode> j : (IJ)Ljava/lang/String;
/*     */     //   642: invokevirtual append : (Ljava/lang/String;)Ljava/lang/StringBuilder;
/*     */     //   645: aload_0
/*     */     //   646: iload #13
/*     */     //   648: i2s
/*     */     //   649: iload #14
/*     */     //   651: iload #15
/*     */     //   653: i2s
/*     */     //   654: invokevirtual h : (SIS)D
/*     */     //   657: invokevirtual append : (D)Ljava/lang/StringBuilder;
/*     */     //   660: ldc_w 'ἥ䉦'
/*     */     //   663: invokevirtual toCharArray : ()[C
/*     */     //   666: dup
/*     */     //   667: dup
/*     */     //   668: iconst_0
/*     */     //   669: dup_x1
/*     */     //   670: caload
/*     */     //   671: sipush #4673
/*     */     //   674: ixor
/*     */     //   675: i2c
/*     */     //   676: castore
/*     */     //   677: sipush #18423
/*     */     //   680: iconst_4
/*     */     //   681: iconst_0
/*     */     //   682: invokestatic L : (Ljava/lang/Object;SBZ)Ljava/lang/String;
/*     */     //   685: invokevirtual append : (Ljava/lang/String;)Ljava/lang/StringBuilder;
/*     */     //   688: pop
/*     */     //   689: aload #19
/*     */     //   691: invokevirtual toString : ()Ljava/lang/String;
/*     */     //   694: areturn
/*     */     // Line number table:
/*     */     //   Java source line number -> byte code offset
/*     */     //   #40	-> 110
/*     */     //   #27	-> 121
/*     */     //   #34	-> 148
/*     */     //   #3	-> 207
/*     */     //   #50	-> 258
/*     */     //   #41	-> 310
/*     */     //   #79	-> 369
/*     */     //   #94	-> 422
/*     */     //   #8	-> 463
/*     */     //   #110	-> 522
/*     */     //   #85	-> 525
/*     */     //   #26	-> 527
/*     */     //   #57	-> 574
/*     */     //   #45	-> 642
/*     */     //   #78	-> 689
/*     */     // Exception table:
/*     */     //   from	to	target	type
/*     */     //   463	522	525	aacinternal/w
/*     */   } public long a() {
/*  42 */     return this.d.c();
/*     */   } public double j(long paramLong) {
/*  44 */     paramLong = o ^ paramLong; long l = paramLong ^ 0x4DFAF1C2D9B6L; return a(l, this.b);
/*     */   }
/*     */ 
/*     */   
/*     */   public double b(double paramDouble, long paramLong) {
/*  49 */     paramLong = o ^ paramLong; long l1 = paramLong ^ 0x1B3C2B9FAFE7L, l2 = paramLong ^ 0x12E06DC9F7D5L; this.h.a(l2, paramDouble);
/*     */ 
/*     */ 
/*     */ 
/*     */ 
/*     */     
/*  55 */     return a(l1, this.h);
/*     */   }
/*     */ 
/*     */ 
/*     */ 
/*     */   
/*     */   public double[] b()
/*     */   {
/*  63 */     return this.d.b(); } public double a(int paramInt1, long paramLong, int paramInt2) {
/*  64 */     long l1 = (paramLong << 32L | paramInt2 << 32L >>> 32L) ^ o, l2 = l1 ^ 0x5BDCAA44263BL; return this.d.a(l2, paramInt1);
/*     */   } am(int paramInt, long paramLong, boolean paramBoolean, double[] paramArrayOfdouble) {
/*     */     // Byte code:
/*     */     //   0: getstatic aacinternal/am.o : J
/*     */     //   3: lload_2
/*     */     //   4: lxor
/*     */     //   5: lstore_2
/*     */     //   6: lload_2
/*     */     //   7: dup2
/*     */     //   8: ldc2_w 29456143616006
/*     */     //   11: lxor
/*     */     //   12: lstore #6
/*     */     //   14: dup2
/*     */     //   15: ldc2_w 41790243885337
/*     */     //   18: lxor
/*     */     //   19: lstore #8
/*     */     //   21: dup2
/*     */     //   22: ldc2_w 67446896873607
/*     */     //   25: lxor
/*     */     //   26: lstore #10
/*     */     //   28: dup2
/*     */     //   29: ldc2_w 131430626113202
/*     */     //   32: lxor
/*     */     //   33: lstore #12
/*     */     //   35: dup2
/*     */     //   36: ldc2_w 119723066381354
/*     */     //   39: lxor
/*     */     //   40: dup2
/*     */     //   41: bipush #48
/*     */     //   43: lushr
/*     */     //   44: l2i
/*     */     //   45: istore #14
/*     */     //   47: dup2
/*     */     //   48: bipush #16
/*     */     //   50: lshl
/*     */     //   51: bipush #32
/*     */     //   53: lushr
/*     */     //   54: l2i
/*     */     //   55: istore #15
/*     */     //   57: dup2
/*     */     //   58: bipush #48
/*     */     //   60: lshl
/*     */     //   61: bipush #48
/*     */     //   63: lushr
/*     */     //   64: l2i
/*     */     //   65: istore #16
/*     */     //   67: pop2
/*     */     //   68: pop2
/*     */     //   69: ldc2_w -2325435483656642814
/*     */     //   72: lload_2
/*     */     //   73: <illegal opcode> w : (JJ)[Lme/konsolas/aac/aN;
/*     */     //   78: aload_0
/*     */     //   79: invokespecial <init> : ()V
/*     */     //   82: astore #17
/*     */     //   84: iload_1
/*     */     //   85: aload #17
/*     */     //   87: ifnull -> 191
/*     */     //   90: iconst_1
/*     */     //   91: if_icmpge -> 189
/*     */     //   94: goto -> 107
/*     */     //   97: ldc2_w -2333141739895291828
/*     */     //   100: lload_2
/*     */     //   101: <illegal opcode> w : (Laacinternal/v;JJ)Laacinternal/v;
/*     */     //   106: athrow
/*     */     //   107: iload_1
/*     */     //   108: aload #17
/*     */     //   110: lload_2
/*     */     //   111: lconst_0
/*     */     //   112: lcmp
/*     */     //   113: iflt -> 199
/*     */     //   116: ifnull -> 191
/*     */     //   119: goto -> 132
/*     */     //   122: ldc2_w -2333141739895291828
/*     */     //   125: lload_2
/*     */     //   126: <illegal opcode> w : (Laacinternal/v;JJ)Laacinternal/v;
/*     */     //   131: athrow
/*     */     //   132: iconst_m1
/*     */     //   133: if_icmpeq -> 189
/*     */     //   136: goto -> 149
/*     */     //   139: ldc2_w -2333141739895291828
/*     */     //   142: lload_2
/*     */     //   143: <illegal opcode> w : (Laacinternal/v;JJ)Laacinternal/v;
/*     */     //   148: athrow
/*     */     //   149: new aacinternal/v
/*     */     //   152: dup
/*     */     //   153: getstatic aacinternal/P.NOT_POSITIVE_WINDOW_SIZE : Laacinternal/P;
/*     */     //   156: iconst_1
/*     */     //   157: anewarray java/lang/Object
/*     */     //   160: dup
/*     */     //   161: iconst_0
/*     */     //   162: iload_1
/*     */     //   163: invokestatic valueOf : (I)Ljava/lang/Integer;
/*     */     //   166: aastore
/*     */     //   167: iload #14
/*     */     //   169: i2s
/*     */     //   170: iload #15
/*     */     //   172: iload #16
/*     */     //   174: i2s
/*     */     //   175: invokespecial <init> : (Laacinternal/H;[Ljava/lang/Object;SIS)V
/*     */     //   178: athrow
/*     */     //   179: ldc2_w -2333141739895291828
/*     */     //   182: lload_2
/*     */     //   183: <illegal opcode> w : (Laacinternal/v;JJ)Laacinternal/v;
/*     */     //   188: athrow
/*     */     //   189: iload #4
/*     */     //   191: lload_2
/*     */     //   192: lconst_0
/*     */     //   193: lcmp
/*     */     //   194: ifle -> 272
/*     */     //   197: aload #17
/*     */     //   199: ifnull -> 272
/*     */     //   202: ifeq -> 245
/*     */     //   205: goto -> 218
/*     */     //   208: ldc2_w -2333141739895291828
/*     */     //   211: lload_2
/*     */     //   212: <illegal opcode> w : (Laacinternal/v;JJ)Laacinternal/v;
/*     */     //   217: athrow
/*     */     //   218: aload #5
/*     */     //   220: getstatic aacinternal/P.INPUT_ARRAY : Laacinternal/P;
/*     */     //   223: iconst_0
/*     */     //   224: anewarray java/lang/Object
/*     */     //   227: lload #12
/*     */     //   229: invokestatic a : (Ljava/lang/Object;Laacinternal/H;[Ljava/lang/Object;J)V
/*     */     //   232: goto -> 245
/*     */     //   235: ldc2_w -2333141739895291828
/*     */     //   238: lload_2
/*     */     //   239: <illegal opcode> w : (Laacinternal/v;JJ)Laacinternal/v;
/*     */     //   244: athrow
/*     */     //   245: aload_0
/*     */     //   246: iload_1
/*     */     //   247: putfield i : I
/*     */     //   250: aload_0
/*     */     //   251: aload #17
/*     */     //   253: ifnull -> 297
/*     */     //   256: getfield i : I
/*     */     //   259: goto -> 272
/*     */     //   262: ldc2_w -2333141739895291828
/*     */     //   265: lload_2
/*     */     //   266: <illegal opcode> w : (Laacinternal/v;JJ)Laacinternal/v;
/*     */     //   271: athrow
/*     */     //   272: lload_2
/*     */     //   273: lconst_0
/*     */     //   274: lcmp
/*     */     //   275: ifle -> 283
/*     */     //   278: ifge -> 296
/*     */     //   281: bipush #100
/*     */     //   283: goto -> 300
/*     */     //   286: ldc2_w -2333141739895291828
/*     */     //   289: lload_2
/*     */     //   290: <illegal opcode> w : (Laacinternal/v;JJ)Laacinternal/v;
/*     */     //   295: athrow
/*     */     //   296: aload_0
/*     */     //   297: getfield i : I
/*     */     //   300: istore #18
/*     */     //   302: aload_0
/*     */     //   303: iload #4
/*     */     //   305: ifeq -> 332
/*     */     //   308: new aacinternal/B
/*     */     //   311: dup
/*     */     //   312: aload #5
/*     */     //   314: lload #8
/*     */     //   316: invokespecial <init> : ([DJ)V
/*     */     //   319: goto -> 343
/*     */     //   322: ldc2_w -2333141739895291828
/*     */     //   325: lload_2
/*     */     //   326: <illegal opcode> w : (Laacinternal/v;JJ)Laacinternal/v;
/*     */     //   331: athrow
/*     */     //   332: new aacinternal/B
/*     */     //   335: dup
/*     */     //   336: iload #18
/*     */     //   338: lload #6
/*     */     //   340: invokespecial <init> : (IJ)V
/*     */     //   343: putfield d : Laacinternal/B;
/*     */     //   346: aload_0
/*     */     //   347: new aacinternal/aq
/*     */     //   350: dup
/*     */     //   351: invokespecial <init> : ()V
/*     */     //   354: putfield m : Laacinternal/aa;
/*     */     //   357: aload_0
/*     */     //   358: new aacinternal/aM
/*     */     //   361: dup
/*     */     //   362: invokespecial <init> : ()V
/*     */     //   365: putfield g : Laacinternal/aa;
/*     */     //   368: aload_0
/*     */     //   369: new aacinternal/aE
/*     */     //   372: dup
/*     */     //   373: invokespecial <init> : ()V
/*     */     //   376: putfield c : Laacinternal/aa;
/*     */     //   379: aload_0
/*     */     //   380: new aacinternal/as
/*     */     //   383: dup
/*     */     //   384: invokespecial <init> : ()V
/*     */     //   387: putfield b : Laacinternal/aa;
/*     */     //   390: aload_0
/*     */     //   391: new aacinternal/aJ
/*     */     //   394: dup
/*     */     //   395: invokespecial <init> : ()V
/*     */     //   398: putfield n : Laacinternal/aa;
/*     */     //   401: aload_0
/*     */     //   402: new aacinternal/a8
/*     */     //   405: dup
/*     */     //   406: invokespecial <init> : ()V
/*     */     //   409: putfield f : Laacinternal/aa;
/*     */     //   412: aload_0
/*     */     //   413: new aacinternal/a4
/*     */     //   416: dup
/*     */     //   417: invokespecial <init> : ()V
/*     */     //   420: putfield a : Laacinternal/aa;
/*     */     //   423: aload_0
/*     */     //   424: new aacinternal/aS
/*     */     //   427: dup
/*     */     //   428: invokespecial <init> : ()V
/*     */     //   431: putfield k : Laacinternal/aa;
/*     */     //   434: aload_0
/*     */     //   435: new aacinternal/av
/*     */     //   438: dup
/*     */     //   439: invokespecial <init> : ()V
/*     */     //   442: putfield j : Laacinternal/aa;
/*     */     //   445: aload_0
/*     */     //   446: new aacinternal/aD
/*     */     //   449: dup
/*     */     //   450: lload #10
/*     */     //   452: invokespecial <init> : (J)V
/*     */     //   455: putfield h : Laacinternal/aD;
/*     */     //   458: aload #17
/*     */     //   460: lload_2
/*     */     //   461: lconst_0
/*     */     //   462: lcmp
/*     */     //   463: iflt -> 473
/*     */     //   466: ifnonnull -> 495
/*     */     //   469: iconst_4
/*     */     //   470: anewarray me/konsolas/aac/aN
/*     */     //   473: ldc2_w -2341643195805727147
/*     */     //   476: lload_2
/*     */     //   477: <illegal opcode> w : ([Lme/konsolas/aac/aN;JJ)V
/*     */     //   482: goto -> 495
/*     */     //   485: ldc2_w -2333141739895291828
/*     */     //   488: lload_2
/*     */     //   489: <illegal opcode> w : (Laacinternal/v;JJ)Laacinternal/v;
/*     */     //   494: athrow
/*     */     //   495: return
/*     */     // Line number table:
/*     */     //   Java source line number -> byte code offset
/*     */     //   #65	-> 78
/*     */     //   #92	-> 84
/*     */     //   #53	-> 149
/*     */     //   #93	-> 163
/*     */     //   #61	-> 189
/*     */     //   #73	-> 218
/*     */     //   #17	-> 245
/*     */     //   #66	-> 250
/*     */     //   #87	-> 302
/*     */     //   #47	-> 346
/*     */     //   #109	-> 357
/*     */     //   #10	-> 368
/*     */     //   #6	-> 379
/*     */     //   #18	-> 390
/*     */     //   #54	-> 401
/*     */     //   #84	-> 412
/*     */     //   #80	-> 423
/*     */     //   #51	-> 434
/*     */     //   #43	-> 445
/*     */     //   #9	-> 458
/*     */     // Exception table:
/*     */     //   from	to	target	type
/*     */     //   84	94	97	aacinternal/v
/*     */     //   90	119	122	aacinternal/v
/*     */     //   107	136	139	aacinternal/v
/*     */     //   132	179	179	aacinternal/v
/*     */     //   191	205	208	aacinternal/v
/*     */     //   202	232	235	aacinternal/v
/*     */     //   245	259	262	aacinternal/v
/*     */     //   272	286	286	aacinternal/v
/*     */     //   302	322	322	aacinternal/v
/*     */     //   343	482	485	aacinternal/v
/*     */   }
/*  68 */   public double h(short paramShort1, int paramInt, short paramShort2) { long l1 = (paramShort1 << 48L | paramInt << 32L >>> 16L | paramShort2 << 48L >>> 48L) ^ o, l2 = l1 ^ 0x5BD948E9B746L; return a(l2, this.k); } public double c(long paramLong) { // Byte code:
/*     */     //   0: lload_1
/*     */     //   1: dup2
/*     */     //   2: ldc2_w 94658237188459
/*     */     //   5: lxor
/*     */     //   6: dup2
/*     */     //   7: bipush #32
/*     */     //   9: lushr
/*     */     //   10: l2i
/*     */     //   11: istore_3
/*     */     //   12: dup2
/*     */     //   13: bipush #32
/*     */     //   15: lshl
/*     */     //   16: bipush #48
/*     */     //   18: lushr
/*     */     //   19: l2i
/*     */     //   20: istore #4
/*     */     //   22: dup2
/*     */     //   23: bipush #48
/*     */     //   25: lshl
/*     */     //   26: bipush #48
/*     */     //   28: lushr
/*     */     //   29: l2i
/*     */     //   30: istore #5
/*     */     //   32: pop2
/*     */     //   33: pop2
/*     */     //   34: ldc2_w 1973537811120675803
/*     */     //   37: lload_1
/*     */     //   38: <illegal opcode> w : (JJ)[Lme/konsolas/aac/aN;
/*     */     //   43: ldc2_w NaN
/*     */     //   46: dstore #7
/*     */     //   48: astore #6
/*     */     //   50: aload_0
/*     */     //   51: invokevirtual a : ()J
/*     */     //   54: lconst_0
/*     */     //   55: lcmp
/*     */     //   56: aload #6
/*     */     //   58: ifnull -> 120
/*     */     //   61: ifle -> 153
/*     */     //   64: goto -> 77
/*     */     //   67: ldc2_w 1965273009213097109
/*     */     //   70: lload_1
/*     */     //   71: <illegal opcode> w : (Laacinternal/v;JJ)Laacinternal/v;
/*     */     //   76: athrow
/*     */     //   77: lload_1
/*     */     //   78: lconst_0
/*     */     //   79: lcmp
/*     */     //   80: iflt -> 145
/*     */     //   83: aload_0
/*     */     //   84: aload #6
/*     */     //   86: ifnull -> 124
/*     */     //   89: goto -> 102
/*     */     //   92: ldc2_w 1965273009213097109
/*     */     //   95: lload_1
/*     */     //   96: <illegal opcode> w : (Laacinternal/v;JJ)Laacinternal/v;
/*     */     //   101: athrow
/*     */     //   102: invokevirtual a : ()J
/*     */     //   105: lconst_1
/*     */     //   106: lcmp
/*     */     //   107: goto -> 120
/*     */     //   110: ldc2_w 1965273009213097109
/*     */     //   113: lload_1
/*     */     //   114: <illegal opcode> w : (Laacinternal/v;JJ)Laacinternal/v;
/*     */     //   119: athrow
/*     */     //   120: ifle -> 150
/*     */     //   123: aload_0
/*     */     //   124: iload_3
/*     */     //   125: iload #4
/*     */     //   127: i2s
/*     */     //   128: iload #5
/*     */     //   130: i2s
/*     */     //   131: invokevirtual f : (ISS)D
/*     */     //   134: invokestatic a : (D)D
/*     */     //   137: lload_1
/*     */     //   138: lconst_0
/*     */     //   139: lcmp
/*     */     //   140: iflt -> 155
/*     */     //   143: dstore #7
/*     */     //   145: aload #6
/*     */     //   147: ifnonnull -> 153
/*     */     //   150: dconst_0
/*     */     //   151: dstore #7
/*     */     //   153: dload #7
/*     */     //   155: dreturn
/*     */     // Line number table:
/*     */     //   Java source line number -> byte code offset
/*     */     //   #69	-> 43
/*     */     //   #96	-> 50
/*     */     //   #89	-> 77
/*     */     //   #99	-> 123
/*     */     //   #12	-> 150
/*     */     //   #58	-> 153
/*     */     // Exception table:
/*     */     //   from	to	target	type
/*     */     //   50	64	67	aacinternal/v
/*     */     //   61	89	92	aacinternal/v
/*     */     //   77	107	110	aacinternal/v }
/*     */   public double b(long paramLong) {
/*  70 */     long l = paramLong ^ 0x242B11652DCL; return a(l, this.n);
/*     */   }
/*     */ 
/*     */ 
/*     */ 
/*     */ 
/*     */ 
/*     */ 
/*     */ 
/*     */   
/*     */   public void accept(double paramDouble) {
/*  81 */     long l1 = o ^ 0x4553C3124DBDL, l2 = l1 ^ 0x24CA1D5EF27AL; a(paramDouble, l2);
/*     */   } public void b(short paramShort, int paramInt1, int paramInt2) {
/*  83 */     long l1 = (paramShort << 48L | paramInt1 << 32L >>> 16L | paramInt2 << 48L >>> 48L) ^ o, l2 = l1 ^ 0x30AE8B9FA0CCL, l3 = l1 ^ 0x2836E839BB33L; try { this.d.c(1, l3); }
/*     */     catch (v v)
/*     */     { throw new w(l2, v, P.NO_DATA, new Object[0]); }
/*     */   
/*     */   } public double a(double paramDouble, long paramLong) {
/*  88 */     paramLong = o ^ paramLong; long l = paramLong ^ 0x64D72E62E1A5L; return this.d.b(paramDouble, l);
/*     */   } public double f(int paramInt, short paramShort1, short paramShort2) {
/*  90 */     long l1 = paramInt << 32L | paramShort1 << 48L >>> 32L | paramShort2 << 48L >>> 48L, l2 = l1 ^ 0x54B61404A38CL; return a(l2, this.f);
/*     */   }
/*     */ 
/*     */ 
/*     */ 
/*     */   
/*     */   public double l(long paramLong) {
/*  97 */     paramLong = o ^ paramLong; long l = paramLong ^ 0x2DB5696D65CBL; return a(l, e);
/*     */   }
/*     */   public void a(int paramInt, long paramLong) {
/*     */     // Byte code:
/*     */     //   0: getstatic aacinternal/am.o : J
/*     */     //   3: lload_2
/*     */     //   4: lxor
/*     */     //   5: lstore_2
/*     */     //   6: lload_2
/*     */     //   7: dup2
/*     */     //   8: ldc2_w 125106714448046
/*     */     //   11: lxor
/*     */     //   12: dup2
/*     */     //   13: bipush #48
/*     */     //   15: lushr
/*     */     //   16: l2i
/*     */     //   17: istore #4
/*     */     //   19: dup2
/*     */     //   20: bipush #16
/*     */     //   22: lshl
/*     */     //   23: bipush #32
/*     */     //   25: lushr
/*     */     //   26: l2i
/*     */     //   27: istore #5
/*     */     //   29: dup2
/*     */     //   30: bipush #48
/*     */     //   32: lshl
/*     */     //   33: bipush #48
/*     */     //   35: lushr
/*     */     //   36: l2i
/*     */     //   37: istore #6
/*     */     //   39: pop2
/*     */     //   40: dup2
/*     */     //   41: ldc2_w 25874954043309
/*     */     //   44: lxor
/*     */     //   45: lstore #7
/*     */     //   47: pop2
/*     */     //   48: ldc2_w 1963140164395948934
/*     */     //   51: lload_2
/*     */     //   52: <illegal opcode> w : (JJ)[Lme/konsolas/aac/aN;
/*     */     //   57: astore #9
/*     */     //   59: iload_1
/*     */     //   60: iconst_1
/*     */     //   61: aload #9
/*     */     //   63: ifnull -> 171
/*     */     //   66: if_icmpge -> 164
/*     */     //   69: goto -> 82
/*     */     //   72: ldc2_w 1953188782521337032
/*     */     //   75: lload_2
/*     */     //   76: <illegal opcode> w : (Laacinternal/v;JJ)Laacinternal/v;
/*     */     //   81: athrow
/*     */     //   82: iload_1
/*     */     //   83: iconst_m1
/*     */     //   84: aload #9
/*     */     //   86: lload_2
/*     */     //   87: lconst_0
/*     */     //   88: lcmp
/*     */     //   89: ifle -> 179
/*     */     //   92: ifnull -> 171
/*     */     //   95: goto -> 108
/*     */     //   98: ldc2_w 1953188782521337032
/*     */     //   101: lload_2
/*     */     //   102: <illegal opcode> w : (Laacinternal/v;JJ)Laacinternal/v;
/*     */     //   107: athrow
/*     */     //   108: if_icmpeq -> 164
/*     */     //   111: goto -> 124
/*     */     //   114: ldc2_w 1953188782521337032
/*     */     //   117: lload_2
/*     */     //   118: <illegal opcode> w : (Laacinternal/v;JJ)Laacinternal/v;
/*     */     //   123: athrow
/*     */     //   124: new aacinternal/v
/*     */     //   127: dup
/*     */     //   128: getstatic aacinternal/P.NOT_POSITIVE_WINDOW_SIZE : Laacinternal/P;
/*     */     //   131: iconst_1
/*     */     //   132: anewarray java/lang/Object
/*     */     //   135: dup
/*     */     //   136: iconst_0
/*     */     //   137: iload_1
/*     */     //   138: invokestatic valueOf : (I)Ljava/lang/Integer;
/*     */     //   141: aastore
/*     */     //   142: iload #4
/*     */     //   144: i2s
/*     */     //   145: iload #5
/*     */     //   147: iload #6
/*     */     //   149: i2s
/*     */     //   150: invokespecial <init> : (Laacinternal/H;[Ljava/lang/Object;SIS)V
/*     */     //   153: athrow
/*     */     //   154: ldc2_w 1953188782521337032
/*     */     //   157: lload_2
/*     */     //   158: <illegal opcode> w : (Laacinternal/v;JJ)Laacinternal/v;
/*     */     //   163: athrow
/*     */     //   164: aload_0
/*     */     //   165: iload_1
/*     */     //   166: putfield i : I
/*     */     //   169: iload_1
/*     */     //   170: iconst_m1
/*     */     //   171: lload_2
/*     */     //   172: lconst_0
/*     */     //   173: lcmp
/*     */     //   174: iflt -> 219
/*     */     //   177: aload #9
/*     */     //   179: ifnull -> 219
/*     */     //   182: if_icmpeq -> 253
/*     */     //   185: goto -> 198
/*     */     //   188: ldc2_w 1953188782521337032
/*     */     //   191: lload_2
/*     */     //   192: <illegal opcode> w : (Laacinternal/v;JJ)Laacinternal/v;
/*     */     //   197: athrow
/*     */     //   198: iload_1
/*     */     //   199: aload_0
/*     */     //   200: getfield d : Laacinternal/B;
/*     */     //   203: invokevirtual c : ()I
/*     */     //   206: goto -> 219
/*     */     //   209: ldc2_w 1953188782521337032
/*     */     //   212: lload_2
/*     */     //   213: <illegal opcode> w : (Laacinternal/v;JJ)Laacinternal/v;
/*     */     //   218: athrow
/*     */     //   219: if_icmpge -> 253
/*     */     //   222: aload_0
/*     */     //   223: getfield d : Laacinternal/B;
/*     */     //   226: aload_0
/*     */     //   227: getfield d : Laacinternal/B;
/*     */     //   230: invokevirtual c : ()I
/*     */     //   233: iload_1
/*     */     //   234: isub
/*     */     //   235: lload #7
/*     */     //   237: invokevirtual a : (IJ)V
/*     */     //   240: goto -> 253
/*     */     //   243: ldc2_w 1953188782521337032
/*     */     //   246: lload_2
/*     */     //   247: <illegal opcode> w : (Laacinternal/v;JJ)Laacinternal/v;
/*     */     //   252: athrow
/*     */     //   253: return
/*     */     // Line number table:
/*     */     //   Java source line number -> byte code offset
/*     */     //   #100	-> 59
/*     */     //   #15	-> 124
/*     */     //   #59	-> 138
/*     */     //   #48	-> 164
/*     */     //   #107	-> 169
/*     */     //   #4	-> 222
/*     */     //   #28	-> 253
/*     */     // Exception table:
/*     */     //   from	to	target	type
/*     */     //   59	69	72	aacinternal/v
/*     */     //   66	95	98	aacinternal/v
/*     */     //   82	111	114	aacinternal/v
/*     */     //   108	154	154	aacinternal/v
/*     */     //   171	185	188	aacinternal/v
/*     */     //   182	206	209	aacinternal/v
/*     */     //   219	240	243	aacinternal/v
/*     */   }
/*     */   
/* 103 */   public int a() { return this.i; }
/*     */   public double k(long paramLong) { // Byte code:
/*     */     //   0: getstatic aacinternal/am.o : J
/*     */     //   3: lload_1
/*     */     //   4: lxor
/*     */     //   5: lstore_1
/*     */     //   6: lload_1
/*     */     //   7: dup2
/*     */     //   8: ldc2_w 72195322371873
/*     */     //   11: lxor
/*     */     //   12: lstore_3
/*     */     //   13: pop2
/*     */     //   14: aload_0
/*     */     //   15: invokevirtual a : ()J
/*     */     //   18: lstore #5
/*     */     //   20: lload #5
/*     */     //   22: lconst_0
/*     */     //   23: lcmp
/*     */     //   24: ifle -> 52
/*     */     //   27: aload_0
/*     */     //   28: lload_3
/*     */     //   29: invokevirtual j : (J)D
/*     */     //   32: lload #5
/*     */     //   34: l2d
/*     */     //   35: ddiv
/*     */     //   36: invokestatic a : (D)D
/*     */     //   39: goto -> 55
/*     */     //   42: ldc2_w -2280389571720659063
/*     */     //   45: lload_1
/*     */     //   46: <illegal opcode> w : (Laacinternal/v;JJ)Laacinternal/v;
/*     */     //   51: athrow
/*     */     //   52: ldc2_w NaN
/*     */     //   55: dreturn
/*     */     // Line number table:
/*     */     //   Java source line number -> byte code offset
/*     */     //   #104	-> 14
/*     */     //   #108	-> 20
/*     */     // Exception table:
/*     */     //   from	to	target	type
/*     */     //   20	42	42	aacinternal/v }
/* 105 */   public am(long paramLong) { this(-1, l); } public double g(long paramLong) {
/* 106 */     paramLong = o ^ paramLong; long l = paramLong ^ 0x74F3DDC7AF71L; return a(l, this.j);
/*     */   }
/*     */   
/*     */   private static v b(v paramv) {
/*     */     return paramv;
/*     */   }
/*     */   
/*     */   private static String a(byte[] paramArrayOfbyte) {
/*     */     byte b1 = 0;
/*     */     int i;
/*     */     char[] arrayOfChar = new char[i = paramArrayOfbyte.length];
/*     */     for (byte b2 = 0; b2 < i; b2++) {
/*     */       int j;
/*     */       if ((j = 0xFF & paramArrayOfbyte[b2]) < 192) {
/*     */         arrayOfChar[b1++] = (char)j;
/*     */       } else if (j < 224) {
/*     */         char c = (char)((char)(j & 0x1F) << 6);
/*     */         j = paramArrayOfbyte[++b2];
/*     */         c = (char)(c | (char)(j & 0x3F));
/*     */         arrayOfChar[b1++] = c;
/*     */       } else if (b2 < i - 2) {
/*     */         char c = (char)((char)(j & 0xF) << 12);
/*     */         j = paramArrayOfbyte[++b2];
/*     */         c = (char)(c | (char)(j & 0x3F) << 6);
/*     */         j = paramArrayOfbyte[++b2];
/*     */         c = (char)(c | (char)(j & 0x3F));
/*     */         arrayOfChar[b1++] = c;
/*     */       } 
/*     */     } 
/*     */     return new String(arrayOfChar, 0, b1);
/*     */   }
/*     */   
/*     */   private static String b(int paramInt, long paramLong) {
/*     */     int i = paramInt ^ (int)(paramLong & 0x7FFFL) ^ 0x578;
/*     */     if (r[i] == null) {
/*     */       Object[] arrayOfObject;
/*     */       try {
/*     */         Long long_ = Long.valueOf(Thread.currentThread().getId());
/*     */         arrayOfObject = (Object[])s.get(long_);
/*     */         if (arrayOfObject == null) {
/*     */           arrayOfObject = new Object[3];
/*     */           "颶覴旊䊖摕ᇅ磷펺ꖩ菪뷀訰헰큞᫣㭿籲┴榱".toCharArray()[16] = (char)("颶覴旊䊖摕ᇅ磷펺ꖩ菪뷀訰헰큞᫣㭿籲┴榱".toCharArray()[16] ^ 0x3B92);
/*     */           arrayOfObject[0] = Cipher.getInstance(aB$aG.q("颶覴旊䊖摕ᇅ磷펺ꖩ菪뷀訰헰큞᫣㭿籲┴榱".toCharArray(), (short)25306, (byte)4, (byte)5));
/*     */           "◗黂䚗恼".toCharArray()[1] = (char)("◗黂䚗恼".toCharArray()[1] ^ 0x277A);
/*     */           arrayOfObject[1] = SecretKeyFactory.getInstance(aB$aG.q("◗黂䚗恼".toCharArray(), (short)6276, (byte)2, (byte)4));
/*     */           arrayOfObject[2] = new IvParameterSpec(new byte[8]);
/*     */           s.put(long_, arrayOfObject);
/*     */         } 
/*     */       } catch (Exception exception) {
/*     */         "屔﮷鄏崒奀骎펝ꃆ䉵奞㷛".toCharArray()[7] = (char)("屔﮷鄏崒奀骎펝ꃆ䉵奞㷛".toCharArray()[7] ^ 0x25B6);
/*     */         throw new RuntimeException(aB$aG.q("屔﮷鄏崒奀骎펝ꃆ䉵奞㷛".toCharArray(), (short)3988, (byte)4, (byte)2), exception);
/*     */       } 
/*     */       byte[] arrayOfByte1 = new byte[8];
/*     */       arrayOfByte1[0] = (byte)(int)(paramLong >>> 56L);
/*     */       for (byte b = 1; b < 8; b++)
/*     */         arrayOfByte1[b] = (byte)(int)(paramLong << b * 8 >>> 56L); 
/*     */       DESKeySpec dESKeySpec = new DESKeySpec(arrayOfByte1);
/*     */       SecretKey secretKey = ((SecretKeyFactory)arrayOfObject[1]).generateSecret(dESKeySpec);
/*     */       ((Cipher)arrayOfObject[0]).init(2, secretKey, (IvParameterSpec)arrayOfObject[2]);
/*     */       "狪抾㋓⩍䭫릷䓾根ꭵ籨䜸".toCharArray()[7] = (char)("狪抾㋓⩍䭫릷䓾根ꭵ籨䜸".toCharArray()[7] ^ 0x1DF8);
/*     */       byte[] arrayOfByte2 = q[i].getBytes(aB$aG.q("狪抾㋓⩍䭫릷䓾根ꭵ籨䜸".toCharArray(), (short)21106, (byte)5, (byte)3));
/*     */       r[i] = a(((Cipher)arrayOfObject[0]).doFinal(arrayOfByte2));
/*     */     } 
/*     */     return r[i];
/*     */   }
/*     */   
/*     */   private static Object a(MethodHandles.Lookup paramLookup, MutableCallSite paramMutableCallSite, String paramString, Object[] paramArrayOfObject) {
/*     */     int i = ((Integer)paramArrayOfObject[0]).intValue();
/*     */     long l = ((Long)paramArrayOfObject[1]).longValue();
/*     */     String str = b(i, l);
/*     */     MethodHandle methodHandle = MethodHandles.constant(String.class, str);
/*     */     paramMutableCallSite.setTarget(MethodHandles.dropArguments(methodHandle, 0, new Class[] { int.class, long.class }));
/*     */     return str;
/*     */   }
/*     */   
/*     */   private static CallSite a(MethodHandles.Lookup paramLookup, String paramString, MethodType paramMethodType) {
/*     */     // Byte code:
/*     */     //   0: new java/lang/invoke/MutableCallSite
/*     */     //   3: dup
/*     */     //   4: aload_2
/*     */     //   5: invokespecial <init> : (Ljava/lang/invoke/MethodType;)V
/*     */     //   8: astore_3
/*     */     //   9: aload_3
/*     */     //   10: ldc_w
/*     */     //   13: ldc_w [Ljava/lang/Object;
/*     */     //   16: aload_2
/*     */     //   17: invokevirtual parameterCount : ()I
/*     */     //   20: invokevirtual asCollector : (Ljava/lang/Class;I)Ljava/lang/invoke/MethodHandle;
/*     */     //   23: iconst_0
/*     */     //   24: iconst_3
/*     */     //   25: anewarray java/lang/Object
/*     */     //   28: dup
/*     */     //   29: iconst_0
/*     */     //   30: aload_0
/*     */     //   31: aastore
/*     */     //   32: dup
/*     */     //   33: iconst_1
/*     */     //   34: aload_3
/*     */     //   35: aastore
/*     */     //   36: dup
/*     */     //   37: iconst_2
/*     */     //   38: aload_1
/*     */     //   39: aastore
/*     */     //   40: invokestatic insertArguments : (Ljava/lang/invoke/MethodHandle;I[Ljava/lang/Object;)Ljava/lang/invoke/MethodHandle;
/*     */     //   43: aload_2
/*     */     //   44: invokestatic explicitCastArguments : (Ljava/lang/invoke/MethodHandle;Ljava/lang/invoke/MethodType;)Ljava/lang/invoke/MethodHandle;
/*     */     //   47: invokevirtual setTarget : (Ljava/lang/invoke/MethodHandle;)V
/*     */     //   50: goto -> 171
/*     */     //   53: astore #4
/*     */     //   55: new java/lang/RuntimeException
/*     */     //   58: dup
/*     */     //   59: new java/lang/StringBuilder
/*     */     //   62: dup
/*     */     //   63: invokespecial <init> : ()V
/*     */     //   66: ldc_w '쿘ဟﶺ뿠쁵뛄਽㾔꾑沆嬍ᯓ'
/*     */     //   69: invokevirtual toCharArray : ()[C
/*     */     //   72: dup
/*     */     //   73: dup
/*     */     //   74: bipush #11
/*     */     //   76: dup_x1
/*     */     //   77: caload
/*     */     //   78: sipush #27638
/*     */     //   81: ixor
/*     */     //   82: i2c
/*     */     //   83: castore
/*     */     //   84: sipush #19939
/*     */     //   87: iconst_5
/*     */     //   88: iconst_5
/*     */     //   89: invokestatic q : (Ljava/lang/Object;SBB)Ljava/lang/String;
/*     */     //   92: invokevirtual append : (Ljava/lang/String;)Ljava/lang/StringBuilder;
/*     */     //   95: ldc_w '싫瀠堧㡰'
/*     */     //   98: invokevirtual toCharArray : ()[C
/*     */     //   101: dup
/*     */     //   102: dup
/*     */     //   103: iconst_2
/*     */     //   104: dup_x1
/*     */     //   105: caload
/*     */     //   106: sipush #23847
/*     */     //   109: ixor
/*     */     //   110: i2c
/*     */     //   111: castore
/*     */     //   112: sipush #29884
/*     */     //   115: iconst_0
/*     */     //   116: iconst_4
/*     */     //   117: invokestatic q : (Ljava/lang/Object;SBB)Ljava/lang/String;
/*     */     //   120: invokevirtual append : (Ljava/lang/String;)Ljava/lang/StringBuilder;
/*     */     //   123: aload_1
/*     */     //   124: invokevirtual append : (Ljava/lang/String;)Ljava/lang/StringBuilder;
/*     */     //   127: ldc_w '꡼ℎ䏒牢'
/*     */     //   130: invokevirtual toCharArray : ()[C
/*     */     //   133: dup
/*     */     //   134: dup
/*     */     //   135: iconst_1
/*     */     //   136: dup_x1
/*     */     //   137: caload
/*     */     //   138: sipush #5316
/*     */     //   141: ixor
/*     */     //   142: i2c
/*     */     //   143: castore
/*     */     //   144: sipush #25793
/*     */     //   147: iconst_5
/*     */     //   148: iconst_5
/*     */     //   149: invokestatic q : (Ljava/lang/Object;SBB)Ljava/lang/String;
/*     */     //   152: invokevirtual append : (Ljava/lang/String;)Ljava/lang/StringBuilder;
/*     */     //   155: aload_2
/*     */     //   156: invokevirtual toString : ()Ljava/lang/String;
/*     */     //   159: invokevirtual append : (Ljava/lang/String;)Ljava/lang/StringBuilder;
/*     */     //   162: invokevirtual toString : ()Ljava/lang/String;
/*     */     //   165: aload #4
/*     */     //   167: invokespecial <init> : (Ljava/lang/String;Ljava/lang/Throwable;)V
/*     */     //   170: athrow
/*     */     //   171: aload_3
/*     */     //   172: areturn
/*     */     // Exception table:
/*     */     //   from	to	target	type
/*     */     //   9	50	53	java/lang/Exception
/*     */   } }


/* Location:              C:\Users\BukkitBypass\Desktop\MatrixAC\AAC\AAC-spigot-5.2.0.jar!\aacinternal\am.class
 * Java compiler version: 8 (52.0)
 * JD-Core Version:       1.1.3
 */